Workbook
Name Access_Control: [1]Elec_Est!#REF!
Name AREAS: #REF!
Name AREAS: [1]ML_Sum!$X$1:$AD$16
Name AREAS: ML_Sum!$X$1:$AD$16
Name CCTV: [1]Elec_Est!#REF!
Name Data: [1]Elec_Est!#REF!
Name Fire_Alarm: [1]Elec_Est!#REF!
Name FO: [1]Elec_Est!#REF!
Name Guard: [1]Elec_Est!#REF!
Name Intercom: [1]Elec_Est!#REF!
Name Intruder_Alarm: [1]Elec_Est!#REF!

Sheet Elec_Rates
B1: CLIENT: | C1: =ML_Sum!$C1 -> 1 | D1: =ML_Sum!$D1 -> Quintano Foods Ltd. | F1: =ML_Sum!$F1 -> 0 | I1: 1 | J1: =ML_Sum!$J1 -> 1 | K1: =ML_Sum!$K1 -> 1 | L1: =ML_Sum!$L1 -> 1 | M1: =ML_Sum!$M1 -> 1 | N1: =ML_Sum!$N1 -> 1 | O1: =ML_Sum!$O1 -> 1 | Q1: =ML_Sum!$Q1 -> € | R1: R/Lab Cont | S1: =ML_Sum!$S1 -> R | T1: =ML_Sum!$T1 -> 1 | U1: =ML_Sum!W1 -> BOQ | V1: INCL | W1: MULT | X1: AREA | Y1: BOQ | Z1: TDWG | AA1: ACT | AB1: DIFF
B2: PROJECT: | C2: =ML_Sum!$C2 -> 1 | D2: =ML_Sum!$D2 -> Warehouse at tal-Handaq, Qormi | F2: =ML_Sum!$F2 -> Electrical | I2: 2 | J2: =ML_Sum!$J2 -> 1 | K2: =ML_Sum!$K2 -> 1 | L2: =ML_Sum!$L2 -> 1 | M2: =ML_Sum!$M2 -> 1 | N2: =ML_Sum!$N2 -> 1 | O2: =ML_Sum!$O2 -> 1 | Q2: =ML_Sum!$Q2 -> 0 | R2: mu_A | S2: =ML_Sum!$S2 -> 1 | T2: =ML_Sum!$T2 -> 27.46
B3: JOB DESC: | C3: =ML_Sum!$C3 -> 1 | D3: =ML_Sum!$D3 -> Electrical installation for Mechanical (HVAC) - Revision B | F3: =ML_Sum!$F3 -> ECA | I3: 3 | J3: =ML_Sum!$J3 -> 1 | K3: =ML_Sum!$K3 -> 1 | L3: =ML_Sum!$L3 -> 1 | M3: =ML_Sum!$M3 -> 1 | N3: =ML_Sum!$N3 -> 1 | O3: =ML_Sum!$O3 -> 1 | Q3: =ML_Sum!$Q3 -> 0 | R3: mu_B | S3: =ML_Sum!$S3 -> 1 | T3: =ML_Sum!$T3 -> 27.46
B4: QUOTE No: | C4: =ML_Sum!$C4 -> 1 | D4: =ML_Sum!$D4 -> ELM-25-0085B | F4: =ML_Sum!$F4 -> 0 | I4: 4 | J4: =ML_Sum!$J4 -> 1 | K4: =ML_Sum!$K4 -> 1 | L4: =ML_Sum!$L4 -> 1 | M4: =ML_Sum!$M4 -> 1 | N4: =ML_Sum!$N4 -> 1 | O4: =ML_Sum!$O4 -> 1 | Q4: =ML_Sum!$Q4 -> 0 | R4: mu_C | S4: =ML_Sum!$S4 -> 1 | T4: =ML_Sum!$T4 -> 27.46
B5: CLIENTs REF: | C5: =ML_Sum!$C5 -> 1 | D5: =ML_Sum!$D5 -> Tender | F5: =ML_Sum!$F5 -> 0 | I5: 5 | J5: =ML_Sum!$J5 -> 1 | K5: =ML_Sum!$K5 -> 1 | L5: =ML_Sum!$L5 -> 1 | M5: =ML_Sum!$M5 -> 1 | N5: =ML_Sum!$N5 -> 1 | O5: =ML_Sum!$O5 -> 1 | Q5: =ML_Sum!$Q5 -> 0 | R5: mu_D | S5: =ML_Sum!$S5 -> 1 | T5: =ML_Sum!$T5 -> 27.46
B6: VAT/DUTIES: | C6: =ML_Sum!$C6 -> 1 | D6: =ML_Sum!$D6 -> VAT EXCL. | F6: =ML_Sum!$F6 -> 0 | I6: 6 | J6: =ML_Sum!$J6 -> 1 | K6: =ML_Sum!$K6 -> 1 | L6: =ML_Sum!$L6 -> 1 | M6: =ML_Sum!$M6 -> 1 | N6: =ML_Sum!$N6 -> 1 | O6: =ML_Sum!$O6 -> 1 | Q6: =ML_Sum!$Q6 -> 0 | R6: mu_E | S6: =ML_Sum!$S6 -> 1 | T6: =ML_Sum!$T6 -> 27.46
B7: SAVED ON: | C7: =ML_Sum!$C7 -> 1 | D7: 39364 | F7: =ML_Sum!$F7 -> 0 | I7: 7 | J7: =ML_Sum!$J7 -> 1 | K7: =ML_Sum!$K7 -> 1 | L7: =ML_Sum!$L7 -> 1 | M7: =ML_Sum!$M7 -> 1 | N7: =ML_Sum!$N7 -> 1 | O7: =ML_Sum!$O7 -> 0 | Q7: =ML_Sum!$Q7 -> 0 | R7: mu_F | S7: =ML_Sum!$S7 -> 1 | T7: =ML_Sum!$T7 -> 27.46
B8: ESTIMATOR: | C8: =ML_Sum!$C8 -> 1 | D8: =ML_Sum!$D8 -> T.Sammut | F8: =ML_Sum!$F8 -> 0 | I8: 8 | J8: =ML_Sum!$J8 -> 1 | K8: =ML_Sum!$K8 -> 1 | L8: =ML_Sum!$L8 -> 1 | M8: =ML_Sum!$M8 -> 1 | N8: =ML_Sum!$N8 -> 1 | O8: =ML_Sum!$O8 -> 0 | Q8: =ML_Sum!$Q8 -> 0 | R8: mu_G | S8: =ML_Sum!$S8 -> 1 | T8: =ML_Sum!$T8 -> 27.46
B9: LABOUR RATE: | C9: =ML_Sum!$C9 -> 1 | D9: =ML_Sum!$D9 -> 27.46 | F9: =ML_Sum!$F9 -> 0 | I9: 9 | J9: =ML_Sum!$J9 -> 1 | K9: =ML_Sum!$K9 -> 1 | L9: =ML_Sum!$L9 -> 1 | M9: =ML_Sum!$M9 -> 1 | N9: =ML_Sum!$N9 -> 1 | O9: =ML_Sum!$O9 -> 0 | Q9: =ML_Sum!$Q9 -> 0 | R9: mu_H | S9: =ML_Sum!$S9 -> 1 | T9: =ML_Sum!$T9 -> 27.46
C10: =ML_Sum!$C10 -> 1 | F10: =ML_Sum!$F10 -> 0 | I10: 10 | J10: =ML_Sum!$J10 -> 1 | K10: =ML_Sum!$K10 -> 1 | L10: =ML_Sum!$L10 -> 1 | M10: =ML_Sum!$M10 -> 1 | N10: =ML_Sum!$N10 -> 1 | O10: =ML_Sum!$O10 -> 1 | Q10: =ML_Sum!$Q10 -> 0 | R10: mu_I | S10: =ML_Sum!$S10 -> 1 | T10: =ML_Sum!$T10 -> 27.46
C11: =ML_Sum!$C11 -> 1 | F11: =ML_Sum!$F11 -> 0 | Q11: =ML_Sum!$Q11 -> 0 | R11: mu_J | S11: =ML_Sum!$S11 -> 1 | T11: =ML_Sum!$T11 -> 27.46
C12: =ML_Sum!$C12 -> 1 | F12: =ML_Sum!$F12 -> 0 | Q12: =ML_Sum!$Q12 -> 0 | R12: MIXED | S12: =ML_Sum!$S12 -> MAT MU | T12: =ML_Sum!$T12 -> LAB RATE
G13: I_CODE | H13: C_CODE | I13: MAKE | J13: PART_NO | K13: MARKUP | L13: TYPE | M13: LIST_P | N13: P_FACT | O13: FIX | P13: DATE | Q13: %Dsct in BOQ | R13: MU TYPE | S13: MAT MU | T13: LAB RATE
C15: t | D15: Item:
D16: Start Typing Header
Q18: Multip
A19: 1 | B19: =Elec_Est!B2140 -> 4 | D19: 037# 5 x 16mm2 F120 Fire Resistant Cable (BS7846) - XLPE/SWA/LSZH | K19: RATE | L19: RATE | Q19: =B19/A19 -> 4 | R19: =IF($B19=0,0,IF($S$1="R",ROUND(R30/$B19,2),R30/$B19)) -> 166.5 | T19: =IF($B19=0,0,IF($S$1="R",ROUND(T30/$B19,2),T30/$B19)) -> 2.86
D20: Based on:
A21: =$Q$19 *(3) -> 12 | B21: m | D21: Power Cable 5c 16 mm2 XLPE SWA-PVC | E21: Fire Rated | F21: Cleveland | G21: CAMC_087 | H21: 616 | I21: (__) | J21: 16mm2 | O21: 2 | P21: 38371 | Q21: 26.22 | R21: =$A21*Q21 -> 314.64 | S21: 0.1 | T21: =$A21*S21*$T$1 -> 1.2
A22: =$Q$19 *(3) -> 12 | B22: No | D22: Cable Tie 225mm | G22: CONS_009 | H22: 875 | I22: (__) | K22: 01-003 | O22: 1 | P22: 34669 | Q22: 0.05 | R22: =$A22*Q22 -> 0.6 | T22: =$A22*S22*$T$1 -> 0
A23: =$Q$19 *(2) -> 8 | B23: No | D23: Gland Indoor 25 BWL 4*10/16mm2 | G23: CAAC_043 | H23: 620 | I23: CMP | O23: 2 | P23: 35431 | Q23: 7.66 | R23: =$A23*Q23 -> 61.28 | S23: 0.4 | T23: =$A23*S23*$T$1 -> 3.2
A24: =$Q$19 *(2) -> 8 | B24: m | D24: Cable Marker 8 digit c/w Carrier Strip | G24: CAAC_091 | H24: 620 | I24: (__) | O24: 2 | P24: 38148 | Q24: 1.5 | R24: =$A24*Q24 -> 12 | S24: 0.08 | T24: =$A24*S24*$T$1 -> 0.64
A25: =$Q$19 *(2*5) -> 40 | B25: No | D25: Cable Lug 16 mm2 | G25: CAAC_009 | H25: 620 | I25: CTT | O25: 2 | P25: 34669 | Q25: 0.14 | R25: =$A25*Q25 -> 5.6 | S25: 0.06 | T25: =$A25*S25*$T$1 -> 2.4
A26: =$Q$19 *(1) -> 4 | B26: No | D26: Labour to connect Mech Equip (FIX 3) | F26: equipment | G26: LABO_009 | H26: 900 | I26: MISC | O26: 1 | R26: =$A26*Q26 -> 0 | S26: 1 | T26: =$A26*S26*$T$1 -> 4 | U26: NoMat?
A27: =$Q$19 *(1/4) -> 1 | B27: LS | D27: Crainage & Transportation | F27: Scissors Lift | G27: CRAI_002 | H27: 962 | I27: MISC | O27: 2 | P27: 38129 | Q27: =1.25 *(12/8*125) -> 234.375 | R27: =$A27*Q27 -> 234.375 | T27: =$A27*S27*$T$1 -> 0
A28: =$Q$19 *(1/4) -> 1 | B28: No | D28: Diesel Fuel | F28: Approx €25/daily - info from Godwin by phone | G28: GENS_022 | H28: 845 | I28: (__) | O28: 3 | P28: 39713 | Q28: =12/8*25 -> 37.5 | R28: =$A28*Q28 -> 37.5 | T28: =$A28*S28*$T$1 -> 0
C29: << ==== TOTAL UNITS | R29: =$A29*Q29 -> 0 | T29: =$A29*S29*$T$1 -> 0
A30: d> | B30: =(R29+T29) -> 0 | D30: Sell_A | E30: =IF($B19=0,0,ROUND(ROUND(($R30*$S$2+($T30*$T$2))/$B19, 2)*$C$2,2)) -> 245.03 | F30: =ROUND($B19*$E30,2) -> 980.12 | K30: ITEM | L30: ITEM | R30: =SUM(R20:R29) -> 665.995 | T30: =SUM(T20:T29) -> 11.44
Q31: Multip
A32: 1 | B32: =Elec_Est!B2141 -> 3 | D32: 039# 5 x 10mm2 F120 Fire Resistant Cable (BS7846) - XLPE/SWA/LSZH | K32: RATE | L32: RATE | Q32: =B32/A32 -> 3 | R32: =IF($B32=0,0,IF($S$1="R",ROUND(R41/$B32,2),R41/$B32)) -> 80.2 | T32: =IF($B32=0,0,IF($S$1="R",ROUND(T41/$B32,2),T41/$B32)) -> 2.58
D33: Based on:
A34: =$Q$32 *(3) -> 9 | B34: m | D34: Power Cable 5c 10 mm2 XLPE SWA-PVC | E34: Fire Rated | F34: Cleveland | G34: CAMC_086 | H34: 616 | I34: (__) | J34: 10mm2 | O34: 2 | P34: 38371 | Q34: 20.11 | R34: =$A34*Q34 -> 180.99 | S34: 0.09 | T34: =$A34*S34*$T$1 -> 0.81
A35: =$Q$32 *(3) -> 9 | B35: No | D35: Cable Tie 225mm | G35: CONS_009 | H35: 875 | I35: (__) | K35: 01-003 | O35: 1 | P35: 34669 | Q35: 0.05 | R35: =$A35*Q35 -> 0.45 | T35: =$A35*S35*$T$1 -> 0
A36: =$Q$32 *(2) -> 6 | B36: No | D36: Gland Indoor 25 BWL 4*10/16mm2 | G36: CAAC_043 | H36: 620 | I36: CMP | O36: 2 | P36: 35431 | Q36: 7.66 | R36: =$A36*Q36 -> 45.96 | S36: 0.4 | T36: =$A36*S36*$T$1 -> 2.4
A37: =$Q$32 *(2) -> 6 | B37: m | D37: Cable Marker 8 digit c/w Carrier Strip | G37: CAAC_091 | H37: 620 | I37: (__) | O37: 2 | P37: 38148 | Q37: 1.5 | R37: =$A37*Q37 -> 9 | S37: 0.08 | T37: =$A37*S37*$T$1 -> 0.48
A38: =$Q$32 *(10) -> 30 | B38: No | D38: Cable Lug 10 mm2 | G38: CAAC_008 | H38: 620 | I38: CTT | O38: 2 | P38: 34669 | Q38: 0.14 | R38: =$A38*Q38 -> 4.2 | S38: 0.06 | T38: =$A38*S38*$T$1 -> 1.8
A39: =$Q$32 *(1) -> 3 | B39: No | D39: Labour to connect Mech Equip (FIX 3) | F39: equipment | G39: LABO_009 | H39: 900 | I39: MISC | O39: 1 | R39: =$A39*Q39 -> 0 | S39: 0.75 | T39: =$A39*S39*$T$1 -> 2.25 | U39: NoMat?
C40: << ==== TOTAL UNITS | R40: =$A40*Q40 -> 0 | T40: =$A40*S40*$T$1 -> 0
A41: d> | B41: =(R40+T40) -> 0 | D41: Sell_A | E41: =IF($B32=0,0,ROUND(ROUND(($R41*$S$2+($T41*$T$2))/$B32, 2)*$C$2,2)) -> 151.05 | F41: =ROUND($B32*$E41,2) -> 453.15 | K41: ITEM | L41: ITEM | R41: =SUM(R33:R40) -> 240.6 | T41: =SUM(T33:T40) -> 7.74
Q42: Multip
A43: 1 | B43: =Elec_Est!B2142 -> 4 | D43: 045# 5 x 4mm2 XLPE/SWA/LSZH | K43: RATE | L43: RATE | Q43: =B43/A43 -> 4 | R43: =IF($B43=0,0,IF($S$1="R",ROUND(R52/$B43,2),R52/$B43)) -> 24.44 | T43: =IF($B43=0,0,IF($S$1="R",ROUND(T52/$B43,2),T52/$B43)) -> 1.77
D44: Based on:
A45: =$Q$43 *(3) -> 12 | B45: m | D45: Power Cable 5c 4.0 mm2 PVC SWA-PVC | F45: Cleveland | G45: CAMC_077 | H45: 616 | I45: (__) | J45: 4.0mm2 | K45: 06-018 | O45: 2 | P45: 38371 | Q45: 3.79 | R45: =$A45*Q45 -> 45.48 | S45: 0.07 | T45: =$A45*S45*$T$1 -> 0.84
A46: =$Q$43 *(3) -> 12 | B46: No | D46: Cable Tie 225mm | G46: CONS_009 | H46: 875 | I46: (__) | K46: 01-003 | O46: 1 | P46: 34669 | Q46: 0.05 | R46: =$A46*Q46 -> 0.6 | T46: =$A46*S46*$T$1 -> 0
A47: =$Q$43 *(2) -> 8 | B47: No | D47: Gland Indoor 20 BWL 4*4/6mm2 | G47: CAAC_040 | H47: 620 | I47: CMP | O47: 2 | P47: 35431 | Q47: 4.71 | R47: =$A47*Q47 -> 37.68 | S47: 0.35 | T47: =$A47*S47*$T$1 -> 2.8
A48: =$Q$43 *(2) -> 8 | B48: m | D48: Cable Marker 8 digit c/w Carrier Strip | G48: CAAC_091 | H48: 620 | I48: (__) | O48: 2 | P48: 38148 | Q48: 1.5 | R48: =$A48*Q48 -> 12 | S48: 0.08 | T48: =$A48*S48*$T$1 -> 0.64
A49: =$Q$43 *(10) -> 40 | B49: No | D49: Cable Lug 4.0 mm2 | G49: CAAC_006 | H49: 620 | I49: CTT | O49: 2 | P49: 34669 | Q49: 0.05 | R49: =$A49*Q49 -> 2 | S49: 0.02 | T49: =$A49*S49*$T$1 -> 0.8
A50: =$Q$43 *(1) -> 4 | B50: No | D50: Labour to connect Mech Equip (FIX 3) | F50: equipment | G50: LABO_009 | H50: 900 | I50: MISC | O50: 1 | R50: =$A50*Q50 -> 0 | S50: 0.5 | T50: =$A50*S50*$T$1 -> 2 | U50: NoMat?
C51: << ==== TOTAL UNITS | R51: =$A51*Q51 -> 0 | T51: =$A51*S51*$T$1 -> 0
A52: d> | B52: =(R51+T51) -> 0 | D52: Sell_A | E52: =IF($B43=0,0,ROUND(ROUND(($R52*$S$2+($T52*$T$2))/$B43, 2)*$C$2,2)) -> 73.04 | F52: =ROUND($B43*$E52,2) -> 292.16 | K52: ITEM | L52: ITEM | R52: =SUM(R44:R51) -> 97.76 | T52: =SUM(T44:T51) -> 7.08
Q53: Multip
A54: 1 | B54: =Elec_Est!B2143 -> 13 | D54: 046# 3 x 4mm2 XLPE/SWA/LSZH | K54: RATE | L54: RATE | Q54: =B54/A54 -> 13 | R54: =IF($B54=0,0,IF($S$1="R",ROUND(R64/$B54,2),R64/$B54)) -> 20.04 | T54: =IF($B54=0,0,IF($S$1="R",ROUND(T64/$B54,2),T64/$B54)) -> 1.66
D55: Based on:
A56: =$Q$54 *(3) -> 39 | B56: m | D56: Power Cable 3c 4.0 mm2 PVC SWA-PVC | F56: Cleveland | G56: CAMC_010 | H56: 616 | I56: CRO | J56: 4.0mm2 | K56: 06-009 | O56: 2 | Q56: 2.39 | R56: =$A56*Q56 -> 93.21 | S56: 0.06 | T56: =$A56*S56*$T$1 -> 2.34
A57: =$Q$54 *(3) -> 39 | B57: No | D57: Cable Tie 225mm | G57: CONS_009 | H57: 875 | I57: (__) | K57: 01-003 | O57: 1 | P57: 34669 | Q57: 0.05 | R57: =$A57*Q57 -> 1.95 | T57: =$A57*S57*$T$1 -> 0
A58: =$Q$54 *(2) -> 26 | B58: No | D58: Gland Indoor 20 BWL 4*4/6mm2 | G58: CAAC_040 | H58: 620 | I58: CMP | O58: 2 | P58: 35431 | Q58: 4.71 | R58: =$A58*Q58 -> 122.46 | S58: 0.35 | T58: =$A58*S58*$T$1 -> 9.1
A59: =$Q$54 *(2) -> 26 | B59: m | D59: Cable Marker 8 digit c/w Carrier Strip | G59: CAAC_091 | H59: 620 | I59: (__) | O59: 2 | P59: 38148 | Q59: 1.5 | R59: =$A59*Q59 -> 39 | S59: 0.08 | T59: =$A59*S59*$T$1 -> 2.08
A60: =$Q$54 *(2*3) -> 78 | B60: No | D60: Cable Lug 4.0 mm2 | G60: CAAC_006 | H60: 620 | I60: CTT | O60: 2 | P60: 34669 | Q60: 0.05 | R60: =$A60*Q60 -> 3.9 | S60: 0.02 | T60: =$A60*S60*$T$1 -> 1.56
A61: =$Q$54 *(2*3) -> 78 | B61: No | D61: Labour to connect Mech Equip (FIX 3) | G61: LABO_009 | H61: 900 | I61: MISC | O61: 1 | R61: =$A61*Q61 -> 0 | T61: =$A61*S61*$T$1 -> 0
A62: =$Q$54 *(1) -> 13 | B62: No | D62: Labour to connect Mech Equip (FIX 3) | F62: equipment | G62: LABO_009 | H62: 900 | I62: MISC | O62: 1 | R62: =$A62*Q62 -> 0 | S62: 0.5 | T62: =$A62*S62*$T$1 -> 6.5 | U62: NoMat?
C63: << ==== TOTAL UNITS | R63: =$A63*Q63 -> 0 | T63: =$A63*S63*$T$1 -> 0
A64: d> | B64: =(R63+T63) -> 0 | D64: Sell_A | E64: =IF($B54=0,0,ROUND(ROUND(($R64*$S$2+($T64*$T$2))/$B54, 2)*$C$2,2)) -> 65.62 | F64: =ROUND($B54*$E64,2) -> 853.06 | K64: ITEM | L64: ITEM | R64: =SUM(R55:R63) -> 260.52 | T64: =SUM(T55:T63) -> 21.58
Q65: Multip
A66: 1 | B66: =Elec_Est!B2144 -> 15 | D66: 047# 5 x 2.5mm2 F120 Fire Resistant Cable (BS7846) - XLPE/SWA/LSZH | K66: RATE | L66: RATE | Q66: =B66/A66 -> 15 | R66: =IF($B66=0,0,IF($S$1="R",ROUND(R75/$B66,2),R75/$B66)) -> 44.34 | T66: =IF($B66=0,0,IF($S$1="R",ROUND(T75/$B66,2),T75/$B66)) -> 1.64
D67: Based on:
A68: =$Q$66 *(3) -> 45 | B68: m | D68: Power Cable 5c 2.5 mm2 XLPE SWA-PVC | E68: Fire Rated | F68: Cleveland | G68: CAMC_084 | H68: 616 | I68: (__) | J68: 2.5mm2 | O68: 2 | P68: 38301 | Q68: 11.19 | R68: =$A68*Q68 -> 503.55 | S68: 0.06 | T68: =$A68*S68*$T$1 -> 2.7
A69: =$Q$66 *(3) -> 45 | B69: No | D69: Cable Tie 225mm | G69: CONS_009 | H69: 875 | I69: (__) | K69: 01-003 | O69: 1 | P69: 34669 | Q69: 0.05 | R69: =$A69*Q69 -> 2.25 | T69: =$A69*S69*$T$1 -> 0
A70: =$Q$66 *(2) -> 30 | B70: No | D70: Gland Indoor 20S BWL 4*1.5/2.5mm2 | G70: CAAC_042 | H70: 620 | I70: CMP | O70: 2 | P70: 35431 | Q70: 3.56 | R70: =$A70*Q70 -> 106.8 | S70: 0.3 | T70: =$A70*S70*$T$1 -> 9
A71: =$Q$66 *(2) -> 30 | B71: m | D71: Cable Marker 8 digit c/w Carrier Strip | G71: CAAC_091 | H71: 620 | I71: (__) | O71: 2 | P71: 38148 | Q71: 1.5 | R71: =$A71*Q71 -> 45 | S71: 0.08 | T71: =$A71*S71*$T$1 -> 2.4
A72: =$Q$66 *(10) -> 150 | B72: No | D72: Cable Lug 2.5 mm2 | G72: CAAC_005 | H72: 620 | I72: CTT | O72: 2 | P72: 34669 | Q72: 0.05 | R72: =$A72*Q72 -> 7.5 | S72: 0.02 | T72: =$A72*S72*$T$1 -> 3
A73: =$Q$66 *(1) -> 15 | B73: No | D73: Labour to connect Mech Equip (FIX 3) | F73: equipment | G73: LABO_009 | H73: 900 | I73: MISC | O73: 1 | R73: =$A73*Q73 -> 0 | S73: 0.5 | T73: =$A73*S73*$T$1 -> 7.5 | U73: NoMat?
C74: << ==== TOTAL UNITS | R74: =$A74*Q74 -> 0 | T74: =$A74*S74*$T$1 -> 0
A75: d> | B75: =(R74+T74) -> 0 | D75: Sell_A | E75: =IF($B66=0,0,ROUND(ROUND(($R75*$S$2+($T75*$T$2))/$B66, 2)*$C$2,2)) -> 89.37 | F75: =ROUND($B66*$E75,2) -> 1340.55 | K75: ITEM | L75: ITEM | R75: =SUM(R67:R74) -> 665.1 | T75: =SUM(T67:T74) -> 24.6
Q76: Multip
A77: 1 | B77: =Elec_Est!B2145 -> 12 | D77: 047# 5 x 2.5mm2 F120 Fire Resistant Cable (BS7846) - XLPE/SWA/LSZH - High level | K77: RATE | L77: RATE | Q77: =B77/A77 -> 12 | R77: =IF($B77=0,0,IF($S$1="R",ROUND(R88/$B77,2),R88/$B77)) -> 82.1 | T77: =IF($B77=0,0,IF($S$1="R",ROUND(T88/$B77,2),T88/$B77)) -> 1.64
D78: Based on: | E78: Impluse fans At High Level
A79: =$Q$77 *(3) -> 36 | B79: m | D79: Power Cable 5c 2.5 mm2 XLPE SWA-PVC | E79: Fire Rated | F79: Cleveland | G79: CAMC_084 | H79: 616 | I79: (__) | J79: 2.5mm2 | O79: 2 | P79: 38301 | Q79: 11.19 | R79: =$A79*Q79 -> 402.84 | S79: 0.06 | T79: =$A79*S79*$T$1 -> 2.16
A80: =$Q$77 *(3) -> 36 | B80: No | D80: Cable Tie 225mm | G80: CONS_009 | H80: 875 | I80: (__) | K80: 01-003 | O80: 1 | P80: 34669 | Q80: 0.05 | R80: =$A80*Q80 -> 1.8 | T80: =$A80*S80*$T$1 -> 0
A81: =$Q$77 *(2) -> 24 | B81: No | D81: Gland Indoor 20S BWL 4*1.5/2.5mm2 | G81: CAAC_042 | H81: 620 | I81: CMP | O81: 2 | P81: 35431 | Q81: 3.56 | R81: =$A81*Q81 -> 85.44 | S81: 0.3 | T81: =$A81*S81*$T$1 -> 7.2
A82: =$Q$77 *(2) -> 24 | B82: m | D82: Cable Marker 8 digit c/w Carrier Strip | G82: CAAC_091 | H82: 620 | I82: (__) | O82: 2 | P82: 38148 | Q82: 1.5 | R82: =$A82*Q82 -> 36 | S82: 0.08 | T82: =$A82*S82*$T$1 -> 1.92
A83: =$Q$77 *(10) -> 120 | B83: No | D83: Cable Lug 2.5 mm2 | G83: CAAC_005 | H83: 620 | I83: CTT | O83: 2 | P83: 34669 | Q83: 0.05 | R83: =$A83*Q83 -> 6 | S83: 0.02 | T83: =$A83*S83*$T$1 -> 2.4
A84: =$Q$77 *(1) -> 12 | B84: No | D84: Labour to connect Mech Equip (FIX 3) | F84: equipment | G84: LABO_009 | H84: 900 | I84: MISC | O84: 1 | R84: =$A84*Q84 -> 0 | S84: 0.5 | T84: =$A84*S84*$T$1 -> 6 | U84: NoMat?
A85: =$Q$77 *(1/12) -> 1 | B85: LS | D85: Crainage & Transportation | F85: Scissors Lift | G85: CRAI_002 | H85: 962 | I85: MISC | O85: 2 | P85: 38129 | Q85: =1.25 *(20/8*125) -> 390.625 | R85: =$A85*Q85 -> 390.625 | T85: =$A85*S85*$T$1 -> 0
A86: =$Q$77 *(1/12) -> 1 | B86: No | D86: Diesel Fuel | F86: Approx €25/daily - info from Godwin by phone | G86: GENS_022 | H86: 845 | I86: (__) | O86: 3 | P86: 39713 | Q86: =20/8*25 -> 62.5 | R86: =$A86*Q86 -> 62.5 | T86: =$A86*S86*$T$1 -> 0
C87: << ==== TOTAL UNITS | R87: =$A87*Q87 -> 0 | T87: =$A87*S87*$T$1 -> 0
A88: d> | B88: =(R87+T87) -> 0 | D88: Sell_A | E88: =IF($B77=0,0,ROUND(ROUND(($R88*$S$2+($T88*$T$2))/$B77, 2)*$C$2,2)) -> 127.13 | F88: =ROUND($B77*$E88,2) -> 1525.56 | K88: ITEM | L88: ITEM | R88: =SUM(R78:R87) -> 985.205 | T88: =SUM(T78:T87) -> 19.68
Q89: Multip
A90: 1 | B90: =Elec_Est!B2146 -> 3 | D90: 044# 5 x 4mm2 F120 Fire Resistant Cable (BS7846) - XLPE/SWA/LSZH | K90: RATE | L90: RATE | Q90: =B90/A90 -> 3 | R90: =IF($B90=0,0,IF($S$1="R",ROUND(R98/$B90,2),R98/$B90)) -> 46.64 | T90: =IF($B90=0,0,IF($S$1="R",ROUND(T98/$B90,2),T98/$B90)) -> 1.27
D91: Based on:
A92: =$Q$90 *(3) -> 9 | B92: m | D92: Power Cable 5c 4.0 mm2 PVC SWA-PVC | E92: Fire Rated | F92: Cleveland | G92: CAMC_077 | H92: 616 | I92: (__) | J92: 4.0mm2 | K92: 06-018 | O92: 2 | P92: 38371 | Q92: 11.19 | R92: =$A92*Q92 -> 100.71 | S92: 0.07 | T92: =$A92*S92*$T$1 -> 0.63
A93: =$Q$90 *(3) -> 9 | B93: No | D93: Cable Tie 225mm | G93: CONS_009 | H93: 875 | I93: (__) | K93: 01-003 | O93: 1 | P93: 34669 | Q93: 0.05 | R93: =$A93*Q93 -> 0.45 | T93: =$A93*S93*$T$1 -> 0
A94: =$Q$90 *(2) -> 6 | B94: No | D94: Gland Indoor 20 BWL 4*4/6mm2 | G94: CAAC_040 | H94: 620 | I94: CMP | O94: 2 | P94: 35431 | Q94: 4.71 | R94: =$A94*Q94 -> 28.26 | S94: 0.35 | T94: =$A94*S94*$T$1 -> 2.1
A95: =$Q$90 *(2) -> 6 | B95: m | D95: Cable Marker 8 digit c/w Carrier Strip | G95: CAAC_091 | H95: 620 | I95: (__) | O95: 2 | P95: 38148 | Q95: 1.5 | R95: =$A95*Q95 -> 9 | S95: 0.08 | T95: =$A95*S95*$T$1 -> 0.48
A96: =$Q$90 *(10) -> 30 | B96: No | D96: Cable Lug 4.0 mm2 | G96: CAAC_006 | H96: 620 | I96: CTT | O96: 2 | P96: 34669 | Q96: 0.05 | R96: =$A96*Q96 -> 1.5 | S96: 0.02 | T96: =$A96*S96*$T$1 -> 0.6
C97: << ==== TOTAL UNITS | R97: =$A97*Q97 -> 0 | T97: =$A97*S97*$T$1 -> 0
A98: d> | B98: =(R97+T97) -> 0 | D98: Sell_A | E98: =IF($B90=0,0,ROUND(ROUND(($R98*$S$2+($T98*$T$2))/$B90, 2)*$C$2,2)) -> 81.51 | F98: =ROUND($B90*$E98,2) -> 244.53 | K98: ITEM | L98: ITEM | R98: =SUM(R91:R97) -> 139.92 | T98: =SUM(T91:T97) -> 3.81
Q99: Multip
A100: 26 | B100: =Elec_Est!B2147 -> 26 | D100: 001# SFDI adjacent to each damper. | K100: RATE | L100: RATE | Q100: =B100/A100 -> 1 | R100: =IF($B100=0,0,IF($S$1="R",ROUND(R119/$B100,2),R119/$B100)) -> 330.73 | T100: =IF($B100=0,0,IF($S$1="R",ROUND(T119/$B100,2),T119/$B100)) -> 3.37
D101: Based on:
D102: Installation of SFDI
...

Sheet Elec_Est
B1: CLIENT: | C1: =ML_Sum!$C1 -> 1 | D1: =ML_Sum!$D1 -> Quintano Foods Ltd. | F1: =ML_Sum!$F1 -> 0 | I1: 1 | J1: =ML_Sum!$J1 -> 1 | K1: =ML_Sum!$K1 -> 1 | L1: =ML_Sum!$L1 -> 1 | M1: =ML_Sum!$M1 -> 1 | N1: =ML_Sum!$N1 -> 1 | O1: =ML_Sum!$O1 -> 1 | Q1: =ML_Sum!$Q1 -> € | R1: R/Lab Cont | S1: =ML_Sum!$S1 -> R | T1: =ML_Sum!$T1 -> 1 | U1: =ML_Sum!W1 -> BOQ | V1: INCL | W1: MULT | X1: AREA | Y1: BOQ | Z1: TDWG | AA1: ACT | AB1: DIFF
B2: PROJECT: | C2: =ML_Sum!$C2 -> 1 | D2: =ML_Sum!$D2 -> Warehouse at tal-Handaq, Qormi | F2: =ML_Sum!$F2 -> Electrical | I2: 2 | J2: =ML_Sum!$J2 -> 1 | K2: =ML_Sum!$K2 -> 1 | L2: =ML_Sum!$L2 -> 1 | M2: =ML_Sum!$M2 -> 1 | N2: =ML_Sum!$N2 -> 1 | O2: =ML_Sum!$O2 -> 1 | Q2: =ML_Sum!$Q2 -> 0 | R2: mu_A | S2: =ML_Sum!$S2 -> 1 | T2: =ML_Sum!$T2 -> 27.46
B3: JOB DESC: | C3: =ML_Sum!$C3 -> 1 | D3: =ML_Sum!$D3 -> Electrical installation for Mechanical (HVAC) - Revision B | F3: =ML_Sum!$F3 -> ECA | I3: 3 | J3: =ML_Sum!$J3 -> 1 | K3: =ML_Sum!$K3 -> 1 | L3: =ML_Sum!$L3 -> 1 | M3: =ML_Sum!$M3 -> 1 | N3: =ML_Sum!$N3 -> 1 | O3: =ML_Sum!$O3 -> 1 | Q3: =ML_Sum!$Q3 -> 0 | R3: mu_B | S3: =ML_Sum!$S3 -> 1 | T3: =ML_Sum!$T3 -> 27.46
B4: QUOTE No: | C4: =ML_Sum!$C4 -> 1 | D4: =ML_Sum!$D4 -> ELM-25-0085B | F4: =ML_Sum!$F4 -> 0 | I4: 4 | J4: =ML_Sum!$J4 -> 1 | K4: =ML_Sum!$K4 -> 1 | L4: =ML_Sum!$L4 -> 1 | M4: =ML_Sum!$M4 -> 1 | N4: =ML_Sum!$N4 -> 1 | O4: =ML_Sum!$O4 -> 1 | Q4: =ML_Sum!$Q4 -> 0 | R4: mu_C | S4: =ML_Sum!$S4 -> 1 | T4: =ML_Sum!$T4 -> 27.46
B5: CLIENTs REF: | C5: =ML_Sum!$C5 -> 1 | D5: =ML_Sum!$D5 -> Tender | F5: =ML_Sum!$F5 -> 0 | I5: 5 | J5: =ML_Sum!$J5 -> 1 | K5: =ML_Sum!$K5 -> 1 | L5: =ML_Sum!$L5 -> 1 | M5: =ML_Sum!$M5 -> 1 | N5: =ML_Sum!$N5 -> 1 | O5: =ML_Sum!$O5 -> 1 | Q5: =ML_Sum!$Q5 -> 0 | R5: mu_D | S5: =ML_Sum!$S5 -> 1 | T5: =ML_Sum!$T5 -> 27.46
B6: VAT/DUTIES: | C6: =ML_Sum!$C6 -> 1 | D6: =ML_Sum!$D6 -> VAT EXCL. | F6: =ML_Sum!$F6 -> 0 | I6: 6 | J6: =ML_Sum!$J6 -> 1 | K6: =ML_Sum!$K6 -> 1 | L6: =ML_Sum!$L6 -> 1 | M6: =ML_Sum!$M6 -> 1 | N6: =ML_Sum!$N6 -> 1 | O6: =ML_Sum!$O6 -> 1 | Q6: =ML_Sum!$Q6 -> 0 | R6: mu_E | S6: =ML_Sum!$S6 -> 1 | T6: =ML_Sum!$T6 -> 27.46
B7: SAVED ON: | C7: =ML_Sum!$C7 -> 1 | D7: 39364 | F7: =ML_Sum!$F7 -> 0 | I7: 7 | J7: =ML_Sum!$J7 -> 1 | K7: =ML_Sum!$K7 -> 1 | L7: =ML_Sum!$L7 -> 1 | M7: =ML_Sum!$M7 -> 1 | N7: =ML_Sum!$N7 -> 1 | O7: =ML_Sum!$O7 -> 0 | Q7: =ML_Sum!$Q7 -> 0 | R7: mu_F | S7: =ML_Sum!$S7 -> 1 | T7: =ML_Sum!$T7 -> 27.46
B8: ESTIMATOR: | C8: =ML_Sum!$C8 -> 1 | D8: =ML_Sum!$D8 -> T.Sammut | F8: =ML_Sum!$F8 -> 0 | I8: 8 | J8: =ML_Sum!$J8 -> 1 | K8: =ML_Sum!$K8 -> 1 | L8: =ML_Sum!$L8 -> 1 | M8: =ML_Sum!$M8 -> 1 | N8: =ML_Sum!$N8 -> 1 | O8: =ML_Sum!$O8 -> 0 | Q8: =ML_Sum!$Q8 -> 0 | R8: mu_G | S8: =ML_Sum!$S8 -> 1 | T8: =ML_Sum!$T8 -> 27.46
B9: LABOUR RATE: | C9: =ML_Sum!$C9 -> 1 | D9: =ML_Sum!$D9 -> 27.46 | F9: =ML_Sum!$F9 -> 0 | I9: 9 | J9: =ML_Sum!$J9 -> 1 | K9: =ML_Sum!$K9 -> 1 | L9: =ML_Sum!$L9 -> 1 | M9: =ML_Sum!$M9 -> 1 | N9: =ML_Sum!$N9 -> 1 | O9: =ML_Sum!$O9 -> 0 | Q9: =ML_Sum!$Q9 -> 0 | R9: mu_H | S9: =ML_Sum!$S9 -> 1 | T9: =ML_Sum!$T9 -> 27.46
C10: =ML_Sum!$C10 -> 1 | F10: =ML_Sum!$F10 -> 0 | I10: 10 | J10: =ML_Sum!$J10 -> 1 | K10: =ML_Sum!$K10 -> 1 | L10: =ML_Sum!$L10 -> 1 | M10: =ML_Sum!$M10 -> 1 | N10: =ML_Sum!$N10 -> 1 | O10: =ML_Sum!$O10 -> 1 | Q10: =ML_Sum!$Q10 -> 0 | R10: mu_I | S10: =ML_Sum!$S10 -> 1 | T10: =ML_Sum!$T10 -> 27.46
C11: =ML_Sum!$C11 -> 1 | F11: =ML_Sum!$F11 -> 0 | Q11: =ML_Sum!$Q11 -> 0 | R11: mu_J | S11: =ML_Sum!$S11 -> 1 | T11: =ML_Sum!$T11 -> 27.46
C12: =ML_Sum!$C12 -> 1 | F12: =ML_Sum!$F12 -> 0 | Q12: =ML_Sum!$Q12 -> 0 | R12: MIXED | S12: =ML_Sum!$S12 -> MAT MU | T12: =ML_Sum!$T12 -> LAB RATE
G13: ISELL | H13: C_CODE | I13: MAKE | J13: PART_NO | K13: MARKUP | L13: TYPE | M13: LIST_P | N13: P_FACT | O13: FIX | P13: DATE | Q13: %Dsct in BOQ | R13: MU TYPE | S13: MAT MU | T13: LAB RATE | AM13: Tot Mat Cost | AN13: Unit Lab phr. | AO13: Tot Lab phr. | AP13: < for ELM / MEE
K14: TB
C15: t | D15: Item: 2
D16: VENTILATION SYSTEM
K18: TB
C19: t
D20: FANS - BASEMENT LEVEL -1
K22: TB
C23: t
D24: Supply, install and connect the following In-line type extract fans c/w 2 silencers - one upstream and one downstream from the fan, variable speed controllers, anti-vibration mountings, chamfered bird screen, transformation pieces etc for a complete system inclusive of connecting up of fans to electrical supply.
E26: Sell Rate | F26: Sell Total | K26: IB | AG26: U_M_Sell | AH26: T_M_Sell | AI26: U_L_Sell | AJ26: T_L_Sell | AK26: Total_Sell | AM26: T_M_Cost | AN26: T_L_Phr | AO26: Mat/Lab=1
A27: 2 | B27: No. | D27: Item: 2.001 | E27: =IF(AND($A27=0,$A$1="DIF"),0, ROUND(ROUND(SUMIF($L29:$L35,"SUBI",$E29:$E35)/$A27,2)*$C$12,2)) -> 245.04 | F27: =ROUND($A27*$E27,2) -> 490.08 | G27: ISELL | L27: ITEM | T27: =IF(AND($R41=0,$T41=0),"0.00","mu :" & ROUND($F27/$C$12/($R41+$T41*$D$9),2)) -> mu :1 | AG27: =IF(A27=0,0,ROUND(SUM(AG29:AG41)/A27,2)) -> 166.5 | AH27: =$AG27*$A27 -> 333 | AI27: =$E27-$AG27 -> 78.54 | AJ27: =$A27*$AI27 -> 157.08 | AK27: =ROUND(($AG27+$AI27)*$A27,2) -> 490.08 | AM27: =ROUND(R41,2) -> 333 | AN27: =ROUND(T41,2) -> 5.72 | AO27: =ROUND(AM27+AN27,2)*A27 -> 677.44
D28: EF-B1U-01 F300 Extract Fan - Norm: 33,000m3/hr at 200Pa; Fire: 55,000m3/hr at 200Pa - installed at Level 0
E29: =F27/$C$12-SUMIF($L26:$L41,"SUBI",$E26:$E41) -> 0.01 | F29: Discrepancy
D30: =$F$2 -> Electrical | E30: =ROUND(($R34*$S$2 + ($T34*$T$2)), 2) -> 490.07 | F30: =$E30*$C$12 -> 490.07 | K30: mu_A | L30: SUBI
C31: h | D31: =CELL("Address",Elec_Rates!D$19) -> [ELM25_0085_Quintano_Elec_Mech_HVAC_Est_Rev_B.xlsx]Elec_Rates!$D$19 | G31: RATE_AAA
A32: 2 | B32: 1 | C32: =$A32*$B32 -> 2 | D32: =Elec_Rates!$D$19 -> 037# 5 x 16mm2 F120 Fire Resistant Cable (BS7846) - XLPE/SWA/LSZH | F32: Local Rate | G32: RTLO_001 | Q32: =$B32*Elec_Rates!$R$19 -> 166.5 | R32: =$A32*Q32 -> 333 | S32: =$B32*Elec_Rates!$T$19 -> 2.86 | T32: =$A32*S32 -> 5.72
R33: =$A33*Q33 -> 0 | T33: =$A33*S33*$T$1 -> 0
A34: d> | B34: =(R33+T33) -> 0 | K34: mu_A | L34: SUBI | R34: =SUM(R30:R33) -> 333 | T34: =SUM(T30:T33) -> 5.72 | AG34: =ROUND($R34*$S$2,2) -> 333
D35: =$F$3 -> ECA | E35: =ROUND(($R39*$S$3 + ($T39*$T$3)), 2) -> 0 | F35: =$F27-SUMIF($L29:$P32,"SUBI",$F29:$F32) -> 0.01 | K35: mu_B | L35: SUBI
B36: >>> mu_B material here >>> | R36: =$A36*Q36 -> 0 | T36: =$A36*S36*$T$1 -> 0
R37: =$A37*Q37 -> 0 | T37: =$A37*S37*$T$1 -> 0
R38: =$A38*Q38 -> 0 | T38: =$A38*S38*$T$1 -> 0
A39: d> | B39: =(R38+T38) -> 0 | K39: mu_B | L39: SUBI | R39: =SUM(R35:R38) -> 0 | T39: =SUM(T35:T38) -> 0 | AG39: =ROUND($R39*$S$3,2) -> 0
G41: ICOST | L41: ITEM | R41: =SUMIF($L28:$L40,"SUBI",R28:R40) -> 333 | T41: =SUMIF($L28:$L40,"SUBI",T28:T40) -> 5.72
E42: Sell Rate | F42: Sell Total | K42: IB | AG42: U_M_Sell | AH42: T_M_Sell | AI42: U_L_Sell | AJ42: T_L_Sell | AK42: Total_Sell | AM42: T_M_Cost | AN42: T_L_Phr | AO42: Mat/Lab=1
A43: 2 | B43: No. | D43: Item: 2.002 | E43: =IF(AND($A43=0,$A$1="DIF"),0, ROUND(ROUND(SUMIF($L45:$L51,"SUBI",$E45:$E51)/$A43,2)*$C$12,2)) -> 245.04 | F43: =ROUND($A43*$E43,2) -> 490.08 | G43: ISELL | L43: ITEM | T43: =IF(AND($R57=0,$T57=0),"0.00","mu :" & ROUND($F43/$C$12/($R57+$T57*$D$9),2)) -> mu :1 | AG43: =IF(A43=0,0,ROUND(SUM(AG45:AG57)/A43,2)) -> 166.5 | AH43: =$AG43*$A43 -> 333 | AI43: =$E43-$AG43 -> 78.54 | AJ43: =$A43*$AI43 -> 157.08 | AK43: =ROUND(($AG43+$AI43)*$A43,2) -> 490.08 | AM43: =ROUND(R57,2) -> 333 | AN43: =ROUND(T57,2) -> 5.72 | AO43: =ROUND(AM43+AN43,2)*A43 -> 677.44
D44: EF-B1L-01 F300 Extract Fan - Norm: 42,800m3/hr at 200Pa; Fire: 71,000m3/hr at 200Pa - installed at Level 0
E45: =F43/$C$12-SUMIF($L42:$L57,"SUBI",$E42:$E57) -> 0.01 | F45: Discrepancy
D46: =$F$2 -> Electrical | E46: =ROUND(($R50*$S$2 + ($T50*$T$2)), 2) -> 490.07 | F46: =$E46*$C$12 -> 490.07 | K46: mu_A | L46: SUBI
C47: h | D47: =CELL("Address",Elec_Rates!D$19) -> [ELM25_0085_Quintano_Elec_Mech_HVAC_Est_Rev_B.xlsx]Elec_Rates!$D$19 | G47: RATE_AAA
A48: 2 | B48: 1 | C48: =$A48*$B48 -> 2 | D48: =Elec_Rates!$D$19 -> 037# 5 x 16mm2 F120 Fire Resistant Cable (BS7846) - XLPE/SWA/LSZH | F48: Local Rate | G48: RTLO_001 | Q48: =$B48*Elec_Rates!$R$19 -> 166.5 | R48: =$A48*Q48 -> 333 | S48: =$B48*Elec_Rates!$T$19 -> 2.86 | T48: =$A48*S48 -> 5.72
R49: =$A49*Q49 -> 0 | T49: =$A49*S49*$T$1 -> 0
A50: d> | B50: =(R49+T49) -> 0 | K50: mu_A | L50: SUBI | R50: =SUM(R46:R49) -> 333 | T50: =SUM(T46:T49) -> 5.72 | AG50: =ROUND($R50*$S$2,2) -> 333
D51: =$F$3 -> ECA | E51: =ROUND(($R55*$S$3 + ($T55*$T$3)), 2) -> 0 | F51: =$F43-SUMIF($L45:$P48,"SUBI",$F45:$F48) -> 0.01 | K51: mu_B | L51: SUBI
B52: >>> mu_B material here >>> | R52: =$A52*Q52 -> 0 | T52: =$A52*S52*$T$1 -> 0
R53: =$A53*Q53 -> 0 | T53: =$A53*S53*$T$1 -> 0
R54: =$A54*Q54 -> 0 | T54: =$A54*S54*$T$1 -> 0
A55: d> | B55: =(R54+T54) -> 0 | K55: mu_B | L55: SUBI | R55: =SUM(R51:R54) -> 0 | T55: =SUM(T51:T54) -> 0 | AG55: =ROUND($R55*$S$3,2) -> 0
G57: ICOST | L57: ITEM | R57: =SUMIF($L44:$L56,"SUBI",R44:R56) -> 333 | T57: =SUMIF($L44:$L56,"SUBI",T44:T56) -> 5.72
E58: Sell Rate | F58: Sell Total | K58: IB | AG58: U_M_Sell | AH58: T_M_Sell | AI58: U_L_Sell | AJ58: T_L_Sell | AK58: Total_Sell | AM58: T_M_Cost | AN58: T_L_Phr | AO58: Mat/Lab=1
A59: 1 | B59: No. | D59: Item: 2.003 | E59: =IF(AND($A59=0,$A$1="DIF"),0, ROUND(ROUND(SUMIF($L61:$L67,"SUBI",$E61:$E67)/$A59,2)*$C$12,2)) -> 65.62 | F59: =ROUND($A59*$E59,2) -> 65.62 | G59: ISELL | L59: ITEM | T59: =IF(AND($R73=0,$T73=0),"0.00","mu :" & ROUND($F59/$C$12/($R73+$T73*$D$9),2)) -> mu :1 | AG59: =IF(A59=0,0,ROUND(SUM(AG61:AG73)/A59,2)) -> 20.04 | AH59: =$AG59*$A59 -> 20.04 | AI59: =$E59-$AG59 -> 45.58 | AJ59: =$A59*$AI59 -> 45.58 | AK59: =ROUND(($AG59+$AI59)*$A59,2) -> 65.62 | AM59: =ROUND(R73,2) -> 20.04 | AN59: =ROUND(T73,2) -> 1.66 | AO59: =ROUND(AM59+AN59,2)*A59 -> 21.7
D60: EF-B1U-02 Extract Fan - 1300m3/hr at 125Pa - installed at Level 0 | K60: n
E61: =F59/$C$12-SUMIF($L58:$L73,"SUBI",$E58:$E73) -> 0 | F61: Discrepancy
D62: =$F$2 -> Electrical | E62: =ROUND(($R66*$S$2 + ($T66*$T$2)), 2) -> 65.62 | F62: =$E62*$C$12 -> 65.62 | K62: mu_A | L62: SUBI
C63: h | D63: =CELL("Address",Elec_Rates!D$54) -> [ELM25_0085_Quintano_Elec_Mech_HVAC_Est_Rev_B.xlsx]Elec_Rates!$D$54 | G63: RATE_AAA
A64: 1 | B64: 1 | C64: =$A64*$B64 -> 1 | D64: =Elec_Rates!$D$54 -> 046# 3 x 4mm2 XLPE/SWA/LSZH | F64: Local Rate | G64: RTLO_001 | Q64: =$B64*Elec_Rates!$R$54 -> 20.04 | R64: =$A64*Q64 -> 20.04 | S64: =$B64*Elec_Rates!$T$54 -> 1.66 | T64: =$A64*S64 -> 1.66
R65: =$A65*Q65 -> 0 | T65: =$A65*S65*$T$1 -> 0
A66: d> | B66: =(R65+T65) -> 0 | K66: mu_A | L66: SUBI | R66: =SUM(R62:R65) -> 20.04 | T66: =SUM(T62:T65) -> 1.66 | AG66: =ROUND($R66*$S$2,2) -> 20.04
D67: =$F$3 -> ECA | E67: =ROUND(($R71*$S$3 + ($T71*$T$3)), 2) -> 0 | F67: =$F59-SUMIF($L61:$P64,"SUBI",$F61:$F64) -> 0 | K67: mu_B | L67: SUBI
B68: >>> mu_B material here >>> | R68: =$A68*Q68 -> 0 | T68: =$A68*S68*$T$1 -> 0
R69: =$A69*Q69 -> 0 | T69: =$A69*S69*$T$1 -> 0
R70: =$A70*Q70 -> 0 | T70: =$A70*S70*$T$1 -> 0
A71: d> | B71: =(R70+T70) -> 0 | K71: mu_B | L71: SUBI | R71: =SUM(R67:R70) -> 0 | T71: =SUM(T67:T70) -> 0 | AG71: =ROUND($R71*$S$3,2) -> 0
G73: ICOST | L73: ITEM | R73: =SUMIF($L60:$L72,"SUBI",R60:R72) -> 20.04 | T73: =SUMIF($L60:$L72,"SUBI",T60:T72) -> 1.66
E74: Sell Rate | F74: Sell Total | K74: IB | AG74: U_M_Sell | AH74: T_M_Sell | AI74: U_L_Sell | AJ74: T_L_Sell | AK74: Total_Sell | AM74: T_M_Cost | AN74: T_L_Phr | AO74: Mat/Lab=1
A75: 1 | B75: No. | D75: Item: 2.004 | E75: =IF(AND($A75=0,$A$1="DIF"),0, ROUND(ROUND(SUMIF($L77:$L83,"SUBI",$E77:$E83)/$A75,2)*$C$12,2)) -> 73.04 | F75: =ROUND($A75*$E75,2) -> 73.04 | G75: ISELL | L75: ITEM | T75: =IF(AND($R89=0,$T89=0),"0.00","mu :" & ROUND($F75/$C$12/($R89+$T89*$D$9),2)) -> mu :1 | AG75: =IF(A75=0,0,ROUND(SUM(AG77:AG89)/A75,2)) -> 24.44 | AH75: =$AG75*$A75 -> 24.44 | AI75: =$E75-$AG75 -> 48.6 | AJ75: =$A75*$AI75 -> 48.6 | AK75: =ROUND(($AG75+$AI75)*$A75,2) -> 73.04 | AM75: =ROUND(R89,2) -> 24.44 | AN75: =ROUND(T89,2) -> 1.77 | AO75: =ROUND(AM75+AN75,2)*A75 -> 26.21
D76: EF-B1L-02 Extract Fan - 32,000m3/hr at 250Pa - installed at Level 1 | K76: n
E77: =F75/$C$12-SUMIF($L74:$L89,"SUBI",$E74:$E89) -> 0 | F77: Discrepancy
D78: =$F$2 -> Electrical | E78: =ROUND(($R82*$S$2 + ($T82*$T$2)), 2) -> 73.04 | F78: =$E78*$C$12 -> 73.04 | K78: mu_A | L78: SUBI
C79: h | D79: =CELL("Address",Elec_Rates!D$43) -> [ELM25_0085_Quintano_Elec_Mech_HVAC_Est_Rev_B.xlsx]Elec_Rates!$D$43 | G79: RATE_AAA
A80: 1 | B80: 1 | C80: =$A80*$B80 -> 1 | D80: =Elec_Rates!$D$43 -> 045# 5 x 4mm2 XLPE/SWA/LSZH | F80: Local Rate | G80: RTLO_002 | Q80: =$B80*Elec_Rates!$R$43 -> 24.44 | R80: =$A80*Q80 -> 24.44 | S80: =$B80*Elec_Rates!$T$43 -> 1.77 | T80: =$A80*S80 -> 1.77
R81: =$A81*Q81 -> 0 | T81: =$A81*S81*$T$1 -> 0
A82: d> | B82: =(R81+T81) -> 0 | K82: mu_A | L82: SUBI | R82: =SUM(R78:R81) -> 24.44 | T82: =SUM(T78:T81) -> 1.77 | AG82: =ROUND($R82*$S$2,2) -> 24.44
D83: =$F$3 -> ECA | E83: =ROUND(($R87*$S$3 + ($T87*$T$3)), 2) -> 0 | F83: =$F75-SUMIF($L77:$P80,"SUBI",$F77:$F80) -> 0 | K83: mu_B | L83: SUBI
B84: >>> mu_B material here >>> | R84: =$A84*Q84 -> 0 | T84: =$A84*S84*$T$1 -> 0
R85: =$A85*Q85 -> 0 | T85: =$A85*S85*$T$1 -> 0
R86: =$A86*Q86 -> 0 | T86: =$A86*S86*$T$1 -> 0
A87: d> | B87: =(R86+T86) -> 0 | K87: mu_B | L87: SUBI | R87: =SUM(R83:R86) -> 0 | T87: =SUM(T83:T86) -> 0 | AG87: =ROUND($R87*$S$3,2) -> 0
G89: ICOST | L89: ITEM | R89: =SUMIF($L76:$L88,"SUBI",R76:R88) -> 24.44 | T89: =SUMIF($L76:$L88,"SUBI",T76:T88) -> 1.77
E90: Sell Rate | F90: Sell Total | K90: IB | AG90: U_M_Sell | AH90: T_M_Sell | AI90: U_L_Sell | AJ90: T_L_Sell | AK90: Total_Sell | AM90: T_M_Cost | AN90: T_L_Phr | AO90: Mat/Lab=1
A91: 1 | B91: No. | D91: Item: 2.005 | E91: =IF(AND($A91=0,$A$1="DIF"),0, ROUND(ROUND(SUMIF($L93:$L100,"SUBI",$E93:$E100)/$A91,2)*$C$12,2)) -> 73.04 | F91: =ROUND($A91*$E91,2) -> 73.04 | G91: ISELL | L91: ITEM | T91: =IF(AND($R106=0,$T106=0),"0.00","mu :" & ROUND($F91/$C$12/($R106+$T106*$D$9),2)) -> mu :1 | AG91: =IF(A91=0,0,ROUND(SUM(AG93:AG106)/A91,2)) -> 24.44 | AH91: =$AG91*$A91 -> 24.44 | AI91: =$E91-$AG91 -> 48.6 | AJ91: =$A91*$AI91 -> 48.6 | AK91: =ROUND(($AG91+$AI91)*$A91,2) -> 73.04 | AM91: =ROUND(R106,2) -> 24.44 | AN91: =ROUND(T106,2) -> 1.77 | AO91: =ROUND(AM91+AN91,2)*A91 -> 26.21
D92: SF-B1L-01 Supply Fan - 35,000m3/hr at 250Pa - installed at Basement Level -1 | K92: n
E93: =F91/$C$12-SUMIF($L90:$L106,"SUBI",$E90:$E106) -> 0 | F93: Discrepancy
D94: =$F$2 -> Electrical | E94: =ROUND(($R99*$S$2 + ($T99*$T$2)), 2) -> 73.04 | F94: =$E94*$C$12 -> 73.04 | K94: mu_A | L94: SUBI
C95: h | D95: =CELL("Address",Elec_Rates!D$43) -> [ELM25_0085_Quintano_Elec_Mech_HVAC_Est_Rev_B.xlsx]Elec_Rates!$D$43 | G95: RATE_AAA
A96: 1 | B96: 1 | C96: =$A96*$B96 -> 1 | D96: =Elec_Rates!$D$43 -> 045# 5 x 4mm2 XLPE/SWA/LSZH | F96: Local Rate | G96: RTLO_002 | Q96: =$B96*Elec_Rates!$R$43 -> 24.44 | R96: =$A96*Q96 -> 24.44 | S96: =$B96*Elec_Rates!$T$43 -> 1.77 | T96: =$A96*S96 -> 1.77
D97: Filter dirty indication - in item 2.006
R98: =$A98*Q98 -> 0 | T98: =$A98*S98*$T$1 -> 0
A99: d> | B99: =(R98+T98) -> 0 | K99: mu_A | L99: SUBI | R99: =SUM(R94:R98) -> 24.44 | T99: =SUM(T94:T98) -> 1.77 | AG99: =ROUND($R99*$S$2,2) -> 24.44
D100: =$F$3 -> ECA | E100: =ROUND(($R104*$S$3 + ($T104*$T$3)), 2) -> 0 | F100: =$F91-SUMIF($L93:$P96,"SUBI",$F93:$F96) -> 0 | K100: mu_B | L100: SUBI
B101: >>> mu_B material here >>> | R101: =$A101*Q101 -> 0 | T101: =$A101*S101*$T$1 -> 0
R102: =$A102*Q102 -> 0 | T102: =$A102*S102*$T$1 -> 0
R103: =$A103*Q103 -> 0 | T103: =$A103*S103*$T$1 -> 0
A104: d> | B104: =(R103+T103) -> 0 | K104: mu_B | L104: SUBI | R104: =SUM(R100:R103) -> 0 | T104: =SUM(T100:T103) -> 0 | AG104: =ROUND($R104*$S$3,2) -> 0
G106: ICOST | L106: ITEM | R106: =SUMIF($L92:$L105,"SUBI",R92:R105) -> 24.44 | T106: =SUMIF($L92:$L105,"SUBI",T92:T105) -> 1.77
E107: Sell Rate | F107: Sell Total | K107: IB | AG107: U_M_Sell | AH107: T_M_Sell | AI107: U_L_Sell | AJ107: T_L_Sell | AK107: Total_Sell | AM107: T_M_Cost | AN107: T_L_Phr | AO107: Mat/Lab=1
A108: 1 | B108: No. | D108: Item: 2.006 | E108: =IF(AND($A108=0,$A$1="DIF"),0, ROUND(ROUND(($R118*$S$2+($T118*$T$2))/A108,2)*$C$2,2)) -> 309.67 | F108: =ROUND($A108*$E108,2) -> 309.67 | G108: ISELL | K108: mu_A | L108: ITEM | T108: =IF(AND($R118=0,$T118=0),"0.00","mu :" & ROUND($F108/$C$2/($R118+$T118*$D$9),2)) -> mu :1 | AG108: =IF($E108=0,0,ROUND($R118*$S$2*$C$2/$A108,2)) -> 114.98 | AH108: =$AG108*$A108 -> 114.98 | AI108: =$E108-$AG108 -> 194.69 | AJ108: =$A108*$AI108 -> 194.69 | AK108: =ROUND(($AG108+$AI108)*$A108,2) -> 309.67 | AM108: =ROUND(R118,2) -> 114.98 | AN108: =ROUND(T118,2) -> 7.09 | AO108: =ROUND(AM108+AN108,2)*A108 -> 122.07
...

Sheet HVAC_BOQ
B2: SECTION 2 - HVAC
A4: ITEM | B4: DESCRIPTION | C4: QTY | D4: UNIT | E4: RATE Euro (Exc of VAT) | F4: TOTAL Euro (Exc of VAT) | G4: Material cost to Panta Ex VAT | H4: Labour pair hours @ €27.46per pair hour | I4: Labour pair hours @ €52.92per pair hour
A5: 1 | B5: PRELIMINARIES
B6: All equipment to be used within this contract is to be approved prior to delivery to site.
A7: =IFERROR(IF(OFFSET(A7,-1,0)>0,OFFSET(A7,-1,0)+0.001,ERROR.TYPE(0)),IFERROR(IF(OFFSET(A7,-2,0)>0,OFFSET(A7,-2,0)+0.001,ERROR.TYPE(0)),IFERROR(IF(OFFSET(A7,-3,0)>0,OFFSET(A7,-3,0)+0.001,ERROR.TYPE(0)),IFERROR(IF(OFFSET(A7,-4,0)>0,OFFSET(A7,-4,0)+0.001,ERROR.TYPE(0)),IFERROR(IF(OFFSET(A7,-5,0)>0,OFFSET(A7,-5,0)+0.001,ERROR.TYPE(0)),IFERROR(IF(OFFSET(A7,-6,0)>0,OFFSET(A7,-6,0)+0.001,ERROR.TYPE(0)),IFERROR(IF(OFFSET(A7,-7,0)>0,OFFSET(A7,-7,0)+0.001,ERROR.TYPE(0)),IFERROR(IF(OFFSET(A7,-8,0)>0,OFFSET(A7,-8,0)+0.001,ERROR.TYPE(0)),IFERROR(IF(OFFSET(A7,-9,0)>0,OFFSET(A7,-9,0)+0.001,ERROR.TYPE(0)),IFERROR(IF(OFFSET(A7,-10,0)>0,OFFSET(A7,-10,0)+0.001,ERROR.TYPE(0)),ERROR.TYPE(0))))))))))) -> 1.001 | B7: Mobilisation of site including the setting up of Storage facilities for materials, Sanitary facilities for the employees, Setting up of temporary site office, etc required to undertake the works | C7: 1 | D7: L.S. | F7: =IFERROR($C7*E7,E7) -> 0
A8: =IFERROR(IF(OFFSET(A8,-1,0)>0,OFFSET(A8,-1,0)+0.001,ERROR.TYPE(0)),IFERROR(IF(OFFSET(A8,-2,0)>0,OFFSET(A8,-2,0)+0.001,ERROR.TYPE(0)),IFERROR(IF(OFFSET(A8,-3,0)>0,OFFSET(A8,-3,0)+0.001,ERROR.TYPE(0)),IFERROR(IF(OFFSET(A8,-4,0)>0,OFFSET(A8,-4,0)+0.001,ERROR.TYPE(0)),IFERROR(IF(OFFSET(A8,-5,0)>0,OFFSET(A8,-5,0)+0.001,ERROR.TYPE(0)),IFERROR(IF(OFFSET(A8,-6,0)>0,OFFSET(A8,-6,0)+0.001,ERROR.TYPE(0)),IFERROR(IF(OFFSET(A8,-7,0)>0,OFFSET(A8,-7,0)+0.001,ERROR.TYPE(0)),IFERROR(IF(OFFSET(A8,-8,0)>0,OFFSET(A8,-8,0)+0.001,ERROR.TYPE(0)),IFERROR(IF(OFFSET(A8,-9,0)>0,OFFSET(A8,-9,0)+0.001,ERROR.TYPE(0)),IFERROR(IF(OFFSET(A8,-10,0)>0,OFFSET(A8,-10,0)+0.001,ERROR.TYPE(0)),ERROR.TYPE(0))))))))))) -> 1.002 | B8: Provision of insurance cover in the joint names of the Client and Contractor insure the Works against loss or damage by fire, storm, tempest, lightning, flood, earthquake, aircraft or anything dropped there from, aerial objects, riot and civil commotion for the full reinstatement value thereof plus 15% of all the Works executed and all unfixed materials and goods so insured until the completion of the Works. The Contractor shall affect a policy of insurance against third party risks to cover an amount of not less than Euro 500,000 (five hundred thousand Euros) for any one accident. The policy shall be in joint names of the Client and Contractor and shall include cross liability clauses. In respect of liability for the death or injury to any person employed by the Contractor and arising out of and in the course of such person's employment by the Contractor the amount insured by the Contractor shall be such as to indemnify the Client against all damages as compensation payable. The Contractor shall comply with and be subject to the terms, exclusions, exceptions, conditions and limitations of the insurance policies and shall bear the amount of the retained liabilities stated therein The Contractor shall deposit with the Client copies of the policy or policies and a copy of the receipt in respect of premiums paid before starting the Works | C8: 1 | D8: L.S. | F8: =IFERROR($C8*E8,E8) -> 0
A9: =IFERROR(IF(OFFSET(A9,-1,0)>0,OFFSET(A9,-1,0)+0.001,ERROR.TYPE(0)),IFERROR(IF(OFFSET(A9,-2,0)>0,OFFSET(A9,-2,0)+0.001,ERROR.TYPE(0)),IFERROR(IF(OFFSET(A9,-3,0)>0,OFFSET(A9,-3,0)+0.001,ERROR.TYPE(0)),IFERROR(IF(OFFSET(A9,-4,0)>0,OFFSET(A9,-4,0)+0.001,ERROR.TYPE(0)),IFERROR(IF(OFFSET(A9,-5,0)>0,OFFSET(A9,-5,0)+0.001,ERROR.TYPE(0)),IFERROR(IF(OFFSET(A9,-6,0)>0,OFFSET(A9,-6,0)+0.001,ERROR.TYPE(0)),IFERROR(IF(OFFSET(A9,-7,0)>0,OFFSET(A9,-7,0)+0.001,ERROR.TYPE(0)),IFERROR(IF(OFFSET(A9,-8,0)>0,OFFSET(A9,-8,0)+0.001,ERROR.TYPE(0)),IFERROR(IF(OFFSET(A9,-9,0)>0,OFFSET(A9,-9,0)+0.001,ERROR.TYPE(0)),IFERROR(IF(OFFSET(A9,-10,0)>0,OFFSET(A9,-10,0)+0.001,ERROR.TYPE(0)),ERROR.TYPE(0))))))))))) -> 1.003 | B9: Implementation of health and safety measures on site including personal safety (e.g safety shoes, helmets scaffolding, harnesses etc) as well as those to render the site safe for employees (e.g staircase handrails, closing of lift shaft openings etc) | C9: 1 | D9: L.S. | F9: =IFERROR($C9*E9,E9) -> 0
A10: =IFERROR(IF(OFFSET(A10,-1,0)>0,OFFSET(A10,-1,0)+0.001,ERROR.TYPE(0)),IFERROR(IF(OFFSET(A10,-2,0)>0,OFFSET(A10,-2,0)+0.001,ERROR.TYPE(0)),IFERROR(IF(OFFSET(A10,-3,0)>0,OFFSET(A10,-3,0)+0.001,ERROR.TYPE(0)),IFERROR(IF(OFFSET(A10,-4,0)>0,OFFSET(A10,-4,0)+0.001,ERROR.TYPE(0)),IFERROR(IF(OFFSET(A10,-5,0)>0,OFFSET(A10,-5,0)+0.001,ERROR.TYPE(0)),IFERROR(IF(OFFSET(A10,-6,0)>0,OFFSET(A10,-6,0)+0.001,ERROR.TYPE(0)),IFERROR(IF(OFFSET(A10,-7,0)>0,OFFSET(A10,-7,0)+0.001,ERROR.TYPE(0)),IFERROR(IF(OFFSET(A10,-8,0)>0,OFFSET(A10,-8,0)+0.001,ERROR.TYPE(0)),IFERROR(IF(OFFSET(A10,-9,0)>0,OFFSET(A10,-9,0)+0.001,ERROR.TYPE(0)),IFERROR(IF(OFFSET(A10,-10,0)>0,OFFSET(A10,-10,0)+0.001,ERROR.TYPE(0)),ERROR.TYPE(0))))))))))) -> 1.004 | B10: Prepare a risk assessment report outlining all risks involved and measures to be taken to minimise or eliminate potential risks. The report is to be prepared and signed by a competent person and to be submitted within three weeks from commencement of works. | C10: 1 | D10: L.S. | F10: =IFERROR($C10*E10,E10) -> 0
A11: =IFERROR(IF(OFFSET(A11,-1,0)>0,OFFSET(A11,-1,0)+0.001,ERROR.TYPE(0)),IFERROR(IF(OFFSET(A11,-2,0)>0,OFFSET(A11,-2,0)+0.001,ERROR.TYPE(0)),IFERROR(IF(OFFSET(A11,-3,0)>0,OFFSET(A11,-3,0)+0.001,ERROR.TYPE(0)),IFERROR(IF(OFFSET(A11,-4,0)>0,OFFSET(A11,-4,0)+0.001,ERROR.TYPE(0)),IFERROR(IF(OFFSET(A11,-5,0)>0,OFFSET(A11,-5,0)+0.001,ERROR.TYPE(0)),IFERROR(IF(OFFSET(A11,-6,0)>0,OFFSET(A11,-6,0)+0.001,ERROR.TYPE(0)),IFERROR(IF(OFFSET(A11,-7,0)>0,OFFSET(A11,-7,0)+0.001,ERROR.TYPE(0)),IFERROR(IF(OFFSET(A11,-8,0)>0,OFFSET(A11,-8,0)+0.001,ERROR.TYPE(0)),IFERROR(IF(OFFSET(A11,-9,0)>0,OFFSET(A11,-9,0)+0.001,ERROR.TYPE(0)),IFERROR(IF(OFFSET(A11,-10,0)>0,OFFSET(A11,-10,0)+0.001,ERROR.TYPE(0)),ERROR.TYPE(0))))))))))) -> 1.005 | B11: Allow for carrying out all surveys, setting out of works unless included elsewhere in the Bills of Quantities. | C11: 1 | D11: L.S. | F11: =IFERROR($C11*E11,E11) -> 0
A12: P | B12: TOTAL FOR PAGE 01 | C12: Euro Exc VAT | F12: =SUM(F7:F11) -> 0 | G12: =SUM(G7:G11) -> 0 | H12: =SUM(H7:H11) -> 0 | I12: =SUM(I7:I11) -> 0
A15: ITEM | B15: DESCRIPTION | C15: QTY | D15: UNIT | E15: RATE Euro (Exc of VAT) | F15: TOTAL Euro (Exc of VAT) | G15: Material cost to Panta Ex VAT | H15: Labour pair hours @ €27.46per pair hour | I15: Labour pair hours @ €52.92per pair hour
A16: =IFERROR(IF(OFFSET(A16,-1,0)>0,OFFSET(A16,-1,0)+0.001,ERROR.TYPE(0)),IFERROR(IF(OFFSET(A16,-2,0)>0,OFFSET(A16,-2,0)+0.001,ERROR.TYPE(0)),IFERROR(IF(OFFSET(A16,-3,0)>0,OFFSET(A16,-3,0)+0.001,ERROR.TYPE(0)),IFERROR(IF(OFFSET(A16,-4,0)>0,OFFSET(A16,-4,0)+0.001,ERROR.TYPE(0)),IFERROR(IF(OFFSET(A16,-5,0)>0,OFFSET(A16,-5,0)+0.001,ERROR.TYPE(0)),IFERROR(IF(OFFSET(A16,-6,0)>0,OFFSET(A16,-6,0)+0.001,ERROR.TYPE(0)),IFERROR(IF(OFFSET(A16,-7,0)>0,OFFSET(A16,-7,0)+0.001,ERROR.TYPE(0)),IFERROR(IF(OFFSET(A16,-8,0)>0,OFFSET(A16,-8,0)+0.001,ERROR.TYPE(0)),IFERROR(IF(OFFSET(A16,-9,0)>0,OFFSET(A16,-9,0)+0.001,ERROR.TYPE(0)),IFERROR(IF(OFFSET(A16,-10,0)>0,OFFSET(A16,-10,0)+0.001,ERROR.TYPE(0)),ERROR.TYPE(0))))))))))) -> 1.006 | B16: Provision for attending to site to take all relevant measurements in order to ascertain the exact quantities of the individual and measured items to be procured as well as keeping of all relevant records of personnel attendance, stock control etc | C16: 1 | D16: L.S. | F16: =IFERROR($C16*E16,E16) -> 0
A17: =IFERROR(IF(OFFSET(A17,-1,0)>0,OFFSET(A17,-1,0)+0.001,ERROR.TYPE(0)),IFERROR(IF(OFFSET(A17,-2,0)>0,OFFSET(A17,-2,0)+0.001,ERROR.TYPE(0)),IFERROR(IF(OFFSET(A17,-3,0)>0,OFFSET(A17,-3,0)+0.001,ERROR.TYPE(0)),IFERROR(IF(OFFSET(A17,-4,0)>0,OFFSET(A17,-4,0)+0.001,ERROR.TYPE(0)),IFERROR(IF(OFFSET(A17,-5,0)>0,OFFSET(A17,-5,0)+0.001,ERROR.TYPE(0)),IFERROR(IF(OFFSET(A17,-6,0)>0,OFFSET(A17,-6,0)+0.001,ERROR.TYPE(0)),IFERROR(IF(OFFSET(A17,-7,0)>0,OFFSET(A17,-7,0)+0.001,ERROR.TYPE(0)),IFERROR(IF(OFFSET(A17,-8,0)>0,OFFSET(A17,-8,0)+0.001,ERROR.TYPE(0)),IFERROR(IF(OFFSET(A17,-9,0)>0,OFFSET(A17,-9,0)+0.001,ERROR.TYPE(0)),IFERROR(IF(OFFSET(A17,-10,0)>0,OFFSET(A17,-10,0)+0.001,ERROR.TYPE(0)),ERROR.TYPE(0))))))))))) -> 1.007 | B17: Provision of security measures on site both as regards the storage facilities as well as to safeguard the materials installed during the latter stages of the project. | C17: 1 | D17: L.S. | F17: =IFERROR($C17*E17,E17) -> 0
A18: =IFERROR(IF(OFFSET(A18,-1,0)>0,OFFSET(A18,-1,0)+0.001,ERROR.TYPE(0)),IFERROR(IF(OFFSET(A18,-2,0)>0,OFFSET(A18,-2,0)+0.001,ERROR.TYPE(0)),IFERROR(IF(OFFSET(A18,-3,0)>0,OFFSET(A18,-3,0)+0.001,ERROR.TYPE(0)),IFERROR(IF(OFFSET(A18,-4,0)>0,OFFSET(A18,-4,0)+0.001,ERROR.TYPE(0)),IFERROR(IF(OFFSET(A18,-5,0)>0,OFFSET(A18,-5,0)+0.001,ERROR.TYPE(0)),IFERROR(IF(OFFSET(A18,-6,0)>0,OFFSET(A18,-6,0)+0.001,ERROR.TYPE(0)),IFERROR(IF(OFFSET(A18,-7,0)>0,OFFSET(A18,-7,0)+0.001,ERROR.TYPE(0)),IFERROR(IF(OFFSET(A18,-8,0)>0,OFFSET(A18,-8,0)+0.001,ERROR.TYPE(0)),IFERROR(IF(OFFSET(A18,-9,0)>0,OFFSET(A18,-9,0)+0.001,ERROR.TYPE(0)),IFERROR(IF(OFFSET(A18,-10,0)>0,OFFSET(A18,-10,0)+0.001,ERROR.TYPE(0)),ERROR.TYPE(0))))))))))) -> 1.008 | B18: Provision for the supply and delivery to site of samples as may be requested by the client / engineer | C18: 1 | D18: L.S. | F18: =IFERROR($C18*E18,E18) -> 0
A19: =IFERROR(IF(OFFSET(A19,-1,0)>0,OFFSET(A19,-1,0)+0.001,ERROR.TYPE(0)),IFERROR(IF(OFFSET(A19,-2,0)>0,OFFSET(A19,-2,0)+0.001,ERROR.TYPE(0)),IFERROR(IF(OFFSET(A19,-3,0)>0,OFFSET(A19,-3,0)+0.001,ERROR.TYPE(0)),IFERROR(IF(OFFSET(A19,-4,0)>0,OFFSET(A19,-4,0)+0.001,ERROR.TYPE(0)),IFERROR(IF(OFFSET(A19,-5,0)>0,OFFSET(A19,-5,0)+0.001,ERROR.TYPE(0)),IFERROR(IF(OFFSET(A19,-6,0)>0,OFFSET(A19,-6,0)+0.001,ERROR.TYPE(0)),IFERROR(IF(OFFSET(A19,-7,0)>0,OFFSET(A19,-7,0)+0.001,ERROR.TYPE(0)),IFERROR(IF(OFFSET(A19,-8,0)>0,OFFSET(A19,-8,0)+0.001,ERROR.TYPE(0)),IFERROR(IF(OFFSET(A19,-9,0)>0,OFFSET(A19,-9,0)+0.001,ERROR.TYPE(0)),IFERROR(IF(OFFSET(A19,-10,0)>0,OFFSET(A19,-10,0)+0.001,ERROR.TYPE(0)),ERROR.TYPE(0))))))))))) -> 1.009 | B19: Allow for continuously keeping the site and building clean and in a workman type condition free from debris, surplus materials and any other type of loose matter arising from works, which will disturb the proper conditions of any internal and external areas, roads and/or adjoining structures. Site Cleaning is to take place during the whole duration of works. Client reserves the right to employ cleaning companies at the contractor's expense if the contractor fails to keep the site clean. | C19: 1 | D19: L.S. | F19: =IFERROR($C19*E19,E19) -> 0
A20: =IFERROR(IF(OFFSET(A20,-1,0)>0,OFFSET(A20,-1,0)+0.001,ERROR.TYPE(0)),IFERROR(IF(OFFSET(A20,-2,0)>0,OFFSET(A20,-2,0)+0.001,ERROR.TYPE(0)),IFERROR(IF(OFFSET(A20,-3,0)>0,OFFSET(A20,-3,0)+0.001,ERROR.TYPE(0)),IFERROR(IF(OFFSET(A20,-4,0)>0,OFFSET(A20,-4,0)+0.001,ERROR.TYPE(0)),IFERROR(IF(OFFSET(A20,-5,0)>0,OFFSET(A20,-5,0)+0.001,ERROR.TYPE(0)),IFERROR(IF(OFFSET(A20,-6,0)>0,OFFSET(A20,-6,0)+0.001,ERROR.TYPE(0)),IFERROR(IF(OFFSET(A20,-7,0)>0,OFFSET(A20,-7,0)+0.001,ERROR.TYPE(0)),IFERROR(IF(OFFSET(A20,-8,0)>0,OFFSET(A20,-8,0)+0.001,ERROR.TYPE(0)),IFERROR(IF(OFFSET(A20,-9,0)>0,OFFSET(A20,-9,0)+0.001,ERROR.TYPE(0)),IFERROR(IF(OFFSET(A20,-10,0)>0,OFFSET(A20,-10,0)+0.001,ERROR.TYPE(0)),ERROR.TYPE(0))))))))))) -> 1.01 | B20: Provision for hauling of equipment on site, including cranage, permits and all necessary fees. | C20: 1 | D20: L.S. | F20: =IFERROR($C20*E20,E20) -> 0
A21: =IFERROR(IF(OFFSET(A21,-1,0)>0,OFFSET(A21,-1,0)+0.001,ERROR.TYPE(0)),IFERROR(IF(OFFSET(A21,-2,0)>0,OFFSET(A21,-2,0)+0.001,ERROR.TYPE(0)),IFERROR(IF(OFFSET(A21,-3,0)>0,OFFSET(A21,-3,0)+0.001,ERROR.TYPE(0)),IFERROR(IF(OFFSET(A21,-4,0)>0,OFFSET(A21,-4,0)+0.001,ERROR.TYPE(0)),IFERROR(IF(OFFSET(A21,-5,0)>0,OFFSET(A21,-5,0)+0.001,ERROR.TYPE(0)),IFERROR(IF(OFFSET(A21,-6,0)>0,OFFSET(A21,-6,0)+0.001,ERROR.TYPE(0)),IFERROR(IF(OFFSET(A21,-7,0)>0,OFFSET(A21,-7,0)+0.001,ERROR.TYPE(0)),IFERROR(IF(OFFSET(A21,-8,0)>0,OFFSET(A21,-8,0)+0.001,ERROR.TYPE(0)),IFERROR(IF(OFFSET(A21,-9,0)>0,OFFSET(A21,-9,0)+0.001,ERROR.TYPE(0)),IFERROR(IF(OFFSET(A21,-10,0)>0,OFFSET(A21,-10,0)+0.001,ERROR.TYPE(0)),ERROR.TYPE(0))))))))))) -> 1.011 | B21: Provision for working at height, including scaffolding, cherry pickers etc. All equipment shall be fully certified. | C21: 1 | D21: L.S. | F21: =IFERROR($C21*E21,E21) -> 0
A22: =IFERROR(IF(OFFSET(A22,-1,0)>0,OFFSET(A22,-1,0)+0.001,ERROR.TYPE(0)),IFERROR(IF(OFFSET(A22,-2,0)>0,OFFSET(A22,-2,0)+0.001,ERROR.TYPE(0)),IFERROR(IF(OFFSET(A22,-3,0)>0,OFFSET(A22,-3,0)+0.001,ERROR.TYPE(0)),IFERROR(IF(OFFSET(A22,-4,0)>0,OFFSET(A22,-4,0)+0.001,ERROR.TYPE(0)),IFERROR(IF(OFFSET(A22,-5,0)>0,OFFSET(A22,-5,0)+0.001,ERROR.TYPE(0)),IFERROR(IF(OFFSET(A22,-6,0)>0,OFFSET(A22,-6,0)+0.001,ERROR.TYPE(0)),IFERROR(IF(OFFSET(A22,-7,0)>0,OFFSET(A22,-7,0)+0.001,ERROR.TYPE(0)),IFERROR(IF(OFFSET(A22,-8,0)>0,OFFSET(A22,-8,0)+0.001,ERROR.TYPE(0)),IFERROR(IF(OFFSET(A22,-9,0)>0,OFFSET(A22,-9,0)+0.001,ERROR.TYPE(0)),IFERROR(IF(OFFSET(A22,-10,0)>0,OFFSET(A22,-10,0)+0.001,ERROR.TYPE(0)),ERROR.TYPE(0))))))))))) -> 1.012 | B22: Provision for Builders Work in order to prepare all openings required to install conduits, pipework, ductwork, etc., and making good and reinstatement of all openings. | C22: 1 | D22: L.S. | F22: =IFERROR($C22*E22,E22) -> 0
A23: =IFERROR(IF(OFFSET(A23,-1,0)>0,OFFSET(A23,-1,0)+0.001,ERROR.TYPE(0)),IFERROR(IF(OFFSET(A23,-2,0)>0,OFFSET(A23,-2,0)+0.001,ERROR.TYPE(0)),IFERROR(IF(OFFSET(A23,-3,0)>0,OFFSET(A23,-3,0)+0.001,ERROR.TYPE(0)),IFERROR(IF(OFFSET(A23,-4,0)>0,OFFSET(A23,-4,0)+0.001,ERROR.TYPE(0)),IFERROR(IF(OFFSET(A23,-5,0)>0,OFFSET(A23,-5,0)+0.001,ERROR.TYPE(0)),IFERROR(IF(OFFSET(A23,-6,0)>0,OFFSET(A23,-6,0)+0.001,ERROR.TYPE(0)),IFERROR(IF(OFFSET(A23,-7,0)>0,OFFSET(A23,-7,0)+0.001,ERROR.TYPE(0)),IFERROR(IF(OFFSET(A23,-8,0)>0,OFFSET(A23,-8,0)+0.001,ERROR.TYPE(0)),IFERROR(IF(OFFSET(A23,-9,0)>0,OFFSET(A23,-9,0)+0.001,ERROR.TYPE(0)),IFERROR(IF(OFFSET(A23,-10,0)>0,OFFSET(A23,-10,0)+0.001,ERROR.TYPE(0)),ERROR.TYPE(0))))))))))) -> 1.013 | B23: Provision for Openings in Insulation Panelling in order to prepare all openings required to install conduits, pipework, ductwork, etc., and making good and reinstatement of all openings. | C23: 1 | D23: L.S. | F23: =IFERROR($C23*E23,E23) -> 0
A24: P | B24: TOTAL FOR PAGE 02 | C24: Euro Exc VAT | F24: =SUM(F16:F23) -> 0 | G24: =SUM(G16:G23) -> 0 | H24: =SUM(H16:H23) -> 0 | I24: =SUM(I16:I23) -> 0
B26: TOTAL FOR PRELIMINARIES | C26: Euro Exc VAT | F26: =F24+F12 -> 0 | G26: =G24+G12 -> 0 | H26: =H24+H12 -> 0 | I26: =I24+I12 -> 0
A29: ITEM | B29: DESCRIPTION | C29: QTY | D29: UNIT | E29: RATE Euro (Exc of VAT) | F29: TOTAL Euro (Exc of VAT) | G29: Material cost to Panta Ex VAT | H29: Labour pair hours @ €27.46per pair hour | I29: Labour pair hours @ €52.92per pair hour
A30: 2T | B30: VENTILATION SYSTEM
A31: T | B31: FANS - BASEMENT LEVEL -1
A32: T | B32: Supply, install and connect the following In-line type extract fans c/w 2 silencers - one upstream and one downstream from the fan, variable speed controllers, anti-vibration mountings, chamfered bird screen, transformation pieces etc for a complete system inclusive of connecting up of fans to electrical supply.
A33: 2.001 | B33: EF-B1U-01 F300 Extract Fan - Norm: 33,000m3/hr at 200Pa; Fire: 55,000m3/hr at 200Pa - installed at Level 0 | C33: 2 | D33: No. | E33: =Elec_Est!E27 -> 245.04 | F33: =IFERROR($C33*E33,E33) -> 490.08 | G33: =Elec_Est!AM27 -> 333 | H33: =Elec_Est!AN27 -> 5.72
A34: =IFERROR(IF(OFFSET(A34,-1,0,1,1)>0,OFFSET(A34,-1,0,1,1)+0.001,ERROR.TYPE(0)),IFERROR(IF(OFFSET(A34,-2,0,1,1)>0,OFFSET(A34,-2,0,1,1)+0.001,ERROR.TYPE(0)),IFERROR(IF(OFFSET(A34,-3,0,1,1)>0,OFFSET(A34,-3,0,1,1)+0.001,ERROR.TYPE(0)),IFERROR(IF(OFFSET(A34,-4,0,1,1)>0,OFFSET(A34,-4,0,1,1)+0.001,ERROR.TYPE(0)),IFERROR(IF(OFFSET(A34,-5,0,1,1)>0,OFFSET(A34,-5,0,1,1)+0.001,ERROR.TYPE(0)),IFERROR(IF(OFFSET(A34,-6,0,1,1)>0,OFFSET(A34,-6,0,1,1)+0.001,ERROR.TYPE(0)),IFERROR(IF(OFFSET(A34,-7,0,1,1)>0,OFFSET(A34,-7,0,1,1)+0.001,ERROR.TYPE(0)),IFERROR(IF(OFFSET(A34,-8,0,1,1)>0,OFFSET(A34,-8,0,1,1)+0.001,ERROR.TYPE(0)),IFERROR(IF(OFFSET(A34,-9,0,1,1)>0,OFFSET(A34,-9,0,1,1)+0.001,ERROR.TYPE(0)),IFERROR(IF(OFFSET(A34,-10,0,1,1)>0,OFFSET(A34,-10,0,1,1)+0.001,ERROR.TYPE(0)),ERROR.TYPE(0))))))))))) -> 2.002 | B34: EF-B1L-01 F300 Extract Fan - Norm: 42,800m3/hr at 200Pa; Fire: 71,000m3/hr at 200Pa - installed at Level 0 | C34: 2 | D34: No. | E34: =Elec_Est!E43 -> 245.04 | F34: =IFERROR($C34*E34,E34) -> 490.08 | G34: =Elec_Est!AM43 -> 333 | H34: =Elec_Est!AN43 -> 5.72
A35: =IFERROR(IF(OFFSET(A35,-1,0,1,1)>0,OFFSET(A35,-1,0,1,1)+0.001,ERROR.TYPE(0)),IFERROR(IF(OFFSET(A35,-2,0,1,1)>0,OFFSET(A35,-2,0,1,1)+0.001,ERROR.TYPE(0)),IFERROR(IF(OFFSET(A35,-3,0,1,1)>0,OFFSET(A35,-3,0,1,1)+0.001,ERROR.TYPE(0)),IFERROR(IF(OFFSET(A35,-4,0,1,1)>0,OFFSET(A35,-4,0,1,1)+0.001,ERROR.TYPE(0)),IFERROR(IF(OFFSET(A35,-5,0,1,1)>0,OFFSET(A35,-5,0,1,1)+0.001,ERROR.TYPE(0)),IFERROR(IF(OFFSET(A35,-6,0,1,1)>0,OFFSET(A35,-6,0,1,1)+0.001,ERROR.TYPE(0)),IFERROR(IF(OFFSET(A35,-7,0,1,1)>0,OFFSET(A35,-7,0,1,1)+0.001,ERROR.TYPE(0)),IFERROR(IF(OFFSET(A35,-8,0,1,1)>0,OFFSET(A35,-8,0,1,1)+0.001,ERROR.TYPE(0)),IFERROR(IF(OFFSET(A35,-9,0,1,1)>0,OFFSET(A35,-9,0,1,1)+0.001,ERROR.TYPE(0)),IFERROR(IF(OFFSET(A35,-10,0,1,1)>0,OFFSET(A35,-10,0,1,1)+0.001,ERROR.TYPE(0)),ERROR.TYPE(0))))))))))) -> 2.003 | B35: EF-B1U-02 Extract Fan - 1300m3/hr at 125Pa - installed at Level 0 | C35: 1 | D35: No. | E35: =Elec_Est!E59 -> 65.62 | F35: =IFERROR($C35*E35,E35) -> 65.62 | G35: =Elec_Est!AM59 -> 20.04 | H35: =Elec_Est!AN59 -> 1.66
A36: =IFERROR(IF(OFFSET(A36,-1,0,1,1)>0,OFFSET(A36,-1,0,1,1)+0.001,ERROR.TYPE(0)),IFERROR(IF(OFFSET(A36,-2,0,1,1)>0,OFFSET(A36,-2,0,1,1)+0.001,ERROR.TYPE(0)),IFERROR(IF(OFFSET(A36,-3,0,1,1)>0,OFFSET(A36,-3,0,1,1)+0.001,ERROR.TYPE(0)),IFERROR(IF(OFFSET(A36,-4,0,1,1)>0,OFFSET(A36,-4,0,1,1)+0.001,ERROR.TYPE(0)),IFERROR(IF(OFFSET(A36,-5,0,1,1)>0,OFFSET(A36,-5,0,1,1)+0.001,ERROR.TYPE(0)),IFERROR(IF(OFFSET(A36,-6,0,1,1)>0,OFFSET(A36,-6,0,1,1)+0.001,ERROR.TYPE(0)),IFERROR(IF(OFFSET(A36,-7,0,1,1)>0,OFFSET(A36,-7,0,1,1)+0.001,ERROR.TYPE(0)),IFERROR(IF(OFFSET(A36,-8,0,1,1)>0,OFFSET(A36,-8,0,1,1)+0.001,ERROR.TYPE(0)),IFERROR(IF(OFFSET(A36,-9,0,1,1)>0,OFFSET(A36,-9,0,1,1)+0.001,ERROR.TYPE(0)),IFERROR(IF(OFFSET(A36,-10,0,1,1)>0,OFFSET(A36,-10,0,1,1)+0.001,ERROR.TYPE(0)),ERROR.TYPE(0))))))))))) -> 2.004 | B36: EF-B1L-02 Extract Fan - 32,000m3/hr at 250Pa - installed at Level 1 | C36: 1 | D36: No. | E36: =Elec_Est!E75 -> 73.04 | F36: =IFERROR($C36*E36,E36) -> 73.04 | G36: =Elec_Est!AM75 -> 24.44 | H36: =Elec_Est!AN75 -> 1.77
A37: =IFERROR(IF(OFFSET(A37,-1,0,1,1)>0,OFFSET(A37,-1,0,1,1)+0.001,ERROR.TYPE(0)),IFERROR(IF(OFFSET(A37,-2,0,1,1)>0,OFFSET(A37,-2,0,1,1)+0.001,ERROR.TYPE(0)),IFERROR(IF(OFFSET(A37,-3,0,1,1)>0,OFFSET(A37,-3,0,1,1)+0.001,ERROR.TYPE(0)),IFERROR(IF(OFFSET(A37,-4,0,1,1)>0,OFFSET(A37,-4,0,1,1)+0.001,ERROR.TYPE(0)),IFERROR(IF(OFFSET(A37,-5,0,1,1)>0,OFFSET(A37,-5,0,1,1)+0.001,ERROR.TYPE(0)),IFERROR(IF(OFFSET(A37,-6,0,1,1)>0,OFFSET(A37,-6,0,1,1)+0.001,ERROR.TYPE(0)),IFERROR(IF(OFFSET(A37,-7,0,1,1)>0,OFFSET(A37,-7,0,1,1)+0.001,ERROR.TYPE(0)),IFERROR(IF(OFFSET(A37,-8,0,1,1)>0,OFFSET(A37,-8,0,1,1)+0.001,ERROR.TYPE(0)),IFERROR(IF(OFFSET(A37,-9,0,1,1)>0,OFFSET(A37,-9,0,1,1)+0.001,ERROR.TYPE(0)),IFERROR(IF(OFFSET(A37,-10,0,1,1)>0,OFFSET(A37,-10,0,1,1)+0.001,ERROR.TYPE(0)),ERROR.TYPE(0))))))))))) -> 2.005 | B37: SF-B1L-01 Supply Fan - 35,000m3/hr at 250Pa - installed at Basement Level -1 | C37: 1 | D37: No. | E37: =Elec_Est!E91 -> 73.04 | F37: =IFERROR($C37*E37,E37) -> 73.04 | G37: =Elec_Est!AM91 -> 24.44 | H37: =Elec_Est!AN91 -> 1.77
A38: =IFERROR(IF(OFFSET(A38,-1,0,1,1)>0,OFFSET(A38,-1,0,1,1)+0.001,ERROR.TYPE(0)),IFERROR(IF(OFFSET(A38,-2,0,1,1)>0,OFFSET(A38,-2,0,1,1)+0.001,ERROR.TYPE(0)),IFERROR(IF(OFFSET(A38,-3,0,1,1)>0,OFFSET(A38,-3,0,1,1)+0.001,ERROR.TYPE(0)),IFERROR(IF(OFFSET(A38,-4,0,1,1)>0,OFFSET(A38,-4,0,1,1)+0.001,ERROR.TYPE(0)),IFERROR(IF(OFFSET(A38,-5,0,1,1)>0,OFFSET(A38,-5,0,1,1)+0.001,ERROR.TYPE(0)),IFERROR(IF(OFFSET(A38,-6,0,1,1)>0,OFFSET(A38,-6,0,1,1)+0.001,ERROR.TYPE(0)),IFERROR(IF(OFFSET(A38,-7,0,1,1)>0,OFFSET(A38,-7,0,1,1)+0.001,ERROR.TYPE(0)),IFERROR(IF(OFFSET(A38,-8,0,1,1)>0,OFFSET(A38,-8,0,1,1)+0.001,ERROR.TYPE(0)),IFERROR(IF(OFFSET(A38,-9,0,1,1)>0,OFFSET(A38,-9,0,1,1)+0.001,ERROR.TYPE(0)),IFERROR(IF(OFFSET(A38,-10,0,1,1)>0,OFFSET(A38,-10,0,1,1)+0.001,ERROR.TYPE(0)),ERROR.TYPE(0))))))))))) -> 2.006 | B38: Supply and install differential pressure alarm complete with remote visual and audible indicators including all cabling etc for a complete system | C38: 1 | D38: No. | E38: =Elec_Est!E108 -> 309.67 | F38: =IFERROR($C38*E38,E38) -> 309.67 | G38: =Elec_Est!AM108 -> 114.98 | H38: =Elec_Est!AN108 -> 7.09
B39: Supply, install and connect the following In-line type extract fans c/w 2 silencers - one upstream and one downstream from the fan, variable speed controllers, anti-vibration mountings, chamfered bird screen, transformation pieces etc for a complete system inclusive of connecting up of fans to electrical supply.
A40: 2.006a | B40: EF-GEN-01 F300 Extract Fan - 9,700m3/hr at 250Pa - installed at Basement Level -1 | C40: 1 | D40: No. | F40: =IFERROR($C40*E40,E40) -> 0 | G40: =Elec_Est!AM123 -> 24.44 | H40: =Elec_Est!AN123 -> 1.77
A41: 2.006b | B41: SF-GEN-01 F300 Supply Fan - 9,700m3/hr at 250Pa - installed at Basement Level -1 | C41: 1 | D41: No. | F41: =IFERROR($C41*E41,E41) -> 0 | G41: =Elec_Est!AM139 -> 24.44 | H41: =Elec_Est!AN139 -> 1.77
A42: T | B42: Supply, install and connect the following Induction Jet fans c/w transformation pieces etc and including the connecting up to the electrical supply for a complete system
A43: =IFERROR(IF(OFFSET(A43,-1,0,1,1)>0,OFFSET(A43,-1,0,1,1)+0.001,ERROR.TYPE(0)),IFERROR(IF(OFFSET(A43,-2,0,1,1)>0,OFFSET(A43,-2,0,1,1)+0.001,ERROR.TYPE(0)),IFERROR(IF(OFFSET(A43,-3,0,1,1)>0,OFFSET(A43,-3,0,1,1)+0.001,ERROR.TYPE(0)),IFERROR(IF(OFFSET(A43,-4,0,1,1)>0,OFFSET(A43,-4,0,1,1)+0.001,ERROR.TYPE(0)),IFERROR(IF(OFFSET(A43,-5,0,1,1)>0,OFFSET(A43,-5,0,1,1)+0.001,ERROR.TYPE(0)),IFERROR(IF(OFFSET(A43,-6,0,1,1)>0,OFFSET(A43,-6,0,1,1)+0.001,ERROR.TYPE(0)),IFERROR(IF(OFFSET(A43,-7,0,1,1)>0,OFFSET(A43,-7,0,1,1)+0.001,ERROR.TYPE(0)),IFERROR(IF(OFFSET(A43,-8,0,1,1)>0,OFFSET(A43,-8,0,1,1)+0.001,ERROR.TYPE(0)),IFERROR(IF(OFFSET(A43,-9,0,1,1)>0,OFFSET(A43,-9,0,1,1)+0.001,ERROR.TYPE(0)),IFERROR(IF(OFFSET(A43,-10,0,1,1)>0,OFFSET(A43,-10,0,1,1)+0.001,ERROR.TYPE(0)),ERROR.TYPE(0))))))))))) -> 2.007 | B43: JF-B1U-01 to 07 Jet Fan - Normal: 3500m3/hr; Fire: 5800m3/hr - installed at Basement Level -1 | C43: 7 | D43: No. | E43: =Elec_Est!E159 -> 89.37 | F43: =IFERROR($C43*E43,E43) -> 625.59 | G43: =Elec_Est!AM159 -> 310.38 | H43: =Elec_Est!AN159 -> 11.48
A44: =IFERROR(IF(OFFSET(A44,-1,0,1,1)>0,OFFSET(A44,-1,0,1,1)+0.001,ERROR.TYPE(0)),IFERROR(IF(OFFSET(A44,-2,0,1,1)>0,OFFSET(A44,-2,0,1,1)+0.001,ERROR.TYPE(0)),IFERROR(IF(OFFSET(A44,-3,0,1,1)>0,OFFSET(A44,-3,0,1,1)+0.001,ERROR.TYPE(0)),IFERROR(IF(OFFSET(A44,-4,0,1,1)>0,OFFSET(A44,-4,0,1,1)+0.001,ERROR.TYPE(0)),IFERROR(IF(OFFSET(A44,-5,0,1,1)>0,OFFSET(A44,-5,0,1,1)+0.001,ERROR.TYPE(0)),IFERROR(IF(OFFSET(A44,-6,0,1,1)>0,OFFSET(A44,-6,0,1,1)+0.001,ERROR.TYPE(0)),IFERROR(IF(OFFSET(A44,-7,0,1,1)>0,OFFSET(A44,-7,0,1,1)+0.001,ERROR.TYPE(0)),IFERROR(IF(OFFSET(A44,-8,0,1,1)>0,OFFSET(A44,-8,0,1,1)+0.001,ERROR.TYPE(0)),IFERROR(IF(OFFSET(A44,-9,0,1,1)>0,OFFSET(A44,-9,0,1,1)+0.001,ERROR.TYPE(0)),IFERROR(IF(OFFSET(A44,-10,0,1,1)>0,OFFSET(A44,-10,0,1,1)+0.001,ERROR.TYPE(0)),ERROR.TYPE(0))))))))))) -> 2.008 | B44: JF-B1L-01 to 08 Jet Fan - Normal: 3500m3/hr; Fire: 5800m3/hr - installed at Basement Level -1 | C44: 8 | D44: No. | E44: =Elec_Est!E175 -> 89.38 | F44: =IFERROR($C44*E44,E44) -> 715.04 | G44: =Elec_Est!AM175 -> 354.72 | H44: =Elec_Est!AN175 -> 13.12
A45: T | B45: FANS - UPPER LEVELS
A46: T | B46: Supply, install and connect the following In-line type extract fans c/w 2 silencers - one upstream and one downstream from the fan, variable speed controllers, anti-vibration mountings, chamfered bird screen, transformation pieces etc for a complete system inclusive of connecting up of fans to electrical supply.
A47: =IFERROR(IF(OFFSET(A47,-1,0,1,1)>0,OFFSET(A47,-1,0,1,1)+0.001,ERROR.TYPE(0)),IFERROR(IF(OFFSET(A47,-2,0,1,1)>0,OFFSET(A47,-2,0,1,1)+0.001,ERROR.TYPE(0)),IFERROR(IF(OFFSET(A47,-3,0,1,1)>0,OFFSET(A47,-3,0,1,1)+0.001,ERROR.TYPE(0)),IFERROR(IF(OFFSET(A47,-4,0,1,1)>0,OFFSET(A47,-4,0,1,1)+0.001,ERROR.TYPE(0)),IFERROR(IF(OFFSET(A47,-5,0,1,1)>0,OFFSET(A47,-5,0,1,1)+0.001,ERROR.TYPE(0)),IFERROR(IF(OFFSET(A47,-6,0,1,1)>0,OFFSET(A47,-6,0,1,1)+0.001,ERROR.TYPE(0)),IFERROR(IF(OFFSET(A47,-7,0,1,1)>0,OFFSET(A47,-7,0,1,1)+0.001,ERROR.TYPE(0)),IFERROR(IF(OFFSET(A47,-8,0,1,1)>0,OFFSET(A47,-8,0,1,1)+0.001,ERROR.TYPE(0)),IFERROR(IF(OFFSET(A47,-9,0,1,1)>0,OFFSET(A47,-9,0,1,1)+0.001,ERROR.TYPE(0)),IFERROR(IF(OFFSET(A47,-10,0,1,1)>0,OFFSET(A47,-10,0,1,1)+0.001,ERROR.TYPE(0)),ERROR.TYPE(0))))))))))) -> 2.009 | B47: EF-OF-01 Extract Fan - 540m3/hr at 125Pa - installed at Level 0 | C47: 1 | D47: No. | E47: =Elec_Est!E199 -> 65.62 | F47: =IFERROR($C47*E47,E47) -> 65.62 | G47: =Elec_Est!AM199 -> 20.04 | H47: =Elec_Est!AN199 -> 1.66
A48: =IFERROR(IF(OFFSET(A48,-1,0,1,1)>0,OFFSET(A48,-1,0,1,1)+0.001,ERROR.TYPE(0)),IFERROR(IF(OFFSET(A48,-2,0,1,1)>0,OFFSET(A48,-2,0,1,1)+0.001,ERROR.TYPE(0)),IFERROR(IF(OFFSET(A48,-3,0,1,1)>0,OFFSET(A48,-3,0,1,1)+0.001,ERROR.TYPE(0)),IFERROR(IF(OFFSET(A48,-4,0,1,1)>0,OFFSET(A48,-4,0,1,1)+0.001,ERROR.TYPE(0)),IFERROR(IF(OFFSET(A48,-5,0,1,1)>0,OFFSET(A48,-5,0,1,1)+0.001,ERROR.TYPE(0)),IFERROR(IF(OFFSET(A48,-6,0,1,1)>0,OFFSET(A48,-6,0,1,1)+0.001,ERROR.TYPE(0)),IFERROR(IF(OFFSET(A48,-7,0,1,1)>0,OFFSET(A48,-7,0,1,1)+0.001,ERROR.TYPE(0)),IFERROR(IF(OFFSET(A48,-8,0,1,1)>0,OFFSET(A48,-8,0,1,1)+0.001,ERROR.TYPE(0)),IFERROR(IF(OFFSET(A48,-9,0,1,1)>0,OFFSET(A48,-9,0,1,1)+0.001,ERROR.TYPE(0)),IFERROR(IF(OFFSET(A48,-10,0,1,1)>0,OFFSET(A48,-10,0,1,1)+0.001,ERROR.TYPE(0)),ERROR.TYPE(0))))))))))) -> 2.01 | B48: EF-OF-02 Extract Fan - 300m3/hr at 125Pa - installed at Roof Level | C48: 1 | D48: No. | E48: =Elec_Est!E215 -> 65.62 | F48: =IFERROR($C48*E48,E48) -> 65.62 | G48: =Elec_Est!AM215 -> 20.04 | H48: =Elec_Est!AN215 -> 1.66
A49: =IFERROR(IF(OFFSET(A49,-1,0,1,1)>0,OFFSET(A49,-1,0,1,1)+0.001,ERROR.TYPE(0)),IFERROR(IF(OFFSET(A49,-2,0,1,1)>0,OFFSET(A49,-2,0,1,1)+0.001,ERROR.TYPE(0)),IFERROR(IF(OFFSET(A49,-3,0,1,1)>0,OFFSET(A49,-3,0,1,1)+0.001,ERROR.TYPE(0)),IFERROR(IF(OFFSET(A49,-4,0,1,1)>0,OFFSET(A49,-4,0,1,1)+0.001,ERROR.TYPE(0)),IFERROR(IF(OFFSET(A49,-5,0,1,1)>0,OFFSET(A49,-5,0,1,1)+0.001,ERROR.TYPE(0)),IFERROR(IF(OFFSET(A49,-6,0,1,1)>0,OFFSET(A49,-6,0,1,1)+0.001,ERROR.TYPE(0)),IFERROR(IF(OFFSET(A49,-7,0,1,1)>0,OFFSET(A49,-7,0,1,1)+0.001,ERROR.TYPE(0)),IFERROR(IF(OFFSET(A49,-8,0,1,1)>0,OFFSET(A49,-8,0,1,1)+0.001,ERROR.TYPE(0)),IFERROR(IF(OFFSET(A49,-9,0,1,1)>0,OFFSET(A49,-9,0,1,1)+0.001,ERROR.TYPE(0)),IFERROR(IF(OFFSET(A49,-10,0,1,1)>0,OFFSET(A49,-10,0,1,1)+0.001,ERROR.TYPE(0)),ERROR.TYPE(0))))))))))) -> 2.011 | B49: EF-AB-01 Extract Fan - 450m3/hr at 150Pa - installed at Level 3 | C49: 1 | D49: No. | E49: =Elec_Est!E231 -> 65.62 | F49: =IFERROR($C49*E49,E49) -> 65.62 | G49: =Elec_Est!AM231 -> 20.04 | H49: =Elec_Est!AN231 -> 1.66
A50: =IFERROR(IF(OFFSET(A50,-1,0,1,1)>0,OFFSET(A50,-1,0,1,1)+0.001,ERROR.TYPE(0)),IFERROR(IF(OFFSET(A50,-2,0,1,1)>0,OFFSET(A50,-2,0,1,1)+0.001,ERROR.TYPE(0)),IFERROR(IF(OFFSET(A50,-3,0,1,1)>0,OFFSET(A50,-3,0,1,1)+0.001,ERROR.TYPE(0)),IFERROR(IF(OFFSET(A50,-4,0,1,1)>0,OFFSET(A50,-4,0,1,1)+0.001,ERROR.TYPE(0)),IFERROR(IF(OFFSET(A50,-5,0,1,1)>0,OFFSET(A50,-5,0,1,1)+0.001,ERROR.TYPE(0)),IFERROR(IF(OFFSET(A50,-6,0,1,1)>0,OFFSET(A50,-6,0,1,1)+0.001,ERROR.TYPE(0)),IFERROR(IF(OFFSET(A50,-7,0,1,1)>0,OFFSET(A50,-7,0,1,1)+0.001,ERROR.TYPE(0)),IFERROR(IF(OFFSET(A50,-8,0,1,1)>0,OFFSET(A50,-8,0,1,1)+0.001,ERROR.TYPE(0)),IFERROR(IF(OFFSET(A50,-9,0,1,1)>0,OFFSET(A50,-9,0,1,1)+0.001,ERROR.TYPE(0)),IFERROR(IF(OFFSET(A50,-10,0,1,1)>0,OFFSET(A50,-10,0,1,1)+0.001,ERROR.TYPE(0)),ERROR.TYPE(0))))))))))) -> 2.012 | B50: SF-AB-01 Supply Fan - 250m3/hr at 200Pa - installed at Level 3 | C50: 1 | D50: No. | E50: =Elec_Est!E247 -> 65.62 | F50: =IFERROR($C50*E50,E50) -> 65.62 | G50: =Elec_Est!AM247 -> 20.04 | H50: =Elec_Est!AN247 -> 1.66
A51: =IFERROR(IF(OFFSET(A51,-1,0,1,1)>0,OFFSET(A51,-1,0,1,1)+0.001,ERROR.TYPE(0)),IFERROR(IF(OFFSET(A51,-2,0,1,1)>0,OFFSET(A51,-2,0,1,1)+0.001,ERROR.TYPE(0)),IFERROR(IF(OFFSET(A51,-3,0,1,1)>0,OFFSET(A51,-3,0,1,1)+0.001,ERROR.TYPE(0)),IFERROR(IF(OFFSET(A51,-4,0,1,1)>0,OFFSET(A51,-4,0,1,1)+0.001,ERROR.TYPE(0)),IFERROR(IF(OFFSET(A51,-5,0,1,1)>0,OFFSET(A51,-5,0,1,1)+0.001,ERROR.TYPE(0)),IFERROR(IF(OFFSET(A51,-6,0,1,1)>0,OFFSET(A51,-6,0,1,1)+0.001,ERROR.TYPE(0)),IFERROR(IF(OFFSET(A51,-7,0,1,1)>0,OFFSET(A51,-7,0,1,1)+0.001,ERROR.TYPE(0)),IFERROR(IF(OFFSET(A51,-8,0,1,1)>0,OFFSET(A51,-8,0,1,1)+0.001,ERROR.TYPE(0)),IFERROR(IF(OFFSET(A51,-9,0,1,1)>0,OFFSET(A51,-9,0,1,1)+0.001,ERROR.TYPE(0)),IFERROR(IF(OFFSET(A51,-10,0,1,1)>0,OFFSET(A51,-10,0,1,1)+0.001,ERROR.TYPE(0)),ERROR.TYPE(0))))))))))) -> 2.013 | B51: Supply and install differential pressure alarm complete with remote visual and audible indicators including all cabling etc for a complete system | C51: 1 | D51: No. | E51: =Elec_Est!E264 -> 366.17 | F51: =IFERROR($C51*E51,E51) -> 366.17 | G51: =Elec_Est!AM264 -> 137.15 | H51: =Elec_Est!AN264 -> 8.34
A52: T | B52: Supply, install and connect the following F300 Wall mounted axial fans c/w transformation pieces etc and including the connecting up to the electrical supply for a complete system
A53: =IFERROR(IF(OFFSET(A53,-1,0,1,1)>0,OFFSET(A53,-1,0,1,1)+0.001,ERROR.TYPE(0)),IFERROR(IF(OFFSET(A53,-2,0,1,1)>0,OFFSET(A53,-2,0,1,1)+0.001,ERROR.TYPE(0)),IFERROR(IF(OFFSET(A53,-3,0,1,1)>0,OFFSET(A53,-3,0,1,1)+0.001,ERROR.TYPE(0)),IFERROR(IF(OFFSET(A53,-4,0,1,1)>0,OFFSET(A53,-4,0,1,1)+0.001,ERROR.TYPE(0)),IFERROR(IF(OFFSET(A53,-5,0,1,1)>0,OFFSET(A53,-5,0,1,1)+0.001,ERROR.TYPE(0)),IFERROR(IF(OFFSET(A53,-6,0,1,1)>0,OFFSET(A53,-6,0,1,1)+0.001,ERROR.TYPE(0)),IFERROR(IF(OFFSET(A53,-7,0,1,1)>0,OFFSET(A53,-7,0,1,1)+0.001,ERROR.TYPE(0)),IFERROR(IF(OFFSET(A53,-8,0,1,1)>0,OFFSET(A53,-8,0,1,1)+0.001,ERROR.TYPE(0)),IFERROR(IF(OFFSET(A53,-9,0,1,1)>0,OFFSET(A53,-9,0,1,1)+0.001,ERROR.TYPE(0)),IFERROR(IF(OFFSET(A53,-10,0,1,1)>0,OFFSET(A53,-10,0,1,1)+0.001,ERROR.TYPE(0)),ERROR.TYPE(0))))))))))) -> 2.014 | B53: SPF1 to 3 Wall Mounted Fan - 34,000m3/hr at 200Pa c/w Cowls etc. as required as per drawing - installed at Level 2 | C53: 3 | D53: No. | E53: =Elec_Est!E280 -> 81.51 | F53: =IFERROR($C53*E53,E53) -> 244.53 | G53: =Elec_Est!AM280 -> 139.92 | H53: =Elec_Est!AN280 -> 3.81
A54: =IFERROR(IF(OFFSET(A54,-1,0,1,1)>0,OFFSET(A54,-1,0,1,1)+0.001,ERROR.TYPE(0)),IFERROR(IF(OFFSET(A54,-2,0,1,1)>0,OFFSET(A54,-2,0,1,1)+0.001,ERROR.TYPE(0)),IFERROR(IF(OFFSET(A54,-3,0,1,1)>0,OFFSET(A54,-3,0,1,1)+0.001,ERROR.TYPE(0)),IFERROR(IF(OFFSET(A54,-4,0,1,1)>0,OFFSET(A54,-4,0,1,1)+0.001,ERROR.TYPE(0)),IFERROR(IF(OFFSET(A54,-5,0,1,1)>0,OFFSET(A54,-5,0,1,1)+0.001,ERROR.TYPE(0)),IFERROR(IF(OFFSET(A54,-6,0,1,1)>0,OFFSET(A54,-6,0,1,1)+0.001,ERROR.TYPE(0)),IFERROR(IF(OFFSET(A54,-7,0,1,1)>0,OFFSET(A54,-7,0,1,1)+0.001,ERROR.TYPE(0)),IFERROR(IF(OFFSET(A54,-8,0,1,1)>0,OFFSET(A54,-8,0,1,1)+0.001,ERROR.TYPE(0)),IFERROR(IF(OFFSET(A54,-9,0,1,1)>0,OFFSET(A54,-9,0,1,1)+0.001,ERROR.TYPE(0)),IFERROR(IF(OFFSET(A54,-10,0,1,1)>0,OFFSET(A54,-10,0,1,1)+0.001,ERROR.TYPE(0)),ERROR.TYPE(0))))))))))) -> 2.015 | B54: EPF1 to 3 Wall Mounted Fan - Norm: 34,000m3/hr at 200Pa; Fire: 57,000m3/hr at 150Pa c/w Gravity shutters etc. as required as per drawing - installed at Level 2 | C54: 3 | D54: No. | E54: =Elec_Est!E296 -> 151.05 | F54: =IFERROR($C54*E54,E54) -> 453.15 | G54: =Elec_Est!AM296 -> 240.6 | H54: =Elec_Est!AN296 -> 7.74
A55: T | B55: Supply, install and connect the following F300 Impulse Jet fans c/w transformation pieces etc and including the connecting up to the electrical supply for a complete system
A56: =IFERROR(IF(OFFSET(A56,-1,0,1,1)>0,OFFSET(A56,-1,0,1,1)+0.001,ERROR.TYPE(0)),IFERROR(IF(OFFSET(A56,-2,0,1,1)>0,OFFSET(A56,-2,0,1,1)+0.001,ERROR.TYPE(0)),IFERROR(IF(OFFSET(A56,-3,0,1,1)>0,OFFSET(A56,-3,0,1,1)+0.001,ERROR.TYPE(0)),IFERROR(IF(OFFSET(A56,-4,0,1,1)>0,OFFSET(A56,-4,0,1,1)+0.001,ERROR.TYPE(0)),IFERROR(IF(OFFSET(A56,-5,0,1,1)>0,OFFSET(A56,-5,0,1,1)+0.001,ERROR.TYPE(0)),IFERROR(IF(OFFSET(A56,-6,0,1,1)>0,OFFSET(A56,-6,0,1,1)+0.001,ERROR.TYPE(0)),IFERROR(IF(OFFSET(A56,-7,0,1,1)>0,OFFSET(A56,-7,0,1,1)+0.001,ERROR.TYPE(0)),IFERROR(IF(OFFSET(A56,-8,0,1,1)>0,OFFSET(A56,-8,0,1,1)+0.001,ERROR.TYPE(0)),IFERROR(IF(OFFSET(A56,-9,0,1,1)>0,OFFSET(A56,-9,0,1,1)+0.001,ERROR.TYPE(0)),IFERROR(IF(OFFSET(A56,-10,0,1,1)>0,OFFSET(A56,-10,0,1,1)+0.001,ERROR.TYPE(0)),ERROR.TYPE(0))))))))))) -> 2.016 | B56: IF1 to 12 Impulse Fan - 8500m3/hr at 100N - installed at Level 2 | C56: 12 | D56: No. | E56: =Elec_Est!E316 -> 127.13 | F56: =IFERROR($C56*E56,E56) -> 1525.56 | G56: =Elec_Est!AM316 -> 985.2 | H56: =Elec_Est!AN316 -> 19.68
A57: T | B57: HRUs - UPPER LEVELS
A58: T | B58: Supply, install and connect the following HRUs c/w variable speed controllers, filters c/w differential pressure alarm, transformation pieces etc for a complete system
A59: =IFERROR(IF(OFFSET(A59,-1,0,1,1)>0,OFFSET(A59,-1,0,1,1)+0.001,ERROR.TYPE(0)),IFERROR(IF(OFFSET(A59,-2,0,1,1)>0,OFFSET(A59,-2,0,1,1)+0.001,ERROR.TYPE(0)),IFERROR(IF(OFFSET(A59,-3,0,1,1)>0,OFFSET(A59,-3,0,1,1)+0.001,ERROR.TYPE(0)),IFERROR(IF(OFFSET(A59,-4,0,1,1)>0,OFFSET(A59,-4,0,1,1)+0.001,ERROR.TYPE(0)),IFERROR(IF(OFFSET(A59,-5,0,1,1)>0,OFFSET(A59,-5,0,1,1)+0.001,ERROR.TYPE(0)),IFERROR(IF(OFFSET(A59,-6,0,1,1)>0,OFFSET(A59,-6,0,1,1)+0.001,ERROR.TYPE(0)),IFERROR(IF(OFFSET(A59,-7,0,1,1)>0,OFFSET(A59,-7,0,1,1)+0.001,ERROR.TYPE(0)),IFERROR(IF(OFFSET(A59,-8,0,1,1)>0,OFFSET(A59,-8,0,1,1)+0.001,ERROR.TYPE(0)),IFERROR(IF(OFFSET(A59,-9,0,1,1)>0,OFFSET(A59,-9,0,1,1)+0.001,ERROR.TYPE(0)),IFERROR(IF(OFFSET(A59,-10,0,1,1)>0,OFFSET(A59,-10,0,1,1)+0.001,ERROR.TYPE(0)),ERROR.TYPE(0))))))))))) -> 2.017 | B59: HRU-OL0-01 Heat Recovery Unit - 650m3/hr at 200Pa - installed at Level 4 | C59: 1 | D59: No. | E59: =Elec_Est!E340 -> 65.62 | F59: =IFERROR($C59*E59,E59) -> 65.62 | G59: =Elec_Est!AM340 -> 20.04 | H59: =Elec_Est!AN340 -> 1.66
A60: =IFERROR(IF(OFFSET(A60,-1,0,1,1)>0,OFFSET(A60,-1,0,1,1)+0.001,ERROR.TYPE(0)),IFERROR(IF(OFFSET(A60,-2,0,1,1)>0,OFFSET(A60,-2,0,1,1)+0.001,ERROR.TYPE(0)),IFERROR(IF(OFFSET(A60,-3,0,1,1)>0,OFFSET(A60,-3,0,1,1)+0.001,ERROR.TYPE(0)),IFERROR(IF(OFFSET(A60,-4,0,1,1)>0,OFFSET(A60,-4,0,1,1)+0.001,ERROR.TYPE(0)),IFERROR(IF(OFFSET(A60,-5,0,1,1)>0,OFFSET(A60,-5,0,1,1)+0.001,ERROR.TYPE(0)),IFERROR(IF(OFFSET(A60,-6,0,1,1)>0,OFFSET(A60,-6,0,1,1)+0.001,ERROR.TYPE(0)),IFERROR(IF(OFFSET(A60,-7,0,1,1)>0,OFFSET(A60,-7,0,1,1)+0.001,ERROR.TYPE(0)),IFERROR(IF(OFFSET(A60,-8,0,1,1)>0,OFFSET(A60,-8,0,1,1)+0.001,ERROR.TYPE(0)),IFERROR(IF(OFFSET(A60,-9,0,1,1)>0,OFFSET(A60,-9,0,1,1)+0.001,ERROR.TYPE(0)),IFERROR(IF(OFFSET(A60,-10,0,1,1)>0,OFFSET(A60,-10,0,1,1)+0.001,ERROR.TYPE(0)),ERROR.TYPE(0))))))))))) -> 2.018 | B60: HRU-OL1-01 Heat Recovery Unit - 750m3/hr at 200Pa - installed at Level 4 | C60: 1 | D60: No. | E60: =Elec_Est!E356 -> 65.62 | F60: =IFERROR($C60*E60,E60) -> 65.62 | G60: =Elec_Est!AM356 -> 20.04 | H60: =Elec_Est!AN356 -> 1.66
A61: =IFERROR(IF(OFFSET(A61,-1,0,1,1)>0,OFFSET(A61,-1,0,1,1)+0.001,ERROR.TYPE(0)),IFERROR(IF(OFFSET(A61,-2,0,1,1)>0,OFFSET(A61,-2,0,1,1)+0.001,ERROR.TYPE(0)),IFERROR(IF(OFFSET(A61,-3,0,1,1)>0,OFFSET(A61,-3,0,1,1)+0.001,ERROR.TYPE(0)),IFERROR(IF(OFFSET(A61,-4,0,1,1)>0,OFFSET(A61,-4,0,1,1)+0.001,ERROR.TYPE(0)),IFERROR(IF(OFFSET(A61,-5,0,1,1)>0,OFFSET(A61,-5,0,1,1)+0.001,ERROR.TYPE(0)),IFERROR(IF(OFFSET(A61,-6,0,1,1)>0,OFFSET(A61,-6,0,1,1)+0.001,ERROR.TYPE(0)),IFERROR(IF(OFFSET(A61,-7,0,1,1)>0,OFFSET(A61,-7,0,1,1)+0.001,ERROR.TYPE(0)),IFERROR(IF(OFFSET(A61,-8,0,1,1)>0,OFFSET(A61,-8,0,1,1)+0.001,ERROR.TYPE(0)),IFERROR(IF(OFFSET(A61,-9,0,1,1)>0,OFFSET(A61,-9,0,1,1)+0.001,ERROR.TYPE(0)),IFERROR(IF(OFFSET(A61,-10,0,1,1)>0,OFFSET(A61,-10,0,1,1)+0.001,ERROR.TYPE(0)),ERROR.TYPE(0))))))))))) -> 2.019 | B61: HRU-OL2-01 Heat Recovery Unit - 1100m3/hr at 250Pa - installed at Level 4 | C61: 1 | D61: No. | E61: =Elec_Est!E372 -> 65.62 | F61: =IFERROR($C61*E61,E61) -> 65.62 | G61: =Elec_Est!AM372 -> 20.04 | H61: =Elec_Est!AN372 -> 1.66
A62: =IFERROR(IF(OFFSET(A62,-1,0,1,1)>0,OFFSET(A62,-1,0,1,1)+0.001,ERROR.TYPE(0)),IFERROR(IF(OFFSET(A62,-2,0,1,1)>0,OFFSET(A62,-2,0,1,1)+0.001,ERROR.TYPE(0)),IFERROR(IF(OFFSET(A62,-3,0,1,1)>0,OFFSET(A62,-3,0,1,1)+0.001,ERROR.TYPE(0)),IFERROR(IF(OFFSET(A62,-4,0,1,1)>0,OFFSET(A62,-4,0,1,1)+0.001,ERROR.TYPE(0)),IFERROR(IF(OFFSET(A62,-5,0,1,1)>0,OFFSET(A62,-5,0,1,1)+0.001,ERROR.TYPE(0)),IFERROR(IF(OFFSET(A62,-6,0,1,1)>0,OFFSET(A62,-6,0,1,1)+0.001,ERROR.TYPE(0)),IFERROR(IF(OFFSET(A62,-7,0,1,1)>0,OFFSET(A62,-7,0,1,1)+0.001,ERROR.TYPE(0)),IFERROR(IF(OFFSET(A62,-8,0,1,1)>0,OFFSET(A62,-8,0,1,1)+0.001,ERROR.TYPE(0)),IFERROR(IF(OFFSET(A62,-9,0,1,1)>0,OFFSET(A62,-9,0,1,1)+0.001,ERROR.TYPE(0)),IFERROR(IF(OFFSET(A62,-10,0,1,1)>0,OFFSET(A62,-10,0,1,1)+0.001,ERROR.TYPE(0)),ERROR.TYPE(0))))))))))) -> 2.02 | B62: HRU-OL2-02 Heat Recovery Unit - 900m3/hr at 250Pa - installed at Level 4 | C62: 1 | D62: No. | E62: =Elec_Est!E388 -> 65.62 | F62: =IFERROR($C62*E62,E62) -> 65.62 | G62: =Elec_Est!AM388 -> 20.04 | H62: =Elec_Est!AN388 -> 1.66
A63: =IFERROR(IF(OFFSET(A63,-1,0,1,1)>0,OFFSET(A63,-1,0,1,1)+0.001,ERROR.TYPE(0)),IFERROR(IF(OFFSET(A63,-2,0,1,1)>0,OFFSET(A63,-2,0,1,1)+0.001,ERROR.TYPE(0)),IFERROR(IF(OFFSET(A63,-3,0,1,1)>0,OFFSET(A63,-3,0,1,1)+0.001,ERROR.TYPE(0)),IFERROR(IF(OFFSET(A63,-4,0,1,1)>0,OFFSET(A63,-4,0,1,1)+0.001,ERROR.TYPE(0)),IFERROR(IF(OFFSET(A63,-5,0,1,1)>0,OFFSET(A63,-5,0,1,1)+0.001,ERROR.TYPE(0)),IFERROR(IF(OFFSET(A63,-6,0,1,1)>0,OFFSET(A63,-6,0,1,1)+0.001,ERROR.TYPE(0)),IFERROR(IF(OFFSET(A63,-7,0,1,1)>0,OFFSET(A63,-7,0,1,1)+0.001,ERROR.TYPE(0)),IFERROR(IF(OFFSET(A63,-8,0,1,1)>0,OFFSET(A63,-8,0,1,1)+0.001,ERROR.TYPE(0)),IFERROR(IF(OFFSET(A63,-9,0,1,1)>0,OFFSET(A63,-9,0,1,1)+0.001,ERROR.TYPE(0)),IFERROR(IF(OFFSET(A63,-10,0,1,1)>0,OFFSET(A63,-10,0,1,1)+0.001,ERROR.TYPE(0)),ERROR.TYPE(0))))))))))) -> 2.021 | B63: HRU-OL3-01 Heat Recovery Unit - 750m3/hr at 200Pa - installed at Level 4 | C63: 1 | D63: No. | E63: =Elec_Est!E404 -> 65.62 | F63: =IFERROR($C63*E63,E63) -> 65.62 | G63: =Elec_Est!AM404 -> 20.04 | H63: =Elec_Est!AN404 -> 1.66
A64: =IFERROR(IF(OFFSET(A64,-1,0,1,1)>0,OFFSET(A64,-1,0,1,1)+0.001,ERROR.TYPE(0)),IFERROR(IF(OFFSET(A64,-2,0,1,1)>0,OFFSET(A64,-2,0,1,1)+0.001,ERROR.TYPE(0)),IFERROR(IF(OFFSET(A64,-3,0,1,1)>0,OFFSET(A64,-3,0,1,1)+0.001,ERROR.TYPE(0)),IFERROR(IF(OFFSET(A64,-4,0,1,1)>0,OFFSET(A64,-4,0,1,1)+0.001,ERROR.TYPE(0)),IFERROR(IF(OFFSET(A64,-5,0,1,1)>0,OFFSET(A64,-5,0,1,1)+0.001,ERROR.TYPE(0)),IFERROR(IF(OFFSET(A64,-6,0,1,1)>0,OFFSET(A64,-6,0,1,1)+0.001,ERROR.TYPE(0)),IFERROR(IF(OFFSET(A64,-7,0,1,1)>0,OFFSET(A64,-7,0,1,1)+0.001,ERROR.TYPE(0)),IFERROR(IF(OFFSET(A64,-8,0,1,1)>0,OFFSET(A64,-8,0,1,1)+0.001,ERROR.TYPE(0)),IFERROR(IF(OFFSET(A64,-9,0,1,1)>0,OFFSET(A64,-9,0,1,1)+0.001,ERROR.TYPE(0)),IFERROR(IF(OFFSET(A64,-10,0,1,1)>0,OFFSET(A64,-10,0,1,1)+0.001,ERROR.TYPE(0)),ERROR.TYPE(0))))))))))) -> 2.022 | B64: HRU-OL3-02 Heat Recovery Unit - 900m3/hr at 250Pa - installed at Level 4 | C64: 1 | D64: No. | E64: =Elec_Est!E420 -> 65.62 | F64: =IFERROR($C64*E64,E64) -> 65.62 | G64: =Elec_Est!AM420 -> 20.04 | H64: =Elec_Est!AN420 -> 1.66
A65: =IFERROR(IF(OFFSET(A65,-1,0,1,1)>0,OFFSET(A65,-1,0,1,1)+0.001,ERROR.TYPE(0)),IFERROR(IF(OFFSET(A65,-2,0,1,1)>0,OFFSET(A65,-2,0,1,1)+0.001,ERROR.TYPE(0)),IFERROR(IF(OFFSET(A65,-3,0,1,1)>0,OFFSET(A65,-3,0,1,1)+0.001,ERROR.TYPE(0)),IFERROR(IF(OFFSET(A65,-4,0,1,1)>0,OFFSET(A65,-4,0,1,1)+0.001,ERROR.TYPE(0)),IFERROR(IF(OFFSET(A65,-5,0,1,1)>0,OFFSET(A65,-5,0,1,1)+0.001,ERROR.TYPE(0)),IFERROR(IF(OFFSET(A65,-6,0,1,1)>0,OFFSET(A65,-6,0,1,1)+0.001,ERROR.TYPE(0)),IFERROR(IF(OFFSET(A65,-7,0,1,1)>0,OFFSET(A65,-7,0,1,1)+0.001,ERROR.TYPE(0)),IFERROR(IF(OFFSET(A65,-8,0,1,1)>0,OFFSET(A65,-8,0,1,1)+0.001,ERROR.TYPE(0)),IFERROR(IF(OFFSET(A65,-9,0,1,1)>0,OFFSET(A65,-9,0,1,1)+0.001,ERROR.TYPE(0)),IFERROR(IF(OFFSET(A65,-10,0,1,1)>0,OFFSET(A65,-10,0,1,1)+0.001,ERROR.TYPE(0)),ERROR.TYPE(0))))))))))) -> 2.023 | B65: HRU-OL3-03 Heat Recovery Unit - 300m3/hr at 250Pa - installed at Level 4 | C65: 1 | D65: No. | E65: =Elec_Est!E436 -> 65.62 | F65: =IFERROR($C65*E65,E65) -> 65.62 | G65: =Elec_Est!AM436 -> 20.04 | H65: =Elec_Est!AN436 -> 1.66
A66: =IFERROR(IF(OFFSET(A66,-1,0,1,1)>0,OFFSET(A66,-1,0,1,1)+0.001,ERROR.TYPE(0)),IFERROR(IF(OFFSET(A66,-2,0,1,1)>0,OFFSET(A66,-2,0,1,1)+0.001,ERROR.TYPE(0)),IFERROR(IF(OFFSET(A66,-3,0,1,1)>0,OFFSET(A66,-3,0,1,1)+0.001,ERROR.TYPE(0)),IFERROR(IF(OFFSET(A66,-4,0,1,1)>0,OFFSET(A66,-4,0,1,1)+0.001,ERROR.TYPE(0)),IFERROR(IF(OFFSET(A66,-5,0,1,1)>0,OFFSET(A66,-5,0,1,1)+0.001,ERROR.TYPE(0)),IFERROR(IF(OFFSET(A66,-6,0,1,1)>0,OFFSET(A66,-6,0,1,1)+0.001,ERROR.TYPE(0)),IFERROR(IF(OFFSET(A66,-7,0,1,1)>0,OFFSET(A66,-7,0,1,1)+0.001,ERROR.TYPE(0)),IFERROR(IF(OFFSET(A66,-8,0,1,1)>0,OFFSET(A66,-8,0,1,1)+0.001,ERROR.TYPE(0)),IFERROR(IF(OFFSET(A66,-9,0,1,1)>0,OFFSET(A66,-9,0,1,1)+0.001,ERROR.TYPE(0)),IFERROR(IF(OFFSET(A66,-10,0,1,1)>0,OFFSET(A66,-10,0,1,1)+0.001,ERROR.TYPE(0)),ERROR.TYPE(0))))))))))) -> 2.024 | B66: HRU-CAN-01 Heat Recovery Unit - 700m3/hr at 200Pa - installed at Level 2 | C66: 1 | D66: No. | E66: =Elec_Est!E452 -> 65.62 | F66: =IFERROR($C66*E66,E66) -> 65.62 | G66: =Elec_Est!AM452 -> 20.04 | H66: =Elec_Est!AN452 -> 1.66
A67: =IFERROR(IF(OFFSET(A67,-1,0,1,1)>0,OFFSET(A67,-1,0,1,1)+0.001,ERROR.TYPE(0)),IFERROR(IF(OFFSET(A67,-2,0,1,1)>0,OFFSET(A67,-2,0,1,1)+0.001,ERROR.TYPE(0)),IFERROR(IF(OFFSET(A67,-3,0,1,1)>0,OFFSET(A67,-3,0,1,1)+0.001,ERROR.TYPE(0)),IFERROR(IF(OFFSET(A67,-4,0,1,1)>0,OFFSET(A67,-4,0,1,1)+0.001,ERROR.TYPE(0)),IFERROR(IF(OFFSET(A67,-5,0,1,1)>0,OFFSET(A67,-5,0,1,1)+0.001,ERROR.TYPE(0)),IFERROR(IF(OFFSET(A67,-6,0,1,1)>0,OFFSET(A67,-6,0,1,1)+0.001,ERROR.TYPE(0)),IFERROR(IF(OFFSET(A67,-7,0,1,1)>0,OFFSET(A67,-7,0,1,1)+0.001,ERROR.TYPE(0)),IFERROR(IF(OFFSET(A67,-8,0,1,1)>0,OFFSET(A67,-8,0,1,1)+0.001,ERROR.TYPE(0)),IFERROR(IF(OFFSET(A67,-9,0,1,1)>0,OFFSET(A67,-9,0,1,1)+0.001,ERROR.TYPE(0)),IFERROR(IF(OFFSET(A67,-10,0,1,1)>0,OFFSET(A67,-10,0,1,1)+0.001,ERROR.TYPE(0)),ERROR.TYPE(0))))))))))) -> 2.025 | B67: Supply and install differential pressure alarm complete with remote visual and audible indicators including all cabling etc for a complete system | C67: 8 | D67: No. | E67: =Elec_Est!E468 -> 709.79 | F67: =IFERROR($C67*E67,E67) -> 5678.32 | G67: =Elec_Est!AM468 -> 2040.4 | H67: =Elec_Est!AN468 -> 132.48
A68: P | B68: TOTAL FOR PAGE 03 | C68: Euro Exc VAT | F68: =SUM(F32:F67) -> 11897.33 | G68: =SUM(G32:G67) -> 5347.63 | H68: =SUM(H32:H67) -> 243.84 | I68: =SUM(I32:I67) -> 0
A71: ITEM | B71: DESCRIPTION | C71: QTY | D71: UNIT | E71: RATE Euro (Exc of VAT) | F71: TOTAL Euro (Exc of VAT) | G71: Material cost to Panta Ex VAT | H71: Labour pair hours @ €27.46per pair hour | I71: Labour pair hours @ €52.92per pair hour
B72: BASEMENT LEVEL -1
B73: Supply and install the following galvanised ductwork inc. all elbows, Tee's, transformation pieces, brackets. All external ductwork shall be c/w weatherproofing.
A74: =IFERROR(IF(OFFSET(A74,-1,0,1,1)>0,OFFSET(A74,-1,0,1,1)+0.001,ERROR.TYPE(0)),IFERROR(IF(OFFSET(A74,-2,0,1,1)>0,OFFSET(A74,-2,0,1,1)+0.001,ERROR.TYPE(0)),IFERROR(IF(OFFSET(A74,-3,0,1,1)>0,OFFSET(A74,-3,0,1,1)+0.001,ERROR.TYPE(0)),IFERROR(IF(OFFSET(A74,-4,0,1,1)>0,OFFSET(A74,-4,0,1,1)+0.001,ERROR.TYPE(0)),IFERROR(IF(OFFSET(A74,-5,0,1,1)>0,OFFSET(A74,-5,0,1,1)+0.001,ERROR.TYPE(0)),IFERROR(IF(OFFSET(A74,-6,0,1,1)>0,OFFSET(A74,-6,0,1,1)+0.001,ERROR.TYPE(0)),IFERROR(IF(OFFSET(A74,-7,0,1,1)>0,OFFSET(A74,-7,0,1,1)+0.001,ERROR.TYPE(0)),IFERROR(IF(OFFSET(A74,-8,0,1,1)>0,OFFSET(A74,-8,0,1,1)+0.001,ERROR.TYPE(0)),IFERROR(IF(OFFSET(A74,-9,0,1,1)>0,OFFSET(A74,-9,0,1,1)+0.001,ERROR.TYPE(0)),IFERROR(IF(OFFSET(A74,-10,0,1,1)>0,OFFSET(A74,-10,0,1,1)+0.001,ERROR.TYPE(0)),ERROR.TYPE(0))))))))))) -> 2.026 | B74: 1000 x 850 mm | C74: 5 | D74: m | F74: =IFERROR($C74*E74,E74) -> 0
A75: =IFERROR(IF(OFFSET(A75,-1,0,1,1)>0,OFFSET(A75,-1,0,1,1)+0.001,ERROR.TYPE(0)),IFERROR(IF(OFFSET(A75,-2,0,1,1)>0,OFFSET(A75,-2,0,1,1)+0.001,ERROR.TYPE(0)),IFERROR(IF(OFFSET(A75,-3,0,1,1)>0,OFFSET(A75,-3,0,1,1)+0.001,ERROR.TYPE(0)),IFERROR(IF(OFFSET(A75,-4,0,1,1)>0,OFFSET(A75,-4,0,1,1)+0.001,ERROR.TYPE(0)),IFERROR(IF(OFFSET(A75,-5,0,1,1)>0,OFFSET(A75,-5,0,1,1)+0.001,ERROR.TYPE(0)),IFERROR(IF(OFFSET(A75,-6,0,1,1)>0,OFFSET(A75,-6,0,1,1)+0.001,ERROR.TYPE(0)),IFERROR(IF(OFFSET(A75,-7,0,1,1)>0,OFFSET(A75,-7,0,1,1)+0.001,ERROR.TYPE(0)),IFERROR(IF(OFFSET(A75,-8,0,1,1)>0,OFFSET(A75,-8,0,1,1)+0.001,ERROR.TYPE(0)),IFERROR(IF(OFFSET(A75,-9,0,1,1)>0,OFFSET(A75,-9,0,1,1)+0.001,ERROR.TYPE(0)),IFERROR(IF(OFFSET(A75,-10,0,1,1)>0,OFFSET(A75,-10,0,1,1)+0.001,ERROR.TYPE(0)),ERROR.TYPE(0))))))))))) -> 2.027 | B75: 1500 x 1700 mm | C75: 5 | D75: m | F75: =IFERROR($C75*E75,E75) -> 0
A76: =IFERROR(IF(OFFSET(A76,-1,0,1,1)>0,OFFSET(A76,-1,0,1,1)+0.001,ERROR.TYPE(0)),IFERROR(IF(OFFSET(A76,-2,0,1,1)>0,OFFSET(A76,-2,0,1,1)+0.001,ERROR.TYPE(0)),IFERROR(IF(OFFSET(A76,-3,0,1,1)>0,OFFSET(A76,-3,0,1,1)+0.001,ERROR.TYPE(0)),IFERROR(IF(OFFSET(A76,-4,0,1,1)>0,OFFSET(A76,-4,0,1,1)+0.001,ERROR.TYPE(0)),IFERROR(IF(OFFSET(A76,-5,0,1,1)>0,OFFSET(A76,-5,0,1,1)+0.001,ERROR.TYPE(0)),IFERROR(IF(OFFSET(A76,-6,0,1,1)>0,OFFSET(A76,-6,0,1,1)+0.001,ERROR.TYPE(0)),IFERROR(IF(OFFSET(A76,-7,0,1,1)>0,OFFSET(A76,-7,0,1,1)+0.001,ERROR.TYPE(0)),IFERROR(IF(OFFSET(A76,-8,0,1,1)>0,OFFSET(A76,-8,0,1,1)+0.001,ERROR.TYPE(0)),IFERROR(IF(OFFSET(A76,-9,0,1,1)>0,OFFSET(A76,-9,0,1,1)+0.001,ERROR.TYPE(0)),IFERROR(IF(OFFSET(A76,-10,0,1,1)>0,OFFSET(A76,-10,0,1,1)+0.001,ERROR.TYPE(0)),ERROR.TYPE(0))))))))))) -> 2.028 | B76: 1500 x 1150 mm | C76: 5 | D76: m | F76: =IFERROR($C76*E76,E76) -> 0
A77: =IFERROR(IF(OFFSET(A77,-1,0,1,1)>0,OFFSET(A77,-1,0,1,1)+0.001,ERROR.TYPE(0)),IFERROR(IF(OFFSET(A77,-2,0,1,1)>0,OFFSET(A77,-2,0,1,1)+0.001,ERROR.TYPE(0)),IFERROR(IF(OFFSET(A77,-3,0,1,1)>0,OFFSET(A77,-3,0,1,1)+0.001,ERROR.TYPE(0)),IFERROR(IF(OFFSET(A77,-4,0,1,1)>0,OFFSET(A77,-4,0,1,1)+0.001,ERROR.TYPE(0)),IFERROR(IF(OFFSET(A77,-5,0,1,1)>0,OFFSET(A77,-5,0,1,1)+0.001,ERROR.TYPE(0)),IFERROR(IF(OFFSET(A77,-6,0,1,1)>0,OFFSET(A77,-6,0,1,1)+0.001,ERROR.TYPE(0)),IFERROR(IF(OFFSET(A77,-7,0,1,1)>0,OFFSET(A77,-7,0,1,1)+0.001,ERROR.TYPE(0)),IFERROR(IF(OFFSET(A77,-8,0,1,1)>0,OFFSET(A77,-8,0,1,1)+0.001,ERROR.TYPE(0)),IFERROR(IF(OFFSET(A77,-9,0,1,1)>0,OFFSET(A77,-9,0,1,1)+0.001,ERROR.TYPE(0)),IFERROR(IF(OFFSET(A77,-10,0,1,1)>0,OFFSET(A77,-10,0,1,1)+0.001,ERROR.TYPE(0)),ERROR.TYPE(0))))))))))) -> 2.029 | B77: 1500 x 600 mm | C77: 5 | D77: m | F77: =IFERROR($C77*E77,E77) -> 0
B78: Supply and install the following linear type supply/extraction grills c/w transformation pieces etc for a complete system.
A79: =IFERROR(IF(OFFSET(A79,-1,0,1,1)>0,OFFSET(A79,-1,0,1,1)+0.001,ERROR.TYPE(0)),IFERROR(IF(OFFSET(A79,-2,0,1,1)>0,OFFSET(A79,-2,0,1,1)+0.001,ERROR.TYPE(0)),IFERROR(IF(OFFSET(A79,-3,0,1,1)>0,OFFSET(A79,-3,0,1,1)+0.001,ERROR.TYPE(0)),IFERROR(IF(OFFSET(A79,-4,0,1,1)>0,OFFSET(A79,-4,0,1,1)+0.001,ERROR.TYPE(0)),IFERROR(IF(OFFSET(A79,-5,0,1,1)>0,OFFSET(A79,-5,0,1,1)+0.001,ERROR.TYPE(0)),IFERROR(IF(OFFSET(A79,-6,0,1,1)>0,OFFSET(A79,-6,0,1,1)+0.001,ERROR.TYPE(0)),IFERROR(IF(OFFSET(A79,-7,0,1,1)>0,OFFSET(A79,-7,0,1,1)+0.001,ERROR.TYPE(0)),IFERROR(IF(OFFSET(A79,-8,0,1,1)>0,OFFSET(A79,-8,0,1,1)+0.001,ERROR.TYPE(0)),IFERROR(IF(OFFSET(A79,-9,0,1,1)>0,OFFSET(A79,-9,0,1,1)+0.001,ERROR.TYPE(0)),IFERROR(IF(OFFSET(A79,-10,0,1,1)>0,OFFSET(A79,-10,0,1,1)+0.001,ERROR.TYPE(0)),ERROR.TYPE(0))))))))))) -> 2.03 | B79: EG 01 - 2500 x 4000 mm | C79: 1 | D79: No. | F79: =IFERROR($C79*E79,E79) -> 0
A80: =IFERROR(IF(OFFSET(A80,-1,0,1,1)>0,OFFSET(A80,-1,0,1,1)+0.001,ERROR.TYPE(0)),IFERROR(IF(OFFSET(A80,-2,0,1,1)>0,OFFSET(A80,-2,0,1,1)+0.001,ERROR.TYPE(0)),IFERROR(IF(OFFSET(A80,-3,0,1,1)>0,OFFSET(A80,-3,0,1,1)+0.001,ERROR.TYPE(0)),IFERROR(IF(OFFSET(A80,-4,0,1,1)>0,OFFSET(A80,-4,0,1,1)+0.001,ERROR.TYPE(0)),IFERROR(IF(OFFSET(A80,-5,0,1,1)>0,OFFSET(A80,-5,0,1,1)+0.001,ERROR.TYPE(0)),IFERROR(IF(OFFSET(A80,-6,0,1,1)>0,OFFSET(A80,-6,0,1,1)+0.001,ERROR.TYPE(0)),IFERROR(IF(OFFSET(A80,-7,0,1,1)>0,OFFSET(A80,-7,0,1,1)+0.001,ERROR.TYPE(0)),IFERROR(IF(OFFSET(A80,-8,0,1,1)>0,OFFSET(A80,-8,0,1,1)+0.001,ERROR.TYPE(0)),IFERROR(IF(OFFSET(A80,-9,0,1,1)>0,OFFSET(A80,-9,0,1,1)+0.001,ERROR.TYPE(0)),IFERROR(IF(OFFSET(A80,-10,0,1,1)>0,OFFSET(A80,-10,0,1,1)+0.001,ERROR.TYPE(0)),ERROR.TYPE(0))))))))))) -> 2.031 | B80: EG 02 - 1200 x 4800 mm | C80: 1 | D80: No. | F80: =IFERROR($C80*E80,E80) -> 0
A81: =IFERROR(IF(OFFSET(A81,-1,0,1,1)>0,OFFSET(A81,-1,0,1,1)+0.001,ERROR.TYPE(0)),IFERROR(IF(OFFSET(A81,-2,0,1,1)>0,OFFSET(A81,-2,0,1,1)+0.001,ERROR.TYPE(0)),IFERROR(IF(OFFSET(A81,-3,0,1,1)>0,OFFSET(A81,-3,0,1,1)+0.001,ERROR.TYPE(0)),IFERROR(IF(OFFSET(A81,-4,0,1,1)>0,OFFSET(A81,-4,0,1,1)+0.001,ERROR.TYPE(0)),IFERROR(IF(OFFSET(A81,-5,0,1,1)>0,OFFSET(A81,-5,0,1,1)+0.001,ERROR.TYPE(0)),IFERROR(IF(OFFSET(A81,-6,0,1,1)>0,OFFSET(A81,-6,0,1,1)+0.001,ERROR.TYPE(0)),IFERROR(IF(OFFSET(A81,-7,0,1,1)>0,OFFSET(A81,-7,0,1,1)+0.001,ERROR.TYPE(0)),IFERROR(IF(OFFSET(A81,-8,0,1,1)>0,OFFSET(A81,-8,0,1,1)+0.001,ERROR.TYPE(0)),IFERROR(IF(OFFSET(A81,-9,0,1,1)>0,OFFSET(A81,-9,0,1,1)+0.001,ERROR.TYPE(0)),IFERROR(IF(OFFSET(A81,-10,0,1,1)>0,OFFSET(A81,-10,0,1,1)+0.001,ERROR.TYPE(0)),ERROR.TYPE(0))))))))))) -> 2.032 | B81: EG 07 - 1500 x 2400 mm | C81: 1 | D81: No. | F81: =IFERROR($C81*E81,E81) -> 0
A82: =IFERROR(IF(OFFSET(A82,-1,0,1,1)>0,OFFSET(A82,-1,0,1,1)+0.001,ERROR.TYPE(0)),IFERROR(IF(OFFSET(A82,-2,0,1,1)>0,OFFSET(A82,-2,0,1,1)+0.001,ERROR.TYPE(0)),IFERROR(IF(OFFSET(A82,-3,0,1,1)>0,OFFSET(A82,-3,0,1,1)+0.001,ERROR.TYPE(0)),IFERROR(IF(OFFSET(A82,-4,0,1,1)>0,OFFSET(A82,-4,0,1,1)+0.001,ERROR.TYPE(0)),IFERROR(IF(OFFSET(A82,-5,0,1,1)>0,OFFSET(A82,-5,0,1,1)+0.001,ERROR.TYPE(0)),IFERROR(IF(OFFSET(A82,-6,0,1,1)>0,OFFSET(A82,-6,0,1,1)+0.001,ERROR.TYPE(0)),IFERROR(IF(OFFSET(A82,-7,0,1,1)>0,OFFSET(A82,-7,0,1,1)+0.001,ERROR.TYPE(0)),IFERROR(IF(OFFSET(A82,-8,0,1,1)>0,OFFSET(A82,-8,0,1,1)+0.001,ERROR.TYPE(0)),IFERROR(IF(OFFSET(A82,-9,0,1,1)>0,OFFSET(A82,-9,0,1,1)+0.001,ERROR.TYPE(0)),IFERROR(IF(OFFSET(A82,-10,0,1,1)>0,OFFSET(A82,-10,0,1,1)+0.001,ERROR.TYPE(0)),ERROR.TYPE(0))))))))))) -> 2.033 | B82: SG 06 - 1200 x 800 mm | C82: 3 | D82: No. | F82: =IFERROR($C82*E82,E82) -> 0
B83: Supply and install the following weatherproof louvers/bird screens c/w transformation pieces etc for a complete system.
A84: =IFERROR(IF(OFFSET(A84,-1,0,1,1)>0,OFFSET(A84,-1,0,1,1)+0.001,ERROR.TYPE(0)),IFERROR(IF(OFFSET(A84,-2,0,1,1)>0,OFFSET(A84,-2,0,1,1)+0.001,ERROR.TYPE(0)),IFERROR(IF(OFFSET(A84,-3,0,1,1)>0,OFFSET(A84,-3,0,1,1)+0.001,ERROR.TYPE(0)),IFERROR(IF(OFFSET(A84,-4,0,1,1)>0,OFFSET(A84,-4,0,1,1)+0.001,ERROR.TYPE(0)),IFERROR(IF(OFFSET(A84,-5,0,1,1)>0,OFFSET(A84,-5,0,1,1)+0.001,ERROR.TYPE(0)),IFERROR(IF(OFFSET(A84,-6,0,1,1)>0,OFFSET(A84,-6,0,1,1)+0.001,ERROR.TYPE(0)),IFERROR(IF(OFFSET(A84,-7,0,1,1)>0,OFFSET(A84,-7,0,1,1)+0.001,ERROR.TYPE(0)),IFERROR(IF(OFFSET(A84,-8,0,1,1)>0,OFFSET(A84,-8,0,1,1)+0.001,ERROR.TYPE(0)),IFERROR(IF(OFFSET(A84,-9,0,1,1)>0,OFFSET(A84,-9,0,1,1)+0.001,ERROR.TYPE(0)),IFERROR(IF(OFFSET(A84,-10,0,1,1)>0,OFFSET(A84,-10,0,1,1)+0.001,ERROR.TYPE(0)),ERROR.TYPE(0))))))))))) -> 2.034 | B84: WL 02 - 1000 x 850 mm | C84: 1 | D84: No. | F84: =IFERROR($C84*E84,E84) -> 0
B85: Supply and install the following phenolic ductwork inc. all elbows, Tee's, transformation pieces, brackets. All external ductwork shall be c/w weatherproofing.
A86: =IFERROR(IF(OFFSET(A86,-1,0,1,1)>0,OFFSET(A86,-1,0,1,1)+0.001,ERROR.TYPE(0)),IFERROR(IF(OFFSET(A86,-2,0,1,1)>0,OFFSET(A86,-2,0,1,1)+0.001,ERROR.TYPE(0)),IFERROR(IF(OFFSET(A86,-3,0,1,1)>0,OFFSET(A86,-3,0,1,1)+0.001,ERROR.TYPE(0)),IFERROR(IF(OFFSET(A86,-4,0,1,1)>0,OFFSET(A86,-4,0,1,1)+0.001,ERROR.TYPE(0)),IFERROR(IF(OFFSET(A86,-5,0,1,1)>0,OFFSET(A86,-5,0,1,1)+0.001,ERROR.TYPE(0)),IFERROR(IF(OFFSET(A86,-6,0,1,1)>0,OFFSET(A86,-6,0,1,1)+0.001,ERROR.TYPE(0)),IFERROR(IF(OFFSET(A86,-7,0,1,1)>0,OFFSET(A86,-7,0,1,1)+0.001,ERROR.TYPE(0)),IFERROR(IF(OFFSET(A86,-8,0,1,1)>0,OFFSET(A86,-8,0,1,1)+0.001,ERROR.TYPE(0)),IFERROR(IF(OFFSET(A86,-9,0,1,1)>0,OFFSET(A86,-9,0,1,1)+0.001,ERROR.TYPE(0)),IFERROR(IF(OFFSET(A86,-10,0,1,1)>0,OFFSET(A86,-10,0,1,1)+0.001,ERROR.TYPE(0)),ERROR.TYPE(0))))))))))) -> 2.035 | B86: 200 x 150 mm | C86: 15 | D86: m | F86: =IFERROR($C86*E86,E86) -> 0
A87: =IFERROR(IF(OFFSET(A87,-1,0,1,1)>0,OFFSET(A87,-1,0,1,1)+0.001,ERROR.TYPE(0)),IFERROR(IF(OFFSET(A87,-2,0,1,1)>0,OFFSET(A87,-2,0,1,1)+0.001,ERROR.TYPE(0)),IFERROR(IF(OFFSET(A87,-3,0,1,1)>0,OFFSET(A87,-3,0,1,1)+0.001,ERROR.TYPE(0)),IFERROR(IF(OFFSET(A87,-4,0,1,1)>0,OFFSET(A87,-4,0,1,1)+0.001,ERROR.TYPE(0)),IFERROR(IF(OFFSET(A87,-5,0,1,1)>0,OFFSET(A87,-5,0,1,1)+0.001,ERROR.TYPE(0)),IFERROR(IF(OFFSET(A87,-6,0,1,1)>0,OFFSET(A87,-6,0,1,1)+0.001,ERROR.TYPE(0)),IFERROR(IF(OFFSET(A87,-7,0,1,1)>0,OFFSET(A87,-7,0,1,1)+0.001,ERROR.TYPE(0)),IFERROR(IF(OFFSET(A87,-8,0,1,1)>0,OFFSET(A87,-8,0,1,1)+0.001,ERROR.TYPE(0)),IFERROR(IF(OFFSET(A87,-9,0,1,1)>0,OFFSET(A87,-9,0,1,1)+0.001,ERROR.TYPE(0)),IFERROR(IF(OFFSET(A87,-10,0,1,1)>0,OFFSET(A87,-10,0,1,1)+0.001,ERROR.TYPE(0)),ERROR.TYPE(0))))))))))) -> 2.036 | B87: 250 x 250 mm | C87: 5 | D87: m | F87: =IFERROR($C87*E87,E87) -> 0
A88: =IFERROR(IF(OFFSET(A88,-1,0,1,1)>0,OFFSET(A88,-1,0,1,1)+0.001,ERROR.TYPE(0)),IFERROR(IF(OFFSET(A88,-2,0,1,1)>0,OFFSET(A88,-2,0,1,1)+0.001,ERROR.TYPE(0)),IFERROR(IF(OFFSET(A88,-3,0,1,1)>0,OFFSET(A88,-3,0,1,1)+0.001,ERROR.TYPE(0)),IFERROR(IF(OFFSET(A88,-4,0,1,1)>0,OFFSET(A88,-4,0,1,1)+0.001,ERROR.TYPE(0)),IFERROR(IF(OFFSET(A88,-5,0,1,1)>0,OFFSET(A88,-5,0,1,1)+0.001,ERROR.TYPE(0)),IFERROR(IF(OFFSET(A88,-6,0,1,1)>0,OFFSET(A88,-6,0,1,1)+0.001,ERROR.TYPE(0)),IFERROR(IF(OFFSET(A88,-7,0,1,1)>0,OFFSET(A88,-7,0,1,1)+0.001,ERROR.TYPE(0)),IFERROR(IF(OFFSET(A88,-8,0,1,1)>0,OFFSET(A88,-8,0,1,1)+0.001,ERROR.TYPE(0)),IFERROR(IF(OFFSET(A88,-9,0,1,1)>0,OFFSET(A88,-9,0,1,1)+0.001,ERROR.TYPE(0)),IFERROR(IF(OFFSET(A88,-10,0,1,1)>0,OFFSET(A88,-10,0,1,1)+0.001,ERROR.TYPE(0)),ERROR.TYPE(0))))))))))) -> 2.037 | B88: 325 x 250 mm | C88: 5 | D88: m | F88: =IFERROR($C88*E88,E88) -> 0
B89: Supply and install the following linear type supply/extraction grills c/w transformation pieces etc for a complete system.
A90: =IFERROR(IF(OFFSET(A90,-1,0,1,1)>0,OFFSET(A90,-1,0,1,1)+0.001,ERROR.TYPE(0)),IFERROR(IF(OFFSET(A90,-2,0,1,1)>0,OFFSET(A90,-2,0,1,1)+0.001,ERROR.TYPE(0)),IFERROR(IF(OFFSET(A90,-3,0,1,1)>0,OFFSET(A90,-3,0,1,1)+0.001,ERROR.TYPE(0)),IFERROR(IF(OFFSET(A90,-4,0,1,1)>0,OFFSET(A90,-4,0,1,1)+0.001,ERROR.TYPE(0)),IFERROR(IF(OFFSET(A90,-5,0,1,1)>0,OFFSET(A90,-5,0,1,1)+0.001,ERROR.TYPE(0)),IFERROR(IF(OFFSET(A90,-6,0,1,1)>0,OFFSET(A90,-6,0,1,1)+0.001,ERROR.TYPE(0)),IFERROR(IF(OFFSET(A90,-7,0,1,1)>0,OFFSET(A90,-7,0,1,1)+0.001,ERROR.TYPE(0)),IFERROR(IF(OFFSET(A90,-8,0,1,1)>0,OFFSET(A90,-8,0,1,1)+0.001,ERROR.TYPE(0)),IFERROR(IF(OFFSET(A90,-9,0,1,1)>0,OFFSET(A90,-9,0,1,1)+0.001,ERROR.TYPE(0)),IFERROR(IF(OFFSET(A90,-10,0,1,1)>0,OFFSET(A90,-10,0,1,1)+0.001,ERROR.TYPE(0)),ERROR.TYPE(0))))))))))) -> 2.038 | B90: EG 04 - 400 x 75 mm | C90: 1 | D90: No. | F90: =IFERROR($C90*E90,E90) -> 0
A91: =IFERROR(IF(OFFSET(A91,-1,0,1,1)>0,OFFSET(A91,-1,0,1,1)+0.001,ERROR.TYPE(0)),IFERROR(IF(OFFSET(A91,-2,0,1,1)>0,OFFSET(A91,-2,0,1,1)+0.001,ERROR.TYPE(0)),IFERROR(IF(OFFSET(A91,-3,0,1,1)>0,OFFSET(A91,-3,0,1,1)+0.001,ERROR.TYPE(0)),IFERROR(IF(OFFSET(A91,-4,0,1,1)>0,OFFSET(A91,-4,0,1,1)+0.001,ERROR.TYPE(0)),IFERROR(IF(OFFSET(A91,-5,0,1,1)>0,OFFSET(A91,-5,0,1,1)+0.001,ERROR.TYPE(0)),IFERROR(IF(OFFSET(A91,-6,0,1,1)>0,OFFSET(A91,-6,0,1,1)+0.001,ERROR.TYPE(0)),IFERROR(IF(OFFSET(A91,-7,0,1,1)>0,OFFSET(A91,-7,0,1,1)+0.001,ERROR.TYPE(0)),IFERROR(IF(OFFSET(A91,-8,0,1,1)>0,OFFSET(A91,-8,0,1,1)+0.001,ERROR.TYPE(0)),IFERROR(IF(OFFSET(A91,-9,0,1,1)>0,OFFSET(A91,-9,0,1,1)+0.001,ERROR.TYPE(0)),IFERROR(IF(OFFSET(A91,-10,0,1,1)>0,OFFSET(A91,-10,0,1,1)+0.001,ERROR.TYPE(0)),ERROR.TYPE(0))))))))))) -> 2.039 | B91: EG 05 - 800 x 150 mm | C91: 1 | D91: No. | F91: =IFERROR($C91*E91,E91) -> 0
A92: =IFERROR(IF(OFFSET(A92,-1,0,1,1)>0,OFFSET(A92,-1,0,1,1)+0.001,ERROR.TYPE(0)),IFERROR(IF(OFFSET(A92,-2,0,1,1)>0,OFFSET(A92,-2,0,1,1)+0.001,ERROR.TYPE(0)),IFERROR(IF(OFFSET(A92,-3,0,1,1)>0,OFFSET(A92,-3,0,1,1)+0.001,ERROR.TYPE(0)),IFERROR(IF(OFFSET(A92,-4,0,1,1)>0,OFFSET(A92,-4,0,1,1)+0.001,ERROR.TYPE(0)),IFERROR(IF(OFFSET(A92,-5,0,1,1)>0,OFFSET(A92,-5,0,1,1)+0.001,ERROR.TYPE(0)),IFERROR(IF(OFFSET(A92,-6,0,1,1)>0,OFFSET(A92,-6,0,1,1)+0.001,ERROR.TYPE(0)),IFERROR(IF(OFFSET(A92,-7,0,1,1)>0,OFFSET(A92,-7,0,1,1)+0.001,ERROR.TYPE(0)),IFERROR(IF(OFFSET(A92,-8,0,1,1)>0,OFFSET(A92,-8,0,1,1)+0.001,ERROR.TYPE(0)),IFERROR(IF(OFFSET(A92,-9,0,1,1)>0,OFFSET(A92,-9,0,1,1)+0.001,ERROR.TYPE(0)),IFERROR(IF(OFFSET(A92,-10,0,1,1)>0,OFFSET(A92,-10,0,1,1)+0.001,ERROR.TYPE(0)),ERROR.TYPE(0))))))))))) -> 2.04 | B92: EG 06 - 400 x 100 mm | C92: 1 | D92: No. | F92: =IFERROR($C92*E92,E92) -> 0
A93: T | B93: Supply and install the following motorized fire dampers c/w transformation pieces including all actuators, in-duct smoke detection and connecting up to the electrical supply etc for a complete system.
A94: =IFERROR(IF(OFFSET(A94,-1,0,1,1)>0,OFFSET(A94,-1,0,1,1)+0.001,ERROR.TYPE(0)),IFERROR(IF(OFFSET(A94,-2,0,1,1)>0,OFFSET(A94,-2,0,1,1)+0.001,ERROR.TYPE(0)),IFERROR(IF(OFFSET(A94,-3,0,1,1)>0,OFFSET(A94,-3,0,1,1)+0.001,ERROR.TYPE(0)),IFERROR(IF(OFFSET(A94,-4,0,1,1)>0,OFFSET(A94,-4,0,1,1)+0.001,ERROR.TYPE(0)),IFERROR(IF(OFFSET(A94,-5,0,1,1)>0,OFFSET(A94,-5,0,1,1)+0.001,ERROR.TYPE(0)),IFERROR(IF(OFFSET(A94,-6,0,1,1)>0,OFFSET(A94,-6,0,1,1)+0.001,ERROR.TYPE(0)),IFERROR(IF(OFFSET(A94,-7,0,1,1)>0,OFFSET(A94,-7,0,1,1)+0.001,ERROR.TYPE(0)),IFERROR(IF(OFFSET(A94,-8,0,1,1)>0,OFFSET(A94,-8,0,1,1)+0.001,ERROR.TYPE(0)),IFERROR(IF(OFFSET(A94,-9,0,1,1)>0,OFFSET(A94,-9,0,1,1)+0.001,ERROR.TYPE(0)),IFERROR(IF(OFFSET(A94,-10,0,1,1)>0,OFFSET(A94,-10,0,1,1)+0.001,ERROR.TYPE(0)),ERROR.TYPE(0))))))))))) -> 2.041 | B94: FD 01 - 200 x 150 mm | C94: 2 | D94: No. | E94: =Elec_Est!$Q492 -> Included in item 1.183 | G94: =Elec_Est!$Q492 -> Included in item 1.183 | H94: =Elec_Est!$Q492 -> Included in item 1.183 | I94: =Elec_Est!$Q492 -> Included in item 1.183
A95: =IFERROR(IF(OFFSET(A95,-1,0,1,1)>0,OFFSET(A95,-1,0,1,1)+0.001,ERROR.TYPE(0)),IFERROR(IF(OFFSET(A95,-2,0,1,1)>0,OFFSET(A95,-2,0,1,1)+0.001,ERROR.TYPE(0)),IFERROR(IF(OFFSET(A95,-3,0,1,1)>0,OFFSET(A95,-3,0,1,1)+0.001,ERROR.TYPE(0)),IFERROR(IF(OFFSET(A95,-4,0,1,1)>0,OFFSET(A95,-4,0,1,1)+0.001,ERROR.TYPE(0)),IFERROR(IF(OFFSET(A95,-5,0,1,1)>0,OFFSET(A95,-5,0,1,1)+0.001,ERROR.TYPE(0)),IFERROR(IF(OFFSET(A95,-6,0,1,1)>0,OFFSET(A95,-6,0,1,1)+0.001,ERROR.TYPE(0)),IFERROR(IF(OFFSET(A95,-7,0,1,1)>0,OFFSET(A95,-7,0,1,1)+0.001,ERROR.TYPE(0)),IFERROR(IF(OFFSET(A95,-8,0,1,1)>0,OFFSET(A95,-8,0,1,1)+0.001,ERROR.TYPE(0)),IFERROR(IF(OFFSET(A95,-9,0,1,1)>0,OFFSET(A95,-9,0,1,1)+0.001,ERROR.TYPE(0)),IFERROR(IF(OFFSET(A95,-10,0,1,1)>0,OFFSET(A95,-10,0,1,1)+0.001,ERROR.TYPE(0)),ERROR.TYPE(0))))))))))) -> 2.042 | B95: FD 08 - 250 x 250 mm | C95: 1 | D95: No. | E95: =Elec_Est!$Q508 -> Included in item 1.183 | G95: =Elec_Est!$Q508 -> Included in item 1.183 | H95: =Elec_Est!$Q508 -> Included in item 1.183 | I95: =Elec_Est!$Q508 -> Included in item 1.183
A96: =IFERROR(IF(OFFSET(A96,-1,0,1,1)>0,OFFSET(A96,-1,0,1,1)+0.001,ERROR.TYPE(0)),IFERROR(IF(OFFSET(A96,-2,0,1,1)>0,OFFSET(A96,-2,0,1,1)+0.001,ERROR.TYPE(0)),IFERROR(IF(OFFSET(A96,-3,0,1,1)>0,OFFSET(A96,-3,0,1,1)+0.001,ERROR.TYPE(0)),IFERROR(IF(OFFSET(A96,-4,0,1,1)>0,OFFSET(A96,-4,0,1,1)+0.001,ERROR.TYPE(0)),IFERROR(IF(OFFSET(A96,-5,0,1,1)>0,OFFSET(A96,-5,0,1,1)+0.001,ERROR.TYPE(0)),IFERROR(IF(OFFSET(A96,-6,0,1,1)>0,OFFSET(A96,-6,0,1,1)+0.001,ERROR.TYPE(0)),IFERROR(IF(OFFSET(A96,-7,0,1,1)>0,OFFSET(A96,-7,0,1,1)+0.001,ERROR.TYPE(0)),IFERROR(IF(OFFSET(A96,-8,0,1,1)>0,OFFSET(A96,-8,0,1,1)+0.001,ERROR.TYPE(0)),IFERROR(IF(OFFSET(A96,-9,0,1,1)>0,OFFSET(A96,-9,0,1,1)+0.001,ERROR.TYPE(0)),IFERROR(IF(OFFSET(A96,-10,0,1,1)>0,OFFSET(A96,-10,0,1,1)+0.001,ERROR.TYPE(0)),ERROR.TYPE(0))))))))))) -> 2.043 | B96: FD 09 - 325 x 250 mm | C96: 1 | D96: No. | E96: =Elec_Est!$Q524 -> Included in item 1.183 | G96: =Elec_Est!$Q524 -> Included in item 1.183 | H96: =Elec_Est!$Q524 -> Included in item 1.183 | I96: =Elec_Est!$Q524 -> Included in item 1.183
B97: Supply and install the following 120min fire rated intumescent expanding transfer grills c/w spacers, bracketing for the following blockwork openings
A98: =IFERROR(IF(OFFSET(A98,-1,0,1,1)>0,OFFSET(A98,-1,0,1,1)+0.001,ERROR.TYPE(0)),IFERROR(IF(OFFSET(A98,-2,0,1,1)>0,OFFSET(A98,-2,0,1,1)+0.001,ERROR.TYPE(0)),IFERROR(IF(OFFSET(A98,-3,0,1,1)>0,OFFSET(A98,-3,0,1,1)+0.001,ERROR.TYPE(0)),IFERROR(IF(OFFSET(A98,-4,0,1,1)>0,OFFSET(A98,-4,0,1,1)+0.001,ERROR.TYPE(0)),IFERROR(IF(OFFSET(A98,-5,0,1,1)>0,OFFSET(A98,-5,0,1,1)+0.001,ERROR.TYPE(0)),IFERROR(IF(OFFSET(A98,-6,0,1,1)>0,OFFSET(A98,-6,0,1,1)+0.001,ERROR.TYPE(0)),IFERROR(IF(OFFSET(A98,-7,0,1,1)>0,OFFSET(A98,-7,0,1,1)+0.001,ERROR.TYPE(0)),IFERROR(IF(OFFSET(A98,-8,0,1,1)>0,OFFSET(A98,-8,0,1,1)+0.001,ERROR.TYPE(0)),IFERROR(IF(OFFSET(A98,-9,0,1,1)>0,OFFSET(A98,-9,0,1,1)+0.001,ERROR.TYPE(0)),IFERROR(IF(OFFSET(A98,-10,0,1,1)>0,OFFSET(A98,-10,0,1,1)+0.001,ERROR.TYPE(0)),ERROR.TYPE(0))))))))))) -> 2.044 | B98: IG 01 - 460 x 795 mm | C98: 3 | D98: No. | F98: =IFERROR($C98*E98,E98) -> 0
A99: =IFERROR(IF(OFFSET(A99,-1,0,1,1)>0,OFFSET(A99,-1,0,1,1)+0.001,ERROR.TYPE(0)),IFERROR(IF(OFFSET(A99,-2,0,1,1)>0,OFFSET(A99,-2,0,1,1)+0.001,ERROR.TYPE(0)),IFERROR(IF(OFFSET(A99,-3,0,1,1)>0,OFFSET(A99,-3,0,1,1)+0.001,ERROR.TYPE(0)),IFERROR(IF(OFFSET(A99,-4,0,1,1)>0,OFFSET(A99,-4,0,1,1)+0.001,ERROR.TYPE(0)),IFERROR(IF(OFFSET(A99,-5,0,1,1)>0,OFFSET(A99,-5,0,1,1)+0.001,ERROR.TYPE(0)),IFERROR(IF(OFFSET(A99,-6,0,1,1)>0,OFFSET(A99,-6,0,1,1)+0.001,ERROR.TYPE(0)),IFERROR(IF(OFFSET(A99,-7,0,1,1)>0,OFFSET(A99,-7,0,1,1)+0.001,ERROR.TYPE(0)),IFERROR(IF(OFFSET(A99,-8,0,1,1)>0,OFFSET(A99,-8,0,1,1)+0.001,ERROR.TYPE(0)),IFERROR(IF(OFFSET(A99,-9,0,1,1)>0,OFFSET(A99,-9,0,1,1)+0.001,ERROR.TYPE(0)),IFERROR(IF(OFFSET(A99,-10,0,1,1)>0,OFFSET(A99,-10,0,1,1)+0.001,ERROR.TYPE(0)),ERROR.TYPE(0))))))))))) -> 2.045 | B99: IG 02 - 460 x 1060 mm | C99: 3 | D99: No. | F99: =IFERROR($C99*E99,E99) -> 0
B100: LEVEL 0
B101: Supply and install the following galvanised ductwork inc. all elbows, Tee's, transformation pieces, brackets. All external ductwork shall be c/w weatherproofing.
A102: =IFERROR(IF(OFFSET(A102,-1,0,1,1)>0,OFFSET(A102,-1,0,1,1)+0.001,ERROR.TYPE(0)),IFERROR(IF(OFFSET(A102,-2,0,1,1)>0,OFFSET(A102,-2,0,1,1)+0.001,ERROR.TYPE(0)),IFERROR(IF(OFFSET(A102,-3,0,1,1)>0,OFFSET(A102,-3,0,1,1)+0.001,ERROR.TYPE(0)),IFERROR(IF(OFFSET(A102,-4,0,1,1)>0,OFFSET(A102,-4,0,1,1)+0.001,ERROR.TYPE(0)),IFERROR(IF(OFFSET(A102,-5,0,1,1)>0,OFFSET(A102,-5,0,1,1)+0.001,ERROR.TYPE(0)),IFERROR(IF(OFFSET(A102,-6,0,1,1)>0,OFFSET(A102,-6,0,1,1)+0.001,ERROR.TYPE(0)),IFERROR(IF(OFFSET(A102,-7,0,1,1)>0,OFFSET(A102,-7,0,1,1)+0.001,ERROR.TYPE(0)),IFERROR(IF(OFFSET(A102,-8,0,1,1)>0,OFFSET(A102,-8,0,1,1)+0.001,ERROR.TYPE(0)),IFERROR(IF(OFFSET(A102,-9,0,1,1)>0,OFFSET(A102,-9,0,1,1)+0.001,ERROR.TYPE(0)),IFERROR(IF(OFFSET(A102,-10,0,1,1)>0,OFFSET(A102,-10,0,1,1)+0.001,ERROR.TYPE(0)),ERROR.TYPE(0))))))))))) -> 2.046 | B102: 1000 x 1500 mm - external | C102: 5 | D102: m | F102: =IFERROR($C102*E102,E102) -> 0
B103: Supply and install the following weatherproof louvers/bird screens c/w transformation pieces etc for a complete system.
A104: =IFERROR(IF(OFFSET(A104,-1,0,1,1)>0,OFFSET(A104,-1,0,1,1)+0.001,ERROR.TYPE(0)),IFERROR(IF(OFFSET(A104,-2,0,1,1)>0,OFFSET(A104,-2,0,1,1)+0.001,ERROR.TYPE(0)),IFERROR(IF(OFFSET(A104,-3,0,1,1)>0,OFFSET(A104,-3,0,1,1)+0.001,ERROR.TYPE(0)),IFERROR(IF(OFFSET(A104,-4,0,1,1)>0,OFFSET(A104,-4,0,1,1)+0.001,ERROR.TYPE(0)),IFERROR(IF(OFFSET(A104,-5,0,1,1)>0,OFFSET(A104,-5,0,1,1)+0.001,ERROR.TYPE(0)),IFERROR(IF(OFFSET(A104,-6,0,1,1)>0,OFFSET(A104,-6,0,1,1)+0.001,ERROR.TYPE(0)),IFERROR(IF(OFFSET(A104,-7,0,1,1)>0,OFFSET(A104,-7,0,1,1)+0.001,ERROR.TYPE(0)),IFERROR(IF(OFFSET(A104,-8,0,1,1)>0,OFFSET(A104,-8,0,1,1)+0.001,ERROR.TYPE(0)),IFERROR(IF(OFFSET(A104,-9,0,1,1)>0,OFFSET(A104,-9,0,1,1)+0.001,ERROR.TYPE(0)),IFERROR(IF(OFFSET(A104,-10,0,1,1)>0,OFFSET(A104,-10,0,1,1)+0.001,ERROR.TYPE(0)),ERROR.TYPE(0))))))))))) -> 2.047 | B104: WL 03 - 1000 x 1000 mm | C104: 2 | D104: No. | F104: =IFERROR($C104*E104,E104) -> 0
B105: Supply and install the following phenolic ductwork inc. all elbows, Tee's, transformation pieces, brackets. All external ductwork shall be c/w weatherproofing.
A106: =IFERROR(IF(OFFSET(A106,-1,0,1,1)>0,OFFSET(A106,-1,0,1,1)+0.001,ERROR.TYPE(0)),IFERROR(IF(OFFSET(A106,-2,0,1,1)>0,OFFSET(A106,-2,0,1,1)+0.001,ERROR.TYPE(0)),IFERROR(IF(OFFSET(A106,-3,0,1,1)>0,OFFSET(A106,-3,0,1,1)+0.001,ERROR.TYPE(0)),IFERROR(IF(OFFSET(A106,-4,0,1,1)>0,OFFSET(A106,-4,0,1,1)+0.001,ERROR.TYPE(0)),IFERROR(IF(OFFSET(A106,-5,0,1,1)>0,OFFSET(A106,-5,0,1,1)+0.001,ERROR.TYPE(0)),IFERROR(IF(OFFSET(A106,-6,0,1,1)>0,OFFSET(A106,-6,0,1,1)+0.001,ERROR.TYPE(0)),IFERROR(IF(OFFSET(A106,-7,0,1,1)>0,OFFSET(A106,-7,0,1,1)+0.001,ERROR.TYPE(0)),IFERROR(IF(OFFSET(A106,-8,0,1,1)>0,OFFSET(A106,-8,0,1,1)+0.001,ERROR.TYPE(0)),IFERROR(IF(OFFSET(A106,-9,0,1,1)>0,OFFSET(A106,-9,0,1,1)+0.001,ERROR.TYPE(0)),IFERROR(IF(OFFSET(A106,-10,0,1,1)>0,OFFSET(A106,-10,0,1,1)+0.001,ERROR.TYPE(0)),ERROR.TYPE(0))))))))))) -> 2.048 | B106: 100 x 100 mm | C106: 5 | D106: m | F106: =IFERROR($C106*E106,E106) -> 0
A107: =IFERROR(IF(OFFSET(A107,-1,0,1,1)>0,OFFSET(A107,-1,0,1,1)+0.001,ERROR.TYPE(0)),IFERROR(IF(OFFSET(A107,-2,0,1,1)>0,OFFSET(A107,-2,0,1,1)+0.001,ERROR.TYPE(0)),IFERROR(IF(OFFSET(A107,-3,0,1,1)>0,OFFSET(A107,-3,0,1,1)+0.001,ERROR.TYPE(0)),IFERROR(IF(OFFSET(A107,-4,0,1,1)>0,OFFSET(A107,-4,0,1,1)+0.001,ERROR.TYPE(0)),IFERROR(IF(OFFSET(A107,-5,0,1,1)>0,OFFSET(A107,-5,0,1,1)+0.001,ERROR.TYPE(0)),IFERROR(IF(OFFSET(A107,-6,0,1,1)>0,OFFSET(A107,-6,0,1,1)+0.001,ERROR.TYPE(0)),IFERROR(IF(OFFSET(A107,-7,0,1,1)>0,OFFSET(A107,-7,0,1,1)+0.001,ERROR.TYPE(0)),IFERROR(IF(OFFSET(A107,-8,0,1,1)>0,OFFSET(A107,-8,0,1,1)+0.001,ERROR.TYPE(0)),IFERROR(IF(OFFSET(A107,-9,0,1,1)>0,OFFSET(A107,-9,0,1,1)+0.001,ERROR.TYPE(0)),IFERROR(IF(OFFSET(A107,-10,0,1,1)>0,OFFSET(A107,-10,0,1,1)+0.001,ERROR.TYPE(0)),ERROR.TYPE(0))))))))))) -> 2.049 | B107: 125 x 100 mm | C107: 10 | D107: m | F107: =IFERROR($C107*E107,E107) -> 0
A108: =IFERROR(IF(OFFSET(A108,-1,0,1,1)>0,OFFSET(A108,-1,0,1,1)+0.001,ERROR.TYPE(0)),IFERROR(IF(OFFSET(A108,-2,0,1,1)>0,OFFSET(A108,-2,0,1,1)+0.001,ERROR.TYPE(0)),IFERROR(IF(OFFSET(A108,-3,0,1,1)>0,OFFSET(A108,-3,0,1,1)+0.001,ERROR.TYPE(0)),IFERROR(IF(OFFSET(A108,-4,0,1,1)>0,OFFSET(A108,-4,0,1,1)+0.001,ERROR.TYPE(0)),IFERROR(IF(OFFSET(A108,-5,0,1,1)>0,OFFSET(A108,-5,0,1,1)+0.001,ERROR.TYPE(0)),IFERROR(IF(OFFSET(A108,-6,0,1,1)>0,OFFSET(A108,-6,0,1,1)+0.001,ERROR.TYPE(0)),IFERROR(IF(OFFSET(A108,-7,0,1,1)>0,OFFSET(A108,-7,0,1,1)+0.001,ERROR.TYPE(0)),IFERROR(IF(OFFSET(A108,-8,0,1,1)>0,OFFSET(A108,-8,0,1,1)+0.001,ERROR.TYPE(0)),IFERROR(IF(OFFSET(A108,-9,0,1,1)>0,OFFSET(A108,-9,0,1,1)+0.001,ERROR.TYPE(0)),IFERROR(IF(OFFSET(A108,-10,0,1,1)>0,OFFSET(A108,-10,0,1,1)+0.001,ERROR.TYPE(0)),ERROR.TYPE(0))))))))))) -> 2.05 | B108: 150 x 100 mm | C108: 5 | D108: m | F108: =IFERROR($C108*E108,E108) -> 0
A109: =IFERROR(IF(OFFSET(A109,-1,0,1,1)>0,OFFSET(A109,-1,0,1,1)+0.001,ERROR.TYPE(0)),IFERROR(IF(OFFSET(A109,-2,0,1,1)>0,OFFSET(A109,-2,0,1,1)+0.001,ERROR.TYPE(0)),IFERROR(IF(OFFSET(A109,-3,0,1,1)>0,OFFSET(A109,-3,0,1,1)+0.001,ERROR.TYPE(0)),IFERROR(IF(OFFSET(A109,-4,0,1,1)>0,OFFSET(A109,-4,0,1,1)+0.001,ERROR.TYPE(0)),IFERROR(IF(OFFSET(A109,-5,0,1,1)>0,OFFSET(A109,-5,0,1,1)+0.001,ERROR.TYPE(0)),IFERROR(IF(OFFSET(A109,-6,0,1,1)>0,OFFSET(A109,-6,0,1,1)+0.001,ERROR.TYPE(0)),IFERROR(IF(OFFSET(A109,-7,0,1,1)>0,OFFSET(A109,-7,0,1,1)+0.001,ERROR.TYPE(0)),IFERROR(IF(OFFSET(A109,-8,0,1,1)>0,OFFSET(A109,-8,0,1,1)+0.001,ERROR.TYPE(0)),IFERROR(IF(OFFSET(A109,-9,0,1,1)>0,OFFSET(A109,-9,0,1,1)+0.001,ERROR.TYPE(0)),IFERROR(IF(OFFSET(A109,-10,0,1,1)>0,OFFSET(A109,-10,0,1,1)+0.001,ERROR.TYPE(0)),ERROR.TYPE(0))))))))))) -> 2.051 | B109: 150 x 150 mm | C109: 5 | D109: m | F109: =IFERROR($C109*E109,E109) -> 0
...

Sheet Notes
A1: NOTES | C1: Rev: 235
C2: checkdesc
A3: ELECTRICAL | C3: Elec_Rates
C4: Elec_Est
A5: Dist Boards | C5: Elv_Rates
A6: 1 | C6: ELV_Est
A7: 2 | C7: Ext_Quote
C8: Int_Quote
A9: Wiring Accessories | C9: Est_BOQ
A10: 1
A11: 2 | C11: Camilleri&Cuschieri Tenders
C12: Conduit
A13: ELV | C13: Wiring
C14: Supply
A15: Fire Alarm
A16: 1
A17: 2
A18: 3
A20: Data
A21: 1
A22: 2
A23: 3

Sheet Quote
A1: =IF(AND(UPPER(LEFT(TRIM($D$8),11))="01",UPPER(LEFT(TRIM($D$9),3))<>"ELM"),"PANTA RETAIL LTD.","PANTA CONTRACTING LIMITED") -> PANTA CONTRACTING LIMITED
A2: =IF(UPPER(LEFT(TRIM($D$9),3))="ELM","ELEC-FOR-MECH INTERNAL QUOTATION","ELECTRICAL INTERNAL QUOTATION") -> ELEC-FOR-MECH INTERNAL QUOTATION
B5: ATT: | D5: =IF(A2="Internal Quotation", "Mechanical Division","") | R5: Dated: | S5: =NOW() -> 45821.462
B6: CLIENT: | C6: Link to ML_SUM $D1 | D6: =ML_Sum!D1 -> Quintano Foods Ltd.
B7: PROJECT: | C7: Link to ML_SUM $D2 | D7: =ML_Sum!D2 -> Warehouse at tal-Handaq, Qormi
B8: JOB DESC: | C8: Link to ML_SUM $D3 | D8: =ML_Sum!D3 -> Electrical installation for Mechanical (HVAC) - Revision B
B9: QUOTE No: | C9: Link to ML_SUM $D4 | D9: =ML_Sum!D4 -> ELM-25-0085B
B10: CLIENT's Ref: | C10: Link to ML_SUM $D5 | D10: =ML_Sum!D5 -> Tender
D21: Material Cost (€) : | E21: =ML_Sum!R35 -> 59910.035 | F21: =ML_Sum!D6 -> VAT EXCL. | G21: VAT EXCLUDED. | H21: VAT EXCLUDED. | I21: VAT EXCLUDED. | J21: VAT EXCLUDED. | K21: VAT EXCLUDED. | L21: VAT EXCLUDED. | M21: VAT EXCLUDED. | N21: VAT EXCLUDED. | O21: VAT EXCLUDED. | P21: VAT EXCLUDED.
D22: Labour Pair Hours : | E22: =ML_Sum!T23 -> 626.36 | F22: at €27.46 Ex VAT cost to Panta
D23: Labour Pair Hours : | E23: =ML_Sum!T24 -> 106 | F23: at €52.92 Ex VAT cost to Panta
A51: Signed for and on behalf of | Q51: Signed for and on behalf of
A52: Electrical Division | Q52: Division
Q54: Records
Q55: Mr. A. Sciberras
Q57: File

Sheet ML_Sum
B1: CLIENT: | C1: 1 | D1: Quintano Foods Ltd. | G1: TRUE | H1: TRUE | I1: 1 | J1: =$Q109 -> 1 | K1: =$Q119 -> 1 | L1: =$Q129 -> 1 | M1: =$Q139 -> 1 | N1: =$Q149 -> 1 | O1: =$Q159 -> 1 | Q1: =IF(C1=1,"€","Curr?") -> € | R1: Recon /Lab.Cont >> | S1: =IF($S$39="PRINT","R","Do Not Print") -> R | T1: 1 | V1: {=IF(OR(X1=AREAS),1,0)} -> 1 | W1: BOQ | X1: x | Y1: x | Z1: x | AA1: x | AB1: x | AC1: x | AD1: x
B2: PROJECT: | C2: =IF($D$6="VAT INCLUDED",1.18,1)*(1-$Q2)*$C$1 -> 1 | D2: Warehouse at tal-Handaq, Qormi | F2: Electrical | G2: TRUE | I2: 2 | J2: =$Q110 -> 1 | K2: =$Q120 -> 1 | L2: =$Q130 -> 1 | M2: =$Q140 -> 1 | N2: =$Q150 -> 1 | O2: =$Q160 -> 1 | R2: ="A) " & IF($S2=0,"",ROUND($S2,2) & "-" & ROUND($T2/$D$9,2)) -> A) 1-1 | S2: 1 | T2: =$S2*$D$9 -> 27.46 | X2: x | Y2: x | Z2: x | AA2: x | AB2: x | AC2: x | AD2: x
B3: JOB DESC: | C3: =IF($D$6="VAT INCLUDED",1.18,1)*(1-$Q3)*$C$1 -> 1 | D3: Electrical installation for Mechanical (HVAC) - Revision B | F3: ECA | G3: TRUE | I3: 3 | J3: =$Q111 -> 1 | K3: =$Q121 -> 1 | L3: =$Q131 -> 1 | M3: =$Q141 -> 1 | N3: =$Q151 -> 1 | O3: =$Q161 -> 1 | R3: ="B) " & IF($S3=0,"",ROUND($S3,2) & "-" & ROUND($T3/$D$9,2)) -> B) 1-1 | S3: 1 | T3: =$S3*$D$9 -> 27.46 | X3: x | Y3: x | Z3: x | AA3: x | AB3: x | AC3: x | AD3: x
B4: INT. QUOT No: | C4: =IF($D$6="VAT INCLUDED",1.18,1)*(1-$Q4)*$C$1 -> 1 | D4: ELM-25-0085B | G4: TRUE | I4: 4 | J4: =$Q112 -> 1 | K4: =$Q122 -> 1 | L4: =$Q132 -> 1 | M4: =$Q142 -> 1 | N4: =$Q152 -> 1 | O4: =$Q162 -> 1 | R4: ="C) " & IF($S4=0,"",ROUND($S4,2) & "-" & ROUND($T4/$D$9,2)) -> C) 1-1 | S4: 1 | T4: =$S4*$D$9 -> 27.46 | X4: x | Y4: x | Z4: x | AA4: x | AB4: x | AC4: x | AD4: x
B5: CLIENTs REF: | C5: =IF($D$6="VAT INCLUDED",1.18,1)*(1-$Q5)*$C$1 -> 1 | D5: Tender | G5: TRUE | I5: 5 | J5: =$Q113 -> 1 | K5: =$Q123 -> 1 | L5: =$Q133 -> 1 | M5: =$Q143 -> 1 | N5: =$Q153 -> 1 | O5: =$Q163 -> 1 | R5: ="D) " & IF($S5=0,"",ROUND($S5,2) & "-" & ROUND($T5/$D$9,2)) -> D) 1-1 | S5: 1 | T5: =$S5*$D$9 -> 27.46 | X5: x | Y5: x | Z5: x | AA5: x | AB5: x | AC5: x | AD5: x
B6: VAT: | C6: =IF($D$6="VAT INCLUDED",1.18,1)*(1-$Q6)*$C$1 -> 1 | D6: VAT EXCL. | G6: TRUE | I6: 6 | J6: =$Q114 -> 1 | K6: =$Q124 -> 1 | L6: =$Q134 -> 1 | M6: =$Q144 -> 1 | N6: =$Q154 -> 1 | O6: =$Q164 -> 1 | R6: ="E) " & IF($S6=0,"",ROUND($S6,2) & "-" & ROUND($T6/$D$9,2)) -> E) 1-1 | S6: 1 | T6: =$S6*$D$9 -> 27.46 | X6: x | Y6: x | Z6: x | AA6: x | AB6: x | AC6: x | AD6: x
B7: SAVED ON: | C7: =IF($D$6="VAT INCLUDED",1.18,1)*(1-$Q7)*$C$1 -> 1 | D7: 13.02.2025 | G7: TRUE | I7: 7 | J7: =$Q115 -> 1 | K7: =$Q125 -> 1 | L7: =$Q135 -> 1 | M7: =$Q145 -> 1 | N7: =$Q155 -> 1 | R7: ="F) " & IF($S7=0,"",ROUND($S7,2) & "-" & ROUND($T7/$D$9,2)) -> F) 1-1 | S7: 1 | T7: =$S7*$D$9 -> 27.46 | X7: x | Y7: x | Z7: x | AA7: x | AB7: x | AC7: x | AD7: x
B8: ESTIMATOR: | C8: =IF($D$6="VAT INCLUDED",1.18,1)*(1-$Q8)*$C$1 -> 1 | D8: T.Sammut | G8: TRUE | I8: 8 | J8: =$Q116 -> 1 | K8: =$Q126 -> 1 | L8: =$Q136 -> 1 | M8: =$Q146 -> 1 | N8: =$Q156 -> 1 | R8: ="G) " & IF($S8=0,"",ROUND($S8,2) & "-" & ROUND($T8/$D$9,2)) -> G) 1-1 | S8: 1 | T8: =$S8*$D$9 -> 27.46 | X8: x | Y8: x | Z8: x | AA8: x | AB8: x | AC8: x | AD8: x
B9: LAB. COST: | C9: =IF($D$6="VAT INCLUDED",1.18,1)*(1-$Q9)*$C$1 -> 1 | D9: 27.46 | G9: TRUE | I9: 9 | J9: =$Q117 -> 1 | K9: =$Q127 -> 1 | L9: =$Q137 -> 1 | M9: =$Q147 -> 1 | N9: =$Q157 -> 1 | R9: ="H) " & IF($S9=0,"",ROUND($S9,2) & "-" & ROUND($T9/$D$9,2)) -> H) 1-1 | S9: 1 | T9: =$S9*$D$9 -> 27.46 | X9: x | Y9: x | Z9: x | AA9: x | AB9: x | AC9: x | AD9: x
C10: =IF($D$6="VAT INCLUDED",1.18,1)*(1-$Q10)*$C$1 -> 1 | G10: TRUE | I10: 10 | J10: =$Q118 -> 1 | K10: =$Q128 -> 1 | L10: =$Q138 -> 1 | M10: =$Q148 -> 1 | N10: =$Q158 -> 1 | O10: =Q108 -> 1 | R10: =" I) " & IF($S10=0,"",ROUND($S10,2) & "-" & ROUND($T10/$D$9,2)) -> I) 1-1 | S10: 1 | T10: =$S10*$D$9 -> 27.46 | X10: x | Y10: x | Z10: x | AA10: x | AB10: x | AC10: x | AD10: x
C11: =IF($D$6="VAT INCLUDED",1.18,1)*(1-$Q11)*$C$1 -> 1 | R11: ="J) " & IF($S11=0,"",ROUND($S11,2) & "-" & ROUND($T11/$D$9,2)) -> J) 1-1 | S11: 1 | T11: =$S11*$D$9 -> 27.46 | X11: x | Y11: x | Z11: x | AA11: x | AB11: x | AC11: x | AD11: x
C12: =IF($D$6="VAT INCLUDED",1.18,1)*(1-$Q12)*$C$1 -> 1 | G12: SYSTEMS | H12: SYSTEMS | I12: SYSTEMS | J12: SYSTEMS | K12: SYSTEMS | L12: SYSTEMS | M12: SYSTEMS | N12: SYSTEMS | O12: SYSTEMS | P12: SYSTEMS | R12: MIXED - X,Y ) | S12: MAT MU | T12: LAB RATE | X12: x | Y12: x | Z12: x | AA12: x | AB12: x | AC12: x | AD12: x
B13: MATERIAL & LABOUR SUMMARY | G13: ItemCode | H13: CostCode | I13: MAKE | J13: PART_NO | K13: MARKUP | L13: TYPE | M13: LIST_P | N13: SET | O13: FIX | P13: DATE | Q13: %Dsct in BOQ | R13: MATMU-LABMU | S13: MAT CONT >> | T13: =SUM(Q108:Q164)/57 -> 1
B14: =IF($D$6<>"VAT EXCL.", "QUOTE ISSUED WITH VAT INCLUDED", "") | X14: x | Y14: x | Z14: x | AA14: x | AB14: x | AC14: x | AD14: x
Q15: =(C72-F35)/C72 -> 0 | R15: Average Discount applied in BOQ (Q2-Q12) | X15: x | Y15: x | Z15: x | AA15: x | AB15: x | AC15: x | AD15: x
B16: =IF($W$1<>"BOQ", "DIFF SET TO " & W1,"") | Q16: =(F35-E35)/F35 -> 0.59118043 | R16: Average Discount applied on Totals (Q23-Q32) | X16: x | Y16: x | Z16: x | AA16: x | AB16: x | AC16: x | AD16: x
Q17: =F74 -> 0.59118043 | R17: Overall Discount
B18: =IF(AND(G1,G2,G3,G4,G5,G6,G7,G8,G9,G10,H1)=TRUE, "", "CHECKLIST INCOMPLETE !" )
B19: =IF(ABS(SUM(A23:A32))>100,"[Discy A-J] are high, Check it out."," ") | Q19: =R83 -> 0.40883225 | R19: Overall Markup (Final Selling Excl.VAT/Total Cost )
E21: DISCOUNTED | F21: SELLING | Q21: % Discnt | R21: MATERIAL | T21: LABOUR
A22: Discy.A-J | B22: Markup/LRate | E22: ="SELLING " & $Q$1 -> SELLING € | F22: =$Q$1 -> € | G22: VAT/DISC | H22: MU | I22: LABRATE | J22: LABCOST | Q22: on Totals | R22: € | T22: Pair Hrs.
A23: =IF($F23=0,"",($F23/$C2)-($R23*$S2+$T23*$T2)) -> 0.0094 | B23: =IF(F23=0,"",IF(R23=0,"A) "&"---, "&ROUND(($F23/$C2-($R23*$S2))/$T23,2),IF(T23=0,"A) "&ROUND(($F23/$C2)/$R23,2),"A) "&ROUND(($F23/$C2-($T23*$T2))/$R23,2)&", " &ROUND(($F23/$C2-($R23*$S2))/$T23,2)))) -> A) 1, 27.46 | D23: =IF($F2="","",$F2) -> Electrical | F23: =Elec_Est!F2055 -> 47306.66 | G23: =C2 -> 1 | H23: =$S2 -> 1 | I23: =$T2 -> 27.46 | J23: =$D$9 -> 27.46 | R23: =Elec_Est!R2055 -> 30106.805 | T23: =Elec_Est!T2055 -> 626.36
A24: =IF($F24=0,"",($F24/$C3)-($R24*$S3+$T24*$T3)) -> -0.09 | B24: =IF(F24=0,"",IF(R24=0,"A) "&"---, "&ROUND(($F24/$C3-($R24*$S3))/$T24,2),IF(T24=0,"A) "&ROUND(($F24/$C3)/$R24,2),"A) "&ROUND(($F24/$C3-($T24*$T3))/$R24,2)&", " &ROUND(($F24/$C3-($R24*$S3))/$T24,2)))) -> A) 1, 27.46 | D24: =IF($F3="","",$F3) -> ECA | E24: =F24*(1-Q24) -> 32713.9 | F24: =Elec_Est!F2056 -> 32713.9 | G24: =C3 -> 1 | H24: =$S3 -> 1 | I24: =$T3 -> 27.46 | J24: =$D$9 -> 27.46 | R24: =Elec_Est!R2056 -> 29803.23 | T24: =Elec_Est!T2056 -> 106
A25: =IF($F25=0,"",($F25/$C4)-($R25*$S4+$T25*$T4)) -> 0.12 | B25: =IF(F25=0,"",IF(R25=0,"A) "&"---, "&ROUND(($F25/$C4-($R25*$S4))/$T25,2),IF(T25=0,"A) "&ROUND(($F25/$C4)/$R25,2),"A) "&ROUND(($F25/$C4-($T25*$T4))/$R25,2)&", " &ROUND(($F25/$C4-($R25*$S4))/$T25,2)))) -> #DIV/0! | D25: =IF($F4="","",$F4) | E25: =F25*(1-Q25) -> 0.12 | F25: =Elec_Est!F2057 -> 0.12 | G25: =C4 -> 1 | H25: =$S4 -> 1 | I25: =$T4 -> 27.46 | J25: =$D$9 -> 27.46 | R25: =Elec_Est!R2057 -> 0 | T25: =Elec_Est!T2057 -> 0
A26: =IF($F26=0,"",($F26/$C5)-($R26*$S5+$T26*$T5)) | B26: =IF(F26=0,"",IF(R26=0,"A) "&"---, "&ROUND(($F26/$C5-($R26*$S5))/$T26,2),IF(T26=0,"A) "&ROUND(($F26/$C5)/$R26,2),"A) "&ROUND(($F26/$C5-($T26*$T5))/$R26,2)&", " &ROUND(($F26/$C5-($R26*$S5))/$T26,2)))) | D26: =IF($F5="","",$F5) | E26: =F26*(1-Q26) -> 0 | F26: =Elec_Est!F2058 -> 0 | G26: =C5 -> 1 | H26: =$S5 -> 1 | I26: =$T5 -> 27.46 | J26: =$D$9 -> 27.46 | R26: =Elec_Est!R2058 -> 0 | T26: =Elec_Est!T2058 -> 0
A27: =IF($F27=0,"",($F27/$C6)-($R27*$S6+$T27*$T6)) | B27: =IF(F27=0,"",IF(R27=0,"A) "&"---, "&ROUND(($F27/$C6-($R27*$S6))/$T27,2),IF(T27=0,"A) "&ROUND(($F27/$C6)/$R27,2),"A) "&ROUND(($F27/$C6-($T27*$T6))/$R27,2)&", " &ROUND(($F27/$C6-($R27*$S6))/$T27,2)))) | D27: =IF($F6="","",$F6) | E27: =F27*(1-Q27) -> 0 | F27: =Elec_Est!F2059 -> 0 | G27: =C6 -> 1 | H27: =$S6 -> 1 | I27: =$T6 -> 27.46 | J27: =$D$9 -> 27.46 | R27: =Elec_Est!R2059 -> 0 | T27: =Elec_Est!T2059 -> 0
A28: =IF($F28=0,"",($F28/$C7)-($R28*$S7+$T28*$T7)) | B28: =IF(F28=0,"",IF(R28=0,"A) "&"---, "&ROUND(($F28/$C7-($R28*$S7))/$T28,2),IF(T28=0,"A) "&ROUND(($F28/$C7)/$R28,2),"A) "&ROUND(($F28/$C7-($T28*$T7))/$R28,2)&", " &ROUND(($F28/$C7-($R28*$S7))/$T28,2)))) | D28: =IF($F7="","",$F7) | E28: =F28*(1-Q28) -> 0 | F28: =Elec_Est!F2060 -> 0 | G28: =C7 -> 1 | H28: =$S7 -> 1 | I28: =$T7 -> 27.46 | J28: =$D$9 -> 27.46 | R28: =Elec_Est!R2060 -> 0 | T28: =Elec_Est!T2060 -> 0
A29: =IF($F29=0,"",($F29/$C8)-($R29*$S8+$T29*$T8)) | B29: =IF(F29=0,"",IF(R29=0,"A) "&"---, "&ROUND(($F29/$C8-($R29*$S8))/$T29,2),IF(T29=0,"A) "&ROUND(($F29/$C8)/$R29,2),"A) "&ROUND(($F29/$C8-($T29*$T8))/$R29,2)&", " &ROUND(($F29/$C8-($R29*$S8))/$T29,2)))) | D29: =IF($F8="","",$F8) | E29: =F29*(1-Q29) -> 0 | F29: =Elec_Est!F2061 -> 0 | G29: =C8 -> 1 | H29: =$S8 -> 1 | I29: =$T8 -> 27.46 | J29: =$D$9 -> 27.46 | R29: =Elec_Est!R2061 -> 0 | T29: =Elec_Est!T2061 -> 0
A30: =IF($F30=0,"",($F30/$C9)-($R30*$S9+$T30*$T9)) | B30: =IF(F30=0,"",IF(R30=0,"A) "&"---, "&ROUND(($F30/$C9-($R30*$S9))/$T30,2),IF(T30=0,"A) "&ROUND(($F30/$C9)/$R30,2),"A) "&ROUND(($F30/$C9-($T30*$T9))/$R30,2)&", " &ROUND(($F30/$C9-($R30*$S9))/$T30,2)))) | D30: =IF($F9="","",$F9) | E30: =F30*(1-Q30) -> 0 | F30: =Elec_Est!F2062 -> 0 | G30: =C9 -> 1 | H30: =$S9 -> 1 | I30: =$T9 -> 27.46 | J30: =$D$9 -> 27.46 | R30: =Elec_Est!R2062 -> 0 | T30: =Elec_Est!T2062 -> 0
A31: =IF($F31=0,"",($F31/$C10)-($R31*$S10+$T31*$T10)) | B31: =IF(F31=0,"",IF(R31=0,"A) "&"---, "&ROUND(($F31/$C10-($R31*$S10))/$T31,2),IF(T31=0,"A) "&ROUND(($F31/$C10)/$R31,2),"A) "&ROUND(($F31/$C10-($T31*$T10))/$R31,2)&", " &ROUND(($F31/$C10-($R31*$S10))/$T31,2)))) | D31: =IF($F10="","",$F10) | E31: =F31*(1-Q31) -> 0 | F31: =Elec_Est!F2063 -> 0 | G31: =C10 -> 1 | H31: =$S10 -> 1 | I31: =$T10 -> 27.46 | J31: =$D$9 -> 27.46 | R31: =Elec_Est!R2063 -> 0 | T31: =Elec_Est!T2063 -> 0
A32: =IF($F32=0,"",($F32/$C11)-($R32*$S11+$T32*$T11)) | B32: =IF(F32=0,"",IF(R32=0,"A) "&"---, "&ROUND(($F32/$C11-($R32*$S11))/$T32,2),IF(T32=0,"A) "&ROUND(($F32/$C11)/$R32,2),"A) "&ROUND(($F32/$C11-($T32*$T11))/$R32,2)&", " &ROUND(($F32/$C11-($R32*$S11))/$T32,2)))) | D32: =IF($F11="","",$F11) | E32: =F32*(1-Q32) -> 0 | F32: =Elec_Est!F2064 -> 0 | G32: =C11 -> 1 | H32: =$S11 -> 1 | I32: =$T11 -> 27.46 | J32: =$D$9 -> 27.46 | R32: =Elec_Est!R2064 -> 0 | T32: =Elec_Est!T2064 -> 0
C33: MIXED | W33: Mat Cost | X33: Lab Hours | Y33: Lab Hours
V34: HVAC | W34: =HVAC_BOQ!G514 -> 59910.04 | X34: =HVAC_BOQ!H514 -> 626.36 | Y34: =HVAC_BOQ!I514 -> 106
A35: Discy.L | B35: =E_BOQ!F56 -> 0 | E35: =SUM(E23:E32) -> 32714.02 | F35: =SUM(F23:F32) -> 80020.68 | R35: =SUM(R23:R32) -> 59910.035 | T35: =SUM(T23:T32) -> 732.36 | V35: Sprinklers
A36: =IF(A39=0,"0.00",A39-(A38*A37)) -> 0.00 | B36: BOQ TOTAL | E36: ="ESTIM TOTAL (" & $Q$1 & ")" -> ESTIM TOTAL (€) | V36: Plumbing
A37: 1.125 | B37: <1 Actual LabCont | R37: =R165 -> 59910.019 | S37: C.C.Totals | T37: =T165 -> 732.27167 | W37: =SUM(W34:W36) -> 59910.04 | X37: =SUM(X34:X36) -> 626.36 | Y37: =SUM(Y34:Y36) -> 106
B38: <2 Phrs @ 1.00
B39: <3 Phrs @ Actual | Q39: Discy.T >> | R39: =R37-R35 -> -0.0165 | S39: PRINT | T39: =T37-T35 -> -0.088333333
B41: Values Only on : | D41: 45701 | R41: 65637.555 | T41: 858.12
B42: Values Only on : | D42: 45757 | R42: 57581.675 | T42: 715.19 | U42: Rev A - Inverrters in VCPs
B43: Values Only on : | D43: 45820 | R43: 58809.955 | T43: 732.36 | U43: Rev B - Redesign by consultant
A46: REMARKS:
A47: 1) VAT and Duties as above.
A48: 2)
A51: ESTIMATOR: | D51: =D8 -> T.Sammut | Q51: APPROVED BY:
A53: SIGNED: | Q53: DATE APPROVED:
A55: FILE LOCATION: | D55: =CELL("filename") -> K:\est\Quintano Foods\Estimates\Redesign June 2025\[ELM25_0085_Quintano_Elec_Mech_HVAC_BOQ_Rev_B.xlsx]Quote
B57: PANTA CONTRACTING LTD. - ELECTRICAL DIVISION
B58: CONTRACT / VARIATION INPUT DOCUMENT
S59: Copy to:-
D60: Client: | E60: =D1 -> Quintano Foods Ltd. | S60: Ms. V. Vella
D61: Project: | E61: =D2 -> Warehouse at tal-Handaq, Qormi | S61: Mr. K. Micallef
D62: Job Description: | E62: =D3 -> Electrical installation for Mechanical (HVAC) - Revision B | S62: Mr. A. Sciberras
D63: Quote No: | E63: =D4 -> ELM-25-0085B
D64: Client's Ref: | E64: =D5 -> Tender
S65: File:-
D66: File No:
D67: Ext. Ref:
E70: Contract /Variation (Excl. VAT)
C72: =IF($A$33="MIXED",F23/(1-Q2)+F24/(1-Q3)+F25/(1-Q4)+F26/(1-Q5)+F27/(1-Q6)+F28/(1-Q7)+F29/(1-Q8)+F30/(1-Q9)+F31/(1-Q10)+F32/(1-Q11)-SUM(A23:A32), F23/(1-Q2)+F24/(1-Q3)+F25/(1-Q4)+F26/(1-Q5)+F27/(1-Q6)+F28/(1-Q7)+F29/(1-Q8)+F30/(1-Q9)+F31/(1-Q10)+F32/(1-Q11)) -> 80020.68 | E72: Estim.Sell before Discounts excl.VAT (€): | F72: =IF(D6="VAT INCLUDED",C72/($C$1*1.18),C72/$C$1) -> 80020.68
E74: Overall Discount: | F74: =(F72-F75)/F72 -> 0.59118043
E75: Final Sell after Discounts excl.VAT (€): | F75: =IF(D6="VAT INCLUDED",E35/($C$1*1.18),E35/$C$1) -> 32714.02
E77: Labour Rate - | F77: =$D$9 -> 27.46 | R77: Mech. Cost to us
D80: Mat. Cost | E80: Labour | F80: Total Cost | R80: Sell Excl.VAT / Total Cost
D81: € | E81: Pair.Hrs | F81: €
D83: =R165 -> 59910.019 | E83: =T165 -> 732.27167 | F83: =R165+S165 -> 80018.198 | R83: =IF(F83=0,0,F75/F83) -> 0.40883225
D84: ( From CostCode Totals )
R87: Advanced Payment:
R88: Retention:
R90: Awarded Date:
R91: Estimated Start Date:
R92: Estimated Completion Date:
D93: .................
D94: K. Micallef | R94: Date issued:
D95: =NOW() -> 45821.462
D98: PANTA CONTRACTING LTD. - ELECTRICAL DIVISION
D99: ELECTRICAL AND ELV CONTRACT / VARIATION BUDGET COST
D101: Project: | E101: =E61 -> Warehouse at tal-Handaq, Qormi
D102: Job Desc: | E102: =E62 -> Electrical installation for Mechanical (HVAC) - Revision B
D103: Client's Ref: | E103: =E64 -> Tender
D106: COSTCODE | F106: Cost | Q106: Mat. | R106: Mat Cost | S106: Lab Cost @ | T106: Labour
F107: Code | Q107: Cont. | R107: € | S107: =$D$9 -> 27.46 | T107: Pair.Hrs
B108: V:56 | D108: BOQ RateOnly Items | P108: FIX | Q108: 1
B109: 1(J) | C109: cc | D109: Erection materials | F109: 501 | P109: 1 | Q109: 1 | R109: =Elec_Est!R2076 -> 1000.866 | S109: =T109*$D$9 -> 165.90417 | T109: =Elec_Est!T2076 -> 6.0416667
B110: 2 | C110: cc | D110: Busbar Trunking | F110: 505 | P110: 1 | Q110: 1 | R110: =Elec_Est!R2077 -> 0 | S110: =T110*$D$9 -> 0 | T110: =Elec_Est!T2077 -> 0
B111: 3 | C111: cc | D111: Switchgear | F111: 510 | P111: 2 | Q111: 1 | R111: =Elec_Est!R2078 -> 0 | S111: =T111*$D$9 -> 0 | T111: =Elec_Est!T2078 -> 0
B112: 4 | C112: cc | D112: MCC Equipment | F112: 511 | P112: 2 | Q112: 1 | R112: =Elec_Est!R2079 -> 0 | S112: =T112*$D$9 -> 0 | T112: =Elec_Est!T2079 -> 0
B113: 5 | C113: cc | D113: BMS Equipment | F113: 512 | P113: 2 | Q113: 1 | R113: =Elec_Est!R2080 -> 100 | S113: =T113*$D$9 -> 219.68 | T113: =Elec_Est!T2080 -> 8
B114: 6 | C114: cc | D114: PVC Pipes / Ducts | F114: 520 | P114: 1 | Q114: 1 | R114: =Elec_Est!R2081 -> 0 | S114: =T114*$D$9 -> 0 | T114: =Elec_Est!T2081 -> 0
B115: 7 | C115: cc | D115: High/medium voltage switchgear | F115: 530 | P115: 2 | Q115: 1 | R115: =Elec_Est!R2082 -> 0 | S115: =T115*$D$9 -> 0 | T115: =Elec_Est!T2082 -> 0
B116: 8 | C116: cc | D116: Power Transformers | F116: 550 | P116: 2 | Q116: 1 | R116: =Elec_Est!R2083 -> 0 | S116: =T116*$D$9 -> 0 | T116: =Elec_Est!T2083 -> 0
B117: 9 | C117: cc | D117: Control Panels | F117: 570 | P117: 2 | Q117: 1 | R117: =Elec_Est!R2084 -> 35503.23 | S117: =T117*$D$9 -> 6247.15 | T117: =Elec_Est!T2084 -> 227.5
B118: 10 | C118: cc | D118: Electrical Single Core Cables | F118: 615 | P118: 2 | Q118: 1 | R118: =Elec_Est!R2085 -> 66.3 | S118: =T118*$D$9 -> 71.396 | T118: =Elec_Est!T2085 -> 2.6
B119: 11(K) | C119: cc | D119: Electrical Multicore Cables | F119: 616 | P119: 2 | Q119: 1 | R119: =Elec_Est!R2086 -> 14618.92 | S119: =T119*$D$9 -> 1487.7828 | T119: =Elec_Est!T2086 -> 54.18
B120: 12 | C120: cc | D120: ELV/BMS/Special Cables | F120: 617 | P120: 2 | Q120: 1 | R120: =Elec_Est!R2087 -> 3971.625 | S120: =T120*$D$9 -> 2891.2634 | T120: =Elec_Est!T2087 -> 105.29
B121: 13 | C121: cc | D121: Cable Accessories | F121: 620 | P121: 2 | Q121: 1 | R121: =Elec_Est!R2088 -> 1188.02 | S121: =T121*$D$9 -> 2954.1468 | T121: =Elec_Est!T2088 -> 107.58
B122: 14 | C122: cc | D122: Galv. Cable Trays | F122: 650 | P122: 1 | Q122: 1 | R122: =Elec_Est!R2089 -> 184.44 | S122: =T122*$D$9 -> 278.719 | T122: =Elec_Est!T2089 -> 10.15
B123: 15 | C123: cc | D123: PVC Cable Trays | F123: 651 | P123: 1 | Q123: 1 | R123: =Elec_Est!R2090 -> 0 | S123: =T123*$D$9 -> 0 | T123: =Elec_Est!T2090 -> 0
B124: 16 | C124: cc | D124: Galv. Cable Basket | F124: 652 | P124: 1 | Q124: 1 | R124: =Elec_Est!R2091 -> 0 | S124: =T124*$D$9 -> 0 | T124: =Elec_Est!T2091 -> 0
B125: 17 | C125: cc | D125: Galv. Cable Ladder | F125: 654 | P125: 1 | Q125: 1 | R125: =Elec_Est!R2092 -> 0 | S125: =T125*$D$9 -> 0 | T125: =Elec_Est!T2092 -> 0
...

Sheet E_BOQ
A1: ITEM NO. | B1: DESCRIPTION | C1: QTY | D1: UNIT | E1: RATE | F1: TOTAL | G1: Mat Cost | H1: Lab Pair
A2: checkdesc | E2: € | F2: € | G2: € | H2: Hrs
B52: Page Total -
B54: Contract Discount -
A56: SB | B56: Discounted Page Total - | D56: =ML_Sum!D6 -> VAT EXCL. | E56: € | F56: =SUM(F3:F55) -> 0 | G56: =SUM(G3:G55) -> 0 | H56: =SUM(H3:H55) -> 0 | I56: =SUM(I3:I55) -> 0 | J56: =SUM(J3:J55) -> 0 | K56: =SUM(K3:K55) -> 0 | L56: =SUM(L3:L55) -> 0 | M56: =SUM(M3:M55) -> 0 | ... R56: =SUM(R3:R55) -> 0
A57: ITEM NO. | B57: DESCRIPTION | C57: QTY | D57: UNIT | E57: RATE | F57: TOTAL | G57: Mat Cost | H57: Lab Pair
E58: € | F58: € | G58: € | H58: Hrs
A112: SB | E112: System total - carried forward to summary page : | F112: =SUM(F59:F111) -> 0 | G112: =SUM(G51:G107) -> 0 | H112: =SUM(H51:H107) -> 0
A113: ITEM NO. | B113: DESCRIPTION | C113: QTY | D113: UNIT | E113: RATE | F113: TOTAL
E114: € | F114: €
A168: SB | E168: System total - carried forward to summary page : | F168: =SUM(F115:F167) -> 0
A169: ITEM NO. | B169: DESCRIPTION | C169: QTY | D169: UNIT | E169: RATE | F169: TOTAL
E170: € | F170: €
A224: SB | E224: System total - carried forward to summary page : | F224: =SUM(F171:F223) -> 0
A225: ITEM NO. | B225: DESCRIPTION | C225: QTY | D225: UNIT | E225: RATE | F225: TOTAL
E226: € | F226: €
A280: SB | E280: System total - carried forward to summary page : | F280: =SUM(F227:F279) -> 0
A281: ITEM NO. | B281: DESCRIPTION | C281: QTY | D281: UNIT | E281: RATE | F281: TOTAL
E282: € | F282: €
A337: SB | E337: System total - carried forward to summary page : | F337: =SUM(F283:F336) -> 0
A338: ITEM NO. | B338: DESCRIPTION | C338: QTY | D338: UNIT | E338: RATE | F338: TOTAL
E339: € | F339: €
A394: SB | E394: System total - carried forward to summary page : | F394: =SUM(F340:F393) -> 0
A395: ITEM NO. | B395: DESCRIPTION | C395: QTY | D395: UNIT | E395: RATE | F395: TOTAL
E396: € | F396: €
A451: SB | E451: System total - carried forward to summary page : | F451: =SUM(F397:F450) -> 0
A452: ITEM NO. | B452: DESCRIPTION | C452: QTY | D452: UNIT | E452: RATE | F452: TOTAL
E453: € | F453: €
A508: SB | E508: System total - carried forward to summary page : | F508: =SUM(F454:F507) -> 0
A509: ITEM NO. | B509: DESCRIPTION | C509: QTY | D509: UNIT | E509: RATE | F509: TOTAL
E510: € | F510: €
A565: SB | E565: System total - carried forward to summary page : | F565: =SUM(F511:F564) -> 0

Sheet E_DBOQ
A1: ITEM | B1: DESCRIPTION | C1: QTY | G1: UNIT | H1: RATE | I1: TOTAL | J1: Unit | K1: Total
C2: BOQ | D2: TDWG | E2: ACT | F2: DIFF | H2: € | I2: € | J2: Hrs | K2: Hrs
A54: SB | F54: System total - carried forward to summary page : | H54: VAT EXCL. | I54: =SUM(I3:I53) -> 0 | K54: =SUM(K3:K53) -> 0
A55: ITEM | B55: DESCRIPTION | C55: QTY | G55: UNIT | H55: RATE | I55: TOTAL | J55: Unit | K55: Total
C56: BOQ | D56: TDWG | E56: ACT | F56: DIFF | H56: € | I56: € | J56: Hrs | K56: Hrs
A111: SB | F111: System total - carried forward to summary page : | H111: VAT EXCL. | I111: =SUM(I57:I110) -> 0 | K111: =SUM(K57:K110) -> 0
A112: ITEM | B112: DESCRIPTION | C112: QTY | G112: UNIT | H112: RATE | I112: TOTAL | J112: Unit | K112: Total
C113: BOQ | D113: TDWG | E113: ACT | F113: DIFF | H113: € | I113: € | J113: Hrs | K113: Hrs
A168: SB | F168: System total - carried forward to summary page : | H168: VAT EXCL. | I168: =SUM(I114:I167) -> 0 | K168: =SUM(K114:K167) -> 0
A169: ITEM | B169: DESCRIPTION | C169: QTY | G169: UNIT | H169: RATE | I169: TOTAL | J169: Unit | K169: Total
C170: BOQ | D170: TDWG | E170: ACT | F170: DIFF | H170: € | I170: € | J170: Hrs | K170: Hrs
A225: SB | F225: System total - carried forward to summary page : | H225: VAT EXCL. | I225: =SUM(I171:I224) -> 0 | K225: =SUM(K171:K224) -> 0
A226: ITEM | B226: DESCRIPTION | C226: QTY | G226: UNIT | H226: RATE | I226: TOTAL | J226: Unit | K226: Total
C227: BOQ | D227: TDWG | E227: ACT | F227: DIFF | H227: € | I227: € | J227: Hrs | K227: Hrs
A282: SB | F282: System total - carried forward to summary page : | H282: VAT EXCL. | I282: =SUM(I228:I281) -> 0 | K282: =SUM(K228:K281) -> 0
A283: ITEM | B283: DESCRIPTION | C283: QTY | G283: UNIT | H283: RATE | I283: TOTAL | J283: Unit | K283: Total
C284: BOQ | D284: TDWG | E284: ACT | F284: DIFF | H284: € | I284: € | J284: Hrs | K284: Hrs
A339: SB | F339: System total - carried forward to summary page : | H339: VAT EXCL. | I339: =SUM(I285:I338) -> 0 | K339: =SUM(K285:K338) -> 0
A340: ITEM | B340: DESCRIPTION | C340: QTY | G340: UNIT | H340: RATE | I340: TOTAL | J340: Unit | K340: Total
C341: BOQ | D341: TDWG | E341: ACT | F341: DIFF | H341: € | I341: € | J341: Hrs | K341: Hrs
A396: SB | F396: System total - carried forward to summary page : | H396: VAT EXCL. | I396: =SUM(I342:I395) -> 0 | K396: =SUM(K342:K395) -> 0
A397: ITEM | B397: DESCRIPTION | C397: QTY | G397: UNIT | H397: RATE | I397: TOTAL | J397: Unit | K397: Total
C398: BOQ | D398: TDWG | E398: ACT | F398: DIFF | H398: € | I398: € | J398: Hrs | K398: Hrs
A453: SB | F453: System total - carried forward to summary page : | H453: VAT EXCL. | I453: =SUM(I399:I452) -> 0 | K453: =SUM(K399:K452) -> 0
A454: ITEM | B454: DESCRIPTION | C454: QTY | G454: UNIT | H454: RATE | I454: TOTAL | J454: Unit | K454: Total
C455: BOQ | D455: TDWG | E455: ACT | F455: DIFF | H455: € | I455: € | J455: Hrs | K455: Hrs
A510: SB | F510: System total - carried forward to summary page : | H510: VAT EXCL. | I510: =SUM(I456:I509) -> 0 | K510: =SUM(K456:K509) -> 0
A511: ITEM | B511: DESCRIPTION | C511: QTY | G511: UNIT | H511: RATE | I511: TOTAL | J511: Unit | K511: Total
C512: BOQ | D512: TDWG | E512: ACT | F512: DIFF | H512: € | I512: € | J512: Hrs | K512: Hrs
A567: SB | F567: System total - carried forward to summary page : | H567: VAT EXCL. | I567: =SUM(I513:I566) -> 0 | K567: =SUM(K513:K566) -> 0
