Workbook
Name Access_Control: #REF!
Name Access_Control: #REF!
Name Access_Control: #REF!
Name Access_Control: #REF!
Name Access_Control: [1]Elec_Est!#REF!
Name AREAS: [2]ML_Sum!$X$1:$AD$16
Name AREAS: [2]ML_Sum!$X$1:$AD$16
Name AREAS: [2]ML_Sum!$X$1:$AD$16
Name AREAS: [2]ML_Sum!$X$1:$AD$16
Name AREAS: [1]ML_Sum!$X$1:$AD$16
Name AREAS: ML_Sum!$X$1:$AD$16
Name CCTV: #REF!
Name CCTV: #REF!
Name CCTV: #REF!
Name CCTV: #REF!
Name CCTV: [1]Elec_Est!#REF!
Name Commissioning: [2]Elec_Est!#REF!
Name Data: #REF!
Name Data: #REF!
Name Data: #REF!
Name Data: #REF!
Name Data: [1]Elec_Est!#REF!
Name Electrical: [2]Elec_Est!#REF!
Name Fire_Alarm: #REF!
Name Fire_Alarm: #REF!
Name Fire_Alarm: #REF!
Name Fire_Alarm: #REF!
Name Fire_Alarm: [1]Elec_Est!#REF!
Name Fire_Barriers: [2]Elec_Est!#REF!
Name FO: #REF!
Name FO: #REF!
Name FO: #REF!
Name FO: #REF!
Name FO: [1]Elec_Est!#REF!
Name Guard: #REF!
Name Guard: #REF!
Name Guard: #REF!
Name Guard: #REF!
Name Guard: [1]Elec_Est!#REF!
Name Intercom: #REF!
Name Intercom: #REF!
Name Intercom: #REF!
Name Intercom: #REF!
Name Intercom: [1]Elec_Est!#REF!
Name Intruder_Alarm: #REF!
Name Intruder_Alarm: #REF!
Name Intruder_Alarm: #REF!
Name Intruder_Alarm: #REF!
Name Intruder_Alarm: [1]Elec_Est!#REF!

Sheet SUMM PG
A1: SUMMARY OF BILLS
F4: € | H4: €
A6: PRELIMINARIES
A8: Collection from page 2
A10: Collection from page 3 | H10: =SUM(F7:F10) -> 0
A13: ELECTRICAL INFRASTRUCTURE
A15: Collection from page 4
A17: Collection from page 5
A19: Collection from page 6
A21: Collection from page 7
A23: Collection from page 8
A25: Collection from page 9 | H25: =SUM(F15:F25) -> 0
A28: FIRE STOPPING
A30: Collection from page 10 | H30: =SUM(F30:G30) -> 0
A33: DISMANTLING EXISTING SERVICES
A35: Collection from page 11 | H35: =SUM(F35:G35) -> 0
A38: CHILLERS DISMANTLING
A40: Collection from page 12 | F40: =Chillers_Dismantling_BOQ!F51 -> 0 | H40: =SUM(F40:G40) -> 0
A43: BOILERS DISMANTLING
A45: Collection from page 13 | F45: =Boilers_Dismantling_BOQ!F53 -> 283.28 | H45: =SUM(F45:G45) -> 283.28
A48: CHILLERS NEW
A50: Collection from page 14 | F50: =Chillers_New_BOQ!G51 -> 17970.63
A52: Collection from page 15 | F52: =Chillers_New_BOQ!G109 -> 14968.5
A54: Collection from page 16 | F54: =Chillers_New_BOQ!G163 -> 14194.89
A56: Collection from page 17 | F56: =Chillers_New_BOQ!G221 -> 15236.34
A58: Collection from page 18 | F58: =Chillers_New_BOQ!G280 -> 136.56
A60: Collection from page 19 | F60: =Chillers_New_BOQ!G332 -> 4769.23
A62: Collection from page 20 | F62: =Chillers_New_BOQ!G389 -> 138.28
A64: Collection from page 21 | F64: =Chillers_New_BOQ!G447 -> 76.62
A66: Collection from page 22 | F66: =Chillers_New_BOQ!G503 -> 0 | H66: =SUM(F50:F66) -> 67491.05
A69: HTHP NEW
A71: Collection from page 23 | F71: =HTHP_New_BOQ!Q54 -> 62.88
A73: Collection from page 24 | F73: =HTHP_New_BOQ!Q106 -> 153.92
A75: Collection from page 25 | F75: =HTHP_New_BOQ!Q162 -> 458.73
A77: Collection from page 26 | F77: =HTHP_New_BOQ!Q211 -> 2791.26
A79: Collection from page 27 | F79: =HTHP_New_BOQ!Q267 -> 0
A81: Collection from page 28 | F81: =HTHP_New_BOQ!Q320 -> 331.8
A83: Collection from page 29 | F83: =HTHP_New_BOQ!Q378 -> 0 | H83: =SUM(F71:F83) -> 3798.59
A86: PUMPS DISMANTLING
A88: Collection from page 30 | F88: =Pumps_Dismantling_BOQ!F52 -> 0
A90: Collection from page 31 | F90: =Pumps_Dismantling_BOQ!F108 -> 0
A92: Collection from page 32 | F92: =Pumps_Dismantling_BOQ!F164 -> 0
A94: Collection from page 33 | F94: =Pumps_Dismantling_BOQ!F216 -> 929.03 | H94: =SUM(F87:F94) -> 929.03
A97: CENTRAL CONTROLLER
A99: Collection from page 34
A101: Collection from page 35 | H101: =SUM(F99:F101) -> 0
A104: PUMPS NEW
A106: Collection from page 36 | F106: =Pumps_New_BOQ!Q57 -> 517.88
A108: Collection from page 37 | F108: =Pumps_New_BOQ!Q115 -> 335.04
A110: Collection from page 38 | F110: =Pumps_New_BOQ!Q173 -> 182.84
A112: Collection from page 39 | F112: =Pumps_New_BOQ!Q232 -> 0
A114: Collection from page 40 | F114: =Pumps_New_BOQ!Q291 -> 0
A116: Collection from page 41 | F116: =Pumps_New_BOQ!Q350 -> 0
A118: Collection from page 42 | F118: =Pumps_New_BOQ!Q409 -> 0
A120: Collection from page 43 | F120: =Pumps_New_BOQ!Q469 -> 0
A122: Collection from page 44 | F122: =Pumps_New_BOQ!Q529 -> 0
A124: Collection from page 45 | F124: =Pumps_New_BOQ!Q589 -> 0
A126: Collection from page 46 | F126: =Pumps_New_BOQ!Q649 -> 0
A128: Collection from page 47 | F128: =Pumps_New_BOQ!Q709 -> 0
A130: Collection from page 48 | F130: =Pumps_New_BOQ!Q769 -> 0
A132: Collection from page 49 | F132: =Pumps_New_BOQ!Q829 -> 0
A134: Collection from page 50 | F134: =Pumps_New_BOQ!Q889 -> 0
A136: Collection from page 51 | F136: =Pumps_New_BOQ!Q949 -> 0
A138: Collection from page 52 | F138: =Pumps_New_BOQ!Q1009 -> 0
A140: Collection from page 53 | F140: =Pumps_New_BOQ!Q1069 -> 0
A142: Collection from page 54 | F142: =Pumps_New_BOQ!Q1129 -> 0
A144: Collection from page 55 | F144: =Pumps_New_BOQ!Q1177 -> 1697.13
A146: Collection from page 56 | F146: =Pumps_New_BOQ!Q1235 -> 331.8
A148: Collection from page 57 | F148: =Pumps_New_BOQ!Q1289 -> 517.88
A150: Collection from page 58 | F150: =Pumps_New_BOQ!Q1346 -> 335.04
A152: Collection from page 59 | F152: =Pumps_New_BOQ!Q1404 -> 182.84 | H152: =SUM(F105:F152) -> 4100.45
A155: AHU MOTORS NEW
A157: Collection from page 60 | F157: =AHU_Motors_New_BOQ!F42 -> 5699.05
A159: Collection from page 61 | F159: =AHU_Motors_New_BOQ!F93 -> 33944.91
A161: Collection from page 62 | F161: =AHU_Motors_New_BOQ!F145 -> 27686.3
A163: Collection from page 63 | F163: =AHU_Motors_New_BOQ!F197 -> 5486.79 | H163: =SUM(F157:F163) -> 72817.05
A166: EXTRACT FANS
A168: Collection from page 64 | F168: =EF_BOQ!O44 -> 15366.1 | H168: =SUM(F168:G168) -> 15366.1
A171: AC SPLIT UNITS
A173: Collection from page 65 | F173: =AC_Split_Unit_BOQ!F55 -> 58 | H173: =SUM(F173:G173) -> 58
A176: BUILDING MANAGEMENT SYSTEM
A178: Collection from page 66 | H178: =SUM(F178:G178) -> 0
A181: COMMISSIONING AND DOCUMENTATION
A183: Collection from page 67 | F183: =Commissioning_BOQ!F42 -> 0 | H183: =SUM(F183:G183) -> 0
A188: MAINTENANCE
A190: Collection from page 68 | F190: =Maintenance_BOQ!G55 -> 0 | H190: =SUM(F190:G190) -> 0
A193: PROVISIONAL SUM
A195: Collection from page 69 | H195: =SUM(F195:G195) -> 0
A198: Add / Omit (to specify):
A200: Total: | H200: =SUM(H1:H199) -> 164843.55
A202: V.A.T. @ 18% | H202: =H200*18% -> 29671.839
A204: Overall Total in Euro: | G204: € | H204: =H202+H200 -> 194515.39
A210: Signature:
A212: Name in Block:
A214: Occupation:
A216: I.D. Card No.:
A218: VAT Reg. No.:
A220: For and on behalf of:
A222: Company Reg. No.:
A224: Address:
...

Sheet Notes
A1: NOTES
A3: ELECTRICAL
B5: General
A6: 1 | B6: Dismantling works - We covered disconnecting of equipment and dismantling of any related controls installations. Dismantling of power cables is excluded. No carting away of electrical material is being allowed as we assume this can be carted away along with the equipment in your quotation.
B8: Chiller New Installation
A9: 1 | B9: Rate includes for installation of a flow switch and pump/chiller interlocks. Connection of power supplies to chillers is included in the electrical BOQ
A11: 2 | B11: Energy Meters and Motorised valves - Any unions / reducers that may be required to fit the device are excluded
B13: High temperature heat pumps
A14: 1 | B14: Rate includes for installation of a flow switch and heat pump/chiller interlocks. Connection of power supplies to chillers is included in the electrical BOQ
A15: 2 | B15: Pumps - rate include connecting of pumps to local power supplies where quoted.
A16: 3 | B16: Energy Meters and Motorised valves - Any unions / reducers that may be required to fit the device are excluded
B18: New Pumps
A19: 1 | B19: New pumps will be connected to the existing power cables. We assume these are adequatly sized and long enough to reach the new pump location.
A20: 2 | B20: Any modifcations and upgrading of the MCC supplying the new pumps is excluded.

Sheet Quote
A1: =IF(AND(UPPER(LEFT(TRIM($D$8),11))="01",UPPER(LEFT(TRIM($D$9),3))<>"ELM"),"PANTA RETAIL LTD.","PANTA CONTRACTING LIMITED") -> PANTA CONTRACTING LIMITED
A2: =IF(UPPER(LEFT(TRIM($D$9),3))="ELM","ELEC-FOR-MECH INTERNAL QUOTATION","ELECTRICAL INTERNAL QUOTATION") -> ELEC-FOR-MECH INTERNAL QUOTATION
B5: ATT: | D5: =IF(A2="Internal Quotation", "Mechanical Division","") | R5: Dated: | S5: =NOW() -> 45925.648
B6: CLIENT: | C6: Link to ML_SUM $D1 | D6: =ML_Sum!D1 -> Eden Lesuire Group
B7: PROJECT: | C7: Link to ML_SUM $D2 | D7: =ML_Sum!D2 -> Intercontinental - Plant Retrofit
B8: JOB DESC: | C8: Link to ML_SUM $D3 | D8: =ML_Sum!D3 -> Retrofitting works for the HVAC plant at Intercontinental Revision A
B9: QUOTE No: | C9: Link to ML_SUM $D4 | D9: =ML_Sum!D4 -> ELM25-0465A
B10: CLIENT's Ref: | C10: Link to ML_SUM $D5 | D10: =ML_Sum!D5 -> Tender
D21: Material Cost (€) : | E21: =ML_Sum!R35 -> 129825.13 | F21: =ML_Sum!D6 -> VAT EXCL. | G21: VAT EXCLUDED. | H21: VAT EXCLUDED. | I21: VAT EXCLUDED. | J21: VAT EXCLUDED. | K21: VAT EXCLUDED. | L21: VAT EXCLUDED. | M21: VAT EXCLUDED. | N21: VAT EXCLUDED. | O21: VAT EXCLUDED. | P21: VAT EXCLUDED.
D22: Labour Pair Hours : | E22: =ML_Sum!T35 -> 949.23
A53: Signed for and on behalf of | Q53: Signed for and on behalf of
A54: Electrical Division | Q54: Division
Q56: Records
Q57: Mr. K. Micallef
Q59: File

Sheet ML_Sum
B1: CLIENT: | C1: 1 | D1: Eden Lesuire Group | G1: TRUE | H1: TRUE | I1: 1 | J1: =$Q109 -> 1 | K1: =$Q119 -> 1 | L1: =$Q129 -> 1 | M1: =$Q139 -> 1 | N1: =$Q149 -> 1 | O1: =$Q159 -> 1 | Q1: =IF(C1=1,"€","Curr?") -> € | R1: Recon /Lab.Cont >> | S1: =IF($S$39="PRINT","R","Do Not Print") -> R | T1: 1 | V1: {=IF(OR(X1=AREAS),1,0)} -> 1 | W1: BOQ | X1: x | Y1: x | Z1: x | AA1: x | AB1: x | AC1: x | AD1: x
B2: PROJECT: | C2: =IF($D$6="VAT INCLUDED",1.18,1)*(1-$Q2)*$C$1 -> 1 | D2: Intercontinental - Plant Retrofit | F2: Electrical | G2: TRUE | I2: 2 | J2: =$Q110 -> 1 | K2: =$Q120 -> 1 | L2: =$Q130 -> 1 | M2: =$Q140 -> 1 | N2: =$Q150 -> 1 | O2: =$Q160 -> 1 | R2: ="A) " & IF($S2=0,"",ROUND($S2,2) & "-" & ROUND($T2/$D$9,2)) -> A) 1.35-1.35 | S2: 1.35 | T2: =$S2*$D9 -> 37.071 | X2: x | Y2: x | Z2: x | AA2: x | AB2: x | AC2: x | AD2: x
B3: JOB DESC: | C3: =IF($D$6="VAT INCLUDED",1.18,1)*(1-$Q3)*$C$1 -> 1 | D3: Retrofitting works for the HVAC plant at Intercontinental Revision A | F3: Technician | G3: TRUE | I3: 3 | J3: =$Q111 -> 1 | K3: =$Q121 -> 1 | L3: =$Q131 -> 1 | M3: =$Q141 -> 1 | N3: =$Q151 -> 1 | O3: =$Q161 -> 1 | R3: ="B) " & IF($S3=0,"",ROUND($S3,2) & "-" & ROUND($T3/$D$9,2)) -> B) 1.35-1.66 | S3: 1.35 | T3: =$S3*$D10 -> 45.522 | X3: x | Y3: x | Z3: x | AA3: x | AB3: x | AC3: x | AD3: x
B4: INT. QUOT No: | C4: =IF($D$6="VAT INCLUDED",1.18,1)*(1-$Q4)*$C$1 -> 1 | D4: ELM25-0465A | F4: Engineer (Man Hours) | G4: TRUE | I4: 4 | J4: =$Q112 -> 1 | K4: =$Q122 -> 1 | L4: =$Q132 -> 1 | M4: =$Q142 -> 1 | N4: =$Q152 -> 1 | O4: =$Q162 -> 1 | R4: ="C) " & IF($S4=0,"",ROUND($S4,2) & "-" & ROUND($T4/$D$9,2)) -> C) 1.35-1.47 | S4: 1.35 | T4: =$S4*$D11 -> 40.5 | X4: x | Y4: x | Z4: x | AA4: x | AB4: x | AC4: x | AD4: x
B5: CLIENTs REF: | C5: =IF($D$6="VAT INCLUDED",1.18,1)*(1-$Q5)*$C$1 -> 1 | D5: Tender | F5: Megaline | G5: TRUE | I5: 5 | J5: =$Q113 -> 1 | K5: =$Q123 -> 1 | L5: =$Q133 -> 1 | M5: =$Q143 -> 1 | N5: =$Q153 -> 1 | O5: =$Q163 -> 1 | R5: ="D) " & IF($S5=0,"",ROUND($S5,2) & "-" & ROUND($T5/$D$9,2)) -> D) 1-1.35 | S5: 1 | T5: =S2*D9 -> 37.071 | X5: x | Y5: x | Z5: x | AA5: x | AB5: x | AC5: x | AD5: x
B6: VAT: | C6: =IF($D$6="VAT INCLUDED",1.18,1)*(1-$Q6)*$C$1 -> 1 | D6: VAT EXCL. | G6: TRUE | I6: 6 | J6: =$Q114 -> 1 | K6: =$Q124 -> 1 | L6: =$Q134 -> 1 | M6: =$Q144 -> 1 | N6: =$Q154 -> 1 | O6: =$Q164 -> 1 | R6: ="E) " & IF($S6=0,"",ROUND($S6,2) & "-" & ROUND($T6/$D$9,2)) -> E) | X6: x | Y6: x | Z6: x | AA6: x | AB6: x | AC6: x | AD6: x
B7: SAVED ON: | C7: =IF($D$6="VAT INCLUDED",1.18,1)*(1-$Q7)*$C$1 -> 1 | D7: 45862 | G7: TRUE | I7: 7 | J7: =$Q115 -> 1 | K7: =$Q125 -> 1 | L7: =$Q135 -> 1 | M7: =$Q145 -> 1 | N7: =$Q155 -> 1 | R7: ="F) " & IF($S7=0,"",ROUND($S7,2) & "-" & ROUND($T7/$D$9,2)) -> F) | X7: x | Y7: x | Z7: x | AA7: x | AB7: x | AC7: x | AD7: x
B8: ESTIMATOR: | C8: =IF($D$6="VAT INCLUDED",1.18,1)*(1-$Q8)*$C$1 -> 1 | D8: T.Sammut | G8: TRUE | I8: 8 | J8: =$Q116 -> 1 | K8: =$Q126 -> 1 | L8: =$Q136 -> 1 | M8: =$Q146 -> 1 | N8: =$Q156 -> 1 | R8: ="G) " & IF($S8=0,"",ROUND($S8,2) & "-" & ROUND($T8/$D$9,2)) -> G) | X8: x | Y8: x | Z8: x | AA8: x | AB8: x | AC8: x | AD8: x
B9: LAB. COST: | C9: =IF($D$6="VAT INCLUDED",1.18,1)*(1-$Q9)*$C$1 -> 1 | D9: 27.46 | E9: Electrician Pairs | G9: TRUE | I9: 9 | J9: =$Q117 -> 1 | K9: =$Q127 -> 1 | L9: =$Q137 -> 1 | M9: =$Q147 -> 1 | N9: =$Q157 -> 1 | R9: ="H) " & IF($S9=0,"",ROUND($S9,2) & "-" & ROUND($T9/$D$9,2)) -> H) | X9: x | Y9: x | Z9: x | AA9: x | AB9: x | AC9: x | AD9: x
C10: =IF($D$6="VAT INCLUDED",1.18,1)*(1-$Q10)*$C$1 -> 1 | D10: 33.72 | E10: Technician Pairs - By Guy 25.07.2025 | G10: TRUE | I10: 10 | J10: =$Q118 -> 1 | K10: =$Q128 -> 1 | L10: =$Q138 -> 1 | M10: =$Q148 -> 1 | N10: =$Q158 -> 1 | O10: =Q108 -> 1 | R10: =" I) " & IF($S10=0,"",ROUND($S10,2) & "-" & ROUND($T10/$D$9,2)) -> I) | X10: x | Y10: x | Z10: x | AA10: x | AB10: x | AC10: x | AD10: x
C11: =IF($D$6="VAT INCLUDED",1.18,1)*(1-$Q11)*$C$1 -> 1 | D11: 30 | E11: Engineer Man Hours - By Guy 25.07.2025 | R11: ="J) " & IF($S11=0,"",ROUND($S11,2) & "-" & ROUND($T11/$D$9,2)) -> J) | X11: x | Y11: x | Z11: x | AA11: x | AB11: x | AC11: x | AD11: x
C12: =IF($D$6="VAT INCLUDED",1.18,1)*(1-$Q12)*$C$1 -> 1 | G12: SYSTEMS | H12: SYSTEMS | I12: SYSTEMS | J12: SYSTEMS | K12: SYSTEMS | L12: SYSTEMS | M12: SYSTEMS | N12: SYSTEMS | O12: SYSTEMS | P12: SYSTEMS | R12: MIXED - X,Y ) | S12: MAT MU | T12: LAB RATE | X12: x | Y12: x | Z12: x | AA12: x | AB12: x | AC12: x | AD12: x
B13: MATERIAL & LABOUR SUMMARY | G13: ItemCode | H13: CostCode | I13: MAKE | J13: PART_NO | K13: MARKUP | L13: TYPE | M13: LIST_P | N13: SET | O13: FIX | P13: DATE | Q13: %Dsct in BOQ | R13: MATMU-LABMU | S13: MAT CONT >> | T13: =SUM(Q108:Q164)/57 -> 1
B14: =IF($D$6<>"VAT EXCL.", "QUOTE ISSUED WITH VAT INCLUDED", "") | X14: x | Y14: x | Z14: x | AA14: x | AB14: x | AC14: x | AD14: x
Q15: =(C72-F35)/C72 -> 1 | R15: Average Discount applied in BOQ (Q2-Q12) | X15: x | Y15: x | Z15: x | AA15: x | AB15: x | AC15: x | AD15: x
B16: =IF($W$1<>"BOQ", "DIFF SET TO " & W1,"") | Q16: =(F35-E35)/F35 -> #DIV/0! | R16: Average Discount applied on Totals (Q23-Q32) | X16: x | Y16: x | Z16: x | AA16: x | AB16: x | AC16: x | AD16: x
Q17: =F74 -> 0 | R17: Overall Discount
B18: =IF(AND(G1,G2,G3,G4,G5,G6,G7,G8,G9,G10,H1)=TRUE, "", "CHECKLIST INCOMPLETE !" )
B19: =IF(ABS(SUM(A23:A32))>100,"[Discy A-J] are high, Check it out."," ") | Q19: =R83 -> 1.3431072 | R19: Overall Markup (Final Selling Excl.VAT/Total Cost )
E21: DISCOUNTED | F21: SELLING | Q21: % Discnt | R21: MATERIAL | T21: LABOUR
A22: Discy.A-J | B22: Markup/LRate | E22: ="SELLING " & $Q$1 -> SELLING € | F22: =$Q$1 -> € | G22: VAT/DISC | H22: MU | I22: LABRATE | J22: LABCOST | Q22: on Totals | R22: € | T22: Pair Hrs.
A23: =IF($F23=0,"",($F23/$C2)-($R23*$S2+$T23*$T2)) -> 0.045045 | B23: =IF(F23=0,"",IF(R23=0,"A) "&"---, "&ROUND(($F23/$C2-($R23*$S2))/$T23,2),IF(T23=0,"A) "&ROUND(($F23/$C2)/$R23,2),"A) "&ROUND(($F23/$C2-($T23*$T2))/$R23,2)&", " &ROUND(($F23/$C2-($R23*$S2))/$T23,2)))) -> A) 1.35, 37.07 | D23: =IF($F2="","",$F2) -> Electrical | E23: =F23*(1-Q23) -> 59159.25 | F23: =Elec_Est!F3130 -> 59159.25 | G23: =C2 -> 1 | H23: =$S2 -> 1.35 | I23: =$T2 -> 37.071 | J23: =$D$9 -> 27.46 | R23: =Elec_Est!R3130 -> 24030.388 | T23: =Elec_Est!T3130 -> 720.73
A24: =IF($F24=0,"",($F24/$C3)-($R24*$S3+$T24*$T3)) -> 0.048 | B24: =IF(F24=0,"",IF(R24=0,"A) "&"---, "&ROUND(($F24/$C3-($R24*$S3))/$T24,2),IF(T24=0,"A) "&ROUND(($F24/$C3)/$R24,2),"A) "&ROUND(($F24/$C3-($T24*$T3))/$R24,2)&", " &ROUND(($F24/$C3-($R24*$S3))/$T24,2)))) -> A) 1.35, 45.52 | D24: =IF($F3="","",$F3) -> Technician | E24: =F24*(1-Q24) -> 139537.56 | F24: =Elec_Est!F3131 -> 139537.56 | G24: =C3 -> 1 | H24: =$S3 -> 1.35 | I24: =$T3 -> 45.522 | J24: =$D$9 -> 27.46 | R24: =Elec_Est!R3131 -> 98353.7 | T24: =Elec_Est!T3131 -> 148.5
A25: =IF($F25=0,"",($F25/$C4)-($R25*$S4+$T25*$T4)) -> 0.01 | B25: =IF(F25=0,"",IF(R25=0,"A) "&"---, "&ROUND(($F25/$C4-($R25*$S4))/$T25,2),IF(T25=0,"A) "&ROUND(($F25/$C4)/$R25,2),"A) "&ROUND(($F25/$C4-($T25*$T4))/$R25,2)&", " &ROUND(($F25/$C4-($R25*$S4))/$T25,2)))) -> A) ---, 40.5 | D25: =IF($F4="","",$F4) -> Engineer (Man Hours) | E25: =F25*(1-Q25) -> 3240.01 | F25: =Elec_Est!F3132 -> 3240.01 | G25: =C4 -> 1 | H25: =$S4 -> 1.35 | I25: =$T4 -> 40.5 | J25: =$D$9 -> 27.46 | R25: =Elec_Est!R3132 -> 0 | T25: =Elec_Est!T3132 -> 80
A26: =IF($F26=0,"",($F26/$C5)-($R26*$S5+$T26*$T5)) -> 0 | B26: =IF(F26=0,"",IF(R26=0,"A) "&"---, "&ROUND(($F26/$C5-($R26*$S5))/$T26,2),IF(T26=0,"A) "&ROUND(($F26/$C5)/$R26,2),"A) "&ROUND(($F26/$C5-($T26*$T5))/$R26,2)&", " &ROUND(($F26/$C5-($R26*$S5))/$T26,2)))) -> A) 1 | D26: =IF($F5="","",$F5) -> Megaline | E26: =F26*(1-Q26) -> 7441.04 | F26: =Elec_Est!F3133 -> 7441.04 | G26: =C5 -> 1 | H26: =$S5 -> 1 | I26: =$T5 -> 37.071 | J26: =$D$9 -> 27.46 | R26: =Elec_Est!R3133 -> 7441.04 | T26: =Elec_Est!T3133 -> 0
A27: =IF($F27=0,"",($F27/$C6)-($R27*$S6+$T27*$T6)) | B27: =IF(F27=0,"",IF(R27=0,"A) "&"---, "&ROUND(($F27/$C6-($R27*$S6))/$T27,2),IF(T27=0,"A) "&ROUND(($F27/$C6)/$R27,2),"A) "&ROUND(($F27/$C6-($T27*$T6))/$R27,2)&", " &ROUND(($F27/$C6-($R27*$S6))/$T27,2)))) | D27: =IF($F6="","",$F6) | E27: =F27*(1-Q27) -> 0 | F27: =Elec_Est!F3134 -> 0 | G27: =C6 -> 1 | H27: =$S6 -> 0 | I27: =$T6 -> 0 | J27: =$D$9 -> 27.46 | R27: =Elec_Est!R3134 -> 0 | T27: =Elec_Est!T3134 -> 0
A28: =IF($F28=0,"",($F28/$C7)-($R28*$S7+$T28*$T7)) | B28: =IF(F28=0,"",IF(R28=0,"A) "&"---, "&ROUND(($F28/$C7-($R28*$S7))/$T28,2),IF(T28=0,"A) "&ROUND(($F28/$C7)/$R28,2),"A) "&ROUND(($F28/$C7-($T28*$T7))/$R28,2)&", " &ROUND(($F28/$C7-($R28*$S7))/$T28,2)))) | D28: =IF($F7="","",$F7) | E28: =F28*(1-Q28) -> 0 | F28: =Elec_Est!F3135 -> 0 | G28: =C7 -> 1 | H28: =$S7 -> 0 | I28: =$T7 -> 0 | J28: =$D$9 -> 27.46 | R28: =Elec_Est!R3135 -> 0 | T28: =Elec_Est!T3135 -> 0
A29: =IF($F29=0,"",($F29/$C8)-($R29*$S8+$T29*$T8)) | B29: =IF(F29=0,"",IF(R29=0,"A) "&"---, "&ROUND(($F29/$C8-($R29*$S8))/$T29,2),IF(T29=0,"A) "&ROUND(($F29/$C8)/$R29,2),"A) "&ROUND(($F29/$C8-($T29*$T8))/$R29,2)&", " &ROUND(($F29/$C8-($R29*$S8))/$T29,2)))) | D29: =IF($F8="","",$F8) | E29: =F29*(1-Q29) -> 0 | F29: =Elec_Est!F3136 -> 0 | G29: =C8 -> 1 | H29: =$S8 -> 0 | I29: =$T8 -> 0 | J29: =$D$9 -> 27.46 | R29: =Elec_Est!R3136 -> 0 | T29: =Elec_Est!T3136 -> 0
A30: =IF($F30=0,"",($F30/$C9)-($R30*$S9+$T30*$T9)) | B30: =IF(F30=0,"",IF(R30=0,"A) "&"---, "&ROUND(($F30/$C9-($R30*$S9))/$T30,2),IF(T30=0,"A) "&ROUND(($F30/$C9)/$R30,2),"A) "&ROUND(($F30/$C9-($T30*$T9))/$R30,2)&", " &ROUND(($F30/$C9-($R30*$S9))/$T30,2)))) | D30: =IF($F9="","",$F9) | E30: =F30*(1-Q30) -> 0 | F30: =Elec_Est!F3137 -> 0 | G30: =C9 -> 1 | H30: =$S9 -> 0 | I30: =$T9 -> 0 | J30: =$D$9 -> 27.46 | R30: =Elec_Est!R3137 -> 0 | T30: =Elec_Est!T3137 -> 0
A31: =IF($F31=0,"",($F31/$C10)-($R31*$S10+$T31*$T10)) | B31: =IF(F31=0,"",IF(R31=0,"A) "&"---, "&ROUND(($F31/$C10-($R31*$S10))/$T31,2),IF(T31=0,"A) "&ROUND(($F31/$C10)/$R31,2),"A) "&ROUND(($F31/$C10-($T31*$T10))/$R31,2)&", " &ROUND(($F31/$C10-($R31*$S10))/$T31,2)))) | D31: =IF($F10="","",$F10) | E31: =F31*(1-Q31) -> 0 | F31: =Elec_Est!F3138 -> 0 | G31: =C10 -> 1 | H31: =$S10 -> 0 | I31: =$T10 -> 0 | J31: =$D$9 -> 27.46 | R31: =Elec_Est!R3138 -> 0 | T31: =Elec_Est!T3138 -> 0
A32: =IF($F32=0,"",($F32/$C11)-($R32*$S11+$T32*$T11)) | B32: =IF(F32=0,"",IF(R32=0,"A) "&"---, "&ROUND(($F32/$C11-($R32*$S11))/$T32,2),IF(T32=0,"A) "&ROUND(($F32/$C11)/$R32,2),"A) "&ROUND(($F32/$C11-($T32*$T11))/$R32,2)&", " &ROUND(($F32/$C11-($R32*$S11))/$T32,2)))) | D32: =IF($F11="","",$F11) | E32: =F32*(1-Q32) -> 0 | F32: =Elec_Est!F3139 -> 0 | G32: =C11 -> 1 | H32: =$S11 -> 0 | I32: =$T11 -> 0 | J32: =$D$9 -> 27.46 | R32: =Elec_Est!R3139 -> 0 | T32: =Elec_Est!T3139 -> 0
C33: MIXED
A35: Discy.L | E35: =SUM(E23:E32) -> 209377.86 | R35: =SUM(R23:R32) -> 129825.13 | T35: =SUM(T23:T32) -> 949.23
A36: =IF(A39=0,"0.00",A39-(A38*A37)) -> 0.00 | B36: BOQ TOTAL | E36: ="ESTIM TOTAL (" & $Q$1 & ")" -> ESTIM TOTAL (€)
A37: 1.125 | B37: <1 Actual LabCont | R37: =R165 -> 129825.08 | S37: C.C.Totals | T37: =T165 -> 949.22
B38: <2 Phrs @ 1.00
B39: <3 Phrs @ Actual | Q39: Discy.T >> | R39: =R37-R35 -> -0.049 | S39: PRINT | T39: =T37-T35 -> -0.01
B41: Values Only on : | D41: 45911 | R41: 100965.05 | T41: 881.23
A46: REMARKS:
A47: 1) VAT and Duties as above.
A48: 2)
A51: ESTIMATOR: | D51: =D8 -> T.Sammut | Q51: APPROVED BY:
A53: SIGNED: | Q53: DATE APPROVED:
A55: FILE LOCATION: | D55: =CELL("filename") -> \\Pclnas\ele\est\Intercontinental Hotel\Estimates\Estimates Sept 2025\As Awarded Contract\[E25_0477_IH_Retro_Elec_Est_Rev_A.xlsx]SUMM PG
B57: PANTA CONTRACTING LTD. - ELECTRICAL DIVISION
B58: CONTRACT / VARIATION INPUT DOCUMENT
S59: Copy to:-
D60: Client: | E60: =D1 -> Eden Lesuire Group | S60: Ms. V. Vella
D61: Project: | E61: =D2 -> Intercontinental - Plant Retrofit | S61: Mr. K. Micallef
D62: Job Description: | E62: =D3 -> Retrofitting works for the HVAC plant at Intercontinental Revision A | S62: Mr. A. Sciberras
D63: Quote No: | E63: =D4 -> ELM25-0465A
D64: Client's Ref: | E64: =D5 -> Tender
S65: File:-
D66: File No:
D67: Ext. Ref:
E70: Contract /Variation (Excl. VAT)
C72: =IF($A$33="MIXED",F23/(1-Q2)+F24/(1-Q3)+F25/(1-Q4)+F26/(1-Q5)+F27/(1-Q6)+F28/(1-Q7)+F29/(1-Q8)+F30/(1-Q9)+F31/(1-Q10)+F32/(1-Q11)-SUM(A23:A32), F23/(1-Q2)+F24/(1-Q3)+F25/(1-Q4)+F26/(1-Q5)+F27/(1-Q6)+F28/(1-Q7)+F29/(1-Q8)+F30/(1-Q9)+F31/(1-Q10)+F32/(1-Q11)) -> 209377.86 | E72: Estim.Sell before Discounts excl.VAT (€): | F72: =IF(D6="VAT INCLUDED",C72/($C$1*1.18),C72/$C$1) -> 209377.86
E74: Overall Discount: | F74: =(F72-F75)/F72 -> 0
E75: Final Sell after Discounts excl.VAT (€): | F75: =IF(D6="VAT INCLUDED",E35/($C$1*1.18),E35/$C$1) -> 209377.86
E77: Labour Rate - | F77: =$D$9 -> 27.46 | R77: Mech. Cost to us
D80: Mat. Cost | E80: Labour | F80: Total Cost | R80: Sell Excl.VAT / Total Cost
D81: € | E81: Pair.Hrs | F81: €
D83: =R165 -> 129825.08 | E83: =T165 -> 949.22 | F83: =R165+S165 -> 155890.66 | R83: =IF(F83=0,0,F75/F83) -> 1.3431072
D84: ( From CostCode Totals )
R87: Advanced Payment:
R88: Retention:
R90: Awarded Date:
R91: Estimated Start Date:
R92: Estimated Completion Date:
D93: .................
D94: K. Micallef | R94: Date issued:
D95: =NOW() -> 45925.648
D98: PANTA CONTRACTING LTD. - ELECTRICAL DIVISION
D99: ELECTRICAL AND ELV CONTRACT / VARIATION BUDGET COST
D101: Project: | E101: =E61 -> Intercontinental - Plant Retrofit
D102: Job Desc: | E102: =E62 -> Retrofitting works for the HVAC plant at Intercontinental Revision A
D103: Client's Ref: | E103: =E64 -> Tender
D106: COSTCODE | F106: Cost | Q106: Mat. | R106: Mat Cost | S106: Lab Cost @ | T106: Labour
F107: Code | Q107: Cont. | R107: € | S107: =$D$9 -> 27.46 | T107: Pair.Hrs
B108: V:56 | D108: BOQ RateOnly Items | P108: FIX | Q108: 1
B109: 1(J) | C109: cc | D109: Erection materials | F109: 501 | P109: 1 | Q109: 1 | R109: =Elec_Est!R3151 -> 1948.364 | S109: =T109*$D$9 -> 0 | T109: =Elec_Est!T3151 -> 0
B110: 2 | C110: cc | D110: Busbar Trunking | F110: 505 | P110: 1 | Q110: 1 | R110: =Elec_Est!R3152 -> 0 | S110: =T110*$D$9 -> 0 | T110: =Elec_Est!T3152 -> 0
B111: 3 | C111: cc | D111: Switchgear | F111: 510 | P111: 2 | Q111: 1 | R111: =Elec_Est!R3153 -> 0 | S111: =T111*$D$9 -> 0 | T111: =Elec_Est!T3153 -> 0
B112: 4 | C112: cc | D112: MCC Equipment | F112: 511 | P112: 2 | Q112: 1 | R112: =Elec_Est!R3154 -> 0 | S112: =T112*$D$9 -> 0 | T112: =Elec_Est!T3154 -> 0
B113: 5 | C113: cc | D113: BMS Equipment | F113: 512 | P113: 2 | Q113: 1 | R113: =Elec_Est!R3155 -> 70901.5 | S113: =T113*$D$9 -> 2196.8 | T113: =Elec_Est!T3155 -> 80
B114: 6 | C114: cc | D114: PVC Pipes / Ducts | F114: 520 | P114: 1 | Q114: 1 | R114: =Elec_Est!R3156 -> 0 | S114: =T114*$D$9 -> 0 | T114: =Elec_Est!T3156 -> 0
B115: 7 | C115: cc | D115: High/medium voltage switchgear | F115: 530 | P115: 2 | Q115: 1 | R115: =Elec_Est!R3157 -> 0 | S115: =T115*$D$9 -> 0 | T115: =Elec_Est!T3157 -> 0
B116: 8 | C116: cc | D116: Power Transformers | F116: 550 | P116: 2 | Q116: 1 | R116: =Elec_Est!R3158 -> 0 | S116: =T116*$D$9 -> 0 | T116: =Elec_Est!T3158 -> 0
B117: 9 | C117: cc | D117: Control Panels | F117: 570 | P117: 2 | Q117: 1 | R117: =Elec_Est!R3159 -> 35715 | S117: =T117*$D$9 -> 6210.3536 | T117: =Elec_Est!T3159 -> 226.16
B118: 10 | C118: cc | D118: Electrical Single Core Cables | F118: 615 | P118: 2 | Q118: 1 | R118: =Elec_Est!R3160 -> 185 | S118: =T118*$D$9 -> 172.998 | T118: =Elec_Est!T3160 -> 6.3
B119: 11(K) | C119: cc | D119: Electrical Multicore Cables | F119: 616 | P119: 2 | Q119: 1 | R119: =Elec_Est!R3161 -> 853.62 | S119: =T119*$D$9 -> 268.5588 | T119: =Elec_Est!T3161 -> 9.78
B120: 12 | C120: cc | D120: ELV/BMS/Special Cables | F120: 617 | P120: 2 | Q120: 1 | R120: =Elec_Est!R3162 -> 3794.9375 | S120: =T120*$D$9 -> 2207.784 | T120: =Elec_Est!T3162 -> 80.4
B121: 13 | C121: cc | D121: Cable Accessories | F121: 620 | P121: 2 | Q121: 1 | R121: =Elec_Est!R3163 -> 1415.06 | S121: =T121*$D$9 -> 2307.1892 | T121: =Elec_Est!T3163 -> 84.02
B122: 14 | C122: cc | D122: Galv. Cable Trays | F122: 650 | P122: 1 | Q122: 1 | R122: =Elec_Est!R3164 -> 221.872 | S122: =T122*$D$9 -> 242.1972 | T122: =Elec_Est!T3164 -> 8.82
B123: 15 | C123: cc | D123: PVC Cable Trays | F123: 651 | P123: 1 | Q123: 1 | R123: =Elec_Est!R3165 -> 0 | S123: =T123*$D$9 -> 0 | T123: =Elec_Est!T3165 -> 0
B124: 16 | C124: cc | D124: Galv. Cable Basket | F124: 652 | P124: 1 | Q124: 1 | R124: =Elec_Est!R3166 -> 0 | S124: =T124*$D$9 -> 0 | T124: =Elec_Est!T3166 -> 0
B125: 17 | C125: cc | D125: Galv. Cable Ladder | F125: 654 | P125: 1 | Q125: 1 | R125: =Elec_Est!R3167 -> 0 | S125: =T125*$D$9 -> 0 | T125: =Elec_Est!T3167 -> 0
B126: 18 | C126: cc | D126: Galv. Cable Trunking | F126: 675 | P126: 1 | Q126: 1 | R126: =Elec_Est!R3168 -> 0 | S126: =T126*$D$9 -> 0 | T126: =Elec_Est!T3168 -> 0
B127: 19 | C127: cc | D127: Alum. Cable Trunking | F127: 676 | P127: 1 | Q127: 1 | R127: =Elec_Est!R3169 -> 0 | S127: =T127*$D$9 -> 0 | T127: =Elec_Est!T3169 -> 0
B128: 20 | C128: cc | D128: PVC Cable Trunking | F128: 680 | P128: 1 | Q128: 1 | R128: =Elec_Est!R3170 -> 0 | S128: =T128*$D$9 -> 0 | T128: =Elec_Est!T3170 -> 0
...

Sheet Elec_Rates
B1: CLIENT: | C1: =ML_Sum!$C1 -> 1 | D1: =ML_Sum!$D1 -> Eden Lesuire Group | F1: =ML_Sum!$F1 -> 0 | I1: 1 | J1: =ML_Sum!$J1 -> 1 | K1: =ML_Sum!$K1 -> 1 | L1: =ML_Sum!$L1 -> 1 | M1: =ML_Sum!$M1 -> 1 | N1: =ML_Sum!$N1 -> 1 | O1: =ML_Sum!$O1 -> 1 | Q1: =ML_Sum!$Q1 -> € | R1: R/Lab Cont | S1: =ML_Sum!$S1 -> R | T1: =ML_Sum!$T1 -> 1 | U1: =ML_Sum!W1 -> BOQ | V1: INCL | W1: MULT | X1: AREA | Y1: BOQ | Z1: TDWG | AA1: ACT | AB1: DIFF
B2: PROJECT: | C2: =ML_Sum!$C2 -> 1 | D2: =ML_Sum!$D2 -> Intercontinental - Plant Retrofit | F2: =ML_Sum!$F2 -> Electrical | I2: 2 | J2: =ML_Sum!$J2 -> 1 | K2: =ML_Sum!$K2 -> 1 | L2: =ML_Sum!$L2 -> 1 | M2: =ML_Sum!$M2 -> 1 | N2: =ML_Sum!$N2 -> 1 | O2: =ML_Sum!$O2 -> 1 | Q2: =ML_Sum!$Q2 -> 0 | R2: mu_A | S2: =ML_Sum!$S2 -> 1.35 | T2: =ML_Sum!$T2 -> 37.071
B3: JOB DESC: | C3: =ML_Sum!$C3 -> 1 | D3: =ML_Sum!$D3 -> Retrofitting works for the HVAC plant at Intercontinental Revision A | F3: =ML_Sum!$F3 -> Technician | I3: 3 | J3: =ML_Sum!$J3 -> 1 | K3: =ML_Sum!$K3 -> 1 | L3: =ML_Sum!$L3 -> 1 | M3: =ML_Sum!$M3 -> 1 | N3: =ML_Sum!$N3 -> 1 | O3: =ML_Sum!$O3 -> 1 | Q3: =ML_Sum!$Q3 -> 0 | R3: mu_B | S3: =ML_Sum!$S3 -> 1.35 | T3: =ML_Sum!$T3 -> 45.522
B4: QUOTE No: | C4: =ML_Sum!$C4 -> 1 | D4: =ML_Sum!$D4 -> ELM25-0465A | F4: =ML_Sum!$F4 -> Engineer (Man Hours) | I4: 4 | J4: =ML_Sum!$J4 -> 1 | K4: =ML_Sum!$K4 -> 1 | L4: =ML_Sum!$L4 -> 1 | M4: =ML_Sum!$M4 -> 1 | N4: =ML_Sum!$N4 -> 1 | O4: =ML_Sum!$O4 -> 1 | Q4: =ML_Sum!$Q4 -> 0 | R4: mu_C | S4: =ML_Sum!$S4 -> 1.35 | T4: =ML_Sum!$T4 -> 40.5
B5: CLIENTs REF: | C5: =ML_Sum!$C5 -> 1 | D5: =ML_Sum!$D5 -> Tender | F5: =ML_Sum!$F5 -> Megaline | I5: 5 | J5: =ML_Sum!$J5 -> 1 | K5: =ML_Sum!$K5 -> 1 | L5: =ML_Sum!$L5 -> 1 | M5: =ML_Sum!$M5 -> 1 | N5: =ML_Sum!$N5 -> 1 | O5: =ML_Sum!$O5 -> 1 | Q5: =ML_Sum!$Q5 -> 0 | R5: mu_D | S5: =ML_Sum!$S5 -> 1 | T5: =ML_Sum!$T5 -> 37.071
B6: VAT/DUTIES: | C6: =ML_Sum!$C6 -> 1 | D6: =ML_Sum!$D6 -> VAT EXCL. | F6: =ML_Sum!$F6 -> 0 | I6: 6 | J6: =ML_Sum!$J6 -> 1 | K6: =ML_Sum!$K6 -> 1 | L6: =ML_Sum!$L6 -> 1 | M6: =ML_Sum!$M6 -> 1 | N6: =ML_Sum!$N6 -> 1 | O6: =ML_Sum!$O6 -> 1 | Q6: =ML_Sum!$Q6 -> 0 | R6: mu_E | S6: =ML_Sum!$S6 -> 0 | T6: =ML_Sum!$T6 -> 0
B7: SAVED ON: | C7: =ML_Sum!$C7 -> 1 | D7: 39364 | F7: =ML_Sum!$F7 -> 0 | I7: 7 | J7: =ML_Sum!$J7 -> 1 | K7: =ML_Sum!$K7 -> 1 | L7: =ML_Sum!$L7 -> 1 | M7: =ML_Sum!$M7 -> 1 | N7: =ML_Sum!$N7 -> 1 | O7: =ML_Sum!$O7 -> 0 | Q7: =ML_Sum!$Q7 -> 0 | R7: mu_F | S7: =ML_Sum!$S7 -> 0 | T7: =ML_Sum!$T7 -> 0
B8: ESTIMATOR: | C8: =ML_Sum!$C8 -> 1 | D8: =ML_Sum!$D8 -> T.Sammut | F8: =ML_Sum!$F8 -> 0 | I8: 8 | J8: =ML_Sum!$J8 -> 1 | K8: =ML_Sum!$K8 -> 1 | L8: =ML_Sum!$L8 -> 1 | M8: =ML_Sum!$M8 -> 1 | N8: =ML_Sum!$N8 -> 1 | O8: =ML_Sum!$O8 -> 0 | Q8: =ML_Sum!$Q8 -> 0 | R8: mu_G | S8: =ML_Sum!$S8 -> 0 | T8: =ML_Sum!$T8 -> 0
B9: LABOUR RATE: | C9: =ML_Sum!$C9 -> 1 | D9: =ML_Sum!$D9 -> 27.46 | F9: =ML_Sum!$F9 -> 0 | I9: 9 | J9: =ML_Sum!$J9 -> 1 | K9: =ML_Sum!$K9 -> 1 | L9: =ML_Sum!$L9 -> 1 | M9: =ML_Sum!$M9 -> 1 | N9: =ML_Sum!$N9 -> 1 | O9: =ML_Sum!$O9 -> 0 | Q9: =ML_Sum!$Q9 -> 0 | R9: mu_H | S9: =ML_Sum!$S9 -> 0 | T9: =ML_Sum!$T9 -> 0
C10: =ML_Sum!$C10 -> 1 | F10: =ML_Sum!$F10 -> 0 | I10: 10 | J10: =ML_Sum!$J10 -> 1 | K10: =ML_Sum!$K10 -> 1 | L10: =ML_Sum!$L10 -> 1 | M10: =ML_Sum!$M10 -> 1 | N10: =ML_Sum!$N10 -> 1 | O10: =ML_Sum!$O10 -> 1 | Q10: =ML_Sum!$Q10 -> 0 | R10: mu_I | S10: =ML_Sum!$S10 -> 0 | T10: =ML_Sum!$T10 -> 0
C11: =ML_Sum!$C11 -> 1 | F11: =ML_Sum!$F11 -> 0 | Q11: =ML_Sum!$Q11 -> 0 | R11: mu_J | S11: =ML_Sum!$S11 -> 0 | T11: =ML_Sum!$T11 -> 0
C12: =ML_Sum!$C12 -> 1 | F12: =ML_Sum!$F12 -> 0 | Q12: =ML_Sum!$Q12 -> 0 | R12: MIXED | S12: =ML_Sum!$S12 -> MAT MU | T12: =ML_Sum!$T12 -> LAB RATE
G13: I_CODE | H13: C_CODE | I13: MAKE | J13: PART_NO | K13: MARKUP | L13: TYPE | M13: LIST_P | N13: P_FACT | O13: FIX | P13: DATE | Q13: %Dsct in BOQ | R13: MU TYPE | S13: MAT MU | T13: LAB RATE
C15: t | D15: Item:
D16: Start Typing Header
Q18: Multip
A19: 1 | B19: =Elec_Est!B3215 -> 2 | D19: 001# Connecting up of 3.0 kW 400Volt motor (Standard) | K19: RATE | L19: RATE | Q19: =B19/A19 -> 2 | R19: =IF($B19=0,0,IF($S$1="R",ROUND(R26/$B19,2),R26/$B19)) -> 11.12 | T19: =IF($B19=0,0,IF($S$1="R",ROUND(T26/$B19,2),T26/$B19)) -> 1.46
D20: Based on: Star/Delta Starting
A21: =$Q$19 *(2) -> 4 | B21: No | D21: Gland Indoor 20S BWL 4*1.5/2.5mm2 | G21: CAAC_042 | H21: 620 | I21: CMP | O21: 2 | P21: 35431 | Q21: 3.56 | R21: =$A21*Q21 -> 14.24 | S21: 0.3 | T21: =$A21*S21*$T$1 -> 1.2
A22: =$Q$19 *(2) -> 4 | B22: m | D22: Cable Marker 8 digit c/w Carrier Strip | G22: CAAC_091 | H22: 620 | I22: (__) | O22: 2 | P22: 38148 | Q22: 1.5 | R22: =$A22*Q22 -> 6 | S22: 0.08 | T22: =$A22*S22*$T$1 -> 0.32
A23: =$Q$19 *(10) -> 20 | B23: No | D23: Cable Lug 2.5 mm2 | G23: CAAC_005 | H23: 620 | I23: CTT | O23: 2 | P23: 34669 | Q23: 0.1 | R23: =$A23*Q23 -> 2 | S23: 0.02 | T23: =$A23*S23*$T$1 -> 0.4
A24: =$Q$19 *(1) -> 2 | B24: No | D24: Labour to Connect Up (FIX 3) | G24: LABO_003 | H24: 900 | I24: MISC | O24: 3 | P24: 34790 | R24: =$A24*Q24 -> 0 | S24: 0.5 | T24: =$A24*S24*$T$1 -> 1
C25: << ==== TOTAL UNITS | R25: =$A25*Q25 -> 0 | T25: =$A25*S25*$T$1 -> 0
A26: d> | B26: =(R25+T25) -> 0 | D26: Sell_A | E26: =IF($B19=0,0,ROUND(ROUND(($R26*$S$2+($T26*$T$2))/$B19, 2)*$C$2,2)) -> 69.14 | F26: =ROUND($B19*$E26,2) -> 138.28 | K26: ITEM | L26: ITEM | R26: =SUM(R20:R25) -> 22.24 | T26: =SUM(T20:T25) -> 2.92
Q27: Multip
A28: 1 | B28: =Elec_Est!B3216 -> 4 | D28: 002# Connecting up of 7.5 kW 400Volt motor (Standard) | K28: RATE | L28: RATE | Q28: =B28/A28 -> 4 | R28: =IF($B28=0,0,IF($S$1="R",ROUND(R35/$B28,2),R35/$B28)) -> 13.92 | T28: =IF($B28=0,0,IF($S$1="R",ROUND(T35/$B28,2),T35/$B28)) -> 1.56
D29: Based on: Star/Delta Starting
A30: =$Q$28 *(2) -> 8 | B30: No | D30: Gland Indoor 20 BWL 4*4/6mm2 | G30: CAAC_040 | H30: 620 | I30: CMP | O30: 2 | P30: 35431 | Q30: 4.71 | R30: =$A30*Q30 -> 37.68 | S30: 0.35 | T30: =$A30*S30*$T$1 -> 2.8
A31: =$Q$28 *(2) -> 8 | B31: m | D31: Cable Marker 8 digit c/w Carrier Strip | G31: CAAC_091 | H31: 620 | I31: (__) | O31: 2 | P31: 38148 | Q31: 1.5 | R31: =$A31*Q31 -> 12 | S31: 0.08 | T31: =$A31*S31*$T$1 -> 0.64
A32: =$Q$28 *(10) -> 40 | B32: No | D32: Cable Lug 4.0 mm2 | G32: CAAC_006 | H32: 620 | I32: CTT | O32: 2 | P32: 34669 | Q32: 0.15 | R32: =$A32*Q32 -> 6 | S32: 0.02 | T32: =$A32*S32*$T$1 -> 0.8
A33: =$Q$28 *(1) -> 4 | B33: No | D33: Labour to Connect Up (FIX 3) | G33: LABO_003 | H33: 900 | I33: MISC | O33: 3 | P33: 34790 | R33: =$A33*Q33 -> 0 | S33: 0.5 | T33: =$A33*S33*$T$1 -> 2
C34: << ==== TOTAL UNITS | R34: =$A34*Q34 -> 0 | T34: =$A34*S34*$T$1 -> 0
A35: d> | B35: =(R34+T34) -> 0 | D35: Sell_A | E35: =IF($B28=0,0,ROUND(ROUND(($R35*$S$2+($T35*$T$2))/$B28, 2)*$C$2,2)) -> 76.62 | F35: =ROUND($B28*$E35,2) -> 306.48 | K35: ITEM | L35: ITEM | R35: =SUM(R29:R34) -> 55.68 | T35: =SUM(T29:T34) -> 6.24
Q36: Multip
A37: 1 | B37: =Elec_Est!B3217 -> 3 | D37: 003# Connecting up of 11.0 kW 400Volt motor (Standard) | K37: RATE | L37: RATE | Q37: =B37/A37 -> 3 | R37: =IF($B37=0,0,IF($S$1="R",ROUND(R44/$B37,2),R44/$B37)) -> 14.42 | T37: =IF($B37=0,0,IF($S$1="R",ROUND(T44/$B37,2),T44/$B37)) -> 1.66
D38: Based on: Star/Delta Starting
A39: =$Q$37 *(2) -> 6 | B39: No | D39: Gland Indoor 20 BWL 4*4/6mm2 | G39: CAAC_040 | H39: 620 | I39: CMP | O39: 2 | P39: 35431 | Q39: 4.71 | R39: =$A39*Q39 -> 28.26 | S39: 0.35 | T39: =$A39*S39*$T$1 -> 2.1
A40: =$Q$37 *(2) -> 6 | B40: m | D40: Cable Marker 8 digit c/w Carrier Strip | G40: CAAC_091 | H40: 620 | I40: (__) | O40: 2 | P40: 38148 | Q40: 1.5 | R40: =$A40*Q40 -> 9 | S40: 0.08 | T40: =$A40*S40*$T$1 -> 0.48
A41: =$Q$37 *(10) -> 30 | B41: No | D41: Cable Lug 6.0 mm2 | G41: CAAC_007 | H41: 620 | I41: CTT | O41: 2 | P41: 34669 | Q41: 0.2 | R41: =$A41*Q41 -> 6 | S41: 0.03 | T41: =$A41*S41*$T$1 -> 0.9
A42: =$Q$37 *(1) -> 3 | B42: No | D42: Labour to Connect Up (FIX 3) | G42: LABO_003 | H42: 900 | I42: MISC | O42: 3 | P42: 34790 | R42: =$A42*Q42 -> 0 | S42: 0.5 | T42: =$A42*S42*$T$1 -> 1.5
C43: << ==== TOTAL UNITS | R43: =$A43*Q43 -> 0 | T43: =$A43*S43*$T$1 -> 0
A44: d> | B44: =(R43+T43) -> 0 | D44: Sell_A | E44: =IF($B37=0,0,ROUND(ROUND(($R44*$S$2+($T44*$T$2))/$B37, 2)*$C$2,2)) -> 81 | F44: =ROUND($B37*$E44,2) -> 243 | K44: ITEM | L44: ITEM | R44: =SUM(R38:R43) -> 43.26 | T44: =SUM(T38:T43) -> 4.98
Q45: Multip
A46: 1 | B46: =Elec_Est!B3218 -> 16 | D46: 004# Connecting up of 3.0/4.0 kW 400Volt motor (VFD) | K46: RATE | L46: RATE | Q46: =B46/A46 -> 16 | R46: =IF($B46=0,0,IF($S$1="R",ROUND(R53/$B46,2),R53/$B46)) -> 5.56 | T46: =IF($B46=0,0,IF($S$1="R",ROUND(T53/$B46,2),T53/$B46)) -> 0.98
D47: Based on: VFD Starting
A48: =$Q$46 *(1) -> 16 | B48: No | D48: Gland Indoor 20S BWL 4*1.5/2.5mm2 | G48: CAAC_042 | H48: 620 | I48: CMP | O48: 2 | P48: 35431 | Q48: 3.56 | R48: =$A48*Q48 -> 56.96 | S48: 0.3 | T48: =$A48*S48*$T$1 -> 4.8
A49: =$Q$46 *(1) -> 16 | B49: m | D49: Cable Marker 8 digit c/w Carrier Strip | G49: CAAC_091 | H49: 620 | I49: (__) | O49: 2 | P49: 38148 | Q49: 1.5 | R49: =$A49*Q49 -> 24 | S49: 0.08 | T49: =$A49*S49*$T$1 -> 1.28
A50: =$Q$46 *(5) -> 80 | B50: No | D50: Cable Lug 2.5 mm2 | G50: CAAC_005 | H50: 620 | I50: CTT | O50: 2 | P50: 34669 | Q50: 0.1 | R50: =$A50*Q50 -> 8 | S50: 0.02 | T50: =$A50*S50*$T$1 -> 1.6
A51: =$Q$46 *(1) -> 16 | B51: No | D51: Labour to Connect Up (FIX 3) | G51: LABO_003 | H51: 900 | I51: MISC | O51: 3 | P51: 34790 | R51: =$A51*Q51 -> 0 | S51: 0.5 | T51: =$A51*S51*$T$1 -> 8
C52: << ==== TOTAL UNITS | R52: =$A52*Q52 -> 0 | T52: =$A52*S52*$T$1 -> 0
A53: d> | B53: =(R52+T52) -> 0 | D53: Sell_A | E53: =IF($B46=0,0,ROUND(ROUND(($R53*$S$2+($T53*$T$2))/$B46, 2)*$C$2,2)) -> 43.84 | F53: =ROUND($B46*$E53,2) -> 701.44 | K53: ITEM | L53: ITEM | R53: =SUM(R47:R52) -> 88.96 | T53: =SUM(T47:T52) -> 15.68
Q54: Multip
A55: 1 | B55: =Elec_Est!B3219 -> 8 | D55: 005# Connecting up of 7.5 kW 400Volt motor (VFD) | K55: RATE | L55: RATE | Q55: =B55/A55 -> 8 | R55: =IF($B55=0,0,IF($S$1="R",ROUND(R62/$B55,2),R62/$B55)) -> 6.96 | T55: =IF($B55=0,0,IF($S$1="R",ROUND(T62/$B55,2),T62/$B55)) -> 1.03
D56: Based on: VFD Starting
A57: =$Q$55 *(1) -> 8 | B57: No | D57: Gland Indoor 20 BWL 4*4/6mm2 | G57: CAAC_040 | H57: 620 | I57: CMP | O57: 2 | P57: 35431 | Q57: 4.71 | R57: =$A57*Q57 -> 37.68 | S57: 0.35 | T57: =$A57*S57*$T$1 -> 2.8
A58: =$Q$55 *(1) -> 8 | B58: m | D58: Cable Marker 8 digit c/w Carrier Strip | G58: CAAC_091 | H58: 620 | I58: (__) | O58: 2 | P58: 38148 | Q58: 1.5 | R58: =$A58*Q58 -> 12 | S58: 0.08 | T58: =$A58*S58*$T$1 -> 0.64
A59: =$Q$55 *(5) -> 40 | B59: No | D59: Cable Lug 4.0 mm2 | G59: CAAC_006 | H59: 620 | I59: CTT | O59: 2 | P59: 34669 | Q59: 0.15 | R59: =$A59*Q59 -> 6 | S59: 0.02 | T59: =$A59*S59*$T$1 -> 0.8
A60: =$Q$55 *(1) -> 8 | B60: No | D60: Labour to Connect Up (FIX 3) | G60: LABO_003 | H60: 900 | I60: MISC | O60: 3 | P60: 34790 | R60: =$A60*Q60 -> 0 | S60: 0.5 | T60: =$A60*S60*$T$1 -> 4
C61: << ==== TOTAL UNITS | R61: =$A61*Q61 -> 0 | T61: =$A61*S61*$T$1 -> 0
A62: d> | B62: =(R61+T61) -> 0 | D62: Sell_A | E62: =IF($B55=0,0,ROUND(ROUND(($R62*$S$2+($T62*$T$2))/$B55, 2)*$C$2,2)) -> 47.58 | F62: =ROUND($B55*$E62,2) -> 380.64 | K62: ITEM | L62: ITEM | R62: =SUM(R56:R61) -> 55.68 | T62: =SUM(T56:T61) -> 8.24
Q63: Multip
A64: 1 | B64: =Elec_Est!B3220 -> 16 | D64: 006# Connecting up of 11.0/18.0 kW 400Volt motor (VFD) | K64: RATE | L64: RATE | Q64: =B64/A64 -> 16 | R64: =IF($B64=0,0,IF($S$1="R",ROUND(R71/$B64,2),R71/$B64)) -> 10.66 | T64: =IF($B64=0,0,IF($S$1="R",ROUND(T71/$B64,2),T71/$B64)) -> 1.28
D65: Based on: VFD Starting
A66: =$Q$64 *(1) -> 16 | B66: No | D66: Gland Indoor 25 BWL 4*10/16mm2 | G66: CAAC_043 | H66: 620 | I66: CMP | O66: 2 | P66: 35431 | Q66: 7.66 | R66: =$A66*Q66 -> 122.56 | S66: 0.4 | T66: =$A66*S66*$T$1 -> 6.4
A67: =$Q$64 *(1) -> 16 | B67: m | D67: Cable Marker 8 digit c/w Carrier Strip | G67: CAAC_091 | H67: 620 | I67: (__) | O67: 2 | P67: 38148 | Q67: 1.5 | R67: =$A67*Q67 -> 24 | S67: 0.08 | T67: =$A67*S67*$T$1 -> 1.28
A68: =$Q$64 *(5) -> 80 | B68: No | D68: Cable Lug 16 mm2 | G68: CAAC_009 | H68: 620 | I68: CTT | O68: 2 | P68: 34669 | Q68: 0.3 | R68: =$A68*Q68 -> 24 | S68: 0.06 | T68: =$A68*S68*$T$1 -> 4.8
A69: =$Q$64 *(1) -> 16 | B69: No | D69: Labour to Connect Up (FIX 3) | G69: LABO_003 | H69: 900 | I69: MISC | O69: 3 | P69: 34790 | R69: =$A69*Q69 -> 0 | S69: 0.5 | T69: =$A69*S69*$T$1 -> 8
C70: << ==== TOTAL UNITS | R70: =$A70*Q70 -> 0 | T70: =$A70*S70*$T$1 -> 0
A71: d> | B71: =(R70+T70) -> 0 | D71: Sell_A | E71: =IF($B64=0,0,ROUND(ROUND(($R71*$S$2+($T71*$T$2))/$B64, 2)*$C$2,2)) -> 61.84 | F71: =ROUND($B64*$E71,2) -> 989.44 | K71: ITEM | L71: ITEM | R71: =SUM(R65:R70) -> 170.56 | T71: =SUM(T65:T70) -> 20.48
Q72: Multip
A73: 57 | B73: =Elec_Est!B3221 -> 0 | D73: 007# 200mm galvanised steel cable tray | K73: RATE | L73: RATE | Q73: =B73/A73 -> 0 | R73: =IF($B73=0,0,IF($S$1="R",ROUND(R82/$B73,2),R82/$B73)) -> 0 | T73: =IF($B73=0,0,IF($S$1="R",ROUND(T82/$B73,2),T82/$B73)) -> 0
D74: Based on:
A75: =$Q$359 *(57) -> 0 | B75: m | D75: Tray 200mm Galv. | E75: Ardic | F75: HDG | G75: TRGV_023 | H75: 650 | I75: (__) | O75: 1 | P75: 36897 | Q75: =ROUNDUP(5.77*1.145,2) -> 6.61 | R75: =$A75*Q75 -> 0 | S75: 0.3 | T75: =$A75*S75*$T$1 -> 0
A76: =$Q$359 *(ROUNDUP(57/3,0)) -> 0 | B76: m | D76: Tray Coupler Galv. | E76: Ardic | G76: TRGV_051 | H76: 650 | I76: (__) | O76: 1 | P76: 35705 | Q76: =ROUNDUP(0.22*2*1.145,2) -> 0.51 | R76: =$A76*Q76 -> 0 | T76: =$A76*S76*$T$1 -> 0
A77: =$Q$359 *(ROUNDUP(57/3*8,0)) -> 0 | B77: No | D77: Roofing Bolt | G77: CONS_031 | H77: 875 | I77: (__) | K77: 02-005 | O77: 1 | P77: 34669 | Q77: 0.07 | R77: =$A77*Q77 -> 0 | T77: =$A77*S77*$T$1 -> 0
A78: =$Q$359 *(ROUNDUP(57*2,0)) -> 0 | B78: No | D78: Wing Nut Hilti M6 | G78: EMAT_059 | H78: 501 | I78: HIL | J78: MKN-FM8 | K78: 04-002 | O78: 1 | P78: 36175 | Q78: 0.51 | R78: =$A78*Q78 -> 0 | T78: =$A78*S78*$T$1 -> 0
A79: =$Q$359 *(ROUNDUP(57*2,0)) -> 0 | B79: No | D79: Hex.Set Screws M6x20 | G79: EMAT_025 | H79: 501 | I79: (__) | K79: 05-002 | O79: 1 | Q79: 0.05 | R79: =$A79*Q79 -> 0 | T79: =$A79*S79*$T$1 -> 0
A80: =$Q$359 *(ROUNDUP(57/3,0)) -> 0 | B80: No | D80: Earth Strips Copper | G80: CONS_012 | H80: 875 | I80: (__) | K80: 01-011 | O80: 1 | P80: 34669 | Q80: 0.5 | R80: =$A80*Q80 -> 0 | S80: 0 | T80: =$A80*S80*$T$1 -> 0
C81: << ==== TOTAL UNITS | R81: =$A81*Q81 -> 0 | T81: =$A81*S81*$T$1 -> 0
A82: d> | B82: =(R81+T81) -> 0 | D82: Sell_A | E82: =IF($B73=0,0,ROUND(ROUND(($R82*$S$2+($T82*$T$2))/$B73, 2)*$C$2,2)) -> 0 | F82: =ROUND($B73*$E82,2) -> 0 | K82: ITEM | L82: ITEM | R82: =SUM(R74:R81) -> 0 | T82: =SUM(T74:T81) -> 0
Q83: Multip
A84: 137 | B84: =Elec_Est!B3222 -> 0 | D84: 008# Bracket for 200-300mm cable tray | K84: RATE | L84: RATE | Q84: =B84/A84 -> 0 | R84: =IF($B84=0,0,IF($S$1="R",ROUND(R95/$B84,2),R95/$B84)) -> 0 | T84: =IF($B84=0,0,IF($S$1="R",ROUND(T95/$B84,2),T95/$B84)) -> 0
D85: Based on: 1metres intervals as per specs
D86: Hanging below ceiling | R86: =$A86*Q86 -> 0 | T86: =$A86*S86*$T$1 -> 0
A87: =$Q$390*(ROUND(137*2,0)) -> 0 | B87: No | D87: Anchor 8mm Hilti HKD-SM8x30 | G87: CONS_003 | H87: 875 | I87: HIL | J87: HKD-SM8x30 | O87: 1 | P87: 36175 | Q87: =2.33 *(0.05) -> 0.1165 | R87: =$A87*Q87 -> 0 | T87: =$A87*S87*$T$1 -> 0
A88: =$Q$390*(ROUND(137*2,0)) -> 0 | B88: m | D88: Threaded Rod Galv. 8mm | E88: Ardic | G88: EMAT_043 | H88: 501 | O88: 1 | P88: 36175 | Q88: =ROUNDUP(0.96*1.145,2) -> 1.1 | R88: =$A88*Q88 -> 0 | T88: =$A88*S88*$T$1 -> 0
A89: =$Q$390*(ROUND(137*2,0)) -> 0 | B89: No | D89: Hilti Channel 40x20 Endcap MQZ-E21 | G89: EMAT_064 | H89: 501 | O89: 1 | Q89: 0.12 | R89: =$A89*Q89 -> 0 | T89: =$A89*S89*$T$1 -> 0
A90: =$Q$390*(ROUND(137*0.4,0)) -> 0 | B90: m | D90: Channel SHALLOW-Galv. Hilti MS-213M | E90: Ardic | G90: EMAT_020 | H90: 501 | I90: HIL | J90: MS-213m | O90: 1 | P90: 36175 | Q90: =ROUNDUP(1.45*1.145,2) -> 1.67 | R90: =$A90*Q90 -> 0 | T90: =$A90*S90*$T$1 -> 0
A91: =$Q$390*(ROUND(137,0)) -> 0 | B91: No | D91: Labour to manufacture brackets | G91: LABO_008 | H91: 501 | I91: MISC | O91: 3 | R91: =$A91*Q91 -> 0 | S91: 0.25 | T91: =$A91*S91*$T$1 -> 0 | U91: NoMat?
A92: =$Q$390*(ROUND(137*4,0)) -> 0 | B92: No | D92: Galv. Nut 8mm | G92: EMAT_022 | H92: 501 | O92: 1 | Q92: =2.33 *(0.03) -> 0.0699 | R92: =$A92*Q92 -> 0 | T92: =$A92*S92*$T$1 -> 0
A93: =$Q$390*(ROUND(137*4,0)) -> 0 | B93: No | D93: Tray Washers M8 | G93: EMAT_057 | H93: 501 | O93: 1 | Q93: =2.33 *(0.01) -> 0.0233 | R93: =$A93*Q93 -> 0 | T93: =$A93*S93*$T$1 -> 0
C94: << ==== TOTAL UNITS | R94: =$A94*Q94 -> 0 | T94: =$A94*S94*$T$1 -> 0
A95: d> | B95: =(R94+T94) -> 0 | D95: Sell_A | E95: =IF($B84=0,0,ROUND(ROUND(($R95*$S$2+($T95*$T$2))/$B84, 2)*$C$2,2)) -> 0 | F95: =ROUND($B84*$E95,2) -> 0 | K95: ITEM | L95: ITEM | R95: =SUM(R85:R94) -> 0 | T95: =SUM(T85:T94) -> 0
Q96: Multip
A97: 1 | B97: =Elec_Est!B3223 -> 3 | D97: 009# Energy Meter M-Bus | K97: RATE | L97: RATE | Q97: =B97/A97 -> 3 | R97: =IF($B97=0,0,IF($S$1="R",ROUND(R105/$B97,2),R105/$B97)) -> 226.8 | T97: =IF($B97=0,0,IF($S$1="R",ROUND(T105/$B97,2),T105/$B97)) -> 11.7
D98: Based on:
A99: =$Q$97 *(1) -> 3 | B99: m | D99: Conduit Galv. FLEX 20mm | G99: COGV_010 | H99: 690 | I99: BAR | J99: 20mm | O99: 1 | P99: 34669 | Q99: 1.86 | R99: =$A99*Q99 -> 5.58 | S99: 0.2 | T99: =$A99*S99*$T$1 -> 0.6
A100: =$Q$97 *(2) -> 6 | B100: m | D100: Conduit BRASS ADAP.FLEX 20mm | G100: COGV_006 | H100: 690 | I100: BAR | J100: 20mm | O100: 1 | P100: 34669 | Q100: 0.98 | R100: =$A100*Q100 -> 5.88 | T100: =$A100*S100*$T$1 -> 0
A101: =$Q$97 *(3+30+9+6) -> 144 | B101: m | D101: Conduit Galv. 20mm RATE | G101: COGV_011 | H101: 690 | I101: BAR | J101: 20mm | O101: 1 | P101: 34669 | Q101: 3.66 | R101: =$A101*Q101 -> 527.04 | S101: 0.2 | T101: =$A101*S101*$T$1 -> 28.8
A102: =$Q$97 *(55) -> 165 | B102: m | D102: M-bus Cab;le | F102: Guy | G102: CASP_083 | H102: 617 | I102: Lappkabel | J102: 0034703 UNITRONIC LiYCY | O102: 2 | P102: 38433 | Q102: 0.86 | R102: =$A102*Q102 -> 141.9 | S102: 0.03 | T102: =$A102*S102*$T$1 -> 4.95
...

Sheet Elec_Est
B1: CLIENT: | C1: =ML_Sum!$C1 -> 1 | D1: =ML_Sum!$D1 -> Eden Lesuire Group | F1: =ML_Sum!$F1 -> 0 | I1: 1 | J1: =ML_Sum!$J1 -> 1 | K1: =ML_Sum!$K1 -> 1 | L1: =ML_Sum!$L1 -> 1 | M1: =ML_Sum!$M1 -> 1 | N1: =ML_Sum!$N1 -> 1 | O1: =ML_Sum!$O1 -> 1 | Q1: =ML_Sum!$Q1 -> € | R1: R/Lab Cont | S1: =ML_Sum!$S1 -> R | T1: =ML_Sum!$T1 -> 1 | U1: =ML_Sum!W1 -> BOQ | V1: INCL | W1: MULT | X1: AREA | Y1: BOQ | Z1: TDWG | AA1: ACT | AB1: DIFF
B2: PROJECT: | C2: =ML_Sum!$C2 -> 1 | D2: =ML_Sum!$D2 -> Intercontinental - Plant Retrofit | F2: =ML_Sum!$F2 -> Electrical | I2: 2 | J2: =ML_Sum!$J2 -> 1 | K2: =ML_Sum!$K2 -> 1 | L2: =ML_Sum!$L2 -> 1 | M2: =ML_Sum!$M2 -> 1 | N2: =ML_Sum!$N2 -> 1 | O2: =ML_Sum!$O2 -> 1 | Q2: =ML_Sum!$Q2 -> 0 | R2: mu_A | S2: =ML_Sum!$S2 -> 1.35 | T2: =ML_Sum!$T2 -> 37.071
B3: JOB DESC: | C3: =ML_Sum!$C3 -> 1 | D3: =ML_Sum!$D3 -> Retrofitting works for the HVAC plant at Intercontinental Revision A | F3: =ML_Sum!$F3 -> Technician | I3: 3 | J3: =ML_Sum!$J3 -> 1 | K3: =ML_Sum!$K3 -> 1 | L3: =ML_Sum!$L3 -> 1 | M3: =ML_Sum!$M3 -> 1 | N3: =ML_Sum!$N3 -> 1 | O3: =ML_Sum!$O3 -> 1 | Q3: =ML_Sum!$Q3 -> 0 | R3: mu_B | S3: =ML_Sum!$S3 -> 1.35 | T3: =ML_Sum!$T3 -> 45.522
B4: QUOTE No: | C4: =ML_Sum!$C4 -> 1 | D4: =ML_Sum!$D4 -> ELM25-0465A | F4: =ML_Sum!$F4 -> Engineer (Man Hours) | I4: 4 | J4: =ML_Sum!$J4 -> 1 | K4: =ML_Sum!$K4 -> 1 | L4: =ML_Sum!$L4 -> 1 | M4: =ML_Sum!$M4 -> 1 | N4: =ML_Sum!$N4 -> 1 | O4: =ML_Sum!$O4 -> 1 | Q4: =ML_Sum!$Q4 -> 0 | R4: mu_C | S4: =ML_Sum!$S4 -> 1.35 | T4: =ML_Sum!$T4 -> 40.5
B5: CLIENTs REF: | C5: =ML_Sum!$C5 -> 1 | D5: =ML_Sum!$D5 -> Tender | F5: =ML_Sum!$F5 -> Megaline | I5: 5 | J5: =ML_Sum!$J5 -> 1 | K5: =ML_Sum!$K5 -> 1 | L5: =ML_Sum!$L5 -> 1 | M5: =ML_Sum!$M5 -> 1 | N5: =ML_Sum!$N5 -> 1 | O5: =ML_Sum!$O5 -> 1 | Q5: =ML_Sum!$Q5 -> 0 | R5: mu_D | S5: =ML_Sum!$S5 -> 1 | T5: =ML_Sum!$T5 -> 37.071
B6: VAT/DUTIES: | C6: =ML_Sum!$C6 -> 1 | D6: =ML_Sum!$D6 -> VAT EXCL. | F6: =ML_Sum!$F6 -> 0 | I6: 6 | J6: =ML_Sum!$J6 -> 1 | K6: =ML_Sum!$K6 -> 1 | L6: =ML_Sum!$L6 -> 1 | M6: =ML_Sum!$M6 -> 1 | N6: =ML_Sum!$N6 -> 1 | O6: =ML_Sum!$O6 -> 1 | Q6: =ML_Sum!$Q6 -> 0 | R6: mu_E | S6: =ML_Sum!$S6 -> 0 | T6: =ML_Sum!$T6 -> 0
B7: SAVED ON: | C7: =ML_Sum!$C7 -> 1 | D7: 39364 | F7: =ML_Sum!$F7 -> 0 | I7: 7 | J7: =ML_Sum!$J7 -> 1 | K7: =ML_Sum!$K7 -> 1 | L7: =ML_Sum!$L7 -> 1 | M7: =ML_Sum!$M7 -> 1 | N7: =ML_Sum!$N7 -> 1 | O7: =ML_Sum!$O7 -> 0 | Q7: =ML_Sum!$Q7 -> 0 | R7: mu_F | S7: =ML_Sum!$S7 -> 0 | T7: =ML_Sum!$T7 -> 0
B8: ESTIMATOR: | C8: =ML_Sum!$C8 -> 1 | D8: =ML_Sum!$D8 -> T.Sammut | F8: =ML_Sum!$F8 -> 0 | I8: 8 | J8: =ML_Sum!$J8 -> 1 | K8: =ML_Sum!$K8 -> 1 | L8: =ML_Sum!$L8 -> 1 | M8: =ML_Sum!$M8 -> 1 | N8: =ML_Sum!$N8 -> 1 | O8: =ML_Sum!$O8 -> 0 | Q8: =ML_Sum!$Q8 -> 0 | R8: mu_G | S8: =ML_Sum!$S8 -> 0 | T8: =ML_Sum!$T8 -> 0
B9: LABOUR RATE: | C9: =ML_Sum!$C9 -> 1 | D9: =ML_Sum!$D9 -> 27.46 | F9: =ML_Sum!$F9 -> 0 | I9: 9 | J9: =ML_Sum!$J9 -> 1 | K9: =ML_Sum!$K9 -> 1 | L9: =ML_Sum!$L9 -> 1 | M9: =ML_Sum!$M9 -> 1 | N9: =ML_Sum!$N9 -> 1 | O9: =ML_Sum!$O9 -> 0 | Q9: =ML_Sum!$Q9 -> 0 | R9: mu_H | S9: =ML_Sum!$S9 -> 0 | T9: =ML_Sum!$T9 -> 0
C10: =ML_Sum!$C10 -> 1 | F10: =ML_Sum!$F10 -> 0 | I10: 10 | J10: =ML_Sum!$J10 -> 1 | K10: =ML_Sum!$K10 -> 1 | L10: =ML_Sum!$L10 -> 1 | M10: =ML_Sum!$M10 -> 1 | N10: =ML_Sum!$N10 -> 1 | O10: =ML_Sum!$O10 -> 1 | Q10: =ML_Sum!$Q10 -> 0 | R10: mu_I | S10: =ML_Sum!$S10 -> 0 | T10: =ML_Sum!$T10 -> 0
C11: =ML_Sum!$C11 -> 1 | F11: =ML_Sum!$F11 -> 0 | Q11: =ML_Sum!$Q11 -> 0 | R11: mu_J | S11: =ML_Sum!$S11 -> 0 | T11: =ML_Sum!$T11 -> 0
C12: =ML_Sum!$C12 -> 1 | F12: =ML_Sum!$F12 -> 0 | Q12: =ML_Sum!$Q12 -> 0 | R12: MIXED | S12: =ML_Sum!$S12 -> MAT MU | T12: =ML_Sum!$T12 -> LAB RATE
G13: ISELL | H13: C_CODE | I13: MAKE | J13: PART_NO | K13: MARKUP | L13: TYPE | M13: LIST_P | N13: P_FACT | O13: FIX | P13: DATE | Q13: %Dsct in BOQ | R13: MU TYPE | S13: MAT MU | T13: LAB RATE | AM13: Tot Mat Cost | AN13: Unit Lab phr. | AO13: Tot Lab phr. | AP13: < for ELM / MEE
K14: TB
C15: t
D16: CHILLER DISMANTLING
K18: TB
C19: t
D20: CHILLERS - EDEN ARENA
E22: Sell Rate | F22: Sell Total | K22: IB | AG22: U_M_Sell | AH22: T_M_Sell | AI22: U_L_Sell | AJ22: T_L_Sell | AK22: Total_Sell | AM22: T_M_Cost | AN22: T_L_Phr | AO22: Mat/Lab=1
A23: 1 | B23: LS | D23: Item: 3 | E23: =IF(AND($A23=0,$A$1="DIF"),0, ROUND(ROUND(($R27*$S$2+($T27*$T$2))/A23,2)*$C$2,2)) -> 0 | F23: =ROUND($A23*$E23,2) -> 0 | G23: ISELL | K23: mu_A | L23: ITEM | Q23: Included in Electrical - Note by Megaline | T23: =IF(AND($R27=0,$T27=0),"0.00","mu :" & ROUND($F23/$C$2/($R27+$T27*$D$9),2)) -> 0.00 | AG23: =IF($E23=0,0,ROUND($R27*$S$2*$C$2/$A23,2)) -> 0 | AH23: =$AG23*$A23 -> 0 | AI23: =$E23-$AG23 -> 0 | AJ23: =$A23*$AI23 -> 0 | AK23: =ROUND(($AG23+$AI23)*$A23,2) -> 0 | AM23: =ROUND(R27,2) -> 0 | AN23: =ROUND(T27,2) -> 0 | AO23: =ROUND(AM23+AN23,2)*A23 -> 0
D24: Allow for disconnection of all existing power, control and piping connections, draining down of existing chillers and making safe including dismantling and removal of existing piping from adjacent isolating valves. To include for disposal of chillers and refrigerant gas in accordance with all current legislation.
A25: 1 | B25: LS | D25: Subcontracting Works (Specify Contractor Name) | F25: Megaline | G25: SUBC_007 | H25: 960 | I25: MISC | O25: 4 | P25: 38594 | R25: =$A25*Q25 -> 0 | T25: =$A25*S25*$T$1 -> 0
R26: =$A26*Q26 -> 0 | T26: =$A26*S26*$T$1 -> 0
A27: d> | B27: =(R26+T26) -> 0 | G27: ICOST | K27: mu_A | L27: ITEM | R27: =SUM(R24:R26) -> 0 | T27: =SUM(T24:T26) -> 0
E28: Sell Rate | F28: Sell Total | K28: IB | AG28: U_M_Sell | AH28: T_M_Sell | AI28: U_L_Sell | AJ28: T_L_Sell | AK28: Total_Sell | AM28: T_M_Cost | AN28: T_L_Phr | AO28: Mat/Lab=1
A29: 1 | B29: LS | D29: Item: 4 | E29: =IF(AND($A29=0,$A$1="DIF"),0, ROUND(ROUND(($R33*$S$2+($T33*$T$2))/A29,2)*$C$2,2)) -> 0 | F29: =ROUND($A29*$E29,2) -> 0 | G29: ISELL | K29: mu_A | L29: ITEM | Q29: Included in Electrical - Note by Megaline | T29: =IF(AND($R33=0,$T33=0),"0.00","mu :" & ROUND($F29/$C$2/($R33+$T33*$D$9),2)) -> 0.00 | AG29: =IF($E29=0,0,ROUND($R33*$S$2*$C$2/$A29,2)) -> 0 | AH29: =$AG29*$A29 -> 0 | AI29: =$E29-$AG29 -> 0 | AJ29: =$A29*$AI29 -> 0 | AK29: =ROUND(($AG29+$AI29)*$A29,2) -> 0 | AM29: =ROUND(R33,2) -> 0 | AN29: =ROUND(T33,2) -> 0 | AO29: =ROUND(AM29+AN29,2)*A29 -> 0
D30: Allow for dismantling and carting away all existing power, cable containment, control and piping services in plantroom at Level 2 and all piping, insulation and brackets between level 2 and level 4 plantrooms
A31: 1 | B31: LS | D31: Subcontracting Works (Specify Contractor Name) | F31: Megaline | G31: SUBC_007 | H31: 960 | I31: MISC | O31: 4 | P31: 38594 | R31: =$A31*Q31 -> 0 | T31: =$A31*S31*$T$1 -> 0
R32: =$A32*Q32 -> 0 | T32: =$A32*S32*$T$1 -> 0
A33: d> | B33: =(R32+T32) -> 0 | G33: ICOST | K33: mu_A | L33: ITEM | R33: =SUM(R30:R32) -> 0 | T33: =SUM(T30:T32) -> 0
A34: SB
B36: =$F36/$C$2-($R36*$S$2+$T36*$T$2) -> 0 | D36: PAGE: | F36: =SUMIF($L27:$L34,"ITEM",F27:F34) -> 0 | L36: PAGE | R36: =SUMIF($L27:$L34,"ITEM",R27:R34) -> 0 | T36: =SUMIF($L27:$L34,"ITEM",T27:T34) -> 0
B37: Discy: | F37: PAGE SELL | R37: PAGE MAT | T37: PAGE LAB
K40: TB
C41: t
D42: CHILLERS - NEW INSTALLATION
K44: TB
C45: t
D46: Take delivery at site inside Car Park of Trane chillers procured by client, hoist into place, install and set to work all systems listed below and as described in the specifications.
K48: TB
C49: t
D50: CHILLERS - HOTEL
E52: Sell Rate | F52: Sell Total | K52: IB | R52: Installation for flow switch | AG52: U_M_Sell | AH52: T_M_Sell | AI52: U_L_Sell | AJ52: T_L_Sell | AK52: Total_Sell | AM52: T_M_Cost | AN52: T_L_Phr | AO52: Mat/Lab=1
A53: 3 | B53: No. | D53: Item: 1 | E53: =IF(AND($A53=0,$A$1="DIF"),0,ROUND(ROUND(SUMIF($L55:$L77,"SUBI",$E55:$E77)/$A53,2)*$C$12,2)) -> 777.51 | F53: =ROUND($A53*$E53,2) -> 2332.53 | G53: ISELL | L53: ITEM | Q53: READY | R53: =D69 -> Connecting up of chiller included in electrical BOQ | T53: =IF(AND($R83=0,$T83=0),"0.00","mu :" & ROUND($F53/$C$12/($R83+$T83*$D$9),2)) -> mu :1.35 | AG53: =IF(A53=0,0,ROUND(SUM(AG55:AG83)/A53,2)) -> 384.55 | AH53: =$AG53*$A53 -> 1153.65 | AI53: =$E53-$AG53 -> 392.96 | AJ53: =$A53*$AI53 -> 1178.88 | AK53: =ROUND(($AG53+$AI53)*$A53,2) -> 2332.53 | AM53: =ROUND(R83,2) -> 854.57 | AN53: =ROUND(T83,2) -> 31.8 | AO53: =ROUND(AM53+AN53,2)*A53 -> 2659.11
D54: Install only Screw type reversible chillers ref. C-1, C-2 and C-3 inclusive of flexible bellows, AVM's, flow switches, controls, etc. as specified.
E55: =F53/$C$12-SUMIF($L52:$L83,"SUBI",$E52:$E83) -> 0.01 | F55: Discrepancy
D56: =$F$2 -> Electrical | E56: =ROUND(($R71*$S$2 + ($T71*$T$2)), 2) -> 2332.52 | F56: =$E56*$C$12 -> 2332.52 | K56: mu_A | L56: SUBI
B57: >>> mu_A material here >>> | D57: Flow switch installation | R57: =$A57*Q57 -> 0 | T57: =$A57*S57*$T$1 -> 0
A58: =3 *(2) -> 6 | B58: m | D58: Conduit Galv. FLEX 20mm | G58: COGV_010 | H58: 690 | I58: BAR | J58: 20mm | O58: 1 | P58: 34669 | Q58: 1.86 | R58: =$A58*Q58 -> 11.16 | S58: 0.2 | T58: =$A58*S58*$T$1 -> 1.2
A59: =3 *(4) -> 12 | B59: m | D59: Conduit BRASS ADAP.FLEX 20mm | G59: COGV_006 | H59: 690 | I59: BAR | J59: 20mm | O59: 1 | P59: 34669 | Q59: 0.98 | R59: =$A59*Q59 -> 11.76 | T59: =$A59*S59*$T$1 -> 0
A60: =3 *(10) -> 30 | B60: m | D60: Conduit Galv. 20mm RATE | G60: COGV_011 | H60: 690 | I60: BAR | J60: 20mm | O60: 1 | P60: 34669 | Q60: 3.66 | R60: =$A60*Q60 -> 109.8 | S60: 0.2 | T60: =$A60*S60*$T$1 -> 6
A61: =3 *(50) -> 150 | B61: m | D61: Indoor Screened 3c Cable 0.75sqmm | F61: Batt Cables | G61: CASP_083 | H61: 617 | I61: Lappkabel | J61: 0034703 UNITRONIC LiYCY | O61: 2 | P61: 38433 | Q61: 1.4525 | R61: =$A61*Q61 -> 217.875 | S61: 0.03 | T61: =$A61*S61*$T$1 -> 4.5
A62: =3 *(1) -> 3 | B62: No | D62: Labour to connect Mech Equip (FIX 3) | F62: Flow switch | G62: LABO_009 | H62: 900 | I62: MISC | O62: 1 | R62: =$A62*Q62 -> 0 | S62: 0.25 | T62: =$A62*S62*$T$1 -> 0.75
B63: >>> mu_A material here >>> | D63: Pump Chiller interlocks | R63: =$A63*Q63 -> 0 | T63: =$A63*S63*$T$1 -> 0
A64: =3 *(2) -> 6 | B64: m | D64: Conduit Galv. FLEX 20mm | G64: COGV_010 | H64: 690 | I64: BAR | J64: 20mm | O64: 1 | P64: 34669 | Q64: 1.86 | R64: =$A64*Q64 -> 11.16 | S64: 0.2 | T64: =$A64*S64*$T$1 -> 1.2
A65: =3 *(4) -> 12 | B65: m | D65: Conduit BRASS ADAP.FLEX 20mm | G65: COGV_006 | H65: 690 | I65: BAR | J65: 20mm | O65: 1 | P65: 34669 | Q65: 0.98 | R65: =$A65*Q65 -> 11.76 | T65: =$A65*S65*$T$1 -> 0
A66: =(2+5+10+3)*3 -> 60 | B66: m | D66: Conduit Galv. 20mm RATE | G66: COGV_011 | H66: 690 | I66: BAR | J66: 20mm | O66: 1 | P66: 34669 | Q66: 3.66 | R66: =$A66*Q66 -> 219.6 | S66: 0.2 | T66: =$A66*S66*$T$1 -> 12
A67: =3 *(60) -> 180 | B67: m | D67: Indoor Screened 3c Cable 0.75sqmm | F67: Batt Cables | G67: CASP_083 | H67: 617 | I67: Lappkabel | J67: 0034703 UNITRONIC LiYCY | O67: 2 | P67: 38433 | Q67: 1.4525 | R67: =$A67*Q67 -> 261.45 | S67: 0.03 | T67: =$A67*S67*$T$1 -> 5.4
A68: =3 *(1) -> 3 | B68: No | D68: Labour to connect Mech Equip (FIX 3) | G68: LABO_009 | H68: 900 | I68: MISC | O68: 1 | R68: =$A68*Q68 -> 0 | S68: 0.25 | T68: =$A68*S68*$T$1 -> 0.75
D69: Connecting up of chiller included in electrical BOQ
R70: =$A70*Q70 -> 0 | T70: =$A70*S70*$T$1 -> 0
A71: d> | B71: =(R70+T70) -> 0 | K71: mu_A | L71: SUBI | R71: =SUM(R56:R70) -> 854.565 | T71: =SUM(T56:T70) -> 31.8 | AG71: =ROUND($R71*$S$2,2) -> 1153.66
D72: =$F$3 -> Technician | E72: =ROUND(($R76*$S$3 + ($T76*$T$3)), 2) -> 0 | F72: =$E72*$C$12 -> 0 | K72: mu_B | L72: SUBI
B73: >>> mu_B material here >>> | R73: =$A73*Q73 -> 0 | T73: =$A73*S73*$T$1 -> 0
R74: =$A74*Q74 -> 0 | T74: =$A74*S74*$T$1 -> 0
R75: =$A75*Q75 -> 0 | T75: =$A75*S75*$T$1 -> 0
A76: d> | B76: =(R75+T75) -> 0 | K76: mu_B | L76: SUBI | R76: =SUM(R72:R75) -> 0 | T76: =SUM(T72:T75) -> 0 | AG76: =ROUND($R76*$S$3,2) -> 0
D77: =$F$4 -> Engineer (Man Hours) | E77: =ROUND(($R81*$S$4 + ($T81*$T$4)), 2) -> 0 | F77: =$F53-SUMIF($L55:$P74,"SUBI",$F55:$F74) -> 0.01 | K77: mu_C | L77: SUBI
B78: >>> mu_C material here >>> | R78: =$A78*Q78 -> 0 | T78: =$A78*S78*$T$1 -> 0
R79: =$A79*Q79 -> 0 | T79: =$A79*S79*$T$1 -> 0
R80: =$A80*Q80 -> 0 | T80: =$A80*S80*$T$1 -> 0
A81: d> | B81: =(R80+T80) -> 0 | K81: mu_C | L81: SUBI | R81: =SUM(R77:R80) -> 0 | T81: =SUM(T77:T80) -> 0 | AG81: =ROUND($R81*$S$4,2) -> 0
G83: ICOST | L83: ITEM | R83: =SUMIF($L54:$L82,"SUBI",R54:R82) -> 854.565 | T83: =SUMIF($L54:$L82,"SUBI",T54:T82) -> 31.8
K84: TB
C85: t | D85: Item: 5.0
D86: Energy Meter with M-Bus output
E88: Sell Rate | F88: Sell Total | K88: IB | AG88: U_M_Sell | AH88: T_M_Sell | AI88: U_L_Sell | AJ88: T_L_Sell | AK88: Total_Sell | AM88: T_M_Cost | AN88: T_L_Phr | AO88: Mat/Lab=1
A89: 3 | B89: No. | D89: Item: 5.0a. | E89: =IF(AND($A89=0,$A$1="DIF"),0, ROUND(ROUND(SUMIF($L91:$L97,"SUBI",$E91:$E97)/$A89,2)*$C$12,2)) -> 3991.72 | F89: =ROUND($A89*$E89,2) -> 11975.16 | G89: ISELL | L89: ITEM | Q89: READY | R89: Supply of meter complete with wiring to hydronic controller | T89: =IF(AND($R102=0,$T102=0),"0.00","mu :" & ROUND($F89/$C$12/($R102+$T102*$D$9),2)) -> mu :1.35 | AG89: =IF(A89=0,0,ROUND(SUM(AG91:AG102)/A89,2)) -> 3946.2 | AH89: =$AG89*$A89 -> 11838.6 | AI89: =$E89-$AG89 -> 45.52 | AJ89: =$A89*$AI89 -> 136.56 | AK89: =ROUND(($AG89+$AI89)*$A89,2) -> 11975.16 | AM89: =ROUND(R102,2) -> 8769.33 | AN89: =ROUND(T102,2) -> 3 | AO89: =ROUND(AM89+AN89,2)*A89 -> 26316.99
D90: DN150 | K90: n
E91: =F89/$C$12-SUMIF($L88:$L102,"SUBI",$E88:$E102) -> 0 | F91: Discrepancy
D92: =$F$2 -> Electrical | E92: =ROUND(($R96*$S$2 + ($T96*$T$2)), 2) -> 0 | F92: =$E92*$C$12 -> 0 | K92: mu_A | L92: SUBI | Q92: Wiring Included in BMS
C93: h | D93: =CELL("Address",Elec_Rates!D$97) -> [E25_0465_IH_Retro_Elec4Mech_Est_Rev_A.xlsx]Elec_Rates!$D$97 | G93: RATE_AAA
A94: 0 | B94: 1 | C94: =$A94*$B94 -> 0 | D94: =Elec_Rates!$D$97 -> 009# Energy Meter M-Bus | F94: Local Rate | G94: RTLO_001 | Q94: =$B94*Elec_Rates!$R$97 -> 226.8 | R94: =$A94*Q94 -> 0 | S94: =$B94*Elec_Rates!$T$97 -> 11.7 | T94: =$A94*S94 -> 0
R95: =$A95*Q95 -> 0 | T95: =$A95*S95*$T$1 -> 0
A96: d> | B96: =(R95+T95) -> 0 | K96: mu_A | L96: SUBI | R96: =SUM(R92:R95) -> 0 | T96: =SUM(T92:T95) -> 0 | AG96: =ROUND($R96*$S$2,2) -> 0
D97: =$F$3 -> Technician | E97: =ROUND(($R100*$S$3 + ($T100*$T$3)), 2) -> 11975.16 | F97: =$F89-SUMIF($L91:$P94,"SUBI",$F91:$F94) -> 11975.16 | K97: mu_B | L97: SUBI
A98: 3 | B98: No | D98: BMS EQUIPMENT | E98: Energy Meter | F98: Raymond - 11.09.2025 | G98: BMSE_001 | H98: 512 | I98: (__) | O98: 3 | Q98: 2923.11 | R98: =$A98*Q98 -> 8769.33 | S98: 1 | T98: =$A98*S98*$T$1 -> 3
R99: =$A99*Q99 -> 0 | T99: =$A99*S99*$T$1 -> 0
A100: d> | B100: =(R99+T99) -> 0 | K100: mu_B | L100: SUBI | R100: =SUM(R97:R99) -> 8769.33 | T100: =SUM(T97:T99) -> 3 | AG100: =ROUND($R100*$S$3,2) -> 11838.6
G102: ICOST | L102: ITEM | R102: =SUMIF($L90:$L101,"SUBI",R90:R101) -> 8769.33 | T102: =SUMIF($L90:$L101,"SUBI",T90:T101) -> 3
K103: TB
C104: t | D104: Item: 6.0
D105: Motorised Valve
E107: Sell Rate | F107: Sell Total | K107: IB | AG107: U_M_Sell | AH107: T_M_Sell | AI107: U_L_Sell | AJ107: T_L_Sell | AK107: Total_Sell | AM107: T_M_Cost | AN107: T_L_Phr | AO107: Mat/Lab=1
A108: 3 | B108: No. | D108: Item: 6.0a. | E108: =IF(AND($A108=0,$A$1="DIF"),0, ROUND(ROUND(SUMIF($L110:$L116,"SUBI",$E110:$E116)/$A108,2)*$C$12,2)) -> 1220.98 | F108: =ROUND($A108*$E108,2) -> 3662.94 | G108: ISELL | L108: ITEM | Q108: READY | R108: Supply of valve complete with wiring to hydronic controller | T108: =IF(AND($R121=0,$T121=0),"0.00","mu :" & ROUND($F108/$C$12/($R121+$T121*$D$9),2)) -> mu :1.35 | AG108: =IF(A108=0,0,ROUND(SUM(AG110:AG121)/A108,2)) -> 1198.22 | AH108: =$AG108*$A108 -> 3594.66 | AI108: =$E108-$AG108 -> 22.76 | AJ108: =$A108*$AI108 -> 68.28 | AK108: =ROUND(($AG108+$AI108)*$A108,2) -> 3662.94 | AM108: =ROUND(R121,2) -> 2662.71 | AN108: =ROUND(T121,2) -> 1.5 | AO108: =ROUND(AM108+AN108,2)*A108 -> 7992.63
D109: DN150 | K109: n
E110: =F108/$C$12-SUMIF($L107:$L121,"SUBI",$E107:$E121) -> 0 | F110: Discrepancy
D111: =$F$2 -> Electrical | E111: =ROUND(($R115*$S$2 + ($T115*$T$2)), 2) -> 0 | F111: =$E111*$C$12 -> 0 | K111: mu_A | L111: SUBI | Q111: Wiring Included in BMS
C112: h | D112: =CELL("Address",Elec_Rates!D$107) -> [E25_0465_IH_Retro_Elec4Mech_Est_Rev_A.xlsx]Elec_Rates!$D$107 | G112: RATE_AAA
...

Sheet Chillers_Dismantling_BOQ
A1: BILL OF QUANTITIES
A2: CHILLERS
A3: DISMANTLING
A5: Item | C5: Qty | D5: Unit | E5: Rate in € | F5: Total
A7: T | B7: Dismantle and cart away all systems listed below and as described in the specifications.
A9: T | B9: CHILLERS - HOTEL
A11: 1 | B11: Screw type chillers ref. C-1, C-2 and C-3 inclusive of flow switches, controls, etc. as specified. | C11: 3 | D11: No. | F11: =E11*C11 -> 0
A14: T | B14: CHILLERS - EDEN ARENA
A16: =A11+1 -> 2 | B16: Screw type chillers ref. C-4 inclusive of flow switches, controls, etc. as specified. | C16: 1 | D16: No. | F16: =E16*C16 -> 0
A19: =A16+1 -> 3 | B19: Allow for disconnection of all existing power, control and piping connections, draining down of existing chillers and making safe including dismantling and removal of existing piping from adjacent isolating valves. To include for disposal of chillers and refrigerant gas in accordance with all current legislation. | C19: 1 | D19: LS | E19: =Elec_Est!Q23 -> Included in Electrical - Note by Megaline | G19: Megaline
A21: =A19+1 -> 4 | B21: Allow for dismantling and carting away all existing power, cable containment, control and piping services in plantroom at Level 2 and all piping, insulation and brackets between level 2 and level 4 plantrooms | C21: 1 | D21: LS | E21: =Elec_Est!Q29 -> Included in Electrical - Note by Megaline | G21: Megaline
B22: NB Chiller power cables to be retained and reused
A51: S | B51: Total carried forward to summary page | F51: =SUM(F11:F49) -> 0

Sheet Chillers_New_BOQ
A1: BILL OF QUANTITIES
A2: CHILLERS
A3: NEW INSTALLATION
A5: Item | B5: Description | D5: Qty | E5: Unit | F5: Rate in € | G5: Total
C7: Take delivery at site inside Car Park of Trane chillers procured by client, hoist into place, install and set to work all systems listed below and as described in the specifications.
C9: CHILLERS - HOTEL
A11: 1 | C11: Install only Screw type reversible chillers ref. C-1, C-2 and C-3 inclusive of flexible bellows, AVM's, flow switches, controls, etc. as specified. | D11: 3 | E11: No. | F11: =Elec_Est!E53 -> 777.51 | G11: =F11*D11 -> 2332.53
A14: =A11+1 -> 2 | C14: Allow for assisting factory-trained employee of the manufacturer to carry out all start up and commissioning of all chillers. | D14: 1 | E14: LS | G14: =F14*D14 -> 0
C17: CHILLED WATER SIDE
A19: =A14+1 -> 3 | C19: Black steel piping to chilled water headers, complete with insulation, brackets, etc.
B21: a. | C21: 6" dia. | D21: =5*2*3 -> 30 | E21: m | G21: =F21*D21 -> 0
A24: =A19+1 -> 4 | C24: Butterfly valves with insulation
B26: a. | C26: DN150 | D26: =4*3 -> 12 | E26: No. | G26: =F26*D26 -> 0
A29: =A24+1 -> 5 | C29: Energy Meter with M-Bus output
B31: a. | C31: DN150 | D31: 3 | E31: No. | F31: =Elec_Est!E89 -> 3991.72 | G31: =F31*D31 -> 11975.16
A34: =A29+1 -> 6 | C34: Motorised Valve
B36: a. | C36: DN150 | D36: 3 | E36: No. | F36: =Elec_Est!E108 -> 1220.98 | G36: =F36*D36 -> 3662.94
A39: =A34+1 -> 7 | C39: Pressure Independent Flow Limiting Valve
B41: a. | C41: DN150 | D41: 3 | E41: No. | G41: =F41*D41 -> 0
A44: =A39+1 -> 8 | C44: Commissioning valves with insulation
B46: a. | C46: DN150 | D46: 3 | E46: No. | G46: =F46*D46 -> 0
C51: Total carried forward to summary page | G51: =SUM(G7:G49) -> 17970.63
A57: Item | B57: Description | D57: Qty | E57: Unit | F57: Rate in € | G57: Total
A59: =A44+1 -> 9 | C59: 3- way motorised valve modulating 0-10V
B61: a. | C61: DN150 | D61: =3*2 -> 6 | E61: No. | F61: =Elec_Est!E127 -> 2368.98 | G61: =F61*D61 -> 14213.88
A64: =A59+1 -> 10 | C64: Flow switch | D64: 3 | E64: No. | F64: =Elec_Est!E142 -> 129.4 | G64: =F64*D64 -> 388.2
A67: =A64+1 -> 11 | C67: Install only temperature sensors (free issued by Trane) | D67: =2*3 -> 6 | E67: No. | F67: =Elec_Est!E156 -> 22.76 | G67: =F67*D67 -> 136.56
A70: =A67+1 -> 12 | C70: Pressure gauges c/w siphon and cock | D70: =2*3 -> 6 | E70: No. | G70: =F70*D70 -> 0
A73: =A70+1 -> 13 | C73: Thermometers | D73: =2*3 -> 6 | E73: No. | G73: =F73*D73 -> 0
A76: =A73+1 -> 14 | C76: Drain cocks | D76: 3 | E76: No. | G76: =F76*D76 -> 0
A79: =A76+1 -> 15 | C79: Chilled water circulating pumps, complete with anti-vibration mountings, differential pressure switch connected to BMS, and pipe flexible connections, etc. as specified.
B81: a. | C81: P-201 | D81: 1 | E81: No. | F81: =Elec_Est!E174 -> 76.62 | G81: =F81*D81 -> 76.62
B83: b. | C83: P-202 | D83: 1 | E83: No. | F83: =Elec_Est!E195 -> 76.62 | G83: =F83*D83 -> 76.62
B85: c. | C85: P-203 | D85: 1 | E85: No. | F85: =Elec_Est!E216 -> 76.62 | G85: =F85*D85 -> 76.62
A88: =A79+1 -> 16 | C88: Butterfly valves with insulation
B90: a. | C90: DN150 | D90: 3 | E90: No. | G90: =F90*D90 -> 0
A93: =A88+1 -> 17 | C93: Strainers with insulation
B95: a. | C95: DN150 | D95: =1*3 -> 3 | E95: No. | G95: =F95*D95 -> 0
A98: =A93+1 -> 18 | C98: Non return valves with insulation
B100: a. | C100: DN150 | D100: =1*3 -> 3 | E100: No. | G100: =F100*D100 -> 0
A103: =A98+1 -> 19 | C103: Pressure gauges c/w siphon and cock | D103: =2*3 -> 6 | E103: No. | G103: =F103*D103 -> 0
C109: Total carried forward to summary page | G109: =SUM(G58:G107) -> 14968.5
A115: Item | B115: Description | D115: Qty | E115: Unit | F115: Rate in € | G115: Total
C117: CHILLED WATER HEADERS
A119: =A103+1 -> 20 | C119: 10" chilled water flow and return headers (7/12C) (approx. 15m length each) at Level 2 manufactured from black mild steel heavy gauge complete with insulation, brackets and having:
C121: - 3 x 6" flanged connections | D121: 2 | E121: No. | G121: =F121*D121 -> 0
C122: - 1 x 10" flanged connections
C123: - 1 x 1" drain connections
C124: - 1 x 1" AAV
A127: =A119+1 -> 21 | C127: Pressure gauges c/w siphon and cock | D127: 2 | E127: No. | G127: =F127*D127 -> 0
A130: =A127+1 -> 22 | C130: Thermometers | D130: 2 | E130: No. | G130: =F130*D130 -> 0
A133: =A130+1 -> 23 | C133: Black steel piping from chilled water flow and return headers in Level 2 to chilled water headers in Level 4 complete with insulation, brackets, etc.
B135: a. | C135: 10" dia. | D135: =80*2 -> 160 | E135: m | G135: =F135*D135 -> 0
A138: =A133+1 -> 24 | C138: Butterfly valves with insulation
B140: a. | C140: DN250 | D140: 4 | E140: No. | G140: =F140*D140 -> 0
C143: HEATING WATER SIDE
A145: =A138+1 -> 25 | C145: Black steel piping to heating water headers, complete with insulation, brackets, etc.
B147: a. | C147: 6" dia. | D147: =12*2*3 -> 72 | E147: m | G147: =F147*D147 -> 0
A150: =A145+1 -> 26 | C150: Butterfly valves with insulation
B152: a. | C152: DN150 | D152: =4*3 -> 12 | E152: No. | G152: =F152*D152 -> 0
A155: =A150+1 -> 27 | C155: Energy Meter with M-Bus output
B157: a. | C157: DN150 | D157: 3 | E157: No. | F157: =Elec_Est!E241 -> 4731.63 | G157: =F157*D157 -> 14194.89
C163: Total carried forward to summary page | G163: =SUM(G118:G161) -> 14194.89
A169: Item | B169: Description | D169: Qty | E169: Unit | F169: Rate in € | G169: Total
A171: =A155+1 -> 28 | C171: Commissioning valves with insulation
B173: a. | C173: DN150 | D173: 3 | E173: No. | G173: =F173*D173 -> 0
A176: =A171+1 -> 29 | C176: 3- way motorised valve on/off
B178: a. | C178: DN150 | D178: =3*2 -> 6 | E178: No. | F178: =Elec_Est!E261 -> 2368.98 | G178: =F178*D178 -> 14213.88
A181: =A176+1 -> 30 | C181: Flow switch | D181: 3 | E181: No. | F181: =Elec_Est!E277 -> 129.4 | G181: =F181*D181 -> 388.2
A184: =A181+1 -> 31 | C184: Install only temperature sensors (free issued by Trane) | D184: =2*3 -> 6 | E184: No. | F184: =Elec_Est!E291 -> 22.76 | G184: =F184*D184 -> 136.56
A187: =A184+1 -> 32 | C187: Pressure gauges c/w siphon and cock | D187: =2*3 -> 6 | E187: No. | G187: =F187*D187 -> 0
A190: =A187+1 -> 33 | C190: Thermometers | D190: =2*3 -> 6 | E190: No. | G190: =F190*D190 -> 0
A193: =A190+1 -> 34 | C193: Drain cocks | D193: 3 | E193: No. | G193: =F193*D193 -> 0
A196: =A193+1 -> 35 | C196: Heating water circulating pumps, complete with anti-vibration mountings, differential pressure switch connected to BMS, and pipe flexible connections, etc. as specified.
B198: a. | C198: P-206 | D198: 1 | E198: No. | F198: =Elec_Est!E309 -> 165.9 | G198: =F198*D198 -> 165.9
B200: b. | C200: P-207 | D200: 1 | E200: No. | F200: =Elec_Est!E336 -> 165.9 | G200: =F200*D200 -> 165.9
B202: c. | C202: P-208 | D202: 1 | E202: No. | F202: =Elec_Est!E363 -> 165.9 | G202: =F202*D202 -> 165.9
A205: =A196+1 -> 36 | C205: Butterfly valves with insulation
B207: a. | C207: DN150 | D207: 3 | E207: No. | G207: =F207*D207 -> 0
A210: =A205+1 -> 37 | C210: Strainers with insulation
B212: a. | C212: DN150 | D212: =1*3 -> 3 | E212: No. | G212: =F212*D212 -> 0
C221: Total carried forward to summary page | G221: =SUM(G170:G219) -> 15236.34
A227: Item | B227: Description | D227: Qty | E227: Unit | F227: Rate in € | G227: Total
A229: =A210+1 -> 38 | C229: Non return valves with insulation
B231: a. | C231: DN150 | D231: =1*3 -> 3 | E231: No. | G231: =F231*D231 -> 0
A234: =A229+1 -> 39 | C234: Pressure gauges c/w siphon and cock | D234: =2*3 -> 6 | E234: No. | G234: =F234*D234 -> 0
C237: SOURCE SIDE
A239: =A234+1 -> 40 | C239: Black steel piping to existing heat exchangers, complete with insulation, brackets, etc.
B241: a. | C241: 6" dia. | D241: =(7+7)*2*3 -> 84 | E241: m | G241: =F241*D241 -> 0
A244: =A239+1 -> 41 | C244: Butterfly valves with insulation
B246: a. | C246: DN150 | D246: =6*3 -> 18 | E246: No. | G246: =F246*D246 -> 0
A249: =A244+1 -> 42 | C249: Install only temperature sensors (free issued by Trane)
B251: a. | C251: DN150 | D251: =2*3 -> 6 | E251: No. | F251: =Elec_Est!E394 -> 22.76 | G251: =F251*D251 -> 136.56
A254: =A249+1 -> 43 | C254: Pressure gauges c/w siphon and cock | D254: =2*3 -> 6 | E254: No. | G254: =F254*D254 -> 0
A257: =A254+1 -> 44 | C257: Thermometers | D257: =2*3 -> 6 | E257: No. | G257: =F257*D257 -> 0
A260: =A257+1 -> 45 | C260: Drain cocks | D260: 3 | E260: No. | G260: =F260*D260 -> 0
C280: Total carried forward to summary page | G280: =SUM(G228:G278) -> 136.56
A286: Item | B286: Description | D286: Qty | E286: Unit | F286: Rate in € | G286: Total
C288: Take delivery at site inside Car Park of Trane chillers procured by client, hoist into place, install and set to work all systems listed below and as described in the specifications.
C290: CHILLERS - EDEN ARENA
...

Sheet Boilers_Dismantling_BOQ
A1: BILL OF QUANTITIES
A2: BOILERS
A3: DISMANTLING
A5: Item | C5: Qty | D5: Unit | E5: Rate in € | F5: Total
A7: T | B7: Dismantle and cart away all systems listed below and as described in the specifications.
A9: T | B9: PLANTROOM (LEVEL 4)
A10: T | B10: BOILERS
A12: 1 | B12: Shell and tube boilers complete as specified. | C12: 2 | D12: No. | F12: =E12*C12 -> 0
A15: =A12+1 -> 2 | B15: Allow for disconnection of all existing power, control and piping connections, draining down of existing boilers and making safe including dismantling and removal of existing piping from adjacent isolating valves. To include for adjustment and blanking off of chimney and disposal of boilers in accordance with all current legislation. | C15: 1 | D15: LS | E15: =Elec_Est!E559 -> 283.28 | F15: =E15*C15 -> 283.28 | G15: 2
A53: S | B53: Total carried forward to summary page | F53: =SUM(F12:F51) -> 283.28

Sheet HTHP_New_BOQ
A1: BILL OF QUANTITIES | K1: BILL OF QUANTITIES
A2: HIGH TEMPERATURE HEAT PUMPS | K2: HIGH TEMPERATURE HEAT PUMPS
A3: NEW INSTALLATION | K3: NEW INSTALLATION
A5: Item | C5: Qty | D5: Unit | E5: Rate in € | F5: Total | K5: Item | L5: Description | N5: Unit | O5: Qty | P5: Rate in € | Q5: Total
A7: T | B7: HEATING SIDE | M7: HEATING HEADERS
A9: 1.0T | B9: Black steel piping to heating water headers, complete with insulation, brackets, etc. | K9: 1 | M9: 10" heating flow and return headers (33/28C) (approx. 4m length each) manufactured from black mild steel heavy gauge complete with insulation, brackets and having:
A11: a. | B11: 8" dia. | C11: =10*2*3 -> 60 | D11: m | F11: =E11*C11 -> 0 | M11: - 3 x 6" flanged connections | N11: No. | O11: 2 | Q11: =P11*O11 -> 0
M12: - 1 x 10" flanged connections
M13: - 1 x 1" drain connections
A14: 2.0T | B14: Butterfly valves with insulation | M14: - 1 x 1" AAV
A16: a. | B16: DN200 | C16: =2*3 -> 6 | D16: No. | F16: =E16*C16 -> 0
K17: =K9+1 -> 2 | M17: Pressure gauges c/w siphon and cock | N17: No. | O17: 2 | Q17: =P17*O17 -> 0
A19: 3.0T | B19: Energy Meter with M-Bus output
K20: =K17+1 -> 3 | M20: Thermometers | N20: No. | O20: 2 | Q20: =P20*O20 -> 0
A21: a. | B21: DN200 | C21: 3 | D21: No. | E21: =Elec_Est!#REF! -> #REF! | F21: =E21*C21 -> #REF! | G21: 2
K23: =K20+1 -> 4 | M23: 1,000 litre make up and expansion tank c/w isolating valve | N23: No. | O23: 1 | Q23: =P23*O23 -> 0
A24: 4 | B24: Pressure gauges c/w siphon and cock | C24: =3*3 -> 9 | D24: No. | F24: =E24*C24 -> 0
K26: =K23+1 -> 5 | M26: Packaged pressurisation unit c/w expansion vessel & safety valve
A27: 5 | B27: Thermometers | C27: =2*3 -> 6 | D27: No. | F27: =E27*C27 -> 0
L28: a. | M28: PU-HTW1 | N28: No. | O28: 1 | P28: =Elec_Est!E586 -> 62.88 | Q28: =P28*O28 -> 62.88
A30: 6.0T | B30: Heating circulating pumps, complete with anti-vibration mountings, differential pressure switch connected to BMS, and pipe flexible connections, etc. as specified.
K31: =K26+1 -> 6 | M31: PPR piping from packaged pressurisation unit to heating return header
A32: a. | B32: P-206 | C32: 1 | D32: No. | E32: =Elec_Est!#REF! -> #REF! | G32: 2
L33: a. | M33: 32mm | N33: m | O33: 30 | Q33: =P33*O33 -> 0
A34: b. | B34: P-207 | C34: 1 | D34: No. | E34: =Elec_Est!#REF! -> #REF! | G34: 2
A36: c. | B36: P-208 | C36: 1 | D36: No. | E36: =Elec_Est!#REF! -> #REF! | G36: 2 | K36: =K31+1 -> 7 | M36: PPR ball valve
L38: a. | M38: 32mm | N38: No. | O38: 1 | Q38: =P38*O38 -> 0
A39: 7.0T | B39: Butterfly valves with insulation
A41: a. | B41: DN200 | C41: =2*3 -> 6 | D41: No. | F41: =E41*C41 -> 0 | K41: =K36+1 -> 8 | M41: Black steel piping from heating flow and return headers to hot water tank, complete with insulation, brackets, etc.
L43: a. | M43: 10" dia. | N43: m | O43: =25*2 -> 50 | Q43: =P43*O43 -> 0
A44: 8.0T | B44: Commissioning Valves with insulation
A46: a. | B46: DN200 | C46: =1*3 -> 3 | D46: No. | F46: =E46*C46 -> 0 | K46: =K41+1 -> 9 | M46: Butterfly valves with insulation
L48: a. | M48: DN250 | N48: No. | O48: 4 | Q48: =P48*O48 -> 0
A49: 9.0T | B49: Strainers with insulation
A51: a. | B51: DN200 | C51: =1*3 -> 3 | D51: No. | F51: =E51*C51 -> 0
M54: Total carried forward to summary page | Q54: =SUM(Q11:Q52) -> 62.88
A56: P | B56: Total carried forward to summary page | F56: =SUM(F11:F54) -> #REF!
K60: Item | L60: Description | N60: Unit | O60: Qty | P60: Rate in € | Q60: Total
A62: Item | C62: Qty | D62: Unit | E62: Rate in € | F62: Total | K62: =K46+1 -> 10 | M62: 3,000 litres vertical hot water tanks (33C) with 4 x 10" connections, air vent, drain, insulation, inspection manhole etc. | N62: No. | O62: 1 | Q62: =P62*O62 -> 0
A64: 10.0T | B64: Non return valves with insulation
K65: =K62+1 -> 11 | M65: Black steel piping from hot water tank to heating flow and return headers, complete with insulation, brackets, etc.
A66: a. | B66: DN200 | C66: =1*3 -> 3 | D66: No. | F66: =E66*C66 -> 0
L67: a. | M67: 10" dia. | N67: m | O67: =10*2 -> 20 | Q67: =P67*O67 -> 0
A69: 11 | B69: Pressure gauges c/w siphon and cock | C69: =2*3 -> 6 | D69: No. | F69: =E69*C69 -> 0
K70: =K65+1 -> 12 | M70: Thermometers | N70: No. | O70: 4 | Q70: =P70*O70 -> 0
K73: =K70+1 -> 13 | M73: Butterfly valves with insulation
L75: a. | M75: 10" dia. | N75: No. | O75: 4 | Q75: =P75*O75 -> 0
K78: =K73+1 -> 14 | M78: Install only temperature sensors (free issued by Trane) | N78: No. | O78: 4 | P78: =Elec_Est!E604 -> 22.76 | Q78: =P78*O78 -> 91.04
K81: =K78+1 -> 15 | M81: 10" heating flow and return headers (33/28C) (approx. 4m length each) manufactured from black mild steel heavy gauge complete with insulation, brackets and having:
M83: - 3 x 6" flanged connections | N83: No. | O83: 2 | Q83: =P83*O83 -> 0
M84: - 1 x 10" flanged connections
M85: - 1 x 1" drain connections
M86: - 1 x 1" AAV
K89: =K81+1 -> 16 | M89: Packaged pressurisation unit c/w expansion vessel & safety valve
L91: a. | M91: PU-HTW2 | N91: No. | O91: 1 | P91: =Elec_Est!E622 -> 62.88 | Q91: =P91*O91 -> 62.88
K94: =K89+1 -> 17 | M94: PPR piping from packaged pressurisation unit to heating return header
L96: a. | M96: 32mm | N96: m | O96: 30 | Q96: =P96*O96 -> 0
K99: =K94+1 -> 18 | M99: PPR ball valve
L101: a. | M101: 32mm | N101: No. | O101: 1 | Q101: =P101*O101 -> 0
M106: Total carried forward to summary page | Q106: =SUM(Q62:Q104) -> 153.92
K112: Item | L112: Description | N112: Unit | O112: Qty | P112: Rate in € | Q112: Total
K114: =K99+1 -> 19 | M114: Black steel piping from heating flow and return headers to high temperature heat pumps, complete with insulation, brackets, etc.
A116: P | B116: Total carried forward to summary page | F116: =SUM(F66:F114) -> 0 | L116: a. | M116: 6" dia. | N116: m | O116: =12*2*3 -> 72 | Q116: =P116*O116 -> 0
K119: =K114+1 -> 20 | M119: Butterfly valves with insulation
L121: a. | M121: DN150 | N121: No. | O121: =4*3 -> 12 | Q121: =P121*O121 -> 0
A122: Item | C122: Qty | D122: Unit | E122: Rate in € | F122: Total
A124: T | B124: HEATING HEADERS | K124: =K119+1 -> 21 | M124: Heating water circulating pumps, complete with anti-vibration mountings, differential pressure switch connected to BMS, and pipe flexible connections, etc. as specified.
A126: 12.0T | B126: 10" heating flow and return headers (45/40C) manufactured from black mild steel heavy gauge complete with insulation, brackets and having: | L126: a. | M126: P-214 | N126: No. | O126: 1 | P126: =Elec_Est!E644 -> 152.91 | Q126: =P126*O126 -> 152.91
A128: a. | B128: - 3 x 8" flanged connections - 1 x 10" flanged connections - 1 x 1" drain connections - 1 x 1" AAV | C128: 2 | D128: No. | F128: =E128*C128 -> 0 | L128: b. | M128: P-215 | N128: No. | O128: 1 | P128: =Elec_Est!E666 -> 152.91 | Q128: =P128*O128 -> 152.91
L130: c. | M130: P-216 | N130: No. | O130: 1 | P130: =Elec_Est!E688 -> 152.91 | Q130: =P130*O130 -> 152.91
K133: =K124+1 -> 22 | M133: Butterfly valves with insulation
A134: 13 | B134: Pressure gauges c/w siphon and cock | C134: 2 | D134: No. | F134: =E134*C134 -> 0
L135: a. | M135: DN150 | N135: No. | O135: 3 | Q135: =P135*O135 -> 0
A137: 14 | B137: Thermometers | C137: 2 | D137: No. | F137: =E137*C137 -> 0
K138: =K133+1 -> 23 | M138: Strainers with insulation
A140: 15 | B140: 1,000 litre make up and expansion tank c/w isolating valve | C140: 1 | D140: No. | F140: =E140*C140 -> 0 | L140: a. | M140: DN150 | N140: No. | O140: 3 | Q140: =P140*O140 -> 0
A143: 16.0T | B143: Packaged pressurisation unit c/w expansion vessel & safety valve | K143: =K138+1 -> 24 | M143: Commissioning valves with insulation
A145: a. | B145: PU-HTW1 | C145: 1 | D145: No. | E145: =Elec_Est!#REF! -> #REF! | F145: =E145*C145 -> #REF! | G145: 2 | L145: a. | M145: DN150 | N145: No. | O145: 3 | Q145: =P145*O145 -> 0
A148: 17.0T | B148: PPR piping from packaged pressurisation unit to heating return header | K148: =K143+1 -> 25 | M148: Thermometers | N148: No. | O148: =2*3 -> 6 | Q148: =P148*O148 -> 0
A150: a. | B150: 32mm | C150: 30 | D150: m | F150: =E150*C150 -> 0
K151: =K148+1 -> 26 | M151: Automatic air vents c/w isolating valve | N151: No. | O151: =2*3 -> 6 | Q151: =P151*O151 -> 0
A153: 18.0T | B153: PPR ball valve
K154: =K151+1 -> 27 | M154: Drain cocks | N154: No. | O154: 3 | Q154: =P154*O154 -> 0
A155: a. | B155: 32mm | C155: 1 | D155: No. | F155: =E155*C155 -> 0
A158: 19.0T | B158: Black steel piping from heating flow and return headers to hot water tank, complete with insulation, brackets, etc.
A160: a. | B160: 10" dia. | C160: =15*2 -> 30 | D160: m | F160: =E160*C160 -> 0
M162: Total carried forward to summary page | Q162: =SUM(Q113:Q160) -> 458.73
A163: 20.0T | B163: Butterfly valves with insulation
A165: a. | B165: DN250 | C165: 4 | D165: No. | F165: =E165*C165 -> 0
K168: Item | L168: Description | N168: Unit | O168: Qty | P168: Rate in € | Q168: Total
A170: P | B170: Total carried forward to summary page | F170: =SUM(F128:F168) -> #REF! | M170: PLANTROOM (LEVEL 2)
M171: HIGH TEMPERATURE HEAT PUMPS
M173: Take delivery at site inside Car Park of Trane HTHP's procured by client, hoist into place, install and set to work all systems listed below and as described in the specifications.
K175: =K154+1 -> 28 | M175: Install only HTHP's ref. HTHP-1, HTHP-2 and HTHP-3 inclusive of flexible bellows, AVM's, flow switches, controls, etc. as specified. | N175: No. | O175: 3 | P175: =Elec_Est!E718 -> 777.51 | Q175: =P175*O175 -> 2332.53
A176: Item | C176: Qty | D176: Unit | E176: Rate in € | F176: Total
A178: 21 | B178: 3,000 litres horizontal hot water tanks (45C) with 2 x 10" and 2 x 8" connections (1 x spare blanked), air vent, drain, insulation, inspection manhole etc. | C178: 1 | D178: No. | F178: =E178*C178 -> 0 | K178: =K175+1 -> 29 | M178: Allow for assisting factory-trained employee of the manufacturer to carry out all start up and commissioning of all HTHP's | N178: LS | O178: 1 | Q178: =P178*O178 -> 0
A181: 22.0T | B181: Black steel piping from hot water tank to heating flow and return headers, complete with insulation, brackets, etc. | K181: =K178+1 -> 30 | M181: Black steel piping from high temperature heat pumps to heating flow and return headers complete with insulation, brackets, etc.
A183: a. | B183: 10" dia. | C183: =15*2 -> 30 | D183: m | F183: =E183*C183 -> 0 | L183: a. | M183: 6" dia. | N183: m | O183: =10*2*3 -> 60 | Q183: =P183*O183 -> 0
A186: 23 | B186: Thermometers | C186: 3 | D186: No. | F186: =E186*C186 -> 0 | K186: =K181+1 -> 31 | M186: Butterfly valves with insulation
L188: a. | M188: DN150 | N188: No. | O188: =4*3 -> 12 | Q188: =P188*O188 -> 0
...

Sheet Pumps_Dismantling_BOQ
A1: BILL OF QUANTITIES
A2: PUMPS
A3: DISMANTLING
A5: Item | C5: Qty | D5: Unit | E5: Rate in € | F5: Total
A7: T | B7: Dismantle and cart away all systems listed below and as described in the specifications.
A8: T | B8: Dismantling to include 2 x isolating valves, strainers, non return valve, strainers and pipe flexible connections and piping from isolating valves to pumps.
A10: T | B10: PUMPS
A12: 1.0T | B12: Heat exchanger to chiller condenser circulating pumps, complete with anti-vibration mountings and pipe flexible connections, etc. as specified.
A14: a. | B14: a. P-101 | C14: 1 | D14: No. | F14: =E14*C14 -> 0
A16: b. | B16: b. P-102 | C16: 1 | D16: No. | F16: =E16*C16 -> 0
A18: c. | B18: c. P-103 | C18: 1 | D18: No. | F18: =E18*C18 -> 0
A20: d. | B20: d. P-104 | C20: 1 | D20: No. | F20: =E20*C20 -> 0
A23: 2.0T | B23: Primary chilled water pumps complete with anti-vibration mountings and pipe flexible connections, etc. as specified.
A25: a. | B25: a. P-201 | C25: 1 | D25: No. | F25: =E25*C25 -> 0
A27: b. | B27: b. P-202 | C27: 1 | D27: No. | F27: =E27*C27 -> 0
A29: c. | B29: c. P-203 | C29: 1 | D29: No. | F29: =E29*C29 -> 0
A31: d. | B31: d. P-204 | C31: 1 | D31: No. | F31: =E31*C31 -> 0
A33: e. | B33: e. P-205 | C33: 1 | D33: No. | F33: =E33*C33 -> 0
A52: P | B52: Total carried forward to summary page | F52: =SUM(F14:F50) -> 0
A58: Item | C58: Qty | D58: Unit | E58: Rate in € | F58: Total
A60: 3.0T | B60: Cooling / heating secondary pumps complete with anti-vibration mounting and pipe flexible connections as specified.
A62: a. | B62: a. P-301 | C62: 1 | D62: No. | F62: =E62*C62 -> 0
A64: b. | B64: b. P-302 | C64: 1 | D64: No. | F64: =E64*C64 -> 0
A66: c. | B66: c. P-303 | C66: 1 | D66: No. | F66: =E66*C66 -> 0
A68: d. | B68: d. P-304 | C68: 1 | D68: No. | F68: =E68*C68 -> 0
A70: e. | B70: e. P-305 | C70: 1 | D70: No. | F70: =E70*C70 -> 0
A72: f. | B72: f. P-306 | C72: 1 | D72: No. | F72: =E72*C72 -> 0
A74: g. | B74: g. P-307 | C74: 1 | D74: No. | F74: =E74*C74 -> 0
A76: h. | B76: h. P-308 | C76: 1 | D76: No. | F76: =E76*C76 -> 0
A78: i. | B78: i. P-309 | C78: 1 | D78: No. | F78: =E78*C78 -> 0
A80: j. | B80: j. P-310 | C80: 1 | D80: No. | F80: =E80*C80 -> 0
A108: P | B108: Total carried forward to summary page | F108: =SUM(F62:F106) -> 0
A114: Item | C114: Qty | D114: Unit | E114: Rate in € | F114: Total
A116: 4.0T | B116: Cooling water secondary pumps complete with anti-vibration mountings, differential pressure switch connected to BMS and pipe flexible connections, etc. as specified.
A118: a. | B118: a. P-401 | C118: 1 | D118: No. | F118: =E118*C118 -> 0
A120: b. | B120: b. P-402 | C120: 1 | D120: No. | F120: =E120*C120 -> 0
A122: c. | B122: c. P-403 | C122: 1 | D122: No. | F122: =E122*C122 -> 0
A124: d. | B124: d. P-404 | C124: 1 | D124: No. | F124: =E124*C124 -> 0
A126: e. | B126: e. P-405 | C126: 1 | D126: No. | F126: =E126*C126 -> 0
A128: f. | B128: f. P-406 | C128: 1 | D128: No. | F128: =E128*C128 -> 0
A164: P | B164: Total carried forward to summary page | F164: =SUM(F118:F162) -> 0
A170: Item | C170: Qty | D170: Unit | E170: Rate in € | F170: Total
A172: 5.0T | B172: Heating water secondary pumps complete with anti-vibration mountings, differential pressure switch connected to BMS and pipe flexible connections, etc. as specified.
A174: a. | B174: a. P-501 | C174: 1 | D174: No. | F174: =E174*C174 -> 0
A176: b. | B176: b. P-502 | C176: 1 | D176: No. | F176: =E176*C176 -> 0
A178: c. | B178: c. P-503 | C178: 1 | D178: No. | F178: =E178*C178 -> 0
A180: d. | B180: d. P-504 | C180: 1 | D180: No. | F180: =E180*C180 -> 0
A183: 6 | B183: Allow for disconnection of all existing power, control and piping connections, draining down of existing pumps and making safe including dismantling and removal of existing piping from adjacent isolating valves. To include for disposal of pumps in accordance with all current legislation. | C183: 1 | D183: LS | E183: =Elec_Est!E893 -> 929.03 | F183: =E183*C183 -> 929.03 | G183: 2
A216: P | B216: Total carried forward to summary page | F216: =SUM(F174:F214) -> 929.03

Sheet Pumps_New_BOQ
A1: BILL OF QUANTITIES | K1: BILL OF QUANTITIES
A2: PUMPS | K2: PUMPS
A3: NEW | K3: NEW
A5: Item | C5: Qty | D5: Unit | E5: Rate in € | F5: Total | K5: Item | L5: Description | N5: Unit | O5: Qty | P5: Rate in € | Q5: Total
A7: T | B7: Supply, deliver to site, install and set to work all systems listed below and as described in the specifications.
K8: 1 | M8: Cooling / heating secondary pumps complete with anti-vibration mounting and pipe flexible connections as specified.
A9: T | B9: PUMPS
M10: a. P-301 | N10: No. | O10: 1 | P10: =Elec_Est!E923 -> 61.84 | Q10: =P10*O10 -> 61.84
A11: 1.0T | B11: Heat exchanger to chiller condenser circulating pumps, complete with anti-vibration mountings, differential pressure switch connected to BMS and pipe flexible connections, etc. as specified.
M12: b. P-302 | N12: No. | O12: 1 | P12: =Elec_Est!E930 -> 61.84 | Q12: =P12*O12 -> 61.84
A13: a. | B13: a. P-101 | C13: 1 | D13: No. | F13: =E13*C13 -> 0
M14: c. P-303 | N14: No. | O14: 1 | P14: =Elec_Est!E937 -> 47.58 | Q14: =P14*O14 -> 47.58
A15: b. | B15: b. P-102 | C15: 1 | D15: No. | F15: =E15*C15 -> 0
M16: d. P-304 | N16: No. | O16: 1 | P16: =Elec_Est!E944 -> 47.58 | Q16: =P16*O16 -> 47.58
A17: c. | B17: c. P-103 | C17: 1 | D17: No. | F17: =E17*C17 -> 0
M18: e. P-305 | N18: No. | O18: 1 | P18: =Elec_Est!E951 -> 61.84 | Q18: =P18*O18 -> 61.84
A19: d. | B19: d. P-104 | C19: 1 | D19: No. | F19: =E19*C19 -> 0
M20: f. P-306 | N20: No. | O20: 1 | P20: =Elec_Est!E958 -> 61.84 | Q20: =P20*O20 -> 61.84
A22: 2.0T | B22: Primary chilled water pumps complete with anti-vibration mountings, differential pressure switch connected to BMS and pipe flexible connections, etc. as specified. | M22: g. P-307 | N22: No. | O22: 1 | P22: =Elec_Est!E965 -> 43.84 | Q22: =P22*O22 -> 43.84
A24: a. | B24: a. P-201 | C24: 1 | D24: No. | E24: =Elec_Est!#REF! -> #REF! | G24: 3 | M24: h. P-308 | N24: No. | O24: 1 | P24: =Elec_Est!E972 -> 43.84 | Q24: =P24*O24 -> 43.84
A26: b. | B26: b. P-202 | C26: 1 | D26: No. | E26: =Elec_Est!#REF! -> #REF! | G26: 3 | M26: i. P-309 | N26: No. | O26: 1 | P26: =Elec_Est!E979 -> 43.84 | Q26: =P26*O26 -> 43.84
A28: c. | B28: c. P-203 | C28: 1 | D28: No. | E28: =Elec_Est!#REF! -> #REF! | G28: 3 | M28: j. P-310 | N28: No. | O28: 1 | P28: =Elec_Est!E986 -> 43.84 | Q28: =P28*O28 -> 43.84
A30: d. | B30: d. P-204 | C30: 1 | D30: No. | E30: =Elec_Est!#REF! -> #REF! | G30: 3
A32: e. | B32: e. P-205 | C32: 1 | D32: No. | E32: =Elec_Est!#REF! -> #REF! | G32: 3
A35: 3.0T | B35: Primary heating water pumps complete with anti-vibration mountings, differential pressure switch connected to BMS and pipe flexible connections, etc. as specified.
A37: a. | B37: a. P-206 | C37: 1 | D37: No. | E37: =Elec_Est!#REF! -> #REF! | G37: 3
A39: b. | B39: b. P-207 | C39: 1 | D39: No. | E39: =Elec_Est!#REF! -> #REF! | G39: 3
A41: c. | B41: c. P-208 | C41: 1 | D41: No. | E41: =Elec_Est!#REF! -> #REF! | G41: 3
A50: P | B50: Total carried forward to summary page | F50: =SUM(F6:F48) -> 0
A56: Item | C56: Qty | D56: Unit | E56: Rate in € | F56: Total
M57: Total carried forward to summary page | Q57: =SUM(Q6:Q55) -> 517.88
A58: 4.0T | B58: Primary heating water pumps complete with anti-vibration mountings, differential pressure switch connected to BMS and pipe flexible connections, etc. as specified.
A60: a. | B60: a. P-209 | C60: 1 | D60: No. | E60: =Elec_Est!#REF! -> #REF! | G60: 3
A62: b. | B62: b. P-210 | C62: 1 | D62: No. | E62: =Elec_Est!#REF! -> #REF! | G62: 3
K63: Item | L63: Description | N63: Unit | O63: Qty | P63: Rate in € | Q63: Total
A65: 5.0T | B65: Cooling / heating secondary pumps complete with anti-vibration mounting and pipe flexible connections as specified. | K65: =K8+1 -> 2 | M65: Cooling water secondary pumps complete with anti-vibration mountings, differential pressure switch connected to BMS and pipe flexible connections, etc. as specified.
A67: a. | B67: a. P-301 | C67: 1 | D67: No. | E67: =Elec_Est!#REF! -> #REF! | G67: 3 | M67: a. P-401 | N67: No. | O67: 1 | P67: =Elec_Est!E997 -> 61.84 | Q67: =P67*O67 -> 61.84
A69: b. | B69: b. P-302 | C69: 1 | D69: No. | E69: =Elec_Est!#REF! -> #REF! | G69: 3 | M69: b. P-402 | N69: No. | O69: 1 | P69: =Elec_Est!E1018 -> 61.84 | Q69: =P69*O69 -> 61.84
A71: c. | B71: c. P-303 | C71: 1 | D71: No. | E71: =Elec_Est!#REF! -> #REF! | G71: 3 | M71: c. P-403 | N71: No. | O71: 1 | P71: =Elec_Est!E1039 -> 61.84 | Q71: =P71*O71 -> 61.84
A73: d. | B73: d. P-304 | C73: 1 | D73: No. | E73: =Elec_Est!#REF! -> #REF! | G73: 3 | M73: d. P-404 | N73: No. | O73: 1 | P73: =Elec_Est!E1060 -> 61.84 | Q73: =P73*O73 -> 61.84
A75: e. | B75: e. P-305 | C75: 1 | D75: No. | E75: =Elec_Est!#REF! -> #REF! | G75: 3 | M75: e. P-405 | N75: No. | O75: 1 | P75: =Elec_Est!E1081 -> 43.84 | Q75: =P75*O75 -> 43.84
A77: f. | B77: f. P-306 | C77: 1 | D77: No. | E77: =Elec_Est!#REF! -> #REF! | G77: 3 | M77: f. P-406 | N77: No. | O77: 1 | P77: =Elec_Est!E1102 -> 43.84 | Q77: =P77*O77 -> 43.84
A79: g. | B79: g. P-307 | C79: 1 | D79: No. | E79: =Elec_Est!#REF! -> #REF! | G79: 3
A81: h. | B81: h. P-308 | C81: 1 | D81: No. | E81: =Elec_Est!#REF! -> #REF! | G81: 3
A83: i. | B83: i. P-309 | C83: 1 | D83: No. | E83: =Elec_Est!#REF! -> #REF! | G83: 3
A85: j. | B85: j. P-310 | C85: 1 | D85: No. | E85: =Elec_Est!#REF! -> #REF! | G85: 3
A106: P | B106: Total carried forward to summary page | F106: =SUM(F57:F104) -> 0
A112: Item | C112: Qty | D112: Unit | E112: Rate in € | F112: Total
A114: 6.0T | B114: Cooling water secondary pumps complete with anti-vibration mountings, differential pressure switch connected to BMS and pipe flexible connections, etc. as specified.
M115: Total carried forward to summary page | Q115: =SUM(Q64:Q113) -> 335.04
A116: a. | B116: a. P-401 | C116: 1 | D116: No. | E116: =Elec_Est!#REF! -> #REF! | G116: 3
A118: b. | B118: b. P-402 | C118: 1 | D118: No. | E118: =Elec_Est!#REF! -> #REF! | G118: 3
A120: c. | B120: c. P-403 | C120: 1 | D120: No. | E120: =Elec_Est!#REF! -> #REF! | G120: 3
K121: Item | L121: Description | N121: Unit | O121: Qty | P121: Rate in € | Q121: Total
A122: d. | B122: d. P-404 | C122: 1 | D122: No. | E122: =Elec_Est!#REF! -> #REF! | G122: 3
K123: =K65+1 -> 3 | M123: Heating water secondary pumps complete with anti-vibration mountings, differential pressure switch connected to BMS and pipe flexible connections, etc. as specified.
A124: e. | B124: e. P-405 | C124: 1 | D124: No. | E124: =Elec_Est!#REF! -> #REF! | G124: 3
M125: a. P-501 | N125: No. | O125: 1 | P125: =Elec_Est!E1127 -> 43.84 | Q125: =P125*O125 -> 43.84
A126: f. | B126: f. P-406 | C126: 1 | D126: No. | E126: =Elec_Est!#REF! -> #REF! | G126: 3
M127: b. P-502 | N127: No. | O127: 1 | P127: =Elec_Est!E1148 -> 43.84 | Q127: =P127*O127 -> 43.84
M129: c. P-503 | N129: No. | O129: 1 | P129: =Elec_Est!E1169 -> 47.58 | Q129: =P129*O129 -> 47.58
M131: d. P-504 | N131: No. | O131: 1 | P131: =Elec_Est!E1190 -> 47.58 | Q131: =P131*O131 -> 47.58
A164: P | B164: Total carried forward to summary page | F164: =SUM(F113:F162) -> 0
A170: Item | C170: Qty | D170: Unit | E170: Rate in € | F170: Total
A172: 7.0T | B172: Heating water secondary pumps complete with anti-vibration mountings, differential pressure switch connected to BMS and pipe flexible connections, etc. as specified.
M173: Total carried forward to summary page | Q173: =SUM(Q123:Q171) -> 182.84
A174: a. | B174: a. P-501 | C174: 1 | D174: No. | E174: =Elec_Est!#REF! -> #REF! | G174: 3
A176: b. | B176: b. P-502 | C176: 1 | D176: No. | E176: =Elec_Est!#REF! -> #REF! | G176: 3
A178: c. | B178: c. P-503 | C178: 1 | D178: No. | E178: =Elec_Est!#REF! -> #REF! | G178: 3
K179: Item | L179: Description | N179: Unit | O179: Qty | P179: Rate in € | Q179: Total
A180: d. | B180: d. P-504 | C180: 1 | D180: No. | E180: =Elec_Est!#REF! -> #REF! | G180: 3
K181: =K123+1 -> 4 | M181: Black steel piping from adjacent isolating valves to new pumps c/w insulation, brackets, etc.
M183: a. P-101 - DN200 | N183: L/S | O183: 1 | Q183: =P183*O183 -> 0
M185: b. P-102 - DN200 | N185: L/S | O185: 1 | Q185: =P185*O185 -> 0
M187: c. P-103 - DN200 | N187: L/S | O187: 1 | Q187: =P187*O187 -> 0
M189: d. P-104 - DN150 | N189: L/S | O189: 1 | Q189: =P189*O189 -> 0
M191: e. P-201 - DN200 | N191: L/S | O191: 1 | Q191: =P191*O191 -> 0
M193: f. P-202 - DN200 | N193: L/S | O193: 1 | Q193: =P193*O193 -> 0
M195: g. P-203 - DN200 | N195: L/S | O195: 1 | Q195: =P195*O195 -> 0
M197: h. P-204 - DN150 | N197: L/S | O197: 1 | Q197: =P197*O197 -> 0
M199: i. P-205 - DN150 | N199: L/S | O199: 1 | Q199: =P199*O199 -> 0
A222: P | B222: Total carried forward to summary page | F222: =SUM(F172:F220) -> 0
A228: Item | C228: Qty | D228: Unit | E228: Rate in € | F228: Total
A230: 8.0T | B230: Black steel piping from adjacent isolating valves to new pumps c/w insulation, brackets, etc.
A232: a. | B232: a. P-101 - DN200 | C232: 1 | D232: L/S | F232: =E232*C232 -> 0 | M232: Total carried forward to summary page | Q232: =SUM(Q180:Q230) -> 0
A234: b. | B234: b. P-102 - DN200 | C234: 1 | D234: L/S | F234: =E234*C234 -> 0
A236: c. | B236: c. P-103 - DN200 | C236: 1 | D236: L/S | F236: =E236*C236 -> 0
A238: d. | B238: d. P-104 - DN150 | C238: 1 | D238: L/S | F238: =E238*C238 -> 0 | K238: Item | L238: Description | N238: Unit | O238: Qty | P238: Rate in € | Q238: Total
A240: e. | B240: a. P-201 - DN200 | C240: 1 | D240: L/S | F240: =E240*C240 -> 0 | K240: =K181+1 -> 5 | M240: Black steel piping from adjacent isolating valves to new pumps c/w insulation, brackets, etc.
A242: f. | B242: b. P-202 - DN200 | C242: 1 | D242: L/S | F242: =E242*C242 -> 0 | M242: a. P-301 - DN100 | N242: L/S | O242: 1 | Q242: =P242*O242 -> 0
A244: g. | B244: c. P-203 - DN200 | C244: 1 | D244: L/S | F244: =E244*C244 -> 0 | M244: b. P-302 - DN100 | N244: L/S | O244: 1 | Q244: =P244*O244 -> 0
A246: h. | B246: d. P-204 - DN150 | C246: 1 | D246: L/S | F246: =E246*C246 -> 0 | M246: c. P-303 - DN150 | N246: L/S | O246: 1 | Q246: =P246*O246 -> 0
A248: i. | B248: e. P-205 - DN150 | C248: 1 | D248: L/S | F248: =E248*C248 -> 0 | M248: d. P-304 - DN150 | N248: L/S | O248: 1 | Q248: =P248*O248 -> 0
M250: e. P-305 - DN150 | N250: L/S | O250: 1 | Q250: =P250*O250 -> 0
M252: f. P-306 - DN150 | N252: L/S | O252: 1 | Q252: =P252*O252 -> 0
M254: g. P-307 - DN125 | N254: L/S | O254: 1 | Q254: =P254*O254 -> 0
M256: h. P-308 - DN125 | N256: L/S | O256: 1 | Q256: =P256*O256 -> 0
M258: i. P-309 - DN80 | N258: L/S | O258: 1 | Q258: =P258*O258 -> 0
M260: j. P-310 - DN80 | N260: L/S | O260: 1 | Q260: =P260*O260 -> 0
A281: P | B281: Total carried forward to summary page | F281: =SUM(F229:F279) -> 0
...

Sheet AHU_Motors_New_BOQ
A1: BILL OF QUANTITIES
A2: AHU'S - NEW FAN MOTORS AND CONTROLS
A5: Item | C5: Qty | D5: Unit | E5: Rate in € | F5: Total
A7: T | B7: Dismantle and remove existing AHU motors, and replace with new high efficiency EC fans with all wiring controls, etc. for a complete working system. System will allow variable speed control based on load requirements. System will be capable of working independently of existing BMS and include facility to interface with existing or future BMS.
A9: T | B9: SYSTEM ON AHU/1
A11: 1 | B11: Air handling unit AHU/1 EC fan complete with all wiring controls, etc. for a complete working system. | C11: 1 | D11: No. | E11: =Elec_Est!R1903 -> Included in PCQ-25-0440 | G11: 3
A13: T | B13: SYSTEM ON AHU/2
A15: 2 | B15: Air handling unit AHU/2 EC fan complete with all wiring controls, etc. for a complete working system. | C15: 1 | D15: No. | E15: =Elec_Est!R1934 -> Not existing on site | G15: 3
A17: T | B17: SYSTEM ON AHU/3
A19: 3 | B19: Air handling unit AHU/3 EC fan complete with all wiring controls, etc. for a complete working system. | C19: 1 | D19: No. | E19: =Elec_Est!R1959 -> Included in PCQ-25-0440 | G19: 3
A21: T | B21: SYSTEM ON AHU/4
A23: 4 | B23: Air handling unit AHU/4 EC fan complete with all wiring controls, etc. for a complete working system. | C23: 1 | D23: No. | E23: =Elec_Est!R1990 -> Included in PCQ-25-0440 | G23: 3
A25: T | B25: SYSTEM ON AHU/5
A27: 5 | B27: Air handling unit AHU/5 EC fan complete with all wiring controls, etc. for a complete working system. | C27: 1 | D27: No. | E27: =Elec_Est!R2021 -> Included in PCQ-25-0440 | G27: 3
A29: T | B29: SYSTEM ON AHU/6
A31: 6 | B31: Air handling unit AHU/6 EC fan complete with all wiring controls, etc. for a complete working system. | C31: 1 | D31: No. | E31: =Elec_Est!R2052 -> Included in PCQ-25-0440 | G31: 3
A33: T | B33: SYSTEM ON AHU/7
A35: 7 | B35: Air handling unit AHU/7 EC fan complete with all wiring controls, etc. for a complete working system. | C35: 1 | D35: No. | E35: =Elec_Est!E2083 -> 5699.05 | F35: =E35*C35 -> 5699.05 | G35: 3
A37: T | B37: SYSTEM ON AHU/8
A39: 8 | B39: Air handling unit AHU/8 EC fan complete with all wiring controls, etc. for a complete working system. | C39: 1 | D39: No. | E39: =Elec_Est!R2114 -> Not existing on site | G39: 3
A42: P | B42: Total carried forward to summary page | F42: =SUM(F11:F40) -> 5699.05
A47: Item | C47: Qty | D47: Unit | E47: Rate in € | F47: Total
A49: T | B49: SYSTEM ON AHU/9
A51: 9 | B51: Air handling unit AHU/9 EC fan complete with all wiring controls, etc. for a complete working system. | C51: 1 | D51: No. | E51: =Elec_Est!E2137 -> 5570.91 | F51: =E51*C51 -> 5570.91 | G51: 3
A54: T | B54: SYSTEM ON AHU/10
A56: 10 | B56: Air handling unit AHU/10 EC fan complete with all wiring controls, etc. for a complete working system. | C56: 1 | D56: No. | E56: =Elec_Est!E2168 -> 5533.83 | F56: =E56*C56 -> 5533.83 | G56: 3
A59: T | B59: SYSTEM ON AHU/11
A61: 11 | B61: Air handling unit AHU/8 EC fan complete with all wiring controls, etc. for a complete working system. | C61: 1 | D61: No. | E61: =Elec_Est!E2199 -> 5570.91 | F61: =E61*C61 -> 5570.91 | G61: 3
A64: T | B64: SYSTEM ON AHU12
A66: 12 | B66: Air handling unit AHU/9 EC fan complete with all wiring controls, etc. for a complete working system. | C66: 1 | D66: No. | E66: =Elec_Est!E2230 -> 6127.44 | F66: =E66*C66 -> 6127.44 | G66: 3
A69: T | B69: SYSTEM ON AHU/13
A71: 13 | B71: Air handling unit AHU/10 EC fan complete with all wiring controls, etc. for a complete working system. | C71: 1 | D71: No. | E71: =Elec_Est!E2261 -> 5570.91 | F71: =E71*C71 -> 5570.91 | G71: 3
A74: T | B74: SYSTEM ON AHU/14
A76: 14 | B76: Air handling unit AHU/14 EC fan complete with all wiring controls, etc. for a complete working system. | C76: 1 | D76: No. | E76: =Elec_Est!R2292 -> Included in PCQ-25-0440 | G76: 3
A79: T | B79: SYSTEM ON AHU/15
A81: 15 | B81: Air handling unit AHU/15 EC fan complete with all wiring controls, etc. for a complete working system. | C81: 1 | D81: No. | E81: =Elec_Est!R2323 -> Included in PCQ-25-0440 | G81: 3
A84: T | B84: SYSTEM ON AHU/16
A86: 16 | B86: Air handling unit AHU/16 EC fan complete with all wiring controls, etc. for a complete working system. | C86: 1 | D86: No. | E86: =Elec_Est!R2354 -> Included in PCQ-25-0440 | G86: 3
A89: T | B89: SYSTEM ON AHU/17
A91: 17 | B91: Air handling unit AHU/17 EC fan complete with all wiring controls, etc. for a complete working system. | C91: 1 | D91: No. | E91: =Elec_Est!E2385 -> 5570.91 | F91: =E91*C91 -> 5570.91 | G91: 3
A93: P | B93: Total carried forward to summary page | F93: =SUM(F49:F91) -> 33944.91
A99: Item | C99: Qty | D99: Unit | E99: Rate in € | F99: Total
A101: T | B101: SYSTEM ON AHU/18
A103: 18 | B103: Air handling unit AHU/18 EC fan complete with all wiring controls, etc. for a complete working system. | C103: 1 | D103: No. | E103: =Elec_Est!E2416 -> 5570.91 | F103: =E103*C103 -> 5570.91 | G103: 3
A106: T | B106: SYSTEM ON AHU/19
A108: 19 | B108: Air handling unit AHU/19 EC fan complete with all wiring controls, etc. for a complete working system. | C108: 1 | D108: No. | E108: =Elec_Est!E2447 -> 5506.83 | F108: =E108*C108 -> 5506.83 | G108: 3
A111: T | B111: SYSTEM ON AHU/20
A113: 20 | B113: Air handling unit AHU/20 EC fan complete with all wiring controls, etc. for a complete working system. | C113: 1 | D113: No. | E113: =Elec_Est!E2478 -> 5570.91 | F113: =E113*C113 -> 5570.91 | G113: 3
A116: T | B116: SYSTEM ON AHU/21
A118: 21 | B118: Air handling unit AHU/21 EC fan complete with all wiring controls, etc. for a complete working system. | C118: 1 | D118: No. | E118: =Elec_Est!R2509 -> Not existing on site | G118: 3
A121: T | B121: SYSTEM ON AHU/22
A123: 22 | B123: Air handling unit AHU/22 EC fan complete with all wiring controls, etc. for a complete working system. | C123: 1 | D123: No. | E123: =Elec_Est!R2534 -> Same as AHU 24 - Isaac 10.09.2025 | G123: 3
A126: T | B126: SYSTEM ON AHU/23
A128: 23 | B128: Air handling unit AHU/23 EC fan complete with all wiring controls, etc. for a complete working system. | C128: 1 | D128: No. | E128: =Elec_Est!R2567 -> Already Awarded | G128: 3
A131: T | B131: SYSTEM ON AHU/24
A133: 24 | B133: Air handling unit AHU/24 EC fan complete with all wiring controls, etc. for a complete working system. | C133: 1 | D133: No. | E133: =Elec_Est!E2592 -> 5550.86 | F133: =E133*C133 -> 5550.86 | G133: 3
A136: T | B136: SYSTEM ON AHU/25A
A138: 25 | B138: Air handling unit AHU/25A EC fan complete with all wiring controls, etc. for a complete working system. | C138: 1 | D138: No. | E138: =Elec_Est!E2623 -> 5486.79 | F138: =E138*C138 -> 5486.79 | G138: 3
A145: P | B145: Total carried forward to summary page | F145: =SUM(F102:F143) -> 27686.3
A151: Item | C151: Qty | D151: Unit | E151: Rate in € | F151: Total
A153: T | B153: SYSTEM ON AHU/25B
A155: 26 | B155: Air handling unit AHU/25B EC fan complete with all wiring controls, etc. for a complete working system. | C155: 1 | D155: No. | E155: =Elec_Est!E2654 -> 5486.79 | F155: =E155*C155 -> 5486.79 | G155: 3
A156: END!
A158: 27 | B158: Allow for survey of existing AHU'S and detailed report. | C158: 1 | D158: LS | F158: =E158*C158 -> 0
A159: T | B159: Before ordering the fans and motors, the contractor is required to survey existing AHU's to confirm existing motor ratings and issue a detailed report including a method statement how the existing motors will be removed and the new motors and fans will be installed prior to order of replacement motors. Report is to consider dimensions and access required to replace new fans and motors.
A197: P | B197: Total carried forward to summary page | F197: =SUM(F152:F195) -> 5486.79

Sheet EF_BOQ
A1: BILL OF QUANTITIES | I1: BILL OF QUANTITIES
A2: EXTRACT FANS | I2: EXTRACT FANS
A5: Item | C5: Qty | D5: Unit | E5: Rate in € | F5: Total | I5: Item | J5: Description | L5: Unit | M5: Qty | N5: Rate in € | O5: Total
A7: T | B7: SYSTEM ON EF/1 | K7: SYSTEM ON EF/2
A9: 1 | B9: Extract fan reference EF/1 complete with mounting hardware, speed controller, flexible duct connections, supports, A.V.M. power supplies etc., as specified. | C9: 1 | D9: No. | E9: =Elec_Est!#REF! -> #REF! | F9: =E9*C9 -> #REF! | G9: 2 | I9: 1 | K9: Extract fan reference EF/2 complete with mounting hardware, speed controller, flexible duct connections, supports, A.V.M. power supplies etc., as specified. | L9: No. | M9: 1 | N9: =Elec_Est!E2691 -> 126.58 | O9: =N9*M9 -> 126.58
A12: 2.T | B12: Weather louvre WL/x | K12: SYSTEM ON EF/3
A14: a. | B14: a. 800 x 600 | C14: 1 | D14: No. | F14: =E14*C14 -> 0 | I14: =I9+1 -> 2 | K14: Extract fan reference EF/3 complete with mounting hardware, speed controller, flexible duct connections, supports, A.V.M. power supplies etc., as specified. | L14: No. | M14: 1 | N14: =Elec_Est!E2717 -> 126.58 | O14: =N14*M14 -> 126.58
A17: T | B17: SYSTEM ON EF/2 | K17: REFRIGERANT LEAK DETECTION
A19: 3 | B19: Extract fan reference EF/2 complete with mounting hardware, speed controller, flexible duct connections, supports, A.V.M. power supplies etc., as specified. | C19: 1 | D19: No. | E19: =Elec_Est!#REF! -> #REF! | F19: =E19*C19 -> #REF! | G19: 2 | I19: =I14+1 -> 3 | K19: Refrigerant leak detectors to detect when refrigerant concentration exceeds 25% of LFL for R1234ze. Detectors must be positioned a maximum of 30 cm from the floor and 1 m from the refrigerator | L19: No. | M19: 7 | N19: =Elec_Est!E2743 -> 1198.92 | O19: =N19*M19 -> 8392.44
A22: T | B22: SYSTEM ON EF/3 | I22: =I19+1 -> 4 | K22: Refrigerant leak control system which automatically triggers visual and audible alarms inside the refrigeration plant room and outside each entrance to the refrigeration plant room, starts mechanical ventilation, and shuts down the system when activated. | L22: L/S | M22: 1 | N22: =Elec_Est!E2764 -> 6720.5 | O22: =N22*M22 -> 6720.5
K23: A remote (emergency) switching device for stopping the refrigeration system must be provided outside the room (near the door). A similarly functioning switch must be placed in a suitable location within the room.
A24: 4 | B24: Extract fan reference EF/3 complete with mounting hardware, speed controller, flexible duct connections, supports, A.V.M. power supplies etc., as specified. | C24: 1 | D24: No. | E24: =Elec_Est!#REF! -> #REF! | F24: =E24*C24 -> #REF! | G24: 2
K44: Total carried forward to summary page | O44: =SUM(O7:O42) -> 15366.1
A53: S | B53: Total carried forward to summary page | F53: =SUM(F7:F51) -> #REF!

Sheet AC_Split_Unit_BOQ
A1: BILL OF QUANTITIES
A2: AC SPLIT UNIT
A5: Item | C5: Qty | D5: Unit | E5: Rate in € | F5: Total
A7: 1.0T | B7: Air cooled packaged heat pump air-conditioning units for Electrical switchgear room, wall mounted type complete with condensing units, controls and power wiring between indoor and outdoor unit, supporting brackets, refrigerant piping, drain pump, insulation, drains, etc
A9: a. | B9: a. AC/1 | C9: 1 | D9: No | E9: =Elec_Est!E2808 -> 58 | F9: =E9*C9 -> 58 | G9: 3
A55: S | B55: Total carried forward to summary page | F55: =SUM(F7:F53) -> 58

Sheet Commissioning_BOQ
A1: BILL OF QUANTITIES
A2: COMMISSIONING AND DOCUMENTATION
A5: Item | C5: Qty | D5: Unit | E5: Rate in € | F5: Total
A7: 1 | B7: Carry out all necessary testing and commissioning to the satisfaction of the Client's Engineer. All commissioning documentation is to be certified for correctness and signed by a Malta accredited Warranted Electrical Engineer, also holding a locally accredited Authorization B, on behalf of the appointed contractor. | C7: 1 | D7: LS | E7: =Elec_Est!Q2842 -> Included with electrical quotation
B9: All costs associated with phasing of works related to chilled water plant and phasing of commissioning to ensure continuous supply of chilled water to the Hotel are to be included in the quoted rates.
A12: =A7+1 -> 2 | B12: Provide sufficient training on the operation and maintenance of all plant and systems to the Employer's representatives as specified. | C12: 1 | D12: LS | F12: =E12*C12 -> 0
A15: =A12+1 -> 3 | B15: Supply and hand-over two complete sets of operation and maintenance manuals together with drawings of works "As Fitted". These shall include: wiring diagrams; test / commissioning data and certificates; equipment data, including manufacturer's details, schedules, specifications and selection / performance data and parts lists. In addition an electronic copy of the "As Fitted" drawings and manuals are to be furnished in both ACAD and pdf format. | C15: 1 | D15: LS | F15: =E15*C15 -> 0
A42: P | B42: Total carried forward to summary page | F42: =SUM(F7:F40) -> 0
A47: END!

Sheet Maintenance_BOQ
A1: BILL OF QUANTITIES
A2: MAINTENANCE
A5: Item | B5: Description | D5: Unit | E5: Qty | F5: Rate in € | G5: Total
A7: 1 | C7: Allow for 3 years preventative maintenance for all contract scope including remote monitoring by factory engineers using cloud based software | D7: Years | E7: 3 | G7: =F7*E7 -> 0
A10: =A7+1 -> 2 | C10: Rate for additional 1 years preventative maintenance for all contract scope including remote monitoring by factory engineers using cloud based software | D10: Rate only | E10: 1 | G10: Rate only
A55: P | C55: Total carried forward to summary page | G55: =SUM(G7:G53) -> 0
A59: END!

Sheet Fire_Barrier_BOQ
A1: BILL OF QUANTITIES
A2: FIRE STOPPING
A5: Item | C5: Qty | D5: Unit | E5: Rate in € | F5: Total
A10: 1 | B10: Fire barrier provisions to maintain fire compartmentation as, required around and within all M&E services. Contractor, to provide itemised cost breakdown under this sheet. | C10: 1 | D10: LS | E10: =Elec_Est!E2886 -> 659.9 | F10: =C10*E10 -> 659.9
A56: P | B56: Total carried forward to summary page | F56: =SUM(F6:F54) -> 659.9
A60: END!

Sheet Prelims_BOQ
A1: BILL OF QUANTITIES
A2: PRELIMINARIES
A5: Item | C5: Qty | D5: Unit | E5: Rate in € | F5: Total
A7: 1 | B7: Mobilisation and demobilisation including setting up of workshop storage facilities and their security. | C7: 1 | D7: LS | E7: =Elec_Est!E2898 -> 411.78 | F7: =E7*C7 -> 411.78
A10: =A7+1 -> 2 | B10: Safety clothing for all site personnel in accordance with statutory requirements. | C10: 1 | D10: LS | E10: =Elec_Est!E2904 -> 514.72 | F10: =E10*C10 -> 514.72
A13: =A10+1 -> 3 | B13: Allowance for weekly progress meetings within project execution period. | C13: 1 | D13: LS | E13: =Elec_Est!E2910 -> 1029.44 | F13: =E13*C13 -> 1029.44
A16: =A13+1 -> 4 | B16: Provision of instrumentation used for commissioning purposes including evidence of associated valid calibration certificates. | C16: 1 | D16: LS | E16: =Elec_Est!Q2916 -> Included
A19: =A16+1 -> 5 | B19: Two copies of a complete set of installation drawings allowing for coordination with sub-contractors, client, interior designer, etc. as applicable. | C19: 1 | D19: LS | E19: =Elec_Est!E2922 -> 615.03 | F19: =E19*C19 -> 615.03
A22: =A19+1 -> 6 | B22: Rate only for the re-issue of one installation drawing, if so requested by the engineer, to include the changes requested through instructions and revisions identified during project execution. | C22: 1 | D22: No | E22: =Elec_Est!E2928 -> 51.47 | F22: Rate Only per drawing
A25: =A22+1 -> 7 | B25: Provision for a quality control engineer to ensure that the items being proposed are in accordance with technical specification and will fulfil the project requirements. | C25: 1 | D25: LS | E25: =Elec_Est!E2934 -> 0 | F25: =E25*C25 -> 0
A28: =A25+1 -> 8 | B28: Provision for a Quality Control Engineer to certify that the equipment and materials are installed, tested and commissioned in accordance with manufacturer's recommendations and / or relevant statutory requirements and / or CIBSE and / or equal and approved documents. | C28: 1 | D28: LS | E28: =Elec_Est!Q2948 -> Included
A31: =A28+1 -> 9 | B31: Allow for the preparation of project administration including minutes of progress meetings and other documentation required by the project Engineer / Client. | C31: 1 | D31: LS | E31: =Elec_Est!E2954 -> 0 | F31: =E31*C31 -> 0
A34: =A31+1 -> 10 | B34: Provision of signing of commissioning documentation by an independent Warranted Engineer. | C34: 1 | D34: LS | E34: =Elec_Est!E2960 -> 171.57 | F34: =E34*C34 -> 171.57
A40: P | B40: Total carried forward to summary page | F40: =SUM(F7:F38) -> 2742.54
A46: Item | C46: Qty | D46: Unit | E46: Rate in € | F46: Total
A48: =A34+1 -> 11 | B48: Provision of signing of as-fitted drawings by an independent Warranted Engineer. | C48: 1 | D48: LS | E48: =Elec_Est!E2972 -> 171.57 | F48: =E48*C48 -> 171.57
A51: =A48+1 -> 12 | B51: To allow for builders works in accordance to the preamble section of the technical specifications. | C51: 1 | D51: LS | E51: =Elec_Est!E2978 -> 1055.84 | F51: =E51*C51 -> 1055.84
A54: =A51+1 -> 13 | B54: Provision for a recognised Health and Safety Officer. | C54: 1 | D54: LS | E54: =Elec_Est!E2984 -> 0 | F54: =E54*C54 -> 0
A57: =A54+1 -> 14 | B57: Provision for completing the necessary risk assessment and method statements required. | C57: 1 | D57: LS | E57: =Elec_Est!E2990 -> 0 | F57: =E57*C57 -> 0
A97: P | B97: Total carried forward to summary page | F97: =SUM(F48:F94) -> 1227.41
A103: END!

Sheet Comm_BOQ
A1: BILL OF QUANTITIES
A2: COMMISSIONING AND DOCUMENTATION
A5: Item | C5: Qty | D5: Unit | E5: Rate in € | F5: Total
A7: 1 | B7: Carry out all necessary testing and commissioning to the satisfaction of the Engineer. All commissioning documentation is to be certified for correctness and signed by a Warranted Engineer. | C7: 1 | D7: LS | E7: =Elec_Est!E3006 -> 1911.03 | F7: =E7*C7 -> 1911.03
B9: All costs associated with phasing of works related to chilled water plant and phasing of commissioning to ensure continuous supply of chilled water to the Hotel are to be included in the quoted rates.
A12: =A7+1 -> 2 | B12: Provide sufficient training on the operation and maintenance of all plant and systems to the Employer's representatives as specified. | C12: 1 | D12: LS | E12: =Elec_Est!E3029 -> 944.57 | F12: =E12*C12 -> 944.57
A15: =A12+1 -> 3 | B15: Supply and hand-over two complete sets of operation and maintenance manuals together with drawings of works "As Fitted". These shall include: wiring diagrams; test / commissioning data and certificates; equipment data, including manufacturer's details, schedules, specifications and selection / performance data and parts lists. In addition an electronic copy of the "As Fitted" drawings and manuals are to be furnished in both ACAD and pdf format. | C15: 1 | D15: LS | E15: =Elec_Est!E3051 -> 1949.91 | F15: =E15*C15 -> 1949.91
B44: Total carried forward to summary page | F44: =SUM(F7:F42) -> 4805.51
A48: END!

Sheet Maint_BOQ
A1: BILL OF QUANTITIES
A2: MAINTENANCE
A5: Item | C5: Qty | D5: Unit | E5: Rate in € | F5: Total
A7: 1 | B7: Allow for 3 years preventative maintenance for all contract scope including remote monitoring by factory engineers using cloud based software | C7: 3 | D7: Years | E7: =Elec_Est!E3082 -> 9864.04 | F7: =E7*C7 -> 29592.12
A10: =A7+1 -> 2 | B10: Rate for additional 1 years preventative maintenance for all contract scope including remote monitoring by factory engineers using cloud based software | C10: 1 | D10: Rate only | E10: =Elec_Est!E3103 -> 11081.29 | F10: Rate only
B55: Total carried forward to summary page | F55: =SUM(F7:F53) -> 29592.12
A58: END!
