Workbook
Name Access_Control: #REF!
Name Access_Control: #REF!
Name Access_Control: #REF!
Name AREAS: ML_Sum!$X$1:$AD$16
Name AREAS: #REF!
Name AREAS: ML_Sum!$X$1:$AD$16
Name CCTV: #REF!
Name CCTV: #REF!
Name CCTV: #REF!
Name Commissioning: Elec_Est!#REF!
Name Commissioning: Old_Est!$A$1146
Name Commissioning: Elec_Est!#REF!
Name Data: #REF!
Name Data: #REF!
Name Data: #REF!
Name Electrical: Elec_Est!#REF!
Name Electrical: Old_Est!$A$16
Name Electrical: Elec_Est!#REF!
Name Fire_Alarm: #REF!
Name Fire_Alarm: #REF!
Name Fire_Alarm: #REF!
Name Fire_Barriers: Elec_Est!#REF!
Name Fire_Barriers: Old_Est!$A$1120
Name Fire_Barriers: Elec_Est!#REF!
Name FO: #REF!
Name FO: #REF!
Name FO: #REF!
Name Guard: #REF!
Name Guard: #REF!
Name Guard: #REF!
Name Intercom: #REF!
Name Intercom: #REF!
Name Intercom: #REF!
Name Intruder_Alarm: #REF!
Name Intruder_Alarm: #REF!
Name Intruder_Alarm: #REF!
Name Preliminaries: Old_Est!#REF!
Name Preliminaries: Elec_Est!#REF!

Sheet Notes
A1: NOTES | C1: Rev: 235
C2: checkdesc
A3: ELECTRICAL | C3: Elec_Rates
C4: Elec_Est
A5: Dist Boards | C5: Elv_Rates
A6: 1 | C6: ELV_Est
A7: 2 | C7: Ext_Quote
C8: Int_Quote
A9: Wiring Accessories | C9: Est_BOQ
A10: 1
A11: 2 | C11: Camilleri&Cuschieri Tenders
C12: Conduit
A13: ELV | C13: Wiring
C14: Supply
A15: Fire Alarm
A16: 1
A17: 2
A18: 3
A20: Data
A21: 1
A22: 2
A23: 3

Sheet ML_Sum
B1: CLIENT: | C1: 1 | D1: Eden Lesuire Group | G1: TRUE | H1: TRUE | I1: 1 | J1: =$Q109 -> 1 | K1: =$Q119 -> 1 | L1: =$Q129 -> 1 | M1: =$Q139 -> 1 | N1: =$Q149 -> 1 | O1: =$Q159 -> 1 | Q1: =IF(C1=1,"€","Curr?") -> € | R1: Recon /Lab.Cont >> | S1: =IF($S$39="PRINT","R","Do Not Print") -> R | T1: 1 | V1: {=IF(OR(X1=AREAS),1,0)} -> 1 | W1: BOQ | X1: x | Y1: x | Z1: x | AA1: x | AB1: x | AC1: x | AD1: x
B2: PROJECT: | C2: =IF($D$6="VAT INCLUDED",1.18,1)*(1-$Q2)*$C$1 -> 0.97379223 | D2: Intercontinental - Plant Retrofit | F2: Electrical | G2: TRUE | I2: 2 | J2: =$Q110 -> 1 | K2: =$Q120 -> 1 | L2: =$Q130 -> 1 | M2: =$Q140 -> 1 | N2: =$Q150 -> 1 | O2: =$Q160 -> 1 | Q2: 0.026207766 | R2: ="A) " & IF($S2=0,"",ROUND($S2,2) & "-" & ROUND($T2/$D$9,2)) -> A) 1.35-1.35 | S2: 1.35 | T2: =$S2*$D$9 -> 37.071 | U2: Mark up as advised by Alexei on 11/09.2025 | X2: x | Y2: x | Z2: x | AA2: x | AB2: x | AC2: x | AD2: x
B3: JOB DESC: | C3: =IF($D$6="VAT INCLUDED",1.18,1)*(1-$Q3)*$C$1 -> 0.97379223 | D3: Retrofitting works for the Electrical Installations | F3: ECA (Technician) | G3: TRUE | I3: 3 | J3: =$Q111 -> 1 | K3: =$Q121 -> 1 | L3: =$Q131 -> 1 | M3: =$Q141 -> 1 | N3: =$Q151 -> 1 | O3: =$Q161 -> 1 | Q3: 0.026207766 | R3: ="B) " & IF($S3=0,"",ROUND($S3,2) & "-" & ROUND($T3/$D$9,2)) -> B) 1.35-1.66 | S3: 1.35 | T3: =$S3*33.73 -> 45.5355 | U3: Mark up as advised by Alexei on 11/09.2026 | X3: x | Y3: x | Z3: x | AA3: x | AB3: x | AC3: x | AD3: x
B4: INT. QUOT No: | C4: =IF($D$6="VAT INCLUDED",1.18,1)*(1-$Q4)*$C$1 -> 0.97379223 | D4: EL25-0477 | F4: ECA (Engineer) | G4: TRUE | I4: 4 | J4: =$Q112 -> 1 | K4: =$Q122 -> 1 | L4: =$Q132 -> 1 | M4: =$Q142 -> 1 | N4: =$Q152 -> 1 | O4: =$Q162 -> 1 | Q4: 0.026207766 | R4: ="C) " & IF($S4=0,"",ROUND($S4,2) & "-" & ROUND($T4/$D$9,2)) -> C) 1.35-1.47 | S4: 1.35 | T4: =$S4*30 -> 40.5 | U4: Mark up as advised by Alexei on 11/09.2027 | X4: x | Y4: x | Z4: x | AA4: x | AB4: x | AC4: x | AD4: x
B5: CLIENTs REF: | C5: =IF($D$6="VAT INCLUDED",1.18,1)*(1-$Q5)*$C$1 -> 1 | D5: Tender | F5: Megaline | G5: TRUE | I5: 5 | J5: =$Q113 -> 1 | K5: =$Q123 -> 1 | L5: =$Q133 -> 1 | M5: =$Q143 -> 1 | N5: =$Q153 -> 1 | O5: =$Q163 -> 1 | R5: ="D) " & IF($S5=0,"",ROUND($S5,2) & "-" & ROUND($T5/$D$9,2)) -> D) 1-1.35 | S5: 1 | T5: =$S2*$D$9 -> 37.071 | X5: x | Y5: x | Z5: x | AA5: x | AB5: x | AC5: x | AD5: x
B6: VAT: | C6: =IF($D$6="VAT INCLUDED",1.18,1)*(1-$Q6)*$C$1 -> 1 | D6: VAT EXCL. | G6: TRUE | I6: 6 | J6: =$Q114 -> 1 | K6: =$Q124 -> 1 | L6: =$Q134 -> 1 | M6: =$Q144 -> 1 | N6: =$Q154 -> 1 | O6: =$Q164 -> 1 | R6: ="E) " & IF($S6=0,"",ROUND($S6,2) & "-" & ROUND($T6/$D$9,2)) -> E) | X6: x | Y6: x | Z6: x | AA6: x | AB6: x | AC6: x | AD6: x
B7: SAVED ON: | C7: =IF($D$6="VAT INCLUDED",1.18,1)*(1-$Q7)*$C$1 -> 1 | D7: 45866 | G7: TRUE | I7: 7 | J7: =$Q115 -> 1 | K7: =$Q125 -> 1 | L7: =$Q135 -> 1 | M7: =$Q145 -> 1 | N7: =$Q155 -> 1 | R7: ="F) " & IF($S7=0,"",ROUND($S7,2) & "-" & ROUND($T7/$D$9,2)) -> F) | X7: x | Y7: x | Z7: x | AA7: x | AB7: x | AC7: x | AD7: x
B8: ESTIMATOR: | C8: =IF($D$6="VAT INCLUDED",1.18,1)*(1-$Q8)*$C$1 -> 1 | D8: M.Scicluna | G8: TRUE | I8: 8 | J8: =$Q116 -> 1 | K8: =$Q126 -> 1 | L8: =$Q136 -> 1 | M8: =$Q146 -> 1 | N8: =$Q156 -> 1 | R8: ="G) " & IF($S8=0,"",ROUND($S8,2) & "-" & ROUND($T8/$D$9,2)) -> G) | X8: x | Y8: x | Z8: x | AA8: x | AB8: x | AC8: x | AD8: x
B9: LAB. COST: | C9: =IF($D$6="VAT INCLUDED",1.18,1)*(1-$Q9)*$C$1 -> 1 | D9: 27.46 | E9: Cost for 2025 | G9: TRUE | I9: 9 | J9: =$Q117 -> 1 | K9: =$Q127 -> 1 | L9: =$Q137 -> 1 | M9: =$Q147 -> 1 | N9: =$Q157 -> 1 | R9: ="H) " & IF($S9=0,"",ROUND($S9,2) & "-" & ROUND($T9/$D$9,2)) -> H) | X9: x | Y9: x | Z9: x | AA9: x | AB9: x | AC9: x | AD9: x
C10: =IF($D$6="VAT INCLUDED",1.18,1)*(1-$Q10)*$C$1 -> 1 | G10: TRUE | I10: 10 | J10: =$Q118 -> 1 | K10: =$Q128 -> 1 | L10: =$Q138 -> 1 | M10: =$Q148 -> 1 | N10: =$Q158 -> 1 | O10: =Q108 -> 1 | R10: =" I) " & IF($S10=0,"",ROUND($S10,2) & "-" & ROUND($T10/$D$9,2)) -> I) | X10: x | Y10: x | Z10: x | AA10: x | AB10: x | AC10: x | AD10: x
C11: =IF($D$6="VAT INCLUDED",1.18,1)*(1-$Q11)*$C$1 -> 1 | R11: ="J) " & IF($S11=0,"",ROUND($S11,2) & "-" & ROUND($T11/$D$9,2)) -> J) | X11: x | Y11: x | Z11: x | AA11: x | AB11: x | AC11: x | AD11: x
C12: =IF($D$6="VAT INCLUDED",1.18,1)*(1-$Q12)*$C$1 -> 0.97379223 | G12: SYSTEMS | H12: SYSTEMS | I12: SYSTEMS | J12: SYSTEMS | K12: SYSTEMS | L12: SYSTEMS | M12: SYSTEMS | N12: SYSTEMS | O12: SYSTEMS | P12: SYSTEMS | Q12: 0.026207766 | R12: MIXED - X,Y ) | S12: MAT MU | T12: LAB RATE | X12: x | Y12: x | Z12: x | AA12: x | AB12: x | AC12: x | AD12: x
B13: MATERIAL & LABOUR SUMMARY | G13: ItemCode | H13: CostCode | I13: MAKE | J13: PART_NO | K13: MARKUP | L13: TYPE | M13: LIST_P | N13: SET | O13: FIX | P13: DATE | Q13: %Dsct in BOQ | R13: MATMU-LABMU | S13: MAT CONT >> | T13: =SUM(Q108:Q164)/57 -> 1
B14: =IF($D$6<>"VAT EXCL.", "QUOTE ISSUED WITH VAT INCLUDED", "") | X14: x | Y14: x | Z14: x | AA14: x | AB14: x | AC14: x | AD14: x
Q15: =(C72-F35)/C72 -> 0.013791728 | R15: Average Discount applied in BOQ (Q2-Q12) | X15: x | Y15: x | Z15: x | AA15: x | AB15: x | AC15: x | AD15: x
B16: =IF($W$1<>"BOQ", "DIFF SET TO " & W1,"") | Q16: =(F35-E35)/F35 -> 0 | R16: Average Discount applied on Totals (Q23-Q32) | X16: x | Y16: x | Z16: x | AA16: x | AB16: x | AC16: x | AD16: x
Q17: =F74 -> 0.013791728 | R17: Overall Discount
B18: =IF(AND(G1,G2,G3,G4,G5,G6,G7,G8,G9,G10,H1)=TRUE, "", "CHECKLIST INCOMPLETE !" )
B19: =IF(ABS(SUM(A23:A32))>100,"[Discy A-J] are high, Check it out."," ") | Q19: =R83 -> 1.1482431 | R19: Overall Markup (Final Selling Excl.VAT/Total Cost )
E21: DISCOUNTED | F21: SELLING | Q21: % Discnt | R21: MATERIAL | T21: LABOUR
A22: Discy.A-J | B22: Markup/LRate | E22: ="SELLING " & $Q$1 -> SELLING € | F22: =$Q$1 -> € | G22: VAT/DISC | H22: MU | I22: LABRATE | J22: LABCOST | Q22: on Totals | R22: € | T22: Pair Hrs. | W22: Undiscounted values | AC22: Discounted Values
A23: =IF($F23=0,"",($F23/$C2)-($R23*$S2+$T23*$T2)) -> -0.0025902801 | B23: =IF(F23=0,"",IF(R23=0,"A) "&"---, "&ROUND(($F23/$C2-($R23*$S2))/$T23,2),IF(T23=0,"A) "&ROUND(($F23/$C2)/$R23,2),"A) "&ROUND(($F23/$C2-($T23*$T2))/$R23,2)&", " &ROUND(($F23/$C2-($R23*$S2))/$T23,2)))) -> A) 1.35, 37.07 | D23: =IF($F2="","",$F2) -> Electrical | E23: =F23*(1-Q23) -> 147372.97 | F23: =Elec_Est!F953 -> 147372.97 | G23: =C2 -> 0.97379223 | H23: =$S2 -> 1.35 | I23: =$T2 -> 37.071 | J23: =$D$9 -> 27.46 | R23: =Elec_Est!R953 -> 40888.73 | T23: =Elec_Est!T953 -> 2593.387 | W23: 151339.24 | X23: 151339.24 | Y23: 40888.73 | AA23: 2593.387 | AC23: =W23*C2 -> 147372.98
A24: =IF($F24=0,"",($F24/$C3)-($R24*$S3+$T24*$T3)) -> -0.007578436 | B24: =IF(F24=0,"",IF(R24=0,"A) "&"---, "&ROUND(($F24/$C3-($R24*$S3))/$T24,2),IF(T24=0,"A) "&ROUND(($F24/$C3)/$R24,2),"A) "&ROUND(($F24/$C3-($T24*$T3))/$R24,2)&", " &ROUND(($F24/$C3-($R24*$S3))/$T24,2)))) -> A) 1.35, 45.54 | D24: =IF($F3="","",$F3) -> ECA (Technician) | E24: =F24*(1-Q24) -> 42268.427 | F24: =Elec_Est!F954 -> 42268.427 | G24: =C3 -> 0.97379223 | H24: =$S3 -> 1.35 | I24: =$T3 -> 45.5355 | J24: =$D$9 -> 27.46 | R24: =Elec_Est!R954 -> 24878.05 | T24: =Elec_Est!T954 -> 215.67 | W24: 43406.01 | X24: 43406.01 | Y24: 24878.05 | AA24: 215.67 | AC24: =W24*C3 -> 42268.435
A25: =IF($F25=0,"",($F25/$C4)-($R25*$S4+$T25*$T4)) -> 0.004501782 | B25: =IF(F25=0,"",IF(R25=0,"A) "&"---, "&ROUND(($F25/$C4-($R25*$S4))/$T25,2),IF(T25=0,"A) "&ROUND(($F25/$C4)/$R25,2),"A) "&ROUND(($F25/$C4-($T25*$T4))/$R25,2)&", " &ROUND(($F25/$C4-($R25*$S4))/$T25,2)))) -> A) 1.35, 40.5 | D25: =IF($F4="","",$F4) -> ECA (Engineer) | E25: =F25*(1-Q25) -> 11447.054 | F25: =Elec_Est!F955 -> 11447.054 | G25: =C4 -> 0.97379223 | H25: =$S4 -> 1.35 | I25: =$T4 -> 40.5 | J25: =$D$9 -> 27.46 | R25: =Elec_Est!R955 -> 3000 | T25: =Elec_Est!T955 -> 190.25 | W25: 11755.13 | X25: 11755.13 | Y25: 3000 | AA25: 190.25 | AC25: =W25*C4 -> 11447.054
A26: =IF($F26=0,"",($F26/$C5)-($R26*$S5+$T26*$T5)) -> 0 | B26: =IF(F26=0,"",IF(R26=0,"A) "&"---, "&ROUND(($F26/$C5-($R26*$S5))/$T26,2),IF(T26=0,"A) "&ROUND(($F26/$C5)/$R26,2),"A) "&ROUND(($F26/$C5-($T26*$T5))/$R26,2)&", " &ROUND(($F26/$C5-($R26*$S5))/$T26,2)))) -> A) 1 | D26: =IF($F5="","",$F5) -> Megaline | E26: =F26*(1-Q26) -> 185902.47 | F26: =Elec_Est!F956 -> 185902.47 | G26: =C5 -> 1 | H26: =$S5 -> 1 | I26: =$T5 -> 37.071 | J26: =$D$9 -> 27.46 | R26: =Elec_Est!R956 -> 185902.47 | T26: =Elec_Est!T956 -> 0 | W26: 185902.47 | X26: 185902.47 | Y26: 185902.47 | AA26: 0 | AC26: =W26*C5 -> 185902.47
A27: =IF($F27=0,"",($F27/$C6)-($R27*$S6+$T27*$T6)) | B27: =IF(F27=0,"",IF(R27=0,"A) "&"---, "&ROUND(($F27/$C6-($R27*$S6))/$T27,2),IF(T27=0,"A) "&ROUND(($F27/$C6)/$R27,2),"A) "&ROUND(($F27/$C6-($T27*$T6))/$R27,2)&", " &ROUND(($F27/$C6-($R27*$S6))/$T27,2)))) | D27: =IF($F6="","",$F6) | E27: =F27*(1-Q27) -> 0 | F27: =Elec_Est!F957 -> 0 | G27: =C6 -> 1 | H27: =$S6 -> 0 | I27: =$T6 -> 0 | J27: =$D$9 -> 27.46 | R27: =Elec_Est!R957 -> 0 | T27: =Elec_Est!T957 -> 0 | W27: The above costs do not include Preliminaires, Fire stopping, commissioning and maintenance
A28: =IF($F28=0,"",($F28/$C7)-($R28*$S7+$T28*$T7)) | B28: =IF(F28=0,"",IF(R28=0,"A) "&"---, "&ROUND(($F28/$C7-($R28*$S7))/$T28,2),IF(T28=0,"A) "&ROUND(($F28/$C7)/$R28,2),"A) "&ROUND(($F28/$C7-($T28*$T7))/$R28,2)&", " &ROUND(($F28/$C7-($R28*$S7))/$T28,2)))) | D28: =IF($F7="","",$F7) | E28: =F28*(1-Q28) -> 0 | F28: =Elec_Est!F958 -> 0 | G28: =C7 -> 1 | H28: =$S7 -> 0 | I28: =$T7 -> 0 | J28: =$D$9 -> 27.46 | R28: =Elec_Est!R958 -> 0 | T28: =Elec_Est!T958 -> 0
A29: =IF($F29=0,"",($F29/$C8)-($R29*$S8+$T29*$T8)) | B29: =IF(F29=0,"",IF(R29=0,"A) "&"---, "&ROUND(($F29/$C8-($R29*$S8))/$T29,2),IF(T29=0,"A) "&ROUND(($F29/$C8)/$R29,2),"A) "&ROUND(($F29/$C8-($T29*$T8))/$R29,2)&", " &ROUND(($F29/$C8-($R29*$S8))/$T29,2)))) | D29: =IF($F8="","",$F8) | E29: =F29*(1-Q29) -> 0 | F29: =Elec_Est!F959 -> 0 | G29: =C8 -> 1 | H29: =$S8 -> 0 | I29: =$T8 -> 0 | J29: =$D$9 -> 27.46 | R29: =Elec_Est!R959 -> 0 | T29: =Elec_Est!T959 -> 0
A30: =IF($F30=0,"",($F30/$C9)-($R30*$S9+$T30*$T9)) | B30: =IF(F30=0,"",IF(R30=0,"A) "&"---, "&ROUND(($F30/$C9-($R30*$S9))/$T30,2),IF(T30=0,"A) "&ROUND(($F30/$C9)/$R30,2),"A) "&ROUND(($F30/$C9-($T30*$T9))/$R30,2)&", " &ROUND(($F30/$C9-($R30*$S9))/$T30,2)))) | D30: =IF($F9="","",$F9) | E30: =F30*(1-Q30) -> 0 | F30: =Elec_Est!F960 -> 0 | G30: =C9 -> 1 | H30: =$S9 -> 0 | I30: =$T9 -> 0 | J30: =$D$9 -> 27.46 | R30: =Elec_Est!R960 -> 0 | T30: =Elec_Est!T960 -> 0
A31: =IF($F31=0,"",($F31/$C10)-($R31*$S10+$T31*$T10)) | B31: =IF(F31=0,"",IF(R31=0,"A) "&"---, "&ROUND(($F31/$C10-($R31*$S10))/$T31,2),IF(T31=0,"A) "&ROUND(($F31/$C10)/$R31,2),"A) "&ROUND(($F31/$C10-($T31*$T10))/$R31,2)&", " &ROUND(($F31/$C10-($R31*$S10))/$T31,2)))) | D31: =IF($F10="","",$F10) | E31: =F31*(1-Q31) -> 0 | F31: =Elec_Est!F961 -> 0 | G31: =C10 -> 1 | H31: =$S10 -> 0 | I31: =$T10 -> 0 | J31: =$D$9 -> 27.46 | R31: =Elec_Est!R961 -> 0 | T31: =Elec_Est!T961 -> 0
A32: =IF($F32=0,"",($F32/$C11)-($R32*$S11+$T32*$T11)) | B32: =IF(F32=0,"",IF(R32=0,"A) "&"---, "&ROUND(($F32/$C11-($R32*$S11))/$T32,2),IF(T32=0,"A) "&ROUND(($F32/$C11)/$R32,2),"A) "&ROUND(($F32/$C11-($T32*$T11))/$R32,2)&", " &ROUND(($F32/$C11-($R32*$S11))/$T32,2)))) | D32: =IF($F11="","",$F11) | E32: =F32*(1-Q32) -> 0 | F32: =Elec_Est!F962 -> 0 | G32: =C11 -> 1 | H32: =$S11 -> 0 | I32: =$T11 -> 0 | J32: =$D$9 -> 27.46 | R32: =Elec_Est!R962 -> 0 | T32: =Elec_Est!T962 -> 0
C33: MIXED
A35: Discy.L | B35: ='SUMM PG '!H200 -> 386990.92 | E35: =SUM(E23:E32) -> 386990.92 | F35: =SUM(F23:F32) -> 386990.92 | R35: =SUM(R23:R32) -> 254669.25 | T35: =SUM(T23:T32) -> 2999.307
A36: =IF(A39=0,"0.00",A39-(A38*A37)) -> 0.00 | B36: BOQ TOTAL | E36: ="ESTIM TOTAL (" & $Q$1 & ")" -> ESTIM TOTAL (€)
A37: 1.125 | B37: <1 Actual LabCont | R37: =R165 -> 254667.68 | S37: C.C.Totals | T37: =T165 -> 2999.31
B38: <2 Phrs @ 1.00
B39: <3 Phrs @ Actual | Q39: Discy.T >> | R39: =R37-R35 -> -1.5711019 | S39: PRINT | T39: =T37-T35 -> 0.003
B41: Values Only on : | D41: 45911 | E41: 429609.01 | F41: 429609.01 | R41: 283529.33 | T41: 3027.307
B42: Values Only on : | D42: 45918 | E42: 431430.43 | F42: 431430.43 | R42: 283529.33 | T42: 3067.307 | U42: This includes 40 hours for the take over of the Trane controller as advised by Guy on 18.09.2025. This was submitted. It also includes preliminaries, fire stopping, commissioning and maintenance. These were transferred to ELM by Mech Div.
B43: Values Only on : | D43: 45930 | E43: 386990.92 | F43: 386990.92 | R43: 254669.25 | T43: 2999.307 | U43: As awarded excluding preliminaries, fire stopping, commissioning and maintenance.
A46: REMARKS:
A47: 1) VAT and Duties as above.
A48: 2)
A51: ESTIMATOR: | D51: =D8 -> M.Scicluna | Q51: APPROVED BY:
A53: SIGNED: | Q53: DATE APPROVED:
A55: FILE LOCATION: | D55: =CELL("filename") -> K:\est\Intercontinental Hotel\Estimates\Estimates Sept 2025\As Awarded Contract\[E25_0477_IH_Retro_Elec_Est_Rev_A_AW.xlsx]Elec_Est
B57: PANTA CONTRACTING LTD. - ELECTRICAL DIVISION
B58: CONTRACT / VARIATION INPUT DOCUMENT
S59: Copy to:-
D60: Client: | E60: =D1 -> Eden Lesuire Group | S60: Ms. S. Magri
D61: Project: | E61: =D2 -> Intercontinental - Plant Retrofit | S61: Mr. K. Micallef
D62: Job Description: | E62: =D3 -> Retrofitting works for the Electrical Installations | S62: Mr. A. Sciberras
D63: Quote No: | E63: =D4 -> EL25-0477
D64: Client's Ref: | E64: =D5 -> Tender
S65: File:-
D66: File No:
D67: Ext. Ref:
E70: Contract /Variation (Excl. VAT)
C72: =IF($A$33="MIXED",F23/(1-Q2)+F24/(1-Q3)+F25/(1-Q4)+F26/(1-Q5)+F27/(1-Q6)+F28/(1-Q7)+F29/(1-Q8)+F30/(1-Q9)+F31/(1-Q10)+F32/(1-Q11)-SUM(A23:A32), F23/(1-Q2)+F24/(1-Q3)+F25/(1-Q4)+F26/(1-Q5)+F27/(1-Q6)+F28/(1-Q7)+F29/(1-Q8)+F30/(1-Q9)+F31/(1-Q10)+F32/(1-Q11)) -> 392402.83 | E72: Estim.Sell before Discounts excl.VAT (€): | F72: =IF(D6="VAT INCLUDED",C72/($C$1*1.18),C72/$C$1) -> 392402.83
E74: Overall Discount: | F74: =(F72-F75)/F72 -> 0.013791728
E75: Final Sell after Discounts excl.VAT (€): | F75: =IF(D6="VAT INCLUDED",E35/($C$1*1.18),E35/$C$1) -> 386990.92
E77: Labour Rate - | F77: =$D$9 -> 27.46 | R77: Mech. Cost to us
D80: Mat. Cost | E80: Labour | F80: Total Cost | R80: Sell Excl.VAT / Total Cost
D81: € | E81: Pair.Hrs | F81: €
D83: =R165 -> 254667.68 | E83: =T165 -> 2999.31 | F83: =R165+S165 -> 337028.73 | R83: =IF(F83=0,0,F75/F83) -> 1.1482431
D84: ( From CostCode Totals )
R87: Advanced Payment:
R88: Retention:
R90: Awarded Date:
R91: Estimated Start Date:
R92: Estimated Completion Date:
D93: .................
D94: A. Sciberras | R94: Date issued:
D95: =NOW() -> 46030.6
D98: PANTA CONTRACTING LTD. - ELECTRICAL DIVISION
D99: ELECTRICAL AND ELV CONTRACT / VARIATION BUDGET COST
D101: Project: | E101: =E61 -> Intercontinental - Plant Retrofit
D102: Job Desc: | E102: =E62 -> Retrofitting works for the Electrical Installations
D103: Client's Ref: | E103: =E64 -> Tender
D106: COSTCODE | F106: Cost | Q106: Mat. | R106: Mat Cost | S106: Lab Cost @ | T106: Labour
F107: Code | Q107: Cont. | R107: € | S107: =$D$9 -> 27.46 | T107: Pair.Hrs
B108: V:56 | D108: BOQ RateOnly Items | P108: FIX | Q108: 1
B109: 1(J) | C109: cc | D109: Erection materials | F109: 501 | P109: 1 | Q109: 1 | R109: =Elec_Est!R974 -> 802.3238 | S109: =T109*$D$9 -> 837.53 | T109: =Elec_Est!T974 -> 30.5
B110: 2 | C110: cc | D110: Busbar Trunking | F110: 505 | P110: 1 | Q110: 1 | R110: =Elec_Est!R975 -> 0 | S110: =T110*$D$9 -> 0 | T110: =Elec_Est!T975 -> 0
B111: 3 | C111: cc | D111: Switchgear | F111: 510 | P111: 2 | Q111: 1 | R111: =Elec_Est!R976 -> 1012.02 | S111: =T111*$D$9 -> 494.28 | T111: =Elec_Est!T976 -> 18
B112: 4 | C112: cc | D112: MCC Equipment | F112: 511 | P112: 2 | Q112: 1 | R112: =Elec_Est!R977 -> 0 | S112: =T112*$D$9 -> 0 | T112: =Elec_Est!T977 -> 0
B113: 5 | C113: cc | D113: BMS Equipment | F113: 512 | P113: 2 | Q113: 1 | R113: =Elec_Est!R978 -> 23991.29 | S113: =T113*$D$9 -> 10168.987 | T113: =Elec_Est!T978 -> 370.32
B114: 6 | C114: cc | D114: PVC Pipes / Ducts | F114: 520 | P114: 1 | Q114: 1 | R114: =Elec_Est!R979 -> 0 | S114: =T114*$D$9 -> 0 | T114: =Elec_Est!T979 -> 0
B115: 7 | C115: cc | D115: High/medium voltage switchgear | F115: 530 | P115: 2 | Q115: 1 | R115: =Elec_Est!R980 -> 0 | S115: =T115*$D$9 -> 0 | T115: =Elec_Est!T980 -> 0
B116: 8 | C116: cc | D116: Power Transformers | F116: 550 | P116: 2 | Q116: 1 | R116: =Elec_Est!R981 -> 0 | S116: =T116*$D$9 -> 0 | T116: =Elec_Est!T981 -> 0
B117: 9 | C117: cc | D117: Control Panels | F117: 570 | P117: 2 | Q117: 1 | R117: =Elec_Est!R982 -> 4136.76 | S117: =T117*$D$9 -> 1537.76 | T117: =Elec_Est!T982 -> 56
B118: 10 | C118: cc | D118: Electrical Single Core Cables | F118: 615 | P118: 2 | Q118: 1 | R118: =Elec_Est!R983 -> 14.52 | S118: =T118*$D$9 -> 18.1236 | T118: =Elec_Est!T983 -> 0.66
B119: 11(K) | C119: cc | D119: Electrical Multicore Cables | F119: 616 | P119: 2 | Q119: 1 | R119: =Elec_Est!R984 -> 5678.7 | S119: =T119*$D$9 -> 1667.6458 | T119: =Elec_Est!T984 -> 60.73
B120: 12 | C120: cc | D120: ELV/BMS/Special Cables | F120: 617 | P120: 2 | Q120: 1 | R120: =Elec_Est!R985 -> 9996.6189 | S120: =T120*$D$9 -> 18606.896 | T120: =Elec_Est!T985 -> 677.6
B121: 13 | C121: cc | D121: Cable Accessories | F121: 620 | P121: 2 | Q121: 1 | R121: =Elec_Est!R986 -> 2038.84 | S121: =T121*$D$9 -> 5321.4185 | T121: =Elec_Est!T986 -> 193.788
B122: 14 | C122: cc | D122: Galv. Cable Trays | F122: 650 | P122: 1 | Q122: 1 | R122: =Elec_Est!R987 -> 597.77625 | S122: =T122*$D$9 -> 823.8 | T122: =Elec_Est!T987 -> 30
B123: 15 | C123: cc | D123: PVC Cable Trays | F123: 651 | P123: 1 | Q123: 1 | R123: =Elec_Est!R988 -> 0 | S123: =T123*$D$9 -> 0 | T123: =Elec_Est!T988 -> 0
B124: 16 | C124: cc | D124: Galv. Cable Basket | F124: 652 | P124: 1 | Q124: 1 | R124: =Elec_Est!R989 -> 0 | S124: =T124*$D$9 -> 0 | T124: =Elec_Est!T989 -> 0
B125: 17 | C125: cc | D125: Galv. Cable Ladder | F125: 654 | P125: 1 | Q125: 1 | R125: =Elec_Est!R990 -> 0 | S125: =T125*$D$9 -> 0 | T125: =Elec_Est!T990 -> 0
B126: 18 | C126: cc | D126: Galv. Cable Trunking | F126: 675 | P126: 1 | Q126: 1 | R126: =Elec_Est!R991 -> 0 | S126: =T126*$D$9 -> 0 | T126: =Elec_Est!T991 -> 0
...

Sheet Quote
A1: =IF(AND(UPPER(LEFT(TRIM($D$8),11))="01",UPPER(LEFT(TRIM($D$9),3))<>"ELM"),"PANTA RETAIL LTD.","PANTA CONTRACTING LIMITED") -> PANTA CONTRACTING LIMITED
A2: =IF(UPPER(LEFT(TRIM($D$9),3))="ELM","ELEC-FOR-MECH INTERNAL QUOTATION","ELECTRICAL INTERNAL QUOTATION") -> ELECTRICAL INTERNAL QUOTATION
B5: ATT: | D5: =IF(A2="Internal Quotation", "Mechanical Division","") | R5: Dated: | S5: =NOW() -> 46030.6
B6: CLIENT: | C6: Link to ML_SUM $D1 | D6: =ML_Sum!D1 -> Eden Lesuire Group
B7: PROJECT: | C7: Link to ML_SUM $D2 | D7: =ML_Sum!D2 -> Intercontinental - Plant Retrofit
B8: JOB DESC: | C8: Link to ML_SUM $D3 | D8: =ML_Sum!D3 -> Retrofitting works for the Electrical Installations
B9: QUOTE No: | C9: Link to ML_SUM $D4 | D9: =ML_Sum!D4 -> EL25-0477
B10: CLIENT's Ref: | C10: Link to ML_SUM $D5 | D10: =ML_Sum!D5 -> Tender
D22: Selling Price (€) : | E22: =ML_Sum!E35 -> 386990.92 | F22: =ML_Sum!D6 -> VAT EXCL. | G22: VAT EXCLUDED. | H22: VAT EXCLUDED. | I22: VAT EXCLUDED. | J22: VAT EXCLUDED. | K22: VAT EXCLUDED. | L22: VAT EXCLUDED. | M22: VAT EXCLUDED. | N22: VAT EXCLUDED. | O22: VAT EXCLUDED. | P22: VAT EXCLUDED.
A51: Signed for and on behalf of | Q51: Signed for and on behalf of
A52: Electrical Division | Q52: Division
Q54: Records
Q55: Mr. A. Sciberras
Q57: File

Sheet Elec_Rates
B1: CLIENT: | C1: =ML_Sum!$C1 -> 1 | D1: =ML_Sum!$D1 -> Eden Lesuire Group | F1: =ML_Sum!$F1 -> 0 | I1: 1 | J1: =ML_Sum!$J1 -> 1 | K1: =ML_Sum!$K1 -> 1 | L1: =ML_Sum!$L1 -> 1 | M1: =ML_Sum!$M1 -> 1 | N1: =ML_Sum!$N1 -> 1 | O1: =ML_Sum!$O1 -> 1 | Q1: =ML_Sum!$Q1 -> € | R1: R/Lab Cont | S1: =ML_Sum!$S1 -> R | T1: =ML_Sum!$T1 -> 1 | U1: =ML_Sum!W1 -> BOQ | V1: INCL | W1: MULT | X1: AREA | Y1: BOQ | Z1: TDWG | AA1: ACT | AB1: DIFF
B2: PROJECT: | C2: =ML_Sum!$C2 -> 0.97379223 | D2: =ML_Sum!$D2 -> Intercontinental - Plant Retrofit | F2: =ML_Sum!$F2 -> Electrical | I2: 2 | J2: =ML_Sum!$J2 -> 1 | K2: =ML_Sum!$K2 -> 1 | L2: =ML_Sum!$L2 -> 1 | M2: =ML_Sum!$M2 -> 1 | N2: =ML_Sum!$N2 -> 1 | O2: =ML_Sum!$O2 -> 1 | Q2: =ML_Sum!$Q2 -> 0.026207766 | R2: mu_A | S2: =ML_Sum!$S2 -> 1.35 | T2: =ML_Sum!$T2 -> 37.071
B3: JOB DESC: | C3: =ML_Sum!$C3 -> 0.97379223 | D3: =ML_Sum!$D3 -> Retrofitting works for the Electrical Installations | F3: =ML_Sum!$F3 -> ECA (Technician) | I3: 3 | J3: =ML_Sum!$J3 -> 1 | K3: =ML_Sum!$K3 -> 1 | L3: =ML_Sum!$L3 -> 1 | M3: =ML_Sum!$M3 -> 1 | N3: =ML_Sum!$N3 -> 1 | O3: =ML_Sum!$O3 -> 1 | Q3: =ML_Sum!$Q3 -> 0.026207766 | R3: mu_B | S3: =ML_Sum!$S3 -> 1.35 | T3: =ML_Sum!$T3 -> 45.5355
B4: QUOTE No: | C4: =ML_Sum!$C4 -> 0.97379223 | D4: =ML_Sum!$D4 -> EL25-0477 | F4: =ML_Sum!$F4 -> ECA (Engineer) | I4: 4 | J4: =ML_Sum!$J4 -> 1 | K4: =ML_Sum!$K4 -> 1 | L4: =ML_Sum!$L4 -> 1 | M4: =ML_Sum!$M4 -> 1 | N4: =ML_Sum!$N4 -> 1 | O4: =ML_Sum!$O4 -> 1 | Q4: =ML_Sum!$Q4 -> 0.026207766 | R4: mu_C | S4: =ML_Sum!$S4 -> 1.35 | T4: =ML_Sum!$T4 -> 40.5
B5: CLIENTs REF: | C5: =ML_Sum!$C5 -> 1 | D5: =ML_Sum!$D5 -> Tender | F5: =ML_Sum!$F5 -> Megaline | I5: 5 | J5: =ML_Sum!$J5 -> 1 | K5: =ML_Sum!$K5 -> 1 | L5: =ML_Sum!$L5 -> 1 | M5: =ML_Sum!$M5 -> 1 | N5: =ML_Sum!$N5 -> 1 | O5: =ML_Sum!$O5 -> 1 | Q5: =ML_Sum!$Q5 -> 0 | R5: mu_D | S5: =ML_Sum!$S5 -> 1 | T5: =ML_Sum!$T5 -> 37.071
B6: VAT/DUTIES: | C6: =ML_Sum!$C6 -> 1 | D6: =ML_Sum!$D6 -> VAT EXCL. | F6: =ML_Sum!$F6 -> 0 | I6: 6 | J6: =ML_Sum!$J6 -> 1 | K6: =ML_Sum!$K6 -> 1 | L6: =ML_Sum!$L6 -> 1 | M6: =ML_Sum!$M6 -> 1 | N6: =ML_Sum!$N6 -> 1 | O6: =ML_Sum!$O6 -> 1 | Q6: =ML_Sum!$Q6 -> 0 | R6: mu_E | S6: =ML_Sum!$S6 -> 0 | T6: =ML_Sum!$T6 -> 0
B7: SAVED ON: | C7: =ML_Sum!$C7 -> 1 | D7: 39364 | F7: =ML_Sum!$F7 -> 0 | I7: 7 | J7: =ML_Sum!$J7 -> 1 | K7: =ML_Sum!$K7 -> 1 | L7: =ML_Sum!$L7 -> 1 | M7: =ML_Sum!$M7 -> 1 | N7: =ML_Sum!$N7 -> 1 | O7: =ML_Sum!$O7 -> 0 | Q7: =ML_Sum!$Q7 -> 0 | R7: mu_F | S7: =ML_Sum!$S7 -> 0 | T7: =ML_Sum!$T7 -> 0
B8: ESTIMATOR: | C8: =ML_Sum!$C8 -> 1 | D8: =ML_Sum!$D8 -> M.Scicluna | F8: =ML_Sum!$F8 -> 0 | I8: 8 | J8: =ML_Sum!$J8 -> 1 | K8: =ML_Sum!$K8 -> 1 | L8: =ML_Sum!$L8 -> 1 | M8: =ML_Sum!$M8 -> 1 | N8: =ML_Sum!$N8 -> 1 | O8: =ML_Sum!$O8 -> 0 | Q8: =ML_Sum!$Q8 -> 0 | R8: mu_G | S8: =ML_Sum!$S8 -> 0 | T8: =ML_Sum!$T8 -> 0
B9: LABOUR RATE: | C9: =ML_Sum!$C9 -> 1 | D9: =ML_Sum!$D9 -> 27.46 | F9: =ML_Sum!$F9 -> 0 | I9: 9 | J9: =ML_Sum!$J9 -> 1 | K9: =ML_Sum!$K9 -> 1 | L9: =ML_Sum!$L9 -> 1 | M9: =ML_Sum!$M9 -> 1 | N9: =ML_Sum!$N9 -> 1 | O9: =ML_Sum!$O9 -> 0 | Q9: =ML_Sum!$Q9 -> 0 | R9: mu_H | S9: =ML_Sum!$S9 -> 0 | T9: =ML_Sum!$T9 -> 0
C10: =ML_Sum!$C10 -> 1 | F10: =ML_Sum!$F10 -> 0 | I10: 10 | J10: =ML_Sum!$J10 -> 1 | K10: =ML_Sum!$K10 -> 1 | L10: =ML_Sum!$L10 -> 1 | M10: =ML_Sum!$M10 -> 1 | N10: =ML_Sum!$N10 -> 1 | O10: =ML_Sum!$O10 -> 1 | Q10: =ML_Sum!$Q10 -> 0 | R10: mu_I | S10: =ML_Sum!$S10 -> 0 | T10: =ML_Sum!$T10 -> 0
C11: =ML_Sum!$C11 -> 1 | F11: =ML_Sum!$F11 -> 0 | Q11: =ML_Sum!$Q11 -> 0 | R11: mu_J | S11: =ML_Sum!$S11 -> 0 | T11: =ML_Sum!$T11 -> 0
C12: =ML_Sum!$C12 -> 0.97379223 | F12: =ML_Sum!$F12 -> 0 | Q12: =ML_Sum!$Q12 -> 0.026207766 | R12: MIXED | S12: =ML_Sum!$S12 -> MAT MU | T12: =ML_Sum!$T12 -> LAB RATE
G13: I_CODE | H13: C_CODE | I13: MAKE | J13: PART_NO | K13: MARKUP | L13: TYPE | M13: LIST_P | N13: P_FACT | O13: FIX | P13: DATE | Q13: %Dsct in BOQ | R13: MU TYPE | S13: MAT MU | T13: LAB RATE
K14: TB
C15: t | D15: Item:
D16: BMS points wiring
Q18: Multip
A19: 1 | B19: =Elec_Est!B1039 -> 202 | D19: 004# BMS point (Low level - Digital and Analogue) - Level 2 | K19: RATE | L19: RATE | Q19: =B19/A19 -> 202 | R19: =IF($B19=0,0,IF($S$1="R",ROUND(R28/$B19,2),R28/$B19)) -> 56.85 | T19: =IF($B19=0,0,IF($S$1="R",ROUND(T28/$B19,2),T28/$B19)) -> 4.39
D20: Based on: Level 2
A21: =$Q$19 *(7) -> 1414 | B21: m | D21: Conduit Galv. 20mm RATE | G21: COGV_011 | H21: 690 | I21: BAR | J21: 20mm | O21: 1 | P21: 34669 | Q21: 3.66 | R21: =$A21*Q21 -> 5175.24 | S21: =1.1 *(0.2) -> 0.22 | T21: =$A21*S21*$T$1 -> 311.08
A22: =$Q$19 *(35) -> 7070 | B22: m | D22: Indoor Screened 3c Cable 1.0mm | G22: CASP_018 | H22: 617 | I22: LAPP | J22: 110CY | O22: 2 | Q22: =0.62*1.25 -> 0.775 | R22: =$A22*Q22 -> 5479.25 | S22: =1.1 *(0.05) -> 0.055 | T22: =$A22*S22*$T$1 -> 388.85
A23: =$Q$19 *(2) -> 404 | B23: No | D23: Gland Skintop EExeII 16 x 1.0 (2-4core) | G23: CAAC_086 | H23: 620 | I23: (__) | O23: 2 | P23: 38148 | Q23: =1.1*1.5 -> 1.65 | R23: =$A23*Q23 -> 666.6 | S23: =1.1 *(0.1) -> 0.11 | T23: =$A23*S23*$T$1 -> 44.44
A24: =$Q$19 *(2) -> 404 | B24: No | D24: Cable Marker Wrap Around Type | G24: CAAC_025 | H24: 620 | I24: (__) | O24: 2 | Q24: 0.2 | R24: =$A24*Q24 -> 80.8 | S24: =1.1 *(0.03) -> 0.033 | T24: =$A24*S24*$T$1 -> 13.332
A25: =$Q$19 *(2*4) -> 1616 | B25: No | D25: Cable Lug 1.5 mm2 | G25: CAAC_004 | H25: 620 | I25: CTT | O25: 2 | P25: 34669 | Q25: 0.05 | R25: =$A25*Q25 -> 80.8 | S25: =1.1 *(0.01) -> 0.011 | T25: =$A25*S25*$T$1 -> 17.776
A26: =$Q$19 *(1) -> 202 | B26: No | D26: Labour to connect Mech Equip (FIX 3) | F26: Device | G26: LABO_009 | H26: 900 | I26: MISC | O26: 1 | R26: =$A26*Q26 -> 0 | S26: =1.1 *(0.5) -> 0.55 | T26: =$A26*S26*$T$1 -> 111.1 | U26: NoMat?
C27: << ==== TOTAL UNITS | R27: =$A27*Q27 -> 0 | T27: =$A27*S27*$T$1 -> 0
A28: d> | B28: =(R27+T27) -> 0 | D28: Sell_A | E28: =IF($B19=0,0,ROUND(ROUND(($R28*$S$2+($T28*$T$2))/$B19, 2)*$C$2,2)) -> 233.17 | F28: =ROUND($B19*$E28,2) -> 47100.34 | K28: ITEM | L28: ITEM | R28: =SUM(R20:R27) -> 11482.69 | T28: =SUM(T20:T27) -> 886.578
Q29: Multip
A30: 1 | B30: =Elec_Est!B1040 -> 72 | D30: 005# BMS point (High level Modbus RTU/BACnet) - Level 2 | K30: RATE | L30: RATE | Q30: =B30/A30 -> 72 | R30: =IF($B30=0,0,IF($S$1="R",ROUND(R40/$B30,2),R40/$B30)) -> 60.69 | T30: =IF($B30=0,0,IF($S$1="R",ROUND(T40/$B30,2),T40/$B30)) -> 4.29
D31: Based on: Level 2
A32: =$Q$30 *(10) -> 720 | B32: m | D32: Conduit Galv. 20mm RATE | G32: COGV_011 | H32: 690 | I32: BAR | J32: 20mm | O32: 1 | P32: 34669 | Q32: 3.66 | R32: =$A32*Q32 -> 2635.2 | S32: =1.1 *(0.2) -> 0.22 | T32: =$A32*S32*$T$1 -> 158.4
A33: =$Q$30 *(20) -> 1440 | B33: m | C33: =3000*1.1 -> 3300 | D33: Indoor Screened 2c Cable 1.0mm (MODBUS) | F33: See Working by Rinoy | G33: CASP_018 | H33: 617 | I33: LAPP | J33: 110CY | O33: 2 | Q33: =228/305*1.25 -> 0.93442623 | R33: =$A33*Q33 -> 1345.5738 | S33: =1.1 *(0.05) -> 0.055 | T33: =$A33*S33*$T$1 -> 79.2
A34: =$Q$30 *(25*1.2) -> 2160 | B34: No | D34: Cable Tie 225mm | G34: CONS_009 | H34: 875 | I34: (__) | O34: 1 | P34: 34669 | Q34: 0.05 | R34: =$A34*Q34 -> 108 | T34: =$A34*S34*$T$1 -> 0
A35: =$Q$30 *(2) -> 144 | B35: No | D35: Gland Skintop EExeII 16 x 1.0 (2-4core) | G35: CAAC_086 | H35: 620 | I35: (__) | O35: 2 | P35: 38148 | Q35: =1.1*1.5 -> 1.65 | R35: =$A35*Q35 -> 237.6 | S35: =1.1 *(0.15) -> 0.165 | T35: =$A35*S35*$T$1 -> 23.76
A36: =$Q$30 *(2) -> 144 | B36: No | D36: Cable Marker Wrap Around Type | G36: CAAC_025 | H36: 620 | I36: (__) | O36: 2 | Q36: 0.2 | R36: =$A36*Q36 -> 28.8 | S36: =1.1 *(0.03) -> 0.033 | T36: =$A36*S36*$T$1 -> 4.752
A37: =$Q$30 *(4) -> 288 | B37: No | D37: Cable Lug 1.5 mm2 | G37: CAAC_004 | H37: 620 | I37: CTT | O37: 2 | P37: 34669 | Q37: 0.05 | R37: =$A37*Q37 -> 14.4 | S37: =1.1 *(0.01) -> 0.011 | T37: =$A37*S37*$T$1 -> 3.168
A38: =$Q$30 *(1) -> 72 | B38: No | D38: Labour to connect Mech Equip (FIX 3) | F38: Device | G38: LABO_009 | H38: 900 | I38: MISC | O38: 1 | R38: =$A38*Q38 -> 0 | S38: =1.1 *(0.5) -> 0.55 | T38: =$A38*S38*$T$1 -> 39.6 | U38: NoMat?
C39: << ==== TOTAL UNITS | R39: =$A39*Q39 -> 0 | T39: =$A39*S39*$T$1 -> 0
A40: d> | B40: =(R39+T39) -> 0 | D40: Sell_A | E40: =IF($B30=0,0,ROUND(ROUND(($R40*$S$2+($T40*$T$2))/$B30, 2)*$C$2,2)) -> 234.64 | F40: =ROUND($B30*$E40,2) -> 16894.08 | K40: ITEM | L40: ITEM | R40: =SUM(R31:R39) -> 4369.5738 | T40: =SUM(T31:T39) -> 308.88
Q41: Multip
A42: 1 | B42: =Elec_Est!B1041 -> 80 | D42: 004# BMS point (Low level - Digital and Analogue) - Level 4 | K42: RATE | L42: RATE | Q42: =B42/A42 -> 80 | R42: =IF($B42=0,0,IF($S$1="R",ROUND(R52/$B42,2),R52/$B42)) -> 120.91 | T42: =IF($B42=0,0,IF($S$1="R",ROUND(T52/$B42,2),T52/$B42)) -> 8.07
D43: Based on: Level 4
A44: =$Q$42 *(26) -> 2080 | B44: m | D44: Conduit Galv. 20mm RATE | G44: COGV_011 | H44: 690 | I44: BAR | J44: 20mm | O44: 1 | P44: 34669 | Q44: 3.66 | R44: =$A44*Q44 -> 7612.8 | S44: =1.1 *(0.2) -> 0.22 | T44: =$A44*S44*$T$1 -> 457.6
A45: =$Q$42 *(26) -> 2080 | B45: m | D45: Indoor Screened 3c Cable 1.0mm | G45: CASP_018 | H45: 617 | I45: LAPP | J45: 110CY | O45: 2 | Q45: =0.62*1.25 -> 0.775 | R45: =$A45*Q45 -> 1612 | S45: =1.1 *(0.05) -> 0.055 | T45: =$A45*S45*$T$1 -> 114.4
A46: =$Q$42 *(30) -> 2400 | B46: No | D46: Cable Tie 225mm | G46: CONS_009 | H46: 875 | I46: (__) | O46: 1 | P46: 34669 | Q46: 0.05 | R46: =$A46*Q46 -> 120 | T46: =$A46*S46*$T$1 -> 0
A47: =$Q$42 *(2) -> 160 | B47: No | D47: Gland Skintop EExeII 16 x 1.0 (2-4core) | G47: CAAC_086 | H47: 620 | I47: (__) | O47: 2 | P47: 38148 | Q47: =1.1*1.5 -> 1.65 | R47: =$A47*Q47 -> 264 | S47: =1.1 *(0.1) -> 0.11 | T47: =$A47*S47*$T$1 -> 17.6
A48: =$Q$42 *(2) -> 160 | B48: No | D48: Cable Marker Wrap Around Type | G48: CAAC_025 | H48: 620 | I48: (__) | O48: 2 | Q48: 0.2 | R48: =$A48*Q48 -> 32 | S48: =1.1 *(0.03) -> 0.033 | T48: =$A48*S48*$T$1 -> 5.28
A49: =$Q$42 *(2*4) -> 640 | B49: No | D49: Cable Lug 1.5 mm2 | G49: CAAC_004 | H49: 620 | I49: CTT | O49: 2 | P49: 34669 | Q49: 0.05 | R49: =$A49*Q49 -> 32 | S49: =1.1 *(0.01) -> 0.011 | T49: =$A49*S49*$T$1 -> 7.04
A50: =$Q$42 *(1) -> 80 | B50: No | D50: Labour to connect Mech Equip (FIX 3) | F50: Device | G50: LABO_009 | H50: 900 | I50: MISC | O50: 1 | R50: =$A50*Q50 -> 0 | S50: =1.1 *(0.5) -> 0.55 | T50: =$A50*S50*$T$1 -> 44 | U50: NoMat?
C51: << ==== TOTAL UNITS | R51: =$A51*Q51 -> 0 | T51: =$A51*S51*$T$1 -> 0
A52: d> | B52: =(R51+T51) -> 0 | D52: Sell_A | E52: =IF($B42=0,0,ROUND(ROUND(($R52*$S$2+($T52*$T$2))/$B42, 2)*$C$2,2)) -> 450.42 | F52: =ROUND($B42*$E52,2) -> 36033.6 | K52: ITEM | L52: ITEM | R52: =SUM(R43:R51) -> 9672.8 | T52: =SUM(T43:T51) -> 645.92
Q53: Multip
A54: 1 | B54: =Elec_Est!B1042 -> 20 | D54: 004# Isolator Interlocks for equipment in level 2 | K54: RATE | L54: RATE | Q54: =B54/A54 -> 20 | R54: =IF($B54=0,0,IF($S$1="R",ROUND(R64/$B54,2),R64/$B54)) -> 58.6 | T54: =IF($B54=0,0,IF($S$1="R",ROUND(T64/$B54,2),T64/$B54)) -> 4.39
D55: Based on: Level 4
A56: =$Q$54 *(7) -> 140 | B56: m | D56: Conduit Galv. 20mm RATE | G56: COGV_011 | H56: 690 | I56: BAR | J56: 20mm | O56: 1 | P56: 34669 | Q56: 3.66 | R56: =$A56*Q56 -> 512.4 | S56: =1.1 *(0.2) -> 0.22 | T56: =$A56*S56*$T$1 -> 30.8
A57: =$Q$54 *(35) -> 700 | B57: m | D57: Indoor Screened 3c Cable 1.0mm | G57: CASP_018 | H57: 617 | I57: LAPP | J57: 110CY | O57: 2 | Q57: =0.62*1.25 -> 0.775 | R57: =$A57*Q57 -> 542.5 | S57: =1.1 *(0.05) -> 0.055 | T57: =$A57*S57*$T$1 -> 38.5
A58: =$Q$54 *(35) -> 700 | B58: No | D58: Cable Tie 225mm | G58: CONS_009 | H58: 875 | I58: (__) | O58: 1 | P58: 34669 | Q58: 0.05 | R58: =$A58*Q58 -> 35 | T58: =$A58*S58*$T$1 -> 0
A59: =$Q$54 *(2) -> 40 | B59: No | D59: Gland Skintop EExeII 16 x 1.0 (2-4core) | G59: CAAC_086 | H59: 620 | I59: (__) | O59: 2 | P59: 38148 | Q59: =1.1*1.5 -> 1.65 | R59: =$A59*Q59 -> 66 | S59: =1.1 *(0.1) -> 0.11 | T59: =$A59*S59*$T$1 -> 4.4
A60: =$Q$54 *(2) -> 40 | B60: No | D60: Cable Marker Wrap Around Type | G60: CAAC_025 | H60: 620 | I60: (__) | O60: 2 | Q60: 0.2 | R60: =$A60*Q60 -> 8 | S60: =1.1 *(0.03) -> 0.033 | T60: =$A60*S60*$T$1 -> 1.32
A61: =$Q$54 *(2*4) -> 160 | B61: No | D61: Cable Lug 1.5 mm2 | G61: CAAC_004 | H61: 620 | I61: CTT | O61: 2 | P61: 34669 | Q61: 0.05 | R61: =$A61*Q61 -> 8 | S61: =1.1 *(0.01) -> 0.011 | T61: =$A61*S61*$T$1 -> 1.76
A62: =$Q$54 *(1) -> 20 | B62: No | D62: Labour to connect Mech Equip (FIX 3) | F62: Device | G62: LABO_009 | H62: 900 | I62: MISC | O62: 1 | R62: =$A62*Q62 -> 0 | S62: =1.1 *(0.5) -> 0.55 | T62: =$A62*S62*$T$1 -> 11 | U62: NoMat?
C63: << ==== TOTAL UNITS | R63: =$A63*Q63 -> 0 | T63: =$A63*S63*$T$1 -> 0
A64: d> | B64: =(R63+T63) -> 0 | D64: Sell_A | E64: =IF($B54=0,0,ROUND(ROUND(($R64*$S$2+($T64*$T$2))/$B54, 2)*$C$2,2)) -> 235.47 | F64: =ROUND($B54*$E64,2) -> 4709.4 | K64: ITEM | L64: ITEM | R64: =SUM(R55:R63) -> 1171.9 | T64: =SUM(T55:T63) -> 87.78
Q65: Multip
A66: 1 | B66: =Elec_Est!B1043 -> 20 | D66: 005# BMS point (High level Modbus RTU/BACnet) - Level 4 | K66: RATE | L66: RATE | Q66: =B66/A66 -> 20 | R66: =IF($B66=0,0,IF($S$1="R",ROUND(R76/$B66,2),R76/$B66)) -> 19.07 | T66: =IF($B66=0,0,IF($S$1="R",ROUND(T76/$B66,2),T76/$B66)) -> 2.37
D67: Based on: Level 4
A68: =$Q$66 *(5) -> 100 | B68: m | D68: Conduit Galv. 20mm RATE | G68: COGV_011 | H68: 690 | I68: BAR | J68: 20mm | O68: 1 | P68: 34669 | Q68: =1.2 *(1.7) -> 2.04 | R68: =$A68*Q68 -> 204 | S68: =1.1 *(0.2) -> 0.22 | T68: =$A68*S68*$T$1 -> 22
A69: =$Q$66 *(5) -> 100 | B69: m | C69: =3000*1.1 -> 3300 | D69: Indoor Screened 2c Cable 1.0mm (MODBUS) | G69: CASP_018 | H69: 617 | I69: LAPP | J69: 110CY | O69: 2 | Q69: =228/305*1.25 -> 0.93442623 | R69: =$A69*Q69 -> 93.442623 | S69: =1.1 *(0.05) -> 0.055 | T69: =$A69*S69*$T$1 -> 5.5
A70: =$Q$66 *(5*1.2) -> 120 | B70: No | D70: Cable Tie 225mm | G70: CONS_009 | H70: 875 | I70: (__) | O70: 1 | P70: 34669 | Q70: 0.05 | R70: =$A70*Q70 -> 6 | T70: =$A70*S70*$T$1 -> 0
A71: =$Q$66 *(2) -> 40 | B71: No | D71: Gland Skintop EExeII 16 x 1.0 (2-4core) | G71: CAAC_086 | H71: 620 | I71: (__) | O71: 2 | P71: 38148 | Q71: =1.1*1.5 -> 1.65 | R71: =$A71*Q71 -> 66 | S71: =1.1 *(0.15) -> 0.165 | T71: =$A71*S71*$T$1 -> 6.6
A72: =$Q$66 *(2) -> 40 | B72: No | D72: Cable Marker Wrap Around Type | G72: CAAC_025 | H72: 620 | I72: (__) | O72: 2 | Q72: 0.2 | R72: =$A72*Q72 -> 8 | S72: =1.1 *(0.03) -> 0.033 | T72: =$A72*S72*$T$1 -> 1.32
A73: =$Q$66 *(4) -> 80 | B73: No | D73: Cable Lug 1.5 mm2 | G73: CAAC_004 | H73: 620 | I73: CTT | O73: 2 | P73: 34669 | Q73: 0.05 | R73: =$A73*Q73 -> 4 | S73: =1.1 *(0.01) -> 0.011 | T73: =$A73*S73*$T$1 -> 0.88
A74: =$Q$66 *(1) -> 20 | B74: No | D74: Labour to connect Mech Equip (FIX 3) | F74: Device | G74: LABO_009 | H74: 900 | I74: MISC | O74: 1 | R74: =$A74*Q74 -> 0 | S74: =1.1 *(0.5) -> 0.55 | T74: =$A74*S74*$T$1 -> 11 | U74: NoMat?
C75: << ==== TOTAL UNITS | R75: =$A75*Q75 -> 0 | T75: =$A75*S75*$T$1 -> 0
A76: d> | B76: =(R75+T75) -> 0 | D76: Sell_A | E76: =IF($B66=0,0,ROUND(ROUND(($R76*$S$2+($T76*$T$2))/$B66, 2)*$C$2,2)) -> 110.45 | F76: =ROUND($B66*$E76,2) -> 2209 | K76: ITEM | L76: ITEM | R76: =SUM(R67:R75) -> 381.44262 | T76: =SUM(T67:T75) -> 47.3
Q77: Multip
A78: 1 | B78: =Elec_Est!B1044 -> 26 | D78: 005# BMS point (High level Modbus RTU/BACnet) - AHUS | K78: RATE | L78: RATE | Q78: =B78/A78 -> 26 | R78: =IF($B78=0,0,IF($S$1="R",ROUND(R88/$B78,2),R88/$B78)) -> 143.53 | T78: =IF($B78=0,0,IF($S$1="R",ROUND(T88/$B78,2),T88/$B78)) -> 9.24
D79: Based on: Level 4
A80: =$Q$78 *(30) -> 780 | B80: m | D80: Conduit Galv. 20mm RATE | G80: COGV_011 | H80: 690 | I80: BAR | J80: 20mm | O80: 1 | P80: 34669 | Q80: 3.66 | R80: =$A80*Q80 -> 2854.8 | S80: =1.1 *(0.2) -> 0.22 | T80: =$A80*S80*$T$1 -> 171.6
A81: =$Q$78 *(30) -> 780 | B81: m | C81: =3000*1.1 -> 3300 | D81: Indoor Screened 2c Cable 1.0mm (MODBUS) | G81: CASP_018 | H81: 617 | I81: LAPP | J81: 110CY | O81: 2 | Q81: =228/305*1.25 -> 0.93442623 | R81: =$A81*Q81 -> 728.85246 | S81: =1.1 *(0.05) -> 0.055 | T81: =$A81*S81*$T$1 -> 42.9
A82: =$Q$78 *(30*1.2) -> 936 | B82: No | D82: Cable Tie 225mm | G82: CONS_009 | H82: 875 | I82: (__) | O82: 1 | P82: 34669 | Q82: 0.05 | R82: =$A82*Q82 -> 46.8 | T82: =$A82*S82*$T$1 -> 0
A83: =$Q$78 *(2) -> 52 | B83: No | D83: Gland Skintop EExeII 16 x 1.0 (2-4core) | G83: CAAC_086 | H83: 620 | I83: (__) | O83: 2 | P83: 38148 | Q83: =1.1*1.5 -> 1.65 | R83: =$A83*Q83 -> 85.8 | S83: =1.1 *(0.15) -> 0.165 | T83: =$A83*S83*$T$1 -> 8.58
A84: =$Q$78 *(2) -> 52 | B84: No | D84: Cable Marker Wrap Around Type | G84: CAAC_025 | H84: 620 | I84: (__) | O84: 2 | Q84: 0.2 | R84: =$A84*Q84 -> 10.4 | S84: =1.1 *(0.03) -> 0.033 | T84: =$A84*S84*$T$1 -> 1.716
A85: =$Q$78 *(4) -> 104 | B85: No | D85: Cable Lug 1.5 mm2 | G85: CAAC_004 | H85: 620 | I85: CTT | O85: 2 | P85: 34669 | Q85: 0.05 | R85: =$A85*Q85 -> 5.2 | S85: =1.1 *(0.01) -> 0.011 | T85: =$A85*S85*$T$1 -> 1.144
A86: =$Q$78 *(1) -> 26 | B86: No | D86: Labour to connect Mech Equip (FIX 3) | F86: Device | G86: LABO_009 | H86: 900 | I86: MISC | O86: 1 | R86: =$A86*Q86 -> 0 | S86: =1.1 *(0.5) -> 0.55 | T86: =$A86*S86*$T$1 -> 14.3 | U86: NoMat?
C87: << ==== TOTAL UNITS | R87: =$A87*Q87 -> 0 | T87: =$A87*S87*$T$1 -> 0
A88: d> | B88: =(R87+T87) -> 0 | D88: Sell_A | E88: =IF($B78=0,0,ROUND(ROUND(($R88*$S$2+($T88*$T$2))/$B78, 2)*$C$2,2)) -> 522.25 | F88: =ROUND($B78*$E88,2) -> 13578.5 | K88: ITEM | L88: ITEM | R88: =SUM(R79:R87) -> 3731.8525 | T88: =SUM(T79:T87) -> 240.24
Q89: Multip
A90: 1 | B90: =Elec_Est!B1045 -> 5 | D90: 013# Data Point + BACnet IP | K90: RATE | L90: RATE | Q90: =B90/A90 -> 5 | R90: =IF($B90=0,0,IF($S$1="R",ROUND(R100/$B90,2),R100/$B90)) -> 76.26 | T90: =IF($B90=0,0,IF($S$1="R",ROUND(T100/$B90,2),T100/$B90)) -> 4.41
D91: Based on: Dual Allowed
A92: =$Q$90 *(6) -> 30 | B92: m | D92: Conduit Galv. 25mm RATE | G92: COGV_013 | H92: 690 | I92: BAR | J92: 25mm | O92: 1 | P92: 34669 | Q92: 3.66 | R92: =$A92*Q92 -> 109.8 | S92: =1.1 *(0.25) -> 0.275 | T92: =$A92*S92*$T$1 -> 8.25
A93: =$Q$90 *(30*2) -> 300 | B93: m | C93: =#REF! *(7*8*1.1) -> #REF! | D93: Data Cable 4Pr UTP CAT5E | G93: CASP_006 | H93: 617 | I93: (__) | O93: 2 | P93: 40767 | Q93: 0.65 | R93: =$A93*Q93 -> 195 | S93: =1.1 *(0.025) -> 0.0275 | T93: =$A93*S93*$T$1 -> 8.25
A94: =$Q$90 *(1) -> 5 | B94: No | D94: WHITE Data Outlet Cat6 Twin on Single Faceplate | F94: Tenovar | G94: WACC_169 | H94: 705 | I94: (__) | O94: 3 | P94: 38094 | Q94: 10 | R94: =$A94*Q94 -> 50 | S94: =1.1 *(0.25) -> 0.275 | T94: =$A94*S94*$T$1 -> 1.375
A95: =$Q$90 *(2) -> 10 | B95: No | D95: Data Cable Termination | G95: DATA_036 | H95: 821 | I95: (__) | O95: 3 | P95: 38475 | R95: =$A95*Q95 -> 0 | S95: =1.1 *(0.17) -> 0.187 | T95: =$A95*S95*$T$1 -> 1.87 | U95: NoMat?
A96: =$Q$90 *(2) -> 10 | B96: No | D96: Cable Marker Wrap Around Type | G96: CAAC_025 | H96: 620 | I96: (__) | O96: 2 | Q96: 0.15 | R96: =$A96*Q96 -> 1.5 | T96: =$A96*S96*$T$1 -> 0
A97: =$Q$90 *(1) -> 5 | B97: No | D97: Data Cable Testing | G97: DATA_036 | H97: 821 | I97: (__) | O97: 3 | P97: 38475 | R97: =$A97*Q97 -> 0 | S97: =1.1 *(0.25) -> 0.275 | T97: =$A97*S97*$T$1 -> 1.375 | U97: NoMat?
A98: =$Q$90 *(1) -> 5 | B98: No | D98: Data Patch Leads CAT5E 3m | G98: DATA_006 | H98: 821 | I98: (__) | O98: 3 | Q98: 5 | R98: =$A98*Q98 -> 25 | S98: =1.1 *(0.17) -> 0.187 | T98: =$A98*S98*$T$1 -> 0.935
C99: << ==== TOTAL UNITS | R99: =$A99*Q99 -> 0 | T99: =$A99*S99*$T$1 -> 0
A100: d> | B100: =(R99+T99) -> 0 | D100: Sell_A | E100: =IF($B90=0,0,ROUND(ROUND(($R100*$S$2+($T100*$T$2))/$B90, 2)*$C$2,2)) -> 259.49 | F100: =ROUND($B90*$E100,2) -> 1297.45 | K100: ITEM | L100: ITEM | R100: =SUM(R91:R99) -> 381.3 | T100: =SUM(T91:T99) -> 22.055
C102: t | D102: Item:
...

Sheet Elec_Est
B1: CLIENT: | C1: =ML_Sum!$C1 -> 1 | D1: =ML_Sum!$D1 -> Eden Lesuire Group | F1: =ML_Sum!$F1 -> 0 | I1: 1 | J1: =ML_Sum!$J1 -> 1 | K1: =ML_Sum!$K1 -> 1 | L1: =ML_Sum!$L1 -> 1 | M1: =ML_Sum!$M1 -> 1 | N1: =ML_Sum!$N1 -> 1 | O1: =ML_Sum!$O1 -> 1 | Q1: =ML_Sum!$Q1 -> € | R1: R/Lab Cont | S1: =ML_Sum!$S1 -> R | T1: =ML_Sum!$T1 -> 1 | U1: =ML_Sum!W1 -> BOQ | V1: INCL | W1: MULT | X1: AREA | Y1: BOQ | Z1: TDWG | AA1: ACT | AB1: DIFF
B2: PROJECT: | C2: =ML_Sum!$C2 -> 0.97379223 | D2: =ML_Sum!$D2 -> Intercontinental - Plant Retrofit | F2: =ML_Sum!$F2 -> Electrical | I2: 2 | J2: =ML_Sum!$J2 -> 1 | K2: =ML_Sum!$K2 -> 1 | L2: =ML_Sum!$L2 -> 1 | M2: =ML_Sum!$M2 -> 1 | N2: =ML_Sum!$N2 -> 1 | O2: =ML_Sum!$O2 -> 1 | Q2: =ML_Sum!$Q2 -> 0.026207766 | R2: mu_A | S2: =ML_Sum!$S2 -> 1.35 | T2: =ML_Sum!$T2 -> 37.071
B3: JOB DESC: | C3: =ML_Sum!$C3 -> 0.97379223 | D3: =ML_Sum!$D3 -> Retrofitting works for the Electrical Installations | F3: =ML_Sum!$F3 -> ECA (Technician) | I3: 3 | J3: =ML_Sum!$J3 -> 1 | K3: =ML_Sum!$K3 -> 1 | L3: =ML_Sum!$L3 -> 1 | M3: =ML_Sum!$M3 -> 1 | N3: =ML_Sum!$N3 -> 1 | O3: =ML_Sum!$O3 -> 1 | Q3: =ML_Sum!$Q3 -> 0.026207766 | R3: mu_B | S3: =ML_Sum!$S3 -> 1.35 | T3: =ML_Sum!$T3 -> 45.5355
B4: QUOTE No: | C4: =ML_Sum!$C4 -> 0.97379223 | D4: =ML_Sum!$D4 -> EL25-0477 | F4: =ML_Sum!$F4 -> ECA (Engineer) | I4: 4 | J4: =ML_Sum!$J4 -> 1 | K4: =ML_Sum!$K4 -> 1 | L4: =ML_Sum!$L4 -> 1 | M4: =ML_Sum!$M4 -> 1 | N4: =ML_Sum!$N4 -> 1 | O4: =ML_Sum!$O4 -> 1 | Q4: =ML_Sum!$Q4 -> 0.026207766 | R4: mu_C | S4: =ML_Sum!$S4 -> 1.35 | T4: =ML_Sum!$T4 -> 40.5
B5: CLIENTs REF: | C5: =ML_Sum!$C5 -> 1 | D5: =ML_Sum!$D5 -> Tender | F5: =ML_Sum!$F5 -> Megaline | I5: 5 | J5: =ML_Sum!$J5 -> 1 | K5: =ML_Sum!$K5 -> 1 | L5: =ML_Sum!$L5 -> 1 | M5: =ML_Sum!$M5 -> 1 | N5: =ML_Sum!$N5 -> 1 | O5: =ML_Sum!$O5 -> 1 | Q5: =ML_Sum!$Q5 -> 0 | R5: mu_D | S5: =ML_Sum!$S5 -> 1 | T5: =ML_Sum!$T5 -> 37.071
B6: VAT/DUTIES: | C6: =ML_Sum!$C6 -> 1 | D6: =ML_Sum!$D6 -> VAT EXCL. | F6: =ML_Sum!$F6 -> 0 | I6: 6 | J6: =ML_Sum!$J6 -> 1 | K6: =ML_Sum!$K6 -> 1 | L6: =ML_Sum!$L6 -> 1 | M6: =ML_Sum!$M6 -> 1 | N6: =ML_Sum!$N6 -> 1 | O6: =ML_Sum!$O6 -> 1 | Q6: =ML_Sum!$Q6 -> 0 | R6: mu_E | S6: =ML_Sum!$S6 -> 0 | T6: =ML_Sum!$T6 -> 0
B7: SAVED ON: | C7: =ML_Sum!$C7 -> 1 | D7: 39364 | F7: =ML_Sum!$F7 -> 0 | I7: 7 | J7: =ML_Sum!$J7 -> 1 | K7: =ML_Sum!$K7 -> 1 | L7: =ML_Sum!$L7 -> 1 | M7: =ML_Sum!$M7 -> 1 | N7: =ML_Sum!$N7 -> 1 | O7: =ML_Sum!$O7 -> 0 | Q7: =ML_Sum!$Q7 -> 0 | R7: mu_F | S7: =ML_Sum!$S7 -> 0 | T7: =ML_Sum!$T7 -> 0
B8: ESTIMATOR: | C8: =ML_Sum!$C8 -> 1 | D8: =ML_Sum!$D8 -> M.Scicluna | F8: =ML_Sum!$F8 -> 0 | I8: 8 | J8: =ML_Sum!$J8 -> 1 | K8: =ML_Sum!$K8 -> 1 | L8: =ML_Sum!$L8 -> 1 | M8: =ML_Sum!$M8 -> 1 | N8: =ML_Sum!$N8 -> 1 | O8: =ML_Sum!$O8 -> 0 | Q8: =ML_Sum!$Q8 -> 0 | R8: mu_G | S8: =ML_Sum!$S8 -> 0 | T8: =ML_Sum!$T8 -> 0
B9: LABOUR RATE: | C9: =ML_Sum!$C9 -> 1 | D9: =ML_Sum!$D9 -> 27.46 | F9: =ML_Sum!$F9 -> 0 | I9: 9 | J9: =ML_Sum!$J9 -> 1 | K9: =ML_Sum!$K9 -> 1 | L9: =ML_Sum!$L9 -> 1 | M9: =ML_Sum!$M9 -> 1 | N9: =ML_Sum!$N9 -> 1 | O9: =ML_Sum!$O9 -> 0 | Q9: =ML_Sum!$Q9 -> 0 | R9: mu_H | S9: =ML_Sum!$S9 -> 0 | T9: =ML_Sum!$T9 -> 0
C10: =ML_Sum!$C10 -> 1 | F10: =ML_Sum!$F10 -> 0 | I10: 10 | J10: =ML_Sum!$J10 -> 1 | K10: =ML_Sum!$K10 -> 1 | L10: =ML_Sum!$L10 -> 1 | M10: =ML_Sum!$M10 -> 1 | N10: =ML_Sum!$N10 -> 1 | O10: =ML_Sum!$O10 -> 1 | Q10: =ML_Sum!$Q10 -> 0 | R10: mu_I | S10: =ML_Sum!$S10 -> 0 | T10: =ML_Sum!$T10 -> 0
C11: =ML_Sum!$C11 -> 1 | F11: =ML_Sum!$F11 -> 0 | Q11: =ML_Sum!$Q11 -> 0 | R11: mu_J | S11: =ML_Sum!$S11 -> 0 | T11: =ML_Sum!$T11 -> 0
C12: =ML_Sum!$C12 -> 0.97379223 | F12: =ML_Sum!$F12 -> 0 | Q12: =ML_Sum!$Q12 -> 0.026207766 | R12: MIXED | S12: =ML_Sum!$S12 -> MAT MU | T12: =ML_Sum!$T12 -> LAB RATE
G13: ISELL | H13: C_CODE | I13: MAKE | J13: PART_NO | K13: MARKUP | L13: TYPE | M13: LIST_P | N13: P_FACT | O13: FIX | P13: DATE | Q13: %Dsct in BOQ | R13: MU TYPE | S13: MAT MU | T13: LAB RATE | AM13: Tot Mat Cost | AN13: Unit Lab phr. | AO13: Tot Lab phr. | AP13: < for ELM / MEE
K14: TB
C15: t
D16: MAIN ELECTRICAL INFRASTRUCTURE
K18: TB
C19: t
D20: SWITCHGEAR AND OTHER ACCESSORIES
K22: TB
C23: t | D23: Item: 1
D24: Supply only the following switchgear and other accessories.
E26: Sell Rate | F26: Sell Total | K26: IB | AG26: U_M_Sell | AH26: T_M_Sell | AI26: U_L_Sell | AJ26: T_L_Sell | AK26: Total_Sell | AM26: T_M_Cost | AN26: T_L_Phr | AO26: Mat/Lab=1
A27: 1 | B27: No. | D27: Item: 1.0a | E27: =IF(AND($A27=0,$A$1="DIF"),0, ROUND(ROUND(($R31*$S$5+($T31*$T$5))/$A27,2)*$C$5,2)) -> 989.85 | F27: =ROUND($A27*$E27,2) -> 989.85 | G27: ISELL | K27: mu_D | L27: ITEM | T27: =IF(AND($R31=0,$T31=0),"0.00","mu: "& ROUND(F27/$C$5/($R31+$T31*$D$9),2)) -> mu: 1 | AG27: =IF($E27=0,0,ROUND($R31*$S$5*$C$5/$A27,2)) -> 989.85 | AH27: =$AG27*$A27 -> 989.85 | AI27: =$E27-$AG27 -> 0 | AJ27: =$A27*$AI27 -> 0 | AK27: =ROUND(($AG27+$AI27)*$A27,2) -> 989.85 | AM27: =ROUND(R31,2) -> 989.85 | AN27: =ROUND(T31,2) -> 0 | AO27: =ROUND(AM27+AN27,2)*A27 -> 989.85
D28: Distribution Board DB-L2PR (metalclad enclosure) | K28: n
A29: 1 | B29: LS | D29: Subcontracting Works (Specify Contractor Name) | F29: Megaline | G29: SUBC_007 | H29: 960 | I29: MISC | O29: 4 | P29: 38594 | Q29: 989.85 | R29: =$A29*Q29 -> 989.85 | T29: =$A29*S29*$T$1 -> 0
R30: =$A30*Q30 -> 0 | T30: =$A30*S30*$T$1 -> 0
A31: d> | B31: =(R30+T30) -> 0 | G31: ICOST | K31: mu_D | L31: ITEM | R31: =SUM(R28:R30) -> 989.85 | T31: =SUM(T28:T30) -> 0
E32: Sell Rate | F32: Sell Total | K32: IB | AG32: U_M_Sell | AH32: T_M_Sell | AI32: U_L_Sell | AJ32: T_L_Sell | AK32: Total_Sell | AM32: T_M_Cost | AN32: T_L_Phr | AO32: Mat/Lab=1
A33: 1 | B33: No. | D33: Item: 1.0b | E33: =IF(AND($A33=0,$A$1="DIF"),0, ROUND(ROUND(($R37*$S$5+($T37*$T$5))/$A33,2)*$C$5,2)) -> 232.28 | F33: =ROUND($A33*$E33,2) -> 232.28 | G33: ISELL | K33: mu_D | L33: ITEM | T33: =IF(AND($R37=0,$T37=0),"0.00","mu: "& ROUND(F33/$C$5/($R37+$T37*$D$9),2)) -> mu: 1 | AG33: =IF($E33=0,0,ROUND($R37*$S$5*$C$5/$A33,2)) -> 232.28 | AH33: =$AG33*$A33 -> 232.28 | AI33: =$E33-$AG33 -> 0 | AJ33: =$A33*$AI33 -> 0 | AK33: =ROUND(($AG33+$AI33)*$A33,2) -> 232.28 | AM33: =ROUND(R37,2) -> 232.28 | AN33: =ROUND(T37,2) -> 0 | AO33: =ROUND(AM33+AN33,2)*A33 -> 232.28
D34: Equipotential earth bonding busbar EB1, rated at 600A or more, wall mounted to the wall on plastic insulators. (approx. 400mm x 50mm x 6mm).
A35: 1 | B35: LS | D35: Subcontracting Works (Specify Contractor Name) | F35: Megaline | G35: SUBC_007 | H35: 960 | I35: MISC | O35: 4 | P35: 38594 | Q35: 232.28 | R35: =$A35*Q35 -> 232.28 | T35: =$A35*S35*$T$1 -> 0
R36: =$A36*Q36 -> 0 | T36: =$A36*S36*$T$1 -> 0
A37: d> | B37: =(R36+T36) -> 0 | G37: ICOST | K37: mu_D | L37: ITEM | R37: =SUM(R34:R36) -> 232.28 | T37: =SUM(T34:T36) -> 0
K38: TB
C39: t | D39: Item: 2
D40: Install and connect only the following switchgear and other accessories.
E42: Sell Rate | F42: Sell Total | K42: IB | AG42: U_M_Sell | AH42: T_M_Sell | AI42: U_L_Sell | AJ42: T_L_Sell | AK42: Total_Sell | AM42: T_M_Cost | AN42: T_L_Phr | AO42: Mat/Lab=1
A43: 1 | B43: No. | D43: Item: 2.0a | E43: =IF(AND($A43=0,$A$1="DIF"),0, ROUND(ROUND(($R47*$S$5+($T47*$T$5))/$A43,2)*$C$5,2)) -> 343.15 | F43: =ROUND($A43*$E43,2) -> 343.15 | G43: ISELL | K43: mu_D | L43: ITEM | T43: =IF(AND($R47=0,$T47=0),"0.00","mu: "& ROUND(F43/$C$5/($R47+$T47*$D$9),2)) -> mu: 1 | AG43: =IF($E43=0,0,ROUND($R47*$S$5*$C$5/$A43,2)) -> 343.15 | AH43: =$AG43*$A43 -> 343.15 | AI43: =$E43-$AG43 -> 0 | AJ43: =$A43*$AI43 -> 0 | AK43: =ROUND(($AG43+$AI43)*$A43,2) -> 343.15 | AM43: =ROUND(R47,2) -> 343.15 | AN43: =ROUND(T47,2) -> 0 | AO43: =ROUND(AM43+AN43,2)*A43 -> 343.15
D44: Distribution Board DB-L2PR (metalclad enclosure) | K44: n
A45: 1 | B45: LS | D45: Subcontracting Works (Specify Contractor Name) | F45: Megaline | G45: SUBC_007 | H45: 960 | I45: MISC | O45: 4 | P45: 38594 | Q45: 343.15 | R45: =$A45*Q45 -> 343.15 | T45: =$A45*S45*$T$1 -> 0
R46: =$A46*Q46 -> 0 | T46: =$A46*S46*$T$1 -> 0
A47: d> | B47: =(R46+T46) -> 0 | G47: ICOST | K47: mu_D | L47: ITEM | R47: =SUM(R44:R46) -> 343.15 | T47: =SUM(T44:T46) -> 0
E48: Sell Rate | F48: Sell Total | K48: IB | AG48: U_M_Sell | AH48: T_M_Sell | AI48: U_L_Sell | AJ48: T_L_Sell | AK48: Total_Sell | AM48: T_M_Cost | AN48: T_L_Phr | AO48: Mat/Lab=1
A49: 1 | B49: No. | D49: Item: 2.0b | E49: =IF(AND($A49=0,$A$1="DIF"),0, ROUND(ROUND(($R53*$S$5+($T53*$T$5))/$A49,2)*$C$5,2)) -> 232.28 | F49: =ROUND($A49*$E49,2) -> 232.28 | G49: ISELL | K49: mu_D | L49: ITEM | T49: =IF(AND($R53=0,$T53=0),"0.00","mu: "& ROUND(F49/$C$5/($R53+$T53*$D$9),2)) -> mu: 1 | AG49: =IF($E49=0,0,ROUND($R53*$S$5*$C$5/$A49,2)) -> 232.28 | AH49: =$AG49*$A49 -> 232.28 | AI49: =$E49-$AG49 -> 0 | AJ49: =$A49*$AI49 -> 0 | AK49: =ROUND(($AG49+$AI49)*$A49,2) -> 232.28 | AM49: =ROUND(R53,2) -> 232.28 | AN49: =ROUND(T53,2) -> 0 | AO49: =ROUND(AM49+AN49,2)*A49 -> 232.28
D50: Equipotential earth bonding busbar EB1, rated at 600A or more, wall mounted to the wall on plastic insulators. (approx. 400mm x 50mm x 6mm).
A51: 1 | B51: LS | D51: Subcontracting Works (Specify Contractor Name) | F51: Megaline | G51: SUBC_007 | H51: 960 | I51: MISC | O51: 4 | P51: 38594 | Q51: 232.28 | R51: =$A51*Q51 -> 232.28 | T51: =$A51*S51*$T$1 -> 0
R52: =$A52*Q52 -> 0 | T52: =$A52*S52*$T$1 -> 0
A53: d> | B53: =(R52+T52) -> 0 | G53: ICOST | K53: mu_D | L53: ITEM | R53: =SUM(R50:R52) -> 232.28 | T53: =SUM(T50:T52) -> 0
K54: TB
C55: t
D56: CABLE MANAGEMENT
K58: TB
C59: t | D59: Item: 3
D60: Supply and install the following galvanized steel cable tray, from MSG-1 to SPB-PR in the new Plant Room. Cost is to include all cantilever bracketing to wall or suspension bracketing to the ceiling as necessary.
E62: Sell Rate | F62: Sell Total | K62: IB | AG62: U_M_Sell | AH62: T_M_Sell | AI62: U_L_Sell | AJ62: T_L_Sell | AK62: Total_Sell | AM62: T_M_Cost | AN62: T_L_Phr | AO62: Mat/Lab=1
A63: 155 | B63: m | D63: Item: 3.0a | E63: =IF(AND($A63=0,$A$1="DIF"),0, ROUND(ROUND(($R67*$S$5+($T67*$T$5))/$A63,2)*$C$5,2)) -> 123.09 | F63: =ROUND($A63*$E63,2) -> 19078.95 | G63: ISELL | K63: mu_D | L63: ITEM | T63: =IF(AND($R67=0,$T67=0),"0.00","mu: "& ROUND(F63/$C$5/($R67+$T67*$D$9),2)) -> mu: 1 | AG63: =IF($E63=0,0,ROUND($R67*$S$5*$C$5/$A63,2)) -> 123.09 | AH63: =$AG63*$A63 -> 19078.95 | AI63: =$E63-$AG63 -> 0 | AJ63: =$A63*$AI63 -> 0 | AK63: =ROUND(($AG63+$AI63)*$A63,2) -> 19078.95 | AM63: =ROUND(R67,2) -> 19078.95 | AN63: =ROUND(T67,2) -> 0 | AO63: =ROUND(AM63+AN63,2)*A63 -> 2957237.2
D64: 500mm x 50mm. | K64: n
A65: =A63 -> 155 | B65: LS | D65: Subcontracting Works (Specify Contractor Name) | F65: Megaline | G65: SUBC_007 | H65: 960 | I65: MISC | O65: 4 | P65: 38594 | Q65: 123.09 | R65: =$A65*Q65 -> 19078.95 | T65: =$A65*S65*$T$1 -> 0
R66: =$A66*Q66 -> 0 | T66: =$A66*S66*$T$1 -> 0
A67: d> | B67: =(R66+T66) -> 0 | G67: ICOST | K67: mu_D | L67: ITEM | R67: =SUM(R64:R66) -> 19078.95 | T67: =SUM(T64:T66) -> 0
K68: TB
C69: t | D69: Item: 4
D70: Supply and install the following galvanized steel cable ladder above SPB-PR. Cost is to include all the support bracketing to wall or ceiling as necessary.
E72: Sell Rate | F72: Sell Total | K72: IB | AG72: U_M_Sell | AH72: T_M_Sell | AI72: U_L_Sell | AJ72: T_L_Sell | AK72: Total_Sell | AM72: T_M_Cost | AN72: T_L_Phr | AO72: Mat/Lab=1
A73: 4 | B73: m | D73: Item: 4.0a | E73: =IF(AND($A73=0,$A$1="DIF"),0, ROUND(ROUND(($R77*$S$5+($T77*$T$5))/$A73,2)*$C$5,2)) -> 126.04 | F73: =ROUND($A73*$E73,2) -> 504.16 | G73: ISELL | K73: mu_D | L73: ITEM | T73: =IF(AND($R77=0,$T77=0),"0.00","mu: "& ROUND(F73/$C$5/($R77+$T77*$D$9),2)) -> mu: 1 | AG73: =IF($E73=0,0,ROUND($R77*$S$5*$C$5/$A73,2)) -> 126.04 | AH73: =$AG73*$A73 -> 504.16 | AI73: =$E73-$AG73 -> 0 | AJ73: =$A73*$AI73 -> 0 | AK73: =ROUND(($AG73+$AI73)*$A73,2) -> 504.16 | AM73: =ROUND(R77,2) -> 504.16 | AN73: =ROUND(T77,2) -> 0 | AO73: =ROUND(AM73+AN73,2)*A73 -> 2016.64
D74: 500mm x 100mm. | K74: n
A75: =A73 -> 4 | B75: LS | D75: Subcontracting Works (Specify Contractor Name) | F75: Megaline | G75: SUBC_007 | H75: 960 | I75: MISC | O75: 4 | P75: 38594 | Q75: 126.04 | R75: =$A75*Q75 -> 504.16 | T75: =$A75*S75*$T$1 -> 0
R76: =$A76*Q76 -> 0 | T76: =$A76*S76*$T$1 -> 0
A77: d> | B77: =(R76+T76) -> 0 | G77: ICOST | K77: mu_D | L77: ITEM | R77: =SUM(R74:R76) -> 504.16 | T77: =SUM(T74:T76) -> 0
A78: SB
B80: =$F80/$C$2-($R80*$S$2+$T80*$T$2) -> -6907.8144 | D80: PAGE: | F80: =SUMIF($L14:$L78,"ITEM",F14:F78) -> 21380.67 | L80: PAGE | R80: =SUMIF($L14:$L78,"ITEM",R14:R78) -> 21380.67 | T80: =SUMIF($L14:$L78,"ITEM",T14:T78) -> 0
B81: Discy: | F81: PAGE SELL | R81: PAGE MAT | T81: PAGE LAB
K84: TB
C85: t
D86: POWER CABLING
K88: TB
C89: t | D89: Item: 5
D90: Supply, install and connect the following power cables. Cost is to include all cable installation and termination accessories as necessary. Cables installed on low level (less than 2.5 metres from FFL) cable trays are to be mechanically protected by cable tray covers.
E92: Sell Rate | F92: Sell Total | K92: IB | AG92: U_M_Sell | AH92: T_M_Sell | AI92: U_L_Sell | AJ92: T_L_Sell | AK92: Total_Sell | AM92: T_M_Cost | AN92: T_L_Phr | AO92: Mat/Lab=1
A93: 160 | B93: mr | D93: Item: 5.0a | E93: =IF(AND($A93=0,$A$1="DIF"),0, ROUND(ROUND(($R97*$S$5+($T97*$T$5))/$A93,2)*$C$5,2)) -> 745.77 | F93: =ROUND($A93*$E93,2) -> 119323.2 | G93: ISELL | K93: mu_D | L93: ITEM | T93: =IF(AND($R97=0,$T97=0),"0.00","mu: "& ROUND(F93/$C$5/($R97+$T97*$D$9),2)) -> mu: 1 | AG93: =IF($E93=0,0,ROUND($R97*$S$5*$C$5/$A93,2)) -> 745.77 | AH93: =$AG93*$A93 -> 119323.2 | AI93: =$E93-$AG93 -> 0 | AJ93: =$A93*$AI93 -> 0 | AK93: =ROUND(($AG93+$AI93)*$A93,2) -> 119323.2 | AM93: =ROUND(R97,2) -> 119323.2 | AN93: =ROUND(T97,2) -> 0 | AO93: =ROUND(AM93+AN93,2)*A93 -> 19091712
D94: 1600A MCCB in existing Main Switchgear Panel MSG-1 to the new Switchgear Panel SPB-PR (Plant Room).6 x (5core x 120.0 mm2 FG16(0)M16).
A95: =A93 -> 160 | B95: LS | D95: Subcontracting Works (Specify Contractor Name) | F95: Megaline | G95: SUBC_007 | H95: 960 | I95: MISC | O95: 4 | P95: 38594 | Q95: 745.77 | R95: =$A95*Q95 -> 119323.2 | T95: =$A95*S95*$T$1 -> 0
R96: =$A96*Q96 -> 0 | T96: =$A96*S96*$T$1 -> 0
A97: d> | B97: =(R96+T96) -> 0 | G97: ICOST | K97: mu_D | L97: ITEM | R97: =SUM(R94:R96) -> 119323.2 | T97: =SUM(T94:T96) -> 0
E98: Sell Rate | F98: Sell Total | K98: IB | AG98: U_M_Sell | AH98: T_M_Sell | AI98: U_L_Sell | AJ98: T_L_Sell | AK98: Total_Sell | AM98: T_M_Cost | AN98: T_L_Phr | AO98: Mat/Lab=1
A99: 12 | B99: mr | D99: Item: 5.0b | E99: =IF(AND($A99=0,$A$1="DIF"),0, ROUND(ROUND(($R103*$S$5+($T103*$T$5))/$A99,2)*$C$5,2)) -> 153.33 | F99: =ROUND($A99*$E99,2) -> 1839.96 | G99: ISELL | K99: mu_D | L99: ITEM | T99: =IF(AND($R103=0,$T103=0),"0.00","mu: "& ROUND(F99/$C$5/($R103+$T103*$D$9),2)) -> mu: 1 | AG99: =IF($E99=0,0,ROUND($R103*$S$5*$C$5/$A99,2)) -> 153.33 | AH99: =$AG99*$A99 -> 1839.96 | AI99: =$E99-$AG99 -> 0 | AJ99: =$A99*$AI99 -> 0 | AK99: =ROUND(($AG99+$AI99)*$A99,2) -> 1839.96 | AM99: =ROUND(R103,2) -> 1839.96 | AN99: =ROUND(T103,2) -> 0 | AO99: =ROUND(AM99+AN99,2)*A99 -> 22079.52
D100: Switchgear Panel SPB-PR (Plant Room) to Motor Control Centre MCC-PR (Plant Room). 2 x (5core x 95.0 mm2 FG16(0)M16). | K100: n
A101: =A99 -> 12 | B101: LS | D101: Subcontracting Works (Specify Contractor Name) | F101: Megaline | G101: SUBC_007 | H101: 960 | I101: MISC | O101: 4 | P101: 38594 | Q101: 153.33 | R101: =$A101*Q101 -> 1839.96 | T101: =$A101*S101*$T$1 -> 0
R102: =$A102*Q102 -> 0 | T102: =$A102*S102*$T$1 -> 0
A103: d> | B103: =(R102+T102) -> 0 | G103: ICOST | K103: mu_D | L103: ITEM | R103: =SUM(R100:R102) -> 1839.96 | T103: =SUM(T100:T102) -> 0
E104: Sell Rate | F104: Sell Total | K104: IB | AG104: U_M_Sell | AH104: T_M_Sell | AI104: U_L_Sell | AJ104: T_L_Sell | AK104: Total_Sell | AM104: T_M_Cost | AN104: T_L_Phr | AO104: Mat/Lab=1
A105: 5 | B105: mr | D105: Item: 5.0c | E105: =IF(AND($A105=0,$A$1="DIF"),0, ROUND(ROUND(($R109*$S$5+($T109*$T$5))/$A105,2)*$C$5,2)) -> 69.3 | F105: =ROUND($A105*$E105,2) -> 346.5 | G105: ISELL | K105: mu_D | L105: ITEM | T105: =IF(AND($R109=0,$T109=0),"0.00","mu: "& ROUND(F105/$C$5/($R109+$T109*$D$9),2)) -> mu: 1 | AG105: =IF($E105=0,0,ROUND($R109*$S$5*$C$5/$A105,2)) -> 69.3 | AH105: =$AG105*$A105 -> 346.5 | AI105: =$E105-$AG105 -> 0 | AJ105: =$A105*$AI105 -> 0 | AK105: =ROUND(($AG105+$AI105)*$A105,2) -> 346.5 | AM105: =ROUND(R109,2) -> 346.5 | AN105: =ROUND(T109,2) -> 0 | AO105: =ROUND(AM105+AN105,2)*A105 -> 1732.5
D106: Earth bar in Switchgear Panel SPB-PR (Plant Room) to Equipotential earth bonding busbar EB1. 2 x (1core x 95.0 mm2 LSZH/Cu). | K106: n
A107: =A105 -> 5 | B107: LS | D107: Subcontracting Works (Specify Contractor Name) | F107: Megaline | G107: SUBC_007 | H107: 960 | I107: MISC | O107: 4 | P107: 38594 | Q107: 69.3 | R107: =$A107*Q107 -> 346.5 | T107: =$A107*S107*$T$1 -> 0
R108: =$A108*Q108 -> 0 | T108: =$A108*S108*$T$1 -> 0
A109: d> | B109: =(R108+T108) -> 0 | G109: ICOST | K109: mu_D | L109: ITEM | R109: =SUM(R106:R108) -> 346.5 | T109: =SUM(T106:T108) -> 0
K110: TB
C111: t
D112: LIGHTING INSTALLATION
...

Sheet AsAwarded_Discount
A1: As awarded Estimate workings
A3: Electrical Estimate (Rev A) | B3: 392402.85 | C3: Excluding Prelims, Fire stopping, Commissioning and Maintenance
A4: Electrical (Megaline) | B4: =ML_Sum!R26 -> 185902.47
A5: Electrical less Megaline | B5: =B3-B4 -> 206500.38
A7: Quoted value including Mechanical | B7: 1792000.9 | C7: Excluding Maintenance and Provisional Sums
A8: 2.34% discount | B8: 42092.252 | C8: Value as per submitted BOQ
A9: Contract value less discount | B9: =B7-B8 -> 1749908.7
A13: Contract value less Megaline | B13: =B7-B4 -> 1606098.5
A14: 2.34% discount | B14: 42092.252
A15: Percentage discount on value less Megaline | B15: =B14/B13 -> 0.026207766

Sheet BMS_Points
B1: Qty | C1: Low Level points | D1: High level points | G1: DDC
C2: Per Unit | E2: Total
A3: Centralised Controller | B3: 1 | C3: 0 | D3: 1 | E3: =C3*B3 -> 0 | F3: =D3*B3 -> 1 | G3: 2
A4: EC Net Trends Alarms | B4: 1 | C4: 0 | D4: 1 | E4: =C4*B4 -> 0 | F4: =D4*B4 -> 1 | G4: 2
B5: 4 | C5: 0 | D5: 1 | E5: =C5*B5 -> 0 | F5: =D5*B5 -> 4 | G5: 2
A6: Pressurisation Units | B6: 3 | C6: 4 | D6: 1 | E6: =C6*B6 -> 12 | F6: =D6*B6 -> 3 | G6: 2
A7: Tanks | B7: 2 | C7: 3 | D7: 0 | E7: =C7*B7 -> 6 | F7: =D7*B7 -> 0 | G7: 2
A8: AC Unit | B8: 1 | C8: 4 | D8: 1 | E8: =C8*B8 -> 4 | F8: =D8*B8 -> 1 | G8: 2
A9: AHUs | B9: 26 | C9: 0 | D9: 1 | E9: =C9*B9 -> 0 | F9: =D9*B9 -> 26 | G9: 4
A10: Pump P301 | B10: 1 | C10: 4 | D10: 1 | E10: =C10*B10 -> 4 | F10: =D10*B10 -> 1 | G10: 4 | H10: BMS
A11: Pump P302 | B11: 1 | C11: 4 | D11: 1 | E11: =C11*B11 -> 4 | F11: =D11*B11 -> 1 | G11: 4 | H11: BMS
A12: Pump P303 | B12: 1 | C12: 4 | D12: 1 | E12: =C12*B12 -> 4 | F12: =D12*B12 -> 1 | G12: 4 | H12: BMS
A13: Pump P304 | B13: 1 | C13: 4 | D13: 1 | E13: =C13*B13 -> 4 | F13: =D13*B13 -> 1 | G13: 4 | H13: BMS
A14: Pump P305 | B14: 1 | C14: 4 | D14: 1 | E14: =C14*B14 -> 4 | F14: =D14*B14 -> 1 | G14: 4 | H14: BMS
A15: Pump P306 | B15: 1 | C15: 4 | D15: 1 | E15: =C15*B15 -> 4 | F15: =D15*B15 -> 1 | G15: 4 | H15: BMS
A16: Pump P307 | B16: 1 | C16: 4 | D16: 1 | E16: =C16*B16 -> 4 | F16: =D16*B16 -> 1 | G16: 4 | H16: BMS
A17: Pump P308 | B17: 1 | C17: 4 | D17: 1 | E17: =C17*B17 -> 4 | F17: =D17*B17 -> 1 | G17: 4 | H17: BMS
A18: Pump P309 | B18: 1 | C18: 4 | D18: 1 | E18: =C18*B18 -> 4 | F18: =D18*B18 -> 1 | G18: 4 | H18: BMS
A19: Pump P310 | B19: 1 | C19: 4 | D19: 1 | E19: =C19*B19 -> 4 | F19: =D19*B19 -> 1 | G19: 4 | H19: BMS
A20: Pump P401 | B20: 1 | C20: 4 | D20: 1 | E20: =C20*B20 -> 4 | F20: =D20*B20 -> 1 | G20: 4 | H20: BMS
A21: Pump P402 | B21: 1 | C21: 4 | D21: 1 | E21: =C21*B21 -> 4 | F21: =D21*B21 -> 1 | G21: 4 | H21: BMS
... A30: Temperature sensor | B30: 16 | C30: 1 | D30: 0 | E30: =C30*B30 -> 16 | F30: =D30*B30 -> 0 | G30: 2 | H30: Chillers C-1, C-2 and C-3
A31: Flow switch | B31: =20-14 -> 6 | C31: 1 | D31: 0 | E31: =C31*B31 -> 6 | F31: =D31*B31 -> 0 | G31: 2 | H31: Chillers C-1, C-2 and C-3
A32: Differnetial Pressure switch | B32: 14 | C32: 1 | D32: 0 | E32: =C32*B32 -> 14 | F32: =D32*B32 -> 0 | G32: 2 | H32: Chillers C-1, C-2 and C-3
A33: Valves | B33: 3 | C33: 2 | D33: 0 | E33: =C33*B33 -> 6 | F33: =D33*B33 -> 0 | G33: 2 | H33: Chillers C-1, C-2 and C-3
A34: Energy meters | B34: 6 | C34: 1 | D34: 1 | E34: =C34*B34 -> 6 | F34: =D34*B34 -> 6 | G34: 2 | H34: Chillers C-1, C-2 and C-3
A35: Temperature sensor | B35: 3 | C35: 1 | D35: 0 | E35: =C35*B35 -> 3 | F35: =D35*B35 -> 0 | G35: 2 | H35: Chiller C-4
A36: Flow switch | B36: =5-2 -> 3 | C36: 1 | D36: 0 | E36: =C36*B36 -> 3 | F36: =D36*B36 -> 0 | G36: 2 | H36: Chiller C-4
A37: Energy meters | B37: 1 | C37: 1 | D37: 1 | E37: =C37*B37 -> 1 | F37: =D37*B37 -> 1 | G37: 2 | H37: Chiller C-4
A38: Differnetial Pressure switch | B38: 2 | C38: 1 | D38: 0 | E38: =C38*B38 -> 2 | F38: =D38*B38 -> 0 | G38: 2 | H38: Chiller C-4
A39: Extract Fan EF/1 | B39: 1 | C39: 4 | D39: 1 | E39: =C39*B39 -> 4 | F39: =D39*B39 -> 1 | G39: 2
A40: Extract Fan EF/2 | B40: 1 | C40: 4 | D40: 1 | E40: =C40*B40 -> 4 | F40: =D40*B40 -> 1 | G40: 2
A41: Extract Fan EF/3 | B41: 1 | C41: 4 | D41: 1 | E41: =C41*B41 -> 4 | F41: =D41*B41 -> 1 | G41: 2
A42: Refrigerant Leakage control panel | B42: 1 | C42: 7 | D42: 1 | E42: =C42*B42 -> 7 | F42: =D42*B42 -> 1 | G42: 2
A43: 3way valves | B43: 12 | C43: 2 | D43: 2 | E43: =C43*B43 -> 24 | F43: =D43*B43 -> 24 | G43: 2
E48: =SUM(E3:E43) -> 202 | F48: =SUM(F3:F43) -> 91 | G48: =SUM(E48:F48) -> 293
E50: Low Level points | F50: High level points
D51: Level 2 | E51: =SUMIF(G3:G43,2,E3:E43) -> 122 | F51: =SUMIF(G3:G43,2,F3:F43) -> 45
D52: Level 4 | E52: =SUMIF(G3:G43,4,E3:E43) -> 80 | F52: =SUMIF(G3:G43,4,F3:F43) -> 46 | G52: =SUM(E51:F52) -> 293
A57: Tracer Points
A58: Pump P101 | B58: 1 | C58: 4 | D58: 1 | E58: =C58*B58 -> 4 | F58: =D58*B58 -> 1 | G58: 2 | H58: Tracer
A59: Pump P102 | B59: 1 | C59: 4 | D59: 1 | E59: =C59*B59 -> 4 | F59: =D59*B59 -> 1 | G59: 2 | H59: Tracer
A60: Pump P103 | B60: 1 | C60: 4 | D60: 1 | E60: =C60*B60 -> 4 | F60: =D60*B60 -> 1 | G60: 2 | H60: Tracer
A61: Pump P104 | B61: 1 | C61: 4 | D61: 1 | E61: =C61*B61 -> 4 | F61: =D61*B61 -> 1 | G61: 2 | H61: Tracer
A62: Pump P201 | B62: 1 | C62: 4 | D62: 1 | E62: =C62*B62 -> 4 | F62: =D62*B62 -> 1 | G62: 2 | H62: Tracer
A63: Pump P202 | B63: 1 | C63: 4 | D63: 1 | E63: =C63*B63 -> 4 | F63: =D63*B63 -> 1 | G63: 2 | H63: Tracer
A64: Pump P203 | B64: 1 | C64: 4 | D64: 1 | E64: =C64*B64 -> 4 | F64: =D64*B64 -> 1 | G64: 2 | H64: Tracer
A65: Pump P204 | B65: 1 | C65: 4 | D65: 1 | E65: =C65*B65 -> 4 | F65: =D65*B65 -> 1 | G65: 2 | H65: Tracer
A66: Pump P205 | B66: 1 | C66: 4 | D66: 1 | E66: =C66*B66 -> 4 | F66: =D66*B66 -> 1 | G66: 2 | H66: Tracer
A67: Pump P206 | B67: 1 | C67: 4 | D67: 1 | E67: =C67*B67 -> 4 | F67: =D67*B67 -> 1 | G67: 2 | H67: Tracer
A68: Pump P207 | B68: 1 | C68: 4 | D68: 1 | E68: =C68*B68 -> 4 | F68: =D68*B68 -> 1 | G68: 2 | H68: Tracer
A69: Pump P208 | B69: 1 | C69: 4 | D69: 1 | E69: =C69*B69 -> 4 | F69: =D69*B69 -> 1 | G69: 2 | H69: Tracer
... A79: Heat Pumps | B79: 3 | C79: 0 | D79: 1 | E79: =C79*B79 -> 0 | F79: =D79*B79 -> 3 | G79: 2 | H79: Tracer
E83: =SUM(E58:E79) -> 80 | F83: =SUM(F58:F79) -> 27 | G83: =SUM(E83:F83) -> 107
E85: Low Level points | F85: High level points
D86: Level 2 | E86: =SUMIF(G58:G79,2,E58:E79) -> 80 | F86: =SUMIF(G58:G79,2,F58:F79) -> 27
D87: Level 4 | E87: =SUMIF(G58:G79,4,E58:E79) -> 0 | F87: =SUMIF(G58:G79,4,F58:F79) -> 0 | G87: =SUM(E86:F87) -> 107
A93: Devices | B93: In Mech BOQ | C93: As per Mech drawings
A94: Temperature sensors | B94: 22 | C94: =B30+B35 -> 19
A95: Energy Meters | B95: 7 | C95: =B34+B37 -> 7
A96: Flow Switches | B96: 6 | C96: =B31+B36 -> 9
A97: Motorised valves | B97: =9+6 -> 15 | C97: =B33+B43 -> 15

Sheet Elec_BOQ
A1: BILL OF QUANTITIES
A2: ELECTRICAL INSTALLATION WORKS
A5: Item | C5: Qty | D5: Unit | E5: Rate in € | F5: Total
A7: T | B7: MAIN ELECTRICAL INFRASTRUCTURE
A9: T | B9: SWITCHGEAR AND OTHER ACCESSORIES
A11: 1T | B11: Supply only the following switchgear and other accessories.
A13: 1.0a | B13: Distribution Board DB-L2PR (metalclad enclosure) | C13: 1 | D13: No. | E13: =Elec_Est!E27 -> 989.85 | F13: =E13*C13 -> 989.85
A15: 1.0b | B15: Equipotential earth bonding busbar EB1, rated at 600A or more, wall mounted to the wall on plastic insulators. (approx. 400mm x 50mm x 6mm). | C15: 1 | D15: No. | E15: =Elec_Est!E33 -> 232.28 | F15: =E15*C15 -> 232.28
A18: 2T | B18: Install and connect only the following switchgear and other accessories.
A20: 2.0a | B20: Distribution Board DB-L2PR (metalclad enclosure) | C20: 1 | D20: No. | E20: =Elec_Est!E43 -> 343.15 | F20: =E20*C20 -> 343.15
A22: 2.0b | B22: Equipotential earth bonding busbar EB1, rated at 600A or more, wall mounted to the wall on plastic insulators. (approx. 400mm x 50mm x 6mm). | C22: 1 | D22: No. | E22: =Elec_Est!E49 -> 232.28 | F22: =E22*C22 -> 232.28
A25: T | B25: CABLE MANAGEMENT
A27: 3T | B27: Supply and install the following galvanized steel cable tray, from MSG-1 to SPB-PR in the new Plant Room. Cost is to include all cantilever bracketing to wall or suspension bracketing to the ceiling as necessary.
A28: 3.0a | B28: 500mm x 50mm. | C28: 155 | D28: m | E28: =Elec_Est!E63 -> 123.09 | F28: =E28*C28 -> 19078.95
A31: 4T | B31: Supply and install the following galvanized steel cable ladder above SPB-PR. Cost is to include all the support bracketing to wall or ceiling as necessary.
A33: 4.0a | B33: 500mm x 100mm. | C33: 4 | D33: m | E33: =Elec_Est!E73 -> 126.04 | F33: =E33*C33 -> 504.16
A49: P | B49: Total carried forward to summary page | F49: =SUM(F7:F47) -> 21380.67
A55: Item | C55: Qty | D55: Unit | E55: Rate in € | F55: Total
A57: T | B57: POWER CABLING
A59: 5T | B59: Supply, install and connect the following power cables. Cost is to include all cable installation and termination accessories as necessary. Cables installed on low level (less than 2.5 metres from FFL) cable trays are to be mechanically protected by cable tray covers.
A61: 5.0a | B61: 1600A MCCB in existing Main Switchgear Panel MSG-1 to the new Switchgear Panel SPB-PR (Plant Room).
B62: 6 x (5core x 120.0 mm2 FG16(0)M16). | C62: 160 | D62: mr | E62: =Elec_Est!E93 -> 745.77 | F62: =E62*C62 -> 119323.2
A64: 5.0b | B64: Switchgear Panel SPB-PR (Plant Room) to Motor Control Centre MCC-PR (Plant Room).
B65: 2 x (5core x 95.0 mm2 FG16(0)M16). | C65: 12 | D65: mr | E65: =Elec_Est!E99 -> 153.33 | F65: =E65*C65 -> 1839.96
A67: 5.0c | B67: Earth bar in Switchgear Panel SPB-PR (Plant Room) to Equipotential earth bonding busbar EB1.
B68: 2 x (1core x 95.0 mm2 LSZH/Cu). | C68: 5 | D68: mr | E68: =Elec_Est!E105 -> 69.3 | F68: =E68*C68 -> 346.5
A71: T | B71: LIGHTING INSTALLATION
A73: 6T | B73: Supply and install the following lighting points in the electrical switchroom for the Plant Room (PR), as specified. (Metalclad Installation)
A75: 6.0a | B75: Two lighting points controlled by one switch. | C75: 2 | D75: No. | E75: =Elec_Est!E119 -> 106.06 | F75: =E75*C75 -> 212.12
A77: 6.0b | B77: Non-maintained emergency lighting points (Fittings Type E4). | C77: 3 | D77: No. | E77: =Elec_Est!E125 -> 106.06 | F77: =E77*C77 -> 318.18
A80: 7T | B80: Supply only the following light fittings and accessories.
A82: 7.0a | B82: Type A | C82: 4 | D82: No. | E82: =Elec_Est!E135 -> 39.59 | F82: =E82*C82 -> 158.36
A84: 7.0b | B84: Type E4 | C84: 3 | D84: No. | E84: =Elec_Est!E141 -> 65.99 | F84: =E84*C84 -> 197.97
A87: 8T | B87: Install and connect only the following light fittings and accessories.
A89: 8.0a | B89: Type A | C89: 4 | D89: No. | E89: =Elec_Est!E151 -> 34.31 | F89: =E89*C89 -> 137.24
A91: 8.0b | B91: Type E4 | C91: 3 | D91: No. | E91: =Elec_Est!E157 -> 34.31 | F91: =E91*C91 -> 102.93
A98: P | B98: Total carried forward to summary page | F98: =SUM(F57:F96) -> 122636.46
A104: Item | C104: Qty | D104: Unit | E104: Rate in € | F104: Total
A106: T | B106: POWER INSTALLATION
A108: 9T | B108: Supply, install and connect the following power points. (Metalclad Installation)
A110: 9.0a | B110: Double socket outlets | C110: 3 | D110: No. | E110: =Elec_Est!E177 -> 138.46 | F110: =E110*C110 -> 415.38
A112: 9.0b | B112: 16A TPN+E Rotary isolated industrial socket outlets | C112: 1 | D112: No. | E112: =Elec_Est!E183 -> 247.73 | F112: =E112*C112 -> 247.73
A114: 9.0c | B114: Fused connection unit (AC unit) | C114: 1 | D114: No. | E114: =Elec_Est!E189 -> 164.2 | F114: =E114*C114 -> 164.2
A117: T | B117: CABLE MANAGEMENT
A119: 10T | B119: Supply and install the following galvanized steel cable tray. Cost is to include all bracketing to wall or ceiling as necessary.
B120: Cost is to include all the support bracketing to wall , to ceiling and floor-to-ceiling, as necessary.
A122: 10.0a | B122: 100mm | C122: 30 | D122: m | E122: =Elec_Est!E203 -> 18.56 | F122: =E122*C122 -> 556.8
A124: 10.0b | B124: 100mm (Vertical drops onto machinery) | C124: 20 | D124: m | E124: =Elec_Est!E209 -> 18.56 | F124: =E124*C124 -> 371.2
A126: 10.0c | B126: 150mm | C126: 25 | D126: m | E126: =Elec_Est!E215 -> 20.56 | F126: =E126*C126 -> 514
A128: 10.0d | B128: 150mm (Vertical drops onto machinery) | C128: 10 | D128: m | E128: =Elec_Est!E221 -> 20.56 | F128: =E128*C128 -> 205.6
A130: 10.0e | B130: 200mm | C130: 28 | D130: m | E130: =Elec_Est!E227 -> 22.62 | F130: =E130*C130 -> 633.36
A132: 10.0f | B132: 200mm (Vertical drops onto machinery) | C132: 15 | D132: m | E132: =Elec_Est!E233 -> 22.62 | F132: =E132*C132 -> 339.3
A134: 10.0g | B134: 300mm | C134: 7 | D134: m | E134: =Elec_Est!E239 -> 30.01 | F134: =E134*C134 -> 210.07
A136: 10.0h | B136: 500mm | C136: 8 | D136: m | E136: =Elec_Est!E245 -> 43.69 | F136: =E136*C136 -> 349.52
A139: T | B139: POWER CABLING TO THE HEAT PUMPS
A141: 11T | B141: Supply, install and connect the following power cables. Cost is to include all cable installation and termination accessories, terminal extension fish plates as necessary. Cables installed on low level (less than 2.5 metres from FFL) cable trays are to be mechanically protected by cable tray covers.
A143: 11.0a | B143: Switchgear Panel SPB-PR (Plant Room) to High Temperature Heat Pump 1 (SPBPR/2)
B144: 2 x (5core x 120.0 mm2 FG16(0)M16) | C144: 25 | D144: mr | E144: =Elec_Est!E259 -> 252.83 | F144: =E144*C144 -> 6320.75
A150: P | B150: Total carried forward to summary page | F150: =SUM(F106:F148) -> 10327.91
A156: Item | C156: Qty | D156: Unit | E156: Rate in € | F156: Total
A158: 11.0b | B158: Switchgear Panel SPB-PR (Plant Room) to High Temperature Heat Pump 2 (SPBPR/3)
B159: 2 x (5core x 120.0 mm2 FG16(0)M16) | C159: 23 | D159: mr | E159: =Elec_Est!E271 -> 255.16 | F159: =E159*C159 -> 5868.68
A161: 11.0c | B161: Switchgear Panel SPB-PR (Plant Room) to High Temperature Heat Pump 3 (SPBPR/4)
B162: 2 x (5core x 120.0 mm2 FG16(0)M16) | C162: 29 | D162: mr | E162: =Elec_Est!E277 -> 249.13 | F162: =E162*C162 -> 7224.77
A165: T | B165: POWER CABLING TO THE CHILLERS
A167: 12T | B167: Supply, install, modify and connect the following power cables. Cost is to include all cable installation and termination accessories as necessary. Cables installed on low level (less than 2.5 metres from FFL) cable trays are to be mechanically protected by cable tray covers.
A169: 12.0a | B169: Disconnect the existing 3 x (5corex120mmsq XLPE/SWA/LSZH/Cu) multicore cables, connected to the temporary Chiller, from both the chiller's power input terminals end and from SPBN2-1. | C169: 1 | D169: LS | E169: =Elec_Est!F291+Elec_Est!F297 -> 1596.32 | F169: =E169*C169 -> 1596.32
A171: 12.0b | B171: Pull back the above cables and install them on the existing 500mm cable tray within the Plant Room, modify and re-connect the above three existing multicore cables directly to the power input terminals of the new Chiller 1 and to SPBN2-1. Cost is to include all cable installation and termination accessories, terminal extension fish plates as necessary and cable termination / glanding box on top of the chiller if required. | C171: 1 | D171: LS | E171: =Elec_Est!E303+Elec_Est!E309 -> 2116.4 | F171: =E171*C171 -> 2116.4
A173: 12.0c | B173: Disconnect the two existing 2 x (4corex120mmsq XLPE/SWA) multicore cables, connected to Chiller 2, from the existing Chiller 2 end only (not from SPBN2-1). | C173: 1 | D173: LS | E173: =Elec_Est!E315+Elec_Est!E321 -> 798.16 | F173: =E173*C173 -> 798.16
A175: 12.0d | B175: Relocate, modify and re-connect the above two existing multicore XLPE/SWA cables directly to the power input terminals of the new Chiller 2. Cost is to include all cable installation and termination accessories, terminal extension fish plates as necessary and cable termination / glanding box on top of the chiller if required. | C175: 1 | D175: LS | E175: =Elec_Est!E327+Elec_Est!E333 -> 1399.21 | F175: =E175*C175 -> 1399.21
A187: P | B187: Total carried forward to summary page | F187: =SUM(F157:F185) -> 19003.54
A193: Item | C193: Qty | D193: Unit | E193: Rate in € | F193: Total
A195: 12.0e | B195: Relocate, modify and re-connect one of the existing multicore XLPE/SWA cables, formerly supplying existing Chiller 1, directly to the power input terminals of the new Chiller 2 and to the existing 800A MCCB within SPBN2-1. Cost is to include all cable installation and termination accessories, terminal extension fish plates etc. as necessary. | C195: 1 | D195: LS | E195: =Elec_Est!E345+Elec_Est!E351 -> 1633.27 | F195: =E195*C195 -> 1633.27
A197: 12.0f | B197: Disconnect the two existing 2 x (4corex120mmsq XLPE/SWA) multicore cables, connected to Chiller 3, from the existing Chiller 3 end only (not from SPBN2-1). | C197: 1 | D197: LS | E197: =Elec_Est!E357+Elec_Est!E363 -> 798.16 | F197: =E197*C197 -> 798.16
A199: 12.0g | B199: Relocate, modify and re-connect the above two existing multicore XLPE/SWA cables directly to the power input terminals of the new Chiller 3. Cost is to include all cable installation and termination accessories, terminal extension fish plates as necessary and cable termination / glanding box on top of the chiller if required. | C199: 1 | D199: LS | E199: =Elec_Est!E369+Elec_Est!E375 -> 1399.21 | F199: =E199*C199 -> 1399.21
A201: 12.0h | B201: Relocate, modify and re-connect one of the existing multicore XLPE/SWA cables, formerly supplying existing Chiller 1, directly to the power input terminals of the new Chiller 2 and to the existing 800A MCCB within SPBN2-1. Cost is to include all cable installation and termination accessories, terminal extension fish plates etc. as necessary. | C201: 1 | D201: LS | E201: =Elec_Est!E381+Elec_Est!E387 -> 1633.27 | F201: =E201*C201 -> 1633.27
A203: 12.0i | B203: Disconnect the existing 1 x (4corex185mmsq XLPE/SWA) multicore XLPE/SWA multicore cable connected to Chiller 4, from both ends, remove and place in client’s store. | C203: 1 | D203: LS | E203: =Elec_Est!E393+Elec_Est!E399 -> 1318.24 | F203: =E203*C203 -> 1318.24
A205: 12.0j | B205: Supply and install new 2 x (4corex95mmsq FG16(0)M16) multicore power cables between the existing 400A TP MCCB within SPBE2-3 and the power input terminals of the new Chiller 4. Cost is to include all cable installation and termination accessories as necessary. | C205: 32 | D205: mr | E205: =Elec_Est!E405 -> 218.18 | F205: =E205*C205 -> 6981.76
A222: P | B222: Total carried forward to summary page | F222: =SUM(F194:F218) -> 13763.91
A228: Item | C228: Qty | D228: Unit | E228: Rate in € | F228: Total
A230: T | B230: GENERAL
A232: 13 | B232: Supply and install external name and internal circuit reference identification labels on all switchgear, including all panelboards, distribution boards etc. | C232: 1 | D232: LS | E232: =Elec_Est!E421 -> 271.88 | F232: =E232*C232 -> 271.88
A235: 14 | B235: Supply and install circuit labels on all wiring accessories, including on all switches, socket outlets and isolators. | C235: 1 | D235: LS | E235: =Elec_Est!E427 -> 150.46 | F235: =E235*C235 -> 150.46
A238: 15 | B238: Supply and install proper circuit identification labels on all multicore cables, in rigid plastic material (UV protected when in external use). | C238: 1 | D238: LS | E238: =Elec_Est!E433 -> 472.49 | F238: =E238*C238 -> 472.49
A241: 16 | B241: Supply and install connecting schedule on all distribution
B242: boards, consumer units and lighting control panels. | C242: 1 | D242: LS | E242: =Elec_Est!E439 -> 0 | F242: =E242*C242 -> 0
A245: 17 | B245: Bonding of all the metallic structures to the Equipotential Earth Bar EB1, using suitably rated minimum 10mmsq LSZH insulated cables or copper tape, as necessary. | C245: 1 | D245: LS | E245: =Elec_Est!E445 -> 747.01 | F245: =E245*C245 -> 747.01
B248: Note: The costs for the disconnection and removal of all the to-be redundant electrical installation within the existing plantroom, thus including small power and control cables, conduit, cable trays, pump control panels, isolators etc. are to be included in other comprehensive "Dismantling" sections of these BOQs.
A269: P | B269: Total carried forward to summary page | F269: =SUM(F229:F267) -> 1641.84
A274: END!

Sheet Central_Controller_BOQ
A1: BILL OF QUANTITIES
A2: CENTRAL CONTROLLER
A5: Item | B5: Description | D5: Unit | E5: Qty | F5: Rate in € | G5: Total
A7: 1 | C7: Take delivery at site of Trane EPC Tracer SC+ control system procured by client, liaise with supplier, engineer, install and set to work all systems listed below and as described in the specifications. | D7: LS | E7: 1 | F7: =Elec_Est!E467 -> 1773.68 | G7: =F7*E7 -> 1773.68
C8: Controlled Items: -
C9: Chillers C-1, C-2 and C-3 - 3 x RTWD 170 HSE R1234ze (HMS Hydronic Multiple System)
C10: C-4 - 1 x GVWF 140 XSE R1234ze
C11: HTHP-1, HTHP-2, HTHP-3 - 3 x RTWF 125 HE R1234ze
C12: Primary circuits pumps
C13: Primary circuits valves
C15: Included in Trane Supply: -
C16: Tracer SC+ controller
C17: UC600 controller
C18: Tracer XM70 expansion modules
C19: TD7 display
C20: Probes
... C32: SWITCHGEAR AND OTHER ACCESSORIES
A34: =A7+1 -> 2 | C34: Supply and install the following switchgear and other accessories.
B36: a. | C36: Motor Control Centre MCC-PR (Pump Room) | D36: No. | E36: 1 | F36: =Elec_Est!E491 -> 8499.86 | G36: =E36*F36 -> 8499.86
C37: MCC-PR to include power and control section and all required wiring to interface with Trane EPC Tracer SC+ control system procured by client
C50: Total carried forward to summary page | G50: =SUM(G7:G48) -> 10273.54
A56: Item | B56: Description | D56: Unit | E56: Qty | F56: Rate in € | G56: Total
C58: POWER AND CONTROL CABLING FROM THE MOTOR CONTROL CENTRE (MCC)
A60: =A34+1 -> 3 | C60: Supply and install the following cables. Cost is to include all cable termination accessories where necessary.
B62: a. | C62: All the power cables from the Motor Control Centre MCC-PR (Pump Room) to all equipment being supplied power from MCC-PR (Refer to schedule) at Level 2. Cost is to include all the necessary metalclad cable management, local multi-pole maintenance isolators on floor brackets or to wall, next to the equipment and all cable termination accessories as necessary.
C64: Power supply cables, using XLPE/SWA/LSZH/Cu cables | D64: LS | E64: 1 | F64: =Elec_Est!E519 -> 15347.06 | G64: =F64*E64 -> 15347.06
B67: b. | C67: All the control cables from the Motor Control Centre MCC-PR (Pump Room) to all equipment being controlled by MCC-PR. Cost is to include all the necessary metalclad cable management.
C69: Control cables (where necessary), using multicore sheathed cables | D69: LS | E69: 1 | F69: =Elec_Est!Q737 -> Included with BMS
C98: Total carried forward to summary page | G98: =SUM(G58:G96) -> 15347.06

Sheet BMS_BOQ
A1: BILL OF QUANTITIES
A2: BUILDING MANAGEMENT SYSTEM
A5: Item | C5: Qty | D5: Unit | E5: Rate in € | F5: Total
A7: T | B7: Supply, deliver to site, install, test and commission the following as specified and as shown on the drawings, unless otherwise noted.
A12: T | B12: BMS Supervisor Software
A14: 1 | B14: Supply, Installation and configuration of the BMS supervisory software, complete with all the implementation of the UI and strategy into a complete solution as per tender document, schedules and BoQ requirements. | C14: 1 | D14: LS | E14: =Elec_Est!E773 -> 4452.57 | F14: =E14*C14 -> 4452.57
A17: T | B17: BMS Server
A19: =A14+1 -> 2 | B19: Supply, installation and configuration of the BMS Windows server. | C19: 1 | D19: LS | E19: =Elec_Est!E798 -> 4259.37 | F19: =E19*C19 -> 4259.37
A22: T | B22: Engineering IP Network
A24: =A19+1 -> 3 | B24: Design, supply and installation of a complete IP network that connects all the MCC's to the main BMS server and other third party systems | C24: 1 | D24: LS | E24: =Elec_Est!E818 -> 6299.5 | F24: =E24*C24 -> 6299.5
A27: T | B27: BMS Alarms
A29: =A24+1 -> 4 | B29: Design, and configuration of alarms per data point as required by project engineer. | C29: 1 | D29: LS | E29: =Elec_Est!E850 -> 2902.99 | F29: =E29*C29 -> 2902.99
A32: T | B32: BMS Trends
A34: =A29+1 -> 5 | B34: The configuration and upkeep of the trends and logs for all the project data points included in the project. | C34: 1 | D34: LS | E34: =Elec_Est!E869 -> 2267.64 | F34: =E34*C34 -> 2267.64
A37: T | B37: Complete working system
A39: =A34+1 -> 6 | B39: All wiring, containment, field devices etc. for a complete working systems | C39: 1 | D39: LS | E39: =Elec_Est!E888 -> 152433.92 | F39: =E39*C39 -> 152433.92
A50: P | B50: Total carried forward to summary page | F50: =SUM(F7:F48) -> 172615.99
A55: END!

Sheet SUMM PG 
A1: SUMMARY OF BILLS
F4: € | H4: €
A6: PRELIMINARIES
A8: Collection from page 2
A10: Collection from page 3 | H10: =SUM(F7:F10) -> 0
A13: ELECTRICAL INFRASTRUCTURE
A15: Collection from page 4 | F15: =Elec_BOQ!F49 -> 21380.67
A17: Collection from page 5 | F17: =Elec_BOQ!F98 -> 122636.46
A19: Collection from page 6 | F19: =Elec_BOQ!F150 -> 10327.91
A21: Collection from page 7 | F21: =Elec_BOQ!F187 -> 19003.54
A23: Collection from page 8 | F23: =Elec_BOQ!F222 -> 13763.91
A25: Collection from page 9 | F25: =Elec_BOQ!F269 -> 1641.84 | H25: =SUM(F15:F25) -> 188754.33 | J25: =Elec_Est!F458 -> 181972.18
A28: FIRE STOPPING
A30: Collection from page 10 | H30: =SUM(F30:G30) -> 0
A33: DISMANTLING EXISTING SERVICES
A35: Collection from page 11 | H35: =SUM(F35:G35) -> 0
A38: CHILLERS DISMANTLING
A40: Collection from page 12 | H40: =SUM(F40:G40) -> 0
A43: BOILERS DISMANTLING
A45: Collection from page 13 | H45: =SUM(F45:G45) -> 0
A48: CHILLERS NEW
A50: Collection from page 14
A52: Collection from page 15
A54: Collection from page 16
A56: Collection from page 17
A58: Collection from page 18
A60: Collection from page 19
A62: Collection from page 20
A64: Collection from page 21
A66: Collection from page 22 | H66: =SUM(F50:F66) -> 0
A69: HTHP NEW
A71: Collection from page 23
A73: Collection from page 24
A75: Collection from page 25
A77: Collection from page 26
A79: Collection from page 27
A81: Collection from page 28
A83: Collection from page 29 | H83: =SUM(F71:F83) -> 0
A86: PUMPS DISMANTLING
A88: Collection from page 30
A90: Collection from page 31
A92: Collection from page 32
A94: Collection from page 33 | H94: =SUM(F87:F94) -> 0
A97: CENTRAL CONTROLLER
A99: Collection from page 34 | F99: =Central_Controller_BOQ!G50 -> 10273.54
A101: Collection from page 35 | F101: =Central_Controller_BOQ!G98 -> 15347.06 | H101: =SUM(F99:F101) -> 25620.6 | J101: =Elec_Est!F760 -> 25620.6
A104: PUMPS NEW
A106: Collection from page 36
A108: Collection from page 37
A110: Collection from page 38
A112: Collection from page 39
A114: Collection from page 40
A116: Collection from page 41
A118: Collection from page 42
A120: Collection from page 43
A122: Collection from page 44
A124: Collection from page 45
A126: Collection from page 46
... A150: Collection from page 58
A152: Collection from page 59 | H152: =SUM(F105:F152) -> 0
A155: AHU MOTORS NEW
A157: Collection from page 60
A159: Collection from page 61
A161: Collection from page 62
A163: Collection from page 63 | H163: =SUM(F157:F163) -> 0
A166: EXTRACT FANS
A168: Collection from page 64 | H168: =SUM(F168:G168) -> 0
A171: AC SPLIT UNITS
A173: Collection from page 65 | H173: =SUM(F173:G173) -> 0
A176: BUILDING MANAGEMENT SYSTEM
A178: Collection from page 66 | F178: =BMS_BOQ!F50 -> 172615.99 | H178: =SUM(F178:G178) -> 172615.99 | J178: =Elec_Est!F948 -> 172615.99
A181: COMMISSIONING AND DOCUMENTATION
A183: Collection from page 67 | H183: =SUM(F183:G183) -> 0
A188: MAINTENANCE
A190: Collection from page 68 | H190: =SUM(F190:G190) -> 0
A193: PROVISIONAL SUM
A195: Collection from page 69 | H195: =SUM(F195:G195) -> 0
A198: Add / Omit (to specify):
A200: Total: | H200: =SUM(H1:H199) -> 386990.92 | J200: =SUM(J1:J199) -> 380208.77
A202: V.A.T. @ 18% | H202: =H200*18% -> 69658.366
A204: Overall Total in Euro: | G204: € | H204: =H202+H200 -> 456649.29
A210: Signature:
A212: Name in Block:
A214: Occupation:
A216: I.D. Card No.:
A218: VAT Reg. No.:
A220: For and on behalf of:
A222: Company Reg. No.:
A224: Address:
A228: Telephone No.:
A230: Fax No.:
A232: E-mail Address:
A234: Date:

Sheet Old_Est
B1: CLIENT: | C1: =ML_Sum!$C1 -> 1 | D1: =ML_Sum!$D1 -> Eden Lesuire Group | F1: =ML_Sum!$F1 -> 0 | I1: 1 | J1: =ML_Sum!$J1 -> 1 | K1: =ML_Sum!$K1 -> 1 | L1: =ML_Sum!$L1 -> 1 | M1: =ML_Sum!$M1 -> 1 | N1: =ML_Sum!$N1 -> 1 | O1: =ML_Sum!$O1 -> 1 | Q1: =ML_Sum!$Q1 -> € | R1: R/Lab Cont | S1: =ML_Sum!$S1 -> R | T1: =ML_Sum!$T1 -> 1 | U1: =ML_Sum!W1 -> BOQ | V1: INCL | W1: MULT | X1: AREA | Y1: BOQ | Z1: TDWG | AA1: ACT | AB1: DIFF
B2: PROJECT: | C2: =ML_Sum!$C2 -> 0.97379223 | D2: =ML_Sum!$D2 -> Intercontinental - Plant Retrofit | F2: =ML_Sum!$F2 -> Electrical | I2: 2 | J2: =ML_Sum!$J2 -> 1 | K2: =ML_Sum!$K2 -> 1 | L2: =ML_Sum!$L2 -> 1 | M2: =ML_Sum!$M2 -> 1 | N2: =ML_Sum!$N2 -> 1 | O2: =ML_Sum!$O2 -> 1 | Q2: =ML_Sum!$Q2 -> 0.026207766 | R2: mu_A | S2: =ML_Sum!$S2 -> 1.35 | T2: =ML_Sum!$T2 -> 37.071
B3: JOB DESC: | C3: =ML_Sum!$C3 -> 0.97379223 | D3: =ML_Sum!$D3 -> Retrofitting works for the Electrical Installations | F3: =ML_Sum!$F3 -> ECA (Technician) | I3: 3 | J3: =ML_Sum!$J3 -> 1 | K3: =ML_Sum!$K3 -> 1 | L3: =ML_Sum!$L3 -> 1 | M3: =ML_Sum!$M3 -> 1 | N3: =ML_Sum!$N3 -> 1 | O3: =ML_Sum!$O3 -> 1 | Q3: =ML_Sum!$Q3 -> 0.026207766 | R3: mu_B | S3: =ML_Sum!$S3 -> 1.35 | T3: =ML_Sum!$T3 -> 45.5355
B4: QUOTE No: | C4: =ML_Sum!$C4 -> 0.97379223 | D4: =ML_Sum!$D4 -> EL25-0477 | F4: =ML_Sum!$F4 -> ECA (Engineer) | I4: 4 | J4: =ML_Sum!$J4 -> 1 | K4: =ML_Sum!$K4 -> 1 | L4: =ML_Sum!$L4 -> 1 | M4: =ML_Sum!$M4 -> 1 | N4: =ML_Sum!$N4 -> 1 | O4: =ML_Sum!$O4 -> 1 | Q4: =ML_Sum!$Q4 -> 0.026207766 | R4: mu_C | S4: =ML_Sum!$S4 -> 1.35 | T4: =ML_Sum!$T4 -> 40.5
B5: CLIENTs REF: | C5: =ML_Sum!$C5 -> 1 | D5: =ML_Sum!$D5 -> Tender | F5: =ML_Sum!$F5 -> Megaline | I5: 5 | J5: =ML_Sum!$J5 -> 1 | K5: =ML_Sum!$K5 -> 1 | L5: =ML_Sum!$L5 -> 1 | M5: =ML_Sum!$M5 -> 1 | N5: =ML_Sum!$N5 -> 1 | O5: =ML_Sum!$O5 -> 1 | Q5: =ML_Sum!$Q5 -> 0 | R5: mu_D | S5: =ML_Sum!$S5 -> 1 | T5: =ML_Sum!$T5 -> 37.071
B6: VAT/DUTIES: | C6: =ML_Sum!$C6 -> 1 | D6: =ML_Sum!$D6 -> VAT EXCL. | F6: =ML_Sum!$F6 -> 0 | I6: 6 | J6: =ML_Sum!$J6 -> 1 | K6: =ML_Sum!$K6 -> 1 | L6: =ML_Sum!$L6 -> 1 | M6: =ML_Sum!$M6 -> 1 | N6: =ML_Sum!$N6 -> 1 | O6: =ML_Sum!$O6 -> 1 | Q6: =ML_Sum!$Q6 -> 0 | R6: mu_E | S6: =ML_Sum!$S6 -> 0 | T6: =ML_Sum!$T6 -> 0
B7: SAVED ON: | C7: =ML_Sum!$C7 -> 1 | D7: 39364 | F7: =ML_Sum!$F7 -> 0 | I7: 7 | J7: =ML_Sum!$J7 -> 1 | K7: =ML_Sum!$K7 -> 1 | L7: =ML_Sum!$L7 -> 1 | M7: =ML_Sum!$M7 -> 1 | N7: =ML_Sum!$N7 -> 1 | O7: =ML_Sum!$O7 -> 0 | Q7: =ML_Sum!$Q7 -> 0 | R7: mu_F | S7: =ML_Sum!$S7 -> 0 | T7: =ML_Sum!$T7 -> 0
B8: ESTIMATOR: | C8: =ML_Sum!$C8 -> 1 | D8: =ML_Sum!$D8 -> M.Scicluna | F8: =ML_Sum!$F8 -> 0 | I8: 8 | J8: =ML_Sum!$J8 -> 1 | K8: =ML_Sum!$K8 -> 1 | L8: =ML_Sum!$L8 -> 1 | M8: =ML_Sum!$M8 -> 1 | N8: =ML_Sum!$N8 -> 1 | O8: =ML_Sum!$O8 -> 0 | Q8: =ML_Sum!$Q8 -> 0 | R8: mu_G | S8: =ML_Sum!$S8 -> 0 | T8: =ML_Sum!$T8 -> 0
B9: LABOUR RATE: | C9: =ML_Sum!$C9 -> 1 | D9: =ML_Sum!$D9 -> 27.46 | F9: =ML_Sum!$F9 -> 0 | I9: 9 | J9: =ML_Sum!$J9 -> 1 | K9: =ML_Sum!$K9 -> 1 | L9: =ML_Sum!$L9 -> 1 | M9: =ML_Sum!$M9 -> 1 | N9: =ML_Sum!$N9 -> 1 | O9: =ML_Sum!$O9 -> 0 | Q9: =ML_Sum!$Q9 -> 0 | R9: mu_H | S9: =ML_Sum!$S9 -> 0 | T9: =ML_Sum!$T9 -> 0
C10: =ML_Sum!$C10 -> 1 | F10: =ML_Sum!$F10 -> 0 | I10: 10 | J10: =ML_Sum!$J10 -> 1 | K10: =ML_Sum!$K10 -> 1 | L10: =ML_Sum!$L10 -> 1 | M10: =ML_Sum!$M10 -> 1 | N10: =ML_Sum!$N10 -> 1 | O10: =ML_Sum!$O10 -> 1 | Q10: =ML_Sum!$Q10 -> 0 | R10: mu_I | S10: =ML_Sum!$S10 -> 0 | T10: =ML_Sum!$T10 -> 0
C11: =ML_Sum!$C11 -> 1 | F11: =ML_Sum!$F11 -> 0 | Q11: =ML_Sum!$Q11 -> 0 | R11: mu_J | S11: =ML_Sum!$S11 -> 0 | T11: =ML_Sum!$T11 -> 0
C12: =ML_Sum!$C12 -> 0.97379223 | F12: =ML_Sum!$F12 -> 0 | Q12: =ML_Sum!$Q12 -> 0.026207766 | R12: MIXED | S12: =ML_Sum!$S12 -> MAT MU | T12: =ML_Sum!$T12 -> LAB RATE
G13: ISELL | H13: C_CODE | I13: MAKE | J13: PART_NO | K13: MARKUP | L13: TYPE | M13: LIST_P | N13: P_FACT | O13: FIX | P13: DATE | Q13: %Dsct in BOQ | R13: MU TYPE | S13: MAT MU | T13: LAB RATE | AM13: Tot Mat Cost | AN13: Unit Lab phr. | AO13: Tot Lab phr. | AP13: < for ELM / MEE
K14: TB
C15: t | D15: Item:
D16: Electrical
K18: TB
C19: t
D20: MODIFICATIONS TO THE EXISTING MAIN SWITCHGEAR AND OTHER PANELS
K22: TB
C23: t
D24: Supply, install and connect the following switchgear and other accessories, to achieve a complete and fully functional works package.
E26: Sell Rate | F26: Sell Total | K26: IB | AG26: U_M_Sell | AH26: T_M_Sell | AI26: U_L_Sell | AJ26: T_L_Sell | AK26: Total_Sell | AM26: T_M_Cost | AN26: T_L_Phr | AO26: Mat/Lab=1
A27: 1 | B27: LS | D27: Item: 1.0a | E27: =IF(AND($A27=0,$A$1="DIF"),0, ROUND(ROUND(($R33*$S$2+($T33*$T$2))/A27,2)*$C$2,2)) -> 420.26 | F27: =ROUND($A27*$E27,2) -> 420.26 | G27: ISELL | K27: mu_A | L27: ITEM | T27: =IF(AND($R33=0,$T33=0),"0.00","mu :" & ROUND($F27/$C$2/($R33+$T33*$D$9),2)) -> mu :1.35 | AG27: =IF($E27=0,0,ROUND($R33*$S$2*$C$2/$A27,2)) -> 131.46 | AH27: =$AG27*$A27 -> 131.46 | AI27: =$E27-$AG27 -> 288.8 | AJ27: =$A27*$AI27 -> 288.8 | AK27: =ROUND(($AG27+$AI27)*$A27,2) -> 420.26 | AM27: =ROUND(R33,2) -> 100 | AN27: =ROUND(T33,2) -> 8 | AO27: =ROUND(AM27+AN27,2)*A27 -> 108
D28: 1250A TPN (4-pole) MCCB, fixed-mounting type, complete within an extension column to the existing Main Switchgear Panel MSG-1, as specified.
A29: 1 | B29: No | D29: Switchgear Arrangement Custom__1 | F29: 1250Amp 4pole MCCB | G29: SWLV_221 | H29: 510 | I29: (__) | K29: 11001 | O29: 2 | R29: =$A29*Q29 -> 0 | T29: =$A29*S29*$T$1 -> 0
A30: 1 | B30: No | D30: Erection Material | G30: EMAT_063 | H30: 501 | I30: (__) | K30: 01-002 | O30: 1 | Q30: 100 | R30: =$A30*Q30 -> 100 | T30: =$A30*S30*$T$1 -> 0
A31: 1 | B31: No | D31: Labour only (FIX 3) | G31: LABO_007 | H31: 900 | I31: MISC | O31: 3 | R31: =$A31*Q31 -> 0 | S31: 8 | T31: =$A31*S31*$T$1 -> 8
R32: =$A32*Q32 -> 0 | T32: =$A32*S32*$T$1 -> 0
A33: d> | B33: =(R32+T32) -> 0 | G33: ICOST | K33: mu_A | L33: ITEM | R33: =SUM(R28:R32) -> 100 | T33: =SUM(T28:T32) -> 8
E34: Sell Rate | K34: IB | AG34: U_M_Sell | AI34: U_L_Sell | AM34: T_M_Cost | AN34: T_L_Phr | AO34: Mat/Lab=1
A35: 1 | B35: LS | D35: Item: 1.0b | E35: =IF(AND($A35=0,$A$1="DIF"),0, ROUND(ROUND(($R41*$S$2+($T41*$T$2))/A35,2)*$C$2,2)) -> 420.26 | G35: ISELL | K35: BRATE | L35: ITEM | T35: =IF(AND($R41=0,$T41=0),"0.00","mu :" & ROUND($A35*$E35/$C$2/($R41+$T41*$D$9),2)) -> mu :1.35 | AG35: =IF($E35=0,0,ROUND($R41*$S$2*$C$2/$A35,2)) -> 131.46 | AI35: =$E35-$AG35 -> 288.8 | AM35: =ROUND(R41,2) -> 100 | AN35: =ROUND(T41,2) -> 8 | AO35: =ROUND(AM35+AN35,2)*A35 -> 108
D36: 1250A TPN (4-pole) MCCB, withdrawable-mounting type, complete within an extension column to the existing Main Switchgear Panel MSG-1, as specified. (Option)
A37: 1 | B37: No | D37: Switchgear Arrangement Custom__1 | E37: RATE_ONLY | F37: 1250Amp 4pole MCCB | G37: SWLV_221 | H37: RTONLY | I37: (__) | K37: 11001 | L37: RTONLY | O37: 2 | R37: =$A37*Q37 -> 0 | T37: =$A37*S37*$T$1 -> 0
A38: 1 | B38: No | D38: Erection Material | E38: RATE_ONLY | G38: EMAT_063 | H38: RTONLY | I38: (__) | K38: 01-002 | L38: RTONLY | O38: 1 | Q38: 100 | R38: =$A38*Q38 -> 100 | T38: =$A38*S38*$T$1 -> 0
A39: 1 | B39: No | D39: Labour only (FIX 3) | E39: RATE_ONLY | G39: LABO_007 | H39: RTONLY | I39: MISC | L39: RTONLY | O39: 3 | R39: =$A39*Q39 -> 0 | S39: 8 | T39: =$A39*S39*$T$1 -> 8
R40: =$A40*Q40 -> 0 | T40: =$A40*S40*$T$1 -> 0
A41: d> | B41: =(R40+T40) -> 0 | G41: ICOST | L41: BRATE | R41: =SUM(R36:R40) -> 100 | T41: =SUM(T36:T40) -> 8
E42: Sell Rate | F42: Sell Total | K42: IB | AG42: U_M_Sell | AH42: T_M_Sell | AI42: U_L_Sell | AJ42: T_L_Sell | AK42: Total_Sell | AM42: T_M_Cost | AN42: T_L_Phr | AO42: Mat/Lab=1
A43: 1 | B43: LS | D43: Item: 2.0a | E43: =IF(AND($A43=0,$A$1="DIF"),0, ROUND(ROUND(($R49*$S$2+($T49*$T$2))/A43,2)*$C$2,2)) -> 420.26 | F43: =ROUND($A43*$E43,2) -> 420.26 | G43: ISELL | K43: mu_A | L43: ITEM | T43: =IF(AND($R49=0,$T49=0),"0.00","mu :" & ROUND($F43/$C$2/($R49+$T49*$D$9),2)) -> mu :1.35 | AG43: =IF($E43=0,0,ROUND($R49*$S$2*$C$2/$A43,2)) -> 131.46 | AH43: =$AG43*$A43 -> 131.46 | AI43: =$E43-$AG43 -> 288.8 | AJ43: =$A43*$AI43 -> 288.8 | AK43: =ROUND(($AG43+$AI43)*$A43,2) -> 420.26 | AM43: =ROUND(R49,2) -> 100 | AN43: =ROUND(T49,2) -> 8 | AO43: =ROUND(AM43+AN43,2)*A43 -> 108
D44: 1600A TPN (4-pole) ACB, fixed-mounting type, as a replacement ACB within the existing MSG-2 (MSG2-N1), as specified.
A45: 1 | B45: No | D45: Switchgear Arrangement Custom__1 | F45: 1600Amp 4pole ACB | G45: SWLV_221 | H45: 510 | I45: (__) | K45: 11001 | O45: 2 | R45: =$A45*Q45 -> 0 | T45: =$A45*S45*$T$1 -> 0
A46: 1 | B46: No | D46: Erection Material | G46: EMAT_063 | H46: 501 | I46: (__) | K46: 01-002 | O46: 1 | Q46: 100 | R46: =$A46*Q46 -> 100 | T46: =$A46*S46*$T$1 -> 0
A47: 1 | B47: No | D47: Labour only (FIX 3) | G47: LABO_007 | H47: 900 | I47: MISC | O47: 3 | R47: =$A47*Q47 -> 0 | S47: 8 | T47: =$A47*S47*$T$1 -> 8
R48: =$A48*Q48 -> 0 | T48: =$A48*S48*$T$1 -> 0
A49: d> | B49: =(R48+T48) -> 0 | G49: ICOST | K49: mu_A | L49: ITEM | R49: =SUM(R44:R48) -> 100 | T49: =SUM(T44:T48) -> 8
E50: Sell Rate | K50: IB | AG50: U_M_Sell | AI50: U_L_Sell | AM50: T_M_Cost | AN50: T_L_Phr | AO50: Mat/Lab=1
A51: 1 | B51: LS | D51: Item: 2.0b | E51: =IF(AND($A51=0,$A$1="DIF"),0, ROUND(ROUND(($R57*$S$2+($T57*$T$2))/A51,2)*$C$2,2)) -> 420.26 | G51: ISELL | K51: BRATE | L51: ITEM | T51: =IF(AND($R57=0,$T57=0),"0.00","mu :" & ROUND($A51*$E51/$C$2/($R57+$T57*$D$9),2)) -> mu :1.35 | AG51: =IF($E51=0,0,ROUND($R57*$S$2*$C$2/$A51,2)) -> 131.46 | AI51: =$E51-$AG51 -> 288.8 | AM51: =ROUND(R57,2) -> 100 | AN51: =ROUND(T57,2) -> 8 | AO51: =ROUND(AM51+AN51,2)*A51 -> 108
D52: 1600A TPN (4-pole) ACB, withdrawable-mounting type, as a replacement ACB within the existing MSG-2 (MSG2-N1), as specified. (Option)
A53: 1 | B53: No | D53: Switchgear Arrangement Custom__1 | E53: RATE_ONLY | F53: 1600Amp 4pole ACB | G53: SWLV_221 | H53: RTONLY | I53: (__) | K53: 11001 | L53: RTONLY | O53: 2 | R53: =$A53*Q53 -> 0 | T53: =$A53*S53*$T$1 -> 0
A54: 1 | B54: No | D54: Erection Material | E54: RATE_ONLY | G54: EMAT_063 | H54: RTONLY | I54: (__) | K54: 01-002 | L54: RTONLY | O54: 1 | Q54: 100 | R54: =$A54*Q54 -> 100 | T54: =$A54*S54*$T$1 -> 0
A55: 1 | B55: No | D55: Labour only (FIX 3) | E55: RATE_ONLY | G55: LABO_007 | H55: RTONLY | I55: MISC | L55: RTONLY | O55: 3 | R55: =$A55*Q55 -> 0 | S55: 8 | T55: =$A55*S55*$T$1 -> 8
R56: =$A56*Q56 -> 0 | T56: =$A56*S56*$T$1 -> 0
A57: d> | B57: =(R56+T56) -> 0 | G57: ICOST | L57: BRATE | R57: =SUM(R52:R56) -> 100 | T57: =SUM(T52:T56) -> 8
E58: Sell Rate | K58: IB | AG58: U_M_Sell | AI58: U_L_Sell | AM58: T_M_Cost | AN58: T_L_Phr | AO58: Mat/Lab=1
A59: 1 | B59: LS | D59: Item: 2.0c | E59: =IF(AND($A59=0,$A$1="DIF"),0, ROUND(ROUND(($R65*$S$2+($T65*$T$2))/A59,2)*$C$2,2)) -> 420.26 | G59: ISELL | K59: BRATE | L59: ITEM | T59: =IF(AND($R65=0,$T65=0),"0.00","mu :" & ROUND($A59*$E59/$C$2/($R65+$T65*$D$9),2)) -> mu :1.35 | AG59: =IF($E59=0,0,ROUND($R65*$S$2*$C$2/$A59,2)) -> 131.46 | AI59: =$E59-$AG59 -> 288.8 | AM59: =ROUND(R65,2) -> 100 | AN59: =ROUND(T65,2) -> 8 | AO59: =ROUND(AM59+AN59,2)*A59 -> 108
D60: 1600A TP (3-pole) ACB, fixed-mounting type, as a replacement ACB within the existing MSG-2 (MSG2-N1). (Option), as specified.
A61: 1 | B61: No | D61: Switchgear Arrangement Custom__1 | E61: RATE_ONLY | F61: 1600Amp 3pole ACB | G61: SWLV_221 | H61: RTONLY | I61: (__) | K61: 11001 | L61: RTONLY | O61: 2 | R61: =$A61*Q61 -> 0 | T61: =$A61*S61*$T$1 -> 0
A62: 1 | B62: No | D62: Erection Material | E62: RATE_ONLY | G62: EMAT_063 | H62: RTONLY | I62: (__) | K62: 01-002 | L62: RTONLY | O62: 1 | Q62: 100 | R62: =$A62*Q62 -> 100 | T62: =$A62*S62*$T$1 -> 0
A63: 1 | B63: No | D63: Labour only (FIX 3) | E63: RATE_ONLY | G63: LABO_007 | H63: RTONLY | I63: MISC | L63: RTONLY | O63: 3 | R63: =$A63*Q63 -> 0 | S63: 8 | T63: =$A63*S63*$T$1 -> 8
R64: =$A64*Q64 -> 0 | T64: =$A64*S64*$T$1 -> 0
A65: d> | B65: =(R64+T64) -> 0 | G65: ICOST | L65: BRATE | R65: =SUM(R60:R64) -> 100 | T65: =SUM(T60:T64) -> 8
E66: Sell Rate | F66: Sell Total | K66: IB | AG66: U_M_Sell | AH66: T_M_Sell | AI66: U_L_Sell | AJ66: T_L_Sell | AK66: Total_Sell | AM66: T_M_Cost | AN66: T_L_Phr | AO66: Mat/Lab=1
A67: 1 | B67: LS | D67: Item: 3.0a | E67: =IF(AND($A67=0,$A$1="DIF"),0, ROUND(ROUND(($R73*$S$2+($T73*$T$2))/A67,2)*$C$2,2)) -> 420.26 | F67: =ROUND($A67*$E67,2) -> 420.26 | G67: ISELL | K67: mu_A | L67: ITEM | T67: =IF(AND($R73=0,$T73=0),"0.00","mu :" & ROUND($F67/$C$2/($R73+$T73*$D$9),2)) -> mu :1.35 | AG67: =IF($E67=0,0,ROUND($R73*$S$2*$C$2/$A67,2)) -> 131.46 | AH67: =$AG67*$A67 -> 131.46 | AI67: =$E67-$AG67 -> 288.8 | AJ67: =$A67*$AI67 -> 288.8 | AK67: =ROUND(($AG67+$AI67)*$A67,2) -> 420.26 | AM67: =ROUND(R73,2) -> 100 | AN67: =ROUND(T73,2) -> 8 | AO67: =ROUND(AM67+AN67,2)*A67 -> 108
D68: 1600A TPN (4-pole) ACB, fixed-mounting type, as a replacement ACB Main Incomer within the existing SPB-N2/1, as specified.
A69: 1 | B69: No | D69: Switchgear Arrangement Custom__1 | F69: 1600Amp 4pole ACB | G69: SWLV_221 | H69: 510 | I69: (__) | K69: 11001 | O69: 2 | R69: =$A69*Q69 -> 0 | T69: =$A69*S69*$T$1 -> 0
A70: 1 | B70: No | D70: Erection Material | G70: EMAT_063 | H70: 501 | I70: (__) | K70: 01-002 | O70: 1 | Q70: 100 | R70: =$A70*Q70 -> 100 | T70: =$A70*S70*$T$1 -> 0
A71: 1 | B71: No | D71: Labour only (FIX 3) | G71: LABO_007 | H71: 900 | I71: MISC | O71: 3 | R71: =$A71*Q71 -> 0 | S71: 8 | T71: =$A71*S71*$T$1 -> 8
R72: =$A72*Q72 -> 0 | T72: =$A72*S72*$T$1 -> 0
A73: d> | B73: =(R72+T72) -> 0 | G73: ICOST | K73: mu_A | L73: ITEM | R73: =SUM(R68:R72) -> 100 | T73: =SUM(T68:T72) -> 8
E74: Sell Rate | K74: IB | AG74: U_M_Sell | AI74: U_L_Sell | AM74: T_M_Cost | AN74: T_L_Phr | AO74: Mat/Lab=1
A75: 1 | B75: LS | D75: Item: 3.0b | E75: =IF(AND($A75=0,$A$1="DIF"),0, ROUND(ROUND(($R81*$S$2+($T81*$T$2))/A75,2)*$C$2,2)) -> 420.26 | G75: ISELL | K75: BRATE | L75: ITEM | T75: =IF(AND($R81=0,$T81=0),"0.00","mu :" & ROUND($A75*$E75/$C$2/($R81+$T81*$D$9),2)) -> mu :1.35 | AG75: =IF($E75=0,0,ROUND($R81*$S$2*$C$2/$A75,2)) -> 131.46 | AI75: =$E75-$AG75 -> 288.8 | AM75: =ROUND(R81,2) -> 100 | AN75: =ROUND(T81,2) -> 8 | AO75: =ROUND(AM75+AN75,2)*A75 -> 108
D76: 1600A TPN (4-pole) ACB, withdrawable-mounting type, as a replacement ACB Main Incomer within the existing SPB-N2/1, as specified. (Option)
A77: 1 | B77: No | D77: Switchgear Arrangement Custom__1 | E77: RATE_ONLY | F77: 1600Amp 4pole ACB | G77: SWLV_221 | H77: RTONLY | I77: (__) | K77: 11001 | L77: RTONLY | O77: 2 | R77: =$A77*Q77 -> 0 | T77: =$A77*S77*$T$1 -> 0
A78: 1 | B78: No | D78: Erection Material | E78: RATE_ONLY | G78: EMAT_063 | H78: RTONLY | I78: (__) | K78: 01-002 | L78: RTONLY | O78: 1 | Q78: 100 | R78: =$A78*Q78 -> 100 | T78: =$A78*S78*$T$1 -> 0
A79: 1 | B79: No | D79: Labour only (FIX 3) | E79: RATE_ONLY | G79: LABO_007 | H79: RTONLY | I79: MISC | L79: RTONLY | O79: 3 | R79: =$A79*Q79 -> 0 | S79: 8 | T79: =$A79*S79*$T$1 -> 8
R80: =$A80*Q80 -> 0 | T80: =$A80*S80*$T$1 -> 0
A81: d> | B81: =(R80+T80) -> 0 | G81: ICOST | L81: BRATE | R81: =SUM(R76:R80) -> 100 | T81: =SUM(T76:T80) -> 8
E82: Sell Rate | K82: IB | AG82: U_M_Sell | AI82: U_L_Sell | AM82: T_M_Cost | AN82: T_L_Phr | AO82: Mat/Lab=1
A83: 1 | B83: LS | D83: Item: 3.0c | E83: =IF(AND($A83=0,$A$1="DIF"),0, ROUND(ROUND(($R89*$S$2+($T89*$T$2))/A83,2)*$C$2,2)) -> 420.26 | G83: ISELL | K83: BRATE | L83: ITEM | T83: =IF(AND($R89=0,$T89=0),"0.00","mu :" & ROUND($A83*$E83/$C$2/($R89+$T89*$D$9),2)) -> mu :1.35 | AG83: =IF($E83=0,0,ROUND($R89*$S$2*$C$2/$A83,2)) -> 131.46 | AI83: =$E83-$AG83 -> 288.8 | AM83: =ROUND(R89,2) -> 100 | AN83: =ROUND(T89,2) -> 8 | AO83: =ROUND(AM83+AN83,2)*A83 -> 108
D84: 1600A TP (3-pole) ACB, fixed-mounting type, as a replacement ACB Main Incomer within the existing SPB-N2/1, as specified. (Option).
A85: 1 | B85: No | D85: Switchgear Arrangement Custom__1 | E85: RATE_ONLY | F85: 1600Amp 3pole ACB | G85: SWLV_221 | H85: RTONLY | I85: (__) | K85: 11001 | L85: RTONLY | O85: 2 | R85: =$A85*Q85 -> 0 | T85: =$A85*S85*$T$1 -> 0
A86: 1 | B86: No | D86: Erection Material | E86: RATE_ONLY | G86: EMAT_063 | H86: RTONLY | I86: (__) | K86: 01-002 | L86: RTONLY | O86: 1 | Q86: 100 | R86: =$A86*Q86 -> 100 | T86: =$A86*S86*$T$1 -> 0
A87: 1 | B87: No | D87: Labour only (FIX 3) | E87: RATE_ONLY | G87: LABO_007 | H87: RTONLY | I87: MISC | L87: RTONLY | O87: 3 | R87: =$A87*Q87 -> 0 | S87: 8 | T87: =$A87*S87*$T$1 -> 8
R88: =$A88*Q88 -> 0 | T88: =$A88*S88*$T$1 -> 0
A89: d> | B89: =(R88+T88) -> 0 | G89: ICOST | L89: BRATE | R89: =SUM(R84:R88) -> 100 | T89: =SUM(T84:T88) -> 8
A90: SB
B92: =$F92/$C$2-($R92*$S$2+$T92*$T$2) -> 0.0074952798 | D92: PAGE: | F92: =SUMIF($L14:$L90,"ITEM",F14:F90) -> 1260.78 | L92: PAGE | R92: =SUMIF($L14:$L90,"ITEM",R14:R90) -> 300 | T92: =SUMIF($L14:$L90,"ITEM",T14:T90) -> 24
B93: Discy: | F93: PAGE SELL | R93: PAGE MAT | T93: PAGE LAB
K96: TB
C97: t
D98: MAIN ELECTRICAL INFRASTRUCTURE
K100: TB
C101: t
D102: SWITCHGEAR AND OTHER ACCESSORIES
K104: TB
C105: t | D105: Item: 4.0
D106: Supply only the following switchgear and other accessories.
E108: Sell Rate | F108: Sell Total | K108: IB | AG108: U_M_Sell | AH108: T_M_Sell | AI108: U_L_Sell | AJ108: T_L_Sell | AK108: Total_Sell | AM108: T_M_Cost | AN108: T_L_Phr | AO108: Mat/Lab=1
A109: 1 | B109: No. | D109: Item: 4.0a | E109: =IF(AND($A109=0,$A$1="DIF"),0, ROUND(ROUND(($R114*$S$2+($T114*$T$2))/A109,2)*$C$2,2)) -> 801.7 | F109: =ROUND($A109*$E109,2) -> 801.7 | G109: ISELL | K109: mu_A | L109: ITEM | T109: =IF(AND($R114=0,$T114=0),"0.00","mu :" & ROUND($F109/$C$2/($R114+$T114*$D$9),2)) -> mu :1.35 | AG109: =IF($E109=0,0,ROUND($R114*$S$2*$C$2/$A109,2)) -> 657.31 | AH109: =$AG109*$A109 -> 657.31 | AI109: =$E109-$AG109 -> 144.39 | AJ109: =$A109*$AI109 -> 144.39 | AK109: =ROUND(($AG109+$AI109)*$A109,2) -> 801.7 | AM109: =ROUND(R114,2) -> 500 | AN109: =ROUND(T114,2) -> 4 | AO109: =ROUND(AM109+AN109,2)*A109 -> 504
...
