Workbook
Name _N: #REF!
Name _N: #REF!
Name A: #REF!
Name A: #REF!
Name Access_BMS: [2]BMS_Estimate!#REF!
Name Access_BMS: [2]BMS_Estimate!#REF!
Name Access_Control: [3]Elec_Est!#REF!
Name Access_Control: [4]Elec_Est!#REF!
Name Access_Supply: [2]BMS_Estimate!#REF!
Name Access_Supply: [2]BMS_Estimate!#REF!
Name Access_Wiring: [2]BMS_Estimate!#REF!
Name Access_Wiring: [2]BMS_Estimate!#REF!
Name ANS: #REF!
Name ANS: #REF!
Name AREAS: #REF!
Name AREAS: [4]ML_Sum!$X$1:$AD$16
Name AREAS: ML_Sum!$X$1:$AD$16
Name C_: #REF!
Name C_: #REF!
Name CCTV: [3]Elec_Est!#REF!
Name CCTV: [4]Elec_Est!#REF!
Name Data: [3]Elec_Est!#REF!
Name Data: [4]Elec_Est!#REF!
Name DATA_SYSTEM: #REF!
Name DD_Head_Foot: [5]!T_HeadFoot[Head-Foot]
Name FIRE_ALARM: #REF!
Name Fire_Alarm: [4]Elec_Est!#REF!
Name FO: [3]Elec_Est!#REF!
Name FO: [4]Elec_Est!#REF!
Name Guard: [3]Elec_Est!#REF!
Name Guard: [4]Elec_Est!#REF!
Name Intercom: [3]Elec_Est!#REF!
Name Intercom: [4]Elec_Est!#REF!
Name Intruder_Alarm: [3]Elec_Est!#REF!
Name Intruder_Alarm: [4]Elec_Est!#REF!
Name LIGHTNING_PROTECTION: #REF!
Name Persons: [6]Estimate!#REF!
Name Persons: [6]Estimate!#REF!
Name RAMON: #REF!
Name T: #REF!
Name T: #REF!
Name Traffic_Barriers: [2]BMS_Estimate!#REF!
Name Traffic_Barriers: [2]BMS_Estimate!#REF!
Name Z: #REF!
Name Z: #REF!

Sheet Notes
A1: NOTES:
A3: PRELIMINARIES BOQ:
A5: 1 | B5: BOQ Item 11 | C5: We have allowed for wall penetrations up to 300x300mm. For safety reason, larger openings are to be carried out by the building contractor.
A7: 2 | B7: BOQ Item 15 | C7: Submittal forms for materials are included. However, samples if required will be charged at cost.
A9: 3 | B9: BOQ Item 17 | C9: Provision of Local Council Permits will be charged at cost against receipts.
A12: ELECTRICAL BOQ:
A14: 1 | B14: BOQ Item 6.0d | C14: We have not quoted to supply the Battery Backup Kit for the light fittings supplied by others Type 'LT-02' and Type 'LT-15'. Also because, for other floors there are only BOQ items for installation and connect only.
A16: 2 | B16: BOQ Item 19.0c | C16: We have allowed for two floor outlet boxes, 1No 3 Compartment and 1No 2 Compartment. The floor outlet boxes are suitable for cleaning with a damp cloth.
A18: 3 | B18: BOQ Item 77 | C18: Since in the tender documents the bonding points to the metallic structures are not indicated, we have allowed for 20No bonding points. Each bond consists of 2m x 10sqmm LSZH Single core cable complete with cable termination.
A20: 4 | B20: Various BOQ Items | C20: Cable containment Tray and Trunking. The tray and trunking fittings will be fabricated on site because the building contour in general is not at a 90deg angle.
A23: EMERGENCY STANDBY GENERATOR BOQ BOQ:
A25: 1 | B25: Emergency Standby Generator BOQ Itemes 1 & 2 | C25: The Generator support structure or plinth is excluded.
C26: We have allowed for the diesel for the commissioning and for filling the day tank after the commissioning.

Sheet LSZH_Conduit
A1: KOUVIDIS - MEDISOL HF CONDUIT (For MFA Project)
E2: KOUVIDS HF Conduit System
E3: FCA | F3: 0.95
A4: Item | B4: Description | C4: Unit | D4: Qty | E4: Unit Price | G4: Total Price
A5: 1 | B5: 3m x 20mm HF Medium type Conduit (Ref. 1005020) | C5: Lenghts | D5: 3600 | E5: =0.595*2.9 -> 1.7255 | F5: =E5*$F$3 -> 1.639225 | G5: =D5*F5 -> 5901.21
A6: 2 | B6: 20mm HF Coupler (Ref. 4001020) | C6: No | D6: 1000 | E6: 0.084 | F6: =E6*$F$3 -> 0.0798 | G6: =D6*F6 -> 79.8
A7: 3 | B7: 20mm HF Bend (Ref. 4015020) | C7: No | D7: 500 | E7: 0.545 | F7: =E7*$F$3 -> 0.51775 | G7: =D7*F7 -> 258.875
A8: 4 | B8: 82x82x43mm HF Watertight Box (Ref. 3001020) | C8: No | D8: 300 | E8: 1.174 | F8: =E8*$F$3 -> 1.1153 | G8: =D8*F8 -> 334.59
A9: 5 | B9: 20mm HF Adaptor for Watertight Box (Ref. 4005020) | C9: No | D9: 500 | E9: 0.074 | F9: =E9*$F$3 -> 0.0703 | G9: =D9*F9 -> 35.15
A10: 6 | B10: 20mm HF Conduit Clip (Ref. 4003020) | C10: No | D10: 700 | E10: 0.096 | F10: =E10*$F$3 -> 0.0912 | G10: =D10*F10 -> 63.84
A11: 7 | B11: 3m x 25mm HF Medium type Conduit (Ref. 1005025) | C11: Lenghts | D11: 120 | E11: =0.889*2.9 -> 2.5781 | F11: =E11*$F$3 -> 2.449195 | G11: =D11*F11 -> 293.9034
A12: 8 | B12: 25mm HF Coupler (Ref. 4001025) | C12: No | D12: 50 | E12: 0.116 | F12: =E12*$F$3 -> 0.1102 | G12: =D12*F12 -> 5.51
A13: 9 | B13: 25mm HF Bend (Ref. 4015025) | C13: No | D13: 50 | E13: 0.983 | F13: =E13*$F$3 -> 0.93385 | G13: =D13*F13 -> 46.6925
A14: 10 | B14: 101x101x51mm HF Watertight Box (Ref. 3001025) | C14: No | D14: 50 | E14: 1.916 | F14: =E14*$F$3 -> 1.8202 | G14: =D14*F14 -> 91.01
A15: 11 | B15: 25mm HF Adaptor for Watertight Box (Ref. 4005025) | C15: No | D15: 150 | E15: 0.167 | F15: =E15*$F$3 -> 0.15865 | G15: =D15*F15 -> 23.7975
A16: 12 | B16: 25mm HF Conduit Clip (Ref. 4003025) | C16: No | D16: 200 | E16: 0.148 | F16: =E16*$F$3 -> 0.1406 | G16: =D16*F16 -> 28.12
A17: 13 | B17: 20mm Flexible Conduit (MEDIFLEX HF 33442) Part No. 2005020 | C17: m | D17: 300 | E17: 0.414 | F17: =E17*$F$3 -> 0.3933 | G17: =D17*F17 -> 117.99
A18: 14 | B18: 25mm Flexible Conduit (MEDIFLEX HF 33442) Part No. 2005025 | C18: m | D18: 100 | E18: 0.616 | F18: =E18*$F$3 -> 0.5852 | G18: =D18*F18 -> 58.52
G20: =SUM(G5:G19) -> 7339.0084
D24: cost/total | E24: m | F24: cost/m
C25: 20mm HF Medium type Conduit | D25: =SUM(G5:G10) -> 6673.465 | E25: =3600*2.9 -> 10440 | F25: =D25/E25 -> 0.63922079 | G25: =F25*$G$35 -> 0.67216064 | H25: /m
C26: 25mm HF Medium type Conduit | D26: =SUM(G11:G16) -> 489.0334 | E26: =120*2.9 -> 348 | F26: =D26/E26 -> 1.4052684 | G26: =F26*$G$35 -> 1.4776836 | H26: /m
C27: 20mm Flexible Conduit (MEDIFLEX HF 33442) Part No. 2005020 | D27: =G17 -> 117.99 | E27: 300 | F27: =D27/E27 -> 0.3933 | G27: =F27*$G$35 -> 0.41356725 | H27: /m
C28: 25mm Flexible Conduit (MEDIFLEX HF 33442) Part No. 2005025 | D28: =G18 -> 58.52 | E28: 100 | F28: =D28/E28 -> 0.5852 | G28: =F28*$G$35 -> 0.61535609 | H28: /m
D30: Stock Order | G30: For MFA
C31: KOUVIDIS PO 100033 | D31: 33183.74 | G31: 7339.01 | H31: Cost excluding the shipping
C32: Shipping and Delivery Cost | D32: 1710 | G32: =G31/D31*D32 -> 378.18845 | H32: Shipping cost
C33: Total | D33: =D31+D32 -> 34893.74 | G33: =G31+G32 -> 7717.1984 | H33: Total Cost
F35: Multiplying factor for the shipping | G35: =G33/G31 -> 1.0515313

Sheet Material_List
A1: QTY | B1: UNIT | C1: MATERIAL DESCRIPTION | D1: C/CODE
A2: 163.07692 | B2: No | C2: Anchor 8mm HKD M8X30 376959 | D2: 501
A3: =SUBTOTAL(9,A2:A2) -> 163.07692 | B3: No | C3: Anchor 8mm HKD M8X30 376959 | D3: 501
A4: 209.67033 | B4: No | C4: Channel 40x20 Endcap MQZ-E21 370598 | D4: 501
A5: =SUBTOTAL(9,A4:A4) -> 209.67033 | B5: No | C5: Channel 40x20 Endcap MQZ-E21 370598 | D5: 501
A6: 93.186813 | B6: No | C6: Channel 40x40 Endcap MQZ-E41 369685 | D6: 501
A7: =SUBTOTAL(9,A6:A6) -> 93.186813 | B7: No | C7: Channel 40x40 Endcap MQZ-E41 369685 | D7: 501
A8: 25.626374 | B8: m | C8: Channel DEEP MQ-41-F 3m 304099 | D8: 501
A9: =SUBTOTAL(9,A8:A8) -> 25.626374 | B9: m | C9: Channel DEEP MQ-41-F 3m 304099 | D9: 501
A10: 43.098901 | B10: m | C10: Channel SHALLOW MQ-21-F 3m 304096 | D10: 501
A11: =SUBTOTAL(9,A10:A10) -> 43.098901 | B11: m | C11: Channel SHALLOW MQ-21-F 3m 304096 | D11: 501
A12: 244.61538 | B12: No | C12: Galv. Nut 8mm M8-F 304764 | D12: 501
A13: =SUBTOTAL(9,A12:A12) -> 244.61538 | B13: No | C13: Galv. Nut 8mm M8-F 304764 | D13: 501
A14: 244.61538 | B14: No | C14: Hex.Set Screw M8x25 216448 | D14: 501
A15: =SUBTOTAL(9,A14:A14) -> 244.61538 | B15: No | C15: Hex.Set Screw M8x25 216448 | D15: 501
A16: 93.186813 | B16: No | C16: HLC Sleeve Anchor 10mm HLC 10x50/15 385820 | D16: 501
A17: =SUBTOTAL(9,A16:A16) -> 93.186813 | B17: No | C17: HLC Sleeve Anchor 10mm HLC 10x50/15 385820 | D17: 501
A18: 163.07692 | B18: No | C18: Pipe Ring Saddle MQA-M 8-F 304138 | D18: 501
A19: =SUBTOTAL(9,A18:A18) -> 163.07692 | B19: No | C19: Pipe Ring Saddle MQA-M 8-F 304138 | D19: 501
A20: 69.89011 | B20: No | C20: Push Button Hilti M10 MQN-F 304130 | D20: 501
A21: =SUBTOTAL(9,A20:A20) -> 69.89011 | B21: No | C21: Push Button Hilti M10 MQN-F 304130 | D21: 501
A22: 81.538462 | B22: m | C22: Threaded Rod Galv. 8mm 339793 | D22: 501
A23: =SUBTOTAL(9,A22:A22) -> 81.538462 | B23: m | C23: Threaded Rod Galv. 8mm 339793 | D23: 501
A24: 23.296703 | B24: No | C24: Three hole angle Hilti 90deg MQW-3-F 304172 | D24: 501
A25: =SUBTOTAL(9,A24:A24) -> 23.296703 | B25: No | C25: Three hole angle Hilti 90deg MQW-3-F 304172 | D25: 501
A26: 244.61538 | B26: No | C26: Tray Washers M8 304769 | D26: 501
A27: =SUBTOTAL(9,A26:A26) -> 244.61538 | B27: No | C27: Tray Washers M8 304769 | D27: 501
A28: 244.61538 | B28: No | C28: Wing Nut Hilti M8 MQM-M8-F 304132 | D28: 501
A29: =SUBTOTAL(9,A28:A28) -> 244.61538 | B29: No | C29: Wing Nut Hilti M8 MQM-M8-F 304132 | D29: 501
A30: 1 | B30: No | C30: 18M KAEDRA ENCLOSURE 1X18 IP65 | D30: 510
A31: 1 | B31: No | C31: 18M KAEDRA ENCLOSURE 1X18 IP65 | D31: 510
A32: =SUBTOTAL(9,A30:A31) -> 2 | B32: No | C32: 18M KAEDRA ENCLOSURE 1X18 IP65 | D32: 510
A33: 1 | B33: No | C33: 60kVAR Power Factor Correction Unit (PFCU) | D33: 510
A34: =SUBTOTAL(9,A33:A33) -> 1 | B34: No | C34: 60kVAR Power Factor Correction Unit (PFCU) | D34: 510
A35: 1 | B35: No | C35: GS DELAY ALARM | D35: 510
A36: 1 | B36: No | C36: GS DELAY ALARM | D36: 510
A37: =SUBTOTAL(9,A35:A36) -> 2 | B37: No | C37: GS DELAY ALARM | D37: 510
A38: 1 | B38: No | C38: MODULAR AUTO CHANGE OVER 63A 4P | D38: 510
A39: 1 | B39: No | C39: MODULAR AUTO CHANGE OVER 63A 4P | D39: 510
A40: =SUBTOTAL(9,A38:A39) -> 2 | B40: No | C40: MODULAR AUTO CHANGE OVER 63A 4P | D40: 510
A41: 1 | B41: No | C41: Panel MSP-ES: 250A 4P MCCB Panel 16 Way | D41: 510
A42: =SUBTOTAL(9,A41:A41) -> 1 | B42: No | C42: Panel MSP-ES: 250A 4P MCCB Panel 16 Way | D42: 510
A43: 1 | B43: No | C43: Panel MSP-ES: Metering Section c/w extension box | D43: 510
A44: =SUBTOTAL(9,A43:A43) -> 1 | B44: No | C44: Panel MSP-ES: Metering Section c/w extension box | D44: 510
A45: 1 | B45: No | C45: Panel MSP-NE: 250A 4P MCCB Panel 8 Way | D45: 510
A46: =SUBTOTAL(9,A45:A45) -> 1 | B46: No | C46: Panel MSP-NE: 250A 4P MCCB Panel 8 Way | D46: 510
A47: 1 | B47: No | C47: Panel MSP-NE: Metering Section c/w extension box | D47: 510
A48: =SUBTOTAL(9,A47:A47) -> 1 | B48: No | C48: Panel MSP-NE: Metering Section c/w extension box | D48: 510
A49: 1 | B49: No | C49: Panel SP-INC: 250A 4P MCCB complete with Shunt Trip and Adjustable Earth Fault Relay | D49: 510
A50: =SUBTOTAL(9,A49:A49) -> 1 | B50: No | C50: Panel SP-INC: 250A 4P MCCB complete with Shunt Trip and Adjustable Earth Fault Relay | D50: 510
A51: 1 | B51: No | C51: Supply only Modular Consumer Unit 'CU-G01' | D51: 510
A52: =SUBTOTAL(9,A51:A51) -> 1 | B52: No | C52: Supply only Modular Consumer Unit 'CU-G01' | D52: 510
A53: 1 | B53: No | C53: Supply only Modular Consumer Unit 'CU-G02' | D53: 510
A54: =SUBTOTAL(9,A53:A53) -> 1 | B54: No | C54: Supply only Modular Consumer Unit 'CU-G02' | D54: 510
A55: 1 | B55: No | C55: Supply only Modular Consumer Unit 'CU-G03' | D55: 510
A56: =SUBTOTAL(9,A55:A55) -> 1 | B56: No | C56: Supply only Modular Consumer Unit 'CU-G03' | D56: 510
A57: 1 | B57: No | C57: Supply only Modular Consumer Unit 'CU-G04' | D57: 510
A58: =SUBTOTAL(9,A57:A57) -> 1 | B58: No | C58: Supply only Modular Consumer Unit 'CU-G04' | D58: 510
A59: 1 | B59: No | C59: Supply only Modular Consumer Unit 'CU-G05' | D59: 510
A60: =SUBTOTAL(9,A59:A59) -> 1 | B60: No | C60: Supply only Modular Consumer Unit 'CU-G05' | D60: 510
A61: 1 | B61: No | C61: Supply only Modular Consumer Unit 'CU-G06' | D61: 510
A62: =SUBTOTAL(9,A61:A61) -> 1 | B62: No | C62: Supply only Modular Consumer Unit 'CU-G06' | D62: 510
A63: 1 | B63: No | C63: Supply only Modular Consumer Unit 'CU-G07' | D63: 510
A64: =SUBTOTAL(9,A63:A63) -> 1 | B64: No | C64: Supply only Modular Consumer Unit 'CU-G07' | D64: 510
A65: 1 | B65: No | C65: Supply only Modular Consumer Unit 'CU-G08' | D65: 510
A66: =SUBTOTAL(9,A65:A65) -> 1 | B66: No | C66: Supply only Modular Consumer Unit 'CU-G08' | D66: 510
A67: 1 | B67: No | C67: Supply only Modular Consumer Unit 'CU-G09' | D67: 510
A68: =SUBTOTAL(9,A67:A67) -> 1 | B68: No | C68: Supply only Modular Consumer Unit 'CU-G09' | D68: 510
A69: 1 | B69: No | C69: Supply only Modular Consumer Unit 'CU-G10' | D69: 510
A70: =SUBTOTAL(9,A69:A69) -> 1 | B70: No | C70: Supply only Modular Consumer Unit 'CU-G10' | D70: 510
A71: 1 | B71: No | C71: Supply only Modular Consumer Unit 'CU-G11' | D71: 510
A72: =SUBTOTAL(9,A71:A71) -> 1 | B72: No | C72: Supply only Modular Consumer Unit 'CU-G11' | D72: 510
A73: 1 | B73: No | C73: Supply only Modular Consumer Unit 'CU-G12' | D73: 510
A74: =SUBTOTAL(9,A73:A73) -> 1 | B74: No | C74: Supply only Modular Consumer Unit 'CU-G12' | D74: 510
A75: 1 | B75: No | C75: Supply only Modular Consumer Unit 'CU-G13' | D75: 510
A76: =SUBTOTAL(9,A75:A75) -> 1 | B76: No | C76: Supply only Modular Consumer Unit 'CU-G13' | D76: 510
A77: 1 | B77: No | C77: Supply only Modular Distribution Board 'DB-B1' 10 Way 40Amp TP&N | D77: 510
A78: =SUBTOTAL(9,A77:A77) -> 1 | B78: No | C78: Supply only Modular Distribution Board 'DB-B1' 10 Way 40Amp TP&N | D78: 510
A79: 1 | B79: No | C79: Supply only Modular Distribution Board 'DB-CA' 4 Way 40Amp TP&N | D79: 510
A80: =SUBTOTAL(9,A79:A79) -> 1 | B80: No | C80: Supply only Modular Distribution Board 'DB-CA' 4 Way 40Amp TP&N | D80: 510
A81: 1 | B81: No | C81: Supply only Modular Distribution Board 'DB-K' 10 Way 80Amp TP&N | D81: 510
A82: =SUBTOTAL(9,A81:A81) -> 1 | B82: No | C82: Supply only Modular Distribution Board 'DB-K' 10 Way 80Amp TP&N | D82: 510
A83: 1 | B83: No | C83: Supply only Modular Distribution Board 'DB-L0' 12 Way 40Amp TP&N | D83: 510
A84: =SUBTOTAL(9,A83:A83) -> 1 | B84: No | C84: Supply only Modular Distribution Board 'DB-L0' 12 Way 40Amp TP&N | D84: 510
A85: 1 | B85: No | C85: Supply only Modular Distribution Board 'DB-L1' 6 Way 40Amp TP&N | D85: 510
A86: =SUBTOTAL(9,A85:A85) -> 1 | B86: No | C86: Supply only Modular Distribution Board 'DB-L1' 6 Way 40Amp TP&N | D86: 510
A87: 1 | B87: No | C87: Supply only Modular Distribution Board 'DB-L2' 6 Way 40Amp TP&N | D87: 510
A88: =SUBTOTAL(9,A87:A87) -> 1 | B88: No | C88: Supply only Modular Distribution Board 'DB-L2' 6 Way 40Amp TP&N | D88: 510
A89: 1 | B89: No | C89: Supply only Modular Distribution Board 'DB-L3' 12 Way 40Amp TP&N | D89: 510
A90: =SUBTOTAL(9,A89:A89) -> 1 | B90: No | C90: Supply only Modular Distribution Board 'DB-L3' 12 Way 40Amp TP&N | D90: 510
A91: 1 | B91: No | C91: Supply only Modular Distribution Board 'DB-L4' 10 Way 40Amp TP&N | D91: 510
A92: =SUBTOTAL(9,A91:A91) -> 1 | B92: No | C92: Supply only Modular Distribution Board 'DB-L4' 10 Way 40Amp TP&N | D92: 510
A93: 1 | B93: No | C93: Supply only Modular Distribution Board 'DB-L5' 4 Way 40Amp TP&N | D93: 510
A94: =SUBTOTAL(9,A93:A93) -> 1 | B94: No | C94: Supply only Modular Distribution Board 'DB-L5' 4 Way 40Amp TP&N | D94: 510
A95: 1 | B95: No | C95: Supply only Modular Distribution Board 'DB-SF' 6 Way 32Amp TP&N | D95: 510
A96: =SUBTOTAL(9,A95:A95) -> 1 | B96: No | C96: Supply only Modular Distribution Board 'DB-SF' 6 Way 32Amp TP&N | D96: 510
A97: 4 | B97: No | C97: Supply only Surface Fire Rated Isolator 20A 4-Pole FEM2005 ESS SQ060933 | D97: 510
A98: =SUBTOTAL(9,A97:A97) -> 4 | B98: No | C98: Supply only Surface Fire Rated Isolator 20A 4-Pole FEM2005 ESS SQ060933 | D98: 510
A99: 1 | B99: No | C99: Supply only Surface Fire Rated Isolator 32A 4-Pole FEM3205.U ESS SQ060933 | D99: 510
A100: =SUBTOTAL(9,A99:A99) -> 1 | B100: No | C100: Supply only Surface Fire Rated Isolator 32A 4-Pole FEM3205.U ESS SQ060933 | D100: 510
...

Sheet HDG_Tray_Brackets
A1: TRAY BRACKETS CALCULATOR
B4: PROJECT: | C4: Britannia Hotel
B6: AREA: | C6: All Areas
C10: Wall (W) | F10: Ceiling (C) | I10: Floor (F) | L10: Riser (R)
B11: Brackets intervals @ (M) | C11: 1 | F11: 1 | I11: 1 | L11: 1
B13: Distance from tray side to wall (M) | C13: 0.2 | D13: =IF($C$13<0.31,0,1) -> 0
B15: Distance from ceiling (M) | F15: 0.5
B17: Distance from floor (M) | I17: 0.1
R21: LABOUR FACTOR
C22: Wall (W) | D22: Wall (W) | E22: Wall (W) | F22: Ceiling (C) | G22: Ceiling (C) | H22: Ceiling (C) | I22: Floor (F) | J22: Floor (F) | K22: Floor (F) | L22: Riser (R) | P22: Total (M) | R22: Unit | S22: Total
E23: Labour | H23: Labour | K23: Labour | N23: Labour
B24: 900mm Tray (Length M) | D24: =1+0.3+$C$13*2 -> 1.7 | E24: 0.6 | G24: =1*$F$15*2 -> 1 | H24: 0.75 | J24: =1+$I$17*2 -> 1.2 | K24: 0.75 | M24: 1 | N24: 0.3 | P24: =C24+F24+I24+L24 -> 0 | R24: 2.6 | S24: =R24*(C24+F24+I24+L24) -> 0
B26: 700mm Tray (Length M) | D26: =0.8+0.3+$C$13*2 -> 1.5 | E26: 0.6 | G26: =0.8*$F$15*2 -> 0.8 | H26: 0.75 | J26: =0.8+$I$17*2 -> 1 | K26: 0.75 | M26: 0.8 | N26: 0.3 | P26: =C26+F26+I26+L26 -> 0 | R26: 2.4 | S26: =R26*(C26+F26+I26+L26) -> 0
B28: 600mm Tray (Length M) | D28: =0.7+0.3+$C$13*2 -> 1.4 | E28: 0.5 | G28: =0.7*$F$15*2 -> 0.7 | H28: 0.65 | J28: =0.7+$I$17*2 -> 0.9 | K28: 0.65 | M28: 0.7 | N28: 0.3 | P28: =C28+F28+I28+L28 -> 0 | R28: 2.2 | S28: =R28*(C28+F28+I28+L28) -> 0
B30: 500mm Tray (Length M) | D30: =0.6+0.3+$C$13*2 -> 1.3 | E30: 0.5 | F30: 10 | G30: =0.6*$F$15*2 -> 0.6 | H30: 0.65 | J30: =0.6+$I$17*2 -> 0.8 | K30: 0.65 | L30: 10 | M30: 0.6 | N30: 0.3 | P30: =C30+F30+I30+L30 -> 20 | R30: 2 | S30: =R30*(C30+F30+I30+L30) -> 40
B32: 400mm Tray (Length M) | D32: =0.5+0.3+$C$13*2 -> 1.2 | E32: 0.4 | F32: 10 | G32: =0.5*$F$15*2 -> 0.5 | H32: 0.5 | J32: =0.5+$I$17*2 -> 0.7 | K32: 0.5 | L32: 20 | M32: 0.5 | N32: 0.25 | P32: =C32+F32+I32+L32 -> 30 | R32: 1.8 | S32: =R32*(C32+F32+I32+L32) -> 54
B34: 300mm Tray (Length M) | D34: =0.41+0.25+$C$13*2 -> 1.06 | E34: 0.4 | F34: 10 | G34: =0.4*$F$15*2 -> 0.4 | H34: 0.5 | J34: =0.4+$I$17*2 -> 0.6 | K34: 0.5 | M34: 0.4 | N34: 0.25 | P34: =C34+F34+I34+L34 -> 10 | R34: 1.6 | S34: =R34*(C34+F34+I34+L34) -> 16
B36: 200mm Tray (Length M) | D36: =0.3+0.25+$C$13*2 -> 0.95 | E36: 0.3 | F36: 30 | G36: =0.3*$F$15*2 -> 0.3 | H36: 0.35 | J36: =0.3+$I$17*2 -> 0.5 | K36: 0.35 | M36: 0.3 | N36: 0.25 | P36: =C36+F36+I36+L36 -> 30 | R36: 1.4 | S36: =R36*(C36+F36+I36+L36) -> 42
B38: 150mm Tray (Length M) | D38: =0.25+0.25+$C$13*2 -> 0.9 | E38: 0.25 | G38: =0.25*$F$15*2 -> 0.25 | H38: 0.35 | J38: =0.25+$I$17*2 -> 0.45 | K38: 0.35 | M38: 0.25 | N38: 0.2 | P38: =C38+F38+I38+L38 -> 0 | R38: 1.2 | S38: =R38*(C38+F38+I38+L38) -> 0
B40: 100mm Tray (Length M) | C40: 20 | D40: =0.2+0.25+$C$13*2 -> 0.85 | E40: 0.25 | F40: 10 | G40: =0.2*$F$15*2 -> 0.2 | H40: 0.3 | J40: =0.2+$I$17*2 -> 0.4 | K40: 0.35 | M40: 0.2 | N40: 0.2 | P40: =C40+F40+I40+L40 -> 30 | R40: 1 | S40: =R40*(C40+F40+I40+L40) -> 30
P42: =SUM(P24:P40) -> 120 | S42: =SUM(S24:S40) -> 182
B46: HILTI Material Description | C46: Part No. | F46: Total Qty | I46: Unit Cost € | L46: Total Cost €
I47: Per M / Each
B48: Channel DEEP MQ-41-F 3m | C48: 304099 | F48: =(((C24*D24)/C11)+((F24*G24)/F11)+((I24*J24)/I11)+((L24*M24)/L11))+(((C26*D26)/C11)+((F26*G26)/F11)+((I26*J26)/I11)+((L26*M26)/L11))+(((C28*D28)/C11)+((F28*G28)/F11)+((I28*J28)/I11)+((L28*M28)/L11))+(((C30*D30)/C11)+((F30*G30)/F11)+((I30*J30)/I11)+((L30*M30)/L11)+((L32*M32)/L11)+((L34*M34)/L11)+((L36*M36)/L11)+((L38*M38)/L11)+((L40*M40)/L11)+((I32*J32)/I11)+((I34*J34)/I11)+((I36*J36)/I11)+((I38*J38)/I11)+((I40*J40)/I11)) -> 22 | I48: 5.05 | L48: =I48*F48 -> 111.1
B49: Channel SHALLOW MQ-21-F 3m | C49: 304096 | F49: =((C32*D32)/C11)+((F32*G32)/F11)+((C34*D34)/C11)+((F34*G34)/F11)+((C36*D36)/C11)+((F36*G36)/F11)+((C38*D38)/C11)+((F38*G38)/F11)+((C40*D40)/C11)+((F40*G40)/F11) -> 37 | I49: 4.05 | L49: =I49*F49 -> 149.85
B50: Channel 40x20 Endcap MQZ-E21 | C50: 370598 | F50: =(((C32/C11)*3)+((F32/F11)*2)+((C34/C11)*3)+((F34/F11)*2)+((C36/C11)*3)+((F36/F11)*2)+((C38/C11)*3)+((F38/F11)*2)+((C40/C11)*3)+((F40/F11)*2)) -> 180 | I50: 0.0524 | L50: =I50*F50 -> 9.432
B51: Channel 40x40 Endcap MQZ-E41 | C51: 369685 | F51: =(((C24/C11)*3)+((F24/F11)*2)+((L24/L11)*2))+(((C26/C11)*3)+((F26/F11)*2)+((L26/L11)*2))+(((C28/C11)*3)+((F28/F11)*2)+((L28/L11)*2))+(((C30/C11)*3)+((F30/F11)*2)+((L30/L11)*2)+((L32/L11)*2)+((L34/L11)*2)+((L36/L11)*2)+((L38/L11)*2)+((L40/L11)*2)) -> 80 | I51: 0.0533 | L51: =I51*F51 -> 4.264
B52: Three hole angle Hilti 90deg MQW-3-F | C52: 304172 | F52: =((C24/C11)+((F24/F11)*4)+((I24/I11)*2))+((C26/C11)+((F26/F11)*4)+((I26/I11)*2))+(((C28/C11)*2)+((I28/I11)*2))+(((C30/C11)*2)+((I30/I11)*2))+(((C32/C11)*1)+((I32/I11)*2))+(((C34/C11)*1)+((I34/I11)*2))+(((C36/C11)*1)+((I36/I11)*2))+(((C38/C11)*1)+((I38/I11)*2))+(((C40/C11)*1)+((I40/I11)*2)) -> 20 | I52: 0.68 | L52: =I52*F52 -> 13.6
B53: Two Hole Angle Hilti 90deg MQW-2-F | C53: 304171 | F53: =(((I24/I11)*2))+(((I26/I11)*2))+(((I28/I11)*2))+(((I30/I11)*2))+(((I32/I11)*2))+(((I34/I11)*2))+(((I36/I11)*2))+(((I38/I11)*2))+(((I40/I11)*2)) -> 0 | I53: 0.53 | L53: =I53*F53 -> 0
B54: Long Angle Brace MQK-SL-F | C54: 304128 | F54: =ROUND(($D$13/$C$11)*(C30+C32+C34+C36+C38+C40)+((C24+C26+C28)/C11),0) -> 0 | I54: 7.03 | L54: =I54*F54 -> 0
B55: HLC Sleeve Anchor 10mm HLC 10x50/15 | C55: 385820 | F55: =(((C24/C11)*2)+((F24/F11)*2)+((I24/I11)*2)+((L24/L11)*2))+(((C26/C11)*2)+((F26/F11)*2)+((I26/I11)*2)+((L26/L11)*2))+((C28/C11)+(L28/L11)*2)+((C30/C11)+(L30/L11)*2)+((C32/C11)+(L32/L11)*2)+((C34/C11)+(L34/L11)*2)+((C36/C11)+(L36/L11)*2)+((C38/C11)+(L38/L11)*2)+((C40/C11)+(L40/L11)*2)+F54+((I24/I11)*2)+((I26/I11)*2)+((I28/I11)*2)+((I30/I11)*2)+((I32/I11)*2)+((I34/I11)*2)+((I36/I11)*2)+((I38/I11)*2)+((I40/I11)*2) -> 80 | I55: 0.1516 | L55: =I55*F55 -> 12.128
B56: Push Button Hilti M10 MQN-F | C56: 304130 | F56: =(((C24/C11)*3)+((F24/F11)*10)+((I24/I11)*6))+(((C26/C11)*3)+((F26/F11)*10)+((I26/I11)*6))+(((C28/C11)*3)+((I28/I11)*6))+(((C30/C11)*3)+((I30/I11)*6))+(((C32/C11)*3)+((I32/I11)*6))+(((C34/C11)*3)+((I34/I11)*6))+(((C36/C11)*3)+((I36/I11)*6))+(((C38/C11)*3)+((I38/I11)*6))+(((C40/C11)*3)+((I40/I11)*6)) -> 60 | I56: 0.91 | L56: =I56*F56 -> 54.6
B57: Pipe Ring Saddle MQA-M 8-F | C57: 304138 | F57: =((F28/F11)*2)+((F30/F11)*2)+((F32/F11)*2)+((F34/F11)*2)+((F36/F11)*2)+((F38/F11)*2)+((F40/F11)*2) -> 140 | I57: 0.8 | L57: =I57*F57 -> 112
B58: Anchor 8mm HKD M8X30 | C58: 376959 | F58: =F57 -> 140 | I58: 0.0943 | L58: =I58*F58 -> 13.202
B59: Wing Nut Hilti M8 MQM-M8-F | C59: 304132 | F59: =(((C24/C11)+(F24/F11)+(I24/I11)+(L24/L11))*2)+(((C26/C11)+(F26/F11)+(I26/I11)+(L26/L11))*2)+(((C28/C11)+(F28/F11)+(I28/I11)+(L28/L11))*2)+(((C30/C11)+(F30/F11)+(I30/I11)+(L30/L11))*2)+(((C32/C11)+(F32/F11)+(I32/I11)+(L32/L11))*2)+(((C34/C11)+(F34/F11)+(I34/I11)+(L34/L11))*2)+(((C36/C11)+(F36/F11)+(I36/I11)+(L36/L11))*2)+(((C38/C11)+(F38/F11)+(I38/I11)+(L38/L11))*1)+(((C40/C11)+(F40/F11)+(I40/I11)+(L40/L11))*1) -> 210 | I59: 0.65 | L59: =I59*F59 -> 136.5
B60: Hex.Set Screw M8x25 | C60: 216448 | F60: =F59 -> 210 | I60: 0.03614 | L60: =I60*F60 -> 7.5894
B61: Threaded Rod Galv. 8mm | C61: 339793 | F61: =(((F28/F11)*F15)*2)+(((F30/F11)*F15)*2)+(((F32/F11)*F15)*2)+(((F34/F11)*F15)*2)+(((F36/F11)*F15)*2)+(((F38/F11)*F15)*2)+(((F40/F11)*F15)*2) -> 70 | I61: 0.47799 | L61: =I61*F61 -> 33.4593
B62: Hex.Set Screw M10x25-F | C62: 304788 | F62: =F54 -> 0 | I62: 0.07683 | L62: =I62*F62 -> 0
B63: Galv. Nut 10mm M10-F | C63: 304765 | F63: =F62 -> 0 | I63: 0.03209 | L63: =I63*F63 -> 0
B64: Washer M10 | C64: 304770 | F64: =F63 -> 0 | I64: 0.02034 | L64: =I64*F64 -> 0
B65: Galv. Nut 8mm M8-F | C65: 304764 | F65: =F60 -> 210 | I65: 0.01667 | L65: =I65*F65 -> 3.5007
B66: Tray Washers M8 | C66: 304769 | F66: =F65 -> 210 | I66: 0.01103 | L66: =I66*F66 -> 2.3163
B68: Total labour pair hours | C68: =(((C24*E24)/C11)+((F24*H24)/F11)+((I24*K24)/I11)+((L24*N24)/L11))+(((C26*E26)/C11)+((F26*H26)/F11)+((I26*K26)/I11)+((L26*N26)/L11))+(((C28*E28)/C11)+((F28*H28)/F11)+((I28*K28)/I11)+((L28*N28)/L11))+(((C30*E30)/C11)+((F30*H30)/F11)+((I30*K30)/I11)+((L30*N30)/L11))+(((C32*E32)/C11)+((F32*H32)/F11)+((I32*K32)/I11)+((L32*N32)/L11))+(((C34*E34)/C11)+((F34*H34)/F11)+((I34*K34)/I11)+((L34*N34)/L11))+(((C36*E36)/C11)+((F36*H36)/F11)+((I36*K36)/I11)+((L36*N36)/L11))+(((C38*E38)/C11)+((F38*H38)/F11)+((I38*K38)/I11)+((L38*N38)/L11))+(((C40*E40)/C11)+((F40*H40)/F11)+((I40*K40)/I11)+((L40*N40)/L11)) -> 43 | L68: =SUM(L48:L67) -> 663.5417

Sheet Elec_Rates
B1: CLIENT: | C1: =ML_Sum!$C1 -> 1 | D1: =ML_Sum!$D1 -> Battery Street Limited | F1: =ML_Sum!$F1 -> 0 | I1: 1 | J1: =ML_Sum!$J1 -> 1 | K1: =ML_Sum!$K1 -> 1 | L1: =ML_Sum!$L1 -> 1 | M1: =ML_Sum!$M1 -> 1 | N1: =ML_Sum!$N1 -> 1 | O1: =ML_Sum!$O1 -> 1 | Q1: =ML_Sum!$Q1 -> € | R1: R/Lab Cont | S1: =ML_Sum!$S1 -> R | T1: =ML_Sum!$T1 -> 1.05 | U1: =ML_Sum!W1 -> BOQ | V1: INCL | W1: MULT | X1: AREA | Y1: BOQ | Z1: TDWG | AA1: ACT | AB1: DIFF
B2: PROJECT: | C2: =ML_Sum!$C2 -> 1 | D2: =ML_Sum!$D2 -> MEP Works British Hotel | F2: =ML_Sum!$F2 -> Electrical | I2: 2 | J2: =ML_Sum!$J2 -> 1 | K2: =ML_Sum!$K2 -> 1 | L2: =ML_Sum!$L2 -> 1 | M2: =ML_Sum!$M2 -> 1 | N2: =ML_Sum!$N2 -> 1 | O2: =ML_Sum!$O2 -> 1 | Q2: =ML_Sum!$Q2 -> 0 | R2: mu_A | S2: =ML_Sum!$S2 -> 1.22 | T2: =ML_Sum!$T2 -> 35.17626
B3: JOB DESC: | C3: =ML_Sum!$C3 -> 1 | D3: =ML_Sum!$D3 -> Electrical and ELV Systems | F3: =ML_Sum!$F3 -> Controls Section (DALI) | I3: 3 | J3: =ML_Sum!$J3 -> 1 | K3: =ML_Sum!$K3 -> 1 | L3: =ML_Sum!$L3 -> 1 | M3: =ML_Sum!$M3 -> 1 | N3: =ML_Sum!$N3 -> 1 | O3: =ML_Sum!$O3 -> 1 | Q3: =ML_Sum!$Q3 -> 0 | R3: mu_B | S3: =ML_Sum!$S3 -> 1.22 | T3: =ML_Sum!$T3 -> 86.64
B4: QUOTE No: | C4: =ML_Sum!$C4 -> 1 | D4: =ML_Sum!$D4 -> EL25-0662B | F4: =ML_Sum!$F4 -> Controls Section Engineer (DALI) | I4: 4 | J4: =ML_Sum!$J4 -> 1 | K4: =ML_Sum!$K4 -> 1 | L4: =ML_Sum!$L4 -> 1 | M4: =ML_Sum!$M4 -> 1 | N4: =ML_Sum!$N4 -> 1 | O4: =ML_Sum!$O4 -> 1 | Q4: =ML_Sum!$Q4 -> 0 | R4: mu_C | S4: =ML_Sum!$S4 -> 1.22 | T4: =ML_Sum!$T4 -> 51.41
B5: CLIENTs REF: | C5: =ML_Sum!$C5 -> 1 | D5: =ML_Sum!$D5 -> MEP REVISED | F5: =ML_Sum!$F5 -> ELV Sub-Contractor - APCO | I5: 5 | J5: =ML_Sum!$J5 -> 1 | K5: =ML_Sum!$K5 -> 1 | L5: =ML_Sum!$L5 -> 1 | M5: =ML_Sum!$M5 -> 1 | N5: =ML_Sum!$N5 -> 1 | O5: =ML_Sum!$O5 -> 1 | Q5: =ML_Sum!$Q5 -> 0 | R5: mu_D | S5: =ML_Sum!$S5 -> 1.075 | T5: =ML_Sum!$T5 -> 30.995475
B6: VAT/DUTIES: | C6: =ML_Sum!$C6 -> 1 | D6: =ML_Sum!$D6 -> VAT EXCL. | F6: =ML_Sum!$F6 -> ELV Sub-Contractor - DATA | I6: 6 | J6: =ML_Sum!$J6 -> 1 | K6: =ML_Sum!$K6 -> 1 | L6: =ML_Sum!$L6 -> 1 | M6: =ML_Sum!$M6 -> 1 | N6: =ML_Sum!$N6 -> 1 | O6: =ML_Sum!$O6 -> 1 | Q6: =ML_Sum!$Q6 -> 0 | R6: mu_E | S6: =ML_Sum!$S6 -> 1.1 | T6: =ML_Sum!$T6 -> 31.7163
B7: SAVED ON: | C7: =ML_Sum!$C7 -> 1 | D7: 39364 | F7: =ML_Sum!$F7 -> 0 | I7: 7 | J7: =ML_Sum!$J7 -> 1 | K7: =ML_Sum!$K7 -> 1 | L7: =ML_Sum!$L7 -> 1 | M7: =ML_Sum!$M7 -> 1 | N7: =ML_Sum!$N7 -> 1 | O7: =ML_Sum!$O7 -> 0 | Q7: =ML_Sum!$Q7 -> 0 | R7: mu_F | S7: =ML_Sum!$S7 -> 0 | T7: =ML_Sum!$T7 -> 0
B8: ESTIMATOR: | C8: =ML_Sum!$C8 -> 1 | D8: =ML_Sum!$D8 -> R.Farrugia | F8: =ML_Sum!$F8 -> 0 | I8: 8 | J8: =ML_Sum!$J8 -> 1 | K8: =ML_Sum!$K8 -> 1 | L8: =ML_Sum!$L8 -> 1 | M8: =ML_Sum!$M8 -> 1 | N8: =ML_Sum!$N8 -> 1 | O8: =ML_Sum!$O8 -> 0 | Q8: =ML_Sum!$Q8 -> 0 | R8: mu_G | S8: =ML_Sum!$S8 -> 0 | T8: =ML_Sum!$T8 -> 0
B9: LABOUR RATE: | C9: =ML_Sum!$C9 -> 1 | D9: =ML_Sum!$D9 -> 28.833 | F9: =ML_Sum!$F9 -> 0 | I9: 9 | J9: =ML_Sum!$J9 -> 1 | K9: =ML_Sum!$K9 -> 1 | L9: =ML_Sum!$L9 -> 1 | M9: =ML_Sum!$M9 -> 1 | N9: =ML_Sum!$N9 -> 1 | O9: =ML_Sum!$O9 -> 0 | Q9: =ML_Sum!$Q9 -> 0 | R9: mu_H | S9: =ML_Sum!$S9 -> 0 | T9: =ML_Sum!$T9 -> 0
C10: =ML_Sum!$C10 -> 1 | F10: =ML_Sum!$F10 -> Enemalta 3Ph Application | I10: 10 | J10: =ML_Sum!$J10 -> 1 | K10: =ML_Sum!$K10 -> 1 | L10: =ML_Sum!$L10 -> 1 | M10: =ML_Sum!$M10 -> 1 | N10: =ML_Sum!$N10 -> 1 | O10: =ML_Sum!$O10 -> 1 | Q10: =ML_Sum!$Q10 -> 0 | R10: mu_I | S10: =ML_Sum!$S10 -> 1.1 | T10: =ML_Sum!$T10 -> 31.7163
C11: =ML_Sum!$C11 -> 1 | F11: =ML_Sum!$F11 -> 0 | Q11: =ML_Sum!$Q11 -> 0 | R11: mu_J | S11: =ML_Sum!$S11 -> 0 | T11: =ML_Sum!$T11 -> 0
C12: =ML_Sum!$C12 -> 1 | F12: =ML_Sum!$F12 -> 0 | Q12: =ML_Sum!$Q12 -> 0 | R12: MIXED | S12: =ML_Sum!$S12 -> MAT MU | T12: =ML_Sum!$T12 -> LAB RATE
G13: I_CODE | H13: C_CODE | I13: MAKE | J13: PART_NO | K13: MARKUP | L13: TYPE | M13: LIST_P | N13: P_FACT | O13: FIX | P13: DATE | Q13: %Dsct in BOQ | R13: MU TYPE | S13: MAT MU | T13: LAB RATE
Q14: Multip
A15: 70 | B15: =Elec_Est!B5539 -> 70 | D15: 001# 5 core x 70 mm2 XLPE/SWA/LSZH/Cu Cable | K15: RATE | L15: RATE | Q15: =B15/A15 -> 1 | R15: =IF($B15=0,0,IF($S$1="R",ROUND(R23/$B15,2),R23/$B15)) -> 43.37 | T15: =IF($B15=0,0,IF($S$1="R",ROUND(T23/$B15,2),T23/$B15)) -> 0.26
D16: Based on:
A17: =$Q$15 *(70) -> 70 | B17: m | D17: 5 core x 70 mm2 XLPE/SWA/LSZH/Cu Cable | F17: AJQ41321 | G17: CAMC_028 | H17: 616 | I17: CRO | J17: 70mm2 | O17: 2 | P17: 40767 | Q17: 41.55 | R17: =$A17*Q17 -> 2908.5 | S17: 0.18 | T17: =$A17*S17*$T$1 -> 13.23
A18: =$Q$15 *(4) -> 4 | B18: No | D18: Gland Indoor 50S BWL 4*95mm2 | G18: CAAC_047 | H18: 620 | I18: CMP | O18: 2 | P18: 35431 | Q18: 25.46 | R18: =$A18*Q18 -> 101.84 | S18: 0.7 | T18: =$A18*S18*$T$1 -> 2.94
A19: =$Q$15 *(4*5) -> 20 | B19: No | D19: Cable Lug 70 mm2 | G19: CAAC_013 | H19: 620 | I19: CTT | O19: 2 | P19: 34669 | Q19: 1 | R19: =$A19*Q19 -> 20 | S19: 0.1 | T19: =$A19*S19*$T$1 -> 2.1
A20: =$Q$15 *(4) -> 4 | B20: No | D20: Cable Marker Wrap Around Type | G20: CAAC_025 | H20: 620 | I20: (__) | O20: 2 | Q20: 0.5 | R20: =$A20*Q20 -> 2 | T20: =$A20*S20*$T$1 -> 0
A21: =$Q$15 *(70) -> 70 | B21: No | D21: Cable Tie 225mm | G21: CONS_009 | H21: 875 | I21: (__) | K21: 01-003 | O21: 1 | P21: 34669 | Q21: 0.05 | R21: =$A21*Q21 -> 3.5 | T21: =$A21*S21*$T$1 -> 0
C22: << ==== TOTAL UNITS | R22: =$A22*Q22 -> 0 | T22: =$A22*S22*$T$1 -> 0
A23: d> | B23: =(R23+T23)-SUM(R16:R22,T16:T22) -> 0 | D23: Sell_A | E23: =IF($B15=0,0,ROUND(ROUND(($R23*$S$2+($T23*$T$2))/$B15, 2)*$C$2,2)) -> 62.09 | F23: =ROUND($B15*$E23,2) -> 4346.3 | K23: ITEM | L23: ITEM | R23: =SUM(R16:R22) -> 3035.84 | T23: =SUM(T16:T22) -> 18.27
Q24: Multip
A25: 10 | B25: =Elec_Est!B5540 -> 10 | D25: 002# 5 core x 70 mm2 FG16(O)M16 Cable | K25: RATE | L25: RATE | Q25: =B25/A25 -> 1 | R25: =IF($B25=0,0,IF($S$1="R",ROUND(R33/$B25,2),R33/$B25)) -> 46.17 | T25: =IF($B25=0,0,IF($S$1="R",ROUND(T33/$B25,2),T33/$B25)) -> 0.48
D26: Based on:
A27: =$Q$25 *(10) -> 10 | B27: m | D27: 5 core x 70 mm2 FG16(O)M16 Cable | G27: CAMC_029 | H27: 616 | I27: CRO | J27: 95mm2 | O27: 2 | P27: 40767 | Q27: 44.2 | R27: =$A27*Q27 -> 442 | S27: 0.18 | T27: =$A27*S27*$T$1 -> 1.89
A28: =$Q$25 *(2) -> 2 | B28: No | D28: M63 PVC Gland | G28: CAAC_027 | H28: 620 | I28: (__) | O28: 2 | P28: 35431 | Q28: 4.51 | R28: =$A28*Q28 -> 9.02 | S28: 0.9 | T28: =$A28*S28*$T$1 -> 1.89
A29: =$Q$25 *(10) -> 10 | B29: No | D29: Cable Lug 70 mm2 | G29: CAAC_013 | H29: 620 | I29: CTT | O29: 2 | P29: 34669 | Q29: 1 | R29: =$A29*Q29 -> 10 | S29: 0.1 | T29: =$A29*S29*$T$1 -> 1.05
A30: =$Q$25 *(2) -> 2 | B30: No | D30: Cable Marker Wrap Around Type | G30: CAAC_025 | H30: 620 | I30: (__) | O30: 2 | Q30: 0.1 | R30: =$A30*Q30 -> 0.2 | T30: =$A30*S30*$T$1 -> 0
A31: =$Q$25 *(10) -> 10 | B31: No | D31: Cable Tie 225mm | G31: CONS_009 | H31: 875 | I31: (__) | K31: 01-003 | O31: 1 | P31: 34669 | Q31: 0.05 | R31: =$A31*Q31 -> 0.5 | T31: =$A31*S31*$T$1 -> 0
C32: << ==== TOTAL UNITS | R32: =$A32*Q32 -> 0 | T32: =$A32*S32*$T$1 -> 0
A33: d> | B33: =(R32+T32) -> 0 | D33: Sell_A | E33: =IF($B25=0,0,ROUND(ROUND(($R33*$S$2+($T33*$T$2))/$B25, 2)*$C$2,2)) -> 73.32 | F33: =ROUND($B25*$E33,2) -> 733.2 | K33: ITEM | L33: ITEM | R33: =SUM(R26:R32) -> 461.72 | T33: =SUM(T26:T32) -> 4.83
Q34: Multip
A35: 170 | B35: =Elec_Est!B5541 -> 170 | D35: 003# 5 core x 50 mm2 FG16(O)M16 Cable | K35: RATE | L35: RATE | Q35: =B35/A35 -> 1 | R35: =IF($B35=0,0,IF($S$1="R",ROUND(R43/$B35,2),R43/$B35)) -> 31.01 | T35: =IF($B35=0,0,IF($S$1="R",ROUND(T43/$B35,2),T43/$B35)) -> 0.29
D36: Based on:
A37: =$Q$35 *(170) -> 170 | B37: m | D37: 5 core x 50 mm2 FG16(O)M16 Cable | G37: CAMC_029 | H37: 616 | I37: CRO | J37: 95mm2 | O37: 2 | P37: 40767 | Q37: 30.41 | R37: =$A37*Q37 -> 5169.7 | S37: 0.18 | T37: =$A37*S37*$T$1 -> 32.13
A38: =$Q$35 *(12) -> 12 | B38: No | D38: M63 PVC Gland | G38: CAAC_027 | H38: 620 | I38: (__) | O38: 2 | P38: 35431 | Q38: 4.51 | R38: =$A38*Q38 -> 54.12 | S38: 0.9 | T38: =$A38*S38*$T$1 -> 11.34
A39: =$Q$35 *(12*5) -> 60 | B39: No | D39: Cable Lug 50 mm2 | G39: CAAC_012 | H39: 620 | I39: CTT | O39: 2 | P39: 34669 | Q39: 0.65 | R39: =$A39*Q39 -> 39 | S39: 0.1 | T39: =$A39*S39*$T$1 -> 6.3
A40: =$Q$35 *(12) -> 12 | B40: No | D40: Cable Marker Wrap Around Type | G40: CAAC_025 | H40: 620 | I40: (__) | O40: 2 | Q40: 0.1 | R40: =$A40*Q40 -> 1.2 | T40: =$A40*S40*$T$1 -> 0
A41: =$Q$35 *(170) -> 170 | B41: No | D41: Cable Tie 225mm | G41: CONS_009 | H41: 875 | I41: (__) | K41: 01-003 | O41: 1 | P41: 34669 | Q41: 0.05 | R41: =$A41*Q41 -> 8.5 | T41: =$A41*S41*$T$1 -> 0
C42: << ==== TOTAL UNITS | R42: =$A42*Q42 -> 0 | T42: =$A42*S42*$T$1 -> 0
A43: d> | B43: =(R42+T42) -> 0 | D43: Sell_A | E43: =IF($B35=0,0,ROUND(ROUND(($R43*$S$2+($T43*$T$2))/$B35, 2)*$C$2,2)) -> 48.14 | F43: =ROUND($B35*$E43,2) -> 8183.8 | K43: ITEM | L43: ITEM | R43: =SUM(R36:R42) -> 5272.52 | T43: =SUM(T36:T42) -> 49.77
Q44: Multip
A45: 76 | B45: =Elec_Est!B5542 -> 76 | D45: 004# 5 core x 25 mm2 FG16(O)M16 Cable | K45: RATE | L45: RATE | Q45: =B45/A45 -> 1 | R45: =IF($B45=0,0,IF($S$1="R",ROUND(R53/$B45,2),R53/$B45)) -> 15.46 | T45: =IF($B45=0,0,IF($S$1="R",ROUND(T53/$B45,2),T53/$B45)) -> 0.17
D46: Based on:
A47: =$Q$45 *(76) -> 76 | B47: m | D47: 5 core x 25 mm2 FG16(O)M16 Cable | G47: CAMC_097 | H47: 616 | I47: (__) | J47: 25mm2 | O47: 2 | P47: 40767 | Q47: 15.31 | R47: =$A47*Q47 -> 1163.56 | S47: 0.12 | T47: =$A47*S47*$T$1 -> 9.576
A48: =$Q$45 *(4) -> 4 | B48: No | D48: M40 PVC Gland | G48: CAAC_027 | H48: 620 | I48: (__) | O48: 2 | P48: 35431 | Q48: 0.98 | R48: =$A48*Q48 -> 3.92 | S48: 0.5 | T48: =$A48*S48*$T$1 -> 2.1
A49: =$Q$45 *(20) -> 20 | B49: No | D49: Cable Lug 25 mm2 | G49: CAAC_010 | H49: 620 | I49: CTT | O49: 2 | P49: 34669 | Q49: 0.16 | R49: =$A49*Q49 -> 3.2 | S49: 0.07 | T49: =$A49*S49*$T$1 -> 1.47
A50: =$Q$45 *(4) -> 4 | B50: No | D50: Cable Marker Wrap Around Type | G50: CAAC_025 | H50: 620 | I50: (__) | O50: 2 | Q50: 0.1 | R50: =$A50*Q50 -> 0.4 | T50: =$A50*S50*$T$1 -> 0
A51: =$Q$45 *(76) -> 76 | B51: No | D51: Cable Tie 225mm | G51: CONS_009 | H51: 875 | I51: (__) | K51: 01-003 | O51: 1 | P51: 34669 | Q51: 0.05 | R51: =$A51*Q51 -> 3.8 | T51: =$A51*S51*$T$1 -> 0
C52: << ==== TOTAL UNITS | R52: =$A52*Q52 -> 0 | T52: =$A52*S52*$T$1 -> 0
A53: d> | B53: =(R52+T52) -> 0 | D53: Sell_A | E53: =IF($B45=0,0,ROUND(ROUND(($R53*$S$2+($T53*$T$2))/$B45, 2)*$C$2,2)) -> 24.94 | F53: =ROUND($B45*$E53,2) -> 1895.44 | K53: ITEM | L53: ITEM | R53: =SUM(R46:R52) -> 1174.88 | T53: =SUM(T46:T52) -> 13.146
Q54: Multip
A55: 267 | B55: =Elec_Est!B5543 -> 267 | D55: 005# 5 core x 10 mm2 FG16(O)M16 Cable | K55: RATE | L55: RATE | Q55: =B55/A55 -> 1 | R55: =IF($B55=0,0,IF($S$1="R",ROUND(R63/$B55,2),R63/$B55)) -> 6.71 | T55: =IF($B55=0,0,IF($S$1="R",ROUND(T63/$B55,2),T63/$B55)) -> 0.14
D56: Based on:
A57: =$Q$55 *(267) -> 267 | B57: m | D57: 5 core x 10 mm2 FG16(O)M16 Cable | G57: CAMC_082 | H57: 616 | I57: (__) | K57: 07-006 | O57: 2 | P57: 38299 | Q57: 6.55 | R57: =$A57*Q57 -> 1748.85 | S57: 0.09 | T57: =$A57*S57*$T$1 -> 25.2315
A58: =$Q$55 *(9*2) -> 18 | B58: No | D58: M32 PVC Gland | G58: CAAC_027 | H58: 620 | I58: (__) | O58: 2 | P58: 35431 | Q58: 0.87 | R58: =$A58*Q58 -> 15.66 | S58: 0.4 | T58: =$A58*S58*$T$1 -> 7.56
A59: =$Q$55 *(18*5) -> 90 | B59: No | D59: Cable Lug 10 mm2 | G59: CAAC_008 | H59: 620 | I59: CTT | O59: 2 | P59: 34669 | Q59: 0.14 | R59: =$A59*Q59 -> 12.6 | S59: 0.06 | T59: =$A59*S59*$T$1 -> 5.67
A60: =$Q$55 *(18) -> 18 | B60: No | D60: Cable Marker Wrap Around Type | G60: CAAC_025 | H60: 620 | I60: (__) | O60: 2 | Q60: 0.1 | R60: =$A60*Q60 -> 1.8 | T60: =$A60*S60*$T$1 -> 0
A61: =$Q$55 *(267) -> 267 | B61: No | D61: Cable Tie 225mm | G61: CONS_009 | H61: 875 | I61: (__) | K61: 01-003 | O61: 1 | P61: 34669 | Q61: 0.05 | R61: =$A61*Q61 -> 13.35 | T61: =$A61*S61*$T$1 -> 0
C62: << ==== TOTAL UNITS | R62: =$A62*Q62 -> 0 | T62: =$A62*S62*$T$1 -> 0
A63: d> | B63: =(R62+T62) -> 0 | D63: Sell_A | E63: =IF($B55=0,0,ROUND(ROUND(($R63*$S$2+($T63*$T$2))/$B55, 2)*$C$2,2)) -> 13.26 | F63: =ROUND($B55*$E63,2) -> 3540.42 | K63: ITEM | L63: ITEM | R63: =SUM(R56:R62) -> 1792.26 | T63: =SUM(T56:T62) -> 38.4615
Q64: Multip
A65: 52 | B65: =Elec_Est!B5544 -> 52 | D65: 006# 5 core x 6.0 mm2 FG16(O)M16 Cable | K65: RATE | L65: RATE | Q65: =B65/A65 -> 1 | R65: =IF($B65=0,0,IF($S$1="R",ROUND(R73/$B65,2),R73/$B65)) -> 4.17 | T65: =IF($B65=0,0,IF($S$1="R",ROUND(T73/$B65,2),T73/$B65)) -> 0.15
D66: Based on:
A67: =$Q$65 *(52) -> 52 | B67: m | D67: 5 core x 6.0 mm2 FG16(O)M16 Cable | G67: CAMC_082 | H67: 616 | I67: (__) | K67: 07-006 | O67: 2 | P67: 38299 | Q67: 3.97 | R67: =$A67*Q67 -> 206.44 | S67: 0.08 | T67: =$A67*S67*$T$1 -> 4.368
A68: =$Q$65 *(6) -> 6 | B68: No | D68: M32 PVC Gland | G68: CAAC_027 | H68: 620 | I68: (__) | O68: 2 | P68: 35431 | Q68: 0.87 | R68: =$A68*Q68 -> 5.22 | S68: 0.4 | T68: =$A68*S68*$T$1 -> 2.52
A69: =$Q$65 *(6*5) -> 30 | B69: No | D69: Cable Lug 6.0 mm2 | G69: CAAC_007 | H69: 620 | I69: CTT | O69: 2 | P69: 34669 | Q69: 0.07 | R69: =$A69*Q69 -> 2.1 | S69: 0.03 | T69: =$A69*S69*$T$1 -> 0.945
A70: =$Q$65 *(6) -> 6 | B70: No | D70: Cable Marker Wrap Around Type | G70: CAAC_025 | H70: 620 | I70: (__) | O70: 2 | Q70: 0.1 | R70: =$A70*Q70 -> 0.6 | T70: =$A70*S70*$T$1 -> 0
A71: =$Q$65 *(52) -> 52 | B71: No | D71: Cable Tie 225mm | G71: CONS_009 | H71: 875 | I71: (__) | K71: 01-003 | O71: 1 | P71: 34669 | Q71: 0.05 | R71: =$A71*Q71 -> 2.6 | T71: =$A71*S71*$T$1 -> 0
C72: << ==== TOTAL UNITS | R72: =$A72*Q72 -> 0 | T72: =$A72*S72*$T$1 -> 0
A73: d> | B73: =(R72+T72) -> 0 | D73: Sell_A | E73: =IF($B65=0,0,ROUND(ROUND(($R73*$S$2+($T73*$T$2))/$B65, 2)*$C$2,2)) -> 10.39 | F73: =ROUND($B65*$E73,2) -> 540.28 | K73: ITEM | L73: ITEM | R73: =SUM(R66:R72) -> 216.96 | T73: =SUM(T66:T72) -> 7.833
Q74: Multip
A75: 30 | B75: =Elec_Est!B5545 -> 30 | D75: 007# 5 core x 2.5 mm2 FG16(O)M16 Cable | K75: RATE | L75: RATE | Q75: =B75/A75 -> 1 | R75: =IF($B75=0,0,IF($S$1="R",ROUND(R83/$B75,2),R83/$B75)) -> 2.08 | T75: =IF($B75=0,0,IF($S$1="R",ROUND(T83/$B75,2),T83/$B75)) -> 0.11
D76: Based on:
A77: =$Q$75 *(30) -> 30 | B77: m | D77: 5 core x 2.5 mm2 FG16(O)M16 Cable | G77: CAMC_082 | H77: 616 | I77: (__) | K77: 07-006 | O77: 2 | P77: 38299 | Q77: 1.93 | R77: =$A77*Q77 -> 57.9 | S77: 0.06 | T77: =$A77*S77*$T$1 -> 1.89
A78: =$Q$75 *(4) -> 4 | B78: No | D78: M20 PVC Gland | G78: CAAC_027 | H78: 620 | I78: (__) | O78: 2 | P78: 35431 | Q78: 0.41 | R78: =$A78*Q78 -> 1.64 | S78: 0.2 | T78: =$A78*S78*$T$1 -> 0.84
A79: =$Q$75 *(20) -> 20 | B79: No | D79: Cable Lug 2.5 mm2 | G79: CAAC_005 | H79: 620 | I79: CTT | O79: 2 | P79: 34669 | Q79: 0.05 | R79: =$A79*Q79 -> 1 | S79: 0.02 | T79: =$A79*S79*$T$1 -> 0.42
A80: =$Q$75 *(4) -> 4 | B80: No | D80: Cable Marker Wrap Around Type | G80: CAAC_025 | H80: 620 | I80: (__) | O80: 2 | Q80: 0.1 | R80: =$A80*Q80 -> 0.4 | T80: =$A80*S80*$T$1 -> 0
A81: =$Q$75 *(30) -> 30 | B81: No | D81: Cable Tie 225mm | G81: CONS_009 | H81: 875 | I81: (__) | K81: 01-003 | O81: 1 | P81: 34669 | Q81: 0.05 | R81: =$A81*Q81 -> 1.5 | T81: =$A81*S81*$T$1 -> 0
C82: << ==== TOTAL UNITS | R82: =$A82*Q82 -> 0 | T82: =$A82*S82*$T$1 -> 0
A83: d> | B83: =(R82+T82) -> 0 | D83: Sell_A | E83: =IF($B75=0,0,ROUND(ROUND(($R83*$S$2+($T83*$T$2))/$B75, 2)*$C$2,2)) -> 6.23 | F83: =ROUND($B75*$E83,2) -> 186.9 | K83: ITEM | L83: ITEM | R83: =SUM(R76:R82) -> 62.44 | T83: =SUM(T76:T82) -> 3.15
Q84: Multip
A85: 5 | B85: =Elec_Est!B5546 -> 5 | D85: 008# 3 core x 6.0 mm2 FG16(O)M16 Cable | K85: RATE | L85: RATE | Q85: =B85/A85 -> 1 | R85: =IF($B85=0,0,IF($S$1="R",ROUND(R93/$B85,2),R93/$B85)) -> 2.94 | T85: =IF($B85=0,0,IF($S$1="R",ROUND(T93/$B85,2),T93/$B85)) -> 0.24
D86: Based on:
A87: =$Q$85 *(5) -> 5 | B87: m | D87: 3 core x 6.0 mm2 FG16(O)M16 Cable | G87: CAMC_082 | H87: 616 | I87: (__) | K87: 07-006 | O87: 2 | P87: 38299 | Q87: 2.53 | R87: =$A87*Q87 -> 12.65 | S87: 0.07 | T87: =$A87*S87*$T$1 -> 0.3675
A88: =$Q$85 *(2) -> 2 | B88: No | D88: M25 PVC Gland | G88: CAAC_027 | H88: 620 | I88: (__) | O88: 2 | P88: 35431 | Q88: 0.6 | R88: =$A88*Q88 -> 1.2 | S88: 0.3 | T88: =$A88*S88*$T$1 -> 0.63
A89: =$Q$85 *(6) -> 6 | B89: No | D89: Cable Lug 6.0 mm2 | G89: CAAC_007 | H89: 620 | I89: CTT | O89: 2 | P89: 34669 | Q89: 0.07 | R89: =$A89*Q89 -> 0.42 | S89: 0.03 | T89: =$A89*S89*$T$1 -> 0.189
A90: =$Q$85 *(2) -> 2 | B90: No | D90: Cable Marker Wrap Around Type | G90: CAAC_025 | H90: 620 | I90: (__) | O90: 2 | Q90: 0.1 | R90: =$A90*Q90 -> 0.2 | T90: =$A90*S90*$T$1 -> 0
A91: =$Q$85 *(5) -> 5 | B91: No | D91: Cable Tie 225mm | G91: CONS_009 | H91: 875 | I91: (__) | K91: 01-003 | O91: 1 | P91: 34669 | Q91: 0.05 | R91: =$A91*Q91 -> 0.25 | T91: =$A91*S91*$T$1 -> 0
C92: << ==== TOTAL UNITS | R92: =$A92*Q92 -> 0 | T92: =$A92*S92*$T$1 -> 0
A93: d> | B93: =(R92+T92) -> 0 | D93: Sell_A | E93: =IF($B85=0,0,ROUND(ROUND(($R93*$S$2+($T93*$T$2))/$B85, 2)*$C$2,2)) -> 11.94 | F93: =ROUND($B85*$E93,2) -> 59.7 | K93: ITEM | L93: ITEM | R93: =SUM(R86:R92) -> 14.72 | T93: =SUM(T86:T92) -> 1.1865
Q94: Multip
A95: 170 | B95: =Elec_Est!B5547 -> 170 | D95: 009# 3 core x 4.0 mm2 FG16(O)M16 Cable | K95: RATE | L95: RATE | Q95: =B95/A95 -> 1 | R95: =IF($B95=0,0,IF($S$1="R",ROUND(R103/$B95,2),R103/$B95)) -> 2.07 | T95: =IF($B95=0,0,IF($S$1="R",ROUND(T103/$B95,2),T103/$B95)) -> 0.12
D96: Based on:
A97: =$Q$95 *(170) -> 170 | B97: m | D97: 3 core x 4.0 mm2 FG16(O)M16 Cable | G97: CAMC_082 | H97: 616 | I97: (__) | K97: 07-006 | O97: 2 | P97: 38299 | Q97: 1.9 | R97: =$A97*Q97 -> 323 | S97: 0.06 | T97: =$A97*S97*$T$1 -> 10.71
A98: =$Q$95 *(24) -> 24 | B98: No | D98: M25 PVC Gland | G98: CAAC_027 | H98: 620 | I98: (__) | O98: 2 | P98: 35431 | Q98: 0.6 | R98: =$A98*Q98 -> 14.4 | S98: 0.3 | T98: =$A98*S98*$T$1 -> 7.56
A99: =$Q$95 *(24*3) -> 72 | B99: No | D99: Cable Lug 4.0 mm2 | G99: CAAC_007 | H99: 620 | I99: CTT | O99: 2 | P99: 34669 | Q99: 0.06 | R99: =$A99*Q99 -> 4.32 | S99: 0.03 | T99: =$A99*S99*$T$1 -> 2.268
A100: =$Q$95 *(24) -> 24 | B100: No | D100: Cable Marker Wrap Around Type | G100: CAAC_025 | H100: 620 | I100: (__) | O100: 2 | Q100: 0.1 | R100: =$A100*Q100 -> 2.4 | T100: =$A100*S100*$T$1 -> 0
...

Sheet Elec_Est
B1: CLIENT: | C1: =ML_Sum!$C1 -> 1 | D1: =ML_Sum!$D1 -> Battery Street Limited | F1: =ML_Sum!$F1 -> 0 | I1: 1 | J1: =ML_Sum!$J1 -> 1 | K1: =ML_Sum!$K1 -> 1 | L1: =ML_Sum!$L1 -> 1 | M1: =ML_Sum!$M1 -> 1 | N1: =ML_Sum!$N1 -> 1 | O1: =ML_Sum!$O1 -> 1 | Q1: =ML_Sum!$Q1 -> € | R1: R/Lab Cont | S1: =ML_Sum!$S1 -> R | T1: =ML_Sum!$T1 -> 1.05 | U1: =ML_Sum!W1 -> BOQ | V1: INCL | W1: MULT | X1: AREA | Y1: BOQ | Z1: TDWG | AA1: ACT | AB1: DIFF
B2: PROJECT: | C2: =ML_Sum!$C2 -> 1 | D2: =ML_Sum!$D2 -> MEP Works British Hotel | F2: =ML_Sum!$F2 -> Electrical | I2: 2 | J2: =ML_Sum!$J2 -> 1 | K2: =ML_Sum!$K2 -> 1 | L2: =ML_Sum!$L2 -> 1 | M2: =ML_Sum!$M2 -> 1 | N2: =ML_Sum!$N2 -> 1 | O2: =ML_Sum!$O2 -> 1 | Q2: =ML_Sum!$Q2 -> 0 | R2: mu_A | S2: =ML_Sum!$S2 -> 1.22 | T2: =ML_Sum!$T2 -> 35.17626
B3: JOB DESC: | C3: =ML_Sum!$C3 -> 1 | D3: =ML_Sum!$D3 -> Electrical and ELV Systems | F3: =ML_Sum!$F3 -> Controls Section (DALI) | I3: 3 | J3: =ML_Sum!$J3 -> 1 | K3: =ML_Sum!$K3 -> 1 | L3: =ML_Sum!$L3 -> 1 | M3: =ML_Sum!$M3 -> 1 | N3: =ML_Sum!$N3 -> 1 | O3: =ML_Sum!$O3 -> 1 | Q3: =ML_Sum!$Q3 -> 0 | R3: mu_B | S3: =ML_Sum!$S3 -> 1.22 | T3: =ML_Sum!$T3 -> 86.64
B4: QUOTE No: | C4: =ML_Sum!$C4 -> 1 | D4: =ML_Sum!$D4 -> EL25-0662B | F4: =ML_Sum!$F4 -> Controls Section Engineer (DALI) | I4: 4 | J4: =ML_Sum!$J4 -> 1 | K4: =ML_Sum!$K4 -> 1 | L4: =ML_Sum!$L4 -> 1 | M4: =ML_Sum!$M4 -> 1 | N4: =ML_Sum!$N4 -> 1 | O4: =ML_Sum!$O4 -> 1 | Q4: =ML_Sum!$Q4 -> 0 | R4: mu_C | S4: =ML_Sum!$S4 -> 1.22 | T4: =ML_Sum!$T4 -> 51.41
B5: CLIENTs REF: | C5: =ML_Sum!$C5 -> 1 | D5: =ML_Sum!$D5 -> MEP REVISED | F5: =ML_Sum!$F5 -> ELV Sub-Contractor - APCO | I5: 5 | J5: =ML_Sum!$J5 -> 1 | K5: =ML_Sum!$K5 -> 1 | L5: =ML_Sum!$L5 -> 1 | M5: =ML_Sum!$M5 -> 1 | N5: =ML_Sum!$N5 -> 1 | O5: =ML_Sum!$O5 -> 1 | Q5: =ML_Sum!$Q5 -> 0 | R5: mu_D | S5: =ML_Sum!$S5 -> 1.075 | T5: =ML_Sum!$T5 -> 30.995475
B6: VAT/DUTIES: | C6: =ML_Sum!$C6 -> 1 | D6: =ML_Sum!$D6 -> VAT EXCL. | F6: =ML_Sum!$F6 -> ELV Sub-Contractor - DATA | I6: 6 | J6: =ML_Sum!$J6 -> 1 | K6: =ML_Sum!$K6 -> 1 | L6: =ML_Sum!$L6 -> 1 | M6: =ML_Sum!$M6 -> 1 | N6: =ML_Sum!$N6 -> 1 | O6: =ML_Sum!$O6 -> 1 | Q6: =ML_Sum!$Q6 -> 0 | R6: mu_E | S6: =ML_Sum!$S6 -> 1.1 | T6: =ML_Sum!$T6 -> 31.7163
B7: SAVED ON: | C7: =ML_Sum!$C7 -> 1 | D7: 39364 | F7: =ML_Sum!$F7 -> 0 | I7: 7 | J7: =ML_Sum!$J7 -> 1 | K7: =ML_Sum!$K7 -> 1 | L7: =ML_Sum!$L7 -> 1 | M7: =ML_Sum!$M7 -> 1 | N7: =ML_Sum!$N7 -> 1 | O7: =ML_Sum!$O7 -> 0 | Q7: =ML_Sum!$Q7 -> 0 | R7: mu_F | S7: =ML_Sum!$S7 -> 0 | T7: =ML_Sum!$T7 -> 0
B8: ESTIMATOR: | C8: =ML_Sum!$C8 -> 1 | D8: =ML_Sum!$D8 -> R.Farrugia | F8: =ML_Sum!$F8 -> 0 | I8: 8 | J8: =ML_Sum!$J8 -> 1 | K8: =ML_Sum!$K8 -> 1 | L8: =ML_Sum!$L8 -> 1 | M8: =ML_Sum!$M8 -> 1 | N8: =ML_Sum!$N8 -> 1 | O8: =ML_Sum!$O8 -> 0 | Q8: =ML_Sum!$Q8 -> 0 | R8: mu_G | S8: =ML_Sum!$S8 -> 0 | T8: =ML_Sum!$T8 -> 0
B9: LABOUR RATE: | C9: =ML_Sum!$C9 -> 1 | D9: =ML_Sum!$D9 -> 28.833 | F9: =ML_Sum!$F9 -> 0 | I9: 9 | J9: =ML_Sum!$J9 -> 1 | K9: =ML_Sum!$K9 -> 1 | L9: =ML_Sum!$L9 -> 1 | M9: =ML_Sum!$M9 -> 1 | N9: =ML_Sum!$N9 -> 1 | O9: =ML_Sum!$O9 -> 0 | Q9: =ML_Sum!$Q9 -> 0 | R9: mu_H | S9: =ML_Sum!$S9 -> 0 | T9: =ML_Sum!$T9 -> 0
C10: =ML_Sum!$C10 -> 1 | F10: =ML_Sum!$F10 -> Enemalta 3Ph Application | I10: 10 | J10: =ML_Sum!$J10 -> 1 | K10: =ML_Sum!$K10 -> 1 | L10: =ML_Sum!$L10 -> 1 | M10: =ML_Sum!$M10 -> 1 | N10: =ML_Sum!$N10 -> 1 | O10: =ML_Sum!$O10 -> 1 | Q10: =ML_Sum!$Q10 -> 0 | R10: mu_I | S10: =ML_Sum!$S10 -> 1.1 | T10: =ML_Sum!$T10 -> 31.7163
C11: =ML_Sum!$C11 -> 1 | F11: =ML_Sum!$F11 -> 0 | Q11: =ML_Sum!$Q11 -> 0 | R11: mu_J | S11: =ML_Sum!$S11 -> 0 | T11: =ML_Sum!$T11 -> 0
C12: =ML_Sum!$C12 -> 1 | F12: =ML_Sum!$F12 -> 0 | Q12: =ML_Sum!$Q12 -> 0 | R12: MIXED | S12: =ML_Sum!$S12 -> MAT MU | T12: =ML_Sum!$T12 -> LAB RATE
G13: ISELL | H13: C_CODE | I13: MAKE | J13: PART_NO | K13: MARKUP | L13: TYPE | M13: LIST_P | N13: P_FACT | O13: FIX | P13: DATE | Q13: %Dsct in BOQ | R13: MU TYPE | S13: MAT MU | T13: LAB RATE | AM13: Tot Mat Cost | AN13: Unit Lab phr. | AO13: Tot Lab phr. | AP13: < for ELM / MEE
K14: TB
C15: t
D16: PRELIMINARIES
E18: Sell Rate | F18: Sell Total | K18: IB | AG18: U_M_Sell | AH18: T_M_Sell | AI18: U_L_Sell | AJ18: T_L_Sell | AK18: Total_Sell | AM18: T_M_Cost | AN18: T_L_Phr | AO18: Mat/Lab=1
A19: 1 | B19: LS | D19: Item: 1 | E19: =IF(AND($A19=0,$A$1="DIF"),0, ROUND(ROUND(($R23*$S$2+($T23*$T$2))/A19,2)*$C$2,2)) -> 610 | F19: =ROUND($A19*$E19,2) -> 610 | G19: ISELL | K19: mu_A | L19: ITEM | T19: =IF(AND($R23=0,$T23=0),"0.00","mu :" & ROUND($F19/$C$2/($R23+$T23*$D$9),2)) -> mu :1.22 | AG19: =IF($E19=0,0,ROUND($R23*$S$2*$C$2/$A19,2)) -> 610 | AH19: =$AG19*$A19 -> 610 | AI19: =$E19-$AG19 -> 0 | AJ19: =$A19*$AI19 -> 0 | AK19: =ROUND(($AG19+$AI19)*$A19,2) -> 610 | AM19: =ROUND(R23,2) -> 500 | AN19: =ROUND(T23,2) -> 0 | AO19: =ROUND(AM19+AN19,2)*A19 -> 500
D20: Mobilisation and demobilisation including setting up of workshop storage facilities and their security.
A21: 1 | B21: No | D21: Mobilisation and demobilisation | G21: CONS_001 | H21: 875 | I21: (__) | K21: 01-001 | O21: 1 | Q21: 500 | R21: =$A21*Q21 -> 500 | T21: =$A21*S21*$T$1 -> 0
R22: =$A22*Q22 -> 0 | T22: =$A22*S22*$T$1 -> 0
A23: d> | B23: =(R22+T22) -> 0 | G23: ICOST | K23: mu_A | L23: ITEM | R23: =SUM(R20:R22) -> 500 | T23: =SUM(T20:T22) -> 0
E24: Sell Rate | F24: Sell Total | K24: IB | AG24: U_M_Sell | AH24: T_M_Sell | AI24: U_L_Sell | AJ24: T_L_Sell | AK24: Total_Sell | AM24: T_M_Cost | AN24: T_L_Phr | AO24: Mat/Lab=1
A25: 1 | B25: LS | D25: Item: 2 | E25: =IF(AND($A25=0,$A$1="DIF"),0, ROUND(ROUND(($R30*$S$2+($T30*$T$2))/A25,2)*$C$2,2)) -> 0 | F25: =ROUND($A25*$E25,2) -> 0 | G25: ISELL | K25: mu_A | L25: ITEM | Q25: Included | T25: =IF(AND($R30=0,$T30=0),"0.00","mu :" & ROUND($F25/$C$2/($R30+$T30*$D$9),2)) -> 0.00 | AG25: =IF($E25=0,0,ROUND($R30*$S$2*$C$2/$A25,2)) -> 0 | AH25: =$AG25*$A25 -> 0 | AI25: =$E25-$AG25 -> 0 | AJ25: =$A25*$AI25 -> 0 | AK25: =ROUND(($AG25+$AI25)*$A25,2) -> 0 | AM25: =ROUND(R30,2) -> 0 | AN25: =ROUND(T30,2) -> 0 | AO25: =ROUND(AM25+AN25,2)*A25 -> 0
D26: Safety clothing for all site personnel in accordance with statutory requirements. | K26: n
R27: =$A27*Q27 -> 0 | T27: =$A27*S27*$T$1 -> 0
D28: Included | R28: =$A28*Q28 -> 0 | T28: =$A28*S28*$T$1 -> 0
R29: =$A29*Q29 -> 0 | T29: =$A29*S29*$T$1 -> 0
A30: d> | B30: =(R29+T29) -> 0 | G30: ICOST | K30: mu_A | L30: ITEM | R30: =SUM(R26:R29) -> 0 | T30: =SUM(T26:T29) -> 0
E31: Sell Rate | F31: Sell Total | K31: IB | AG31: U_M_Sell | AH31: T_M_Sell | AI31: U_L_Sell | AJ31: T_L_Sell | AK31: Total_Sell | AM31: T_M_Cost | AN31: T_L_Phr | AO31: Mat/Lab=1
A32: 1 | B32: LS | D32: Item: 3 | E32: =IF(AND($A32=0,$A$1="DIF"),0, ROUND(ROUND(($R36*$S$2+($T36*$T$2))/A32,2)*$C$2,2)) -> 0 | F32: =ROUND($A32*$E32,2) -> 0 | G32: ISELL | K32: mu_A | L32: ITEM | Q32: Included | T32: =IF(AND($R36=0,$T36=0),"0.00","mu :" & ROUND($F32/$C$2/($R36+$T36*$D$9),2)) -> 0.00 | AG32: =IF($E32=0,0,ROUND($R36*$S$2*$C$2/$A32,2)) -> 0 | AH32: =$AG32*$A32 -> 0 | AI32: =$E32-$AG32 -> 0 | AJ32: =$A32*$AI32 -> 0 | AK32: =ROUND(($AG32+$AI32)*$A32,2) -> 0 | AM32: =ROUND(R36,2) -> 0 | AN32: =ROUND(T36,2) -> 0 | AO32: =ROUND(AM32+AN32,2)*A32 -> 0
D33: Allowance for weekly progress meetings within project execution period. | K33: n
B34: Trips | D34: Bolt car service for office employees for attending site meetings | G34: PROV_001 | H34: 970 | I34: MISC | O34: 4 | P34: 38129 | Q34: 10 | R34: =$A34*Q34 -> 0 | S34: 1 | T34: =$A34*S34*$T$1 -> 0 | U34: 20
R35: =$A35*Q35 -> 0 | T35: =$A35*S35*$T$1 -> 0
A36: d> | B36: =(R35+T35) -> 0 | G36: ICOST | K36: mu_A | L36: ITEM | R36: =SUM(R33:R35) -> 0 | T36: =SUM(T33:T35) -> 0
E37: Sell Rate | F37: Sell Total | K37: IB | AG37: U_M_Sell | AH37: T_M_Sell | AI37: U_L_Sell | AJ37: T_L_Sell | AK37: Total_Sell | AM37: T_M_Cost | AN37: T_L_Phr | AO37: Mat/Lab=1
A38: 1 | B38: LS | D38: Item: 4 | E38: =IF(AND($A38=0,$A$1="DIF"),0, ROUND(ROUND(($R43*$S$2+($T43*$T$2))/A38,2)*$C$2,2)) -> 0 | F38: =ROUND($A38*$E38,2) -> 0 | G38: ISELL | K38: mu_A | L38: ITEM | Q38: Included | T38: =IF(AND($R43=0,$T43=0),"0.00","mu :" & ROUND($F38/$C$2/($R43+$T43*$D$9),2)) -> 0.00 | AG38: =IF($E38=0,0,ROUND($R43*$S$2*$C$2/$A38,2)) -> 0 | AH38: =$AG38*$A38 -> 0 | AI38: =$E38-$AG38 -> 0 | AJ38: =$A38*$AI38 -> 0 | AK38: =ROUND(($AG38+$AI38)*$A38,2) -> 0 | AM38: =ROUND(R43,2) -> 0 | AN38: =ROUND(T43,2) -> 0 | AO38: =ROUND(AM38+AN38,2)*A38 -> 0
D39: Provision of instrumentation used for commissioning purposes including evidence of associated valid calibration certificates.
R40: =$A40*Q40 -> 0 | T40: =$A40*S40*$T$1 -> 0
D41: Included | R41: =$A41*Q41 -> 0 | T41: =$A41*S41*$T$1 -> 0
R42: =$A42*Q42 -> 0 | T42: =$A42*S42*$T$1 -> 0
A43: d> | B43: =(R42+T42) -> 0 | G43: ICOST | K43: mu_A | L43: ITEM | R43: =SUM(R39:R42) -> 0 | T43: =SUM(T39:T42) -> 0
E44: Sell Rate | F44: Sell Total | K44: IB | AG44: U_M_Sell | AH44: T_M_Sell | AI44: U_L_Sell | AJ44: T_L_Sell | AK44: Total_Sell | AM44: T_M_Cost | AN44: T_L_Phr | AO44: Mat/Lab=1
A45: 1 | B45: LS | D45: Item: 5 | E45: =IF(AND($A45=0,$A$1="DIF"),0, ROUND(ROUND(($R50*$S$2+($T50*$T$2))/A45,2)*$C$2,2)) -> 0 | F45: =ROUND($A45*$E45,2) -> 0 | G45: ISELL | K45: mu_A | L45: ITEM | Q45: Included | T45: =IF(AND($R50=0,$T50=0),"0.00","mu :" & ROUND($F45/$C$2/($R50+$T50*$D$9),2)) -> 0.00 | AG45: =IF($E45=0,0,ROUND($R50*$S$2*$C$2/$A45,2)) -> 0 | AH45: =$AG45*$A45 -> 0 | AI45: =$E45-$AG45 -> 0 | AJ45: =$A45*$AI45 -> 0 | AK45: =ROUND(($AG45+$AI45)*$A45,2) -> 0 | AM45: =ROUND(R50,2) -> 0 | AN45: =ROUND(T50,2) -> 0 | AO45: =ROUND(AM45+AN45,2)*A45 -> 0
D46: Two copies of a complete set of installation drawings allowing for coordination with sub-contractors, client, interior designer, etc. as applicable.
R47: =$A47*Q47 -> 0 | T47: =$A47*S47*$T$1 -> 0
D48: Included | R48: =$A48*Q48 -> 0 | T48: =$A48*S48*$T$1 -> 0
R49: =$A49*Q49 -> 0 | T49: =$A49*S49*$T$1 -> 0
A50: d> | B50: =(R49+T49) -> 0 | G50: ICOST | K50: mu_A | L50: ITEM | R50: =SUM(R46:R49) -> 0 | T50: =SUM(T46:T49) -> 0
E51: Sell Rate | F51: Sell Total | K51: IB | AG51: U_M_Sell | AH51: T_M_Sell | AI51: U_L_Sell | AJ51: T_L_Sell | AK51: Total_Sell | AM51: T_M_Cost | AN51: T_L_Phr | AO51: Mat/Lab=1
A52: 1 | B52: LS | D52: Item: 6 | E52: =IF(AND($A52=0,$A$1="DIF"),0, ROUND(ROUND(($R57*$S$2+($T57*$T$2))/A52,2)*$C$2,2)) -> 0 | F52: =ROUND($A52*$E52,2) -> 0 | G52: ISELL | K52: mu_A | L52: ITEM | Q52: Included | T52: =IF(AND($R57=0,$T57=0),"0.00","mu :" & ROUND($F52/$C$2/($R57+$T57*$D$9),2)) -> 0.00 | AG52: =IF($E52=0,0,ROUND($R57*$S$2*$C$2/$A52,2)) -> 0 | AH52: =$AG52*$A52 -> 0 | AI52: =$E52-$AG52 -> 0 | AJ52: =$A52*$AI52 -> 0 | AK52: =ROUND(($AG52+$AI52)*$A52,2) -> 0 | AM52: =ROUND(R57,2) -> 0 | AN52: =ROUND(T57,2) -> 0 | AO52: =ROUND(AM52+AN52,2)*A52 -> 0
D53: Provision for a quality control engineer to ensure that the items being proposed are in accordance with technical specification and will fulfil the project requirements.
R54: =$A54*Q54 -> 0 | T54: =$A54*S54*$T$1 -> 0
D55: Included | R55: =$A55*Q55 -> 0 | T55: =$A55*S55*$T$1 -> 0
R56: =$A56*Q56 -> 0 | T56: =$A56*S56*$T$1 -> 0
A57: d> | B57: =(R56+T56) -> 0 | G57: ICOST | K57: mu_A | L57: ITEM | R57: =SUM(R53:R56) -> 0 | T57: =SUM(T53:T56) -> 0
E58: Sell Rate | F58: Sell Total | K58: IB | AG58: U_M_Sell | AH58: T_M_Sell | AI58: U_L_Sell | AJ58: T_L_Sell | AK58: Total_Sell | AM58: T_M_Cost | AN58: T_L_Phr | AO58: Mat/Lab=1
A59: 1 | B59: LS | D59: Item: 7 | E59: =IF(AND($A59=0,$A$1="DIF"),0, ROUND(ROUND(($R63*$S$2+($T63*$T$2))/A59,2)*$C$2,2)) -> 0 | F59: =ROUND($A59*$E59,2) -> 0 | G59: ISELL | K59: mu_A | L59: ITEM | Q59: Included | T59: =IF(AND($R63=0,$T63=0),"0.00","mu :" & ROUND($F59/$C$2/($R63+$T63*$D$9),2)) -> 0.00 | AG59: =IF($E59=0,0,ROUND($R63*$S$2*$C$2/$A59,2)) -> 0 | AH59: =$AG59*$A59 -> 0 | AI59: =$E59-$AG59 -> 0 | AJ59: =$A59*$AI59 -> 0 | AK59: =ROUND(($AG59+$AI59)*$A59,2) -> 0 | AM59: =ROUND(R63,2) -> 0 | AN59: =ROUND(T63,2) -> 0 | AO59: =ROUND(AM59+AN59,2)*A59 -> 0
D60: Provision for a Quality Control Engineer to certify that the equipment and materials are installed, tested and commissioned in accordance with manufacturer's recommendations and / or relevant statutory requirements and / or CIBSE and / or equal and approved documents.
B61: LS | D61: Provision for a Quality Control Engineer | G61: COMM_004 | H61: 902 | I61: MISC | O61: 3 | P61: 38317 | Q61: 1050 | R61: =$A61*Q61 -> 0 | T61: =$A61*S61*$T$1 -> 0 | U61: 1
R62: =$A62*Q62 -> 0 | T62: =$A62*S62*$T$1 -> 0
A63: d> | B63: =(R62+T62) -> 0 | G63: ICOST | K63: mu_A | L63: ITEM | R63: =SUM(R60:R62) -> 0 | T63: =SUM(T60:T62) -> 0
E64: Sell Rate | F64: Sell Total | K64: IB | AG64: U_M_Sell | AH64: T_M_Sell | AI64: U_L_Sell | AJ64: T_L_Sell | AK64: Total_Sell | AM64: T_M_Cost | AN64: T_L_Phr | AO64: Mat/Lab=1
A65: 1 | B65: LS | D65: Item: 8 | E65: =IF(AND($A65=0,$A$1="DIF"),0, ROUND(ROUND(($R70*$S$2+($T70*$T$2))/A65,2)*$C$2,2)) -> 0 | F65: =ROUND($A65*$E65,2) -> 0 | G65: ISELL | K65: mu_A | L65: ITEM | Q65: Included | T65: =IF(AND($R70=0,$T70=0),"0.00","mu :" & ROUND($F65/$C$2/($R70+$T70*$D$9),2)) -> 0.00 | AG65: =IF($E65=0,0,ROUND($R70*$S$2*$C$2/$A65,2)) -> 0 | AH65: =$AG65*$A65 -> 0 | AI65: =$E65-$AG65 -> 0 | AJ65: =$A65*$AI65 -> 0 | AK65: =ROUND(($AG65+$AI65)*$A65,2) -> 0 | AM65: =ROUND(R70,2) -> 0 | AN65: =ROUND(T70,2) -> 0 | AO65: =ROUND(AM65+AN65,2)*A65 -> 0
D66: Provision to identify access requirements for maintenance purposes in accordance with manufacturer's guidelines and common practice.
R67: =$A67*Q67 -> 0 | T67: =$A67*S67*$T$1 -> 0
D68: Included | R68: =$A68*Q68 -> 0 | T68: =$A68*S68*$T$1 -> 0
R69: =$A69*Q69 -> 0 | T69: =$A69*S69*$T$1 -> 0
A70: d> | B70: =(R69+T69) -> 0 | G70: ICOST | K70: mu_A | L70: ITEM | R70: =SUM(R66:R69) -> 0 | T70: =SUM(T66:T69) -> 0
E71: Sell Rate | F71: Sell Total | K71: IB | AG71: U_M_Sell | AH71: T_M_Sell | AI71: U_L_Sell | AJ71: T_L_Sell | AK71: Total_Sell | AM71: T_M_Cost | AN71: T_L_Phr | AO71: Mat/Lab=1
A72: 1 | B72: LS | D72: Item: 9 | E72: =IF(AND($A72=0,$A$1="DIF"),0, ROUND(ROUND(($R76*$S$2+($T76*$T$2))/A72,2)*$C$2,2)) -> 1049.2 | F72: =ROUND($A72*$E72,2) -> 1049.2 | G72: ISELL | K72: mu_A | L72: ITEM | T72: =IF(AND($R76=0,$T76=0),"0.00","mu :" & ROUND($F72/$C$2/($R76+$T76*$D$9),2)) -> mu :1.22 | AG72: =IF($E72=0,0,ROUND($R76*$S$2*$C$2/$A72,2)) -> 1049.2 | AH72: =$AG72*$A72 -> 1049.2 | AI72: =$E72-$AG72 -> 0 | AJ72: =$A72*$AI72 -> 0 | AK72: =ROUND(($AG72+$AI72)*$A72,2) -> 1049.2 | AM72: =ROUND(R76,2) -> 860 | AN72: =ROUND(T76,2) -> 0 | AO72: =ROUND(AM72+AN72,2)*A72 -> 860
D73: Provision of signing of commissioning documentation by an independent Warranted Engineer. | K73: n
A74: 1 | B74: LS | D74: Provision of signing of commissioning documentation by an independent Warranted Engineer | G74: COMM_004 | H74: 902 | I74: MISC | O74: 3 | P74: 38317 | Q74: 860 | R74: =$A74*Q74 -> 860 | T74: =$A74*S74*$T$1 -> 0
R75: =$A75*Q75 -> 0 | T75: =$A75*S75*$T$1 -> 0
A76: d> | B76: =(R75+T75) -> 0 | G76: ICOST | K76: mu_A | L76: ITEM | R76: =SUM(R73:R75) -> 860 | T76: =SUM(T73:T75) -> 0
E77: Sell Rate | F77: Sell Total | K77: IB | AG77: U_M_Sell | AH77: T_M_Sell | AI77: U_L_Sell | AJ77: T_L_Sell | AK77: Total_Sell | AM77: T_M_Cost | AN77: T_L_Phr | AO77: Mat/Lab=1
A78: 1 | B78: LS | D78: Item: 10 | E78: =IF(AND($A78=0,$A$1="DIF"),0, ROUND(ROUND(($R82*$S$2+($T82*$T$2))/A78,2)*$C$2,2)) -> 585.6 | F78: =ROUND($A78*$E78,2) -> 585.6 | G78: ISELL | K78: mu_A | L78: ITEM | T78: =IF(AND($R82=0,$T82=0),"0.00","mu :" & ROUND($F78/$C$2/($R82+$T82*$D$9),2)) -> mu :1.22 | AG78: =IF($E78=0,0,ROUND($R82*$S$2*$C$2/$A78,2)) -> 585.6 | AH78: =$AG78*$A78 -> 585.6 | AI78: =$E78-$AG78 -> 0 | AJ78: =$A78*$AI78 -> 0 | AK78: =ROUND(($AG78+$AI78)*$A78,2) -> 585.6 | AM78: =ROUND(R82,2) -> 480 | AN78: =ROUND(T82,2) -> 0 | AO78: =ROUND(AM78+AN78,2)*A78 -> 480
D79: Provision of signing of as-fitted drawings by an independent Warranted Engineer. | K79: n
A80: 1 | B80: LS | D80: Provision of signing of as-fitted drawings by an independent Warranted Engineer | G80: COMM_004 | H80: 902 | I80: MISC | O80: 3 | P80: 38317 | Q80: 480 | R80: =$A80*Q80 -> 480 | T80: =$A80*S80*$T$1 -> 0
R81: =$A81*Q81 -> 0 | T81: =$A81*S81*$T$1 -> 0
A82: d> | B82: =(R81+T81) -> 0 | G82: ICOST | K82: mu_A | L82: ITEM | R82: =SUM(R79:R81) -> 480 | T82: =SUM(T79:T81) -> 0
A83: SB
B85: =$F85/$C$2-($R85*$S$2+$T85*$T$2) -> 0 | D85: PAGE: | F85: =SUMIF($L14:$L83,"ITEM",F14:F83) -> 2244.8 | L85: PAGE | R85: =SUMIF($L14:$L83,"ITEM",R14:R83) -> 1840 | T85: =SUMIF($L14:$L83,"ITEM",T14:T83) -> 0
B86: Discy: | F86: PAGE SELL | R86: PAGE MAT | T86: PAGE LAB
E89: Sell Rate | F89: Sell Total | K89: IB | AG89: U_M_Sell | AH89: T_M_Sell | AI89: U_L_Sell | AJ89: T_L_Sell | AK89: Total_Sell | AM89: T_M_Cost | AN89: T_L_Phr | AO89: Mat/Lab=1
A90: 1 | B90: LS | D90: Item: 11 | E90: =IF(AND($A90=0,$A$1="DIF"),0, ROUND(ROUND(($R95*$S$2+($T95*$T$2))/A90,2)*$C$2,2)) -> 0 | F90: =ROUND($A90*$E90,2) -> 0 | G90: ISELL | K90: mu_A | L90: ITEM | Q90: Refer to covering letter. | T90: =IF(AND($R95=0,$T95=0),"0.00","mu :" & ROUND($F90/$C$2/($R95+$T95*$D$9),2)) -> 0.00 | AG90: =IF($E90=0,0,ROUND($R95*$S$2*$C$2/$A90,2)) -> 0 | AH90: =$AG90*$A90 -> 0 | AI90: =$E90-$AG90 -> 0 | AJ90: =$A90*$AI90 -> 0 | AK90: =ROUND(($AG90+$AI90)*$A90,2) -> 0 | AM90: =ROUND(R95,2) -> 0 | AN90: =ROUND(T95,2) -> 0 | AO90: =ROUND(AM90+AN90,2)*A90 -> 0
D91: To allow for builders works in accordance to the preamble section of the technical specifications.
R92: =$A92*Q92 -> 0 | T92: =$A92*S92*$T$1 -> 0
D93: Refer to covering letter. | R93: =$A93*Q93 -> 0 | T93: =$A93*S93*$T$1 -> 0
R94: =$A94*Q94 -> 0 | T94: =$A94*S94*$T$1 -> 0
A95: d> | B95: =(R94+T94) -> 0 | G95: ICOST | K95: mu_A | L95: ITEM | R95: =SUM(R91:R94) -> 0 | T95: =SUM(T91:T94) -> 0
E96: Sell Rate | F96: Sell Total | K96: IB | AG96: U_M_Sell | AH96: T_M_Sell | AI96: U_L_Sell | AJ96: T_L_Sell | AK96: Total_Sell | AM96: T_M_Cost | AN96: T_L_Phr | AO96: Mat/Lab=1
A97: 1 | B97: LS | D97: Item: 12 | E97: =IF(AND($A97=0,$A$1="DIF"),0, ROUND(ROUND(($R102*$S$2+($T102*$T$2))/A97,2)*$C$2,2)) -> 0 | F97: =ROUND($A97*$E97,2) -> 0 | G97: ISELL | K97: mu_A | L97: ITEM | Q97: Included | T97: =IF(AND($R102=0,$T102=0),"0.00","mu :" & ROUND($F97/$C$2/($R102+$T102*$D$9),2)) -> 0.00 | AG97: =IF($E97=0,0,ROUND($R102*$S$2*$C$2/$A97,2)) -> 0 | AH97: =$AG97*$A97 -> 0 | AI97: =$E97-$AG97 -> 0 | AJ97: =$A97*$AI97 -> 0 | AK97: =ROUND(($AG97+$AI97)*$A97,2) -> 0 | AM97: =ROUND(R102,2) -> 0 | AN97: =ROUND(T102,2) -> 0 | AO97: =ROUND(AM97+AN97,2)*A97 -> 0
D98: Provision for a recognised Health and Safety Officer. | K98: n
R99: =$A99*Q99 -> 0 | T99: =$A99*S99*$T$1 -> 0
D100: Included | R100: =$A100*Q100 -> 0 | T100: =$A100*S100*$T$1 -> 0
R101: =$A101*Q101 -> 0 | T101: =$A101*S101*$T$1 -> 0
A102: d> | B102: =(R101+T101) -> 0 | G102: ICOST | K102: mu_A | L102: ITEM | R102: =SUM(R98:R101) -> 0 | T102: =SUM(T98:T101) -> 0
E103: Sell Rate | F103: Sell Total | K103: IB | AG103: U_M_Sell | AH103: T_M_Sell | AI103: U_L_Sell | AJ103: T_L_Sell | AK103: Total_Sell | AM103: T_M_Cost | AN103: T_L_Phr | AO103: Mat/Lab=1
A104: 1 | B104: LS | D104: Item: 13 | E104: =IF(AND($A104=0,$A$1="DIF"),0, ROUND(ROUND(($R109*$S$2+($T109*$T$2))/A104,2)*$C$2,2)) -> 2623 | F104: =ROUND($A104*$E104,2) -> 2623 | G104: ISELL | K104: mu_A | L104: ITEM | T104: =IF(AND($R109=0,$T109=0),"0.00","mu :" & ROUND($F104/$C$2/($R109+$T109*$D$9),2)) -> mu :1.22 | AG104: =IF($E104=0,0,ROUND($R109*$S$2*$C$2/$A104,2)) -> 2623 | AH104: =$AG104*$A104 -> 2623 | AI104: =$E104-$AG104 -> 0 | AJ104: =$A104*$AI104 -> 0 | AK104: =ROUND(($AG104+$AI104)*$A104,2) -> 2623 | AM104: =ROUND(R109,2) -> 2150 | AN104: =ROUND(T109,2) -> 0 | AO104: =ROUND(AM104+AN104,2)*A104 -> 2150
...

Sheet ML_Sum
B1: CLIENT: | C1: 1 | D1: Battery Street Limited | G1: TRUE | H1: TRUE | I1: 1 | J1: =$Q110 -> 1 | K1: =$Q120 -> 1 | L1: =$Q130 -> 1 | M1: =$Q140 -> 1 | N1: =$Q150 -> 1 | O1: =$Q160 -> 1 | Q1: =IF(C1=1,"€","Curr?") -> € | R1: Recon /Lab.Cont >> | S1: =IF($S$39="PRINT","R","Do Not Print") -> R | T1: 1.05 | V1: {=IF(OR(X1=AREAS),1,0)} -> 1 | W1: BOQ | X1: x | Y1: x | Z1: x | AA1: x | AB1: x | AC1: x | AD1: x
B2: PROJECT: | C2: =IF($D$6="VAT INCLUDED",1.18,1)*(1-$Q2)*$C$1 -> 1 | D2: MEP Works British Hotel | F2: Electrical | G2: TRUE | I2: 2 | J2: =$Q111 -> 1 | K2: =$Q121 -> 1 | L2: =$Q131 -> 1 | M2: =$Q141 -> 1 | N2: =$Q151 -> 1 | O2: =$Q161 -> 1 | R2: ="A) " & IF($S2=0,"",ROUND($S2,2) & "-" & ROUND($T2/$D$9,2)) -> A) 1.22-1.22 | S2: 1.22 | T2: =$S2*$D$9 -> 35.17626 | U2: 1.26 | X2: x | Y2: x | Z2: x | AA2: x | AB2: x | AC2: x | AD2: x
B3: JOB DESC: | C3: =IF($D$6="VAT INCLUDED",1.18,1)*(1-$Q3)*$C$1 -> 1 | D3: Electrical and ELV Systems | F3: Controls Section (DALI) | G3: TRUE | I3: 3 | J3: =$Q112 -> 1 | K3: =$Q122 -> 1 | L3: =$Q132 -> 1 | M3: =$Q142 -> 1 | N3: =$Q152 -> 1 | O3: =$Q162 -> 1 | R3: ="B) " & IF($S3=0,"",ROUND($S3,2) & "-" & ROUND($T3/$D$9,2)) -> B) 1.22-3 | S3: 1.22 | T3: =$D$11 -> 86.64 | U3: 1.26 | X3: x | Y3: x | Z3: x | AA3: x | AB3: x | AC3: x | AD3: x
B4: INT. QUOT No: | C4: =IF($D$6="VAT INCLUDED",1.18,1)*(1-$Q4)*$C$1 -> 1 | D4: EL25-0662B | F4: Controls Section Engineer (DALI) | G4: TRUE | I4: 4 | J4: =$Q113 -> 1 | K4: =$Q123 -> 1 | L4: =$Q133 -> 1 | M4: =$Q143 -> 1 | N4: =$Q153 -> 1 | O4: =$Q163 -> 1 | R4: ="C) " & IF($S4=0,"",ROUND($S4,2) & "-" & ROUND($T4/$D$9,2)) -> C) 1.22-1.78 | S4: 1.22 | T4: =D10 -> 51.41 | U4: 1.26 | X4: x | Y4: x | Z4: x | AA4: x | AB4: x | AC4: x | AD4: x
B5: CLIENTs REF: | C5: =IF($D$6="VAT INCLUDED",1.18,1)*(1-$Q5)*$C$1 -> 1 | D5: MEP REVISED | F5: ELV Sub-Contractor - APCO | G5: TRUE | I5: 5 | J5: =$Q114 -> 1 | K5: =$Q124 -> 1 | L5: =$Q134 -> 1 | M5: =$Q144 -> 1 | N5: =$Q154 -> 1 | O5: =$Q164 -> 1 | R5: ="D) " & IF($S5=0,"",ROUND($S5,2) & "-" & ROUND($T5/$D$9,2)) -> D) 1.08-1.08 | S5: 1.075 | T5: =$S5*$D$9 -> 30.995475 | U5: =1.1 -> 1.1 | X5: x | Y5: x | Z5: x | AA5: x | AB5: x | AC5: x | AD5: x
B6: VAT: | C6: =IF($D$6="VAT INCLUDED",1.18,1)*(1-$Q6)*$C$1 -> 1 | D6: VAT EXCL. | F6: ELV Sub-Contractor - DATA | G6: TRUE | I6: 6 | J6: =$Q115 -> 1 | K6: =$Q125 -> 1 | L6: =$Q135 -> 1 | M6: =$Q145 -> 1 | N6: =$Q155 -> 1 | O6: =$Q165 -> 1 | R6: ="E) " & IF($S6=0,"",ROUND($S6,2) & "-" & ROUND($T6/$D$9,2)) -> E) 1.1-1.1 | S6: 1.1 | T6: =$S6*$D$9 -> 31.7163 | U6: =1.15 -> 1.15 | X6: x | Y6: x | Z6: x | AA6: x | AB6: x | AC6: x | AD6: x
B7: SAVED ON: | C7: =IF($D$6="VAT INCLUDED",1.18,1)*(1-$Q7)*$C$1 -> 1 | D7: 46034 | G7: TRUE | I7: 7 | J7: =$Q116 -> 1 | K7: =$Q126 -> 1 | L7: =$Q136 -> 1 | M7: =$Q146 -> 1 | N7: =$Q156 -> 1 | R7: ="F) " & IF($S7=0,"",ROUND($S7,2) & "-" & ROUND($T7/$D$9,2)) -> F) | X7: x | Y7: x | Z7: x | AA7: x | AB7: x | AC7: x | AD7: x
B8: ESTIMATOR: | C8: =IF($D$6="VAT INCLUDED",1.18,1)*(1-$Q8)*$C$1 -> 1 | D8: R.Farrugia | G8: TRUE | I8: 8 | J8: =$Q117 -> 1 | K8: =$Q127 -> 1 | L8: =$Q137 -> 1 | M8: =$Q147 -> 1 | N8: =$Q157 -> 1 | R8: ="G) " & IF($S8=0,"",ROUND($S8,2) & "-" & ROUND($T8/$D$9,2)) -> G) | X8: x | Y8: x | Z8: x | AA8: x | AB8: x | AC8: x | AD8: x
B9: LAB. COST: | C9: =IF($D$6="VAT INCLUDED",1.18,1)*(1-$Q9)*$C$1 -> 1 | D9: 28.833 | E9: Cost for 2026 | G9: TRUE | I9: 9 | J9: =$Q118 -> 1 | K9: =$Q128 -> 1 | L9: =$Q138 -> 1 | M9: =$Q148 -> 1 | N9: =$Q158 -> 1 | R9: ="H) " & IF($S9=0,"",ROUND($S9,2) & "-" & ROUND($T9/$D$9,2)) -> H) | X9: x | Y9: x | Z9: x | AA9: x | AB9: x | AC9: x | AD9: x
C10: =IF($D$6="VAT INCLUDED",1.18,1)*(1-$Q10)*$C$1 -> 1 | D10: 51.41 | E10: Single Engineer | F10: Enemalta 3Ph Application | G10: TRUE | I10: 10 | J10: =$Q119 -> 1 | K10: =$Q129 -> 1 | L10: =$Q139 -> 1 | M10: =$Q149 -> 1 | N10: =$Q159 -> 1 | O10: =Q109 -> 1 | R10: =" I) " & IF($S10=0,"",ROUND($S10,2) & "-" & ROUND($T10/$D$9,2)) -> I) 1.1-1.1 | S10: =1.1 -> 1.1 | T10: =$S10*$D$9 -> 31.7163 | U10: =1.1 -> 1.1 | X10: x | Y10: x | Z10: x | AA10: x | AB10: x | AC10: x | AD10: x
C11: =IF($D$6="VAT INCLUDED",1.18,1)*(1-$Q11)*$C$1 -> 1 | D11: =43.32*2 -> 86.64 | E11: Pair Technician | R11: ="J) " & IF($S11=0,"",ROUND($S11,2) & "-" & ROUND($T11/$D$9,2)) -> J) | X11: x | Y11: x | Z11: x | AA11: x | AB11: x | AC11: x | AD11: x
C12: =IF($D$6="VAT INCLUDED",1.18,1)*(1-$Q12)*$C$1 -> 1 | G12: SYSTEMS | H12: SYSTEMS | I12: SYSTEMS | J12: SYSTEMS | K12: SYSTEMS | L12: SYSTEMS | M12: SYSTEMS | N12: SYSTEMS | O12: SYSTEMS | P12: SYSTEMS | R12: MIXED - X,Y ) | S12: MAT MU | T12: LAB RATE | X12: x | Y12: x | Z12: x | AA12: x | AB12: x | AC12: x | AD12: x
B13: MATERIAL & LABOUR SUMMARY | G13: ItemCode | H13: CostCode | I13: MAKE | J13: PART_NO | K13: MARKUP | L13: TYPE | M13: LIST_P | N13: SET | O13: FIX | P13: DATE | Q13: %Dsct in BOQ | R13: MATMU-LABMU | S13: MAT CONT >> | T13: =SUM(Q109:Q165)/57 -> 1
B14: =IF($D$6<>"VAT EXCL.", "QUOTE ISSUED WITH VAT INCLUDED", "") | X14: x | Y14: x | Z14: x | AA14: x | AB14: x | AC14: x | AD14: x
Q15: =(C73-F35)/C73 -> 0 | R15: Average Discount applied in BOQ (Q2-Q12) | X15: x | Y15: x | Z15: x | AA15: x | AB15: x | AC15: x | AD15: x
B16: =IF($W$1<>"BOQ", "DIFF SET TO " & W1,"") | Q16: =(F35-E35)/F35 -> 0 | R16: Average Discount applied on Totals (Q23-Q32) | X16: x | Y16: x | Z16: x | AA16: x | AB16: x | AC16: x | AD16: x
Q17: =F75 -> 0 | R17: Overall Discount
B18: =IF(AND(G1,G2,G3,G4,G5,G6,G7,G8,G9,G10,H1)=TRUE, "", "CHECKLIST INCOMPLETE !" )
B19: =IF(ABS(SUM(A23:A32))>100,"[Discy A-J] are high, Check it out."," ") | Q19: =R84 -> 1.2039064 | R19: Overall Markup (Final Selling Excl.VAT/Total Cost )
E21: DISCOUNTED | F21: SELLING | Q21: % Discnt | R21: MATERIAL | T21: LABOUR
A22: Discy.A-J | B22: Markup/LRate | E22: ="SELLING " & $Q$1 -> SELLING € | F22: =$Q$1 -> € | G22: VAT/DISC | H22: MU | I22: LABRATE | J22: LABCOST | Q22: on Totals | R22: € | T22: Pair Hrs.
A23: =IF($F23=0,"",($F23/$C2)-($R23*$S2+$T23*$T2)) -> -2.0069441 | B23: =IF(F23=0,"",IF(R23=0,"A) "&"---, "&ROUND(($F23/$C2-($R23*$S2))/$T23,2),IF(T23=0,"A) "&ROUND(($F23/$C2)/$R23,2),"A) "&ROUND(($F23/$C2-($T23*$T2))/$R23,2)&", " &ROUND(($F23/$C2-($R23*$S2))/$T23,2)))) -> A) 1.22, 35.18 | D23: =IF($F2="","",$F2) -> Electrical | E23: =F23*(1-Q23) -> 225676.34 | F23: =Elec_Est!F5454 -> 225676.34 | G23: =C2 -> 1 | H23: =$S2 -> 1.22 | I23: =$T2 -> 35.17626 | J23: =$D$9 -> 28.833 | R23: =Elec_Est!R5454 -> 113304.29 | T23: =Elec_Est!T5454 -> 2485.9695
A24: =IF($F24=0,"",($F24/$C3)-($R24*$S3+$T24*$T3)) -> 0.0626 | B24: =IF(F24=0,"",IF(R24=0,"A) "&"---, "&ROUND(($F24/$C3-($R24*$S3))/$T24,2),IF(T24=0,"A) "&ROUND(($F24/$C3)/$R24,2),"A) "&ROUND(($F24/$C3-($T24*$T3))/$R24,2)&", " &ROUND(($F24/$C3-($R24*$S3))/$T24,2)))) -> A) 1.22, 86.64 | D24: =IF($F3="","",$F3) -> Controls Section (DALI) | E24: =F24*(1-Q24) -> 5699.92 | F24: =Elec_Est!F5455 -> 5699.92 | G24: =C3 -> 1 | H24: =$S3 -> 1.22 | I24: =$T3 -> 86.64 | J24: =$D$9 -> 28.833 | R24: =Elec_Est!R5455 -> 3180.67 | T24: =Elec_Est!T5455 -> 21
A25: =IF($F25=0,"",($F25/$C4)-($R25*$S4+$T25*$T4)) -> 0.003 | B25: =IF(F25=0,"",IF(R25=0,"A) "&"---, "&ROUND(($F25/$C4-($R25*$S4))/$T25,2),IF(T25=0,"A) "&ROUND(($F25/$C4)/$R25,2),"A) "&ROUND(($F25/$C4-($T25*$T4))/$R25,2)&", " &ROUND(($F25/$C4-($R25*$S4))/$T25,2)))) -> A) ---, 51.41 | D25: =IF($F4="","",$F4) -> Controls Section Engineer (DALI) | E25: =F25*(1-Q25) -> 5074.17 | F25: =Elec_Est!F5456 -> 5074.17 | G25: =C4 -> 1 | H25: =$S4 -> 1.22 | I25: =$T4 -> 51.41 | J25: =$D$9 -> 28.833 | R25: =Elec_Est!R5456 -> 0 | T25: =Elec_Est!T5456 -> 98.7
A26: =IF($F26=0,"",($F26/$C5)-($R26*$S5+$T26*$T5)) -> -1.62875 | B26: =IF(F26=0,"",IF(R26=0,"A) "&"---, "&ROUND(($F26/$C5-($R26*$S5))/$T26,2),IF(T26=0,"A) "&ROUND(($F26/$C5)/$R26,2),"A) "&ROUND(($F26/$C5-($T26*$T5))/$R26,2)&", " &ROUND(($F26/$C5-($R26*$S5))/$T26,2)))) -> A) 1.07 | D26: =IF($F5="","",$F5) -> ELV Sub-Contractor - APCO | E26: =F26*(1-Q26) -> 42819.76 | F26: =Elec_Est!F5457 -> 42819.76 | G26: =C5 -> 1 | H26: =$S5 -> 1.075 | I26: =$T5 -> 30.995475 | J26: =$D$9 -> 28.833 | R26: =Elec_Est!R5457 -> 39833.85 | T26: =Elec_Est!T5457 -> 0
A27: =IF($F27=0,"",($F27/$C6)-($R27*$S6+$T27*$T6)) -> -9.094947e-13 | B27: =IF(F27=0,"",IF(R27=0,"A) "&"---, "&ROUND(($F27/$C6-($R27*$S6))/$T27,2),IF(T27=0,"A) "&ROUND(($F27/$C6)/$R27,2),"A) "&ROUND(($F27/$C6-($T27*$T6))/$R27,2)&", " &ROUND(($F27/$C6-($R27*$S6))/$T27,2)))) -> A) 1.1 | D27: =IF($F6="","",$F6) -> ELV Sub-Contractor - DATA | E27: =F27*(1-Q27) -> 6072 | F27: =Elec_Est!F5458 -> 6072 | G27: =C6 -> 1 | H27: =$S6 -> 1.1 | I27: =$T6 -> 31.7163 | J27: =$D$9 -> 28.833 | R27: =Elec_Est!R5458 -> 5520 | T27: =Elec_Est!T5458 -> 0
A28: =IF($F28=0,"",($F28/$C7)-($R28*$S7+$T28*$T7)) | B28: =IF(F28=0,"",IF(R28=0,"A) "&"---, "&ROUND(($F28/$C7-($R28*$S7))/$T28,2),IF(T28=0,"A) "&ROUND(($F28/$C7)/$R28,2),"A) "&ROUND(($F28/$C7-($T28*$T7))/$R28,2)&", " &ROUND(($F28/$C7-($R28*$S7))/$T28,2)))) | D28: =IF($F7="","",$F7) | E28: =F28*(1-Q28) -> 0 | F28: =Elec_Est!F5459 -> 0 | G28: =C7 -> 1 | H28: =$S7 -> 0 | I28: =$T7 -> 0 | J28: =$D$9 -> 28.833 | R28: =Elec_Est!R5459 -> 0 | T28: =Elec_Est!T5459 -> 0
A29: =IF($F29=0,"",($F29/$C8)-($R29*$S8+$T29*$T8)) | B29: =IF(F29=0,"",IF(R29=0,"A) "&"---, "&ROUND(($F29/$C8-($R29*$S8))/$T29,2),IF(T29=0,"A) "&ROUND(($F29/$C8)/$R29,2),"A) "&ROUND(($F29/$C8-($T29*$T8))/$R29,2)&", " &ROUND(($F29/$C8-($R29*$S8))/$T29,2)))) | D29: =IF($F8="","",$F8) | E29: =F29*(1-Q29) -> 0 | F29: =Elec_Est!F5460 -> 0 | G29: =C8 -> 1 | H29: =$S8 -> 0 | I29: =$T8 -> 0 | J29: =$D$9 -> 28.833 | R29: =Elec_Est!R5460 -> 0 | T29: =Elec_Est!T5460 -> 0
A30: =IF($F30=0,"",($F30/$C9)-($R30*$S9+$T30*$T9)) | B30: =IF(F30=0,"",IF(R30=0,"A) "&"---, "&ROUND(($F30/$C9-($R30*$S9))/$T30,2),IF(T30=0,"A) "&ROUND(($F30/$C9)/$R30,2),"A) "&ROUND(($F30/$C9-($T30*$T9))/$R30,2)&", " &ROUND(($F30/$C9-($R30*$S9))/$T30,2)))) | D30: =IF($F9="","",$F9) | E30: =F30*(1-Q30) -> 0 | F30: =Elec_Est!F5461 -> 0 | G30: =C9 -> 1 | H30: =$S9 -> 0 | I30: =$T9 -> 0 | J30: =$D$9 -> 28.833 | R30: =Elec_Est!R5461 -> 0 | T30: =Elec_Est!T5461 -> 0
A31: =IF($F31=0,"",($F31/$C10)-($R31*$S10+$T31*$T10)) -> -0.00423 | B31: =IF(F31=0,"",IF(R31=0,"A) "&"---, "&ROUND(($F31/$C10-($R31*$S10))/$T31,2),IF(T31=0,"A) "&ROUND(($F31/$C10)/$R31,2),"A) "&ROUND(($F31/$C10-($T31*$T10))/$R31,2)&", " &ROUND(($F31/$C10-($R31*$S10))/$T31,2)))) -> A) 1.1, 31.71 | D31: =IF($F10="","",$F10) -> Enemalta 3Ph Application | E31: =F31*(1-Q31) -> 1056.6 | F31: =Elec_Est!F5462 -> 1056.6 | G31: =C10 -> 1 | H31: =$S10 -> 1.1 | I31: =$T10 -> 31.7163 | J31: =$D$9 -> 28.833 | R31: =Elec_Est!R5462 -> 900 | T31: =Elec_Est!T5462 -> 2.1
A32: =IF($F32=0,"",($F32/$C11)-($R32*$S11+$T32*$T11)) | B32: =IF(F32=0,"",IF(R32=0,"A) "&"---, "&ROUND(($F32/$C11-($R32*$S11))/$T32,2),IF(T32=0,"A) "&ROUND(($F32/$C11)/$R32,2),"A) "&ROUND(($F32/$C11-($T32*$T11))/$R32,2)&", " &ROUND(($F32/$C11-($R32*$S11))/$T32,2)))) | D32: =IF($F11="","",$F11) | E32: =F32*(1-Q32) -> 0 | F32: =Elec_Est!F5463 -> 0 | G32: =C11 -> 1 | H32: =$S11 -> 0 | I32: =$T11 -> 0 | J32: =$D$9 -> 28.833 | R32: =Elec_Est!R5463 -> 0 | T32: =Elec_Est!T5463 -> 0
C33: MIXED
A35: Discy.L | B35: ='SUMMARY PG'!H233 -> 286398.79 | D35: =B35-E35 -> 0 | E35: =SUM(E23:E32) -> 286398.79 | F35: =SUM(F23:F32) -> 286398.79 | R35: =SUM(R23:R32) -> 162738.81 | T35: =SUM(T23:T32) -> 2607.7695
A36: =IF(A39=0,"0.00",A39-(A38*A37)) -> 0.00 | B36: BOQ TOTAL | E36: ="ESTIM TOTAL (" & $Q$1 & ")" -> ESTIM TOTAL (€)
A37: 1.125 | B37: <1 Actual LabCont | R37: =R166 -> 162742.86 | S37: C.C.Totals | T37: =T166 -> 2606.3322
B38: <2 Phrs @ 1.00
B39: <3 Phrs @ Actual | Q39: Discy.T >> | R39: =R37-R35 -> 4.0513703 | S39: PRINT | T39: =T37-T35 -> -1.4372621
B41: Values Only on : | D41: 45953 | E41: 315655.24 | F41: 315655.24 | R41: 173598.97 | T41: 2779.944
B42: Values Only on : | D42: 45957 | E42: 310694.81 | F42: 310694.81 | R42: 172956 | T42: 2715.044
B43: Values Only on : | D43: 46002 | E43: 310900.8 | F43: 310900.8 | R43: 173103.63 | T43: 2715.594
B44: Values Only on : | D44: 46034 | E44: 301797.2 | F44: 301797.2 | R44: 167814.21 | T44: 2715.594
B45: Values Only on : | D45: 46072 | E45: 286398.79 | F45: 286398.79 | R45: 162738.81 | T45: 2607.7695
B47: Note: The 1% measuring fee is included directly in the client BOQ Summary Page.
A48: REMARKS:
A49: 1) VAT and Duties as above.
A52: ESTIMATOR: | D52: =D8 -> R.Farrugia | Q52: APPROVED BY:
A54: SIGNED: | Q54: DATE APPROVED:
A56: FILE LOCATION: | D56: =CELL("filename") -> https://d.docs.live.net/d8e42587b76b10ba/Documents/Visual Code Studio/Claude/BMS-Attribution-Model/projects/J01111_Brit_Hotel/[EL25_0662B_Brittania_Hotel_Elec_Revised_Estim_B.xlsx]Elec_Est
B58: PANTA CONTRACTING LTD. - ELECTRICAL DIVISION
B59: CONTRACT / VARIATION INPUT DOCUMENT
S60: Copy to:-
D61: Client: | E61: =D1 -> Battery Street Limited | S61: Ms. S. Magri
D62: Project: | E62: =D2 -> MEP Works British Hotel | S62: Mr. K. Micallef
D63: Job Description: | E63: =D3 -> Electrical and ELV Systems | S63: Mr. A. Sciberras
D64: Quote No: | E64: =D4 -> EL25-0662B
D65: Client's Ref: | E65: =D5 -> MEP REVISED
S66: File:-
D67: File No:
D68: Ext. Ref:
E71: Contract /Variation (Excl. VAT)
C73: =IF($A$33="MIXED",F23/(1-Q2)+F24/(1-Q3)+F25/(1-Q4)+F26/(1-Q5)+F27/(1-Q6)+F28/(1-Q7)+F29/(1-Q8)+F30/(1-Q9)+F31/(1-Q10)+F32/(1-Q11)-SUM(A23:A32), F23/(1-Q2)+F24/(1-Q3)+F25/(1-Q4)+F26/(1-Q5)+F27/(1-Q6)+F28/(1-Q7)+F29/(1-Q8)+F30/(1-Q9)+F31/(1-Q10)+F32/(1-Q11)) -> 286398.79 | E73: Estim.Sell before Discounts excl.VAT (€): | F73: =IF(D6="VAT INCLUDED",C73/($C$1*1.18),C73/$C$1) -> 286398.79
E75: Overall Discount: | F75: =(F73-F76)/F73 -> 0
E76: Final Sell after Discounts excl.VAT (€): | F76: =IF(D6="VAT INCLUDED",E35/($C$1*1.18),E35/$C$1) -> 286398.79
E78: Labour Rate - | F78: =$D$9 -> 28.833 | R78: Mech. Cost to us
D81: Mat. Cost | E81: Labour | F81: Total Cost | R81: Sell Excl.VAT / Total Cost
D82: € | E82: Pair.Hrs | F82: €
D84: =R166 -> 162742.86 | E84: =T166 -> 2606.3322 | F84: =R166+S166 -> 237891.24 | R84: =IF(F84=0,0,F76/F84) -> 1.2039064
D85: ( From CostCode Totals )
R88: Advanced Payment:
R89: Retention:
R91: Awarded Date:
R92: Estimated Start Date:
R93: Estimated Completion Date:
D94: .................
D95: A. Sciberras | R95: Date issued:
D96: =NOW() -> 46114.408
D99: PANTA CONTRACTING LTD. - ELECTRICAL DIVISION
D100: ELECTRICAL AND ELV CONTRACT / VARIATION BUDGET COST
D102: Project: | E102: =E62 -> MEP Works British Hotel
D103: Job Desc: | E103: =E63 -> Electrical and ELV Systems
D104: Client's Ref: | E104: =E65 -> MEP REVISED
D107: COSTCODE | F107: Cost | Q107: Mat. | R107: Mat Cost | S107: Lab Cost @ | T107: Labour
F108: Code | Q108: Cont. | R108: € | S108: =$D$9 -> 28.833 | T108: Pair.Hrs
B109: V:56 | D109: BOQ RateOnly Items | P109: FIX | Q109: 1
B110: 1(J) | C110: cc | D110: Erection materials | F110: 501 | P110: 1 | Q110: 1 | R110: =Elec_Est!R5475 -> 772.91671 | S110: =T110*$D$9 -> 1516.394 | T110: =Elec_Est!T5475 -> 52.592308
B111: 2 | C111: cc | D111: Busbar Trunking | F111: 505 | P111: 1 | Q111: 1 | R111: =Elec_Est!R5476 -> 0 | S111: =T111*$D$9 -> 0 | T111: =Elec_Est!T5476 -> 0
B112: 3 | C112: cc | D112: Switchgear | F112: 510 | P112: 2 | Q112: 1 | R112: =Elec_Est!R5477 -> 39380.27 | S112: =T112*$D$9 -> 5292.0088 | T112: =Elec_Est!T5477 -> 183.54
B113: 4 | C113: cc | D113: MCC Equipment | F113: 511 | P113: 2 | Q113: 1 | R113: =Elec_Est!R5478 -> 0 | S113: =T113*$D$9 -> 0 | T113: =Elec_Est!T5478 -> 0
B114: 5 | C114: cc | D114: BMS Equipment | F114: 512 | P114: 2 | Q114: 1 | R114: =Elec_Est!R5479 -> 3180.67 | S114: =T114*$D$9 -> 605.493 | T114: =Elec_Est!T5479 -> 21
B115: 6 | C115: cc | D115: PVC Pipes / Ducts | F115: 520 | P115: 1 | Q115: 1 | R115: =Elec_Est!R5480 -> 0 | S115: =T115*$D$9 -> 0 | T115: =Elec_Est!T5480 -> 0
B116: 7 | C116: cc | D116: High/medium voltage switchgear | F116: 530 | P116: 2 | Q116: 1 | R116: =Elec_Est!R5481 -> 0 | S116: =T116*$D$9 -> 0 | T116: =Elec_Est!T5481 -> 0
B117: 8 | C117: cc | D117: Power Transformers | F117: 550 | P117: 2 | Q117: 1 | R117: =Elec_Est!R5482 -> 0 | S117: =T117*$D$9 -> 0 | T117: =Elec_Est!T5482 -> 0
B118: 9 | C118: cc | D118: Control Panels | F118: 570 | P118: 2 | Q118: 1 | R118: =Elec_Est!R5483 -> 1358.465 | S118: =T118*$D$9 -> 484.3944 | T118: =Elec_Est!T5483 -> 16.8
B119: 10 | C119: cc | D119: Electrical Single Core Cables | F119: 615 | P119: 2 | Q119: 1 | R119: =Elec_Est!R5484 -> 7055.8075 | S119: =T119*$D$9 -> 15193.484 | T119: =Elec_Est!T5484 -> 526.94775
B120: 11(K) | C120: cc | D120: Electrical Multicore Cables | F120: 616 | P120: 2 | Q120: 1 | R120: =Elec_Est!R5485 -> 15341.309 | S120: =T120*$D$9 -> 3493.0891 | T120: =Elec_Est!T5485 -> 121.149
B121: 12 | C121: cc | D121: ELV/BMS/Special Cables | F121: 617 | P121: 2 | Q121: 1 | R121: =Elec_Est!R5486 -> 0 | S121: =T121*$D$9 -> 0 | T121: =Elec_Est!T5486 -> 0
B122: 13 | C122: cc | D122: Cable Accessories | F122: 620 | P122: 2 | Q122: 1 | R122: =Elec_Est!R5487 -> 418.7 | S122: =T122*$D$9 -> 1977.5401 | T122: =Elec_Est!T5487 -> 68.586
B123: 14 | C123: cc | D123: Galv. Cable Trays | F123: 650 | P123: 1 | Q123: 1 | R123: =Elec_Est!R5488 -> 947.64267 | S123: =T123*$D$9 -> 1256.398 | T123: =Elec_Est!T5488 -> 43.575
B124: 15 | C124: cc | D124: PVC Cable Trays | F124: 651 | P124: 1 | Q124: 1 | R124: =Elec_Est!R5489 -> 0 | S124: =T124*$D$9 -> 0 | T124: =Elec_Est!T5489 -> 0
B125: 16 | C125: cc | D125: Galv. Cable Basket | F125: 652 | P125: 1 | Q125: 1 | R125: =Elec_Est!R5490 -> 0 | S125: =T125*$D$9 -> 0 | T125: =Elec_Est!T5490 -> 0
...

Sheet Quote
A1: =IF(AND(UPPER(LEFT(TRIM($D$8),11))="01",UPPER(LEFT(TRIM($D$9),3))<>"ELM"),"PANTA RETAIL LTD.","PANTA CONTRACTING LIMITED") -> PANTA CONTRACTING LIMITED
A2: =IF(UPPER(LEFT(TRIM($D$9),3))="ELM","ELEC-FOR-MECH INTERNAL QUOTATION","ELECTRICAL INTERNAL QUOTATION") -> ELECTRICAL INTERNAL QUOTATION
B5: ATT: | D5: =IF(A2="Internal Quotation", "Mechanical Division","") | R5: Dated: | S5: =NOW() -> 46114.408
B6: CLIENT: | C6: Link to ML_SUM $D1 | D6: =ML_Sum!D1 -> Battery Street Limited
B7: PROJECT: | C7: Link to ML_SUM $D2 | D7: =ML_Sum!D2 -> MEP Works British Hotel
B8: JOB DESC: | C8: Link to ML_SUM $D3 | D8: =ML_Sum!D3 -> Electrical and ELV Systems
B9: QUOTE No: | C9: Link to ML_SUM $D4 | D9: =ML_Sum!D4 -> EL25-0662B
B10: CLIENT's Ref: | C10: Link to ML_SUM $D5 | D10: =ML_Sum!D5 -> MEP REVISED
D22: Selling Price (€) : | E22: =ML_Sum!E35 -> 286398.79 | F22: =ML_Sum!D6 -> VAT EXCL. | G22: VAT EXCLUDED. | H22: VAT EXCLUDED. | I22: VAT EXCLUDED. | J22: VAT EXCLUDED. | K22: VAT EXCLUDED. | L22: VAT EXCLUDED. | M22: VAT EXCLUDED. | N22: VAT EXCLUDED. | O22: VAT EXCLUDED. | P22: VAT EXCLUDED.
A51: Signed for and on behalf of | Q51: Signed for and on behalf of
A52: Electrical Division | Q52: Division
Q54: Records
Q55: Mr. A. Sciberras
Q57: File

Sheet Preliminaries
A1: BILL OF QUANTITIES
A2: PRELIMINARIES
A5: Item | C5: Qty | D5: Unit | E5: Rate in € | F5: Total
A8: 1 | B8: Mobilisation and demobilisation including setting up of workshop storage facilities and their security. | C8: 1 | D8: LS | E8: =Elec_Est!E19 -> 610 | F8: =E8*C8 -> 610
A11: 2 | B11: Safety clothing for all site personnel in accordance with statutory requirements. | C11: 1 | D11: LS | E11: =Elec_Est!Q25 -> Included
A14: 3 | B14: Allowance for weekly progress meetings within project execution period. | C14: 1 | D14: LS | E14: =Elec_Est!Q32 -> Included
A17: 4 | B17: Provision of instrumentation used for commissioning purposes including evidence of associated valid calibration certificates. | C17: 1 | D17: LS | E17: =Elec_Est!Q38 -> Included
A20: 5 | B20: Two copies of a complete set of installation drawings allowing for coordination with sub-contractors, client, interior designer, etc. as applicable. | C20: 1 | D20: LS | E20: =Elec_Est!Q45 -> Included
A23: 6 | B23: Provision for a quality control engineer to ensure that the items being proposed are in accordance with technical specification and will fulfil the project requirements. | C23: 1 | D23: LS | E23: =Elec_Est!Q52 -> Included
A26: 7 | B26: Provision for a Quality Control Engineer to certify that the equipment and materials are installed, tested and commissioned in accordance with manufacturer's recommendations and / or relevant statutory requirements and / or CIBSE and / or equal and approved documents. | C26: 1 | D26: LS | E26: =Elec_Est!Q59 -> Included
A29: 8 | B29: Provision to identify access requirements for maintenance purposes in accordance with manufacturer's guidelines and common practice. | C29: 1 | D29: LS | E29: =Elec_Est!Q65 -> Included
A32: 9 | B32: Provision of signing of commissioning documentation by an independent Warranted Engineer. | C32: 1 | D32: LS | E32: =Elec_Est!E72 -> 1049.2 | F32: =E32*C32 -> 1049.2
A35: 10 | B35: Provision of signing of as-fitted drawings by an independent Warranted Engineer. | C35: 1 | D35: LS | E35: =Elec_Est!E78 -> 585.6 | F35: =E35*C35 -> 585.6
A42: P | B42: Total carried forward to summary page | F42: =SUM(F6:F40) -> 2244.8 | G42: =Elec_Est!F85 -> 2244.8
A48: Item | C48: Qty | D48: Unit | E48: Rate in € | F48: Total
A51: 11 | B51: To allow for builders works in accordance to the preamble section of the technical specifications. | C51: 1 | D51: LS | E51: =Elec_Est!Q90 -> Refer to covering letter.
A54: 12 | B54: Provision for a recognised Health and Safety Officer. | C54: 1 | D54: LS | E54: =Elec_Est!Q97 -> Included
A57: 13 | B57: Provision for completing the necessary risk assessment and method statements required. | C57: 1 | D57: LS | E57: =Elec_Est!E104 -> 2623 | F57: =E57*C57 -> 2623
A60: 14 | B60: Provision for an initial Program of Works and monthly updates | C60: 1 | D60: LS | E60: =Elec_Est!Q111 -> Included
A63: 15 | B63: Provision of Submittal Form for materials and Supply of Samples | C63: 1 | D63: LS | E63: =Elec_Est!Q118 -> Refer to covering letter.
A66: 16 | B66: Provision for Housekeeping and Waste Management | C66: 1 | D66: LS | E66: =Elec_Est!E125 -> 2913.72 | F66: =E66*C66 -> 2913.72
A69: 17 | B69: Provision of Local Council Permits to be charged at cost against receipts | C69: 1 | D69: LS | E69: =Elec_Est!Q132 -> Refer to covering letter.
A97: P | B97: Total carried forward to summary page | F97: =SUM(F49:F95) -> 5536.72 | G97: =Elec_Est!F141 -> 5536.72

Sheet Electrical
A1: BILL OF QUANTITIES
A2: ELECTRICAL SYSTEM
A5: Item | B5: Description | C5: Qty | D5: Unit | E5: Rate in € | F5: Total
A7: T | B7: MAIN INFRASTRUCTURE
A9: T | B9: SWITCHGEAR AND OTHER APPARATUS
A11: 1T | B11: Supply only the following switchgear and other accessories.
A13: a. | B13: Incomer Switchgear Panel SP-INC complete with Shunt Trip and Adjustable Earth Fault Relay | C13: 1 | D13: LS | E13: =Elec_Est!E168 -> 1256.56 | F13: =E13*C13 -> 1256.56
A15: b. | B15: Main Switchgear Panel MSP-NE including Transient Surge Protection | C15: 1 | D15: LS | E15: =Elec_Est!E174 -> 8432.71 | F15: =E15*C15 -> 8432.71
A17: c. | B17: Main Switchgear Panel MSP-ES | C17: 1 | D17: LS | E17: =Elec_Est!E181 -> 15258.49 | F17: =E17*C17 -> 15258.49
A19: d. | B19: 60kVAR Power Factor Correction Unit (PFCU) | C19: 1 | D19: LS | E19: =Elec_Est!E188 -> 4016.24 | F19: =E19*C19 -> 4016.24
A21: e. | B21: Switchgear Panel for Generator SP-GEN including Transient Surge Protection | C21: 1 | D21: LS | E21: =Elec_Est!E194 -> 7182.43 | F21: =E21*C21 -> 7182.43
A24: 2T | B24: Install and connect only the following switchgear and other accessories.
A26: a. | B26: Incomer Switchgear Panel SP-INC complete with Shunt Trip and Adjustable Earth Fault Relay | C26: 1 | D26: LS | E26: =Elec_Est!E204 -> 204.92 | F26: =E26*C26 -> 204.92
A28: b. | B28: Main Switchgear Panel MSP-NE including Transient Surge Protection | C28: 1 | D28: LS | E28: =Elec_Est!E213 -> 940.25 | F28: =E28*C28 -> 940.25
A30: c. | B30: Main Switchgear Panel MSP-ES | C30: 1 | D30: LS | E30: =Elec_Est!E226 -> 1198.79 | F30: =E30*C30 -> 1198.79
A32: d. | B32: 60kVAR Power Factor Correction Unit (PFCU) | C32: 1 | D32: LS | E32: =Elec_Est!E239 -> 462.67 | F32: =E32*C32 -> 462.67
A34: e. | B34: Switchgear Panel for Generator SP-GEN including Transient Surge Protection | C34: 1 | D34: LS | E34: =Elec_Est!E248 -> 915.41 | F34: =E34*C34 -> 915.41
A51: P | B51: Total carried forward to summary page | F51: =SUM(F6:F49) -> 39868.47 | G51: =Elec_Est!F258 -> 39868.47 | H51: =F51-G51 -> 0
A57: Item | B57: Description | C57: Qty | D57: Unit | E57: Rate in € | F57: Total
A59: T | B59: POWER CABLING
A61: 3T | B61: Supply and install the following power cables. Cost is to, include all cable terminations and fixing accessories as, necessary.
A66: a. | B66: From SP-INC to MSP-NE, 2 x (5 core x 70 mm2 ) XLPE/SWA/LSZH/Cu Cable | C66: 35 | D66: m/r | E66: =Elec_Est!E271 -> 124.11 | F66: =E66*C66 -> 4343.85
A69: b. | B69: From SP-GEN to ATS, 2 x (5 core x 50 mm2 ) FG16(O)M16 Cable | C69: 65 | D69: m/r | E69: =Elec_Est!E278 -> 96.07 | F69: =E69*C69 -> 6244.55
A72: c. | B72: From MSP-NE to ATS, 2 x (5 core x 50 mm2 ) FG16(O)M16 Cable | C72: 10 | D72: m/r | E72: =Elec_Est!E285 -> 96.07 | F72: =E72*C72 -> 960.7
A75: d. | B75: From ATS to MSP-ES, 2 x (5 core x 50 mm2 ) FG16(O)M16 Cable | C75: 10 | D75: m/r | E75: =Elec_Est!E292 -> 96.07 | F75: =E75*C75 -> 960.7
A78: e. | B78: From MSP-NE to PFCU, 5 core x 70 mm2 FG16(O)M16 Cable | C78: 10 | D78: m/r | E78: =Elec_Est!E299 -> 73.21 | F78: =E78*C78 -> 732.1
A81: f. | B81: From MSP-NE to DB-OU, 5 core x 25 mm2 FG16(O)M16 Cable | C81: 54 | D81: m/r | E81: =Elec_Est!E306 -> 24.84 | F81: =E81*C81 -> 1341.36
A84: g. | B84: From MSP-NE to Fire Fighting Lift ATS, 5 core x 6.0 mm2 Fire Rated F120 Cable | C84: 55 | D84: m/r | E84: =Elec_Est!E313 -> 23.58 | F84: =E84*C84 -> 1296.9
A87: h. | B87: From SP-GEN to Smoke Fans ATS, 5 core x 6.0 mm2 Fire Rated F120 Cable | C87: 20 | D87: m/r | E87: =Elec_Est!E320 -> 23.58 | F87: =E87*C87 -> 471.6
A90: i. | B90: From SP-GEN to Fire Fighting Lift ATS, 5 core x 6.0 mm2 Fire Rated F120 Cable | C90: 15 | D90: m/r | E90: =Elec_Est!E327 -> 23.58 | F90: =E90*C90 -> 353.7
A93: j. | B93: From MSP-ES to DB-B1, 5 core x 10 mm2 FG16(O)M16 Cable | C93: 13 | D93: m/r | E93: =Elec_Est!E334 -> 13.11 | F93: =E93*C93 -> 170.43
A96: k. | B96: From MSP-ES to DB-K, 5 core x 25 mm2 FG16(O)M16 Cable | C96: 22 | D96: m/r | E96: =Elec_Est!E341 -> 24.84 | F96: =E96*C96 -> 546.48
A99: l. | B99: From MSP-ES to DB-L0, 5 core x 10 mm2 FG16(O)M16 Cable | C99: 7 | D99: m/r | E99: =Elec_Est!E348 -> 13.11 | F99: =E99*C99 -> 91.77
A102: m. | B102: From MSP-ES to DB-L1, 5 core x 10 mm2 FG16(O)M16 Cable | C102: 38 | D102: m/r | E102: =Elec_Est!E355 -> 13.11 | F102: =E102*C102 -> 498.18
A105: n. | B105: From MSP-ES to DB-L2, 5 core x 10 mm2 FG16(O)M16 Cable | C105: 40 | D105: m/r | E105: =Elec_Est!E362 -> 13.11 | F105: =E105*C105 -> 524.4
A109: P | B109: Total carried forward to summary page | F109: =SUM(F58:F107) -> 18536.72 | G109: =Elec_Est!F370 -> 18536.72 | H109: =F109-G109 -> 0
A115: Item | B115: Description | C115: Qty | D115: Unit | E115: Rate in € | F115: Total
A118: o. | B118: From MSP-ES to DB-L3, 5 core x 10 mm2 FG16(O)M16 Cable | C118: 48 | D118: m/r | E118: =Elec_Est!E375 -> 13.11 | F118: =E118*C118 -> 629.28
A121: p. | B121: From MSP-ES to DB-L4, 5 core x 10 mm2 FG16(O)M16 Cable | C121: 51 | D121: m/r | E121: =Elec_Est!E382 -> 13.11 | F121: =E121*C121 -> 668.61
A124: q. | B124: From MSP-ES to DB-L5, 5 core x 10 mm2 FG16(O)M16 Cable | C124: 51 | D124: m/r | E124: =Elec_Est!E389 -> 13.11 | F124: =E124*C124 -> 668.61
A127: r. | B127: From MSP-ES to DB-CA, 5 core x 10 mm2 FG16(O)M16 Cable | C127: 7 | D127: m/r | E127: =Elec_Est!E396 -> 13.11 | F127: =E127*C127 -> 91.77
A130: s. | B130: From MSP-ES to Fire Alarm Panel, 3 core x 2.5 mm2 Fire Rated F120 Cable | C130: 35 | D130: m/r | E130: =Elec_Est!E403 -> 13.4 | F130: =E130*C130 -> 469
A133: t. | B133: From MSP-ES to Fire Damper Control Panel, 3 core x 2.5 mm2 Fire Rated F120 Cable | C133: 35 | D133: m/r | E133: =Elec_Est!E410 -> 13.4 | F133: =E133*C133 -> 469
A136: u. | B136: From MSP-ES to Kitchen Hood Suppression System, 3 core x 2.5 mm2 Fire Rated F120 Cable | C136: 32 | D136: m/r | E136: =Elec_Est!E417 -> 13.4 | F136: =E136*C136 -> 428.8
A139: v. | B139: From MSP-NE to Smoke Fans ATS, 5 core x 6.0 mm2 Fire Rated F120 Cable | C139: 65 | D139: m/r | E139: =Elec_Est!E424 -> 23.58 | F139: =E139*C139 -> 1532.7
A142: T | B142: CABLE MANAGEMENT
A144: 4T | B144: Supply and install the following galvanised steel cable, tray. The cost is to include all bracketing as necessary.
A147: a. | B147: 100mm | C147: 30 | D147: m | E147: =Elec_Est!E439 -> 25.53 | F147: =E147*C147 -> 765.9
A149: b. | B149: 200mm | C149: 30 | D149: m | E149: =Elec_Est!E448 -> 36.52 | F149: =E149*C149 -> 1095.6
A151: c. | B151: 300mm | C151: 10 | D151: m | E151: =Elec_Est!E457 -> 42.77 | F151: =E151*C151 -> 427.7
A153: d. | B153: 400mm | C153: 30 | D153: m | E153: =Elec_Est!E466 -> 51.17 | F153: =E153*C153 -> 1535.1
A155: e. | B155: 500mm | C155: 20 | D155: m | E155: =Elec_Est!E475 -> 57.85 | F155: =E155*C155 -> 1157
A168: P | B168: Total carried forward to summary page | F168: =SUM(F116:F166) -> 9939.07 | G168: =Elec_Est!F485 -> 9939.07 | H168: =F168-G168 -> 0
A174: Item | B174: Description | C174: Qty | D174: Unit | E174: Rate in € | F174: Total
A176: T | B176: BASEMENT LEVEL -1
A178: T | B178: LIGHTING INSTALLATION
A180: 5T | B180: Supply and install the following lighting points as specified. (Moulded Plastic Installation)
A182: a. | B182: One light point controlled by one switch | C182: 1 | D182: No. | E182: =Elec_Est!E502 -> 57.85 | F182: =E182*C182 -> 57.85
A184: b. | B184: Eight light points controlled by one switch | C184: 1 | D184: No. | E184: =Elec_Est!E509 -> 260.34 | F184: =E184*C184 -> 260.34
A186: c. | B186: One light point controlled by two two-way switches | C186: 1 | D186: No. | E186: =Elec_Est!E516 -> 86.78 | F186: =E186*C186 -> 86.78
A188: d. | B188: Two light points controlled by two two-way switches | C188: 1 | D188: No. | E188: =Elec_Est!E523 -> 115.71 | F188: =E188*C188 -> 115.71
A190: e. | B190: Four light points controlled by two two-way switches | C190: 1 | D190: No. | E190: =Elec_Est!E530 -> 173.56 | F190: =E190*C190 -> 173.56
A192: f. | B192: One light point controlled by one movement detector | C192: 3 | D192: No. | E192: =Elec_Est!E537 -> 88.56 | F192: =E192*C192 -> 265.68
A194: g. | B194: Two light points controlled by one movement detector | C194: 2 | D194: No. | E194: =Elec_Est!E546 -> 117.48 | F194: =E194*C194 -> 234.96
A196: h. | B196: Three light points and one extractor fan controlled by one movement detector | C196: 1 | D196: No. | E196: =Elec_Est!E555 -> 175.34 | F196: =E196*C196 -> 175.34
A198: i. | B198: Four light points controlled by one movement detector | C198: 1 | D198: No. | E198: =Elec_Est!E564 -> 175.34 | F198: =E198*C198 -> 175.34
A200: j. | B200: Maintained emergency light points | C200: 6 | D200: No. | E200: =Elec_Est!E573 -> 57.85 | F200: =E200*C200 -> 347.1
A203: 6T | B203: Supply only the following light fittings and accessories
A205: a. | B205: 600mm x 600mm, 40W Soffit Recessed LED Panel | C205: 8 | D205: No. | E205: =Elec_Est!E584 -> 43.07 | F205: =E205*C205 -> 344.56
A207: b. | B207: Type 'E1' - Single Sided, Wall Mounted, Directional Exit Signage | C207: 5 | D207: No. | E207: =Elec_Est!E591 -> 28.98 | F207: =E207*C207 -> 144.9
A209: c. | B209: Type 'E2' - Double Sided, Ceiling Mounted/ Soffit Recessed, Directional Exit Signage | C209: 1 | D209: No. | E209: =Elec_Est!E598 -> 43.86 | F209: =E209*C209 -> 43.86
A211: d. | B211: Battery Backup Kit for Type 'LT-02' and Type 'LT-15' | C211: 7 | D211: No. | E211: =Elec_Est!Q605 -> No Quote
A214: 7T | B214: Install and connect only the following light fittings and accessories. Light Fittings to be supplied by client.
A216: a. | B216: Type 'LT-02' - 11W Soffit Recessed Light Fitting | C216: 4 | D216: No. | E216: =Elec_Est!E616 -> 14.36 | F216: =E216*C216 -> 57.44
A218: b. | B218: Type 'LT-03' - Wall Light | C218: 2 | D218: No. | E218: =Elec_Est!E623 -> 11.35 | F218: =E218*C218 -> 22.7
A220: c. | B220: Type 'LT-15' - 8.5W Soffit Recessed Downlighter | C220: 8 | D220: No. | E220: =Elec_Est!E630 -> 14.36 | F220: =E220*C220 -> 114.88
A223: P | B223: Total carried forward to summary page | F223: =SUM(F175:F221) -> 2621 | G223: =Elec_Est!F638 -> 2621 | H223: =F223-G223 -> 0
A229: Item | B229: Description | C229: Qty | D229: Unit | E229: Rate in € | F229: Total
A231: d. | B231: Type 'LT-16' - 8.5W Soffit Recessed Downlighter | C231: 1 | D231: No. | E231: =Elec_Est!E643 -> 14.36 | F231: =E231*C231 -> 14.36
A233: e. | B233: Type ' LD-11' - Hallway Wall Light | C233: 4 | D233: No. | E233: =Elec_Est!E650 -> 11.35 | F233: =E233*C233 -> 45.4
A235: f. | B235: Type 'LD-16' - Toilets Wall Light | C235: 3 | D235: No. | E235: =Elec_Est!E657 -> 11.35 | F235: =E235*C235 -> 34.05
A237: g. | B237: 600mm x 600mm, 40W Soffit Recessed LED Panel | C237: 8 | D237: No. | E237: =Elec_Est!E664 -> 21.74 | F237: =E237*C237 -> 173.92
A239: h. | B239: Type 'E1' - Single Sided, Wall Mounted, Directional Exit Signage | C239: 5 | D239: No. | E239: =Elec_Est!E671 -> 13.21 | F239: =E239*C239 -> 66.05
A241: i. | B241: Type 'E2' - Double Sided, Ceiling Mounted/ Soffit Recessed, Directional Exit Signage | C241: 1 | D241: No. | E241: =Elec_Est!E678 -> 17.87 | F241: =E241*C241 -> 17.87
A243: j. | B243: Battery Backup Kit for Type 'LT-02' and Type 'LT-15' | C243: 7 | D243: No. | E243: =Elec_Est!E685 -> 16.12 | F243: =E243*C243 -> 112.84
A246: T | B246: POWER INSTALLATION
A248: 8T | B248: Supply and install the following power points in LSZH, conduit chased in wall.
A251: a. | B251: 13Amp BS1363 Single Socket Outlet | C251: 6 | D251: No. | E251: =Elec_Est!E700 -> 77.31 | F251: =E251*C251 -> 463.86
A253: b. | B253: 13Amp BS1363 Double Socket Outlet | C253: 3 | D253: No. | E253: =Elec_Est!E708 -> 79.36 | F253: =E253*C253 -> 238.08
A255: c. | B255: 13Amp BS1363 Double Socket Outlet complete with Type 'A' and Type 'C' USBs | C255: 2 | D255: No. | E255: =Elec_Est!E716 -> 119.8 | F255: =E255*C255 -> 239.6
A257: d. | B257: 13Amp BS1363 Weatherproof Double Socket Outlet | C257: 10 | D257: No. | E257: =Elec_Est!E724 -> 115.17 | F257: =E257*C257 -> 1151.7
A259: e. | B259: 13Amp Switched Fuse Connection Unit | C259: 6 | D259: No. | E259: =Elec_Est!E732 -> 79.88 | F259: =E259*C259 -> 479.28
A261: f. | B261: 13Amp Unswitched Fuse Connection Unit | C261: 6 | D261: No. | E261: =Elec_Est!E740 -> 79.88 | F261: =E261*C261 -> 479.28
A264: T | B264: SWITCHGEAR AND OTHER APPARATUS
A266: 9 | B266: Supply only the following switchgear and other accessories.
A268: a. | B268: Distribution Board DB-B1 in Staff Area Corridor | C268: 1 | D268: No. | E268: =Elec_Est!E756 -> 996.39 | F268: =E268*C268 -> 996.39
A270: b. | B270: Distribution Board DB-K in Kitchen | C270: 1 | D270: No. | E270: =Elec_Est!E762 -> 947.59 | F270: =E270*C270 -> 947.59
A272: c. | B272: 16Amp Double Pole Rotary Isolator, IP65 | C272: 6 | D272: No. | E272: =Elec_Est!E768 -> 23.42 | F272: =E272*C272 -> 140.52
A274: d. | B274: 16Amp Four Pole Rotary Isolator, IP65 | C274: 2 | D274: No. | E274: =Elec_Est!E774 -> 25.03 | F274: =E274*C274 -> 50.06
A279: P | B279: Total carried forward to summary page | F279: =SUM(F230:F277) -> 5650.85 | G279: =Elec_Est!F781 -> 5650.85 | H279: =F279-G279 -> 0
...

Sheet Emergency Standby Generator
A1: BILL OF QUANTITIES
A2: EMERGENCY STANDBY GENERATOR
A5: Item | C5: Qty | D5: Unit | E5: Rate in € | F5: Total
A8: 1 | B8: Supply, deliver to site and place in its final location one prime rated power (PRP) 135kVA/ 400V/ 50Hz, diesel auto start stand-by generator set, complete as specified (excluding cost of ATS) | C8: 1 | D8: No. | E8: =Elec_Est!E4243 -> 24912.4 | F8: =E8*C8 -> 24912.4
A14: 2 | B14: Install, test and commission the 135kVA/ 400V/ 50Hz prime rated power (PRP) Generator Set, and associated switchgear in accordance with manufacturer's instructions and Enemalta Corporation Regulations, , Cost shall include all the necessary small power (battery charging) and control cables between the generator set and the ATS change-over panel, complete as specified., All commissioning documentation is to be certified for correctness and signed by a Warranted Engineer. | C14: 1 | D14: LS | E14: =Elec_Est!E4251 -> 1265.03 | F14: =E14*C14 -> 1265.03
A17: 3 | B17: Supply and deliver to site 250Amp TPN Automatic Transfer Switch (ATS) | C17: 1 | D17: No. | E17: =Elec_Est!E4262 -> 1220 | F17: =E17*C17 -> 1220
A20: 4 | B20: Install and connect 250Amp TPN Automatic Transfer Switch (ATS) | C20: 1 | D20: No. | E20: =Elec_Est!E4268 -> 161.74 | F20: =E20*C20 -> 161.74
A48: P | B48: Total carried forward to summary page | F48: =SUM(F6:F46) -> 27559.17 | G48: =Elec_Est!F4278 -> 27559.17

Sheet FIRE STOPPING
A1: BILL OF QUANTITIES
A2: FIRE STOPPING
A5: Item | C5: Qty | D5: Unit | E5: Rate in € | F5: Total
A7: 1 | B7: Fire barrier provisions to maintain fire compartmentation as required around and within all M&E services. Contractor to provide itemised cost breakdown under this sheet. | C7: 1 | D7: LS | E7: =Elec_Est!E4293 -> 2293.18 | F7: =E7*C7 -> 2293.18
A56: P | B56: Total carried forward to summary page | F56: =SUM(F6:F54) -> 2293.18 | G56: =Elec_Est!F4307 -> 2293.18

Sheet Fire Detection
A1: BILL OF QUANTITIES
A2: FIRE DETECTION & ALARM SYSTEM
A5: Item | C5: Qty | D5: Unit | E5: Rate in € | F5: Total
A7: T | B7: FIRE DETECTION AND ALARM
A9: T | B9: Supply, install, connect, test, commission and certify the following:
A11: T | B11: Basement Level -1
A13: 1 | B13: Analogue addressable optical smoke detectors c/w base | C13: 24 | D13: No. | E13: =Elec_Est!E4330 -> 62.88 | F13: =E13*C13 -> 1509.12
A16: =A13+1 -> 2 | B16: Analogue addressable optical smoke detectors c/w base sounder | C16: 1 | D16: No. | E16: =Elec_Est!E4336 -> 100.53 | F16: =E16*C16 -> 100.53
A19: =A16+1 -> 3 | B19: Analogue addressable heat detectors c/w base | C19: 3 | D19: No. | E19: =Elec_Est!E4342 -> 62.82 | F19: =E19*C19 -> 188.46
A22: =A19+1 -> 4 | B22: Open area sounder plus beacon | C22: 1 | D22: No. | E22: =Elec_Est!E4348 -> 162.55 | F22: =E22*C22 -> 162.55
A25: =A22+1 -> 5 | B25: Remote LED Alarm Indicators | C25: 21 | D25: No. | E25: =Elec_Est!E4354 -> 32.67 | F25: =E25*C25 -> 686.07
A28: =A25+1 -> 6 | B28: Manual call points as specified | C28: 2 | D28: No. | E28: =Elec_Est!E4360 -> 90.3 | F28: =E28*C28 -> 180.6
A31: =A28+1 -> 7 | B31: Interface modules | C31: 3 | D31: No. | E31: =Elec_Est!E4376 -> 341.21 | F31: =E31*C31 -> 1023.63
A34: =A31+1 -> 8 | B34: Cabling in 'Standard' fire alarm cable | C34: 120 | D34: m | E34: =Elec_Est!E4392 -> 10.78 | F34: =E34*C34 -> 1293.6
A37: =A34+1 -> 9 | B37: Fire Blanket | C37: 3 | D37: No. | E37: =Elec_Est!E4398 -> 23.5 | F37: =E37*C37 -> 70.5
A40: T | B40: GROUND FLOOR
A42: =A37+1 -> 10 | B42: Four loop analogue addressable fire alarm control panel, c/w auto dialer, power supply unit & backup batteries | C42: 1 | D42: No. | E42: =Elec_Est!E4408 -> 4117.53 | F42: =E42*C42 -> 4117.53
A45: =A42+1 -> 11 | B45: Analogue addressable optical smoke detectors c/w base | C45: 17 | D45: No. | E45: =Elec_Est!E4424 -> 62.88 | F45: =E45*C45 -> 1068.96
A56: P | B56: Total carried forward to summary page | F56: =SUM(F6:F54) -> 10401.55 | G56: =Elec_Est!F4431 -> 10401.55
A62: Item | B62: Description | C62: Qty | D62: Unit | E62: Rate in € | F62: Total
A64: =A45+1 -> 12 | B64: Analogue addressable optical smoke detectors c/w base sounder | C64: 4 | D64: No. | E64: =Elec_Est!E4436 -> 100.53 | F64: =E64*C64 -> 402.12
A67: =A64+1 -> 13 | B67: Remote LED Alarm Indicators | C67: 9 | D67: No. | E67: =Elec_Est!E4442 -> 32.67 | F67: =E67*C67 -> 294.03
A70: =A67+1 -> 14 | B70: Manual call points as specified | C70: 3 | D70: No. | E70: =Elec_Est!E4448 -> 90.29 | F70: =E70*C70 -> 270.87
A73: =A70+1 -> 15 | B73: Interface modules | C73: 4 | D73: No. | E73: =Elec_Est!E4464 -> 341.22 | F73: =E73*C73 -> 1364.88
A76: =A73+1 -> 16 | B76: Cabling in 'Standard' fire alarm cable | C76: 160 | D76: m | E76: =Elec_Est!E4480 -> 10.78 | F76: =E76*C76 -> 1724.8
A79: =A76+1 -> 17 | B79: Magnetic Door Holders | C79: 4 | D79: No. | E79: =Elec_Est!E4486 -> 143.14 | F79: =E79*C79 -> 572.56
A82: T | B82: FIRST FLOOR
A85: =A79+1 -> 18 | B85: Analogue addressable optical smoke detectors c/w base | C85: 11 | D85: No. | E85: =Elec_Est!E4506 -> 62.88 | F85: =E85*C85 -> 691.68
A88: =A85+1 -> 19 | B88: Analogue addressable optical smoke detectors c/w base sounder | C88: 4 | D88: No. | E88: =Elec_Est!E4512 -> 100.53 | F88: =E88*C88 -> 402.12
A91: =A88+1 -> 20 | B91: Open area sounder plus beacon | C91: 1 | D91: No. | E91: =Elec_Est!E4518 -> 162.55 | F91: =E91*C91 -> 162.55
A94: =A91+1 -> 21 | B94: Remote LED Alarm Indicators | C94: 4 | D94: No. | E94: =Elec_Est!E4524 -> 32.67 | F94: =E94*C94 -> 130.68
A97: =A94+1 -> 22 | B97: Manual call points as specified | C97: 2 | D97: No. | E97: =Elec_Est!E4530 -> 90.3 | F97: =E97*C97 -> 180.6
A100: =A97+1 -> 23 | B100: Interface modules | C100: 1 | D100: No. | E100: =Elec_Est!E4546 -> 341.22 | F100: =E100*C100 -> 341.22
A103: =A100+1 -> 24 | B103: Cabling in 'Standard' fire alarm cable | C103: 120 | D103: m | E103: =Elec_Est!E4562 -> 10.78 | F103: =E103*C103 -> 1293.6
A106: =A103+1 -> 25 | B106: Magnetic Door Holders | C106: 4 | D106: No. | E106: =Elec_Est!E4568 -> 143.14 | F106: =E106*C106 -> 572.56
A114: P | B114: Total carried forward to summary page | F114: =SUM(F63:F112) -> 8404.27 | G114: =Elec_Est!F4585 -> 8404.27
A120: Item | B120: Description | C120: Qty | D120: Unit | E120: Rate in € | F120: Total
A122: T | B122: SECOND FLOOR
A124: =A106+1 -> 26 | B124: Analogue addressable optical smoke detectors c/w base | C124: 13 | D124: No. | E124: =Elec_Est!E4594 -> 62.88 | F124: =E124*C124 -> 817.44
A127: =A124+1 -> 27 | B127: Analogue addressable optical smoke detectors c/w base sounder | C127: 4 | D127: No. | E127: =Elec_Est!E4600 -> 100.53 | F127: =E127*C127 -> 402.12
A130: =A127+1 -> 28 | B130: Remote LED Alarm Indicators | C130: 6 | D130: No. | E130: =Elec_Est!E4606 -> 32.67 | F130: =E130*C130 -> 196.02
A133: =A130+1 -> 29 | B133: Manual call points as specified | C133: 2 | D133: No. | E133: =Elec_Est!E4612 -> 90.3 | F133: =E133*C133 -> 180.6
A136: =A133+1 -> 30 | B136: Interface modules | C136: 1 | D136: No. | E136: =Elec_Est!E4628 -> 341.22 | F136: =E136*C136 -> 341.22
A139: =A136+1 -> 31 | B139: Cabling in 'Standard' fire alarm cable | C139: 120 | D139: m | E139: =Elec_Est!E4644 -> 10.78 | F139: =E139*C139 -> 1293.6
A142: =A139+1 -> 32 | B142: Magnetic Door Holders | C142: 3 | D142: No. | E142: =Elec_Est!E4650 -> 143.14 | F142: =E142*C142 -> 429.42
A145: T | B145: THIRD FLOOR
A147: =A142+1 -> 33 | B147: Analogue addressable optical smoke detectors c/w base | C147: 18 | D147: No. | E147: =Elec_Est!E4670 -> 62.88 | F147: =E147*C147 -> 1131.84
A150: =A147+1 -> 34 | B150: Analogue addressable optical smoke detectors c/w base sounder | C150: 4 | D150: No. | E150: =Elec_Est!E4676 -> 100.53 | F150: =E150*C150 -> 402.12
A153: =A150+1 -> 35 | B153: Remote LED Alarm Indicators | C153: 10 | D153: No. | E153: =Elec_Est!E4682 -> 32.67 | F153: =E153*C153 -> 326.7
A156: =A153+1 -> 36 | B156: Manual call points as specified | C156: 1 | D156: No. | E156: =Elec_Est!E4688 -> 90.3 | F156: =E156*C156 -> 90.3
A159: =A156+1 -> 37 | B159: Interface modules | C159: 1 | D159: No. | E159: =Elec_Est!E4704 -> 341.22 | F159: =E159*C159 -> 341.22
A172: P | B172: Total carried forward to summary page | F172: =SUM(F121:F170) -> 5952.6 | G172: =Elec_Est!F4721 -> 5952.6
A178: Item | B178: Description | C178: Qty | D178: Unit | E178: Rate in € | F178: Total
A180: =A159+1 -> 38 | B180: Cabling in 'Standard' fire alarm cable | C180: 120 | D180: m | E180: =Elec_Est!E4726 -> 10.78 | F180: =E180*C180 -> 1293.6
A183: =A180+1 -> 39 | B183: Magnetic Door Holders | C183: 3 | D183: No. | E183: =Elec_Est!E4732 -> 143.14 | F183: =E183*C183 -> 429.42
A186: T | B186: FOURTH FLOOR
A189: =A183+1 -> 40 | B189: Analogue addressable optical smoke detectors c/w base | C189: 10 | D189: No. | E189: =Elec_Est!E4752 -> 62.88 | F189: =E189*C189 -> 628.8
A192: =A189+1 -> 41 | B192: Analogue addressable optical smoke detectors c/w base sounder | C192: 4 | D192: No. | E192: =Elec_Est!E4758 -> 100.53 | F192: =E192*C192 -> 402.12
A195: =A192+1 -> 42 | B195: Remote LED Alarm Indicators | C195: 3 | D195: No. | E195: =Elec_Est!E4764 -> 32.67 | F195: =E195*C195 -> 98.01
A198: =A195+1 -> 43 | B198: Manual call points as specified | C198: 1 | D198: No. | E198: =Elec_Est!E4770 -> 90.3 | F198: =E198*C198 -> 90.3
A201: =A198+1 -> 44 | B201: Interface modules | C201: 1 | D201: No. | E201: =Elec_Est!E4786 -> 341.22 | F201: =E201*C201 -> 341.22
A204: =A201+1 -> 45 | B204: Cabling in 'Standard' fire alarm cable | C204: 120 | D204: m | E204: =Elec_Est!E4802 -> 10.78 | F204: =E204*C204 -> 1293.6
A207: =A204+1 -> 46 | B207: Magnetic Door Holders | C207: 3 | D207: No. | E207: =Elec_Est!E4808 -> 143.14 | F207: =E207*C207 -> 429.42
A210: T | B210: FIFTH FLOOR
A213: =A207+1 -> 47 | B213: Analogue addressable optical smoke detectors c/w base | C213: 12 | D213: No. | E213: =Elec_Est!E4828 -> 62.88 | F213: =E213*C213 -> 754.56
A216: =A213+1 -> 48 | B216: Analogue addressable optical smoke detectors c/w base sounder | C216: 2 | D216: No. | E216: =Elec_Est!E4834 -> 100.53 | F216: =E216*C216 -> 201.06
A219: =A216+1 -> 49 | B219: Analogue addressable heat detectors c/w base | C219: 1 | D219: No. | E219: =Elec_Est!E4840 -> 62.82 | F219: =E219*C219 -> 62.82
A222: =A219+1 -> 50 | B222: Remote LED Alarm Indicators | C222: 6 | D222: No. | E222: =Elec_Est!E4846 -> 32.67 | F222: =E222*C222 -> 196.02
A225: =A222+1 -> 51 | B225: Manual call points as specified | C225: 1 | D225: No. | E225: =Elec_Est!E4852 -> 90.3 | F225: =E225*C225 -> 90.3
A230: P | B230: Total carried forward to summary page | F230: =SUM(F179:F228) -> 6311.25 | G230: =Elec_Est!F4869 -> 6311.25
A236: Item | B236: Description | C236: Qty | D236: Unit | E236: Rate in € | F236: Total
A238: =A225+1 -> 52 | B238: Interface modules | C238: 2 | D238: No. | E238: =Elec_Est!E4874 -> 341.22 | F238: =E238*C238 -> 682.44
A241: =A238+1 -> 53 | B241: Cabling in 'Standard' fire alarm cable | C241: 100 | D241: m | E241: =Elec_Est!E4890 -> 10.78 | F241: =E241*C241 -> 1078
A244: =A241+1 -> 54 | B244: Fire Blanket | C244: 1 | D244: No. | E244: =Elec_Est!E4896 -> 23.5 | F244: =E244*C244 -> 23.5
A247: T | B247: Nurse Call System
A249: 55 | B249: Nurse Call system to be interfaced with Fire Alarm System including Pull Chord, Reset Button, etc. | C249: 2 | D249: No. | E249: =Elec_Est!E4906 -> 636.77 | F249: =E249*C249 -> 1273.54
A288: P | B288: Total carried forward to summary page | F288: =SUM(F237:F286) -> 3057.48 | G288: =Elec_Est!F4923 -> 3057.48

Sheet CCTV
A1: BILL OF QUANTITIES
A2: CCTV SYSTEM
A5: Item | C5: Qty | D5: Unit | E5: Rate in € | F5: Total
A7: T | B7: IP CCTV SYSTEM
A9: T | B9: Supply, install, connect, test, commission and certify the following:
A11: T | B11: Basement Level -1
A13: 1 | B13: IP Dome Cameras | C13: 1 | D13: No. | E13: =Elec_Est!E4950 -> 183.5 | F13: =E13*C13 -> 183.5
A16: T | B16: Ground Floor
A19: =A13+1 -> 2 | B19: IP Dome Cameras | C19: 3 | D19: No. | E19: =Elec_Est!E4960 -> 183.5 | F19: =E19*C19 -> 550.5
A22: =A19+1 -> 3 | B22: External type IP Dome Cameras | C22: 2 | D22: No. | E22: =Elec_Est!E4966 -> 202.32 | F22: =E22*C22 -> 404.64
A25: =A22+1 -> 4 | B25: 16-Channel Network Video Recorder (NVR) with PoE ports | C25: 1 | D25: No. | E25: =Elec_Est!E4972 -> 803.46 | F25: =E25*C25 -> 803.46
A28: T | B28: First Floor
A31: =A25+1 -> 5 | B31: External type IP Dome Cameras | C31: 2 | D31: No. | E31: =Elec_Est!E4982 -> 202.32 | F31: =E31*C31 -> 404.64
A34: T | B34: Fifth Floor
A37: =A31+1 -> 6 | B37: IP Dome Cameras | C37: 1 | D37: No. | E37: =Elec_Est!E4992 -> 183.5 | F37: =E37*C37 -> 183.5
A42: T | B42: Note: Data points for CCTV are included in the data bill.
A57: P | B57: Total carried forward to summary page | F57: =SUM(F6:F55) -> 2530.24 | G57: =Elec_Est!F5003 -> 2530.24

Sheet Structured Cabling
A1: BILL OF QUANTITIES
A2: STRUCTURED CABLING
A5: Item | C5: Qty | D5: Unit | E5: Rate in € | F5: Total
A7: T | B7: STRUCTURED CABLING
A9: T | B9: Supply, install, connect, test, commission and certify the following:
A11: T | B11: Basement Level -1
A13: 1 | B13: RJ45 Cat 6 Single socket outlets. | C13: 2 | D13: No. | E13: =Elec_Est!E5026 -> 66.71 | F13: =E13*C13 -> 133.42
A16: =A13+1 -> 2 | B16: RJ45 Cat 6 Double socket outlets. | C16: 1 | D16: No. | E16: =Elec_Est!E5042 -> 77.71 | F16: =E16*C16 -> 77.71
A19: =A16+1 -> 3 | B19: Cat 6 cable from patch panel cabinet to data points | C19: 60 | D19: m | E19: =Elec_Est!E5058 -> 1.1 | F19: =E19*C19 -> 66
A22: T | B22: Ground Floor
A25: =A19+1 -> 4 | B25: 20U 600x600mm Floor Standing Data Cabinet | C25: 1 | D25: No. | E25: =Elec_Est!E5068 -> 990 | F25: =E25*C25 -> 990
A28: =A25+1 -> 5 | B28: Rack mount 24 port RJ45 Cat 6 patch panel | C28: 4 | D28: No. | E28: =Elec_Est!E5074 -> 82.5 | F28: =E28*C28 -> 330
A31: =A28+1 -> 6 | B31: 19" 1U Patchcord management panel | C31: 7 | D31: No. | E31: =Elec_Est!E5080 -> 16.5 | F31: =E31*C31 -> 115.5
A34: =A31+1 -> 7 | B34: Rack mount power distribution unit with 6No. 13Amp BS socket outlets, including in built surge protection | C34: 1 | D34: No. | E34: =Elec_Est!E5086 -> 71.5 | F34: =E34*C34 -> 71.5
A37: =A34+1 -> 8 | B37: RJ45 Cat 6 Single socket outlets. | C37: 7 | D37: No. | E37: =Elec_Est!E5092 -> 66.71 | F37: =E37*C37 -> 466.97
A40: =A37+1 -> 9 | B40: RJ45 Cat 6 Double socket outlets. | C40: 2 | D40: No. | E40: =Elec_Est!E5108 -> 77.71 | F40: =E40*C40 -> 155.42
A43: =A40+1 -> 10 | B43: Cat 6 cable from patch panel cabinet to data points | C43: 320 | D43: m | E43: =Elec_Est!E5124 -> 1.1 | F43: =E43*C43 -> 352
A57: P | B57: Total carried forward to summary page | F57: =SUM(F6:F55) -> 2758.52 | G57: =Elec_Est!F5131 -> 2758.52
A63: Item | B63: Description | C63: Qty | D63: Unit | E63: Rate in € | F63: Total
A65: T | B65: First Floor
A67: =A43+1 -> 11 | B67: RJ45 Cat 6 Single socket outlets. | C67: 14 | D67: No. | E67: =Elec_Est!E5140 -> 66.71 | F67: =E67*C67 -> 933.94
A70: =A67+1 -> 12 | B70: Cat 6 cable from patch panel cabinet to data points | C70: 435 | D70: m | E70: =Elec_Est!E5156 -> 1.1 | F70: =E70*C70 -> 478.5
A73: T | B73: Second Floor
A75: =A70+1 -> 13 | B75: RJ45 Cat 6 Single socket outlets. | C75: 11 | D75: No. | E75: =Elec_Est!E5166 -> 66.71 | F75: =E75*C75 -> 733.81
A78: =A75+1 -> 14 | B78: RJ45 Cat 6 Double socket outlets. | C78: 3 | D78: No. | E78: =Elec_Est!E5182 -> 77.71 | F78: =E78*C78 -> 233.13
A81: =A78+1 -> 15 | B81: Cat 6 cable from patch panel cabinet to data points | C81: 765 | D81: m | E81: =Elec_Est!E5198 -> 1.1 | F81: =E81*C81 -> 841.5
A84: T | B84: Third Floor
A86: =A81+1 -> 16 | B86: RJ45 Cat 6 Single socket outlets. | C86: 11 | D86: No. | E86: =Elec_Est!E5208 -> 66.71 | F86: =E86*C86 -> 733.81
A89: =A86+1 -> 17 | B89: Cat 6 cable from patch panel cabinet to data points | C89: 470 | D89: m | E89: =Elec_Est!E5224 -> 1.1 | F89: =E89*C89 -> 517
A92: T | B92: Fourth Floor
A94: =A89+1 -> 18 | B94: RJ45 Cat 6 Single socket outlets. | C94: 11 | D94: No. | E94: =Elec_Est!E5234 -> 66.71 | F94: =E94*C94 -> 733.81
A97: =A94+1 -> 19 | B97: Cat 6 cable from patch panel cabinet to data points | C97: 535 | D97: m | E97: =Elec_Est!E5250 -> 1.1 | F97: =E97*C97 -> 588.5
A100: T | B100: Fifth Floor
A102: =A97+1 -> 20 | B102: RJ45 Cat 6 Single socket outlets. | C102: 9 | D102: No. | E102: =Elec_Est!E5260 -> 66.71 | F102: =E102*C102 -> 600.39
A105: =A102+1 -> 21 | B105: Cat 6 cable from patch panel cabinet to data points | C105: 440 | D105: m | E105: =Elec_Est!E5276 -> 1.1 | F105: =E105*C105 -> 484
A117: P | B117: Total carried forward to summary page | F117: =SUM(F64:F115) -> 6878.39 | G117: =Elec_Est!F5283 -> 6878.39

Sheet Access Control
A1: BILL OF QUANTITIES
A2: ACCESS CONTROL
A5: Item | C5: Qty | D5: Unit | E5: Rate in € | F5: Total
A7: T | B7: ACCESS CONTROL
A9: T | B9: Supply, install, connect, test, commission and certify the following:
A11: 1 | B11: Main Controller, inclusive of Software License Module including any licenses for the door readers, contacts etc. for a complete working solution. | C11: 1 | D11: LS | E11: =Elec_Est!E5306 -> 3424.43 | F11: =E11*C11 -> 3424.43
A14: 2 | B14: Proximity Card Reader | C14: 7 | D14: No. | E14: =Elec_Est!E5312 -> 335.79 | F14: =E14*C14 -> 2350.53
A17: 3 | B17: Magnetic Lock | C17: 7 | D17: No. | E17: =Elec_Est!E5328 -> 151.88 | F17: =E17*C17 -> 1063.16
A20: 4 | B20: Door Release Button | C20: 7 | D20: No. | E20: =Elec_Est!E5344 -> 125.6 | F20: =E20*C20 -> 879.2
A23: 5 | B23: Cabling as necessary | C23: 1 | D23: LS | E23: =Elec_Est!E5360 -> 2569.18 | F23: =E23*C23 -> 2569.18
A26: 6 | B26: Access control cards | C26: 15 | D26: No. | E26: =Elec_Est!E5366 -> 6.47 | F26: =E26*C26 -> 97.05
A55: P | B55: Total carried forward to summary page | F55: =SUM(F6:F53) -> 10383.55 | G55: =Elec_Est!F5373 -> 10383.55

Sheet AC cut-out switches
A1: BILL OF QUANTITIES
A2: AC CUT-OUT SWITCHES
A5: Item | C5: Qty | D5: Unit | E5: Rate in € | F5: Total
A7: T | B7: AC CUT-OUT SWITCHES
A9: T | B9: Supply, install, connect, test, commission and certify the following:
A11: 1 | B11: Magnetic reed switch set (normally closed) for windows and doors, surface mount type, suitable for integration with AC cut-off control system | C11: 16 | D11: No. | E11: =Elec_Est!E5392 -> 21.43 | F11: =E11*C11 -> 342.88
A14: 2 | B14: Low voltage control cable for signal connection between switches and AC thermostat | C14: 16 | D14: No. | E14: =Elec_Est!E5398 -> 43.23 | F14: =E14*C14 -> 691.68
A55: P | B55: Total carried forward to summary page | F55: =SUM(F6:F53) -> 1034.56 | G55: =Elec_Est!F5406 -> 1034.56

Sheet COMMISSIONING
A1: BILL OF QUANTITIES
A2: COMMISSIONING AND DOCUMENTATION
A5: Item | C5: Qty | D5: Unit | E5: Rate in € | F5: Total
A8: 1 | B8: Carry out all necessary testing and commissioning to the satisfaction of the Engineer. All commissioning documentation is to be certified for correctness and signed by a Warranted Engineer. | C8: 1 | D8: LS | E8: =Elec_Est!Q5421 -> Included
A11: 2 | B11: Provide sufficient training on the operation and maintenance of all plant and systems to the Employer's representatives. | C11: 1 | D11: LS | E11: =Elec_Est!Q5428 -> Included
A14: 3 | B14: Supply and hand-over two complete sets of operation and maintenance manuals together with drawings of works "As Fitted". These shall include: wiring diagrams; test / commissioning data and certificates; equipment data, including manufacturer's details, schedules, specifications and selection / performance data and parts lists. In addition an electronic copy of the "As Fitted" drawings and manuals are to be furnished in both ACAD and pdf format. (An unlocked electronic version of the tender drawings as listed in the 'List of Drawings' can be made available to the successful Tenderer who is awarded the contract against a fee of 0.2% of the contract value or a minimum charge of €30 excluding VAT, which ever is the greatest). | C14: 1 | D14: LS | E14: =Elec_Est!Q5435 -> Included
A39: P | B39: Total carried forward to summary page | F39: =SUM(F6:F37) -> 0 | G39: =Elec_Est!F5443 -> 0

Sheet SUMMARY PG
A1: SUMMARY OF BILLS
F4: € | H4: €
A7: PRELIMINARIES
A9: Collection from page 2 | F9: =Preliminaries!F42 -> 2244.8
A11: Collection from page 3 | F11: =Preliminaries!F97 -> 5536.72 | H11: =SUM(F9:F11) -> 7781.52
A14: ELECTRICAL
A16: Collection from page 4 | F16: =Electrical!F51 -> 39868.47
A18: Collection from page 5 | F18: =Electrical!F109 -> 18536.72
A20: Collection from page 6 | F20: =Electrical!F168 -> 9939.07
A22: Collection from page 7 | F22: =Electrical!F223 -> 2621
A24: Collection from page 8 | F24: =Electrical!F279 -> 5650.85
A26: Collection from page 9 | F26: =Electrical!F336 -> 1750.32
A28: Collection from page 10 | F28: =Electrical!F388 -> 8675.38
A30: Collection from page 11 | F30: =Electrical!F442 -> 5595.83
A32: Collection from page 12 | F32: =Electrical!F501 -> 1981.47
A34: Collection from page 13 | F34: =Electrical!F555 -> 7076.9
A36: Collection from page 14 | F36: =Electrical!F610 -> 2883.69
A38: Collection from page 15 | F38: =Electrical!F666 -> 6405.56
A40: Collection from page 16 | F40: =Electrical!F726 -> 478.05
A42: Collection from page 17 | F42: =Electrical!F779 -> 8056.84
A44: Collection from page 18 | F44: =Electrical!F831 -> 2796.17
A46: Collection from page 19 | F46: =Electrical!F886 -> 5165.61
A48: Collection from page 20 | F48: =Electrical!F944 -> 2045.17
A50: Collection from page 21 | F50: =Electrical!F997 -> 5155.36
A52: Collection from page 22 | F52: =Electrical!F1053 -> 3838.15
A54: Collection from page 23 | F54: =Electrical!F1109 -> 6066.94
A56: Collection from page 24 | F56: =Electrical!F1168 -> 1096.91
A58: Collection from page 25 | F58: =Electrical!F1222 -> 6249.38
A60: Collection from page 26 | F60: =Electrical!F1278 -> 2657.09
A62: Collection from page 27 | F62: =Electrical!F1336 -> 6562.95
A64: Collection from page 28 | F64: =Electrical!F1396 -> 276.75
A66: Collection from page 29 | F66: =Electrical!F1452 -> 4075.04
A68: Collection from page 30 | F68: =Electrical!F1508 -> 2259.3
A70: Collection from page 31 | F70: =Electrical!F1565 -> 5813.41
A72: Collection from page 32 | F72: =Electrical!F1620 -> 3613.7
A74: Collection from page 33 | F74: =Electrical!F1680 -> 646.72
A76: Collection from page 34 | F76: =Electrical!F1735 -> 3512.08
A78: Collection from page 35 | F78: =Electrical!F1787 -> 9701.63 | H78: =SUM(F14:F78) -> 191052.51
A81: EMERGENCY STANDBY GENERATOR
A83: Collection from page 36 | F83: ='Emergency Standby Generator'!F48 -> 27559.17 | H83: =SUM(F83:G83) -> 27559.17
A86: HVAC
A88: Collection from page 37
A90: Collection from page 38
A92: Collection from page 39
A94: Collection from page 40
A96: Collection from page 41
A98: Collection from page 42
A100: Collection from page 43
A102: Collection from page 44
A104: Collection from page 45
A106: Collection from page 46
A108: Collection from page 47
... A136: Collection from page 61
A138: Collection from page 62 | H138: =SUM(F88:F138) -> 0
A141: PLUMBING
A143: Collection from page 63
A145: Collection from page 64
A147: Collection from page 65
A149: Collection from page 66
A151: Collection from page 67
A153: Collection from page 68
A155: Collection from page 69
A157: Collection from page 70
A159: Collection from page 71
A161: Collection from page 72
A163: Collection from page 73
A165: Collection from page 74 | H165: =SUM(F142:F165) -> 0
A168: RAINWATER AND DRAINAGE
A170: Collection from page 75
A172: Collection from page 76
A174: Collection from page 77
A176: Collection from page 78 | H176: =SUM(F170:F176) -> 0
A179: FIRE SAFETY AND FIRE FIGHTING
A181: Collection from page 79
A183: Collection from page 80 | H183: =SUM(F181:F183) -> 0
A186: FIRE STOPPING
A188: Collection from page 81 | F188: ='FIRE STOPPING'!F56 -> 2293.18 | H188: =SUM(F188:G188) -> 2293.18
A191: FIRE DETECTION AND ALARM
A193: Collection from page 82 | F193: ='Fire Detection'!F56 -> 10401.55
A195: Collection from page 83 | F195: ='Fire Detection'!F114 -> 8404.27
A197: Collection from page 84 | F197: ='Fire Detection'!F172 -> 5952.6
A199: Collection from page 85 | F199: ='Fire Detection'!F230 -> 6311.25
A201: Collection from page 86 | F201: ='Fire Detection'!F288 -> 3057.48 | H201: =SUM(F192:F201) -> 34127.15
A204: CCTV
A206: Collection from page 87 | F206: =CCTV!F57 -> 2530.24 | H206: =F206 -> 2530.24
A209: STRUCTURED CABLING
A211: Collection from page 88 | F211: ='Structured Cabling'!F57 -> 2758.52
A213: Collection from page 89 | F213: ='Structured Cabling'!F117 -> 6878.39 | H213: =SUM(F211:F213) -> 9636.91
A216: ACCESS CONTROL
A218: Collection from page 90 | F218: ='Access Control'!F55 -> 10383.55 | H218: =SUM(F218:G218) -> 10383.55
A221: AC CUT-OUT SWITCHES
A223: Collection from page 91 | F223: ='AC cut-out switches'!F55 -> 1034.56 | H223: =SUM(F223:G223) -> 1034.56
A226: COMMISSIONING
A228: Collection from page 92 | F228: =COMMISSIONING!F39 -> 0 | H228: =SUM(F228:G228) -> 0
A233: Total for all services: | H233: =SUM(H7:H232) -> 286398.79
A235: Add / Omit (to specify):
A237: 1% Measurement Fee | H237: =(H233+H235)*0.01 -> 2863.9879
A239: Total: | H239: =H237+H235+H233 -> 289262.78
A241: V.A.T. @ 18% | H241: =H239*0.18 -> 52067.3
A243: Overall Total in Euro: | G243: € | H243: =H239+H241 -> 341330.08
...
