Workbook
Name Access_Control: [1]Elec_Est!#REF!
Name AREAS: [1]ML_Sum!$X$1:$AD$16
Name AREAS: ML_Sum!$X$1:$AD$16
Name CCTV: [1]Elec_Est!#REF!
Name Data: [1]Elec_Est!#REF!
Name Fire_Alarm: [1]Elec_Est!#REF!
Name FO: [1]Elec_Est!#REF!
Name Guard: [1]Elec_Est!#REF!
Name Intercom: [1]Elec_Est!#REF!
Name Intruder_Alarm: [1]Elec_Est!#REF!

Sheet Notes
A1: NOTES

Sheet Elec_Rates
B1: CLIENT: | C1: =ML_Sum!$C1 -> 1 | D1: =ML_Sum!$D1 -> Battery Street Limited | F1: =ML_Sum!$F1 -> 0 | I1: 1 | J1: =ML_Sum!$J1 -> 1 | K1: =ML_Sum!$K1 -> 1 | L1: =ML_Sum!$L1 -> 1 | M1: =ML_Sum!$M1 -> 1 | N1: =ML_Sum!$N1 -> 1 | O1: =ML_Sum!$O1 -> 1 | Q1: =ML_Sum!$Q1 -> € | R1: R/Lab Cont | S1: =ML_Sum!$S1 -> R | T1: =ML_Sum!$T1 -> 1 | U1: =ML_Sum!W1 -> BOQ | V1: INCL | W1: MULT | X1: AREA | Y1: BOQ | Z1: TDWG | AA1: ACT | AB1: DIFF
B2: PROJECT: | C2: =ML_Sum!$C2 -> 1 | D2: =ML_Sum!$D2 -> MEP Works British Hotel | F2: =ML_Sum!$F2 -> Electrical | I2: 2 | J2: =ML_Sum!$J2 -> 1 | K2: =ML_Sum!$K2 -> 1 | L2: =ML_Sum!$L2 -> 1 | M2: =ML_Sum!$M2 -> 1 | N2: =ML_Sum!$N2 -> 1 | O2: =ML_Sum!$O2 -> 1 | Q2: =ML_Sum!$Q2 -> 0 | R2: mu_A | S2: =ML_Sum!$S2 -> 1 | T2: =ML_Sum!$T2 -> 27.46
B3: JOB DESC: | C3: =ML_Sum!$C3 -> 1 | D3: =ML_Sum!$D3 -> Electrical for Mechanical Services | F3: =ML_Sum!$F3 -> Controls | I3: 3 | J3: =ML_Sum!$J3 -> 1 | K3: =ML_Sum!$K3 -> 1 | L3: =ML_Sum!$L3 -> 1 | M3: =ML_Sum!$M3 -> 1 | N3: =ML_Sum!$N3 -> 1 | O3: =ML_Sum!$O3 -> 1 | Q3: =ML_Sum!$Q3 -> 0 | R3: mu_B | S3: =ML_Sum!$S3 -> 1 | T3: =ML_Sum!$T3 -> 27.46
B4: QUOTE No: | C4: =ML_Sum!$C4 -> 1 | D4: =ML_Sum!$D4 -> ELM25-0665 | F4: =ML_Sum!$F4 -> 0 | I4: 4 | J4: =ML_Sum!$J4 -> 1 | K4: =ML_Sum!$K4 -> 1 | L4: =ML_Sum!$L4 -> 1 | M4: =ML_Sum!$M4 -> 1 | N4: =ML_Sum!$N4 -> 1 | O4: =ML_Sum!$O4 -> 1 | Q4: =ML_Sum!$Q4 -> 0 | R4: mu_C | S4: =ML_Sum!$S4 -> 0 | T4: =ML_Sum!$T4 -> 0
B5: CLIENTs REF: | C5: =ML_Sum!$C5 -> 1 | D5: =ML_Sum!$D5 -> 0 | F5: =ML_Sum!$F5 -> 0 | I5: 5 | J5: =ML_Sum!$J5 -> 1 | K5: =ML_Sum!$K5 -> 1 | L5: =ML_Sum!$L5 -> 1 | M5: =ML_Sum!$M5 -> 1 | N5: =ML_Sum!$N5 -> 1 | O5: =ML_Sum!$O5 -> 1 | Q5: =ML_Sum!$Q5 -> 0 | R5: mu_D | S5: =ML_Sum!$S5 -> 0 | T5: =ML_Sum!$T5 -> 0
B6: VAT/DUTIES: | C6: =ML_Sum!$C6 -> 1 | D6: =ML_Sum!$D6 -> VAT EXCL. | F6: =ML_Sum!$F6 -> 0 | I6: 6 | J6: =ML_Sum!$J6 -> 1 | K6: =ML_Sum!$K6 -> 1 | L6: =ML_Sum!$L6 -> 1 | M6: =ML_Sum!$M6 -> 1 | N6: =ML_Sum!$N6 -> 1 | O6: =ML_Sum!$O6 -> 1 | Q6: =ML_Sum!$Q6 -> 0 | R6: mu_E | S6: =ML_Sum!$S6 -> 0 | T6: =ML_Sum!$T6 -> 0
B7: SAVED ON: | C7: =ML_Sum!$C7 -> 1 | D7: 39364 | F7: =ML_Sum!$F7 -> 0 | I7: 7 | J7: =ML_Sum!$J7 -> 1 | K7: =ML_Sum!$K7 -> 1 | L7: =ML_Sum!$L7 -> 1 | M7: =ML_Sum!$M7 -> 1 | N7: =ML_Sum!$N7 -> 1 | O7: =ML_Sum!$O7 -> 0 | Q7: =ML_Sum!$Q7 -> 0 | R7: mu_F | S7: =ML_Sum!$S7 -> 0 | T7: =ML_Sum!$T7 -> 0
B8: ESTIMATOR: | C8: =ML_Sum!$C8 -> 1 | D8: =ML_Sum!$D8 -> Umut Kaymak | F8: =ML_Sum!$F8 -> 0 | I8: 8 | J8: =ML_Sum!$J8 -> 1 | K8: =ML_Sum!$K8 -> 1 | L8: =ML_Sum!$L8 -> 1 | M8: =ML_Sum!$M8 -> 1 | N8: =ML_Sum!$N8 -> 1 | O8: =ML_Sum!$O8 -> 0 | Q8: =ML_Sum!$Q8 -> 0 | R8: mu_G | S8: =ML_Sum!$S8 -> 0 | T8: =ML_Sum!$T8 -> 0
B9: LABOUR RATE: | C9: =ML_Sum!$C9 -> 1 | D9: =ML_Sum!$D9 -> 27.46 | F9: =ML_Sum!$F9 -> 0 | I9: 9 | J9: =ML_Sum!$J9 -> 1 | K9: =ML_Sum!$K9 -> 1 | L9: =ML_Sum!$L9 -> 1 | M9: =ML_Sum!$M9 -> 1 | N9: =ML_Sum!$N9 -> 1 | O9: =ML_Sum!$O9 -> 0 | Q9: =ML_Sum!$Q9 -> 0 | R9: mu_H | S9: =ML_Sum!$S9 -> 0 | T9: =ML_Sum!$T9 -> 0
C10: =ML_Sum!$C10 -> 1 | F10: =ML_Sum!$F10 -> 0 | I10: 10 | J10: =ML_Sum!$J10 -> 1 | K10: =ML_Sum!$K10 -> 1 | L10: =ML_Sum!$L10 -> 1 | M10: =ML_Sum!$M10 -> 1 | N10: =ML_Sum!$N10 -> 1 | O10: =ML_Sum!$O10 -> 1 | Q10: =ML_Sum!$Q10 -> 0 | R10: mu_I | S10: =ML_Sum!$S10 -> 0 | T10: =ML_Sum!$T10 -> 0
C11: =ML_Sum!$C11 -> 1 | F11: =ML_Sum!$F11 -> 0 | Q11: =ML_Sum!$Q11 -> 0 | R11: mu_J | S11: =ML_Sum!$S11 -> 0 | T11: =ML_Sum!$T11 -> 0
C12: =ML_Sum!$C12 -> 1 | F12: =ML_Sum!$F12 -> 0 | Q12: =ML_Sum!$Q12 -> 0 | R12: MIXED | S12: =ML_Sum!$S12 -> MAT MU | T12: =ML_Sum!$T12 -> LAB RATE
G13: I_CODE | H13: C_CODE | I13: MAKE | J13: PART_NO | K13: MARKUP | L13: TYPE | M13: LIST_P | N13: P_FACT | O13: FIX | P13: DATE | Q13: %Dsct in BOQ | R13: MU TYPE | S13: MAT MU | T13: LAB RATE
Q14: Multip
A15: 1 | B15: =$A15 -> 1 | D15: 000# | K15: RATE | L15: RATE | Q15: =B15/A15 -> 1 | R15: =IF($B15=0,0,IF($S$1="R",ROUND(R23/$B15,2),R23/$B15)) -> 0 | T15: =IF($B15=0,0,IF($S$1="R",ROUND(T23/$B15,2),T23/$B15)) -> 0
D16: Based on:
R17: =$A17*Q17 -> 0 | T17: =$A17*S17*$T$1 -> 0
R18: =$A18*Q18 -> 0 | T18: =$A18*S18*$T$1 -> 0
R19: =$A19*Q19 -> 0 | T19: =$A19*S19*$T$1 -> 0
R20: =$A20*Q20 -> 0 | T20: =$A20*S20*$T$1 -> 0
R21: =$A21*Q21 -> 0 | T21: =$A21*S21*$T$1 -> 0
C22: << ==== TOTAL UNITS | R22: =$A22*Q22 -> 0 | T22: =$A22*S22*$T$1 -> 0
A23: d> | B23: =(R22+T22) -> 0 | D23: Sell_A | E23: =IF($B15=0,0,ROUND(ROUND(($R23*$S$2+($T23*$T$2))/$B15, 2)*$C$2,2)) -> 0 | F23: =ROUND($B15*$E23,2) -> 0 | K23: ITEM | L23: ITEM | R23: =SUM(R16:R22) -> 0 | T23: =SUM(T16:T22) -> 0
A24: END!
A25: END! | D25: RATE SHEET GRAND TOTAL | R25: MATERIAL | T25: LABOUR
A26: END!
A27: END! | D27: COMPONENTS | L27: COMP_RT | R27: =SUMIF($L$12:$L25,"",R$12:R25) -> 0 | T27: =SUMIF($L$12:$L25,"",T$12:T25) -> 0
A28: END! | D28: RATE SUMS (ITEMS) | L28: ITEM_RT | R28: =SUMIF($L$12:$L25,"ITEM",R$12:R25) -> 0 | T28: =SUMIF($L$12:$L25,"ITEM",T$12:T25) -> 0
A29: SB!
B30: V:56 | E30: COSTCODE TOTAL | R30: =SUM(R31:R86) -> 0 | T30: =SUM(T31:T86) -> 0
B31: 1 | C31: cc | D31: Erection materials | F31: 501 | P31: 1 | R31: =SUMIF($H$12:$H$24,$F31,R$12:R$24) -> 0 | T31: =SUMIF($H$12:$H$24,$F31,T$12:T$24) -> 0
B32: 2 | C32: cc | D32: Busbar Trunking | F32: 505 | P32: 1 | R32: =SUMIF($H$12:$H$24,$F32,R$12:R$24) -> 0 | T32: =SUMIF($H$12:$H$24,$F32,T$12:T$24) -> 0
B33: 3 | C33: cc | D33: Switchgear | F33: 510 | P33: 2 | R33: =SUMIF($H$12:$H$24,$F33,R$12:R$24) -> 0 | T33: =SUMIF($H$12:$H$24,$F33,T$12:T$24) -> 0
B34: 4 | C34: cc | D34: MCC Equipment | F34: 511 | P34: 2 | R34: =SUMIF($H$12:$H$24,$F34,R$12:R$24) -> 0 | T34: =SUMIF($H$12:$H$24,$F34,T$12:T$24) -> 0
B35: 5 | C35: cc | D35: BMS Equipment | F35: 512 | P35: 2 | R35: =SUMIF($H$12:$H$24,$F35,R$12:R$24) -> 0 | T35: =SUMIF($H$12:$H$24,$F35,T$12:T$24) -> 0
B36: 6 | C36: cc | D36: PVC Pipes / Ducts | F36: 520 | P36: 1 | R36: =SUMIF($H$12:$H$24,$F36,R$12:R$24) -> 0 | T36: =SUMIF($H$12:$H$24,$F36,T$12:T$24) -> 0
B37: 7 | C37: cc | D37: High/medium voltage switchgear | F37: 530 | P37: 2 | R37: =SUMIF($H$12:$H$24,$F37,R$12:R$24) -> 0 | T37: =SUMIF($H$12:$H$24,$F37,T$12:T$24) -> 0
B38: 8 | C38: cc | D38: Power Transformers | F38: 550 | P38: 2 | R38: =SUMIF($H$12:$H$24,$F38,R$12:R$24) -> 0 | T38: =SUMIF($H$12:$H$24,$F38,T$12:T$24) -> 0
B39: 9 | C39: cc | D39: Control Panels | F39: 570 | P39: 2 | R39: =SUMIF($H$12:$H$24,$F39,R$12:R$24) -> 0 | T39: =SUMIF($H$12:$H$24,$F39,T$12:T$24) -> 0
B40: 10 | C40: cc | D40: Electrical Single Core Cables | F40: 615 | P40: 2 | R40: =SUMIF($H$12:$H$24,$F40,R$12:R$24) -> 0 | T40: =SUMIF($H$12:$H$24,$F40,T$12:T$24) -> 0
B41: 11 | C41: cc | D41: Electrical Multicore Cables | F41: 616 | P41: 2 | R41: =SUMIF($H$12:$H$24,$F41,R$12:R$24) -> 0 | T41: =SUMIF($H$12:$H$24,$F41,T$12:T$24) -> 0
B42: 12 | C42: cc | D42: ELV/BMS/Special Cables | F42: 617 | P42: 2 | R42: =SUMIF($H$12:$H$24,$F42,R$12:R$24) -> 0 | T42: =SUMIF($H$12:$H$24,$F42,T$12:T$24) -> 0
... B86: 56 | C86: cc | D86: Provisional Sum | F86: 970 | P86: 4 | R86: =SUMIF($H$12:$H$24,$F86,R$12:R$24) -> 0 | T86: =SUMIF($H$12:$H$24,$F86,T$12:T$24) -> 0
C88: cc | F88: Fix 1 | H88: 1 | R88: =SUMIF($P31:$P86,1,R31:R86) -> 0 | T88: =SUMIF($P31:$P86,1,T31:T86) -> 0
C89: cc | F89: Fix 2 | H89: 2 | R89: =SUMIF($P31:$P86,2,R31:R86) -> 0 | T89: =SUMIF($P31:$P86,2,T31:T86) -> 0
C90: cc | F90: Fix 3 | H90: 2 | R90: =SUMIF($P31:$P86,3,R31:R86) -> 0 | T90: =SUMIF($P31:$P86,3,T31:T86) -> 0
C91: cc | F91: Others | H91: 3 | R91: =SUMIF($P31:$P86,4,R31:R86) -> 0 | T91: =SUMIF($P31:$P86,4,T31:T86) -> 0
C92: cc | F92: TOTAL | R92: =SUM(R88:R91) -> 0 | T92: =SUM(T88:T91) -> 0

Sheet Elec_Est
B1: CLIENT: | C1: =ML_Sum!$C1 -> 1 | D1: =ML_Sum!$D1 -> Battery Street Limited | F1: =ML_Sum!$F1 -> 0 | I1: 1 | J1: =ML_Sum!$J1 -> 1 | K1: =ML_Sum!$K1 -> 1 | L1: =ML_Sum!$L1 -> 1 | M1: =ML_Sum!$M1 -> 1 | N1: =ML_Sum!$N1 -> 1 | O1: =ML_Sum!$O1 -> 1 | Q1: =ML_Sum!$Q1 -> € | R1: R/Lab Cont | S1: =ML_Sum!$S1 -> R | T1: =ML_Sum!$T1 -> 1 | U1: =ML_Sum!W1 -> BOQ | V1: INCL | W1: MULT | X1: AREA | Y1: BOQ | Z1: TDWG | AA1: ACT | AB1: DIFF
B2: PROJECT: | C2: =ML_Sum!$C2 -> 1 | D2: =ML_Sum!$D2 -> MEP Works British Hotel | F2: =ML_Sum!$F2 -> Electrical | I2: 2 | J2: =ML_Sum!$J2 -> 1 | K2: =ML_Sum!$K2 -> 1 | L2: =ML_Sum!$L2 -> 1 | M2: =ML_Sum!$M2 -> 1 | N2: =ML_Sum!$N2 -> 1 | O2: =ML_Sum!$O2 -> 1 | Q2: =ML_Sum!$Q2 -> 0 | R2: mu_A | S2: =ML_Sum!$S2 -> 1 | T2: =ML_Sum!$T2 -> 27.46
B3: JOB DESC: | C3: =ML_Sum!$C3 -> 1 | D3: =ML_Sum!$D3 -> Electrical for Mechanical Services | F3: =ML_Sum!$F3 -> Controls | I3: 3 | J3: =ML_Sum!$J3 -> 1 | K3: =ML_Sum!$K3 -> 1 | L3: =ML_Sum!$L3 -> 1 | M3: =ML_Sum!$M3 -> 1 | N3: =ML_Sum!$N3 -> 1 | O3: =ML_Sum!$O3 -> 1 | Q3: =ML_Sum!$Q3 -> 0 | R3: mu_B | S3: =ML_Sum!$S3 -> 1 | T3: =ML_Sum!$T3 -> 27.46
B4: QUOTE No: | C4: =ML_Sum!$C4 -> 1 | D4: =ML_Sum!$D4 -> ELM25-0665 | F4: =ML_Sum!$F4 -> 0 | I4: 4 | J4: =ML_Sum!$J4 -> 1 | K4: =ML_Sum!$K4 -> 1 | L4: =ML_Sum!$L4 -> 1 | M4: =ML_Sum!$M4 -> 1 | N4: =ML_Sum!$N4 -> 1 | O4: =ML_Sum!$O4 -> 1 | Q4: =ML_Sum!$Q4 -> 0 | R4: mu_C | S4: =ML_Sum!$S4 -> 0 | T4: =ML_Sum!$T4 -> 0
B5: CLIENTs REF: | C5: =ML_Sum!$C5 -> 1 | D5: =ML_Sum!$D5 -> 0 | F5: =ML_Sum!$F5 -> 0 | I5: 5 | J5: =ML_Sum!$J5 -> 1 | K5: =ML_Sum!$K5 -> 1 | L5: =ML_Sum!$L5 -> 1 | M5: =ML_Sum!$M5 -> 1 | N5: =ML_Sum!$N5 -> 1 | O5: =ML_Sum!$O5 -> 1 | Q5: =ML_Sum!$Q5 -> 0 | R5: mu_D | S5: =ML_Sum!$S5 -> 0 | T5: =ML_Sum!$T5 -> 0
B6: VAT/DUTIES: | C6: =ML_Sum!$C6 -> 1 | D6: =ML_Sum!$D6 -> VAT EXCL. | F6: =ML_Sum!$F6 -> 0 | I6: 6 | J6: =ML_Sum!$J6 -> 1 | K6: =ML_Sum!$K6 -> 1 | L6: =ML_Sum!$L6 -> 1 | M6: =ML_Sum!$M6 -> 1 | N6: =ML_Sum!$N6 -> 1 | O6: =ML_Sum!$O6 -> 1 | Q6: =ML_Sum!$Q6 -> 0 | R6: mu_E | S6: =ML_Sum!$S6 -> 0 | T6: =ML_Sum!$T6 -> 0
B7: SAVED ON: | C7: =ML_Sum!$C7 -> 1 | D7: 39364 | F7: =ML_Sum!$F7 -> 0 | I7: 7 | J7: =ML_Sum!$J7 -> 1 | K7: =ML_Sum!$K7 -> 1 | L7: =ML_Sum!$L7 -> 1 | M7: =ML_Sum!$M7 -> 1 | N7: =ML_Sum!$N7 -> 1 | O7: =ML_Sum!$O7 -> 0 | Q7: =ML_Sum!$Q7 -> 0 | R7: mu_F | S7: =ML_Sum!$S7 -> 0 | T7: =ML_Sum!$T7 -> 0
B8: ESTIMATOR: | C8: =ML_Sum!$C8 -> 1 | D8: =ML_Sum!$D8 -> Umut Kaymak | F8: =ML_Sum!$F8 -> 0 | I8: 8 | J8: =ML_Sum!$J8 -> 1 | K8: =ML_Sum!$K8 -> 1 | L8: =ML_Sum!$L8 -> 1 | M8: =ML_Sum!$M8 -> 1 | N8: =ML_Sum!$N8 -> 1 | O8: =ML_Sum!$O8 -> 0 | Q8: =ML_Sum!$Q8 -> 0 | R8: mu_G | S8: =ML_Sum!$S8 -> 0 | T8: =ML_Sum!$T8 -> 0
B9: LABOUR RATE: | C9: =ML_Sum!$C9 -> 1 | D9: =ML_Sum!$D9 -> 27.46 | F9: =ML_Sum!$F9 -> 0 | I9: 9 | J9: =ML_Sum!$J9 -> 1 | K9: =ML_Sum!$K9 -> 1 | L9: =ML_Sum!$L9 -> 1 | M9: =ML_Sum!$M9 -> 1 | N9: =ML_Sum!$N9 -> 1 | O9: =ML_Sum!$O9 -> 0 | Q9: =ML_Sum!$Q9 -> 0 | R9: mu_H | S9: =ML_Sum!$S9 -> 0 | T9: =ML_Sum!$T9 -> 0
C10: =ML_Sum!$C10 -> 1 | F10: =ML_Sum!$F10 -> 0 | I10: 10 | J10: =ML_Sum!$J10 -> 1 | K10: =ML_Sum!$K10 -> 1 | L10: =ML_Sum!$L10 -> 1 | M10: =ML_Sum!$M10 -> 1 | N10: =ML_Sum!$N10 -> 1 | O10: =ML_Sum!$O10 -> 1 | Q10: =ML_Sum!$Q10 -> 0 | R10: mu_I | S10: =ML_Sum!$S10 -> 0 | T10: =ML_Sum!$T10 -> 0
C11: =ML_Sum!$C11 -> 1 | F11: =ML_Sum!$F11 -> 0 | Q11: =ML_Sum!$Q11 -> 0 | R11: mu_J | S11: =ML_Sum!$S11 -> 0 | T11: =ML_Sum!$T11 -> 0
C12: =ML_Sum!$C12 -> 1 | F12: =ML_Sum!$F12 -> 0 | Q12: =ML_Sum!$Q12 -> 0 | R12: MIXED | S12: =ML_Sum!$S12 -> MAT MU | T12: =ML_Sum!$T12 -> LAB RATE
G13: ISELL | H13: C_CODE | I13: MAKE | J13: PART_NO | K13: MARKUP | L13: TYPE | M13: LIST_P | N13: P_FACT | O13: FIX | P13: DATE | Q13: %Dsct in BOQ | R13: MU TYPE | S13: MAT MU | T13: LAB RATE | AM13: Tot Mat Cost | AN13: Unit Lab phr. | AO13: Tot Lab phr. | AP13: < for ELM / MEE
K14: TB
C15: t
D16: PLUMBING SYSTEMS
K18: TB
C19: t
D20: DOMESTIC COLD WATER SYSTEM
E22: Sell Rate | F22: Sell Total | K22: IB | AG22: U_M_Sell | AH22: T_M_Sell | AI22: U_L_Sell | AJ22: T_L_Sell | AK22: Total_Sell | AM22: T_M_Cost | AN22: T_L_Phr | AO22: Mat/Lab=1
A23: 1 | B23: No | D23: Item: 4 | E23: =IF(AND($A23=0,$A$1="DIF"),0, ROUND(ROUND(($R32*$S$2+($T32*$T$2))/A23,2)*$C$2,2)) -> 39.03 | F23: =ROUND($A23*$E23,2) -> 39.03 | G23: ISELL | K23: mu_A | L23: ITEM | T23: =IF(AND($R32=0,$T32=0),"0.00","mu :" & ROUND($F23/$C$2/($R32+$T32*$D$9),2)) -> mu :1 | AG23: =IF($E23=0,0,ROUND($R32*$S$2*$C$2/$A23,2)) -> 5.53 | AH23: =$AG23*$A23 -> 5.53 | AI23: =$E23-$AG23 -> 33.5 | AJ23: =$A23*$AI23 -> 33.5 | AK23: =ROUND(($AG23+$AI23)*$A23,2) -> 39.03 | AM23: =ROUND(R32,2) -> 5.53 | AN23: =ROUND(T32,2) -> 1.22 | AO23: =ROUND(AM23+AN23,2)*A23 -> 6.75
D24: Domestic Cold Water booster set - PDCW1/2 complete with control panel, inlet/outlet headers, isolating valves, strainers, check valves, pressure gauges, pressure vessel etc. as per specifications and equipment schedule
A25: 1 | B25: LS | D25: Connectring-up | G25: EMAT_001 | H25: 501 | I25: (__) | K25: 01-001 | O25: 1 | P25: 35705 | Q25: 0 | R25: =$A25*Q25 -> 0 | S25: 0.5 | T25: =$A25*S25*$T$1 -> 0.5
A26: 2 | B26: m | D26: 5 core x 2.5 mm2 FG16(O)M16 Cable | G26: CAMC_082 | H26: 616 | I26: (__) | K26: 07-006 | O26: 2 | P26: 38299 | Q26: 1.93 | R26: =$A26*Q26 -> 3.86 | S26: 0.06 | T26: =$A26*S26*$T$1 -> 0.12
A27: 2 | B27: No | D27: M20 PVC Gland | G27: CAAC_027 | H27: 620 | I27: (__) | O27: 2 | P27: 35431 | Q27: 0.41 | R27: =$A27*Q27 -> 0.82 | S27: 0.2 | T27: =$A27*S27*$T$1 -> 0.4
A28: 10 | B28: No | D28: Cable Lug 2.5 mm2 | G28: CAAC_005 | H28: 620 | I28: CTT | O28: 2 | P28: 34669 | Q28: 0.05 | R28: =$A28*Q28 -> 0.5 | S28: 0.02 | T28: =$A28*S28*$T$1 -> 0.2
A29: 2 | B29: No | D29: Cable Marker Wrap Around Type | G29: CAAC_025 | H29: 620 | I29: (__) | O29: 2 | Q29: 0.1 | R29: =$A29*Q29 -> 0.2 | T29: =$A29*S29*$T$1 -> 0
A30: 3 | B30: No | D30: Cable Tie 225mm | G30: CONS_009 | H30: 875 | I30: (__) | K30: 01-003 | O30: 1 | P30: 34669 | Q30: 0.05 | R30: =$A30*Q30 -> 0.15 | T30: =$A30*S30*$T$1 -> 0
D31: Pump Set with Control Panel | R31: =$A31*Q31 -> 0 | T31: =$A31*S31*$T$1 -> 0
A32: d> | B32: =(R31+T31) -> 0 | G32: ICOST | K32: mu_A | L32: ITEM | R32: =SUM(R24:R31) -> 5.53 | T32: =SUM(T24:T31) -> 1.22
K33: TB
C34: t
D35: REVERSE OSMOSIS WATER SYSTEM
E37: Sell Rate | F37: Sell Total | K37: IB | AG37: U_M_Sell | AH37: T_M_Sell | AI37: U_L_Sell | AJ37: T_L_Sell | AK37: Total_Sell | AM37: T_M_Cost | AN37: T_L_Phr | AO37: Mat/Lab=1
A38: 1 | B38: No | D38: Item: 17 | E38: =IF(AND($A38=0,$A$1="DIF"),0, ROUND(ROUND(($R47*$S$2+($T47*$T$2))/A38,2)*$C$2,2)) -> 39.03 | F38: =ROUND($A38*$E38,2) -> 39.03 | G38: ISELL | K38: mu_A | L38: ITEM | T38: =IF(AND($R47=0,$T47=0),"0.00","mu :" & ROUND($F38/$C$2/($R47+$T47*$D$9),2)) -> mu :1 | AG38: =IF($E38=0,0,ROUND($R47*$S$2*$C$2/$A38,2)) -> 5.53 | AH38: =$AG38*$A38 -> 5.53 | AI38: =$E38-$AG38 -> 33.5 | AJ38: =$A38*$AI38 -> 33.5 | AK38: =ROUND(($AG38+$AI38)*$A38,2) -> 39.03 | AM38: =ROUND(R47,2) -> 5.53 | AN38: =ROUND(T47,2) -> 1.22 | AO38: =ROUND(AM38+AN38,2)*A38 -> 6.75
D39: Reverse Osmosis Water booster set - PRO-1/2 set complete with control panel, inlet/outlet headers, isolating valves, strainers, check valves, pressure gauges, etc. as per specifications and equipment schedule
A40: 1 | B40: LS | D40: Connectring-up | G40: EMAT_001 | H40: 501 | I40: (__) | K40: 01-001 | O40: 1 | P40: 35705 | Q40: 0 | R40: =$A40*Q40 -> 0 | S40: 0.5 | T40: =$A40*S40*$T$1 -> 0.5
A41: 2 | B41: m | D41: 5 core x 2.5 mm2 FG16(O)M16 Cable | G41: CAMC_082 | H41: 616 | I41: (__) | K41: 07-006 | O41: 2 | P41: 38299 | Q41: 1.93 | R41: =$A41*Q41 -> 3.86 | S41: 0.06 | T41: =$A41*S41*$T$1 -> 0.12
A42: 2 | B42: No | D42: M20 PVC Gland | G42: CAAC_027 | H42: 620 | I42: (__) | O42: 2 | P42: 35431 | Q42: 0.41 | R42: =$A42*Q42 -> 0.82 | S42: 0.2 | T42: =$A42*S42*$T$1 -> 0.4
A43: 10 | B43: No | D43: Cable Lug 2.5 mm2 | G43: CAAC_005 | H43: 620 | I43: CTT | O43: 2 | P43: 34669 | Q43: 0.05 | R43: =$A43*Q43 -> 0.5 | S43: 0.02 | T43: =$A43*S43*$T$1 -> 0.2
A44: 2 | B44: No | D44: Cable Marker Wrap Around Type | G44: CAAC_025 | H44: 620 | I44: (__) | O44: 2 | Q44: 0.1 | R44: =$A44*Q44 -> 0.2 | T44: =$A44*S44*$T$1 -> 0
A45: 3 | B45: No | D45: Cable Tie 225mm | G45: CONS_009 | H45: 875 | I45: (__) | K45: 01-003 | O45: 1 | P45: 34669 | Q45: 0.05 | R45: =$A45*Q45 -> 0.15 | T45: =$A45*S45*$T$1 -> 0
D46: Pump Set with Control Panel | R46: =$A46*Q46 -> 0 | T46: =$A46*S46*$T$1 -> 0
A47: d> | B47: =(#REF!+#REF!) -> #REF! | G47: ICOST | K47: mu_A | L47: ITEM | R47: =SUM(R39:R46) -> 5.53 | T47: =SUM(T39:T46) -> 1.22
K48: TB
C49: t
D50: MAKE UP WATER SYSTEM FOR THE DOMESTIC HOT WATER SYSTEM
E52: Sell Rate | F52: Sell Total | K52: IB | AG52: U_M_Sell | AH52: T_M_Sell | AI52: U_L_Sell | AJ52: T_L_Sell | AK52: Total_Sell | AM52: T_M_Cost | AN52: T_L_Phr | AO52: Mat/Lab=1
A53: 1 | B53: No | D53: Item: 25 | E53: =IF(AND($A53=0,$A$1="DIF"),0, ROUND(ROUND(($R63*$S$2+($T63*$T$2))/A53,2)*$C$2,2)) -> 34.77 | F53: =ROUND($A53*$E53,2) -> 34.77 | G53: ISELL | K53: mu_A | L53: ITEM | T53: =IF(AND($R63=0,$T63=0),"0.00","mu :" & ROUND($F53/$C$2/($R63+$T63*$D$9),2)) -> mu :1 | AG53: =IF($E53=0,0,ROUND($R63*$S$2*$C$2/$A53,2)) -> 4.01 | AH53: =$AG53*$A53 -> 4.01 | AI53: =$E53-$AG53 -> 30.76 | AJ53: =$A53*$AI53 -> 30.76 | AK53: =ROUND(($AG53+$AI53)*$A53,2) -> 34.77 | AM53: =ROUND(R63,2) -> 4.01 | AN53: =ROUND(T63,2) -> 1.12 | AO53: =ROUND(AM53+AN53,2)*A53 -> 5.13
D54: Pressurisation unit PU-1 complete with control panel, inlet/outlet headers, isolating valves, strainers, check valves, pressure gauges, etc. as per specifications and equipment schedule
A55: 1 | B55: LS | D55: Connectring-up | G55: EMAT_001 | H55: 501 | I55: (__) | K55: 01-001 | O55: 1 | P55: 35705 | Q55: 0 | R55: =$A55*Q55 -> 0 | S55: 0.5 | T55: =$A55*S55*$T$1 -> 0.5
A56: 2 | B56: m | D56: 3 core 2.5mm² CU/XLPE/LSZH Cable | G56: CAMC_082 | H56: 616 | I56: (__) | K56: 07-006 | O56: 2 | P56: 38299 | Q56: 1.27 | R56: =$A56*Q56 -> 2.54 | S56: 0.05 | T56: =$A56*S56*$T$1 -> 0.1
A57: 2 | B57: No | D57: M20 PVC Gland | G57: CAAC_027 | H57: 620 | I57: (__) | O57: 2 | P57: 35431 | Q57: 0.41 | R57: =$A57*Q57 -> 0.82 | S57: 0.2 | T57: =$A57*S57*$T$1 -> 0.4
A58: 6 | B58: No | D58: Cable Lug 2.5 mm2 | G58: CAAC_005 | H58: 620 | I58: CTT | O58: 2 | P58: 34669 | Q58: 0.05 | R58: =$A58*Q58 -> 0.3 | S58: 0.02 | T58: =$A58*S58*$T$1 -> 0.12
A59: 2 | B59: No | D59: Cable Marker Wrap Around Type | G59: CAAC_025 | H59: 620 | I59: (__) | O59: 2 | Q59: 0.1 | R59: =$A59*Q59 -> 0.2 | T59: =$A59*S59*$T$1 -> 0
A60: 3 | B60: No | D60: Cable Tie 225mm | G60: CONS_009 | H60: 875 | I60: (__) | K60: 01-003 | O60: 1 | P60: 34669 | Q60: 0.05 | R60: =$A60*Q60 -> 0.15 | T60: =$A60*S60*$T$1 -> 0
D61: On-board inverter+ControlPanel | R61: =$A61*Q61 -> 0 | T61: =$A61*S61*$T$1 -> 0
R62: =$A62*Q62 -> 0 | T62: =$A62*S62*$T$1 -> 0
A63: d> | B63: =(R62+T62) -> 0 | G63: ICOST | K63: mu_A | L63: ITEM | R63: =SUM(R54:R62) -> 4.01 | T63: =SUM(T54:T62) -> 1.12
K64: TB
C65: t
D66: DOMESTIC HOT WATER SYSTEM
K68: TB
C69: t | D69: Item: 33
D70: Outdoor air to water Heat Pump unit 2-pipe complete with suitable anti-vibration mountings. Cost to include for power wiring to isolator in the vicinity, labelling, etc. as required for a complete working system
E72: Sell Rate | F72: Sell Total | K72: IB | AG72: U_M_Sell | AH72: T_M_Sell | AI72: U_L_Sell | AJ72: T_L_Sell | AK72: Total_Sell | AM72: T_M_Cost | AN72: T_L_Phr | AO72: Mat/Lab=1
A73: 1 | B73: No | D73: Item: a. | E73: =IF(AND($A73=0,$A$1="DIF"),0, ROUND(ROUND(SUMIF($L75:$L93,"SUBI",$E75:$E93)/$A73,2)*$C$12,2)) -> 94.74 | F73: =ROUND($A73*$E73,2) -> 94.74 | G73: ISELL | L73: ITEM | T73: =IF(AND($R99=0,$T99=0),"0.00","mu :" & ROUND($F73/$C$12/($R99+$T99*$D$9),2)) -> mu :1 | AG73: =IF(A73=0,0,ROUND(SUM(AG75:AG99)/A73,2)) -> 20.6 | AH73: =$AG73*$A73 -> 20.6 | AI73: =$E73-$AG73 -> 74.14 | AJ73: =$A73*$AI73 -> 74.14 | AK73: =ROUND(($AG73+$AI73)*$A73,2) -> 94.74 | AM73: =ROUND(R99,2) -> 20.6 | AN73: =ROUND(T99,2) -> 2.7 | AO73: =ROUND(AM73+AN73,2)*A73 -> 23.3
D74: Heat Pump HP-01: 47kW | K74: n
E75: =F73/$C$12-SUMIF($L72:$L99,"SUBI",$E72:$E99) -> 0 | F75: Discrepancy
D76: =$F$2 -> Electrical | E76: =ROUND(($R92*$S$2 + ($T92*$T$2)), 2) -> 94.74 | F76: =$E76*$C$12 -> 94.74 | K76: mu_A | L76: SUBI
B77: >>> mu_A material here >>> | R77: =$A77*Q77 -> 0 | T77: =$A77*S77*$T$1 -> 0
A78: 2 | B78: m | D78: 5 core x 10 mm2 FG16(O)M16 Cable | G78: CAMC_082 | H78: 616 | I78: (__) | K78: 07-006 | O78: 2 | P78: 38299 | Q78: 6.55 | R78: =$A78*Q78 -> 13.1 | S78: 0.09 | T78: =$A78*S78*$T$1 -> 0.18
A79: 2 | B79: No | D79: M32 PVC Gland | G79: CAAC_027 | H79: 620 | I79: (__) | O79: 2 | P79: 35431 | Q79: 0.87 | R79: =$A79*Q79 -> 1.74 | S79: 0.4 | T79: =$A79*S79*$T$1 -> 0.8
A80: 10 | B80: No | D80: Cable Lug 10 mm2 | G80: CAAC_008 | H80: 620 | I80: CTT | O80: 2 | P80: 34669 | Q80: 0.14 | R80: =$A80*Q80 -> 1.4 | S80: 0.06 | T80: =$A80*S80*$T$1 -> 0.6
A81: 2 | B81: No | D81: Cable Marker Wrap Around Type | G81: CAAC_025 | H81: 620 | I81: (__) | O81: 2 | Q81: 0.1 | R81: =$A81*Q81 -> 0.2 | T81: =$A81*S81*$T$1 -> 0
A82: 3 | B82: No | D82: Cable Tie 225mm | G82: CONS_009 | H82: 875 | I82: (__) | K82: 01-003 | O82: 1 | P82: 34669 | Q82: 0.05 | R82: =$A82*Q82 -> 0.15 | T82: =$A82*S82*$T$1 -> 0
D83: Connecting-up ⬆️ Heat Pump | R83: =$A83*Q83 -> 0 | T83: =$A83*S83*$T$1 -> 0
A84: 1 | B84: LS | D84: Connectring-up | G84: EMAT_001 | H84: 501 | I84: (__) | K84: 01-001 | O84: 1 | P84: 35705 | Q84: 0 | R84: =$A84*Q84 -> 0 | S84: 0.5 | T84: =$A84*S84*$T$1 -> 0.5
A85: 2 | B85: m | D85: 3 core 2.5mm² CU/XLPE/LSZH Cable | G85: CAMC_082 | H85: 616 | I85: (__) | K85: 07-006 | O85: 2 | P85: 38299 | Q85: 1.27 | R85: =$A85*Q85 -> 2.54 | S85: 0.05 | T85: =$A85*S85*$T$1 -> 0.1
A86: 2 | B86: No | D86: M20 PVC Gland | G86: CAAC_027 | H86: 620 | I86: (__) | O86: 2 | P86: 35431 | Q86: 0.41 | R86: =$A86*Q86 -> 0.82 | S86: 0.2 | T86: =$A86*S86*$T$1 -> 0.4
A87: 6 | B87: No | D87: Cable Lug 2.5 mm2 | G87: CAAC_005 | H87: 620 | I87: CTT | O87: 2 | P87: 34669 | Q87: 0.05 | R87: =$A87*Q87 -> 0.3 | S87: 0.02 | T87: =$A87*S87*$T$1 -> 0.12
A88: 2 | B88: No | D88: Cable Marker Wrap Around Type | G88: CAAC_025 | H88: 620 | I88: (__) | O88: 2 | Q88: 0.1 | R88: =$A88*Q88 -> 0.2 | T88: =$A88*S88*$T$1 -> 0
A89: 3 | B89: No | D89: Cable Tie 225mm | G89: CONS_009 | H89: 875 | I89: (__) | K89: 01-003 | O89: 1 | P89: 34669 | Q89: 0.05 | R89: =$A89*Q89 -> 0.15 | T89: =$A89*S89*$T$1 -> 0
D90: Additional Pump ⬆️ on the system
R91: =$A91*Q91 -> 0 | T91: =$A91*S91*$T$1 -> 0
A92: d> | B92: =(R91+T91) -> 0 | K92: mu_A | L92: SUBI | R92: =SUM(R76:R91) -> 20.6 | T92: =SUM(T76:T91) -> 2.7 | AG92: =ROUND($R92*$S$2,2) -> 20.6
D93: =$F$3 -> Controls | E93: =ROUND(($R97*$S$3 + ($T97*$T$3)), 2) -> 0 | F93: =$F73-SUMIF($L75:$P90,"SUBI",$F75:$F90) -> 0 | K93: mu_B | L93: SUBI
B94: >>> mu_B material here >>> | R94: =$A94*Q94 -> 0 | T94: =$A94*S94*$T$1 -> 0
R95: =$A95*Q95 -> 0 | T95: =$A95*S95*$T$1 -> 0
R96: =$A96*Q96 -> 0 | T96: =$A96*S96*$T$1 -> 0
A97: d> | B97: =(R96+T96) -> 0 | K97: mu_B | L97: SUBI | R97: =SUM(R93:R96) -> 0 | T97: =SUM(T93:T96) -> 0 | AG97: =ROUND($R97*$S$3,2) -> 0
G99: ICOST | L99: ITEM | R99: =SUMIF($L74:$L98,"SUBI",R74:R98) -> 20.6 | T99: =SUMIF($L74:$L98,"SUBI",T74:T98) -> 2.7
K100: TB
C101: t | D101: Item: 35
D102: Plumbing ancillaries on the above primary hot water pipework
E104: Sell Rate | F104: Sell Total | K104: IB | AG104: U_M_Sell | AH104: T_M_Sell | AI104: U_L_Sell | AJ104: T_L_Sell | AK104: Total_Sell | AM104: T_M_Cost | AN104: T_L_Phr | AO104: Mat/Lab=1
A105: 1 | B105: No | D105: Item: e. | E105: =IF(AND($A105=0,$A$1="DIF"),0, ROUND(ROUND(SUMIF($L107:$L114,"SUBI",$E107:$E114)/$A105,2)*$C$12,2)) -> 804.74 | F105: =ROUND($A105*$E105,2) -> 804.74 | G105: ISELL | L105: ITEM | T105: =IF(AND($R121=0,$T121=0),"0.00","mu :" & ROUND($F105/$C$12/($R121+$T121*$D$9),2)) -> mu :1 | AG105: =IF(A105=0,0,ROUND(SUM(AG107:AG121)/A105,2)) -> 766.3 | AH105: =$AG105*$A105 -> 766.3 | AI105: =$E105-$AG105 -> 38.44 | AJ105: =$A105*$AI105 -> 38.44 | AK105: =ROUND(($AG105+$AI105)*$A105,2) -> 804.74 | AM105: =ROUND(R121,2) -> 766.3 | AN105: =ROUND(T121,2) -> 1.4 | AO105: =ROUND(AM105+AN105,2)*A105 -> 767.7
D106: OD 75 mm 2-port modulating Valves | K106: n
E107: =F105/$C$12-SUMIF($L104:$L121,"SUBI",$E104:$E121) -> 0 | F107: Discrepancy
D108: =$F$2 -> Electrical | E108: =ROUND(($R113*$S$2 + ($T113*$T$2)), 2) -> 51.93 | F108: =$E108*$C$12 -> 51.93 | K108: mu_A | L108: SUBI
...

Sheet ML_Sum
B1: CLIENT: | C1: 1 | D1: Battery Street Limited | G1: FALSE | H1: FALSE | I1: 1 | J1: =$Q109 -> 1 | K1: =$Q119 -> 1 | L1: =$Q129 -> 1 | M1: =$Q139 -> 1 | N1: =$Q149 -> 1 | O1: =$Q159 -> 1 | Q1: =IF(C1=1,"€","Curr?") -> € | R1: Recon /Lab.Cont >> | S1: =IF($S$39="PRINT","R","Do Not Print") -> R | T1: 1 | V1: {=IF(OR(X1=AREAS),1,0)} -> 1 | W1: BOQ | X1: x | Y1: x | Z1: x | AA1: x | AB1: x | AC1: x | AD1: x
B2: PROJECT: | C2: =IF($D$6="VAT INCLUDED",1.18,1)*(1-$Q2)*$C$1 -> 1 | D2: MEP Works British Hotel | F2: Electrical | G2: FALSE | I2: 2 | J2: =$Q110 -> 1 | K2: =$Q120 -> 1 | L2: =$Q130 -> 1 | M2: =$Q140 -> 1 | N2: =$Q150 -> 1 | O2: =$Q160 -> 1 | R2: ="A) " & IF($S2=0,"",ROUND($S2,2) & "-" & ROUND($T2/$D$9,2)) -> A) 1-1 | S2: 1 | T2: =$S2*$D$9 -> 27.46 | X2: x | Y2: x | Z2: x | AA2: x | AB2: x | AC2: x | AD2: x
B3: JOB DESC: | C3: =IF($D$6="VAT INCLUDED",1.18,1)*(1-$Q3)*$C$1 -> 1 | D3: Electrical for Mechanical Services | F3: Controls | G3: FALSE | I3: 3 | J3: =$Q111 -> 1 | K3: =$Q121 -> 1 | L3: =$Q131 -> 1 | M3: =$Q141 -> 1 | N3: =$Q151 -> 1 | O3: =$Q161 -> 1 | R3: ="B) " & IF($S3=0,"",ROUND($S3,2) & "-" & ROUND($T3/$D$9,2)) -> B) 1-1 | S3: 1 | T3: =$S3*$D$9 -> 27.46 | X3: x | Y3: x | Z3: x | AA3: x | AB3: x | AC3: x | AD3: x
B4: INT. QUOT No: | C4: =IF($D$6="VAT INCLUDED",1.18,1)*(1-$Q4)*$C$1 -> 1 | D4: ELM25-0665 | G4: FALSE | I4: 4 | J4: =$Q112 -> 1 | K4: =$Q122 -> 1 | L4: =$Q132 -> 1 | M4: =$Q142 -> 1 | N4: =$Q152 -> 1 | O4: =$Q162 -> 1 | R4: ="C) " & IF($S4=0,"",ROUND($S4,2) & "-" & ROUND($T4/$D$9,2)) -> C) | T4: =$S4*$D$10 -> 0 | X4: x | Y4: x | Z4: x | AA4: x | AB4: x | AC4: x | AD4: x
B5: CLIENTs REF: | C5: =IF($D$6="VAT INCLUDED",1.18,1)*(1-$Q5)*$C$1 -> 1 | G5: FALSE | I5: 5 | J5: =$Q113 -> 1 | K5: =$Q123 -> 1 | L5: =$Q133 -> 1 | M5: =$Q143 -> 1 | N5: =$Q153 -> 1 | O5: =$Q163 -> 1 | R5: ="D) " & IF($S5=0,"",ROUND($S5,2) & "-" & ROUND($T5/$D$9,2)) -> D) | T5: =$S5*$D$9 -> 0 | X5: x | Y5: x | Z5: x | AA5: x | AB5: x | AC5: x | AD5: x
B6: VAT: | C6: =IF($D$6="VAT INCLUDED",1.18,1)*(1-$Q6)*$C$1 -> 1 | D6: VAT EXCL. | G6: FALSE | I6: 6 | J6: =$Q114 -> 1 | K6: =$Q124 -> 1 | L6: =$Q134 -> 1 | M6: =$Q144 -> 1 | N6: =$Q154 -> 1 | O6: =$Q164 -> 1 | R6: ="E) " & IF($S6=0,"",ROUND($S6,2) & "-" & ROUND($T6/$D$9,2)) -> E) | T6: =$S6*$D$9 -> 0 | X6: x | Y6: x | Z6: x | AA6: x | AB6: x | AC6: x | AD6: x
B7: SAVED ON: | C7: =IF($D$6="VAT INCLUDED",1.18,1)*(1-$Q7)*$C$1 -> 1 | G7: FALSE | I7: 7 | J7: =$Q115 -> 1 | K7: =$Q125 -> 1 | L7: =$Q135 -> 1 | M7: =$Q145 -> 1 | N7: =$Q155 -> 1 | R7: ="F) " & IF($S7=0,"",ROUND($S7,2) & "-" & ROUND($T7/$D$9,2)) -> F) | T7: =$S7*$D$9 -> 0 | X7: x | Y7: x | Z7: x | AA7: x | AB7: x | AC7: x | AD7: x
B8: ESTIMATOR: | C8: =IF($D$6="VAT INCLUDED",1.18,1)*(1-$Q8)*$C$1 -> 1 | D8: Umut Kaymak | G8: FALSE | I8: 8 | J8: =$Q116 -> 1 | K8: =$Q126 -> 1 | L8: =$Q136 -> 1 | M8: =$Q146 -> 1 | N8: =$Q156 -> 1 | R8: ="G) " & IF($S8=0,"",ROUND($S8,2) & "-" & ROUND($T8/$D$9,2)) -> G) | T8: =$S8*$D$9 -> 0 | X8: x | Y8: x | Z8: x | AA8: x | AB8: x | AC8: x | AD8: x
B9: LAB. COST: | C9: =IF($D$6="VAT INCLUDED",1.18,1)*(1-$Q9)*$C$1 -> 1 | D9: 27.46 | G9: FALSE | I9: 9 | J9: =$Q117 -> 1 | K9: =$Q127 -> 1 | L9: =$Q137 -> 1 | M9: =$Q147 -> 1 | N9: =$Q157 -> 1 | R9: ="H) " & IF($S9=0,"",ROUND($S9,2) & "-" & ROUND($T9/$D$9,2)) -> H) | T9: =$S9*$D$9 -> 0 | X9: x | Y9: x | Z9: x | AA9: x | AB9: x | AC9: x | AD9: x
C10: =IF($D$6="VAT INCLUDED",1.18,1)*(1-$Q10)*$C$1 -> 1 | G10: FALSE | I10: 10 | J10: =$Q118 -> 1 | K10: =$Q128 -> 1 | L10: =$Q138 -> 1 | M10: =$Q148 -> 1 | N10: =$Q158 -> 1 | O10: =Q108 -> 1 | R10: =" I) " & IF($S10=0,"",ROUND($S10,2) & "-" & ROUND($T10/$D$9,2)) -> I) | T10: =$S10*$D$9 -> 0 | X10: x | Y10: x | Z10: x | AA10: x | AB10: x | AC10: x | AD10: x
C11: =IF($D$6="VAT INCLUDED",1.18,1)*(1-$Q11)*$C$1 -> 1 | R11: ="J) " & IF($S11=0,"",ROUND($S11,2) & "-" & ROUND($T11/$D$9,2)) -> J) | T11: =$S11*$D$9 -> 0 | X11: x | Y11: x | Z11: x | AA11: x | AB11: x | AC11: x | AD11: x
C12: =IF($D$6="VAT INCLUDED",1.18,1)*(1-$Q12)*$C$1 -> 1 | G12: SYSTEMS | H12: SYSTEMS | I12: SYSTEMS | J12: SYSTEMS | K12: SYSTEMS | L12: SYSTEMS | M12: SYSTEMS | N12: SYSTEMS | O12: SYSTEMS | P12: SYSTEMS | R12: MIXED - X,Y ) | S12: MAT MU | T12: LAB RATE | X12: x | Y12: x | Z12: x | AA12: x | AB12: x | AC12: x | AD12: x
B13: MATERIAL & LABOUR SUMMARY | G13: ItemCode | H13: CostCode | I13: MAKE | J13: PART_NO | K13: MARKUP | L13: TYPE | M13: LIST_P | N13: SET | O13: FIX | P13: DATE | Q13: %Dsct in BOQ | R13: MATMU-LABMU | S13: MAT CONT >> | T13: =SUM(Q108:Q164)/57 -> 1
B14: =IF($D$6<>"VAT EXCL.", "QUOTE ISSUED WITH VAT INCLUDED", "") | X14: x | Y14: x | Z14: x | AA14: x | AB14: x | AC14: x | AD14: x
Q15: =(C72-F35)/C72 -> 0 | R15: Average Discount applied in BOQ (Q2-Q12) | X15: x | Y15: x | Z15: x | AA15: x | AB15: x | AC15: x | AD15: x
B16: =IF($W$1<>"BOQ", "DIFF SET TO " & W1,"") | Q16: =(F35-E35)/F35 -> 0 | R16: Average Discount applied on Totals (Q23-Q32) | X16: x | Y16: x | Z16: x | AA16: x | AB16: x | AC16: x | AD16: x
Q17: =F74 -> 0 | R17: Overall Discount
B18: =IF(AND(G1,G2,G3,G4,G5,G6,G7,G8,G9,G10,H1)=TRUE, "", "CHECKLIST INCOMPLETE !" ) -> CHECKLIST INCOMPLETE !
B19: =IF(ABS(SUM(A23:A32))>100,"[Discy A-J] are high, Check it out."," ") | Q19: =R83 -> 0.99998551 | R19: Overall Markup (Final Selling Excl.VAT/Total Cost )
E21: DISCOUNTED | F21: SELLING | Q21: % Discnt | R21: MATERIAL | T21: LABOUR
A22: Discy.A-J | B22: Markup/LRate | E22: ="SELLING " & $Q$1 -> SELLING € | F22: =$Q$1 -> € | G22: VAT/DISC | H22: MU | I22: LABRATE | J22: LABCOST | Q22: on Totals | R22: € | T22: Pair Hrs.
A23: =IF($F23=0,"",($F23/$C2)-($R23*$S2+$T23*$T2)) -> -0.085745098 | B23: =IF(F23=0,"",IF(R23=0,"A) "&"---, "&ROUND(($F23/$C2-($R23*$S2))/$T23,2),IF(T23=0,"A) "&ROUND(($F23/$C2)/$R23,2),"A) "&ROUND(($F23/$C2-($T23*$T2))/$R23,2)&", " &ROUND(($F23/$C2-($R23*$S2))/$T23,2)))) -> A) 1, 27.46 | D23: =IF($F2="","",$F2) -> Electrical | E23: =F23*(1-Q23) -> 1777.17 | F23: =Elec_Est!F429 -> 1777.17 | G23: =C2 -> 1 | H23: =$S2 -> 1 | I23: =$T2 -> 27.46 | J23: =$D$9 -> 27.46 | R23: =Elec_Est!R429 -> 539.63355 | T23: =Elec_Est!T429 -> 45.07
A24: =IF($F24=0,"",($F24/$C3)-($R24*$S3+$T24*$T3)) -> 0.04 | B24: =IF(F24=0,"",IF(R24=0,"A) "&"---, "&ROUND(($F24/$C3-($R24*$S3))/$T24,2),IF(T24=0,"A) "&ROUND(($F24/$C3)/$R24,2),"A) "&ROUND(($F24/$C3-($T24*$T3))/$R24,2)&", " &ROUND(($F24/$C3-($R24*$S3))/$T24,2)))) -> A) 1 | D24: =IF($F3="","",$F3) -> Controls | E24: =F24*(1-Q24) -> 1380.77 | F24: =Elec_Est!F430 -> 1380.77 | G24: =C3 -> 1 | H24: =$S3 -> 1 | I24: =$T3 -> 27.46 | J24: =$D$9 -> 27.46 | R24: =Elec_Est!R430 -> 1380.73 | T24: =Elec_Est!T430 -> 0
A25: =IF($F25=0,"",($F25/$C4)-($R25*$S4+$T25*$T4)) | B25: =IF(F25=0,"",IF(R25=0,"A) "&"---, "&ROUND(($F25/$C4-($R25*$S4))/$T25,2),IF(T25=0,"A) "&ROUND(($F25/$C4)/$R25,2),"A) "&ROUND(($F25/$C4-($T25*$T4))/$R25,2)&", " &ROUND(($F25/$C4-($R25*$S4))/$T25,2)))) | D25: =IF($F4="","",$F4) | E25: =F25*(1-Q25) -> 0 | F25: =Elec_Est!F431 -> 0 | G25: =C4 -> 1 | H25: =$S4 -> 0 | I25: =$T4 -> 0 | J25: =$D$9 -> 27.46 | R25: =Elec_Est!R431 -> 0 | T25: =Elec_Est!T431 -> 0
A26: =IF($F26=0,"",($F26/$C5)-($R26*$S5+$T26*$T5)) | B26: =IF(F26=0,"",IF(R26=0,"A) "&"---, "&ROUND(($F26/$C5-($R26*$S5))/$T26,2),IF(T26=0,"A) "&ROUND(($F26/$C5)/$R26,2),"A) "&ROUND(($F26/$C5-($T26*$T5))/$R26,2)&", " &ROUND(($F26/$C5-($R26*$S5))/$T26,2)))) | D26: =IF($F5="","",$F5) | E26: =F26*(1-Q26) -> 0 | F26: =Elec_Est!F432 -> 0 | G26: =C5 -> 1 | H26: =$S5 -> 0 | I26: =$T5 -> 0 | J26: =$D$9 -> 27.46 | R26: =Elec_Est!R432 -> 0 | T26: =Elec_Est!T432 -> 0
A27: =IF($F27=0,"",($F27/$C6)-($R27*$S6+$T27*$T6)) | B27: =IF(F27=0,"",IF(R27=0,"A) "&"---, "&ROUND(($F27/$C6-($R27*$S6))/$T27,2),IF(T27=0,"A) "&ROUND(($F27/$C6)/$R27,2),"A) "&ROUND(($F27/$C6-($T27*$T6))/$R27,2)&", " &ROUND(($F27/$C6-($R27*$S6))/$T27,2)))) | D27: =IF($F6="","",$F6) | E27: =F27*(1-Q27) -> 0 | F27: =Elec_Est!F433 -> 0 | G27: =C6 -> 1 | H27: =$S6 -> 0 | I27: =$T6 -> 0 | J27: =$D$9 -> 27.46 | R27: =Elec_Est!R433 -> 0 | T27: =Elec_Est!T433 -> 0
A28: =IF($F28=0,"",($F28/$C7)-($R28*$S7+$T28*$T7)) | B28: =IF(F28=0,"",IF(R28=0,"A) "&"---, "&ROUND(($F28/$C7-($R28*$S7))/$T28,2),IF(T28=0,"A) "&ROUND(($F28/$C7)/$R28,2),"A) "&ROUND(($F28/$C7-($T28*$T7))/$R28,2)&", " &ROUND(($F28/$C7-($R28*$S7))/$T28,2)))) | D28: =IF($F7="","",$F7) | E28: =F28*(1-Q28) -> 0 | F28: =Elec_Est!F434 -> 0 | G28: =C7 -> 1 | H28: =$S7 -> 0 | I28: =$T7 -> 0 | J28: =$D$9 -> 27.46 | R28: =Elec_Est!R434 -> 0 | T28: =Elec_Est!T434 -> 0
A29: =IF($F29=0,"",($F29/$C8)-($R29*$S8+$T29*$T8)) | B29: =IF(F29=0,"",IF(R29=0,"A) "&"---, "&ROUND(($F29/$C8-($R29*$S8))/$T29,2),IF(T29=0,"A) "&ROUND(($F29/$C8)/$R29,2),"A) "&ROUND(($F29/$C8-($T29*$T8))/$R29,2)&", " &ROUND(($F29/$C8-($R29*$S8))/$T29,2)))) | D29: =IF($F8="","",$F8) | E29: =F29*(1-Q29) -> 0 | F29: =Elec_Est!F435 -> 0 | G29: =C8 -> 1 | H29: =$S8 -> 0 | I29: =$T8 -> 0 | J29: =$D$9 -> 27.46 | R29: =Elec_Est!R435 -> 0 | T29: =Elec_Est!T435 -> 0
A30: =IF($F30=0,"",($F30/$C9)-($R30*$S9+$T30*$T9)) | B30: =IF(F30=0,"",IF(R30=0,"A) "&"---, "&ROUND(($F30/$C9-($R30*$S9))/$T30,2),IF(T30=0,"A) "&ROUND(($F30/$C9)/$R30,2),"A) "&ROUND(($F30/$C9-($T30*$T9))/$R30,2)&", " &ROUND(($F30/$C9-($R30*$S9))/$T30,2)))) | D30: =IF($F9="","",$F9) | E30: =F30*(1-Q30) -> 0 | F30: =Elec_Est!F436 -> 0 | G30: =C9 -> 1 | H30: =$S9 -> 0 | I30: =$T9 -> 0 | J30: =$D$9 -> 27.46 | R30: =Elec_Est!R436 -> 0 | T30: =Elec_Est!T436 -> 0
A31: =IF($F31=0,"",($F31/$C10)-($R31*$S10+$T31*$T10)) | B31: =IF(F31=0,"",IF(R31=0,"A) "&"---, "&ROUND(($F31/$C10-($R31*$S10))/$T31,2),IF(T31=0,"A) "&ROUND(($F31/$C10)/$R31,2),"A) "&ROUND(($F31/$C10-($T31*$T10))/$R31,2)&", " &ROUND(($F31/$C10-($R31*$S10))/$T31,2)))) | D31: =IF($F10="","",$F10) | E31: =F31*(1-Q31) -> 0 | F31: =Elec_Est!F437 -> 0 | G31: =C10 -> 1 | H31: =$S10 -> 0 | I31: =$T10 -> 0 | J31: =$D$9 -> 27.46 | R31: =Elec_Est!R437 -> 0 | T31: =Elec_Est!T437 -> 0
A32: =IF($F32=0,"",($F32/$C11)-($R32*$S11+$T32*$T11)) | B32: =IF(F32=0,"",IF(R32=0,"A) "&"---, "&ROUND(($F32/$C11-($R32*$S11))/$T32,2),IF(T32=0,"A) "&ROUND(($F32/$C11)/$R32,2),"A) "&ROUND(($F32/$C11-($T32*$T11))/$R32,2)&", " &ROUND(($F32/$C11-($R32*$S11))/$T32,2)))) | D32: =IF($F11="","",$F11) | E32: =F32*(1-Q32) -> 0 | F32: =Elec_Est!F438 -> 0 | G32: =C11 -> 1 | H32: =$S11 -> 0 | I32: =$T11 -> 0 | J32: =$D$9 -> 27.46 | R32: =Elec_Est!R438 -> 0 | T32: =Elec_Est!T438 -> 0
C33: MIXED
A35: Discy.L | B35: =Plumbing!H45+Plumbing!H104+Plumbing!H155+Plumbing!H204+Plumbing!H254+Plumbing!H307+Plumbing!H348+Plumbing!H399+Plumbing!H449+Plumbing!H504+Plumbing!H561+Plumbing!H618+'Rain water & Drainage'!H48+'Rain water & Drainage'!H100+'Rain water & Drainage'!H148+'Rain water & Drainage'!H202+'Fire Fighting'!H54+'Fire Fighting'!H97 -> 3157.94 | D35: =B35-E35 -> 0 | E35: =SUM(E23:E32) -> 3157.94 | F35: =SUM(F23:F32) -> 3157.94 | R35: =SUM(R23:R32) -> 1920.3635 | T35: =SUM(T23:T32) -> 45.07
A36: =IF(A39=0,"0.00",A39-(A38*A37)) -> 0.00 | B36: BOQ TOTAL | E36: ="ESTIM TOTAL (" & $Q$1 & ")" -> ESTIM TOTAL (€)
A37: 1.125 | B37: <1 Actual LabCont | R37: =R165 -> 1920.3635 | S37: C.C.Totals | T37: =T165 -> 45.07
B38: <2 Phrs @ 1.00
B39: <3 Phrs @ Actual | Q39: Discy.T >> | R39: =R37-R35 -> 0 | S39: PRINT | T39: =T37-T35 -> 0
B41: Values Only on : | D41: 45573 | E41: 3171.67 | F41: 3171.67 | R41: 1920.3635 | T41: 45.57
A46: REMARKS:
A47: 1) VAT and Duties as above.
A51: ESTIMATOR: | D51: =D8 -> Umut Kaymak | Q51: APPROVED BY:
A53: SIGNED: | Q53: DATE APPROVED:
A55: FILE LOCATION: | D55: =CELL("filename") -> https://d.docs.live.net/d8e42587b76b10ba/Documents/Visual Code Studio/Claude/BMS-Attribution-Model/projects/J01111_Brit_Hotel/[ELM25_0665_Brittania_Hotel_Mech_Estimate.xlsx]ML_Sum
B57: PANTA CONTRACTING LTD. - ELECTRICAL DIVISION
B58: CONTRACT / VARIATION INPUT DOCUMENT
S59: Copy to:-
D60: Client: | E60: =D1 -> Battery Street Limited | S60: Ms. V. Vella
D61: Project: | E61: =D2 -> MEP Works British Hotel | S61: Mr. K. Micallef
D62: Job Description: | E62: =D3 -> Electrical for Mechanical Services | S62: Mr. A. Sciberras
D63: Quote No: | E63: =D4 -> ELM25-0665
D64: Client's Ref: | E64: =D5 -> 0
S65: File:-
D66: File No:
D67: Ext. Ref:
E70: Contract /Variation (Excl. VAT)
C72: =IF($A$33="MIXED",F23/(1-Q2)+F24/(1-Q3)+F25/(1-Q4)+F26/(1-Q5)+F27/(1-Q6)+F28/(1-Q7)+F29/(1-Q8)+F30/(1-Q9)+F31/(1-Q10)+F32/(1-Q11)-SUM(A23:A32), F23/(1-Q2)+F24/(1-Q3)+F25/(1-Q4)+F26/(1-Q5)+F27/(1-Q6)+F28/(1-Q7)+F29/(1-Q8)+F30/(1-Q9)+F31/(1-Q10)+F32/(1-Q11)) -> 3157.94 | E72: Estim.Sell before Discounts excl.VAT (€): | F72: =IF(D6="VAT INCLUDED",C72/($C$1*1.18),C72/$C$1) -> 3157.94
E74: Overall Discount: | F74: =(F72-F75)/F72 -> 0
E75: Final Sell after Discounts excl.VAT (€): | F75: =IF(D6="VAT INCLUDED",E35/($C$1*1.18),E35/$C$1) -> 3157.94
E77: Labour Rate - | F77: =$D$9 -> 27.46 | R77: Mech. Cost to us
D80: Mat. Cost | E80: Labour | F80: Total Cost | R80: Sell Excl.VAT / Total Cost
D81: € | E81: Pair.Hrs | F81: €
D83: =R165 -> 1920.3635 | E83: =T165 -> 45.07 | F83: =R165+S165 -> 3157.9857 | R83: =IF(F83=0,0,F75/F83) -> 0.99998551
D84: ( From CostCode Totals )
R87: Advanced Payment:
R88: Retention:
R90: Awarded Date:
R91: Estimated Start Date:
R92: Estimated Completion Date:
D93: .................
D94: K. Micallef | R94: Date issued:
D95: =NOW() -> 46114.361
D98: PANTA CONTRACTING LTD. - ELECTRICAL DIVISION
D99: ELECTRICAL AND ELV CONTRACT / VARIATION BUDGET COST
D101: Project: | E101: =E61 -> MEP Works British Hotel
D102: Job Desc: | E102: =E62 -> Electrical for Mechanical Services
D103: Client's Ref: | E103: =E64 -> 0
D106: COSTCODE | F106: Cost | Q106: Mat. | R106: Mat Cost | S106: Lab Cost @ | T106: Labour
F107: Code | Q107: Cont. | R107: € | S107: =$D$9 -> 27.46 | T107: Pair.Hrs
B108: V:56 | D108: BOQ RateOnly Items | P108: FIX | Q108: 1
B109: 1(J) | C109: cc | D109: Erection materials | F109: 501 | P109: 1 | Q109: 1 | R109: =Elec_Est!R450 -> 0 | S109: =T109*$D$9 -> 219.68 | T109: =Elec_Est!T450 -> 8
B110: 2 | C110: cc | D110: Busbar Trunking | F110: 505 | P110: 1 | Q110: 1 | R110: =Elec_Est!R451 -> 0 | S110: =T110*$D$9 -> 0 | T110: =Elec_Est!T451 -> 0
B111: 3 | C111: cc | D111: Switchgear | F111: 510 | P111: 2 | Q111: 1 | R111: =Elec_Est!R452 -> 0 | S111: =T111*$D$9 -> 0 | T111: =Elec_Est!T452 -> 0
B112: 4 | C112: cc | D112: MCC Equipment | F112: 511 | P112: 2 | Q112: 1 | R112: =Elec_Est!R453 -> 0 | S112: =T112*$D$9 -> 0 | T112: =Elec_Est!T453 -> 0
B113: 5 | C113: cc | D113: BMS Equipment | F113: 512 | P113: 2 | Q113: 1 | R113: =Elec_Est!R454 -> 1380.73 | S113: =T113*$D$9 -> 27.46 | T113: =Elec_Est!T454 -> 1
B114: 6 | C114: cc | D114: PVC Pipes / Ducts | F114: 520 | P114: 1 | Q114: 1 | R114: =Elec_Est!R455 -> 0 | S114: =T114*$D$9 -> 0 | T114: =Elec_Est!T455 -> 0
B115: 7 | C115: cc | D115: High/medium voltage switchgear | F115: 530 | P115: 2 | Q115: 1 | R115: =Elec_Est!R456 -> 0 | S115: =T115*$D$9 -> 0 | T115: =Elec_Est!T456 -> 0
B116: 8 | C116: cc | D116: Power Transformers | F116: 550 | P116: 2 | Q116: 1 | R116: =Elec_Est!R457 -> 0 | S116: =T116*$D$9 -> 0 | T116: =Elec_Est!T457 -> 0
B117: 9 | C117: cc | D117: Control Panels | F117: 570 | P117: 2 | Q117: 1 | R117: =Elec_Est!R458 -> 0 | S117: =T117*$D$9 -> 0 | T117: =Elec_Est!T458 -> 0
B118: 10 | C118: cc | D118: Electrical Single Core Cables | F118: 615 | P118: 2 | Q118: 1 | R118: =Elec_Est!R459 -> 44 | S118: =T118*$D$9 -> 54.92 | T118: =Elec_Est!T459 -> 2
B119: 11(K) | C119: cc | D119: Electrical Multicore Cables | F119: 616 | P119: 2 | Q119: 1 | R119: =Elec_Est!R460 -> 163.15355 | S119: =T119*$D$9 -> 67.8262 | T119: =Elec_Est!T460 -> 2.47
B120: 12 | C120: cc | D120: ELV/BMS/Special Cables | F120: 617 | P120: 2 | Q120: 1 | R120: =Elec_Est!R461 -> 154.8 | S120: =T120*$D$9 -> 145.538 | T120: =Elec_Est!T461 -> 5.3
B121: 13 | C121: cc | D121: Cable Accessories | F121: 620 | P121: 2 | Q121: 1 | R121: =Elec_Est!R462 -> 75.14 | S121: =T121*$D$9 -> 335.012 | T121: =Elec_Est!T462 -> 12.2
B122: 14 | C122: cc | D122: Galv. Cable Trays | F122: 650 | P122: 1 | Q122: 1 | R122: =Elec_Est!R463 -> 0 | S122: =T122*$D$9 -> 0 | T122: =Elec_Est!T463 -> 0
B123: 15 | C123: cc | D123: PVC Cable Trays | F123: 651 | P123: 1 | Q123: 1 | R123: =Elec_Est!R464 -> 0 | S123: =T123*$D$9 -> 0 | T123: =Elec_Est!T464 -> 0
B124: 16 | C124: cc | D124: Galv. Cable Basket | F124: 652 | P124: 1 | Q124: 1 | R124: =Elec_Est!R465 -> 0 | S124: =T124*$D$9 -> 0 | T124: =Elec_Est!T465 -> 0
B125: 17 | C125: cc | D125: Galv. Cable Ladder | F125: 654 | P125: 1 | Q125: 1 | R125: =Elec_Est!R466 -> 0 | S125: =T125*$D$9 -> 0 | T125: =Elec_Est!T466 -> 0
B126: 18 | C126: cc | D126: Galv. Cable Trunking | F126: 675 | P126: 1 | Q126: 1 | R126: =Elec_Est!R467 -> 0 | S126: =T126*$D$9 -> 0 | T126: =Elec_Est!T467 -> 0
B127: 19 | C127: cc | D127: Alum. Cable Trunking | F127: 676 | P127: 1 | Q127: 1 | R127: =Elec_Est!R468 -> 0 | S127: =T127*$D$9 -> 0 | T127: =Elec_Est!T468 -> 0
B128: 20 | C128: cc | D128: PVC Cable Trunking | F128: 680 | P128: 1 | Q128: 1 | R128: =Elec_Est!R469 -> 0 | S128: =T128*$D$9 -> 0 | T128: =Elec_Est!T469 -> 0
B129: 21(L) | C129: cc | D129: Underfloor Cable Trunking | F129: 681 | P129: 1 | Q129: 1 | R129: =Elec_Est!R470 -> 0 | S129: =T129*$D$9 -> 0 | T129: =Elec_Est!T470 -> 0
...

Sheet Quote
A1: =IF(AND(UPPER(LEFT(TRIM($D$8),11))="01",UPPER(LEFT(TRIM($D$9),3))<>"ELM"),"PANTA RETAIL LTD.","PANTA CONTRACTING LIMITED") -> PANTA CONTRACTING LIMITED
A2: =IF(UPPER(LEFT(TRIM($D$9),3))="ELM","ELEC-FOR-MECH INTERNAL QUOTATION","ELECTRICAL INTERNAL QUOTATION") -> ELEC-FOR-MECH INTERNAL QUOTATION
B5: ATT: | D5: Jason Camilleri | R5: Dated: | S5: =NOW() -> 46114.361
B6: CLIENT: | C6: Link to ML_SUM $D1 | D6: =ML_Sum!D1 -> Battery Street Limited
B7: PROJECT: | C7: Link to ML_SUM $D2 | D7: =ML_Sum!D2 -> MEP Works British Hotel
B8: JOB DESC: | C8: Link to ML_SUM $D3 | D8: =ML_Sum!D3 -> Electrical for Mechanical Services
B9: QUOTE No: | C9: Link to ML_SUM $D4 | D9: =ML_Sum!D4 -> ELM25-0665
B10: CLIENT's Ref: | C10: Link to ML_SUM $D5 | D10: =ML_Sum!D5 -> 0
D21: Material Cost (€) : | E21: =ML_Sum!R35 -> 1920.3635 | F21: =ML_Sum!D6 -> VAT EXCL. | G21: VAT EXCLUDED. | H21: VAT EXCLUDED. | I21: VAT EXCLUDED. | J21: VAT EXCLUDED. | K21: VAT EXCLUDED. | L21: VAT EXCLUDED. | M21: VAT EXCLUDED. | N21: VAT EXCLUDED. | O21: VAT EXCLUDED. | P21: VAT EXCLUDED.
D22: Labour Pair Hours : | E22: =ML_Sum!T35 -> 45.07
A53: Signed for and on behalf of | Q53: Signed for and on behalf of
A54: Electrical Division | Q54: Division
Q56: Records
Q57: Mr. K. Micallef
Q59: File

Sheet Plumbing
A1: BILL OF QUANTITIES
A2: PLUMBING SYSTEMS
A5: Item | C5: Qty | D5: Unit | E5: Total Material | F5: Total Labour | G5: Rate in € | H5: Total
B7: Supply, install, connect, test and commission the following as specified for a complete working system
B9: MAINS WATER SYSTEM
A11: 1 | B11: Incoming mains water pipework polypropylene (PPR) SDR 7.4. Cost to include for all fittings, any necessary adaptors, brackets and all accessories as necessary for a complete working installation.
B13: OD25mm | C13: 50 | D13: m | H13: =G13*C13 -> 0
B15: OD32mm | C15: 45 | D15: m | H15: =G15*C15 -> 0
A18: 2 | B18: Isolating valves in PPR on mains distribution pipework:
B20: OD25mm | C20: 5 | D20: No | H20: =G20*C20 -> 0
B22: OD32mm | C22: 3 | D22: No | H22: =G22*C22 -> 0
A25: T | B25: DOMESTIC COLD WATER SYSTEM
A27: 3 | B27: Domestic Cold Water VERTICAL storage tanks, 1500L storage capacity, complete with inlet and outlet valves, float valve and adequate supports, as required for a complete installation. | C27: 2 | D27: No | H27: =G27*C27 -> 0
A30: 4 | B30: Domestic Cold Water booster set - PDCW1/2 complete with control panel, inlet/outlet headers, isolating valves, strainers, check valves, pressure gauges, pressure vessel etc. as per specifications and equipment schedule | C30: 1 | D30: No | E30: =Elec_Est!AM23 -> 5.53 | F30: =Elec_Est!AN23 -> 1.22 | G30: =Elec_Est!E23 -> 39.03 | H30: =G30*C30 -> 39.03
A33: 5 | B33: Domestic cold water (DCW) pipework polypropylene (PPR) SDR 7.4. Cost to include for all fittings, any necessary adaptors, brackets, wall penetrations, and all accessories as necessary for a complete working installation.
B35: OD25mm | C35: 8 | D35: m | H35: =G35*C35 -> 0
B37: OD32mm | C37: 20 | D37: m | H37: =G37*C37 -> 0
B39: OD40mm | C39: 60 | D39: m | H39: =G39*C39 -> 0
B45: Total carried forward to summary page | E45: =SUM(E6:E43) -> 5.53 | F45: =SUM(F6:F43) -> 1.22 | H45: =SUM(H6:H43) -> 39.03
A51: Item | C51: Qty | D51: Unit | E51: Total Material | F51: Total Labour | G51: Rate in € | H51: Total
B53: OD50mm | C53: 30 | D53: m | H53: =G53*C53 -> 0
B55: OD63mm | C55: 30 | D55: m | H55: =G55*C55 -> 0
A58: 6 | B58: Isolating valves on the DCW distribution pipework:
B60: OD25mm | C60: 4 | D60: No | H60: =G60*C60 -> 0
B62: OD32mm | C62: 8 | D62: No | H62: =G62*C62 -> 0
B64: OD40mm | C64: 11 | D64: No | H64: =G64*C64 -> 0
B66: OD63mm | C66: 9 | D66: No | H66: =G66*C66 -> 0
A69: 7 | B69: Automatic Air Vents (AAV) on the DCW distribution pipework:
B71: OD25mm | C71: 2 | D71: No | H71: =G71*C71 -> 0
A74: 8 | B74: Drain Valves (DV) on the DCW distribution pipework:
B76: OD25mm | C76: 2 | D76: No | H76: =G76*C76 -> 0
A79: 9 | B79: Non-return valves on the DCW distribution pipework:
B81: OD32mm | C81: 2 | D81: No | H81: =G81*C81 -> 0
B83: OD63mm | C83: 2 | D83: No | H83: =G83*C83 -> 0
A86: 10 | B86: Strainers on the DCW distribution pipework:
B88: OD63mm | C88: 2 | D88: No | H88: =G88*C88 -> 0
H89: =G89*C89 -> 0
B104: Total carried forward to summary page | E104: =SUM(E52:E102) -> 0 | F104: =SUM(F52:F102) -> 0 | H104: =SUM(H52:H102) -> 0
A110: Item | C110: Qty | D110: Unit | E110: Total Material | F110: Total Labour | G110: Rate in € | H110: Total
B112: DOMESTIC COLD WATER TREATMENT PLANT
A114: 11 | B114: DCW Treatment Plant (DCWTP) - Packaged chlorination system equipped with pump, dosing solution tank, automatic monitoring/control panel, pipework and accessories etc. for a complete installation. | C114: 1 | D114: No | H114: =G114*C114 -> 0
A117: 12 | B117: DCWTP HORIZONTAL storage tanks, 200L storage capacity, complete with inlet and outlet valves, float valve and adequate supports, as required for a complete installation. | C117: 1 | D117: No | H117: =G117*C117 -> 0
A120: 13 | B120: DCWTP pipework polypropylene (PPR) SDR 7.4. Cost to include for all fittings, any necessary adaptors, brackets, wall penetrations, and all accessories as necessary for a complete working installation.
B122: OD25mm | C122: 8 | D122: m | H122: =G122*C122 -> 0
A125: 14 | B125: Isolating valves on the DCW distribution pipework:
B127: OD25mm | C127: 2 | D127: No | H127: =G127*C127 -> 0
B155: Total carried forward to summary page | E155: =SUM(E111:E153) -> 0 | F155: =SUM(F111:F153) -> 0 | H155: =SUM(H111:H153) -> 0
A161: Item | C161: Qty | D161: Unit | E161: Total Material | F161: Total Labour | G161: Rate in € | H161: Total
A164: T | B164: REVERSE OSMOSIS WATER SYSTEM
A166: 15 | B166: Reverse Osmosis System Plant, complete with control panel, filters, inlet and outlet valves, adequate supports, as required for a complete installation as per specifications. | C166: 1 | D166: No
A169: 16 | B169: WRAS Approved Reverse Osmosis Vertical Water Storage Tank, 200L storage capacity, complete with inlet and outlet valves, float valve and adequate supports, as required for a complete installation. | C169: 1 | D169: No | H169: =G169*C169 -> 0
A172: 17 | B172: Reverse Osmosis Water booster set - PRO-1/2 set complete with control panel, inlet/outlet headers, isolating valves, strainers, check valves, pressure gauges, etc. as per specifications and equipment schedule | C172: 1 | D172: No | E172: =Elec_Est!AM38 -> 5.53 | F172: =Elec_Est!AN38 -> 1.22 | G172: =Elec_Est!E38 -> 39.03 | H172: =G172*C172 -> 39.03
A175: 18 | B175: Reverse Osmosis (RO) pipework polypropylene (PPR) SDR 7.4. Cost to include for all fittings, any necessary adaptors, brackets, wall penetrations, and all accessories as necessary for a complete working installation.
B177: OD40mm | C177: 40 | D177: m | H177: =G177*C177 -> 0
A180: 19 | B180: Isolating valves on the RO distribution pipework:
B182: OD40mm | C182: 7 | D182: No | H182: =G182*C182 -> 0
A185: 20 | B185: Automatic Air Vent (AAV) on the RO distribution pipework:
B187: OD25mm | C187: 1 | D187: No | H187: =G187*C187 -> 0
A190: 21 | B190: Drain Valve (DV) on the RO distribution pipework:
B192: OD25mm | C192: 1 | D192: No | H192: =G192*C192 -> 0
A195: 22 | B195: Non-return valve on the RO distribution pipework:
B197: OD40mm | C197: 2 | D197: No | H197: =G197*C197 -> 0
A200: 23 | B200: Strainers on the RO water pipework:
B202: OD 40mm | C202: 2 | D202: No | H202: =G202*C202 -> 0
B204: Total carried forward to summary page | E204: =SUM(E162:E202) -> 5.53 | F204: =SUM(F162:F202) -> 1.22 | H204: =SUM(H162:H202) -> 39.03
A210: Item | C210: Qty | D210: Unit | E210: Total Material | F210: Total Labour | G210: Rate in € | H210: Total
A212: T | B212: MAKE UP WATER SYSTEM FOR THE DOMESTIC HOT WATER SYSTEM
A214: 24 | B214: Make Up HORIZONTAL storage tanks, 500L storage capacity, complete with inlet and outlet valves, float valve and adequate supports, as required for a complete installation. | C214: 1 | D214: No | H214: =G214*C214 -> 0
A217: 25 | B217: Pressurisation unit PU-1 complete with control panel, inlet/outlet headers, isolating valves, strainers, check valves, pressure gauges, etc. as per specifications and equipment schedule | C217: 1 | D217: No | E217: =Elec_Est!AM53 -> 4.01 | F217: =Elec_Est!AN53 -> 1.12 | G217: =Elec_Est!E53 -> 34.77 | H217: =G217*C217 -> 34.77
A220: 26 | B220: Pipework polypropylene (PPR) SDR 7.4. Cost to include for all fittings, any necessary adaptors, brackets, wall penetrations, and all accessories as necessary for a complete working installation.
B222: OD25mm | C222: 10 | D222: m | H222: =G222*C222 -> 0
A225: 27 | B225: Isolating valves on the distribution pipework:
B227: OD25mm | C227: 4 | D227: No | H227: =G227*C227 -> 0
A230: 28 | B230: Automatic Air Vent (AAV) on the distribution pipework:
B232: OD25mm | C232: 1 | D232: No | H232: =G232*C232 -> 0
A235: 29 | B235: Drain Valve (DV) on the distribution pipework:
B237: OD25mm | C237: 1 | D237: No | H237: =G237*C237 -> 0
A240: 30 | B240: Non-return valve on the distribution pipework:
B242: OD25mm | C242: 1 | D242: No | H242: =G242*C242 -> 0
A245: 31 | B245: Strainers on the distribution pipework:
B247: OD25mm | C247: 1 | D247: No | H247: =G247*C247 -> 0
A250: 32 | B250: Expansion Vessel on the distribution pipework 30L: | C250: 1 | D250: No | H250: =G250*C250 -> 0
B254: Total carried forward to summary page | E254: =SUM(E211:E252) -> 4.01 | F254: =SUM(F211:F252) -> 1.12 | H254: =SUM(H211:H252) -> 34.77
A260: Item | C260: Qty | D260: Unit | E260: Total Material | F260: Total Labour | G260: Rate in € | H260: Total
A262: T | B262: DOMESTIC HOT WATER SYSTEM | H262: =G262*C262 -> 0
A264: 33T | B264: Outdoor air to water Heat Pump unit 2-pipe complete with suitable anti-vibration mountings. Cost to include for power wiring to isolator in the vicinity, labelling, etc. as required for a complete working system
A266: a. | B266: Heat Pump HP-01: 47kW | C266: 1 | D266: No | E266: =Elec_Est!AM73 -> 20.6 | F266: =Elec_Est!AN73 -> 2.7 | G266: =Elec_Est!E73 -> 94.74 | H266: =G266*C266 -> 94.74
A269: 34 | B269: Primary hot water pipework in PPR Fibre Composite PN20 SDR 7.4 complete with all the necessary fittings and adaptors, insulation, bracketing, fixing material, labelling, etc. as required for a complete installation
B271: OD 75 mm | C271: 45 | D271: m | H271: =G271*C271 -> 0
A274: 35T | B274: Plumbing ancillaries on the above primary hot water pipework
B276: OD 75 mm Isolating valves | C276: 16 | D276: No | H276: =G276*C276 -> 0
B278: OD 75 mm Non return valves | C278: 4 | D278: No | H278: =G278*C278 -> 0
B280: OD 75 mm Strainers | C280: 3 | D280: No | H280: =G280*C280 -> 0
B282: OD 75 mm Commissioning Valves | C282: 2 | D282: No | H282: =G282*C282 -> 0
A284: e. | B284: OD 75 mm 2-port modulating Valves | C284: 1 | D284: No | E284: =Elec_Est!AM105 -> 766.3 | F284: =Elec_Est!AN105 -> 1.4 | G284: =Elec_Est!E105 -> 804.74 | H284: =G284*C284 -> 804.74
A286: f. | B286: OD 75 mm 3-port modulating Valves | C286: 1 | D286: No | E286: =Elec_Est!AM123 -> 521.41 | F286: =Elec_Est!AN123 -> 1.4 | G286: =Elec_Est!E123 -> 559.85 | H286: =G286*C286 -> 559.85
B288: OD 25 mm Automatic Air vent | C288: 4 | D288: No | H288: =G288*C288 -> 0
B290: OD 25 mm Drain Valve | C290: 4 | D290: No | H290: =G290*C290 -> 0
B292: 100 mm Stainless Steel Pressure Gauges (0-6 bar) | C292: 4 | D292: No | H292: =G292*C292 -> 0
B294: 100 mm Stainless Steel Pressure Gauges (0-6 bar) | C294: 4 | D294: No | H294: =G294*C294 -> 0
...

Sheet Rain water & Drainage
A1: BILL OF QUANTITIES
A2: DRAINAGE AND RAIN WATER SYSTEMS
A5: Item | C5: Qty | D5: Unit | E5: Total Material | F5: Total Labour | G5: Rate in € | H5: Total
B7: Supply, install and connect up the following drainage and rainwater systems allowing for all necessary fittings including bends, reducers, and galvanised steel brackets:
B9: Note: All Drainage and rainwater pipework, including related fittings, for Gravity Systems, shall be of the polypropylene (PP) silent type and suitable for hot water discharge.
B10: Any trenching below ground level, coring in slabs and making good shall form part of this scope of works and are to be included in the below rates.
B12: Drainage Installation
B14: Waste Water PP pipework from the drain points in the respective area to main stack allowing for all necessary fittings, brackets, branch-offs, etc. as required for a complete installation;
A16: 1 | B16: Low Level Horizontal Runs, laid to falls
B18: OD40 mm dia. | C18: 30 | D18: m | H18: =G18*C18 -> 0
B20: OD50 mm dia. | C20: 90 | D20: m | H20: =G20*C20 -> 0
B22: OD63 mm dia. | C22: 8 | D22: m | H22: =G22*C22 -> 0
B24: OD90 mm dia. | C24: 2 | D24: m | H24: =G24*C24 -> 0
B26: OD110 mm dia. | C26: 30 | D26: m | H26: =G26*C26 -> 0
A29: 2 | B29: High Level Horizontal Runs, laid to falls
B31: OD50 mm dia. | C31: 3 | D31: m | H31: =G31*C31 -> 0
B33: OD90 mm dia. | C33: 8 | D33: m | H33: =G33*C33 -> 0
B35: OD110 mm dia. | C35: 40 | D35: m | H35: =G35*C35 -> 0
B37: OD125 mm dia. | C37: 6 | D37: m | H37: =G37*C37 -> 0
B39: OD150 mm dia. | C39: 12 | D39: m | H39: =G39*C39 -> 0
A42: 3 | B42: Vertical Stacks, in shafts, exposed, etc.
B44: OD110 mm dia. | C44: 50 | D44: m | H44: =G44*C44 -> 0
B48: Total carried forward to summary page | E48: =SUM(E6:E46) -> 0 | F48: =SUM(F6:F46) -> 0 | H48: =SUM(H6:H46) -> 0
A54: Item | C54: Qty | D54: Unit | E54: Total Material | F54: Total Labour | G54: Rate in € | H54: Total
A56: 4 | B56: Waste Water Ventilation PP pipework from the drain points at Low Level to main vent stack at High level allowing for all necessary fittings, brackets, branch-offs, etc. including chased in walls as required for a complete installation;
B58: OD40 mm dia. | C58: 30 | D58: m | H58: =G58*C58 -> 0
B60: OD75 mm dia. | C60: 35 | D60: m | H60: =G60*C60 -> 0
A63: 5 | B63: Provision of the following waste water outlet points, run in chased down drops in PP:
B65: OD40mm Drains for wash hand basin | C65: 29 | D65: No | H65: =G65*C65 -> 0
B67: OD50mm Drains for kitchen sink/equipment | C67: 5 | D67: No | H67: =G67*C67 -> 0
B69: OD63mm Drains for kitchen equipment | C69: 1 | D69: No | H69: =G69*C69 -> 0
B71: OD110mm Drains for WC | C71: 18 | D71: No | H71: =G71*C71 -> 0
A74: 6 | B74: Drainage ancillaries, allowing for all necessary fittings, brackets, branch-offs, etc. to compliment the above listed pipework, as required for a complete installation.
B76: Aeration Valves OD75mm at the termination of the Ventilation pipework at level -01 | C76: 1 | D76: No | H76: =G76*C76 -> 0
B100: Total carried forward to summary page | E100: =SUM(E55:E98) -> 0 | F100: =SUM(F55:F98) -> 0 | H100: =SUM(H55:H98) -> 0
A106: Item | C106: Qty | D106: Unit | E106: Total Material | F106: Total Labour | G106: Rate in € | H106: Total
B108: Rainwater Installation
B110: Rainwater PP pipework from the collection points in the respective area to main stack allowing for all necessary fittings, brackets, branch-offs, etc. as required for a complete installation;
A112: 7 | B112: Low Level Horizontal Runs, laid to falls
B114: OD110 mm dia. | C114: 1 | D114: m | H114: =G114*C114 -> 0
A117: 8 | B117: High Level Horizontal Runs, laid to falls
B119: OD110 mm dia. | C119: 30 | D119: m | H119: =G119*C119 -> 0
A122: 9 | B122: Vertical Stacks, in shafts, exposed, etc.
B124: OD110 mm dia. | C124: 25 | D124: m | H124: =G124*C124 -> 0
B127: High Pressure Installation (HDPE)
A129: 10 | B129: Heavy gauge HIGH PRESSURE HDPE pipework allowing for all necessary fittings including bends, reducers, and galvanised steel brackets:
B131: OD63 mm dia. | C131: 20 | D131: m | H131: =G131*C131 -> 0
A134: T | B134: Other
A136: 11T | B136: Waste Water Lifting Station, complete with control panel, inlet/outlet headers, isolating valves, strainers, check valves, pressure gauges, etc. to make a complete working system. System shall be as per specifications and equipment schedule
A138: a. | B138: LS1 | C138: 1 | D138: No | E138: =Elec_Est!AM301 -> 11.06 | F138: =Elec_Est!AN301 -> 4.44 | G138: =Elec_Est!E301 -> 132.98 | H138: =G138*C138 -> 132.98
A141: 12T | B141: Sump pump, complete with control panel, non-return valves, inlet/outlet headers, isolating valves, strainers, check valves, pressure gauges, etc. to make a complete working system
A143: a. | B143: SP1 | C143: 1 | D143: No | E143: =Elec_Est!AM325 -> 3.3 | F143: =Elec_Est!AN325 -> 0.59 | G143: =Elec_Est!E325 -> 19.5 | H143: =G143*C143 -> 19.5
B148: Total carried forward to summary page | E148: =SUM(E107:E146) -> 14.36 | F148: =SUM(F107:F146) -> 5.03 | H148: =SUM(H107:H146) -> 152.48
A154: Item | C154: Qty | D154: Unit | E154: Total Material | F154: Total Labour | G154: Rate in € | H154: Total
A156: 13T | B156: Grease Trap, complete with control panel, non-return valves, inlet/outlet headers, isolating valves, strainers, check valves, pressure gauges, etc. to make a complete working system
A158: a. | B158: GT01 | C158: 1 | D158: No | E158: =Elec_Est!AM336 -> 2.2 | F158: =Elec_Est!AN336 -> 0.56 | G158: =Elec_Est!E336 -> 17.58 | H158: =G158*C158 -> 17.58
A160: a. | B160: GT02 | C160: 1 | D160: No | E160: =Elec_Est!AM343 -> 2.2 | F160: =Elec_Est!AN343 -> 0.56 | G160: =Elec_Est!E343 -> 17.58 | H160: =G160*C160 -> 17.58
A163: 14 | B163: Gutters
B165: 2.5 m x 200 mm c/w bottom outlet | C165: 1 | D165: No | H165: =G165*C165 -> 0
B167: 5 m x 200 mm c/w bottom outlet | C167: 1 | D167: No | H167: =G167*C167 -> 0
B170: General
A172: 15 | B172: Allow for the connection of site drains pipework to main sewer network, allowing for all necessary fittings, brackets, branch-offs, trenching, etc. as required for a complete installation. | C172: 1 | D172: No | H172: =G172*C172 -> 0
B202: Total carried forward to summary page | E202: =SUM(E155:E200) -> 4.4 | F202: =SUM(F155:F200) -> 1.12 | H202: =SUM(H155:H200) -> 35.16

Sheet Fire Fighting
A1: BILL OF QUANTITIES
A2: FIRE SAFETY AND FIRE FIGHTING SYSTEMS
A5: Item | C5: Qty | D5: Unit | E5: Total Material | F5: Total Labour | G5: Rate in € | H5: Total
B7: Design, supply, install, connect, test and commission the following as specified and as shown on the drawings, unless otherwise noted.
B9: DRY RISER INSTALLATION
A11: 1 | B11: Galvanised pipework c/w painting for a complete system, appropriate support brackets, etc. System to include all necessary accessories and ancillaries for a complete working system.
B13: DN 100 mm | C13: 40 | D13: m | H13: =G13*C13 -> 0
B15: DN 63 mm | C15: 15 | D15: m | H15: =G15*C15 -> 0
A18: 2 | B18: Landing valves c/w isolating valves and end caps.
B20: DN 63 mm | C20: 7 | D20: No | H20: =G20*C20 -> 0
A23: 3 | B23: Breaching inlet externally on façade complete with isolating valve | C23: 1 | D23: No | H23: =G23*C23 -> 0
A26: 4 | B26: Automatic Air Vent DN 63 mm | C26: 1 | D26: No | H26: =G26*C26 -> 0
A29: 5 | B29: Drain valve DN 63 mm | C29: 1 | D29: No | H29: =G29*C29 -> 0
B32: PORTABLE FIRE EXTINGUISHERS
A34: 6 | B34: Portable Fire Extinguishers:
B36: 2kg CO2 Class 34B | C36: 1 | D36: No | H36: =G36*C36 -> 0
B38: 6 Litre AFFF Class 13A | C38: 14 | D38: No | H38: =G38*C38 -> 0
B40: 6 Litre Wet Chemcial Class F | C40: 1 | D40: No | H40: =G40*C40 -> 0
A43: 7 | B43: Fire extinguisher point signs and signage | C43: 9 | D43: No | H43: =G43*C43 -> 0
B54: Total carried forward to summary page | E54: =SUM(E6:E52) -> 0 | F54: =SUM(F6:F52) -> 0 | H54: =SUM(H6:H52) -> 0
A60: Item | C60: Qty | D60: Unit | E60: Total Material | F60: Total Labour | G60: Rate in € | H60: Total
A62: T | B62: AUTOMATIC WET CHEMICAL SYSTEM
A64: 8T | B64: Automatic wet chemical system including cylinders, pipework, nozzles, interfaces to fire alarm, control panel etc. as required for a complete installation.
A66: a. | B66: 1700x1000mm Hood 1 in kitchen | C66: 1 | D66: No | G66: =Elec_Est!E368 -> 0 | H66: =G66*C66 -> 0
A68: b. | B68: 1700x1000mm Hood 2 in kitchen | C68: 1 | D68: No | G68: =Elec_Est!E374 -> 0 | H68: =G68*C68 -> 0
A71: T | B71: SMOKE CONTROL PRESSURIZATION SYSTEM
A73: 9 | B73: Smoke control pressurization system for the protected staircase, PF-01 as marked on the drawings including pressurization fan PF-01, interfaces to fire alarm, control panel, ancillaries etc. as required for a complete installation. (Tenderer is requested to visit the site prior to design of pressurization system, coordination with other services is also very important) | C73: 1 | D73: LS | E73: =Elec_Est!AM384 -> 127.89 | F73: =Elec_Est!AN384 -> 3.16 | G73: =Elec_Est!E384 -> 214.66 | H73: =G73*C73 -> 214.66
A76: 10 | B76: Smoke control pressurization system for the protected lobbies, PF-02 as marked on the drawings including pressurization fan PF-02, interfaces to fire alarm, control panel, ancillaries etc. as required for a complete installation. (Tenderer is requested to visit the site prior to design of pressurization system, coordination with other services is also very important) | C76: 1 | D76: LS | E76: =Elec_Est!AM403 -> 127.89 | F76: =Elec_Est!AN403 -> 3.16 | G76: =Elec_Est!E403 -> 214.66 | H76: =G76*C76 -> 214.66
B79: GENERAL
A81: 11 | B81: Provision and issue of full system design and hydraulic calculations for approval of each of the above systems | C81: 1 | D81: LS | H81: =G81*C81 -> 0
A84: 12 | B84: Issuing of detailed coordinated workshop drawings including pipework dimenisons, centre lines, levels, distances from wall, heights from FFL, etc. for approval prior to installations | C84: 1 | D84: LS | H84: =G84*C84 -> 0
B97: Total carried forward to summary page | E97: =SUM(E61:E95) -> 255.78 | F97: =SUM(F61:F95) -> 6.32 | H97: =SUM(H61:H95) -> 429.32
