Workbook
Name Access_Control: [1]Elec_Est!#REF!
Name AREAS: #REF!
Name AREAS: [2]ML_Sum!$X$1:$AD$16
Name AREAS: [1]ML_Sum!$X$1:$AD$16
Name AREAS: ML_Sum!$X$1:$AD$16
Name CCTV: [1]Elec_Est!#REF!
Name Data: [1]Elec_Est!#REF!
Name Fire_Alarm: [1]Elec_Est!#REF!
Name FO: [1]Elec_Est!#REF!
Name Guard: [1]Elec_Est!#REF!
Name Intercom: [1]Elec_Est!#REF!
Name Intruder_Alarm: [1]Elec_Est!#REF!

Sheet Notes
A1: NOTES | C1: Rev: 235
C2: checkdesc
A3: ELECTRICAL | C3: Elec_Rates
C4: Elec_Est
A5: Dist Boards | C5: Elv_Rates
A6: 1 | C6: ELV_Est
A7: 2 | C7: Ext_Quote
C8: Int_Quote
A9: Wiring Accessories | C9: Est_BOQ
A10: 1
A11: 2 | C11: Camilleri&Cuschieri Tenders
C12: Conduit
A13: ELV | C13: Wiring
C14: Supply
A15: Fire Alarm
A16: 1
A17: 2
A18: 3
A20: Data
A21: 1
A22: 2
A23: 3
B25: Double pole required
B26: Price includes delivery, fitting, basic power test
B27: Signal / Control wire excluded
B28: Non-Failsafe 230V Fast Running Modulating Actuator
B29: Documentation Attached
B30: Fitment comprises - installing on Damper, Connection to double pole, basic power test.
B31: 0-10V Signal for modulation. 2V closed / 10V open

Sheet ML_Sum
B1: CLIENT: | C1: 1 | D1: UMUT - Electrical Team | G1: FALSE | H1: FALSE | I1: 1 | J1: =$Q109 -> 1 | K1: =$Q119 -> 1 | L1: =$Q129 -> 1 | M1: =$Q139 -> 1 | N1: =$Q149 -> 1 | O1: =$Q159 -> 1 | Q1: =IF(C1=1,"€","Curr?") -> € | R1: Recon /Lab.Cont >> | S1: =IF($S$39="PRINT","R","Do Not Print") -> R | T1: 1.1 | V1: {=IF(OR(X1=AREAS),1,0)} -> 1 | W1: BOQ | X1: x | Y1: x | Z1: x | AA1: x | AB1: x | AC1: x | AD1: x
B2: PROJECT: | C2: =IF($D$6="VAT INCLUDED",1.18,1)*(1-$Q2)*$C$1 -> 1 | D2: Portomaso L4 Dampers | F2: Electrical Site Pair | G2: FALSE | I2: 2 | J2: =$Q110 -> 1 | K2: =$Q120 -> 1 | L2: =$Q130 -> 1 | M2: =$Q140 -> 1 | N2: =$Q150 -> 1 | O2: =$Q160 -> 1 | R2: ="A) " & IF($S2=0,"",ROUND($S2,2) & "-" & ROUND($T2/$D$9,2)) -> A) 1-1 | S2: 1 | T2: =D9*S2 -> 28.53 | X2: x | Y2: x | Z2: x | AA2: x | AB2: x | AC2: x | AD2: x
B3: JOB DESC: | C3: =IF($D$6="VAT INCLUDED",1.18,1)*(1-$Q3)*$C$1 -> 1 | D3: Damper for VAV boxes | F3: ECA/BMS Pair | G3: FALSE | I3: 3 | J3: =$Q111 -> 1 | K3: =$Q121 -> 1 | L3: =$Q131 -> 1 | M3: =$Q141 -> 1 | N3: =$Q151 -> 1 | O3: =$Q161 -> 1 | R3: ="B) " & IF($S3=0,"",ROUND($S3,2) & "-" & ROUND($T3/$D$9,2)) -> B) 1-1.18 | S3: 1 | T3: =D10*S3 -> 33.72 | X3: x | Y3: x | Z3: x | AA3: x | AB3: x | AC3: x | AD3: x
B4: INT. QUOT No: | C4: =IF($D$6="VAT INCLUDED",1.18,1)*(1-$Q4)*$C$1 -> 1 | D4: EL | F4: ECA/BMS Engineer | G4: FALSE | I4: 4 | J4: =$Q112 -> 1 | K4: =$Q122 -> 1 | L4: =$Q132 -> 1 | M4: =$Q142 -> 1 | N4: =$Q152 -> 1 | O4: =$Q162 -> 1 | R4: ="C) " & IF($S4=0,"",ROUND($S4,2) & "-" & ROUND($T4/$D$9,2)) -> C) 1-1.09 | S4: 1 | T4: =D11*S4 -> 31 | X4: x | Y4: x | Z4: x | AA4: x | AB4: x | AC4: x | AD4: x
B5: CLIENTs REF: | C5: =IF($D$6="VAT INCLUDED",1.18,1)*(1-$Q5)*$C$1 -> 1 | F5: BMS - Tech - Single | G5: FALSE | I5: 5 | J5: =$Q113 -> 1 | K5: =$Q123 -> 1 | L5: =$Q133 -> 1 | M5: =$Q143 -> 1 | N5: =$Q153 -> 1 | O5: =$Q163 -> 1 | R5: ="D) " & IF($S5=0,"",ROUND($S5,2) & "-" & ROUND($T5/$D$9,2)) -> D) 1-0.75 | S5: 1 | T5: =D12*S5 -> 21.44 | X5: x | Y5: x | Z5: x | AA5: x | AB5: x | AC5: x | AD5: x
B6: VAT: | C6: =IF($D$6="VAT INCLUDED",1.18,1)*(1-$Q6)*$C$1 -> 1 | D6: VAT EXCL. | F6: Edward/Mark + AGV | G6: FALSE | I6: 6 | J6: =$Q114 -> 1 | K6: =$Q124 -> 1 | L6: =$Q134 -> 1 | M6: =$Q144 -> 1 | N6: =$Q154 -> 1 | O6: =$Q176 -> 1 | R6: ="E) " & IF($S6=0,"",ROUND($S6,2) & "-" & ROUND($T6/$D$9,2)) -> E) 1-1.18 | S6: 1 | T6: =S6*(D12+12.28) -> 33.72 | X6: x | Y6: x | Z6: x | AA6: x | AB6: x | AC6: x | AD6: x
B7: SAVED ON: | C7: =IF($D$6="VAT INCLUDED",1.18,1)*(1-$Q7)*$C$1 -> 1 | G7: FALSE | I7: 7 | J7: =$Q115 -> 1 | K7: =$Q125 -> 1 | L7: =$Q135 -> 1 | M7: =$Q145 -> 1 | N7: =$Q155 -> 1 | R7: ="F) " & IF($S7=0,"",ROUND($S7,2) & "-" & ROUND($T7/$D$9,2)) -> F) | X7: x | Y7: x | Z7: x | AA7: x | AB7: x | AC7: x | AD7: x
B8: ESTIMATOR: | C8: =IF($D$6="VAT INCLUDED",1.18,1)*(1-$Q8)*$C$1 -> 1 | D8: G. Baranyay | G8: FALSE | I8: 8 | J8: =$Q116 -> 1 | K8: =$Q126 -> 1 | L8: =$Q136 -> 1 | M8: =$Q146 -> 1 | N8: =$Q156 -> 1 | R8: ="G) " & IF($S8=0,"",ROUND($S8,2) & "-" & ROUND($T8/$D$9,2)) -> G) | X8: x | Y8: x | Z8: x | AA8: x | AB8: x | AC8: x | AD8: x
B9: LAB. COST: | C9: =IF($D$6="VAT INCLUDED",1.18,1)*(1-$Q9)*$C$1 -> 1 | D9: 28.53 | E9: Cost for 2025 | G9: FALSE | I9: 9 | J9: =$Q117 -> 1 | K9: =$Q127 -> 1 | L9: =$Q137 -> 1 | M9: =$Q147 -> 1 | N9: =$Q157 -> 1 | R9: ="H) " & IF($S9=0,"",ROUND($S9,2) & "-" & ROUND($T9/$D$9,2)) -> H) | X9: x | Y9: x | Z9: x | AA9: x | AB9: x | AC9: x | AD9: x
C10: =IF($D$6="VAT INCLUDED",1.18,1)*(1-$Q10)*$C$1 -> 1 | D10: =12.28+21.44 -> 33.72 | E10: BMS Pair 2025 | G10: FALSE | I10: 10 | J10: =$Q118 -> 1 | K10: =$Q128 -> 1 | L10: =$Q138 -> 1 | M10: =$Q148 -> 1 | N10: =$Q158 -> 1 | O10: =Q108 -> 1 | R10: =" I) " & IF($S10=0,"",ROUND($S10,2) & "-" & ROUND($T10/$D$9,2)) -> I) | X10: x | Y10: x | Z10: x | AA10: x | AB10: x | AC10: x | AD10: x
C11: =IF($D$6="VAT INCLUDED",1.18,1)*(1-$Q11)*$C$1 -> 1 | D11: 31 | E11: BMS Engineer 2025 | R11: ="J) " & IF($S11=0,"",ROUND($S11,2) & "-" & ROUND($T11/$D$9,2)) -> J) | X11: x | Y11: x | Z11: x | AA11: x | AB11: x | AC11: x | AD11: x
C12: =IF($D$6="VAT INCLUDED",1.18,1)*(1-$Q12)*$C$1 -> 1 | D12: 21.44 | E12: BMS Tech 2025 | G12: SYSTEMS | H12: SYSTEMS | I12: SYSTEMS | J12: SYSTEMS | K12: SYSTEMS | L12: SYSTEMS | M12: SYSTEMS | N12: SYSTEMS | O12: SYSTEMS | P12: SYSTEMS | R12: MIXED - X,Y ) | S12: MAT MU | T12: LAB RATE | X12: x | Y12: x | Z12: x | AA12: x | AB12: x | AC12: x | AD12: x
B13: MATERIAL & LABOUR SUMMARY | G13: ItemCode | H13: CostCode | I13: MAKE | J13: PART_NO | K13: MARKUP | L13: TYPE | M13: LIST_P | N13: SET | O13: FIX | P13: DATE | Q13: %Dsct in BOQ | R13: MATMU-LABMU | S13: MAT CONT >> | T13: =SUM(Q108:Q176)/COUNT(Q108:Q176) -> 1
B14: =IF($D$6<>"VAT EXCL.", "QUOTE ISSUED WITH VAT INCLUDED", "") | X14: x | Y14: x | Z14: x | AA14: x | AB14: x | AC14: x | AD14: x
Q15: =(C72-F35)/C72 -> 0 | R15: Average Discount applied in BOQ (Q2-Q12) | X15: x | Y15: x | Z15: x | AA15: x | AB15: x | AC15: x | AD15: x
B16: =IF($W$1<>"BOQ", "DIFF SET TO " & W1,"") | Q16: =(F35-E35)/F35 -> 0 | R16: Average Discount applied on Totals (Q23-Q32) | X16: x | Y16: x | Z16: x | AA16: x | AB16: x | AC16: x | AD16: x
Q17: =F74 -> 0 | R17: Overall Discount
B18: =IF(AND(G1,G2,G3,G4,G5,G6,G7,G8,G9,G10,H1)=TRUE, "", "CHECKLIST INCOMPLETE !" ) -> CHECKLIST INCOMPLETE !
B19: =IF(ABS(SUM(A23:A32))>100,"[Discy A-J] are high, Check it out."," ") | Q19: =R83 -> 1.0574444 | R19: Overall Markup (Final Selling Excl.VAT/Total Cost )
E21: DISCOUNTED | F21: SELLING | Q21: % Discnt | R21: MATERIAL | T21: LABOUR
A22: Discy.A-J | B22: Markup/LRate | E22: ="SELLING " & $Q$1 -> SELLING € | F22: =$Q$1 -> € | G22: VAT/DISC | H22: MU | I22: LABRATE | J22: LABCOST | Q22: on Totals | R22: € | T22: Pair Hrs.
A23: =IF($F23=0,"",($F23/$C2)-($R23*$S2+$T23*$T2)) | B23: =IF(F23=0,"",IF(R23=0,"A) "&"---, "&ROUND(($F23/$C2-($R23*$S2))/$T23,2),IF(T23=0,"A) "&ROUND(($F23/$C2)/$R23,2),"A) "&ROUND(($F23/$C2-($T23*$T2))/$R23,2)&", " &ROUND(($F23/$C2-($R23*$S2))/$T23,2)))) | D23: =IF($F2="","",$F2) -> Electrical Site Pair | E23: =F23*(1-Q23) -> 0 | F23: =Elec_Est!F65 -> 0 | G23: =C2 -> 1 | H23: =$S2 -> 1 | I23: =$T2 -> 28.53 | J23: =$D$9 -> 28.53 | R23: =Elec_Est!R65 -> 0 | T23: =Elec_Est!T65 -> 0
A24: =IF($F24=0,"",($F24/$C3)-($R24*$S3+$T24*$T3)) -> 0 | B24: =IF(F24=0,"",IF(R24=0,"A) "&"---, "&ROUND(($F24/$C3-($R24*$S3))/$T24,2),IF(T24=0,"A) "&ROUND(($F24/$C3)/$R24,2),"A) "&ROUND(($F24/$C3-($T24*$T3))/$R24,2)&", " &ROUND(($F24/$C3-($R24*$S3))/$T24,2)))) -> A) 1, 33.72 | D24: =IF($F3="","",$F3) -> ECA/BMS Pair | E24: =F24*(1-Q24) -> 1050.92 | F24: =Elec_Est!F66 -> 1050.92 | G24: =C3 -> 1 | H24: =$S3 -> 1 | I24: =$T3 -> 33.72 | J24: =$D$9 -> 28.53 | R24: =Elec_Est!R66 -> 680 | T24: =Elec_Est!T66 -> 11
A25: =IF($F25=0,"",($F25/$C4)-($R25*$S4+$T25*$T4)) | B25: =IF(F25=0,"",IF(R25=0,"A) "&"---, "&ROUND(($F25/$C4-($R25*$S4))/$T25,2),IF(T25=0,"A) "&ROUND(($F25/$C4)/$R25,2),"A) "&ROUND(($F25/$C4-($T25*$T4))/$R25,2)&", " &ROUND(($F25/$C4-($R25*$S4))/$T25,2)))) | D25: =IF($F4="","",$F4) -> ECA/BMS Engineer | E25: =F25*(1-Q25) -> 0 | F25: =Elec_Est!F67 -> 0 | G25: =C4 -> 1 | H25: =$S4 -> 1 | I25: =$T4 -> 31 | J25: =$D$9 -> 28.53 | R25: =Elec_Est!R67 -> 0 | T25: =Elec_Est!T67 -> 0
A26: =IF($F26=0,"",($F26/$C5)-($R26*$S5+$T26*$T5)) | B26: =IF(F26=0,"",IF(R26=0,"A) "&"---, "&ROUND(($F26/$C5-($R26*$S5))/$T26,2),IF(T26=0,"A) "&ROUND(($F26/$C5)/$R26,2),"A) "&ROUND(($F26/$C5-($T26*$T5))/$R26,2)&", " &ROUND(($F26/$C5-($R26*$S5))/$T26,2)))) | D26: =IF($F5="","",$F5) -> BMS - Tech - Single | E26: =F26*(1-Q26) -> 0 | F26: =Elec_Est!F68 -> 0 | G26: =C5 -> 1 | H26: =$S5 -> 1 | I26: =$T5 -> 21.44 | J26: 21.44 | R26: =Elec_Est!R68 -> 0 | T26: =Elec_Est!T68 -> 0
A27: =IF($F27=0,"",($F27/$C6)-($R27*$S6+$T27*$T6)) | B27: =IF(F27=0,"",IF(R27=0,"A) "&"---, "&ROUND(($F27/$C6-($R27*$S6))/$T27,2),IF(T27=0,"A) "&ROUND(($F27/$C6)/$R27,2),"A) "&ROUND(($F27/$C6-($T27*$T6))/$R27,2)&", " &ROUND(($F27/$C6-($R27*$S6))/$T27,2)))) | D27: =IF($F6="","",$F6) -> Edward/Mark + AGV | E27: =F27*(1-Q27) -> 0 | F27: =Elec_Est!F69 -> 0 | G27: =C6 -> 1 | H27: =$S6 -> 1 | I27: =$T6 -> 33.72 | J27: 30 | R27: =Elec_Est!R69 -> 0 | T27: =Elec_Est!T69 -> 0
A28: =IF($F28=0,"",($F28/$C7)-($R28*$S7+$T28*$T7)) | B28: =IF(F28=0,"",IF(R28=0,"A) "&"---, "&ROUND(($F28/$C7-($R28*$S7))/$T28,2),IF(T28=0,"A) "&ROUND(($F28/$C7)/$R28,2),"A) "&ROUND(($F28/$C7-($T28*$T7))/$R28,2)&", " &ROUND(($F28/$C7-($R28*$S7))/$T28,2)))) | D28: =IF($F7="","",$F7) | E28: =F28*(1-Q28) -> 0 | F28: =Elec_Est!F70 -> 0 | G28: =C7 -> 1 | H28: =$S7 -> 0 | I28: =$T7 -> 0 | J28: =$D$9 -> 28.53 | R28: =Elec_Est!R70 -> 0 | T28: =Elec_Est!T70 -> 0
A29: =IF($F29=0,"",($F29/$C8)-($R29*$S8+$T29*$T8)) | B29: =IF(F29=0,"",IF(R29=0,"A) "&"---, "&ROUND(($F29/$C8-($R29*$S8))/$T29,2),IF(T29=0,"A) "&ROUND(($F29/$C8)/$R29,2),"A) "&ROUND(($F29/$C8-($T29*$T8))/$R29,2)&", " &ROUND(($F29/$C8-($R29*$S8))/$T29,2)))) | D29: =IF($F8="","",$F8) | E29: =F29*(1-Q29) -> 0 | F29: =Elec_Est!F71 -> 0 | G29: =C8 -> 1 | H29: =$S8 -> 0 | I29: =$T8 -> 0 | J29: =$D$9 -> 28.53 | R29: =Elec_Est!R71 -> 0 | T29: =Elec_Est!T71 -> 0
A30: =IF($F30=0,"",($F30/$C9)-($R30*$S9+$T30*$T9)) | B30: =IF(F30=0,"",IF(R30=0,"A) "&"---, "&ROUND(($F30/$C9-($R30*$S9))/$T30,2),IF(T30=0,"A) "&ROUND(($F30/$C9)/$R30,2),"A) "&ROUND(($F30/$C9-($T30*$T9))/$R30,2)&", " &ROUND(($F30/$C9-($R30*$S9))/$T30,2)))) | D30: =IF($F9="","",$F9) | E30: =F30*(1-Q30) -> 0 | F30: =Elec_Est!F72 -> 0 | G30: =C9 -> 1 | H30: =$S9 -> 0 | I30: =$T9 -> 0 | J30: =$D$9 -> 28.53 | R30: =Elec_Est!R72 -> 0 | T30: =Elec_Est!T72 -> 0
A31: =IF($F31=0,"",($F31/$C10)-($R31*$S10+$T31*$T10)) | B31: =IF(F31=0,"",IF(R31=0,"A) "&"---, "&ROUND(($F31/$C10-($R31*$S10))/$T31,2),IF(T31=0,"A) "&ROUND(($F31/$C10)/$R31,2),"A) "&ROUND(($F31/$C10-($T31*$T10))/$R31,2)&", " &ROUND(($F31/$C10-($R31*$S10))/$T31,2)))) | D31: =IF($F10="","",$F10) | E31: =F31*(1-Q31) -> 0 | F31: =Elec_Est!F73 -> 0 | G31: =C10 -> 1 | H31: =$S10 -> 0 | I31: =$T10 -> 0 | J31: =$D$9 -> 28.53 | R31: =Elec_Est!R73 -> 0 | T31: =Elec_Est!T73 -> 0
A32: =IF($F32=0,"",($F32/$C11)-($R32*$S11+$T32*$T11)) | B32: =IF(F32=0,"",IF(R32=0,"A) "&"---, "&ROUND(($F32/$C11-($R32*$S11))/$T32,2),IF(T32=0,"A) "&ROUND(($F32/$C11)/$R32,2),"A) "&ROUND(($F32/$C11-($T32*$T11))/$R32,2)&", " &ROUND(($F32/$C11-($R32*$S11))/$T32,2)))) | D32: =IF($F11="","",$F11) | E32: =F32*(1-Q32) -> 0 | F32: =Elec_Est!F74 -> 0 | G32: =C11 -> 1 | H32: =$S11 -> 0 | I32: =$T11 -> 0 | J32: =$D$9 -> 28.53 | R32: =Elec_Est!R74 -> 0 | T32: =Elec_Est!T74 -> 0
C33: MIXED
A35: Discy.L | B35: =E_BOQ!F56 -> 680 | E35: =SUM(E23:E32) -> 1050.92 | F35: =SUM(F23:F32) -> 1050.92 | R35: =SUM(R23:R32) -> 680 | T35: =SUM(T23:T32) -> 11
A36: =IF(A39=0,"0.00",A39-(A38*A37)) -> 0.00 | B36: BOQ TOTAL | E36: ="ESTIM TOTAL (" & $Q$1 & ")" -> ESTIM TOTAL (€)
A37: 1.125 | B37: <1 Actual LabCont | R37: =R177 -> 680 | S37: C.C.Totals | T37: =T177 -> 11
B38: <2 Phrs @ 1.00
B39: <3 Phrs @ Actual | Q39: Discy.T >> | R39: =R37-R35 -> 0 | S39: PRINT | T39: =T37-T35 -> 0
B41: Values Only on : | D41: 36892 | E41: values only | F41: values only | R41: values only | T41: values only
A46: REMARKS:
A47: 1) VAT and Duties as above.
A48: 2)
A51: ESTIMATOR: | D51: =D8 -> G. Baranyay | Q51: APPROVED BY:
A53: SIGNED: | Q53: DATE APPROVED:
A55: FILE LOCATION: | D55: =CELL("filename") -> \\pclnas\bms\1. Estimates\3. Small Jobs\SJ585 - Portomaso Level 4 - Dampers\1. Estimate\[C26_Portomaso_L4_Dampers_SJ585.1_R0.1.xlsx]Quote
B57: PANTA CONTRACTING LTD. - ELECTRICAL DIVISION
B58: CONTRACT / VARIATION INPUT DOCUMENT
S59: Copy to:-
D60: Client: | E60: =D1 -> UMUT - Electrical Team | S60: Ms. S. Magri
D61: Project: | E61: =D2 -> Portomaso L4 Dampers | S61: Mr. K. Micallef
D62: Job Description: | E62: =D3 -> Damper for VAV boxes | S62: Mr. A. Sciberras
D63: Quote No: | E63: =D4 -> EL
D64: Client's Ref: | E64: =D5 -> 0
S65: File:-
D66: File No:
D67: Ext. Ref:
E70: Contract /Variation (Excl. VAT)
C72: =IF($A$33="MIXED",F23/(1-Q2)+F24/(1-Q3)+F25/(1-Q4)+F26/(1-Q5)+F27/(1-Q6)+F28/(1-Q7)+F29/(1-Q8)+F30/(1-Q9)+F31/(1-Q10)+F32/(1-Q11)-SUM(A23:A32), F23/(1-Q2)+F24/(1-Q3)+F25/(1-Q4)+F26/(1-Q5)+F27/(1-Q6)+F28/(1-Q7)+F29/(1-Q8)+F30/(1-Q9)+F31/(1-Q10)+F32/(1-Q11)) -> 1050.92 | E72: Estim.Sell before Discounts excl.VAT (€): | F72: =IF(D6="VAT INCLUDED",C72/($C$1*1.18),C72/$C$1) -> 1050.92
E74: Overall Discount: | F74: =(F72-F75)/F72 -> 0
E75: Final Sell after Discounts excl.VAT (€): | F75: =IF(D6="VAT INCLUDED",E35/($C$1*1.18),E35/$C$1) -> 1050.92
E77: Labour Rate - | F77: =$D$9 -> 28.53 | R77: Mech. Cost to us
D80: Mat. Cost | E80: Labour | F80: Total Cost | R80: Sell Excl.VAT / Total Cost
D81: € | E81: Pair.Hrs | F81: €
D83: =R177 -> 680 | E83: =T177 -> 11 | F83: =R177+S177 -> 993.83 | R83: =IF(F83=0,0,F75/F83) -> 1.0574444
D84: ( From CostCode Totals )
R87: Advanced Payment:
R88: Retention:
R90: Awarded Date:
R91: Estimated Start Date:
R92: Estimated Completion Date:
D93: .................
D94: A. Sciberras | R94: Date issued:
D95: =NOW() -> 46119.647
D98: PANTA CONTRACTING LTD. - ELECTRICAL DIVISION
D99: ELECTRICAL AND ELV CONTRACT / VARIATION BUDGET COST
D101: Project: | E101: =E61 -> Portomaso L4 Dampers
D102: Job Desc: | E102: =E62 -> Damper for VAV boxes
D103: Client's Ref: | E103: =E64 -> 0
D106: COSTCODE | F106: Cost | Q106: Mat. | R106: Mat Cost | S106: Lab Cost @ | T106: Labour
F107: Code | Q107: Cont. | R107: € | S107: =$D$9 -> 28.53 | T107: Pair.Hrs
B108: V:56 | D108: BOQ RateOnly Items | P108: FIX | Q108: 1
B109: 1(J) | C109: cc | D109: Erection materials | F109: 501 | P109: 1 | Q109: 1 | R109: =Elec_Est!R86 -> 0 | S109: =T109*$D$9 -> 0 | T109: =Elec_Est!T86 -> 0
B110: 2 | C110: cc | D110: Busbar Trunking | F110: 505 | P110: 1 | Q110: 1 | R110: =Elec_Est!R87 -> 0 | S110: =T110*$D$9 -> 0 | T110: =Elec_Est!T87 -> 0
B111: 3 | C111: cc | D111: Switchgear | F111: 510 | P111: 2 | Q111: 1 | R111: =Elec_Est!R88 -> 0 | S111: =T111*$D$9 -> 0 | T111: =Elec_Est!T88 -> 0
B112: 4 | C112: cc | D112: MCC Equipment | F112: 511 | P112: 2 | Q112: 1 | R112: =Elec_Est!R89 -> 0 | S112: =T112*$D$9 -> 0 | T112: =Elec_Est!T89 -> 0
B113: 5 | C113: cc | D113: BMS Equipment | F113: 512 | P113: 2 | Q113: 1 | R113: =Elec_Est!R90 -> 0 | S113: =T113*$D$9 -> 0 | T113: =Elec_Est!T90 -> 0
B114: 6 | C114: cc | D114: PVC Pipes / Ducts | F114: 520 | P114: 1 | Q114: 1 | R114: =Elec_Est!R91 -> 0 | S114: =T114*$D$9 -> 0 | T114: =Elec_Est!T91 -> 0
B115: 7 | C115: cc | D115: High/medium voltage switchgear | F115: 530 | P115: 2 | Q115: 1 | R115: =Elec_Est!R92 -> 0 | S115: =T115*$D$9 -> 0 | T115: =Elec_Est!T92 -> 0
B116: 8 | C116: cc | D116: Power Transformers | F116: 550 | P116: 2 | Q116: 1 | R116: =Elec_Est!R93 -> 0 | S116: =T116*$D$9 -> 0 | T116: =Elec_Est!T93 -> 0
B117: 9 | C117: cc | D117: Control Panels | F117: 570 | P117: 2 | Q117: 1 | R117: =Elec_Est!R94 -> 0 | S117: =T117*$D$9 -> 0 | T117: =Elec_Est!T94 -> 0
B118: 10 | C118: cc | D118: Electrical Single Core Cables | F118: 615 | P118: 2 | Q118: 1 | R118: =Elec_Est!R95 -> 0 | S118: =T118*$D$9 -> 0 | T118: =Elec_Est!T95 -> 0
B119: 11(K) | C119: cc | D119: Electrical Multicore Cables | F119: 616 | P119: 2 | Q119: 1 | R119: =Elec_Est!R96 -> 0 | S119: =T119*$D$9 -> 0 | T119: =Elec_Est!T96 -> 0
B120: 12 | C120: cc | D120: ELV/BMS/Special Cables | F120: 617 | P120: 2 | Q120: 1 | R120: =Elec_Est!R97 -> 0 | S120: =T120*$D$9 -> 0 | T120: =Elec_Est!T97 -> 0
B121: 13 | C121: cc | D121: Cable Accessories | F121: 620 | P121: 2 | Q121: 1 | R121: =Elec_Est!R98 -> 0 | S121: =T121*$D$9 -> 0 | T121: =Elec_Est!T98 -> 0
B122: 14 | C122: cc | D122: Galv. Cable Trays | F122: 650 | P122: 1 | Q122: 1 | R122: =Elec_Est!R99 -> 0 | S122: =T122*$D$9 -> 0 | T122: =Elec_Est!T99 -> 0
B123: 15 | C123: cc | D123: PVC Cable Trays | F123: 651 | P123: 1 | Q123: 1 | R123: =Elec_Est!R100 -> 0 | S123: =T123*$D$9 -> 0 | T123: =Elec_Est!T100 -> 0
B124: 16 | C124: cc | D124: Galv. Cable Basket | F124: 652 | P124: 1 | Q124: 1 | R124: =Elec_Est!R101 -> 0 | S124: =T124*$D$9 -> 0 | T124: =Elec_Est!T101 -> 0
B125: 17 | C125: cc | D125: Galv. Cable Ladder | F125: 654 | P125: 1 | Q125: 1 | R125: =Elec_Est!R102 -> 0 | S125: =T125*$D$9 -> 0 | T125: =Elec_Est!T102 -> 0
B126: 18 | C126: cc | D126: Galv. Cable Trunking | F126: 675 | P126: 1 | Q126: 1 | R126: =Elec_Est!R103 -> 0 | S126: =T126*$D$9 -> 0 | T126: =Elec_Est!T103 -> 0
B127: 19 | C127: cc | D127: Alum. Cable Trunking | F127: 676 | P127: 1 | Q127: 1 | R127: =Elec_Est!R104 -> 0 | S127: =T127*$D$9 -> 0 | T127: =Elec_Est!T104 -> 0
B128: 20 | C128: cc | D128: PVC Cable Trunking | F128: 680 | P128: 1 | Q128: 1 | R128: =Elec_Est!R105 -> 0 | S128: =T128*$D$9 -> 0 | T128: =Elec_Est!T105 -> 0
...

Sheet Quote
A1: =IF(AND(UPPER(LEFT(TRIM($D$8),11))="01",UPPER(LEFT(TRIM($D$9),3))<>"ELM"),"PANTA RETAIL LTD.","PANTA CONTRACTING LIMITED") -> PANTA CONTRACTING LIMITED
A2: =IF(UPPER(LEFT(TRIM($D$9),3))="ELM","ELEC-FOR-MECH INTERNAL QUOTATION","ELECTRICAL INTERNAL QUOTATION") -> ELECTRICAL INTERNAL QUOTATION
B5: ATT: | D5: =IF(A2="Internal Quotation", "Mechanical Division","") | R5: Dated: | S5: =NOW() -> 46119.647
B6: CLIENT: | C6: Link to ML_SUM $D1 | D6: =ML_Sum!D1 -> UMUT - Electrical Team
B7: PROJECT: | C7: Link to ML_SUM $D2 | D7: =ML_Sum!D2 -> Portomaso L4 Dampers
B8: JOB DESC: | C8: Link to ML_SUM $D3 | D8: =ML_Sum!D3 -> Damper for VAV boxes
B9: QUOTE No: | C9: Link to ML_SUM $D4 | D9: =ML_Sum!D4 -> EL
B10: CLIENT's Ref: | C10: Link to ML_SUM $D5 | D10: =ML_Sum!D5 -> 0
D22: Selling Price (€) : | E22: =ML_Sum!E35 -> 1050.92 | F22: =ML_Sum!D6 -> VAT EXCL. | G22: VAT EXCLUDED. | H22: VAT EXCLUDED. | I22: VAT EXCLUDED. | J22: VAT EXCLUDED. | K22: VAT EXCLUDED. | L22: VAT EXCLUDED. | M22: VAT EXCLUDED. | N22: VAT EXCLUDED. | O22: VAT EXCLUDED. | P22: VAT EXCLUDED.
A51: Signed for and on behalf of | Q51: Signed for and on behalf of
A52: Electrical Division | Q52: Division
Q54: Records
Q55: Mr. A. Sciberras
Q57: File

Sheet Elec_Rates
B1: CLIENT: | C1: =ML_Sum!$C1 -> 1 | D1: =ML_Sum!$D1 -> UMUT - Electrical Team | F1: =ML_Sum!$F1 -> 0 | I1: 1 | J1: =ML_Sum!$J1 -> 1 | K1: =ML_Sum!$K1 -> 1 | L1: =ML_Sum!$L1 -> 1 | M1: =ML_Sum!$M1 -> 1 | N1: =ML_Sum!$N1 -> 1 | O1: =ML_Sum!$O1 -> 1 | Q1: =ML_Sum!$Q1 -> € | R1: R/Lab Cont | S1: =ML_Sum!$S1 -> R | T1: =ML_Sum!$T1 -> 1.1 | U1: =ML_Sum!W1 -> BOQ | V1: INCL | W1: MULT | X1: AREA | Y1: BOQ | Z1: TDWG | AA1: ACT | AB1: DIFF
B2: PROJECT: | C2: =ML_Sum!$C2 -> 1 | D2: =ML_Sum!$D2 -> Portomaso L4 Dampers | F2: =ML_Sum!$F2 -> Electrical Site Pair | I2: 2 | J2: =ML_Sum!$J2 -> 1 | K2: =ML_Sum!$K2 -> 1 | L2: =ML_Sum!$L2 -> 1 | M2: =ML_Sum!$M2 -> 1 | N2: =ML_Sum!$N2 -> 1 | O2: =ML_Sum!$O2 -> 1 | Q2: =ML_Sum!$Q2 -> 0 | R2: mu_A | S2: =ML_Sum!$S2 -> 1 | T2: =ML_Sum!$T2 -> 28.53
B3: JOB DESC: | C3: =ML_Sum!$C3 -> 1 | D3: =ML_Sum!$D3 -> Damper for VAV boxes | F3: =ML_Sum!$F3 -> ECA/BMS Pair | I3: 3 | J3: =ML_Sum!$J3 -> 1 | K3: =ML_Sum!$K3 -> 1 | L3: =ML_Sum!$L3 -> 1 | M3: =ML_Sum!$M3 -> 1 | N3: =ML_Sum!$N3 -> 1 | O3: =ML_Sum!$O3 -> 1 | Q3: =ML_Sum!$Q3 -> 0 | R3: mu_B | S3: =ML_Sum!$S3 -> 1 | T3: =ML_Sum!$T3 -> 33.72
B4: QUOTE No: | C4: =ML_Sum!$C4 -> 1 | D4: =ML_Sum!$D4 -> EL | F4: =ML_Sum!$F4 -> ECA/BMS Engineer | I4: 4 | J4: =ML_Sum!$J4 -> 1 | K4: =ML_Sum!$K4 -> 1 | L4: =ML_Sum!$L4 -> 1 | M4: =ML_Sum!$M4 -> 1 | N4: =ML_Sum!$N4 -> 1 | O4: =ML_Sum!$O4 -> 1 | Q4: =ML_Sum!$Q4 -> 0 | R4: mu_C | S4: =ML_Sum!$S4 -> 1 | T4: =ML_Sum!$T4 -> 31
B5: CLIENTs REF: | C5: =ML_Sum!$C5 -> 1 | D5: =ML_Sum!$D5 -> 0 | F5: =ML_Sum!$F5 -> BMS - Tech - Single | I5: 5 | J5: =ML_Sum!$J5 -> 1 | K5: =ML_Sum!$K5 -> 1 | L5: =ML_Sum!$L5 -> 1 | M5: =ML_Sum!$M5 -> 1 | N5: =ML_Sum!$N5 -> 1 | O5: =ML_Sum!$O5 -> 1 | Q5: =ML_Sum!$Q5 -> 0 | R5: mu_D | S5: =ML_Sum!$S5 -> 1 | T5: =ML_Sum!$T5 -> 21.44
B6: VAT/DUTIES: | C6: =ML_Sum!$C6 -> 1 | D6: =ML_Sum!$D6 -> VAT EXCL. | F6: =ML_Sum!$F6 -> Edward/Mark + AGV | I6: 6 | J6: =ML_Sum!$J6 -> 1 | K6: =ML_Sum!$K6 -> 1 | L6: =ML_Sum!$L6 -> 1 | M6: =ML_Sum!$M6 -> 1 | N6: =ML_Sum!$N6 -> 1 | O6: =ML_Sum!$O6 -> 1 | Q6: =ML_Sum!$Q6 -> 0 | R6: mu_E | S6: =ML_Sum!$S6 -> 1 | T6: =ML_Sum!$T6 -> 33.72
B7: SAVED ON: | C7: =ML_Sum!$C7 -> 1 | D7: 39364 | F7: =ML_Sum!$F7 -> 0 | I7: 7 | J7: =ML_Sum!$J7 -> 1 | K7: =ML_Sum!$K7 -> 1 | L7: =ML_Sum!$L7 -> 1 | M7: =ML_Sum!$M7 -> 1 | N7: =ML_Sum!$N7 -> 1 | O7: =ML_Sum!$O7 -> 0 | Q7: =ML_Sum!$Q7 -> 0 | R7: mu_F | S7: =ML_Sum!$S7 -> 0 | T7: =ML_Sum!$T7 -> 0
B8: ESTIMATOR: | C8: =ML_Sum!$C8 -> 1 | D8: =ML_Sum!$D8 -> G. Baranyay | F8: =ML_Sum!$F8 -> 0 | I8: 8 | J8: =ML_Sum!$J8 -> 1 | K8: =ML_Sum!$K8 -> 1 | L8: =ML_Sum!$L8 -> 1 | M8: =ML_Sum!$M8 -> 1 | N8: =ML_Sum!$N8 -> 1 | O8: =ML_Sum!$O8 -> 0 | Q8: =ML_Sum!$Q8 -> 0 | R8: mu_G | S8: =ML_Sum!$S8 -> 0 | T8: =ML_Sum!$T8 -> 0
B9: LABOUR RATE: | C9: =ML_Sum!$C9 -> 1 | D9: =ML_Sum!$D9 -> 28.53 | F9: =ML_Sum!$F9 -> 0 | I9: 9 | J9: =ML_Sum!$J9 -> 1 | K9: =ML_Sum!$K9 -> 1 | L9: =ML_Sum!$L9 -> 1 | M9: =ML_Sum!$M9 -> 1 | N9: =ML_Sum!$N9 -> 1 | O9: =ML_Sum!$O9 -> 0 | Q9: =ML_Sum!$Q9 -> 0 | R9: mu_H | S9: =ML_Sum!$S9 -> 0 | T9: =ML_Sum!$T9 -> 0
C10: =ML_Sum!$C10 -> 1 | F10: =ML_Sum!$F10 -> 0 | I10: 10 | J10: =ML_Sum!$J10 -> 1 | K10: =ML_Sum!$K10 -> 1 | L10: =ML_Sum!$L10 -> 1 | M10: =ML_Sum!$M10 -> 1 | N10: =ML_Sum!$N10 -> 1 | O10: =ML_Sum!$O10 -> 1 | Q10: =ML_Sum!$Q10 -> 0 | R10: mu_I | S10: =ML_Sum!$S10 -> 0 | T10: =ML_Sum!$T10 -> 0
C11: =ML_Sum!$C11 -> 1 | F11: =ML_Sum!$F11 -> 0 | Q11: =ML_Sum!$Q11 -> 0 | R11: mu_J | S11: =ML_Sum!$S11 -> 0 | T11: =ML_Sum!$T11 -> 0
C12: =ML_Sum!$C12 -> 1 | F12: =ML_Sum!$F12 -> 0 | Q12: =ML_Sum!$Q12 -> 0 | R12: MIXED | S12: =ML_Sum!$S12 -> MAT MU | T12: =ML_Sum!$T12 -> LAB RATE
G13: I_CODE | H13: C_CODE | I13: MAKE | J13: PART_NO | K13: MARKUP | L13: TYPE | M13: LIST_P | N13: P_FACT | O13: FIX | P13: DATE | Q13: %Dsct in BOQ | R13: MU TYPE | S13: MAT MU | T13: LAB RATE
C15: t | D15: Item:
D16: Start Typing Header
Q18: Multip
A19: 1 | B19: =Elec_Est!B162 -> 0 | D19: 001# Controllers | K19: RATE | L19: RATE | Q19: =B19/A19 -> 0 | R19: =IF($B19=0,0,IF($S$1="R",ROUND(R25/$B19,2),R25/$B19)) -> 0 | T19: =IF($B19=0,0,IF($S$1="R",ROUND(T25/$B19,2),T25/$B19)) -> 0
D20: Based on:
R21: =$A21*Q21 -> 0 | T21: =$A21*S21*$T$1 -> 0
A22: 1 | B22: No | D22: Controllers | G22: BMSE_001 | H22: 410 | I22: (__) | O22: 3 | R22: =$A22*Q22 -> 0 | T22: =$A22*S22*$T$1 -> 0
R23: =$A23*Q23 -> 0 | T23: =$A23*S23*$T$1 -> 0
C24: << ==== TOTAL UNITS | R24: =$A24*Q24 -> 0 | T24: =$A24*S24*$T$1 -> 0
A25: d> | B25: =(R25+T25)-SUM(R20:R24,T20:T24) -> 0 | D25: Sell_A | E25: =IF($B19=0,0,ROUND(ROUND(($R25*$S$2+($T25*$T$2))/$B19, 2)*$C$2,2)) -> 0 | F25: =ROUND($B19*$E25,2) -> 0 | K25: ITEM | L25: ITEM | R25: =SUM(R20:R24) -> 0 | T25: =SUM(T20:T24) -> 0
Q26: Multip
A27: 1 | B27: =Elec_Est!B163 -> 0 | D27: 002# Controller Modules | K27: RATE | L27: RATE | Q27: =B27/A27 -> 0 | R27: =IF($B27=0,0,IF($S$1="R",ROUND(R33/$B27,2),R33/$B27)) -> 0 | T27: =IF($B27=0,0,IF($S$1="R",ROUND(T33/$B27,2),T33/$B27)) -> 0
D28: Based on:
R29: =$A29*Q29 -> 0 | T29: =$A29*S29*$T$1 -> 0
A30: 1 | B30: No | D30: Controller Modules | G30: BMSE_001 | H30: 411 | I30: (__) | O30: 3 | R30: =$A30*Q30 -> 0 | T30: =$A30*S30*$T$1 -> 0
R31: =$A31*Q31 -> 0 | T31: =$A31*S31*$T$1 -> 0
C32: << ==== TOTAL UNITS | R32: =$A32*Q32 -> 0 | T32: =$A32*S32*$T$1 -> 0
A33: d> | B33: =(R33+T33)-SUM(R28:R32,T28:T32) -> 0 | D33: Sell_A | E33: =IF($B27=0,0,ROUND(ROUND(($R33*$S$2+($T33*$T$2))/$B27, 2)*$C$2,2)) -> 0 | F33: =ROUND($B27*$E33,2) -> 0 | K33: ITEM | L33: ITEM | R33: =SUM(R28:R32) -> 0 | T33: =SUM(T28:T32) -> 0
Q34: Multip
A35: 1 | B35: =Elec_Est!B164 -> 0 | D35: 003# Signal Cable | K35: RATE | L35: RATE | Q35: =B35/A35 -> 0 | R35: =IF($B35=0,0,IF($S$1="R",ROUND(R41/$B35,2),R41/$B35)) -> 0 | T35: =IF($B35=0,0,IF($S$1="R",ROUND(T41/$B35,2),T41/$B35)) -> 0
D36: Based on:
R37: =$A37*Q37 -> 0 | T37: =$A37*S37*$T$1 -> 0
A38: 1 | B38: No | D38: Signal Cable | G38: BMSE_001 | H38: 412 | I38: (__) | O38: 3 | R38: =$A38*Q38 -> 0 | T38: =$A38*S38*$T$1 -> 0
R39: =$A39*Q39 -> 0 | T39: =$A39*S39*$T$1 -> 0
C40: << ==== TOTAL UNITS | R40: =$A40*Q40 -> 0 | T40: =$A40*S40*$T$1 -> 0
A41: d> | B41: =(R41+T41)-SUM(R36:R40,T36:T40) -> 0 | D41: Sell_A | E41: =IF($B35=0,0,ROUND(ROUND(($R41*$S$2+($T41*$T$2))/$B35, 2)*$C$2,2)) -> 0 | F41: =ROUND($B35*$E41,2) -> 0 | K41: ITEM | L41: ITEM | R41: =SUM(R36:R40) -> 0 | T41: =SUM(T36:T40) -> 0
Q42: Multip
A43: 1 | B43: =Elec_Est!B165 -> 0 | D43: 004# Modbus Cable | K43: RATE | L43: RATE | Q43: =B43/A43 -> 0 | R43: =IF($B43=0,0,IF($S$1="R",ROUND(R49/$B43,2),R49/$B43)) -> 0 | T43: =IF($B43=0,0,IF($S$1="R",ROUND(T49/$B43,2),T49/$B43)) -> 0
D44: Based on:
R45: =$A45*Q45 -> 0 | T45: =$A45*S45*$T$1 -> 0
A46: 1 | B46: No | D46: Modbus Cable | G46: BMSE_001 | H46: 413 | I46: (__) | O46: 3 | R46: =$A46*Q46 -> 0 | T46: =$A46*S46*$T$1 -> 0
R47: =$A47*Q47 -> 0 | T47: =$A47*S47*$T$1 -> 0
C48: << ==== TOTAL UNITS | R48: =$A48*Q48 -> 0 | T48: =$A48*S48*$T$1 -> 0
A49: d> | B49: =(R49+T49)-SUM(R44:R48,T44:T48) -> 0 | D49: Sell_A | E49: =IF($B43=0,0,ROUND(ROUND(($R49*$S$2+($T49*$T$2))/$B43, 2)*$C$2,2)) -> 0 | F49: =ROUND($B43*$E49,2) -> 0 | K49: ITEM | L49: ITEM | R49: =SUM(R44:R48) -> 0 | T49: =SUM(T44:T48) -> 0
Q50: Multip
A51: 1 | B51: =Elec_Est!B166 -> 0 | D51: 005# CAT Cable | K51: RATE | L51: RATE | Q51: =B51/A51 -> 0 | R51: =IF($B51=0,0,IF($S$1="R",ROUND(R57/$B51,2),R57/$B51)) -> 0 | T51: =IF($B51=0,0,IF($S$1="R",ROUND(T57/$B51,2),T57/$B51)) -> 0
D52: Based on:
R53: =$A53*Q53 -> 0 | T53: =$A53*S53*$T$1 -> 0
A54: 1 | B54: No | D54: CAT Cable | G54: BMSE_001 | H54: 414 | I54: (__) | O54: 3 | R54: =$A54*Q54 -> 0 | T54: =$A54*S54*$T$1 -> 0
R55: =$A55*Q55 -> 0 | T55: =$A55*S55*$T$1 -> 0
C56: << ==== TOTAL UNITS | R56: =$A56*Q56 -> 0 | T56: =$A56*S56*$T$1 -> 0
A57: d> | B57: =(R57+T57)-SUM(R52:R56,T52:T56) -> 0 | D57: Sell_A | E57: =IF($B51=0,0,ROUND(ROUND(($R57*$S$2+($T57*$T$2))/$B51, 2)*$C$2,2)) -> 0 | F57: =ROUND($B51*$E57,2) -> 0 | K57: ITEM | L57: ITEM | R57: =SUM(R52:R56) -> 0 | T57: =SUM(T52:T56) -> 0
Q58: Multip
A59: 1 | B59: =Elec_Est!B167 -> 0 | D59: 006# Control Panels MCC DDC Security Fire | K59: RATE | L59: RATE | Q59: =B59/A59 -> 0 | R59: =IF($B59=0,0,IF($S$1="R",ROUND(R65/$B59,2),R65/$B59)) -> 0 | T59: =IF($B59=0,0,IF($S$1="R",ROUND(T65/$B59,2),T65/$B59)) -> 0
D60: Based on:
R61: =$A61*Q61 -> 0 | T61: =$A61*S61*$T$1 -> 0
A62: 1 | B62: No | D62: Control Panels MCC DDC Security Fire | G62: BMSE_001 | H62: 415 | I62: (__) | O62: 3 | R62: =$A62*Q62 -> 0 | T62: =$A62*S62*$T$1 -> 0
R63: =$A63*Q63 -> 0 | T63: =$A63*S63*$T$1 -> 0
C64: << ==== TOTAL UNITS | R64: =$A64*Q64 -> 0 | T64: =$A64*S64*$T$1 -> 0
A65: d> | B65: =(R65+T65)-SUM(R60:R64,T60:T64) -> 0 | D65: Sell_A | E65: =IF($B59=0,0,ROUND(ROUND(($R65*$S$2+($T65*$T$2))/$B59, 2)*$C$2,2)) -> 0 | F65: =ROUND($B59*$E65,2) -> 0 | K65: ITEM | L65: ITEM | R65: =SUM(R60:R64) -> 0 | T65: =SUM(T60:T64) -> 0
Q66: Multip
A67: 1 | B67: =Elec_Est!B168 -> 0 | D67: 007# Field Devices | K67: RATE | L67: RATE | Q67: =B67/A67 -> 0 | R67: =IF($B67=0,0,IF($S$1="R",ROUND(R73/$B67,2),R73/$B67)) -> 0 | T67: =IF($B67=0,0,IF($S$1="R",ROUND(T73/$B67,2),T73/$B67)) -> 0
D68: Based on:
R69: =$A69*Q69 -> 0 | T69: =$A69*S69*$T$1 -> 0
A70: 1 | B70: No | D70: Field Devices | G70: BMSE_001 | H70: 416 | I70: (__) | O70: 3 | R70: =$A70*Q70 -> 0 | T70: =$A70*S70*$T$1 -> 0
R71: =$A71*Q71 -> 0 | T71: =$A71*S71*$T$1 -> 0
C72: << ==== TOTAL UNITS | R72: =$A72*Q72 -> 0 | T72: =$A72*S72*$T$1 -> 0
A73: d> | B73: =(R73+T73)-SUM(R68:R72,T68:T72) -> 0 | D73: Sell_A | E73: =IF($B67=0,0,ROUND(ROUND(($R73*$S$2+($T73*$T$2))/$B67, 2)*$C$2,2)) -> 0 | F73: =ROUND($B67*$E73,2) -> 0 | K73: ITEM | L73: ITEM | R73: =SUM(R68:R72) -> 0 | T73: =SUM(T68:T72) -> 0
Q74: Multip
A75: 1 | B75: =Elec_Est!B169 -> 0 | D75: 008# DALI - KNX | K75: RATE | L75: RATE | Q75: =B75/A75 -> 0 | R75: =IF($B75=0,0,IF($S$1="R",ROUND(R81/$B75,2),R81/$B75)) -> 0 | T75: =IF($B75=0,0,IF($S$1="R",ROUND(T81/$B75,2),T81/$B75)) -> 0
D76: Based on:
R77: =$A77*Q77 -> 0 | T77: =$A77*S77*$T$1 -> 0
A78: 1 | B78: No | D78: DALI - KNX | G78: BMSE_001 | H78: 417 | I78: (__) | O78: 3 | R78: =$A78*Q78 -> 0 | T78: =$A78*S78*$T$1 -> 0
R79: =$A79*Q79 -> 0 | T79: =$A79*S79*$T$1 -> 0
C80: << ==== TOTAL UNITS | R80: =$A80*Q80 -> 0 | T80: =$A80*S80*$T$1 -> 0
A81: d> | B81: =(R81+T81)-SUM(R76:R80,T76:T80) -> 0 | D81: Sell_A | E81: =IF($B75=0,0,ROUND(ROUND(($R81*$S$2+($T81*$T$2))/$B75, 2)*$C$2,2)) -> 0 | F81: =ROUND($B75*$E81,2) -> 0 | K81: ITEM | L81: ITEM | R81: =SUM(R76:R80) -> 0 | T81: =SUM(T76:T80) -> 0
Q82: Multip
A83: 1 | B83: =Elec_Est!B170 -> 0 | D83: 009# Fire Equipment | K83: RATE | L83: RATE | Q83: =B83/A83 -> 0 | R83: =IF($B83=0,0,IF($S$1="R",ROUND(R89/$B83,2),R89/$B83)) -> 0 | T83: =IF($B83=0,0,IF($S$1="R",ROUND(T89/$B83,2),T89/$B83)) -> 0
D84: Based on:
R85: =$A85*Q85 -> 0 | T85: =$A85*S85*$T$1 -> 0
A86: 1 | B86: No | D86: Fire Equipment | G86: BMSE_001 | H86: 418 | I86: (__) | O86: 3 | R86: =$A86*Q86 -> 0 | T86: =$A86*S86*$T$1 -> 0
R87: =$A87*Q87 -> 0 | T87: =$A87*S87*$T$1 -> 0
C88: << ==== TOTAL UNITS | R88: =$A88*Q88 -> 0 | T88: =$A88*S88*$T$1 -> 0
A89: d> | B89: =(R89+T89)-SUM(R84:R88,T84:T88) -> 0 | D89: Sell_A | E89: =IF($B83=0,0,ROUND(ROUND(($R89*$S$2+($T89*$T$2))/$B83, 2)*$C$2,2)) -> 0 | F89: =ROUND($B83*$E89,2) -> 0 | K89: ITEM | L89: ITEM | R89: =SUM(R84:R88) -> 0 | T89: =SUM(T84:T88) -> 0
Q90: Multip
A91: 1 | B91: =Elec_Est!B171 -> 0 | D91: 010# Data Networks Equipment | K91: RATE | L91: RATE | Q91: =B91/A91 -> 0 | R91: =IF($B91=0,0,IF($S$1="R",ROUND(R97/$B91,2),R97/$B91)) -> 0 | T91: =IF($B91=0,0,IF($S$1="R",ROUND(T97/$B91,2),T97/$B91)) -> 0
D92: Based on:
R93: =$A93*Q93 -> 0 | T93: =$A93*S93*$T$1 -> 0
A94: 1 | B94: No | D94: Data Networks Equipment | G94: BMSE_001 | H94: 419 | I94: (__) | O94: 3 | R94: =$A94*Q94 -> 0 | T94: =$A94*S94*$T$1 -> 0
R95: =$A95*Q95 -> 0 | T95: =$A95*S95*$T$1 -> 0
C96: << ==== TOTAL UNITS | R96: =$A96*Q96 -> 0 | T96: =$A96*S96*$T$1 -> 0
A97: d> | B97: =(R97+T97)-SUM(R92:R96,T92:T96) -> 0 | D97: Sell_A | E97: =IF($B91=0,0,ROUND(ROUND(($R97*$S$2+($T97*$T$2))/$B91, 2)*$C$2,2)) -> 0 | F97: =ROUND($B91*$E97,2) -> 0 | K97: ITEM | L97: ITEM | R97: =SUM(R92:R96) -> 0 | T97: =SUM(T92:T96) -> 0
Q98: Multip
A99: 1 | B99: =Elec_Est!B172 -> 0 | D99: 011# Panel Building | K99: RATE | L99: RATE | Q99: =B99/A99 -> 0 | R99: =IF($B99=0,0,IF($S$1="R",ROUND(R105/$B99,2),R105/$B99)) -> 0 | T99: =IF($B99=0,0,IF($S$1="R",ROUND(T105/$B99,2),T105/$B99)) -> 0
D100: Based on:
R101: =$A101*Q101 -> 0 | T101: =$A101*S101*$T$1 -> 0
A102: 1 | B102: No | D102: Panel Building | G102: BMSE_001 | H102: 420 | I102: (__) | O102: 3 | R102: =$A102*Q102 -> 0 | T102: =$A102*S102*$T$1 -> 0
...

Sheet Elec_Est
B1: CLIENT: | C1: =ML_Sum!$C1 -> 1 | D1: =ML_Sum!$D1 -> UMUT - Electrical Team | F1: =ML_Sum!$F1 -> 0 | I1: 1 | J1: =ML_Sum!$J1 -> 1 | K1: =ML_Sum!$K1 -> 1 | L1: =ML_Sum!$L1 -> 1 | M1: =ML_Sum!$M1 -> 1 | N1: =ML_Sum!$N1 -> 1 | O1: =ML_Sum!$O1 -> 1 | Q1: =ML_Sum!$Q1 -> € | R1: R/Lab Cont | S1: =ML_Sum!$S1 -> R | T1: =ML_Sum!$T1 -> 1.1 | U1: =ML_Sum!W1 -> BOQ | V1: INCL | W1: MULT | X1: AREA | Y1: BOQ | Z1: TDWG | AA1: ACT | AB1: DIFF
B2: PROJECT: | C2: =ML_Sum!$C2 -> 1 | D2: =ML_Sum!$D2 -> Portomaso L4 Dampers | F2: =ML_Sum!$F2 -> Electrical Site Pair | I2: 2 | J2: =ML_Sum!$J2 -> 1 | K2: =ML_Sum!$K2 -> 1 | L2: =ML_Sum!$L2 -> 1 | M2: =ML_Sum!$M2 -> 1 | N2: =ML_Sum!$N2 -> 1 | O2: =ML_Sum!$O2 -> 1 | Q2: =ML_Sum!$Q2 -> 0 | R2: mu_A | S2: =ML_Sum!$S2 -> 1 | T2: =ML_Sum!$T2 -> 28.53
B3: JOB DESC: | C3: =ML_Sum!$C3 -> 1 | D3: =ML_Sum!$D3 -> Damper for VAV boxes | F3: =ML_Sum!$F3 -> ECA/BMS Pair | I3: 3 | J3: =ML_Sum!$J3 -> 1 | K3: =ML_Sum!$K3 -> 1 | L3: =ML_Sum!$L3 -> 1 | M3: =ML_Sum!$M3 -> 1 | N3: =ML_Sum!$N3 -> 1 | O3: =ML_Sum!$O3 -> 1 | Q3: =ML_Sum!$Q3 -> 0 | R3: mu_B | S3: =ML_Sum!$S3 -> 1 | T3: =ML_Sum!$T3 -> 33.72
B4: QUOTE No: | C4: =ML_Sum!$C4 -> 1 | D4: =ML_Sum!$D4 -> EL | F4: =ML_Sum!$F4 -> ECA/BMS Engineer | I4: 4 | J4: =ML_Sum!$J4 -> 1 | K4: =ML_Sum!$K4 -> 1 | L4: =ML_Sum!$L4 -> 1 | M4: =ML_Sum!$M4 -> 1 | N4: =ML_Sum!$N4 -> 1 | O4: =ML_Sum!$O4 -> 1 | Q4: =ML_Sum!$Q4 -> 0 | R4: mu_C | S4: =ML_Sum!$S4 -> 1 | T4: =ML_Sum!$T4 -> 31
B5: CLIENTs REF: | C5: =ML_Sum!$C5 -> 1 | D5: =ML_Sum!$D5 -> 0 | F5: =ML_Sum!$F5 -> BMS - Tech - Single | I5: 5 | J5: =ML_Sum!$J5 -> 1 | K5: =ML_Sum!$K5 -> 1 | L5: =ML_Sum!$L5 -> 1 | M5: =ML_Sum!$M5 -> 1 | N5: =ML_Sum!$N5 -> 1 | O5: =ML_Sum!$O5 -> 1 | Q5: =ML_Sum!$Q5 -> 0 | R5: mu_D | S5: =ML_Sum!$S5 -> 1 | T5: =ML_Sum!$T5 -> 21.44
B6: VAT/DUTIES: | C6: =ML_Sum!$C6 -> 1 | D6: =ML_Sum!$D6 -> VAT EXCL. | F6: =ML_Sum!$F6 -> Edward/Mark + AGV | I6: 6 | J6: =ML_Sum!$J6 -> 1 | K6: =ML_Sum!$K6 -> 1 | L6: =ML_Sum!$L6 -> 1 | M6: =ML_Sum!$M6 -> 1 | N6: =ML_Sum!$N6 -> 1 | O6: =ML_Sum!$O6 -> 1 | Q6: =ML_Sum!$Q6 -> 0 | R6: mu_E | S6: =ML_Sum!$S6 -> 1 | T6: =ML_Sum!$T6 -> 33.72
B7: SAVED ON: | C7: =ML_Sum!$C7 -> 1 | D7: 39364 | F7: =ML_Sum!$F7 -> 0 | I7: 7 | J7: =ML_Sum!$J7 -> 1 | K7: =ML_Sum!$K7 -> 1 | L7: =ML_Sum!$L7 -> 1 | M7: =ML_Sum!$M7 -> 1 | N7: =ML_Sum!$N7 -> 1 | O7: =ML_Sum!$O7 -> 0 | Q7: =ML_Sum!$Q7 -> 0 | R7: mu_F | S7: =ML_Sum!$S7 -> 0 | T7: =ML_Sum!$T7 -> 0
B8: ESTIMATOR: | C8: =ML_Sum!$C8 -> 1 | D8: =ML_Sum!$D8 -> G. Baranyay | F8: =ML_Sum!$F8 -> 0 | I8: 8 | J8: =ML_Sum!$J8 -> 1 | K8: =ML_Sum!$K8 -> 1 | L8: =ML_Sum!$L8 -> 1 | M8: =ML_Sum!$M8 -> 1 | N8: =ML_Sum!$N8 -> 1 | O8: =ML_Sum!$O8 -> 0 | Q8: =ML_Sum!$Q8 -> 0 | R8: mu_G | S8: =ML_Sum!$S8 -> 0 | T8: =ML_Sum!$T8 -> 0
B9: LABOUR RATE: | C9: =ML_Sum!$C9 -> 1 | D9: =ML_Sum!$D9 -> 28.53 | F9: =ML_Sum!$F9 -> 0 | I9: 9 | J9: =ML_Sum!$J9 -> 1 | K9: =ML_Sum!$K9 -> 1 | L9: =ML_Sum!$L9 -> 1 | M9: =ML_Sum!$M9 -> 1 | N9: =ML_Sum!$N9 -> 1 | O9: =ML_Sum!$O9 -> 0 | Q9: =ML_Sum!$Q9 -> 0 | R9: mu_H | S9: =ML_Sum!$S9 -> 0 | T9: =ML_Sum!$T9 -> 0
C10: =ML_Sum!$C10 -> 1 | F10: =ML_Sum!$F10 -> 0 | I10: 10 | J10: =ML_Sum!$J10 -> 1 | K10: =ML_Sum!$K10 -> 1 | L10: =ML_Sum!$L10 -> 1 | M10: =ML_Sum!$M10 -> 1 | N10: =ML_Sum!$N10 -> 1 | O10: =ML_Sum!$O10 -> 1 | Q10: =ML_Sum!$Q10 -> 0 | R10: mu_I | S10: =ML_Sum!$S10 -> 0 | T10: =ML_Sum!$T10 -> 0
C11: =ML_Sum!$C11 -> 1 | F11: =ML_Sum!$F11 -> 0 | Q11: =ML_Sum!$Q11 -> 0 | R11: mu_J | S11: =ML_Sum!$S11 -> 0 | T11: =ML_Sum!$T11 -> 0
C12: =ML_Sum!$C12 -> 1 | F12: =ML_Sum!$F12 -> 0 | Q12: =ML_Sum!$Q12 -> 0 | R12: MIXED | S12: =ML_Sum!$S12 -> MAT MU | T12: =ML_Sum!$T12 -> LAB RATE
G13: ISELL | H13: C_CODE | I13: MAKE | J13: PART_NO | K13: MARKUP | L13: TYPE | M13: LIST_P | N13: P_FACT | O13: FIX | P13: DATE | Q13: %Dsct in BOQ | R13: MU TYPE | S13: MAT MU | T13: LAB RATE | AM13: Tot Mat Cost | AN13: Unit Lab phr. | AO13: Tot Lab phr. | AP13: < for ELM / MEE
K14: TB
C15: t | D15: Item:
D16: Supply and Installation of the following:
E18: Sell Rate | F18: Sell Total | K18: IB | AG18: U_M_Sell | AH18: T_M_Sell | AI18: U_L_Sell | AJ18: T_L_Sell | AK18: Total_Sell | AM18: T_M_Cost | AN18: U_L_Phr | AO18: T_L_Phr | AP18: Mat/Lab=1
A19: 1 | B19: No | D19: Item: 14 | E19: =IF(AND($A19=0,$A$1="DIF"),0, ROUND(ROUND(($R27*$S$3+($T27*$T$3))/$A19,2)*$C$3,2)) -> 262.73 | F19: =ROUND($A19*$E19,2) -> 262.73 | G19: ISELL | K19: mu_B | L19: ITEM | T19: =IF(AND($R27=0,$T27=0),"0.00","mu: "& ROUND(F19/$C$3/($R27+$T27*$D$9),2)) -> mu: 1.06 | AG19: =IF($E19=0,0,ROUND($R27*$S$3*$C$3/$A19,2)) -> 170 | AH19: =$AG19*$A19 -> 170 | AI19: =$E19-$AG19 -> 92.73 | AJ19: =$A19*$AI19 -> 92.73 | AK19: =ROUND(($AG19+$AI19)*$A19,2) -> 262.73 | AM19: =ROUND(R27,2) -> 170 | AN19: =IF(A19=0,0,AO19/A19) -> 2.75 | AO19: =ROUND(T27,2) -> 2.75 | AP19: =ROUND(AM19+AO19,2)*A19 -> 172.75
D20: 230V / 0-10V - Actuator - 2NM for VAV box 350mm x 350mm | K20: n
R21: =$A21*Q21 -> 0 | T21: =$A21*S21*$T$1 -> 0
A22: 1 | B22: No | D22: Fast running rotary actuator, 2 Nm, AC 100...240 V, 2...10 V | E22: TMC230ASR | F22: Belimo | G22: BMSE_001 | H22: 416 | I22: (__) | O22: 3 | Q22: =135+20 -> 155 | R22: =$A22*Q22 -> 155 | T22: =$A22*S22*$T$1 -> 0
D23: (incl Delivery Fee and Fitment) | R23: =$A23*Q23 -> 0 | T23: =$A23*S23*$T$1 -> 0
A24: 1 | B24: No | D24: Termination, Testing, Sundries for Fitment | G24: BMSE_001 | H24: 421 | I24: (__) | O24: 3 | Q24: 15 | R24: =$A24*Q24 -> 15 | S24: 2.5 | T24: =$A24*S24*$T$1 -> 2.75
R25: =$A25*Q25 -> 0 | T25: =$A25*S25*$T$1 -> 0
R26: =$A26*Q26 -> 0 | T26: =$A26*S26*$T$1 -> 0
A27: d> | B27: =(R26+T26) -> 0 | G27: ICOST | K27: mu_B | L27: ITEM | R27: =SUM(R20:R26) -> 170 | T27: =SUM(T20:T26) -> 2.75
E28: Sell Rate | F28: Sell Total | K28: IB | AG28: U_M_Sell | AH28: T_M_Sell | AI28: U_L_Sell | AJ28: T_L_Sell | AK28: Total_Sell | AM28: T_M_Cost | AN28: U_L_Phr | AO28: T_L_Phr | AP28: Mat/Lab=1
A29: 1 | B29: No | D29: Item: 21 | E29: =IF(AND($A29=0,$A$1="DIF"),0, ROUND(ROUND(($R37*$S$3+($T37*$T$3))/$A29,2)*$C$3,2)) -> 262.73 | F29: =ROUND($A29*$E29,2) -> 262.73 | G29: ISELL | K29: mu_B | L29: ITEM | T29: =IF(AND($R37=0,$T37=0),"0.00","mu: "& ROUND(F29/$C$3/($R37+$T37*$D$9),2)) -> mu: 1.06 | AG29: =IF($E29=0,0,ROUND($R37*$S$3*$C$3/$A29,2)) -> 170 | AH29: =$AG29*$A29 -> 170 | AI29: =$E29-$AG29 -> 92.73 | AJ29: =$A29*$AI29 -> 92.73 | AK29: =ROUND(($AG29+$AI29)*$A29,2) -> 262.73 | AM29: =ROUND(R37,2) -> 170 | AN29: =IF(A29=0,0,AO29/A29) -> 2.75 | AO29: =ROUND(T37,2) -> 2.75 | AP29: =ROUND(AM29+AO29,2)*A29 -> 172.75
D30: 230V / 0-10V - Actuator - 2NM for VAV box 350mm x 350mm | K30: n
R31: =$A31*Q31 -> 0 | T31: =$A31*S31*$T$1 -> 0
A32: 1 | B32: No | D32: Fast running rotary actuator, 2 Nm, AC 100...240 V, 2...10 V | E32: TMC230ASR | F32: Belimo | G32: BMSE_001 | H32: 416 | I32: (__) | O32: 3 | Q32: =135+20 -> 155 | R32: =$A32*Q32 -> 155 | T32: =$A32*S32*$T$1 -> 0
D33: (incl Delivery Fee and Fitment) | R33: =$A33*Q33 -> 0 | T33: =$A33*S33*$T$1 -> 0
A34: 1 | B34: No | D34: Termination, Testing, Sundries for Fitment | G34: BMSE_001 | H34: 421 | I34: (__) | O34: 3 | Q34: 15 | R34: =$A34*Q34 -> 15 | S34: 2.5 | T34: =$A34*S34*$T$1 -> 2.75
R35: =$A35*Q35 -> 0 | T35: =$A35*S35*$T$1 -> 0
R36: =$A36*Q36 -> 0 | T36: =$A36*S36*$T$1 -> 0
A37: d> | B37: =(R36+T36) -> 0 | G37: ICOST | K37: mu_B | L37: ITEM | R37: =SUM(R30:R36) -> 170 | T37: =SUM(T30:T36) -> 2.75
E38: Sell Rate | F38: Sell Total | K38: IB | AG38: U_M_Sell | AH38: T_M_Sell | AI38: U_L_Sell | AJ38: T_L_Sell | AK38: Total_Sell | AM38: T_M_Cost | AN38: U_L_Phr | AO38: T_L_Phr | AP38: Mat/Lab=1
A39: 1 | B39: No | D39: Item: 27 | E39: =IF(AND($A39=0,$A$1="DIF"),0, ROUND(ROUND(($R47*$S$3+($T47*$T$3))/$A39,2)*$C$3,2)) -> 262.73 | F39: =ROUND($A39*$E39,2) -> 262.73 | G39: ISELL | K39: mu_B | L39: ITEM | T39: =IF(AND($R47=0,$T47=0),"0.00","mu: "& ROUND(F39/$C$3/($R47+$T47*$D$9),2)) -> mu: 1.06 | AG39: =IF($E39=0,0,ROUND($R47*$S$3*$C$3/$A39,2)) -> 170 | AH39: =$AG39*$A39 -> 170 | AI39: =$E39-$AG39 -> 92.73 | AJ39: =$A39*$AI39 -> 92.73 | AK39: =ROUND(($AG39+$AI39)*$A39,2) -> 262.73 | AM39: =ROUND(R47,2) -> 170 | AN39: =IF(A39=0,0,AO39/A39) -> 2.75 | AO39: =ROUND(T47,2) -> 2.75 | AP39: =ROUND(AM39+AO39,2)*A39 -> 172.75
D40: 230V / 0-10V - Actuator - 2NM for VAV box 400mm x 200mm | K40: n
R41: =$A41*Q41 -> 0 | T41: =$A41*S41*$T$1 -> 0
A42: 1 | B42: No | D42: Fast running rotary actuator, 2 Nm, AC 100...240 V, 2...10 V | E42: TMC230ASR | F42: Belimo | G42: BMSE_001 | H42: 416 | I42: (__) | O42: 3 | Q42: =135+20 -> 155 | R42: =$A42*Q42 -> 155 | T42: =$A42*S42*$T$1 -> 0
D43: (incl Delivery Fee and Fitment) | R43: =$A43*Q43 -> 0 | T43: =$A43*S43*$T$1 -> 0
A44: 1 | B44: No | D44: Termination, Testing, Sundries for Fitment | G44: BMSE_001 | H44: 421 | I44: (__) | O44: 3 | Q44: 15 | R44: =$A44*Q44 -> 15 | S44: 2.5 | T44: =$A44*S44*$T$1 -> 2.75
R45: =$A45*Q45 -> 0 | T45: =$A45*S45*$T$1 -> 0
R46: =$A46*Q46 -> 0 | T46: =$A46*S46*$T$1 -> 0
A47: d> | B47: =(R46+T46) -> 0 | G47: ICOST | K47: mu_B | L47: ITEM | R47: =SUM(R40:R46) -> 170 | T47: =SUM(T40:T46) -> 2.75
E48: Sell Rate | F48: Sell Total | K48: IB | AG48: U_M_Sell | AH48: T_M_Sell | AI48: U_L_Sell | AJ48: T_L_Sell | AK48: Total_Sell | AM48: T_M_Cost | AN48: U_L_Phr | AO48: T_L_Phr | AP48: Mat/Lab=1
A49: 1 | B49: No | D49: Item: 34 | E49: =IF(AND($A49=0,$A$1="DIF"),0, ROUND(ROUND(($R57*$S$3+($T57*$T$3))/$A49,2)*$C$3,2)) -> 262.73 | F49: =ROUND($A49*$E49,2) -> 262.73 | G49: ISELL | K49: mu_B | L49: ITEM | T49: =IF(AND($R57=0,$T57=0),"0.00","mu: "& ROUND(F49/$C$3/($R57+$T57*$D$9),2)) -> mu: 1.06 | AG49: =IF($E49=0,0,ROUND($R57*$S$3*$C$3/$A49,2)) -> 170 | AH49: =$AG49*$A49 -> 170 | AI49: =$E49-$AG49 -> 92.73 | AJ49: =$A49*$AI49 -> 92.73 | AK49: =ROUND(($AG49+$AI49)*$A49,2) -> 262.73 | AM49: =ROUND(R57,2) -> 170 | AN49: =IF(A49=0,0,AO49/A49) -> 2.75 | AO49: =ROUND(T57,2) -> 2.75 | AP49: =ROUND(AM49+AO49,2)*A49 -> 172.75
D50: 230V / 0-10V - Actuator - 2NM for VAV box 400mm x 200mm | K50: n
R51: =$A51*Q51 -> 0 | T51: =$A51*S51*$T$1 -> 0
A52: 1 | B52: No | D52: Fast running rotary actuator, 2 Nm, AC 100...240 V, 2...10 V | E52: TMC230ASR | F52: Belimo | G52: BMSE_001 | H52: 416 | I52: (__) | O52: 3 | Q52: =135+20 -> 155 | R52: =$A52*Q52 -> 155 | T52: =$A52*S52*$T$1 -> 0
D53: (incl Delivery Fee and Fitment) | R53: =$A53*Q53 -> 0 | T53: =$A53*S53*$T$1 -> 0
A54: 1 | B54: No | D54: Termination, Testing, Sundries for Fitment | G54: BMSE_001 | H54: 421 | I54: (__) | O54: 3 | Q54: 15 | R54: =$A54*Q54 -> 15 | S54: 2.5 | T54: =$A54*S54*$T$1 -> 2.75
R55: =$A55*Q55 -> 0 | T55: =$A55*S55*$T$1 -> 0
R56: =$A56*Q56 -> 0 | T56: =$A56*S56*$T$1 -> 0
A57: d> | B57: =(R56+T56) -> 0 | G57: ICOST | K57: mu_B | L57: ITEM | R57: =SUM(R50:R56) -> 170 | T57: =SUM(T50:T56) -> 2.75
A58: SB
B60: =($R60*$S$2+$T60*$T$2)-$F60 -> -57.09 | D60: PAGE : | F60: =SUMIF($L14:$L58,"ITEM",F14:F58) -> 1050.92 | L60: PAGE | R60: =SUMIF($L14:$L58,"ITEM",R14:R58) -> 680 | T60: =SUMIF($L14:$L58,"ITEM",T14:T58) -> 11
B61: Disc: | F61: PAGE SELL | R61: PAGE MAT | T61: PAGE LAB
AH63: T_M_Sell | AJ63: T_L_Sell | AK63: Total_Sell
A64: SB! | AH64: =SUM(AH$15:AH63) -> 680 | AJ64: =SUM(AJ$15:AJ63) -> 370.92 | AK64: =SUM(AK$15:AK63) -> 1050.92
B65: =$F65/$C$2-($R65*$S$2+$T65*$T$2) -> 0 | C65: cc | E65: =$F$2 & " (mu_A) :" -> Electrical Site Pair (mu_A) : | F65: =SUMIF($K$13:$K64,"mu_A",F$13:F64) -> 0 | R65: =SUMIF($K$13:$K64,"mu_A",R$13:R$64) -> 0 | T65: =SUMIF($K$13:$K64,"mu_A",T$13:T$64) -> 0 | AH65: =R65*$S$2 -> 0 | AJ65: =T65*$T$2 -> 0
B66: =$F66/$C$3-($R66*$S$3+$T66*$T$3) -> 0 | C66: cc | E66: =$F$3& " (mu_B) :" -> ECA/BMS Pair (mu_B) : | F66: =SUMIF($K$13:$K64,"mu_B",F$13:F64) -> 1050.92 | R66: =SUMIF($K$13:$K64,"mu_B",R$13:R64) -> 680 | T66: =SUMIF($K$13:$K64,"mu_B",T$13:T64) -> 11 | AH66: =R66*$S$3 -> 680 | AJ66: =T66*$T$3 -> 370.92
B67: =$F67/$C$4-($R67*$S$4+$T67*$T$4) -> 0 | C67: cc | E67: =$F$4& " (mu_C) :" -> ECA/BMS Engineer (mu_C) : | F67: =SUMIF($K$13:$K64,"mu_C",F$13:F64) -> 0 | R67: =SUMIF($K$13:$K64,"mu_C",R$13:R64) -> 0 | T67: =SUMIF($K$13:$K64,"mu_C",T$13:T64) -> 0 | AH67: =R67*$S$4 -> 0 | AJ67: =T67*$T$4 -> 0
B68: =$F68/$C$5-($R68*$S$5+$T68*$T$5) -> 0 | C68: cc | E68: =$F$5& " (mu_D) :" -> BMS - Tech - Single (mu_D) : | F68: =SUMIF($K$13:$K64,"mu_D",F$13:F64) -> 0 | R68: =SUMIF($K$13:$K64,"mu_D",R$13:R64) -> 0 | T68: =SUMIF($K$13:$K64,"mu_D",T$13:T64) -> 0 | AH68: =R68*$S$5 -> 0 | AJ68: =T68*$T$5 -> 0
B69: =$F69/$C$6-($R69*$S$6+$T69*$T$6) -> 0 | C69: cc | E69: =$F$6& " (mu_E) :" -> Edward/Mark + AGV (mu_E) : | F69: =SUMIF($K$13:$K64,"mu_E",F$13:F64) -> 0 | R69: =SUMIF($K$13:$K64,"mu_E",R$13:R64) -> 0 | T69: =SUMIF($K$13:$K64,"mu_E",T$13:T64) -> 0 | AH69: =R69*$S$6 -> 0 | AJ69: =T69*$T$6 -> 0
B70: =$F70/$C$7-($R70*$S$7+$T70*$T$7) -> 0 | C70: cc | E70: =$F$7& " (mu_F) :" -> 0 (mu_F) : | F70: =SUMIF($K$13:$K64,"mu_F",F$13:F64) -> 0 | R70: =SUMIF($K$13:$K64,"mu_F",R$13:R64) -> 0 | T70: =SUMIF($K$13:$K64,"mu_F",T$13:T64) -> 0 | AH70: =R70*$S$7 -> 0 | AJ70: =T70*$T$7 -> 0
B71: =$F71/$C$8-($R71*$S$8+$T71*$T$8) -> 0 | C71: cc | E71: =$F$8& " (mu_G) :" -> 0 (mu_G) : | F71: =SUMIF($K$13:$K64,"mu_G",F$13:F64) -> 0 | R71: =SUMIF($K$13:$K64,"mu_G",R$13:R64) -> 0 | T71: =SUMIF($K$13:$K64,"mu_G",T$13:T64) -> 0 | AH71: =R71*$S$8 -> 0 | AJ71: =T71*$T$8 -> 0
B72: =$F72/$C$9-($R72*$S$9+$T72*$T$9) -> 0 | C72: cc | E72: =$F$9& " (mu_H) :" -> 0 (mu_H) : | F72: =SUMIF($K$13:$K64,"mu_H",F$13:F64) -> 0 | R72: =SUMIF($K$13:$K64,"mu_H",R$13:R64) -> 0 | T72: =SUMIF($K$13:$K64,"mu_H",T$13:T64) -> 0 | AH72: =R72*$S$9 -> 0 | AJ72: =T72*$T$9 -> 0
B73: =$F73/$C$10-($R73*$S$10+$T73*$T$10) -> 0 | C73: cc | E73: =$F$10& " (mu_I) :" -> 0 (mu_I) : | F73: =SUMIF($K$13:$K64,"mu_I",F$13:F64) -> 0 | R73: =SUMIF($K$13:$K64,"mu_I",R$13:R64) -> 0 | T73: =SUMIF($K$13:$K64,"mu_I",T$13:T64) -> 0 | AH73: =R73*$S$10 -> 0 | AJ73: =T73*$T$10 -> 0
B74: =$F74/$C$11-($R74*$S$11+$T74*$T$11) -> 0 | E74: =$F$11& " (mu_J) :" -> 0 (mu_J) : | F74: =SUMIF($K$13:$K65,"mu_J",F$13:F65) -> 0 | R74: =SUMIF($K$13:$K65,"mu_J",R$13:R64) -> 0 | T74: =SUMIF($K$13:$K65,"mu_J",T$13:T65) -> 0 | AH74: =R74*$S$11 -> 0 | AJ74: =T74*$T$11 -> 0
C75: MATERIAL SUMMARY | E75: MU SUMMARY TOTAL | F75: =SUM(F65:F74) -> 1050.92 | G75: ISELL | R75: =SUM(R65:R74) -> 680 | T75: =SUM(T65:T74) -> 11 | AH75: =SUM(AH65:AH74) -> 680 | AJ75: =SUM(AJ65:AJ74) -> 370.92 | AK75: =AH75+AJ75 -> 1050.92
AH76: =AH64-AH75 -> 0 | AJ76: =AJ64-AJ75 -> 0 | AK76: =AK64-AK75 -> 0
B77: Discy with | E77: MATERIAL ITEMS TOTAL | L77: COMP_GT | R77: =SUMIF($L$13:$L64,"",R$13:R64) -> 680 | T77: =SUMIF($L$13:$L64,"",T$13:T64) -> 11
B78: equal Mus
B79: =$F79/$C$2-($R79*$S$2+$T79*$T$2) -> 57.09 | E79: BOQ ITEMS TOTAL | F79: =SUMIF($L$13:$L64,"ITEM",F$13:F64) -> 1050.92 | L79: ITEM_GT | R79: =SUMIF($L$13:$L64,"ITEM",R$13:R64) -> 680 | T79: =SUMIF($L$13:$L64,"ITEM",T$13:T64) -> 11
B81: =$F81/$C$2-($R81*$S$2+$T81*$T$2) -> 57.09 | E81: PAGES TOTAL | F81: =SUMIF($L$13:$L64,"PAGE",F$13:F64) -> 1050.92 | L81: PAGE_GT | R81: =SUMIF($L$13:$L64,"PAGE",R$13:R64) -> 680 | T81: =SUMIF($L$13:$L64,"PAGE",T$13:T64) -> 11
A83: SB | B83: =$F83/$C$2-($R83*$S$2+$T83*$T$2) -> 0 | E83: SECTIONS TOTAL | F83: =SUMIF($L$13:$L64,"SECT",F$13:F64) -> 0 | L83: SECT_GT | R83: =SUMIF($L$13:$L64,"SECT",R$13:R64) -> 0 | T83: =SUMIF($L$13:$L64,"SECT",T$13:T64) -> 0
A84: END!
B85: V:56 | E85: COSTCODE TOTAL | R85: =SUM(R86:R153) -> 680 | T85: =SUM(T86:T153) -> 11
B86: 1 | C86: cc | D86: Erection materials | F86: 501 | P86: 1 | R86: =SUMIF($H$13:$H$64,$F86,R$13:R$64)+Elec_Rates!R187 -> 0 | T86: =SUMIF($H$13:$H$64,$F86,T$13:T$64)+Elec_Rates!T187 -> 0
B87: 2 | C87: cc | D87: Busbar Trunking | F87: 505 | P87: 1 | R87: =SUMIF($H$13:$H$64,$F87,R$13:R$64)+Elec_Rates!R188 -> 0 | T87: =SUMIF($H$13:$H$64,$F87,T$13:T$64)+Elec_Rates!T188 -> 0
B88: 3 | C88: cc | D88: Switchgear | F88: 510 | P88: 2 | R88: =SUMIF($H$13:$H$64,$F88,R$13:R$64)+Elec_Rates!R189 -> 0 | T88: =SUMIF($H$13:$H$64,$F88,T$13:T$64)+Elec_Rates!T189 -> 0
B89: 4 | C89: cc | D89: MCC Equipment | F89: 511 | P89: 2 | R89: =SUMIF($H$13:$H$64,$F89,R$13:R$64)+Elec_Rates!R190 -> 0 | T89: =SUMIF($H$13:$H$64,$F89,T$13:T$64)+Elec_Rates!T190 -> 0
B90: 5 | C90: cc | D90: BMS Equipment | F90: 512 | P90: 2 | R90: =SUMIF($H$13:$H$64,$F90,R$13:R$64)+Elec_Rates!R191 -> 0 | T90: =SUMIF($H$13:$H$64,$F90,T$13:T$64)+Elec_Rates!T191 -> 0
B91: 6 | C91: cc | D91: PVC Pipes / Ducts | F91: 520 | P91: 1 | R91: =SUMIF($H$13:$H$64,$F91,R$13:R$64)+Elec_Rates!R192 -> 0 | T91: =SUMIF($H$13:$H$64,$F91,T$13:T$64)+Elec_Rates!T192 -> 0
B92: 7 | C92: cc | D92: High/medium voltage switchgear | F92: 530 | P92: 2 | R92: =SUMIF($H$13:$H$64,$F92,R$13:R$64)+Elec_Rates!R193 -> 0 | T92: =SUMIF($H$13:$H$64,$F92,T$13:T$64)+Elec_Rates!T193 -> 0
B93: 8 | C93: cc | D93: Power Transformers | F93: 550 | P93: 2 | R93: =SUMIF($H$13:$H$64,$F93,R$13:R$64)+Elec_Rates!R194 -> 0 | T93: =SUMIF($H$13:$H$64,$F93,T$13:T$64)+Elec_Rates!T194 -> 0
B94: 9 | C94: cc | D94: Control Panels | F94: 570 | P94: 2 | R94: =SUMIF($H$13:$H$64,$F94,R$13:R$64)+Elec_Rates!R195 -> 0 | T94: =SUMIF($H$13:$H$64,$F94,T$13:T$64)+Elec_Rates!T195 -> 0
B95: 10 | C95: cc | D95: Electrical Single Core Cables | F95: 615 | P95: 2 | R95: =SUMIF($H$13:$H$64,$F95,R$13:R$64)+Elec_Rates!R196 -> 0 | T95: =SUMIF($H$13:$H$64,$F95,T$13:T$64)+Elec_Rates!T196 -> 0
B96: 11 | C96: cc | D96: Electrical Multicore Cables | F96: 616 | P96: 2 | R96: =SUMIF($H$13:$H$64,$F96,R$13:R$64)+Elec_Rates!R197 -> 0 | T96: =SUMIF($H$13:$H$64,$F96,T$13:T$64)+Elec_Rates!T197 -> 0
B97: 12 | C97: cc | D97: ELV/BMS/Special Cables | F97: 617 | P97: 2 | R97: =SUMIF($H$13:$H$64,$F97,R$13:R$64)+Elec_Rates!R198 -> 0 | T97: =SUMIF($H$13:$H$64,$F97,T$13:T$64)+Elec_Rates!T198 -> 0
... B153: 56 | C153: cc | D153: Provisional Sum | F153: 970 | P153: 4 | R153: =SUMIF($H$13:$H$64,$F153,R$13:R$64)+Elec_Rates!R254 -> 0 | T153: =SUMIF($H$13:$H$64,$F153,T$13:T$64)+Elec_Rates!T254 -> 0
C155: cc | F155: Fix 1 | H155: 1 | R155: =SUMIF($P86:$P153,1,R86:R153) -> 0 | T155: =SUMIF($P86:$P153,1,T86:T153) -> 0
C156: cc | F156: Fix 2 | H156: 2 | R156: =SUMIF($P86:$P153,2,R86:R153) -> 0 | T156: =SUMIF($P86:$P153,2,T86:T153) -> 0
C157: cc | F157: Fix 3 | H157: 2 | R157: =SUMIF($P86:$P153,3,R86:R153) -> 0 | T157: =SUMIF($P86:$P153,3,T86:T153) -> 0
C158: cc | F158: Others | H158: 3 | R158: =SUMIF($P86:$P153,4,R86:R153) -> 680 | T158: =SUMIF($P86:$P153,4,T86:T153) -> 11
C159: cc | F159: TOTAL | R159: =SUM(R155:R158) -> 680 | T159: =SUM(T155:T158) -> 11
B160: RATE TOTALS IN CURRENT SHEET | C160: RATE TOTALS IN CURRENT SHEET
B162: =SUMIF($D$13:$D$64,D162,$C$13:$C$64) -> 0 | D162: =Elec_Rates!$D$19 -> 001# Controllers
...

Sheet Example_Blocks
B1: CLIENT: | C1: =[2]ML_Sum!$C1 -> 1 | D1: =[2]ML_Sum!$D1 -> 0 | F1: =[2]ML_Sum!$F1 -> 0 | I1: 1 | J1: =[2]ML_Sum!$J1 -> 1 | K1: =[2]ML_Sum!$K1 -> 1 | L1: =[2]ML_Sum!$L1 -> 1 | M1: =[2]ML_Sum!$M1 -> 1 | N1: =[2]ML_Sum!$N1 -> 1 | O1: =[2]ML_Sum!$O1 -> 1 | Q1: =[2]ML_Sum!$Q1 -> € | R1: R/Lab Cont | S1: =[2]ML_Sum!$S1 -> R | T1: =[2]ML_Sum!$T1 -> 1 | U1: =[2]ML_Sum!W1 -> BOQ | V1: INCL | W1: MULT | X1: AREA | Y1: BOQ | Z1: TDWG | AA1: ACT | AB1: DIFF
B2: PROJECT: | C2: =[2]ML_Sum!$C2 -> 1 | D2: =[2]ML_Sum!$D2 -> Marsa Warehouse | F2: =[2]ML_Sum!$F2 -> Controls | I2: 2 | J2: =[2]ML_Sum!$J2 -> 1 | K2: =[2]ML_Sum!$K2 -> 1 | L2: =[2]ML_Sum!$L2 -> 1 | M2: =[2]ML_Sum!$M2 -> 1 | N2: =[2]ML_Sum!$N2 -> 1 | O2: =[2]ML_Sum!$O2 -> 1 | Q2: =[2]ML_Sum!$Q2 -> 0 | R2: mu_A | S2: =[2]ML_Sum!$S2 -> 1 | T2: =[2]ML_Sum!$T2 -> 27.46
B3: JOB DESC: | C3: =[2]ML_Sum!$C3 -> 1 | D3: =[2]ML_Sum!$D3 -> Tender | F3: =[2]ML_Sum!$F3 -> Preliminaries | I3: 3 | J3: =[2]ML_Sum!$J3 -> 1 | K3: =[2]ML_Sum!$K3 -> 1 | L3: =[2]ML_Sum!$L3 -> 1 | M3: =[2]ML_Sum!$M3 -> 1 | N3: =[2]ML_Sum!$N3 -> 1 | O3: =[2]ML_Sum!$O3 -> 1 | Q3: =[2]ML_Sum!$Q3 -> 0 | R3: mu_B | S3: =[2]ML_Sum!$S3 -> 1 | T3: =[2]ML_Sum!$T3 -> 27.46
B4: QUOTE No: | C4: =[2]ML_Sum!$C4 -> 1 | D4: =[2]ML_Sum!$D4 -> TBC | F4: =[2]ML_Sum!$F4 -> BMS - Pair | I4: 4 | J4: =[2]ML_Sum!$J4 -> 1 | K4: =[2]ML_Sum!$K4 -> 1 | L4: =[2]ML_Sum!$L4 -> 1 | M4: =[2]ML_Sum!$M4 -> 1 | N4: =[2]ML_Sum!$N4 -> 1 | O4: =[2]ML_Sum!$O4 -> 1 | Q4: =[2]ML_Sum!$Q4 -> 0 | R4: mu_C | S4: =[2]ML_Sum!$S4 -> 1.3 | T4: =[2]ML_Sum!$T4 -> 43.836
B5: CLIENTs REF: | C5: =[2]ML_Sum!$C5 -> 1 | D5: =[2]ML_Sum!$D5 -> 0 | F5: =[2]ML_Sum!$F5 -> BMS - Tech | I5: 5 | J5: =[2]ML_Sum!$J5 -> 1 | K5: =[2]ML_Sum!$K5 -> 1 | L5: =[2]ML_Sum!$L5 -> 1 | M5: =[2]ML_Sum!$M5 -> 1 | N5: =[2]ML_Sum!$N5 -> 1 | O5: =[2]ML_Sum!$O5 -> 1 | Q5: =[2]ML_Sum!$Q5 -> 0 | R5: mu_D | S5: =[2]ML_Sum!$S5 -> 1.3 | T5: =[2]ML_Sum!$T5 -> 27.872
B6: VAT/DUTIES: | C6: =[2]ML_Sum!$C6 -> 1 | D6: =[2]ML_Sum!$D6 -> VAT EXCL. | F6: =[2]ML_Sum!$F6 -> BMS - Engineer | I6: 6 | J6: =[2]ML_Sum!$J6 -> 1 | K6: =[2]ML_Sum!$K6 -> 1 | L6: =[2]ML_Sum!$L6 -> 1 | M6: =[2]ML_Sum!$M6 -> 1 | N6: =[2]ML_Sum!$N6 -> 1 | O6: =[2]ML_Sum!$O6 -> 1 | Q6: =[2]ML_Sum!$Q6 -> 0 | R6: mu_E | S6: =[2]ML_Sum!$S6 -> 1.3 | T6: =[2]ML_Sum!$T6 -> 39
B7: SAVED ON: | C7: =[2]ML_Sum!$C7 -> 1 | D7: 39364 | F7: =[2]ML_Sum!$F7 -> 0 | I7: 7 | J7: =[2]ML_Sum!$J7 -> 1 | K7: =[2]ML_Sum!$K7 -> 1 | L7: =[2]ML_Sum!$L7 -> 1 | M7: =[2]ML_Sum!$M7 -> 1 | N7: =[2]ML_Sum!$N7 -> 1 | O7: =[2]ML_Sum!$O7 -> 0 | Q7: =[2]ML_Sum!$Q7 -> 0 | R7: mu_F | S7: =[2]ML_Sum!$S7 -> 0 | T7: =[2]ML_Sum!$T7 -> 0
B8: ESTIMATOR: | C8: =[2]ML_Sum!$C8 -> 1 | D8: =[2]ML_Sum!$D8 -> G. Baranyay | F8: =[2]ML_Sum!$F8 -> 0 | I8: 8 | J8: =[2]ML_Sum!$J8 -> 1 | K8: =[2]ML_Sum!$K8 -> 1 | L8: =[2]ML_Sum!$L8 -> 1 | M8: =[2]ML_Sum!$M8 -> 1 | N8: =[2]ML_Sum!$N8 -> 1 | O8: =[2]ML_Sum!$O8 -> 0 | Q8: =[2]ML_Sum!$Q8 -> 0 | R8: mu_G | S8: =[2]ML_Sum!$S8 -> 0 | T8: =[2]ML_Sum!$T8 -> 0
B9: LABOUR RATE: | C9: =[2]ML_Sum!$C9 -> 1 | D9: =[2]ML_Sum!$D9 -> 27.46 | F9: =[2]ML_Sum!$F9 -> 0 | I9: 9 | J9: =[2]ML_Sum!$J9 -> 1 | K9: =[2]ML_Sum!$K9 -> 1 | L9: =[2]ML_Sum!$L9 -> 1 | M9: =[2]ML_Sum!$M9 -> 1 | N9: =[2]ML_Sum!$N9 -> 1 | O9: =[2]ML_Sum!$O9 -> 0 | Q9: =[2]ML_Sum!$Q9 -> 0 | R9: mu_H | S9: =[2]ML_Sum!$S9 -> 0 | T9: =[2]ML_Sum!$T9 -> 0
C10: =[2]ML_Sum!$C10 -> 1 | F10: =[2]ML_Sum!$F10 -> 0 | I10: 10 | J10: =[2]ML_Sum!$J10 -> 1 | K10: =[2]ML_Sum!$K10 -> 1 | L10: =[2]ML_Sum!$L10 -> 1 | M10: =[2]ML_Sum!$M10 -> 1 | N10: =[2]ML_Sum!$N10 -> 1 | O10: =[2]ML_Sum!$O10 -> 1 | Q10: =[2]ML_Sum!$Q10 -> 0 | R10: mu_I | S10: =[2]ML_Sum!$S10 -> 0 | T10: =[2]ML_Sum!$T10 -> 0
C11: =[2]ML_Sum!$C11 -> 1 | F11: =[2]ML_Sum!$F11 -> 0 | Q11: =[2]ML_Sum!$Q11 -> 0 | R11: mu_J | S11: =[2]ML_Sum!$S11 -> 0 | T11: =[2]ML_Sum!$T11 -> 0
C12: =[2]ML_Sum!$C12 -> 1 | F12: =[2]ML_Sum!$F12 -> 0 | Q12: =[2]ML_Sum!$Q12 -> 0 | R12: MIXED | S12: =[2]ML_Sum!$S12 -> MAT MU | T12: =[2]ML_Sum!$T12 -> LAB RATE
G13: ISELL | H13: C_CODE | I13: MAKE | J13: PART_NO | K13: MARKUP | L13: TYPE | M13: LIST_P | N13: P_FACT | O13: FIX | P13: DATE | Q13: %Dsct in BOQ | R13: MU TYPE | S13: MAT MU | T13: LAB RATE | AM13: Tot Mat Cost | AN13: Unit Lab phr. | AO13: Tot Lab phr. | AP13: < for ELM / MEE
K14: TB
C15: t | D15: Item:
D16: Supply and Installation of the following:
E18: Sell Rate | F18: Sell Total | K18: IB | AG18: U_M_Sell | AH18: T_M_Sell | AI18: U_L_Sell | AJ18: T_L_Sell | AK18: Total_Sell | AM18: T_M_Cost | AN18: U_L_Phr | AO18: T_L_Phr | AP18: Mat/Lab=1
A19: 1 | B19: No | D19: Item: 1.1 | E19: =IF(AND($A19=0,$A$1="DIF"),0, ROUND(ROUND(($R44*$S$4+($T44*$T$4))/$A19,2)*$C$4,2)) -> 645.72 | F19: =ROUND($A19*$E19,2) -> 645.72 | G19: ISELL | K19: mu_C | L19: ITEM | T19: =IF(AND($R44=0,$T44=0),"0.00","mu: "& ROUND(F19/$C$4/($R44+$T44*$D$9),2)) -> mu: 1.3 | AG19: =IF($E19=0,0,ROUND($R44*$S$4*$C$4/$A19,2)) -> 645.72 | AH19: =$AG19*$A19 -> 645.72 | AI19: =$E19-$AG19 -> 0 | AJ19: =$A19*$AI19 -> 0 | AK19: =ROUND(($AG19+$AI19)*$A19,2) -> 645.72 | AM19: =ROUND(R44,2) -> 496.71 | AN19: =IF(A19=0,0,AO19/A19) -> 0 | AO19: =ROUND(T44,2) -> 0 | AP19: =ROUND(AM19+AO19,2)*A19 -> 496.71
D20: Basic EF Control Panel - DoL | K20: n
R21: =$A21*Q21 -> 0 | T21: =$A21*S21*$T$1 -> 0
A22: 1 | B22: No | D22: Wall‑mounted enclosure 1 door IP66 H=500 W=400 D=300mm | E22: Schrack | F22: WSA5040300 | G22: BMSE_001 | H22: 415 | I22: (__) | O22: 3 | Q22: 80.91 | R22: =$A22*Q22 -> 80.91 | T22: =$A22*S22*$T$1 -> 0
A23: 1 | B23: No | D23: Wall-mounting brackets for WSA, WKT, WKA and BUS enclosures | E23: Schrack | F23: WSAWB004 | G23: BMSE_001 | H23: 415 | I23: (__) | O23: 3 | Q23: 3.43 | R23: =$A23*Q23 -> 3.43 | T23: =$A23*S23*$T$1 -> 0
A24: 1 | B24: No | D24: Knitted earthing cable 260mm long, blank | E24: Schrack | F24: WSTCUF260 | G24: BMSE_001 | H24: 415 | I24: (__) | O24: 3 | Q24: 2.55 | R24: =$A24*Q24 -> 2.55 | T24: =$A24*S24*$T$1 -> 0
A25: 1 | B25: No | D25: Selector switch, 3 pos, stay-put, clamp handle | E25: Schrack | F25: MM216872 + accessories | G25: BMSE_001 | H25: 415 | I25: (__) | O25: 3 | Q25: 8 | R25: =$A25*Q25 -> 8 | T25: =$A25*S25*$T$1 -> 0
A26: 1 | B26: No | D26: Motor Protection Circuit Breaker BE2, 3-pole, 6-10A | E26: Schrack | F26: BE201000 | G26: BMSE_001 | H26: 415 | I26: (__) | O26: 3 | Q26: 9.55 | R26: =$A26*Q26 -> 9.55 | T26: =$A26*S26*$T$1 -> 0
A27: 2 | B27: No | D27: Screw earth terminal 6/10 mm², type AVK 6/10 T | E27: Schrack | F27: IK622010 | G27: BMSE_001 | H27: 415 | I27: (__) | O27: 3 | Q27: 1.25 | R27: =$A27*Q27 -> 2.5 | T27: =$A27*S27*$T$1 -> 0
A28: 2 | B28: No | D28: Auxiliary contact, front-mounting for BE2 | E28: Schrack | F28: BE2ZAF11 | G28: BMSE_001 | H28: 415 | I28: (__) | O28: 3 | Q28: 0.094 | R28: =$A28*Q28 -> 0.188 | T28: =$A28*S28*$T$1 -> 0
A29: 1 | B29: No | D29: CAPUS Panel - Switch-disconnector 3 pole 25A | E29: Schrack | F29: SI338120 | G29: BMSE_001 | H29: 415 | I29: (__) | O29: 3 | Q29: 16.91 | R29: =$A29*Q29 -> 16.91 | T29: =$A29*S29*$T$1 -> 0
A30: 1 | B30: No | D30: CAPUS Panel - Set connection space cover | E30: Schrack | F30: SI336940 | G30: BMSE_001 | H30: 415 | I30: (__) | O30: 3 | Q30: 5.57 | R30: =$A30*Q30 -> 5.57 | T30: =$A30*S30*$T$1 -> 0
A31: 1 | B31: No | D31: CAPUS Panel - Extension shaft, length 300 mm | E31: Schrack | F31: SI336820 | G31: BMSE_001 | H31: 415 | I31: (__) | O31: 3 | Q31: 5.7 | R31: =$A31*Q31 -> 5.7 | T31: =$A31*S31*$T$1 -> 0
A32: 1 | B32: No | D32: CAPUS Panel - Rotary handle for door coupling drive, black | E32: Schrack | F32: SI336650 | G32: BMSE_001 | H32: 415 | I32: (__) | O32: 3 | Q32: 7.4 | R32: =$A32*Q32 -> 7.4 | T32: =$A32*S32*$T$1 -> 0
A33: 1 | B33: No | D33: LED-indicator monobloc 230VAC/DC red | E33: Schrack | F33: BZ501215-B | G33: BMSE_001 | H33: 415 | I33: (__) | O33: 3 | Q33: 0.98 | R33: =$A33*Q33 -> 0.98 | T33: =$A33*S33*$T$1 -> 0
... A36: 0 | B36: No | D36: Digital 1 channel day/week timer | E36: Schrack | F36: BZH14071 | G36: BMSE_001 | H36: 415 | I36: (__) | O36: 3 | Q36: 24.4 | R36: =$A36*Q36 -> 0 | T36: =$A36*S36*$T$1 -> 0
A37: =A33+A34+A35 -> 5 | B37: No | D37: Miniature Circuit Breaker (MCB) AMPARO 10kA, B 2A, 1-pole | E37: Schrack | F37: AM018102 | G37: BMSE_001 | H37: 415 | I37: (__) | O37: 3 | Q37: 2.42 | R37: =$A37*Q37 -> 12.1 | T37: =$A37*S37*$T$1 -> 0
A38: 1 | B38: No | D38: Single Phase Control Transformer 230V/24V, 100VA, IP00 | E38: Schrack | F38: LP602010T | G38: BMSE_001 | H38: 415 | I38: (__) | O38: 3 | Q38: 30 | R38: =$A38*Q38 -> 30 | T38: =$A38*S38*$T$1 -> 0
A39: 1 | B39: No | D39: Contactor 3‑pole, CUBICO Classic, 5,5kW, 12A, 1NO+1NC, 24VAC | E39: Schrack | F39: LZDC12B0 | G39: BMSE_001 | H39: 415 | I39: (__) | O39: 3 | Q39: 7 | R39: =$A39*Q39 -> 7 | T39: =$A39*S39*$T$1 -> 0
A40: 1 | B40: No | D40: Consumables | E40: Misc | G40: BMSE_001 | H40: 415 | I40: (__) | O40: 3 | Q40: 50 | R40: =$A40*Q40 -> 50 | T40: =$A40*S40*$T$1 -> 0
A41: 1 | B41: No | D41: Panel Building | E41: Catania | G41: BMSE_001 | H41: 420 | I41: (__) | O41: 3 | Q41: 250 | R41: =$A41*Q41 -> 250 | T41: =$A41*S41*$T$1 -> 0
R42: =$A42*Q42 -> 0 | T42: =$A42*S42*$T$1 -> 0
R43: =$A43*Q43 -> 0 | T43: =$A43*S43*$T$1 -> 0
A44: d> | B44: =(R43+T43) -> 0 | G44: ICOST | K44: mu_C | L44: ITEM | R44: =SUM(R20:R43) -> 496.708 | T44: =SUM(T20:T43) -> 0
E45: Sell Rate | F45: Sell Total | K45: IB | AG45: U_M_Sell | AH45: T_M_Sell | AI45: U_L_Sell | AJ45: T_L_Sell | AK45: Total_Sell | AM45: T_M_Cost | AN45: U_L_Phr | AO45: T_L_Phr | AP45: Mat/Lab=1
A46: 1 | B46: No | D46: Item: 1.1 | E46: =IF(AND($A46=0,$A$1="DIF"),0, ROUND(ROUND(($R72*$S$4+($T72*$T$4))/$A46,2)*$C$4,2)) -> 11595.62 | F46: =ROUND($A46*$E46,2) -> 11595.62 | G46: ISELL | K46: mu_C | L46: ITEM | T46: =IF(AND($R72=0,$T72=0),"0.00","mu: "& ROUND(F46/$C$4/($R72+$T72*$D$9),2)) -> mu: 1.58 | AG46: =IF($E46=0,0,ROUND($R72*$S$4*$C$4/$A46,2)) -> 636.62 | AH46: =$AG46*$A46 -> 636.62 | AI46: =$E46-$AG46 -> 10959 | AJ46: =$A46*$AI46 -> 10959 | AK46: =ROUND(($AG46+$AI46)*$A46,2) -> 11595.62 | AM46: =ROUND(R72,2) -> 489.71 | AN46: =IF(A46=0,0,AO46/A46) -> 250 | AO46: =ROUND(T72,2) -> 250 | AP46: =ROUND(AM46+AO46,2)*A46 -> 739.71
D47: Basic EF Control Panel - With Inverter | K47: n
R48: =$A48*Q48 -> 0 | T48: =$A48*S48*$T$1 -> 0
A49: 1 | B49: No | D49: Wall‑mounted enclosure 1 door IP66 H=500 W=400 D=300mm | E49: Schrack | F49: WSA5040300 | G49: BMSE_001 | H49: 415 | I49: (__) | O49: 3 | Q49: 80.91 | R49: =$A49*Q49 -> 80.91 | T49: =$A49*S49*$T$1 -> 0
A50: 1 | B50: No | D50: Wall-mounting brackets for WSA, WKT, WKA and BUS enclosures | E50: Schrack | F50: WSAWB004 | G50: BMSE_001 | H50: 415 | I50: (__) | O50: 3 | Q50: 3.43 | R50: =$A50*Q50 -> 3.43 | T50: =$A50*S50*$T$1 -> 0
A51: 1 | B51: No | D51: Knitted earthing cable 260mm long, blank | E51: Schrack | F51: WSTCUF260 | G51: BMSE_001 | H51: 415 | I51: (__) | O51: 3 | Q51: 2.55 | R51: =$A51*Q51 -> 2.55 | T51: =$A51*S51*$T$1 -> 0
A52: 1 | B52: No | D52: Selector switch, 3 pos, stay-put, clamp handle | E52: Schrack | F52: MM216872 + accessories | G52: BMSE_001 | H52: 415 | I52: (__) | O52: 3 | Q52: 8 | R52: =$A52*Q52 -> 8 | T52: =$A52*S52*$T$1 -> 0
A53: 1 | B53: No | D53: Motor Protection Circuit Breaker BE2, 3-pole, 6-10A | E53: Schrack | F53: BE201000 | G53: BMSE_001 | H53: 415 | I53: (__) | O53: 3 | Q53: 9.55 | R53: =$A53*Q53 -> 9.55 | T53: =$A53*S53*$T$1 -> 0
A54: 2 | B54: No | D54: Screw earth terminal 6/10 mm², type AVK 6/10 T | E54: Schrack | F54: IK622010 | G54: BMSE_001 | H54: 415 | I54: (__) | O54: 3 | Q54: 1.25 | R54: =$A54*Q54 -> 2.5 | T54: =$A54*S54*$T$1 -> 0
A55: 2 | B55: No | D55: Auxiliary contact, front-mounting for BE2 | E55: Schrack | F55: BE2ZAF11 | G55: BMSE_001 | H55: 415 | I55: (__) | O55: 3 | Q55: 0.094 | R55: =$A55*Q55 -> 0.188 | T55: =$A55*S55*$T$1 -> 0
A56: 1 | B56: No | D56: CAPUS Panel - Switch-disconnector 3 pole 25A | E56: Schrack | F56: SI338120 | G56: BMSE_001 | H56: 415 | I56: (__) | O56: 3 | Q56: 16.91 | R56: =$A56*Q56 -> 16.91 | T56: =$A56*S56*$T$1 -> 0
A57: 1 | B57: No | D57: CAPUS Panel - Set connection space cover | E57: Schrack | F57: SI336940 | G57: BMSE_001 | H57: 415 | I57: (__) | O57: 3 | Q57: 5.57 | R57: =$A57*Q57 -> 5.57 | T57: =$A57*S57*$T$1 -> 0
A58: 1 | B58: No | D58: CAPUS Panel - Extension shaft, length 300 mm | E58: Schrack | F58: SI336820 | G58: BMSE_001 | H58: 415 | I58: (__) | O58: 3 | Q58: 5.7 | R58: =$A58*Q58 -> 5.7 | T58: =$A58*S58*$T$1 -> 0
A59: 1 | B59: No | D59: CAPUS Panel - Rotary handle for door coupling drive, black | E59: Schrack | F59: SI336650 | G59: BMSE_001 | H59: 415 | I59: (__) | O59: 3 | Q59: 7.4 | R59: =$A59*Q59 -> 7.4 | T59: =$A59*S59*$T$1 -> 0
A60: 1 | B60: No | D60: LED-indicator monobloc 230VAC/DC red | E60: Schrack | F60: BZ501215-B | G60: BMSE_001 | H60: 415 | I60: (__) | O60: 3 | Q60: 0.98 | R60: =$A60*Q60 -> 0.98 | T60: =$A60*S60*$T$1 -> 0
... A63: 0 | B63: No | D63: Digital 1 channel day/week timer | E63: Schrack | F63: BZH14071 | G63: BMSE_001 | H63: 415 | I63: (__) | O63: 3 | Q63: 24.4 | R63: =$A63*Q63 -> 0 | T63: =$A63*S63*$T$1 -> 0
A64: =A60+A61+A62 -> 5 | B64: No | D64: Miniature Circuit Breaker (MCB) AMPARO 10kA, B 2A, 1-pole | E64: Schrack | F64: AM018102 | G64: BMSE_001 | H64: 415 | I64: (__) | O64: 3 | Q64: 2.42 | R64: =$A64*Q64 -> 12.1 | T64: =$A64*S64*$T$1 -> 0
A65: 1 | B65: No | D65: Single Phase Control Transformer 230V/24V, 100VA, IP00 | E65: Schrack | F65: LP602010T | G65: BMSE_001 | H65: 415 | I65: (__) | O65: 3 | Q65: 30 | R65: =$A65*Q65 -> 30 | T65: =$A65*S65*$T$1 -> 0
A66: 1 | B66: No | D66: Inverter Added per Specific Fan Requirement | E66: Fuji Electric | Q66: 0 | R66: =$A66*Q66 -> 0 | T66: =$A66*S66*$T$1 -> 0
A67: 1 | B67: No | D67: Consumables | E67: Misc | G67: BMSE_001 | H67: 415 | I67: (__) | O67: 3 | Q67: 50 | R67: =$A67*Q67 -> 50 | T67: =$A67*S67*$T$1 -> 0
A68: 1 | B68: No | D68: Panel Building | E68: Catania | G68: BMSE_001 | H68: 420 | I68: (__) | O68: 3 | Q68: 250 | R68: =$A68*Q68 -> 250 | T68: =$A68*S68*$T$1 -> 0
A69: =$Q$147 *(1) -> 250 | B69: No | D69: Labour - Delivery etc | E69: BMS Team | G69: BMSE_001 | H69: 420 | I69: (__) | O69: 3 | Q69: 0 | R69: =$A69*Q69 -> 0 | S69: 1 | T69: =$A69*S69*$T$1 -> 250
R70: =$A70*Q70 -> 0 | T70: =$A70*S70*$T$1 -> 0
R71: =$A71*Q71 -> 0 | T71: =$A71*S71*$T$1 -> 0
A72: d> | B72: =(R71+T71) -> 0 | G72: ICOST | K72: mu_C | L72: ITEM | R72: =SUM(R47:R71) -> 489.708 | T72: =SUM(T47:T71) -> 250
E73: Sell Rate | F73: Sell Total | K73: IB | AG73: U_M_Sell | AH73: T_M_Sell | AI73: U_L_Sell | AJ73: T_L_Sell | AK73: Total_Sell | AM73: T_M_Cost | AN73: U_L_Phr | AO73: T_L_Phr | AP73: Mat/Lab=1
A74: 1 | B74: No | D74: Item: 1.2 | E74: =IF(AND($A74=0,$A$1="DIF"),0, ROUND(ROUND(($R107*$S$4+($T107*$T$4))/$A74,2)*$C$4,2)) -> 1503.92 | F74: =ROUND($A74*$E74,2) -> 1503.92 | G74: ISELL | K74: mu_C | L74: ITEM | T74: =IF(AND($R107=0,$T107=0),"0.00","mu: "& ROUND(F74/$C$4/($R107+$T107*$D$9),2)) -> mu: 1.3 | AG74: =IF($E74=0,0,ROUND($R107*$S$4*$C$4/$A74,2)) -> 1503.92 | AH74: =$AG74*$A74 -> 1503.92 | AI74: =$E74-$AG74 -> 0 | AJ74: =$A74*$AI74 -> 0 | AK74: =ROUND(($AG74+$AI74)*$A74,2) -> 1503.92 | AM74: =ROUND(R107,2) -> 1156.86 | AN74: =IF(A74=0,0,AO74/A74) -> 0 | AO74: =ROUND(T107,2) -> 0 | AP74: =ROUND(AM74+AO74,2)*A74 -> 1156.86
D75: Basic ERV Control Panel | K75: n
R76: =$A76*Q76 -> 0 | T76: =$A76*S76*$T$1 -> 0
A77: 4 | B77: No | D77: Duct/Immersion Temperature sensor 300mm – NTC10K | E77: Distech | F77: TS-DI 300 | G77: BMSE_001 | H77: 416 | I77: (__) | O77: 3 | Q77: 20 | R77: =$A77*Q77 -> 80 | T77: =$A77*S77*$T$1 -> 0
A78: 2 | B78: No | D78: Air Differential Pressure switch, 100..1500 Pa | E78: Distech | F78: PS-DPS1500 | G78: BMSE_001 | H78: 416 | I78: (__) | O78: 3 | Q78: 20 | R78: =$A78*Q78 -> 40 | T78: =$A78*S78*$T$1 -> 0
A79: 1 | B79: No | D79: 4th Pole for LTS63‑LTS80 E | E79: Shrack | F79: IN809003 | G79: BMSE_001 | H79: 416 | I79: (__) | O79: 3 | Q79: 7.16 | R79: =$A79*Q79 -> 7.16 | T79: =$A79*S79*$T$1 -> 0
A80: 1 | B80: No | D80: Indicator light flat, white | E80: Shrack | F80: MM216771 | G80: BMSE_001 | H80: 416 | I80: (__) | O80: 3 | Q80: 1.61 | R80: =$A80*Q80 -> 1.61 | T80: =$A80*S80*$T$1 -> 0
A81: 2 | B81: No | D81: Indicator light flat, red | E81: Shrack | F81: MM216772 | G81: BMSE_001 | H81: 416 | I81: (__) | O81: 3 | Q81: 1.6 | R81: =$A81*Q81 -> 3.2 | T81: =$A81*S81*$T$1 -> 0
A82: 1 | B82: No | D82: Push-button flat, spring-return, black | E82: Shrack | F82: MM216590 | G82: BMSE_001 | H82: 416 | I82: (__) | O82: 3 | Q82: 1.69 | R82: =$A82*Q82 -> 1.69 | T82: =$A82*S82*$T$1 -> 0
A83: 1 | B83: No | D83: Single Phase Control Transformer 230V/24V, 100VA, IP00 | E83: Shrack | F83: LP612010T | G83: BMSE_001 | H83: 416 | I83: (__) | O83: 3 | Q83: 27.29 | R83: =$A83*Q83 -> 27.29 | T83: =$A83*S83*$T$1 -> 0
A84: 1 | B84: No | D84: Buzzer, continous tone, 18 - 30VDC | E84: Shrack | F84: MM229025 | G84: BMSE_001 | H84: 416 | I84: (__) | O84: 3 | Q84: 6.57 | R84: =$A84*Q84 -> 6.57 | T84: =$A84*S84*$T$1 -> 0
A85: 1 | B85: No | D85: Fuse Carrier 3-pole, 32A, 10x38 | E85: Shrack | F85: IS506103 | G85: BMSE_001 | H85: 416 | I85: (__) | O85: 3 | Q85: 3.53 | R85: =$A85*Q85 -> 3.53 | T85: =$A85*S85*$T$1 -> 0
A86: 2 | B86: No | D86: Fuse Carrier 1-pole, 32A, 10x38 | E86: Shrack | F86: IS506101 | G86: BMSE_001 | H86: 416 | I86: (__) | O86: 3 | Q86: 1.1 | R86: =$A86*Q86 -> 2.2 | T86: =$A86*S86*$T$1 -> 0
A87: 4 | B87: No | D87: Cylindrical fuse link 10x38, 1A, characteristic gG, 500VAC | E87: Shrack | F87: ISZ10001 | G87: BMSE_001 | H87: 416 | I87: (__) | O87: 3 | Q87: 0.33 | R87: =$A87*Q87 -> 1.32 | T87: =$A87*S87*$T$1 -> 0
A88: 1 | B88: No | D88: Mini Contactor 3NO + 1NC, 20A, 230 VAC | E88: Shrack | F88: LA100923 | G88: BMSE_001 | H88: 416 | I88: (__) | O88: 3 | Q88: 12.15 | R88: =$A88*Q88 -> 12.15 | T88: =$A88*S88*$T$1 -> 0
... A104: 4 | B104: No | D104: Screw socket, logical arrangement for 2-pole RXT relay | E104: Shrack | F104: YRXT2010 | G104: BMSE_001 | H104: 416 | I104: (__) | O104: 3 | Q104: 1.05 | R104: =$A104*Q104 -> 4.2 | T104: =$A104*S104*$T$1 -> 0
A105: 1 | B105: No | D105: Panel Building | E105: Mark Catania | G105: BMSE_001 | H105: 420 | I105: (__) | O105: 3 | Q105: 250 | R105: =$A105*Q105 -> 250 | T105: =$A105*S105*$T$1 -> 0
A107: d> | B107: =(R106+T106) -> 0 | G107: ICOST | K107: mu_C | L107: ITEM | R107: =SUM(R75:R106) -> 1156.86 | T107: =SUM(T75:T106) -> 0
E108: Sell Rate | F108: Sell Total | K108: IB | AG108: U_M_Sell | AH108: T_M_Sell | AI108: U_L_Sell | AJ108: T_L_Sell | AK108: Total_Sell | AM108: T_M_Cost | AN108: U_L_Phr | AO108: T_L_Phr | AP108: Mat/Lab=1
A109: 1 | B109: No | D109: Item: 1.3 | E109: =IF(AND($A109=0,$A$1="DIF"),0, ROUND(ROUND(($R152*$S$4+($T152*$T$4))/$A109,2)*$C$4,2)) -> 1380.59 | F109: =ROUND($A109*$E109,2) -> 1380.59 | G109: ISELL | K109: mu_C | L109: ITEM | T109: =IF(AND($R152=0,$T152=0),"0.00","mu: "& ROUND(F109/$C$4/($R152+$T152*$D$9),2)) -> mu: 1.3 | AG109: =IF($E109=0,0,ROUND($R152*$S$4*$C$4/$A109,2)) -> 1380.59 | AH109: =$AG109*$A109 -> 1380.59 | AI109: =$E109-$AG109 -> 0 | AJ109: =$A109*$AI109 -> 0 | AK109: =ROUND(($AG109+$AI109)*$A109,2) -> 1380.59 | AM109: =ROUND(R152,2) -> 1061.99 | AN109: =IF(A109=0,0,AO109/A109) -> 0 | AO109: =ROUND(T152,2) -> 0 | AP109: =ROUND(AM109+AO109,2)*A109 -> 1061.99
D110: Basic HRU Control Panel | K110: n
A112: 0 | B112: No | D112: Duct/Immersion Temperature sensor 300mm – NTC10K | E112: Distech | F112: TS-DI 300 | G112: BMSE_001 | H112: 416 | I112: (__) | O112: 3 | Q112: 20 | R112: =$A112*Q112 -> 0 | T112: =$A112*S112*$T$1 -> 0
A113: 3 | B113: No | D113: Air Differential Pressure switch, 100..1500 Pa | E113: Distech | F113: PS-DPS1500 | G113: BMSE_001 | H113: 416 | I113: (__) | O113: 3 | Q113: 20 | R113: =$A113*Q113 -> 60 | T113: =$A113*S113*$T$1 -> 0
A114: 2 | B114: No | D114: Duct Humidity and Temperature (2%) transducer - 140mm - 2x 0..10 V | E114: Distech | F114: HS-D TH 140 VV | G114: BMSE_001 | H114: 416 | I114: (__) | O114: 3 | Q114: 103.17 | R114: =$A114*Q114 -> 206.34 | T114: =$A114*S114*$T$1 -> 0
A115: 1 | B115: No | D115: CAPUS Panel - Switch-disconnector 3 pole + N, 80A | E115: Shrack | F115: SI338890-- | G115: BMSE_001 | H115: 416 | I115: (__) | O115: 3 | Q115: 49.46 | R115: =$A115*Q115 -> 49.46 | T115: =$A115*S115*$T$1 -> 0
A116: 1 | B116: No | D116: CAPUS Panel - Set connection space cover | E116: Shrack | F116: SI336980-- | G116: BMSE_001 | H116: 416 | I116: (__) | O116: 3 | Q116: 5.29 | R116: =$A116*Q116 -> 5.29 | T116: =$A116*S116*$T$1 -> 0
A117: 1 | B117: No | D117: CAPUS Panel Rotary handle for door coupling drive yellow-red | E117: Shrack | F117: SI336660-- | G117: BMSE_001 | H117: 416 | I117: (__) | O117: 3 | Q117: 7.4 | R117: =$A117*Q117 -> 7.4 | T117: =$A117*S117*$T$1 -> 0
A118: 1 | B118: No | D118: CAPUS Panel - Extension shaft, length 300 mm | E118: Shrack | F118: SI336820-- | G118: BMSE_001 | H118: 416 | I118: (__) | O118: 3 | Q118: 5.7 | R118: =$A118*Q118 -> 5.7 | T118: =$A118*S118*$T$1 -> 0
A119: 1 | B119: No | D119: CAPUS Panel - Set connection space cover | E119: Shrack | F119: SI336950-- | G119: BMSE_001 | H119: 416 | I119: (__) | O119: 3 | Q119: 6.27 | R119: =$A119*Q119 -> 6.27 | T119: =$A119*S119*$T$1 -> 0
A120: 4 | B120: No | D120: Indicator light flat, white | E120: Shrack | F120: MM216771 | G120: BMSE_001 | H120: 416 | I120: (__) | O120: 3 | Q120: 1.61 | R120: =$A120*Q120 -> 6.44 | T120: =$A120*S120*$T$1 -> 0
A121: 4 | B121: No | D121: Indicator light flat, red | E121: Shrack | F121: MM216772 | G121: BMSE_001 | H121: 416 | I121: (__) | O121: 3 | Q121: 1.6 | R121: =$A121*Q121 -> 6.4 | T121: =$A121*S121*$T$1 -> 0
A122: 1 | B122: No | D122: Push-button flat, spring-return, black | E122: Shrack | F122: MM216590 | G122: BMSE_001 | H122: 416 | I122: (__) | O122: 3 | Q122: 1.69 | R122: =$A122*Q122 -> 1.69 | T122: =$A122*S122*$T$1 -> 0
...

Sheet E_BOQ
A1: ITEM NO. | B1: DESCRIPTION | C1: QTY | D1: UNIT | E1: RATE | F1: TOTAL | R1: Labour Hours
A2: checkdesc | E2: € | F2: € | R2: @ €33.72
A3: =TRIM(MID(Elec_Est!D15,6,30)) | B3: =Elec_Est!D16 -> Supply and Installation of the following:
A5: =TRIM(MID(Elec_Est!D19,6,30)) -> 14 | B5: =Elec_Est!D20 -> 230V / 0-10V - Actuator - 2NM for VAV box 350mm x 350mm | C5: =Elec_Est!A19 -> 1 | D5: =Elec_Est!B19 -> No | E5: 170 | F5: =C5*E5 -> 170 | R5: 2.5
A7: =TRIM(MID(Elec_Est!D29,6,30)) -> 21 | B7: =Elec_Est!D30 -> 230V / 0-10V - Actuator - 2NM for VAV box 350mm x 350mm | C7: =Elec_Est!A29 -> 1 | D7: =Elec_Est!B29 -> No | E7: 170 | F7: =C7*E7 -> 170 | R7: 2.5
A9: =TRIM(MID(Elec_Est!D39,6,30)) -> 27 | B9: =Elec_Est!D40 -> 230V / 0-10V - Actuator - 2NM for VAV box 400mm x 200mm | C9: =Elec_Est!A39 -> 1 | D9: =Elec_Est!B39 -> No | E9: 170 | F9: =C9*E9 -> 170 | R9: 2.5
A11: =TRIM(MID(Elec_Est!D49,6,30)) -> 34 | B11: =Elec_Est!D50 -> 230V / 0-10V - Actuator - 2NM for VAV box 400mm x 200mm | C11: =Elec_Est!A49 -> 1 | D11: =Elec_Est!B49 -> No | E11: 170 | F11: =C11*E11 -> 170 | R11: 2.5
B52: Page Total -
B54: Contract Discount -
A56: SB | B56: Discounted Page Total - | D56: =ML_Sum!D6 -> VAT EXCL. | E56: € | F56: =SUM(F3:F55) -> 680 | G56: =SUM(G3:G55) -> 0 | H56: =SUM(H3:H55) -> 0 | I56: =SUM(I3:I55) -> 0 | J56: =SUM(J3:J55) -> 0 | K56: =SUM(K3:K55) -> 0 | L56: =SUM(L3:L55) -> 0 | M56: =SUM(M3:M55) -> 0 | ... P56: =SUM(P3:P55) -> 0 | R56: €
A57: ITEM NO. | B57: DESCRIPTION | C57: QTY | D57: UNIT | E57: RATE | F57: TOTAL | R57: RATE
E58: € | F58: € | R58: €
A112: SB | E112: System total - carried forward to summary page : | F112: =SUM(F59:F111) -> 0 | R112: System total - carried forward to summary page :
A113: ITEM NO. | B113: DESCRIPTION | C113: QTY | D113: UNIT | E113: RATE | F113: TOTAL | R113: RATE
E114: € | F114: € | R114: €
A168: SB | E168: System total - carried forward to summary page : | F168: =SUM(F115:F167) -> 0 | R168: System total - carried forward to summary page :
A169: ITEM NO. | B169: DESCRIPTION | C169: QTY | D169: UNIT | E169: RATE | F169: TOTAL | R169: RATE
E170: € | F170: € | R170: €
A224: SB | E224: System total - carried forward to summary page : | F224: =SUM(F171:F223) -> 0 | R224: System total - carried forward to summary page :
A225: ITEM NO. | B225: DESCRIPTION | C225: QTY | D225: UNIT | E225: RATE | F225: TOTAL | R225: RATE
E226: € | F226: € | R226: €
A280: SB | E280: System total - carried forward to summary page : | F280: =SUM(F227:F279) -> 0 | R280: System total - carried forward to summary page :
A281: ITEM NO. | B281: DESCRIPTION | C281: QTY | D281: UNIT | E281: RATE | F281: TOTAL | R281: RATE
E282: € | F282: € | R282: €
A337: SB | E337: System total - carried forward to summary page : | F337: =SUM(F283:F336) -> 0 | R337: System total - carried forward to summary page :
A338: ITEM NO. | B338: DESCRIPTION | C338: QTY | D338: UNIT | E338: RATE | F338: TOTAL | R338: RATE
E339: € | F339: € | R339: €
A394: SB | E394: System total - carried forward to summary page : | F394: =SUM(F340:F393) -> 0 | R394: System total - carried forward to summary page :
A395: ITEM NO. | B395: DESCRIPTION | C395: QTY | D395: UNIT | E395: RATE | F395: TOTAL | R395: RATE
E396: € | F396: € | R396: €
A451: SB | E451: System total - carried forward to summary page : | F451: =SUM(F397:F450) -> 0 | R451: System total - carried forward to summary page :
A452: ITEM NO. | B452: DESCRIPTION | C452: QTY | D452: UNIT | E452: RATE | F452: TOTAL | R452: RATE
E453: € | F453: € | R453: €
A508: SB | E508: System total - carried forward to summary page : | F508: =SUM(F454:F507) -> 0 | R508: System total - carried forward to summary page :
A509: ITEM NO. | B509: DESCRIPTION | C509: QTY | D509: UNIT | E509: RATE | F509: TOTAL | R509: RATE
E510: € | F510: € | R510: €
A565: SB | E565: System total - carried forward to summary page : | F565: =SUM(F511:F564) -> 0 | R565: System total - carried forward to summary page :

Sheet E_DBOQ
A1: ITEM | B1: DESCRIPTION | C1: QTY | G1: UNIT | H1: RATE | I1: TOTAL | J1: Unit | K1: Total
C2: BOQ | D2: TDWG | E2: ACT | F2: DIFF | H2: € | I2: € | J2: Hrs | K2: Hrs
A54: SB | F54: System total - carried forward to summary page : | H54: VAT EXCL. | I54: =SUM(I3:I53) -> 0 | K54: =SUM(K3:K53) -> 0
A55: ITEM | B55: DESCRIPTION | C55: QTY | G55: UNIT | H55: RATE | I55: TOTAL | J55: Unit | K55: Total
C56: BOQ | D56: TDWG | E56: ACT | F56: DIFF | H56: € | I56: € | J56: Hrs | K56: Hrs
A111: SB | F111: System total - carried forward to summary page : | H111: VAT EXCL. | I111: =SUM(I57:I110) -> 0 | K111: =SUM(K57:K110) -> 0
A112: ITEM | B112: DESCRIPTION | C112: QTY | G112: UNIT | H112: RATE | I112: TOTAL | J112: Unit | K112: Total
C113: BOQ | D113: TDWG | E113: ACT | F113: DIFF | H113: € | I113: € | J113: Hrs | K113: Hrs
A168: SB | F168: System total - carried forward to summary page : | H168: VAT EXCL. | I168: =SUM(I114:I167) -> 0 | K168: =SUM(K114:K167) -> 0
A169: ITEM | B169: DESCRIPTION | C169: QTY | G169: UNIT | H169: RATE | I169: TOTAL | J169: Unit | K169: Total
C170: BOQ | D170: TDWG | E170: ACT | F170: DIFF | H170: € | I170: € | J170: Hrs | K170: Hrs
A225: SB | F225: System total - carried forward to summary page : | H225: VAT EXCL. | I225: =SUM(I171:I224) -> 0 | K225: =SUM(K171:K224) -> 0
A226: ITEM | B226: DESCRIPTION | C226: QTY | G226: UNIT | H226: RATE | I226: TOTAL | J226: Unit | K226: Total
C227: BOQ | D227: TDWG | E227: ACT | F227: DIFF | H227: € | I227: € | J227: Hrs | K227: Hrs
A282: SB | F282: System total - carried forward to summary page : | H282: VAT EXCL. | I282: =SUM(I228:I281) -> 0 | K282: =SUM(K228:K281) -> 0
A283: ITEM | B283: DESCRIPTION | C283: QTY | G283: UNIT | H283: RATE | I283: TOTAL | J283: Unit | K283: Total
C284: BOQ | D284: TDWG | E284: ACT | F284: DIFF | H284: € | I284: € | J284: Hrs | K284: Hrs
A339: SB | F339: System total - carried forward to summary page : | H339: VAT EXCL. | I339: =SUM(I285:I338) -> 0 | K339: =SUM(K285:K338) -> 0
A340: ITEM | B340: DESCRIPTION | C340: QTY | G340: UNIT | H340: RATE | I340: TOTAL | J340: Unit | K340: Total
C341: BOQ | D341: TDWG | E341: ACT | F341: DIFF | H341: € | I341: € | J341: Hrs | K341: Hrs
A396: SB | F396: System total - carried forward to summary page : | H396: VAT EXCL. | I396: =SUM(I342:I395) -> 0 | K396: =SUM(K342:K395) -> 0
A397: ITEM | B397: DESCRIPTION | C397: QTY | G397: UNIT | H397: RATE | I397: TOTAL | J397: Unit | K397: Total
C398: BOQ | D398: TDWG | E398: ACT | F398: DIFF | H398: € | I398: € | J398: Hrs | K398: Hrs
A453: SB | F453: System total - carried forward to summary page : | H453: VAT EXCL. | I453: =SUM(I399:I452) -> 0 | K453: =SUM(K399:K452) -> 0
A454: ITEM | B454: DESCRIPTION | C454: QTY | G454: UNIT | H454: RATE | I454: TOTAL | J454: Unit | K454: Total
C455: BOQ | D455: TDWG | E455: ACT | F455: DIFF | H455: € | I455: € | J455: Hrs | K455: Hrs
A510: SB | F510: System total - carried forward to summary page : | H510: VAT EXCL. | I510: =SUM(I456:I509) -> 0 | K510: =SUM(K456:K509) -> 0
A511: ITEM | B511: DESCRIPTION | C511: QTY | G511: UNIT | H511: RATE | I511: TOTAL | J511: Unit | K511: Total
C512: BOQ | D512: TDWG | E512: ACT | F512: DIFF | H512: € | I512: € | J512: Hrs | K512: Hrs
A567: SB | F567: System total - carried forward to summary page : | H567: VAT EXCL. | I567: =SUM(I513:I566) -> 0 | K567: =SUM(K513:K566) -> 0
