Workbook
Name __tab89: '[1]Table 8 & 9'!$B$4:$D$440
Name _N: #REF!
Name _tab89: '[1]Table 8 & 9'!$B$4:$D$440
Name A: #REF!
Name aaaa: #REF!
Name abcd: #REF!
Name Access_BMS: [3]BMS_Estimate!#REF!
Name Access_Control: [4]Elec_Est!#REF!
Name Access_Supply: [3]BMS_Estimate!#REF!
Name Access_Wiring: [3]BMS_Estimate!#REF!
Name AddedMat: '[5]Data Upload D'!$E$8:$E$9
Name ANS: #REF!
Name AREAS: #REF!
Name AREAS: [4]ML_Sum!$X$1:$AD$16
Name AREAS: ML_Sum!$X$1:$AD$16
Name ASD: #REF!
Name B: #REF!
Name BILL3: [6]LIST!$B$56:$B$114
Name BILL4: [6]LIST!$B$116:$B$223
Name BILL5: [6]LIST!$B$225:$B$290
Name BILL6: [6]LIST!$B$293:$B$357
Name BILL7: [6]LIST!$B$360:$B$423
Name Bill9: [6]BoQ_1020!$B$638:$B$702
Name boq: #REF!
Name C_: #REF!
Name CCTV: [4]Elec_Est!#REF!
Name Cert: [7]Data!$A$1:$H$65536
Name CHILLERS: Elec_Est!$A$16
Name CONCRETE: #REF!
Name Contractor2: '[8]1. Cover Sheet'!$C$11
Name Data: [4]Elec_Est!#REF!
Name DATA_5: [9]Data!$A$1:$H$65536
Name DATA_SYSTEM: #REF!
Name day_works: #REF!
Name DAYWORKS: #REF!
Name Excavation: [10]List!$B$275:$B$307
Name Excel_BuiltIn__FilterDatabase_1: #REF!
Name Excel_BuiltIn__FilterDatabase_4: #REF!
Name Excel_BuiltIn_Print_Area_4: #REF!
Name Fire_Alarm: [4]Elec_Est!#REF!
Name FO: [4]Elec_Est!#REF!
Name ghuk: [11]Data!$A$1:$H$65536
Name Guard: [4]Elec_Est!#REF!
Name Intercom: [4]Elec_Est!#REF!
Name Intruder_Alarm: [4]Elec_Est!#REF!
Name LEVEL: #REF!
Name LIGHTNING_PROTECTION: #REF!
Name list: [12]workings!$K$5:$K$6
Name LIST2: #REF!
Name list3: '[13]MoW 1010'!$B$161:$B$183
Name MASONRY: #REF!
Name MISCELLANEOUS: #REF!
Name Persons: [14]Estimate!#REF!
Name Print_Area_MI: #REF!
Name Pumps: Elec_Est!#REF!
Name RAMON: #REF!
Name REINFORCEMENT: #REF!
Name ROOFING: #REF!
Name sdgdfg: [15]Data!$A$1:$H$65536
Name steel: [10]List!$B$161:$B$178

Sheet Notes
A1: NOTES:

Sheet Quote
A1: =IF(AND(UPPER(LEFT(TRIM($D$8),11))="01",UPPER(LEFT(TRIM($D$9),3))<>"ELM"),"PANTA RETAIL LTD.","PANTA CONTRACTING LIMITED") -> PANTA CONTRACTING LIMITED
A2: =IF(UPPER(LEFT(TRIM($D$9),3))="ELM","ELEC-FOR-MECH INTERNAL QUOTATION","ELECTRICAL INTERNAL QUOTATION") -> ELEC-FOR-MECH INTERNAL QUOTATION
B5: ATT: | D5: =IF(A2="Internal Quotation", "Mechanical Division","") | R5: Dated: | S5: =NOW() -> 46127.715
B6: CLIENT: | C6: Link to ML_SUM $D1 | D6: =ML_Sum!D1 -> ST Microelectronics (Malta) Ltd.
B7: PROJECT: | C7: Link to ML_SUM $D2 | D7: =ML_Sum!D2 -> KK2 General Exhaust Replacement
B8: JOB DESC: | C8: Link to ML_SUM $D3 | D8: =ML_Sum!D3 -> Electrical Supply and Installation
B9: QUOTE No: | C9: Link to ML_SUM $D4 | D9: =ML_Sum!D4 -> ELM25-0560
B10: CLIENT's Ref: | C10: Link to ML_SUM $D5 | D10: =ML_Sum!D5 -> Tender
D22: Total Material Cost (€) : | E22: =ML_Sum!R35 -> 4954.73
D23: Total Labour (hrs) | E23: =ML_Sum!T35 -> 90.254065
A51: Signed for and on behalf of | Q51: Signed for and on behalf of
A52: Electrical Division | Q52: Division
Q54: Records
Q55: Mr. K. Micallef
Q57: File

Sheet ML_Sum
B1: CLIENT: | C1: 1 | D1: ST Microelectronics (Malta) Ltd. | G1: TRUE | H1: TRUE | I1: 1 | J1: =$Q109 -> 1 | K1: =$Q119 -> 1 | L1: =$Q129 -> 1 | M1: =$Q139 -> 1 | N1: =$Q149 -> 1 | O1: =$Q159 -> 1 | Q1: =IF(C1=1,"€","Curr?") -> € | R1: Recon /Lab.Cont >> | S1: =IF($S$39="PRINT","R","Do Not Print") -> R | T1: 1.15 | V1: {=IF(OR(X1=AREAS),1,0)} -> 1 | W1: BOQ | X1: x | Y1: x | Z1: x | AA1: x | AB1: x | AC1: x | AD1: x
B2: PROJECT: | C2: =IF($D$6="VAT INCLUDED",1.18,1)*(1-$Q2)*$C$1 -> 1 | D2: KK2 General Exhaust Replacement | F2: Electrical | G2: TRUE | I2: 2 | J2: =$Q110 -> 1 | K2: =$Q120 -> 1 | L2: =$Q130 -> 1 | M2: =$Q140 -> 1 | N2: =$Q150 -> 1 | O2: =$Q160 -> 1 | R2: ="A) " & IF($S2=0,"",ROUND($S2,2) & "-" & ROUND($T2/$D$9,2)) -> A) 1-1 | S2: 1 | T2: =$S2*$D$9 -> 27.46 | X2: x | Y2: x | Z2: x | AA2: x | AB2: x | AC2: x | AD2: x
B3: JOB DESC: | C3: =IF($D$6="VAT INCLUDED",1.18,1)*(1-$Q3)*$C$1 -> 1 | D3: Electrical Supply and Installation | F3: Controls | G3: TRUE | I3: 3 | J3: =$Q111 -> 1 | K3: =$Q121 -> 1 | L3: =$Q131 -> 1 | M3: =$Q141 -> 1 | N3: =$Q151 -> 1 | O3: =$Q161 -> 1 | R3: ="B) " & IF($S3=0,"",ROUND($S3,2) & "-" & ROUND($T3/$D$9,2)) -> B) 1-1 | S3: 1 | T3: =$S3*$D$9 -> 27.46 | X3: x | Y3: x | Z3: x | AA3: x | AB3: x | AC3: x | AD3: x
B4: INT. QUOT No: | C4: =IF($D$6="VAT INCLUDED",1.18,1)*(1-$Q4)*$C$1 -> 1 | D4: ELM25-0560 | F4: Controls | G4: TRUE | I4: 4 | J4: =$Q112 -> 1 | K4: =$Q122 -> 1 | L4: =$Q132 -> 1 | M4: =$Q142 -> 1 | N4: =$Q152 -> 1 | O4: =$Q162 -> 1 | R4: ="C) " & IF($S4=0,"",ROUND($S4,2) & "-" & ROUND($T4/$D$9,2)) -> C) 1-1 | S4: 1 | T4: =$S4*$D$9 -> 27.46 | X4: x | Y4: x | Z4: x | AA4: x | AB4: x | AC4: x | AD4: x
B5: CLIENTs REF: | C5: =IF($D$6="VAT INCLUDED",1.18,1)*(1-$Q5)*$C$1 -> 1 | D5: Tender | G5: TRUE | I5: 5 | J5: =$Q113 -> 1 | K5: =$Q123 -> 1 | L5: =$Q133 -> 1 | M5: =$Q143 -> 1 | N5: =$Q153 -> 1 | O5: =$Q163 -> 1 | R5: ="D) " & IF($S5=0,"",ROUND($S5,2) & "-" & ROUND($T5/$D$9,2)) -> D) | X5: x | Y5: x | Z5: x | AA5: x | AB5: x | AC5: x | AD5: x
B6: VAT: | C6: =IF($D$6="VAT INCLUDED",1.18,1)*(1-$Q6)*$C$1 -> 1 | D6: VAT EXCL. | G6: TRUE | I6: 6 | J6: =$Q114 -> 1 | K6: =$Q124 -> 1 | L6: =$Q134 -> 1 | M6: =$Q144 -> 1 | N6: =$Q154 -> 1 | O6: =$Q164 -> 1 | R6: ="E) " & IF($S6=0,"",ROUND($S6,2) & "-" & ROUND($T6/$D$9,2)) -> E) | X6: x | Y6: x | Z6: x | AA6: x | AB6: x | AC6: x | AD6: x
B7: SAVED ON: | C7: =IF($D$6="VAT INCLUDED",1.18,1)*(1-$Q7)*$C$1 -> 1 | D7: 45902 | G7: TRUE | I7: 7 | J7: =$Q115 -> 1 | K7: =$Q125 -> 1 | L7: =$Q135 -> 1 | M7: =$Q145 -> 1 | N7: =$Q155 -> 1 | R7: ="F) " & IF($S7=0,"",ROUND($S7,2) & "-" & ROUND($T7/$D$9,2)) -> F) | X7: x | Y7: x | Z7: x | AA7: x | AB7: x | AC7: x | AD7: x
B8: ESTIMATOR: | C8: =IF($D$6="VAT INCLUDED",1.18,1)*(1-$Q8)*$C$1 -> 1 | D8: Umut Kaymak | G8: TRUE | I8: 8 | J8: =$Q116 -> 1 | K8: =$Q126 -> 1 | L8: =$Q136 -> 1 | M8: =$Q146 -> 1 | N8: =$Q156 -> 1 | R8: ="G) " & IF($S8=0,"",ROUND($S8,2) & "-" & ROUND($T8/$D$9,2)) -> G) | X8: x | Y8: x | Z8: x | AA8: x | AB8: x | AC8: x | AD8: x
B9: LAB. COST: | C9: =IF($D$6="VAT INCLUDED",1.18,1)*(1-$Q9)*$C$1 -> 1 | D9: 27.46 | G9: TRUE | I9: 9 | J9: =$Q117 -> 1 | K9: =$Q127 -> 1 | L9: =$Q137 -> 1 | M9: =$Q147 -> 1 | N9: =$Q157 -> 1 | R9: ="H) " & IF($S9=0,"",ROUND($S9,2) & "-" & ROUND($T9/$D$9,2)) -> H) | X9: x | Y9: x | Z9: x | AA9: x | AB9: x | AC9: x | AD9: x
C10: =IF($D$6="VAT INCLUDED",1.18,1)*(1-$Q10)*$C$1 -> 1 | G10: TRUE | I10: 10 | J10: =$Q118 -> 1 | K10: =$Q128 -> 1 | L10: =$Q138 -> 1 | M10: =$Q148 -> 1 | N10: =$Q158 -> 1 | O10: =Q108 -> 1 | R10: =" I) " & IF($S10=0,"",ROUND($S10,2) & "-" & ROUND($T10/$D$9,2)) -> I) | X10: x | Y10: x | Z10: x | AA10: x | AB10: x | AC10: x | AD10: x
C11: =IF($D$6="VAT INCLUDED",1.18,1)*(1-$Q11)*$C$1 -> 1 | R11: ="J) " & IF($S11=0,"",ROUND($S11,2) & "-" & ROUND($T11/$D$9,2)) -> J) | X11: x | Y11: x | Z11: x | AA11: x | AB11: x | AC11: x | AD11: x
C12: =IF($D$6="VAT INCLUDED",1.18,1)*(1-$Q12)*$C$1 -> 1 | G12: SYSTEMS | H12: SYSTEMS | I12: SYSTEMS | J12: SYSTEMS | K12: SYSTEMS | L12: SYSTEMS | M12: SYSTEMS | N12: SYSTEMS | O12: SYSTEMS | P12: SYSTEMS | R12: MIXED - X,Y ) | S12: MAT MU | T12: LAB RATE | X12: x | Y12: x | Z12: x | AA12: x | AB12: x | AC12: x | AD12: x
B13: MATERIAL & LABOUR SUMMARY | G13: ItemCode | H13: CostCode | I13: MAKE | J13: PART_NO | K13: MARKUP | L13: TYPE | M13: LIST_P | N13: SET | O13: FIX | P13: DATE | Q13: %Dsct in BOQ | R13: MATMU-LABMU | S13: MAT CONT >> | T13: =SUM(Q108:Q164)/57 -> 1
B14: =IF($D$6<>"VAT EXCL.", "QUOTE ISSUED WITH VAT INCLUDED", "") | X14: x | Y14: x | Z14: x | AA14: x | AB14: x | AC14: x | AD14: x
Q15: =(C72-F35)/C72 -> 0 | R15: Average Discount applied in BOQ (Q2-Q12) | X15: x | Y15: x | Z15: x | AA15: x | AB15: x | AC15: x | AD15: x
B16: =IF($W$1<>"BOQ", "DIFF SET TO " & W1,"") | Q16: =(F35-E35)/F35 -> 0 | R16: Average Discount applied on Totals (Q23-Q32) | X16: x | Y16: x | Z16: x | AA16: x | AB16: x | AC16: x | AD16: x
Q17: =F74 -> 0 | R17: Overall Discount
B18: =IF(AND(G1,G2,G3,G4,G5,G6,G7,G8,G9,G10,H1)=TRUE, "", "CHECKLIST INCOMPLETE !" )
B19: =IF(ABS(SUM(A23:A32))>100,"[Discy A-J] are high, Check it out."," ") | Q19: =R83 -> 1.0000299 | R19: Overall Markup (Final Selling Excl.VAT/Total Cost )
E21: DISCOUNTED | F21: SELLING | Q21: % Discnt | R21: MATERIAL | T21: LABOUR
A22: Discy.A-J | B22: Markup/LRate | E22: ="SELLING " & $Q$1 -> SELLING € | F22: =$Q$1 -> € | G22: VAT/DISC | H22: MU | I22: LABRATE | J22: LABCOST | Q22: on Totals | R22: € | T22: Pair Hrs.
A23: =IF($F23=0,"",($F23/$C2)-($R23*$S2+$T23*$T2)) -> 0.00238 | B23: =IF(F23=0,"",IF(R23=0,"A) "&"---, "&ROUND(($F23/$C2-($R23*$S2))/$T23,2),IF(T23=0,"A) "&ROUND(($F23/$C2)/$R23,2),"A) "&ROUND(($F23/$C2-($T23*$T2))/$R23,2)&", " &ROUND(($F23/$C2-($R23*$S2))/$T23,2)))) -> A) 1, 27.46 | D23: =IF($F2="","",$F2) -> Electrical | E23: =F23*(1-Q23) -> 3598.99 | F23: =Elec_Est!F127 -> 3598.99 | G23: =C2 -> 1 | H23: =$S2 -> 1 | I23: =$T2 -> 27.46 | J23: =$D$9 -> 27.46 | R23: =Elec_Est!R127 -> 1731.79 | T23: =Elec_Est!T127 -> 67.997
A24: =IF($F24=0,"",($F24/$C3)-($R24*$S3+$T24*$T3)) -> -0.009 | B24: =IF(F24=0,"",IF(R24=0,"A) "&"---, "&ROUND(($F24/$C3-($R24*$S3))/$T24,2),IF(T24=0,"A) "&ROUND(($F24/$C3)/$R24,2),"A) "&ROUND(($F24/$C3-($T24*$T3))/$R24,2)&", " &ROUND(($F24/$C3-($R24*$S3))/$T24,2)))) -> A) 1, 27.46 | D24: =IF($F3="","",$F3) -> Controls | E24: =F24*(1-Q24) -> 3834.11 | F24: =Elec_Est!F128 -> 3834.11 | G24: =C3 -> 1 | H24: =$S3 -> 1 | I24: =$T3 -> 27.46 | J24: =$D$9 -> 27.46 | R24: =Elec_Est!R128 -> 3222.94 | T24: =Elec_Est!T128 -> 22.257065
A25: =IF($F25=0,"",($F25/$C4)-($R25*$S4+$T25*$T4)) | B25: =IF(F25=0,"",IF(R25=0,"A) "&"---, "&ROUND(($F25/$C4-($R25*$S4))/$T25,2),IF(T25=0,"A) "&ROUND(($F25/$C4)/$R25,2),"A) "&ROUND(($F25/$C4-($T25*$T4))/$R25,2)&", " &ROUND(($F25/$C4-($R25*$S4))/$T25,2)))) | D25: =IF($F4="","",$F4) -> Controls | E25: =F25*(1-Q25) -> 0 | F25: =Elec_Est!F129 -> 0 | G25: =C4 -> 1 | H25: =$S4 -> 1 | I25: =$T4 -> 27.46 | J25: =$D$9 -> 27.46 | R25: =Elec_Est!R129 -> 0 | T25: =Elec_Est!T129 -> 0
A26: =IF($F26=0,"",($F26/$C5)-($R26*$S5+$T26*$T5)) | B26: =IF(F26=0,"",IF(R26=0,"A) "&"---, "&ROUND(($F26/$C5-($R26*$S5))/$T26,2),IF(T26=0,"A) "&ROUND(($F26/$C5)/$R26,2),"A) "&ROUND(($F26/$C5-($T26*$T5))/$R26,2)&", " &ROUND(($F26/$C5-($R26*$S5))/$T26,2)))) | D26: =IF($F5="","",$F5) | E26: =F26*(1-Q26) -> 0 | F26: =Elec_Est!F130 -> 0 | G26: =C5 -> 1 | H26: =$S5 -> 0 | I26: =$T5 -> 0 | J26: =$D$9 -> 27.46 | R26: =Elec_Est!R130 -> 0 | T26: =Elec_Est!T130 -> 0
A27: =IF($F27=0,"",($F27/$C6)-($R27*$S6+$T27*$T6)) | B27: =IF(F27=0,"",IF(R27=0,"A) "&"---, "&ROUND(($F27/$C6-($R27*$S6))/$T27,2),IF(T27=0,"A) "&ROUND(($F27/$C6)/$R27,2),"A) "&ROUND(($F27/$C6-($T27*$T6))/$R27,2)&", " &ROUND(($F27/$C6-($R27*$S6))/$T27,2)))) | D27: =IF($F6="","",$F6) | E27: =F27*(1-Q27) -> 0 | F27: =Elec_Est!F131 -> 0 | G27: =C6 -> 1 | H27: =$S6 -> 0 | I27: =$T6 -> 0 | J27: =$D$9 -> 27.46 | R27: =Elec_Est!R131 -> 0 | T27: =Elec_Est!T131 -> 0
A28: =IF($F28=0,"",($F28/$C7)-($R28*$S7+$T28*$T7)) | B28: =IF(F28=0,"",IF(R28=0,"A) "&"---, "&ROUND(($F28/$C7-($R28*$S7))/$T28,2),IF(T28=0,"A) "&ROUND(($F28/$C7)/$R28,2),"A) "&ROUND(($F28/$C7-($T28*$T7))/$R28,2)&", " &ROUND(($F28/$C7-($R28*$S7))/$T28,2)))) | D28: =IF($F7="","",$F7) | E28: =F28*(1-Q28) -> 0 | F28: =Elec_Est!F132 -> 0 | G28: =C7 -> 1 | H28: =$S7 -> 0 | I28: =$T7 -> 0 | J28: =$D$9 -> 27.46 | R28: =Elec_Est!R132 -> 0 | T28: =Elec_Est!T132 -> 0
A29: =IF($F29=0,"",($F29/$C8)-($R29*$S8+$T29*$T8)) | B29: =IF(F29=0,"",IF(R29=0,"A) "&"---, "&ROUND(($F29/$C8-($R29*$S8))/$T29,2),IF(T29=0,"A) "&ROUND(($F29/$C8)/$R29,2),"A) "&ROUND(($F29/$C8-($T29*$T8))/$R29,2)&", " &ROUND(($F29/$C8-($R29*$S8))/$T29,2)))) | D29: =IF($F8="","",$F8) | E29: =F29*(1-Q29) -> 0 | F29: =Elec_Est!F133 -> 0 | G29: =C8 -> 1 | H29: =$S8 -> 0 | I29: =$T8 -> 0 | J29: =$D$9 -> 27.46 | R29: =Elec_Est!R133 -> 0 | T29: =Elec_Est!T133 -> 0
A30: =IF($F30=0,"",($F30/$C9)-($R30*$S9+$T30*$T9)) | B30: =IF(F30=0,"",IF(R30=0,"A) "&"---, "&ROUND(($F30/$C9-($R30*$S9))/$T30,2),IF(T30=0,"A) "&ROUND(($F30/$C9)/$R30,2),"A) "&ROUND(($F30/$C9-($T30*$T9))/$R30,2)&", " &ROUND(($F30/$C9-($R30*$S9))/$T30,2)))) | D30: =IF($F9="","",$F9) | E30: =F30*(1-Q30) -> 0 | F30: =Elec_Est!F134 -> 0 | G30: =C9 -> 1 | H30: =$S9 -> 0 | I30: =$T9 -> 0 | J30: =$D$9 -> 27.46 | R30: =Elec_Est!R134 -> 0 | T30: =Elec_Est!T134 -> 0
A31: =IF($F31=0,"",($F31/$C10)-($R31*$S10+$T31*$T10)) | B31: =IF(F31=0,"",IF(R31=0,"A) "&"---, "&ROUND(($F31/$C10-($R31*$S10))/$T31,2),IF(T31=0,"A) "&ROUND(($F31/$C10)/$R31,2),"A) "&ROUND(($F31/$C10-($T31*$T10))/$R31,2)&", " &ROUND(($F31/$C10-($R31*$S10))/$T31,2)))) | D31: =IF($F10="","",$F10) | E31: =F31*(1-Q31) -> 0 | F31: =Elec_Est!F135 -> 0 | G31: =C10 -> 1 | H31: =$S10 -> 0 | I31: =$T10 -> 0 | J31: =$D$9 -> 27.46 | R31: =Elec_Est!R135 -> 0 | T31: =Elec_Est!T135 -> 0
A32: =IF($F32=0,"",($F32/$C11)-($R32*$S11+$T32*$T11)) | B32: =IF(F32=0,"",IF(R32=0,"A) "&"---, "&ROUND(($F32/$C11-($R32*$S11))/$T32,2),IF(T32=0,"A) "&ROUND(($F32/$C11)/$R32,2),"A) "&ROUND(($F32/$C11-($T32*$T11))/$R32,2)&", " &ROUND(($F32/$C11-($R32*$S11))/$T32,2)))) | D32: =IF($F11="","",$F11) | E32: =F32*(1-Q32) -> 0 | F32: =Elec_Est!F136 -> 0 | G32: =C11 -> 1 | H32: =$S11 -> 0 | I32: =$T11 -> 0 | J32: =$D$9 -> 27.46 | R32: =Elec_Est!R136 -> 0 | T32: =Elec_Est!T136 -> 0
C33: MIXED
A35: Discy.L | B35: =E_BOQ!F51 -> 7433.1 | E35: =SUM(E23:E32) -> 7433.1 | F35: =SUM(F23:F32) -> 7433.1 | R35: =SUM(R23:R32) -> 4954.73 | T35: =SUM(T23:T32) -> 90.254065
A36: =IF(A39=0,"0.00",A39-(A38*A37)) -> 0.00 | B36: BOQ TOTAL | E36: ="ESTIM TOTAL (" & $Q$1 & ")" -> ESTIM TOTAL (€)
A37: 1.125 | B37: <1 Actual LabCont | R37: =R165 -> 4954.7482 | S37: C.C.Totals | T37: =T165 -> 90.245065
B38: <2 Phrs @ 1.00
B39: <3 Phrs @ Actual | Q39: Discy.T >> | R39: =R37-R35 -> 0.01819 | S39: PRINT | T39: =T37-T35 -> -0.009
B41: Values Only on : | D41: 45902 | E41: 3567.42 | F41: 3567.42 | R41: 1731.79 | T41: 66.847
A46: REMARKS:
A47: 1) VAT and Duties as above.
A48: 2)
A51: ESTIMATOR: | D51: =D8 -> Umut Kaymak | Q51: APPROVED BY:
A53: SIGNED: | Q53: DATE APPROVED:
A55: FILE LOCATION: | D55: =CELL("filename") -> https://d.docs.live.net/d8e42587b76b10ba/Documents/Visual Code Studio/Claude/BMS-Attribution-Model/projects/ST_Micro_Exhaust_Fans/[ELM25_0560_ST_Electronics_Exhaust_Replacement_Est_.xlsx]E_BOQ
B57: PANTA CONTRACTING LTD. - ELECTRICAL DIVISION
B58: CONTRACT / VARIATION INPUT DOCUMENT
S59: Copy to:-
D60: Client: | E60: =D1 -> ST Microelectronics (Malta) Ltd. | S60: Ms. S. Magri
D61: Project: | E61: =D2 -> KK2 General Exhaust Replacement | S61: Mr. K. Micallef
D62: Job Description: | E62: =D3 -> Electrical Supply and Installation | S62: Mr. A. Sciberras
D63: Quote No: | E63: =D4 -> ELM25-0560
D64: Client's Ref: | E64: =D5 -> Tender
S65: File:-
D66: File No:
D67: Ext. Ref:
E70: Contract /Variation (Excl. VAT)
C72: =IF($A$33="MIXED",F23/(1-Q2)+F24/(1-Q3)+F25/(1-Q4)+F26/(1-Q5)+F27/(1-Q6)+F28/(1-Q7)+F29/(1-Q8)+F30/(1-Q9)+F31/(1-Q10)+F32/(1-Q11)-SUM(A23:A32), F23/(1-Q2)+F24/(1-Q3)+F25/(1-Q4)+F26/(1-Q5)+F27/(1-Q6)+F28/(1-Q7)+F29/(1-Q8)+F30/(1-Q9)+F31/(1-Q10)+F32/(1-Q11)) -> 7433.1 | E72: Estim.Sell before Discounts excl.VAT (€): | F72: =IF(D6="VAT INCLUDED",C72/($C$1*1.18),C72/$C$1) -> 7433.1
E74: Overall Discount: | F74: =(F72-F75)/F72 -> 0
E75: Final Sell after Discounts excl.VAT (€): | F75: =IF(D6="VAT INCLUDED",E35/($C$1*1.18),E35/$C$1) -> 7433.1
E77: Labour Rate - | F77: =$D$9 -> 27.46 | R77: Mech. Cost to us
D80: Mat. Cost | E80: Labour | F80: Total Cost | R80: Sell Excl.VAT / Total Cost
D81: € | E81: Pair.Hrs | F81: €
D83: =R165 -> 4954.7482 | E83: =T165 -> 90.245065 | F83: =R165+S165 -> 7432.8777 | R83: =IF(F83=0,0,F75/F83) -> 1.0000299
D84: ( From CostCode Totals )
R87: Advanced Payment:
R88: Retention:
R90: Awarded Date:
R91: Estimated Start Date:
R92: Estimated Completion Date:
D93: .................
D94: A. Sciberras | R94: Date issued:
D95: =NOW() -> 46127.715
D98: PANTA CONTRACTING LTD. - ELECTRICAL DIVISION
D99: ELECTRICAL AND ELV CONTRACT / VARIATION BUDGET COST
D101: Project: | E101: =E61 -> KK2 General Exhaust Replacement
D102: Job Desc: | E102: =E62 -> Electrical Supply and Installation
D103: Client's Ref: | E103: =E64 -> Tender
D106: COSTCODE | F106: Cost | Q106: Mat. | R106: Mat Cost | S106: Lab Cost @ | T106: Labour
F107: Code | Q107: Cont. | R107: € | S107: =$D$9 -> 27.46 | T107: Pair.Hrs
B108: V:56 | D108: BOQ RateOnly Items | P108: FIX | Q108: 1
B109: 1(J) | C109: cc | D109: Erection materials | F109: 501 | P109: 1 | Q109: 1 | R109: =Elec_Est!R148 -> 428.489 | S109: =T109*$D$9 -> 94.737 | T109: =Elec_Est!T148 -> 3.45
B110: 2 | C110: cc | D110: Busbar Trunking | F110: 505 | P110: 1 | Q110: 1 | R110: =Elec_Est!R149 -> 0 | S110: =T110*$D$9 -> 0 | T110: =Elec_Est!T149 -> 0
B111: 3 | C111: cc | D111: Switchgear | F111: 510 | P111: 2 | Q111: 1 | R111: =Elec_Est!R150 -> 130.3 | S111: =T111*$D$9 -> 78.9475 | T111: =Elec_Est!T150 -> 2.875
B112: 4 | C112: cc | D112: MCC Equipment | F112: 511 | P112: 2 | Q112: 1 | R112: =Elec_Est!R151 -> 0 | S112: =T112*$D$9 -> 0 | T112: =Elec_Est!T151 -> 0
B113: 5 | C113: cc | D113: BMS Equipment | F113: 512 | P113: 2 | Q113: 1 | R113: =Elec_Est!R152 -> 3222.94 | S113: =T113*$D$9 -> 642.758 | T113: =Elec_Est!T152 -> 23.407065
B114: 6 | C114: cc | D114: PVC Pipes / Ducts | F114: 520 | P114: 1 | Q114: 1 | R114: =Elec_Est!R153 -> 0 | S114: =T114*$D$9 -> 0 | T114: =Elec_Est!T153 -> 0
B115: 7 | C115: cc | D115: High/medium voltage switchgear | F115: 530 | P115: 2 | Q115: 1 | R115: =Elec_Est!R154 -> 0 | S115: =T115*$D$9 -> 0 | T115: =Elec_Est!T154 -> 0
B116: 8 | C116: cc | D116: Power Transformers | F116: 550 | P116: 2 | Q116: 1 | R116: =Elec_Est!R155 -> 0 | S116: =T116*$D$9 -> 0 | T116: =Elec_Est!T155 -> 0
B117: 9 | C117: cc | D117: Control Panels | F117: 570 | P117: 2 | Q117: 1 | R117: =Elec_Est!R156 -> 0 | S117: =T117*$D$9 -> 0 | T117: =Elec_Est!T156 -> 0
B118: 10 | C118: cc | D118: Electrical Single Core Cables | F118: 615 | P118: 2 | Q118: 1 | R118: =Elec_Est!R157 -> 0 | S118: =T118*$D$9 -> 0 | T118: =Elec_Est!T157 -> 0
B119: 11(K) | C119: cc | D119: Electrical Multicore Cables | F119: 616 | P119: 2 | Q119: 1 | R119: =Elec_Est!R158 -> 224 | S119: =T119*$D$9 -> 91.5791 | T119: =Elec_Est!T158 -> 3.335
B120: 12 | C120: cc | D120: ELV/BMS/Special Cables | F120: 617 | P120: 2 | Q120: 1 | R120: =Elec_Est!R159 -> 288 | S120: =T120*$D$9 -> 227.3688 | T120: =Elec_Est!T159 -> 8.28
B121: 13 | C121: cc | D121: Cable Accessories | F121: 620 | P121: 2 | Q121: 1 | R121: =Elec_Est!R160 -> 70.16 | S121: =T121*$D$9 -> 217.26352 | T121: =Elec_Est!T160 -> 7.912
B122: 14 | C122: cc | D122: Galv. Cable Trays | F122: 650 | P122: 1 | Q122: 1 | R122: =Elec_Est!R161 -> 396.50919 | S122: =T122*$D$9 -> 130.73706 | T122: =Elec_Est!T161 -> 4.761
B123: 15 | C123: cc | D123: PVC Cable Trays | F123: 651 | P123: 1 | Q123: 1 | R123: =Elec_Est!R162 -> 0 | S123: =T123*$D$9 -> 0 | T123: =Elec_Est!T162 -> 0
B124: 16 | C124: cc | D124: Galv. Cable Basket | F124: 652 | P124: 1 | Q124: 1 | R124: =Elec_Est!R163 -> 0 | S124: =T124*$D$9 -> 0 | T124: =Elec_Est!T163 -> 0
B125: 17 | C125: cc | D125: Galv. Cable Ladder | F125: 654 | P125: 1 | Q125: 1 | R125: =Elec_Est!R164 -> 0 | S125: =T125*$D$9 -> 0 | T125: =Elec_Est!T164 -> 0
B126: 18 | C126: cc | D126: Galv. Cable Trunking | F126: 675 | P126: 1 | Q126: 1 | R126: =Elec_Est!R165 -> 0 | S126: =T126*$D$9 -> 0 | T126: =Elec_Est!T165 -> 0
B127: 19 | C127: cc | D127: Alum. Cable Trunking | F127: 676 | P127: 1 | Q127: 1 | R127: =Elec_Est!R166 -> 0 | S127: =T127*$D$9 -> 0 | T127: =Elec_Est!T166 -> 0
B128: 20 | C128: cc | D128: PVC Cable Trunking | F128: 680 | P128: 1 | Q128: 1 | R128: =Elec_Est!R167 -> 0 | S128: =T128*$D$9 -> 0 | T128: =Elec_Est!T167 -> 0
...

Sheet Elec_Rates
B1: CLIENT: | C1: =ML_Sum!$C1 -> 1 | D1: =ML_Sum!$D1 -> ST Microelectronics (Malta) Ltd. | F1: =ML_Sum!$F1 -> 0 | I1: 1 | J1: =ML_Sum!$J1 -> 1 | K1: =ML_Sum!$K1 -> 1 | L1: =ML_Sum!$L1 -> 1 | M1: =ML_Sum!$M1 -> 1 | N1: =ML_Sum!$N1 -> 1 | O1: =ML_Sum!$O1 -> 1 | Q1: =ML_Sum!$Q1 -> € | R1: R/Lab Cont | S1: =ML_Sum!$S1 -> R | T1: =ML_Sum!$T1 -> 1.15 | U1: =ML_Sum!W1 -> BOQ | V1: INCL | W1: MULT | X1: AREA | Y1: BOQ | Z1: TDWG | AA1: ACT | AB1: DIFF
B2: PROJECT: | C2: =ML_Sum!$C2 -> 1 | D2: =ML_Sum!$D2 -> KK2 General Exhaust Replacement | F2: =ML_Sum!$F2 -> Electrical | I2: 2 | J2: =ML_Sum!$J2 -> 1 | K2: =ML_Sum!$K2 -> 1 | L2: =ML_Sum!$L2 -> 1 | M2: =ML_Sum!$M2 -> 1 | N2: =ML_Sum!$N2 -> 1 | O2: =ML_Sum!$O2 -> 1 | Q2: =ML_Sum!$Q2 -> 0 | R2: mu_A | S2: =ML_Sum!$S2 -> 1 | T2: =ML_Sum!$T2 -> 27.46
B3: JOB DESC: | C3: =ML_Sum!$C3 -> 1 | D3: =ML_Sum!$D3 -> Electrical Supply and Installation | F3: =ML_Sum!$F3 -> Controls | I3: 3 | J3: =ML_Sum!$J3 -> 1 | K3: =ML_Sum!$K3 -> 1 | L3: =ML_Sum!$L3 -> 1 | M3: =ML_Sum!$M3 -> 1 | N3: =ML_Sum!$N3 -> 1 | O3: =ML_Sum!$O3 -> 1 | Q3: =ML_Sum!$Q3 -> 0 | R3: mu_B | S3: =ML_Sum!$S3 -> 1 | T3: =ML_Sum!$T3 -> 27.46
B4: QUOTE No: | C4: =ML_Sum!$C4 -> 1 | D4: =ML_Sum!$D4 -> ELM25-0560 | F4: =ML_Sum!$F4 -> Controls | I4: 4 | J4: =ML_Sum!$J4 -> 1 | K4: =ML_Sum!$K4 -> 1 | L4: =ML_Sum!$L4 -> 1 | M4: =ML_Sum!$M4 -> 1 | N4: =ML_Sum!$N4 -> 1 | O4: =ML_Sum!$O4 -> 1 | Q4: =ML_Sum!$Q4 -> 0 | R4: mu_C | S4: =ML_Sum!$S4 -> 1 | T4: =ML_Sum!$T4 -> 27.46
B5: CLIENTs REF: | C5: =ML_Sum!$C5 -> 1 | D5: =ML_Sum!$D5 -> Tender | F5: =ML_Sum!$F5 -> 0 | I5: 5 | J5: =ML_Sum!$J5 -> 1 | K5: =ML_Sum!$K5 -> 1 | L5: =ML_Sum!$L5 -> 1 | M5: =ML_Sum!$M5 -> 1 | N5: =ML_Sum!$N5 -> 1 | O5: =ML_Sum!$O5 -> 1 | Q5: =ML_Sum!$Q5 -> 0 | R5: mu_D | S5: =ML_Sum!$S5 -> 0 | T5: =ML_Sum!$T5 -> 0
B6: VAT/DUTIES: | C6: =ML_Sum!$C6 -> 1 | D6: =ML_Sum!$D6 -> VAT EXCL. | F6: =ML_Sum!$F6 -> 0 | I6: 6 | J6: =ML_Sum!$J6 -> 1 | K6: =ML_Sum!$K6 -> 1 | L6: =ML_Sum!$L6 -> 1 | M6: =ML_Sum!$M6 -> 1 | N6: =ML_Sum!$N6 -> 1 | O6: =ML_Sum!$O6 -> 1 | Q6: =ML_Sum!$Q6 -> 0 | R6: mu_E | S6: =ML_Sum!$S6 -> 0 | T6: =ML_Sum!$T6 -> 0
B7: SAVED ON: | C7: =ML_Sum!$C7 -> 1 | D7: 39364 | F7: =ML_Sum!$F7 -> 0 | I7: 7 | J7: =ML_Sum!$J7 -> 1 | K7: =ML_Sum!$K7 -> 1 | L7: =ML_Sum!$L7 -> 1 | M7: =ML_Sum!$M7 -> 1 | N7: =ML_Sum!$N7 -> 1 | O7: =ML_Sum!$O7 -> 0 | Q7: =ML_Sum!$Q7 -> 0 | R7: mu_F | S7: =ML_Sum!$S7 -> 0 | T7: =ML_Sum!$T7 -> 0
B8: ESTIMATOR: | C8: =ML_Sum!$C8 -> 1 | D8: =ML_Sum!$D8 -> Umut Kaymak | F8: =ML_Sum!$F8 -> 0 | I8: 8 | J8: =ML_Sum!$J8 -> 1 | K8: =ML_Sum!$K8 -> 1 | L8: =ML_Sum!$L8 -> 1 | M8: =ML_Sum!$M8 -> 1 | N8: =ML_Sum!$N8 -> 1 | O8: =ML_Sum!$O8 -> 0 | Q8: =ML_Sum!$Q8 -> 0 | R8: mu_G | S8: =ML_Sum!$S8 -> 0 | T8: =ML_Sum!$T8 -> 0
B9: LABOUR RATE: | C9: =ML_Sum!$C9 -> 1 | D9: =ML_Sum!$D9 -> 27.46 | F9: =ML_Sum!$F9 -> 0 | I9: 9 | J9: =ML_Sum!$J9 -> 1 | K9: =ML_Sum!$K9 -> 1 | L9: =ML_Sum!$L9 -> 1 | M9: =ML_Sum!$M9 -> 1 | N9: =ML_Sum!$N9 -> 1 | O9: =ML_Sum!$O9 -> 0 | Q9: =ML_Sum!$Q9 -> 0 | R9: mu_H | S9: =ML_Sum!$S9 -> 0 | T9: =ML_Sum!$T9 -> 0
C10: =ML_Sum!$C10 -> 1 | F10: =ML_Sum!$F10 -> 0 | I10: 10 | J10: =ML_Sum!$J10 -> 1 | K10: =ML_Sum!$K10 -> 1 | L10: =ML_Sum!$L10 -> 1 | M10: =ML_Sum!$M10 -> 1 | N10: =ML_Sum!$N10 -> 1 | O10: =ML_Sum!$O10 -> 1 | Q10: =ML_Sum!$Q10 -> 0 | R10: mu_I | S10: =ML_Sum!$S10 -> 0 | T10: =ML_Sum!$T10 -> 0
C11: =ML_Sum!$C11 -> 1 | F11: =ML_Sum!$F11 -> 0 | Q11: =ML_Sum!$Q11 -> 0 | R11: mu_J | S11: =ML_Sum!$S11 -> 0 | T11: =ML_Sum!$T11 -> 0
C12: =ML_Sum!$C12 -> 1 | F12: =ML_Sum!$F12 -> 0 | Q12: =ML_Sum!$Q12 -> 0 | R12: MIXED | S12: =ML_Sum!$S12 -> MAT MU | T12: =ML_Sum!$T12 -> LAB RATE
G13: I_CODE | H13: C_CODE | I13: MAKE | J13: PART_NO | K13: MARKUP | L13: TYPE | M13: LIST_P | N13: P_FACT | O13: FIX | P13: DATE | Q13: %Dsct in BOQ | R13: MU TYPE | S13: MAT MU | T13: LAB RATE
C15: t | D15: Item:
D16: Start Typing Header
Q18: Multip
A19: 1850 | B19: =Elec_Est!B212 -> 0 | D19: 001# 1c x 240sqmm FG160M1 cables | K19: RATE | L19: RATE | Q19: =B19/A19 -> 0 | R19: =IF($B19=0,0,IF($S$1="R",ROUND(R24/$B19,2),R24/$B19)) -> 0 | T19: =IF($B19=0,0,IF($S$1="R",ROUND(T24/$B19,2),T24/$B19)) -> 0
D20: Based on:
D21: 1c x 240sqmm FG160M1 XLPE/LSZH cables from KK2A S/S to Chiller 3 (Quantity 9 cables)
D22: Labour for connecting up in existing switchboards and Chillers
C23: << ==== TOTAL UNITS | R23: =$A23*Q23 -> 0 | T23: =$A23*S23*$T$1 -> 0
A24: d> | B24: =(R24+T24)-SUM(R20:R23,T20:T23) -> 0 | D24: Sell_A | E24: =IF($B19=0,0,ROUND(ROUND(($R24*$S$2+($T24*$T$2))/$B19, 2)*$C$2,2)) -> 0 | F24: =ROUND($B19*$E24,2) -> 0 | K24: ITEM | L24: ITEM | R24: =SUM(R20:R23) -> 0 | T24: =SUM(T20:T23) -> 0
Q25: Multip
A26: 150 | B26: =Elec_Est!B213 -> 6 | D26: 002# 200mm galvanised steel cable tray complete with cover | K26: RATE | L26: RATE | Q26: =B26/A26 -> 0.04 | R26: =IF($B26=0,0,IF($S$1="R",ROUND(R39/$B26,2),R39/$B26)) -> 69.42 | T26: =IF($B26=0,0,IF($S$1="R",ROUND(T39/$B26,2),T39/$B26)) -> 0.79
D27: Based on:
A28: =$Q$26 *(150) -> 6 | B28: m | D28: 200x50mm Tray | F28: Cleveland | G28: TRGV_009 | H28: 650 | I28: (__) | O28: 1 | P28: 36897 | Q28: =1.477*32.11/3 -> 15.808823 | R28: =$A28*Q28 -> 94.85294 | S28: 0.3 | T28: =$A28*S28*$T$1 -> 2.07
A29: =$Q$26 *(150) -> 6 | B29: m | D29: Tray 200mm Galv. Cover | F29: Cleveland | G29: TRGV_057 | H29: 650 | I29: (__) | O29: 1 | Q29: =1.477*48.6/3 -> 23.9274 | R29: =$A29*Q29 -> 143.5644 | S29: 0.3 | T29: =$A29*S29*$T$1 -> 2.07
A30: =$Q$26 *(150*2) -> 12 | B30: m | D30: Tray 200mm Galv. Cover clamp | F30: Cleveland | G30: TRGV_057 | H30: 650 | I30: (__) | O30: 1 | Q30: =1.477*2.2 -> 3.2494 | R30: =$A30*Q30 -> 38.9928 | T30: =$A30*S30*$T$1 -> 0
A31: =$Q$26 *(150/3) -> 2 | B31: No. | D31: 200x50mm Tray Coupler | F31: Cleveland | H31: 650 | Q31: =1.477*2.48 -> 3.66296 | R31: =$A31*Q31 -> 7.32592 | S31: 0.02 | T31: =$A31*S31*$T$1 -> 0.046
A32: =$Q$26 *(15) -> 0.6 | B32: m | D32: FLAT BEND | F32: Cleveland | G32: TRGV_057 | H32: 650 | I32: (__) | O32: 1 | Q32: =1.477*26.65 -> 39.36205 | R32: =$A32*Q32 -> 23.61723 | S32: 0.3 | T32: =$A32*S32*$T$1 -> 0.207
A33: 1 | B33: m | D33: EXTERNAL RISER BEND | F33: Cleveland | G33: TRGV_057 | H33: 650 | I33: (__) | O33: 1 | Q33: =1.477*14.91 -> 22.02207 | R33: =$A33*Q33 -> 22.02207 | T33: =$A33*S33*$T$1 -> 0
A34: 1 | B34: m | D34: TEE | F34: Cleveland | G34: TRGV_057 | H34: 650 | I34: (__) | O34: 1 | Q34: =1.477*35.79 -> 52.86183 | R34: =$A34*Q34 -> 52.86183 | S34: 0.3 | T34: =$A34*S34*$T$1 -> 0.345
A35: =$Q$26 *(150/3) -> 2 | B35: No. | D35: Tray Earth Links | F35: Not quoted by Legrand | H35: 650 | Q35: 1.596 | R35: =$A35*Q35 -> 3.192 | S35: 0.01 | T35: =$A35*S35*$T$1 -> 0.023
A36: =$Q$26 *(150*8) -> 48 | B36: No. | D36: Tray Coupling Bolts | F36: Legrand - ESS | H36: 650 | Q36: 0.21 | R36: =$A36*Q36 -> 10.08 | T36: =$A36*S36*$T$1 -> 0
A37: =$Q$26 *(1) -> 0.04 | B37: LS | D37: SUBCONTRACTING WORKS | F37: Crane to carry the materials to the roof | G37: SUBC_001 | H37: 960 | I37: MISC | O37: 4 | P37: 38274 | Q37: 500 | R37: =$A37*Q37 -> 20 | T37: =$A37*S37*$T$1 -> 0
C38: << ==== TOTAL UNITS | R38: =$A38*Q38 -> 0 | T38: =$A38*S38*$T$1 -> 0
A39: d> | B39: =(R38+T38) -> 0 | D39: Sell_A | E39: =IF($B26=0,0,ROUND(ROUND(($R39*$S$2+($T39*$T$2))/$B26, 2)*$C$2,2)) -> 91.21 | F39: =ROUND($B26*$E39,2) -> 547.26 | K39: ITEM | L39: ITEM | R39: =SUM(R27:R38) -> 416.50919 | T39: =SUM(T27:T38) -> 4.761
Q40: Multip
A41: 150 | B41: =Elec_Est!B214 -> 6 | D41: 003# Cable Containment Support | K41: RATE | L41: RATE | Q41: =B41/A41 -> 0.04 | R41: =IF($B41=0,0,IF($S$1="R",ROUND(R108/$B41,2),R108/$B41)) -> 71.41 | T41: =IF($B41=0,0,IF($S$1="R",ROUND(T108/$B41,2),T108/$B41)) -> 0.58
D42: Based on: brackets spaced at metres intervals
D43: Supports - HDG - Switch Room | F43: 5 metres Riser | R43: =$A43*Q43 -> 0 | T43: =$A43*S43*$T$1 -> 0 | W43: 2
A44: =$Q$41 *(2) -> 0.08 | B44: m | D44: Channel MT-40 S OC | F44: Hilti | G44: EMAT_019 | H44: 501 | I44: HIL | J44: MS-413m | K44: 02-018 | O44: 1 | P44: 36175 | Q44: 15.65 | R44: =$A44*Q44 -> 1.252 | T44: =$A44*S44*$T$1 -> 0 | W44: 10
A45: =$Q$41 *(10) -> 0.4 | B45: No. | D45: Channel 40x40 Endcap MT-EC-40/50 | F45: Hilti | H45: 501 | Q45: 0.15 | R45: =$A45*Q45 -> 0.06 | T45: =$A45*S45*$T$1 -> 0 | W45: 10
A46: =$Q$41 *(10) -> 0.4 | B46: No. | D46: HLC Sleeve Anchor 10mm HLC 10x50/15 | F46: Hilti | H46: 501 | Q46: 0.31 | R46: =$A46*Q46 -> 0.124 | T46: =$A46*S46*$T$1 -> 0 | W46: 10
A47: =$Q$41 *(10) -> 0.4 | B47: No. | D47: Wing Nut Hilti M8 MQM-M8-F | F47: Hilti | H47: 501 | Q47: 0.66 | R47: =$A47*Q47 -> 0.264 | T47: =$A47*S47*$T$1 -> 0 | W47: 10
A48: =$Q$41 *(10) -> 0.4 | B48: No. | D48: Hex.Set Screw M8x25 | F48: Hilti | H48: 501 | Q48: 0.05 | R48: =$A48*Q48 -> 0.02 | T48: =$A48*S48*$T$1 -> 0 | W48: 10
A49: =$Q$41 *(10) -> 0.4 | B49: No. | D49: Galv. Nut 8mm M8-F | F49: Hilti | H49: 501 | Q49: 0.05 | R49: =$A49*Q49 -> 0.02 | T49: =$A49*S49*$T$1 -> 0 | W49: 10
A50: =$Q$41 *(10) -> 0.4 | B50: No. | D50: Tray Washers M8 | H50: 501 | Q50: 0.01 | R50: =$A50*Q50 -> 0.004 | T50: =$A50*S50*$T$1 -> 0
D51: Supports - HDG - Tunnel | F51: 15 metres Wall | R51: =$A51*Q51 -> 0 | T51: =$A51*S51*$T$1 -> 0 | W51: 7.5
A52: =$Q$41 *(7.5) -> 0.3 | B52: m | D52: Channel MT-40 S OC | F52: Hilti | G52: EMAT_019 | H52: 501 | I52: HIL | J52: MS-413m | K52: 02-018 | O52: 1 | P52: 36175 | Q52: 15.65 | R52: =$A52*Q52 -> 4.695 | T52: =$A52*S52*$T$1 -> 0 | W52: 15
A53: =$Q$41 *(15) -> 0.6 | B53: No. | D53: Channel 40x40 Endcap MT-EC-40/50 | F53: Hilti | H53: 501 | Q53: 0.15 | R53: =$A53*Q53 -> 0.09 | T53: =$A53*S53*$T$1 -> 0 | W53: 15
A54: =$Q$41 *(15) -> 0.6 | B54: No. | D54: Channel Base Hilti MT-B-O2-OC | F54: Hilti | H54: 501 | Q54: 14.47 | R54: =$A54*Q54 -> 8.682 | T54: =$A54*S54*$T$1 -> 0 | W54: 60
A55: =$Q$41 *(60) -> 2.4 | B55: No. | D55: HLC Sleeve Anchor 10mm HLC 10x50/15 | F55: Hilti | H55: 501 | Q55: 0.31 | R55: =$A55*Q55 -> 0.744 | T55: =$A55*S55*$T$1 -> 0 | W55: 60
A56: =$Q$41 *(60) -> 2.4 | B56: No. | D56: Push Button Hilti M10 MQN-F | F56: Hilti | H56: 501 | Q56: 2.52 | R56: =$A56*Q56 -> 6.048 | T56: =$A56*S56*$T$1 -> 0 | W56: 30
A57: =$Q$41 *(30) -> 1.2 | B57: No. | D57: Wing Nut Hilti M8 MQM-M8-F | F57: Hilti | H57: 501 | Q57: 0.66 | R57: =$A57*Q57 -> 0.792 | T57: =$A57*S57*$T$1 -> 0 | W57: 30
A58: =$Q$41 *(30) -> 1.2 | B58: No. | D58: Hex.Set Screw M8x25 | F58: Hilti | H58: 501 | Q58: 0.05 | R58: =$A58*Q58 -> 0.06 | T58: =$A58*S58*$T$1 -> 0 | W58: 30
A59: =$Q$41 *(30) -> 1.2 | B59: No. | D59: Galv. Nut 8mm M8-F | F59: Hilti | H59: 501 | Q59: 0.05 | R59: =$A59*Q59 -> 0.06 | T59: =$A59*S59*$T$1 -> 0 | W59: 30
A60: =$Q$41 *(30) -> 1.2 | B60: No. | D60: Tray Washers M8 | H60: 501 | Q60: 0.01 | R60: =$A60*Q60 -> 0.012 | T60: =$A60*S60*$T$1 -> 0
D61: Supports - HDG - Tunnel | F61: 70 metres Ceiling 0.5m height | R61: =$A61*Q61 -> 0 | T61: =$A61*S61*$T$1 -> 0 | W61: 112
A62: =$Q$41 *(112) -> 4.48 | B62: m | D62: Channel MT-40 S OC | F62: Hilti | G62: EMAT_019 | H62: 501 | I62: HIL | J62: MS-413m | K62: 02-018 | O62: 1 | P62: 36175 | Q62: 15.65 | R62: =$A62*Q62 -> 70.112 | T62: =$A62*S62*$T$1 -> 0 | W62: 140
A63: =$Q$41 *(140) -> 5.6 | B63: No. | D63: Channel 40x40 Endcap MT-EC-40/50 | F63: Hilti | H63: 501 | Q63: 0.15 | R63: =$A63*Q63 -> 0.84 | T63: =$A63*S63*$T$1 -> 0 | W63: 140
A64: =$Q$41 *(140) -> 5.6 | B64: No. | D64: Angle Hilti 90deg MT-C-LL1 OC | F64: Hilti | H64: 501 | Q64: 5.39 | R64: =$A64*Q64 -> 30.184 | T64: =$A64*S64*$T$1 -> 0 | W64: 140
A65: =$Q$41 *(140) -> 5.6 | B65: No. | D65: Channel Base Hilti MT-B-O2-OC | F65: Hilti | H65: 501 | Q65: 14.47 | R65: =$A65*Q65 -> 81.032 | T65: =$A65*S65*$T$1 -> 0 | W65: 280
A66: =$Q$41 *(280) -> 11.2 | B66: No. | D66: HLC Sleeve Anchor 10mm HLC 10x50/15 | F66: Hilti | H66: 501 | Q66: 0.31 | R66: =$A66*Q66 -> 3.472 | T66: =$A66*S66*$T$1 -> 0 | W66: 140
A67: =$Q$41 *(8*70) -> 22.4 | B67: No. | D67: Push Button Hilti M10 MQN-F | F67: Hilti | H67: 501 | Q67: 2.52 | R67: =$A67*Q67 -> 56.448 | T67: =$A67*S67*$T$1 -> 0 | W67: 30
A68: =$Q$41 *(140) -> 5.6 | B68: No. | D68: Wing Nut Hilti M8 MQM-M8-F | F68: Hilti | H68: 501 | Q68: 0.66 | R68: =$A68*Q68 -> 3.696 | T68: =$A68*S68*$T$1 -> 0 | W68: 140
A69: =$Q$41 *(140) -> 5.6 | B69: No. | D69: Hex.Set Screw M8x25 | F69: Hilti | H69: 501 | Q69: 0.05 | R69: =$A69*Q69 -> 0.28 | T69: =$A69*S69*$T$1 -> 0 | W69: 140
A70: =$Q$41 *(140) -> 5.6 | B70: No. | D70: Galv. Nut 8mm M8-F | F70: Hilti | H70: 501 | Q70: 0.05 | R70: =$A70*Q70 -> 0.28 | T70: =$A70*S70*$T$1 -> 0 | W70: 140
A71: =$Q$41 *(140) -> 5.6 | B71: No. | D71: Tray Washers M8 | H71: 501 | Q71: 0.01 | R71: =$A71*Q71 -> 0.056 | T71: =$A71*S71*$T$1 -> 0
D72: Supports - HDG - Boiler | F72: 15 metres Ceiling 1.2m height | R72: =$A72*Q72 -> 0 | T72: =$A72*S72*$T$1 -> 0 | W72: 48
A73: =$Q$41 *(48) -> 1.92 | B73: m | D73: Channel MT-40 S OC | F73: Hilti | G73: EMAT_019 | H73: 501 | I73: HIL | J73: MS-413m | K73: 02-018 | O73: 1 | P73: 36175 | Q73: 15.65 | R73: =$A73*Q73 -> 30.048 | T73: =$A73*S73*$T$1 -> 0 | W73: 30
A74: =$Q$41 *(30) -> 1.2 | B74: No. | D74: Channel 40x40 Endcap MT-EC-40/50 | F74: Hilti | H74: 501 | Q74: 0.15 | R74: =$A74*Q74 -> 0.18 | T74: =$A74*S74*$T$1 -> 0 | W74: 30
A75: =$Q$41 *(30) -> 1.2 | B75: No. | D75: Angle Hilti 90deg MT-C-LL1 OC | F75: Hilti | H75: 501 | Q75: 5.39 | R75: =$A75*Q75 -> 6.468 | T75: =$A75*S75*$T$1 -> 0 | W75: 30
A76: =$Q$41 *(30) -> 1.2 | B76: No. | D76: Channel Base Hilti MT-B-O2-OC | F76: Hilti | H76: 501 | Q76: 14.47 | R76: =$A76*Q76 -> 17.364 | T76: =$A76*S76*$T$1 -> 0 | W76: 60
A77: =$Q$41 *(60) -> 2.4 | B77: No. | D77: HLC Sleeve Anchor 10mm HLC 10x50/15 | F77: Hilti | H77: 501 | Q77: 0.31 | R77: =$A77*Q77 -> 0.744 | T77: =$A77*S77*$T$1 -> 0 | W77: 30
A78: =$Q$41 *(8*15) -> 4.8 | B78: No. | D78: Push Button Hilti M10 MQN-F | F78: Hilti | H78: 501 | Q78: 2.52 | R78: =$A78*Q78 -> 12.096 | T78: =$A78*S78*$T$1 -> 0 | W78: 30
A79: =$Q$41 *(30) -> 1.2 | B79: No. | D79: Wing Nut Hilti M8 MQM-M8-F | F79: Hilti | H79: 501 | Q79: 0.66 | R79: =$A79*Q79 -> 0.792 | T79: =$A79*S79*$T$1 -> 0 | W79: 30
A80: =$Q$41 *(30) -> 1.2 | B80: No. | D80: Hex.Set Screw M8x25 | F80: Hilti | H80: 501 | Q80: 0.05 | R80: =$A80*Q80 -> 0.06 | T80: =$A80*S80*$T$1 -> 0 | W80: 30
A81: =$Q$41 *(30) -> 1.2 | B81: No. | D81: Galv. Nut 8mm M8-F | F81: Hilti | H81: 501 | Q81: 0.05 | R81: =$A81*Q81 -> 0.06 | T81: =$A81*S81*$T$1 -> 0 | W81: 30
A82: =$Q$41 *(30) -> 1.2 | B82: No. | D82: Tray Washers M8 | H82: 501 | Q82: 0.01 | R82: =$A82*Q82 -> 0.012 | T82: =$A82*S82*$T$1 -> 0 | AB82: new | AC82: 11250
D83: Supports - HDG - Shaft | F83: 20 metres Riser 0.15m height | R83: =$A83*Q83 -> 0 | T83: =$A83*S83*$T$1 -> 0 | W83: 14 | AB83: old
A84: =$Q$41 *(14) -> 0.56 | B84: m | D84: Channel MT-40 S OC | F84: Hilti | G84: EMAT_019 | H84: 501 | I84: HIL | J84: MS-413m | K84: 02-018 | O84: 1 | P84: 36175 | Q84: 15.65 | R84: =$A84*Q84 -> 8.764 | T84: =$A84*S84*$T$1 -> 0 | W84: 40
A85: =$Q$41 *(40) -> 1.6 | B85: No. | D85: Channel 40x40 Endcap MT-EC-40/50 | F85: Hilti | H85: 501 | Q85: 0.15 | R85: =$A85*Q85 -> 0.24 | T85: =$A85*S85*$T$1 -> 0 | W85: 40
A86: =$Q$41 *(40) -> 1.6 | B86: No. | D86: Angle Hilti 90deg MT-C-LL1 OC | F86: Hilti | H86: 501 | Q86: 5.39 | R86: =$A86*Q86 -> 8.624 | T86: =$A86*S86*$T$1 -> 0 | W86: 40
A87: =$Q$41 *(40) -> 1.6 | B87: No. | D87: Channel Base Hilti MT-B-O2-OC | F87: Hilti | H87: 501 | Q87: 14.47 | R87: =$A87*Q87 -> 23.152 | T87: =$A87*S87*$T$1 -> 0 | W87: 80
A88: =$Q$41 *(80) -> 3.2 | B88: No. | D88: HLC Sleeve Anchor 10mm HLC 10x50/15 | F88: Hilti | H88: 501 | Q88: 0.31 | R88: =$A88*Q88 -> 0.992 | T88: =$A88*S88*$T$1 -> 0 | W88: 40
A89: =$Q$41 *(8*20) -> 6.4 | B89: No. | D89: Push Button Hilti M10 MQN-F | F89: Hilti | H89: 501 | Q89: 2.52 | R89: =$A89*Q89 -> 16.128 | T89: =$A89*S89*$T$1 -> 0 | W89: 30
A90: =$Q$41 *(40) -> 1.6 | B90: No. | D90: Wing Nut Hilti M8 MQM-M8-F | F90: Hilti | H90: 501 | Q90: 0.66 | R90: =$A90*Q90 -> 1.056 | T90: =$A90*S90*$T$1 -> 0 | W90: 40
A91: =$Q$41 *(40) -> 1.6 | B91: No. | D91: Hex.Set Screw M8x25 | F91: Hilti | H91: 501 | Q91: 0.05 | R91: =$A91*Q91 -> 0.08 | T91: =$A91*S91*$T$1 -> 0 | W91: 40
A92: =$Q$41 *(40) -> 1.6 | B92: No. | D92: Galv. Nut 8mm M8-F | F92: Hilti | H92: 501 | Q92: 0.05 | R92: =$A92*Q92 -> 0.08 | T92: =$A92*S92*$T$1 -> 0 | W92: 40
A93: =$Q$41 *(40) -> 1.6 | B93: No. | D93: Tray Washers M8 | H93: 501 | Q93: 0.01 | R93: =$A93*Q93 -> 0.016 | T93: =$A93*S93*$T$1 -> 0
D94: Supports - HDG - Roof | F94: 25 m Roof excluding the structure | R94: =$A94*Q94 -> 0 | T94: =$A94*S94*$T$1 -> 0 | W94: 17
A95: =$Q$41 *(17) -> 0.68 | B95: m | D95: Channel MT-40 S OC | F95: Hilti | G95: EMAT_019 | H95: 501 | I95: HIL | J95: MS-413m | K95: 02-018 | O95: 1 | P95: 36175 | Q95: 15.65 | R95: =$A95*Q95 -> 10.642 | T95: =$A95*S95*$T$1 -> 0 | W95: 30
A96: =$Q$41 *(30) -> 1.2 | B96: No. | D96: Channel 40x40 Endcap MT-EC-40/50 | F96: Hilti | H96: 501 | Q96: 0.15 | R96: =$A96*Q96 -> 0.18 | T96: =$A96*S96*$T$1 -> 0 | W96: 34
A97: =$Q$41 *(34) -> 1.36 | B97: No. | D97: Angle Hilti 90deg MT-C-LL1 OC | F97: Hilti | H97: 501 | Q97: 5.39 | R97: =$A97*Q97 -> 7.3304 | T97: =$A97*S97*$T$1 -> 0 | W97: 16
A98: =$Q$41 *(16) -> 0.64 | B98: No. | D98: Channel Base Hilti MT-B-O2-OC | F98: Hilti | H98: 501 | Q98: 14.47 | R98: =$A98*Q98 -> 9.2608 | T98: =$A98*S98*$T$1 -> 0 | W98: 32
A99: =$Q$41 *(32) -> 1.28 | B99: No. | D99: HLC Sleeve Anchor 10mm HLC 10x50/15 | F99: Hilti | H99: 501 | Q99: 0.31 | R99: =$A99*Q99 -> 0.3968 | T99: =$A99*S99*$T$1 -> 0 | W99: 38
A100: =$Q$41 *(32) -> 1.28 | B100: No. | D100: Push Button Hilti M10 MQN-F | F100: Hilti | H100: 501 | Q100: 2.52 | R100: =$A100*Q100 -> 3.2256 | T100: =$A100*S100*$T$1 -> 0 | W100: 30
A101: =$Q$41 *(38) -> 1.52 | B101: No. | D101: Wing Nut Hilti M8 MQM-M8-F | F101: Hilti | H101: 501 | Q101: 0.66 | R101: =$A101*Q101 -> 1.0032 | T101: =$A101*S101*$T$1 -> 0 | W101: 38
A102: =$Q$41 *(38) -> 1.52 | B102: No. | D102: Hex.Set Screw M8x25 | F102: Hilti | H102: 501 | Q102: 0.05 | R102: =$A102*Q102 -> 0.076 | T102: =$A102*S102*$T$1 -> 0 | W102: 38
...

Sheet Elec_Est
B1: CLIENT: | C1: =ML_Sum!$C1 -> 1 | D1: =ML_Sum!$D1 -> ST Microelectronics (Malta) Ltd. | F1: =ML_Sum!$F1 -> 0 | I1: 1 | J1: =ML_Sum!$J1 -> 1 | K1: =ML_Sum!$K1 -> 1 | L1: =ML_Sum!$L1 -> 1 | M1: =ML_Sum!$M1 -> 1 | N1: =ML_Sum!$N1 -> 1 | O1: =ML_Sum!$O1 -> 1 | Q1: =ML_Sum!$Q1 -> € | R1: R/Lab Cont | S1: =ML_Sum!$S1 -> R | T1: =ML_Sum!$T1 -> 1.15 | U1: =ML_Sum!W1 -> BOQ | V1: INCL | W1: MULT | X1: AREA | Y1: BOQ | Z1: TDWG | AA1: ACT | AB1: DIFF
B2: PROJECT: | C2: =ML_Sum!$C2 -> 1 | D2: =ML_Sum!$D2 -> KK2 General Exhaust Replacement | F2: =ML_Sum!$F2 -> Electrical | I2: 2 | J2: =ML_Sum!$J2 -> 1 | K2: =ML_Sum!$K2 -> 1 | L2: =ML_Sum!$L2 -> 1 | M2: =ML_Sum!$M2 -> 1 | N2: =ML_Sum!$N2 -> 1 | O2: =ML_Sum!$O2 -> 1 | Q2: =ML_Sum!$Q2 -> 0 | R2: mu_A | S2: =ML_Sum!$S2 -> 1 | T2: =ML_Sum!$T2 -> 27.46
B3: JOB DESC: | C3: =ML_Sum!$C3 -> 1 | D3: =ML_Sum!$D3 -> Electrical Supply and Installation | F3: =ML_Sum!$F3 -> Controls | I3: 3 | J3: =ML_Sum!$J3 -> 1 | K3: =ML_Sum!$K3 -> 1 | L3: =ML_Sum!$L3 -> 1 | M3: =ML_Sum!$M3 -> 1 | N3: =ML_Sum!$N3 -> 1 | O3: =ML_Sum!$O3 -> 1 | Q3: =ML_Sum!$Q3 -> 0 | R3: mu_B | S3: =ML_Sum!$S3 -> 1 | T3: =ML_Sum!$T3 -> 27.46
B4: QUOTE No: | C4: =ML_Sum!$C4 -> 1 | D4: =ML_Sum!$D4 -> ELM25-0560 | F4: =ML_Sum!$F4 -> Controls | I4: 4 | J4: =ML_Sum!$J4 -> 1 | K4: =ML_Sum!$K4 -> 1 | L4: =ML_Sum!$L4 -> 1 | M4: =ML_Sum!$M4 -> 1 | N4: =ML_Sum!$N4 -> 1 | O4: =ML_Sum!$O4 -> 1 | Q4: =ML_Sum!$Q4 -> 0 | R4: mu_C | S4: =ML_Sum!$S4 -> 1 | T4: =ML_Sum!$T4 -> 27.46
B5: CLIENTs REF: | C5: =ML_Sum!$C5 -> 1 | D5: =ML_Sum!$D5 -> Tender | F5: =ML_Sum!$F5 -> 0 | I5: 5 | J5: =ML_Sum!$J5 -> 1 | K5: =ML_Sum!$K5 -> 1 | L5: =ML_Sum!$L5 -> 1 | M5: =ML_Sum!$M5 -> 1 | N5: =ML_Sum!$N5 -> 1 | O5: =ML_Sum!$O5 -> 1 | Q5: =ML_Sum!$Q5 -> 0 | R5: mu_D | S5: =ML_Sum!$S5 -> 0 | T5: =ML_Sum!$T5 -> 0
B6: VAT/DUTIES: | C6: =ML_Sum!$C6 -> 1 | D6: =ML_Sum!$D6 -> VAT EXCL. | F6: =ML_Sum!$F6 -> 0 | I6: 6 | J6: =ML_Sum!$J6 -> 1 | K6: =ML_Sum!$K6 -> 1 | L6: =ML_Sum!$L6 -> 1 | M6: =ML_Sum!$M6 -> 1 | N6: =ML_Sum!$N6 -> 1 | O6: =ML_Sum!$O6 -> 1 | Q6: =ML_Sum!$Q6 -> 0 | R6: mu_E | S6: =ML_Sum!$S6 -> 0 | T6: =ML_Sum!$T6 -> 0
B7: SAVED ON: | C7: =ML_Sum!$C7 -> 1 | D7: 39364 | F7: =ML_Sum!$F7 -> 0 | I7: 7 | J7: =ML_Sum!$J7 -> 1 | K7: =ML_Sum!$K7 -> 1 | L7: =ML_Sum!$L7 -> 1 | M7: =ML_Sum!$M7 -> 1 | N7: =ML_Sum!$N7 -> 1 | O7: =ML_Sum!$O7 -> 0 | Q7: =ML_Sum!$Q7 -> 0 | R7: mu_F | S7: =ML_Sum!$S7 -> 0 | T7: =ML_Sum!$T7 -> 0
B8: ESTIMATOR: | C8: =ML_Sum!$C8 -> 1 | D8: =ML_Sum!$D8 -> Umut Kaymak | F8: =ML_Sum!$F8 -> 0 | I8: 8 | J8: =ML_Sum!$J8 -> 1 | K8: =ML_Sum!$K8 -> 1 | L8: =ML_Sum!$L8 -> 1 | M8: =ML_Sum!$M8 -> 1 | N8: =ML_Sum!$N8 -> 1 | O8: =ML_Sum!$O8 -> 0 | Q8: =ML_Sum!$Q8 -> 0 | R8: mu_G | S8: =ML_Sum!$S8 -> 0 | T8: =ML_Sum!$T8 -> 0
B9: LABOUR RATE: | C9: =ML_Sum!$C9 -> 1 | D9: =ML_Sum!$D9 -> 27.46 | F9: =ML_Sum!$F9 -> 0 | I9: 9 | J9: =ML_Sum!$J9 -> 1 | K9: =ML_Sum!$K9 -> 1 | L9: =ML_Sum!$L9 -> 1 | M9: =ML_Sum!$M9 -> 1 | N9: =ML_Sum!$N9 -> 1 | O9: =ML_Sum!$O9 -> 0 | Q9: =ML_Sum!$Q9 -> 0 | R9: mu_H | S9: =ML_Sum!$S9 -> 0 | T9: =ML_Sum!$T9 -> 0
C10: =ML_Sum!$C10 -> 1 | F10: =ML_Sum!$F10 -> 0 | I10: 10 | J10: =ML_Sum!$J10 -> 1 | K10: =ML_Sum!$K10 -> 1 | L10: =ML_Sum!$L10 -> 1 | M10: =ML_Sum!$M10 -> 1 | N10: =ML_Sum!$N10 -> 1 | O10: =ML_Sum!$O10 -> 1 | Q10: =ML_Sum!$Q10 -> 0 | R10: mu_I | S10: =ML_Sum!$S10 -> 0 | T10: =ML_Sum!$T10 -> 0
C11: =ML_Sum!$C11 -> 1 | F11: =ML_Sum!$F11 -> 0 | Q11: =ML_Sum!$Q11 -> 0 | R11: mu_J | S11: =ML_Sum!$S11 -> 0 | T11: =ML_Sum!$T11 -> 0
C12: =ML_Sum!$C12 -> 1 | F12: =ML_Sum!$F12 -> 0 | Q12: =ML_Sum!$Q12 -> 0 | R12: MIXED | S12: =ML_Sum!$S12 -> MAT MU | T12: =ML_Sum!$T12 -> LAB RATE
G13: ISELL | H13: C_CODE | I13: MAKE | J13: PART_NO | K13: MARKUP | L13: TYPE | M13: LIST_P | N13: P_FACT | O13: FIX | P13: DATE | Q13: %Dsct in BOQ | R13: MU TYPE | S13: MAT MU | T13: LAB RATE | AM13: Tot Mat Cost | AN13: Unit Lab phr. | AO13: Tot Lab phr. | AP13: < for ELM / MEE
K14: TB
C15: t | D15: Item:
D16: Electrical For Mechanical Works,
E18: Sell Rate | F18: Sell Total | K18: IB | AG18: U_M_Sell | AH18: T_M_Sell | AI18: U_L_Sell | AJ18: T_L_Sell | AK18: Total_Sell | AM18: T_M_Cost | AN18: T_L_Phr | AO18: Mat/Lab=1
A19: 1 | B19: L/S | D19: Item: 1.01 | E19: =IF(AND($A19=0,$A$1="DIF"),0, ROUND(ROUND(($R23*$S$2+($T23*$T$2))/A19,2)*$C$2,2)) -> 126.32 | F19: =ROUND($A19*$E19,2) -> 126.32 | G19: ISELL | K19: mu_A | L19: ITEM | T19: =IF(AND($R23=0,$T23=0),"0.00","mu :" & ROUND($F19/$C$2/($R23+$T23*$D$9),2)) -> mu :1 | AG19: =IF($E19=0,0,ROUND($R23*$S$2*$C$2/$A19,2)) -> 0 | AH19: =$AG19*$A19 -> 0 | AI19: =$E19-$AG19 -> 126.32 | AJ19: =$A19*$AI19 -> 126.32 | AK19: =ROUND(($AG19+$AI19)*$A19,2) -> 126.32 | AM19: =ROUND(R23,2) -> 0 | AN19: =ROUND(T23,2) -> 4.6 | AO19: =ROUND(AM19+AN19,2)*A19 -> 4.6
D20: Dismantling the Old AHU
A21: 1 | B21: LS | D21: LABOUR ONLY | G21: LABO_001 | H21: 900 | I21: MISC | O21: 1 | Q21: 0 | R21: =$A21*Q21 -> 0 | S21: 4 | T21: =$A21*S21*$T$1 -> 4.6
R22: =$A22*Q22 -> 0 | T22: =$A22*S22*$T$1 -> 0
A23: d> | B23: =(R22+T22) -> 0 | G23: ICOST | K23: mu_A | L23: ITEM | R23: =SUM(R20:R22) -> 0 | T23: =SUM(T20:T22) -> 4.6
E24: Sell Rate | F24: Sell Total | K24: IB | AG24: U_M_Sell | AH24: T_M_Sell | AI24: U_L_Sell | AJ24: T_L_Sell | AK24: Total_Sell | AM24: T_M_Cost | AN24: T_L_Phr | AO24: Mat/Lab=1
A25: 2 | B25: No | D25: Item: 1.02 | E25: =IF(AND($A25=0,$A$1="DIF"),0, ROUND(ROUND(($R36*$S$2+($T36*$T$2))/A25,2)*$C$2,2)) -> 803.68 | F25: =ROUND($A25*$E25,2) -> 1607.36 | G25: ISELL | K25: mu_A | L25: ITEM | T25: =IF(AND($R36=0,$T36=0),"0.00","mu :" & ROUND($F25/$C$2/($R36+$T36*$D$9),2)) -> mu :1 | AG25: =IF($E25=0,0,ROUND($R36*$S$2*$C$2/$A25,2)) -> 572.4 | AH25: =$AG25*$A25 -> 1144.8 | AI25: =$E25-$AG25 -> 231.28 | AJ25: =$A25*$AI25 -> 462.56 | AK25: =ROUND(($AG25+$AI25)*$A25,2) -> 1607.36 | AM25: =ROUND(R36,2) -> 1144.8 | AN25: =ROUND(T36,2) -> 16.85 | AO25: =ROUND(AM25+AN25,2)*A25 -> 2323.3
D26: Electrical Power for Air Conditioning Outdoor Units including connecting Up of Outdoor units
A27: 40 | B27: m | D27: 5c6.0mm FG16OR LSF Grey | F27: AJ | G27: CAMC_092 | H27: 616 | I27: (__) | J27: 6.0mm2 | K27: 05-004 | O27: 2 | P27: 38847 | Q27: 4.1 | R27: =$A27*Q27 -> 164 | S27: 0.05 | T27: =$A27*S27*$T$1 -> 2.3
A28: 2 | B28: No | D28: Surface Isolator 32A 4-Pole | F28: AJ | G28: SWLV_177 | H28: 510 | I28: KM | J28: P3-63/I/N | K28: 10 | O28: 2 | P28: 36880 | Q28: 47.67 | R28: =$A28*Q28 -> 95.34 | S28: 0.75 | T28: =$A28*S28*$T$1 -> 1.725
A29: 8 | B29: No | D29: Gland Indoor 20 BWL 4*4/6mm2 | G29: CAAC_040 | H29: 620 | I29: CMP | O29: 2 | P29: 35431 | Q29: 4.71 | R29: =$A29*Q29 -> 37.68 | S29: 0.35 | T29: =$A29*S29*$T$1 -> 3.22
A30: 40 | B30: No | D30: Cable Lug 6.0 mm2 | G30: CAAC_007 | H30: 620 | I30: CTT | O30: 2 | P30: 34669 | Q30: 0.07 | R30: =$A30*Q30 -> 2.8 | S30: 0.03 | T30: =$A30*S30*$T$1 -> 1.38
C31: h | D31: =CELL("Address",Elec_Rates!D$41) -> [ELM25_0560_ST_Electronics_Exhaust_Replacement_Est_.xlsx]Elec_Rates!$D$41 | G31: RATE_AAA
A32: 6 | B32: 1 | C32: =$A32*$B32 -> 6 | D32: =Elec_Rates!$D$41 -> 003# Cable Containment Support | E32: 100mm cable tray | F32: Local Rate | G32: RTLO_002 | Q32: =$B32*Elec_Rates!$R$41 -> 71.41 | R32: =$A32*Q32 -> 428.46 | S32: =$B32*Elec_Rates!$T$41 -> 0.58 | T32: =$A32*S32 -> 3.48
C33: h | D33: =CELL("Address",Elec_Rates!D$26) -> [ELM25_0560_ST_Electronics_Exhaust_Replacement_Est_.xlsx]Elec_Rates!$D$26 | G33: RATE_AAA
A34: 6 | B34: 1 | C34: =$A34*$B34 -> 6 | D34: =Elec_Rates!$D$26 -> 002# 200mm galvanised steel cable tray complete with cover | F34: Local Rate | G34: RTLO_002 | Q34: =$B34*Elec_Rates!$R$26 -> 69.42 | R34: =$A34*Q34 -> 416.52 | S34: =$B34*Elec_Rates!$T$26 -> 0.79 | T34: =$A34*S34 -> 4.74
R35: =$A35*Q35 -> 0 | T35: =$A35*S35*$T$1 -> 0
A36: d> | B36: =(R35+T35) -> 0 | G36: ICOST | K36: mu_A | L36: ITEM | R36: =SUM(R26:R35) -> 1144.8 | T36: =SUM(T26:T35) -> 16.845
E37: Sell Rate | F37: Sell Total | K37: IB | AG37: U_M_Sell | AH37: T_M_Sell | AI37: U_L_Sell | AJ37: T_L_Sell | AK37: Total_Sell | AM37: T_M_Cost | AN37: T_L_Phr | AO37: Mat/Lab=1
A38: 2 | B38: No | D38: Item: 1.03 | E38: =IF(AND($A38=0,$A$1="DIF"),0, ROUND(ROUND(($R46*$S$2+($T46*$T$2))/A38,2)*$C$2,2)) -> 196.27 | F38: =ROUND($A38*$E38,2) -> 392.54 | G38: ISELL | K38: mu_A | L38: ITEM | T38: =IF(AND($R46=0,$T46=0),"0.00","mu :" & ROUND($F38/$C$2/($R46+$T46*$D$9),2)) -> mu :1 | AG38: =IF($E38=0,0,ROUND($R46*$S$2*$C$2/$A38,2)) -> 81.32 | AH38: =$AG38*$A38 -> 162.64 | AI38: =$E38-$AG38 -> 114.95 | AJ38: =$A38*$AI38 -> 229.9 | AK38: =ROUND(($AG38+$AI38)*$A38,2) -> 392.54 | AM38: =ROUND(R46,2) -> 162.64 | AN38: =ROUND(T46,2) -> 8.37 | AO38: =ROUND(AM38+AN38,2)*A38 -> 342.02
D39: Electrical Power for Air Conditioning Indoor Units including connecting Up of Indoor units
A40: 10 | B40: m | D40: Conduit Galv. 25mm RATE | F40: price from quintano | G40: COGV_013 | H40: 690 | I40: BAR | J40: 25mm | O40: 1 | P40: 34669 | Q40: 3.8 | R40: =$A40*Q40 -> 38 | S40: 0.25 | T40: =$A40*S40*$T$1 -> 2.875 | AR40: 75
A41: 30 | B41: m | D41: Wiring Cable 3c 2.5 mm2 PVC Non-Arm | G41: CAMC_049 | H41: 616 | I41: CRO | J41: 2.5mm2 | K41: 03-003 | O41: 2 | P41: 40767 | Q41: 2 | R41: =$A41*Q41 -> 60 | S41: 0.03 | T41: =$A41*S41*$T$1 -> 1.035
A42: 2 | B42: No | D42: Surface Isolator 16A 2-Pole | F42: AJ | G42: SWLV_143 | H42: 510 | I42: KM | J42: T0-1-102/I | K42: 10-001 | O42: 2 | P42: 36880 | Q42: 17.48 | R42: =$A42*Q42 -> 34.96 | S42: 0.5 | T42: =$A42*S42*$T$1 -> 1.15
A43: 8 | B43: No | D43: Gland Indoor 20S BWL 4*1.5/2.5mm2 | G43: CAAC_042 | H43: 620 | I43: CMP | O43: 2 | P43: 35431 | Q43: 3.56 | R43: =$A43*Q43 -> 28.48 | S43: 0.3 | T43: =$A43*S43*$T$1 -> 2.76
A44: 24 | B44: No | D44: Cable Lug 2.5 mm2 | G44: CAAC_005 | H44: 620 | I44: CTT | O44: 2 | P44: 34669 | Q44: 0.05 | R44: =$A44*Q44 -> 1.2 | S44: 0.02 | T44: =$A44*S44*$T$1 -> 0.552
R45: =$A45*Q45 -> 0 | T45: =$A45*S45*$T$1 -> 0
A46: d> | B46: =(R45+T45) -> 0 | G46: ICOST | K46: mu_A | L46: ITEM | R46: =SUM(R39:R45) -> 162.64 | T46: =SUM(T39:T45) -> 8.372
E47: Sell Rate | F47: Sell Total | K47: IB | AG47: U_M_Sell | AH47: T_M_Sell | AI47: U_L_Sell | AJ47: T_L_Sell | AK47: Total_Sell | AM47: T_M_Cost | AN47: T_L_Phr | AO47: Mat/Lab=1
A48: 1 | B48: No | D48: Item: 1.04 | E48: =IF(AND($A48=0,$A$1="DIF"),0,ROUND(ROUND(SUMIF($L50:$L62,"SUBI",$E50:$E62)/$A48,2)*$C$12,2)) -> 3450.94 | F48: =ROUND($A48*$E48,2) -> 3450.94 | G48: ISELL | L48: ITEM | T48: =IF(AND($R67=0,$T67=0),"0.00","mu :" & ROUND($F48/$C$12/($R67+$T67*$D$9),2)) -> mu :1 | AG48: =IF(A48=0,0,ROUND(SUM(AG50:AG67)/A48,2)) -> 3010.39 | AH48: =$AG48*$A48 -> 3010.39 | AI48: =$E48-$AG48 -> 440.55 | AJ48: =$A48*$AI48 -> 440.55 | AK48: =ROUND(($AG48+$AI48)*$A48,2) -> 3450.94 | AM48: =ROUND(R67,2) -> 3010.39 | AN48: =ROUND(T67,2) -> 16.04 | AO48: =ROUND(AM48+AN48,2)*A48 -> 3026.43
D49: Flowmeter
E50: =F48/$C$12-SUMIF($L47:$L67,"SUBI",$E47:$E67) -> 0 | F50: Discrepancy
D51: =$F$2 -> Electrical | E51: =ROUND(($R56*$S$2 + ($T56*$T$2)), 2) -> 300.61 | F51: =$E51*$C$12 -> 300.61 | K51: mu_A | L51: SUBI
A52: 15 | B52: m | D52: Conduit Galv. 20mm RATE | F52: price from quintano | G52: COGV_013 | H52: 690 | I52: BAR | J52: 25mm | O52: 1 | P52: 34669 | Q52: 3.03 | R52: =$A52*Q52 -> 45.45 | S52: 0.2 | T52: =$A52*S52*$T$1 -> 3.45 | AR52: 75
A53: 60 | B53: m | D53: Screened 3c Cable 0.75sqmm | G53: CASP_083 | H53: 617 | I53: Lappkabel | J53: 0034703 UNITRONIC LiYCY | O53: 2 | P53: 38433 | Q53: 1.2 | R53: =$A53*Q53 -> 72 | S53: 0.03 | T53: =$A53*S53*$T$1 -> 2.07
A54: 1 | B54: No | D54: Dwyer - Air Flow Grid and Meter Cabinet Installation | G54: BMSE_001 | H54: 512 | I54: (__) | O54: 3 | R54: =$A54*Q54 -> 0 | S54: 1 | T54: =$A54*S54*$T$1 -> 1.15
R55: =$A55*Q55 -> 0 | T55: =$A55*S55*$T$1 -> 0
A56: d> | B56: =(R55+T55) -> 0 | K56: mu_A | L56: SUBI | R56: =SUM(R51:R55) -> 117.45 | T56: =SUM(T51:T55) -> 6.67 | AG56: =ROUND($R56*$S$2,2) -> 117.45
D57: =$F$3 -> Controls | E57: =ROUND(($R61*$S$3 + ($T61*$T$3)), 2) -> 3150.33 | F57: =$E57*$C$12 -> 3150.33 | K57: mu_B | L57: SUBI
A58: 1 | B58: No | D58: Dwyer - Air Flow Grid and Meter | G58: BMSE_001 | H58: 512 | I58: (__) | O58: 3 | Q58: 2738.94 | R58: =$A58*Q58 -> 2738.94 | S58: =2*35/27.46+2*41.91/27.46 -> 5.6016023 | T58: =$A58*S58*$T$1 -> 6.4418427
A59: 1 | B59: No | D59: Dwyer - Air Flow Grid and Meter Cabinet | G59: BMSE_001 | H59: 512 | I59: (__) | O59: 3 | Q59: 154 | R59: =$A59*Q59 -> 154 | S59: =2*35/27.46 -> 2.5491624 | T59: =$A59*S59*$T$1 -> 2.9315368
R60: =$A60*Q60 -> 0 | T60: =$A60*S60*$T$1 -> 0
A61: d> | B61: =(R60+T60) -> 0 | K61: mu_B | L61: SUBI | R61: =SUM(R57:R60) -> 2892.94 | T61: =SUM(T57:T60) -> 9.3733795 | AG61: =ROUND($R61*$S$3,2) -> 2892.94
D62: =$F$4 -> Controls | E62: =ROUND(($R65*$S$4 + ($T65*$T$4)), 2) -> 0 | F62: =$F48-SUMIF($L50:$P58,"SUBI",$F50:$F58) -> 0 | K62: mu_C | L62: SUBI
R63: =$A63*Q63 -> 0 | T63: =$A63*S63*$T$1 -> 0
R64: =$A64*Q64 -> 0 | T64: =$A64*S64*$T$1 -> 0
A65: d> | B65: =(R64+T64) -> 0 | K65: mu_C | L65: SUBI | R65: =SUM(R62:R64) -> 0 | T65: =SUM(T62:T64) -> 0 | AG65: =ROUND($R65*$S$4,2) -> 0
G67: ICOST | L67: ITEM | R67: =SUMIF($L49:$L66,"SUBI",R49:R66) -> 3010.39 | T67: =SUMIF($L49:$L66,"SUBI",T49:T66) -> 16.043379
E68: Sell Rate | F68: Sell Total | K68: IB | AG68: U_M_Sell | AH68: T_M_Sell | AI68: U_L_Sell | AJ68: T_L_Sell | AK68: Total_Sell | AM68: T_M_Cost | AN68: T_L_Phr | AO68: Mat/Lab=1
A69: 1 | B69: No | D69: Item: 1.05 | E69: =IF(AND($A69=0,$A$1="DIF"),0,ROUND(ROUND(SUMIF($L71:$L81,"SUBI",$E71:$E81)/$A69,2)*$C$12,2)) -> 577.92 | F69: =ROUND($A69*$E69,2) -> 577.92 | G69: ISELL | L69: ITEM | T69: =IF(AND($R87=0,$T87=0),"0.00","mu :" & ROUND($F69/$C$12/($R87+$T87*$D$9),2)) -> mu :1 | AG69: =IF(A69=0,0,ROUND(SUM(AG71:AG87)/A69,2)) -> 249.45 | AH69: =$AG69*$A69 -> 249.45 | AI69: =$E69-$AG69 -> 328.47 | AJ69: =$A69*$AI69 -> 328.47 | AK69: =ROUND(($AG69+$AI69)*$A69,2) -> 577.92 | AM69: =ROUND(R87,2) -> 249.45 | AN69: =ROUND(T87,2) -> 11.96 | AO69: =ROUND(AM69+AN69,2)*A69 -> 261.41
D70: Delta Pressure Sensor
E71: =F69/$C$12-SUMIF($L68:$L87,"SUBI",$E68:$E87) -> 0 | F71: Discrepancy
D72: =$F$2 -> Electrical | E72: =ROUND(($R76*$S$2 + ($T76*$T$2)), 2) -> 269.03 | F72: =$E72*$C$12 -> 269.03 | K72: mu_A | L72: SUBI
A73: 15 | B73: m | D73: Conduit Galv. 20mm RATE | F73: price from quintano | G73: COGV_013 | H73: 690 | I73: BAR | J73: 25mm | O73: 1 | P73: 34669 | Q73: 3.03 | R73: =$A73*Q73 -> 45.45 | S73: 0.2 | T73: =$A73*S73*$T$1 -> 3.45 | AR73: 75
A74: 60 | B74: m | D74: Screened 3c Cable 0.75sqmm | G74: CASP_083 | H74: 617 | I74: Lappkabel | J74: 0034703 UNITRONIC LiYCY | O74: 2 | P74: 38433 | Q74: 1.2 | R74: =$A74*Q74 -> 72 | S74: 0.03 | T74: =$A74*S74*$T$1 -> 2.07
R75: =$A75*Q75 -> 0 | T75: =$A75*S75*$T$1 -> 0
A76: d> | B76: =(R75+T75) -> 0 | K76: mu_A | L76: SUBI | R76: =SUM(R72:R75) -> 117.45 | T76: =SUM(T72:T75) -> 5.52 | AG76: =ROUND($R76*$S$2,2) -> 117.45
D77: =$F$3 -> Controls | E77: =ROUND(($R80*$S$3 + ($T80*$T$3)), 2) -> 308.89 | F77: =$E77*$C$12 -> 308.89 | K77: mu_B | L77: SUBI
A78: 1 | B78: No | D78: Differantial Pressure Sensor with LCD | G78: BMSE_001 | H78: 512 | I78: (__) | O78: 3 | Q78: 132 | R78: =$A78*Q78 -> 132 | S78: =2*35/27.46+2*41.91/27.46 -> 5.6016023 | T78: =$A78*S78*$T$1 -> 6.4418427
R79: =$A79*Q79 -> 0 | T79: =$A79*S79*$T$1 -> 0
A80: d> | B80: =(R79+T79) -> 0 | K80: mu_B | L80: SUBI | R80: =SUM(R77:R79) -> 132 | T80: =SUM(T77:T79) -> 6.4418427 | AG80: =ROUND($R80*$S$3,2) -> 132
D81: =$F$4 -> Controls | E81: =ROUND(($R85*$S$4 + ($T85*$T$4)), 2) -> 0 | F81: =$F69-SUMIF($L71:$P78,"SUBI",$F71:$F78) -> 0 | K81: mu_C | L81: SUBI
B82: >>> mu_C material here >>> | R82: =$A82*Q82 -> 0 | T82: =$A82*S82*$T$1 -> 0
R83: =$A83*Q83 -> 0 | T83: =$A83*S83*$T$1 -> 0
R84: =$A84*Q84 -> 0 | T84: =$A84*S84*$T$1 -> 0
A85: d> | B85: =(R84+T84) -> 0 | K85: mu_C | L85: SUBI | R85: =SUM(R81:R84) -> 0 | T85: =SUM(T81:T84) -> 0 | AG85: =ROUND($R85*$S$4,2) -> 0
G87: ICOST | L87: ITEM | R87: =SUMIF($L70:$L86,"SUBI",R70:R86) -> 249.45 | T87: =SUMIF($L70:$L86,"SUBI",T70:T86) -> 11.961843
E88: Sell Rate | F88: Sell Total | K88: IB | AG88: U_M_Sell | AH88: T_M_Sell | AI88: U_L_Sell | AJ88: T_L_Sell | AK88: Total_Sell | AM88: T_M_Cost | AN88: T_L_Phr | AO88: Mat/Lab=1
A89: 2 | B89: No | D89: Item: 1.06 | E89: =IF(AND($A89=0,$A$1="DIF"),0,ROUND(ROUND(SUMIF($L91:$L101,"SUBI",$E91:$E101)/$A89,2)*$C$12,2)) -> 386.38 | F89: =ROUND($A89*$E89,2) -> 772.76 | G89: ISELL | L89: ITEM | T89: =IF(AND($R107=0,$T107=0),"0.00","mu :" & ROUND($F89/$C$12/($R107+$T107*$D$9),2)) -> mu :1 | AG89: =IF(A89=0,0,ROUND(SUM(AG91:AG107)/A89,2)) -> 193.73 | AH89: =$AG89*$A89 -> 387.46 | AI89: =$E89-$AG89 -> 192.65 | AJ89: =$A89*$AI89 -> 385.3 | AK89: =ROUND(($AG89+$AI89)*$A89,2) -> 772.76 | AM89: =ROUND(R107,2) -> 387.45 | AN89: =ROUND(T107,2) -> 14.03 | AO89: =ROUND(AM89+AN89,2)*A89 -> 802.96
D90: Damper
E91: =F89/$C$12-SUMIF($L88:$L107,"SUBI",$E88:$E107) -> 0 | F91: Discrepancy
D92: =$F$2 -> Electrical | E92: =ROUND(($R96*$S$2 + ($T96*$T$2)), 2) -> 397.87 | F92: =$E92*$C$12 -> 397.87 | K92: mu_A | L92: SUBI
A93: 15 | B93: m | D93: Conduit Galv. 20mm RATE | F93: price from quintano | G93: COGV_013 | H93: 690 | I93: BAR | J93: 25mm | O93: 1 | P93: 34669 | Q93: 3.03 | R93: =$A93*Q93 -> 45.45 | S93: 0.2 | T93: =$A93*S93*$T$1 -> 3.45 | AR93: 75
A94: 120 | B94: m | D94: Screened 3c Cable 0.75sqmm | G94: CASP_083 | H94: 617 | I94: Lappkabel | J94: 0034703 UNITRONIC LiYCY | O94: 2 | P94: 38433 | Q94: 1.2 | R94: =$A94*Q94 -> 144 | S94: 0.03 | T94: =$A94*S94*$T$1 -> 4.14
R95: =$A95*Q95 -> 0 | T95: =$A95*S95*$T$1 -> 0
A96: d> | B96: =(R95+T95) -> 0 | K96: mu_A | L96: SUBI | R96: =SUM(R92:R95) -> 189.45 | T96: =SUM(T92:T95) -> 7.59 | AG96: =ROUND($R96*$S$2,2) -> 189.45
D97: =$F$3 -> Controls | E97: =ROUND(($R100*$S$3 + ($T100*$T$3)), 2) -> 374.89 | F97: =$E97*$C$12 -> 374.89 | K97: mu_B | L97: SUBI
A98: 2 | B98: No | D98: Motorised Actuators for Dampers | G98: BMSE_001 | H98: 512 | I98: (__) | O98: 3 | Q98: =198/2 -> 99 | R98: =$A98*Q98 -> 198 | S98: =(2*35/27.46+2*41.91/27.46)/2 -> 2.8008012 | T98: =$A98*S98*$T$1 -> 6.4418427
R99: =$A99*Q99 -> 0 | T99: =$A99*S99*$T$1 -> 0
A100: d> | B100: =(R99+T99) -> 0 | K100: mu_B | L100: SUBI | R100: =SUM(R97:R99) -> 198 | T100: =SUM(T97:T99) -> 6.4418427 | AG100: =ROUND($R100*$S$3,2) -> 198
D101: =$F$4 -> Controls | E101: =ROUND(($R105*$S$4 + ($T105*$T$4)), 2) -> 0 | F101: =$F89-SUMIF($L91:$P98,"SUBI",$F91:$F98) -> 0 | K101: mu_C | L101: SUBI
B102: >>> mu_C material here >>> | R102: =$A102*Q102 -> 0 | T102: =$A102*S102*$T$1 -> 0
R103: =$A103*Q103 -> 0 | T103: =$A103*S103*$T$1 -> 0
...

Sheet E_BOQ
A1: ITEM NO. | B1: DESCRIPTION | C1: QTY | D1: UNIT | E1: RATE | F1: TOTAL | G1: Material Cost | H1: Labour (hrs)
E2: € | F2: € | G2: € | H2: €
A3: =TRIM(MID(Elec_Est!D15,6,30)) | B3: =Elec_Est!D16 -> Electrical For Mechanical Works,
A5: =TRIM(MID(Elec_Est!D19,6,30)) -> 1.01 | B5: =Elec_Est!D20 -> Dismantling the Old AHU | C5: =Elec_Est!A19 -> 1 | D5: =Elec_Est!B19 -> L/S | E5: =Elec_Est!E19 -> 126.32 | F5: =C5*E5 -> 126.32 | G5: =Elec_Est!AM19 -> 0 | H5: =Elec_Est!AN19 -> 4.6
A7: =TRIM(MID(Elec_Est!D25,6,30)) -> 1.02 | B7: =Elec_Est!D26 -> Electrical Power for Air Conditioning Outdoor Units including connecting Up of Outdoor units | C7: =Elec_Est!A25 -> 2 | D7: =Elec_Est!B25 -> No | E7: =Elec_Est!E25 -> 803.68 | F7: =C7*E7 -> 1607.36 | G7: =Elec_Est!AM25 -> 1144.8 | H7: =Elec_Est!AN25 -> 16.85
A9: =TRIM(MID(Elec_Est!D38,6,30)) -> 1.03 | B9: =Elec_Est!D39 -> Electrical Power for Air Conditioning Indoor Units including connecting Up of Indoor units | C9: =Elec_Est!A38 -> 2 | D9: =Elec_Est!B38 -> No | E9: =Elec_Est!E38 -> 196.27 | F9: =C9*E9 -> 392.54 | G9: =Elec_Est!AM38 -> 162.64 | H9: =Elec_Est!AN38 -> 8.37
A11: =TRIM(MID(Elec_Est!D48,6,30)) -> 1.04 | B11: =Elec_Est!D49 -> Flowmeter | C11: =Elec_Est!A48 -> 1 | D11: =Elec_Est!B48 -> No | E11: =Elec_Est!E48 -> 3450.94 | F11: =C11*E11 -> 3450.94 | G11: =Elec_Est!AM48 -> 3010.39 | H11: =Elec_Est!AN48 -> 16.04
A13: =TRIM(MID(Elec_Est!D69,6,30)) -> 1.05 | B13: =Elec_Est!D70 -> Delta Pressure Sensor | C13: =Elec_Est!A69 -> 1 | D13: =Elec_Est!B69 -> No | E13: =Elec_Est!E69 -> 577.92 | F13: =C13*E13 -> 577.92 | G13: =Elec_Est!AM69 -> 249.45 | H13: =Elec_Est!AN69 -> 11.96
A15: =TRIM(MID(Elec_Est!D89,6,30)) -> 1.06 | B15: =Elec_Est!D90 -> Damper | C15: =Elec_Est!A89 -> 2 | D15: =Elec_Est!B89 -> No | E15: =Elec_Est!E89 -> 386.38 | F15: =C15*E15 -> 772.76 | G15: =Elec_Est!AM89 -> 387.45 | H15: =Elec_Est!AN89 -> 14.03
A17: =TRIM(MID(Elec_Est!D109,6,30)) -> 1.07 | B17: =Elec_Est!D110 -> Dismantling the Old Extractors | C17: =Elec_Est!A109 -> 1 | D17: =Elec_Est!B109 -> LS | E17: =Elec_Est!E109 -> 505.26 | F17: =C17*E17 -> 505.26 | G17: =Elec_Est!AM109 -> 0 | H17: =Elec_Est!AN109 -> 18.4
A51: SB | B51: Total - | D51: =[16]ML_Sum!D6 -> VAT EXCL. | E51: € | F51: =SUM(F4:F50) -> 7433.1 | G51: =SUM(G5:G50) -> 4954.73 | H51: =SUM(H5:H50) -> 90.25
