Workbook
Name Access_Bathroom: Fire_Stopping_Est!#REF!
Name Access_Bathroom: Elec_Est!$A$11001
Name Access_Control: Fire_Stopping_Est!#REF!
Name Access_Control: Elec_Est!$A$10069
Name AREAS: ML_Sum!$X$1:$AD$16
Name AREAS: #REF!
Name AREAS: ML_Sum!$X$1:$AD$16
Name CCTV: Fire_Stopping_Est!#REF!
Name CCTV: Elec_Est!$A$9809
Name Data: Fire_Stopping_Est!#REF!
Name Data: Elec_Est!$A$6644
Name Electrical: Fire_Stopping_Est!#REF!
Name Electrical: Elec_Est!$A$131
Name Fire_Alarm: Fire_Stopping_Est!#REF!
Name Fire_Alarm: Elec_Est!$A$8157
Name Fire_Stopping: Fire_Stopping_Est!#REF!
Name Fire_Stopping: Elec_Est!$A$7844
Name FO: #REF!
Name Guard: #REF!
Name Intercom: Fire_Stopping_Est!#REF!
Name Intercom: Elec_Est!$A$10379
Name Intruder_Alarm: #REF!
Name LPS: Elec_Est!$A$7739
Name Preliminaries: Fire_Stopping_Est!#REF!
Name Preliminaries: Elec_Est!$A$16
Name Security: Fire_Stopping_Est!#REF!
Name Security: Elec_Est!$A$10539

Sheet ELV_Fire_Security_BOQ
B2: SECTION 3 - ELV, FIRE AND SECURITY
A4: ITEM | B4: DESCRIPTION | C4: QTY | D4: UNIT | E4: RATE Euro (Exc of VAT) | F4: TOTAL Euro (Exc of VAT)
A5: 1 | B5: PRELIMINARIES
B6: All equipment to be used within this contract is to be approved prior to delivery to site.
A7: =IFERROR(IF(OFFSET(A7,-1,0)>0,OFFSET(A7,-1,0)+0.001,ERROR.TYPE(0)),IFERROR(IF(OFFSET(A7,-2,0)>0,OFFSET(A7,-2,0)+0.001,ERROR.TYPE(0)),IFERROR(IF(OFFSET(A7,-3,0)>0,OFFSET(A7,-3,0)+0.001,ERROR.TYPE(0)),IFERROR(IF(OFFSET(A7,-4,0)>0,OFFSET(A7,-4,0)+0.001,ERROR.TYPE(0)),IFERROR(IF(OFFSET(A7,-5,0)>0,OFFSET(A7,-5,0)+0.001,ERROR.TYPE(0)),IFERROR(IF(OFFSET(A7,-6,0)>0,OFFSET(A7,-6,0)+0.001,ERROR.TYPE(0)),IFERROR(IF(OFFSET(A7,-7,0)>0,OFFSET(A7,-7,0)+0.001,ERROR.TYPE(0)),IFERROR(IF(OFFSET(A7,-8,0)>0,OFFSET(A7,-8,0)+0.001,ERROR.TYPE(0)),IFERROR(IF(OFFSET(A7,-9,0)>0,OFFSET(A7,-9,0)+0.001,ERROR.TYPE(0)),IFERROR(IF(OFFSET(A7,-10,0)>0,OFFSET(A7,-10,0)+0.001,ERROR.TYPE(0)),ERROR.TYPE(0))))))))))) -> 1.001 | B7: Mobilisation of site including the setting up of Storage facilities for materials, Sanitary facilities for the employees, Setting up of temporary site office, etc required to undertake the works | C7: 1 | D7: L.S. | E7: =Elec_Est!Q8014 -> Included with MEP preliminaries
A8: =IFERROR(IF(OFFSET(A8,-1,0)>0,OFFSET(A8,-1,0)+0.001,ERROR.TYPE(0)),IFERROR(IF(OFFSET(A8,-2,0)>0,OFFSET(A8,-2,0)+0.001,ERROR.TYPE(0)),IFERROR(IF(OFFSET(A8,-3,0)>0,OFFSET(A8,-3,0)+0.001,ERROR.TYPE(0)),IFERROR(IF(OFFSET(A8,-4,0)>0,OFFSET(A8,-4,0)+0.001,ERROR.TYPE(0)),IFERROR(IF(OFFSET(A8,-5,0)>0,OFFSET(A8,-5,0)+0.001,ERROR.TYPE(0)),IFERROR(IF(OFFSET(A8,-6,0)>0,OFFSET(A8,-6,0)+0.001,ERROR.TYPE(0)),IFERROR(IF(OFFSET(A8,-7,0)>0,OFFSET(A8,-7,0)+0.001,ERROR.TYPE(0)),IFERROR(IF(OFFSET(A8,-8,0)>0,OFFSET(A8,-8,0)+0.001,ERROR.TYPE(0)),IFERROR(IF(OFFSET(A8,-9,0)>0,OFFSET(A8,-9,0)+0.001,ERROR.TYPE(0)),IFERROR(IF(OFFSET(A8,-10,0)>0,OFFSET(A8,-10,0)+0.001,ERROR.TYPE(0)),ERROR.TYPE(0))))))))))) -> 1.002 | B8: Provision of insurance cover in the joint names of the Client and Contractor insure the Works against loss or damage by fire, storm, tempest, lightning, flood, earthquake, aircraft or anything dropped there from, aerial objects, riot and civil commotion for the full reinstatement value thereof plus 15% of all the Works executed and all unfixed materials and goods so insured until the completion of the Works. The Contractor shall affect a policy of insurance against third party risks to cover an amount of not less than Euro 500,000 (five hundred thousand Euros) for any one accident. The policy shall be in joint names of the Client and Contractor and shall include cross liability clauses. In respect of liability for the death or injury to any person employed by the Contractor and arising out of and in the course of such person's employment by the Contractor the amount insured by the Contractor shall be such as to indemnify the Client against all damages as compensation payable. The Contractor shall comply with and be subject to the terms, exclusions, exceptions, conditions and limitations of the insurance policies and shall bear the amount of the retained liabilities stated therein The Contractor shall deposit with the Client copies of the policy or policies and a copy of the receipt in respect of premiums paid before starting the Works | C8: 1 | D8: L.S. | E8: =Elec_Est!Q8024 -> Included with MEP preliminaries
A9: =IFERROR(IF(OFFSET(A9,-1,0)>0,OFFSET(A9,-1,0)+0.001,ERROR.TYPE(0)),IFERROR(IF(OFFSET(A9,-2,0)>0,OFFSET(A9,-2,0)+0.001,ERROR.TYPE(0)),IFERROR(IF(OFFSET(A9,-3,0)>0,OFFSET(A9,-3,0)+0.001,ERROR.TYPE(0)),IFERROR(IF(OFFSET(A9,-4,0)>0,OFFSET(A9,-4,0)+0.001,ERROR.TYPE(0)),IFERROR(IF(OFFSET(A9,-5,0)>0,OFFSET(A9,-5,0)+0.001,ERROR.TYPE(0)),IFERROR(IF(OFFSET(A9,-6,0)>0,OFFSET(A9,-6,0)+0.001,ERROR.TYPE(0)),IFERROR(IF(OFFSET(A9,-7,0)>0,OFFSET(A9,-7,0)+0.001,ERROR.TYPE(0)),IFERROR(IF(OFFSET(A9,-8,0)>0,OFFSET(A9,-8,0)+0.001,ERROR.TYPE(0)),IFERROR(IF(OFFSET(A9,-9,0)>0,OFFSET(A9,-9,0)+0.001,ERROR.TYPE(0)),IFERROR(IF(OFFSET(A9,-10,0)>0,OFFSET(A9,-10,0)+0.001,ERROR.TYPE(0)),ERROR.TYPE(0))))))))))) -> 1.003 | B9: Implementation of health and safety measures on site including personal safety (e.g safety shoes, helmets scaffolding, harnesses etc) as well as those to render the site safe for employees (e.g staircase handrails, closing of lift shaft openings etc) | C9: 1 | D9: L.S. | E9: =Elec_Est!Q8034 -> Included with MEP preliminaries
A10: =IFERROR(IF(OFFSET(A10,-1,0)>0,OFFSET(A10,-1,0)+0.001,ERROR.TYPE(0)),IFERROR(IF(OFFSET(A10,-2,0)>0,OFFSET(A10,-2,0)+0.001,ERROR.TYPE(0)),IFERROR(IF(OFFSET(A10,-3,0)>0,OFFSET(A10,-3,0)+0.001,ERROR.TYPE(0)),IFERROR(IF(OFFSET(A10,-4,0)>0,OFFSET(A10,-4,0)+0.001,ERROR.TYPE(0)),IFERROR(IF(OFFSET(A10,-5,0)>0,OFFSET(A10,-5,0)+0.001,ERROR.TYPE(0)),IFERROR(IF(OFFSET(A10,-6,0)>0,OFFSET(A10,-6,0)+0.001,ERROR.TYPE(0)),IFERROR(IF(OFFSET(A10,-7,0)>0,OFFSET(A10,-7,0)+0.001,ERROR.TYPE(0)),IFERROR(IF(OFFSET(A10,-8,0)>0,OFFSET(A10,-8,0)+0.001,ERROR.TYPE(0)),IFERROR(IF(OFFSET(A10,-9,0)>0,OFFSET(A10,-9,0)+0.001,ERROR.TYPE(0)),IFERROR(IF(OFFSET(A10,-10,0)>0,OFFSET(A10,-10,0)+0.001,ERROR.TYPE(0)),ERROR.TYPE(0))))))))))) -> 1.004 | B10: Prepare a risk assessment report outlining all risks involved and measures to be taken to minimise or eliminate potential risks. The report is to be prepared and signed by a competent person and to be submitted within three weeks from commencement of works. | C10: 1 | D10: L.S. | E10: =Elec_Est!Q8044 -> Included with MEP preliminaries
A11: =IFERROR(IF(OFFSET(A11,-1,0)>0,OFFSET(A11,-1,0)+0.001,ERROR.TYPE(0)),IFERROR(IF(OFFSET(A11,-2,0)>0,OFFSET(A11,-2,0)+0.001,ERROR.TYPE(0)),IFERROR(IF(OFFSET(A11,-3,0)>0,OFFSET(A11,-3,0)+0.001,ERROR.TYPE(0)),IFERROR(IF(OFFSET(A11,-4,0)>0,OFFSET(A11,-4,0)+0.001,ERROR.TYPE(0)),IFERROR(IF(OFFSET(A11,-5,0)>0,OFFSET(A11,-5,0)+0.001,ERROR.TYPE(0)),IFERROR(IF(OFFSET(A11,-6,0)>0,OFFSET(A11,-6,0)+0.001,ERROR.TYPE(0)),IFERROR(IF(OFFSET(A11,-7,0)>0,OFFSET(A11,-7,0)+0.001,ERROR.TYPE(0)),IFERROR(IF(OFFSET(A11,-8,0)>0,OFFSET(A11,-8,0)+0.001,ERROR.TYPE(0)),IFERROR(IF(OFFSET(A11,-9,0)>0,OFFSET(A11,-9,0)+0.001,ERROR.TYPE(0)),IFERROR(IF(OFFSET(A11,-10,0)>0,OFFSET(A11,-10,0)+0.001,ERROR.TYPE(0)),ERROR.TYPE(0))))))))))) -> 1.005 | B11: Allow for carrying out all surveys, setting out of works unless included elsewhere in the Bills of Quantities. | C11: 1 | D11: L.S. | E11: =Elec_Est!Q8054 -> Included with MEP preliminaries
B12: TOTAL FOR PAGE 01 | C12: Euro Exc VAT | F12: =SUM(F7:F11) -> 0
A15: ITEM | B15: DESCRIPTION | C15: QTY | D15: UNIT | E15: RATE Euro (Exc of VAT) | F15: TOTAL Euro (Exc of VAT)
A16: =IFERROR(IF(OFFSET(A16,-1,0)>0,OFFSET(A16,-1,0)+0.001,ERROR.TYPE(0)),IFERROR(IF(OFFSET(A16,-2,0)>0,OFFSET(A16,-2,0)+0.001,ERROR.TYPE(0)),IFERROR(IF(OFFSET(A16,-3,0)>0,OFFSET(A16,-3,0)+0.001,ERROR.TYPE(0)),IFERROR(IF(OFFSET(A16,-4,0)>0,OFFSET(A16,-4,0)+0.001,ERROR.TYPE(0)),IFERROR(IF(OFFSET(A16,-5,0)>0,OFFSET(A16,-5,0)+0.001,ERROR.TYPE(0)),IFERROR(IF(OFFSET(A16,-6,0)>0,OFFSET(A16,-6,0)+0.001,ERROR.TYPE(0)),IFERROR(IF(OFFSET(A16,-7,0)>0,OFFSET(A16,-7,0)+0.001,ERROR.TYPE(0)),IFERROR(IF(OFFSET(A16,-8,0)>0,OFFSET(A16,-8,0)+0.001,ERROR.TYPE(0)),IFERROR(IF(OFFSET(A16,-9,0)>0,OFFSET(A16,-9,0)+0.001,ERROR.TYPE(0)),IFERROR(IF(OFFSET(A16,-10,0)>0,OFFSET(A16,-10,0)+0.001,ERROR.TYPE(0)),ERROR.TYPE(0))))))))))) -> 1.006 | B16: Provision for attending to site to take all relevant measurements in order to ascertain the exact quantities of the individual and measured items to be procured as well as keeping of all relevant records of personnel attendance, stock control etc | C16: 1 | D16: L.S. | E16: =Elec_Est!Q8064 -> Included with MEP preliminaries
A17: =IFERROR(IF(OFFSET(A17,-1,0)>0,OFFSET(A17,-1,0)+0.001,ERROR.TYPE(0)),IFERROR(IF(OFFSET(A17,-2,0)>0,OFFSET(A17,-2,0)+0.001,ERROR.TYPE(0)),IFERROR(IF(OFFSET(A17,-3,0)>0,OFFSET(A17,-3,0)+0.001,ERROR.TYPE(0)),IFERROR(IF(OFFSET(A17,-4,0)>0,OFFSET(A17,-4,0)+0.001,ERROR.TYPE(0)),IFERROR(IF(OFFSET(A17,-5,0)>0,OFFSET(A17,-5,0)+0.001,ERROR.TYPE(0)),IFERROR(IF(OFFSET(A17,-6,0)>0,OFFSET(A17,-6,0)+0.001,ERROR.TYPE(0)),IFERROR(IF(OFFSET(A17,-7,0)>0,OFFSET(A17,-7,0)+0.001,ERROR.TYPE(0)),IFERROR(IF(OFFSET(A17,-8,0)>0,OFFSET(A17,-8,0)+0.001,ERROR.TYPE(0)),IFERROR(IF(OFFSET(A17,-9,0)>0,OFFSET(A17,-9,0)+0.001,ERROR.TYPE(0)),IFERROR(IF(OFFSET(A17,-10,0)>0,OFFSET(A17,-10,0)+0.001,ERROR.TYPE(0)),ERROR.TYPE(0))))))))))) -> 1.007 | B17: Provision of security measures on site both as regards the storage facilities as well as to safeguard the materials installed during the latter stages of the project. | C17: 1 | D17: L.S. | E17: =Elec_Est!Q8074 -> Included with MEP preliminaries
A18: =IFERROR(IF(OFFSET(A18,-1,0)>0,OFFSET(A18,-1,0)+0.001,ERROR.TYPE(0)),IFERROR(IF(OFFSET(A18,-2,0)>0,OFFSET(A18,-2,0)+0.001,ERROR.TYPE(0)),IFERROR(IF(OFFSET(A18,-3,0)>0,OFFSET(A18,-3,0)+0.001,ERROR.TYPE(0)),IFERROR(IF(OFFSET(A18,-4,0)>0,OFFSET(A18,-4,0)+0.001,ERROR.TYPE(0)),IFERROR(IF(OFFSET(A18,-5,0)>0,OFFSET(A18,-5,0)+0.001,ERROR.TYPE(0)),IFERROR(IF(OFFSET(A18,-6,0)>0,OFFSET(A18,-6,0)+0.001,ERROR.TYPE(0)),IFERROR(IF(OFFSET(A18,-7,0)>0,OFFSET(A18,-7,0)+0.001,ERROR.TYPE(0)),IFERROR(IF(OFFSET(A18,-8,0)>0,OFFSET(A18,-8,0)+0.001,ERROR.TYPE(0)),IFERROR(IF(OFFSET(A18,-9,0)>0,OFFSET(A18,-9,0)+0.001,ERROR.TYPE(0)),IFERROR(IF(OFFSET(A18,-10,0)>0,OFFSET(A18,-10,0)+0.001,ERROR.TYPE(0)),ERROR.TYPE(0))))))))))) -> 1.008 | B18: Provision for the supply and delivery to site of samples as may be requested by the client / engineer | C18: 1 | D18: L.S. | E18: =Elec_Est!Q8084 -> Included with MEP preliminaries
A19: =IFERROR(IF(OFFSET(A19,-1,0)>0,OFFSET(A19,-1,0)+0.001,ERROR.TYPE(0)),IFERROR(IF(OFFSET(A19,-2,0)>0,OFFSET(A19,-2,0)+0.001,ERROR.TYPE(0)),IFERROR(IF(OFFSET(A19,-3,0)>0,OFFSET(A19,-3,0)+0.001,ERROR.TYPE(0)),IFERROR(IF(OFFSET(A19,-4,0)>0,OFFSET(A19,-4,0)+0.001,ERROR.TYPE(0)),IFERROR(IF(OFFSET(A19,-5,0)>0,OFFSET(A19,-5,0)+0.001,ERROR.TYPE(0)),IFERROR(IF(OFFSET(A19,-6,0)>0,OFFSET(A19,-6,0)+0.001,ERROR.TYPE(0)),IFERROR(IF(OFFSET(A19,-7,0)>0,OFFSET(A19,-7,0)+0.001,ERROR.TYPE(0)),IFERROR(IF(OFFSET(A19,-8,0)>0,OFFSET(A19,-8,0)+0.001,ERROR.TYPE(0)),IFERROR(IF(OFFSET(A19,-9,0)>0,OFFSET(A19,-9,0)+0.001,ERROR.TYPE(0)),IFERROR(IF(OFFSET(A19,-10,0)>0,OFFSET(A19,-10,0)+0.001,ERROR.TYPE(0)),ERROR.TYPE(0))))))))))) -> 1.009 | B19: Allow for continuously keeping the site and building clean and in a workman type condition free from debris, surplus materials and any other type of loose matter arising from works, which will disturb the proper conditions of any internal and external areas, roads and/or adjoining structures. Site Cleaning is to take place during the whole duration of works. Client reserves the right to employ cleaning companies at the contractor's expense if the contractor fails to keep the site clean. | C19: 1 | D19: L.S. | E19: =Elec_Est!Q8094 -> Included with MEP preliminaries
A20: =IFERROR(IF(OFFSET(A20,-1,0)>0,OFFSET(A20,-1,0)+0.001,ERROR.TYPE(0)),IFERROR(IF(OFFSET(A20,-2,0)>0,OFFSET(A20,-2,0)+0.001,ERROR.TYPE(0)),IFERROR(IF(OFFSET(A20,-3,0)>0,OFFSET(A20,-3,0)+0.001,ERROR.TYPE(0)),IFERROR(IF(OFFSET(A20,-4,0)>0,OFFSET(A20,-4,0)+0.001,ERROR.TYPE(0)),IFERROR(IF(OFFSET(A20,-5,0)>0,OFFSET(A20,-5,0)+0.001,ERROR.TYPE(0)),IFERROR(IF(OFFSET(A20,-6,0)>0,OFFSET(A20,-6,0)+0.001,ERROR.TYPE(0)),IFERROR(IF(OFFSET(A20,-7,0)>0,OFFSET(A20,-7,0)+0.001,ERROR.TYPE(0)),IFERROR(IF(OFFSET(A20,-8,0)>0,OFFSET(A20,-8,0)+0.001,ERROR.TYPE(0)),IFERROR(IF(OFFSET(A20,-9,0)>0,OFFSET(A20,-9,0)+0.001,ERROR.TYPE(0)),IFERROR(IF(OFFSET(A20,-10,0)>0,OFFSET(A20,-10,0)+0.001,ERROR.TYPE(0)),ERROR.TYPE(0))))))))))) -> 1.01 | B20: Provision for hauling of equipment on site, including cranage, permits and all necessary fees. | C20: 1 | D20: L.S. | E20: =Elec_Est!Q8104 -> Included with MEP preliminaries
A21: =IFERROR(IF(OFFSET(A21,-1,0)>0,OFFSET(A21,-1,0)+0.001,ERROR.TYPE(0)),IFERROR(IF(OFFSET(A21,-2,0)>0,OFFSET(A21,-2,0)+0.001,ERROR.TYPE(0)),IFERROR(IF(OFFSET(A21,-3,0)>0,OFFSET(A21,-3,0)+0.001,ERROR.TYPE(0)),IFERROR(IF(OFFSET(A21,-4,0)>0,OFFSET(A21,-4,0)+0.001,ERROR.TYPE(0)),IFERROR(IF(OFFSET(A21,-5,0)>0,OFFSET(A21,-5,0)+0.001,ERROR.TYPE(0)),IFERROR(IF(OFFSET(A21,-6,0)>0,OFFSET(A21,-6,0)+0.001,ERROR.TYPE(0)),IFERROR(IF(OFFSET(A21,-7,0)>0,OFFSET(A21,-7,0)+0.001,ERROR.TYPE(0)),IFERROR(IF(OFFSET(A21,-8,0)>0,OFFSET(A21,-8,0)+0.001,ERROR.TYPE(0)),IFERROR(IF(OFFSET(A21,-9,0)>0,OFFSET(A21,-9,0)+0.001,ERROR.TYPE(0)),IFERROR(IF(OFFSET(A21,-10,0)>0,OFFSET(A21,-10,0)+0.001,ERROR.TYPE(0)),ERROR.TYPE(0))))))))))) -> 1.011 | B21: Provision for working at height, including scaffolding, cherry pickers etc. All equipment shall be fully certified. | C21: 1 | D21: L.S. | E21: =Elec_Est!Q8114 -> Included with MEP preliminaries
A22: =IFERROR(IF(OFFSET(A22,-1,0)>0,OFFSET(A22,-1,0)+0.001,ERROR.TYPE(0)),IFERROR(IF(OFFSET(A22,-2,0)>0,OFFSET(A22,-2,0)+0.001,ERROR.TYPE(0)),IFERROR(IF(OFFSET(A22,-3,0)>0,OFFSET(A22,-3,0)+0.001,ERROR.TYPE(0)),IFERROR(IF(OFFSET(A22,-4,0)>0,OFFSET(A22,-4,0)+0.001,ERROR.TYPE(0)),IFERROR(IF(OFFSET(A22,-5,0)>0,OFFSET(A22,-5,0)+0.001,ERROR.TYPE(0)),IFERROR(IF(OFFSET(A22,-6,0)>0,OFFSET(A22,-6,0)+0.001,ERROR.TYPE(0)),IFERROR(IF(OFFSET(A22,-7,0)>0,OFFSET(A22,-7,0)+0.001,ERROR.TYPE(0)),IFERROR(IF(OFFSET(A22,-8,0)>0,OFFSET(A22,-8,0)+0.001,ERROR.TYPE(0)),IFERROR(IF(OFFSET(A22,-9,0)>0,OFFSET(A22,-9,0)+0.001,ERROR.TYPE(0)),IFERROR(IF(OFFSET(A22,-10,0)>0,OFFSET(A22,-10,0)+0.001,ERROR.TYPE(0)),ERROR.TYPE(0))))))))))) -> 1.012 | B22: Provision for Builders Work in order to prepare all openings required to install conduits, pipework, ductwork, etc., and making good and reinstatement of all openings. | C22: 1 | D22: L.S. | E22: =Elec_Est!Q8124 -> Included with MEP preliminaries
A23: =IFERROR(IF(OFFSET(A23,-1,0)>0,OFFSET(A23,-1,0)+0.001,ERROR.TYPE(0)),IFERROR(IF(OFFSET(A23,-2,0)>0,OFFSET(A23,-2,0)+0.001,ERROR.TYPE(0)),IFERROR(IF(OFFSET(A23,-3,0)>0,OFFSET(A23,-3,0)+0.001,ERROR.TYPE(0)),IFERROR(IF(OFFSET(A23,-4,0)>0,OFFSET(A23,-4,0)+0.001,ERROR.TYPE(0)),IFERROR(IF(OFFSET(A23,-5,0)>0,OFFSET(A23,-5,0)+0.001,ERROR.TYPE(0)),IFERROR(IF(OFFSET(A23,-6,0)>0,OFFSET(A23,-6,0)+0.001,ERROR.TYPE(0)),IFERROR(IF(OFFSET(A23,-7,0)>0,OFFSET(A23,-7,0)+0.001,ERROR.TYPE(0)),IFERROR(IF(OFFSET(A23,-8,0)>0,OFFSET(A23,-8,0)+0.001,ERROR.TYPE(0)),IFERROR(IF(OFFSET(A23,-9,0)>0,OFFSET(A23,-9,0)+0.001,ERROR.TYPE(0)),IFERROR(IF(OFFSET(A23,-10,0)>0,OFFSET(A23,-10,0)+0.001,ERROR.TYPE(0)),ERROR.TYPE(0))))))))))) -> 1.013 | B23: Provision for Openings in Insulation Panelling in order to prepare all openings required to install conduits, pipework, ductwork, etc., and making good and reinstatement of all openings. | C23: 1 | D23: L.S. | E23: =Elec_Est!Q8134 -> Included with MEP preliminaries
B24: TOTAL FOR PAGE 02 | C24: Euro Exc VAT | F24: =SUM(F16:F23) -> 0
B26: TOTAL FOR PRELIMINARIES | C26: Euro Exc VAT | F26: =F24+F12 -> 0
A29: ITEM | B29: DESCRIPTION | C29: QTY | D29: UNIT | E29: RATE Euro (Exc of VAT) | F29: TOTAL Euro (Exc of VAT)
A30: 2 | B30: FIRE ALARM & DETECTION SYSTEM
B31: In general all the points except manual call points shall be wired with cables clipped directly to the wall / ceiling unless otherwise indicated. All conduit rates are none the less to be quoted for since these may be required in some instances.
B32: Basement Level -1 - FAP1
B33: Supply and install galvanised conduit surface mounted from fire alarm panel via galvanised trunking to the following fire alarm points.
A34: =IFERROR(IF(OFFSET(A34,-1,0)>0,OFFSET(A34,-1,0)+0.001,ERROR.TYPE(0)),IFERROR(IF(OFFSET(A34,-2,0)>0,OFFSET(A34,-2,0)+0.001,ERROR.TYPE(0)),IFERROR(IF(OFFSET(A34,-3,0)>0,OFFSET(A34,-3,0)+0.001,ERROR.TYPE(0)),IFERROR(IF(OFFSET(A34,-4,0)>0,OFFSET(A34,-4,0)+0.001,ERROR.TYPE(0)),IFERROR(IF(OFFSET(A34,-5,0)>0,OFFSET(A34,-5,0)+0.001,ERROR.TYPE(0)),IFERROR(IF(OFFSET(A34,-6,0)>0,OFFSET(A34,-6,0)+0.001,ERROR.TYPE(0)),IFERROR(IF(OFFSET(A34,-7,0)>0,OFFSET(A34,-7,0)+0.001,ERROR.TYPE(0)),IFERROR(IF(OFFSET(A34,-8,0)>0,OFFSET(A34,-8,0)+0.001,ERROR.TYPE(0)),IFERROR(IF(OFFSET(A34,-9,0)>0,OFFSET(A34,-9,0)+0.001,ERROR.TYPE(0)),IFERROR(IF(OFFSET(A34,-10,0)>0,OFFSET(A34,-10,0)+0.001,ERROR.TYPE(0)),ERROR.TYPE(0))))))))))) -> 2.001 | B34: Optical smoke detector | C34: 14 | D34: No | E34: =Elec_Est!E8172 -> 98.17 | F34: =IFERROR($C34*E34,E34) -> 1374.38
A35: =IFERROR(IF(OFFSET(A35,-1,0)>0,OFFSET(A35,-1,0)+0.001,ERROR.TYPE(0)),IFERROR(IF(OFFSET(A35,-2,0)>0,OFFSET(A35,-2,0)+0.001,ERROR.TYPE(0)),IFERROR(IF(OFFSET(A35,-3,0)>0,OFFSET(A35,-3,0)+0.001,ERROR.TYPE(0)),IFERROR(IF(OFFSET(A35,-4,0)>0,OFFSET(A35,-4,0)+0.001,ERROR.TYPE(0)),IFERROR(IF(OFFSET(A35,-5,0)>0,OFFSET(A35,-5,0)+0.001,ERROR.TYPE(0)),IFERROR(IF(OFFSET(A35,-6,0)>0,OFFSET(A35,-6,0)+0.001,ERROR.TYPE(0)),IFERROR(IF(OFFSET(A35,-7,0)>0,OFFSET(A35,-7,0)+0.001,ERROR.TYPE(0)),IFERROR(IF(OFFSET(A35,-8,0)>0,OFFSET(A35,-8,0)+0.001,ERROR.TYPE(0)),IFERROR(IF(OFFSET(A35,-9,0)>0,OFFSET(A35,-9,0)+0.001,ERROR.TYPE(0)),IFERROR(IF(OFFSET(A35,-10,0)>0,OFFSET(A35,-10,0)+0.001,ERROR.TYPE(0)),ERROR.TYPE(0))))))))))) -> 2.002 | B35: Combined optical smoke detector c/w internal sounder & flashing beacon | C35: 5 | D35: No | E35: =Elec_Est!E8179 -> 98.17 | F35: =IFERROR($C35*E35,E35) -> 490.85
A36: =IFERROR(IF(OFFSET(A36,-1,0)>0,OFFSET(A36,-1,0)+0.001,ERROR.TYPE(0)),IFERROR(IF(OFFSET(A36,-2,0)>0,OFFSET(A36,-2,0)+0.001,ERROR.TYPE(0)),IFERROR(IF(OFFSET(A36,-3,0)>0,OFFSET(A36,-3,0)+0.001,ERROR.TYPE(0)),IFERROR(IF(OFFSET(A36,-4,0)>0,OFFSET(A36,-4,0)+0.001,ERROR.TYPE(0)),IFERROR(IF(OFFSET(A36,-5,0)>0,OFFSET(A36,-5,0)+0.001,ERROR.TYPE(0)),IFERROR(IF(OFFSET(A36,-6,0)>0,OFFSET(A36,-6,0)+0.001,ERROR.TYPE(0)),IFERROR(IF(OFFSET(A36,-7,0)>0,OFFSET(A36,-7,0)+0.001,ERROR.TYPE(0)),IFERROR(IF(OFFSET(A36,-8,0)>0,OFFSET(A36,-8,0)+0.001,ERROR.TYPE(0)),IFERROR(IF(OFFSET(A36,-9,0)>0,OFFSET(A36,-9,0)+0.001,ERROR.TYPE(0)),IFERROR(IF(OFFSET(A36,-10,0)>0,OFFSET(A36,-10,0)+0.001,ERROR.TYPE(0)),ERROR.TYPE(0))))))))))) -> 2.003 | B36: Rate of rise heat detector | C36: 77 | D36: No | E36: =Elec_Est!E8186 -> 98.17 | F36: =IFERROR($C36*E36,E36) -> 7559.09
A37: =IFERROR(IF(OFFSET(A37,-1,0)>0,OFFSET(A37,-1,0)+0.001,ERROR.TYPE(0)),IFERROR(IF(OFFSET(A37,-2,0)>0,OFFSET(A37,-2,0)+0.001,ERROR.TYPE(0)),IFERROR(IF(OFFSET(A37,-3,0)>0,OFFSET(A37,-3,0)+0.001,ERROR.TYPE(0)),IFERROR(IF(OFFSET(A37,-4,0)>0,OFFSET(A37,-4,0)+0.001,ERROR.TYPE(0)),IFERROR(IF(OFFSET(A37,-5,0)>0,OFFSET(A37,-5,0)+0.001,ERROR.TYPE(0)),IFERROR(IF(OFFSET(A37,-6,0)>0,OFFSET(A37,-6,0)+0.001,ERROR.TYPE(0)),IFERROR(IF(OFFSET(A37,-7,0)>0,OFFSET(A37,-7,0)+0.001,ERROR.TYPE(0)),IFERROR(IF(OFFSET(A37,-8,0)>0,OFFSET(A37,-8,0)+0.001,ERROR.TYPE(0)),IFERROR(IF(OFFSET(A37,-9,0)>0,OFFSET(A37,-9,0)+0.001,ERROR.TYPE(0)),IFERROR(IF(OFFSET(A37,-10,0)>0,OFFSET(A37,-10,0)+0.001,ERROR.TYPE(0)),ERROR.TYPE(0))))))))))) -> 2.004 | B37: Combined rate of rise heat detector c/w internal sounder & flashing beacon | C37: 8 | D37: No | E37: =Elec_Est!E8193 -> 98.17 | F37: =IFERROR($C37*E37,E37) -> 785.36
A38: =IFERROR(IF(OFFSET(A38,-1,0)>0,OFFSET(A38,-1,0)+0.001,ERROR.TYPE(0)),IFERROR(IF(OFFSET(A38,-2,0)>0,OFFSET(A38,-2,0)+0.001,ERROR.TYPE(0)),IFERROR(IF(OFFSET(A38,-3,0)>0,OFFSET(A38,-3,0)+0.001,ERROR.TYPE(0)),IFERROR(IF(OFFSET(A38,-4,0)>0,OFFSET(A38,-4,0)+0.001,ERROR.TYPE(0)),IFERROR(IF(OFFSET(A38,-5,0)>0,OFFSET(A38,-5,0)+0.001,ERROR.TYPE(0)),IFERROR(IF(OFFSET(A38,-6,0)>0,OFFSET(A38,-6,0)+0.001,ERROR.TYPE(0)),IFERROR(IF(OFFSET(A38,-7,0)>0,OFFSET(A38,-7,0)+0.001,ERROR.TYPE(0)),IFERROR(IF(OFFSET(A38,-8,0)>0,OFFSET(A38,-8,0)+0.001,ERROR.TYPE(0)),IFERROR(IF(OFFSET(A38,-9,0)>0,OFFSET(A38,-9,0)+0.001,ERROR.TYPE(0)),IFERROR(IF(OFFSET(A38,-10,0)>0,OFFSET(A38,-10,0)+0.001,ERROR.TYPE(0)),ERROR.TYPE(0))))))))))) -> 2.005 | B38: Manual call point | C38: 2 | D38: No | E38: =Elec_Est!E8200 -> 98.17 | F38: =IFERROR($C38*E38,E38) -> 196.34
A39: =IFERROR(IF(OFFSET(A39,-1,0)>0,OFFSET(A39,-1,0)+0.001,ERROR.TYPE(0)),IFERROR(IF(OFFSET(A39,-2,0)>0,OFFSET(A39,-2,0)+0.001,ERROR.TYPE(0)),IFERROR(IF(OFFSET(A39,-3,0)>0,OFFSET(A39,-3,0)+0.001,ERROR.TYPE(0)),IFERROR(IF(OFFSET(A39,-4,0)>0,OFFSET(A39,-4,0)+0.001,ERROR.TYPE(0)),IFERROR(IF(OFFSET(A39,-5,0)>0,OFFSET(A39,-5,0)+0.001,ERROR.TYPE(0)),IFERROR(IF(OFFSET(A39,-6,0)>0,OFFSET(A39,-6,0)+0.001,ERROR.TYPE(0)),IFERROR(IF(OFFSET(A39,-7,0)>0,OFFSET(A39,-7,0)+0.001,ERROR.TYPE(0)),IFERROR(IF(OFFSET(A39,-8,0)>0,OFFSET(A39,-8,0)+0.001,ERROR.TYPE(0)),IFERROR(IF(OFFSET(A39,-9,0)>0,OFFSET(A39,-9,0)+0.001,ERROR.TYPE(0)),IFERROR(IF(OFFSET(A39,-10,0)>0,OFFSET(A39,-10,0)+0.001,ERROR.TYPE(0)),ERROR.TYPE(0))))))))))) -> 2.006 | B39: Interface unit for Zone Assembly Valve | C39: 1 | D39: No | E39: =Elec_Est!E8207 -> 98.17 | F39: =IFERROR($C39*E39,E39) -> 98.17
A40: =IFERROR(IF(OFFSET(A40,-1,0)>0,OFFSET(A40,-1,0)+0.001,ERROR.TYPE(0)),IFERROR(IF(OFFSET(A40,-2,0)>0,OFFSET(A40,-2,0)+0.001,ERROR.TYPE(0)),IFERROR(IF(OFFSET(A40,-3,0)>0,OFFSET(A40,-3,0)+0.001,ERROR.TYPE(0)),IFERROR(IF(OFFSET(A40,-4,0)>0,OFFSET(A40,-4,0)+0.001,ERROR.TYPE(0)),IFERROR(IF(OFFSET(A40,-5,0)>0,OFFSET(A40,-5,0)+0.001,ERROR.TYPE(0)),IFERROR(IF(OFFSET(A40,-6,0)>0,OFFSET(A40,-6,0)+0.001,ERROR.TYPE(0)),IFERROR(IF(OFFSET(A40,-7,0)>0,OFFSET(A40,-7,0)+0.001,ERROR.TYPE(0)),IFERROR(IF(OFFSET(A40,-8,0)>0,OFFSET(A40,-8,0)+0.001,ERROR.TYPE(0)),IFERROR(IF(OFFSET(A40,-9,0)>0,OFFSET(A40,-9,0)+0.001,ERROR.TYPE(0)),IFERROR(IF(OFFSET(A40,-10,0)>0,OFFSET(A40,-10,0)+0.001,ERROR.TYPE(0)),ERROR.TYPE(0))))))))))) -> 2.007 | B40: Interface unit for Fire Suppression System | C40: 3 | D40: No | E40: =Elec_Est!E8214 -> 98.17 | F40: =IFERROR($C40*E40,E40) -> 294.51
A41: =IFERROR(IF(OFFSET(A41,-1,0)>0,OFFSET(A41,-1,0)+0.001,ERROR.TYPE(0)),IFERROR(IF(OFFSET(A41,-2,0)>0,OFFSET(A41,-2,0)+0.001,ERROR.TYPE(0)),IFERROR(IF(OFFSET(A41,-3,0)>0,OFFSET(A41,-3,0)+0.001,ERROR.TYPE(0)),IFERROR(IF(OFFSET(A41,-4,0)>0,OFFSET(A41,-4,0)+0.001,ERROR.TYPE(0)),IFERROR(IF(OFFSET(A41,-5,0)>0,OFFSET(A41,-5,0)+0.001,ERROR.TYPE(0)),IFERROR(IF(OFFSET(A41,-6,0)>0,OFFSET(A41,-6,0)+0.001,ERROR.TYPE(0)),IFERROR(IF(OFFSET(A41,-7,0)>0,OFFSET(A41,-7,0)+0.001,ERROR.TYPE(0)),IFERROR(IF(OFFSET(A41,-8,0)>0,OFFSET(A41,-8,0)+0.001,ERROR.TYPE(0)),IFERROR(IF(OFFSET(A41,-9,0)>0,OFFSET(A41,-9,0)+0.001,ERROR.TYPE(0)),IFERROR(IF(OFFSET(A41,-10,0)>0,OFFSET(A41,-10,0)+0.001,ERROR.TYPE(0)),ERROR.TYPE(0))))))))))) -> 2.008 | B41: Interface unit for VCP | C41: 1 | D41: No | E41: =Elec_Est!E8221 -> 98.17 | F41: =IFERROR($C41*E41,E41) -> 98.17
A42: =IFERROR(IF(OFFSET(A42,-1,0)>0,OFFSET(A42,-1,0)+0.001,ERROR.TYPE(0)),IFERROR(IF(OFFSET(A42,-2,0)>0,OFFSET(A42,-2,0)+0.001,ERROR.TYPE(0)),IFERROR(IF(OFFSET(A42,-3,0)>0,OFFSET(A42,-3,0)+0.001,ERROR.TYPE(0)),IFERROR(IF(OFFSET(A42,-4,0)>0,OFFSET(A42,-4,0)+0.001,ERROR.TYPE(0)),IFERROR(IF(OFFSET(A42,-5,0)>0,OFFSET(A42,-5,0)+0.001,ERROR.TYPE(0)),IFERROR(IF(OFFSET(A42,-6,0)>0,OFFSET(A42,-6,0)+0.001,ERROR.TYPE(0)),IFERROR(IF(OFFSET(A42,-7,0)>0,OFFSET(A42,-7,0)+0.001,ERROR.TYPE(0)),IFERROR(IF(OFFSET(A42,-8,0)>0,OFFSET(A42,-8,0)+0.001,ERROR.TYPE(0)),IFERROR(IF(OFFSET(A42,-9,0)>0,OFFSET(A42,-9,0)+0.001,ERROR.TYPE(0)),IFERROR(IF(OFFSET(A42,-10,0)>0,OFFSET(A42,-10,0)+0.001,ERROR.TYPE(0)),ERROR.TYPE(0))))))))))) -> 2.009 | B42: Interface unit for DB-EV | C42: 1 | D42: No | E42: =Elec_Est!E8228 -> 98.17 | F42: =IFERROR($C42*E42,E42) -> 98.17
B43: Wiring of the following fire alarm points from the Fire alarm panel, using fire proof cable clipped directly to the wall / ceiling or through conduits, as per specification
A44: =IFERROR(IF(OFFSET(A44,-1,0)>0,OFFSET(A44,-1,0)+0.001,ERROR.TYPE(0)),IFERROR(IF(OFFSET(A44,-2,0)>0,OFFSET(A44,-2,0)+0.001,ERROR.TYPE(0)),IFERROR(IF(OFFSET(A44,-3,0)>0,OFFSET(A44,-3,0)+0.001,ERROR.TYPE(0)),IFERROR(IF(OFFSET(A44,-4,0)>0,OFFSET(A44,-4,0)+0.001,ERROR.TYPE(0)),IFERROR(IF(OFFSET(A44,-5,0)>0,OFFSET(A44,-5,0)+0.001,ERROR.TYPE(0)),IFERROR(IF(OFFSET(A44,-6,0)>0,OFFSET(A44,-6,0)+0.001,ERROR.TYPE(0)),IFERROR(IF(OFFSET(A44,-7,0)>0,OFFSET(A44,-7,0)+0.001,ERROR.TYPE(0)),IFERROR(IF(OFFSET(A44,-8,0)>0,OFFSET(A44,-8,0)+0.001,ERROR.TYPE(0)),IFERROR(IF(OFFSET(A44,-9,0)>0,OFFSET(A44,-9,0)+0.001,ERROR.TYPE(0)),IFERROR(IF(OFFSET(A44,-10,0)>0,OFFSET(A44,-10,0)+0.001,ERROR.TYPE(0)),ERROR.TYPE(0))))))))))) -> 2.01 | B44: Optical smoke detector | C44: 14 | D44: No | E44: =Elec_Est!E8239 -> 36.95 | F44: =IFERROR($C44*E44,E44) -> 517.3
A45: =IFERROR(IF(OFFSET(A45,-1,0)>0,OFFSET(A45,-1,0)+0.001,ERROR.TYPE(0)),IFERROR(IF(OFFSET(A45,-2,0)>0,OFFSET(A45,-2,0)+0.001,ERROR.TYPE(0)),IFERROR(IF(OFFSET(A45,-3,0)>0,OFFSET(A45,-3,0)+0.001,ERROR.TYPE(0)),IFERROR(IF(OFFSET(A45,-4,0)>0,OFFSET(A45,-4,0)+0.001,ERROR.TYPE(0)),IFERROR(IF(OFFSET(A45,-5,0)>0,OFFSET(A45,-5,0)+0.001,ERROR.TYPE(0)),IFERROR(IF(OFFSET(A45,-6,0)>0,OFFSET(A45,-6,0)+0.001,ERROR.TYPE(0)),IFERROR(IF(OFFSET(A45,-7,0)>0,OFFSET(A45,-7,0)+0.001,ERROR.TYPE(0)),IFERROR(IF(OFFSET(A45,-8,0)>0,OFFSET(A45,-8,0)+0.001,ERROR.TYPE(0)),IFERROR(IF(OFFSET(A45,-9,0)>0,OFFSET(A45,-9,0)+0.001,ERROR.TYPE(0)),IFERROR(IF(OFFSET(A45,-10,0)>0,OFFSET(A45,-10,0)+0.001,ERROR.TYPE(0)),ERROR.TYPE(0))))))))))) -> 2.011 | B45: Combined optical smoke detector c/w internal sounder & flashing beacon | C45: 5 | D45: No | E45: =Elec_Est!E8245 -> 36.95 | F45: =IFERROR($C45*E45,E45) -> 184.75
A46: =IFERROR(IF(OFFSET(A46,-1,0)>0,OFFSET(A46,-1,0)+0.001,ERROR.TYPE(0)),IFERROR(IF(OFFSET(A46,-2,0)>0,OFFSET(A46,-2,0)+0.001,ERROR.TYPE(0)),IFERROR(IF(OFFSET(A46,-3,0)>0,OFFSET(A46,-3,0)+0.001,ERROR.TYPE(0)),IFERROR(IF(OFFSET(A46,-4,0)>0,OFFSET(A46,-4,0)+0.001,ERROR.TYPE(0)),IFERROR(IF(OFFSET(A46,-5,0)>0,OFFSET(A46,-5,0)+0.001,ERROR.TYPE(0)),IFERROR(IF(OFFSET(A46,-6,0)>0,OFFSET(A46,-6,0)+0.001,ERROR.TYPE(0)),IFERROR(IF(OFFSET(A46,-7,0)>0,OFFSET(A46,-7,0)+0.001,ERROR.TYPE(0)),IFERROR(IF(OFFSET(A46,-8,0)>0,OFFSET(A46,-8,0)+0.001,ERROR.TYPE(0)),IFERROR(IF(OFFSET(A46,-9,0)>0,OFFSET(A46,-9,0)+0.001,ERROR.TYPE(0)),IFERROR(IF(OFFSET(A46,-10,0)>0,OFFSET(A46,-10,0)+0.001,ERROR.TYPE(0)),ERROR.TYPE(0))))))))))) -> 2.012 | B46: Rate of rise heat detector | C46: 77 | D46: No | E46: =Elec_Est!E8251 -> 36.95 | F46: =IFERROR($C46*E46,E46) -> 2845.15
A47: =IFERROR(IF(OFFSET(A47,-1,0)>0,OFFSET(A47,-1,0)+0.001,ERROR.TYPE(0)),IFERROR(IF(OFFSET(A47,-2,0)>0,OFFSET(A47,-2,0)+0.001,ERROR.TYPE(0)),IFERROR(IF(OFFSET(A47,-3,0)>0,OFFSET(A47,-3,0)+0.001,ERROR.TYPE(0)),IFERROR(IF(OFFSET(A47,-4,0)>0,OFFSET(A47,-4,0)+0.001,ERROR.TYPE(0)),IFERROR(IF(OFFSET(A47,-5,0)>0,OFFSET(A47,-5,0)+0.001,ERROR.TYPE(0)),IFERROR(IF(OFFSET(A47,-6,0)>0,OFFSET(A47,-6,0)+0.001,ERROR.TYPE(0)),IFERROR(IF(OFFSET(A47,-7,0)>0,OFFSET(A47,-7,0)+0.001,ERROR.TYPE(0)),IFERROR(IF(OFFSET(A47,-8,0)>0,OFFSET(A47,-8,0)+0.001,ERROR.TYPE(0)),IFERROR(IF(OFFSET(A47,-9,0)>0,OFFSET(A47,-9,0)+0.001,ERROR.TYPE(0)),IFERROR(IF(OFFSET(A47,-10,0)>0,OFFSET(A47,-10,0)+0.001,ERROR.TYPE(0)),ERROR.TYPE(0))))))))))) -> 2.013 | B47: Combined rate of rise heat detector c/w internal sounder & flashing beacon | C47: 8 | D47: No | E47: =Elec_Est!E8257 -> 36.95 | F47: =IFERROR($C47*E47,E47) -> 295.6
A48: =IFERROR(IF(OFFSET(A48,-1,0)>0,OFFSET(A48,-1,0)+0.001,ERROR.TYPE(0)),IFERROR(IF(OFFSET(A48,-2,0)>0,OFFSET(A48,-2,0)+0.001,ERROR.TYPE(0)),IFERROR(IF(OFFSET(A48,-3,0)>0,OFFSET(A48,-3,0)+0.001,ERROR.TYPE(0)),IFERROR(IF(OFFSET(A48,-4,0)>0,OFFSET(A48,-4,0)+0.001,ERROR.TYPE(0)),IFERROR(IF(OFFSET(A48,-5,0)>0,OFFSET(A48,-5,0)+0.001,ERROR.TYPE(0)),IFERROR(IF(OFFSET(A48,-6,0)>0,OFFSET(A48,-6,0)+0.001,ERROR.TYPE(0)),IFERROR(IF(OFFSET(A48,-7,0)>0,OFFSET(A48,-7,0)+0.001,ERROR.TYPE(0)),IFERROR(IF(OFFSET(A48,-8,0)>0,OFFSET(A48,-8,0)+0.001,ERROR.TYPE(0)),IFERROR(IF(OFFSET(A48,-9,0)>0,OFFSET(A48,-9,0)+0.001,ERROR.TYPE(0)),IFERROR(IF(OFFSET(A48,-10,0)>0,OFFSET(A48,-10,0)+0.001,ERROR.TYPE(0)),ERROR.TYPE(0))))))))))) -> 2.014 | B48: Manual call point | C48: 2 | D48: No | E48: =Elec_Est!E8263 -> 36.95 | F48: =IFERROR($C48*E48,E48) -> 73.9
A49: =IFERROR(IF(OFFSET(A49,-1,0)>0,OFFSET(A49,-1,0)+0.001,ERROR.TYPE(0)),IFERROR(IF(OFFSET(A49,-2,0)>0,OFFSET(A49,-2,0)+0.001,ERROR.TYPE(0)),IFERROR(IF(OFFSET(A49,-3,0)>0,OFFSET(A49,-3,0)+0.001,ERROR.TYPE(0)),IFERROR(IF(OFFSET(A49,-4,0)>0,OFFSET(A49,-4,0)+0.001,ERROR.TYPE(0)),IFERROR(IF(OFFSET(A49,-5,0)>0,OFFSET(A49,-5,0)+0.001,ERROR.TYPE(0)),IFERROR(IF(OFFSET(A49,-6,0)>0,OFFSET(A49,-6,0)+0.001,ERROR.TYPE(0)),IFERROR(IF(OFFSET(A49,-7,0)>0,OFFSET(A49,-7,0)+0.001,ERROR.TYPE(0)),IFERROR(IF(OFFSET(A49,-8,0)>0,OFFSET(A49,-8,0)+0.001,ERROR.TYPE(0)),IFERROR(IF(OFFSET(A49,-9,0)>0,OFFSET(A49,-9,0)+0.001,ERROR.TYPE(0)),IFERROR(IF(OFFSET(A49,-10,0)>0,OFFSET(A49,-10,0)+0.001,ERROR.TYPE(0)),ERROR.TYPE(0))))))))))) -> 2.015 | B49: Interface unit for Zone Assembly Valve | C49: 1 | D49: No | E49: =Elec_Est!E8269 -> 36.95 | F49: =IFERROR($C49*E49,E49) -> 36.95
A50: =IFERROR(IF(OFFSET(A50,-1,0)>0,OFFSET(A50,-1,0)+0.001,ERROR.TYPE(0)),IFERROR(IF(OFFSET(A50,-2,0)>0,OFFSET(A50,-2,0)+0.001,ERROR.TYPE(0)),IFERROR(IF(OFFSET(A50,-3,0)>0,OFFSET(A50,-3,0)+0.001,ERROR.TYPE(0)),IFERROR(IF(OFFSET(A50,-4,0)>0,OFFSET(A50,-4,0)+0.001,ERROR.TYPE(0)),IFERROR(IF(OFFSET(A50,-5,0)>0,OFFSET(A50,-5,0)+0.001,ERROR.TYPE(0)),IFERROR(IF(OFFSET(A50,-6,0)>0,OFFSET(A50,-6,0)+0.001,ERROR.TYPE(0)),IFERROR(IF(OFFSET(A50,-7,0)>0,OFFSET(A50,-7,0)+0.001,ERROR.TYPE(0)),IFERROR(IF(OFFSET(A50,-8,0)>0,OFFSET(A50,-8,0)+0.001,ERROR.TYPE(0)),IFERROR(IF(OFFSET(A50,-9,0)>0,OFFSET(A50,-9,0)+0.001,ERROR.TYPE(0)),IFERROR(IF(OFFSET(A50,-10,0)>0,OFFSET(A50,-10,0)+0.001,ERROR.TYPE(0)),ERROR.TYPE(0))))))))))) -> 2.016 | B50: Interface unit for Fire Suppression System | C50: 3 | D50: No | E50: =Elec_Est!E8275 -> 36.95 | F50: =IFERROR($C50*E50,E50) -> 110.85
A51: =IFERROR(IF(OFFSET(A51,-1,0)>0,OFFSET(A51,-1,0)+0.001,ERROR.TYPE(0)),IFERROR(IF(OFFSET(A51,-2,0)>0,OFFSET(A51,-2,0)+0.001,ERROR.TYPE(0)),IFERROR(IF(OFFSET(A51,-3,0)>0,OFFSET(A51,-3,0)+0.001,ERROR.TYPE(0)),IFERROR(IF(OFFSET(A51,-4,0)>0,OFFSET(A51,-4,0)+0.001,ERROR.TYPE(0)),IFERROR(IF(OFFSET(A51,-5,0)>0,OFFSET(A51,-5,0)+0.001,ERROR.TYPE(0)),IFERROR(IF(OFFSET(A51,-6,0)>0,OFFSET(A51,-6,0)+0.001,ERROR.TYPE(0)),IFERROR(IF(OFFSET(A51,-7,0)>0,OFFSET(A51,-7,0)+0.001,ERROR.TYPE(0)),IFERROR(IF(OFFSET(A51,-8,0)>0,OFFSET(A51,-8,0)+0.001,ERROR.TYPE(0)),IFERROR(IF(OFFSET(A51,-9,0)>0,OFFSET(A51,-9,0)+0.001,ERROR.TYPE(0)),IFERROR(IF(OFFSET(A51,-10,0)>0,OFFSET(A51,-10,0)+0.001,ERROR.TYPE(0)),ERROR.TYPE(0))))))))))) -> 2.017 | B51: Interface unit for VCP | C51: 1 | D51: No | E51: =Elec_Est!E8281 -> 36.95 | F51: =IFERROR($C51*E51,E51) -> 36.95
A52: =IFERROR(IF(OFFSET(A52,-1,0)>0,OFFSET(A52,-1,0)+0.001,ERROR.TYPE(0)),IFERROR(IF(OFFSET(A52,-2,0)>0,OFFSET(A52,-2,0)+0.001,ERROR.TYPE(0)),IFERROR(IF(OFFSET(A52,-3,0)>0,OFFSET(A52,-3,0)+0.001,ERROR.TYPE(0)),IFERROR(IF(OFFSET(A52,-4,0)>0,OFFSET(A52,-4,0)+0.001,ERROR.TYPE(0)),IFERROR(IF(OFFSET(A52,-5,0)>0,OFFSET(A52,-5,0)+0.001,ERROR.TYPE(0)),IFERROR(IF(OFFSET(A52,-6,0)>0,OFFSET(A52,-6,0)+0.001,ERROR.TYPE(0)),IFERROR(IF(OFFSET(A52,-7,0)>0,OFFSET(A52,-7,0)+0.001,ERROR.TYPE(0)),IFERROR(IF(OFFSET(A52,-8,0)>0,OFFSET(A52,-8,0)+0.001,ERROR.TYPE(0)),IFERROR(IF(OFFSET(A52,-9,0)>0,OFFSET(A52,-9,0)+0.001,ERROR.TYPE(0)),IFERROR(IF(OFFSET(A52,-10,0)>0,OFFSET(A52,-10,0)+0.001,ERROR.TYPE(0)),ERROR.TYPE(0))))))))))) -> 2.018 | B52: Interface unit for DB-EV | C52: 1 | D52: No | E52: =Elec_Est!E8287 -> 36.95 | F52: =IFERROR($C52*E52,E52) -> 36.95
B53: Supply, install and connect of the following equipment:
A54: =IFERROR(IF(OFFSET(A54,-1,0)>0,OFFSET(A54,-1,0)+0.001,ERROR.TYPE(0)),IFERROR(IF(OFFSET(A54,-2,0)>0,OFFSET(A54,-2,0)+0.001,ERROR.TYPE(0)),IFERROR(IF(OFFSET(A54,-3,0)>0,OFFSET(A54,-3,0)+0.001,ERROR.TYPE(0)),IFERROR(IF(OFFSET(A54,-4,0)>0,OFFSET(A54,-4,0)+0.001,ERROR.TYPE(0)),IFERROR(IF(OFFSET(A54,-5,0)>0,OFFSET(A54,-5,0)+0.001,ERROR.TYPE(0)),IFERROR(IF(OFFSET(A54,-6,0)>0,OFFSET(A54,-6,0)+0.001,ERROR.TYPE(0)),IFERROR(IF(OFFSET(A54,-7,0)>0,OFFSET(A54,-7,0)+0.001,ERROR.TYPE(0)),IFERROR(IF(OFFSET(A54,-8,0)>0,OFFSET(A54,-8,0)+0.001,ERROR.TYPE(0)),IFERROR(IF(OFFSET(A54,-9,0)>0,OFFSET(A54,-9,0)+0.001,ERROR.TYPE(0)),IFERROR(IF(OFFSET(A54,-10,0)>0,OFFSET(A54,-10,0)+0.001,ERROR.TYPE(0)),ERROR.TYPE(0))))))))))) -> 2.019 | B54: Optical smoke detector | C54: 14 | D54: No | E54: =Elec_Est!E8297 -> 52.23 | F54: =IFERROR($C54*E54,E54) -> 731.22
A55: =IFERROR(IF(OFFSET(A55,-1,0)>0,OFFSET(A55,-1,0)+0.001,ERROR.TYPE(0)),IFERROR(IF(OFFSET(A55,-2,0)>0,OFFSET(A55,-2,0)+0.001,ERROR.TYPE(0)),IFERROR(IF(OFFSET(A55,-3,0)>0,OFFSET(A55,-3,0)+0.001,ERROR.TYPE(0)),IFERROR(IF(OFFSET(A55,-4,0)>0,OFFSET(A55,-4,0)+0.001,ERROR.TYPE(0)),IFERROR(IF(OFFSET(A55,-5,0)>0,OFFSET(A55,-5,0)+0.001,ERROR.TYPE(0)),IFERROR(IF(OFFSET(A55,-6,0)>0,OFFSET(A55,-6,0)+0.001,ERROR.TYPE(0)),IFERROR(IF(OFFSET(A55,-7,0)>0,OFFSET(A55,-7,0)+0.001,ERROR.TYPE(0)),IFERROR(IF(OFFSET(A55,-8,0)>0,OFFSET(A55,-8,0)+0.001,ERROR.TYPE(0)),IFERROR(IF(OFFSET(A55,-9,0)>0,OFFSET(A55,-9,0)+0.001,ERROR.TYPE(0)),IFERROR(IF(OFFSET(A55,-10,0)>0,OFFSET(A55,-10,0)+0.001,ERROR.TYPE(0)),ERROR.TYPE(0))))))))))) -> 2.02 | B55: Combined optical smoke detector c/w internal sounder & flashing beacon | C55: 5 | D55: No | E55: =Elec_Est!E8303 -> 93.61 | F55: =IFERROR($C55*E55,E55) -> 468.05
A56: =IFERROR(IF(OFFSET(A56,-1,0)>0,OFFSET(A56,-1,0)+0.001,ERROR.TYPE(0)),IFERROR(IF(OFFSET(A56,-2,0)>0,OFFSET(A56,-2,0)+0.001,ERROR.TYPE(0)),IFERROR(IF(OFFSET(A56,-3,0)>0,OFFSET(A56,-3,0)+0.001,ERROR.TYPE(0)),IFERROR(IF(OFFSET(A56,-4,0)>0,OFFSET(A56,-4,0)+0.001,ERROR.TYPE(0)),IFERROR(IF(OFFSET(A56,-5,0)>0,OFFSET(A56,-5,0)+0.001,ERROR.TYPE(0)),IFERROR(IF(OFFSET(A56,-6,0)>0,OFFSET(A56,-6,0)+0.001,ERROR.TYPE(0)),IFERROR(IF(OFFSET(A56,-7,0)>0,OFFSET(A56,-7,0)+0.001,ERROR.TYPE(0)),IFERROR(IF(OFFSET(A56,-8,0)>0,OFFSET(A56,-8,0)+0.001,ERROR.TYPE(0)),IFERROR(IF(OFFSET(A56,-9,0)>0,OFFSET(A56,-9,0)+0.001,ERROR.TYPE(0)),IFERROR(IF(OFFSET(A56,-10,0)>0,OFFSET(A56,-10,0)+0.001,ERROR.TYPE(0)),ERROR.TYPE(0))))))))))) -> 2.021 | B56: Rate of rise heat detector | C56: 77 | D56: No | E56: =Elec_Est!E8309 -> 51.24 | F56: =IFERROR($C56*E56,E56) -> 3945.48
A57: =IFERROR(IF(OFFSET(A57,-1,0)>0,OFFSET(A57,-1,0)+0.001,ERROR.TYPE(0)),IFERROR(IF(OFFSET(A57,-2,0)>0,OFFSET(A57,-2,0)+0.001,ERROR.TYPE(0)),IFERROR(IF(OFFSET(A57,-3,0)>0,OFFSET(A57,-3,0)+0.001,ERROR.TYPE(0)),IFERROR(IF(OFFSET(A57,-4,0)>0,OFFSET(A57,-4,0)+0.001,ERROR.TYPE(0)),IFERROR(IF(OFFSET(A57,-5,0)>0,OFFSET(A57,-5,0)+0.001,ERROR.TYPE(0)),IFERROR(IF(OFFSET(A57,-6,0)>0,OFFSET(A57,-6,0)+0.001,ERROR.TYPE(0)),IFERROR(IF(OFFSET(A57,-7,0)>0,OFFSET(A57,-7,0)+0.001,ERROR.TYPE(0)),IFERROR(IF(OFFSET(A57,-8,0)>0,OFFSET(A57,-8,0)+0.001,ERROR.TYPE(0)),IFERROR(IF(OFFSET(A57,-9,0)>0,OFFSET(A57,-9,0)+0.001,ERROR.TYPE(0)),IFERROR(IF(OFFSET(A57,-10,0)>0,OFFSET(A57,-10,0)+0.001,ERROR.TYPE(0)),ERROR.TYPE(0))))))))))) -> 2.022 | B57: Combined rate of rise heat detector c/w internal sounder & flashing beacon | C57: 8 | D57: No | E57: =Elec_Est!E8315 -> 92.63 | F57: =IFERROR($C57*E57,E57) -> 741.04
A58: =IFERROR(IF(OFFSET(A58,-1,0)>0,OFFSET(A58,-1,0)+0.001,ERROR.TYPE(0)),IFERROR(IF(OFFSET(A58,-2,0)>0,OFFSET(A58,-2,0)+0.001,ERROR.TYPE(0)),IFERROR(IF(OFFSET(A58,-3,0)>0,OFFSET(A58,-3,0)+0.001,ERROR.TYPE(0)),IFERROR(IF(OFFSET(A58,-4,0)>0,OFFSET(A58,-4,0)+0.001,ERROR.TYPE(0)),IFERROR(IF(OFFSET(A58,-5,0)>0,OFFSET(A58,-5,0)+0.001,ERROR.TYPE(0)),IFERROR(IF(OFFSET(A58,-6,0)>0,OFFSET(A58,-6,0)+0.001,ERROR.TYPE(0)),IFERROR(IF(OFFSET(A58,-7,0)>0,OFFSET(A58,-7,0)+0.001,ERROR.TYPE(0)),IFERROR(IF(OFFSET(A58,-8,0)>0,OFFSET(A58,-8,0)+0.001,ERROR.TYPE(0)),IFERROR(IF(OFFSET(A58,-9,0)>0,OFFSET(A58,-9,0)+0.001,ERROR.TYPE(0)),IFERROR(IF(OFFSET(A58,-10,0)>0,OFFSET(A58,-10,0)+0.001,ERROR.TYPE(0)),ERROR.TYPE(0))))))))))) -> 2.023 | B58: Manual call point c/w cover | C58: 2 | D58: No | E58: =Elec_Est!E8321 -> 54.2 | F58: =IFERROR($C58*E58,E58) -> 108.4
A59: =IFERROR(IF(OFFSET(A59,-1,0)>0,OFFSET(A59,-1,0)+0.001,ERROR.TYPE(0)),IFERROR(IF(OFFSET(A59,-2,0)>0,OFFSET(A59,-2,0)+0.001,ERROR.TYPE(0)),IFERROR(IF(OFFSET(A59,-3,0)>0,OFFSET(A59,-3,0)+0.001,ERROR.TYPE(0)),IFERROR(IF(OFFSET(A59,-4,0)>0,OFFSET(A59,-4,0)+0.001,ERROR.TYPE(0)),IFERROR(IF(OFFSET(A59,-5,0)>0,OFFSET(A59,-5,0)+0.001,ERROR.TYPE(0)),IFERROR(IF(OFFSET(A59,-6,0)>0,OFFSET(A59,-6,0)+0.001,ERROR.TYPE(0)),IFERROR(IF(OFFSET(A59,-7,0)>0,OFFSET(A59,-7,0)+0.001,ERROR.TYPE(0)),IFERROR(IF(OFFSET(A59,-8,0)>0,OFFSET(A59,-8,0)+0.001,ERROR.TYPE(0)),IFERROR(IF(OFFSET(A59,-9,0)>0,OFFSET(A59,-9,0)+0.001,ERROR.TYPE(0)),IFERROR(IF(OFFSET(A59,-10,0)>0,OFFSET(A59,-10,0)+0.001,ERROR.TYPE(0)),ERROR.TYPE(0))))))))))) -> 2.024 | B59: Interface unit for Zone Assembly Valve | C59: 1 | D59: No | E59: =Elec_Est!E8327 -> 77.85 | F59: =IFERROR($C59*E59,E59) -> 77.85
A60: =IFERROR(IF(OFFSET(A60,-1,0)>0,OFFSET(A60,-1,0)+0.001,ERROR.TYPE(0)),IFERROR(IF(OFFSET(A60,-2,0)>0,OFFSET(A60,-2,0)+0.001,ERROR.TYPE(0)),IFERROR(IF(OFFSET(A60,-3,0)>0,OFFSET(A60,-3,0)+0.001,ERROR.TYPE(0)),IFERROR(IF(OFFSET(A60,-4,0)>0,OFFSET(A60,-4,0)+0.001,ERROR.TYPE(0)),IFERROR(IF(OFFSET(A60,-5,0)>0,OFFSET(A60,-5,0)+0.001,ERROR.TYPE(0)),IFERROR(IF(OFFSET(A60,-6,0)>0,OFFSET(A60,-6,0)+0.001,ERROR.TYPE(0)),IFERROR(IF(OFFSET(A60,-7,0)>0,OFFSET(A60,-7,0)+0.001,ERROR.TYPE(0)),IFERROR(IF(OFFSET(A60,-8,0)>0,OFFSET(A60,-8,0)+0.001,ERROR.TYPE(0)),IFERROR(IF(OFFSET(A60,-9,0)>0,OFFSET(A60,-9,0)+0.001,ERROR.TYPE(0)),IFERROR(IF(OFFSET(A60,-10,0)>0,OFFSET(A60,-10,0)+0.001,ERROR.TYPE(0)),ERROR.TYPE(0))))))))))) -> 2.025 | B60: Interface unit for Fire Suppression System | C60: 3 | D60: No | E60: =Elec_Est!E8333 -> 77.85 | F60: =IFERROR($C60*E60,E60) -> 233.55
A61: =IFERROR(IF(OFFSET(A61,-1,0)>0,OFFSET(A61,-1,0)+0.001,ERROR.TYPE(0)),IFERROR(IF(OFFSET(A61,-2,0)>0,OFFSET(A61,-2,0)+0.001,ERROR.TYPE(0)),IFERROR(IF(OFFSET(A61,-3,0)>0,OFFSET(A61,-3,0)+0.001,ERROR.TYPE(0)),IFERROR(IF(OFFSET(A61,-4,0)>0,OFFSET(A61,-4,0)+0.001,ERROR.TYPE(0)),IFERROR(IF(OFFSET(A61,-5,0)>0,OFFSET(A61,-5,0)+0.001,ERROR.TYPE(0)),IFERROR(IF(OFFSET(A61,-6,0)>0,OFFSET(A61,-6,0)+0.001,ERROR.TYPE(0)),IFERROR(IF(OFFSET(A61,-7,0)>0,OFFSET(A61,-7,0)+0.001,ERROR.TYPE(0)),IFERROR(IF(OFFSET(A61,-8,0)>0,OFFSET(A61,-8,0)+0.001,ERROR.TYPE(0)),IFERROR(IF(OFFSET(A61,-9,0)>0,OFFSET(A61,-9,0)+0.001,ERROR.TYPE(0)),IFERROR(IF(OFFSET(A61,-10,0)>0,OFFSET(A61,-10,0)+0.001,ERROR.TYPE(0)),ERROR.TYPE(0))))))))))) -> 2.026 | B61: Interface unit for VCP | C61: 1 | D61: No | E61: =Elec_Est!E8339 -> 77.85 | F61: =IFERROR($C61*E61,E61) -> 77.85
A62: =IFERROR(IF(OFFSET(A62,-1,0)>0,OFFSET(A62,-1,0)+0.001,ERROR.TYPE(0)),IFERROR(IF(OFFSET(A62,-2,0)>0,OFFSET(A62,-2,0)+0.001,ERROR.TYPE(0)),IFERROR(IF(OFFSET(A62,-3,0)>0,OFFSET(A62,-3,0)+0.001,ERROR.TYPE(0)),IFERROR(IF(OFFSET(A62,-4,0)>0,OFFSET(A62,-4,0)+0.001,ERROR.TYPE(0)),IFERROR(IF(OFFSET(A62,-5,0)>0,OFFSET(A62,-5,0)+0.001,ERROR.TYPE(0)),IFERROR(IF(OFFSET(A62,-6,0)>0,OFFSET(A62,-6,0)+0.001,ERROR.TYPE(0)),IFERROR(IF(OFFSET(A62,-7,0)>0,OFFSET(A62,-7,0)+0.001,ERROR.TYPE(0)),IFERROR(IF(OFFSET(A62,-8,0)>0,OFFSET(A62,-8,0)+0.001,ERROR.TYPE(0)),IFERROR(IF(OFFSET(A62,-9,0)>0,OFFSET(A62,-9,0)+0.001,ERROR.TYPE(0)),IFERROR(IF(OFFSET(A62,-10,0)>0,OFFSET(A62,-10,0)+0.001,ERROR.TYPE(0)),ERROR.TYPE(0))))))))))) -> 2.027 | B62: Interface unit for DB-EV | C62: 1 | D62: No | E62: =Elec_Est!E8345 -> 88.04 | F62: =IFERROR($C62*E62,E62) -> 88.04
B63: TOTAL FOR PAGE 03 | C63: Euro Exc VAT | F63: =SUM(F31:F62) -> 21604.92
A66: ITEM | B66: DESCRIPTION | C66: QTY | D66: UNIT | E66: RATE Euro (Exc of VAT) | F66: TOTAL Euro (Exc of VAT)
B67: Basement Level -1 - FAP2
B68: Supply and install galvanised conduit surface mounted from fire alarm panel via galvanised trunking to the following fire alarm points.
A69: =IFERROR(IF(OFFSET(A69,-1,0)>0,OFFSET(A69,-1,0)+0.001,ERROR.TYPE(0)),IFERROR(IF(OFFSET(A69,-2,0)>0,OFFSET(A69,-2,0)+0.001,ERROR.TYPE(0)),IFERROR(IF(OFFSET(A69,-3,0)>0,OFFSET(A69,-3,0)+0.001,ERROR.TYPE(0)),IFERROR(IF(OFFSET(A69,-4,0)>0,OFFSET(A69,-4,0)+0.001,ERROR.TYPE(0)),IFERROR(IF(OFFSET(A69,-5,0)>0,OFFSET(A69,-5,0)+0.001,ERROR.TYPE(0)),IFERROR(IF(OFFSET(A69,-6,0)>0,OFFSET(A69,-6,0)+0.001,ERROR.TYPE(0)),IFERROR(IF(OFFSET(A69,-7,0)>0,OFFSET(A69,-7,0)+0.001,ERROR.TYPE(0)),IFERROR(IF(OFFSET(A69,-8,0)>0,OFFSET(A69,-8,0)+0.001,ERROR.TYPE(0)),IFERROR(IF(OFFSET(A69,-9,0)>0,OFFSET(A69,-9,0)+0.001,ERROR.TYPE(0)),IFERROR(IF(OFFSET(A69,-10,0)>0,OFFSET(A69,-10,0)+0.001,ERROR.TYPE(0)),ERROR.TYPE(0))))))))))) -> 2.028 | B69: Optical smoke detector | C69: 8 | D69: No | E69: =Elec_Est!E8365 -> 98.17 | F69: =IFERROR($C69*E69,E69) -> 785.36
A70: =IFERROR(IF(OFFSET(A70,-1,0)>0,OFFSET(A70,-1,0)+0.001,ERROR.TYPE(0)),IFERROR(IF(OFFSET(A70,-2,0)>0,OFFSET(A70,-2,0)+0.001,ERROR.TYPE(0)),IFERROR(IF(OFFSET(A70,-3,0)>0,OFFSET(A70,-3,0)+0.001,ERROR.TYPE(0)),IFERROR(IF(OFFSET(A70,-4,0)>0,OFFSET(A70,-4,0)+0.001,ERROR.TYPE(0)),IFERROR(IF(OFFSET(A70,-5,0)>0,OFFSET(A70,-5,0)+0.001,ERROR.TYPE(0)),IFERROR(IF(OFFSET(A70,-6,0)>0,OFFSET(A70,-6,0)+0.001,ERROR.TYPE(0)),IFERROR(IF(OFFSET(A70,-7,0)>0,OFFSET(A70,-7,0)+0.001,ERROR.TYPE(0)),IFERROR(IF(OFFSET(A70,-8,0)>0,OFFSET(A70,-8,0)+0.001,ERROR.TYPE(0)),IFERROR(IF(OFFSET(A70,-9,0)>0,OFFSET(A70,-9,0)+0.001,ERROR.TYPE(0)),IFERROR(IF(OFFSET(A70,-10,0)>0,OFFSET(A70,-10,0)+0.001,ERROR.TYPE(0)),ERROR.TYPE(0))))))))))) -> 2.029 | B70: Combined optical smoke detector c/w internal sounder & flashing beacon | C70: 5 | D70: No | E70: =Elec_Est!E8372 -> 98.17 | F70: =IFERROR($C70*E70,E70) -> 490.85
A71: =IFERROR(IF(OFFSET(A71,-1,0)>0,OFFSET(A71,-1,0)+0.001,ERROR.TYPE(0)),IFERROR(IF(OFFSET(A71,-2,0)>0,OFFSET(A71,-2,0)+0.001,ERROR.TYPE(0)),IFERROR(IF(OFFSET(A71,-3,0)>0,OFFSET(A71,-3,0)+0.001,ERROR.TYPE(0)),IFERROR(IF(OFFSET(A71,-4,0)>0,OFFSET(A71,-4,0)+0.001,ERROR.TYPE(0)),IFERROR(IF(OFFSET(A71,-5,0)>0,OFFSET(A71,-5,0)+0.001,ERROR.TYPE(0)),IFERROR(IF(OFFSET(A71,-6,0)>0,OFFSET(A71,-6,0)+0.001,ERROR.TYPE(0)),IFERROR(IF(OFFSET(A71,-7,0)>0,OFFSET(A71,-7,0)+0.001,ERROR.TYPE(0)),IFERROR(IF(OFFSET(A71,-8,0)>0,OFFSET(A71,-8,0)+0.001,ERROR.TYPE(0)),IFERROR(IF(OFFSET(A71,-9,0)>0,OFFSET(A71,-9,0)+0.001,ERROR.TYPE(0)),IFERROR(IF(OFFSET(A71,-10,0)>0,OFFSET(A71,-10,0)+0.001,ERROR.TYPE(0)),ERROR.TYPE(0))))))))))) -> 2.03 | B71: Rate of rise heat detector | C71: 52 | D71: No | E71: =Elec_Est!E8379 -> 98.17 | F71: =IFERROR($C71*E71,E71) -> 5104.84
A72: =IFERROR(IF(OFFSET(A72,-1,0)>0,OFFSET(A72,-1,0)+0.001,ERROR.TYPE(0)),IFERROR(IF(OFFSET(A72,-2,0)>0,OFFSET(A72,-2,0)+0.001,ERROR.TYPE(0)),IFERROR(IF(OFFSET(A72,-3,0)>0,OFFSET(A72,-3,0)+0.001,ERROR.TYPE(0)),IFERROR(IF(OFFSET(A72,-4,0)>0,OFFSET(A72,-4,0)+0.001,ERROR.TYPE(0)),IFERROR(IF(OFFSET(A72,-5,0)>0,OFFSET(A72,-5,0)+0.001,ERROR.TYPE(0)),IFERROR(IF(OFFSET(A72,-6,0)>0,OFFSET(A72,-6,0)+0.001,ERROR.TYPE(0)),IFERROR(IF(OFFSET(A72,-7,0)>0,OFFSET(A72,-7,0)+0.001,ERROR.TYPE(0)),IFERROR(IF(OFFSET(A72,-8,0)>0,OFFSET(A72,-8,0)+0.001,ERROR.TYPE(0)),IFERROR(IF(OFFSET(A72,-9,0)>0,OFFSET(A72,-9,0)+0.001,ERROR.TYPE(0)),IFERROR(IF(OFFSET(A72,-10,0)>0,OFFSET(A72,-10,0)+0.001,ERROR.TYPE(0)),ERROR.TYPE(0))))))))))) -> 2.031 | B72: Combined rate of rise heat detector c/w internal sounder & flashing beacon | C72: 9 | D72: No | E72: =Elec_Est!E8386 -> 98.17 | F72: =IFERROR($C72*E72,E72) -> 883.53
A73: =IFERROR(IF(OFFSET(A73,-1,0)>0,OFFSET(A73,-1,0)+0.001,ERROR.TYPE(0)),IFERROR(IF(OFFSET(A73,-2,0)>0,OFFSET(A73,-2,0)+0.001,ERROR.TYPE(0)),IFERROR(IF(OFFSET(A73,-3,0)>0,OFFSET(A73,-3,0)+0.001,ERROR.TYPE(0)),IFERROR(IF(OFFSET(A73,-4,0)>0,OFFSET(A73,-4,0)+0.001,ERROR.TYPE(0)),IFERROR(IF(OFFSET(A73,-5,0)>0,OFFSET(A73,-5,0)+0.001,ERROR.TYPE(0)),IFERROR(IF(OFFSET(A73,-6,0)>0,OFFSET(A73,-6,0)+0.001,ERROR.TYPE(0)),IFERROR(IF(OFFSET(A73,-7,0)>0,OFFSET(A73,-7,0)+0.001,ERROR.TYPE(0)),IFERROR(IF(OFFSET(A73,-8,0)>0,OFFSET(A73,-8,0)+0.001,ERROR.TYPE(0)),IFERROR(IF(OFFSET(A73,-9,0)>0,OFFSET(A73,-9,0)+0.001,ERROR.TYPE(0)),IFERROR(IF(OFFSET(A73,-10,0)>0,OFFSET(A73,-10,0)+0.001,ERROR.TYPE(0)),ERROR.TYPE(0))))))))))) -> 2.032 | B73: Manual call point | C73: 1 | D73: No | E73: =Elec_Est!E8393 -> 98.17 | F73: =IFERROR($C73*E73,E73) -> 98.17
A74: =IFERROR(IF(OFFSET(A74,-1,0)>0,OFFSET(A74,-1,0)+0.001,ERROR.TYPE(0)),IFERROR(IF(OFFSET(A74,-2,0)>0,OFFSET(A74,-2,0)+0.001,ERROR.TYPE(0)),IFERROR(IF(OFFSET(A74,-3,0)>0,OFFSET(A74,-3,0)+0.001,ERROR.TYPE(0)),IFERROR(IF(OFFSET(A74,-4,0)>0,OFFSET(A74,-4,0)+0.001,ERROR.TYPE(0)),IFERROR(IF(OFFSET(A74,-5,0)>0,OFFSET(A74,-5,0)+0.001,ERROR.TYPE(0)),IFERROR(IF(OFFSET(A74,-6,0)>0,OFFSET(A74,-6,0)+0.001,ERROR.TYPE(0)),IFERROR(IF(OFFSET(A74,-7,0)>0,OFFSET(A74,-7,0)+0.001,ERROR.TYPE(0)),IFERROR(IF(OFFSET(A74,-8,0)>0,OFFSET(A74,-8,0)+0.001,ERROR.TYPE(0)),IFERROR(IF(OFFSET(A74,-9,0)>0,OFFSET(A74,-9,0)+0.001,ERROR.TYPE(0)),IFERROR(IF(OFFSET(A74,-10,0)>0,OFFSET(A74,-10,0)+0.001,ERROR.TYPE(0)),ERROR.TYPE(0))))))))))) -> 2.033 | B74: Interface unit for Fire Fighting Pump Set | C74: 4 | D74: No | E74: =Elec_Est!E8400 -> 98.17 | F74: =IFERROR($C74*E74,E74) -> 392.68
A75: =IFERROR(IF(OFFSET(A75,-1,0)>0,OFFSET(A75,-1,0)+0.001,ERROR.TYPE(0)),IFERROR(IF(OFFSET(A75,-2,0)>0,OFFSET(A75,-2,0)+0.001,ERROR.TYPE(0)),IFERROR(IF(OFFSET(A75,-3,0)>0,OFFSET(A75,-3,0)+0.001,ERROR.TYPE(0)),IFERROR(IF(OFFSET(A75,-4,0)>0,OFFSET(A75,-4,0)+0.001,ERROR.TYPE(0)),IFERROR(IF(OFFSET(A75,-5,0)>0,OFFSET(A75,-5,0)+0.001,ERROR.TYPE(0)),IFERROR(IF(OFFSET(A75,-6,0)>0,OFFSET(A75,-6,0)+0.001,ERROR.TYPE(0)),IFERROR(IF(OFFSET(A75,-7,0)>0,OFFSET(A75,-7,0)+0.001,ERROR.TYPE(0)),IFERROR(IF(OFFSET(A75,-8,0)>0,OFFSET(A75,-8,0)+0.001,ERROR.TYPE(0)),IFERROR(IF(OFFSET(A75,-9,0)>0,OFFSET(A75,-9,0)+0.001,ERROR.TYPE(0)),IFERROR(IF(OFFSET(A75,-10,0)>0,OFFSET(A75,-10,0)+0.001,ERROR.TYPE(0)),ERROR.TYPE(0))))))))))) -> 2.034 | B75: Interface unit for Sprinkler Pump Set | C75: 4 | D75: No | E75: =Elec_Est!E8407 -> 98.17 | F75: =IFERROR($C75*E75,E75) -> 392.68
A76: =IFERROR(IF(OFFSET(A76,-1,0)>0,OFFSET(A76,-1,0)+0.001,ERROR.TYPE(0)),IFERROR(IF(OFFSET(A76,-2,0)>0,OFFSET(A76,-2,0)+0.001,ERROR.TYPE(0)),IFERROR(IF(OFFSET(A76,-3,0)>0,OFFSET(A76,-3,0)+0.001,ERROR.TYPE(0)),IFERROR(IF(OFFSET(A76,-4,0)>0,OFFSET(A76,-4,0)+0.001,ERROR.TYPE(0)),IFERROR(IF(OFFSET(A76,-5,0)>0,OFFSET(A76,-5,0)+0.001,ERROR.TYPE(0)),IFERROR(IF(OFFSET(A76,-6,0)>0,OFFSET(A76,-6,0)+0.001,ERROR.TYPE(0)),IFERROR(IF(OFFSET(A76,-7,0)>0,OFFSET(A76,-7,0)+0.001,ERROR.TYPE(0)),IFERROR(IF(OFFSET(A76,-8,0)>0,OFFSET(A76,-8,0)+0.001,ERROR.TYPE(0)),IFERROR(IF(OFFSET(A76,-9,0)>0,OFFSET(A76,-9,0)+0.001,ERROR.TYPE(0)),IFERROR(IF(OFFSET(A76,-10,0)>0,OFFSET(A76,-10,0)+0.001,ERROR.TYPE(0)),ERROR.TYPE(0))))))))))) -> 2.035 | B76: Interface unit for Fire Appliance Pump Set | C76: 4 | D76: No | E76: =Elec_Est!E8414 -> 98.17 | F76: =IFERROR($C76*E76,E76) -> 392.68
A77: =IFERROR(IF(OFFSET(A77,-1,0)>0,OFFSET(A77,-1,0)+0.001,ERROR.TYPE(0)),IFERROR(IF(OFFSET(A77,-2,0)>0,OFFSET(A77,-2,0)+0.001,ERROR.TYPE(0)),IFERROR(IF(OFFSET(A77,-3,0)>0,OFFSET(A77,-3,0)+0.001,ERROR.TYPE(0)),IFERROR(IF(OFFSET(A77,-4,0)>0,OFFSET(A77,-4,0)+0.001,ERROR.TYPE(0)),IFERROR(IF(OFFSET(A77,-5,0)>0,OFFSET(A77,-5,0)+0.001,ERROR.TYPE(0)),IFERROR(IF(OFFSET(A77,-6,0)>0,OFFSET(A77,-6,0)+0.001,ERROR.TYPE(0)),IFERROR(IF(OFFSET(A77,-7,0)>0,OFFSET(A77,-7,0)+0.001,ERROR.TYPE(0)),IFERROR(IF(OFFSET(A77,-8,0)>0,OFFSET(A77,-8,0)+0.001,ERROR.TYPE(0)),IFERROR(IF(OFFSET(A77,-9,0)>0,OFFSET(A77,-9,0)+0.001,ERROR.TYPE(0)),IFERROR(IF(OFFSET(A77,-10,0)>0,OFFSET(A77,-10,0)+0.001,ERROR.TYPE(0)),ERROR.TYPE(0))))))))))) -> 2.036 | B77: Interface unit for Zone Assembly Valve | C77: 1 | D77: No | E77: =Elec_Est!E8421 -> 98.17 | F77: =IFERROR($C77*E77,E77) -> 98.17
A78: =IFERROR(IF(OFFSET(A78,-1,0)>0,OFFSET(A78,-1,0)+0.001,ERROR.TYPE(0)),IFERROR(IF(OFFSET(A78,-2,0)>0,OFFSET(A78,-2,0)+0.001,ERROR.TYPE(0)),IFERROR(IF(OFFSET(A78,-3,0)>0,OFFSET(A78,-3,0)+0.001,ERROR.TYPE(0)),IFERROR(IF(OFFSET(A78,-4,0)>0,OFFSET(A78,-4,0)+0.001,ERROR.TYPE(0)),IFERROR(IF(OFFSET(A78,-5,0)>0,OFFSET(A78,-5,0)+0.001,ERROR.TYPE(0)),IFERROR(IF(OFFSET(A78,-6,0)>0,OFFSET(A78,-6,0)+0.001,ERROR.TYPE(0)),IFERROR(IF(OFFSET(A78,-7,0)>0,OFFSET(A78,-7,0)+0.001,ERROR.TYPE(0)),IFERROR(IF(OFFSET(A78,-8,0)>0,OFFSET(A78,-8,0)+0.001,ERROR.TYPE(0)),IFERROR(IF(OFFSET(A78,-9,0)>0,OFFSET(A78,-9,0)+0.001,ERROR.TYPE(0)),IFERROR(IF(OFFSET(A78,-10,0)>0,OFFSET(A78,-10,0)+0.001,ERROR.TYPE(0)),ERROR.TYPE(0))))))))))) -> 2.037 | B78: Interface unit for VCP | C78: 1 | D78: No | E78: =Elec_Est!E8428 -> 98.17 | F78: =IFERROR($C78*E78,E78) -> 98.17
B79: Wiring of the following fire alarm points from the Fire alarm panel, using fire proof cable clipped directly to the wall / ceiling or through conduits, as per specification
A80: =IFERROR(IF(OFFSET(A80,-1,0)>0,OFFSET(A80,-1,0)+0.001,ERROR.TYPE(0)),IFERROR(IF(OFFSET(A80,-2,0)>0,OFFSET(A80,-2,0)+0.001,ERROR.TYPE(0)),IFERROR(IF(OFFSET(A80,-3,0)>0,OFFSET(A80,-3,0)+0.001,ERROR.TYPE(0)),IFERROR(IF(OFFSET(A80,-4,0)>0,OFFSET(A80,-4,0)+0.001,ERROR.TYPE(0)),IFERROR(IF(OFFSET(A80,-5,0)>0,OFFSET(A80,-5,0)+0.001,ERROR.TYPE(0)),IFERROR(IF(OFFSET(A80,-6,0)>0,OFFSET(A80,-6,0)+0.001,ERROR.TYPE(0)),IFERROR(IF(OFFSET(A80,-7,0)>0,OFFSET(A80,-7,0)+0.001,ERROR.TYPE(0)),IFERROR(IF(OFFSET(A80,-8,0)>0,OFFSET(A80,-8,0)+0.001,ERROR.TYPE(0)),IFERROR(IF(OFFSET(A80,-9,0)>0,OFFSET(A80,-9,0)+0.001,ERROR.TYPE(0)),IFERROR(IF(OFFSET(A80,-10,0)>0,OFFSET(A80,-10,0)+0.001,ERROR.TYPE(0)),ERROR.TYPE(0))))))))))) -> 2.038 | B80: Optical smoke detector | C80: 8 | D80: No | E80: =Elec_Est!E8439 -> 36.95 | F80: =IFERROR($C80*E80,E80) -> 295.6
A81: =IFERROR(IF(OFFSET(A81,-1,0)>0,OFFSET(A81,-1,0)+0.001,ERROR.TYPE(0)),IFERROR(IF(OFFSET(A81,-2,0)>0,OFFSET(A81,-2,0)+0.001,ERROR.TYPE(0)),IFERROR(IF(OFFSET(A81,-3,0)>0,OFFSET(A81,-3,0)+0.001,ERROR.TYPE(0)),IFERROR(IF(OFFSET(A81,-4,0)>0,OFFSET(A81,-4,0)+0.001,ERROR.TYPE(0)),IFERROR(IF(OFFSET(A81,-5,0)>0,OFFSET(A81,-5,0)+0.001,ERROR.TYPE(0)),IFERROR(IF(OFFSET(A81,-6,0)>0,OFFSET(A81,-6,0)+0.001,ERROR.TYPE(0)),IFERROR(IF(OFFSET(A81,-7,0)>0,OFFSET(A81,-7,0)+0.001,ERROR.TYPE(0)),IFERROR(IF(OFFSET(A81,-8,0)>0,OFFSET(A81,-8,0)+0.001,ERROR.TYPE(0)),IFERROR(IF(OFFSET(A81,-9,0)>0,OFFSET(A81,-9,0)+0.001,ERROR.TYPE(0)),IFERROR(IF(OFFSET(A81,-10,0)>0,OFFSET(A81,-10,0)+0.001,ERROR.TYPE(0)),ERROR.TYPE(0))))))))))) -> 2.039 | B81: Combined optical smoke detector c/w internal sounder & flashing beacon | C81: 5 | D81: No | E81: =Elec_Est!E8445 -> 36.95 | F81: =IFERROR($C81*E81,E81) -> 184.75
A82: =IFERROR(IF(OFFSET(A82,-1,0)>0,OFFSET(A82,-1,0)+0.001,ERROR.TYPE(0)),IFERROR(IF(OFFSET(A82,-2,0)>0,OFFSET(A82,-2,0)+0.001,ERROR.TYPE(0)),IFERROR(IF(OFFSET(A82,-3,0)>0,OFFSET(A82,-3,0)+0.001,ERROR.TYPE(0)),IFERROR(IF(OFFSET(A82,-4,0)>0,OFFSET(A82,-4,0)+0.001,ERROR.TYPE(0)),IFERROR(IF(OFFSET(A82,-5,0)>0,OFFSET(A82,-5,0)+0.001,ERROR.TYPE(0)),IFERROR(IF(OFFSET(A82,-6,0)>0,OFFSET(A82,-6,0)+0.001,ERROR.TYPE(0)),IFERROR(IF(OFFSET(A82,-7,0)>0,OFFSET(A82,-7,0)+0.001,ERROR.TYPE(0)),IFERROR(IF(OFFSET(A82,-8,0)>0,OFFSET(A82,-8,0)+0.001,ERROR.TYPE(0)),IFERROR(IF(OFFSET(A82,-9,0)>0,OFFSET(A82,-9,0)+0.001,ERROR.TYPE(0)),IFERROR(IF(OFFSET(A82,-10,0)>0,OFFSET(A82,-10,0)+0.001,ERROR.TYPE(0)),ERROR.TYPE(0))))))))))) -> 2.04 | B82: Rate of rise heat detector | C82: 52 | D82: No | E82: =Elec_Est!E8451 -> 36.95 | F82: =IFERROR($C82*E82,E82) -> 1921.4
A83: =IFERROR(IF(OFFSET(A83,-1,0)>0,OFFSET(A83,-1,0)+0.001,ERROR.TYPE(0)),IFERROR(IF(OFFSET(A83,-2,0)>0,OFFSET(A83,-2,0)+0.001,ERROR.TYPE(0)),IFERROR(IF(OFFSET(A83,-3,0)>0,OFFSET(A83,-3,0)+0.001,ERROR.TYPE(0)),IFERROR(IF(OFFSET(A83,-4,0)>0,OFFSET(A83,-4,0)+0.001,ERROR.TYPE(0)),IFERROR(IF(OFFSET(A83,-5,0)>0,OFFSET(A83,-5,0)+0.001,ERROR.TYPE(0)),IFERROR(IF(OFFSET(A83,-6,0)>0,OFFSET(A83,-6,0)+0.001,ERROR.TYPE(0)),IFERROR(IF(OFFSET(A83,-7,0)>0,OFFSET(A83,-7,0)+0.001,ERROR.TYPE(0)),IFERROR(IF(OFFSET(A83,-8,0)>0,OFFSET(A83,-8,0)+0.001,ERROR.TYPE(0)),IFERROR(IF(OFFSET(A83,-9,0)>0,OFFSET(A83,-9,0)+0.001,ERROR.TYPE(0)),IFERROR(IF(OFFSET(A83,-10,0)>0,OFFSET(A83,-10,0)+0.001,ERROR.TYPE(0)),ERROR.TYPE(0))))))))))) -> 2.041 | B83: Combined rate of rise heat detector c/w internal sounder & flashing beacon | C83: 9 | D83: No | E83: =Elec_Est!E8457 -> 36.95 | F83: =IFERROR($C83*E83,E83) -> 332.55
A84: =IFERROR(IF(OFFSET(A84,-1,0)>0,OFFSET(A84,-1,0)+0.001,ERROR.TYPE(0)),IFERROR(IF(OFFSET(A84,-2,0)>0,OFFSET(A84,-2,0)+0.001,ERROR.TYPE(0)),IFERROR(IF(OFFSET(A84,-3,0)>0,OFFSET(A84,-3,0)+0.001,ERROR.TYPE(0)),IFERROR(IF(OFFSET(A84,-4,0)>0,OFFSET(A84,-4,0)+0.001,ERROR.TYPE(0)),IFERROR(IF(OFFSET(A84,-5,0)>0,OFFSET(A84,-5,0)+0.001,ERROR.TYPE(0)),IFERROR(IF(OFFSET(A84,-6,0)>0,OFFSET(A84,-6,0)+0.001,ERROR.TYPE(0)),IFERROR(IF(OFFSET(A84,-7,0)>0,OFFSET(A84,-7,0)+0.001,ERROR.TYPE(0)),IFERROR(IF(OFFSET(A84,-8,0)>0,OFFSET(A84,-8,0)+0.001,ERROR.TYPE(0)),IFERROR(IF(OFFSET(A84,-9,0)>0,OFFSET(A84,-9,0)+0.001,ERROR.TYPE(0)),IFERROR(IF(OFFSET(A84,-10,0)>0,OFFSET(A84,-10,0)+0.001,ERROR.TYPE(0)),ERROR.TYPE(0))))))))))) -> 2.042 | B84: Manual call point | C84: 1 | D84: No | E84: =Elec_Est!E8463 -> 36.95 | F84: =IFERROR($C84*E84,E84) -> 36.95
A85: =IFERROR(IF(OFFSET(A85,-1,0)>0,OFFSET(A85,-1,0)+0.001,ERROR.TYPE(0)),IFERROR(IF(OFFSET(A85,-2,0)>0,OFFSET(A85,-2,0)+0.001,ERROR.TYPE(0)),IFERROR(IF(OFFSET(A85,-3,0)>0,OFFSET(A85,-3,0)+0.001,ERROR.TYPE(0)),IFERROR(IF(OFFSET(A85,-4,0)>0,OFFSET(A85,-4,0)+0.001,ERROR.TYPE(0)),IFERROR(IF(OFFSET(A85,-5,0)>0,OFFSET(A85,-5,0)+0.001,ERROR.TYPE(0)),IFERROR(IF(OFFSET(A85,-6,0)>0,OFFSET(A85,-6,0)+0.001,ERROR.TYPE(0)),IFERROR(IF(OFFSET(A85,-7,0)>0,OFFSET(A85,-7,0)+0.001,ERROR.TYPE(0)),IFERROR(IF(OFFSET(A85,-8,0)>0,OFFSET(A85,-8,0)+0.001,ERROR.TYPE(0)),IFERROR(IF(OFFSET(A85,-9,0)>0,OFFSET(A85,-9,0)+0.001,ERROR.TYPE(0)),IFERROR(IF(OFFSET(A85,-10,0)>0,OFFSET(A85,-10,0)+0.001,ERROR.TYPE(0)),ERROR.TYPE(0))))))))))) -> 2.043 | B85: Interface unit for Fire Fighting Pump Set | C85: 4 | D85: No | E85: =Elec_Est!E8469 -> 36.95 | F85: =IFERROR($C85*E85,E85) -> 147.8
A86: =IFERROR(IF(OFFSET(A86,-1,0)>0,OFFSET(A86,-1,0)+0.001,ERROR.TYPE(0)),IFERROR(IF(OFFSET(A86,-2,0)>0,OFFSET(A86,-2,0)+0.001,ERROR.TYPE(0)),IFERROR(IF(OFFSET(A86,-3,0)>0,OFFSET(A86,-3,0)+0.001,ERROR.TYPE(0)),IFERROR(IF(OFFSET(A86,-4,0)>0,OFFSET(A86,-4,0)+0.001,ERROR.TYPE(0)),IFERROR(IF(OFFSET(A86,-5,0)>0,OFFSET(A86,-5,0)+0.001,ERROR.TYPE(0)),IFERROR(IF(OFFSET(A86,-6,0)>0,OFFSET(A86,-6,0)+0.001,ERROR.TYPE(0)),IFERROR(IF(OFFSET(A86,-7,0)>0,OFFSET(A86,-7,0)+0.001,ERROR.TYPE(0)),IFERROR(IF(OFFSET(A86,-8,0)>0,OFFSET(A86,-8,0)+0.001,ERROR.TYPE(0)),IFERROR(IF(OFFSET(A86,-9,0)>0,OFFSET(A86,-9,0)+0.001,ERROR.TYPE(0)),IFERROR(IF(OFFSET(A86,-10,0)>0,OFFSET(A86,-10,0)+0.001,ERROR.TYPE(0)),ERROR.TYPE(0))))))))))) -> 2.044 | B86: Interface unit for Sprinkler Pump Set | C86: 4 | D86: No | E86: =Elec_Est!E8475 -> 36.95 | F86: =IFERROR($C86*E86,E86) -> 147.8
A87: =IFERROR(IF(OFFSET(A87,-1,0)>0,OFFSET(A87,-1,0)+0.001,ERROR.TYPE(0)),IFERROR(IF(OFFSET(A87,-2,0)>0,OFFSET(A87,-2,0)+0.001,ERROR.TYPE(0)),IFERROR(IF(OFFSET(A87,-3,0)>0,OFFSET(A87,-3,0)+0.001,ERROR.TYPE(0)),IFERROR(IF(OFFSET(A87,-4,0)>0,OFFSET(A87,-4,0)+0.001,ERROR.TYPE(0)),IFERROR(IF(OFFSET(A87,-5,0)>0,OFFSET(A87,-5,0)+0.001,ERROR.TYPE(0)),IFERROR(IF(OFFSET(A87,-6,0)>0,OFFSET(A87,-6,0)+0.001,ERROR.TYPE(0)),IFERROR(IF(OFFSET(A87,-7,0)>0,OFFSET(A87,-7,0)+0.001,ERROR.TYPE(0)),IFERROR(IF(OFFSET(A87,-8,0)>0,OFFSET(A87,-8,0)+0.001,ERROR.TYPE(0)),IFERROR(IF(OFFSET(A87,-9,0)>0,OFFSET(A87,-9,0)+0.001,ERROR.TYPE(0)),IFERROR(IF(OFFSET(A87,-10,0)>0,OFFSET(A87,-10,0)+0.001,ERROR.TYPE(0)),ERROR.TYPE(0))))))))))) -> 2.045 | B87: Interface unit for Fire Appliance Pump Set | C87: 4 | D87: No | E87: =Elec_Est!E8481 -> 36.95 | F87: =IFERROR($C87*E87,E87) -> 147.8
A88: =IFERROR(IF(OFFSET(A88,-1,0)>0,OFFSET(A88,-1,0)+0.001,ERROR.TYPE(0)),IFERROR(IF(OFFSET(A88,-2,0)>0,OFFSET(A88,-2,0)+0.001,ERROR.TYPE(0)),IFERROR(IF(OFFSET(A88,-3,0)>0,OFFSET(A88,-3,0)+0.001,ERROR.TYPE(0)),IFERROR(IF(OFFSET(A88,-4,0)>0,OFFSET(A88,-4,0)+0.001,ERROR.TYPE(0)),IFERROR(IF(OFFSET(A88,-5,0)>0,OFFSET(A88,-5,0)+0.001,ERROR.TYPE(0)),IFERROR(IF(OFFSET(A88,-6,0)>0,OFFSET(A88,-6,0)+0.001,ERROR.TYPE(0)),IFERROR(IF(OFFSET(A88,-7,0)>0,OFFSET(A88,-7,0)+0.001,ERROR.TYPE(0)),IFERROR(IF(OFFSET(A88,-8,0)>0,OFFSET(A88,-8,0)+0.001,ERROR.TYPE(0)),IFERROR(IF(OFFSET(A88,-9,0)>0,OFFSET(A88,-9,0)+0.001,ERROR.TYPE(0)),IFERROR(IF(OFFSET(A88,-10,0)>0,OFFSET(A88,-10,0)+0.001,ERROR.TYPE(0)),ERROR.TYPE(0))))))))))) -> 2.046 | B88: Interface unit for Zone Assembly Valve | C88: 1 | D88: No | E88: =Elec_Est!E8487 -> 36.95 | F88: =IFERROR($C88*E88,E88) -> 36.95
A89: =IFERROR(IF(OFFSET(A89,-1,0)>0,OFFSET(A89,-1,0)+0.001,ERROR.TYPE(0)),IFERROR(IF(OFFSET(A89,-2,0)>0,OFFSET(A89,-2,0)+0.001,ERROR.TYPE(0)),IFERROR(IF(OFFSET(A89,-3,0)>0,OFFSET(A89,-3,0)+0.001,ERROR.TYPE(0)),IFERROR(IF(OFFSET(A89,-4,0)>0,OFFSET(A89,-4,0)+0.001,ERROR.TYPE(0)),IFERROR(IF(OFFSET(A89,-5,0)>0,OFFSET(A89,-5,0)+0.001,ERROR.TYPE(0)),IFERROR(IF(OFFSET(A89,-6,0)>0,OFFSET(A89,-6,0)+0.001,ERROR.TYPE(0)),IFERROR(IF(OFFSET(A89,-7,0)>0,OFFSET(A89,-7,0)+0.001,ERROR.TYPE(0)),IFERROR(IF(OFFSET(A89,-8,0)>0,OFFSET(A89,-8,0)+0.001,ERROR.TYPE(0)),IFERROR(IF(OFFSET(A89,-9,0)>0,OFFSET(A89,-9,0)+0.001,ERROR.TYPE(0)),IFERROR(IF(OFFSET(A89,-10,0)>0,OFFSET(A89,-10,0)+0.001,ERROR.TYPE(0)),ERROR.TYPE(0))))))))))) -> 2.047 | B89: Interface unit for VCP | C89: 1 | D89: No | E89: =Elec_Est!E8493 -> 36.95 | F89: =IFERROR($C89*E89,E89) -> 36.95
B90: Supply, install and connect of the following equipment:
A91: =IFERROR(IF(OFFSET(A91,-1,0)>0,OFFSET(A91,-1,0)+0.001,ERROR.TYPE(0)),IFERROR(IF(OFFSET(A91,-2,0)>0,OFFSET(A91,-2,0)+0.001,ERROR.TYPE(0)),IFERROR(IF(OFFSET(A91,-3,0)>0,OFFSET(A91,-3,0)+0.001,ERROR.TYPE(0)),IFERROR(IF(OFFSET(A91,-4,0)>0,OFFSET(A91,-4,0)+0.001,ERROR.TYPE(0)),IFERROR(IF(OFFSET(A91,-5,0)>0,OFFSET(A91,-5,0)+0.001,ERROR.TYPE(0)),IFERROR(IF(OFFSET(A91,-6,0)>0,OFFSET(A91,-6,0)+0.001,ERROR.TYPE(0)),IFERROR(IF(OFFSET(A91,-7,0)>0,OFFSET(A91,-7,0)+0.001,ERROR.TYPE(0)),IFERROR(IF(OFFSET(A91,-8,0)>0,OFFSET(A91,-8,0)+0.001,ERROR.TYPE(0)),IFERROR(IF(OFFSET(A91,-9,0)>0,OFFSET(A91,-9,0)+0.001,ERROR.TYPE(0)),IFERROR(IF(OFFSET(A91,-10,0)>0,OFFSET(A91,-10,0)+0.001,ERROR.TYPE(0)),ERROR.TYPE(0))))))))))) -> 2.048 | B91: Optical smoke detector | C91: 8 | D91: No | E91: =Elec_Est!E8503 -> 52.23 | F91: =IFERROR($C91*E91,E91) -> 417.84
A92: =IFERROR(IF(OFFSET(A92,-1,0)>0,OFFSET(A92,-1,0)+0.001,ERROR.TYPE(0)),IFERROR(IF(OFFSET(A92,-2,0)>0,OFFSET(A92,-2,0)+0.001,ERROR.TYPE(0)),IFERROR(IF(OFFSET(A92,-3,0)>0,OFFSET(A92,-3,0)+0.001,ERROR.TYPE(0)),IFERROR(IF(OFFSET(A92,-4,0)>0,OFFSET(A92,-4,0)+0.001,ERROR.TYPE(0)),IFERROR(IF(OFFSET(A92,-5,0)>0,OFFSET(A92,-5,0)+0.001,ERROR.TYPE(0)),IFERROR(IF(OFFSET(A92,-6,0)>0,OFFSET(A92,-6,0)+0.001,ERROR.TYPE(0)),IFERROR(IF(OFFSET(A92,-7,0)>0,OFFSET(A92,-7,0)+0.001,ERROR.TYPE(0)),IFERROR(IF(OFFSET(A92,-8,0)>0,OFFSET(A92,-8,0)+0.001,ERROR.TYPE(0)),IFERROR(IF(OFFSET(A92,-9,0)>0,OFFSET(A92,-9,0)+0.001,ERROR.TYPE(0)),IFERROR(IF(OFFSET(A92,-10,0)>0,OFFSET(A92,-10,0)+0.001,ERROR.TYPE(0)),ERROR.TYPE(0))))))))))) -> 2.049 | B92: Combined optical smoke detector c/w internal sounder & flashing beacon | C92: 5 | D92: No | E92: =Elec_Est!E8509 -> 93.61 | F92: =IFERROR($C92*E92,E92) -> 468.05
A93: =IFERROR(IF(OFFSET(A93,-1,0)>0,OFFSET(A93,-1,0)+0.001,ERROR.TYPE(0)),IFERROR(IF(OFFSET(A93,-2,0)>0,OFFSET(A93,-2,0)+0.001,ERROR.TYPE(0)),IFERROR(IF(OFFSET(A93,-3,0)>0,OFFSET(A93,-3,0)+0.001,ERROR.TYPE(0)),IFERROR(IF(OFFSET(A93,-4,0)>0,OFFSET(A93,-4,0)+0.001,ERROR.TYPE(0)),IFERROR(IF(OFFSET(A93,-5,0)>0,OFFSET(A93,-5,0)+0.001,ERROR.TYPE(0)),IFERROR(IF(OFFSET(A93,-6,0)>0,OFFSET(A93,-6,0)+0.001,ERROR.TYPE(0)),IFERROR(IF(OFFSET(A93,-7,0)>0,OFFSET(A93,-7,0)+0.001,ERROR.TYPE(0)),IFERROR(IF(OFFSET(A93,-8,0)>0,OFFSET(A93,-8,0)+0.001,ERROR.TYPE(0)),IFERROR(IF(OFFSET(A93,-9,0)>0,OFFSET(A93,-9,0)+0.001,ERROR.TYPE(0)),IFERROR(IF(OFFSET(A93,-10,0)>0,OFFSET(A93,-10,0)+0.001,ERROR.TYPE(0)),ERROR.TYPE(0))))))))))) -> 2.05 | B93: Rate of rise heat detector | C93: 52 | D93: No | E93: =Elec_Est!E8515 -> 51.24 | F93: =IFERROR($C93*E93,E93) -> 2664.48
A94: =IFERROR(IF(OFFSET(A94,-1,0)>0,OFFSET(A94,-1,0)+0.001,ERROR.TYPE(0)),IFERROR(IF(OFFSET(A94,-2,0)>0,OFFSET(A94,-2,0)+0.001,ERROR.TYPE(0)),IFERROR(IF(OFFSET(A94,-3,0)>0,OFFSET(A94,-3,0)+0.001,ERROR.TYPE(0)),IFERROR(IF(OFFSET(A94,-4,0)>0,OFFSET(A94,-4,0)+0.001,ERROR.TYPE(0)),IFERROR(IF(OFFSET(A94,-5,0)>0,OFFSET(A94,-5,0)+0.001,ERROR.TYPE(0)),IFERROR(IF(OFFSET(A94,-6,0)>0,OFFSET(A94,-6,0)+0.001,ERROR.TYPE(0)),IFERROR(IF(OFFSET(A94,-7,0)>0,OFFSET(A94,-7,0)+0.001,ERROR.TYPE(0)),IFERROR(IF(OFFSET(A94,-8,0)>0,OFFSET(A94,-8,0)+0.001,ERROR.TYPE(0)),IFERROR(IF(OFFSET(A94,-9,0)>0,OFFSET(A94,-9,0)+0.001,ERROR.TYPE(0)),IFERROR(IF(OFFSET(A94,-10,0)>0,OFFSET(A94,-10,0)+0.001,ERROR.TYPE(0)),ERROR.TYPE(0))))))))))) -> 2.051 | B94: Combined rate of rise heat detector c/w internal sounder & flashing beacon | C94: 9 | D94: No | E94: =Elec_Est!E8521 -> 92.63 | F94: =IFERROR($C94*E94,E94) -> 833.67
A95: =IFERROR(IF(OFFSET(A95,-1,0)>0,OFFSET(A95,-1,0)+0.001,ERROR.TYPE(0)),IFERROR(IF(OFFSET(A95,-2,0)>0,OFFSET(A95,-2,0)+0.001,ERROR.TYPE(0)),IFERROR(IF(OFFSET(A95,-3,0)>0,OFFSET(A95,-3,0)+0.001,ERROR.TYPE(0)),IFERROR(IF(OFFSET(A95,-4,0)>0,OFFSET(A95,-4,0)+0.001,ERROR.TYPE(0)),IFERROR(IF(OFFSET(A95,-5,0)>0,OFFSET(A95,-5,0)+0.001,ERROR.TYPE(0)),IFERROR(IF(OFFSET(A95,-6,0)>0,OFFSET(A95,-6,0)+0.001,ERROR.TYPE(0)),IFERROR(IF(OFFSET(A95,-7,0)>0,OFFSET(A95,-7,0)+0.001,ERROR.TYPE(0)),IFERROR(IF(OFFSET(A95,-8,0)>0,OFFSET(A95,-8,0)+0.001,ERROR.TYPE(0)),IFERROR(IF(OFFSET(A95,-9,0)>0,OFFSET(A95,-9,0)+0.001,ERROR.TYPE(0)),IFERROR(IF(OFFSET(A95,-10,0)>0,OFFSET(A95,-10,0)+0.001,ERROR.TYPE(0)),ERROR.TYPE(0))))))))))) -> 2.052 | B95: Manual call point c/w cover | C95: 1 | D95: No | E95: =Elec_Est!E8527 -> 54.2 | F95: =IFERROR($C95*E95,E95) -> 54.2
A96: =IFERROR(IF(OFFSET(A96,-1,0)>0,OFFSET(A96,-1,0)+0.001,ERROR.TYPE(0)),IFERROR(IF(OFFSET(A96,-2,0)>0,OFFSET(A96,-2,0)+0.001,ERROR.TYPE(0)),IFERROR(IF(OFFSET(A96,-3,0)>0,OFFSET(A96,-3,0)+0.001,ERROR.TYPE(0)),IFERROR(IF(OFFSET(A96,-4,0)>0,OFFSET(A96,-4,0)+0.001,ERROR.TYPE(0)),IFERROR(IF(OFFSET(A96,-5,0)>0,OFFSET(A96,-5,0)+0.001,ERROR.TYPE(0)),IFERROR(IF(OFFSET(A96,-6,0)>0,OFFSET(A96,-6,0)+0.001,ERROR.TYPE(0)),IFERROR(IF(OFFSET(A96,-7,0)>0,OFFSET(A96,-7,0)+0.001,ERROR.TYPE(0)),IFERROR(IF(OFFSET(A96,-8,0)>0,OFFSET(A96,-8,0)+0.001,ERROR.TYPE(0)),IFERROR(IF(OFFSET(A96,-9,0)>0,OFFSET(A96,-9,0)+0.001,ERROR.TYPE(0)),IFERROR(IF(OFFSET(A96,-10,0)>0,OFFSET(A96,-10,0)+0.001,ERROR.TYPE(0)),ERROR.TYPE(0))))))))))) -> 2.053 | B96: Interface unit for Fire Fighting Pump Set | C96: 4 | D96: No | E96: =Elec_Est!E8533 -> 77.85 | F96: =IFERROR($C96*E96,E96) -> 311.4
A97: =IFERROR(IF(OFFSET(A97,-1,0)>0,OFFSET(A97,-1,0)+0.001,ERROR.TYPE(0)),IFERROR(IF(OFFSET(A97,-2,0)>0,OFFSET(A97,-2,0)+0.001,ERROR.TYPE(0)),IFERROR(IF(OFFSET(A97,-3,0)>0,OFFSET(A97,-3,0)+0.001,ERROR.TYPE(0)),IFERROR(IF(OFFSET(A97,-4,0)>0,OFFSET(A97,-4,0)+0.001,ERROR.TYPE(0)),IFERROR(IF(OFFSET(A97,-5,0)>0,OFFSET(A97,-5,0)+0.001,ERROR.TYPE(0)),IFERROR(IF(OFFSET(A97,-6,0)>0,OFFSET(A97,-6,0)+0.001,ERROR.TYPE(0)),IFERROR(IF(OFFSET(A97,-7,0)>0,OFFSET(A97,-7,0)+0.001,ERROR.TYPE(0)),IFERROR(IF(OFFSET(A97,-8,0)>0,OFFSET(A97,-8,0)+0.001,ERROR.TYPE(0)),IFERROR(IF(OFFSET(A97,-9,0)>0,OFFSET(A97,-9,0)+0.001,ERROR.TYPE(0)),IFERROR(IF(OFFSET(A97,-10,0)>0,OFFSET(A97,-10,0)+0.001,ERROR.TYPE(0)),ERROR.TYPE(0))))))))))) -> 2.054 | B97: Interface unit for Sprinkler Pump Set | C97: 4 | D97: No | E97: =Elec_Est!E8539 -> 77.85 | F97: =IFERROR($C97*E97,E97) -> 311.4
A98: =IFERROR(IF(OFFSET(A98,-1,0)>0,OFFSET(A98,-1,0)+0.001,ERROR.TYPE(0)),IFERROR(IF(OFFSET(A98,-2,0)>0,OFFSET(A98,-2,0)+0.001,ERROR.TYPE(0)),IFERROR(IF(OFFSET(A98,-3,0)>0,OFFSET(A98,-3,0)+0.001,ERROR.TYPE(0)),IFERROR(IF(OFFSET(A98,-4,0)>0,OFFSET(A98,-4,0)+0.001,ERROR.TYPE(0)),IFERROR(IF(OFFSET(A98,-5,0)>0,OFFSET(A98,-5,0)+0.001,ERROR.TYPE(0)),IFERROR(IF(OFFSET(A98,-6,0)>0,OFFSET(A98,-6,0)+0.001,ERROR.TYPE(0)),IFERROR(IF(OFFSET(A98,-7,0)>0,OFFSET(A98,-7,0)+0.001,ERROR.TYPE(0)),IFERROR(IF(OFFSET(A98,-8,0)>0,OFFSET(A98,-8,0)+0.001,ERROR.TYPE(0)),IFERROR(IF(OFFSET(A98,-9,0)>0,OFFSET(A98,-9,0)+0.001,ERROR.TYPE(0)),IFERROR(IF(OFFSET(A98,-10,0)>0,OFFSET(A98,-10,0)+0.001,ERROR.TYPE(0)),ERROR.TYPE(0))))))))))) -> 2.055 | B98: Interface unit for Fire Appliance Pump Set | C98: 4 | D98: No | E98: =Elec_Est!E8545 -> 77.85 | F98: =IFERROR($C98*E98,E98) -> 311.4
A99: =IFERROR(IF(OFFSET(A99,-1,0)>0,OFFSET(A99,-1,0)+0.001,ERROR.TYPE(0)),IFERROR(IF(OFFSET(A99,-2,0)>0,OFFSET(A99,-2,0)+0.001,ERROR.TYPE(0)),IFERROR(IF(OFFSET(A99,-3,0)>0,OFFSET(A99,-3,0)+0.001,ERROR.TYPE(0)),IFERROR(IF(OFFSET(A99,-4,0)>0,OFFSET(A99,-4,0)+0.001,ERROR.TYPE(0)),IFERROR(IF(OFFSET(A99,-5,0)>0,OFFSET(A99,-5,0)+0.001,ERROR.TYPE(0)),IFERROR(IF(OFFSET(A99,-6,0)>0,OFFSET(A99,-6,0)+0.001,ERROR.TYPE(0)),IFERROR(IF(OFFSET(A99,-7,0)>0,OFFSET(A99,-7,0)+0.001,ERROR.TYPE(0)),IFERROR(IF(OFFSET(A99,-8,0)>0,OFFSET(A99,-8,0)+0.001,ERROR.TYPE(0)),IFERROR(IF(OFFSET(A99,-9,0)>0,OFFSET(A99,-9,0)+0.001,ERROR.TYPE(0)),IFERROR(IF(OFFSET(A99,-10,0)>0,OFFSET(A99,-10,0)+0.001,ERROR.TYPE(0)),ERROR.TYPE(0))))))))))) -> 2.056 | B99: Interface unit for Zone Assembly Valve | C99: 1 | D99: No | E99: =Elec_Est!E8551 -> 77.85 | F99: =IFERROR($C99*E99,E99) -> 77.85
A100: =IFERROR(IF(OFFSET(A100,-1,0)>0,OFFSET(A100,-1,0)+0.001,ERROR.TYPE(0)),IFERROR(IF(OFFSET(A100,-2,0)>0,OFFSET(A100,-2,0)+0.001,ERROR.TYPE(0)),IFERROR(IF(OFFSET(A100,-3,0)>0,OFFSET(A100,-3,0)+0.001,ERROR.TYPE(0)),IFERROR(IF(OFFSET(A100,-4,0)>0,OFFSET(A100,-4,0)+0.001,ERROR.TYPE(0)),IFERROR(IF(OFFSET(A100,-5,0)>0,OFFSET(A100,-5,0)+0.001,ERROR.TYPE(0)),IFERROR(IF(OFFSET(A100,-6,0)>0,OFFSET(A100,-6,0)+0.001,ERROR.TYPE(0)),IFERROR(IF(OFFSET(A100,-7,0)>0,OFFSET(A100,-7,0)+0.001,ERROR.TYPE(0)),IFERROR(IF(OFFSET(A100,-8,0)>0,OFFSET(A100,-8,0)+0.001,ERROR.TYPE(0)),IFERROR(IF(OFFSET(A100,-9,0)>0,OFFSET(A100,-9,0)+0.001,ERROR.TYPE(0)),IFERROR(IF(OFFSET(A100,-10,0)>0,OFFSET(A100,-10,0)+0.001,ERROR.TYPE(0)),ERROR.TYPE(0))))))))))) -> 2.057 | B100: Interface unit for VCP | C100: 1 | D100: No | E100: =Elec_Est!E8557 -> 77.85 | F100: =IFERROR($C100*E100,E100) -> 77.85
B101: TOTAL FOR PAGE 04 | C101: Euro Exc VAT | F101: =SUM(F68:F100) -> 17553.82
A104: ITEM | B104: DESCRIPTION | C104: QTY | D104: UNIT | E104: RATE Euro (Exc of VAT) | F104: TOTAL Euro (Exc of VAT)
B105: Level 0 - FAP1
B106: Supply and install LSZH conduit recessed in wall or in screed under tiles from fire alarm panel via galvanised trunking to the following fire alarm points.
A107: =IFERROR(IF(OFFSET(A107,-1,0)>0,OFFSET(A107,-1,0)+0.001,ERROR.TYPE(0)),IFERROR(IF(OFFSET(A107,-2,0)>0,OFFSET(A107,-2,0)+0.001,ERROR.TYPE(0)),IFERROR(IF(OFFSET(A107,-3,0)>0,OFFSET(A107,-3,0)+0.001,ERROR.TYPE(0)),IFERROR(IF(OFFSET(A107,-4,0)>0,OFFSET(A107,-4,0)+0.001,ERROR.TYPE(0)),IFERROR(IF(OFFSET(A107,-5,0)>0,OFFSET(A107,-5,0)+0.001,ERROR.TYPE(0)),IFERROR(IF(OFFSET(A107,-6,0)>0,OFFSET(A107,-6,0)+0.001,ERROR.TYPE(0)),IFERROR(IF(OFFSET(A107,-7,0)>0,OFFSET(A107,-7,0)+0.001,ERROR.TYPE(0)),IFERROR(IF(OFFSET(A107,-8,0)>0,OFFSET(A107,-8,0)+0.001,ERROR.TYPE(0)),IFERROR(IF(OFFSET(A107,-9,0)>0,OFFSET(A107,-9,0)+0.001,ERROR.TYPE(0)),IFERROR(IF(OFFSET(A107,-10,0)>0,OFFSET(A107,-10,0)+0.001,ERROR.TYPE(0)),ERROR.TYPE(0))))))))))) -> 2.058 | B107: Optical smoke detector | C107: 12 | D107: No | E107: =Elec_Est!E8577 -> 49.52 | F107: =IFERROR($C107*E107,E107) -> 594.24
A108: =IFERROR(IF(OFFSET(A108,-1,0)>0,OFFSET(A108,-1,0)+0.001,ERROR.TYPE(0)),IFERROR(IF(OFFSET(A108,-2,0)>0,OFFSET(A108,-2,0)+0.001,ERROR.TYPE(0)),IFERROR(IF(OFFSET(A108,-3,0)>0,OFFSET(A108,-3,0)+0.001,ERROR.TYPE(0)),IFERROR(IF(OFFSET(A108,-4,0)>0,OFFSET(A108,-4,0)+0.001,ERROR.TYPE(0)),IFERROR(IF(OFFSET(A108,-5,0)>0,OFFSET(A108,-5,0)+0.001,ERROR.TYPE(0)),IFERROR(IF(OFFSET(A108,-6,0)>0,OFFSET(A108,-6,0)+0.001,ERROR.TYPE(0)),IFERROR(IF(OFFSET(A108,-7,0)>0,OFFSET(A108,-7,0)+0.001,ERROR.TYPE(0)),IFERROR(IF(OFFSET(A108,-8,0)>0,OFFSET(A108,-8,0)+0.001,ERROR.TYPE(0)),IFERROR(IF(OFFSET(A108,-9,0)>0,OFFSET(A108,-9,0)+0.001,ERROR.TYPE(0)),IFERROR(IF(OFFSET(A108,-10,0)>0,OFFSET(A108,-10,0)+0.001,ERROR.TYPE(0)),ERROR.TYPE(0))))))))))) -> 2.059 | B108: Combined optical smoke detector c/w internal sounder & flashing beacon | C108: 2 | D108: No | E108: =Elec_Est!E8584 -> 49.52 | F108: =IFERROR($C108*E108,E108) -> 99.04
A109: =IFERROR(IF(OFFSET(A109,-1,0)>0,OFFSET(A109,-1,0)+0.001,ERROR.TYPE(0)),IFERROR(IF(OFFSET(A109,-2,0)>0,OFFSET(A109,-2,0)+0.001,ERROR.TYPE(0)),IFERROR(IF(OFFSET(A109,-3,0)>0,OFFSET(A109,-3,0)+0.001,ERROR.TYPE(0)),IFERROR(IF(OFFSET(A109,-4,0)>0,OFFSET(A109,-4,0)+0.001,ERROR.TYPE(0)),IFERROR(IF(OFFSET(A109,-5,0)>0,OFFSET(A109,-5,0)+0.001,ERROR.TYPE(0)),IFERROR(IF(OFFSET(A109,-6,0)>0,OFFSET(A109,-6,0)+0.001,ERROR.TYPE(0)),IFERROR(IF(OFFSET(A109,-7,0)>0,OFFSET(A109,-7,0)+0.001,ERROR.TYPE(0)),IFERROR(IF(OFFSET(A109,-8,0)>0,OFFSET(A109,-8,0)+0.001,ERROR.TYPE(0)),IFERROR(IF(OFFSET(A109,-9,0)>0,OFFSET(A109,-9,0)+0.001,ERROR.TYPE(0)),IFERROR(IF(OFFSET(A109,-10,0)>0,OFFSET(A109,-10,0)+0.001,ERROR.TYPE(0)),ERROR.TYPE(0))))))))))) -> 2.06 | B109: External fire sounder | C109: 1 | D109: No | E109: =Elec_Est!E8591 -> 49.52 | F109: =IFERROR($C109*E109,E109) -> 49.52
A110: =IFERROR(IF(OFFSET(A110,-1,0)>0,OFFSET(A110,-1,0)+0.001,ERROR.TYPE(0)),IFERROR(IF(OFFSET(A110,-2,0)>0,OFFSET(A110,-2,0)+0.001,ERROR.TYPE(0)),IFERROR(IF(OFFSET(A110,-3,0)>0,OFFSET(A110,-3,0)+0.001,ERROR.TYPE(0)),IFERROR(IF(OFFSET(A110,-4,0)>0,OFFSET(A110,-4,0)+0.001,ERROR.TYPE(0)),IFERROR(IF(OFFSET(A110,-5,0)>0,OFFSET(A110,-5,0)+0.001,ERROR.TYPE(0)),IFERROR(IF(OFFSET(A110,-6,0)>0,OFFSET(A110,-6,0)+0.001,ERROR.TYPE(0)),IFERROR(IF(OFFSET(A110,-7,0)>0,OFFSET(A110,-7,0)+0.001,ERROR.TYPE(0)),IFERROR(IF(OFFSET(A110,-8,0)>0,OFFSET(A110,-8,0)+0.001,ERROR.TYPE(0)),IFERROR(IF(OFFSET(A110,-9,0)>0,OFFSET(A110,-9,0)+0.001,ERROR.TYPE(0)),IFERROR(IF(OFFSET(A110,-10,0)>0,OFFSET(A110,-10,0)+0.001,ERROR.TYPE(0)),ERROR.TYPE(0))))))))))) -> 2.061 | B110: Manual call point | C110: 4 | D110: No | E110: =Elec_Est!E8598 -> 49.52 | F110: =IFERROR($C110*E110,E110) -> 198.08
A111: =IFERROR(IF(OFFSET(A111,-1,0)>0,OFFSET(A111,-1,0)+0.001,ERROR.TYPE(0)),IFERROR(IF(OFFSET(A111,-2,0)>0,OFFSET(A111,-2,0)+0.001,ERROR.TYPE(0)),IFERROR(IF(OFFSET(A111,-3,0)>0,OFFSET(A111,-3,0)+0.001,ERROR.TYPE(0)),IFERROR(IF(OFFSET(A111,-4,0)>0,OFFSET(A111,-4,0)+0.001,ERROR.TYPE(0)),IFERROR(IF(OFFSET(A111,-5,0)>0,OFFSET(A111,-5,0)+0.001,ERROR.TYPE(0)),IFERROR(IF(OFFSET(A111,-6,0)>0,OFFSET(A111,-6,0)+0.001,ERROR.TYPE(0)),IFERROR(IF(OFFSET(A111,-7,0)>0,OFFSET(A111,-7,0)+0.001,ERROR.TYPE(0)),IFERROR(IF(OFFSET(A111,-8,0)>0,OFFSET(A111,-8,0)+0.001,ERROR.TYPE(0)),IFERROR(IF(OFFSET(A111,-9,0)>0,OFFSET(A111,-9,0)+0.001,ERROR.TYPE(0)),IFERROR(IF(OFFSET(A111,-10,0)>0,OFFSET(A111,-10,0)+0.001,ERROR.TYPE(0)),ERROR.TYPE(0))))))))))) -> 2.062 | B111: Interface unit for Autodialler | C111: 1 | D111: No | E111: =Elec_Est!E8605 -> 49.52 | F111: =IFERROR($C111*E111,E111) -> 49.52
...

Sheet Notes
A1: NOTES | C1: Rev: 235
C2: checkdesc
A3: ELECTRICAL | C3: Elec_Rates
C4: Elec_Est
A5: Dist Boards | C5: Elv_Rates
A6: 1 | C6: ELV_Est
A7: 2 | C7: Ext_Quote
C8: Int_Quote
A9: Wiring Accessories | C9: Est_BOQ
A10: 1
A11: 2 | C11: Camilleri&Cuschieri Tenders
C12: Conduit
A13: ELV | C13: Wiring
C14: Supply
A15: Fire Alarm
A16: 1
A17: 2
A18: 3
A20: Data
A21: 1
A22: 2
A23: 3

Sheet Quote
A1: =IF(AND(UPPER(LEFT(TRIM($D$8),11))="01",UPPER(LEFT(TRIM($D$9),3))<>"ELM"),"PANTA RETAIL LTD.","PANTA CONTRACTING LIMITED") -> PANTA CONTRACTING LIMITED
A2: =IF(UPPER(LEFT(TRIM($D$9),3))="ELM","ELEC-FOR-MECH INTERNAL QUOTATION","ELECTRICAL INTERNAL QUOTATION") -> ELECTRICAL INTERNAL QUOTATION
B5: ATT: | D5: =IF(A2="Internal Quotation", "Mechanical Division","") | R5: Dated: | S5: =NOW() -> 46114.371
B6: CLIENT: | C6: Link to ML_SUM $D1 | D6: =ML_Sum!D1 -> Quintano Foods Ltd.
B7: PROJECT: | C7: Link to ML_SUM $D2 | D7: =ML_Sum!D2 -> Warehouse at tal-Handaq, Qormi
B8: JOB DESC: | C8: Link to ML_SUM $D3 | D8: =ML_Sum!D3 -> Electrical and ELV installations (Rev A)
B9: QUOTE No: | C9: Link to ML_SUM $D4 | D9: =ML_Sum!D4 -> EL25-0062A
B10: CLIENT's Ref: | C10: Link to ML_SUM $D5 | D10: =ML_Sum!D5 -> Tender
D22: Selling Price (€) : | E22: =ML_Sum!E35 -> 1478219.1 | F22: =ML_Sum!D6 -> VAT EXCL. | G22: VAT EXCLUDED. | H22: VAT EXCLUDED. | I22: VAT EXCLUDED. | J22: VAT EXCLUDED. | K22: VAT EXCLUDED. | L22: VAT EXCLUDED. | M22: VAT EXCLUDED. | N22: VAT EXCLUDED. | O22: VAT EXCLUDED. | P22: VAT EXCLUDED.
A51: Signed for and on behalf of | Q51: Signed for and on behalf of
A52: Electrical Division | Q52: Division
Q54: Records
Q55: Mr. A. Sciberras
Q57: File

Sheet ML_Sum
B1: CLIENT: | C1: 1 | D1: Quintano Foods Ltd. | G1: TRUE | H1: TRUE | I1: 1 | J1: =$Q109 -> 1 | K1: =$Q119 -> 1 | L1: =$Q129 -> 1 | M1: =$Q139 -> 1 | N1: =$Q149 -> 1 | O1: =$Q159 -> 1 | Q1: =IF(C1=1,"€","Curr?") -> € | R1: Recon /Lab.Cont >> | S1: =IF($S$39="PRINT","R","Do Not Print") -> R | T1: 0.9 | V1: {=IF(OR(X1=AREAS),1,0)} -> 1 | W1: BOQ | X1: x | Y1: x | Z1: x | AA1: x | AB1: x | AC1: x | AD1: x
B2: PROJECT: | C2: =IF($D$6="VAT INCLUDED",1.18,1)*(1-$Q2)*$C$1 -> 1 | D2: Warehouse at tal-Handaq, Qormi | F2: Electrical | G2: TRUE | I2: 2 | J2: =$Q110 -> 1 | K2: =$Q120 -> 1 | L2: =$Q130 -> 1 | M2: =$Q140 -> 1 | N2: =$Q150 -> 1 | O2: =$Q160 -> 1 | R2: ="A) " & IF($S2=0,"",ROUND($S2,2) & "-" & ROUND($T2/$D$9,2)) -> A) 1.23-1.23 | S2: =1.2*1.02*1.006 -> 1.231344 | T2: =$S2*$D$9 -> 33.812706 | U2: Note: Mark Ups include 2% measurement fee for C&C and 0.6% CAR insurance - Email from Kris Micallef dated 11th February 2025 | X2: x | Y2: x | Z2: x | AA2: x | AB2: x | AC2: x | AD2: x
B3: JOB DESC: | C3: =IF($D$6="VAT INCLUDED",1.18,1)*(1-$Q3)*$C$1 -> 1 | D3: Electrical and ELV installations (Rev A) | F3: ELV Installation (NAS Ltd) | G3: TRUE | I3: 3 | J3: =$Q111 -> 1 | K3: =$Q121 -> 1 | L3: =$Q131 -> 1 | M3: =$Q141 -> 1 | N3: =$Q151 -> 1 | O3: =$Q161 -> 1 | R3: ="B) " & IF($S3=0,"",ROUND($S3,2) & "-" & ROUND($T3/$D$9,2)) -> B) 1.13-1.13 | S3: =1.1*1.02*1.006 -> 1.128732 | T3: =$S3*$D$9 -> 30.994981 | X3: x | Y3: x | Z3: x | AA3: x | AB3: x | AC3: x | AD3: x
B4: INT. QUOT No: | C4: =IF($D$6="VAT INCLUDED",1.18,1)*(1-$Q4)*$C$1 -> 1 | D4: EL25-0062A | F4: Lightning Protection System (MCE Ltd) | G4: TRUE | I4: 4 | J4: =$Q112 -> 1 | K4: =$Q122 -> 1 | L4: =$Q132 -> 1 | M4: =$Q142 -> 1 | N4: =$Q152 -> 1 | O4: =$Q162 -> 1 | R4: ="C) " & IF($S4=0,"",ROUND($S4,2) & "-" & ROUND($T4/$D$9,2)) -> C) 1.13-1.13 | S4: =1.1*1.02*1.006 -> 1.128732 | T4: =$S4*$D$9 -> 30.994981 | X4: x | Y4: x | Z4: x | AA4: x | AB4: x | AC4: x | AD4: x
B5: CLIENTs REF: | C5: =IF($D$6="VAT INCLUDED",1.18,1)*(1-$Q5)*$C$1 -> 1 | D5: Tender | F5: Controls ECA | G5: TRUE | I5: 5 | J5: =$Q113 -> 1 | K5: =$Q123 -> 1 | L5: =$Q133 -> 1 | M5: =$Q143 -> 1 | N5: =$Q153 -> 1 | O5: =$Q163 -> 1 | R5: ="D) " & IF($S5=0,"",ROUND($S5,2) & "-" & ROUND($T5/$D$9,2)) -> D) 1.23-1.94 | S5: =1.2*1.02*1.006 -> 1.231344 | T5: =$S5*43.32 -> 53.341822 | X5: x | Y5: x | Z5: x | AA5: x | AB5: x | AC5: x | AD5: x
B6: VAT: | C6: =IF($D$6="VAT INCLUDED",1.18,1)*(1-$Q6)*$C$1 -> 1 | D6: VAT EXCL. | F6: Testing and Commissiong | G6: TRUE | I6: 6 | J6: =$Q114 -> 1 | K6: =$Q124 -> 1 | L6: =$Q134 -> 1 | M6: =$Q144 -> 1 | N6: =$Q154 -> 1 | O6: =$Q164 -> 1 | R6: ="E) " & IF($S6=0,"",ROUND($S6,2) & "-" & ROUND($T6/$D$9,2)) -> E) 1.23-2.37 | S6: =1.2*1.02*1.006 -> 1.231344 | T6: =$S6*52.92 -> 65.162724 | X6: x | Y6: x | Z6: x | AA6: x | AB6: x | AC6: x | AD6: x
B7: SAVED ON: | C7: =IF($D$6="VAT INCLUDED",1.18,1)*(1-$Q7)*$C$1 -> 1 | D7: 45694 | F7: Fire Stopping rates | G7: TRUE | I7: 7 | J7: =$Q115 -> 1 | K7: =$Q125 -> 1 | L7: =$Q135 -> 1 | M7: =$Q145 -> 1 | N7: =$Q155 -> 1 | R7: ="F) " & IF($S7=0,"",ROUND($S7,2) & "-" & ROUND($T7/$D$9,2)) -> F) 1.23-1.23 | S7: =1.2*1.02*1.006 -> 1.231344 | T7: =$S7*$D$9 -> 33.812706 | X7: x | Y7: x | Z7: x | AA7: x | AB7: x | AC7: x | AD7: x
B8: ESTIMATOR: | C8: =IF($D$6="VAT INCLUDED",1.18,1)*(1-$Q8)*$C$1 -> 1 | D8: T.Sammut | F8: Main Equipment (Gen Set / Main Switchboards) | G8: TRUE | I8: 8 | J8: =$Q116 -> 1 | K8: =$Q126 -> 1 | L8: =$Q136 -> 1 | M8: =$Q146 -> 1 | N8: =$Q156 -> 1 | R8: ="G) " & IF($S8=0,"",ROUND($S8,2) & "-" & ROUND($T8/$D$9,2)) -> G) 1.18-1.18 | S8: =1.15*1.02*1.006 -> 1.180038 | T8: =$S8*$D$9 -> 32.403843 | X8: x | Y8: x | Z8: x | AA8: x | AB8: x | AC8: x | AD8: x
B9: LAB. COST: | C9: =IF($D$6="VAT INCLUDED",1.18,1)*(1-$Q9)*$C$1 -> 1 | D9: 27.46 | E9: Cost for 2025 | F9: DBs and Changeover | G9: TRUE | I9: 9 | J9: =$Q117 -> 1 | K9: =$Q127 -> 1 | L9: =$Q137 -> 1 | M9: =$Q147 -> 1 | N9: =$Q157 -> 1 | R9: ="H) " & IF($S9=0,"",ROUND($S9,2) & "-" & ROUND($T9/$D$9,2)) -> H) 1.18-1.18 | S9: =1.15*1.02*1.006 -> 1.180038 | T9: =$S9*$D$9 -> 32.403843 | X9: x | Y9: x | Z9: x | AA9: x | AB9: x | AC9: x | AD9: x
C10: =IF($D$6="VAT INCLUDED",1.18,1)*(1-$Q10)*$C$1 -> 1 | F10: Armoured Cables | G10: TRUE | I10: 10 | J10: =$Q118 -> 1 | K10: =$Q128 -> 1 | L10: =$Q138 -> 1 | M10: =$Q148 -> 1 | N10: =$Q158 -> 1 | O10: =Q108 -> 1 | R10: =" I) " & IF($S10=0,"",ROUND($S10,2) & "-" & ROUND($T10/$D$9,2)) -> I) 1.18-1.18 | S10: =1.15*1.02*1.006 -> 1.180038 | T10: =$S10*$D$9 -> 32.403843 | X10: x | Y10: x | Z10: x | AA10: x | AB10: x | AC10: x | AD10: x
C11: =IF($D$6="VAT INCLUDED",1.18,1)*(1-$Q11)*$C$1 -> 1 | R11: ="J) " & IF($S11=0,"",ROUND($S11,2) & "-" & ROUND($T11/$D$9,2)) -> J) | X11: x | Y11: x | Z11: x | AA11: x | AB11: x | AC11: x | AD11: x
C12: =IF($D$6="VAT INCLUDED",1.18,1)*(1-$Q12)*$C$1 -> 1 | G12: SYSTEMS | H12: SYSTEMS | I12: SYSTEMS | J12: SYSTEMS | K12: SYSTEMS | L12: SYSTEMS | M12: SYSTEMS | N12: SYSTEMS | O12: SYSTEMS | P12: SYSTEMS | R12: MIXED - X,Y ) | S12: MAT MU | T12: LAB RATE | X12: x | Y12: x | Z12: x | AA12: x | AB12: x | AC12: x | AD12: x
B13: MATERIAL & LABOUR SUMMARY | G13: ItemCode | H13: CostCode | I13: MAKE | J13: PART_NO | K13: MARKUP | L13: TYPE | M13: LIST_P | N13: SET | O13: FIX | P13: DATE | Q13: %Dsct in BOQ | R13: MATMU-LABMU | S13: MAT CONT >> | T13: =SUM(Q108:Q164)/57 -> 1
B14: =IF($D$6<>"VAT EXCL.", "QUOTE ISSUED WITH VAT INCLUDED", "") | X14: x | Y14: x | Z14: x | AA14: x | AB14: x | AC14: x | AD14: x
Q15: =(C72-F35)/C72 -> 0 | R15: Average Discount applied in BOQ (Q2-Q12) | X15: x | Y15: x | Z15: x | AA15: x | AB15: x | AC15: x | AD15: x
B16: =IF($W$1<>"BOQ", "DIFF SET TO " & W1,"") | Q16: =(F35-E35)/F35 -> 0.0969519 | R16: Average Discount applied on Totals (Q23-Q32) | X16: x | Y16: x | Z16: x | AA16: x | AB16: x | AC16: x | AD16: x
Q17: =F74 -> 0.0969519 | R17: Overall Discount
B18: =IF(AND(G1,G2,G3,G4,G5,G6,G7,G8,G9,G10,H1)=TRUE, "", "CHECKLIST INCOMPLETE !" )
B19: =IF(ABS(SUM(A23:A32))>100,"[Discy A-J] are high, Check it out."," ") | Q19: =R83 -> 1.0825877 | R19: Overall Markup (Final Selling Excl.VAT/Total Cost )
E21: DISCOUNTED | F21: SELLING | Q21: % Discnt | R21: MATERIAL | T21: LABOUR
A22: Discy.A-J | B22: Markup/LRate | E22: ="SELLING " & $Q$1 -> SELLING € | F22: =$Q$1 -> € | G22: VAT/DISC | H22: MU | I22: LABRATE | J22: LABCOST | Q22: on Totals | R22: € | T22: Pair Hrs.
A23: =IF($F23=0,"",($F23/$C2)-($R23*$S2+$T23*$T2)) -> -2.7910798 | B23: =IF(F23=0,"",IF(R23=0,"A) "&"---, "&ROUND(($F23/$C2-($R23*$S2))/$T23,2),IF(T23=0,"A) "&ROUND(($F23/$C2)/$R23,2),"A) "&ROUND(($F23/$C2-($T23*$T2))/$R23,2)&", " &ROUND(($F23/$C2-($R23*$S2))/$T23,2)))) -> A) 1.23, 33.81 | D23: =IF($F2="","",$F2) -> Electrical | E23: =F23*(1-Q23) -> 593489.32 | F23: =Elec_Est!F11462+Fire_Stopping_Est!F401 -> 657206.77 | G23: =C2 -> 1 | H23: =$S2 -> 1.231344 | I23: =$T2 -> 33.812706 | J23: =$D$9 -> 27.46 | Q23: 0.0969519 | R23: =Elec_Est!R11462+Fire_Stopping_Est!R401 -> 349590.82 | T23: =Elec_Est!T11462+Fire_Stopping_Est!T401 -> 6705.852
A24: =IF($F24=0,"",($F24/$C3)-($R24*$S3+$T24*$T3)) -> -0.31921065 | B24: =IF(F24=0,"",IF(R24=0,"A) "&"---, "&ROUND(($F24/$C3-($R24*$S3))/$T24,2),IF(T24=0,"A) "&ROUND(($F24/$C3)/$R24,2),"A) "&ROUND(($F24/$C3-($T24*$T3))/$R24,2)&", " &ROUND(($F24/$C3-($R24*$S3))/$T24,2)))) -> A) 1.13, 30.96 | D24: =IF($F3="","",$F3) -> ELV Installation (NAS Ltd) | E24: =F24*(1-Q24) -> 134683.06 | F24: =Elec_Est!F11463+Fire_Stopping_Est!F402 -> 149142.73 | G24: =C3 -> 1 | H24: =$S3 -> 1.128732 | I24: =$T3 -> 30.994981 | J24: =$D$9 -> 27.46 | Q24: 0.0969519 | R24: =Elec_Est!R11463+Fire_Stopping_Est!R402 -> 131910.84 | T24: =Elec_Est!T11463+Fire_Stopping_Est!T402 -> 8.1
A25: =IF($F25=0,"",($F25/$C4)-($R25*$S4+$T25*$T4)) -> 1.7301422 | B25: =IF(F25=0,"",IF(R25=0,"A) "&"---, "&ROUND(($F25/$C4-($R25*$S4))/$T25,2),IF(T25=0,"A) "&ROUND(($F25/$C4)/$R25,2),"A) "&ROUND(($F25/$C4-($T25*$T4))/$R25,2)&", " &ROUND(($F25/$C4-($R25*$S4))/$T25,2)))) -> A) 1.13 | D25: =IF($F4="","",$F4) -> Lightning Protection System (MCE Ltd) | E25: =F25*(1-Q25) -> 47155.041 | F25: =Elec_Est!F11464+Fire_Stopping_Est!F403 -> 52217.64 | G25: =C4 -> 1 | H25: =$S4 -> 1.128732 | I25: =$T4 -> 30.994981 | J25: =$D$9 -> 27.46 | Q25: 0.0969519 | R25: =Elec_Est!R11464+Fire_Stopping_Est!R403 -> 46260.68 | T25: =Elec_Est!T11464+Fire_Stopping_Est!T403 -> 0
A26: =IF($F26=0,"",($F26/$C5)-($R26*$S5+$T26*$T5)) -> -0.006800032 | B26: =IF(F26=0,"",IF(R26=0,"A) "&"---, "&ROUND(($F26/$C5-($R26*$S5))/$T26,2),IF(T26=0,"A) "&ROUND(($F26/$C5)/$R26,2),"A) "&ROUND(($F26/$C5-($T26*$T5))/$R26,2)&", " &ROUND(($F26/$C5-($R26*$S5))/$T26,2)))) -> A) 1.23, 53.34 | D26: =IF($F5="","",$F5) -> Controls ECA | E26: =F26*(1-Q26) -> 3025.5091 | F26: =Elec_Est!F11465+Fire_Stopping_Est!F404 -> 3350.33 | G26: =C5 -> 1 | H26: =$S5 -> 1.231344 | I26: =$T5 -> 53.341822 | J26: =$D$9 -> 27.46 | Q26: 0.0969519 | R26: =Elec_Est!R11465+Fire_Stopping_Est!R404 -> 2486.95 | T26: =Elec_Est!T11465+Fire_Stopping_Est!T404 -> 5.4
A27: =IF($F27=0,"",($F27/$C6)-($R27*$S6+$T27*$T6)) -> -0.004256832 | B27: =IF(F27=0,"",IF(R27=0,"A) "&"---, "&ROUND(($F27/$C6-($R27*$S6))/$T27,2),IF(T27=0,"A) "&ROUND(($F27/$C6)/$R27,2),"A) "&ROUND(($F27/$C6-($T27*$T6))/$R27,2)&", " &ROUND(($F27/$C6-($R27*$S6))/$T27,2)))) -> A) ---, 65.16 | D27: =IF($F6="","",$F6) -> Testing and Commissiong | E27: =F27*(1-Q27) -> 7997.0418 | F27: =Elec_Est!F11466+Fire_Stopping_Est!F405 -> 8855.61 | G27: =C6 -> 1 | H27: =$S6 -> 1.231344 | I27: =$T6 -> 65.162724 | J27: =$D$9 -> 27.46 | Q27: 0.0969519 | R27: =Elec_Est!R11466+Fire_Stopping_Est!R405 -> 0 | T27: =Elec_Est!T11466+Fire_Stopping_Est!T405 -> 135.9
A28: =IF($F28=0,"",($F28/$C7)-($R28*$S7+$T28*$T7)) -> -0.03534904 | B28: =IF(F28=0,"",IF(R28=0,"A) "&"---, "&ROUND(($F28/$C7-($R28*$S7))/$T28,2),IF(T28=0,"A) "&ROUND(($F28/$C7)/$R28,2),"A) "&ROUND(($F28/$C7-($T28*$T7))/$R28,2)&", " &ROUND(($F28/$C7-($R28*$S7))/$T28,2)))) -> A) 1.23, 33.81 | D28: =IF($F7="","",$F7) -> Fire Stopping rates | E28: =F28*(1-Q28) -> 49942.985 | F28: =Elec_Est!F11467+Fire_Stopping_Est!F406 -> 55304.9 | G28: =C7 -> 1 | H28: =$S7 -> 1.231344 | I28: =$T7 -> 33.812706 | J28: =$D$9 -> 27.46 | Q28: 0.0969519 | R28: =Elec_Est!R11467+Fire_Stopping_Est!R406 -> 28788.4 | T28: =Elec_Est!T11467+Fire_Stopping_Est!T406 -> 587.25
A29: =IF($F29=0,"",($F29/$C8)-($R29*$S8+$T29*$T8)) -> 0.0037939126 | B29: =IF(F29=0,"",IF(R29=0,"A) "&"---, "&ROUND(($F29/$C8-($R29*$S8))/$T29,2),IF(T29=0,"A) "&ROUND(($F29/$C8)/$R29,2),"A) "&ROUND(($F29/$C8-($T29*$T8))/$R29,2)&", " &ROUND(($F29/$C8-($R29*$S8))/$T29,2)))) -> A) 1.18, 32.4 | D29: =IF($F8="","",$F8) -> Main Equipment (Gen Set / Main Switchboards) | E29: =F29*(1-Q29) -> 258266.88 | F29: =Elec_Est!F11468+Fire_Stopping_Est!F407 -> 285994.6 | G29: =C8 -> 1 | H29: =$S8 -> 1.180038 | I29: =$T8 -> 32.403843 | J29: =$D$9 -> 27.46 | Q29: 0.0969519 | R29: =Elec_Est!R11468+Fire_Stopping_Est!R407 -> 236420.24 | T29: =Elec_Est!T11468+Fire_Stopping_Est!T407 -> 216.324
A30: =IF($F30=0,"",($F30/$C9)-($R30*$S9+$T30*$T9)) -> -0.019634288 | B30: =IF(F30=0,"",IF(R30=0,"A) "&"---, "&ROUND(($F30/$C9-($R30*$S9))/$T30,2),IF(T30=0,"A) "&ROUND(($F30/$C9)/$R30,2),"A) "&ROUND(($F30/$C9-($T30*$T9))/$R30,2)&", " &ROUND(($F30/$C9-($R30*$S9))/$T30,2)))) -> A) 1.18, 32.4 | D30: =IF($F9="","",$F9) -> DBs and Changeover | E30: =F30*(1-Q30) -> 64335.296 | F30: =Elec_Est!F11469+Fire_Stopping_Est!F408 -> 71242.38 | G30: =C9 -> 1 | H30: =$S9 -> 1.180038 | I30: =$T9 -> 32.403843 | J30: =$D$9 -> 27.46 | Q30: 0.0969519 | R30: =Elec_Est!R11469+Fire_Stopping_Est!R408 -> 50142.734 | T30: =Elec_Est!T11469+Fire_Stopping_Est!T408 -> 372.5505
A31: =IF($F31=0,"",($F31/$C10)-($R31*$S10+$T31*$T10)) -> 1.1836456 | B31: =IF(F31=0,"",IF(R31=0,"A) "&"---, "&ROUND(($F31/$C10-($R31*$S10))/$T31,2),IF(T31=0,"A) "&ROUND(($F31/$C10)/$R31,2),"A) "&ROUND(($F31/$C10-($T31*$T10))/$R31,2)&", " &ROUND(($F31/$C10-($R31*$S10))/$T31,2)))) -> A) 1.18, 32.41 | D31: =IF($F10="","",$F10) -> Armoured Cables | E31: =F31*(1-Q31) -> 319323.99 | F31: =Elec_Est!F11470+Fire_Stopping_Est!F409 -> 353606.85 | G31: =C10 -> 1 | H31: =$S10 -> 1.180038 | I31: =$T10 -> 32.403843 | J31: =$D$9 -> 27.46 | Q31: 0.0969519 | R31: =Elec_Est!R11470+Fire_Stopping_Est!R409 -> 280841.95 | T31: =Elec_Est!T11470+Fire_Stopping_Est!T409 -> 685.15 | V31: Value of Rev A - Discounted | W31: 1615942.8
A32: =IF($F32=0,"",($F32/$C11)-($R32*$S11+$T32*$T11)) | B32: =IF(F32=0,"",IF(R32=0,"A) "&"---, "&ROUND(($F32/$C11-($R32*$S11))/$T32,2),IF(T32=0,"A) "&ROUND(($F32/$C11)/$R32,2),"A) "&ROUND(($F32/$C11-($T32*$T11))/$R32,2)&", " &ROUND(($F32/$C11-($R32*$S11))/$T32,2)))) | D32: =IF($F11="","",$F11) | E32: =F32*(1-Q32) -> 0 | F32: =Elec_Est!F11471+Fire_Stopping_Est!F410 -> 0 | G32: =C11 -> 1 | H32: =$S11 -> 0 | I32: =$T11 -> 0 | J32: =$D$9 -> 27.46 | R32: =Elec_Est!R11471+Fire_Stopping_Est!R410 -> 0 | T32: =Elec_Est!T11471+Fire_Stopping_Est!T410 -> 0
C33: MIXED
X34: changed interval of brackets from 1.2m to 1.5m
A35: Discy.L | B35: =Summary!E54 -> 1478219.1 | E35: =SUM(E23:E32) -> 1478219.1 | F35: =SUM(F23:F32) -> 1636921.8 | R35: =SUM(R23:R32) -> 1126442.6 | T35: =SUM(T23:T32) -> 8716.5265 | V35: =W31-E35 -> 137723.65 | X35: reduced labour for the stainless steel conduit
A36: =IF(A39=0,"0.00",A39-(A38*A37)) -> 0.00 | B36: BOQ TOTAL | E36: ="ESTIM TOTAL (" & $Q$1 & ")" -> ESTIM TOTAL (€) | X36: removed the 5% contingency on all cables
A37: 1.125 | B37: <1 Actual LabCont | R37: =R165 -> 1126454.5 | S37: C.C.Totals | T37: =T165 -> 8703.3967 | X37: reduced the 50% contingency to 10% on fire barriers material cost
B38: <2 Phrs @ 1.00 | X38: deducted 5% discount from NAS Ltd quote
B39: <3 Phrs @ Actual | Q39: Discy.T >> | R39: =R37-R35 -> 11.903889 | S39: PRINT | T39: =T37-T35 -> -13.129731 | X39: reduced mark ups by 5%
X40: reduced rate for galvanised conduit
B41: Values Only on : | D41: 45705 | E41: 2372471.2 | F41: 2372471.2 | R41: 1470470.4 | T41: 11882.59 | V41: =E41-E35 -> 894252.09 | W41: total cost saving | X41: Updated rate in item 7.052 - Data
X42: Removed 25% contingency for scissors lift
E43: Deduction 1 | F43: 250866.93 | R43: 93653.823 | T43: 1121.275 | X43: Reduced labour hours for installation of fire barriers
E44: Deduction 2 | F44: 399264.48 | R44: 124598.72 | T44: 1621.86 | X44: Deducted stainless steel conduit for armoured cables in freezer
E45: Deduction 3 | F45: =F41-F35 -> 735549.41 | R45: =R41-R35 -> 344027.81 | T45: =T41-T35 -> 3166.0635 | X45: Reduced scissors lift rate in ware house bracketing
A46: REMARKS: | D46: As Awarded | E46: 1478219.1 | F46: 1636921.8 | R46: 1126442.6 | T46: 8716.5265 | X46: Reduced price of OVR for EV Chargers
A47: 1) VAT and Duties as above. | X47: Added more take offs for external lights
A48: 2) | V48: Mechanical BOQs (As Awarded) | X48: Saddles for stainless steel at 1.5metres
V49: Sprinkler System | W49: 341763.49 | X49: Reduced scissors lift in item 7.052 - data
V50: HVAC | W50: 471773.83 | X50: Reduced small cable trunking labour - rate includes fittings
A51: ESTIMATOR: | D51: =D8 -> T.Sammut | Q51: APPROVED BY: | V51: Fire fighting | W51: 797820.23 | X51: Lowered bracket labour for lighting in warehouse - rate 007
V52: Fire Stopping | W52: 10422.92 | X52: Reduced gen set control cable length
A53: SIGNED: | Q53: DATE APPROVED: | V53: Total | W53: =SUM(W49:W52) -> 1621780.5 | X53: Reduced rate for socket outlets in item 4.319
A55: FILE LOCATION: | D55: =CELL("filename") -> https://d.docs.live.net/d8e42587b76b10ba/Documents/Visual Code Studio/Claude/BMS-Attribution-Model/projects/J01111_Brit_Hotel/[EL25_0662B_Brittania_Hotel_Elec_Revised_Estim_B.xlsx]Elec_Est
B57: PANTA CONTRACTING LTD. - ELECTRICAL DIVISION | X57: Second deductions | AA57: 07.04.2025
B58: CONTRACT / VARIATION INPUT DOCUMENT | X58: 10% deduction from labour on multicore armoured cables only
S59: Copy to:- | X59: Lighting and power rates updated
D60: Client: | E60: =D1 -> Quintano Foods Ltd. | S60: Ms. S. Magri | X60: Reduced data galvanised, LSZH and stainless steel conduit rates
D61: Project: | E61: =D2 -> Warehouse at tal-Handaq, Qormi | S61: Mr. K. Micallef | X61: Cost of EV chargers reduced
D62: Job Description: | E62: =D3 -> Electrical and ELV installations (Rev A) | S62: Mr. A. Sciberras | X62: Original Cost of fire barriers split on Elec and ELV
D63: Quote No: | E63: =D4 -> EL25-0062A | X63: Reduced cost of scissors lift (now €14,000 below the cost required for the project)
D64: Client's Ref: | E64: =D5 -> Tender | X64: Reduced cost of control panels by Raymond Muscat
S65: File:- | X65: Changed distribution boards brand from Hager to Schneider Electric with an additional cost of €2,500 not covered in our estimates
D66: File No: | X66: Introduction of a protective rain hood and powder coating for the external switchboard. Addiitonal cost to be incurred by Panta.
D67: Ext. Ref:
X69: Third reductions (Redesign - Rev A) | AA69: 12.06.2025
E70: Contract /Variation (Excl. VAT) | X70: Updated BOQ and drawings from consultant
C72: =IF($A$33="MIXED",F23/(1-Q2)+F24/(1-Q3)+F25/(1-Q4)+F26/(1-Q5)+F27/(1-Q6)+F28/(1-Q7)+F29/(1-Q8)+F30/(1-Q9)+F31/(1-Q10)+F32/(1-Q11)-SUM(A23:A32), F23/(1-Q2)+F24/(1-Q3)+F25/(1-Q4)+F26/(1-Q5)+F27/(1-Q6)+F28/(1-Q7)+F29/(1-Q8)+F30/(1-Q9)+F31/(1-Q10)+F32/(1-Q11)) -> 1636921.8 | E72: Estim.Sell before Discounts excl.VAT (€): | F72: =IF(D6="VAT INCLUDED",C72/($C$1*1.18),C72/$C$1) -> 1636921.8 | X72: Fourth reductions - Rev B | AA72: 14.07.2025
X73: Corrected error for socket outlets - item 4.379
E74: Overall Discount: | F74: =(F72-F75)/F72 -> 0.0969519 | X74: Upgraded price for light fittings as per latest clarifications
E75: Final Sell after Discounts excl.VAT (€): | F75: =IF(D6="VAT INCLUDED",E35/($C$1*1.18),E35/$C$1) -> 1478219.1 | X75: Reduced labour hours by 10%
X76: Included additional discount from NAS for ELV systems (new factor x 0.873)
E77: Labour Rate - | F77: =$D$9 -> 27.46 | R77: Mech. Cost to us | X77: Included additional discount from NAS for Generator set and changed genrator flue from Panta to NAS
D80: Mat. Cost | E80: Labour | F80: Total Cost | R80: Sell Excl.VAT / Total Cost
D81: € | E81: Pair.Hrs | F81: €
D83: =R165 -> 1126454.5 | E83: =T165 -> 8703.3967 | F83: =R165+S165 -> 1365449.8 | R83: =IF(F83=0,0,F75/F83) -> 1.0825877
D84: ( From CostCode Totals )
R87: Advanced Payment:
R88: Retention:
R90: Awarded Date:
R91: Estimated Start Date:
R92: Estimated Completion Date:
D93: .................
D94: A. Sciberras | R94: Date issued:
D95: =NOW() -> 46114.371
D98: PANTA CONTRACTING LTD. - ELECTRICAL DIVISION
D99: ELECTRICAL AND ELV CONTRACT / VARIATION BUDGET COST
D101: Project: | E101: =E61 -> Warehouse at tal-Handaq, Qormi
D102: Job Desc: | E102: =E62 -> Electrical and ELV installations (Rev A)
D103: Client's Ref: | E103: =E64 -> Tender
D106: COSTCODE | F106: Cost | Q106: Mat. | R106: Mat Cost | S106: Lab Cost @ | T106: Labour
F107: Code | Q107: Cont. | R107: € | S107: =$D$9 -> 27.46 | T107: Pair.Hrs
B108: V:56 | D108: BOQ RateOnly Items | P108: FIX | Q108: 1 | Y108: Original | AD108: Difference
B109: 1(J) | C109: cc | D109: Erection materials | F109: 501 | P109: 1 | Q109: 1 | R109: =Elec_Est!R11483+Fire_Stopping_Est!R422 -> 42863.204 | S109: =T109*$D$9 -> 9080.3265 | T109: =Elec_Est!T11483+Fire_Stopping_Est!T422 -> 330.67467 | Y109: 51220.26 | Z109: 18120.854 | AA109: 659.9 | AD109: =Y109-R109 -> 8357.0555 | AE109: =Z109-S109 -> 9040.5275 | AF109: =AA109-T109 -> 329.22533
B110: 2 | C110: cc | D110: Busbar Trunking | F110: 505 | P110: 1 | Q110: 1 | R110: =Elec_Est!R11484+Fire_Stopping_Est!R423 -> 0 | S110: =T110*$D$9 -> 0 | T110: =Elec_Est!T11484+Fire_Stopping_Est!T423 -> 0 | Y110: 0 | Z110: 0 | AA110: 0 | AD110: =Y110-R110 -> 0 | AE110: =Z110-S110 -> 0 | AF110: =AA110-T110 -> 0
B111: 3 | C111: cc | D111: Switchgear | F111: 510 | P111: 2 | Q111: 1 | R111: =Elec_Est!R11485+Fire_Stopping_Est!R424 -> 222629.17 | S111: =T111*$D$9 -> 16762.271 | T111: =Elec_Est!T11485+Fire_Stopping_Est!T424 -> 610.425 | V111: 4822.42 | X111: 212970.15 | Y111: 255857.79 | Z111: 19036.645 | AA111: 693.25 | AD111: =Y111-R111 -> 33228.618 | AE111: =Z111-S111 -> 2274.3745 | AF111: =AA111-T111 -> 82.825
B112: 4 | C112: cc | D112: MCC Equipment | F112: 511 | P112: 2 | Q112: 1 | R112: =Elec_Est!R11486+Fire_Stopping_Est!R425 -> 0 | S112: =T112*$D$9 -> 0 | T112: =Elec_Est!T11486+Fire_Stopping_Est!T425 -> 0 | Y112: 0 | Z112: 0 | AA112: 0 | AD112: =Y112-R112 -> 0 | AE112: =Z112-S112 -> 0 | AF112: =AA112-T112 -> 0
B113: 5 | C113: cc | D113: BMS Equipment | F113: 512 | P113: 2 | Q113: 1 | R113: =Elec_Est!R11487+Fire_Stopping_Est!R426 -> 0 | S113: =T113*$D$9 -> 0 | T113: =Elec_Est!T11487+Fire_Stopping_Est!T426 -> 0 | Y113: 0 | Z113: 0 | AA113: 0 | AD113: =Y113-R113 -> 0 | AE113: =Z113-S113 -> 0 | AF113: =AA113-T113 -> 0
B114: 6 | C114: cc | D114: PVC Pipes / Ducts | F114: 520 | P114: 1 | Q114: 1 | R114: =Elec_Est!R11488+Fire_Stopping_Est!R427 -> 710 | S114: =T114*$D$9 -> 1223.343 | T114: =Elec_Est!T11488+Fire_Stopping_Est!T427 -> 44.55 | Y114: 710 | Z114: 1359.27 | AA114: 49.5 | AD114: =Y114-R114 -> 0 | AE114: =Z114-S114 -> 135.927 | AF114: =AA114-T114 -> 4.95
B115: 7 | C115: cc | D115: High/medium voltage switchgear | F115: 530 | P115: 2 | Q115: 1 | R115: =Elec_Est!R11489+Fire_Stopping_Est!R428 -> 0 | S115: =T115*$D$9 -> 0 | T115: =Elec_Est!T11489+Fire_Stopping_Est!T428 -> 0 | Y115: 0 | Z115: 0 | AA115: 0 | AD115: =Y115-R115 -> 0 | AE115: =Z115-S115 -> 0 | AF115: =AA115-T115 -> 0
B116: 8 | C116: cc | D116: Power Transformers | F116: 550 | P116: 2 | Q116: 1 | R116: =Elec_Est!R11490+Fire_Stopping_Est!R429 -> 0 | S116: =T116*$D$9 -> 0 | T116: =Elec_Est!T11490+Fire_Stopping_Est!T429 -> 0 | Y116: 0 | Z116: 0 | AA116: 0 | AD116: =Y116-R116 -> 0 | AE116: =Z116-S116 -> 0 | AF116: =AA116-T116 -> 0
...

Sheet Elec_Rates
B1: CLIENT: | C1: =ML_Sum!$C1 -> 1 | D1: =ML_Sum!$D1 -> Quintano Foods Ltd. | F1: =ML_Sum!$F1 -> 0 | I1: 1 | J1: =ML_Sum!$J1 -> 1 | K1: =ML_Sum!$K1 -> 1 | L1: =ML_Sum!$L1 -> 1 | M1: =ML_Sum!$M1 -> 1 | N1: =ML_Sum!$N1 -> 1 | O1: =ML_Sum!$O1 -> 1 | Q1: =ML_Sum!$Q1 -> € | R1: R/Lab Cont | S1: =ML_Sum!$S1 -> R | T1: =ML_Sum!$T1 -> 0.9 | U1: =ML_Sum!W1 -> BOQ | V1: INCL | W1: MULT | X1: AREA | Y1: BOQ | Z1: TDWG | AA1: ACT | AB1: DIFF | AD1: 0
B2: PROJECT: | C2: =ML_Sum!$C2 -> 1 | D2: =ML_Sum!$D2 -> Warehouse at tal-Handaq, Qormi | F2: =ML_Sum!$F2 -> Electrical | I2: 2 | J2: =ML_Sum!$J2 -> 1 | K2: =ML_Sum!$K2 -> 1 | L2: =ML_Sum!$L2 -> 1 | M2: =ML_Sum!$M2 -> 1 | N2: =ML_Sum!$N2 -> 1 | O2: =ML_Sum!$O2 -> 1 | Q2: =ML_Sum!$Q2 -> 0 | R2: mu_A | S2: =ML_Sum!$S2 -> 1.231344 | T2: =ML_Sum!$T2 -> 33.812706 | AD2: Electrical
B3: JOB DESC: | C3: =ML_Sum!$C3 -> 1 | D3: =ML_Sum!$D3 -> Electrical and ELV installations (Rev A) | F3: =ML_Sum!$F3 -> ELV Installation (NAS Ltd) | I3: 3 | J3: =ML_Sum!$J3 -> 1 | K3: =ML_Sum!$K3 -> 1 | L3: =ML_Sum!$L3 -> 1 | M3: =ML_Sum!$M3 -> 1 | N3: =ML_Sum!$N3 -> 1 | O3: =ML_Sum!$O3 -> 1 | Q3: =ML_Sum!$Q3 -> 0 | R3: mu_B | S3: =ML_Sum!$S3 -> 1.128732 | T3: =ML_Sum!$T3 -> 30.994981 | AD3: ELV Installation (NAS Ltd)
B4: QUOTE No: | C4: =ML_Sum!$C4 -> 1 | D4: =ML_Sum!$D4 -> EL25-0062A | F4: =ML_Sum!$F4 -> Lightning Protection System (MCE Ltd) | I4: 4 | J4: =ML_Sum!$J4 -> 1 | K4: =ML_Sum!$K4 -> 1 | L4: =ML_Sum!$L4 -> 1 | M4: =ML_Sum!$M4 -> 1 | N4: =ML_Sum!$N4 -> 1 | O4: =ML_Sum!$O4 -> 1 | Q4: =ML_Sum!$Q4 -> 0 | R4: mu_C | S4: =ML_Sum!$S4 -> 1.128732 | T4: =ML_Sum!$T4 -> 30.994981 | AD4: Lightning Protection System (MCE Ltd)
B5: CLIENTs REF: | C5: =ML_Sum!$C5 -> 1 | D5: =ML_Sum!$D5 -> Tender | F5: =ML_Sum!$F5 -> Controls ECA | I5: 5 | J5: =ML_Sum!$J5 -> 1 | K5: =ML_Sum!$K5 -> 1 | L5: =ML_Sum!$L5 -> 1 | M5: =ML_Sum!$M5 -> 1 | N5: =ML_Sum!$N5 -> 1 | O5: =ML_Sum!$O5 -> 1 | Q5: =ML_Sum!$Q5 -> 0 | R5: mu_D | S5: =ML_Sum!$S5 -> 1.231344 | T5: =ML_Sum!$T5 -> 53.341822 | AD5: Controls ECA
B6: VAT/DUTIES: | C6: =ML_Sum!$C6 -> 1 | D6: =ML_Sum!$D6 -> VAT EXCL. | F6: =ML_Sum!$F6 -> Testing and Commissiong | I6: 6 | J6: =ML_Sum!$J6 -> 1 | K6: =ML_Sum!$K6 -> 1 | L6: =ML_Sum!$L6 -> 1 | M6: =ML_Sum!$M6 -> 1 | N6: =ML_Sum!$N6 -> 1 | O6: =ML_Sum!$O6 -> 1 | Q6: =ML_Sum!$Q6 -> 0 | R6: mu_E | S6: =ML_Sum!$S6 -> 1.231344 | T6: =ML_Sum!$T6 -> 65.162724 | AD6: Testing and Commissiong
B7: SAVED ON: | C7: =ML_Sum!$C7 -> 1 | D7: 39364 | F7: =ML_Sum!$F7 -> Fire Stopping rates | I7: 7 | J7: =ML_Sum!$J7 -> 1 | K7: =ML_Sum!$K7 -> 1 | L7: =ML_Sum!$L7 -> 1 | M7: =ML_Sum!$M7 -> 1 | N7: =ML_Sum!$N7 -> 1 | O7: =ML_Sum!$O7 -> 0 | Q7: =ML_Sum!$Q7 -> 0 | R7: mu_F | S7: =ML_Sum!$S7 -> 1.231344 | T7: =ML_Sum!$T7 -> 33.812706 | AD7: Fire Stopping rates
B8: ESTIMATOR: | C8: =ML_Sum!$C8 -> 1 | D8: =ML_Sum!$D8 -> T.Sammut | F8: =ML_Sum!$F8 -> Main Equipment (Gen Set / Main Switchboards) | I8: 8 | J8: =ML_Sum!$J8 -> 1 | K8: =ML_Sum!$K8 -> 1 | L8: =ML_Sum!$L8 -> 1 | M8: =ML_Sum!$M8 -> 1 | N8: =ML_Sum!$N8 -> 1 | O8: =ML_Sum!$O8 -> 0 | Q8: =ML_Sum!$Q8 -> 0 | R8: mu_G | S8: =ML_Sum!$S8 -> 1.180038 | T8: =ML_Sum!$T8 -> 32.403843 | AD8: 0
B9: LABOUR RATE: | C9: =ML_Sum!$C9 -> 1 | D9: =ML_Sum!$D9 -> 27.46 | F9: =ML_Sum!$F9 -> DBs and Changeover | I9: 9 | J9: =ML_Sum!$J9 -> 1 | K9: =ML_Sum!$K9 -> 1 | L9: =ML_Sum!$L9 -> 1 | M9: =ML_Sum!$M9 -> 1 | N9: =ML_Sum!$N9 -> 1 | O9: =ML_Sum!$O9 -> 0 | Q9: =ML_Sum!$Q9 -> 0 | R9: mu_H | S9: =ML_Sum!$S9 -> 1.180038 | T9: =ML_Sum!$T9 -> 32.403843 | AD9: 0
C10: =ML_Sum!$C10 -> 1 | F10: =ML_Sum!$F10 -> Armoured Cables | I10: 10 | J10: =ML_Sum!$J10 -> 1 | K10: =ML_Sum!$K10 -> 1 | L10: =ML_Sum!$L10 -> 1 | M10: =ML_Sum!$M10 -> 1 | N10: =ML_Sum!$N10 -> 1 | O10: =ML_Sum!$O10 -> 1 | Q10: =ML_Sum!$Q10 -> 0 | R10: mu_I | S10: =ML_Sum!$S10 -> 1.180038 | T10: =ML_Sum!$T10 -> 32.403843 | AD10: 0
C11: =ML_Sum!$C11 -> 1 | F11: =ML_Sum!$F11 -> 0 | Q11: =ML_Sum!$Q11 -> 0 | R11: mu_J | S11: =ML_Sum!$S11 -> 0 | T11: =ML_Sum!$T11 -> 0 | AD11: 0
C12: =ML_Sum!$C12 -> 1 | F12: =ML_Sum!$F12 -> 0 | Q12: =ML_Sum!$Q12 -> 0 | R12: MIXED | S12: =ML_Sum!$S12 -> MAT MU | T12: =ML_Sum!$T12 -> LAB RATE | AD12: 0
G13: I_CODE | H13: C_CODE | I13: MAKE | J13: PART_NO | K13: MARKUP | L13: TYPE | M13: LIST_P | N13: P_FACT | O13: FIX | P13: DATE | Q13: %Dsct in BOQ | R13: MU TYPE | S13: MAT MU | T13: LAB RATE
C15: t | D15: Item:
D16: Start Typing Header
Q18: Multip
A19: =(1.5*2)+2.5+5.5+5.5+3.5+3.5+4.5+2.5+2.5+5 -> 38 | B19: =Elec_Est!B11547 -> 225 | D19: 001# Light Point Rate (LSZH Conduit) | F19: Remained as cost saving 1 | K19: RATE | L19: RATE | Q19: =B19/A19 -> 5.9210526 | R19: =IF($B19=0,0,IF($S$1="R",ROUND(R28/$B19,2),R28/$B19)) -> 18.48 | T19: =IF($B19=0,0,IF($S$1="R",ROUND(T28/$B19,2),T28/$B19)) -> 1.34
D20: Based on: | F20: OK | AD20: OK
A21: =$Q$19 *(40+40+18+44) -> 840.78947 | B21: m | D21: Conduit PVC 20mm HG RATE | F21: LSZH - Ramon | G21: COPV_003 | H21: 700 | I21: GEN | J21: 20mm | O21: 1 | P21: 42213 | Q21: 1.8 | R21: =$A21*Q21 -> 1513.4211 | S21: 0.13 | T21: =$A21*S21*$T$1 -> 98.372368 | AD21: LSZH - Ramon
A22: =$Q$19 *((402+455+425+420)) -> 10077.632 | B22: m | D22: Wiring Cable 1c 1.5 mm2 PVC Non-Arm | E22: AJ Electric | F22: LSZH | G22: CASC_017 | H22: 615 | I22: CRO | K22: 02-002 | O22: 2 | P22: 38988 | Q22: =0.2*0.95 -> 0.19 | R22: =$A22*Q22 -> 1914.75 | S22: 0.015 | T22: =$A22*S22*$T$1 -> 136.04803 | AD22: LSZH
A23: =$Q$19 *(4+4+12+12+8+8+8) -> 331.57895 | B23: No | D23: WHITE Ceiling Rose | G23: WACC_037 | H23: 705 | I23: (__) | J23: China | O23: 3 | P23: 39128 | Q23: 0.93 | R23: =$A23*Q23 -> 308.36842 | S23: 0.17 | T23: =$A23*S23*$T$1 -> 50.731579
A24: =$Q$19 *(4+4+12+12+8+8+8) -> 331.57895 | B24: m | D24: Wiring Cable 3c 1.0 mm2 PVC Non-Arm | G24: CAMC_047 | H24: 616 | I24: CRO | J24: 1.0mm2 | K24: 03-001 | O24: 2 | P24: 40767 | Q24: 1.1 | R24: =$A24*Q24 -> 364.73684 | S24: 0.025 | T24: =$A24*S24*$T$1 -> 7.4605263
A25: =$Q$19 *(5) -> 29.605263 | B25: No | D25: WHITE Switch 1G 2W | E25: ESS | F25: SC-CMA401 | G25: WACC_054 | H25: 705 | I25: BG | J25: 912 | O25: 3 | P25: 34669 | Q25: 1.06 | R25: =$A25*Q25 -> 31.381579 | S25: 0.17 | T25: =$A25*S25*$T$1 -> 4.5296053 | AD25: SC-CMA401
A26: =$Q$19 *(4) -> 23.684211 | B26: No | D26: WHITE Switch 2G 2W | E26: ESS | F26: SC-CMA402 | G26: WACC_055 | H26: 705 | I26: BG | J26: 942 | O26: 3 | P26: 34669 | Q26: 1.1 | R26: =$A26*Q26 -> 26.052632 | S26: 0.17 | T26: =$A26*S26*$T$1 -> 3.6236842 | AD26: SC-CMA402
C27: << ==== TOTAL UNITS | R27: =$A27*Q27 -> 0 | T27: =$A27*S27*$T$1 -> 0
A28: d> | B28: =(R27+T27) -> 0 | D28: Sell_A | E28: =IF($B19=0,0,ROUND(ROUND(($R28*$S$2+($T28*$T$2))/$B19, 2)*$C$2,2)) -> 67.96 | F28: =ROUND($B19*$E28,2) -> 15291 | K28: ITEM | L28: ITEM | R28: =SUM(R20:R27) -> 4158.7105 | T28: =SUM(T20:T27) -> 300.76579 | AD28: 17104.5
Q29: Multip
A30: 5 | B30: =Elec_Est!B11548 -> 22 | D30: 002# Maintaned Emergency Light point rate (LSZH Conduit) | F30: Remained as cost saving 1 | K30: RATE | L30: RATE | Q30: =B30/A30 -> 4.4 | R30: =IF($B30=0,0,IF($S$1="R",ROUND(R37/$B30,2),R37/$B30)) -> 12.85 | T30: =IF($B30=0,0,IF($S$1="R",ROUND(T37/$B30,2),T37/$B30)) -> 0.92
D31: Based on: | F31: OK | AD31: OK
A32: =$Q$30 *(5*2) -> 44 | B32: m | D32: Conduit PVC 20mm HG RATE | F32: LSZH - Ramon | G32: COPV_003 | H32: 700 | I32: GEN | J32: 20mm | O32: 1 | P32: 42213 | Q32: 1.8 | R32: =$A32*Q32 -> 79.2 | S32: 0.13 | T32: =$A32*S32*$T$1 -> 5.148 | AD32: LSZH - Ramon
A33: =$Q$30 *(190) -> 836 | B33: m | D33: Wiring Cable 1c 1.5 mm2 PVC Non-Arm | E33: AJ Electric | F33: LSZH | G33: CASC_017 | H33: 615 | I33: CRO | K33: 02-002 | O33: 2 | P33: 38988 | Q33: =0.2*0.95 -> 0.19 | R33: =$A33*Q33 -> 158.84 | S33: 0.015 | T33: =$A33*S33*$T$1 -> 11.286 | AD33: LSZH
A34: =$Q$30 *(5) -> 22 | B34: No | D34: WHITE Ceiling Rose | G34: WACC_037 | H34: 705 | I34: (__) | J34: China | O34: 3 | P34: 39128 | Q34: 0.93 | R34: =$A34*Q34 -> 20.46 | S34: 0.17 | T34: =$A34*S34*$T$1 -> 3.366
A35: =$Q$30 *(5) -> 22 | B35: m | D35: Wiring Cable 3c 1.0 mm2 PVC Non-Arm | G35: CAMC_047 | H35: 616 | I35: CRO | J35: 1.0mm2 | K35: 03-001 | O35: 2 | P35: 40767 | Q35: 1.1 | R35: =$A35*Q35 -> 24.2 | S35: 0.025 | T35: =$A35*S35*$T$1 -> 0.495
C36: << ==== TOTAL UNITS | R36: =$A36*Q36 -> 0 | T36: =$A36*S36*$T$1 -> 0
A37: d> | B37: =(R36+T36) -> 0 | D37: Sell_A | E37: =IF($B30=0,0,ROUND(ROUND(($R37*$S$2+($T37*$T$2))/$B30, 2)*$C$2,2)) -> 47.01 | F37: =ROUND($B30*$E37,2) -> 1034.22 | K37: ITEM | L37: ITEM | R37: =SUM(R31:R36) -> 282.7 | T37: =SUM(T31:T36) -> 20.295 | AD37: 1156.76
Q38: Multip
A39: =5+4+7+15+10+5+3 -> 49 | B39: =Elec_Est!B11549 -> 315 | D39: 003# Power Point Rate (LSZH Conduit) | F39: Updated - reduced | K39: RATE | L39: RATE | Q39: =B39/A39 -> 6.4285714 | R39: =IF($B39=0,0,IF($S$1="R",ROUND(R44/$B39,2),R44/$B39)) -> 18.92 | T39: =IF($B39=0,0,IF($S$1="R",ROUND(T44/$B39,2),T44/$B39)) -> 0.89
D40: Based on: | F40: OK | AD40: OK
A41: =$Q$39 *(22+29+55+30+30+18) -> 1182.8571 | B41: m | D41: Conduit PVC 20mm HG RATE | F41: LSZH - Ramon | G41: COPV_003 | H41: 700 | I41: GEN | J41: 20mm | O41: 1 | P41: 42213 | Q41: 1.8 | R41: =$A41*Q41 -> 2129.1429 | S41: 0.13 | T41: =$A41*S41*$T$1 -> 138.39429 | AD41: LSZH - Ramon
A42: =$Q$39 *((105+195+520+230+105+75)) -> 7907.1429 | B42: m | D42: Wiring Cable 1c 4.0 mm2 PVC Non-Arm | E42: AJ Electric | F42: LSZH | G42: CASC_019 | H42: 615 | I42: CRO | K42: 02-004 | O42: 2 | P42: 38988 | Q42: =0.51*0.95 -> 0.4845 | R42: =$A42*Q42 -> 3831.0107 | S42: 0.02 | T42: =$A42*S42*$T$1 -> 142.32857 | AD42: LSZH
C43: << ==== TOTAL UNITS | R43: =$A43*Q43 -> 0 | T43: =$A43*S43*$T$1 -> 0
A44: d> | B44: =(R43+T43) -> 0 | D44: Sell_A | E44: =IF($B39=0,0,ROUND(ROUND(($R44*$S$2+($T44*$T$2))/$B39, 2)*$C$2,2)) -> 53.43 | F44: =ROUND($B39*$E44,2) -> 16830.45 | K44: ITEM | L44: ITEM | R44: =SUM(R40:R43) -> 5960.1536 | T44: =SUM(T40:T43) -> 280.72286 | AD44: 19722.15
Q45: Multip
A46: =8+8.5+5.5+3+3+7.5 -> 35.5 | B46: =Elec_Est!B11550 -> 208.5 | D46: 004# Light point rate (Galvanised Conduit) | F46: Updated - increased | K46: RATE | L46: RATE | Q46: =B46/A46 -> 5.8732394 | R46: =IF($B46=0,0,IF($S$1="R",ROUND(R54/$B46,2),R54/$B46)) -> 46.61 | T46: =IF($B46=0,0,IF($S$1="R",ROUND(T54/$B46,2),T54/$B46)) -> 2.98
A47: =$Q$46 *(A48/B46) -> 62.206705 | D47: Based on:
A48: =$Q$46 *(103+107+30+43+93) -> 2208.338 | B48: m | D48: Conduit Galv. 20mm RATE | G48: COGV_011 | H48: 690 | I48: BAR | J48: 20mm | O48: 1 | P48: 34669 | Q48: 3.03 | R48: =$A48*Q48 -> 6691.2642 | S48: 0.2 | T48: =$A48*S48*$T$1 -> 397.50085
A49: =$Q$46 *((545+440+245+240+490)) -> 11511.549 | B49: m | D49: Wiring Cable 1c 1.5 mm2 PVC Non-Arm | E49: AJ Electric | F49: LSZH | G49: CASC_017 | H49: 615 | I49: CRO | K49: 02-002 | O49: 2 | P49: 38988 | Q49: =0.2*0.95 -> 0.19 | R49: =$A49*Q49 -> 2187.1944 | S49: 0.015 | T49: =$A49*S49*$T$1 -> 155.40592 | AD49: LSZH
A50: =$Q$46 *(3) -> 17.619718 | B50: No | D50: MC Switch 1G 2W 10A | E50: ESS | F50: SC-CL011 | G50: WACC_225 | H50: 705 | I50: MK | J50: K3591ALM | O50: 3 | P50: 38278 | Q50: 4.3 | R50: =$A50*Q50 -> 75.764789 | S50: 0.17 | T50: =$A50*S50*$T$1 -> 2.6958169 | AD50: SC-CL011
A51: =$Q$46 *(15+16+9+10+14) -> 375.88732 | B51: No | D51: WHITE Ceiling Rose | G51: WACC_037 | H51: 705 | I51: (__) | J51: China | O51: 3 | P51: 39128 | Q51: 0.93 | R51: =$A51*Q51 -> 349.57521 | S51: 0.17 | T51: =$A51*S51*$T$1 -> 57.510761
A52: =$Q$46 *(15+16+9+10+14) -> 375.88732 | B52: m | D52: Wiring Cable 3c 1.0 mm2 PVC Non-Arm | G52: CAMC_047 | H52: 616 | I52: CRO | J52: 1.0mm2 | K52: 03-001 | O52: 2 | P52: 40767 | Q52: 1.1 | R52: =$A52*Q52 -> 413.47606 | S52: 0.025 | T52: =$A52*S52*$T$1 -> 8.4574648
C53: << ==== TOTAL UNITS | R53: =$A53*Q53 -> 0 | T53: =$A53*S53*$T$1 -> 0
A54: d> | B54: =(R53+T53) -> 0 | D54: Sell_A | E54: =IF($B46=0,0,ROUND(ROUND(($R54*$S$2+($T54*$T$2))/$B46, 2)*$C$2,2)) -> 158.19 | F54: =ROUND($B46*$E54,2) -> 32982.62 | K54: ITEM | L54: ITEM | R54: =SUM(R47:R53) -> 9717.2746 | T54: =SUM(T47:T53) -> 621.5708 | AD54: 34608.92
Q55: Multip
A56: =7+7+7+7 -> 28 | B56: =Elec_Est!B11551 -> 43 | D56: 005# Externall Light point rate (Galvanised Conduit) | F56: Updated - increased | K56: RATE | L56: RATE | Q56: =B56/A56 -> 1.5357143 | R56: =IF($B56=0,0,IF($S$1="R",ROUND(R77/$B56,2),R77/$B56)) -> 67.52 | T56: =IF($B56=0,0,IF($S$1="R",ROUND(T77/$B56,2),T77/$B56)) -> 4.19
A57: =$Q$56 *(A71/B56) -> 13.218112 | D57: Based on:
D58: L/LA1/04 | E58: New take off
A59: =$Q$56 *(120) -> 184.28571 | B59: m | D59: Conduit Galv. 20mm RATE | G59: COGV_011 | H59: 690 | I59: BAR | J59: 20mm | O59: 1 | P59: 34669 | Q59: 3.03 | R59: =$A59*Q59 -> 558.38571 | S59: 0.2 | T59: =$A59*S59*$T$1 -> 33.171429
A60: =$Q$56 *((150*3)) -> 691.07143 | B60: m | D60: Wiring Cable 1c 1.5 mm2 PVC Non-Arm | E60: AJ Electric | F60: LSZH | G60: CASC_017 | H60: 615 | I60: CRO | K60: 02-002 | O60: 2 | P60: 38988 | Q60: =0.2*0.95 -> 0.19 | R60: =$A60*Q60 -> 131.30357 | S60: 0.015 | T60: =$A60*S60*$T$1 -> 9.3294643 | AD60: LSZH
A61: =$Q$56 *(1) -> 1.5357143 | B61: No | D61: MC Switch 1G 2W 10A | E61: ESS | F61: SC-CL011 | G61: WACC_225 | H61: 705 | I61: MK | J61: K3591ALM | O61: 3 | P61: 38278 | Q61: 4.3 | R61: =$A61*Q61 -> 6.6035714 | S61: 0.17 | T61: =$A61*S61*$T$1 -> 0.23496429 | AD61: SC-CL011
A62: =$Q$56 *(7) -> 10.75 | B62: No | D62: WHITE Ceiling Rose | G62: WACC_037 | H62: 705 | I62: (__) | J62: China | O62: 3 | P62: 39128 | Q62: 0.93 | R62: =$A62*Q62 -> 9.9975 | S62: 0.17 | T62: =$A62*S62*$T$1 -> 1.64475
A63: =$Q$56 *(7) -> 10.75 | B63: m | D63: Wiring Cable 3c 1.0 mm2 PVC Non-Arm | G63: CAMC_047 | H63: 616 | I63: CRO | J63: 1.0mm2 | K63: 03-001 | O63: 2 | P63: 40767 | Q63: 1.1 | R63: =$A63*Q63 -> 11.825 | S63: 0.025 | T63: =$A63*S63*$T$1 -> 0.241875
D64: L/LA1/05 | E64: New take off
A65: =$Q$56 *(130) -> 199.64286 | B65: m | D65: Conduit Galv. 20mm RATE | G65: COGV_011 | H65: 690 | I65: BAR | J65: 20mm | O65: 1 | P65: 34669 | Q65: 3.03 | R65: =$A65*Q65 -> 604.91786 | S65: 0.2 | T65: =$A65*S65*$T$1 -> 35.935714
A66: =$Q$56 *((150*3)) -> 691.07143 | B66: m | D66: Wiring Cable 1c 1.5 mm2 PVC Non-Arm | E66: AJ Electric | F66: LSZH | G66: CASC_017 | H66: 615 | I66: CRO | K66: 02-002 | O66: 2 | P66: 38988 | Q66: =0.2*0.95 -> 0.19 | R66: =$A66*Q66 -> 131.30357 | S66: 0.015 | T66: =$A66*S66*$T$1 -> 9.3294643 | AD66: LSZH
A67: =$Q$56 *(1) -> 1.5357143 | B67: No | D67: MC Switch 1G 2W 10A | E67: ESS | F67: SC-CL011 | G67: WACC_225 | H67: 705 | I67: MK | J67: K3591ALM | O67: 3 | P67: 38278 | Q67: 4.3 | R67: =$A67*Q67 -> 6.6035714 | S67: 0.17 | T67: =$A67*S67*$T$1 -> 0.23496429 | AD67: SC-CL011
A68: =$Q$56 *(7) -> 10.75 | B68: No | D68: WHITE Ceiling Rose | G68: WACC_037 | H68: 705 | I68: (__) | J68: China | O68: 3 | P68: 39128 | Q68: 0.93 | R68: =$A68*Q68 -> 9.9975 | S68: 0.17 | T68: =$A68*S68*$T$1 -> 1.64475
A69: =$Q$56 *(7) -> 10.75 | B69: m | D69: Wiring Cable 3c 1.0 mm2 PVC Non-Arm | G69: CAMC_047 | H69: 616 | I69: CRO | J69: 1.0mm2 | K69: 03-001 | O69: 2 | P69: 40767 | Q69: 1.1 | R69: =$A69*Q69 -> 11.825 | S69: 0.025 | T69: =$A69*S69*$T$1 -> 0.241875
A71: =$Q$56 *(150+91) -> 370.10714 | B71: m | D71: Conduit Galv. 20mm RATE | G71: COGV_011 | H71: 690 | I71: BAR | J71: 20mm | O71: 1 | P71: 34669 | Q71: 3.03 | R71: =$A71*Q71 -> 1121.4246 | S71: 0.2 | T71: =$A71*S71*$T$1 -> 66.619286
A72: =$Q$56 *((490+340)) -> 1274.6429 | B72: m | D72: Wiring Cable 1c 1.5 mm2 PVC Non-Arm | E72: AJ Electric | F72: LSZH | G72: CASC_017 | H72: 615 | I72: CRO | K72: 02-002 | O72: 2 | P72: 38988 | Q72: =0.2*0.95 -> 0.19 | R72: =$A72*Q72 -> 242.18214 | S72: 0.015 | T72: =$A72*S72*$T$1 -> 17.207679 | AD72: LSZH
A73: =$Q$56 *(1+1) -> 3.0714286 | B73: No | D73: MC Switch 1G 2W 10A | E73: ESS | F73: SC-CL011 | G73: WACC_225 | H73: 705 | I73: MK | J73: K3591ALM | O73: 3 | P73: 38278 | Q73: 4.3 | R73: =$A73*Q73 -> 13.207143 | S73: 0.17 | T73: =$A73*S73*$T$1 -> 0.46992857 | AD73: SC-CL011
A74: =$Q$56 *(7+7) -> 21.5 | B74: No | D74: WHITE Ceiling Rose | G74: WACC_037 | H74: 705 | I74: (__) | J74: China | O74: 3 | P74: 39128 | Q74: 0.93 | R74: =$A74*Q74 -> 19.995 | S74: 0.17 | T74: =$A74*S74*$T$1 -> 3.2895
A75: =$Q$56 *(7+7) -> 21.5 | B75: m | D75: Wiring Cable 3c 1.0 mm2 PVC Non-Arm | G75: CAMC_047 | H75: 616 | I75: CRO | J75: 1.0mm2 | K75: 03-001 | O75: 2 | P75: 40767 | Q75: 1.1 | R75: =$A75*Q75 -> 23.65 | S75: 0.025 | T75: =$A75*S75*$T$1 -> 0.48375
C76: << ==== TOTAL UNITS | R76: =$A76*Q76 -> 0 | T76: =$A76*S76*$T$1 -> 0
A77: d> | B77: =(R76+T76) -> 0 | D77: Sell_A | E77: =IF($B56=0,0,ROUND(ROUND(($R77*$S$2+($T77*$T$2))/$B56, 2)*$C$2,2)) -> 224.74 | F77: =ROUND($B56*$E77,2) -> 9663.82 | K77: ITEM | L77: ITEM | R77: =SUM(R57:R76) -> 2903.2218 | T77: =SUM(T57:T76) -> 180.07939 | AD77: 8289.06
Q78: Multip
A79: =8.5*4+6.5*2 -> 47 | B79: =Elec_Est!B11552 -> 77 | D79: 006# Light point rate (Galvanised Conduit) in Warehouse | F79: Updated - reduced | K79: RATE | L79: RATE | Q79: =B79/A79 -> 1.6382979 | R79: =IF($B79=0,0,IF($S$1="R",ROUND(R89/$B79,2),R89/$B79)) -> 57.28 | T79: =IF($B79=0,0,IF($S$1="R",ROUND(T89/$B79,2),T89/$B79)) -> 2.36
A80: =$Q$79 *(A81/B79) -> 13.629244 | D80: Based on:
A81: =$Q$79 *(65+72+82+92+40+40) -> 640.57447 | B81: m | D81: Conduit Galv. 20mm RATE | G81: COGV_011 | H81: 690 | I81: BAR | J81: 20mm | O81: 1 | P81: 34669 | Q81: 3.03 | R81: =$A81*Q81 -> 1940.9406 | S81: 0.2 | T81: =$A81*S81*$T$1 -> 115.3034
A82: =$Q$79 *((314+324+334+344+243+308)) -> 3058.7021 | B82: m | D82: Wiring Cable 1c 1.5 mm2 PVC Non-Arm | E82: AJ Electric | F82: LSZH | G82: CASC_017 | H82: 615 | I82: CRO | K82: 02-002 | O82: 2 | P82: 38988 | Q82: =0.2*0.95 -> 0.19 | R82: =$A82*Q82 -> 581.1534 | S82: 0.015 | T82: =$A82*S82*$T$1 -> 41.292479 | AD82: LSZH
A83: =$Q$79 *(16*4+12*2) -> 144.17021 | B83: No | D83: WHITE Ceiling Rose | G83: WACC_037 | H83: 705 | I83: (__) | J83: China | O83: 3 | P83: 39128 | Q83: 0.93 | R83: =$A83*Q83 -> 134.0783 | S83: 0.17 | T83: =$A83*S83*$T$1 -> 22.058043
A84: =$Q$79 *(16*4+12*2) -> 144.17021 | B84: m | D84: Wiring Cable 3c 1.0 mm2 PVC Non-Arm | G84: CAMC_047 | H84: 616 | I84: CRO | J84: 1.0mm2 | K84: 03-001 | O84: 2 | P84: 40767 | Q84: 1.1 | R84: =$A84*Q84 -> 158.58723 | S84: 0.025 | T84: =$A84*S84*$T$1 -> 3.2438298
A85: =$Q$79 *(1/1.64) -> 0.99896212 | B85: LS | D85: Crainage & Transportation | F85: Scissors Lift | G85: CRAI_002 | H85: 962 | I85: MISC | O85: 2 | P85: 38129 | Q85: =0.41 *(1 *(215/8*120)) -> 1322.25 | R85: =$A85*Q85 -> 1320.8777 | T85: =$A85*S85*$T$1 -> 0 | AD85: Scissors Lift
A86: =$Q$79 *(1/1.64) -> 0.99896212 | B86: No | D86: Diesel Fuel | F86: Approx €25/daily - info from Godwin by phone | G86: GENS_022 | H86: 845 | I86: (__) | O86: 3 | P86: 39713 | Q86: =0.41 *(215/8*25) -> 275.46875 | R86: =$A86*Q86 -> 275.18285 | T86: =$A86*S86*$T$1 -> 0 | AD86: Approx €25/daily - info from Godwin by phone
D87: Bracketing in warehouse - in next rate
C88: << ==== TOTAL UNITS | R88: =$A88*Q88 -> 0 | T88: =$A88*S88*$T$1 -> 0
A89: d> | B89: =(R88+T88) -> 0 | D89: Sell_A | E89: =IF($B79=0,0,ROUND(ROUND(($R89*$S$2+($T89*$T$2))/$B79, 2)*$C$2,2)) -> 150.41 | F89: =ROUND($B79*$E89,2) -> 11581.57 | K89: ITEM | L89: ITEM | R89: =SUM(R80:R88) -> 4410.8201 | T89: =SUM(T80:T88) -> 181.89776 | AD89: 16396.38
Q90: Multip
A91: 140 | B91: =Elec_Est!B11553 -> 140 | D91: 007# Bracketing for Lighting in Warehouse | K91: RATE | L91: RATE | Q91: =B91/A91 -> 1 | R91: =IF($B91=0,0,IF($S$1="R",ROUND(R101/$B91,2),R101/$B91)) -> 28.4 | T91: =IF($B91=0,0,IF($S$1="R",ROUND(T101/$B91,2),T101/$B91)) -> 1.04
D92: Based on:
D93: Bracketing in warehouse
A94: =$Q$91 *(9*9*2) -> 162 | B94: No | D94: Hilti Beam Clamps Galvanised | F94: MQT-21-41 | G94: EMAT_074 | H94: 501 | I94: HIL | J94: MKL-21-41 244874/1 | K94: 07-011 | O94: 1 | P94: 38302 | Q94: 5 | R94: =$A94*Q94 -> 810 | T94: =$A94*S94*$T$1 -> 0 | AD94: MQT-21-41
A95: =$Q$91 *(9*45*2) -> 810 | B95: m | D95: Channel DEEP-Galv. Hilti MS-413M | E95: Ardic | F95: Double | G95: EMAT_019 | H95: 501 | I95: HIL | J95: MS-413m | K95: 02-018 | O95: 1 | P95: 36175 | Q95: =ROUNDUP(2.07*1.145,2) -> 2.38 | R95: =$A95*Q95 -> 1927.8 | S95: 0.2 | T95: =$A95*S95*$T$1 -> 145.8 | X95: 0.25 | AD95: Double
A96: =$Q$91 *(9*2*2) -> 36 | B96: No | D96: Hilti Channel 40x40 Endcap MQZ-E41 | G96: EMAT_065 | H96: 501 | I96: (__) | K96: 02-020 | O96: 1 | Q96: 0.35 | R96: =$A96*Q96 -> 12.6 | T96: =$A96*S96*$T$1 -> 0
A97: =$Q$91 *(9*9) -> 81 | B97: No | D97: Labour to manufacture Brackets (FIX 1) | F97: Included above | G97: LABO_008 | H97: 900 | I97: MISC | O97: 1 | R97: =$A97*Q97 -> 0 | T97: =$A97*S97*$T$1 -> 0 | U97: NoMat? | AD97: Included above
A98: =$Q$91 *(1) -> 1 | B98: LS | D98: Crainage & Transportation | F98: Scissors Lift | G98: CRAI_002 | H98: 962 | I98: MISC | O98: 2 | P98: 38129 | Q98: =0.41 *(1 *(165/8*120)) -> 1014.75 | R98: =$A98*Q98 -> 1014.75 | T98: =$A98*S98*$T$1 -> 0 | AD98: Scissors Lift
A99: =$Q$91 *(1) -> 1 | B99: No | D99: Diesel Fuel | F99: Approx €25/daily - info from Godwin by phone | G99: GENS_022 | H99: 845 | I99: (__) | O99: 3 | P99: 39713 | Q99: =0.41 *(165/8*25) -> 211.40625 | R99: =$A99*Q99 -> 211.40625 | T99: =$A99*S99*$T$1 -> 0 | AD99: Approx €25/daily - info from Godwin by phone
C100: << ==== TOTAL UNITS | R100: =$A100*Q100 -> 0 | T100: =$A100*S100*$T$1 -> 0
A101: d> | B101: =(R100+T100) -> 0 | D101: Sell_A | E101: =IF($B91=0,0,ROUND(ROUND(($R101*$S$2+($T101*$T$2))/$B91, 2)*$C$2,2)) -> 70.19 | F101: =ROUND($B91*$E101,2) -> 9826.6 | K101: ITEM | L101: ITEM | R101: =SUM(R92:R100) -> 3976.5563 | T101: =SUM(T92:T100) -> 145.8 | AD101: 13069
Q102: Multip
A103: 9 | B103: =Elec_Est!B11554 -> 65 | D103: 008# Maintained Emergency Light point rate (Galvanised Conduit) | F103: Remained as cost saving 1 | K103: RATE | L103: RATE | Q103: =B103/A103 -> 7.2222222 | R103: =IF($B103=0,0,IF($S$1="R",ROUND(R110/$B103,2),R110/$B103)) -> 44.58 | T103: =IF($B103=0,0,IF($S$1="R",ROUND(T110/$B103,2),T110/$B103)) -> 2.87
...

Sheet Elec_Est
B1: CLIENT: | C1: =ML_Sum!$C1 -> 1 | D1: =ML_Sum!$D1 -> Quintano Foods Ltd. | F1: =ML_Sum!$F1 -> 0 | I1: 1 | J1: =ML_Sum!$J1 -> 1 | K1: =ML_Sum!$K1 -> 1 | L1: =ML_Sum!$L1 -> 1 | M1: =ML_Sum!$M1 -> 1 | N1: =ML_Sum!$N1 -> 1 | O1: =ML_Sum!$O1 -> 1 | Q1: =ML_Sum!$Q1 -> € | R1: R/Lab Cont | S1: =ML_Sum!$S1 -> R | T1: =ML_Sum!$T1 -> 0.9 | U1: =ML_Sum!W1 -> BOQ | V1: INCL | W1: MULT | X1: AREA | Y1: BOQ | Z1: TDWG | AA1: ACT | AB1: DIFF | AS1: 0
B2: PROJECT: | C2: =ML_Sum!$C2 -> 1 | D2: =ML_Sum!$D2 -> Warehouse at tal-Handaq, Qormi | F2: =ML_Sum!$F2 -> Electrical | I2: 2 | J2: =ML_Sum!$J2 -> 1 | K2: =ML_Sum!$K2 -> 1 | L2: =ML_Sum!$L2 -> 1 | M2: =ML_Sum!$M2 -> 1 | N2: =ML_Sum!$N2 -> 1 | O2: =ML_Sum!$O2 -> 1 | Q2: =ML_Sum!$Q2 -> 0 | R2: mu_A | S2: =ML_Sum!$S2 -> 1.231344 | T2: =ML_Sum!$T2 -> 33.812706 | AS2: Electrical
B3: JOB DESC: | C3: =ML_Sum!$C3 -> 1 | D3: =ML_Sum!$D3 -> Electrical and ELV installations (Rev A) | F3: =ML_Sum!$F3 -> ELV Installation (NAS Ltd) | I3: 3 | J3: =ML_Sum!$J3 -> 1 | K3: =ML_Sum!$K3 -> 1 | L3: =ML_Sum!$L3 -> 1 | M3: =ML_Sum!$M3 -> 1 | N3: =ML_Sum!$N3 -> 1 | O3: =ML_Sum!$O3 -> 1 | Q3: =ML_Sum!$Q3 -> 0 | R3: mu_B | S3: =ML_Sum!$S3 -> 1.128732 | T3: =ML_Sum!$T3 -> 30.994981 | AS3: ELV Installation (NAS Ltd)
B4: QUOTE No: | C4: =ML_Sum!$C4 -> 1 | D4: =ML_Sum!$D4 -> EL25-0062A | F4: =ML_Sum!$F4 -> Lightning Protection System (MCE Ltd) | I4: 4 | J4: =ML_Sum!$J4 -> 1 | K4: =ML_Sum!$K4 -> 1 | L4: =ML_Sum!$L4 -> 1 | M4: =ML_Sum!$M4 -> 1 | N4: =ML_Sum!$N4 -> 1 | O4: =ML_Sum!$O4 -> 1 | Q4: =ML_Sum!$Q4 -> 0 | R4: mu_C | S4: =ML_Sum!$S4 -> 1.128732 | T4: =ML_Sum!$T4 -> 30.994981 | AS4: Lightning Protection System (MCE Ltd)
B5: CLIENTs REF: | C5: =ML_Sum!$C5 -> 1 | D5: =ML_Sum!$D5 -> Tender | F5: =ML_Sum!$F5 -> Controls ECA | I5: 5 | J5: =ML_Sum!$J5 -> 1 | K5: =ML_Sum!$K5 -> 1 | L5: =ML_Sum!$L5 -> 1 | M5: =ML_Sum!$M5 -> 1 | N5: =ML_Sum!$N5 -> 1 | O5: =ML_Sum!$O5 -> 1 | Q5: =ML_Sum!$Q5 -> 0 | R5: mu_D | S5: =ML_Sum!$S5 -> 1.231344 | T5: =ML_Sum!$T5 -> 53.341822 | AS5: Controls ECA
B6: VAT/DUTIES: | C6: =ML_Sum!$C6 -> 1 | D6: =ML_Sum!$D6 -> VAT EXCL. | F6: =ML_Sum!$F6 -> Testing and Commissiong | I6: 6 | J6: =ML_Sum!$J6 -> 1 | K6: =ML_Sum!$K6 -> 1 | L6: =ML_Sum!$L6 -> 1 | M6: =ML_Sum!$M6 -> 1 | N6: =ML_Sum!$N6 -> 1 | O6: =ML_Sum!$O6 -> 1 | Q6: =ML_Sum!$Q6 -> 0 | R6: mu_E | S6: =ML_Sum!$S6 -> 1.231344 | T6: =ML_Sum!$T6 -> 65.162724 | AS6: Testing and Commissiong
B7: SAVED ON: | C7: =ML_Sum!$C7 -> 1 | D7: 39364 | F7: =ML_Sum!$F7 -> Fire Stopping rates | I7: 7 | J7: =ML_Sum!$J7 -> 1 | K7: =ML_Sum!$K7 -> 1 | L7: =ML_Sum!$L7 -> 1 | M7: =ML_Sum!$M7 -> 1 | N7: =ML_Sum!$N7 -> 1 | O7: =ML_Sum!$O7 -> 0 | Q7: =ML_Sum!$Q7 -> 0 | R7: mu_F | S7: =ML_Sum!$S7 -> 1.231344 | T7: =ML_Sum!$T7 -> 33.812706 | AS7: Fire Stopping rates
B8: ESTIMATOR: | C8: =ML_Sum!$C8 -> 1 | D8: =ML_Sum!$D8 -> T.Sammut | F8: =ML_Sum!$F8 -> Main Equipment (Gen Set / Main Switchboards) | I8: 8 | J8: =ML_Sum!$J8 -> 1 | K8: =ML_Sum!$K8 -> 1 | L8: =ML_Sum!$L8 -> 1 | M8: =ML_Sum!$M8 -> 1 | N8: =ML_Sum!$N8 -> 1 | O8: =ML_Sum!$O8 -> 0 | Q8: =ML_Sum!$Q8 -> 0 | R8: mu_G | S8: =ML_Sum!$S8 -> 1.180038 | T8: =ML_Sum!$T8 -> 32.403843 | AS8: Main Equipment (Gen Set / Main Switchboards)
B9: LABOUR RATE: | C9: =ML_Sum!$C9 -> 1 | D9: =ML_Sum!$D9 -> 27.46 | F9: =ML_Sum!$F9 -> DBs and Changeover | I9: 9 | J9: =ML_Sum!$J9 -> 1 | K9: =ML_Sum!$K9 -> 1 | L9: =ML_Sum!$L9 -> 1 | M9: =ML_Sum!$M9 -> 1 | N9: =ML_Sum!$N9 -> 1 | O9: =ML_Sum!$O9 -> 0 | Q9: =ML_Sum!$Q9 -> 0 | R9: mu_H | S9: =ML_Sum!$S9 -> 1.180038 | T9: =ML_Sum!$T9 -> 32.403843 | AS9: 0
C10: =ML_Sum!$C10 -> 1 | F10: =ML_Sum!$F10 -> Armoured Cables | I10: 10 | J10: =ML_Sum!$J10 -> 1 | K10: =ML_Sum!$K10 -> 1 | L10: =ML_Sum!$L10 -> 1 | M10: =ML_Sum!$M10 -> 1 | N10: =ML_Sum!$N10 -> 1 | O10: =ML_Sum!$O10 -> 1 | Q10: =ML_Sum!$Q10 -> 0 | R10: mu_I | S10: =ML_Sum!$S10 -> 1.180038 | T10: =ML_Sum!$T10 -> 32.403843 | AS10: 0
C11: =ML_Sum!$C11 -> 1 | F11: =ML_Sum!$F11 -> 0 | Q11: =ML_Sum!$Q11 -> 0 | R11: mu_J | S11: =ML_Sum!$S11 -> 0 | T11: =ML_Sum!$T11 -> 0 | AS11: 0
C12: =ML_Sum!$C12 -> 1 | F12: =ML_Sum!$F12 -> 0 | Q12: =ML_Sum!$Q12 -> 0 | R12: MIXED | S12: =ML_Sum!$S12 -> MAT MU | T12: =ML_Sum!$T12 -> LAB RATE | AS12: 0
G13: ISELL | H13: C_CODE | I13: MAKE | J13: PART_NO | K13: MARKUP | L13: TYPE | M13: LIST_P | N13: P_FACT | O13: FIX | P13: DATE | Q13: %Dsct in BOQ | R13: MU TYPE | S13: MAT MU | T13: LAB RATE | AM13: Tot Mat Cost | AN13: Unit Lab phr. | AO13: Tot Lab phr. | AP13: < for ELM / MEE
K14: TB
C15: t | D15: Item: 1
D16: PRELIMINARIES
K18: TB
C19: t
D20: All equipment to be used within this contract is to be approved prior to delivery to site.
E22: Sell Rate | F22: Sell Total | K22: IB | AG22: U_M_Sell | AH22: T_M_Sell | AI22: U_L_Sell | AJ22: T_L_Sell | AK22: Total_Sell | AM22: T_M_Cost | AN22: T_L_Phr | AO22: Mat/Lab=1 | AS22: Sell Total
A23: 1 | B23: L.S. | D23: Item: 1.001 | E23: =IF(AND($A23=0,$A$1="DIF"),0, ROUND(ROUND(($R27*$S$2+($T27*$T$2))/A23,2)*$C$2,2)) -> 2462.69 | F23: =ROUND($A23*$E23,2) -> 2462.69 | G23: ISELL | K23: mu_A | L23: ITEM | T23: =IF(AND($R27=0,$T27=0),"0.00","mu :" & ROUND($F23/$C$2/($R27+$T27*$D$9),2)) -> mu :1.23 | AG23: =IF($E23=0,0,ROUND($R27*$S$2*$C$2/$A23,2)) -> 2462.69 | AH23: =$AG23*$A23 -> 2462.69 | AI23: =$E23-$AG23 -> 0 | AJ23: =$A23*$AI23 -> 0 | AK23: =ROUND(($AG23+$AI23)*$A23,2) -> 2462.69 | AM23: =ROUND(R27,2) -> 2000 | AN23: =ROUND(T27,2) -> 0 | AO23: =ROUND(AM23+AN23,2)*A23 -> 2000 | AR23: 1 | AS23: 2462.69
D24: Mobilisation of site including the setting up of Storage facilities for materials, Sanitary facilities for the employees, Setting up of temporary site office, etc required to undertake the works
A25: 1 | B25: No | D25: Mobilisation | G25: DOCS_001 | H25: 880 | I25: (__) | O25: 3 | Q25: 2000 | R25: =$A25*Q25 -> 2000 | T25: =$A25*S25*$T$1 -> 0 | AR25: 1
R26: =$A26*Q26 -> 0 | T26: =$A26*S26*$T$1 -> 0
A27: d> | B27: =(R26+T26) -> 0 | G27: ICOST | K27: mu_A | L27: ITEM | R27: =SUM(R24:R26) -> 2000 | T27: =SUM(T24:T26) -> 0 | AR27: d>
E28: Sell Rate | F28: Sell Total | K28: IB | AG28: U_M_Sell | AH28: T_M_Sell | AI28: U_L_Sell | AJ28: T_L_Sell | AK28: Total_Sell | AM28: T_M_Cost | AN28: T_L_Phr | AO28: Mat/Lab=1 | AS28: Sell Total
A29: 1 | B29: L.S. | D29: Item: 1.002 | E29: =IF(AND($A29=0,$A$1="DIF"),0, ROUND(ROUND(($R37*$S$2+($T37*$T$2))/$A29,2)*$C$2,2)) -> 0 | F29: =ROUND($A29*$E29,2) -> 0 | G29: ISELL | K29: mu_A | L29: ITEM | Q29: Included | T29: =IF(AND($R37=0,$T37=0),"0.00","mu: "& ROUND(F29/$C$2/($R37+$T37*$D$9),2)) -> 0.00 | AG29: =IF($E29=0,0,ROUND($R37*$S$2*$C$2/$A29,2)) -> 0 | AH29: =$AG29*$A29 -> 0 | AI29: =$E29-$AG29 -> 0 | AJ29: =$A29*$AI29 -> 0 | AK29: =ROUND(($AG29+$AI29)*$A29,2) -> 0 | AM29: =ROUND(R37,2) -> 0 | AN29: =ROUND(T37,2) -> 0 | AO29: =ROUND(AM29+AN29,2)*A29 -> 0 | AR29: 1 | AS29: 0
D30: Provision of insurance cover in the joint names of the Client and Contractor insure the Works against loss or damage by fire, storm, tempest, lightning, flood, earthquake, aircraft or anything dropped there from, aerial objects, riot and civil commotion for the full reinstatement value thereof plus 15% of all the Works executed and all unfixed materials and goods so insured until the completion of the Works. The Contractor shall affect a policy of insurance against third party risks to cover an amount of not less than Euro 500,000 (five hundred thousand Euros) for any one accident. The policy shall be in joint names of the Client and Contractor and shall include cross liability clauses. In respect of liability for the death or injury to any person employed by the Contractor and arising out of and in the course of such person's employment by the Contractor the amount insured by the Contractor shall be such as to indemnify the Client against all damages as compensation payable. The Contractor shall comply with and be subject to the terms, exclusions, exceptions, conditions and limitations of the insurance policies and shall bear the amount of the retained liabilities stated therein The Contractor shall deposit with the Client copies of the policy or policies and a copy of the receipt in respect of premiums paid before starting the Works
R31: =$A31*Q31 -> 0 | T31: =$A31*S31*$T$1 -> 0
R32: =$A32*Q32 -> 0 | T32: =$A32*S32*$T$1 -> 0
R33: =$A33*Q33 -> 0 | T33: =$A33*S33*$T$1 -> 0
R34: =$A34*Q34 -> 0 | T34: =$A34*S34*$T$1 -> 0
R35: =$A35*Q35 -> 0 | T35: =$A35*S35*$T$1 -> 0
R36: =$A36*Q36 -> 0 | T36: =$A36*S36*$T$1 -> 0
A37: d> | B37: =(R36+T36) -> 0 | G37: ICOST | K37: mu_A | L37: ITEM | R37: =SUM(R30:R36) -> 0 | T37: =SUM(T30:T36) -> 0 | AR37: d>
E38: Sell Rate | F38: Sell Total | K38: IB | AG38: U_M_Sell | AH38: T_M_Sell | AI38: U_L_Sell | AJ38: T_L_Sell | AK38: Total_Sell | AM38: T_M_Cost | AN38: T_L_Phr | AO38: Mat/Lab=1 | AS38: Sell Total
A39: 1 | B39: L.S. | D39: Item: 1.003 | E39: =IF(AND($A39=0,$A$1="DIF"),0, ROUND(ROUND(($R47*$S$2+($T47*$T$2))/A39,2)*$C$2,2)) -> 0 | F39: =ROUND($A39*$E39,2) -> 0 | G39: ISELL | K39: mu_A | L39: ITEM | Q39: Refer to covering letter | T39: =IF(AND($R47=0,$T47=0),"0.00","mu :" & ROUND($F39/$C$2/($R47+$T47*$D$9),2)) -> 0.00 | AG39: =IF($E39=0,0,ROUND($R47*$S$2*$C$2/$A39,2)) -> 0 | AH39: =$AG39*$A39 -> 0 | AI39: =$E39-$AG39 -> 0 | AJ39: =$A39*$AI39 -> 0 | AK39: =ROUND(($AG39+$AI39)*$A39,2) -> 0 | AM39: =ROUND(R47,2) -> 0 | AN39: =ROUND(T47,2) -> 0 | AO39: =ROUND(AM39+AN39,2)*A39 -> 0 | AR39: 1 | AS39: 0
D40: Implementation of health and safety measures on site including personal safety (e.g safety shoes, helmets scaffolding, harnesses etc) as well as those to render the site safe for employees (e.g staircase handrails, closing of lift shaft openings etc)
R41: =$A41*Q41 -> 0 | T41: =$A41*S41*$T$1 -> 0
R42: =$A42*Q42 -> 0 | T42: =$A42*S42*$T$1 -> 0
R43: =$A43*Q43 -> 0 | T43: =$A43*S43*$T$1 -> 0
R44: =$A44*Q44 -> 0 | T44: =$A44*S44*$T$1 -> 0
R45: =$A45*Q45 -> 0 | T45: =$A45*S45*$T$1 -> 0
R46: =$A46*Q46 -> 0 | T46: =$A46*S46*$T$1 -> 0
A47: d> | B47: =(R46+T46) -> 0 | G47: ICOST | K47: mu_A | L47: ITEM | R47: =SUM(R40:R46) -> 0 | T47: =SUM(T40:T46) -> 0 | AR47: d>
E48: Sell Rate | F48: Sell Total | K48: IB | AG48: U_M_Sell | AH48: T_M_Sell | AI48: U_L_Sell | AJ48: T_L_Sell | AK48: Total_Sell | AM48: T_M_Cost | AN48: T_L_Phr | AO48: Mat/Lab=1 | AS48: Sell Total
A49: 1 | B49: L.S. | D49: Item: 1.004 | E49: =IF(AND($A49=0,$A$1="DIF"),0, ROUND(ROUND(($R56*$S$2+($T56*$T$2))/A49,2)*$C$2,2)) -> 4369.3 | F49: =ROUND($A49*$E49,2) -> 4369.3 | G49: ISELL | K49: mu_A | L49: ITEM | T49: =IF(AND($R56=0,$T56=0),"0.00","mu :" & ROUND($F49/$C$2/($R56+$T56*$D$9),2)) -> mu :1.23 | AG49: =IF($E49=0,0,ROUND($R56*$S$2*$C$2/$A49,2)) -> 4369.3 | AH49: =$AG49*$A49 -> 4369.3 | AI49: =$E49-$AG49 -> 0 | AJ49: =$A49*$AI49 -> 0 | AK49: =ROUND(($AG49+$AI49)*$A49,2) -> 4369.3 | AM49: =ROUND(R56,2) -> 3548.4 | AN49: =ROUND(T56,2) -> 0 | AO49: =ROUND(AM49+AN49,2)*A49 -> 3548.4 | AR49: 1 | AS49: 4369.3
D50: Prepare a risk assessment report outlining all risks involved and measures to be taken to minimise or eliminate potential risks. The report is to be prepared and signed by a competent person and to be submitted within three weeks from commencement of works.
A51: 6 | B51: No | D51: Risk Assessment | G51: DOCS_001 | H51: 880 | I51: (__) | O51: 3 | Q51: 150 | R51: =$A51*Q51 -> 900 | T51: =$A51*S51*$T$1 -> 0 | AR51: 6
A52: 14 | B52: No | D52: H&S Site Visits | G52: DOCS_001 | H52: 880 | I52: (__) | O52: 3 | Q52: 60 | R52: =$A52*Q52 -> 840 | T52: =$A52*S52*$T$1 -> 0 | AR52: 14
A53: 16 | B53: Hours | D53: Risk Assessment | G53: DOCS_001 | H53: 880 | I53: (__) | O53: 3 | Q53: 35 | R53: =$A53*Q53 -> 560 | T53: =$A53*S53*$T$1 -> 0 | AR53: 16
A54: 1 | B54: No | D54: Office labour | G54: DOCS_001 | H54: 880 | I54: (__) | O54: 3 | Q54: =40*31.21 -> 1248.4 | R54: =$A54*Q54 -> 1248.4 | T54: =$A54*S54*$T$1 -> 0 | AR54: 1
R55: =$A55*Q55 -> 0 | T55: =$A55*S55*$T$1 -> 0
A56: d> | B56: =(R55+T55) -> 0 | G56: ICOST | K56: mu_A | L56: ITEM | R56: =SUM(R50:R55) -> 3548.4 | T56: =SUM(T50:T55) -> 0 | AR56: d>
E57: Sell Rate | F57: Sell Total | K57: IB | AG57: U_M_Sell | AH57: T_M_Sell | AI57: U_L_Sell | AJ57: T_L_Sell | AK57: Total_Sell | AM57: T_M_Cost | AN57: T_L_Phr | AO57: Mat/Lab=1 | AS57: Sell Total
A58: 1 | B58: L.S. | D58: Item: 1.005 | E58: =IF(AND($A58=0,$A$1="DIF"),0, ROUND(ROUND(($R62*$S$2+($T62*$T$2))/A58,2)*$C$2,2)) -> 0 | F58: =ROUND($A58*$E58,2) -> 0 | G58: ISELL | K58: mu_A | L58: ITEM | Q58: Included | T58: =IF(AND($R62=0,$T62=0),"0.00","mu :" & ROUND($F58/$C$2/($R62+$T62*$D$9),2)) -> 0.00 | AG58: =IF($E58=0,0,ROUND($R62*$S$2*$C$2/$A58,2)) -> 0 | AH58: =$AG58*$A58 -> 0 | AI58: =$E58-$AG58 -> 0 | AJ58: =$A58*$AI58 -> 0 | AK58: =ROUND(($AG58+$AI58)*$A58,2) -> 0 | AM58: =ROUND(R62,2) -> 0 | AN58: =ROUND(T62,2) -> 0 | AO58: =ROUND(AM58+AN58,2)*A58 -> 0 | AR58: 1 | AS58: 0
D59: Allow for carrying out all surveys, setting out of works unless included elsewhere in the Bills of Quantities.
R60: =$A60*Q60 -> 0 | T60: =$A60*S60*$T$1 -> 0
R61: =$A61*Q61 -> 0 | T61: =$A61*S61*$T$1 -> 0
A62: d> | B62: =(R61+T61) -> 0 | G62: ICOST | K62: mu_A | L62: ITEM | R62: =SUM(R59:R61) -> 0 | T62: =SUM(T59:T61) -> 0 | AR62: d>
A63: SB | AR63: SB
B65: =$F65/$C$2-($R65*$S$2+$T65*$T$2) -> 0.0009504 | D65: PAGE: 1 | F65: =SUMIF($L14:$L63,"ITEM",F14:F63) -> 6831.99 | L65: PAGE | R65: =SUMIF($L14:$L63,"ITEM",R14:R63) -> 5548.4 | T65: =SUMIF($L14:$L63,"ITEM",T14:T63) -> 0 | AS65: 6831.99
B66: Discy: | F66: PAGE SELL | R66: PAGE MAT | T66: PAGE LAB | AS66: PAGE SELL
E69: Sell Rate | F69: Sell Total | K69: IB | AG69: U_M_Sell | AH69: T_M_Sell | AI69: U_L_Sell | AJ69: T_L_Sell | AK69: Total_Sell | AM69: T_M_Cost | AN69: T_L_Phr | AO69: Mat/Lab=1 | AS69: Sell Total
A70: 1 | B70: L.S. | D70: Item: 1.006 | E70: =IF(AND($A70=0,$A$1="DIF"),0, ROUND(ROUND(($R74*$S$2+($T74*$T$2))/A70,2)*$C$2,2)) -> 0 | F70: =ROUND($A70*$E70,2) -> 0 | G70: ISELL | K70: mu_A | L70: ITEM | Q70: Included | T70: =IF(AND($R74=0,$T74=0),"0.00","mu :" & ROUND($F70/$C$2/($R74+$T74*$D$9),2)) -> 0.00 | AG70: =IF($E70=0,0,ROUND($R74*$S$2*$C$2/$A70,2)) -> 0 | AH70: =$AG70*$A70 -> 0 | AI70: =$E70-$AG70 -> 0 | AJ70: =$A70*$AI70 -> 0 | AK70: =ROUND(($AG70+$AI70)*$A70,2) -> 0 | AM70: =ROUND(R74,2) -> 0 | AN70: =ROUND(T74,2) -> 0 | AO70: =ROUND(AM70+AN70,2)*A70 -> 0 | AR70: 1 | AS70: 0
D71: Provision for attending to site to take all relevant measurements in order to ascertain the exact quantities of the individual and measured items to be procured as well as keeping of all relevant records of personnel attendance, stock control etc
R72: =$A72*Q72 -> 0 | T72: =$A72*S72*$T$1 -> 0
R73: =$A73*Q73 -> 0 | T73: =$A73*S73*$T$1 -> 0
A74: d> | B74: =(R73+T73) -> 0 | G74: ICOST | K74: mu_A | L74: ITEM | R74: =SUM(R71:R73) -> 0 | T74: =SUM(T71:T73) -> 0 | AR74: d>
E75: Sell Rate | F75: Sell Total | K75: IB | AG75: U_M_Sell | AH75: T_M_Sell | AI75: U_L_Sell | AJ75: T_L_Sell | AK75: Total_Sell | AM75: T_M_Cost | AN75: T_L_Phr | AO75: Mat/Lab=1 | AS75: Sell Total
A76: 1 | B76: L.S. | D76: Item: 1.007 | E76: =IF(AND($A76=0,$A$1="DIF"),0, ROUND(ROUND(($R80*$S$2+($T80*$T$2))/A76,2)*$C$2,2)) -> 0 | F76: =ROUND($A76*$E76,2) -> 0 | G76: ISELL | K76: mu_A | L76: ITEM | Q76: By Client | T76: =IF(AND($R80=0,$T80=0),"0.00","mu :" & ROUND($F76/$C$2/($R80+$T80*$D$9),2)) -> 0.00 | AG76: =IF($E76=0,0,ROUND($R80*$S$2*$C$2/$A76,2)) -> 0 | AH76: =$AG76*$A76 -> 0 | AI76: =$E76-$AG76 -> 0 | AJ76: =$A76*$AI76 -> 0 | AK76: =ROUND(($AG76+$AI76)*$A76,2) -> 0 | AM76: =ROUND(R80,2) -> 0 | AN76: =ROUND(T80,2) -> 0 | AO76: =ROUND(AM76+AN76,2)*A76 -> 0 | AR76: 1 | AS76: 0
D77: Provision of security measures on site both as regards the storage facilities as well as to safeguard the materials installed during the latter stages of the project.
R78: =$A78*Q78 -> 0 | T78: =$A78*S78*$T$1 -> 0
R79: =$A79*Q79 -> 0 | T79: =$A79*S79*$T$1 -> 0
A80: d> | B80: =(R79+T79) -> 0 | G80: ICOST | K80: mu_A | L80: ITEM | R80: =SUM(R77:R79) -> 0 | T80: =SUM(T77:T79) -> 0 | AR80: d>
E81: Sell Rate | F81: Sell Total | K81: IB | AG81: U_M_Sell | AH81: T_M_Sell | AI81: U_L_Sell | AJ81: T_L_Sell | AK81: Total_Sell | AM81: T_M_Cost | AN81: T_L_Phr | AO81: Mat/Lab=1 | AS81: Sell Total
A82: 1 | B82: L.S. | D82: Item: 1.008 | E82: =IF(AND($A82=0,$A$1="DIF"),0, ROUND(ROUND(($R86*$S$2+($T86*$T$2))/A82,2)*$C$2,2)) -> 0 | F82: =ROUND($A82*$E82,2) -> 0 | G82: ISELL | K82: mu_A | L82: ITEM | Q82: To be advised | T82: =IF(AND($R86=0,$T86=0),"0.00","mu :" & ROUND($F82/$C$2/($R86+$T86*$D$9),2)) -> 0.00 | AG82: =IF($E82=0,0,ROUND($R86*$S$2*$C$2/$A82,2)) -> 0 | AH82: =$AG82*$A82 -> 0 | AI82: =$E82-$AG82 -> 0 | AJ82: =$A82*$AI82 -> 0 | AK82: =ROUND(($AG82+$AI82)*$A82,2) -> 0 | AM82: =ROUND(R86,2) -> 0 | AN82: =ROUND(T86,2) -> 0 | AO82: =ROUND(AM82+AN82,2)*A82 -> 0 | AR82: 1 | AS82: 0
D83: Provision for the supply and delivery to site of samples as may be requested by the client / engineer
R84: =$A84*Q84 -> 0 | T84: =$A84*S84*$T$1 -> 0
R85: =$A85*Q85 -> 0 | T85: =$A85*S85*$T$1 -> 0
A86: d> | B86: =(R85+T85) -> 0 | G86: ICOST | K86: mu_A | L86: ITEM | R86: =SUM(R83:R85) -> 0 | T86: =SUM(T83:T85) -> 0 | AR86: d>
E87: Sell Rate | F87: Sell Total | K87: IB | AG87: U_M_Sell | AH87: T_M_Sell | AI87: U_L_Sell | AJ87: T_L_Sell | AK87: Total_Sell | AM87: T_M_Cost | AN87: T_L_Phr | AO87: Mat/Lab=1 | AS87: Sell Total
A88: 1 | B88: L.S. | D88: Item: 1.009 | E88: =IF(AND($A88=0,$A$1="DIF"),0, ROUND(ROUND(($R92*$S$2+($T92*$T$2))/A88,2)*$C$2,2)) -> 4320.24 | F88: =ROUND($A88*$E88,2) -> 4320.24 | G88: ISELL | K88: mu_A | L88: ITEM | T88: =IF(AND($R92=0,$T92=0),"0.00","mu :" & ROUND($F88/$C$2/($R92+$T92*$D$9),2)) -> mu :1.23 | AG88: =IF($E88=0,0,ROUND($R92*$S$2*$C$2/$A88,2)) -> 3102.99 | AH88: =$AG88*$A88 -> 3102.99 | AI88: =$E88-$AG88 -> 1217.25 | AJ88: =$A88*$AI88 -> 1217.25 | AK88: =ROUND(($AG88+$AI88)*$A88,2) -> 4320.24 | AM88: =ROUND(R92,2) -> 2520 | AN88: =ROUND(T92,2) -> 36 | AO88: =ROUND(AM88+AN88,2)*A88 -> 2556 | AR88: 1 | AS88: 4455.5
D89: Allow for continuously keeping the site and building clean and in a workman type condition free from debris, surplus materials and any other type of loose matter arising from works, which will disturb the proper conditions of any internal and external areas, roads and/or adjoining structures. Site Cleaning is to take place during the whole duration of works. Client reserves the right to employ cleaning companies at the contractor's expense if the contractor fails to keep the site clean.
A90: 14 | B90: No | D90: SUBCONTRACTING WORKS | E90: Skips | G90: SUBC_001 | H90: 960 | I90: MISC | O90: 4 | P90: 38274 | Q90: 180 | R90: =$A90*Q90 -> 2520 | S90: =40/14 -> 2.8571429 | T90: =$A90*S90*$T$1 -> 36 | AR90: 14
R91: =$A91*Q91 -> 0 | T91: =$A91*S91*$T$1 -> 0
A92: d> | B92: =(R91+T91) -> 0 | G92: ICOST | K92: mu_A | L92: ITEM | R92: =SUM(R89:R91) -> 2520 | T92: =SUM(T89:T91) -> 36 | AR92: d>
E93: Sell Rate | F93: Sell Total | K93: IB | AG93: U_M_Sell | AH93: T_M_Sell | AI93: U_L_Sell | AJ93: T_L_Sell | AK93: Total_Sell | AM93: T_M_Cost | AN93: T_L_Phr | AO93: Mat/Lab=1 | AS93: Sell Total
A94: 1 | B94: L.S. | D94: Item: 1.01 | E94: =IF(AND($A94=0,$A$1="DIF"),0, ROUND(ROUND(($R98*$S$2+($T98*$T$2))/A94,2)*$C$2,2)) -> 0 | F94: =ROUND($A94*$E94,2) -> 0 | G94: ISELL | K94: mu_A | L94: ITEM | Q94: Included | T94: =IF(AND($R98=0,$T98=0),"0.00","mu :" & ROUND($F94/$C$2/($R98+$T98*$D$9),2)) -> 0.00 | AG94: =IF($E94=0,0,ROUND($R98*$S$2*$C$2/$A94,2)) -> 0 | AH94: =$AG94*$A94 -> 0 | AI94: =$E94-$AG94 -> 0 | AJ94: =$A94*$AI94 -> 0 | AK94: =ROUND(($AG94+$AI94)*$A94,2) -> 0 | AM94: =ROUND(R98,2) -> 0 | AN94: =ROUND(T98,2) -> 0 | AO94: =ROUND(AM94+AN94,2)*A94 -> 0 | AR94: 1 | AS94: 0
D95: Provision for hauling of equipment on site, including cranage, permits and all necessary fees.
R96: =$A96*Q96 -> 0 | T96: =$A96*S96*$T$1 -> 0
R97: =$A97*Q97 -> 0 | T97: =$A97*S97*$T$1 -> 0
A98: d> | B98: =(R97+T97) -> 0 | G98: ICOST | K98: mu_A | L98: ITEM | R98: =SUM(R95:R97) -> 0 | T98: =SUM(T95:T97) -> 0 | AR98: d>
E99: Sell Rate | F99: Sell Total | K99: IB | AG99: U_M_Sell | AH99: T_M_Sell | AI99: U_L_Sell | AJ99: T_L_Sell | AK99: Total_Sell | AM99: T_M_Cost | AN99: T_L_Phr | AO99: Mat/Lab=1 | AS99: Sell Total
A100: 1 | B100: L.S. | D100: Item: 1.011 | E100: =IF(AND($A100=0,$A$1="DIF"),0, ROUND(ROUND(($R104*$S$2+($T104*$T$2))/A100,2)*$C$2,2)) -> 0 | F100: =ROUND($A100*$E100,2) -> 0 | G100: ISELL | K100: mu_A | L100: ITEM | Q100: Included | T100: =IF(AND($R104=0,$T104=0),"0.00","mu :" & ROUND($F100/$C$2/($R104+$T104*$D$9),2)) -> 0.00 | AG100: =IF($E100=0,0,ROUND($R104*$S$2*$C$2/$A100,2)) -> 0 | AH100: =$AG100*$A100 -> 0 | AI100: =$E100-$AG100 -> 0 | AJ100: =$A100*$AI100 -> 0 | AK100: =ROUND(($AG100+$AI100)*$A100,2) -> 0 | AM100: =ROUND(R104,2) -> 0 | AN100: =ROUND(T104,2) -> 0 | AO100: =ROUND(AM100+AN100,2)*A100 -> 0 | AR100: 1 | AS100: 0
D101: Provision for working at height, including scaffolding, cherry pickers etc. All equipment shall be fully certified.
R102: =$A102*Q102 -> 0 | T102: =$A102*S102*$T$1 -> 0
R103: =$A103*Q103 -> 0 | T103: =$A103*S103*$T$1 -> 0
A104: d> | B104: =(R103+T103) -> 0 | G104: ICOST | K104: mu_A | L104: ITEM | R104: =SUM(R101:R103) -> 0 | T104: =SUM(T101:T103) -> 0 | AR104: d>
E105: Sell Rate | F105: Sell Total | K105: IB | AG105: U_M_Sell | AH105: T_M_Sell | AI105: U_L_Sell | AJ105: T_L_Sell | AK105: Total_Sell | AM105: T_M_Cost | AN105: T_L_Phr | AO105: Mat/Lab=1 | AS105: Sell Total
...

Sheet Fire_Stopping_Est
B1: CLIENT: | C1: =ML_Sum!$C1 -> 1 | D1: =ML_Sum!$D1 -> Quintano Foods Ltd. | F1: =ML_Sum!$F1 -> 0 | I1: 1 | J1: =ML_Sum!$J1 -> 1 | K1: =ML_Sum!$K1 -> 1 | L1: =ML_Sum!$L1 -> 1 | M1: =ML_Sum!$M1 -> 1 | N1: =ML_Sum!$N1 -> 1 | O1: =ML_Sum!$O1 -> 1 | Q1: =ML_Sum!$Q1 -> € | R1: R/Lab Cont | S1: =ML_Sum!$S1 -> R | T1: =ML_Sum!$T1 -> 0.9 | U1: =ML_Sum!W1 -> BOQ | V1: INCL | W1: MULT | X1: AREA | Y1: BOQ | Z1: TDWG | AA1: ACT | AB1: DIFF
B2: PROJECT: | C2: =ML_Sum!$C2 -> 1 | D2: =ML_Sum!$D2 -> Warehouse at tal-Handaq, Qormi | F2: =ML_Sum!$F2 -> Electrical | I2: 2 | J2: =ML_Sum!$J2 -> 1 | K2: =ML_Sum!$K2 -> 1 | L2: =ML_Sum!$L2 -> 1 | M2: =ML_Sum!$M2 -> 1 | N2: =ML_Sum!$N2 -> 1 | O2: =ML_Sum!$O2 -> 1 | Q2: =ML_Sum!$Q2 -> 0 | R2: mu_A | S2: =ML_Sum!$S2 -> 1.231344 | T2: =ML_Sum!$T2 -> 33.812706
B3: JOB DESC: | C3: =ML_Sum!$C3 -> 1 | D3: =ML_Sum!$D3 -> Electrical and ELV installations (Rev A) | F3: =ML_Sum!$F3 -> ELV Installation (NAS Ltd) | I3: 3 | J3: =ML_Sum!$J3 -> 1 | K3: =ML_Sum!$K3 -> 1 | L3: =ML_Sum!$L3 -> 1 | M3: =ML_Sum!$M3 -> 1 | N3: =ML_Sum!$N3 -> 1 | O3: =ML_Sum!$O3 -> 1 | Q3: =ML_Sum!$Q3 -> 0 | R3: mu_B | S3: =ML_Sum!$S3 -> 1.128732 | T3: =ML_Sum!$T3 -> 30.994981
B4: QUOTE No: | C4: =ML_Sum!$C4 -> 1 | D4: =ML_Sum!$D4 -> EL25-0062A | F4: =ML_Sum!$F4 -> Lightning Protection System (MCE Ltd) | I4: 4 | J4: =ML_Sum!$J4 -> 1 | K4: =ML_Sum!$K4 -> 1 | L4: =ML_Sum!$L4 -> 1 | M4: =ML_Sum!$M4 -> 1 | N4: =ML_Sum!$N4 -> 1 | O4: =ML_Sum!$O4 -> 1 | Q4: =ML_Sum!$Q4 -> 0 | R4: mu_C | S4: =ML_Sum!$S4 -> 1.128732 | T4: =ML_Sum!$T4 -> 30.994981
B5: CLIENTs REF: | C5: =ML_Sum!$C5 -> 1 | D5: =ML_Sum!$D5 -> Tender | F5: =ML_Sum!$F5 -> Controls ECA | I5: 5 | J5: =ML_Sum!$J5 -> 1 | K5: =ML_Sum!$K5 -> 1 | L5: =ML_Sum!$L5 -> 1 | M5: =ML_Sum!$M5 -> 1 | N5: =ML_Sum!$N5 -> 1 | O5: =ML_Sum!$O5 -> 1 | Q5: =ML_Sum!$Q5 -> 0 | R5: mu_D | S5: =ML_Sum!$S5 -> 1.231344 | T5: =ML_Sum!$T5 -> 53.341822
B6: VAT/DUTIES: | C6: =ML_Sum!$C6 -> 1 | D6: =ML_Sum!$D6 -> VAT EXCL. | F6: =ML_Sum!$F6 -> Testing and Commissiong | I6: 6 | J6: =ML_Sum!$J6 -> 1 | K6: =ML_Sum!$K6 -> 1 | L6: =ML_Sum!$L6 -> 1 | M6: =ML_Sum!$M6 -> 1 | N6: =ML_Sum!$N6 -> 1 | O6: =ML_Sum!$O6 -> 1 | Q6: =ML_Sum!$Q6 -> 0 | R6: mu_E | S6: =ML_Sum!$S6 -> 1.231344 | T6: =ML_Sum!$T6 -> 65.162724
B7: SAVED ON: | C7: =ML_Sum!$C7 -> 1 | D7: 39364 | F7: =ML_Sum!$F7 -> Fire Stopping rates | I7: 7 | J7: =ML_Sum!$J7 -> 1 | K7: =ML_Sum!$K7 -> 1 | L7: =ML_Sum!$L7 -> 1 | M7: =ML_Sum!$M7 -> 1 | N7: =ML_Sum!$N7 -> 1 | O7: =ML_Sum!$O7 -> 0 | Q7: =ML_Sum!$Q7 -> 0 | R7: mu_F | S7: =ML_Sum!$S7 -> 1.231344 | T7: =ML_Sum!$T7 -> 33.812706
B8: ESTIMATOR: | C8: =ML_Sum!$C8 -> 1 | D8: =ML_Sum!$D8 -> T.Sammut | F8: =ML_Sum!$F8 -> Main Equipment (Gen Set / Main Switchboards) | I8: 8 | J8: =ML_Sum!$J8 -> 1 | K8: =ML_Sum!$K8 -> 1 | L8: =ML_Sum!$L8 -> 1 | M8: =ML_Sum!$M8 -> 1 | N8: =ML_Sum!$N8 -> 1 | O8: =ML_Sum!$O8 -> 0 | Q8: =ML_Sum!$Q8 -> 0 | R8: mu_G | S8: =ML_Sum!$S8 -> 1.180038 | T8: =ML_Sum!$T8 -> 32.403843
B9: LABOUR RATE: | C9: =ML_Sum!$C9 -> 1 | D9: =ML_Sum!$D9 -> 27.46 | F9: =ML_Sum!$F9 -> DBs and Changeover | I9: 9 | J9: =ML_Sum!$J9 -> 1 | K9: =ML_Sum!$K9 -> 1 | L9: =ML_Sum!$L9 -> 1 | M9: =ML_Sum!$M9 -> 1 | N9: =ML_Sum!$N9 -> 1 | O9: =ML_Sum!$O9 -> 0 | Q9: =ML_Sum!$Q9 -> 0 | R9: mu_H | S9: =ML_Sum!$S9 -> 1.180038 | T9: =ML_Sum!$T9 -> 32.403843
C10: =ML_Sum!$C10 -> 1 | F10: =ML_Sum!$F10 -> Armoured Cables | I10: 10 | J10: =ML_Sum!$J10 -> 1 | K10: =ML_Sum!$K10 -> 1 | L10: =ML_Sum!$L10 -> 1 | M10: =ML_Sum!$M10 -> 1 | N10: =ML_Sum!$N10 -> 1 | O10: =ML_Sum!$O10 -> 1 | Q10: =ML_Sum!$Q10 -> 0 | R10: mu_I | S10: =ML_Sum!$S10 -> 1.180038 | T10: =ML_Sum!$T10 -> 32.403843
C11: =ML_Sum!$C11 -> 1 | F11: =ML_Sum!$F11 -> 0 | Q11: =ML_Sum!$Q11 -> 0 | R11: mu_J | S11: =ML_Sum!$S11 -> 0 | T11: =ML_Sum!$T11 -> 0
C12: =ML_Sum!$C12 -> 1 | F12: =ML_Sum!$F12 -> 0 | Q12: =ML_Sum!$Q12 -> 0 | R12: MIXED | S12: =ML_Sum!$S12 -> MAT MU | T12: =ML_Sum!$T12 -> LAB RATE
G13: ISELL | H13: C_CODE | I13: MAKE | J13: PART_NO | K13: MARKUP | L13: TYPE | M13: LIST_P | N13: P_FACT | O13: FIX | P13: DATE | Q13: %Dsct in BOQ | R13: MU TYPE | S13: MAT MU | T13: LAB RATE | AM13: Tot Mat Cost | AN13: Unit Lab phr. | AO13: Tot Lab phr. | AP13: < for ELM / MEE
K14: TB
C15: t | D15: Item: 2
D16: FIRE STOPPING | E16: Rates quoted by Gledys updated by 50%
K18: TB
C19: t | D19: Item: 2
D20: Fire stopping of all services through fire compartments including all supplies of firestopping intumescent blocks, fire rated expanding foam, intumescent mastic, intumescent pillows, etc. for a complete installation. Fire stopping shall be done from both sides of the fire compartment.
E22: Sell Rate | F22: Sell Total | K22: IB | AG22: U_M_Sell | AH22: T_M_Sell | AI22: U_L_Sell | AJ22: T_L_Sell | AK22: Total_Sell | AM22: T_M_Cost | AN22: T_L_Phr | AO22: Mat/Lab=1
A23: 5 | B23: No | D23: Item: 2.001 | E23: =IF(AND($A23=0,$A$1="DIF"),0, ROUND(ROUND(($R27*$S$7+($T27*$T$7))/$A23,2)*$C$7,2)) -> 57.02 | F23: =ROUND($A23*$E23,2) -> 285.1 | G23: ISELL | K23: mu_F | L23: ITEM | T23: =IF(AND($R27=0,$T27=0),"0.00","mu: "& ROUND(F23/$C$7/($R27+$T27*$D$9),2)) -> mu: 1.23 | AG23: =IF($E23=0,0,ROUND($R27*$S$7*$C$7/$A23,2)) -> 11.38 | AH23: =$AG23*$A23 -> 56.9 | AI23: =$E23-$AG23 -> 45.64 | AJ23: =$A23*$AI23 -> 228.2 | AK23: =ROUND(($AG23+$AI23)*$A23,2) -> 285.1 | AM23: =ROUND(R27,2) -> 46.2 | AN23: =ROUND(T27,2) -> 6.75 | AO23: =ROUND(AM23+AN23,2)*A23 -> 264.75
D24: 150 x 150 mm | K24: n
A25: 5 | B25: LS | D25: FIRE BARRIERS | E25: =D24 -> 150 x 150 mm | G25: FIBA_001 | H25: 726 | I25: (__) | O25: 3 | Q25: =1.1 *(8.4) -> 9.24 | R25: =$A25*Q25 -> 46.2 | S25: 1.5 | T25: =$A25*S25*$T$1 -> 6.75 | W25: 2
R26: =$A26*Q26 -> 0 | T26: =$A26*S26*$T$1 -> 0
A27: d> | B27: =(R26+T26) -> 0 | G27: ICOST | K27: mu_F | L27: ITEM | R27: =SUM(R24:R26) -> 46.2 | T27: =SUM(T24:T26) -> 6.75
E28: Sell Rate | F28: Sell Total | K28: IB | AG28: U_M_Sell | AH28: T_M_Sell | AI28: U_L_Sell | AJ28: T_L_Sell | AK28: Total_Sell | AM28: T_M_Cost | AN28: T_L_Phr | AO28: Mat/Lab=1
A29: 5 | B29: No | D29: Item: 2.002 | E29: =IF(AND($A29=0,$A$1="DIF"),0, ROUND(ROUND(($R33*$S$7+($T33*$T$7))/$A29,2)*$C$7,2)) -> 55.75 | F29: =ROUND($A29*$E29,2) -> 278.75 | G29: ISELL | K29: mu_F | L29: ITEM | T29: =IF(AND($R33=0,$T33=0),"0.00","mu: "& ROUND(F29/$C$7/($R33+$T33*$D$9),2)) -> mu: 1.23 | AG29: =IF($E29=0,0,ROUND($R33*$S$7*$C$7/$A29,2)) -> 10.1 | AH29: =$AG29*$A29 -> 50.5 | AI29: =$E29-$AG29 -> 45.65 | AJ29: =$A29*$AI29 -> 228.25 | AK29: =ROUND(($AG29+$AI29)*$A29,2) -> 278.75 | AM29: =ROUND(R33,2) -> 41.03 | AN29: =ROUND(T33,2) -> 6.75 | AO29: =ROUND(AM29+AN29,2)*A29 -> 238.9
D30: 200 x 100 mm | K30: n
A31: 5 | B31: LS | D31: FIRE BARRIERS | E31: =D30 -> 200 x 100 mm | G31: FIBA_001 | H31: 726 | I31: (__) | O31: 3 | Q31: =1.1 *(7.46) -> 8.206 | R31: =$A31*Q31 -> 41.03 | S31: 1.5 | T31: =$A31*S31*$T$1 -> 6.75 | W31: 2
R32: =$A32*Q32 -> 0 | T32: =$A32*S32*$T$1 -> 0
A33: d> | B33: =(R32+T32) -> 0 | G33: ICOST | K33: mu_F | L33: ITEM | R33: =SUM(R30:R32) -> 41.03 | T33: =SUM(T30:T32) -> 6.75
E34: Sell Rate | F34: Sell Total | K34: IB | AG34: U_M_Sell | AH34: T_M_Sell | AI34: U_L_Sell | AJ34: T_L_Sell | AK34: Total_Sell | AM34: T_M_Cost | AN34: T_L_Phr | AO34: Mat/Lab=1
A35: 5 | B35: No | D35: Item: 2.003 | E35: =IF(AND($A35=0,$A$1="DIF"),0, ROUND(ROUND(($R39*$S$7+($T39*$T$7))/$A35,2)*$C$7,2)) -> 65.87 | F35: =ROUND($A35*$E35,2) -> 329.35 | G35: ISELL | K35: mu_F | L35: ITEM | T35: =IF(AND($R39=0,$T39=0),"0.00","mu: "& ROUND(F35/$C$7/($R39+$T39*$D$9),2)) -> mu: 1.23 | AG35: =IF($E35=0,0,ROUND($R39*$S$7*$C$7/$A35,2)) -> 20.22 | AH35: =$AG35*$A35 -> 101.1 | AI35: =$E35-$AG35 -> 45.65 | AJ35: =$A35*$AI35 -> 228.25 | AK35: =ROUND(($AG35+$AI35)*$A35,2) -> 329.35 | AM35: =ROUND(R39,2) -> 82.12 | AN35: =ROUND(T39,2) -> 6.75 | AO35: =ROUND(AM35+AN35,2)*A35 -> 444.35
D36: 200 x 200 mm | K36: n
A37: 5 | B37: LS | D37: FIRE BARRIERS | E37: =D36 -> 200 x 200 mm | G37: FIBA_001 | H37: 726 | I37: (__) | O37: 3 | Q37: =1.1 *(14.93) -> 16.423 | R37: =$A37*Q37 -> 82.115 | S37: 1.5 | T37: =$A37*S37*$T$1 -> 6.75 | W37: 2
R38: =$A38*Q38 -> 0 | T38: =$A38*S38*$T$1 -> 0
A39: d> | B39: =(R38+T38) -> 0 | G39: ICOST | K39: mu_F | L39: ITEM | R39: =SUM(R36:R38) -> 82.115 | T39: =SUM(T36:T38) -> 6.75
E40: Sell Rate | F40: Sell Total | K40: IB | AG40: U_M_Sell | AH40: T_M_Sell | AI40: U_L_Sell | AJ40: T_L_Sell | AK40: Total_Sell | AM40: T_M_Cost | AN40: T_L_Phr | AO40: Mat/Lab=1
A41: 5 | B41: No | D41: Item: 2.004 | E41: =IF(AND($A41=0,$A$1="DIF"),0, ROUND(ROUND(($R45*$S$7+($T45*$T$7))/$A41,2)*$C$7,2)) -> 60.8 | F41: =ROUND($A41*$E41,2) -> 304 | G41: ISELL | K41: mu_F | L41: ITEM | T41: =IF(AND($R45=0,$T45=0),"0.00","mu: "& ROUND(F41/$C$7/($R45+$T45*$D$9),2)) -> mu: 1.23 | AG41: =IF($E41=0,0,ROUND($R45*$S$7*$C$7/$A41,2)) -> 15.16 | AH41: =$AG41*$A41 -> 75.8 | AI41: =$E41-$AG41 -> 45.64 | AJ41: =$A41*$AI41 -> 228.2 | AK41: =ROUND(($AG41+$AI41)*$A41,2) -> 304 | AM41: =ROUND(R45,2) -> 61.55 | AN41: =ROUND(T45,2) -> 6.75 | AO41: =ROUND(AM41+AN41,2)*A41 -> 341.5
D42: 300 x 100 mm | K42: n
A43: 5 | B43: LS | D43: FIRE BARRIERS | E43: =D42 -> 300 x 100 mm | G43: FIBA_001 | H43: 726 | I43: (__) | O43: 3 | Q43: =1.1 *(11.19) -> 12.309 | R43: =$A43*Q43 -> 61.545 | S43: 1.5 | T43: =$A43*S43*$T$1 -> 6.75 | W43: 2
R44: =$A44*Q44 -> 0 | T44: =$A44*S44*$T$1 -> 0
A45: d> | B45: =(R44+T44) -> 0 | G45: ICOST | K45: mu_F | L45: ITEM | R45: =SUM(R42:R44) -> 61.545 | T45: =SUM(T42:T44) -> 6.75
E46: Sell Rate | F46: Sell Total | K46: IB | AG46: U_M_Sell | AH46: T_M_Sell | AI46: U_L_Sell | AJ46: T_L_Sell | AK46: Total_Sell | AM46: T_M_Cost | AN46: T_L_Phr | AO46: Mat/Lab=1
A47: 5 | B47: No | D47: Item: 2.005 | E47: =IF(AND($A47=0,$A$1="DIF"),0, ROUND(ROUND(($R51*$S$7+($T51*$T$7))/$A47,2)*$C$7,2)) -> 75.97 | F47: =ROUND($A47*$E47,2) -> 379.85 | G47: ISELL | K47: mu_F | L47: ITEM | T47: =IF(AND($R51=0,$T51=0),"0.00","mu: "& ROUND(F47/$C$7/($R51+$T51*$D$9),2)) -> mu: 1.23 | AG47: =IF($E47=0,0,ROUND($R51*$S$7*$C$7/$A47,2)) -> 30.33 | AH47: =$AG47*$A47 -> 151.65 | AI47: =$E47-$AG47 -> 45.64 | AJ47: =$A47*$AI47 -> 228.2 | AK47: =ROUND(($AG47+$AI47)*$A47,2) -> 379.85 | AM47: =ROUND(R51,2) -> 123.15 | AN47: =ROUND(T51,2) -> 6.75 | AO47: =ROUND(AM47+AN47,2)*A47 -> 649.5
D48: 300 x 200 mm | K48: n
A49: 5 | B49: LS | D49: FIRE BARRIERS | E49: =D48 -> 300 x 200 mm | G49: FIBA_001 | H49: 726 | I49: (__) | O49: 3 | Q49: =1.1 *(22.39) -> 24.629 | R49: =$A49*Q49 -> 123.145 | S49: 1.5 | T49: =$A49*S49*$T$1 -> 6.75 | W49: 2
R50: =$A50*Q50 -> 0 | T50: =$A50*S50*$T$1 -> 0
A51: d> | B51: =(R50+T50) -> 0 | G51: ICOST | K51: mu_F | L51: ITEM | R51: =SUM(R48:R50) -> 123.145 | T51: =SUM(T48:T50) -> 6.75
E52: Sell Rate | F52: Sell Total | K52: IB | AG52: U_M_Sell | AH52: T_M_Sell | AI52: U_L_Sell | AJ52: T_L_Sell | AK52: Total_Sell | AM52: T_M_Cost | AN52: T_L_Phr | AO52: Mat/Lab=1
A53: 5 | B53: No | D53: Item: 2.006 | E53: =IF(AND($A53=0,$A$1="DIF"),0, ROUND(ROUND(($R57*$S$7+($T57*$T$7))/$A53,2)*$C$7,2)) -> 91.13 | F53: =ROUND($A53*$E53,2) -> 455.65 | G53: ISELL | K53: mu_F | L53: ITEM | T53: =IF(AND($R57=0,$T57=0),"0.00","mu: "& ROUND(F53/$C$7/($R57+$T57*$D$9),2)) -> mu: 1.23 | AG53: =IF($E53=0,0,ROUND($R57*$S$7*$C$7/$A53,2)) -> 45.48 | AH53: =$AG53*$A53 -> 227.4 | AI53: =$E53-$AG53 -> 45.65 | AJ53: =$A53*$AI53 -> 228.25 | AK53: =ROUND(($AG53+$AI53)*$A53,2) -> 455.65 | AM53: =ROUND(R57,2) -> 184.69 | AN53: =ROUND(T57,2) -> 6.75 | AO53: =ROUND(AM53+AN53,2)*A53 -> 957.2
D54: 300 x 300 mm | K54: n
A55: 5 | B55: LS | D55: FIRE BARRIERS | E55: =D54 -> 300 x 300 mm | G55: FIBA_001 | H55: 726 | I55: (__) | O55: 3 | Q55: =1.1 *(33.58) -> 36.938 | R55: =$A55*Q55 -> 184.69 | S55: 1.5 | T55: =$A55*S55*$T$1 -> 6.75 | W55: 2
R56: =$A56*Q56 -> 0 | T56: =$A56*S56*$T$1 -> 0
A57: d> | B57: =(R56+T56) -> 0 | G57: ICOST | K57: mu_F | L57: ITEM | R57: =SUM(R54:R56) -> 184.69 | T57: =SUM(T54:T56) -> 6.75
E58: Sell Rate | F58: Sell Total | K58: IB | AG58: U_M_Sell | AH58: T_M_Sell | AI58: U_L_Sell | AJ58: T_L_Sell | AK58: Total_Sell | AM58: T_M_Cost | AN58: T_L_Phr | AO58: Mat/Lab=1
A59: 5 | B59: No | D59: Item: 2.007 | E59: =IF(AND($A59=0,$A$1="DIF"),0, ROUND(ROUND(($R63*$S$7+($T63*$T$7))/$A59,2)*$C$7,2)) -> 65.87 | F59: =ROUND($A59*$E59,2) -> 329.35 | G59: ISELL | K59: mu_F | L59: ITEM | T59: =IF(AND($R63=0,$T63=0),"0.00","mu: "& ROUND(F59/$C$7/($R63+$T63*$D$9),2)) -> mu: 1.23 | AG59: =IF($E59=0,0,ROUND($R63*$S$7*$C$7/$A59,2)) -> 20.22 | AH59: =$AG59*$A59 -> 101.1 | AI59: =$E59-$AG59 -> 45.65 | AJ59: =$A59*$AI59 -> 228.25 | AK59: =ROUND(($AG59+$AI59)*$A59,2) -> 329.35 | AM59: =ROUND(R63,2) -> 82.12 | AN59: =ROUND(T63,2) -> 6.75 | AO59: =ROUND(AM59+AN59,2)*A59 -> 444.35
D60: 400 x 100 mm | K60: n
A61: 5 | B61: LS | D61: FIRE BARRIERS | E61: =D60 -> 400 x 100 mm | G61: FIBA_001 | H61: 726 | I61: (__) | O61: 3 | Q61: =1.1 *(14.93) -> 16.423 | R61: =$A61*Q61 -> 82.115 | S61: 1.5 | T61: =$A61*S61*$T$1 -> 6.75 | W61: 2
R62: =$A62*Q62 -> 0 | T62: =$A62*S62*$T$1 -> 0
A63: d> | B63: =(R62+T62) -> 0 | G63: ICOST | K63: mu_F | L63: ITEM | R63: =SUM(R60:R62) -> 82.115 | T63: =SUM(T60:T62) -> 6.75
E64: Sell Rate | F64: Sell Total | K64: IB | AG64: U_M_Sell | AH64: T_M_Sell | AI64: U_L_Sell | AJ64: T_L_Sell | AK64: Total_Sell | AM64: T_M_Cost | AN64: T_L_Phr | AO64: Mat/Lab=1
A65: 5 | B65: No | D65: Item: 2.008 | E65: =IF(AND($A65=0,$A$1="DIF"),0, ROUND(ROUND(($R69*$S$7+($T69*$T$7))/$A65,2)*$C$7,2)) -> 86.08 | F65: =ROUND($A65*$E65,2) -> 430.4 | G65: ISELL | K65: mu_F | L65: ITEM | T65: =IF(AND($R69=0,$T69=0),"0.00","mu: "& ROUND(F65/$C$7/($R69+$T69*$D$9),2)) -> mu: 1.23 | AG65: =IF($E65=0,0,ROUND($R69*$S$7*$C$7/$A65,2)) -> 40.43 | AH65: =$AG65*$A65 -> 202.15 | AI65: =$E65-$AG65 -> 45.65 | AJ65: =$A65*$AI65 -> 228.25 | AK65: =ROUND(($AG65+$AI65)*$A65,2) -> 430.4 | AM65: =ROUND(R69,2) -> 164.18 | AN65: =ROUND(T69,2) -> 6.75 | AO65: =ROUND(AM65+AN65,2)*A65 -> 854.65
D66: 400 x 200 mm | K66: n
A67: 5 | B67: LS | D67: FIRE BARRIERS | E67: =D66 -> 400 x 200 mm | G67: FIBA_001 | H67: 726 | I67: (__) | O67: 3 | Q67: =1.1 *(29.85) -> 32.835 | R67: =$A67*Q67 -> 164.175 | S67: 1.5 | T67: =$A67*S67*$T$1 -> 6.75 | W67: 2
R68: =$A68*Q68 -> 0 | T68: =$A68*S68*$T$1 -> 0
A69: d> | B69: =(R68+T68) -> 0 | G69: ICOST | K69: mu_F | L69: ITEM | R69: =SUM(R66:R68) -> 164.175 | T69: =SUM(T66:T68) -> 6.75
E70: Sell Rate | F70: Sell Total | K70: IB | AG70: U_M_Sell | AH70: T_M_Sell | AI70: U_L_Sell | AJ70: T_L_Sell | AK70: Total_Sell | AM70: T_M_Cost | AN70: T_L_Phr | AO70: Mat/Lab=1
A71: 5 | B71: No | D71: Item: 2.009 | E71: =IF(AND($A71=0,$A$1="DIF"),0, ROUND(ROUND(($R75*$S$7+($T75*$T$7))/$A71,2)*$C$7,2)) -> 106.3 | F71: =ROUND($A71*$E71,2) -> 531.5 | G71: ISELL | K71: mu_F | L71: ITEM | T71: =IF(AND($R75=0,$T75=0),"0.00","mu: "& ROUND(F71/$C$7/($R75+$T75*$D$9),2)) -> mu: 1.23 | AG71: =IF($E71=0,0,ROUND($R75*$S$7*$C$7/$A71,2)) -> 60.65 | AH71: =$AG71*$A71 -> 303.25 | AI71: =$E71-$AG71 -> 45.65 | AJ71: =$A71*$AI71 -> 228.25 | AK71: =ROUND(($AG71+$AI71)*$A71,2) -> 531.5 | AM71: =ROUND(R75,2) -> 246.29 | AN71: =ROUND(T75,2) -> 6.75 | AO71: =ROUND(AM71+AN71,2)*A71 -> 1265.2
D72: 400 x 300 mm | K72: n
A73: 5 | B73: LS | D73: FIRE BARRIERS | E73: =D72 -> 400 x 300 mm | G73: FIBA_001 | H73: 726 | I73: (__) | O73: 3 | Q73: =1.1 *(44.78) -> 49.258 | R73: =$A73*Q73 -> 246.29 | S73: 1.5 | T73: =$A73*S73*$T$1 -> 6.75 | W73: 2
R74: =$A74*Q74 -> 0 | T74: =$A74*S74*$T$1 -> 0
A75: d> | B75: =(R74+T74) -> 0 | G75: ICOST | K75: mu_F | L75: ITEM | R75: =SUM(R72:R74) -> 246.29 | T75: =SUM(T72:T74) -> 6.75
E76: Sell Rate | F76: Sell Total | K76: IB | AG76: U_M_Sell | AH76: T_M_Sell | AI76: U_L_Sell | AJ76: T_L_Sell | AK76: Total_Sell | AM76: T_M_Cost | AN76: T_L_Phr | AO76: Mat/Lab=1
A77: 5 | B77: No | D77: Item: 2.01 | E77: =IF(AND($A77=0,$A$1="DIF"),0, ROUND(ROUND(($R81*$S$7+($T81*$T$7))/$A77,2)*$C$7,2)) -> 126.51 | F77: =ROUND($A77*$E77,2) -> 632.55 | G77: ISELL | K77: mu_F | L77: ITEM | T77: =IF(AND($R81=0,$T81=0),"0.00","mu: "& ROUND(F77/$C$7/($R81+$T81*$D$9),2)) -> mu: 1.23 | AG77: =IF($E77=0,0,ROUND($R81*$S$7*$C$7/$A77,2)) -> 80.86 | AH77: =$AG77*$A77 -> 404.3 | AI77: =$E77-$AG77 -> 45.65 | AJ77: =$A77*$AI77 -> 228.25 | AK77: =ROUND(($AG77+$AI77)*$A77,2) -> 632.55 | AM77: =ROUND(R81,2) -> 328.35 | AN77: =ROUND(T81,2) -> 6.75 | AO77: =ROUND(AM77+AN77,2)*A77 -> 1675.5
D78: 400 x 400 mm | K78: n
A79: 5 | B79: LS | D79: FIRE BARRIERS | E79: =D78 -> 400 x 400 mm | G79: FIBA_001 | H79: 726 | I79: (__) | O79: 3 | Q79: =1.1 *(59.7) -> 65.67 | R79: =$A79*Q79 -> 328.35 | S79: 1.5 | T79: =$A79*S79*$T$1 -> 6.75 | W79: 2
R80: =$A80*Q80 -> 0 | T80: =$A80*S80*$T$1 -> 0
A81: d> | B81: =(R80+T80) -> 0 | G81: ICOST | K81: mu_F | L81: ITEM | R81: =SUM(R78:R80) -> 328.35 | T81: =SUM(T78:T80) -> 6.75
E82: Sell Rate | F82: Sell Total | K82: IB | AG82: U_M_Sell | AH82: T_M_Sell | AI82: U_L_Sell | AJ82: T_L_Sell | AK82: Total_Sell | AM82: T_M_Cost | AN82: T_L_Phr | AO82: Mat/Lab=1
A83: 5 | B83: No | D83: Item: 2.011 | E83: =IF(AND($A83=0,$A$1="DIF"),0, ROUND(ROUND(($R87*$S$7+($T87*$T$7))/$A83,2)*$C$7,2)) -> 70.92 | F83: =ROUND($A83*$E83,2) -> 354.6 | G83: ISELL | K83: mu_F | L83: ITEM | T83: =IF(AND($R87=0,$T87=0),"0.00","mu: "& ROUND(F83/$C$7/($R87+$T87*$D$9),2)) -> mu: 1.23 | AG83: =IF($E83=0,0,ROUND($R87*$S$7*$C$7/$A83,2)) -> 25.27 | AH83: =$AG83*$A83 -> 126.35 | AI83: =$E83-$AG83 -> 45.65 | AJ83: =$A83*$AI83 -> 228.25 | AK83: =ROUND(($AG83+$AI83)*$A83,2) -> 354.6 | AM83: =ROUND(R87,2) -> 102.63 | AN83: =ROUND(T87,2) -> 6.75 | AO83: =ROUND(AM83+AN83,2)*A83 -> 546.9
D84: 500 x 100 mm | K84: n
A85: 5 | B85: LS | D85: FIRE BARRIERS | E85: =D84 -> 500 x 100 mm | G85: FIBA_001 | H85: 726 | I85: (__) | O85: 3 | Q85: =1.1 *(18.66) -> 20.526 | R85: =$A85*Q85 -> 102.63 | S85: 1.5 | T85: =$A85*S85*$T$1 -> 6.75 | W85: 2
R86: =$A86*Q86 -> 0 | T86: =$A86*S86*$T$1 -> 0
A87: d> | B87: =(R86+T86) -> 0 | G87: ICOST | K87: mu_F | L87: ITEM | R87: =SUM(R84:R86) -> 102.63 | T87: =SUM(T84:T86) -> 6.75
E88: Sell Rate | F88: Sell Total | K88: IB | AG88: U_M_Sell | AH88: T_M_Sell | AI88: U_L_Sell | AJ88: T_L_Sell | AK88: Total_Sell | AM88: T_M_Cost | AN88: T_L_Phr | AO88: Mat/Lab=1
A89: 5 | B89: No | D89: Item: 2.012 | E89: =IF(AND($A89=0,$A$1="DIF"),0, ROUND(ROUND(($R93*$S$7+($T93*$T$7))/$A89,2)*$C$7,2)) -> 96.18 | F89: =ROUND($A89*$E89,2) -> 480.9 | G89: ISELL | K89: mu_F | L89: ITEM | T89: =IF(AND($R93=0,$T93=0),"0.00","mu: "& ROUND(F89/$C$7/($R93+$T93*$D$9),2)) -> mu: 1.23 | AG89: =IF($E89=0,0,ROUND($R93*$S$7*$C$7/$A89,2)) -> 50.54 | AH89: =$AG89*$A89 -> 252.7 | AI89: =$E89-$AG89 -> 45.64 | AJ89: =$A89*$AI89 -> 228.2 | AK89: =ROUND(($AG89+$AI89)*$A89,2) -> 480.9 | AM89: =ROUND(R93,2) -> 205.21 | AN89: =ROUND(T93,2) -> 6.75 | AO89: =ROUND(AM89+AN89,2)*A89 -> 1059.8
D90: 500 x 200 mm | K90: n
A91: 5 | B91: LS | D91: FIRE BARRIERS | E91: =D90 -> 500 x 200 mm | G91: FIBA_001 | H91: 726 | I91: (__) | O91: 3 | Q91: =1.1 *(37.31) -> 41.041 | R91: =$A91*Q91 -> 205.205 | S91: 1.5 | T91: =$A91*S91*$T$1 -> 6.75 | W91: 2
R92: =$A92*Q92 -> 0 | T92: =$A92*S92*$T$1 -> 0
A93: d> | B93: =(R92+T92) -> 0 | G93: ICOST | K93: mu_F | L93: ITEM | R93: =SUM(R90:R92) -> 205.205 | T93: =SUM(T90:T92) -> 6.75
E94: Sell Rate | F94: Sell Total | K94: IB | AG94: U_M_Sell | AH94: T_M_Sell | AI94: U_L_Sell | AJ94: T_L_Sell | AK94: Total_Sell | AM94: T_M_Cost | AN94: T_L_Phr | AO94: Mat/Lab=1
A95: 5 | B95: No | D95: Item: 2.013 | E95: =IF(AND($A95=0,$A$1="DIF"),0, ROUND(ROUND(($R99*$S$7+($T99*$T$7))/$A95,2)*$C$7,2)) -> 121.46 | F95: =ROUND($A95*$E95,2) -> 607.3 | G95: ISELL | K95: mu_F | L95: ITEM | T95: =IF(AND($R99=0,$T99=0),"0.00","mu: "& ROUND(F95/$C$7/($R99+$T99*$D$9),2)) -> mu: 1.23 | AG95: =IF($E95=0,0,ROUND($R99*$S$7*$C$7/$A95,2)) -> 75.81 | AH95: =$AG95*$A95 -> 379.05 | AI95: =$E95-$AG95 -> 45.65 | AJ95: =$A95*$AI95 -> 228.25 | AK95: =ROUND(($AG95+$AI95)*$A95,2) -> 607.3 | AM95: =ROUND(R99,2) -> 307.84 | AN95: =ROUND(T99,2) -> 6.75 | AO95: =ROUND(AM95+AN95,2)*A95 -> 1572.95
D96: 500 x 300 mm | K96: n
A97: 5 | B97: LS | D97: FIRE BARRIERS | E97: =D96 -> 500 x 300 mm | G97: FIBA_001 | H97: 726 | I97: (__) | O97: 3 | Q97: =1.1 *(55.97) -> 61.567 | R97: =$A97*Q97 -> 307.835 | S97: 1.5 | T97: =$A97*S97*$T$1 -> 6.75 | W97: 2
R98: =$A98*Q98 -> 0 | T98: =$A98*S98*$T$1 -> 0
A99: d> | B99: =(R98+T98) -> 0 | G99: ICOST | K99: mu_F | L99: ITEM | R99: =SUM(R96:R98) -> 307.835 | T99: =SUM(T96:T98) -> 6.75
E100: Sell Rate | F100: Sell Total | K100: IB | AG100: U_M_Sell | AH100: T_M_Sell | AI100: U_L_Sell | AJ100: T_L_Sell | AK100: Total_Sell | AM100: T_M_Cost | AN100: T_L_Phr | AO100: Mat/Lab=1
A101: 5 | B101: No | D101: Item: 2.014 | E101: =IF(AND($A101=0,$A$1="DIF"),0, ROUND(ROUND(($R105*$S$7+($T105*$T$7))/$A101,2)*$C$7,2)) -> 146.73 | F101: =ROUND($A101*$E101,2) -> 733.65 | G101: ISELL | K101: mu_F | L101: ITEM | T101: =IF(AND($R105=0,$T105=0),"0.00","mu: "& ROUND(F101/$C$7/($R105+$T105*$D$9),2)) -> mu: 1.23 | AG101: =IF($E101=0,0,ROUND($R105*$S$7*$C$7/$A101,2)) -> 101.08 | AH101: =$AG101*$A101 -> 505.4 | AI101: =$E101-$AG101 -> 45.65 | AJ101: =$A101*$AI101 -> 228.25 | AK101: =ROUND(($AG101+$AI101)*$A101,2) -> 733.65 | AM101: =ROUND(R105,2) -> 410.47 | AN101: =ROUND(T105,2) -> 6.75 | AO101: =ROUND(AM101+AN101,2)*A101 -> 2086.1
D102: 500 x 400 mm | K102: n
...

Sheet MEP_BOQ
B2: SECTION 1 - MECHANICAL, ELECTRICAL AND PLUMBING
A4: ITEM | B4: DESCRIPTION | C4: QTY | D4: UNIT | E4: RATE Euro (Exc of VAT) | F4: TOTAL Euro (Exc of VAT)
A5: 1 | B5: PRELIMINARIES
B6: All equipment to be used within this contract is to be approved prior to delivery to site.
A7: =IFERROR(IF(OFFSET(A7,-1,0)>0,OFFSET(A7,-1,0)+0.001,ERROR.TYPE(0)),IFERROR(IF(OFFSET(A7,-2,0)>0,OFFSET(A7,-2,0)+0.001,ERROR.TYPE(0)),IFERROR(IF(OFFSET(A7,-3,0)>0,OFFSET(A7,-3,0)+0.001,ERROR.TYPE(0)),IFERROR(IF(OFFSET(A7,-4,0)>0,OFFSET(A7,-4,0)+0.001,ERROR.TYPE(0)),IFERROR(IF(OFFSET(A7,-5,0)>0,OFFSET(A7,-5,0)+0.001,ERROR.TYPE(0)),IFERROR(IF(OFFSET(A7,-6,0)>0,OFFSET(A7,-6,0)+0.001,ERROR.TYPE(0)),IFERROR(IF(OFFSET(A7,-7,0)>0,OFFSET(A7,-7,0)+0.001,ERROR.TYPE(0)),IFERROR(IF(OFFSET(A7,-8,0)>0,OFFSET(A7,-8,0)+0.001,ERROR.TYPE(0)),IFERROR(IF(OFFSET(A7,-9,0)>0,OFFSET(A7,-9,0)+0.001,ERROR.TYPE(0)),IFERROR(IF(OFFSET(A7,-10,0)>0,OFFSET(A7,-10,0)+0.001,ERROR.TYPE(0)),ERROR.TYPE(0))))))))))) -> 1.001 | B7: Mobilisation of site including the setting up of Storage facilities for materials, Sanitary facilities for the employees, Setting up of temporary site office, etc required to undertake the works | C7: 1 | D7: L.S. | E7: =Elec_Est!E23 -> 2462.69 | F7: =IFERROR($C7*E7,E7) -> 2462.69
A8: =IFERROR(IF(OFFSET(A8,-1,0)>0,OFFSET(A8,-1,0)+0.001,ERROR.TYPE(0)),IFERROR(IF(OFFSET(A8,-2,0)>0,OFFSET(A8,-2,0)+0.001,ERROR.TYPE(0)),IFERROR(IF(OFFSET(A8,-3,0)>0,OFFSET(A8,-3,0)+0.001,ERROR.TYPE(0)),IFERROR(IF(OFFSET(A8,-4,0)>0,OFFSET(A8,-4,0)+0.001,ERROR.TYPE(0)),IFERROR(IF(OFFSET(A8,-5,0)>0,OFFSET(A8,-5,0)+0.001,ERROR.TYPE(0)),IFERROR(IF(OFFSET(A8,-6,0)>0,OFFSET(A8,-6,0)+0.001,ERROR.TYPE(0)),IFERROR(IF(OFFSET(A8,-7,0)>0,OFFSET(A8,-7,0)+0.001,ERROR.TYPE(0)),IFERROR(IF(OFFSET(A8,-8,0)>0,OFFSET(A8,-8,0)+0.001,ERROR.TYPE(0)),IFERROR(IF(OFFSET(A8,-9,0)>0,OFFSET(A8,-9,0)+0.001,ERROR.TYPE(0)),IFERROR(IF(OFFSET(A8,-10,0)>0,OFFSET(A8,-10,0)+0.001,ERROR.TYPE(0)),ERROR.TYPE(0))))))))))) -> 1.002 | B8: Provision of insurance cover in the joint names of the Client and Contractor insure the Works against loss or damage by fire, storm, tempest, lightning, flood, earthquake, aircraft or anything dropped there from, aerial objects, riot and civil commotion for the full reinstatement value thereof plus 15% of all the Works executed and all unfixed materials and goods so insured until the completion of the Works. The Contractor shall affect a policy of insurance against third party risks to cover an amount of not less than Euro 500,000 (five hundred thousand Euros) for any one accident. The policy shall be in joint names of the Client and Contractor and shall include cross liability clauses. In respect of liability for the death or injury to any person employed by the Contractor and arising out of and in the course of such person's employment by the Contractor the amount insured by the Contractor shall be such as to indemnify the Client against all damages as compensation payable. The Contractor shall comply with and be subject to the terms, exclusions, exceptions, conditions and limitations of the insurance policies and shall bear the amount of the retained liabilities stated therein The Contractor shall deposit with the Client copies of the policy or policies and a copy of the receipt in respect of premiums paid before starting the Works | C8: 1 | D8: L.S. | E8: =Elec_Est!Q29 -> Included
A9: =IFERROR(IF(OFFSET(A9,-1,0)>0,OFFSET(A9,-1,0)+0.001,ERROR.TYPE(0)),IFERROR(IF(OFFSET(A9,-2,0)>0,OFFSET(A9,-2,0)+0.001,ERROR.TYPE(0)),IFERROR(IF(OFFSET(A9,-3,0)>0,OFFSET(A9,-3,0)+0.001,ERROR.TYPE(0)),IFERROR(IF(OFFSET(A9,-4,0)>0,OFFSET(A9,-4,0)+0.001,ERROR.TYPE(0)),IFERROR(IF(OFFSET(A9,-5,0)>0,OFFSET(A9,-5,0)+0.001,ERROR.TYPE(0)),IFERROR(IF(OFFSET(A9,-6,0)>0,OFFSET(A9,-6,0)+0.001,ERROR.TYPE(0)),IFERROR(IF(OFFSET(A9,-7,0)>0,OFFSET(A9,-7,0)+0.001,ERROR.TYPE(0)),IFERROR(IF(OFFSET(A9,-8,0)>0,OFFSET(A9,-8,0)+0.001,ERROR.TYPE(0)),IFERROR(IF(OFFSET(A9,-9,0)>0,OFFSET(A9,-9,0)+0.001,ERROR.TYPE(0)),IFERROR(IF(OFFSET(A9,-10,0)>0,OFFSET(A9,-10,0)+0.001,ERROR.TYPE(0)),ERROR.TYPE(0))))))))))) -> 1.003 | B9: Implementation of health and safety measures on site including personal safety (e.g safety shoes, helmets scaffolding, harnesses etc) as well as those to render the site safe for employees (e.g staircase handrails, closing of lift shaft openings etc) | C9: 1 | D9: L.S. | E9: =Elec_Est!Q39 -> Refer to covering letter
A10: =IFERROR(IF(OFFSET(A10,-1,0)>0,OFFSET(A10,-1,0)+0.001,ERROR.TYPE(0)),IFERROR(IF(OFFSET(A10,-2,0)>0,OFFSET(A10,-2,0)+0.001,ERROR.TYPE(0)),IFERROR(IF(OFFSET(A10,-3,0)>0,OFFSET(A10,-3,0)+0.001,ERROR.TYPE(0)),IFERROR(IF(OFFSET(A10,-4,0)>0,OFFSET(A10,-4,0)+0.001,ERROR.TYPE(0)),IFERROR(IF(OFFSET(A10,-5,0)>0,OFFSET(A10,-5,0)+0.001,ERROR.TYPE(0)),IFERROR(IF(OFFSET(A10,-6,0)>0,OFFSET(A10,-6,0)+0.001,ERROR.TYPE(0)),IFERROR(IF(OFFSET(A10,-7,0)>0,OFFSET(A10,-7,0)+0.001,ERROR.TYPE(0)),IFERROR(IF(OFFSET(A10,-8,0)>0,OFFSET(A10,-8,0)+0.001,ERROR.TYPE(0)),IFERROR(IF(OFFSET(A10,-9,0)>0,OFFSET(A10,-9,0)+0.001,ERROR.TYPE(0)),IFERROR(IF(OFFSET(A10,-10,0)>0,OFFSET(A10,-10,0)+0.001,ERROR.TYPE(0)),ERROR.TYPE(0))))))))))) -> 1.004 | B10: Prepare a risk assessment report outlining all risks involved and measures to be taken to minimise or eliminate potential risks. The report is to be prepared and signed by a competent person and to be submitted within three weeks from commencement of works. | C10: 1 | D10: L.S. | E10: =Elec_Est!E49 -> 4369.3 | F10: =IFERROR($C10*E10,E10) -> 4369.3
A11: =IFERROR(IF(OFFSET(A11,-1,0)>0,OFFSET(A11,-1,0)+0.001,ERROR.TYPE(0)),IFERROR(IF(OFFSET(A11,-2,0)>0,OFFSET(A11,-2,0)+0.001,ERROR.TYPE(0)),IFERROR(IF(OFFSET(A11,-3,0)>0,OFFSET(A11,-3,0)+0.001,ERROR.TYPE(0)),IFERROR(IF(OFFSET(A11,-4,0)>0,OFFSET(A11,-4,0)+0.001,ERROR.TYPE(0)),IFERROR(IF(OFFSET(A11,-5,0)>0,OFFSET(A11,-5,0)+0.001,ERROR.TYPE(0)),IFERROR(IF(OFFSET(A11,-6,0)>0,OFFSET(A11,-6,0)+0.001,ERROR.TYPE(0)),IFERROR(IF(OFFSET(A11,-7,0)>0,OFFSET(A11,-7,0)+0.001,ERROR.TYPE(0)),IFERROR(IF(OFFSET(A11,-8,0)>0,OFFSET(A11,-8,0)+0.001,ERROR.TYPE(0)),IFERROR(IF(OFFSET(A11,-9,0)>0,OFFSET(A11,-9,0)+0.001,ERROR.TYPE(0)),IFERROR(IF(OFFSET(A11,-10,0)>0,OFFSET(A11,-10,0)+0.001,ERROR.TYPE(0)),ERROR.TYPE(0))))))))))) -> 1.005 | B11: Allow for carrying out all surveys, setting out of works unless included elsewhere in the Bills of Quantities. | C11: 1 | D11: L.S. | E11: =Elec_Est!Q58 -> Included
B12: TOTAL FOR PAGE 01 | C12: Euro Exc VAT | F12: =SUM(F7:F11) -> 6831.99
A15: ITEM | B15: DESCRIPTION | C15: QTY | D15: UNIT | E15: RATE Euro (Exc of VAT) | F15: TOTAL Euro (Exc of VAT)
A16: =IFERROR(IF(OFFSET(A16,-1,0)>0,OFFSET(A16,-1,0)+0.001,ERROR.TYPE(0)),IFERROR(IF(OFFSET(A16,-2,0)>0,OFFSET(A16,-2,0)+0.001,ERROR.TYPE(0)),IFERROR(IF(OFFSET(A16,-3,0)>0,OFFSET(A16,-3,0)+0.001,ERROR.TYPE(0)),IFERROR(IF(OFFSET(A16,-4,0)>0,OFFSET(A16,-4,0)+0.001,ERROR.TYPE(0)),IFERROR(IF(OFFSET(A16,-5,0)>0,OFFSET(A16,-5,0)+0.001,ERROR.TYPE(0)),IFERROR(IF(OFFSET(A16,-6,0)>0,OFFSET(A16,-6,0)+0.001,ERROR.TYPE(0)),IFERROR(IF(OFFSET(A16,-7,0)>0,OFFSET(A16,-7,0)+0.001,ERROR.TYPE(0)),IFERROR(IF(OFFSET(A16,-8,0)>0,OFFSET(A16,-8,0)+0.001,ERROR.TYPE(0)),IFERROR(IF(OFFSET(A16,-9,0)>0,OFFSET(A16,-9,0)+0.001,ERROR.TYPE(0)),IFERROR(IF(OFFSET(A16,-10,0)>0,OFFSET(A16,-10,0)+0.001,ERROR.TYPE(0)),ERROR.TYPE(0))))))))))) -> 1.006 | B16: Provision for attending to site to take all relevant measurements in order to ascertain the exact quantities of the individual and measured items to be procured as well as keeping of all relevant records of personnel attendance, stock control etc | C16: 1 | D16: L.S. | E16: =Elec_Est!Q70 -> Included
A17: =IFERROR(IF(OFFSET(A17,-1,0)>0,OFFSET(A17,-1,0)+0.001,ERROR.TYPE(0)),IFERROR(IF(OFFSET(A17,-2,0)>0,OFFSET(A17,-2,0)+0.001,ERROR.TYPE(0)),IFERROR(IF(OFFSET(A17,-3,0)>0,OFFSET(A17,-3,0)+0.001,ERROR.TYPE(0)),IFERROR(IF(OFFSET(A17,-4,0)>0,OFFSET(A17,-4,0)+0.001,ERROR.TYPE(0)),IFERROR(IF(OFFSET(A17,-5,0)>0,OFFSET(A17,-5,0)+0.001,ERROR.TYPE(0)),IFERROR(IF(OFFSET(A17,-6,0)>0,OFFSET(A17,-6,0)+0.001,ERROR.TYPE(0)),IFERROR(IF(OFFSET(A17,-7,0)>0,OFFSET(A17,-7,0)+0.001,ERROR.TYPE(0)),IFERROR(IF(OFFSET(A17,-8,0)>0,OFFSET(A17,-8,0)+0.001,ERROR.TYPE(0)),IFERROR(IF(OFFSET(A17,-9,0)>0,OFFSET(A17,-9,0)+0.001,ERROR.TYPE(0)),IFERROR(IF(OFFSET(A17,-10,0)>0,OFFSET(A17,-10,0)+0.001,ERROR.TYPE(0)),ERROR.TYPE(0))))))))))) -> 1.007 | B17: Provision of security measures on site both as regards the storage facilities as well as to safeguard the materials installed during the latter stages of the project. | C17: 1 | D17: L.S. | E17: =Elec_Est!Q76 -> By Client
A18: =IFERROR(IF(OFFSET(A18,-1,0)>0,OFFSET(A18,-1,0)+0.001,ERROR.TYPE(0)),IFERROR(IF(OFFSET(A18,-2,0)>0,OFFSET(A18,-2,0)+0.001,ERROR.TYPE(0)),IFERROR(IF(OFFSET(A18,-3,0)>0,OFFSET(A18,-3,0)+0.001,ERROR.TYPE(0)),IFERROR(IF(OFFSET(A18,-4,0)>0,OFFSET(A18,-4,0)+0.001,ERROR.TYPE(0)),IFERROR(IF(OFFSET(A18,-5,0)>0,OFFSET(A18,-5,0)+0.001,ERROR.TYPE(0)),IFERROR(IF(OFFSET(A18,-6,0)>0,OFFSET(A18,-6,0)+0.001,ERROR.TYPE(0)),IFERROR(IF(OFFSET(A18,-7,0)>0,OFFSET(A18,-7,0)+0.001,ERROR.TYPE(0)),IFERROR(IF(OFFSET(A18,-8,0)>0,OFFSET(A18,-8,0)+0.001,ERROR.TYPE(0)),IFERROR(IF(OFFSET(A18,-9,0)>0,OFFSET(A18,-9,0)+0.001,ERROR.TYPE(0)),IFERROR(IF(OFFSET(A18,-10,0)>0,OFFSET(A18,-10,0)+0.001,ERROR.TYPE(0)),ERROR.TYPE(0))))))))))) -> 1.008 | B18: Provision for the supply and delivery to site of samples as may be requested by the client / engineer | C18: 1 | D18: L.S. | E18: =Elec_Est!Q82 -> To be advised
A19: =IFERROR(IF(OFFSET(A19,-1,0)>0,OFFSET(A19,-1,0)+0.001,ERROR.TYPE(0)),IFERROR(IF(OFFSET(A19,-2,0)>0,OFFSET(A19,-2,0)+0.001,ERROR.TYPE(0)),IFERROR(IF(OFFSET(A19,-3,0)>0,OFFSET(A19,-3,0)+0.001,ERROR.TYPE(0)),IFERROR(IF(OFFSET(A19,-4,0)>0,OFFSET(A19,-4,0)+0.001,ERROR.TYPE(0)),IFERROR(IF(OFFSET(A19,-5,0)>0,OFFSET(A19,-5,0)+0.001,ERROR.TYPE(0)),IFERROR(IF(OFFSET(A19,-6,0)>0,OFFSET(A19,-6,0)+0.001,ERROR.TYPE(0)),IFERROR(IF(OFFSET(A19,-7,0)>0,OFFSET(A19,-7,0)+0.001,ERROR.TYPE(0)),IFERROR(IF(OFFSET(A19,-8,0)>0,OFFSET(A19,-8,0)+0.001,ERROR.TYPE(0)),IFERROR(IF(OFFSET(A19,-9,0)>0,OFFSET(A19,-9,0)+0.001,ERROR.TYPE(0)),IFERROR(IF(OFFSET(A19,-10,0)>0,OFFSET(A19,-10,0)+0.001,ERROR.TYPE(0)),ERROR.TYPE(0))))))))))) -> 1.009 | B19: Allow for continuously keeping the site and building clean and in a workman type condition free from debris, surplus materials and any other type of loose matter arising from works, which will disturb the proper conditions of any internal and external areas, roads and/or adjoining structures. Site Cleaning is to take place during the whole duration of works. Client reserves the right to employ cleaning companies at the contractor's expense if the contractor fails to keep the site clean. | C19: 1 | D19: L.S. | E19: =Elec_Est!E88 -> 4320.24 | F19: =IFERROR($C19*E19,E19) -> 4320.24
A20: =IFERROR(IF(OFFSET(A20,-1,0)>0,OFFSET(A20,-1,0)+0.001,ERROR.TYPE(0)),IFERROR(IF(OFFSET(A20,-2,0)>0,OFFSET(A20,-2,0)+0.001,ERROR.TYPE(0)),IFERROR(IF(OFFSET(A20,-3,0)>0,OFFSET(A20,-3,0)+0.001,ERROR.TYPE(0)),IFERROR(IF(OFFSET(A20,-4,0)>0,OFFSET(A20,-4,0)+0.001,ERROR.TYPE(0)),IFERROR(IF(OFFSET(A20,-5,0)>0,OFFSET(A20,-5,0)+0.001,ERROR.TYPE(0)),IFERROR(IF(OFFSET(A20,-6,0)>0,OFFSET(A20,-6,0)+0.001,ERROR.TYPE(0)),IFERROR(IF(OFFSET(A20,-7,0)>0,OFFSET(A20,-7,0)+0.001,ERROR.TYPE(0)),IFERROR(IF(OFFSET(A20,-8,0)>0,OFFSET(A20,-8,0)+0.001,ERROR.TYPE(0)),IFERROR(IF(OFFSET(A20,-9,0)>0,OFFSET(A20,-9,0)+0.001,ERROR.TYPE(0)),IFERROR(IF(OFFSET(A20,-10,0)>0,OFFSET(A20,-10,0)+0.001,ERROR.TYPE(0)),ERROR.TYPE(0))))))))))) -> 1.01 | B20: Provision for hauling of equipment on site, including cranage, permits and all necessary fees. | C20: 1 | D20: L.S. | E20: =Elec_Est!Q94 -> Included
A21: =IFERROR(IF(OFFSET(A21,-1,0)>0,OFFSET(A21,-1,0)+0.001,ERROR.TYPE(0)),IFERROR(IF(OFFSET(A21,-2,0)>0,OFFSET(A21,-2,0)+0.001,ERROR.TYPE(0)),IFERROR(IF(OFFSET(A21,-3,0)>0,OFFSET(A21,-3,0)+0.001,ERROR.TYPE(0)),IFERROR(IF(OFFSET(A21,-4,0)>0,OFFSET(A21,-4,0)+0.001,ERROR.TYPE(0)),IFERROR(IF(OFFSET(A21,-5,0)>0,OFFSET(A21,-5,0)+0.001,ERROR.TYPE(0)),IFERROR(IF(OFFSET(A21,-6,0)>0,OFFSET(A21,-6,0)+0.001,ERROR.TYPE(0)),IFERROR(IF(OFFSET(A21,-7,0)>0,OFFSET(A21,-7,0)+0.001,ERROR.TYPE(0)),IFERROR(IF(OFFSET(A21,-8,0)>0,OFFSET(A21,-8,0)+0.001,ERROR.TYPE(0)),IFERROR(IF(OFFSET(A21,-9,0)>0,OFFSET(A21,-9,0)+0.001,ERROR.TYPE(0)),IFERROR(IF(OFFSET(A21,-10,0)>0,OFFSET(A21,-10,0)+0.001,ERROR.TYPE(0)),ERROR.TYPE(0))))))))))) -> 1.011 | B21: Provision for working at height, including scaffolding, cherry pickers etc. All equipment shall be fully certified. | C21: 1 | D21: L.S. | E21: =Elec_Est!Q100 -> Included
A22: =IFERROR(IF(OFFSET(A22,-1,0)>0,OFFSET(A22,-1,0)+0.001,ERROR.TYPE(0)),IFERROR(IF(OFFSET(A22,-2,0)>0,OFFSET(A22,-2,0)+0.001,ERROR.TYPE(0)),IFERROR(IF(OFFSET(A22,-3,0)>0,OFFSET(A22,-3,0)+0.001,ERROR.TYPE(0)),IFERROR(IF(OFFSET(A22,-4,0)>0,OFFSET(A22,-4,0)+0.001,ERROR.TYPE(0)),IFERROR(IF(OFFSET(A22,-5,0)>0,OFFSET(A22,-5,0)+0.001,ERROR.TYPE(0)),IFERROR(IF(OFFSET(A22,-6,0)>0,OFFSET(A22,-6,0)+0.001,ERROR.TYPE(0)),IFERROR(IF(OFFSET(A22,-7,0)>0,OFFSET(A22,-7,0)+0.001,ERROR.TYPE(0)),IFERROR(IF(OFFSET(A22,-8,0)>0,OFFSET(A22,-8,0)+0.001,ERROR.TYPE(0)),IFERROR(IF(OFFSET(A22,-9,0)>0,OFFSET(A22,-9,0)+0.001,ERROR.TYPE(0)),IFERROR(IF(OFFSET(A22,-10,0)>0,OFFSET(A22,-10,0)+0.001,ERROR.TYPE(0)),ERROR.TYPE(0))))))))))) -> 1.012 | B22: Provision for Builders Work in order to prepare all openings required to install conduits, pipework, ductwork, etc., and making good and reinstatement of all openings. | C22: 1 | D22: L.S. | E22: =Elec_Est!Q106 -> Refer to covering letter
A23: =IFERROR(IF(OFFSET(A23,-1,0)>0,OFFSET(A23,-1,0)+0.001,ERROR.TYPE(0)),IFERROR(IF(OFFSET(A23,-2,0)>0,OFFSET(A23,-2,0)+0.001,ERROR.TYPE(0)),IFERROR(IF(OFFSET(A23,-3,0)>0,OFFSET(A23,-3,0)+0.001,ERROR.TYPE(0)),IFERROR(IF(OFFSET(A23,-4,0)>0,OFFSET(A23,-4,0)+0.001,ERROR.TYPE(0)),IFERROR(IF(OFFSET(A23,-5,0)>0,OFFSET(A23,-5,0)+0.001,ERROR.TYPE(0)),IFERROR(IF(OFFSET(A23,-6,0)>0,OFFSET(A23,-6,0)+0.001,ERROR.TYPE(0)),IFERROR(IF(OFFSET(A23,-7,0)>0,OFFSET(A23,-7,0)+0.001,ERROR.TYPE(0)),IFERROR(IF(OFFSET(A23,-8,0)>0,OFFSET(A23,-8,0)+0.001,ERROR.TYPE(0)),IFERROR(IF(OFFSET(A23,-9,0)>0,OFFSET(A23,-9,0)+0.001,ERROR.TYPE(0)),IFERROR(IF(OFFSET(A23,-10,0)>0,OFFSET(A23,-10,0)+0.001,ERROR.TYPE(0)),ERROR.TYPE(0))))))))))) -> 1.013 | B23: Provision for Openings in Insulation Panelling in order to prepare all openings required to install conduits, pipework, ductwork, etc., and making good and reinstatement of all openings. | C23: 1 | D23: L.S. | E23: =Elec_Est!Q112 -> Refer to covering letter
B24: TOTAL FOR PAGE 02 | C24: Euro Exc VAT | F24: =SUM(F16:F23) -> 4320.24
B26: TOTAL FOR PRELIMINARIES | C26: Euro Exc VAT | F26: =F24+F12 -> 11152.23
A29: ITEM | B29: DESCRIPTION | C29: QTY | D29: UNIT | E29: RATE Euro (Exc of VAT) | F29: TOTAL Euro (Exc of VAT)
A30: 2 | B30: PLUMBING INSTALLATION
B31: PIPEWORK
B32: Supply and install the following Polypropylene PN 16 pipework, c/w weatherproof covering for all external runs, inclusive of all accessories, fittings sleeves in walls, brackets fixing, vents and all necessary to provide a complete system. Pipes to have the following Internal Ø in mm.
A33: =IFERROR(IF(OFFSET(A33,-1,0,1,1)>0,OFFSET(A33,-1,0,1,1)+0.001,ERROR.TYPE(0)),IFERROR(IF(OFFSET(A33,-2,0,1,1)>0,OFFSET(A33,-2,0,1,1)+0.001,ERROR.TYPE(0)),IFERROR(IF(OFFSET(A33,-3,0,1,1)>0,OFFSET(A33,-3,0,1,1)+0.001,ERROR.TYPE(0)),IFERROR(IF(OFFSET(A33,-4,0,1,1)>0,OFFSET(A33,-4,0,1,1)+0.001,ERROR.TYPE(0)),IFERROR(IF(OFFSET(A33,-5,0,1,1)>0,OFFSET(A33,-5,0,1,1)+0.001,ERROR.TYPE(0)),IFERROR(IF(OFFSET(A33,-6,0,1,1)>0,OFFSET(A33,-6,0,1,1)+0.001,ERROR.TYPE(0)),IFERROR(IF(OFFSET(A33,-7,0,1,1)>0,OFFSET(A33,-7,0,1,1)+0.001,ERROR.TYPE(0)),IFERROR(IF(OFFSET(A33,-8,0,1,1)>0,OFFSET(A33,-8,0,1,1)+0.001,ERROR.TYPE(0)),IFERROR(IF(OFFSET(A33,-9,0,1,1)>0,OFFSET(A33,-9,0,1,1)+0.001,ERROR.TYPE(0)),IFERROR(IF(OFFSET(A33,-10,0,1,1)>0,OFFSET(A33,-10,0,1,1)+0.001,ERROR.TYPE(0)),ERROR.TYPE(0))))))))))) -> 2.001 | B33: 15mm dia. | C33: 85 | D33: m | F33: =IFERROR($C33*E33,E33) -> 0
A34: =IFERROR(IF(OFFSET(A34,-1,0,1,1)>0,OFFSET(A34,-1,0,1,1)+0.001,ERROR.TYPE(0)),IFERROR(IF(OFFSET(A34,-2,0,1,1)>0,OFFSET(A34,-2,0,1,1)+0.001,ERROR.TYPE(0)),IFERROR(IF(OFFSET(A34,-3,0,1,1)>0,OFFSET(A34,-3,0,1,1)+0.001,ERROR.TYPE(0)),IFERROR(IF(OFFSET(A34,-4,0,1,1)>0,OFFSET(A34,-4,0,1,1)+0.001,ERROR.TYPE(0)),IFERROR(IF(OFFSET(A34,-5,0,1,1)>0,OFFSET(A34,-5,0,1,1)+0.001,ERROR.TYPE(0)),IFERROR(IF(OFFSET(A34,-6,0,1,1)>0,OFFSET(A34,-6,0,1,1)+0.001,ERROR.TYPE(0)),IFERROR(IF(OFFSET(A34,-7,0,1,1)>0,OFFSET(A34,-7,0,1,1)+0.001,ERROR.TYPE(0)),IFERROR(IF(OFFSET(A34,-8,0,1,1)>0,OFFSET(A34,-8,0,1,1)+0.001,ERROR.TYPE(0)),IFERROR(IF(OFFSET(A34,-9,0,1,1)>0,OFFSET(A34,-9,0,1,1)+0.001,ERROR.TYPE(0)),IFERROR(IF(OFFSET(A34,-10,0,1,1)>0,OFFSET(A34,-10,0,1,1)+0.001,ERROR.TYPE(0)),ERROR.TYPE(0))))))))))) -> 2.002 | B34: 22mm dia. | C34: 360 | D34: m | F34: =IFERROR($C34*E34,E34) -> 0
A35: =IFERROR(IF(OFFSET(A35,-1,0,1,1)>0,OFFSET(A35,-1,0,1,1)+0.001,ERROR.TYPE(0)),IFERROR(IF(OFFSET(A35,-2,0,1,1)>0,OFFSET(A35,-2,0,1,1)+0.001,ERROR.TYPE(0)),IFERROR(IF(OFFSET(A35,-3,0,1,1)>0,OFFSET(A35,-3,0,1,1)+0.001,ERROR.TYPE(0)),IFERROR(IF(OFFSET(A35,-4,0,1,1)>0,OFFSET(A35,-4,0,1,1)+0.001,ERROR.TYPE(0)),IFERROR(IF(OFFSET(A35,-5,0,1,1)>0,OFFSET(A35,-5,0,1,1)+0.001,ERROR.TYPE(0)),IFERROR(IF(OFFSET(A35,-6,0,1,1)>0,OFFSET(A35,-6,0,1,1)+0.001,ERROR.TYPE(0)),IFERROR(IF(OFFSET(A35,-7,0,1,1)>0,OFFSET(A35,-7,0,1,1)+0.001,ERROR.TYPE(0)),IFERROR(IF(OFFSET(A35,-8,0,1,1)>0,OFFSET(A35,-8,0,1,1)+0.001,ERROR.TYPE(0)),IFERROR(IF(OFFSET(A35,-9,0,1,1)>0,OFFSET(A35,-9,0,1,1)+0.001,ERROR.TYPE(0)),IFERROR(IF(OFFSET(A35,-10,0,1,1)>0,OFFSET(A35,-10,0,1,1)+0.001,ERROR.TYPE(0)),ERROR.TYPE(0))))))))))) -> 2.003 | B35: 28mm dia. | C35: 135 | D35: m | F35: =IFERROR($C35*E35,E35) -> 0
A36: =IFERROR(IF(OFFSET(A36,-1,0,1,1)>0,OFFSET(A36,-1,0,1,1)+0.001,ERROR.TYPE(0)),IFERROR(IF(OFFSET(A36,-2,0,1,1)>0,OFFSET(A36,-2,0,1,1)+0.001,ERROR.TYPE(0)),IFERROR(IF(OFFSET(A36,-3,0,1,1)>0,OFFSET(A36,-3,0,1,1)+0.001,ERROR.TYPE(0)),IFERROR(IF(OFFSET(A36,-4,0,1,1)>0,OFFSET(A36,-4,0,1,1)+0.001,ERROR.TYPE(0)),IFERROR(IF(OFFSET(A36,-5,0,1,1)>0,OFFSET(A36,-5,0,1,1)+0.001,ERROR.TYPE(0)),IFERROR(IF(OFFSET(A36,-6,0,1,1)>0,OFFSET(A36,-6,0,1,1)+0.001,ERROR.TYPE(0)),IFERROR(IF(OFFSET(A36,-7,0,1,1)>0,OFFSET(A36,-7,0,1,1)+0.001,ERROR.TYPE(0)),IFERROR(IF(OFFSET(A36,-8,0,1,1)>0,OFFSET(A36,-8,0,1,1)+0.001,ERROR.TYPE(0)),IFERROR(IF(OFFSET(A36,-9,0,1,1)>0,OFFSET(A36,-9,0,1,1)+0.001,ERROR.TYPE(0)),IFERROR(IF(OFFSET(A36,-10,0,1,1)>0,OFFSET(A36,-10,0,1,1)+0.001,ERROR.TYPE(0)),ERROR.TYPE(0))))))))))) -> 2.004 | B36: 32mm dia. | C36: 640 | D36: m | F36: =IFERROR($C36*E36,E36) -> 0
A37: =IFERROR(IF(OFFSET(A37,-1,0,1,1)>0,OFFSET(A37,-1,0,1,1)+0.001,ERROR.TYPE(0)),IFERROR(IF(OFFSET(A37,-2,0,1,1)>0,OFFSET(A37,-2,0,1,1)+0.001,ERROR.TYPE(0)),IFERROR(IF(OFFSET(A37,-3,0,1,1)>0,OFFSET(A37,-3,0,1,1)+0.001,ERROR.TYPE(0)),IFERROR(IF(OFFSET(A37,-4,0,1,1)>0,OFFSET(A37,-4,0,1,1)+0.001,ERROR.TYPE(0)),IFERROR(IF(OFFSET(A37,-5,0,1,1)>0,OFFSET(A37,-5,0,1,1)+0.001,ERROR.TYPE(0)),IFERROR(IF(OFFSET(A37,-6,0,1,1)>0,OFFSET(A37,-6,0,1,1)+0.001,ERROR.TYPE(0)),IFERROR(IF(OFFSET(A37,-7,0,1,1)>0,OFFSET(A37,-7,0,1,1)+0.001,ERROR.TYPE(0)),IFERROR(IF(OFFSET(A37,-8,0,1,1)>0,OFFSET(A37,-8,0,1,1)+0.001,ERROR.TYPE(0)),IFERROR(IF(OFFSET(A37,-9,0,1,1)>0,OFFSET(A37,-9,0,1,1)+0.001,ERROR.TYPE(0)),IFERROR(IF(OFFSET(A37,-10,0,1,1)>0,OFFSET(A37,-10,0,1,1)+0.001,ERROR.TYPE(0)),ERROR.TYPE(0))))))))))) -> 2.005 | B37: 40mm dia. | C37: 50 | D37: m | F37: =IFERROR($C37*E37,E37) -> 0
A38: =IFERROR(IF(OFFSET(A38,-1,0,1,1)>0,OFFSET(A38,-1,0,1,1)+0.001,ERROR.TYPE(0)),IFERROR(IF(OFFSET(A38,-2,0,1,1)>0,OFFSET(A38,-2,0,1,1)+0.001,ERROR.TYPE(0)),IFERROR(IF(OFFSET(A38,-3,0,1,1)>0,OFFSET(A38,-3,0,1,1)+0.001,ERROR.TYPE(0)),IFERROR(IF(OFFSET(A38,-4,0,1,1)>0,OFFSET(A38,-4,0,1,1)+0.001,ERROR.TYPE(0)),IFERROR(IF(OFFSET(A38,-5,0,1,1)>0,OFFSET(A38,-5,0,1,1)+0.001,ERROR.TYPE(0)),IFERROR(IF(OFFSET(A38,-6,0,1,1)>0,OFFSET(A38,-6,0,1,1)+0.001,ERROR.TYPE(0)),IFERROR(IF(OFFSET(A38,-7,0,1,1)>0,OFFSET(A38,-7,0,1,1)+0.001,ERROR.TYPE(0)),IFERROR(IF(OFFSET(A38,-8,0,1,1)>0,OFFSET(A38,-8,0,1,1)+0.001,ERROR.TYPE(0)),IFERROR(IF(OFFSET(A38,-9,0,1,1)>0,OFFSET(A38,-9,0,1,1)+0.001,ERROR.TYPE(0)),IFERROR(IF(OFFSET(A38,-10,0,1,1)>0,OFFSET(A38,-10,0,1,1)+0.001,ERROR.TYPE(0)),ERROR.TYPE(0))))))))))) -> 2.006 | B38: 50mm dia. | C38: 75 | D38: m | F38: =IFERROR($C38*E38,E38) -> 0
B39: VALVES
B40: Supply, install and connect the following valves on main runs as per schematic. Valves on Hot Water runs shall be properly insulated with closed-cell foam insulation rated min B-S2,d0 and weatherproofed for external runs
A41: =IFERROR(IF(OFFSET(A41,-1,0,1,1)>0,OFFSET(A41,-1,0,1,1)+0.001,ERROR.TYPE(0)),IFERROR(IF(OFFSET(A41,-2,0,1,1)>0,OFFSET(A41,-2,0,1,1)+0.001,ERROR.TYPE(0)),IFERROR(IF(OFFSET(A41,-3,0,1,1)>0,OFFSET(A41,-3,0,1,1)+0.001,ERROR.TYPE(0)),IFERROR(IF(OFFSET(A41,-4,0,1,1)>0,OFFSET(A41,-4,0,1,1)+0.001,ERROR.TYPE(0)),IFERROR(IF(OFFSET(A41,-5,0,1,1)>0,OFFSET(A41,-5,0,1,1)+0.001,ERROR.TYPE(0)),IFERROR(IF(OFFSET(A41,-6,0,1,1)>0,OFFSET(A41,-6,0,1,1)+0.001,ERROR.TYPE(0)),IFERROR(IF(OFFSET(A41,-7,0,1,1)>0,OFFSET(A41,-7,0,1,1)+0.001,ERROR.TYPE(0)),IFERROR(IF(OFFSET(A41,-8,0,1,1)>0,OFFSET(A41,-8,0,1,1)+0.001,ERROR.TYPE(0)),IFERROR(IF(OFFSET(A41,-9,0,1,1)>0,OFFSET(A41,-9,0,1,1)+0.001,ERROR.TYPE(0)),IFERROR(IF(OFFSET(A41,-10,0,1,1)>0,OFFSET(A41,-10,0,1,1)+0.001,ERROR.TYPE(0)),ERROR.TYPE(0))))))))))) -> 2.007 | B41: 15mm dia. - Isolating valve | C41: 2 | D41: No. | F41: =IFERROR($C41*E41,E41) -> 0
A42: =IFERROR(IF(OFFSET(A42,-1,0,1,1)>0,OFFSET(A42,-1,0,1,1)+0.001,ERROR.TYPE(0)),IFERROR(IF(OFFSET(A42,-2,0,1,1)>0,OFFSET(A42,-2,0,1,1)+0.001,ERROR.TYPE(0)),IFERROR(IF(OFFSET(A42,-3,0,1,1)>0,OFFSET(A42,-3,0,1,1)+0.001,ERROR.TYPE(0)),IFERROR(IF(OFFSET(A42,-4,0,1,1)>0,OFFSET(A42,-4,0,1,1)+0.001,ERROR.TYPE(0)),IFERROR(IF(OFFSET(A42,-5,0,1,1)>0,OFFSET(A42,-5,0,1,1)+0.001,ERROR.TYPE(0)),IFERROR(IF(OFFSET(A42,-6,0,1,1)>0,OFFSET(A42,-6,0,1,1)+0.001,ERROR.TYPE(0)),IFERROR(IF(OFFSET(A42,-7,0,1,1)>0,OFFSET(A42,-7,0,1,1)+0.001,ERROR.TYPE(0)),IFERROR(IF(OFFSET(A42,-8,0,1,1)>0,OFFSET(A42,-8,0,1,1)+0.001,ERROR.TYPE(0)),IFERROR(IF(OFFSET(A42,-9,0,1,1)>0,OFFSET(A42,-9,0,1,1)+0.001,ERROR.TYPE(0)),IFERROR(IF(OFFSET(A42,-10,0,1,1)>0,OFFSET(A42,-10,0,1,1)+0.001,ERROR.TYPE(0)),ERROR.TYPE(0))))))))))) -> 2.008 | B42: 22mm dia. - Isolating valve | C42: 24 | D42: No. | F42: =IFERROR($C42*E42,E42) -> 0
A43: =IFERROR(IF(OFFSET(A43,-1,0,1,1)>0,OFFSET(A43,-1,0,1,1)+0.001,ERROR.TYPE(0)),IFERROR(IF(OFFSET(A43,-2,0,1,1)>0,OFFSET(A43,-2,0,1,1)+0.001,ERROR.TYPE(0)),IFERROR(IF(OFFSET(A43,-3,0,1,1)>0,OFFSET(A43,-3,0,1,1)+0.001,ERROR.TYPE(0)),IFERROR(IF(OFFSET(A43,-4,0,1,1)>0,OFFSET(A43,-4,0,1,1)+0.001,ERROR.TYPE(0)),IFERROR(IF(OFFSET(A43,-5,0,1,1)>0,OFFSET(A43,-5,0,1,1)+0.001,ERROR.TYPE(0)),IFERROR(IF(OFFSET(A43,-6,0,1,1)>0,OFFSET(A43,-6,0,1,1)+0.001,ERROR.TYPE(0)),IFERROR(IF(OFFSET(A43,-7,0,1,1)>0,OFFSET(A43,-7,0,1,1)+0.001,ERROR.TYPE(0)),IFERROR(IF(OFFSET(A43,-8,0,1,1)>0,OFFSET(A43,-8,0,1,1)+0.001,ERROR.TYPE(0)),IFERROR(IF(OFFSET(A43,-9,0,1,1)>0,OFFSET(A43,-9,0,1,1)+0.001,ERROR.TYPE(0)),IFERROR(IF(OFFSET(A43,-10,0,1,1)>0,OFFSET(A43,-10,0,1,1)+0.001,ERROR.TYPE(0)),ERROR.TYPE(0))))))))))) -> 2.009 | B43: 28mm dia. - Isolating valve | C43: 2 | D43: No. | F43: =IFERROR($C43*E43,E43) -> 0
A44: =IFERROR(IF(OFFSET(A44,-1,0,1,1)>0,OFFSET(A44,-1,0,1,1)+0.001,ERROR.TYPE(0)),IFERROR(IF(OFFSET(A44,-2,0,1,1)>0,OFFSET(A44,-2,0,1,1)+0.001,ERROR.TYPE(0)),IFERROR(IF(OFFSET(A44,-3,0,1,1)>0,OFFSET(A44,-3,0,1,1)+0.001,ERROR.TYPE(0)),IFERROR(IF(OFFSET(A44,-4,0,1,1)>0,OFFSET(A44,-4,0,1,1)+0.001,ERROR.TYPE(0)),IFERROR(IF(OFFSET(A44,-5,0,1,1)>0,OFFSET(A44,-5,0,1,1)+0.001,ERROR.TYPE(0)),IFERROR(IF(OFFSET(A44,-6,0,1,1)>0,OFFSET(A44,-6,0,1,1)+0.001,ERROR.TYPE(0)),IFERROR(IF(OFFSET(A44,-7,0,1,1)>0,OFFSET(A44,-7,0,1,1)+0.001,ERROR.TYPE(0)),IFERROR(IF(OFFSET(A44,-8,0,1,1)>0,OFFSET(A44,-8,0,1,1)+0.001,ERROR.TYPE(0)),IFERROR(IF(OFFSET(A44,-9,0,1,1)>0,OFFSET(A44,-9,0,1,1)+0.001,ERROR.TYPE(0)),IFERROR(IF(OFFSET(A44,-10,0,1,1)>0,OFFSET(A44,-10,0,1,1)+0.001,ERROR.TYPE(0)),ERROR.TYPE(0))))))))))) -> 2.01 | B44: 32mm dia. - Isolating valve | C44: 6 | D44: No. | F44: =IFERROR($C44*E44,E44) -> 0
A45: =IFERROR(IF(OFFSET(A45,-1,0,1,1)>0,OFFSET(A45,-1,0,1,1)+0.001,ERROR.TYPE(0)),IFERROR(IF(OFFSET(A45,-2,0,1,1)>0,OFFSET(A45,-2,0,1,1)+0.001,ERROR.TYPE(0)),IFERROR(IF(OFFSET(A45,-3,0,1,1)>0,OFFSET(A45,-3,0,1,1)+0.001,ERROR.TYPE(0)),IFERROR(IF(OFFSET(A45,-4,0,1,1)>0,OFFSET(A45,-4,0,1,1)+0.001,ERROR.TYPE(0)),IFERROR(IF(OFFSET(A45,-5,0,1,1)>0,OFFSET(A45,-5,0,1,1)+0.001,ERROR.TYPE(0)),IFERROR(IF(OFFSET(A45,-6,0,1,1)>0,OFFSET(A45,-6,0,1,1)+0.001,ERROR.TYPE(0)),IFERROR(IF(OFFSET(A45,-7,0,1,1)>0,OFFSET(A45,-7,0,1,1)+0.001,ERROR.TYPE(0)),IFERROR(IF(OFFSET(A45,-8,0,1,1)>0,OFFSET(A45,-8,0,1,1)+0.001,ERROR.TYPE(0)),IFERROR(IF(OFFSET(A45,-9,0,1,1)>0,OFFSET(A45,-9,0,1,1)+0.001,ERROR.TYPE(0)),IFERROR(IF(OFFSET(A45,-10,0,1,1)>0,OFFSET(A45,-10,0,1,1)+0.001,ERROR.TYPE(0)),ERROR.TYPE(0))))))))))) -> 2.011 | B45: 40mm dia. - Isolating valve | C45: 3 | D45: No. | F45: =IFERROR($C45*E45,E45) -> 0
A46: =IFERROR(IF(OFFSET(A46,-1,0,1,1)>0,OFFSET(A46,-1,0,1,1)+0.001,ERROR.TYPE(0)),IFERROR(IF(OFFSET(A46,-2,0,1,1)>0,OFFSET(A46,-2,0,1,1)+0.001,ERROR.TYPE(0)),IFERROR(IF(OFFSET(A46,-3,0,1,1)>0,OFFSET(A46,-3,0,1,1)+0.001,ERROR.TYPE(0)),IFERROR(IF(OFFSET(A46,-4,0,1,1)>0,OFFSET(A46,-4,0,1,1)+0.001,ERROR.TYPE(0)),IFERROR(IF(OFFSET(A46,-5,0,1,1)>0,OFFSET(A46,-5,0,1,1)+0.001,ERROR.TYPE(0)),IFERROR(IF(OFFSET(A46,-6,0,1,1)>0,OFFSET(A46,-6,0,1,1)+0.001,ERROR.TYPE(0)),IFERROR(IF(OFFSET(A46,-7,0,1,1)>0,OFFSET(A46,-7,0,1,1)+0.001,ERROR.TYPE(0)),IFERROR(IF(OFFSET(A46,-8,0,1,1)>0,OFFSET(A46,-8,0,1,1)+0.001,ERROR.TYPE(0)),IFERROR(IF(OFFSET(A46,-9,0,1,1)>0,OFFSET(A46,-9,0,1,1)+0.001,ERROR.TYPE(0)),IFERROR(IF(OFFSET(A46,-10,0,1,1)>0,OFFSET(A46,-10,0,1,1)+0.001,ERROR.TYPE(0)),ERROR.TYPE(0))))))))))) -> 2.012 | B46: 50mm dia. - Isolating valve | C46: 1 | D46: No. | F46: =IFERROR($C46*E46,E46) -> 0
A47: =IFERROR(IF(OFFSET(A47,-1,0,1,1)>0,OFFSET(A47,-1,0,1,1)+0.001,ERROR.TYPE(0)),IFERROR(IF(OFFSET(A47,-2,0,1,1)>0,OFFSET(A47,-2,0,1,1)+0.001,ERROR.TYPE(0)),IFERROR(IF(OFFSET(A47,-3,0,1,1)>0,OFFSET(A47,-3,0,1,1)+0.001,ERROR.TYPE(0)),IFERROR(IF(OFFSET(A47,-4,0,1,1)>0,OFFSET(A47,-4,0,1,1)+0.001,ERROR.TYPE(0)),IFERROR(IF(OFFSET(A47,-5,0,1,1)>0,OFFSET(A47,-5,0,1,1)+0.001,ERROR.TYPE(0)),IFERROR(IF(OFFSET(A47,-6,0,1,1)>0,OFFSET(A47,-6,0,1,1)+0.001,ERROR.TYPE(0)),IFERROR(IF(OFFSET(A47,-7,0,1,1)>0,OFFSET(A47,-7,0,1,1)+0.001,ERROR.TYPE(0)),IFERROR(IF(OFFSET(A47,-8,0,1,1)>0,OFFSET(A47,-8,0,1,1)+0.001,ERROR.TYPE(0)),IFERROR(IF(OFFSET(A47,-9,0,1,1)>0,OFFSET(A47,-9,0,1,1)+0.001,ERROR.TYPE(0)),IFERROR(IF(OFFSET(A47,-10,0,1,1)>0,OFFSET(A47,-10,0,1,1)+0.001,ERROR.TYPE(0)),ERROR.TYPE(0))))))))))) -> 2.013 | B47: 50mm dia. - Non-return valve | C47: 1 | D47: No. | F47: =IFERROR($C47*E47,E47) -> 0
A48: =IFERROR(IF(OFFSET(A48,-1,0,1,1)>0,OFFSET(A48,-1,0,1,1)+0.001,ERROR.TYPE(0)),IFERROR(IF(OFFSET(A48,-2,0,1,1)>0,OFFSET(A48,-2,0,1,1)+0.001,ERROR.TYPE(0)),IFERROR(IF(OFFSET(A48,-3,0,1,1)>0,OFFSET(A48,-3,0,1,1)+0.001,ERROR.TYPE(0)),IFERROR(IF(OFFSET(A48,-4,0,1,1)>0,OFFSET(A48,-4,0,1,1)+0.001,ERROR.TYPE(0)),IFERROR(IF(OFFSET(A48,-5,0,1,1)>0,OFFSET(A48,-5,0,1,1)+0.001,ERROR.TYPE(0)),IFERROR(IF(OFFSET(A48,-6,0,1,1)>0,OFFSET(A48,-6,0,1,1)+0.001,ERROR.TYPE(0)),IFERROR(IF(OFFSET(A48,-7,0,1,1)>0,OFFSET(A48,-7,0,1,1)+0.001,ERROR.TYPE(0)),IFERROR(IF(OFFSET(A48,-8,0,1,1)>0,OFFSET(A48,-8,0,1,1)+0.001,ERROR.TYPE(0)),IFERROR(IF(OFFSET(A48,-9,0,1,1)>0,OFFSET(A48,-9,0,1,1)+0.001,ERROR.TYPE(0)),IFERROR(IF(OFFSET(A48,-10,0,1,1)>0,OFFSET(A48,-10,0,1,1)+0.001,ERROR.TYPE(0)),ERROR.TYPE(0))))))))))) -> 2.014 | B48: 15mm dia. - Pressure reducing valve | C48: 2 | D48: No. | F48: =IFERROR($C48*E48,E48) -> 0
A49: =IFERROR(IF(OFFSET(A49,-1,0,1,1)>0,OFFSET(A49,-1,0,1,1)+0.001,ERROR.TYPE(0)),IFERROR(IF(OFFSET(A49,-2,0,1,1)>0,OFFSET(A49,-2,0,1,1)+0.001,ERROR.TYPE(0)),IFERROR(IF(OFFSET(A49,-3,0,1,1)>0,OFFSET(A49,-3,0,1,1)+0.001,ERROR.TYPE(0)),IFERROR(IF(OFFSET(A49,-4,0,1,1)>0,OFFSET(A49,-4,0,1,1)+0.001,ERROR.TYPE(0)),IFERROR(IF(OFFSET(A49,-5,0,1,1)>0,OFFSET(A49,-5,0,1,1)+0.001,ERROR.TYPE(0)),IFERROR(IF(OFFSET(A49,-6,0,1,1)>0,OFFSET(A49,-6,0,1,1)+0.001,ERROR.TYPE(0)),IFERROR(IF(OFFSET(A49,-7,0,1,1)>0,OFFSET(A49,-7,0,1,1)+0.001,ERROR.TYPE(0)),IFERROR(IF(OFFSET(A49,-8,0,1,1)>0,OFFSET(A49,-8,0,1,1)+0.001,ERROR.TYPE(0)),IFERROR(IF(OFFSET(A49,-9,0,1,1)>0,OFFSET(A49,-9,0,1,1)+0.001,ERROR.TYPE(0)),IFERROR(IF(OFFSET(A49,-10,0,1,1)>0,OFFSET(A49,-10,0,1,1)+0.001,ERROR.TYPE(0)),ERROR.TYPE(0))))))))))) -> 2.015 | B49: 22mm dia. - Pressure reducing valve | C49: 6 | D49: No. | F49: =IFERROR($C49*E49,E49) -> 0
A50: =IFERROR(IF(OFFSET(A50,-1,0,1,1)>0,OFFSET(A50,-1,0,1,1)+0.001,ERROR.TYPE(0)),IFERROR(IF(OFFSET(A50,-2,0,1,1)>0,OFFSET(A50,-2,0,1,1)+0.001,ERROR.TYPE(0)),IFERROR(IF(OFFSET(A50,-3,0,1,1)>0,OFFSET(A50,-3,0,1,1)+0.001,ERROR.TYPE(0)),IFERROR(IF(OFFSET(A50,-4,0,1,1)>0,OFFSET(A50,-4,0,1,1)+0.001,ERROR.TYPE(0)),IFERROR(IF(OFFSET(A50,-5,0,1,1)>0,OFFSET(A50,-5,0,1,1)+0.001,ERROR.TYPE(0)),IFERROR(IF(OFFSET(A50,-6,0,1,1)>0,OFFSET(A50,-6,0,1,1)+0.001,ERROR.TYPE(0)),IFERROR(IF(OFFSET(A50,-7,0,1,1)>0,OFFSET(A50,-7,0,1,1)+0.001,ERROR.TYPE(0)),IFERROR(IF(OFFSET(A50,-8,0,1,1)>0,OFFSET(A50,-8,0,1,1)+0.001,ERROR.TYPE(0)),IFERROR(IF(OFFSET(A50,-9,0,1,1)>0,OFFSET(A50,-9,0,1,1)+0.001,ERROR.TYPE(0)),IFERROR(IF(OFFSET(A50,-10,0,1,1)>0,OFFSET(A50,-10,0,1,1)+0.001,ERROR.TYPE(0)),ERROR.TYPE(0))))))))))) -> 2.016 | B50: 40mm dia. - Pressure reducing valve | C50: 1 | D50: No. | F50: =IFERROR($C50*E50,E50) -> 0
A51: =IFERROR(IF(OFFSET(A51,-1,0,1,1)>0,OFFSET(A51,-1,0,1,1)+0.001,ERROR.TYPE(0)),IFERROR(IF(OFFSET(A51,-2,0,1,1)>0,OFFSET(A51,-2,0,1,1)+0.001,ERROR.TYPE(0)),IFERROR(IF(OFFSET(A51,-3,0,1,1)>0,OFFSET(A51,-3,0,1,1)+0.001,ERROR.TYPE(0)),IFERROR(IF(OFFSET(A51,-4,0,1,1)>0,OFFSET(A51,-4,0,1,1)+0.001,ERROR.TYPE(0)),IFERROR(IF(OFFSET(A51,-5,0,1,1)>0,OFFSET(A51,-5,0,1,1)+0.001,ERROR.TYPE(0)),IFERROR(IF(OFFSET(A51,-6,0,1,1)>0,OFFSET(A51,-6,0,1,1)+0.001,ERROR.TYPE(0)),IFERROR(IF(OFFSET(A51,-7,0,1,1)>0,OFFSET(A51,-7,0,1,1)+0.001,ERROR.TYPE(0)),IFERROR(IF(OFFSET(A51,-8,0,1,1)>0,OFFSET(A51,-8,0,1,1)+0.001,ERROR.TYPE(0)),IFERROR(IF(OFFSET(A51,-9,0,1,1)>0,OFFSET(A51,-9,0,1,1)+0.001,ERROR.TYPE(0)),IFERROR(IF(OFFSET(A51,-10,0,1,1)>0,OFFSET(A51,-10,0,1,1)+0.001,ERROR.TYPE(0)),ERROR.TYPE(0))))))))))) -> 2.017 | B51: 50mm dia. - Pressure reducing valve | C51: 1 | D51: No. | F51: =IFERROR($C51*E51,E51) -> 0
A52: =IFERROR(IF(OFFSET(A52,-1,0,1,1)>0,OFFSET(A52,-1,0,1,1)+0.001,ERROR.TYPE(0)),IFERROR(IF(OFFSET(A52,-2,0,1,1)>0,OFFSET(A52,-2,0,1,1)+0.001,ERROR.TYPE(0)),IFERROR(IF(OFFSET(A52,-3,0,1,1)>0,OFFSET(A52,-3,0,1,1)+0.001,ERROR.TYPE(0)),IFERROR(IF(OFFSET(A52,-4,0,1,1)>0,OFFSET(A52,-4,0,1,1)+0.001,ERROR.TYPE(0)),IFERROR(IF(OFFSET(A52,-5,0,1,1)>0,OFFSET(A52,-5,0,1,1)+0.001,ERROR.TYPE(0)),IFERROR(IF(OFFSET(A52,-6,0,1,1)>0,OFFSET(A52,-6,0,1,1)+0.001,ERROR.TYPE(0)),IFERROR(IF(OFFSET(A52,-7,0,1,1)>0,OFFSET(A52,-7,0,1,1)+0.001,ERROR.TYPE(0)),IFERROR(IF(OFFSET(A52,-8,0,1,1)>0,OFFSET(A52,-8,0,1,1)+0.001,ERROR.TYPE(0)),IFERROR(IF(OFFSET(A52,-9,0,1,1)>0,OFFSET(A52,-9,0,1,1)+0.001,ERROR.TYPE(0)),IFERROR(IF(OFFSET(A52,-10,0,1,1)>0,OFFSET(A52,-10,0,1,1)+0.001,ERROR.TYPE(0)),ERROR.TYPE(0))))))))))) -> 2.018 | B52: 22mm dia. - Solenoid Valve | C52: 1 | D52: No. | F52: =IFERROR($C52*E52,E52) -> 0
... A54: =IFERROR(IF(OFFSET(A54,-1,0,1,1)>0,OFFSET(A54,-1,0,1,1)+0.001,ERROR.TYPE(0)),IFERROR(IF(OFFSET(A54,-2,0,1,1)>0,OFFSET(A54,-2,0,1,1)+0.001,ERROR.TYPE(0)),IFERROR(IF(OFFSET(A54,-3,0,1,1)>0,OFFSET(A54,-3,0,1,1)+0.001,ERROR.TYPE(0)),IFERROR(IF(OFFSET(A54,-4,0,1,1)>0,OFFSET(A54,-4,0,1,1)+0.001,ERROR.TYPE(0)),IFERROR(IF(OFFSET(A54,-5,0,1,1)>0,OFFSET(A54,-5,0,1,1)+0.001,ERROR.TYPE(0)),IFERROR(IF(OFFSET(A54,-6,0,1,1)>0,OFFSET(A54,-6,0,1,1)+0.001,ERROR.TYPE(0)),IFERROR(IF(OFFSET(A54,-7,0,1,1)>0,OFFSET(A54,-7,0,1,1)+0.001,ERROR.TYPE(0)),IFERROR(IF(OFFSET(A54,-8,0,1,1)>0,OFFSET(A54,-8,0,1,1)+0.001,ERROR.TYPE(0)),IFERROR(IF(OFFSET(A54,-9,0,1,1)>0,OFFSET(A54,-9,0,1,1)+0.001,ERROR.TYPE(0)),IFERROR(IF(OFFSET(A54,-10,0,1,1)>0,OFFSET(A54,-10,0,1,1)+0.001,ERROR.TYPE(0)),ERROR.TYPE(0))))))))))) -> 2.02 | B54: 50mm dia. - Solenoid Valve | C54: 1 | D54: No. | F54: =IFERROR($C54*E54,E54) -> 0
B55: Basement Level -1
B56: Plumbing hot and cold water using Polypropylene PN 16 pipework chased in wall/ surface mounted from header in shaft / main distribution pipework to final sanitary fittings including the supply of all fittings, brackets etc. for a complete installation as per drawing.
A57: =IFERROR(IF(OFFSET(A57,-1,0)>0,OFFSET(A57,-1,0)+0.001,ERROR.TYPE(0)),IFERROR(IF(OFFSET(A57,-2,0)>0,OFFSET(A57,-2,0)+0.001,ERROR.TYPE(0)),IFERROR(IF(OFFSET(A57,-3,0)>0,OFFSET(A57,-3,0)+0.001,ERROR.TYPE(0)),IFERROR(IF(OFFSET(A57,-4,0)>0,OFFSET(A57,-4,0)+0.001,ERROR.TYPE(0)),IFERROR(IF(OFFSET(A57,-5,0)>0,OFFSET(A57,-5,0)+0.001,ERROR.TYPE(0)),IFERROR(IF(OFFSET(A57,-6,0)>0,OFFSET(A57,-6,0)+0.001,ERROR.TYPE(0)),IFERROR(IF(OFFSET(A57,-7,0)>0,OFFSET(A57,-7,0)+0.001,ERROR.TYPE(0)),IFERROR(IF(OFFSET(A57,-8,0)>0,OFFSET(A57,-8,0)+0.001,ERROR.TYPE(0)),IFERROR(IF(OFFSET(A57,-9,0)>0,OFFSET(A57,-9,0)+0.001,ERROR.TYPE(0)),IFERROR(IF(OFFSET(A57,-10,0)>0,OFFSET(A57,-10,0)+0.001,ERROR.TYPE(0)),ERROR.TYPE(0))))))))))) -> 2.021 | B57: Bib Tap | C57: 3 | D57: No. | F57: =IFERROR($C57*E57,E57) -> 0
B58: Supply, Install and connect the following chrome fittings
A59: =IFERROR(IF(OFFSET(A59,-1,0)>0,OFFSET(A59,-1,0)+0.001,ERROR.TYPE(0)),IFERROR(IF(OFFSET(A59,-2,0)>0,OFFSET(A59,-2,0)+0.001,ERROR.TYPE(0)),IFERROR(IF(OFFSET(A59,-3,0)>0,OFFSET(A59,-3,0)+0.001,ERROR.TYPE(0)),IFERROR(IF(OFFSET(A59,-4,0)>0,OFFSET(A59,-4,0)+0.001,ERROR.TYPE(0)),IFERROR(IF(OFFSET(A59,-5,0)>0,OFFSET(A59,-5,0)+0.001,ERROR.TYPE(0)),IFERROR(IF(OFFSET(A59,-6,0)>0,OFFSET(A59,-6,0)+0.001,ERROR.TYPE(0)),IFERROR(IF(OFFSET(A59,-7,0)>0,OFFSET(A59,-7,0)+0.001,ERROR.TYPE(0)),IFERROR(IF(OFFSET(A59,-8,0)>0,OFFSET(A59,-8,0)+0.001,ERROR.TYPE(0)),IFERROR(IF(OFFSET(A59,-9,0)>0,OFFSET(A59,-9,0)+0.001,ERROR.TYPE(0)),IFERROR(IF(OFFSET(A59,-10,0)>0,OFFSET(A59,-10,0)+0.001,ERROR.TYPE(0)),ERROR.TYPE(0))))))))))) -> 2.022 | B59: Bib Tap | C59: 3 | D59: No. | F59: =IFERROR($C59*E59,E59) -> 0
B60: Level 0
B61: Plumbing hot and cold water using Polypropylene PN 16 pipework chased in wall/ surface mounted from header in shaft / main distribution pipework to final sanitary fittings including the supply of all fittings, brackets etc. for a complete installation as per drawing.
A62: =IFERROR(IF(OFFSET(A62,-1,0)>0,OFFSET(A62,-1,0)+0.001,ERROR.TYPE(0)),IFERROR(IF(OFFSET(A62,-2,0)>0,OFFSET(A62,-2,0)+0.001,ERROR.TYPE(0)),IFERROR(IF(OFFSET(A62,-3,0)>0,OFFSET(A62,-3,0)+0.001,ERROR.TYPE(0)),IFERROR(IF(OFFSET(A62,-4,0)>0,OFFSET(A62,-4,0)+0.001,ERROR.TYPE(0)),IFERROR(IF(OFFSET(A62,-5,0)>0,OFFSET(A62,-5,0)+0.001,ERROR.TYPE(0)),IFERROR(IF(OFFSET(A62,-6,0)>0,OFFSET(A62,-6,0)+0.001,ERROR.TYPE(0)),IFERROR(IF(OFFSET(A62,-7,0)>0,OFFSET(A62,-7,0)+0.001,ERROR.TYPE(0)),IFERROR(IF(OFFSET(A62,-8,0)>0,OFFSET(A62,-8,0)+0.001,ERROR.TYPE(0)),IFERROR(IF(OFFSET(A62,-9,0)>0,OFFSET(A62,-9,0)+0.001,ERROR.TYPE(0)),IFERROR(IF(OFFSET(A62,-10,0)>0,OFFSET(A62,-10,0)+0.001,ERROR.TYPE(0)),ERROR.TYPE(0))))))))))) -> 2.023 | B62: Wash hand basin | C62: 4 | D62: No. | F62: =IFERROR($C62*E62,E62) -> 0
A63: =IFERROR(IF(OFFSET(A63,-1,0)>0,OFFSET(A63,-1,0)+0.001,ERROR.TYPE(0)),IFERROR(IF(OFFSET(A63,-2,0)>0,OFFSET(A63,-2,0)+0.001,ERROR.TYPE(0)),IFERROR(IF(OFFSET(A63,-3,0)>0,OFFSET(A63,-3,0)+0.001,ERROR.TYPE(0)),IFERROR(IF(OFFSET(A63,-4,0)>0,OFFSET(A63,-4,0)+0.001,ERROR.TYPE(0)),IFERROR(IF(OFFSET(A63,-5,0)>0,OFFSET(A63,-5,0)+0.001,ERROR.TYPE(0)),IFERROR(IF(OFFSET(A63,-6,0)>0,OFFSET(A63,-6,0)+0.001,ERROR.TYPE(0)),IFERROR(IF(OFFSET(A63,-7,0)>0,OFFSET(A63,-7,0)+0.001,ERROR.TYPE(0)),IFERROR(IF(OFFSET(A63,-8,0)>0,OFFSET(A63,-8,0)+0.001,ERROR.TYPE(0)),IFERROR(IF(OFFSET(A63,-9,0)>0,OFFSET(A63,-9,0)+0.001,ERROR.TYPE(0)),IFERROR(IF(OFFSET(A63,-10,0)>0,OFFSET(A63,-10,0)+0.001,ERROR.TYPE(0)),ERROR.TYPE(0))))))))))) -> 2.024 | B63: WC complete c/w flushing | C63: 4 | D63: No. | F63: =IFERROR($C63*E63,E63) -> 0
A64: =IFERROR(IF(OFFSET(A64,-1,0)>0,OFFSET(A64,-1,0)+0.001,ERROR.TYPE(0)),IFERROR(IF(OFFSET(A64,-2,0)>0,OFFSET(A64,-2,0)+0.001,ERROR.TYPE(0)),IFERROR(IF(OFFSET(A64,-3,0)>0,OFFSET(A64,-3,0)+0.001,ERROR.TYPE(0)),IFERROR(IF(OFFSET(A64,-4,0)>0,OFFSET(A64,-4,0)+0.001,ERROR.TYPE(0)),IFERROR(IF(OFFSET(A64,-5,0)>0,OFFSET(A64,-5,0)+0.001,ERROR.TYPE(0)),IFERROR(IF(OFFSET(A64,-6,0)>0,OFFSET(A64,-6,0)+0.001,ERROR.TYPE(0)),IFERROR(IF(OFFSET(A64,-7,0)>0,OFFSET(A64,-7,0)+0.001,ERROR.TYPE(0)),IFERROR(IF(OFFSET(A64,-8,0)>0,OFFSET(A64,-8,0)+0.001,ERROR.TYPE(0)),IFERROR(IF(OFFSET(A64,-9,0)>0,OFFSET(A64,-9,0)+0.001,ERROR.TYPE(0)),IFERROR(IF(OFFSET(A64,-10,0)>0,OFFSET(A64,-10,0)+0.001,ERROR.TYPE(0)),ERROR.TYPE(0))))))))))) -> 2.025 | B64: Bib Tap | C64: 12 | D64: No. | F64: =IFERROR($C64*E64,E64) -> 0
A65: =IFERROR(IF(OFFSET(A65,-1,0)>0,OFFSET(A65,-1,0)+0.001,ERROR.TYPE(0)),IFERROR(IF(OFFSET(A65,-2,0)>0,OFFSET(A65,-2,0)+0.001,ERROR.TYPE(0)),IFERROR(IF(OFFSET(A65,-3,0)>0,OFFSET(A65,-3,0)+0.001,ERROR.TYPE(0)),IFERROR(IF(OFFSET(A65,-4,0)>0,OFFSET(A65,-4,0)+0.001,ERROR.TYPE(0)),IFERROR(IF(OFFSET(A65,-5,0)>0,OFFSET(A65,-5,0)+0.001,ERROR.TYPE(0)),IFERROR(IF(OFFSET(A65,-6,0)>0,OFFSET(A65,-6,0)+0.001,ERROR.TYPE(0)),IFERROR(IF(OFFSET(A65,-7,0)>0,OFFSET(A65,-7,0)+0.001,ERROR.TYPE(0)),IFERROR(IF(OFFSET(A65,-8,0)>0,OFFSET(A65,-8,0)+0.001,ERROR.TYPE(0)),IFERROR(IF(OFFSET(A65,-9,0)>0,OFFSET(A65,-9,0)+0.001,ERROR.TYPE(0)),IFERROR(IF(OFFSET(A65,-10,0)>0,OFFSET(A65,-10,0)+0.001,ERROR.TYPE(0)),ERROR.TYPE(0))))))))))) -> 2.026 | B65: Water Heater | C65: 1 | D65: No. | F65: =IFERROR($C65*E65,E65) -> 0
A66: =IFERROR(IF(OFFSET(A66,-1,0)>0,OFFSET(A66,-1,0)+0.001,ERROR.TYPE(0)),IFERROR(IF(OFFSET(A66,-2,0)>0,OFFSET(A66,-2,0)+0.001,ERROR.TYPE(0)),IFERROR(IF(OFFSET(A66,-3,0)>0,OFFSET(A66,-3,0)+0.001,ERROR.TYPE(0)),IFERROR(IF(OFFSET(A66,-4,0)>0,OFFSET(A66,-4,0)+0.001,ERROR.TYPE(0)),IFERROR(IF(OFFSET(A66,-5,0)>0,OFFSET(A66,-5,0)+0.001,ERROR.TYPE(0)),IFERROR(IF(OFFSET(A66,-6,0)>0,OFFSET(A66,-6,0)+0.001,ERROR.TYPE(0)),IFERROR(IF(OFFSET(A66,-7,0)>0,OFFSET(A66,-7,0)+0.001,ERROR.TYPE(0)),IFERROR(IF(OFFSET(A66,-8,0)>0,OFFSET(A66,-8,0)+0.001,ERROR.TYPE(0)),IFERROR(IF(OFFSET(A66,-9,0)>0,OFFSET(A66,-9,0)+0.001,ERROR.TYPE(0)),IFERROR(IF(OFFSET(A66,-10,0)>0,OFFSET(A66,-10,0)+0.001,ERROR.TYPE(0)),ERROR.TYPE(0))))))))))) -> 2.027 | B66: Instant Water Heater | C66: 1 | D66: No. | F66: =IFERROR($C66*E66,E66) -> 0
A67: =IFERROR(IF(OFFSET(A67,-1,0)>0,OFFSET(A67,-1,0)+0.001,ERROR.TYPE(0)),IFERROR(IF(OFFSET(A67,-2,0)>0,OFFSET(A67,-2,0)+0.001,ERROR.TYPE(0)),IFERROR(IF(OFFSET(A67,-3,0)>0,OFFSET(A67,-3,0)+0.001,ERROR.TYPE(0)),IFERROR(IF(OFFSET(A67,-4,0)>0,OFFSET(A67,-4,0)+0.001,ERROR.TYPE(0)),IFERROR(IF(OFFSET(A67,-5,0)>0,OFFSET(A67,-5,0)+0.001,ERROR.TYPE(0)),IFERROR(IF(OFFSET(A67,-6,0)>0,OFFSET(A67,-6,0)+0.001,ERROR.TYPE(0)),IFERROR(IF(OFFSET(A67,-7,0)>0,OFFSET(A67,-7,0)+0.001,ERROR.TYPE(0)),IFERROR(IF(OFFSET(A67,-8,0)>0,OFFSET(A67,-8,0)+0.001,ERROR.TYPE(0)),IFERROR(IF(OFFSET(A67,-9,0)>0,OFFSET(A67,-9,0)+0.001,ERROR.TYPE(0)),IFERROR(IF(OFFSET(A67,-10,0)>0,OFFSET(A67,-10,0)+0.001,ERROR.TYPE(0)),ERROR.TYPE(0))))))))))) -> 2.028 | B67: Irrigation controller | C67: 1 | D67: No. | F67: =IFERROR($C67*E67,E67) -> 0
B68: Supply and install U-PVC drains from sanitary fitting to main sewerage run including all fittings, gulleys, elbows, Tee-s, etc. as may be necessary for a complete installation for the following:
A69: =IFERROR(IF(OFFSET(A69,-1,0)>0,OFFSET(A69,-1,0)+0.001,ERROR.TYPE(0)),IFERROR(IF(OFFSET(A69,-2,0)>0,OFFSET(A69,-2,0)+0.001,ERROR.TYPE(0)),IFERROR(IF(OFFSET(A69,-3,0)>0,OFFSET(A69,-3,0)+0.001,ERROR.TYPE(0)),IFERROR(IF(OFFSET(A69,-4,0)>0,OFFSET(A69,-4,0)+0.001,ERROR.TYPE(0)),IFERROR(IF(OFFSET(A69,-5,0)>0,OFFSET(A69,-5,0)+0.001,ERROR.TYPE(0)),IFERROR(IF(OFFSET(A69,-6,0)>0,OFFSET(A69,-6,0)+0.001,ERROR.TYPE(0)),IFERROR(IF(OFFSET(A69,-7,0)>0,OFFSET(A69,-7,0)+0.001,ERROR.TYPE(0)),IFERROR(IF(OFFSET(A69,-8,0)>0,OFFSET(A69,-8,0)+0.001,ERROR.TYPE(0)),IFERROR(IF(OFFSET(A69,-9,0)>0,OFFSET(A69,-9,0)+0.001,ERROR.TYPE(0)),IFERROR(IF(OFFSET(A69,-10,0)>0,OFFSET(A69,-10,0)+0.001,ERROR.TYPE(0)),ERROR.TYPE(0))))))))))) -> 2.029 | B69: Wash hand basin | C69: 4 | D69: No. | F69: =IFERROR($C69*E69,E69) -> 0
A70: =IFERROR(IF(OFFSET(A70,-1,0)>0,OFFSET(A70,-1,0)+0.001,ERROR.TYPE(0)),IFERROR(IF(OFFSET(A70,-2,0)>0,OFFSET(A70,-2,0)+0.001,ERROR.TYPE(0)),IFERROR(IF(OFFSET(A70,-3,0)>0,OFFSET(A70,-3,0)+0.001,ERROR.TYPE(0)),IFERROR(IF(OFFSET(A70,-4,0)>0,OFFSET(A70,-4,0)+0.001,ERROR.TYPE(0)),IFERROR(IF(OFFSET(A70,-5,0)>0,OFFSET(A70,-5,0)+0.001,ERROR.TYPE(0)),IFERROR(IF(OFFSET(A70,-6,0)>0,OFFSET(A70,-6,0)+0.001,ERROR.TYPE(0)),IFERROR(IF(OFFSET(A70,-7,0)>0,OFFSET(A70,-7,0)+0.001,ERROR.TYPE(0)),IFERROR(IF(OFFSET(A70,-8,0)>0,OFFSET(A70,-8,0)+0.001,ERROR.TYPE(0)),IFERROR(IF(OFFSET(A70,-9,0)>0,OFFSET(A70,-9,0)+0.001,ERROR.TYPE(0)),IFERROR(IF(OFFSET(A70,-10,0)>0,OFFSET(A70,-10,0)+0.001,ERROR.TYPE(0)),ERROR.TYPE(0))))))))))) -> 2.03 | B70: WC | C70: 4 | D70: No. | F70: =IFERROR($C70*E70,E70) -> 0
B71: Install and connect the following sanitary ware and chrome
