Workbook
Name __tab89: '[1]Table 8 & 9'!$B$4:$D$440
Name _N: #REF!
Name _tab89: '[1]Table 8 & 9'!$B$4:$D$440
Name A: #REF!
Name aaaa: #REF!
Name abcd: #REF!
Name Access_BMS: [3]BMS_Estimate!#REF!
Name Access_Control: [4]Elec_Est!#REF!
Name Access_Supply: [3]BMS_Estimate!#REF!
Name Access_Wiring: [3]BMS_Estimate!#REF!
Name AddedMat: '[5]Data Upload D'!$E$8:$E$9
Name ANS: #REF!
Name AREAS: #REF!
Name AREAS: [4]ML_Sum!$X$1:$AD$16
Name AREAS: ML_Sum!$X$1:$AD$16
Name ASD: #REF!
Name B: #REF!
Name BILL3: [6]LIST!$B$56:$B$114
Name BILL4: [6]LIST!$B$116:$B$223
Name BILL5: [6]LIST!$B$225:$B$290
Name BILL6: [6]LIST!$B$293:$B$357
Name BILL7: [6]LIST!$B$360:$B$423
Name Bill9: [6]BoQ_1020!$B$638:$B$702
Name boq: #REF!
Name C_: #REF!
Name CCTV: [4]Elec_Est!#REF!
Name Cert: [7]Data!$A$1:$H$65536
Name CHILLERS: Elec_Est!$A$16
Name CONCRETE: #REF!
Name Contractor2: '[8]1. Cover Sheet'!$C$11
Name Data: [4]Elec_Est!#REF!
Name DATA_5: [9]Data!$A$1:$H$65536
Name DATA_SYSTEM: #REF!
Name day_works: #REF!
Name DAYWORKS: #REF!
Name Excavation: [10]List!$B$275:$B$307
Name Excel_BuiltIn__FilterDatabase_1: #REF!
Name Excel_BuiltIn__FilterDatabase_4: #REF!
Name Excel_BuiltIn_Print_Area_4: #REF!
Name Fire_Alarm: [4]Elec_Est!#REF!
Name FO: [4]Elec_Est!#REF!
Name ghuk: [11]Data!$A$1:$H$65536
Name Guard: [4]Elec_Est!#REF!
Name Intercom: [4]Elec_Est!#REF!
Name Intruder_Alarm: [4]Elec_Est!#REF!
Name LEVEL: #REF!
Name LIGHTNING_PROTECTION: #REF!
Name list: [12]workings!$K$5:$K$6
Name LIST2: #REF!
Name list3: '[13]MoW 1010'!$B$161:$B$183
Name MASONRY: #REF!
Name MISCELLANEOUS: #REF!
Name Persons: [14]Estimate!#REF!
Name Print_Area_MI: #REF!
Name Pumps: Elec_Est!#REF!
Name RAMON: #REF!
Name REINFORCEMENT: #REF!
Name ROOFING: #REF!
Name sdgdfg: [15]Data!$A$1:$H$65536
Name steel: [10]List!$B$161:$B$178

Sheet Notes
A1: NOTES:

Sheet Quote
A1: =IF(AND(UPPER(LEFT(TRIM($D$8),11))="01",UPPER(LEFT(TRIM($D$9),3))<>"ELM"),"PANTA RETAIL LTD.","PANTA CONTRACTING LIMITED") -> PANTA CONTRACTING LIMITED
A2: =IF(UPPER(LEFT(TRIM($D$9),3))="ELM","ELEC-FOR-MECH INTERNAL QUOTATION","ELECTRICAL INTERNAL QUOTATION") -> ELECTRICAL INTERNAL QUOTATION
B5: ATT: | D5: =IF(A2="Internal Quotation", "Mechanical Division","") | R5: Dated: | S5: =NOW() -> 45903.549
B6: CLIENT: | C6: Link to ML_SUM $D1 | D6: =ML_Sum!D1 -> ST Microelectronics (Malta) Ltd.
B7: PROJECT: | C7: Link to ML_SUM $D2 | D7: =ML_Sum!D2 -> KK2 General Exhaust Replacement
B8: JOB DESC: | C8: Link to ML_SUM $D3 | D8: =ML_Sum!D3 -> Electrical Supply and Installation
B9: QUOTE No: | C9: Link to ML_SUM $D4 | D9: =ML_Sum!D4 -> EL25-0559
B10: CLIENT's Ref: | C10: Link to ML_SUM $D5 | D10: =ML_Sum!D5 -> Tender
D22: Selling Price (€) : | E22: =ML_Sum!E35 -> 12486.23 | F22: =ML_Sum!D6 -> VAT EXCL. | G22: VAT EXCLUDED. | H22: VAT EXCLUDED. | I22: VAT EXCLUDED. | J22: VAT EXCLUDED. | K22: VAT EXCLUDED. | L22: VAT EXCLUDED. | M22: VAT EXCLUDED. | N22: VAT EXCLUDED. | O22: VAT EXCLUDED. | P22: VAT EXCLUDED.
A51: Signed for and on behalf of | Q51: Signed for and on behalf of
A52: Electrical Division | Q52: Division
Q54: Records
Q55: Mr. K. Micallef
Q57: File

Sheet ML_Sum
B1: CLIENT: | C1: 1 | D1: ST Microelectronics (Malta) Ltd. | G1: TRUE | H1: TRUE | I1: 1 | J1: =$Q109 -> 1 | K1: =$Q119 -> 1 | L1: =$Q129 -> 1 | M1: =$Q139 -> 1 | N1: =$Q149 -> 1 | O1: =$Q159 -> 1 | Q1: =IF(C1=1,"€","Curr?") -> € | R1: Recon /Lab.Cont >> | S1: =IF($S$39="PRINT","R","Do Not Print") -> R | T1: 1.25 | V1: {=IF(OR(X1=AREAS),1,0)} -> 1 | W1: BOQ | X1: x | Y1: x | Z1: x | AA1: x | AB1: x | AC1: x | AD1: x
B2: PROJECT: | C2: =IF($D$6="VAT INCLUDED",1.18,1)*(1-$Q2)*$C$1 -> 1 | D2: KK2 General Exhaust Replacement | F2: Electrical | G2: TRUE | I2: 2 | J2: =$Q110 -> 1 | K2: =$Q120 -> 1 | L2: =$Q130 -> 1 | M2: =$Q140 -> 1 | N2: =$Q150 -> 1 | O2: =$Q160 -> 1 | R2: ="A) " & IF($S2=0,"",ROUND($S2,2) & "-" & ROUND($T2/$D$9,2)) -> A) 1.25-1.25 | S2: 1.25 | T2: =$S2*$D$9 -> 34.325 | X2: x | Y2: x | Z2: x | AA2: x | AB2: x | AC2: x | AD2: x
B3: JOB DESC: | C3: =IF($D$6="VAT INCLUDED",1.18,1)*(1-$Q3)*$C$1 -> 1 | D3: Electrical Supply and Installation | F3: Controls | G3: TRUE | I3: 3 | J3: =$Q111 -> 1 | K3: =$Q121 -> 1 | L3: =$Q131 -> 1 | M3: =$Q141 -> 1 | N3: =$Q151 -> 1 | O3: =$Q161 -> 1 | R3: ="B) " & IF($S3=0,"",ROUND($S3,2) & "-" & ROUND($T3/$D$9,2)) -> B) 1.25-1.25 | S3: 1.25 | T3: =$S3*$D$9 -> 34.325 | X3: x | Y3: x | Z3: x | AA3: x | AB3: x | AC3: x | AD3: x
B4: INT. QUOT No: | C4: =IF($D$6="VAT INCLUDED",1.18,1)*(1-$Q4)*$C$1 -> 1 | D4: EL25-0559 | G4: TRUE | I4: 4 | J4: =$Q112 -> 1 | K4: =$Q122 -> 1 | L4: =$Q132 -> 1 | M4: =$Q142 -> 1 | N4: =$Q152 -> 1 | O4: =$Q162 -> 1 | R4: ="C) " & IF($S4=0,"",ROUND($S4,2) & "-" & ROUND($T4/$D$9,2)) -> C) | X4: x | Y4: x | Z4: x | AA4: x | AB4: x | AC4: x | AD4: x
B5: CLIENTs REF: | C5: =IF($D$6="VAT INCLUDED",1.18,1)*(1-$Q5)*$C$1 -> 1 | D5: Tender | G5: TRUE | I5: 5 | J5: =$Q113 -> 1 | K5: =$Q123 -> 1 | L5: =$Q133 -> 1 | M5: =$Q143 -> 1 | N5: =$Q153 -> 1 | O5: =$Q163 -> 1 | R5: ="D) " & IF($S5=0,"",ROUND($S5,2) & "-" & ROUND($T5/$D$9,2)) -> D) | X5: x | Y5: x | Z5: x | AA5: x | AB5: x | AC5: x | AD5: x
B6: VAT: | C6: =IF($D$6="VAT INCLUDED",1.18,1)*(1-$Q6)*$C$1 -> 1 | D6: VAT EXCL. | G6: TRUE | I6: 6 | J6: =$Q114 -> 1 | K6: =$Q124 -> 1 | L6: =$Q134 -> 1 | M6: =$Q144 -> 1 | N6: =$Q154 -> 1 | O6: =$Q164 -> 1 | R6: ="E) " & IF($S6=0,"",ROUND($S6,2) & "-" & ROUND($T6/$D$9,2)) -> E) | X6: x | Y6: x | Z6: x | AA6: x | AB6: x | AC6: x | AD6: x
B7: SAVED ON: | C7: =IF($D$6="VAT INCLUDED",1.18,1)*(1-$Q7)*$C$1 -> 1 | D7: 45897 | G7: TRUE | I7: 7 | J7: =$Q115 -> 1 | K7: =$Q125 -> 1 | L7: =$Q135 -> 1 | M7: =$Q145 -> 1 | N7: =$Q155 -> 1 | R7: ="F) " & IF($S7=0,"",ROUND($S7,2) & "-" & ROUND($T7/$D$9,2)) -> F) | X7: x | Y7: x | Z7: x | AA7: x | AB7: x | AC7: x | AD7: x
B8: ESTIMATOR: | C8: =IF($D$6="VAT INCLUDED",1.18,1)*(1-$Q8)*$C$1 -> 1 | D8: Umut Kaymak | G8: TRUE | I8: 8 | J8: =$Q116 -> 1 | K8: =$Q126 -> 1 | L8: =$Q136 -> 1 | M8: =$Q146 -> 1 | N8: =$Q156 -> 1 | R8: ="G) " & IF($S8=0,"",ROUND($S8,2) & "-" & ROUND($T8/$D$9,2)) -> G) | X8: x | Y8: x | Z8: x | AA8: x | AB8: x | AC8: x | AD8: x
B9: LAB. COST: | C9: =IF($D$6="VAT INCLUDED",1.18,1)*(1-$Q9)*$C$1 -> 1 | D9: 27.46 | G9: TRUE | I9: 9 | J9: =$Q117 -> 1 | K9: =$Q127 -> 1 | L9: =$Q137 -> 1 | M9: =$Q147 -> 1 | N9: =$Q157 -> 1 | R9: ="H) " & IF($S9=0,"",ROUND($S9,2) & "-" & ROUND($T9/$D$9,2)) -> H) | X9: x | Y9: x | Z9: x | AA9: x | AB9: x | AC9: x | AD9: x
C10: =IF($D$6="VAT INCLUDED",1.18,1)*(1-$Q10)*$C$1 -> 1 | G10: TRUE | I10: 10 | J10: =$Q118 -> 1 | K10: =$Q128 -> 1 | L10: =$Q138 -> 1 | M10: =$Q148 -> 1 | N10: =$Q158 -> 1 | O10: =Q108 -> 1 | R10: =" I) " & IF($S10=0,"",ROUND($S10,2) & "-" & ROUND($T10/$D$9,2)) -> I) | X10: x | Y10: x | Z10: x | AA10: x | AB10: x | AC10: x | AD10: x
C11: =IF($D$6="VAT INCLUDED",1.18,1)*(1-$Q11)*$C$1 -> 1 | R11: ="J) " & IF($S11=0,"",ROUND($S11,2) & "-" & ROUND($T11/$D$9,2)) -> J) | X11: x | Y11: x | Z11: x | AA11: x | AB11: x | AC11: x | AD11: x
C12: =IF($D$6="VAT INCLUDED",1.18,1)*(1-$Q12)*$C$1 -> 1 | G12: SYSTEMS | H12: SYSTEMS | I12: SYSTEMS | J12: SYSTEMS | K12: SYSTEMS | L12: SYSTEMS | M12: SYSTEMS | N12: SYSTEMS | O12: SYSTEMS | P12: SYSTEMS | R12: MIXED - X,Y ) | S12: MAT MU | T12: LAB RATE | X12: x | Y12: x | Z12: x | AA12: x | AB12: x | AC12: x | AD12: x
B13: MATERIAL & LABOUR SUMMARY | G13: ItemCode | H13: CostCode | I13: MAKE | J13: PART_NO | K13: MARKUP | L13: TYPE | M13: LIST_P | N13: SET | O13: FIX | P13: DATE | Q13: %Dsct in BOQ | R13: MATMU-LABMU | S13: MAT CONT >> | T13: =SUM(Q108:Q164)/57 -> 1
B14: =IF($D$6<>"VAT EXCL.", "QUOTE ISSUED WITH VAT INCLUDED", "") | X14: x | Y14: x | Z14: x | AA14: x | AB14: x | AC14: x | AD14: x
Q15: =(C72-F35)/C72 -> 0 | R15: Average Discount applied in BOQ (Q2-Q12) | X15: x | Y15: x | Z15: x | AA15: x | AB15: x | AC15: x | AD15: x
B16: =IF($W$1<>"BOQ", "DIFF SET TO " & W1,"") | Q16: =(F35-E35)/F35 -> 0 | R16: Average Discount applied on Totals (Q23-Q32) | X16: x | Y16: x | Z16: x | AA16: x | AB16: x | AC16: x | AD16: x
Q17: =F74 -> 0 | R17: Overall Discount
B18: =IF(AND(G1,G2,G3,G4,G5,G6,G7,G8,G9,G10,H1)=TRUE, "", "CHECKLIST INCOMPLETE !" )
B19: =IF(ABS(SUM(A23:A32))>100,"[Discy A-J] are high, Check it out."," ") | Q19: =R83 -> 1.2502523 | R19: Overall Markup (Final Selling Excl.VAT/Total Cost )
E21: DISCOUNTED | F21: SELLING | Q21: % Discnt | R21: MATERIAL | T21: LABOUR
A22: Discy.A-J | B22: Markup/LRate | E22: ="SELLING " & $Q$1 -> SELLING € | F22: =$Q$1 -> € | G22: VAT/DISC | H22: MU | I22: LABRATE | J22: LABCOST | Q22: on Totals | R22: € | T22: Pair Hrs.
A23: =IF($F23=0,"",($F23/$C2)-($R23*$S2+$T23*$T2)) -> 0.2525 | B23: =IF(F23=0,"",IF(R23=0,"A) "&"---, "&ROUND(($F23/$C2-($R23*$S2))/$T23,2),IF(T23=0,"A) "&ROUND(($F23/$C2)/$R23,2),"A) "&ROUND(($F23/$C2-($T23*$T2))/$R23,2)&", " &ROUND(($F23/$C2-($R23*$S2))/$T23,2)))) -> A) 1.25, 34.33 | D23: =IF($F2="","",$F2) -> Electrical | E23: =F23*(1-Q23) -> 8500.53 | F23: =Elec_Est!F105 -> 8500.53 | G23: =C2 -> 1 | H23: =$S2 -> 1.25 | I23: =$T2 -> 34.325 | J23: =$D$9 -> 27.46 | R23: =Elec_Est!R105 -> 4584.2 | T23: =Elec_Est!T105 -> 80.7
A24: =IF($F24=0,"",($F24/$C3)-($R24*$S3+$T24*$T3)) -> 0.0125 | B24: =IF(F24=0,"",IF(R24=0,"A) "&"---, "&ROUND(($F24/$C3-($R24*$S3))/$T24,2),IF(T24=0,"A) "&ROUND(($F24/$C3)/$R24,2),"A) "&ROUND(($F24/$C3-($T24*$T3))/$R24,2)&", " &ROUND(($F24/$C3-($R24*$S3))/$T24,2)))) -> A) 1.25, 34.33 | D24: =IF($F3="","",$F3) -> Controls | E24: =F24*(1-Q24) -> 3985.7 | F24: =Elec_Est!F106 -> 3985.7 | G24: =C3 -> 1 | H24: =$S3 -> 1.25 | I24: =$T3 -> 34.325 | J24: =$D$9 -> 27.46 | R24: =Elec_Est!R106 -> 2629 | T24: =Elec_Est!T106 -> 20.376912
A25: =IF($F25=0,"",($F25/$C4)-($R25*$S4+$T25*$T4)) | B25: =IF(F25=0,"",IF(R25=0,"A) "&"---, "&ROUND(($F25/$C4-($R25*$S4))/$T25,2),IF(T25=0,"A) "&ROUND(($F25/$C4)/$R25,2),"A) "&ROUND(($F25/$C4-($T25*$T4))/$R25,2)&", " &ROUND(($F25/$C4-($R25*$S4))/$T25,2)))) | D25: =IF($F4="","",$F4) | E25: =F25*(1-Q25) -> 0 | F25: =Elec_Est!F107 -> 0 | G25: =C4 -> 1 | H25: =$S4 -> 0 | I25: =$T4 -> 0 | J25: =$D$9 -> 27.46 | R25: =Elec_Est!R107 -> 0 | T25: =Elec_Est!T107 -> 0
A26: =IF($F26=0,"",($F26/$C5)-($R26*$S5+$T26*$T5)) | B26: =IF(F26=0,"",IF(R26=0,"A) "&"---, "&ROUND(($F26/$C5-($R26*$S5))/$T26,2),IF(T26=0,"A) "&ROUND(($F26/$C5)/$R26,2),"A) "&ROUND(($F26/$C5-($T26*$T5))/$R26,2)&", " &ROUND(($F26/$C5-($R26*$S5))/$T26,2)))) | D26: =IF($F5="","",$F5) | E26: =F26*(1-Q26) -> 0 | F26: =Elec_Est!F108 -> 0 | G26: =C5 -> 1 | H26: =$S5 -> 0 | I26: =$T5 -> 0 | J26: =$D$9 -> 27.46 | R26: =Elec_Est!R108 -> 0 | T26: =Elec_Est!T108 -> 0
A27: =IF($F27=0,"",($F27/$C6)-($R27*$S6+$T27*$T6)) | B27: =IF(F27=0,"",IF(R27=0,"A) "&"---, "&ROUND(($F27/$C6-($R27*$S6))/$T27,2),IF(T27=0,"A) "&ROUND(($F27/$C6)/$R27,2),"A) "&ROUND(($F27/$C6-($T27*$T6))/$R27,2)&", " &ROUND(($F27/$C6-($R27*$S6))/$T27,2)))) | D27: =IF($F6="","",$F6) | E27: =F27*(1-Q27) -> 0 | F27: =Elec_Est!F109 -> 0 | G27: =C6 -> 1 | H27: =$S6 -> 0 | I27: =$T6 -> 0 | J27: =$D$9 -> 27.46 | R27: =Elec_Est!R109 -> 0 | T27: =Elec_Est!T109 -> 0
A28: =IF($F28=0,"",($F28/$C7)-($R28*$S7+$T28*$T7)) | B28: =IF(F28=0,"",IF(R28=0,"A) "&"---, "&ROUND(($F28/$C7-($R28*$S7))/$T28,2),IF(T28=0,"A) "&ROUND(($F28/$C7)/$R28,2),"A) "&ROUND(($F28/$C7-($T28*$T7))/$R28,2)&", " &ROUND(($F28/$C7-($R28*$S7))/$T28,2)))) | D28: =IF($F7="","",$F7) | E28: =F28*(1-Q28) -> 0 | F28: =Elec_Est!F110 -> 0 | G28: =C7 -> 1 | H28: =$S7 -> 0 | I28: =$T7 -> 0 | J28: =$D$9 -> 27.46 | R28: =Elec_Est!R110 -> 0 | T28: =Elec_Est!T110 -> 0
A29: =IF($F29=0,"",($F29/$C8)-($R29*$S8+$T29*$T8)) | B29: =IF(F29=0,"",IF(R29=0,"A) "&"---, "&ROUND(($F29/$C8-($R29*$S8))/$T29,2),IF(T29=0,"A) "&ROUND(($F29/$C8)/$R29,2),"A) "&ROUND(($F29/$C8-($T29*$T8))/$R29,2)&", " &ROUND(($F29/$C8-($R29*$S8))/$T29,2)))) | D29: =IF($F8="","",$F8) | E29: =F29*(1-Q29) -> 0 | F29: =Elec_Est!F111 -> 0 | G29: =C8 -> 1 | H29: =$S8 -> 0 | I29: =$T8 -> 0 | J29: =$D$9 -> 27.46 | R29: =Elec_Est!R111 -> 0 | T29: =Elec_Est!T111 -> 0
A30: =IF($F30=0,"",($F30/$C9)-($R30*$S9+$T30*$T9)) | B30: =IF(F30=0,"",IF(R30=0,"A) "&"---, "&ROUND(($F30/$C9-($R30*$S9))/$T30,2),IF(T30=0,"A) "&ROUND(($F30/$C9)/$R30,2),"A) "&ROUND(($F30/$C9-($T30*$T9))/$R30,2)&", " &ROUND(($F30/$C9-($R30*$S9))/$T30,2)))) | D30: =IF($F9="","",$F9) | E30: =F30*(1-Q30) -> 0 | F30: =Elec_Est!F112 -> 0 | G30: =C9 -> 1 | H30: =$S9 -> 0 | I30: =$T9 -> 0 | J30: =$D$9 -> 27.46 | R30: =Elec_Est!R112 -> 0 | T30: =Elec_Est!T112 -> 0
A31: =IF($F31=0,"",($F31/$C10)-($R31*$S10+$T31*$T10)) | B31: =IF(F31=0,"",IF(R31=0,"A) "&"---, "&ROUND(($F31/$C10-($R31*$S10))/$T31,2),IF(T31=0,"A) "&ROUND(($F31/$C10)/$R31,2),"A) "&ROUND(($F31/$C10-($T31*$T10))/$R31,2)&", " &ROUND(($F31/$C10-($R31*$S10))/$T31,2)))) | D31: =IF($F10="","",$F10) | E31: =F31*(1-Q31) -> 0 | F31: =Elec_Est!F113 -> 0 | G31: =C10 -> 1 | H31: =$S10 -> 0 | I31: =$T10 -> 0 | J31: =$D$9 -> 27.46 | R31: =Elec_Est!R113 -> 0 | T31: =Elec_Est!T113 -> 0
A32: =IF($F32=0,"",($F32/$C11)-($R32*$S11+$T32*$T11)) | B32: =IF(F32=0,"",IF(R32=0,"A) "&"---, "&ROUND(($F32/$C11-($R32*$S11))/$T32,2),IF(T32=0,"A) "&ROUND(($F32/$C11)/$R32,2),"A) "&ROUND(($F32/$C11-($T32*$T11))/$R32,2)&", " &ROUND(($F32/$C11-($R32*$S11))/$T32,2)))) | D32: =IF($F11="","",$F11) | E32: =F32*(1-Q32) -> 0 | F32: =Elec_Est!F114 -> 0 | G32: =C11 -> 1 | H32: =$S11 -> 0 | I32: =$T11 -> 0 | J32: =$D$9 -> 27.46 | R32: =Elec_Est!R114 -> 0 | T32: =Elec_Est!T114 -> 0
C33: MIXED
A35: Discy.L | B35: =E_BOQ!F48 -> 12486.23 | E35: =SUM(E23:E32) -> 12486.23 | F35: =SUM(F23:F32) -> 12486.23 | R35: =SUM(R23:R32) -> 7213.2 | T35: =SUM(T23:T32) -> 101.07691
A36: =IF(A39=0,"0.00",A39-(A38*A37)) -> 0.00 | B36: BOQ TOTAL | E36: ="ESTIM TOTAL (" & $Q$1 & ")" -> ESTIM TOTAL (€)
A37: 1.125 | B37: <1 Actual LabCont | R37: =R165 -> 7213.4554 | S37: C.C.Totals | T37: =T165 -> 101.00191
B38: <2 Phrs @ 1.00
B39: <3 Phrs @ Actual | Q39: Discy.T >> | R39: =R37-R35 -> 0.25535 | S39: PRINT | T39: =T37-T35 -> -0.075
B41: Values Only on : | D41: 45897 | E41: 12486.23 | F41: 12486.23 | R41: 7213.2 | T41: 101.07691
A46: REMARKS:
A47: 1) VAT and Duties as above.
A48: 2)
A51: ESTIMATOR: | D51: =D8 -> Umut Kaymak | Q51: APPROVED BY:
A53: SIGNED: | Q53: DATE APPROVED:
A55: FILE LOCATION: | D55: =CELL("filename") -> K:\est\ST Microelectronics Malta\Estimates\[E25_0559_ST_Electronics_Exhaust_Replacement_Est_.xlsx]Elec_Est
B57: PANTA CONTRACTING LTD. - ELECTRICAL DIVISION
B58: CONTRACT / VARIATION INPUT DOCUMENT
S59: Copy to:-
D60: Client: | E60: =D1 -> ST Microelectronics (Malta) Ltd. | S60: Ms. S. Magri
D61: Project: | E61: =D2 -> KK2 General Exhaust Replacement | S61: Mr. K. Micallef
D62: Job Description: | E62: =D3 -> Electrical Supply and Installation | S62: Mr. A. Sciberras
D63: Quote No: | E63: =D4 -> EL25-0559
D64: Client's Ref: | E64: =D5 -> Tender
S65: File:-
D66: File No:
D67: Ext. Ref:
E70: Contract /Variation (Excl. VAT)
C72: =IF($A$33="MIXED",F23/(1-Q2)+F24/(1-Q3)+F25/(1-Q4)+F26/(1-Q5)+F27/(1-Q6)+F28/(1-Q7)+F29/(1-Q8)+F30/(1-Q9)+F31/(1-Q10)+F32/(1-Q11)-SUM(A23:A32), F23/(1-Q2)+F24/(1-Q3)+F25/(1-Q4)+F26/(1-Q5)+F27/(1-Q6)+F28/(1-Q7)+F29/(1-Q8)+F30/(1-Q9)+F31/(1-Q10)+F32/(1-Q11)) -> 12486.23 | E72: Estim.Sell before Discounts excl.VAT (€): | F72: =IF(D6="VAT INCLUDED",C72/($C$1*1.18),C72/$C$1) -> 12486.23
E74: Overall Discount: | F74: =(F72-F75)/F72 -> 0
E75: Final Sell after Discounts excl.VAT (€): | F75: =IF(D6="VAT INCLUDED",E35/($C$1*1.18),E35/$C$1) -> 12486.23
E77: Labour Rate - | F77: =$D$9 -> 27.46 | R77: Mech. Cost to us
D80: Mat. Cost | E80: Labour | F80: Total Cost | R80: Sell Excl.VAT / Total Cost
D81: € | E81: Pair.Hrs | F81: €
D83: =R165 -> 7213.4554 | E83: =T165 -> 101.00191 | F83: =R165+S165 -> 9986.9679 | R83: =IF(F83=0,0,F75/F83) -> 1.2502523
D84: ( From CostCode Totals )
R87: Advanced Payment:
R88: Retention:
R90: Awarded Date:
R91: Estimated Start Date:
R92: Estimated Completion Date:
D93: .................
D94: A. Sciberras | R94: Date issued:
D95: =NOW() -> 45903.549
D98: PANTA CONTRACTING LTD. - ELECTRICAL DIVISION
D99: ELECTRICAL AND ELV CONTRACT / VARIATION BUDGET COST
D101: Project: | E101: =E61 -> KK2 General Exhaust Replacement
D102: Job Desc: | E102: =E62 -> Electrical Supply and Installation
D103: Client's Ref: | E103: =E64 -> Tender
D106: COSTCODE | F106: Cost | Q106: Mat. | R106: Mat Cost | S106: Lab Cost @ | T106: Labour
F107: Code | Q107: Cont. | R107: € | S107: =$D$9 -> 27.46 | T107: Pair.Hrs
B108: V:56 | D108: BOQ RateOnly Items | P108: FIX | Q108: 1
B109: 1(J) | C109: cc | D109: Erection materials | F109: 501 | P109: 1 | Q109: 1 | R109: =Elec_Est!R126 -> 2142.445 | S109: =T109*$D$9 -> 514.875 | T109: =Elec_Est!T126 -> 18.75
B110: 2 | C110: cc | D110: Busbar Trunking | F110: 505 | P110: 1 | Q110: 1 | R110: =Elec_Est!R127 -> 0 | S110: =T110*$D$9 -> 0 | T110: =Elec_Est!T127 -> 0
B111: 3 | C111: cc | D111: Switchgear | F111: 510 | P111: 2 | Q111: 1 | R111: =Elec_Est!R128 -> 0 | S111: =T111*$D$9 -> 0 | T111: =Elec_Est!T128 -> 0
B112: 4 | C112: cc | D112: MCC Equipment | F112: 511 | P112: 2 | Q112: 1 | R112: =Elec_Est!R129 -> 0 | S112: =T112*$D$9 -> 0 | T112: =Elec_Est!T129 -> 0
B113: 5 | C113: cc | D113: BMS Equipment | F113: 512 | P113: 2 | Q113: 1 | R113: =Elec_Est!R130 -> 2629 | S113: =T113*$D$9 -> 834.15 | T113: =Elec_Est!T130 -> 30.376912
B114: 6 | C114: cc | D114: PVC Pipes / Ducts | F114: 520 | P114: 1 | Q114: 1 | R114: =Elec_Est!R131 -> 0 | S114: =T114*$D$9 -> 0 | T114: =Elec_Est!T131 -> 0
B115: 7 | C115: cc | D115: High/medium voltage switchgear | F115: 530 | P115: 2 | Q115: 1 | R115: =Elec_Est!R132 -> 0 | S115: =T115*$D$9 -> 0 | T115: =Elec_Est!T132 -> 0
B116: 8 | C116: cc | D116: Power Transformers | F116: 550 | P116: 2 | Q116: 1 | R116: =Elec_Est!R133 -> 0 | S116: =T116*$D$9 -> 0 | T116: =Elec_Est!T133 -> 0
B117: 9 | C117: cc | D117: Control Panels | F117: 570 | P117: 2 | Q117: 1 | R117: =Elec_Est!R134 -> 0 | S117: =T117*$D$9 -> 0 | T117: =Elec_Est!T134 -> 0
B118: 10 | C118: cc | D118: Electrical Single Core Cables | F118: 615 | P118: 2 | Q118: 1 | R118: =Elec_Est!R135 -> 0 | S118: =T118*$D$9 -> 0 | T118: =Elec_Est!T135 -> 0
B119: 11(K) | C119: cc | D119: Electrical Multicore Cables | F119: 616 | P119: 2 | Q119: 1 | R119: =Elec_Est!R136 -> 540 | S119: =T119*$D$9 -> 102.975 | T119: =Elec_Est!T136 -> 3.75
B120: 12 | C120: cc | D120: ELV/BMS/Special Cables | F120: 617 | P120: 2 | Q120: 1 | R120: =Elec_Est!R137 -> 0 | S120: =T120*$D$9 -> 0 | T120: =Elec_Est!T137 -> 0
B121: 13 | C121: cc | D121: Cable Accessories | F121: 620 | P121: 2 | Q121: 1 | R121: =Elec_Est!R138 -> 119 | S121: =T121*$D$9 -> 240.275 | T121: =Elec_Est!T138 -> 8.75
B122: 14 | C122: cc | D122: Galv. Cable Trays | F122: 650 | P122: 1 | Q122: 1 | R122: =Elec_Est!R139 -> 1683.0104 | S122: =T122*$D$9 -> 669.3375 | T122: =Elec_Est!T139 -> 24.375
B123: 15 | C123: cc | D123: PVC Cable Trays | F123: 651 | P123: 1 | Q123: 1 | R123: =Elec_Est!R140 -> 0 | S123: =T123*$D$9 -> 0 | T123: =Elec_Est!T140 -> 0
B124: 16 | C124: cc | D124: Galv. Cable Basket | F124: 652 | P124: 1 | Q124: 1 | R124: =Elec_Est!R141 -> 0 | S124: =T124*$D$9 -> 0 | T124: =Elec_Est!T141 -> 0
B125: 17 | C125: cc | D125: Galv. Cable Ladder | F125: 654 | P125: 1 | Q125: 1 | R125: =Elec_Est!R142 -> 0 | S125: =T125*$D$9 -> 0 | T125: =Elec_Est!T142 -> 0
B126: 18 | C126: cc | D126: Galv. Cable Trunking | F126: 675 | P126: 1 | Q126: 1 | R126: =Elec_Est!R143 -> 0 | S126: =T126*$D$9 -> 0 | T126: =Elec_Est!T143 -> 0
B127: 19 | C127: cc | D127: Alum. Cable Trunking | F127: 676 | P127: 1 | Q127: 1 | R127: =Elec_Est!R144 -> 0 | S127: =T127*$D$9 -> 0 | T127: =Elec_Est!T144 -> 0
B128: 20 | C128: cc | D128: PVC Cable Trunking | F128: 680 | P128: 1 | Q128: 1 | R128: =Elec_Est!R145 -> 0 | S128: =T128*$D$9 -> 0 | T128: =Elec_Est!T145 -> 0
...

Sheet Elec_Rates
B1: CLIENT: | C1: =ML_Sum!$C1 -> 1 | D1: =ML_Sum!$D1 -> ST Microelectronics (Malta) Ltd. | F1: =ML_Sum!$F1 -> 0 | I1: 1 | J1: =ML_Sum!$J1 -> 1 | K1: =ML_Sum!$K1 -> 1 | L1: =ML_Sum!$L1 -> 1 | M1: =ML_Sum!$M1 -> 1 | N1: =ML_Sum!$N1 -> 1 | O1: =ML_Sum!$O1 -> 1 | Q1: =ML_Sum!$Q1 -> € | R1: R/Lab Cont | S1: =ML_Sum!$S1 -> R | T1: =ML_Sum!$T1 -> 1.25 | U1: =ML_Sum!W1 -> BOQ | V1: INCL | W1: MULT | X1: AREA | Y1: BOQ | Z1: TDWG | AA1: ACT | AB1: DIFF
B2: PROJECT: | C2: =ML_Sum!$C2 -> 1 | D2: =ML_Sum!$D2 -> KK2 General Exhaust Replacement | F2: =ML_Sum!$F2 -> Electrical | I2: 2 | J2: =ML_Sum!$J2 -> 1 | K2: =ML_Sum!$K2 -> 1 | L2: =ML_Sum!$L2 -> 1 | M2: =ML_Sum!$M2 -> 1 | N2: =ML_Sum!$N2 -> 1 | O2: =ML_Sum!$O2 -> 1 | Q2: =ML_Sum!$Q2 -> 0 | R2: mu_A | S2: =ML_Sum!$S2 -> 1.25 | T2: =ML_Sum!$T2 -> 34.325
B3: JOB DESC: | C3: =ML_Sum!$C3 -> 1 | D3: =ML_Sum!$D3 -> Electrical Supply and Installation | F3: =ML_Sum!$F3 -> Controls | I3: 3 | J3: =ML_Sum!$J3 -> 1 | K3: =ML_Sum!$K3 -> 1 | L3: =ML_Sum!$L3 -> 1 | M3: =ML_Sum!$M3 -> 1 | N3: =ML_Sum!$N3 -> 1 | O3: =ML_Sum!$O3 -> 1 | Q3: =ML_Sum!$Q3 -> 0 | R3: mu_B | S3: =ML_Sum!$S3 -> 1.25 | T3: =ML_Sum!$T3 -> 34.325
B4: QUOTE No: | C4: =ML_Sum!$C4 -> 1 | D4: =ML_Sum!$D4 -> EL25-0559 | F4: =ML_Sum!$F4 -> 0 | I4: 4 | J4: =ML_Sum!$J4 -> 1 | K4: =ML_Sum!$K4 -> 1 | L4: =ML_Sum!$L4 -> 1 | M4: =ML_Sum!$M4 -> 1 | N4: =ML_Sum!$N4 -> 1 | O4: =ML_Sum!$O4 -> 1 | Q4: =ML_Sum!$Q4 -> 0 | R4: mu_C | S4: =ML_Sum!$S4 -> 0 | T4: =ML_Sum!$T4 -> 0
B5: CLIENTs REF: | C5: =ML_Sum!$C5 -> 1 | D5: =ML_Sum!$D5 -> Tender | F5: =ML_Sum!$F5 -> 0 | I5: 5 | J5: =ML_Sum!$J5 -> 1 | K5: =ML_Sum!$K5 -> 1 | L5: =ML_Sum!$L5 -> 1 | M5: =ML_Sum!$M5 -> 1 | N5: =ML_Sum!$N5 -> 1 | O5: =ML_Sum!$O5 -> 1 | Q5: =ML_Sum!$Q5 -> 0 | R5: mu_D | S5: =ML_Sum!$S5 -> 0 | T5: =ML_Sum!$T5 -> 0
B6: VAT/DUTIES: | C6: =ML_Sum!$C6 -> 1 | D6: =ML_Sum!$D6 -> VAT EXCL. | F6: =ML_Sum!$F6 -> 0 | I6: 6 | J6: =ML_Sum!$J6 -> 1 | K6: =ML_Sum!$K6 -> 1 | L6: =ML_Sum!$L6 -> 1 | M6: =ML_Sum!$M6 -> 1 | N6: =ML_Sum!$N6 -> 1 | O6: =ML_Sum!$O6 -> 1 | Q6: =ML_Sum!$Q6 -> 0 | R6: mu_E | S6: =ML_Sum!$S6 -> 0 | T6: =ML_Sum!$T6 -> 0
B7: SAVED ON: | C7: =ML_Sum!$C7 -> 1 | D7: 39364 | F7: =ML_Sum!$F7 -> 0 | I7: 7 | J7: =ML_Sum!$J7 -> 1 | K7: =ML_Sum!$K7 -> 1 | L7: =ML_Sum!$L7 -> 1 | M7: =ML_Sum!$M7 -> 1 | N7: =ML_Sum!$N7 -> 1 | O7: =ML_Sum!$O7 -> 0 | Q7: =ML_Sum!$Q7 -> 0 | R7: mu_F | S7: =ML_Sum!$S7 -> 0 | T7: =ML_Sum!$T7 -> 0
B8: ESTIMATOR: | C8: =ML_Sum!$C8 -> 1 | D8: =ML_Sum!$D8 -> Umut Kaymak | F8: =ML_Sum!$F8 -> 0 | I8: 8 | J8: =ML_Sum!$J8 -> 1 | K8: =ML_Sum!$K8 -> 1 | L8: =ML_Sum!$L8 -> 1 | M8: =ML_Sum!$M8 -> 1 | N8: =ML_Sum!$N8 -> 1 | O8: =ML_Sum!$O8 -> 0 | Q8: =ML_Sum!$Q8 -> 0 | R8: mu_G | S8: =ML_Sum!$S8 -> 0 | T8: =ML_Sum!$T8 -> 0
B9: LABOUR RATE: | C9: =ML_Sum!$C9 -> 1 | D9: =ML_Sum!$D9 -> 27.46 | F9: =ML_Sum!$F9 -> 0 | I9: 9 | J9: =ML_Sum!$J9 -> 1 | K9: =ML_Sum!$K9 -> 1 | L9: =ML_Sum!$L9 -> 1 | M9: =ML_Sum!$M9 -> 1 | N9: =ML_Sum!$N9 -> 1 | O9: =ML_Sum!$O9 -> 0 | Q9: =ML_Sum!$Q9 -> 0 | R9: mu_H | S9: =ML_Sum!$S9 -> 0 | T9: =ML_Sum!$T9 -> 0
C10: =ML_Sum!$C10 -> 1 | F10: =ML_Sum!$F10 -> 0 | I10: 10 | J10: =ML_Sum!$J10 -> 1 | K10: =ML_Sum!$K10 -> 1 | L10: =ML_Sum!$L10 -> 1 | M10: =ML_Sum!$M10 -> 1 | N10: =ML_Sum!$N10 -> 1 | O10: =ML_Sum!$O10 -> 1 | Q10: =ML_Sum!$Q10 -> 0 | R10: mu_I | S10: =ML_Sum!$S10 -> 0 | T10: =ML_Sum!$T10 -> 0
C11: =ML_Sum!$C11 -> 1 | F11: =ML_Sum!$F11 -> 0 | Q11: =ML_Sum!$Q11 -> 0 | R11: mu_J | S11: =ML_Sum!$S11 -> 0 | T11: =ML_Sum!$T11 -> 0
C12: =ML_Sum!$C12 -> 1 | F12: =ML_Sum!$F12 -> 0 | Q12: =ML_Sum!$Q12 -> 0 | R12: MIXED | S12: =ML_Sum!$S12 -> MAT MU | T12: =ML_Sum!$T12 -> LAB RATE
G13: I_CODE | H13: C_CODE | I13: MAKE | J13: PART_NO | K13: MARKUP | L13: TYPE | M13: LIST_P | N13: P_FACT | O13: FIX | P13: DATE | Q13: %Dsct in BOQ | R13: MU TYPE | S13: MAT MU | T13: LAB RATE
C15: t | D15: Item:
D16: Start Typing Header
Q18: Multip
A19: 1850 | B19: =Elec_Est!B190 -> 0 | D19: 001# 1c x 240sqmm FG160M1 cables | K19: RATE | L19: RATE | Q19: =B19/A19 -> 0 | R19: =IF($B19=0,0,IF($S$1="R",ROUND(R24/$B19,2),R24/$B19)) -> 0 | T19: =IF($B19=0,0,IF($S$1="R",ROUND(T24/$B19,2),T24/$B19)) -> 0
D20: Based on:
D21: 1c x 240sqmm FG160M1 XLPE/LSZH cables from KK2A S/S to Chiller 3 (Quantity 9 cables)
D22: Labour for connecting up in existing switchboards and Chillers
C23: << ==== TOTAL UNITS | R23: =$A23*Q23 -> 0 | T23: =$A23*S23*$T$1 -> 0
A24: d> | B24: =(R24+T24)-SUM(R20:R23,T20:T23) -> 0 | D24: Sell_A | E24: =IF($B19=0,0,ROUND(ROUND(($R24*$S$2+($T24*$T$2))/$B19, 2)*$C$2,2)) -> 0 | F24: =ROUND($B19*$E24,2) -> 0 | K24: ITEM | L24: ITEM | R24: =SUM(R20:R23) -> 0 | T24: =SUM(T20:T23) -> 0
Q25: Multip
A26: 150 | B26: =Elec_Est!B191 -> 30 | D26: 002# 200mm galvanised steel cable tray complete with cover | K26: RATE | L26: RATE | Q26: =B26/A26 -> 0.2 | R26: =IF($B26=0,0,IF($S$1="R",ROUND(R39/$B26,2),R39/$B26)) -> 59.43 | T26: =IF($B26=0,0,IF($S$1="R",ROUND(T39/$B26,2),T39/$B26)) -> 0.81
D27: Based on:
A28: =$Q$26 *(150) -> 30 | B28: m | D28: 200x50mm Tray | F28: Cleveland | G28: TRGV_009 | H28: 650 | I28: (__) | O28: 1 | P28: 36897 | Q28: =1.477*32.11/3 -> 15.808823 | R28: =$A28*Q28 -> 474.2647 | S28: 0.3 | T28: =$A28*S28*$T$1 -> 11.25
A29: =$Q$26 *(150) -> 30 | B29: m | D29: Tray 200mm Galv. Cover | F29: Cleveland | G29: TRGV_057 | H29: 650 | I29: (__) | O29: 1 | Q29: =1.477*48.6/3 -> 23.9274 | R29: =$A29*Q29 -> 717.822 | S29: 0.3 | T29: =$A29*S29*$T$1 -> 11.25
A30: =$Q$26 *(150*2) -> 60 | B30: m | D30: Tray 200mm Galv. Cover clamp | F30: Cleveland | G30: TRGV_057 | H30: 650 | I30: (__) | O30: 1 | Q30: =1.477*2.2 -> 3.2494 | R30: =$A30*Q30 -> 194.964 | T30: =$A30*S30*$T$1 -> 0
A31: =$Q$26 *(150/3) -> 10 | B31: No. | D31: 200x50mm Tray Coupler | F31: Cleveland | H31: 650 | Q31: =1.477*2.48 -> 3.66296 | R31: =$A31*Q31 -> 36.6296 | S31: 0.02 | T31: =$A31*S31*$T$1 -> 0.25
A32: =$Q$26 *(15) -> 3 | B32: m | D32: FLAT BEND | F32: Cleveland | G32: TRGV_057 | H32: 650 | I32: (__) | O32: 1 | Q32: =1.477*26.65 -> 39.36205 | R32: =$A32*Q32 -> 118.08615 | S32: 0.3 | T32: =$A32*S32*$T$1 -> 1.125
A33: 1 | B33: m | D33: EXTERNAL RISER BEND | F33: Cleveland | G33: TRGV_057 | H33: 650 | I33: (__) | O33: 1 | Q33: =1.477*14.91 -> 22.02207 | R33: =$A33*Q33 -> 22.02207 | T33: =$A33*S33*$T$1 -> 0
A34: 1 | B34: m | D34: TEE | F34: Cleveland | G34: TRGV_057 | H34: 650 | I34: (__) | O34: 1 | Q34: =1.477*35.79 -> 52.86183 | R34: =$A34*Q34 -> 52.86183 | S34: 0.3 | T34: =$A34*S34*$T$1 -> 0.375
A35: =$Q$26 *(150/3) -> 10 | B35: No. | D35: Tray Earth Links | F35: Not quoted by Legrand | H35: 650 | Q35: 1.596 | R35: =$A35*Q35 -> 15.96 | S35: 0.01 | T35: =$A35*S35*$T$1 -> 0.125
A36: =$Q$26 *(150*8) -> 240 | B36: No. | D36: Tray Coupling Bolts | F36: Legrand - ESS | H36: 650 | Q36: 0.21 | R36: =$A36*Q36 -> 50.4 | T36: =$A36*S36*$T$1 -> 0
A37: =$Q$26 *(1) -> 0.2 | B37: LS | D37: SUBCONTRACTING WORKS | F37: Crane to carry the materials to the roof | G37: SUBC_001 | H37: 960 | I37: MISC | O37: 4 | P37: 38274 | Q37: 500 | R37: =$A37*Q37 -> 100 | T37: =$A37*S37*$T$1 -> 0
C38: << ==== TOTAL UNITS | R38: =$A38*Q38 -> 0 | T38: =$A38*S38*$T$1 -> 0
A39: d> | B39: =(R38+T38) -> 0 | D39: Sell_A | E39: =IF($B26=0,0,ROUND(ROUND(($R39*$S$2+($T39*$T$2))/$B26, 2)*$C$2,2)) -> 102.18 | F39: =ROUND($B26*$E39,2) -> 3065.4 | K39: ITEM | L39: ITEM | R39: =SUM(R27:R38) -> 1783.0104 | T39: =SUM(T27:T38) -> 24.375
Q40: Multip
A41: 150 | B41: =Elec_Est!B192 -> 30 | D41: 003# Cable Containment Support | K41: RATE | L41: RATE | Q41: =B41/A41 -> 0.2 | R41: =IF($B41=0,0,IF($S$1="R",ROUND(R108/$B41,2),R108/$B41)) -> 71.41 | T41: =IF($B41=0,0,IF($S$1="R",ROUND(T108/$B41,2),T108/$B41)) -> 0.63
D42: Based on: brackets spaced at metres intervals
D43: Supports - HDG - Switch Room | F43: 5 metres Riser | R43: =$A43*Q43 -> 0 | T43: =$A43*S43*$T$1 -> 0 | W43: 2
A44: =$Q$41 *(2) -> 0.4 | B44: m | D44: Channel MT-40 S OC | F44: Hilti | G44: EMAT_019 | H44: 501 | I44: HIL | J44: MS-413m | K44: 02-018 | O44: 1 | P44: 36175 | Q44: 15.65 | R44: =$A44*Q44 -> 6.26 | T44: =$A44*S44*$T$1 -> 0 | W44: 10
A45: =$Q$41 *(10) -> 2 | B45: No. | D45: Channel 40x40 Endcap MT-EC-40/50 | F45: Hilti | H45: 501 | Q45: 0.15 | R45: =$A45*Q45 -> 0.3 | T45: =$A45*S45*$T$1 -> 0 | W45: 10
A46: =$Q$41 *(10) -> 2 | B46: No. | D46: HLC Sleeve Anchor 10mm HLC 10x50/15 | F46: Hilti | H46: 501 | Q46: 0.31 | R46: =$A46*Q46 -> 0.62 | T46: =$A46*S46*$T$1 -> 0 | W46: 10
A47: =$Q$41 *(10) -> 2 | B47: No. | D47: Wing Nut Hilti M8 MQM-M8-F | F47: Hilti | H47: 501 | Q47: 0.66 | R47: =$A47*Q47 -> 1.32 | T47: =$A47*S47*$T$1 -> 0 | W47: 10
A48: =$Q$41 *(10) -> 2 | B48: No. | D48: Hex.Set Screw M8x25 | F48: Hilti | H48: 501 | Q48: 0.05 | R48: =$A48*Q48 -> 0.1 | T48: =$A48*S48*$T$1 -> 0 | W48: 10
A49: =$Q$41 *(10) -> 2 | B49: No. | D49: Galv. Nut 8mm M8-F | F49: Hilti | H49: 501 | Q49: 0.05 | R49: =$A49*Q49 -> 0.1 | T49: =$A49*S49*$T$1 -> 0 | W49: 10
A50: =$Q$41 *(10) -> 2 | B50: No. | D50: Tray Washers M8 | H50: 501 | Q50: 0.01 | R50: =$A50*Q50 -> 0.02 | T50: =$A50*S50*$T$1 -> 0
D51: Supports - HDG - Tunnel | F51: 15 metres Wall | R51: =$A51*Q51 -> 0 | T51: =$A51*S51*$T$1 -> 0 | W51: 7.5
A52: =$Q$41 *(7.5) -> 1.5 | B52: m | D52: Channel MT-40 S OC | F52: Hilti | G52: EMAT_019 | H52: 501 | I52: HIL | J52: MS-413m | K52: 02-018 | O52: 1 | P52: 36175 | Q52: 15.65 | R52: =$A52*Q52 -> 23.475 | T52: =$A52*S52*$T$1 -> 0 | W52: 15
A53: =$Q$41 *(15) -> 3 | B53: No. | D53: Channel 40x40 Endcap MT-EC-40/50 | F53: Hilti | H53: 501 | Q53: 0.15 | R53: =$A53*Q53 -> 0.45 | T53: =$A53*S53*$T$1 -> 0 | W53: 15
A54: =$Q$41 *(15) -> 3 | B54: No. | D54: Channel Base Hilti MT-B-O2-OC | F54: Hilti | H54: 501 | Q54: 14.47 | R54: =$A54*Q54 -> 43.41 | T54: =$A54*S54*$T$1 -> 0 | W54: 60
A55: =$Q$41 *(60) -> 12 | B55: No. | D55: HLC Sleeve Anchor 10mm HLC 10x50/15 | F55: Hilti | H55: 501 | Q55: 0.31 | R55: =$A55*Q55 -> 3.72 | T55: =$A55*S55*$T$1 -> 0 | W55: 60
A56: =$Q$41 *(60) -> 12 | B56: No. | D56: Push Button Hilti M10 MQN-F | F56: Hilti | H56: 501 | Q56: 2.52 | R56: =$A56*Q56 -> 30.24 | T56: =$A56*S56*$T$1 -> 0 | W56: 30
A57: =$Q$41 *(30) -> 6 | B57: No. | D57: Wing Nut Hilti M8 MQM-M8-F | F57: Hilti | H57: 501 | Q57: 0.66 | R57: =$A57*Q57 -> 3.96 | T57: =$A57*S57*$T$1 -> 0 | W57: 30
A58: =$Q$41 *(30) -> 6 | B58: No. | D58: Hex.Set Screw M8x25 | F58: Hilti | H58: 501 | Q58: 0.05 | R58: =$A58*Q58 -> 0.3 | T58: =$A58*S58*$T$1 -> 0 | W58: 30
A59: =$Q$41 *(30) -> 6 | B59: No. | D59: Galv. Nut 8mm M8-F | F59: Hilti | H59: 501 | Q59: 0.05 | R59: =$A59*Q59 -> 0.3 | T59: =$A59*S59*$T$1 -> 0 | W59: 30
A60: =$Q$41 *(30) -> 6 | B60: No. | D60: Tray Washers M8 | H60: 501 | Q60: 0.01 | R60: =$A60*Q60 -> 0.06 | T60: =$A60*S60*$T$1 -> 0
D61: Supports - HDG - Tunnel | F61: 70 metres Ceiling 0.5m height | R61: =$A61*Q61 -> 0 | T61: =$A61*S61*$T$1 -> 0 | W61: 112
A62: =$Q$41 *(112) -> 22.4 | B62: m | D62: Channel MT-40 S OC | F62: Hilti | G62: EMAT_019 | H62: 501 | I62: HIL | J62: MS-413m | K62: 02-018 | O62: 1 | P62: 36175 | Q62: 15.65 | R62: =$A62*Q62 -> 350.56 | T62: =$A62*S62*$T$1 -> 0 | W62: 140
A63: =$Q$41 *(140) -> 28 | B63: No. | D63: Channel 40x40 Endcap MT-EC-40/50 | F63: Hilti | H63: 501 | Q63: 0.15 | R63: =$A63*Q63 -> 4.2 | T63: =$A63*S63*$T$1 -> 0 | W63: 140
A64: =$Q$41 *(140) -> 28 | B64: No. | D64: Angle Hilti 90deg MT-C-LL1 OC | F64: Hilti | H64: 501 | Q64: 5.39 | R64: =$A64*Q64 -> 150.92 | T64: =$A64*S64*$T$1 -> 0 | W64: 140
A65: =$Q$41 *(140) -> 28 | B65: No. | D65: Channel Base Hilti MT-B-O2-OC | F65: Hilti | H65: 501 | Q65: 14.47 | R65: =$A65*Q65 -> 405.16 | T65: =$A65*S65*$T$1 -> 0 | W65: 280
A66: =$Q$41 *(280) -> 56 | B66: No. | D66: HLC Sleeve Anchor 10mm HLC 10x50/15 | F66: Hilti | H66: 501 | Q66: 0.31 | R66: =$A66*Q66 -> 17.36 | T66: =$A66*S66*$T$1 -> 0 | W66: 140
A67: =$Q$41 *(8*70) -> 112 | B67: No. | D67: Push Button Hilti M10 MQN-F | F67: Hilti | H67: 501 | Q67: 2.52 | R67: =$A67*Q67 -> 282.24 | T67: =$A67*S67*$T$1 -> 0 | W67: 30
A68: =$Q$41 *(140) -> 28 | B68: No. | D68: Wing Nut Hilti M8 MQM-M8-F | F68: Hilti | H68: 501 | Q68: 0.66 | R68: =$A68*Q68 -> 18.48 | T68: =$A68*S68*$T$1 -> 0 | W68: 140
A69: =$Q$41 *(140) -> 28 | B69: No. | D69: Hex.Set Screw M8x25 | F69: Hilti | H69: 501 | Q69: 0.05 | R69: =$A69*Q69 -> 1.4 | T69: =$A69*S69*$T$1 -> 0 | W69: 140
A70: =$Q$41 *(140) -> 28 | B70: No. | D70: Galv. Nut 8mm M8-F | F70: Hilti | H70: 501 | Q70: 0.05 | R70: =$A70*Q70 -> 1.4 | T70: =$A70*S70*$T$1 -> 0 | W70: 140
A71: =$Q$41 *(140) -> 28 | B71: No. | D71: Tray Washers M8 | H71: 501 | Q71: 0.01 | R71: =$A71*Q71 -> 0.28 | T71: =$A71*S71*$T$1 -> 0
D72: Supports - HDG - Boiler | F72: 15 metres Ceiling 1.2m height | R72: =$A72*Q72 -> 0 | T72: =$A72*S72*$T$1 -> 0 | W72: 48
A73: =$Q$41 *(48) -> 9.6 | B73: m | D73: Channel MT-40 S OC | F73: Hilti | G73: EMAT_019 | H73: 501 | I73: HIL | J73: MS-413m | K73: 02-018 | O73: 1 | P73: 36175 | Q73: 15.65 | R73: =$A73*Q73 -> 150.24 | T73: =$A73*S73*$T$1 -> 0 | W73: 30
A74: =$Q$41 *(30) -> 6 | B74: No. | D74: Channel 40x40 Endcap MT-EC-40/50 | F74: Hilti | H74: 501 | Q74: 0.15 | R74: =$A74*Q74 -> 0.9 | T74: =$A74*S74*$T$1 -> 0 | W74: 30
A75: =$Q$41 *(30) -> 6 | B75: No. | D75: Angle Hilti 90deg MT-C-LL1 OC | F75: Hilti | H75: 501 | Q75: 5.39 | R75: =$A75*Q75 -> 32.34 | T75: =$A75*S75*$T$1 -> 0 | W75: 30
A76: =$Q$41 *(30) -> 6 | B76: No. | D76: Channel Base Hilti MT-B-O2-OC | F76: Hilti | H76: 501 | Q76: 14.47 | R76: =$A76*Q76 -> 86.82 | T76: =$A76*S76*$T$1 -> 0 | W76: 60
A77: =$Q$41 *(60) -> 12 | B77: No. | D77: HLC Sleeve Anchor 10mm HLC 10x50/15 | F77: Hilti | H77: 501 | Q77: 0.31 | R77: =$A77*Q77 -> 3.72 | T77: =$A77*S77*$T$1 -> 0 | W77: 30
A78: =$Q$41 *(8*15) -> 24 | B78: No. | D78: Push Button Hilti M10 MQN-F | F78: Hilti | H78: 501 | Q78: 2.52 | R78: =$A78*Q78 -> 60.48 | T78: =$A78*S78*$T$1 -> 0 | W78: 30
A79: =$Q$41 *(30) -> 6 | B79: No. | D79: Wing Nut Hilti M8 MQM-M8-F | F79: Hilti | H79: 501 | Q79: 0.66 | R79: =$A79*Q79 -> 3.96 | T79: =$A79*S79*$T$1 -> 0 | W79: 30
A80: =$Q$41 *(30) -> 6 | B80: No. | D80: Hex.Set Screw M8x25 | F80: Hilti | H80: 501 | Q80: 0.05 | R80: =$A80*Q80 -> 0.3 | T80: =$A80*S80*$T$1 -> 0 | W80: 30
A81: =$Q$41 *(30) -> 6 | B81: No. | D81: Galv. Nut 8mm M8-F | F81: Hilti | H81: 501 | Q81: 0.05 | R81: =$A81*Q81 -> 0.3 | T81: =$A81*S81*$T$1 -> 0 | W81: 30
A82: =$Q$41 *(30) -> 6 | B82: No. | D82: Tray Washers M8 | H82: 501 | Q82: 0.01 | R82: =$A82*Q82 -> 0.06 | T82: =$A82*S82*$T$1 -> 0 | AB82: new | AC82: 11250
D83: Supports - HDG - Shaft | F83: 20 metres Riser 0.15m height | R83: =$A83*Q83 -> 0 | T83: =$A83*S83*$T$1 -> 0 | W83: 14 | AB83: old
A84: =$Q$41 *(14) -> 2.8 | B84: m | D84: Channel MT-40 S OC | F84: Hilti | G84: EMAT_019 | H84: 501 | I84: HIL | J84: MS-413m | K84: 02-018 | O84: 1 | P84: 36175 | Q84: 15.65 | R84: =$A84*Q84 -> 43.82 | T84: =$A84*S84*$T$1 -> 0 | W84: 40
A85: =$Q$41 *(40) -> 8 | B85: No. | D85: Channel 40x40 Endcap MT-EC-40/50 | F85: Hilti | H85: 501 | Q85: 0.15 | R85: =$A85*Q85 -> 1.2 | T85: =$A85*S85*$T$1 -> 0 | W85: 40
A86: =$Q$41 *(40) -> 8 | B86: No. | D86: Angle Hilti 90deg MT-C-LL1 OC | F86: Hilti | H86: 501 | Q86: 5.39 | R86: =$A86*Q86 -> 43.12 | T86: =$A86*S86*$T$1 -> 0 | W86: 40
A87: =$Q$41 *(40) -> 8 | B87: No. | D87: Channel Base Hilti MT-B-O2-OC | F87: Hilti | H87: 501 | Q87: 14.47 | R87: =$A87*Q87 -> 115.76 | T87: =$A87*S87*$T$1 -> 0 | W87: 80
A88: =$Q$41 *(80) -> 16 | B88: No. | D88: HLC Sleeve Anchor 10mm HLC 10x50/15 | F88: Hilti | H88: 501 | Q88: 0.31 | R88: =$A88*Q88 -> 4.96 | T88: =$A88*S88*$T$1 -> 0 | W88: 40
A89: =$Q$41 *(8*20) -> 32 | B89: No. | D89: Push Button Hilti M10 MQN-F | F89: Hilti | H89: 501 | Q89: 2.52 | R89: =$A89*Q89 -> 80.64 | T89: =$A89*S89*$T$1 -> 0 | W89: 30
A90: =$Q$41 *(40) -> 8 | B90: No. | D90: Wing Nut Hilti M8 MQM-M8-F | F90: Hilti | H90: 501 | Q90: 0.66 | R90: =$A90*Q90 -> 5.28 | T90: =$A90*S90*$T$1 -> 0 | W90: 40
A91: =$Q$41 *(40) -> 8 | B91: No. | D91: Hex.Set Screw M8x25 | F91: Hilti | H91: 501 | Q91: 0.05 | R91: =$A91*Q91 -> 0.4 | T91: =$A91*S91*$T$1 -> 0 | W91: 40
A92: =$Q$41 *(40) -> 8 | B92: No. | D92: Galv. Nut 8mm M8-F | F92: Hilti | H92: 501 | Q92: 0.05 | R92: =$A92*Q92 -> 0.4 | T92: =$A92*S92*$T$1 -> 0 | W92: 40
A93: =$Q$41 *(40) -> 8 | B93: No. | D93: Tray Washers M8 | H93: 501 | Q93: 0.01 | R93: =$A93*Q93 -> 0.08 | T93: =$A93*S93*$T$1 -> 0
D94: Supports - HDG - Roof | F94: 25 m Roof excluding the structure | R94: =$A94*Q94 -> 0 | T94: =$A94*S94*$T$1 -> 0 | W94: 17
A95: =$Q$41 *(17) -> 3.4 | B95: m | D95: Channel MT-40 S OC | F95: Hilti | G95: EMAT_019 | H95: 501 | I95: HIL | J95: MS-413m | K95: 02-018 | O95: 1 | P95: 36175 | Q95: 15.65 | R95: =$A95*Q95 -> 53.21 | T95: =$A95*S95*$T$1 -> 0 | W95: 30
A96: =$Q$41 *(30) -> 6 | B96: No. | D96: Channel 40x40 Endcap MT-EC-40/50 | F96: Hilti | H96: 501 | Q96: 0.15 | R96: =$A96*Q96 -> 0.9 | T96: =$A96*S96*$T$1 -> 0 | W96: 34
A97: =$Q$41 *(34) -> 6.8 | B97: No. | D97: Angle Hilti 90deg MT-C-LL1 OC | F97: Hilti | H97: 501 | Q97: 5.39 | R97: =$A97*Q97 -> 36.652 | T97: =$A97*S97*$T$1 -> 0 | W97: 16
A98: =$Q$41 *(16) -> 3.2 | B98: No. | D98: Channel Base Hilti MT-B-O2-OC | F98: Hilti | H98: 501 | Q98: 14.47 | R98: =$A98*Q98 -> 46.304 | T98: =$A98*S98*$T$1 -> 0 | W98: 32
A99: =$Q$41 *(32) -> 6.4 | B99: No. | D99: HLC Sleeve Anchor 10mm HLC 10x50/15 | F99: Hilti | H99: 501 | Q99: 0.31 | R99: =$A99*Q99 -> 1.984 | T99: =$A99*S99*$T$1 -> 0 | W99: 38
A100: =$Q$41 *(32) -> 6.4 | B100: No. | D100: Push Button Hilti M10 MQN-F | F100: Hilti | H100: 501 | Q100: 2.52 | R100: =$A100*Q100 -> 16.128 | T100: =$A100*S100*$T$1 -> 0 | W100: 30
A101: =$Q$41 *(38) -> 7.6 | B101: No. | D101: Wing Nut Hilti M8 MQM-M8-F | F101: Hilti | H101: 501 | Q101: 0.66 | R101: =$A101*Q101 -> 5.016 | T101: =$A101*S101*$T$1 -> 0 | W101: 38
A102: =$Q$41 *(38) -> 7.6 | B102: No. | D102: Hex.Set Screw M8x25 | F102: Hilti | H102: 501 | Q102: 0.05 | R102: =$A102*Q102 -> 0.38 | T102: =$A102*S102*$T$1 -> 0 | W102: 38
...

Sheet Elec_Est
B1: CLIENT: | C1: =ML_Sum!$C1 -> 1 | D1: =ML_Sum!$D1 -> ST Microelectronics (Malta) Ltd. | F1: =ML_Sum!$F1 -> 0 | I1: 1 | J1: =ML_Sum!$J1 -> 1 | K1: =ML_Sum!$K1 -> 1 | L1: =ML_Sum!$L1 -> 1 | M1: =ML_Sum!$M1 -> 1 | N1: =ML_Sum!$N1 -> 1 | O1: =ML_Sum!$O1 -> 1 | Q1: =ML_Sum!$Q1 -> € | R1: R/Lab Cont | S1: =ML_Sum!$S1 -> R | T1: =ML_Sum!$T1 -> 1.25 | U1: =ML_Sum!W1 -> BOQ | V1: INCL | W1: MULT | X1: AREA | Y1: BOQ | Z1: TDWG | AA1: ACT | AB1: DIFF
B2: PROJECT: | C2: =ML_Sum!$C2 -> 1 | D2: =ML_Sum!$D2 -> KK2 General Exhaust Replacement | F2: =ML_Sum!$F2 -> Electrical | I2: 2 | J2: =ML_Sum!$J2 -> 1 | K2: =ML_Sum!$K2 -> 1 | L2: =ML_Sum!$L2 -> 1 | M2: =ML_Sum!$M2 -> 1 | N2: =ML_Sum!$N2 -> 1 | O2: =ML_Sum!$O2 -> 1 | Q2: =ML_Sum!$Q2 -> 0 | R2: mu_A | S2: =ML_Sum!$S2 -> 1.25 | T2: =ML_Sum!$T2 -> 34.325
B3: JOB DESC: | C3: =ML_Sum!$C3 -> 1 | D3: =ML_Sum!$D3 -> Electrical Supply and Installation | F3: =ML_Sum!$F3 -> Controls | I3: 3 | J3: =ML_Sum!$J3 -> 1 | K3: =ML_Sum!$K3 -> 1 | L3: =ML_Sum!$L3 -> 1 | M3: =ML_Sum!$M3 -> 1 | N3: =ML_Sum!$N3 -> 1 | O3: =ML_Sum!$O3 -> 1 | Q3: =ML_Sum!$Q3 -> 0 | R3: mu_B | S3: =ML_Sum!$S3 -> 1.25 | T3: =ML_Sum!$T3 -> 34.325
B4: QUOTE No: | C4: =ML_Sum!$C4 -> 1 | D4: =ML_Sum!$D4 -> EL25-0559 | F4: =ML_Sum!$F4 -> 0 | I4: 4 | J4: =ML_Sum!$J4 -> 1 | K4: =ML_Sum!$K4 -> 1 | L4: =ML_Sum!$L4 -> 1 | M4: =ML_Sum!$M4 -> 1 | N4: =ML_Sum!$N4 -> 1 | O4: =ML_Sum!$O4 -> 1 | Q4: =ML_Sum!$Q4 -> 0 | R4: mu_C | S4: =ML_Sum!$S4 -> 0 | T4: =ML_Sum!$T4 -> 0
B5: CLIENTs REF: | C5: =ML_Sum!$C5 -> 1 | D5: =ML_Sum!$D5 -> Tender | F5: =ML_Sum!$F5 -> 0 | I5: 5 | J5: =ML_Sum!$J5 -> 1 | K5: =ML_Sum!$K5 -> 1 | L5: =ML_Sum!$L5 -> 1 | M5: =ML_Sum!$M5 -> 1 | N5: =ML_Sum!$N5 -> 1 | O5: =ML_Sum!$O5 -> 1 | Q5: =ML_Sum!$Q5 -> 0 | R5: mu_D | S5: =ML_Sum!$S5 -> 0 | T5: =ML_Sum!$T5 -> 0
B6: VAT/DUTIES: | C6: =ML_Sum!$C6 -> 1 | D6: =ML_Sum!$D6 -> VAT EXCL. | F6: =ML_Sum!$F6 -> 0 | I6: 6 | J6: =ML_Sum!$J6 -> 1 | K6: =ML_Sum!$K6 -> 1 | L6: =ML_Sum!$L6 -> 1 | M6: =ML_Sum!$M6 -> 1 | N6: =ML_Sum!$N6 -> 1 | O6: =ML_Sum!$O6 -> 1 | Q6: =ML_Sum!$Q6 -> 0 | R6: mu_E | S6: =ML_Sum!$S6 -> 0 | T6: =ML_Sum!$T6 -> 0
B7: SAVED ON: | C7: =ML_Sum!$C7 -> 1 | D7: 39364 | F7: =ML_Sum!$F7 -> 0 | I7: 7 | J7: =ML_Sum!$J7 -> 1 | K7: =ML_Sum!$K7 -> 1 | L7: =ML_Sum!$L7 -> 1 | M7: =ML_Sum!$M7 -> 1 | N7: =ML_Sum!$N7 -> 1 | O7: =ML_Sum!$O7 -> 0 | Q7: =ML_Sum!$Q7 -> 0 | R7: mu_F | S7: =ML_Sum!$S7 -> 0 | T7: =ML_Sum!$T7 -> 0
B8: ESTIMATOR: | C8: =ML_Sum!$C8 -> 1 | D8: =ML_Sum!$D8 -> Umut Kaymak | F8: =ML_Sum!$F8 -> 0 | I8: 8 | J8: =ML_Sum!$J8 -> 1 | K8: =ML_Sum!$K8 -> 1 | L8: =ML_Sum!$L8 -> 1 | M8: =ML_Sum!$M8 -> 1 | N8: =ML_Sum!$N8 -> 1 | O8: =ML_Sum!$O8 -> 0 | Q8: =ML_Sum!$Q8 -> 0 | R8: mu_G | S8: =ML_Sum!$S8 -> 0 | T8: =ML_Sum!$T8 -> 0
B9: LABOUR RATE: | C9: =ML_Sum!$C9 -> 1 | D9: =ML_Sum!$D9 -> 27.46 | F9: =ML_Sum!$F9 -> 0 | I9: 9 | J9: =ML_Sum!$J9 -> 1 | K9: =ML_Sum!$K9 -> 1 | L9: =ML_Sum!$L9 -> 1 | M9: =ML_Sum!$M9 -> 1 | N9: =ML_Sum!$N9 -> 1 | O9: =ML_Sum!$O9 -> 0 | Q9: =ML_Sum!$Q9 -> 0 | R9: mu_H | S9: =ML_Sum!$S9 -> 0 | T9: =ML_Sum!$T9 -> 0
C10: =ML_Sum!$C10 -> 1 | F10: =ML_Sum!$F10 -> 0 | I10: 10 | J10: =ML_Sum!$J10 -> 1 | K10: =ML_Sum!$K10 -> 1 | L10: =ML_Sum!$L10 -> 1 | M10: =ML_Sum!$M10 -> 1 | N10: =ML_Sum!$N10 -> 1 | O10: =ML_Sum!$O10 -> 1 | Q10: =ML_Sum!$Q10 -> 0 | R10: mu_I | S10: =ML_Sum!$S10 -> 0 | T10: =ML_Sum!$T10 -> 0
C11: =ML_Sum!$C11 -> 1 | F11: =ML_Sum!$F11 -> 0 | Q11: =ML_Sum!$Q11 -> 0 | R11: mu_J | S11: =ML_Sum!$S11 -> 0 | T11: =ML_Sum!$T11 -> 0
C12: =ML_Sum!$C12 -> 1 | F12: =ML_Sum!$F12 -> 0 | Q12: =ML_Sum!$Q12 -> 0 | R12: MIXED | S12: =ML_Sum!$S12 -> MAT MU | T12: =ML_Sum!$T12 -> LAB RATE
G13: ISELL | H13: C_CODE | I13: MAKE | J13: PART_NO | K13: MARKUP | L13: TYPE | M13: LIST_P | N13: P_FACT | O13: FIX | P13: DATE | Q13: %Dsct in BOQ | R13: MU TYPE | S13: MAT MU | T13: LAB RATE | AM13: Tot Mat Cost | AN13: Unit Lab phr. | AO13: Tot Lab phr. | AP13: < for ELM / MEE
K14: TB
C15: t | D15: Item:
D16: Cable Tray Supply & Installation
E18: Sell Rate | F18: Sell Total | K18: IB | AG18: U_M_Sell | AH18: T_M_Sell | AI18: U_L_Sell | AJ18: T_L_Sell | AK18: Total_Sell | AM18: T_M_Cost | AN18: T_L_Phr | AO18: Mat/Lab=1
A19: 30 | B19: MT | D19: Item: 1.01 | E19: =IF(AND($A19=0,$A$1="DIF"),0, ROUND(ROUND(($R26*$S$2+($T26*$T$2))/A19,2)*$C$2,2)) -> 212.98 | F19: =ROUND($A19*$E19,2) -> 6389.4 | G19: ISELL | K19: mu_A | L19: ITEM | T19: =IF(AND($R26=0,$T26=0),"0.00","mu :" & ROUND($F19/$C$2/($R26+$T26*$D$9),2)) -> mu :1.25 | AG19: =IF($E19=0,0,ROUND($R26*$S$2*$C$2/$A19,2)) -> 163.55 | AH19: =$AG19*$A19 -> 4906.5 | AI19: =$E19-$AG19 -> 49.43 | AJ19: =$A19*$AI19 -> 1482.9 | AK19: =ROUND(($AG19+$AI19)*$A19,2) -> 6389.4 | AM19: =ROUND(R26,2) -> 3925.2 | AN19: =ROUND(T26,2) -> 43.2 | AO19: =ROUND(AM19+AN19,2)*A19 -> 119052
D20: Hot diped Galvenized Cable tray 200*50mm complete with brackets with lids
C21: h | D21: =CELL("Address",Elec_Rates!D$26) -> [E25_0559_ST_Electronics_Exhaust_Replacement_Est_.xlsx]Elec_Rates!$D$26 | G21: RATE_AAA
A22: 30 | B22: 1 | C22: =$A22*$B22 -> 30 | D22: =Elec_Rates!$D$26 -> 002# 200mm galvanised steel cable tray complete with cover | F22: Local Rate | G22: RTLO_002 | Q22: =$B22*Elec_Rates!$R$26 -> 59.43 | R22: =$A22*Q22 -> 1782.9 | S22: =$B22*Elec_Rates!$T$26 -> 0.81 | T22: =$A22*S22 -> 24.3
C23: h | D23: =CELL("Address",Elec_Rates!D$41) -> [E25_0559_ST_Electronics_Exhaust_Replacement_Est_.xlsx]Elec_Rates!$D$41 | G23: RATE_AAA
A24: 30 | B24: 1 | C24: =$A24*$B24 -> 30 | D24: =Elec_Rates!$D$41 -> 003# Cable Containment Support | F24: Local Rate | G24: RTLO_002 | Q24: =$B24*Elec_Rates!$R$41 -> 71.41 | R24: =$A24*Q24 -> 2142.3 | S24: =$B24*Elec_Rates!$T$41 -> 0.63 | T24: =$A24*S24 -> 18.9
R25: =$A25*Q25 -> 0 | T25: =$A25*S25*$T$1 -> 0
A26: d> | B26: =(R25+T25) -> 0 | G26: ICOST | K26: mu_A | L26: ITEM | R26: =SUM(R20:R25) -> 3925.2 | T26: =SUM(T20:T25) -> 43.2
E27: Sell Rate | F27: Sell Total | K27: IB | AG27: U_M_Sell | AH27: T_M_Sell | AI27: U_L_Sell | AJ27: T_L_Sell | AK27: Total_Sell | AM27: T_M_Cost | AN27: T_L_Phr | AO27: Mat/Lab=1
A28: 1 | B28: LS | D28: Item: 1.02 | E28: =IF(AND($A28=0,$A$1="DIF"),0, ROUND(ROUND(($R32*$S$2+($T32*$T$2))/A28,2)*$C$2,2)) -> 0 | F28: =ROUND($A28*$E28,2) -> 0 | G28: ISELL | K28: mu_A | L28: ITEM | Q28: Included in item 1.01 | T28: =IF(AND($R32=0,$T32=0),"0.00","mu :" & ROUND($F28/$C$2/($R32+$T32*$D$9),2)) -> 0.00 | AG28: =IF($E28=0,0,ROUND($R32*$S$2*$C$2/$A28,2)) -> 0 | AH28: =$AG28*$A28 -> 0 | AI28: =$E28-$AG28 -> 0 | AJ28: =$A28*$AI28 -> 0 | AK28: =ROUND(($AG28+$AI28)*$A28,2) -> 0 | AM28: =ROUND(R32,2) -> 0 | AN28: =ROUND(T32,2) -> 0 | AO28: =ROUND(AM28+AN28,2)*A28 -> 0
D29: Hot Diped galvanized Hilti structures
R31: =$A31*Q31 -> 0 | T31: =$A31*S31*$T$1 -> 0
A32: d> | B32: =(R31+T31) -> 0 | G32: ICOST | K32: mu_A | L32: ITEM | R32: =SUM(R29:R31) -> 0 | T32: =SUM(T29:T31) -> 0
K33: TB
C34: t | D34: Item:
D35: Power Cable Supply, Laying & Wiring
E37: Sell Rate | F37: Sell Total | K37: IB | AG37: U_M_Sell | AH37: T_M_Sell | AI37: U_L_Sell | AJ37: T_L_Sell | AK37: Total_Sell | AM37: T_M_Cost | AN37: T_L_Phr | AO37: Mat/Lab=1
A38: 50 | B38: MT | D38: Item: 1.03 | E38: =IF(AND($A38=0,$A$1="DIF"),0, ROUND(ROUND(($R44*$S$2+($T44*$T$2))/A38,2)*$C$2,2)) -> 24.51 | F38: =ROUND($A38*$E38,2) -> 1225.5 | G38: ISELL | K38: mu_A | L38: ITEM | T38: =IF(AND($R44=0,$T44=0),"0.00","mu :" & ROUND($F38/$C$2/($R44+$T44*$D$9),2)) -> mu :1.25 | AG38: =IF($E38=0,0,ROUND($R44*$S$2*$C$2/$A38,2)) -> 16.44 | AH38: =$AG38*$A38 -> 822 | AI38: =$E38-$AG38 -> 8.07 | AJ38: =$A38*$AI38 -> 403.5 | AK38: =ROUND(($AG38+$AI38)*$A38,2) -> 1225.5 | AM38: =ROUND(R44,2) -> 657.6 | AN38: =ROUND(T44,2) -> 11.75 | AO38: =ROUND(AM38+AN38,2)*A38 -> 33467.5
D39: FG16OM16 0,6/1 Kmtr grn lszh 5g16 MMSQ fg160m1 .6/1V
A40: 50 | B40: m | D40: FG16OM5G016 | E40: 4 circuits | F40: AJ | G40: CAMC_091 | H40: 616 | I40: (__) | J40: 16mm2 | K40: 05-006 | O40: 2 | P40: 38434 | Q40: 10.8 | R40: =$A40*Q40 -> 540 | S40: 0.06 | T40: =$A40*S40*$T$1 -> 3.75
A41: 40 | B41: No | D41: Cable Lug 16 mm2 | G41: CAAC_009 | H41: 620 | I41: CTT | O41: 2 | P41: 34669 | Q41: 0.14 | R41: =$A41*Q41 -> 5.6 | S41: 0.06 | T41: =$A41*S41*$T$1 -> 3
A42: 8 | B42: No | D42: Gland Indoor 32 BWL 4*25/35mm2 | G42: CAAC_044 | H42: 620 | I42: CMP | O42: 2 | P42: 35431 | Q42: 14 | R42: =$A42*Q42 -> 112 | S42: 0.5 | T42: =$A42*S42*$T$1 -> 5
R43: =$A43*Q43 -> 0 | T43: =$A43*S43*$T$1 -> 0
A44: d> | B44: =(R43+T43) -> 0 | G44: ICOST | K44: mu_A | L44: ITEM | R44: =SUM(R39:R43) -> 657.6 | T44: =SUM(T39:T43) -> 11.75
K45: TB
C46: t | D46: Item:
D47: Termination of the Power Cables to Existing MCCs
E49: Sell Rate | F49: Sell Total | K49: IB | AG49: U_M_Sell | AH49: T_M_Sell | AI49: U_L_Sell | AJ49: T_L_Sell | AK49: Total_Sell | AM49: T_M_Cost | AN49: T_L_Phr | AO49: Mat/Lab=1
A50: 2 | B50: No | D50: Item: 2.01 | E50: =IF(AND($A50=0,$A$1="DIF"),0, ROUND(ROUND(($R54*$S$2+($T54*$T$2))/A50,2)*$C$2,2)) -> 42.91 | F50: =ROUND($A50*$E50,2) -> 85.82 | G50: ISELL | K50: mu_A | L50: ITEM | T50: =IF(AND($R54=0,$T54=0),"0.00","mu :" & ROUND($F50/$C$2/($R54+$T54*$D$9),2)) -> mu :1.25 | AG50: =IF($E50=0,0,ROUND($R54*$S$2*$C$2/$A50,2)) -> 0 | AH50: =$AG50*$A50 -> 0 | AI50: =$E50-$AG50 -> 42.91 | AJ50: =$A50*$AI50 -> 85.82 | AK50: =ROUND(($AG50+$AI50)*$A50,2) -> 85.82 | AM50: =ROUND(R54,2) -> 0 | AN50: =ROUND(T54,2) -> 2.5 | AO50: =ROUND(AM50+AN50,2)*A50 -> 5
D51: Termination of the FG16OM16 0,6/1 Kmtr grn lszh 5g16 MMSQ fg160m1 .6/1V Cable to Existing MCCs
A52: 2 | B52: No | D52: Cable Termination only | G52: LABO_001 | H52: 900 | I52: MISC | O52: 1 | Q52: 0 | R52: =$A52*Q52 -> 0 | S52: 1 | T52: =$A52*S52*$T$1 -> 2.5
R53: =$A53*Q53 -> 0 | T53: =$A53*S53*$T$1 -> 0
A54: d> | B54: =(R53+T53) -> 0 | G54: ICOST | K54: mu_A | L54: ITEM | R54: =SUM(R51:R53) -> 0 | T54: =SUM(T51:T53) -> 2.5
K55: TB
C56: t | D56: Item:
D57: Dismantling Existing Distribution Board
E59: Sell Rate | F59: Sell Total | K59: IB | AG59: U_M_Sell | AH59: T_M_Sell | AI59: U_L_Sell | AJ59: T_L_Sell | AK59: Total_Sell | AM59: T_M_Cost | AN59: T_L_Phr | AO59: Mat/Lab=1
A60: 1 | B60: LS | D60: Item: 2.01 | E60: =IF(AND($A60=0,$A$1="DIF"),0, ROUND(ROUND(($R64*$S$2+($T64*$T$2))/A60,2)*$C$2,2)) -> 257.44 | F60: =ROUND($A60*$E60,2) -> 257.44 | G60: ISELL | K60: mu_A | L60: ITEM | T60: =IF(AND($R64=0,$T64=0),"0.00","mu :" & ROUND($F60/$C$2/($R64+$T64*$D$9),2)) -> mu :1.25 | AG60: =IF($E60=0,0,ROUND($R64*$S$2*$C$2/$A60,2)) -> 0 | AH60: =$AG60*$A60 -> 0 | AI60: =$E60-$AG60 -> 257.44 | AJ60: =$A60*$AI60 -> 257.44 | AK60: =ROUND(($AG60+$AI60)*$A60,2) -> 257.44 | AM60: =ROUND(R64,2) -> 0 | AN60: =ROUND(T64,2) -> 7.5 | AO60: =ROUND(AM60+AN60,2)*A60 -> 7.5
D61: Dismantling the existing Board
A62: 1 | B62: LS | D62: Dismantling the Existing Board | G62: LABO_001 | H62: 900 | I62: MISC | O62: 1 | R62: =$A62*Q62 -> 0 | S62: 6 | T62: =$A62*S62*$T$1 -> 7.5
R63: =$A63*Q63 -> 0 | T63: =$A63*S63*$T$1 -> 0
A64: d> | B64: =(R63+T63) -> 0 | G64: ICOST | K64: mu_A | L64: ITEM | R64: =SUM(R61:R63) -> 0 | T64: =SUM(T61:T63) -> 7.5
E65: Sell Rate | F65: Sell Total | K65: IB | AG65: U_M_Sell | AH65: T_M_Sell | AI65: U_L_Sell | AJ65: T_L_Sell | AK65: Total_Sell | AM65: T_M_Cost | AN65: T_L_Phr | AO65: Mat/Lab=1
A66: 1 | B66: LS | D66: Item: 2.02 | E66: =IF(AND($A66=0,$A$1="DIF"),0, ROUND(ROUND(($R70*$S$2+($T70*$T$2))/A66,2)*$C$2,2)) -> 171.63 | F66: =ROUND($A66*$E66,2) -> 171.63 | G66: ISELL | K66: mu_A | L66: ITEM | T66: =IF(AND($R70=0,$T70=0),"0.00","mu :" & ROUND($F66/$C$2/($R70+$T70*$D$9),2)) -> mu :1.25 | AG66: =IF($E66=0,0,ROUND($R70*$S$2*$C$2/$A66,2)) -> 0 | AH66: =$AG66*$A66 -> 0 | AI66: =$E66-$AG66 -> 171.63 | AJ66: =$A66*$AI66 -> 171.63 | AK66: =ROUND(($AG66+$AI66)*$A66,2) -> 171.63 | AM66: =ROUND(R70,2) -> 0 | AN66: =ROUND(T70,2) -> 5 | AO66: =ROUND(AM66+AN66,2)*A66 -> 5
D67: Terminating the Dismantled cables to existing control panel adjacent to distribution board
A68: 1 | B68: LS | D68: Termination of 3 x 5x16 cable | G68: LABO_001 | H68: 900 | I68: MISC | O68: 1 | R68: =$A68*Q68 -> 0 | S68: 4 | T68: =$A68*S68*$T$1 -> 5
R69: =$A69*Q69 -> 0 | T69: =$A69*S69*$T$1 -> 0
A70: d> | B70: =(R69+T69) -> 0 | G70: ICOST | K70: mu_A | L70: ITEM | R70: =SUM(R67:R69) -> 0 | T70: =SUM(T67:T69) -> 5
K71: TB
C72: t | D72: Item:
D73: VRFs Supply and Installation
E75: Sell Rate | F75: Sell Total | K75: IB | AG75: U_M_Sell | AH75: T_M_Sell | AI75: U_L_Sell | AJ75: T_L_Sell | AK75: Total_Sell | AM75: T_M_Cost | AN75: T_L_Phr | AO75: Mat/Lab=1
A76: 2 | B76: No | D76: Item: 3.01 | E76: =IF(AND($A76=0,$A$1="DIF"),0, ROUND(ROUND(SUMIF($L78:$L86,"SUBI",$E78:$E86)/$A76,2)*$C$12,2)) -> 2178.22 | F76: =ROUND($A76*$E76,2) -> 4356.44 | G76: ISELL | L76: ITEM | T76: =IF(AND($R91=0,$T91=0),"0.00","mu :" & ROUND($F76/$C$12/($R91+$T91*$D$9),2)) -> mu :1.25 | AG76: =IF(A76=0,0,ROUND(SUM(AG78:AG91)/A76,2)) -> 1644 | AH76: =$AG76*$A76 -> 3288 | AI76: =$E76-$AG76 -> 534.22 | AJ76: =$A76*$AI76 -> 1068.44 | AK76: =ROUND(($AG76+$AI76)*$A76,2) -> 4356.44 | AM76: =ROUND(R91,2) -> 2630.4 | AN76: =ROUND(T91,2) -> 31.13 | AO76: =ROUND(AM76+AN76,2)*A76 -> 5323.06
D77: Supply and Install VRFs | K77: n
E78: =F76/$C$12-SUMIF($L75:$L91,"SUBI",$E75:$E91) -> 0.01 | F78: Discrepancy
D79: =$F$2 -> Electrical | E79: =ROUND(($R85*$S$2 + ($T85*$T$2)), 2) -> 370.74 | F79: =$E79*$C$12 -> 370.74 | K79: mu_A | L79: SUBI
B80: >>> mu_A material here >>> | R80: =$A80*Q80 -> 0 | T80: =$A80*S80*$T$1 -> 0
A81: 2 | B81: No | D81: VRF Installation Only | G81: BMSE_001 | H81: 512 | I81: (__) | O81: 3 | Q81: 0 | R81: =$A81*Q81 -> 0 | S81: 3 | T81: =$A81*S81*$T$1 -> 7.5
A82: 2 | B82: No | D82: VRF Termination Only | G82: BMSE_001 | H82: 512 | I82: (__) | O82: 3 | Q82: 0 | R82: =$A82*Q82 -> 0 | S82: 1 | T82: =$A82*S82*$T$1 -> 2.5
A83: 10 | B83: No | D83: Cable Lug 16 mm2 | G83: CAAC_009 | H83: 620 | I83: CTT | O83: 2 | P83: 34669 | Q83: 0.14 | R83: =$A83*Q83 -> 1.4 | S83: 0.06 | T83: =$A83*S83*$T$1 -> 0.75
R84: =$A84*Q84 -> 0 | T84: =$A84*S84*$T$1 -> 0
A85: d> | B85: =(R84+T84) -> 0 | K85: mu_A | L85: SUBI | R85: =SUM(R79:R84) -> 1.4 | T85: =SUM(T79:T84) -> 10.75 | AG85: =ROUND($R85*$S$2,2) -> 1.75
D86: =$F$3 -> Controls | E86: =ROUND(($R89*$S$3 + ($T89*$T$3)), 2) -> 3985.69 | F86: =$F76-SUMIF($L78:$P83,"SUBI",$F78:$F83) -> 3985.7 | K86: mu_B | L86: SUBI
A87: 2 | B87: No | D87: VRF | G87: BMSE_001 | H87: 512 | I87: (__) | O87: 3 | Q87: =2629/2 -> 1314.5 | R87: =$A87*Q87 -> 2629 | S87: =4*35/27.46+2*41.91/27.46 -> 8.1507647 | T87: =$A87*S87*$T$1 -> 20.376912
R88: =$A88*Q88 -> 0 | T88: =$A88*S88*$T$1 -> 0
A89: d> | B89: =(R88+T88) -> 0 | K89: mu_B | L89: SUBI | R89: =SUM(R86:R88) -> 2629 | T89: =SUM(T86:T88) -> 20.376912 | AG89: =ROUND($R89*$S$3,2) -> 3286.25
G91: ICOST | L91: ITEM | R91: =SUMIF($L77:$L90,"SUBI",R77:R90) -> 2630.4 | T91: =SUMIF($L77:$L90,"SUBI",T77:T90) -> 31.126912
A92: SB
B94: =$F94/$C$2-($R94*$S$2+$T94*$T$2) -> 0.265 | D94: PAGE: | F94: =SUMIF($L14:$L92,"ITEM",F14:F92) -> 12486.23 | L94: PAGE | R94: =SUMIF($L14:$L92,"ITEM",R14:R92) -> 7213.2 | T94: =SUMIF($L14:$L92,"ITEM",T14:T92) -> 101.07691
B95: Discy: | F95: PAGE SELL | R95: PAGE MAT | T95: PAGE LAB
A98: SB
B100: =$F100/$C$2-($R100*$S$2+$T100*$T$2) -> 0.265 | D100: TOTAL FOR ADDITIONAL ITEMS | F100: =SUMIF($L92:$L98,"PAGE",F92:F98) -> 12486.23 | L100: SECT | R100: =SUMIF($L92:$L98,"PAGE",R92:R98) -> 7213.2 | T100: =SUMIF($L92:$L98,"PAGE",T92:T98) -> 101.07691
B101: Discy: | F101: SECT SELL | R101: SECT MAT | T101: SECT LAB
A104: SB! | AH104: =SUM(#REF!) -> #REF! | AJ104: =SUM(#REF!) -> #REF! | AK104: =SUM(#REF!) -> #REF!
B105: =$F105/$C$2-($R105*$S$2+$T105*$T$2) -> 0.2525 | C105: cc | E105: =$F$2 & " (mu_A) :" -> Electrical (mu_A) : | F105: =SUMIF($K$13:$K104,"mu_A",F$13:F104) -> 8500.53 | R105: =SUMIF($K$13:$K104,"mu_A",R$13:R$104) -> 4584.2 | T105: =SUMIF($K$13:$K104,"mu_A",T$13:T$104) -> 80.7 | AH105: =R105*$S$2 -> 5730.25 | AJ105: =T105*$T$2 -> 2770.0275
B106: =$F106/$C$3-($R106*$S$3+$T106*$T$3) -> 0.0125 | C106: cc | E106: =$F$3& " (mu_B) :" -> Controls (mu_B) : | F106: =SUMIF($K$13:$K104,"mu_B",F$13:F104) -> 3985.7 | R106: =SUMIF($K$13:$K104,"mu_B",R$13:R104) -> 2629 | T106: =SUMIF($K$13:$K104,"mu_B",T$13:T104) -> 20.376912 | AH106: =R106*$S$3 -> 3286.25 | AJ106: =T106*$T$3 -> 699.4375
B107: =$F107/$C$4-($R107*$S$4+$T107*$T$4) -> 0 | C107: cc | E107: =$F$4& " (mu_C) :" -> 0 (mu_C) : | F107: =SUMIF($K$13:$K104,"mu_C",F$13:F104) -> 0 | R107: =SUMIF($K$13:$K104,"mu_C",R$13:R104) -> 0 | T107: =SUMIF($K$13:$K104,"mu_C",T$13:T104) -> 0 | AH107: =R107*$S$4 -> 0 | AJ107: =T107*$T$4 -> 0
B108: =$F108/$C$5-($R108*$S$5+$T108*$T$5) -> 0 | C108: cc | E108: =$F$5& " (mu_D) :" -> 0 (mu_D) : | F108: =SUMIF($K$13:$K104,"mu_D",F$13:F104) -> 0 | R108: =SUMIF($K$13:$K104,"mu_D",R$13:R104) -> 0 | T108: =SUMIF($K$13:$K104,"mu_D",T$13:T104) -> 0 | AH108: =R108*$S$5 -> 0 | AJ108: =T108*$T$5 -> 0
B109: =$F109/$C$6-($R109*$S$6+$T109*$T$6) -> 0 | C109: cc | E109: =$F$6& " (mu_E) :" -> 0 (mu_E) : | F109: =SUMIF($K$13:$K104,"mu_E",F$13:F104) -> 0 | R109: =SUMIF($K$13:$K104,"mu_E",R$13:R104) -> 0 | T109: =SUMIF($K$13:$K104,"mu_E",T$13:T104) -> 0 | AH109: =R109*$S$6 -> 0 | AJ109: =T109*$T$6 -> 0
B110: =$F110/$C$7-($R110*$S$7+$T110*$T$7) -> 0 | C110: cc | E110: =$F$7& " (mu_F) :" -> 0 (mu_F) : | F110: =SUMIF($K$13:$K104,"mu_F",F$13:F104) -> 0 | R110: =SUMIF($K$13:$K104,"mu_F",R$13:R104) -> 0 | T110: =SUMIF($K$13:$K104,"mu_F",T$13:T104) -> 0 | AH110: =R110*$S$7 -> 0 | AJ110: =T110*$T$7 -> 0
B111: =$F111/$C$8-($R111*$S$8+$T111*$T$8) -> 0 | C111: cc | E111: =$F$8& " (mu_G) :" -> 0 (mu_G) : | F111: =SUMIF($K$13:$K104,"mu_G",F$13:F104) -> 0 | R111: =SUMIF($K$13:$K104,"mu_G",R$13:R104) -> 0 | T111: =SUMIF($K$13:$K104,"mu_G",T$13:T104) -> 0 | AH111: =R111*$S$8 -> 0 | AJ111: =T111*$T$8 -> 0
B112: =$F112/$C$9-($R112*$S$9+$T112*$T$9) -> 0 | C112: cc | E112: =$F$9& " (mu_H) :" -> 0 (mu_H) : | F112: =SUMIF($K$13:$K104,"mu_H",F$13:F104) -> 0 | R112: =SUMIF($K$13:$K104,"mu_H",R$13:R104) -> 0 | T112: =SUMIF($K$13:$K104,"mu_H",T$13:T104) -> 0 | AH112: =R112*$S$9 -> 0 | AJ112: =T112*$T$9 -> 0
B113: =$F113/$C$10-($R113*$S$10+$T113*$T$10) -> 0 | C113: cc | E113: =$F$10& " (mu_I) :" -> 0 (mu_I) : | F113: =SUMIF($K$13:$K104,"mu_I",F$13:F104) -> 0 | R113: =SUMIF($K$13:$K104,"mu_I",R$13:R104) -> 0 | T113: =SUMIF($K$13:$K104,"mu_I",T$13:T104) -> 0 | AH113: =R113*$S$10 -> 0 | AJ113: =T113*$T$10 -> 0
...

Sheet E_BOQ
A1: ITEM NO. | B1: DESCRIPTION | C1: QTY | D1: UNIT | E1: RATE | F1: TOTAL
E2: € | F2: €
A3: =TRIM(MID(Elec_Est!D15,6,30)) | B3: =Elec_Est!D16 -> Cable Tray Supply & Installation
A5: =TRIM(MID(Elec_Est!D19,6,30)) -> 1.01 | B5: =Elec_Est!D20 -> Hot diped Galvenized Cable tray 200*50mm complete with brackets with lids | C5: =Elec_Est!A19 -> 30 | D5: =Elec_Est!B19 -> MT | E5: =Elec_Est!E19 -> 212.98 | F5: =C5*E5 -> 6389.4
A7: =TRIM(MID(Elec_Est!D28,6,30)) -> 1.02 | B7: =Elec_Est!D29 -> Hot Diped galvanized Hilti structures | C7: =Elec_Est!A28 -> 1 | D7: =Elec_Est!B28 -> LS | E7: =Elec_Est!E28 -> 0 | F7: =C7*E7 -> 0
A10: =TRIM(MID(Elec_Est!D34,6,30)) | B10: =Elec_Est!D35 -> Power Cable Supply, Laying & Wiring
A12: =TRIM(MID(Elec_Est!D38,6,30)) -> 1.03 | B12: =Elec_Est!D39 -> FG16OM16 0,6/1 Kmtr grn lszh 5g16 MMSQ fg160m1 .6/1V | C12: =Elec_Est!A38 -> 50 | D12: =Elec_Est!B38 -> MT | E12: =Elec_Est!E38 -> 24.51 | F12: =C12*E12 -> 1225.5
A15: =TRIM(MID(Elec_Est!D46,6,30)) | B15: =Elec_Est!D47 -> Termination of the Power Cables to Existing MCCs
A17: =TRIM(MID(Elec_Est!D50,6,30)) -> 2.01 | B17: =Elec_Est!D51 -> Termination of the FG16OM16 0,6/1 Kmtr grn lszh 5g16 MMSQ fg160m1 .6/1V Cable to Existing MCCs | C17: =Elec_Est!A50 -> 2 | D17: =Elec_Est!B50 -> No | E17: =Elec_Est!E50 -> 42.91 | F17: =C17*E17 -> 85.82
A20: =TRIM(MID(Elec_Est!D56,6,30)) | B20: =Elec_Est!D57 -> Dismantling Existing Distribution Board
A22: =TRIM(MID(Elec_Est!D60,6,30)) -> 2.01 | B22: =Elec_Est!D61 -> Dismantling the existing Board | C22: =Elec_Est!A60 -> 1 | D22: =Elec_Est!B60 -> LS | E22: =Elec_Est!E60 -> 257.44 | F22: =C22*E22 -> 257.44
A24: =TRIM(MID(Elec_Est!D66,6,30)) -> 2.02 | B24: =Elec_Est!D67 -> Terminating the Dismantled cables to existing control panel adjacent to distribution board | C24: =Elec_Est!A66 -> 1 | D24: =Elec_Est!B66 -> LS | E24: =Elec_Est!E66 -> 171.63 | F24: =C24*E24 -> 171.63
A27: =TRIM(MID(Elec_Est!D72,6,30)) | B27: =Elec_Est!D73 -> VRFs Supply and Installation
A29: =TRIM(MID(Elec_Est!D76,6,30)) -> 3.01 | B29: =Elec_Est!D77 -> Supply and Install VRFs | C29: =Elec_Est!A76 -> 2 | D29: =Elec_Est!B76 -> No | E29: =Elec_Est!E76 -> 2178.22 | F29: =C29*E29 -> 4356.44
A48: SB | B48: Total - | D48: =[16]ML_Sum!D6 -> VAT EXCL. | E48: € | F48: =SUM(F4:F47) -> 12486.23
