Workbook
Name Access_Control: [1]Elec_Est!#REF!
Name AREAS: [1]ML_Sum!$X$1:$AD$16
Name AREAS: ML_Sum!$X$1:$AD$16
Name CCTV: [1]Elec_Est!#REF!
Name Data: [1]Elec_Est!#REF!
Name Fire_Alarm: [1]Elec_Est!#REF!
Name FO: [1]Elec_Est!#REF!
Name Guard: [1]Elec_Est!#REF!
Name Intercom: [1]Elec_Est!#REF!
Name Intruder_Alarm: [1]Elec_Est!#REF!

Sheet Notes
A1: NOTES
A3: 1 | B3: BOQ Item 6.001 | C3: We have allowed to connect the Fan to a 13A DP Fused Outlet included in the electrical BOQ.
A5: 2 | B5: BOQ Item 6.002 | C5: We have allowed to connect the Damper to a 13A DP Fused Outlet included in the electrical BOQ. The control wiring installation is included in the REMS BOQ.
A7: 3 | B7: BOQ Item 6.008 | C7: The wiring and programming are included within the REMS BOQ
A9: 4 | B9: BOQ Item 6.009 | C9: We have allowed to connect the Fan to a 13A DP Fused Outlet included in the electrical BOQ. The control wiring installation is included in the REMS BOQ,. Whilst, the Fan Time OFF delay can be achived by the REMS logic controller.
A11: 5 | B11: BOQ Items 7.002 & 7.005 | C11: We have allowed for an empty conduit between the AC Indoor units and the room temperature/fan speed controller.
A13: 6 | B13: BOQ Item 7.007 | C13: The AC Connecting up and control wiring installation, are excluded.

Sheet Elec_Est
B1: CLIENT: | C1: =ML_Sum!$C1 -> 1 | D1: =ML_Sum!$D1 -> SUNCREST HOTELS plc | F1: =ML_Sum!$F1 -> 0 | I1: 1 | J1: =ML_Sum!$J1 -> 1 | K1: =ML_Sum!$K1 -> 1 | L1: =ML_Sum!$L1 -> 1 | M1: =ML_Sum!$M1 -> 1 | N1: =ML_Sum!$N1 -> 1 | O1: =ML_Sum!$O1 -> 1 | Q1: =ML_Sum!$Q1 -> € | R1: R/Lab Cont | S1: =ML_Sum!$S1 -> R | T1: =ML_Sum!$T1 -> 1 | U1: =ML_Sum!W1 -> BOQ | V1: INCL | W1: MULT | X1: AREA | Y1: BOQ | Z1: TDWG | AA1: ACT | AB1: DIFF
B2: PROJECT: | C2: =ML_Sum!$C2 -> 1 | D2: =ML_Sum!$D2 -> Sunny Cost and Lido Redevelopment | F2: =ML_Sum!$F2 -> Electrical | I2: 2 | J2: =ML_Sum!$J2 -> 1 | K2: =ML_Sum!$K2 -> 1 | L2: =ML_Sum!$L2 -> 1 | M2: =ML_Sum!$M2 -> 1 | N2: =ML_Sum!$N2 -> 1 | O2: =ML_Sum!$O2 -> 1 | Q2: =ML_Sum!$Q2 -> 0 | R2: mu_A | S2: =ML_Sum!$S2 -> 1.3 | T2: =ML_Sum!$T2 -> 35.698
B3: JOB DESC: | C3: =ML_Sum!$C3 -> 1 | D3: =ML_Sum!$D3 -> Sample Room - Electrical for Mechanical | F3: =ML_Sum!$F3 -> Controls Section (Guy) | I3: 3 | J3: =ML_Sum!$J3 -> 1 | K3: =ML_Sum!$K3 -> 1 | L3: =ML_Sum!$L3 -> 1 | M3: =ML_Sum!$M3 -> 1 | N3: =ML_Sum!$N3 -> 1 | O3: =ML_Sum!$O3 -> 1 | Q3: =ML_Sum!$Q3 -> 0 | R3: mu_B | S3: =ML_Sum!$S3 -> 1.3 | T3: =ML_Sum!$T3 -> 35.698
B4: QUOTE No: | C4: =ML_Sum!$C4 -> 1 | D4: =ML_Sum!$D4 -> ELM25-0699 | F4: =ML_Sum!$F4 -> 0 | I4: 4 | J4: =ML_Sum!$J4 -> 1 | K4: =ML_Sum!$K4 -> 1 | L4: =ML_Sum!$L4 -> 1 | M4: =ML_Sum!$M4 -> 1 | N4: =ML_Sum!$N4 -> 1 | O4: =ML_Sum!$O4 -> 1 | Q4: =ML_Sum!$Q4 -> 0 | R4: mu_C | S4: =ML_Sum!$S4 -> 0 | T4: =ML_Sum!$T4 -> 0
B5: CLIENTs REF: | C5: =ML_Sum!$C5 -> 1 | D5: =ML_Sum!$D5 -> Sample Room | F5: =ML_Sum!$F5 -> 0 | I5: 5 | J5: =ML_Sum!$J5 -> 1 | K5: =ML_Sum!$K5 -> 1 | L5: =ML_Sum!$L5 -> 1 | M5: =ML_Sum!$M5 -> 1 | N5: =ML_Sum!$N5 -> 1 | O5: =ML_Sum!$O5 -> 1 | Q5: =ML_Sum!$Q5 -> 0 | R5: mu_D | S5: =ML_Sum!$S5 -> 0 | T5: =ML_Sum!$T5 -> 0
B6: VAT/DUTIES: | C6: =ML_Sum!$C6 -> 1 | D6: =ML_Sum!$D6 -> VAT EXCL. | F6: =ML_Sum!$F6 -> 0 | I6: 6 | J6: =ML_Sum!$J6 -> 1 | K6: =ML_Sum!$K6 -> 1 | L6: =ML_Sum!$L6 -> 1 | M6: =ML_Sum!$M6 -> 1 | N6: =ML_Sum!$N6 -> 1 | O6: =ML_Sum!$O6 -> 1 | Q6: =ML_Sum!$Q6 -> 0 | R6: mu_E | S6: =ML_Sum!$S6 -> 0 | T6: =ML_Sum!$T6 -> 0
B7: SAVED ON: | C7: =ML_Sum!$C7 -> 1 | D7: 39364 | F7: =ML_Sum!$F7 -> 0 | I7: 7 | J7: =ML_Sum!$J7 -> 1 | K7: =ML_Sum!$K7 -> 1 | L7: =ML_Sum!$L7 -> 1 | M7: =ML_Sum!$M7 -> 1 | N7: =ML_Sum!$N7 -> 1 | O7: =ML_Sum!$O7 -> 0 | Q7: =ML_Sum!$Q7 -> 0 | R7: mu_F | S7: =ML_Sum!$S7 -> 0 | T7: =ML_Sum!$T7 -> 0
B8: ESTIMATOR: | C8: =ML_Sum!$C8 -> 1 | D8: =ML_Sum!$D8 -> R.Farrugia | F8: =ML_Sum!$F8 -> 0 | I8: 8 | J8: =ML_Sum!$J8 -> 1 | K8: =ML_Sum!$K8 -> 1 | L8: =ML_Sum!$L8 -> 1 | M8: =ML_Sum!$M8 -> 1 | N8: =ML_Sum!$N8 -> 1 | O8: =ML_Sum!$O8 -> 0 | Q8: =ML_Sum!$Q8 -> 0 | R8: mu_G | S8: =ML_Sum!$S8 -> 0 | T8: =ML_Sum!$T8 -> 0
B9: LABOUR RATE: | C9: =ML_Sum!$C9 -> 1 | D9: =ML_Sum!$D9 -> 27.46 | F9: =ML_Sum!$F9 -> 0 | I9: 9 | J9: =ML_Sum!$J9 -> 1 | K9: =ML_Sum!$K9 -> 1 | L9: =ML_Sum!$L9 -> 1 | M9: =ML_Sum!$M9 -> 1 | N9: =ML_Sum!$N9 -> 1 | O9: =ML_Sum!$O9 -> 0 | Q9: =ML_Sum!$Q9 -> 0 | R9: mu_H | S9: =ML_Sum!$S9 -> 0 | T9: =ML_Sum!$T9 -> 0
C10: =ML_Sum!$C10 -> 1 | F10: =ML_Sum!$F10 -> 0 | I10: 10 | J10: =ML_Sum!$J10 -> 1 | K10: =ML_Sum!$K10 -> 1 | L10: =ML_Sum!$L10 -> 1 | M10: =ML_Sum!$M10 -> 1 | N10: =ML_Sum!$N10 -> 1 | O10: =ML_Sum!$O10 -> 1 | Q10: =ML_Sum!$Q10 -> 0 | R10: mu_I | S10: =ML_Sum!$S10 -> 0 | T10: =ML_Sum!$T10 -> 0
C11: =ML_Sum!$C11 -> 1 | F11: =ML_Sum!$F11 -> 0 | Q11: =ML_Sum!$Q11 -> 0 | R11: mu_J | S11: =ML_Sum!$S11 -> 0 | T11: =ML_Sum!$T11 -> 0
C12: =ML_Sum!$C12 -> 1 | F12: =ML_Sum!$F12 -> 0 | Q12: =ML_Sum!$Q12 -> 0 | R12: MIXED | S12: =ML_Sum!$S12 -> MAT MU | T12: =ML_Sum!$T12 -> LAB RATE
G13: ISELL | H13: C_CODE | I13: MAKE | J13: PART_NO | K13: MARKUP | L13: TYPE | M13: LIST_P | N13: P_FACT | O13: FIX | P13: DATE | Q13: %Dsct in BOQ | R13: MU TYPE | S13: MAT MU | T13: LAB RATE | AM13: Tot Mat Cost | AN13: Unit Lab phr. | AO13: Tot Lab phr. | AP13: < for ELM / MEE
K14: TB
C15: t | D15: Item:
D16: VENTILATION INSTALLATION
K18: TB
C19: t | D19: Item:
D20: SF 01 [Delta P to be as per selected accessories] for bedroom
E22: Sell Rate | F22: Sell Total | K22: IB | AG22: U_M_Sell | AH22: T_M_Sell | AI22: U_L_Sell | AJ22: T_L_Sell | AK22: Total_Sell | AM22: T_M_Cost | AN22: U_L_Phr | AO22: T_L_Phr | AP22: Mat/Lab=1
A23: 1 | B23: LS | D23: Item: 6.001 | E23: =IF(AND($A23=0,$A$1="DIF"),0, ROUND(ROUND(($R28*$S$2+($T28*$T$2))/A23,2)*$C$2,2)) -> 24.28 | F23: =ROUND($A23*$E23,2) -> 24.28 | G23: ISELL | K23: mu_A | L23: ITEM | T23: =IF(AND($R28=0,$T28=0),"0.00","mu :" & ROUND($F23/$C$2/($R28+$T28*$D$9),2)) -> mu :1.3 | AG23: =IF($E23=0,0,ROUND($R28*$S$2*$C$2/$A23,2)) -> 2.86 | AH23: =$AG23*$A23 -> 2.86 | AI23: =$E23-$AG23 -> 21.42 | AJ23: =$A23*$AI23 -> 21.42 | AK23: =ROUND(($AG23+$AI23)*$A23,2) -> 24.28 | AM23: =ROUND(R28,2) -> 2.2 | AN23: =IF(A23=0,0,AO23/A23) -> 0.6 | AO23: =ROUND(T28,2) -> 0.6 | AP23: =ROUND(AM23+AO23,2)*A23 -> 2.8
D24: 30 litres/sec mixed flow fan including electrical connection to double pole provided, complete. Fan to be very silent with silencers if required | K24: n
A25: 2 | B25: m | D25: Wiring Cable 3c 1.5 mm2 PVC Non-Arm | G25: CASC_017 | H25: 615 | I25: CRO | K25: 02-002 | O25: 2 | P25: 38988 | Q25: 1.1 | R25: =$A25*Q25 -> 2.2 | S25: 0.05 | T25: =$A25*S25*$T$1 -> 0.1
A26: 1 | B26: No | D26: Labour to connect Mech Equip (SF01) | G26: LABO_009 | H26: 900 | I26: MISC | O26: 1 | Q26: 0 | R26: =$A26*Q26 -> 0 | S26: 0.5 | T26: =$A26*S26*$T$1 -> 0.5
R27: =$A27*Q27 -> 0 | T27: =$A27*S27*$T$1 -> 0
A28: d> | B28: =(R27+T27) -> 0 | G28: ICOST | K28: mu_A | L28: ITEM | R28: =SUM(R24:R27) -> 2.2 | T28: =SUM(T24:T27) -> 0.6
E29: Sell Rate | F29: Sell Total | K29: IB | AG29: U_M_Sell | AH29: T_M_Sell | AI29: U_L_Sell | AJ29: T_L_Sell | AK29: Total_Sell | AM29: T_M_Cost | AN29: U_L_Phr | AO29: T_L_Phr | AP29: Mat/Lab=1
A30: 1 | B30: LS | D30: Item: 6.002 | E30: =IF(AND($A30=0,$A$1="DIF"),0, ROUND(ROUND(($R35*$S$2+($T35*$T$2))/A30,2)*$C$2,2)) -> 24.28 | F30: =ROUND($A30*$E30,2) -> 24.28 | G30: ISELL | K30: mu_A | L30: ITEM | T30: =IF(AND($R35=0,$T35=0),"0.00","mu :" & ROUND($F30/$C$2/($R35+$T35*$D$9),2)) -> mu :1.3 | AG30: =IF($E30=0,0,ROUND($R35*$S$2*$C$2/$A30,2)) -> 2.86 | AH30: =$AG30*$A30 -> 2.86 | AI30: =$E30-$AG30 -> 21.42 | AJ30: =$A30*$AI30 -> 21.42 | AK30: =ROUND(($AG30+$AI30)*$A30,2) -> 24.28 | AM30: =ROUND(R35,2) -> 2.2 | AN30: =IF(A30=0,0,AO30/A30) -> 0.6 | AO30: =ROUND(T35,2) -> 0.6 | AP30: =ROUND(AM30+AO30,2)*A30 -> 2.8
D31: Motorised 0-10V damper with leakage Class 3 to EN1751-2014 which will be connected to the RMS system for modulation control of damper by CO2 sensor feedback | K31: n
A32: 2 | B32: m | D32: Wiring Cable 3c 1.5 mm2 PVC Non-Arm | G32: CASC_017 | H32: 615 | I32: CRO | K32: 02-002 | O32: 2 | P32: 38988 | Q32: 1.1 | R32: =$A32*Q32 -> 2.2 | S32: 0.05 | T32: =$A32*S32*$T$1 -> 0.1
A33: 1 | B33: No | D33: Labour to connect Mech Equip (Motorised 0-10V damper) | G33: LABO_009 | H33: 900 | I33: MISC | O33: 1 | Q33: 0 | R33: =$A33*Q33 -> 0 | S33: 0.5 | T33: =$A33*S33*$T$1 -> 0.5
R34: =$A34*Q34 -> 0 | T34: =$A34*S34*$T$1 -> 0
A35: d> | B35: =(R34+T34) -> 0 | G35: ICOST | K35: mu_A | L35: ITEM | R35: =SUM(R31:R34) -> 2.2 | T35: =SUM(T31:T34) -> 0.6
E36: Sell Rate | F36: Sell Total | K36: IB | AG36: U_M_Sell | AH36: T_M_Sell | AI36: U_L_Sell | AJ36: T_L_Sell | AK36: Total_Sell | AM36: T_M_Cost | AN36: U_L_Phr | AO36: T_L_Phr | AP36: Mat/Lab=1
A37: 1 | B37: LS | D37: Item: 6.008 | E37: =IF(AND($A37=0,$A$1="DIF"),0, ROUND(ROUND(($R43*$S$3+($T43*$T$3))/$A37,2)*$C$3,2)) -> 234 | F37: =ROUND($A37*$E37,2) -> 234 | G37: ISELL | K37: mu_B | L37: ITEM | T37: =IF(AND($R43=0,$T43=0),"0.00","mu: "& ROUND(F37/$C$3/($R43+$T43*$D$9),2)) -> mu: 1.3 | AG37: =IF($E37=0,0,ROUND($R43*$S$3*$C$3/$A37,2)) -> 234 | AH37: =$AG37*$A37 -> 234 | AI37: =$E37-$AG37 -> 0 | AJ37: =$A37*$AI37 -> 0 | AK37: =ROUND(($AG37+$AI37)*$A37,2) -> 234 | AM37: =ROUND(R43,2) -> 180 | AN37: =IF(A37=0,0,AO37/A37) -> 0 | AO37: =ROUND(T43,2) -> 0 | AP37: =ROUND(AM37+AO37,2)*A37 -> 180
D38: Provide an indirect OA monitroing devices such as differential pressure sensor, airflow switch or current trasnducer on supply fan, complete with wiring to main door | K38: n
A39: 1 | B39: No | D39: Differential pressure sensor | G39: BMSE_007 | H39: 512 | I39: FRER | J39: 1MCOEAR | O39: 2 | P39: 38496 | Q39: 180 | R39: =$A39*Q39 -> 180 | T39: =$A39*S39*$T$1 -> 0
R40: =$A40*Q40 -> 0 | T40: =$A40*S40*$T$1 -> 0
D41: Note: The wiring and programming are included within the REMS BOQ | R41: =$A41*Q41 -> 0 | T41: =$A41*S41*$T$1 -> 0
R42: =$A42*Q42 -> 0 | T42: =$A42*S42*$T$1 -> 0
A43: d> | B43: =(R42+T42) -> 0 | G43: ICOST | K43: mu_B | L43: ITEM | R43: =SUM(R38:R42) -> 180 | T43: =SUM(T38:T42) -> 0
E44: Sell Rate | F44: Sell Total | K44: IB | AG44: U_M_Sell | AH44: T_M_Sell | AI44: U_L_Sell | AJ44: T_L_Sell | AK44: Total_Sell | AM44: T_M_Cost | AN44: U_L_Phr | AO44: T_L_Phr | AP44: Mat/Lab=1
A45: 1 | B45: LS | D45: Item: 6.009 | E45: =IF(AND($A45=0,$A$1="DIF"),0, ROUND(ROUND(($R53*$S$2+($T53*$T$2))/A45,2)*$C$2,2)) -> 24.28 | F45: =ROUND($A45*$E45,2) -> 24.28 | G45: ISELL | K45: mu_A | L45: ITEM | T45: =IF(AND($R53=0,$T53=0),"0.00","mu :" & ROUND($F45/$C$2/($R53+$T53*$D$9),2)) -> mu :1.3 | AG45: =IF($E45=0,0,ROUND($R53*$S$2*$C$2/$A45,2)) -> 2.86 | AH45: =$AG45*$A45 -> 2.86 | AI45: =$E45-$AG45 -> 21.42 | AJ45: =$A45*$AI45 -> 21.42 | AK45: =ROUND(($AG45+$AI45)*$A45,2) -> 24.28 | AM45: =ROUND(R53,2) -> 2.2 | AN45: =IF(A45=0,0,AO45/A45) -> 0.6 | AO45: =ROUND(T53,2) -> 0.6 | AP45: =ROUND(AM45+AO45,2)*A45 -> 2.8
D46: 50 litres/sec mixed flow fan including electrical connection to double pole provided, delay off timer | K46: n
A47: 2 | B47: m | D47: Wiring Cable 3c 1.5 mm2 PVC Non-Arm | G47: CASC_017 | H47: 615 | I47: CRO | K47: 02-002 | O47: 2 | P47: 38988 | Q47: 1.1 | R47: =$A47*Q47 -> 2.2 | S47: 0.05 | T47: =$A47*S47*$T$1 -> 0.1
A48: 1 | B48: No | D48: Labour to connect Mech Equip (Bathroom 50 litres/sec mixed flow fan) | G48: LABO_009 | H48: 900 | I48: MISC | O48: 1 | Q48: 0 | R48: =$A48*Q48 -> 0 | S48: 0.5 | T48: =$A48*S48*$T$1 -> 0.5
B49: No | D49: 16A 1 Channel Modular Relay Time Off Delay | F49: ESS SQ057269 | G49: WACC_258 | H49: 705 | I49: MEM | J49: F8000 | O49: 3 | P49: 38421 | Q49: =24.39*1.1 -> 26.829 | R49: =$A49*Q49 -> 0 | S49: 0.35 | T49: =$A49*S49*$T$1 -> 0 | U49: 1
R50: =$A50*Q50 -> 0 | T50: =$A50*S50*$T$1 -> 0
D51: Note: The Time Off Deley can be achived by the REMS logic controller | R51: =$A51*Q51 -> 0 | T51: =$A51*S51*$T$1 -> 0
R52: =$A52*Q52 -> 0 | T52: =$A52*S52*$T$1 -> 0
A53: d> | B53: =(R52+T52) -> 0 | G53: ICOST | K53: mu_A | L53: ITEM | R53: =SUM(R46:R52) -> 2.2 | T53: =SUM(T46:T52) -> 0.6
K54: TB
C55: t | D55: Item:
D56: AIR CONDITIONING INSTALLATION
E58: Sell Rate | F58: Sell Total | K58: IB | AG58: U_M_Sell | AH58: T_M_Sell | AI58: U_L_Sell | AJ58: T_L_Sell | AK58: Total_Sell | AM58: T_M_Cost | AN58: U_L_Phr | AO58: T_L_Phr | AP58: Mat/Lab=1
A59: 1 | B59: No | D59: Item: 7.002 | E59: =IF(AND($A59=0,$A$1="DIF"),0, ROUND(ROUND(($R64*$S$2+($T64*$T$2))/A59,2)*$C$2,2)) -> 21.37 | F59: =ROUND($A59*$E59,2) -> 21.37 | G59: ISELL | K59: mu_A | L59: ITEM | T59: =IF(AND($R64=0,$T64=0),"0.00","mu :" & ROUND($F59/$C$2/($R64+$T64*$D$9),2)) -> mu :1.3 | AG59: =IF($E59=0,0,ROUND($R64*$S$2*$C$2/$A59,2)) -> 2.81 | AH59: =$AG59*$A59 -> 2.81 | AI59: =$E59-$AG59 -> 18.56 | AJ59: =$A59*$AI59 -> 18.56 | AK59: =ROUND(($AG59+$AI59)*$A59,2) -> 21.37 | AM59: =ROUND(R64,2) -> 2.16 | AN59: =IF(A59=0,0,AO59/A59) -> 0.52 | AO59: =ROUND(T64,2) -> 0.52 | AP59: =ROUND(AM59+AO59,2)*A59 -> 2.68
D60: Wall mounted controller | K60: n
A61: 2 | B61: m | D61: 20mm Conduit LSZH - RATE | G61: COPV_003 | H61: 700 | I61: GEN | J61: 20mm | O61: 1 | P61: 42213 | Q61: 0.67 | R61: =$A61*Q61 -> 1.34 | S61: 0.13 | T61: =$A61*S61*$T$1 -> 0.26
A62: 2 | B62: m | D62: 20mm Flexible Conduit LSZH - RATE | G62: COPV_003 | H62: 700 | I62: GEN | J62: 20mm | O62: 1 | P62: 42213 | Q62: 0.41 | R62: =$A62*Q62 -> 0.82 | S62: 0.13 | T62: =$A62*S62*$T$1 -> 0.26
R63: =$A63*Q63 -> 0 | T63: =$A63*S63*$T$1 -> 0
A64: d> | B64: =(R63+T63) -> 0 | G64: ICOST | K64: mu_A | L64: ITEM | R64: =SUM(R60:R63) -> 2.16 | T64: =SUM(T60:T63) -> 0.52
E65: Sell Rate | F65: Sell Total | K65: IB | AG65: U_M_Sell | AH65: T_M_Sell | AI65: U_L_Sell | AJ65: T_L_Sell | AK65: Total_Sell | AM65: T_M_Cost | AN65: U_L_Phr | AO65: T_L_Phr | AP65: Mat/Lab=1
A66: 1 | B66: No | D66: Item: 7.005 | E66: =IF(AND($A66=0,$A$1="DIF"),0, ROUND(ROUND(($R71*$S$2+($T71*$T$2))/A66,2)*$C$2,2)) -> 21.37 | F66: =ROUND($A66*$E66,2) -> 21.37 | G66: ISELL | K66: mu_A | L66: ITEM | T66: =IF(AND($R71=0,$T71=0),"0.00","mu :" & ROUND($F66/$C$2/($R71+$T71*$D$9),2)) -> mu :1.3 | AG66: =IF($E66=0,0,ROUND($R71*$S$2*$C$2/$A66,2)) -> 2.81 | AH66: =$AG66*$A66 -> 2.81 | AI66: =$E66-$AG66 -> 18.56 | AJ66: =$A66*$AI66 -> 18.56 | AK66: =ROUND(($AG66+$AI66)*$A66,2) -> 21.37 | AM66: =ROUND(R71,2) -> 2.16 | AN66: =IF(A66=0,0,AO66/A66) -> 0.52 | AO66: =ROUND(T71,2) -> 0.52 | AP66: =ROUND(AM66+AO66,2)*A66 -> 2.68
D67: Wall mounted controller | K67: n
A68: 2 | B68: m | D68: 20mm Conduit LSZH - RATE | G68: COPV_003 | H68: 700 | I68: GEN | J68: 20mm | O68: 1 | P68: 42213 | Q68: 0.67 | R68: =$A68*Q68 -> 1.34 | S68: 0.13 | T68: =$A68*S68*$T$1 -> 0.26
A69: 2 | B69: m | D69: 20mm Flexible Conduit LSZH - RATE | G69: COPV_003 | H69: 700 | I69: GEN | J69: 20mm | O69: 1 | P69: 42213 | Q69: 0.41 | R69: =$A69*Q69 -> 0.82 | S69: 0.13 | T69: =$A69*S69*$T$1 -> 0.26
R70: =$A70*Q70 -> 0 | T70: =$A70*S70*$T$1 -> 0
A71: d> | B71: =(R70+T70) -> 0 | G71: ICOST | K71: mu_A | L71: ITEM | R71: =SUM(R67:R70) -> 2.16 | T71: =SUM(T67:T70) -> 0.52
E72: Sell Rate | F72: Sell Total | K72: IB | AG72: U_M_Sell | AH72: T_M_Sell | AI72: U_L_Sell | AJ72: T_L_Sell | AK72: Total_Sell | AM72: T_M_Cost | AN72: U_L_Phr | AO72: T_L_Phr | AP72: Mat/Lab=1
A73: 1 | B73: LS | D73: Item: 7.007 | E73: =IF(AND($A73=0,$A$1="DIF"),0, ROUND(ROUND(($R78*$S$2+($T78*$T$2))/A73,2)*$C$2,2)) -> 0 | F73: =ROUND($A73*$E73,2) -> 0 | G73: ISELL | K73: mu_A | L73: ITEM | Q73: NA | T73: =IF(AND($R78=0,$T78=0),"0.00","mu :" & ROUND($F73/$C$2/($R78+$T78*$D$9),2)) -> 0.00 | AG73: =IF($E73=0,0,ROUND($R78*$S$2*$C$2/$A73,2)) -> 0 | AH73: =$AG73*$A73 -> 0 | AI73: =$E73-$AG73 -> 0 | AJ73: =$A73*$AI73 -> 0 | AK73: =ROUND(($AG73+$AI73)*$A73,2) -> 0 | AM73: =ROUND(R78,2) -> 0 | AN73: =IF(A73=0,0,AO73/A73) -> 0 | AO73: =ROUND(T78,2) -> 0 | AP73: =ROUND(AM73+AO73,2)*A73 -> 0
D74: Provide means of having ac indoor unit fan working without outdoor, with speed hi-med-low modes for noise level similuation | K74: n
R75: =$A75*Q75 -> 0 | T75: =$A75*S75*$T$1 -> 0
D76: NA | R76: =$A76*Q76 -> 0 | T76: =$A76*S76*$T$1 -> 0
R77: =$A77*Q77 -> 0 | T77: =$A77*S77*$T$1 -> 0
A78: d> | B78: =(R77+T77) -> 0 | G78: ICOST | K78: mu_A | L78: ITEM | R78: =SUM(R74:R77) -> 0 | T78: =SUM(T74:T77) -> 0
A79: SB
B81: =($R81*$S$2+$T81*$T$2)-$F81 -> -0.00168 | D81: PAGE : | F81: =SUMIF($L18:$L79,"ITEM",F18:F79) -> 349.58 | L81: PAGE | R81: =SUMIF($L18:$L79,"ITEM",R18:R79) -> 190.92 | T81: =SUMIF($L18:$L79,"ITEM",T18:T79) -> 2.84
B82: Disc: | F82: PAGE SELL | R82: PAGE MAT | T82: PAGE LAB
AH84: T_M_Sell | AJ84: T_L_Sell | AK84: Total_Sell
A85: SB! | AH85: =SUM(AH$18:AH84) -> 248.2 | AJ85: =SUM(AJ$18:AJ84) -> 101.38 | AK85: =SUM(AK$18:AK84) -> 349.58
B86: =$F86/$C$2-($R86*$S$2+$T86*$T$2) -> 0.00168 | C86: cc | E86: =$F$2 & " (mu_A) :" -> Electrical (mu_A) : | F86: =SUMIF($K$13:$K85,"mu_A",F$13:F85) -> 115.58 | R86: =SUMIF($K$13:$K85,"mu_A",R$13:R$85) -> 10.92 | T86: =SUMIF($K$13:$K85,"mu_A",T$13:T$85) -> 2.84 | AH86: =R86*$S$2 -> 14.196 | AJ86: =T86*$T$2 -> 101.38232
B87: =$F87/$C$3-($R87*$S$3+$T87*$T$3) -> 0 | C87: cc | E87: =$F$3& " (mu_B) :" -> Controls Section (Guy) (mu_B) : | F87: =SUMIF($K$13:$K85,"mu_B",F$13:F85) -> 234 | R87: =SUMIF($K$13:$K85,"mu_B",R$13:R85) -> 180 | T87: =SUMIF($K$13:$K85,"mu_B",T$13:T85) -> 0 | AH87: =R87*$S$3 -> 234 | AJ87: =T87*$T$3 -> 0
B88: =$F88/$C$4-($R88*$S$4+$T88*$T$4) -> 0 | C88: cc | E88: =$F$4& " (mu_C) :" -> 0 (mu_C) : | F88: =SUMIF($K$13:$K85,"mu_C",F$13:F85) -> 0 | R88: =SUMIF($K$13:$K85,"mu_C",R$13:R85) -> 0 | T88: =SUMIF($K$13:$K85,"mu_C",T$13:T85) -> 0 | AH88: =R88*$S$4 -> 0 | AJ88: =T88*$T$4 -> 0
B89: =$F89/$C$5-($R89*$S$5+$T89*$T$5) -> 0 | C89: cc | E89: =$F$5& " (mu_D) :" -> 0 (mu_D) : | F89: =SUMIF($K$13:$K85,"mu_D",F$13:F85) -> 0 | R89: =SUMIF($K$13:$K85,"mu_D",R$13:R85) -> 0 | T89: =SUMIF($K$13:$K85,"mu_D",T$13:T85) -> 0 | AH89: =R89*$S$5 -> 0 | AJ89: =T89*$T$5 -> 0
B90: =$F90/$C$6-($R90*$S$6+$T90*$T$6) -> 0 | C90: cc | E90: =$F$6& " (mu_E) :" -> 0 (mu_E) : | F90: =SUMIF($K$13:$K85,"mu_E",F$13:F85) -> 0 | R90: =SUMIF($K$13:$K85,"mu_E",R$13:R85) -> 0 | T90: =SUMIF($K$13:$K85,"mu_E",T$13:T85) -> 0 | AH90: =R90*$S$6 -> 0 | AJ90: =T90*$T$6 -> 0
B91: =$F91/$C$7-($R91*$S$7+$T91*$T$7) -> 0 | C91: cc | E91: =$F$7& " (mu_F) :" -> 0 (mu_F) : | F91: =SUMIF($K$13:$K85,"mu_F",F$13:F85) -> 0 | R91: =SUMIF($K$13:$K85,"mu_F",R$13:R85) -> 0 | T91: =SUMIF($K$13:$K85,"mu_F",T$13:T85) -> 0 | AH91: =R91*$S$7 -> 0 | AJ91: =T91*$T$7 -> 0
B92: =$F92/$C$8-($R92*$S$8+$T92*$T$8) -> 0 | C92: cc | E92: =$F$8& " (mu_G) :" -> 0 (mu_G) : | F92: =SUMIF($K$13:$K85,"mu_G",F$13:F85) -> 0 | R92: =SUMIF($K$13:$K85,"mu_G",R$13:R85) -> 0 | T92: =SUMIF($K$13:$K85,"mu_G",T$13:T85) -> 0 | AH92: =R92*$S$8 -> 0 | AJ92: =T92*$T$8 -> 0
B93: =$F93/$C$9-($R93*$S$9+$T93*$T$9) -> 0 | C93: cc | E93: =$F$9& " (mu_H) :" -> 0 (mu_H) : | F93: =SUMIF($K$13:$K85,"mu_H",F$13:F85) -> 0 | R93: =SUMIF($K$13:$K85,"mu_H",R$13:R85) -> 0 | T93: =SUMIF($K$13:$K85,"mu_H",T$13:T85) -> 0 | AH93: =R93*$S$9 -> 0 | AJ93: =T93*$T$9 -> 0
B94: =$F94/$C$10-($R94*$S$10+$T94*$T$10) -> 0 | C94: cc | E94: =$F$10& " (mu_I) :" -> 0 (mu_I) : | F94: =SUMIF($K$13:$K85,"mu_I",F$13:F85) -> 0 | R94: =SUMIF($K$13:$K85,"mu_I",R$13:R85) -> 0 | T94: =SUMIF($K$13:$K85,"mu_I",T$13:T85) -> 0 | AH94: =R94*$S$10 -> 0 | AJ94: =T94*$T$10 -> 0
B95: =$F95/$C$11-($R95*$S$11+$T95*$T$11) -> 0 | E95: =$F$11& " (mu_J) :" -> 0 (mu_J) : | F95: =SUMIF($K$13:$K86,"mu_J",F$13:F86) -> 0 | R95: =SUMIF($K$13:$K86,"mu_J",R$13:R85) -> 0 | T95: =SUMIF($K$13:$K86,"mu_J",T$13:T86) -> 0 | AH95: =R95*$S$11 -> 0 | AJ95: =T95*$T$11 -> 0
C96: MATERIAL SUMMARY | E96: MU SUMMARY TOTAL | F96: =SUM(F86:F95) -> 349.58 | G96: ISELL | R96: =SUM(R86:R95) -> 190.92 | T96: =SUM(T86:T95) -> 2.84 | AH96: =SUM(AH86:AH95) -> 248.196 | AJ96: =SUM(AJ86:AJ95) -> 101.38232 | AK96: =AH96+AJ96 -> 349.57832
AH97: =AH85-AH96 -> 0.004 | AJ97: =AJ85-AJ96 -> -0.00232 | AK97: =AK85-AK96 -> 0.00168
B98: Discy with | E98: MATERIAL ITEMS TOTAL | L98: COMP_GT | R98: =SUMIF($L$13:$L85,"",R$13:R85) -> 190.92 | T98: =SUMIF($L$13:$L85,"",T$13:T85) -> 2.84
B99: equal Mus
B100: =$F100/$C$2-($R100*$S$2+$T100*$T$2) -> 0.00168 | E100: BOQ ITEMS TOTAL | F100: =SUMIF($L$13:$L85,"ITEM",F$13:F85) -> 349.58 | L100: ITEM_GT | R100: =SUMIF($L$13:$L85,"ITEM",R$13:R85) -> 190.92 | T100: =SUMIF($L$13:$L85,"ITEM",T$13:T85) -> 2.84
B102: =$F102/$C$2-($R102*$S$2+$T102*$T$2) -> 0.00168 | E102: PAGES TOTAL | F102: =SUMIF($L$13:$L85,"PAGE",F$13:F85) -> 349.58 | L102: PAGE_GT | R102: =SUMIF($L$13:$L85,"PAGE",R$13:R85) -> 190.92 | T102: =SUMIF($L$13:$L85,"PAGE",T$13:T85) -> 2.84
A104: SB | B104: =$F104/$C$2-($R104*$S$2+$T104*$T$2) -> 0 | E104: SECTIONS TOTAL | F104: =SUMIF($L$13:$L85,"SECT",F$13:F85) -> 0 | L104: SECT_GT | R104: =SUMIF($L$13:$L85,"SECT",R$13:R85) -> 0 | T104: =SUMIF($L$13:$L85,"SECT",T$13:T85) -> 0
A105: END!
B106: V:56 | E106: COSTCODE TOTAL | R106: =SUM(R107:R162) -> 190.92 | T106: =SUM(T107:T162) -> 2.84
B107: 1 | C107: cc | D107: Erection materials | F107: 501 | P107: 1 | R107: =SUMIF($H$13:$H$85,$F107,R$13:R$85) -> 0 | T107: =SUMIF($H$13:$H$85,$F107,T$13:T$85) -> 0
...

Sheet ML_Sum
B1: CLIENT: | C1: 1 | D1: SUNCREST HOTELS plc | G1: TRUE | H1: TRUE | I1: 1 | J1: =$Q109 -> 1 | K1: =$Q119 -> 1 | L1: =$Q129 -> 1 | M1: =$Q139 -> 1 | N1: =$Q149 -> 1 | O1: =$Q159 -> 1 | Q1: =IF(C1=1,"€","Curr?") -> € | R1: Recon /Lab.Cont >> | S1: =IF($S$39="PRINT","R","Do Not Print") -> R | T1: 1 | V1: {=IF(OR(X1=AREAS),1,0)} -> 1 | W1: BOQ | X1: x | Y1: x | Z1: x | AA1: x | AB1: x | AC1: x | AD1: x
B2: PROJECT: | C2: =IF($D$6="VAT INCLUDED",1.18,1)*(1-$Q2)*$C$1 -> 1 | D2: Sunny Cost and Lido Redevelopment | F2: Electrical | G2: TRUE | I2: 2 | J2: =$Q110 -> 1 | K2: =$Q120 -> 1 | L2: =$Q130 -> 1 | M2: =$Q140 -> 1 | N2: =$Q150 -> 1 | O2: =$Q160 -> 1 | R2: ="A) " & IF($S2=0,"",ROUND($S2,2) & "-" & ROUND($T2/$D$9,2)) -> A) 1.3-1.3 | S2: 1.3 | T2: =$S2*$D$9 -> 35.698 | X2: x | Y2: x | Z2: x | AA2: x | AB2: x | AC2: x | AD2: x
B3: JOB DESC: | C3: =IF($D$6="VAT INCLUDED",1.18,1)*(1-$Q3)*$C$1 -> 1 | D3: Sample Room - Electrical for Mechanical | F3: Controls Section (Guy) | G3: TRUE | I3: 3 | J3: =$Q111 -> 1 | K3: =$Q121 -> 1 | L3: =$Q131 -> 1 | M3: =$Q141 -> 1 | N3: =$Q151 -> 1 | O3: =$Q161 -> 1 | R3: ="B) " & IF($S3=0,"",ROUND($S3,2) & "-" & ROUND($T3/$D$9,2)) -> B) 1.3-1.3 | S3: 1.3 | T3: =$S3*$D$9 -> 35.698 | X3: x | Y3: x | Z3: x | AA3: x | AB3: x | AC3: x | AD3: x
B4: INT. QUOT No: | C4: =IF($D$6="VAT INCLUDED",1.18,1)*(1-$Q4)*$C$1 -> 1 | D4: ELM25-0699 | G4: TRUE | I4: 4 | J4: =$Q112 -> 1 | K4: =$Q122 -> 1 | L4: =$Q132 -> 1 | M4: =$Q142 -> 1 | N4: =$Q152 -> 1 | O4: =$Q162 -> 1 | R4: ="C) " & IF($S4=0,"",ROUND($S4,2) & "-" & ROUND($T4/$D$9,2)) -> C) | T4: =$S4*$D$10 -> 0 | X4: x | Y4: x | Z4: x | AA4: x | AB4: x | AC4: x | AD4: x
B5: CLIENTs REF: | C5: =IF($D$6="VAT INCLUDED",1.18,1)*(1-$Q5)*$C$1 -> 1 | D5: Sample Room | G5: TRUE | I5: 5 | J5: =$Q113 -> 1 | K5: =$Q123 -> 1 | L5: =$Q133 -> 1 | M5: =$Q143 -> 1 | N5: =$Q153 -> 1 | O5: =$Q163 -> 1 | R5: ="D) " & IF($S5=0,"",ROUND($S5,2) & "-" & ROUND($T5/$D$9,2)) -> D) | T5: =$S5*$D$9 -> 0 | X5: x | Y5: x | Z5: x | AA5: x | AB5: x | AC5: x | AD5: x
B6: VAT: | C6: =IF($D$6="VAT INCLUDED",1.18,1)*(1-$Q6)*$C$1 -> 1 | D6: VAT EXCL. | G6: TRUE | I6: 6 | J6: =$Q114 -> 1 | K6: =$Q124 -> 1 | L6: =$Q134 -> 1 | M6: =$Q144 -> 1 | N6: =$Q154 -> 1 | O6: =$Q164 -> 1 | R6: ="E) " & IF($S6=0,"",ROUND($S6,2) & "-" & ROUND($T6/$D$9,2)) -> E) | T6: =$S6*$D$9 -> 0 | X6: x | Y6: x | Z6: x | AA6: x | AB6: x | AC6: x | AD6: x
B7: SAVED ON: | C7: =IF($D$6="VAT INCLUDED",1.18,1)*(1-$Q7)*$C$1 -> 1 | D7: 45971 | G7: TRUE | I7: 7 | J7: =$Q115 -> 1 | K7: =$Q125 -> 1 | L7: =$Q135 -> 1 | M7: =$Q145 -> 1 | N7: =$Q155 -> 1 | R7: ="F) " & IF($S7=0,"",ROUND($S7,2) & "-" & ROUND($T7/$D$9,2)) -> F) | T7: =$S7*$D$9 -> 0 | X7: x | Y7: x | Z7: x | AA7: x | AB7: x | AC7: x | AD7: x
B8: ESTIMATOR: | C8: =IF($D$6="VAT INCLUDED",1.18,1)*(1-$Q8)*$C$1 -> 1 | D8: R.Farrugia | G8: TRUE | I8: 8 | J8: =$Q116 -> 1 | K8: =$Q126 -> 1 | L8: =$Q136 -> 1 | M8: =$Q146 -> 1 | N8: =$Q156 -> 1 | R8: ="G) " & IF($S8=0,"",ROUND($S8,2) & "-" & ROUND($T8/$D$9,2)) -> G) | T8: =$S8*$D$9 -> 0 | X8: x | Y8: x | Z8: x | AA8: x | AB8: x | AC8: x | AD8: x
B9: LAB. COST: | C9: =IF($D$6="VAT INCLUDED",1.18,1)*(1-$Q9)*$C$1 -> 1 | D9: 27.46 | G9: TRUE | I9: 9 | J9: =$Q117 -> 1 | K9: =$Q127 -> 1 | L9: =$Q137 -> 1 | M9: =$Q147 -> 1 | N9: =$Q157 -> 1 | R9: ="H) " & IF($S9=0,"",ROUND($S9,2) & "-" & ROUND($T9/$D$9,2)) -> H) | T9: =$S9*$D$9 -> 0 | X9: x | Y9: x | Z9: x | AA9: x | AB9: x | AC9: x | AD9: x
C10: =IF($D$6="VAT INCLUDED",1.18,1)*(1-$Q10)*$C$1 -> 1 | G10: TRUE | I10: 10 | J10: =$Q118 -> 1 | K10: =$Q128 -> 1 | L10: =$Q138 -> 1 | M10: =$Q148 -> 1 | N10: =$Q158 -> 1 | O10: =Q108 -> 1 | R10: =" I) " & IF($S10=0,"",ROUND($S10,2) & "-" & ROUND($T10/$D$9,2)) -> I) | T10: =$S10*$D$9 -> 0 | X10: x | Y10: x | Z10: x | AA10: x | AB10: x | AC10: x | AD10: x
C11: =IF($D$6="VAT INCLUDED",1.18,1)*(1-$Q11)*$C$1 -> 1 | R11: ="J) " & IF($S11=0,"",ROUND($S11,2) & "-" & ROUND($T11/$D$9,2)) -> J) | T11: =$S11*$D$9 -> 0 | X11: x | Y11: x | Z11: x | AA11: x | AB11: x | AC11: x | AD11: x
C12: =IF($D$6="VAT INCLUDED",1.18,1)*(1-$Q12)*$C$1 -> 1 | G12: SYSTEMS | H12: SYSTEMS | I12: SYSTEMS | J12: SYSTEMS | K12: SYSTEMS | L12: SYSTEMS | M12: SYSTEMS | N12: SYSTEMS | O12: SYSTEMS | P12: SYSTEMS | R12: MIXED - X,Y ) | S12: MAT MU | T12: LAB RATE | X12: x | Y12: x | Z12: x | AA12: x | AB12: x | AC12: x | AD12: x
B13: MATERIAL & LABOUR SUMMARY | G13: ItemCode | H13: CostCode | I13: MAKE | J13: PART_NO | K13: MARKUP | L13: TYPE | M13: LIST_P | N13: SET | O13: FIX | P13: DATE | Q13: %Dsct in BOQ | R13: MATMU-LABMU | S13: MAT CONT >> | T13: =SUM(Q108:Q164)/57 -> 1
B14: =IF($D$6<>"VAT EXCL.", "QUOTE ISSUED WITH VAT INCLUDED", "") | X14: x | Y14: x | Z14: x | AA14: x | AB14: x | AC14: x | AD14: x
Q15: =(C72-F35)/C72 -> 0 | R15: Average Discount applied in BOQ (Q2-Q12) | X15: x | Y15: x | Z15: x | AA15: x | AB15: x | AC15: x | AD15: x
B16: =IF($W$1<>"BOQ", "DIFF SET TO " & W1,"") | Q16: =(F35-E35)/F35 -> 0 | R16: Average Discount applied on Totals (Q23-Q32) | X16: x | Y16: x | Z16: x | AA16: x | AB16: x | AC16: x | AD16: x
Q17: =F74 -> 0 | R17: Overall Discount
B18: =IF(AND(G1,G2,G3,G4,G5,G6,G7,G8,G9,G10,H1)=TRUE, "", "CHECKLIST INCOMPLETE !" )
B19: =IF(ABS(SUM(A23:A32))>100,"[Discy A-J] are high, Check it out."," ") | Q19: =R83 -> 1.3000062 | R19: Overall Markup (Final Selling Excl.VAT/Total Cost )
E21: DISCOUNTED | F21: SELLING | Q21: % Discnt | R21: MATERIAL | T21: LABOUR
A22: Discy.A-J | B22: Markup/LRate | E22: ="SELLING " & $Q$1 -> SELLING € | F22: =$Q$1 -> € | G22: VAT/DISC | H22: MU | I22: LABRATE | J22: LABCOST | Q22: on Totals | R22: € | T22: Pair Hrs.
A23: =IF($F23=0,"",($F23/$C2)-($R23*$S2+$T23*$T2)) -> 0.00168 | B23: =IF(F23=0,"",IF(R23=0,"A) "&"---, "&ROUND(($F23/$C2-($R23*$S2))/$T23,2),IF(T23=0,"A) "&ROUND(($F23/$C2)/$R23,2),"A) "&ROUND(($F23/$C2-($T23*$T2))/$R23,2)&", " &ROUND(($F23/$C2-($R23*$S2))/$T23,2)))) -> A) 1.3, 35.7 | D23: =IF($F2="","",$F2) -> Electrical | E23: =F23*(1-Q23) -> 115.58 | F23: =Elec_Est!F86 -> 115.58 | G23: =C2 -> 1 | H23: =$S2 -> 1.3 | I23: =$T2 -> 35.698 | J23: =$D$9 -> 27.46 | R23: =Elec_Est!R86 -> 10.92 | T23: =Elec_Est!T86 -> 2.84
A24: =IF($F24=0,"",($F24/$C3)-($R24*$S3+$T24*$T3)) -> 0 | B24: =IF(F24=0,"",IF(R24=0,"A) "&"---, "&ROUND(($F24/$C3-($R24*$S3))/$T24,2),IF(T24=0,"A) "&ROUND(($F24/$C3)/$R24,2),"A) "&ROUND(($F24/$C3-($T24*$T3))/$R24,2)&", " &ROUND(($F24/$C3-($R24*$S3))/$T24,2)))) -> A) 1.3 | D24: =IF($F3="","",$F3) -> Controls Section (Guy) | E24: =F24*(1-Q24) -> 234 | F24: =Elec_Est!F87 -> 234 | G24: =C3 -> 1 | H24: =$S3 -> 1.3 | I24: =$T3 -> 35.698 | J24: =$D$9 -> 27.46 | R24: =Elec_Est!R87 -> 180 | T24: =Elec_Est!T87 -> 0
A25: =IF($F25=0,"",($F25/$C4)-($R25*$S4+$T25*$T4)) | B25: =IF(F25=0,"",IF(R25=0,"A) "&"---, "&ROUND(($F25/$C4-($R25*$S4))/$T25,2),IF(T25=0,"A) "&ROUND(($F25/$C4)/$R25,2),"A) "&ROUND(($F25/$C4-($T25*$T4))/$R25,2)&", " &ROUND(($F25/$C4-($R25*$S4))/$T25,2)))) | D25: =IF($F4="","",$F4) | E25: =F25*(1-Q25) -> 0 | F25: =Elec_Est!F88 -> 0 | G25: =C4 -> 1 | H25: =$S4 -> 0 | I25: =$T4 -> 0 | J25: =$D$9 -> 27.46 | R25: =Elec_Est!R88 -> 0 | T25: =Elec_Est!T88 -> 0
A26: =IF($F26=0,"",($F26/$C5)-($R26*$S5+$T26*$T5)) | B26: =IF(F26=0,"",IF(R26=0,"A) "&"---, "&ROUND(($F26/$C5-($R26*$S5))/$T26,2),IF(T26=0,"A) "&ROUND(($F26/$C5)/$R26,2),"A) "&ROUND(($F26/$C5-($T26*$T5))/$R26,2)&", " &ROUND(($F26/$C5-($R26*$S5))/$T26,2)))) | D26: =IF($F5="","",$F5) | E26: =F26*(1-Q26) -> 0 | F26: =Elec_Est!F89 -> 0 | G26: =C5 -> 1 | H26: =$S5 -> 0 | I26: =$T5 -> 0 | J26: =$D$9 -> 27.46 | R26: =Elec_Est!R89 -> 0 | T26: =Elec_Est!T89 -> 0
A27: =IF($F27=0,"",($F27/$C6)-($R27*$S6+$T27*$T6)) | B27: =IF(F27=0,"",IF(R27=0,"A) "&"---, "&ROUND(($F27/$C6-($R27*$S6))/$T27,2),IF(T27=0,"A) "&ROUND(($F27/$C6)/$R27,2),"A) "&ROUND(($F27/$C6-($T27*$T6))/$R27,2)&", " &ROUND(($F27/$C6-($R27*$S6))/$T27,2)))) | D27: =IF($F6="","",$F6) | E27: =F27*(1-Q27) -> 0 | F27: =Elec_Est!F90 -> 0 | G27: =C6 -> 1 | H27: =$S6 -> 0 | I27: =$T6 -> 0 | J27: =$D$9 -> 27.46 | R27: =Elec_Est!R90 -> 0 | T27: =Elec_Est!T90 -> 0
A28: =IF($F28=0,"",($F28/$C7)-($R28*$S7+$T28*$T7)) | B28: =IF(F28=0,"",IF(R28=0,"A) "&"---, "&ROUND(($F28/$C7-($R28*$S7))/$T28,2),IF(T28=0,"A) "&ROUND(($F28/$C7)/$R28,2),"A) "&ROUND(($F28/$C7-($T28*$T7))/$R28,2)&", " &ROUND(($F28/$C7-($R28*$S7))/$T28,2)))) | D28: =IF($F7="","",$F7) | E28: =F28*(1-Q28) -> 0 | F28: =Elec_Est!F91 -> 0 | G28: =C7 -> 1 | H28: =$S7 -> 0 | I28: =$T7 -> 0 | J28: =$D$9 -> 27.46 | R28: =Elec_Est!R91 -> 0 | T28: =Elec_Est!T91 -> 0
A29: =IF($F29=0,"",($F29/$C8)-($R29*$S8+$T29*$T8)) | B29: =IF(F29=0,"",IF(R29=0,"A) "&"---, "&ROUND(($F29/$C8-($R29*$S8))/$T29,2),IF(T29=0,"A) "&ROUND(($F29/$C8)/$R29,2),"A) "&ROUND(($F29/$C8-($T29*$T8))/$R29,2)&", " &ROUND(($F29/$C8-($R29*$S8))/$T29,2)))) | D29: =IF($F8="","",$F8) | E29: =F29*(1-Q29) -> 0 | F29: =Elec_Est!F92 -> 0 | G29: =C8 -> 1 | H29: =$S8 -> 0 | I29: =$T8 -> 0 | J29: =$D$9 -> 27.46 | R29: =Elec_Est!R92 -> 0 | T29: =Elec_Est!T92 -> 0
A30: =IF($F30=0,"",($F30/$C9)-($R30*$S9+$T30*$T9)) | B30: =IF(F30=0,"",IF(R30=0,"A) "&"---, "&ROUND(($F30/$C9-($R30*$S9))/$T30,2),IF(T30=0,"A) "&ROUND(($F30/$C9)/$R30,2),"A) "&ROUND(($F30/$C9-($T30*$T9))/$R30,2)&", " &ROUND(($F30/$C9-($R30*$S9))/$T30,2)))) | D30: =IF($F9="","",$F9) | E30: =F30*(1-Q30) -> 0 | F30: =Elec_Est!F93 -> 0 | G30: =C9 -> 1 | H30: =$S9 -> 0 | I30: =$T9 -> 0 | J30: =$D$9 -> 27.46 | R30: =Elec_Est!R93 -> 0 | T30: =Elec_Est!T93 -> 0
A31: =IF($F31=0,"",($F31/$C10)-($R31*$S10+$T31*$T10)) | B31: =IF(F31=0,"",IF(R31=0,"A) "&"---, "&ROUND(($F31/$C10-($R31*$S10))/$T31,2),IF(T31=0,"A) "&ROUND(($F31/$C10)/$R31,2),"A) "&ROUND(($F31/$C10-($T31*$T10))/$R31,2)&", " &ROUND(($F31/$C10-($R31*$S10))/$T31,2)))) | D31: =IF($F10="","",$F10) | E31: =F31*(1-Q31) -> 0 | F31: =Elec_Est!F94 -> 0 | G31: =C10 -> 1 | H31: =$S10 -> 0 | I31: =$T10 -> 0 | J31: =$D$9 -> 27.46 | R31: =Elec_Est!R94 -> 0 | T31: =Elec_Est!T94 -> 0
A32: =IF($F32=0,"",($F32/$C11)-($R32*$S11+$T32*$T11)) | B32: =IF(F32=0,"",IF(R32=0,"A) "&"---, "&ROUND(($F32/$C11-($R32*$S11))/$T32,2),IF(T32=0,"A) "&ROUND(($F32/$C11)/$R32,2),"A) "&ROUND(($F32/$C11-($T32*$T11))/$R32,2)&", " &ROUND(($F32/$C11-($R32*$S11))/$T32,2)))) | D32: =IF($F11="","",$F11) | E32: =F32*(1-Q32) -> 0 | F32: =Elec_Est!F95 -> 0 | G32: =C11 -> 1 | H32: =$S11 -> 0 | I32: =$T11 -> 0 | J32: =$D$9 -> 27.46 | R32: =Elec_Est!R95 -> 0 | T32: =Elec_Est!T95 -> 0
C33: MIXED
A35: Discy.L | B35: ='MUR MEP BOQ'!H255 -> 349.58 | E35: =SUM(E23:E32) -> 349.58 | F35: =SUM(F23:F32) -> 349.58 | R35: =SUM(R23:R32) -> 190.92 | T35: =SUM(T23:T32) -> 2.84
A36: =IF(A39=0,"0.00",A39-(A38*A37)) -> 0.00 | B36: BOQ TOTAL | E36: ="ESTIM TOTAL (" & $Q$1 & ")" -> ESTIM TOTAL (€)
A37: 1.125 | B37: <1 Actual LabCont | R37: =R165 -> 190.92 | S37: C.C.Totals | T37: =T165 -> 2.84
B38: <2 Phrs @ 1.00
B39: <3 Phrs @ Actual | Q39: Discy.T >> | R39: =R37-R35 -> 0 | S39: PRINT | T39: =T37-T35 -> 0
B41: Values Only on : | D41: 45971 | R41: 190.92 | T41: 2.84
A46: REMARKS:
A47: 1) VAT and Duties as above.
A51: ESTIMATOR: | D51: =D8 -> R.Farrugia | Q51: APPROVED BY:
A53: SIGNED: | Q53: DATE APPROVED:
A55: FILE LOCATION: | D55: =CELL("filename") -> K:\est\Sunny Coast Hotel\Estimates\[ELM25_0699_Mock_Up_Room_Elec_for_Mech.xlsx]ML_Sum
B57: PANTA CONTRACTING LTD. - ELECTRICAL DIVISION
B58: CONTRACT / VARIATION INPUT DOCUMENT
S59: Copy to:-
D60: Client: | E60: =D1 -> SUNCREST HOTELS plc | S60: Ms. S. Magri
D61: Project: | E61: =D2 -> Sunny Cost and Lido Redevelopment | S61: Mr. K. Micallef
D62: Job Description: | E62: =D3 -> Sample Room - Electrical for Mechanical | S62: Mr. A. Sciberras
D63: Quote No: | E63: =D4 -> ELM25-0699
D64: Client's Ref: | E64: =D5 -> Sample Room
S65: File:-
D66: File No:
D67: Ext. Ref:
E70: Contract /Variation (Excl. VAT)
C72: =IF($A$33="MIXED",F23/(1-Q2)+F24/(1-Q3)+F25/(1-Q4)+F26/(1-Q5)+F27/(1-Q6)+F28/(1-Q7)+F29/(1-Q8)+F30/(1-Q9)+F31/(1-Q10)+F32/(1-Q11)-SUM(A23:A32), F23/(1-Q2)+F24/(1-Q3)+F25/(1-Q4)+F26/(1-Q5)+F27/(1-Q6)+F28/(1-Q7)+F29/(1-Q8)+F30/(1-Q9)+F31/(1-Q10)+F32/(1-Q11)) -> 349.58 | E72: Estim.Sell before Discounts excl.VAT (€): | F72: =IF(D6="VAT INCLUDED",C72/($C$1*1.18),C72/$C$1) -> 349.58
E74: Overall Discount: | F74: =(F72-F75)/F72 -> 0
E75: Final Sell after Discounts excl.VAT (€): | F75: =IF(D6="VAT INCLUDED",E35/($C$1*1.18),E35/$C$1) -> 349.58
E77: Labour Rate - | F77: =$D$9 -> 27.46 | R77: Mech. Cost to us
D80: Mat. Cost | E80: Labour | F80: Total Cost | R80: Sell Excl.VAT / Total Cost
D81: € | E81: Pair.Hrs | F81: €
D83: =R165 -> 190.92 | E83: =T165 -> 2.84 | F83: =R165+S165 -> 268.9064 | R83: =IF(F83=0,0,F75/F83) -> 1.3000062
D84: ( From CostCode Totals )
R87: Advanced Payment:
R88: Retention:
R90: Awarded Date:
R91: Estimated Start Date:
R92: Estimated Completion Date:
D93: .................
D94: A. Sciberras | R94: Date issued:
D95: =D15 -> 0
D98: PANTA CONTRACTING LTD. - ELECTRICAL DIVISION
D99: ELECTRICAL AND ELV CONTRACT / VARIATION BUDGET COST
D101: Project: | E101: =E61 -> Sunny Cost and Lido Redevelopment
D102: Job Desc: | E102: =E62 -> Sample Room - Electrical for Mechanical
D103: Client's Ref: | E103: =E64 -> Sample Room
D106: COSTCODE | F106: Cost | Q106: Mat. | R106: Mat Cost | S106: Lab Cost @ | T106: Labour
F107: Code | Q107: Cont. | R107: € | S107: =$D$9 -> 27.46 | T107: Pair.Hrs
B108: V:56 | D108: BOQ RateOnly Items | P108: FIX | Q108: 1
B109: 1(J) | C109: cc | D109: Erection materials | F109: 501 | P109: 1 | Q109: 1 | R109: =Elec_Est!R107 -> 0 | S109: =T109*$D$9 -> 0 | T109: =Elec_Est!T107 -> 0
B110: 2 | C110: cc | D110: Busbar Trunking | F110: 505 | P110: 1 | Q110: 1 | R110: =Elec_Est!R108 -> 0 | S110: =T110*$D$9 -> 0 | T110: =Elec_Est!T108 -> 0
B111: 3 | C111: cc | D111: Switchgear | F111: 510 | P111: 2 | Q111: 1 | R111: =Elec_Est!R109 -> 0 | S111: =T111*$D$9 -> 0 | T111: =Elec_Est!T109 -> 0
B112: 4 | C112: cc | D112: MCC Equipment | F112: 511 | P112: 2 | Q112: 1 | R112: =Elec_Est!R110 -> 0 | S112: =T112*$D$9 -> 0 | T112: =Elec_Est!T110 -> 0
B113: 5 | C113: cc | D113: BMS Equipment | F113: 512 | P113: 2 | Q113: 1 | R113: =Elec_Est!R111 -> 180 | S113: =T113*$D$9 -> 0 | T113: =Elec_Est!T111 -> 0
B114: 6 | C114: cc | D114: PVC Pipes / Ducts | F114: 520 | P114: 1 | Q114: 1 | R114: =Elec_Est!R112 -> 0 | S114: =T114*$D$9 -> 0 | T114: =Elec_Est!T112 -> 0
B115: 7 | C115: cc | D115: High/medium voltage switchgear | F115: 530 | P115: 2 | Q115: 1 | R115: =Elec_Est!R113 -> 0 | S115: =T115*$D$9 -> 0 | T115: =Elec_Est!T113 -> 0
B116: 8 | C116: cc | D116: Power Transformers | F116: 550 | P116: 2 | Q116: 1 | R116: =Elec_Est!R114 -> 0 | S116: =T116*$D$9 -> 0 | T116: =Elec_Est!T114 -> 0
B117: 9 | C117: cc | D117: Control Panels | F117: 570 | P117: 2 | Q117: 1 | R117: =Elec_Est!R115 -> 0 | S117: =T117*$D$9 -> 0 | T117: =Elec_Est!T115 -> 0
B118: 10 | C118: cc | D118: Electrical Single Core Cables | F118: 615 | P118: 2 | Q118: 1 | R118: =Elec_Est!R116 -> 6.6 | S118: =T118*$D$9 -> 8.238 | T118: =Elec_Est!T116 -> 0.3
B119: 11(K) | C119: cc | D119: Electrical Multicore Cables | F119: 616 | P119: 2 | Q119: 1 | R119: =Elec_Est!R117 -> 0 | S119: =T119*$D$9 -> 0 | T119: =Elec_Est!T117 -> 0
B120: 12 | C120: cc | D120: ELV/BMS/Special Cables | F120: 617 | P120: 2 | Q120: 1 | R120: =Elec_Est!R118 -> 0 | S120: =T120*$D$9 -> 0 | T120: =Elec_Est!T118 -> 0
B121: 13 | C121: cc | D121: Cable Accessories | F121: 620 | P121: 2 | Q121: 1 | R121: =Elec_Est!R119 -> 0 | S121: =T121*$D$9 -> 0 | T121: =Elec_Est!T119 -> 0
B122: 14 | C122: cc | D122: Galv. Cable Trays | F122: 650 | P122: 1 | Q122: 1 | R122: =Elec_Est!R120 -> 0 | S122: =T122*$D$9 -> 0 | T122: =Elec_Est!T120 -> 0
B123: 15 | C123: cc | D123: PVC Cable Trays | F123: 651 | P123: 1 | Q123: 1 | R123: =Elec_Est!R121 -> 0 | S123: =T123*$D$9 -> 0 | T123: =Elec_Est!T121 -> 0
B124: 16 | C124: cc | D124: Galv. Cable Basket | F124: 652 | P124: 1 | Q124: 1 | R124: =Elec_Est!R122 -> 0 | S124: =T124*$D$9 -> 0 | T124: =Elec_Est!T122 -> 0
B125: 17 | C125: cc | D125: Galv. Cable Ladder | F125: 654 | P125: 1 | Q125: 1 | R125: =Elec_Est!R123 -> 0 | S125: =T125*$D$9 -> 0 | T125: =Elec_Est!T123 -> 0
B126: 18 | C126: cc | D126: Galv. Cable Trunking | F126: 675 | P126: 1 | Q126: 1 | R126: =Elec_Est!R124 -> 0 | S126: =T126*$D$9 -> 0 | T126: =Elec_Est!T124 -> 0
B127: 19 | C127: cc | D127: Alum. Cable Trunking | F127: 676 | P127: 1 | Q127: 1 | R127: =Elec_Est!R125 -> 0 | S127: =T127*$D$9 -> 0 | T127: =Elec_Est!T125 -> 0
B128: 20 | C128: cc | D128: PVC Cable Trunking | F128: 680 | P128: 1 | Q128: 1 | R128: =Elec_Est!R126 -> 0 | S128: =T128*$D$9 -> 0 | T128: =Elec_Est!T126 -> 0
B129: 21(L) | C129: cc | D129: Underfloor Cable Trunking | F129: 681 | P129: 1 | Q129: 1 | R129: =Elec_Est!R127 -> 0 | S129: =T129*$D$9 -> 0 | T129: =Elec_Est!T127 -> 0
...

Sheet Quote
A1: =IF(AND(UPPER(LEFT(TRIM($D$8),11))="01",UPPER(LEFT(TRIM($D$9),3))<>"ELM"),"PANTA RETAIL LTD.","PANTA CONTRACTING LIMITED") -> PANTA CONTRACTING LIMITED
A2: =IF(UPPER(LEFT(TRIM($D$9),3))="ELM","ELEC-FOR-MECH INTERNAL QUOTATION","ELECTRICAL INTERNAL QUOTATION") -> ELEC-FOR-MECH INTERNAL QUOTATION
B5: ATT: | D5: Jason Camilleri | R5: Dated: | S5: =NOW() -> 45971.674
B6: CLIENT: | C6: Link to ML_SUM $D1 | D6: =ML_Sum!D1 -> SUNCREST HOTELS plc
B7: PROJECT: | C7: Link to ML_SUM $D2 | D7: =ML_Sum!D2 -> Sunny Cost and Lido Redevelopment
B8: JOB DESC: | C8: Link to ML_SUM $D3 | D8: =ML_Sum!D3 -> Sample Room - Electrical for Mechanical
B9: QUOTE No: | C9: Link to ML_SUM $D4 | D9: =ML_Sum!D4 -> ELM25-0699
B10: CLIENT's Ref: | C10: Link to ML_SUM $D5 | D10: =ML_Sum!D5 -> Sample Room
D21: Material Cost (€) : | E21: =ML_Sum!R35 -> 190.92 | F21: =ML_Sum!D6 -> VAT EXCL. | G21: VAT EXCLUDED. | H21: VAT EXCLUDED. | I21: VAT EXCLUDED. | J21: VAT EXCLUDED. | K21: VAT EXCLUDED. | L21: VAT EXCLUDED. | M21: VAT EXCLUDED. | N21: VAT EXCLUDED. | O21: VAT EXCLUDED. | P21: VAT EXCLUDED.
D22: Labour Pair Hours : | E22: =ML_Sum!T35 -> 2.84
A53: Signed for and on behalf of | Q53: Signed for and on behalf of
A54: Electrical Division | Q54: Division
Q56: Records
Q57: Mr. K. Micallef
Q59: File

Sheet MUR MEP BOQ
B1: SUNNY COAST MOCK UP ROOM MEP Bill of Quantities | H1: REV00
B3: Preliminaries and General Conditions
A4: ITEM | B4: DESCRIPTION | C4: QTY | D4: UNIT | G4: RATE EXC. VAT | H4: TOTAL EXC. VAT
B5: The Preliminary Items included hereunder apply to the whole of the works contained in these Bills of Quantities and the rates and / or amounts inserted by the Contractor shall be deemed to apply to the whole of the works carried out under this Contract. The Contractor shall be deemed to have allowed in his tender for all costs in respect of all items described in the Preliminaries section of the Bills of Quantities. In the absence of any sum against any item or items , any monetary cost attributable thereto shall be deemed to be included elsewhere in the Preliminaries section or the unit rates for the measured works. The documents forming the Contract are to be taken as mutually explanatory to one another and any sum inserted here shall be deemed to cover the complete requirements of the Conditions of Contract, In the event of no amounts being inserted by the Contractor in respect of this Bill, no relative payment will be included in interim payments and the final All prices quoted in this tender are exclusive of V.A.T, but inclusive of all applicable Taxes and Levies. The contractor will be responsible for obtaining and incurring all expenses related to any permits that might be required by the local council and for any other fees that might become due to the local council or the competent authorities, bodies and /or agencies in relation to obstruction to traffic and pedestrians, necessary hoardings etc. Prior to submitting this tender document, the contractor is required to consult with the local council in relation to all requirements to carry out the scope of works of this tender.
B7: Health and Safety
A8: 1 | B8: Allow all costs for the employment of a licenced Health and Safety Officer for the entire duration of the Contract. The officer shall be responsible for enforcing all health and safety measures required by law, preparation of risk assessments for approval and work in conjuction with the H&S Officer appointed by the Employer. The Contractor shall also make provisions for a services of Fire Marshal during the works, in order to prevent any fires caused by Hot Works and other risks. | C8: 1 | D8: LS | G8: INC | H8: INC
B10: Regular Cleaning
A11: 1.003 | B11: Daily clean the site from any debris or material which may be intentionally or accidentally deposited during the course of works and during the transportation of material to the approariate disposal point | C11: 1 | D11: LS | G11: INC | H11: INC
B13: Preliminary Review of Project
A14: 1.004 | B14: The contractor shall obtain all the required operational information from Client, Perit and Engineers pertaining to the Risks related to Fire, so as to enable the full understanding of the design intent. The information shall include: materials, raw and finished, processes and chemicals used, quantities, packaging and storage format, shelving and stacking, ventilation requirements related to pharmaceutical industry, air pressure in rooms and corridors, safety and security, etc. | C14: 1 | D14: LS | G14: INC | H14: INC
A15: 1.005 | B15: The contractor shall review the M&E project documentation, and understand the services that will interface or clash (in terms of routing, levels and space allocation) and thus liaise with the Engineers for solutions. Any preparatory works as well as builders' works, preparation, openings, plinths, etc must be delth with at this stage. | C15: 1 | D15: LS | G15: INC | H15: INC
B17: Drawings
A18: 1.004 | B18: Provision of working drawings and reengineering as necessary including updating of drawings as required and as the works proceed. | C18: 1 | D18: LS | G18: INC | H18: INC
B20: Insurances
A21: 1.005 | B21: Contractor's Insurance CAR Policy covering the total contract value. The contractor must also take out a professional Indemnity Insurance to cover the design and therefore its warranted Engineers. | C21: 1 | D21: LS | G21: INC | H21: INC
A22: 1.006 | B22: Contractor's Insurance covering death or injury to Contractor's Personnel | C22: 1 | D22: LS | G22: INC | H22: INC
A23: 1.007 | B23: Contractor's Insurance covering loss or damage to Contractor's plant and equipment. | C23: 1 | D23: LS | G23: INC | H23: INC
B25: Builder's Works Drawings
A26: 1.008 | B26: The contractor must submit detailed builders work drawings, coordinated with the M&E drawings and the Fire compartmentation drawings issued by the Fire Engineer and Perit. The builder's work must provide clear information regarding all penetrations, holes and cores needed, the position with x & y dimensions, hole diameters, etc. The drawings must also detail whether the builder or finishes contractor will need to carry out future interventions of making good. the drawings must include additional works such as plinths (dimensions), puddle flanges, overflows and sleeves, doorways or hatches for equipment access. Where contractor may need access to lifters, cherry pickers, scaffolding, crane, etc, this must be agreed upon from this stage of the project. | C26: 1 | D26: LS | G26: INC | H26: INC
B28: Others
A29: 1.009 | B29: Provision of mobile toilets facilities on site, incl. emptying, cleaning etc | C29: 1 | D29: LS | G29: by client | H29: by client
A30: 1.01 | B30: Provision of security services on site | C30: 1 | D30: LS | G30: by client | H30: by client
A31: 1.011 | B31: Provision of CONTRACTOR MEP Project management | C31: 1 | D31: LS | G31: INC | H31: INC
A32: 1.012 | B32: Prepare coordinated drawings for all services | C32: 1 | D32: LS | G32: INC | H32: INC
A33: 1.014 | B33: Any other works, Contractor to list | C33: 1 | D33: LS | G33: INC | H33: INC
B34: TOTAL FOR PRELIMINARIES in € exc VAT | H34: INC
B35: *INC. = included, LS= lump sump, m= meters, No. =Number
B38: SPRINKLER INSTALLATION
A39: ITEM | B39: DESCRIPTION | C39: QTY | D39: UNIT | G39: RATE EXC. VAT | H39: TOTAL EXC. VAT
A40: 4 | B40: Take over design , reengineer and produce coordinated working drawings | C40: 1 | D40: LS | G40: INC | H40: INC
B41: Supply, install and connect the following medium gauge galvanised steel pipework including all brackets, fittings etc
A42: =IF(ISBLANK(C42),"",(MAX($A$38:A41)+0.001)) -> 4.001 | B42: 25mm | C42: 16 | D42: m | H42: =C42*G42 -> 0
A43: =IF(ISBLANK(C43),"",(MAX($A$38:A42)+0.001)) -> 4.002 | B43: 32mm | C43: 2 | D43: m | H43: =C43*G43 -> 0
A44: =IF(ISBLANK(C44),"",(MAX($A$38:A43)+0.001)) -> 4.003 | B44: 50mm | C44: 8 | D44: m | H44: =C44*G44 -> 0
A45: =IF(ISBLANK(C45),"",(MAX($A$38:A44)+0.001)) -> 4.004 | B45: Supply, install and connect Pendent type Sprinkler Quick Response, K80, 68DegC, concealed | C45: 2 | D45: No. | H45: =C45*G45 -> 0
A46: =IF(ISBLANK(C46),"",(MAX($A$38:A45)+0.001)) -> 4.005 | B46: Supply, install and connect, Sidewall type Sprinkler Quick Response, K80, 68DegC, escutcheon plate | C46: 5 | D46: No. | H46: =C46*G46 -> 0
A47: =IF(ISBLANK(C47),"",(MAX($A$38:A46)+0.001)) -> 4.006 | B47: Flexibles, if required | C47: 2 | D47: No. | H47: =C47*G47 -> 0
A48: =IF(ISBLANK(C48),"",(MAX($A$38:A47)+0.001)) -> 4.007 | B48: White Cover plate for concealed sprinkler | C48: 2 | D48: No. | H48: =C48*G48 -> 0
A49: =IF(ISBLANK(C49),"",(MAX($A49:A$58)+0.001))
A50: =IF(ISBLANK(C50),"",(MAX($A49:A$58)+0.001)) | B50: Builder's Work
A51: =IF(ISBLANK(C51),"",(MAX($A$38:A50)+0.001)) -> 4.008 | B51: Allow for all builder's work penetrations in structural walls, slabs or ceilings and including making good c/w with rendering and painting around pipework penetrations up to 300x300mm size | C51: 1 | D51: L.S. | G51: INC | H51: INC
A52: =IF(ISBLANK(C52),"",(MAX($A$38:A51)+0.001)) -> 4.009 | B52: Allow for sealing of all M&E pentrations with fire collars, fire bags, and fire retardant foam of the intumescent type, for all penetrations carried out in the building crossing fire zones/compartments/barriers. Refer to Fire Safety Report for fire compartments & REI rating. All fire zone sealing to be individually labeled, photographed and documented in a fire file. | C52: 1 | D52: L.S. | G52: INC | H52: INC
A53: =IF(ISBLANK(C53),"",(MAX($A52:A$58)+0.001))
A54: =IF(ISBLANK(C54),"",(MAX($A54:A$58)+0.001))
A55: =IF(ISBLANK(C55),"",(MAX($A54:A$58)+0.001)) | B55: Ancillary Items
A56: =IF(ISBLANK(C56),"",(MAX($A$38:A55)+0.001)) -> 4.01 | B56: Provision for extra structures, brackets, fittings etc required to mount equipment | C56: 1 | D56: L.S. | G56: INC | H56: INC
B57: TOTAL FOR SPRINKLER SYSTEM in € exc VAT | H57: =SUM(H41:H56) -> 0
B59: VENTILATION INSTALLATION
A60: ITEM | B60: DESCRIPTION | C60: QTY | D60: UNIT | E60: Total Material Cost | F60: Total Labour Hours | G60: RATE EXC. VAT | H60: TOTAL EXC. VAT
A61: 6 | B61: Take over design , reengineer and produce coordinated working drawings | C61: 1 | D61: LS | G61: INC | H61: INC
A63: =IF(ISBLANK(C63),"",(MAX($A61:A$61)+0.001)) | B63: Supply and install the following mixed flow fans including power supply connection, all conduit,trunking, chasing, penetrations, sleeves, wiring and all other items necessary for a complete and functional system
B65: SF 01 [Delta P to be as per selected accessories] for bedroom
A66: =IF(ISBLANK(C66),"",(MAX($A$61:A64)+0.001)) -> 6.001 | B66: 30 litres/sec mixed flow fan including electrical connection to double pole provided, complete. Fan to be very silent with silencers if required | C66: 1 | D66: LS | E66: =Elec_Est!AM23 -> 2.2 | F66: =Elec_Est!AO23 -> 0.6 | G66: =Elec_Est!E23 -> 24.28 | H66: =C66*G66 -> 24.28
A67: =IF(ISBLANK(C67),"",(MAX($A$61:A66)+0.001)) -> 6.002 | B67: Motorised 0-10V damper with leakage Class 3 to EN1751-2014 which will be connected to the RMS system for modulation control of damper by CO2 sensor feedback | C67: 1 | D67: LS | E67: =Elec_Est!AM30 -> 2.2 | F67: =Elec_Est!AO30 -> 0.6 | G67: =Elec_Est!E30 -> 24.28 | H67: =C67*G67 -> 24.28
A68: =IF(ISBLANK(C68),"",(MAX($A$61:A67)+0.001)) -> 6.003 | B68: Washable Class F7 filter with Filter Box | C68: 1 | D68: LS | H68: =C68*G68 -> 0
A69: =IF(ISBLANK(C69),"",(MAX($A$61:A68)+0.001)) -> 6.004 | B69: Circular ducting with 13mm insulation to sealing class A, Ductwork designed to operate at a static pressure greater than 750 Pa. Sealing to EN 15727-2010, UNI EN 1507-2008, UNI EN 12237-2004, and UNI EN 13403-2004 standards are applicable | C69: 1 | D69: LS | H69: =C69*G69 -> 0
A70: =IF(ISBLANK(C70),"",(MAX($A$61:A69)+0.001)) -> 6.005 | B70: Flexible ducting to connect to fan and grille | C70: 1 | D70: LS | H70: =C70*G70 -> 0
A71: =IF(ISBLANK(C71),"",(MAX($A$61:A70)+0.001)) -> 6.006 | B71: Extract grille | C71: 1 | D71: LS | H71: =C71*G71 -> 0
A72: =IF(ISBLANK(C72),"",(MAX($A$61:A71)+0.001)) -> 6.007 | B72: Extra over to achieve < NC30 or 35dBA | C72: 1 | D72: LS | G72: INC | H72: INC
A73: =IF(ISBLANK(C73),"",(MAX($A$61:A72)+0.001)) -> 6.008 | B73: Provide an indirect OA monitroing devices such as differential pressure sensor, airflow switch or current trasnducer on supply fan, complete with wiring to main door | C73: 1 | D73: LS | E73: =Elec_Est!AM37 -> 180 | F73: =Elec_Est!AO37 -> 0 | G73: =Elec_Est!E37 -> 234 | H73: =C73*G73 -> 234
A74: =IF(ISBLANK(C74),"",(MAX($A$61:A73)+0.001))
A75: =IF(ISBLANK(C75),"",(MAX($A$61:A73)+0.001)) | B75: EF 01 [Delta P to be as per selected accessories] for shower and toilet
A76: =IF(ISBLANK(C76),"",(MAX($A$61:A75)+0.001)) -> 6.009 | B76: 50 litres/sec mixed flow fan including electrical connection to double pole provided, delay off timer | C76: 1 | D76: LS | E76: =Elec_Est!AM45 -> 2.2 | F76: =Elec_Est!AO45 -> 0.6 | G76: =Elec_Est!E45 -> 24.28 | H76: =C76*G76 -> 24.28
A77: =IF(ISBLANK(C77),"",(MAX($A$61:A76)+0.001)) -> 6.01 | B77: Circular ducting with 13mm insulation . Ductwork designed to operate at a static pressure greater than 750 Pa. Sealing to EN 15727-2010, UNI EN 1507-2008, UNI EN 12237-2004, and UNI EN 13403-2004 standards are applicable | C77: 1 | D77: LS | H77: =C77*G77 -> 0
A78: =IF(ISBLANK(C78),"",(MAX($A$61:A77)+0.001)) -> 6.011 | B78: Disc Valve | C78: 2 | D78: LS | H78: =C78*G78 -> 0
A79: =IF(ISBLANK(C79),"",(MAX($A$61:A78)+0.001)) -> 6.012 | B79: Extract grille | C79: 1 | D79: LS | H79: =C79*G79 -> 0
A80: =IF(ISBLANK(C80),"",(MAX($A$61:A79)+0.001)) -> 6.013 | B80: Extra over to achieve < NC30 or 35dBA | C80: 1 | D80: LS | G80: INC | H80: INC
A81: =IF(ISBLANK(C81),"",(MAX($A$61:A80)+0.001)) -> 6.014 | B81: Non motorised back draft damper with leakage Class 3 to EN1751-2014 | C81: 1 | D81: LS | H81: =C81*G81 -> 0
A82: =IF(ISBLANK(C82),"",(MAX($A$61:A80)+0.001)) | H82: =C82*G82 -> 0
A83: =IF(ISBLANK(C83),"",(MAX($A$61:A82)+0.001)) | B83: Kitchen hood | H83: =C83*G83 -> 0
A84: =IF(ISBLANK(C84),"",(MAX($A$61:A83)+0.001)) -> 6.015 | B84: Circular ducting | C84: 1 | D84: LS | H84: =C84*G84 -> 0
A85: =IF(ISBLANK(C85),"",(MAX($A$61:A84)+0.001)) -> 6.016 | B85: Non motorised back draft damper with leakage Class 3 to EN1751-2014 | C85: 1 | D85: LS | H85: =C85*G85 -> 0
A86: =IF(ISBLANK(C86),"",(MAX($A$61:A85)+0.001)) -> 6.017 | B86: Extract grille | C86: 1 | D86: LS | H86: =C86*G86 -> 0
A87: =IF(ISBLANK(C87),"",(MAX($A$61:A86)+0.001)) | H87: =C87*G87 -> 0
A88: =IF(ISBLANK(C88),"",(MAX($A$61:A87)+0.001)) | B88: Builder's Work | H88: =C88*G88 -> 0
A89: =IF(ISBLANK(C89),"",(MAX($A$61:A88)+0.001)) -> 6.018 | B89: Allow for all builder's work penetrations in structural walls, slabs or ceilings and including making good c/w with rendering and painting around pipework penetrations up to 300x300mm size | C89: 1 | D89: L.S. | H89: =C89*G89 -> 0
A90: =IF(ISBLANK(C90),"",(MAX($A$61:A89)+0.001)) -> 6.019 | B90: Allow for sealing of all M&E pentrations with fire collars, fire bags, and fire retardant foam of the intumescent type, for all penetrations carried out in the building crossing fire zones/compartments/barriers. Refer to Fire Safety Report for fire compartments & REI rating. All fire zone sealing to be individually labeled, photographed and documented in a fire file. | C90: 1 | D90: L.S. | H90: =C90*G90 -> 0
A91: =IF(ISBLANK(C91),"",(MAX($A$61:A90)+0.001)) | H91: =C91*G91 -> 0
A92: =IF(ISBLANK(C92),"",(MAX($A$61:A91)+0.001)) | B92: Labelling | H92: =C92*G92 -> 0
A93: =IF(ISBLANK(C93),"",(MAX($A$61:A92)+0.001)) -> 6.02 | B93: Supply and install labelling using proper fixing adhesive on all salient equipment such as pipes, valves, cables, switchgear | C93: 1 | D93: L.S. | G93: INC | H93: INC
A94: =IF(ISBLANK(C94),"",(MAX($A$61:A93)+0.001))
A95: =IF(ISBLANK(C95),"",(MAX($A$61:A94)+0.001)) | B95: Ancillary Items
A96: =IF(ISBLANK(C96),"",(MAX($A$61:A95)+0.001)) -> 6.021 | B96: Provision for extra structures, brackets, fittings etc required to mount equipment | C96: 1 | D96: L.S. | G96: INC | H96: INC
A97: =IF(ISBLANK(C97),"",(MAX($A$61:A96)+0.001)) -> 6.022 | B97: Testing, commissioning & Certification of all installations | C97: 1 | D97: L.S. | H97: =C97*G97 -> 0
A98: =IF(ISBLANK(C98),"",(MAX($A$61:A97)+0.001)) -> 6.023 | B98: Supply two sets of printed as-fitted drawings and operation manuals and one copy in electronic format | C98: 1 | D98: L.S. | H98: =C98*G98 -> 0
B99: TOTAL FOR VENTILATION INSTALLATION in € exc VAT | E99: =SUM(E61:E98) -> 186.6 | F99: =SUM(F61:F98) -> 1.8 | H99: =SUM(H61:H98) -> 306.84
B101: AIR CONDITIONING INSTALLATION
A102: ITEM | B102: DESCRIPTION | C102: QTY | D102: UNIT | E102: Total Material Cost | F102: Total Labour Hours | G102: RATE EXC. VAT | H102: TOTAL EXC. VAT
A103: 7 | B103: Take over design , reengineer and produce coordinated working drawings | C103: 1 | D103: LS | G103: INC | H103: INC
A104: =IF(ISBLANK(C104),"",(MAX(#REF!)+0.001)) | H104: =C104*G104 -> 0
A105: =IF(ISBLANK(C105),"",(MAX($A$104:A104)+0.001)) | B105: Supply and install the following indoor units | H105: =C105*G105 -> 0
A106: =IF(ISBLANK(C106),"",(MAX($A$104:A105)+0.001)) | H106: =C106*G106 -> 0
A107: =IF(ISBLANK(C107),"",(MAX($A$103:A106)+0.001)) -> 7.001 | B107: Concealed indoor unit for 3.5kW bedroom complete with supply and return grille, c/w wall mounted controller, chased conduit, wiring, connection to double pole. Indoor model to be compatabile with water cooled outdoor VR units range. | C107: 1 | D107: No. | H107: =C107*G107 -> 0
A108: =IF(ISBLANK(C108),"",(MAX($A$104:A107)+0.001)) -> 7.002 | B108: Wall mounted controller | C108: 1 | D108: No. | E108: =Elec_Est!AM59 -> 2.16 | F108: =Elec_Est!AO59 -> 0.52 | G108: =Elec_Est!E59 -> 21.37 | H108: =C108*G108 -> 21.37
A109: =IF(ISBLANK(C109),"",(MAX($A$104:A108)+0.001)) -> 7.003 | B109: Provide means of having ac indoor unit fan working without outdoor, with speed hi-med-low modes for noise level similuation | C109: 1 | D109: LS | H109: =C109*G109 -> 0
A110: =IF(ISBLANK(C110),"",(MAX($A$104:A108)+0.001)) | B110: Extra over to achieve < NC30 or 35dBA
A111: =IF(ISBLANK(C111),"",(MAX($A$104:A107)+0.001)) | B111: Note. The controller to be suitable for hotel, (important this is not an over complicated type of control), The controller or the indoor unit must have dry contact to enable/disable unit. Any power supplies to be included if requried. | H111: =C111*G111 -> 0
A112: =IF(ISBLANK(C112),"",(MAX($A$104:A111)+0.001)) -> 7.004 | B112: Concealed indoor unit for 7.1kW main living area complete with supply and return grille | C112: 1 | D112: No. | H112: =C112*G112 -> 0
A113: =IF(ISBLANK(C113),"",(MAX($A$104:A112)+0.001)) -> 7.005 | B113: Wall mounted controller | C113: 1 | D113: No. | E113: =Elec_Est!AM66 -> 2.16 | F113: =Elec_Est!AO66 -> 0.52 | G113: =Elec_Est!E66 -> 21.37 | H113: =C113*G113 -> 21.37
A114: =IF(ISBLANK(C114),"",(MAX($A$104:A113)+0.001)) -> 7.006 | B114: Pheonlic ducting 600X200, the resistance R of the insulation must not exceed R-0.6, Ductwork designed to operate at a static pressure greater than 750 Pa. Sealing to EN 15727-2010, UNI EN 1507-2008, UNI EN 12237-2004, and UNI EN 13403-2004 standards are applicable | C114: 4 | D114: m | H114: =C114*G114 -> 0
...
